{
  "type": "Feature",
  "properties": {
    "addr:full":"Steindlbachweg 18 Peuerbach Ober\u00f6sterreich 4722",
    "addr:housenumber":"18",
    "addr:postcode":"4722",
    "addr:street":"Steindlbachweg",
    "iso:country":"AT",
    "sg:address":"Steindlbachweg 18",
    "sg:city":"Peuerbach",
    "sg:orig_category":"Stempel",
    "sg:phone":"+43 7276 3476",
    "sg:postcode":"4722",
    "sg:province":"Ober\u00f6sterreich",
    "wof:name":"MBS Lasergravur J\u00f6rn Svoboda",
    "wof:placetype":"venue"
},
  "geometry": {"coordinates":[13.780872345,48.346950531],"type":"Point"}
}