{
  "type": "Feature",
  "properties": {
    "addr:full":"Hauptstr 168 Prutz Tirol 6522",
    "addr:housenumber":"168",
    "addr:postcode":"6522",
    "addr:street":"Hauptstr;Tirol",
    "iso:country":"AT",
    "sg:address":"Hauptstr 168",
    "sg:city":"Prutz",
    "sg:orig_category":"Zimmereien",
    "sg:phone":"+43 5472 6330",
    "sg:postcode":"6522",
    "sg:province":"Tirol",
    "wof:name":"Ortner Holzcenter GesmbH & Co KG",
    "wof:placetype":"venue"
},
  "geometry": {"coordinates":[10.6638202667,47.0765533447],"type":"Point"}
}