{
  "type": "Feature",
  "properties": {
    "iso:country":"AT",
    "sg:address":"Alte Landstr 5",
    "sg:city":"Bludenz",
    "sg:orig_category":"Versicherungsunternehmen",
    "sg:phone":"+43 5552 66166",
    "sg:postcode":"6700",
    "sg:province":"Vorarlberg",
    "wof:name":"Allianz Versicherungs-Agentur - Stemer & Burtscher OEG",
    "wof:placetype":"venue"
},
  "geometry": {"coordinates":[9.81798172,47.1581993103],"type":"Point"}
}