{
  "type": "Feature",
  "properties": {
    "addr:full":"Saller 69 Schruns Vorarlberg 6780",
    "addr:housenumber":"69",
    "addr:postcode":"6780",
    "addr:street":"Saller",
    "iso:country":"AT",
    "sg:address":"Saller 69",
    "sg:city":"Schruns",
    "sg:orig_category":"Appartements / Ferienwohnungen",
    "sg:phone":"+43 5556 74224",
    "sg:postcode":"6780",
    "sg:province":"Vorarlberg",
    "wof:name":"Erhard Herlinde",
    "wof:placetype":"venue"
},
  "geometry": {"coordinates":[9.9074554443,47.0924110413],"type":"Point"}
}