{
  "type": "Feature",
  "properties": {
    "addr:full":"Mariahilfer Str. 47/5/17 Wien Wien 1060",
    "addr:housenumber":"47 / 5 / 17",
    "addr:postcode":"1060",
    "addr:street":"Str.",
    "iso:country":"AT",
    "sg:address":"Mariahilfer Str. 47/5/17",
    "sg:city":"Wien",
    "sg:orig_category":"Dienstleistungen, Telekommunikation",
    "sg:phone":"+43 4315 813261",
    "sg:postcode":"1060",
    "sg:province":"Wien",
    "sg:website":"http://www.crosat.co.at/",
    "wof:name":"Crosat Telekommunikation GmbH.",
    "wof:placetype":"venue"
},
  "geometry": {"coordinates":[16.3504657745,48.1947135925],"type":"Point"}
}