{
  "type": "Feature",
  "properties": {
    "addr:full":"Stollhofer Strasse 25 Hohe Wand-Stollhof Nieder\u00f6sterreich 2724",
    "addr:housenumber":"25",
    "addr:postcode":"2724",
    "addr:street":"Stollhofer Strasse;Hohe Wand-Stollhof",
    "iso:country":"AT",
    "sg:address":"Stollhofer Strasse 25",
    "sg:city":"Hohe Wand-Stollhof",
    "sg:classifiers":[
        {
            "category":"Utilities",
            "subcategory":"Fuel Oil & Lpg",
            "type":"Services"
        }
    ],
    "sg:phone":"+43 2638 88325",
    "sg:postcode":"2724",
    "sg:province":"Nieder\u00f6sterreich",
    "sg:tags":[
        "blasting",
        "explosive"
    ],
    "wof:name":"Ing. Haider Ges.m.b.H.",
    "wof:placetype":"venue"
},
  "geometry": {"coordinates":[16.0538883209,47.8195228577],"type":"Point"}
}