{
  "type": "Feature",
  "properties": {
    "addr:full":"Grazer Str 11+18 Mitterdorf im M\u00fcrztal Steiermark 8662",
    "addr:housenumber":"+ 18;im",
    "addr:postcode":"8662",
    "addr:street":"Str;Mitterdorf",
    "iso:country":"AT",
    "sg:address":"Grazer Str 11+18",
    "sg:city":"Mitterdorf im M\u00fcrztal",
    "sg:orig_category":"Autohandel",
    "sg:phone":"+43 4338 5822090",
    "sg:postcode":"8662",
    "sg:province":"Steiermark",
    "wof:name":"Koubek GmbH & Co KG",
    "wof:placetype":"venue"
},
  "geometry": {"coordinates":[15.5201072693,47.5357971191],"type":"Point"}
}