{
  "type": "Feature",
  "properties": {
    "addr:full":"K\u00fcrnbergblick 3 Leonding Ober\u00f6sterreich 4060",
    "addr:housenumber":"3",
    "addr:postcode":"4060",
    "addr:street":"Kuernbergblick",
    "iso:country":"AT",
    "sg:address":"K\u00fcrnbergblick 3",
    "sg:city":"Leonding",
    "sg:classifiers":[
        {
            "category":"Professional",
            "subcategory":"Advertising",
            "type":"Services"
        }
    ],
    "sg:phone":"+43 732 674041",
    "sg:postcode":"4060",
    "sg:province":"Ober\u00f6sterreich",
    "sg:tags":[
        "agency"
    ],
    "sg:website":"conquest.at",
    "wof:name":"CONQUEST Werbeagentur GmbH",
    "wof:placetype":"venue"
},
  "geometry": {"coordinates":[14.2491264343,48.2792434692],"type":"Point"}
}