{
  "type": "Feature",
  "properties": {
    "iso:country":"AT",
    "sg:address":"Freiheitspl 5",
    "sg:city":"Eisenerz",
    "sg:orig_category":"\u00c3\u201erzte / F Allgemeinmedizin",
    "sg:phone":"+43 3848 23600",
    "sg:postcode":"8790",
    "sg:province":"Steiermark",
    "wof:name":"Flick Michael Dr",
    "wof:placetype":"venue"
},
  "geometry": {"coordinates":[14.8859710693,47.5418014526],"type":"Point"}
}