{
  "type": "Feature",
  "properties": {
    "iso:country":"AT",
    "sg:address":"Schulstr 23",
    "sg:city":"Irnfritz",
    "sg:orig_category":"Friseure U Frisiersalons",
    "sg:phone":"+43 2986 6344",
    "sg:postcode":"3754",
    "sg:province":"Nieder\u00f6sterreich",
    "wof:name":"Asenbaum Elfriede",
    "wof:placetype":"venue"
},
  "geometry": {"coordinates":[15.5585279465,48.7394676208],"type":"Point"}
}