{
  "type": "Feature",
  "properties": {
    "addr:full":"Obachgasse 14 Wien Wien 1220",
    "addr:housenumber":"14",
    "addr:postcode":"1220",
    "addr:street":"Obachgasse",
    "iso:country":"AT",
    "sg:address":"Obachgasse 14",
    "sg:city":"Wien",
    "sg:classifiers":[
        {
            "category":"Shopping",
            "subcategory":"Photographic Equipment",
            "type":"Retail Goods"
        }
    ],
    "sg:phone":"+43 1 25965480",
    "sg:postcode":"1220",
    "sg:province":"Wien",
    "sg:tags":[
        "camera",
        "digital"
    ],
    "wof:name":"Ka Ra Fot Ilse Breinh\u00f6lder Ges.m.b.H.",
    "wof:placetype":"venue"
},
  "geometry": {"coordinates":[16.460975647,48.2561759949],"type":"Point"}
}