{
  "type": "Feature",
  "properties": {
    "addr:full":"Welser Str 1 Leonding Ober\u00f6sterreich 4060",
    "addr:housenumber":"1",
    "addr:postcode":"4060",
    "addr:street":"Str",
    "iso:country":"AT",
    "sg:address":"Welser Str 1",
    "sg:city":"Leonding",
    "sg:orig_category":"Tabaktrafiken",
    "sg:phone":"+43 732 683931",
    "sg:postcode":"4060",
    "sg:province":"Ober\u00f6sterreich",
    "wof:name":"K\u00f6hnhofer Klaus",
    "wof:placetype":"venue"
},
  "geometry": {"coordinates":[14.2652177811,48.2675132751],"type":"Point"}
}