{
  "type": "Feature",
  "properties": {
    "addr:full":"Franz-Wolfram-Scherer-Str 32 5028",
    "addr:housenumber":"32",
    "addr:postcode":"5028",
    "addr:street":"Franz-Wolfram-Scherer-Str",
    "iso:country":"AT",
    "sg:address":"Franz-Wolfram-Scherer-Str 32",
    "sg:orig_category":"Schmiermittel",
    "sg:phone":"+43 4366 24527050",
    "sg:postcode":"5028",
    "wof:name":"Kl\u00fcber Lubrication Austria GesmbH",
    "wof:placetype":"venue"
},
  "geometry": {"coordinates":[13.0617351532,47.8326950073],"type":"Point"}
}