{
  "type": "Feature",
  "properties": {
    "addr:full":"Nr 220 Kirchbach in Steiermark Steiermark 8082",
    "addr:postcode":"8082",
    "addr:street":"Nr",
    "iso:country":"AT",
    "sg:address":"Nr 220",
    "sg:city":"Kirchbach in Steiermark",
    "sg:orig_category":"Installationsunternehmen",
    "sg:phone":"+43 4331 1625510",
    "sg:postcode":"8082",
    "sg:province":"Steiermark",
    "sg:website":"veit.at",
    "wof:name":"Veit Johann",
    "wof:placetype":"venue"
},
  "geometry": {"coordinates":[15.6588878632,46.937297821],"type":"Point"}
}