{
  "type": "Feature",
  "properties": {
    "iso:country":"AT",
    "sg:address":"Billrothstr 18",
    "sg:city":"Wien",
    "sg:classifiers":[
        {
            "category":"Restaurant",
            "type":"Food & Drink"
        }
    ],
    "sg:phone":"+43 1 3696868",
    "sg:postcode":"1190",
    "sg:province":"Wien",
    "sg:tags":[
        "pizzeria"
    ],
    "wof:name":"SiSi Pizzaboy",
    "wof:placetype":"venue"
},
  "geometry": {"coordinates":[16.3496570587,48.2363815308],"type":"Point"}
}