{
  "type": "Feature",
  "properties": {
    "addr:full":"Hettenkoferg 30 Wien Wien 1160",
    "addr:housenumber":"30",
    "addr:postcode":"1160",
    "addr:street":"Hettenkoferg",
    "iso:country":"AT",
    "sg:address":"Hettenkoferg 30",
    "sg:city":"Wien",
    "sg:orig_category":"Gasme\u00c3\u0178- U Gasalarmanlagen",
    "sg:phone":"+43 1 4840657",
    "sg:postcode":"1160",
    "sg:province":"Wien",
    "sg:website":"www.ultratech.at",
    "wof:name":"Ultratech Service- und HandelsgesmbH",
    "wof:placetype":"venue"
},
  "geometry": {"coordinates":[16.3146343231,48.2124938965],"type":"Point"}
}