{
  "type": "Feature",
  "properties": {
    "iso:country":"AT",
    "sg:address":"Greifensteiner Str 14",
    "sg:city":"St. Andr\u00e4-W\u00f6rdern",
    "sg:orig_category":"Feuerwehren",
    "sg:phone":"+43 2242 32222",
    "sg:postcode":"3423",
    "sg:province":"Nieder\u00f6sterreich",
    "wof:name":"Freiwillige Feuerwehr St Andr\u00e4-W\u00f6rdern",
    "wof:placetype":"venue"
},
  "geometry": {"coordinates":[16.2093811035,48.3222045898],"type":"Point"}
}