{
  "type": "Feature",
  "properties": {
    "addr:full":"Unterdorf 10 Kematen in Tirol Tirol 6175",
    "addr:housenumber":"10",
    "addr:postcode":"6175",
    "addr:street":"Unterdorf;Tirol",
    "iso:country":"AT",
    "sg:address":"Unterdorf 10",
    "sg:city":"Kematen in Tirol",
    "sg:orig_category":"Lebensmittel / Einzelhandel",
    "sg:phone":"+43 5232 81163",
    "sg:postcode":"6175",
    "sg:province":"Tirol",
    "wof:name":"Plunser Hubert",
    "wof:placetype":"venue"
},
  "geometry": {"coordinates":[11.2104082108,47.2581787109],"type":"Point"}
}