{
  "type": "Feature",
  "properties": {
    "addr:full":"Alser Str 12 Wien Wien 1090",
    "addr:postcode":"1090",
    "addr:street":"Str 12",
    "iso:country":"AT",
    "sg:address":"Alser Str 12",
    "sg:city":"Wien",
    "sg:orig_category":"Apotheken",
    "sg:phone":"+43 1 4057123",
    "sg:postcode":"1090",
    "sg:province":"Wien",
    "wof:name":"Tiger Apotheke",
    "wof:placetype":"venue"
},
  "geometry": {"coordinates":[16.3500728607,48.2152366638],"type":"Point"}
}