{
  "type": "Feature",
  "properties": {
    "iso:country":"AT",
    "sg:address":"Favoritenstr 132",
    "sg:city":"Wien",
    "sg:orig_category":"Bankomat-Standorte",
    "sg:phone":"+43 1 60413360",
    "sg:postcode":"1100",
    "sg:province":"Wien",
    "wof:name":"Bankomat d Bank f Arbeit und Wirtschaft AG",
    "wof:placetype":"venue"
},
  "geometry": {"coordinates":[16.3784675598,48.1729927063],"type":"Point"}
}