{
  "type": "Feature",
  "properties": {
    "addr:full":"Adolf-Purtscher-Str 1 Lienz Tirol 9900",
    "addr:housenumber":"1",
    "addr:postcode":"9900",
    "addr:street":"Adolf-Purtscher-Str;Tirol",
    "iso:country":"AT",
    "sg:address":"Adolf-Purtscher-Str 1",
    "sg:city":"Lienz",
    "sg:orig_category":"Schuhmachereien",
    "sg:phone":"+43 4852 63961",
    "sg:postcode":"9900",
    "sg:province":"Tirol",
    "wof:name":"Unterassinger Schuhhandwerk KEG",
    "wof:placetype":"venue"
},
  "geometry": {"coordinates":[12.7599868774,46.831363678],"type":"Point"}
}