{
  "type": "Feature",
  "properties": {
    "iso:country":"AT",
    "sg:address":"Brunnenfeld, Alfenzstr. 1",
    "sg:city":"Bludenz",
    "sg:classifiers":[
        {
            "category":"Autos & Motor Vehicles",
            "subcategory":"Automobile Sales",
            "type":"Retail Goods"
        }
    ],
    "sg:phone":"+43 4355 5263536",
    "sg:postcode":"6700",
    "sg:province":"Vorarlberg",
    "sg:tags":[
        "motor-cars"
    ],
    "wof:name":"AUTOHANDEL GERSTER GMBH BLUDENZ",
    "wof:placetype":"venue"
},
  "geometry": {"coordinates":[9.8189496994,47.1569137573],"type":"Point"}
}