{
  "type": "Feature",
  "properties": {
    "iso:country":"AT",
    "sg:address":"Kreuzweg 6",
    "sg:city":"Walding",
    "sg:classifiers":[
        {
            "category":"Manufacturing",
            "subcategory":"Wood Products",
            "type":"Manufacturing & Wholesale Goods"
        }
    ],
    "sg:phone":"+43 7234 83871",
    "sg:postcode":"4111",
    "sg:province":"Ober\u00f6sterreich",
    "sg:tags":[
        "derived",
        "timber",
        "component",
        "furniture"
    ],
    "wof:name":"Klaus Lueghammer",
    "wof:placetype":"venue"
},
  "geometry": {"coordinates":[14.1583356857,48.3518676758],"type":"Point"}
}