{
  "type": "Feature",
  "properties": {
    "addr:full":"Niedermauern 17 Virgen Tirol 9972",
    "addr:housenumber":"17",
    "addr:postcode":"9972",
    "addr:street":"Niedermauern;Tirol",
    "iso:country":"AT",
    "sg:address":"Niedermauern 17",
    "sg:city":"Virgen",
    "sg:orig_category":"Pensionen / Privatzimmer",
    "sg:phone":"+43 4874 5261",
    "sg:postcode":"9972",
    "sg:province":"Tirol",
    "wof:name":"Habererhof",
    "wof:placetype":"venue"
},
  "geometry": {"coordinates":[12.4230089188,46.9972991943],"type":"Point"}
}