{
  "type": "Feature",
  "properties": {
    "addr:full":"Oberfeistritz 176 Anger Steiermark 8184",
    "addr:housenumber":"176",
    "addr:postcode":"8184",
    "addr:street":"Oberfeistritz",
    "iso:country":"AT",
    "sg:address":"Oberfeistritz 176",
    "sg:city":"Anger",
    "sg:classifiers":[
        {
            "category":"Utilities",
            "subcategory":"Water",
            "type":"Services"
        }
    ],
    "sg:phone":"+43 3175 30557",
    "sg:postcode":"8184",
    "sg:province":"Steiermark",
    "sg:tags":[
        "waste",
        "wetland",
        "treatment",
        "artificial"
    ],
    "sg:website":"klaerautomat.com",
    "wof:name":"KLAERAUTOMAT P.B.A. Gmbh Sackl-Kl\u00e4rautomat",
    "wof:placetype":"venue"
},
  "geometry": {"coordinates":[15.7008781433,47.2695770264],"type":"Point"}
}