{
  "type": "Feature",
  "properties": {
    "addr:full":"Pulgarn 28 Steyregg Ober\u00f6sterreich 4221",
    "addr:housenumber":"28",
    "addr:postcode":"4221",
    "addr:street":"Pulgarn",
    "iso:country":"AT",
    "sg:address":"Pulgarn 28",
    "sg:city":"Steyregg",
    "sg:classifiers":[
        {
            "category":"Home & Garden",
            "subcategory":"Building Materials",
            "type":"Retail Goods"
        }
    ],
    "sg:phone":"+43 732 6400170",
    "sg:postcode":"4221",
    "sg:province":"Ober\u00f6sterreich",
    "sg:tags":[
        "railing",
        "balcony"
    ],
    "wof:name":"Erwin Johann Kreindl",
    "wof:placetype":"venue"
},
  "geometry": {"coordinates":[14.3908948898,48.2809791565],"type":"Point"}
}