{
  "type": "Feature",
  "properties": {
    "addr:full":"Breitenweg 4/44 St. Peter Steiermark 8042",
    "addr:housenumber":"4 / 44",
    "addr:postcode":"8042",
    "addr:street":"Breitenweg",
    "iso:country":"AT",
    "sg:address":"Breitenweg 4/44",
    "sg:city":"St. Peter",
    "sg:orig_category":"Weiterbildungsinstitute M Allg U Berufl Bildungsangebot",
    "sg:phone":"+43 4331 6421738",
    "sg:postcode":"8042",
    "sg:province":"Steiermark",
    "wof:name":"saluto aesthetic akademie f gesundheits- u bewegungskultur",
    "wof:placetype":"venue"
},
  "geometry": {"coordinates":[15.4753828049,47.0578689575],"type":"Point"}
}