{
  "type": "Feature",
  "properties": {
    "addr:full":"Industriezentrum N\u00f6 S\u00fcd Stra\u00dfe 7 58c 2355",
    "addr:housenumber":"7 58c",
    "addr:postcode":"2355",
    "addr:street":"Industriezentrum Noe Sued Strasse",
    "iso:country":"AT",
    "sg:address":"Industriezentrum N\u00f6 S\u00fcd Stra\u00dfe 7 58c",
    "sg:orig_category":"Optiker",
    "sg:phone":"+43 4322 36304260",
    "sg:postcode":"2355",
    "wof:name":"Nikon Brillengl\u00e4ser",
    "wof:placetype":"venue"
},
  "geometry": {"coordinates":[16.3183326721,48.0863113403],"type":"Point"}
}