{
  "type": "Feature",
  "properties": {
    "iso:country":"AT",
    "sg:address":"Stadtpl 41",
    "sg:city":"Mattighofen",
    "sg:orig_category":"Bekleidung / Einzelhandel",
    "sg:phone":"+43 7742 2324",
    "sg:postcode":"5230",
    "sg:province":"Ober\u00f6sterreich",
    "wof:name":"Mittermayr Karl",
    "wof:placetype":"venue"
},
  "geometry": {"coordinates":[13.1505117416,48.1029891968],"type":"Point"}
}