{
  "type": "Feature",
  "properties": {
    "iso:country":"AT",
    "sg:address":"Bahnhofstr 251",
    "sg:city":"Greifenburg",
    "sg:orig_category":"Raumausstattung",
    "sg:phone":"+43 4712 349",
    "sg:postcode":"9761",
    "sg:province":"K\u00e4rnten",
    "wof:name":"Emberger Gerhild",
    "wof:placetype":"venue"
},
  "geometry": {"coordinates":[13.1846418381,46.7443618774],"type":"Point"}
}