{
  "type": "Feature",
  "properties": {
    "addr:full":"Ringweg 24 Zeltweg Steiermark 8740",
    "addr:housenumber":"24",
    "addr:postcode":"8740",
    "addr:street":"Ringweg",
    "iso:country":"AT",
    "sg:address":"Ringweg 24",
    "sg:city":"Zeltweg",
    "sg:orig_category":"Maler, Anstreicher U Lackierer",
    "sg:phone":"+43 3577 26644",
    "sg:postcode":"8740",
    "sg:province":"Steiermark",
    "wof:name":"Schneeberger Malerei & Anstreichunternehmen",
    "wof:placetype":"venue"
},
  "geometry": {"coordinates":[14.7652950287,47.1957473755],"type":"Point"}
}