{
  "type": "Feature",
  "properties": {
    "addr:full":"Burgauberg 230 Burgau Steiermark 8291",
    "addr:housenumber":"230",
    "addr:postcode":"8291",
    "addr:street":"Burgauberg",
    "iso:country":"AT",
    "sg:address":"Burgauberg 230",
    "sg:city":"Burgau",
    "sg:classifiers":[
        {
            "category":"Manufacturing",
            "subcategory":"Wood Products",
            "type":"Manufacturing & Wholesale Goods"
        }
    ],
    "sg:phone":"+43 3326 54133",
    "sg:postcode":"8291",
    "sg:province":"Steiermark",
    "sg:tags":[
        "lumber"
    ],
    "sg:website":"ferstl-holz.at",
    "wof:name":"Heinrich Ferstl",
    "wof:placetype":"venue"
},
  "geometry": {"coordinates":[16.126701355,47.1626243591],"type":"Point"}
}