{
  "type": "Feature",
  "properties": {
    "addr:full":"Kroateng 2 Linz Ober\u00f6sterreich 4020",
    "addr:housenumber":"2",
    "addr:postcode":"4020",
    "addr:street":"Kroateng",
    "iso:country":"AT",
    "sg:address":"Kroateng 2",
    "sg:city":"Linz",
    "sg:orig_category":"\u00c3\u201erzte- U Spitalsbedarf",
    "sg:phone":"+43 4369 910413201",
    "sg:postcode":"4020",
    "sg:province":"Ober\u00f6sterreich",
    "wof:name":"Dental-Trading Brilo GesmbH",
    "wof:placetype":"venue"
},
  "geometry": {"coordinates":[14.2841796875,48.2973442078],"type":"Point"}
}