{
  "type": "Feature",
  "properties": {
    "iso:country":"AT",
    "sg:address":"Alte Wiener Str 25",
    "sg:city":"Bruck an der Leitha",
    "sg:orig_category":"Biologische Produkte",
    "sg:phone":"+43 4321 6264504",
    "sg:postcode":"2460",
    "sg:province":"Nieder\u00f6sterreich",
    "wof:name":"Landgarten Herbert Stava KEG",
    "wof:placetype":"venue"
},
  "geometry": {"coordinates":[16.7722568512,48.0228805542],"type":"Point"}
}