{
  "type": "Feature",
  "properties": {
    "addr:full":"Mariahilfer Str 167/12 Wien Wien 1150",
    "addr:housenumber":"167 / 12",
    "addr:postcode":"1150",
    "iso:country":"AT",
    "sg:address":"Mariahilfer Str 167/12",
    "sg:city":"Wien",
    "sg:orig_category":"Unternehmensberatung",
    "sg:phone":"+43 1 2697936",
    "sg:postcode":"1150",
    "sg:province":"Wien",
    "wof:name":"KIPPERER & LAGGER OEG",
    "wof:placetype":"venue"
},
  "geometry": {"coordinates":[16.333820343,48.1929168701],"type":"Point"}
}