{
  "type": "Feature",
  "properties": {
    "addr:full":"Sto\u00df im Himmel 3 Wien Wien 1010",
    "addr:housenumber":"3",
    "addr:postcode":"1010",
    "addr:street":"Stoss Im Himmel",
    "iso:country":"AT",
    "sg:address":"Sto\u00df im Himmel 3",
    "sg:city":"Wien",
    "sg:orig_category":"Speditionen",
    "sg:phone":"+43 1 5338407",
    "sg:postcode":"1010",
    "sg:province":"Wien",
    "wof:name":"Pannosch Friedrich Mag",
    "wof:placetype":"venue"
},
  "geometry": {"coordinates":[16.37059021,48.212436676],"type":"Point"}
}