{
  "type": "Feature",
  "properties": {
    "iso:country":"AT",
    "sg:address":"Kaltnerg 1",
    "sg:city":"Salzburg",
    "sg:orig_category":"Werbeagenturen",
    "sg:phone":"+43 662 622010",
    "sg:postcode":"5020",
    "sg:province":"Salzburg",
    "wof:name":"CONTACT PROMOTION Karl & Fiebiger OEG",
    "wof:placetype":"venue"
},
  "geometry": {"coordinates":[13.0621137619,47.7957801819],"type":"Point"}
}