{
  "type": "Feature",
  "properties": {
    "addr:full":"Zirmweg 94 Steinach am Brenner Tirol 6150",
    "addr:housenumber":"94",
    "addr:postcode":"6150",
    "addr:street":"Zirmweg;Tirol",
    "iso:country":"AT",
    "sg:address":"Zirmweg 94",
    "sg:city":"Steinach am Brenner",
    "sg:orig_category":"Pensionen / Privatzimmer",
    "sg:phone":"+43 5272 6358",
    "sg:postcode":"6150",
    "sg:province":"Tirol",
    "wof:name":"Waldheim Fr\u00fchst\u00fcckspension",
    "wof:placetype":"venue"
},
  "geometry": {"coordinates":[11.4658479691,47.0899887085],"type":"Point"}
}