{
  "type": "Feature",
  "properties": {
    "addr:full":"Neudorf 79 St. Veit Steiermark 8046",
    "addr:housenumber":"79",
    "addr:postcode":"8046",
    "addr:street":"Neudorf",
    "iso:country":"AT",
    "sg:address":"Neudorf 79",
    "sg:city":"St. Veit",
    "sg:classifiers":[
        {
            "category":"Manufacturing",
            "subcategory":"Tools & Machinery",
            "type":"Manufacturing & Wholesale Goods"
        }
    ],
    "sg:phone":"+43 3123 2291",
    "sg:postcode":"8046",
    "sg:province":"Steiermark",
    "sg:tags":[
        "machining",
        "cnc"
    ],
    "wof:name":"Deimbacher KEG",
    "wof:placetype":"venue"
},
  "geometry": {"coordinates":[15.4190244675,47.1442832947],"type":"Point"}
}