{
  "type": "Feature",
  "properties": {
    "iso:country":"AT",
    "sg:address":"\u00f6lbergg 6",
    "sg:city":"Waidhofen an der Ybbs",
    "sg:orig_category":"Friseure U Frisiersalons",
    "sg:phone":"+43 4374 4252840",
    "sg:postcode":"3340",
    "sg:province":"Nieder\u00f6sterreich",
    "wof:name":"HAAR-TOTAL Math\u00e4 KEG",
    "wof:placetype":"venue"
},
  "geometry": {"coordinates":[14.7746295929,47.960559845],"type":"Point"}
}