{
  "type": "Feature",
  "properties": {
    "addr:full":"Salzburger Strasse 199  Linz Ober\u00f6sterreich 4030",
    "addr:housenumber":"199",
    "addr:postcode":"4030",
    "addr:street":"Salzburger Strasse",
    "iso:country":"AT",
    "sg:address":"Salzburger Strasse 199 ",
    "sg:city":"Linz",
    "sg:classifiers":[
        {
            "category":"Home & Garden",
            "subcategory":"Mobile Homes",
            "type":"Retail Goods"
        }
    ],
    "sg:phone":"+43 732 38800",
    "sg:postcode":"4030",
    "sg:province":"Ober\u00f6sterreich",
    "sg:tags":[
        "awning",
        "outdoor",
        "marquee"
    ],
    "sg:website":"www.klotzner.at",
    "wof:name":"Klotzner Ges.m.b.H. & Co KG",
    "wof:placetype":"venue"
},
  "geometry": {"coordinates":[14.292342186,48.2576904297],"type":"Point"}
}