{
  "type": "Feature",
  "properties": {
    "iso:country":"AT",
    "sg:address":"Nr 45",
    "sg:city":"Mieming",
    "sg:orig_category":"Non-Classified Establishments",
    "sg:phone":"+43 5264 5384",
    "sg:postcode":"6414",
    "sg:province":"Tirol",
    "wof:name":"Pfarramt",
    "wof:placetype":"venue"
},
  "geometry": {"coordinates":[11.0065221786,47.3184700012],"type":"Point"}
}