{
  "type": "Feature",
  "properties": {
    "addr:full":"Traunuferstr 28 Ansfelden Ober\u00f6sterreich 4052",
    "addr:housenumber":"28",
    "addr:postcode":"4052",
    "addr:street":"Traunuferstr",
    "iso:country":"AT",
    "sg:address":"Traunuferstr 28",
    "sg:city":"Ansfelden",
    "sg:orig_category":"Non-Classified Establishments",
    "sg:phone":"+43 4373 2300182",
    "sg:postcode":"4052",
    "sg:province":"Ober\u00f6sterreich",
    "wof:name":"Catoffice Communications",
    "wof:placetype":"venue"
},
  "geometry": {"coordinates":[14.2858695984,48.2185516357],"type":"Point"}
}