{
  "type": "Feature",
  "properties": {
    "iso:country":"AT",
    "sg:address":"Teichstr 6",
    "sg:city":"Reifnitz",
    "sg:classifiers":[
        {
            "category":"Restaurant",
            "type":"Food & Drink"
        }
    ],
    "sg:phone":"+43 4273 2236",
    "sg:postcode":"9081",
    "sg:province":"K\u00e4rnten",
    "wof:name":"Restaurant Paulitsch",
    "wof:placetype":"venue"
},
  "geometry": {"coordinates":[14.1815433502,46.6068840027],"type":"Point"}
}