{
  "type": "Feature",
  "properties": {
    "addr:full":"Schmelz 16 Dellach im Drautal K\u00e4rnten 9772",
    "addr:housenumber":"16",
    "addr:postcode":"9772",
    "addr:street":"Schmelz",
    "iso:country":"AT",
    "sg:address":"Schmelz 16",
    "sg:city":"Dellach im Drautal",
    "sg:orig_category":"Hafnereien",
    "sg:phone":"+43 4366 43616655",
    "sg:postcode":"9772",
    "sg:province":"K\u00e4rnten",
    "wof:name":"Heregger Thomas",
    "wof:placetype":"venue"
},
  "geometry": {"coordinates":[13.0910167694,46.7464828491],"type":"Point"}
}