{
  "type": "Feature",
  "properties": {
    "iso:country":"AT",
    "sg:address":"Spiegelg 15",
    "sg:city":"Wien",
    "sg:orig_category":"Geschenkartikel",
    "sg:phone":"+43 1 5124192",
    "sg:postcode":"1010",
    "sg:province":"Wien",
    "wof:name":"Kontor Inh Mag Angelika G\u00fcrtler",
    "wof:placetype":"venue"
},
  "geometry": {"coordinates":[16.3700008392,48.2067756653],"type":"Point"}
}