{
  "type": "Feature",
  "properties": {
    "addr:full":"Spiegelg 15 Wien Wien 1010",
    "addr:housenumber":"15",
    "addr:postcode":"1010",
    "addr:street":"Spiegelg",
    "iso:country":"AT",
    "sg:address":"Spiegelg 15",
    "sg:city":"Wien",
    "sg:orig_category":"Geschenkartikel",
    "sg:phone":"+43 1 5124192",
    "sg:postcode":"1010",
    "sg:province":"Wien",
    "wof:name":"Kontor Inh Mag Angelika G\u00fcrtler",
    "wof:placetype":"venue"
},
  "geometry": {"coordinates":[16.3700008392,48.2067756653],"type":"Point"}
}