{
  "type": "Feature",
  "properties": {
    "addr:full":"Salzachstr 12a Aigen Salzburg 5026",
    "addr:housenumber":"12a",
    "addr:postcode":"5026",
    "addr:street":"Salzachstr;Salzburg",
    "iso:country":"AT",
    "sg:address":"Salzachstr 12a",
    "sg:city":"Aigen",
    "sg:orig_category":"Telekommunikation",
    "sg:phone":"+43 662 630094",
    "sg:postcode":"5026",
    "sg:province":"Salzburg",
    "wof:name":"TVC The Virtual Company New Media GmbH",
    "wof:placetype":"venue"
},
  "geometry": {"coordinates":[13.0786504745,47.7850112915],"type":"Point"}
}