{
  "type": "Feature",
  "properties": {
    "iso:country":"AT",
    "sg:address":"Drei L\u00e4rchen 29",
    "sg:city":"Bad Bleiberg",
    "sg:classifiers":[
        {
            "category":"Travel",
            "subcategory":"Hotels & Motels",
            "type":"Entertainment"
        }
    ],
    "sg:phone":"+43 4244 23180",
    "sg:postcode":"9530",
    "sg:province":"K\u00e4rnten",
    "wof:name":"Familienhotel K\u00e4rnten",
    "wof:placetype":"venue"
},
  "geometry": {"coordinates":[13.6877374649,46.6243476868],"type":"Point"}
}