{
  "type": "Feature",
  "properties": {
    "addr:full":"St.Martin 24 St. Martin im M\u00fchlkreis Ober\u00f6sterreich 4113",
    "addr:housenumber":"24",
    "addr:postcode":"4113",
    "addr:street":"St.Martin;Im Muehlkreis Oberoesterreich",
    "iso:country":"AT",
    "sg:address":"St.Martin 24",
    "sg:city":"St. Martin im M\u00fchlkreis",
    "sg:classifiers":[
        {
            "category":"Home & Garden",
            "subcategory":"Building Materials",
            "type":"Retail Goods"
        }
    ],
    "sg:phone":"+43 7232 2326",
    "sg:postcode":"4113",
    "sg:province":"Ober\u00f6sterreich",
    "sg:tags":[
        "railing",
        "balcony"
    ],
    "wof:name":"Fritz Schaubschl\u00e4ger",
    "wof:placetype":"venue"
},
  "geometry": {"coordinates":[14.8434352875,48.6537437439],"type":"Point"}
}