{
  "type": "Feature",
  "properties": {
    "iso:country":"AT",
    "sg:address":"Breitenfurter Str 99",
    "sg:city":"Wien",
    "sg:orig_category":"Autoersatzteile",
    "sg:phone":"+43 1 80406060",
    "sg:postcode":"1120",
    "sg:province":"Wien",
    "wof:name":"Gatterwe Maria",
    "wof:placetype":"venue"
},
  "geometry": {"coordinates":[16.3176994324,48.1663093567],"type":"Point"}
}