{
  "type": "Feature",
  "properties": {
    "addr:full":"Renng 6-8 Wien Wien 1010",
    "addr:housenumber":"6-8",
    "addr:postcode":"1010",
    "addr:street":"Renng",
    "iso:country":"AT",
    "sg:address":"Renng 6-8",
    "sg:city":"Wien",
    "sg:orig_category":"Internationale Organisationen",
    "sg:phone":"+43 1 71389300",
    "sg:postcode":"1010",
    "sg:province":"Wien",
    "wof:name":"St\u00e4ndige Vertretung Italiens bei der OSZE",
    "wof:placetype":"venue"
},
  "geometry": {"coordinates":[16.3668174744,48.2121315002],"type":"Point"}
}