{
  "type": "Feature",
  "properties": {
    "addr:full":"Innsdlg Ebbs Tirol 6341",
    "addr:postcode":"6341",
    "iso:country":"AT",
    "sg:address":"Innsdlg",
    "sg:city":"Ebbs",
    "sg:orig_category":"Alteisen U Altmetalle, Entsorgungen",
    "sg:phone":"+43 5372 63514",
    "sg:postcode":"6341",
    "sg:province":"Tirol",
    "wof:name":"Schrotthof Unterland GmbH",
    "wof:placetype":"venue"
},
  "geometry": {"coordinates":[12.2144241333,47.6297264099],"type":"Point"}
}