{
  "type": "Feature",
  "properties": {
    "addr:full":"Untermarkt 23 Reutte Tirol 6600",
    "addr:housenumber":"23",
    "addr:postcode":"6600",
    "addr:street":"Untermarkt;Tirol",
    "iso:country":"AT",
    "sg:address":"Untermarkt 23",
    "sg:city":"Reutte",
    "sg:orig_category":"Volkshochschulen",
    "sg:phone":"+43 5672 72645",
    "sg:postcode":"6600",
    "sg:province":"Tirol",
    "wof:name":"Volkshochschule Reutte",
    "wof:placetype":"venue"
},
  "geometry": {"coordinates":[10.7175445557,47.4906463623],"type":"Point"}
}