{
  "type": "Feature",
  "properties": {
    "addr:full":"Uttenhofen 2 Saalfelden am Steinernen Meer Salzburg 5760",
    "addr:housenumber":"2",
    "addr:postcode":"5760",
    "addr:street":"Uttenhofen",
    "iso:country":"AT",
    "sg:address":"Uttenhofen 2",
    "sg:city":"Saalfelden am Steinernen Meer",
    "sg:orig_category":"Appartements / Ferienwohnungen",
    "sg:phone":"+43 6582 73397",
    "sg:postcode":"5760",
    "sg:province":"Salzburg",
    "wof:name":"Thomanhof",
    "wof:placetype":"venue"
},
  "geometry": {"coordinates":[12.8170118332,47.4374351501],"type":"Point"}
}