{
  "type": "Feature",
  "properties": {
    "iso:country":"AT",
    "sg:address":"Berger \u00e4cker 17",
    "sg:city":"Zirl",
    "sg:orig_category":"Zahntechnische Laboratorien",
    "sg:phone":"+43 4352 3852150",
    "sg:postcode":"6170",
    "sg:province":"Tirol",
    "wof:name":"H & H Dental Labor GmbH",
    "wof:placetype":"venue"
},
  "geometry": {"coordinates":[11.2341842651,47.2735557556],"type":"Point"}
}