{
  "type": "Feature",
  "properties": {
    "addr:full":"Industriestr 3 Hard Vorarlberg 6971",
    "addr:housenumber":"3",
    "addr:postcode":"6971",
    "addr:street":"Industriestr",
    "iso:country":"AT",
    "sg:address":"Industriestr 3",
    "sg:city":"Hard",
    "sg:orig_category":"Autoreparatur",
    "sg:phone":"+43 5574 61307",
    "sg:postcode":"6971",
    "sg:province":"Vorarlberg",
    "wof:name":"Schmatz Rudolf",
    "wof:placetype":"venue"
},
  "geometry": {"coordinates":[9.677482605,47.4840621948],"type":"Point"}
}