{
  "type": "Feature",
  "properties": {
    "addr:full":"Weidenweg 14  Feldbach Steiermark 8330",
    "addr:housenumber":"14",
    "addr:postcode":"8330",
    "addr:street":"Weidenweg",
    "iso:country":"AT",
    "sg:address":"Weidenweg 14 ",
    "sg:city":"Feldbach",
    "sg:classifiers":[
        {
            "category":"Wholesale",
            "subcategory":"Drugs",
            "type":"Manufacturing & Wholesale Goods"
        }
    ],
    "sg:phone":"+43 4331 5247110",
    "sg:postcode":"8330",
    "sg:province":"Steiermark",
    "sg:tags":[
        "chemical",
        "pharmaceutical"
    ],
    "wof:name":"DYCKERHOFF AUSTRIA AUSBAUPRODUKTE GMBH",
    "wof:placetype":"venue"
},
  "geometry": {"coordinates":[15.8986206055,46.9547996521],"type":"Point"}
}