{
  "type": "Feature",
  "properties": {
    "addr:full":"Achstr 35c Wolfurt Vorarlberg 6922",
    "addr:housenumber":"35c",
    "addr:postcode":"6922",
    "addr:street":"Achstr",
    "iso:country":"AT",
    "sg:address":"Achstr 35c",
    "sg:city":"Wolfurt",
    "sg:orig_category":"Feuerwerksartikel U Feuerwerke",
    "sg:phone":"+43 4366 41611580",
    "sg:postcode":"6922",
    "sg:province":"Vorarlberg",
    "sg:website":"helios-feuerwerke.at",
    "wof:name":"HELIOS Feuerwerke - Gerold Pointner",
    "wof:placetype":"venue"
},
  "geometry": {"coordinates":[9.7555789948,47.4790840149],"type":"Point"}
}