{
  "type": "Feature",
  "properties": {
    "iso:country":"AT",
    "sg:address":"Hauptstr 56",
    "sg:city":"Rottenmann",
    "sg:orig_category":"Gemeinden",
    "sg:phone":"+43 3614 24110",
    "sg:postcode":"8786",
    "sg:province":"Steiermark",
    "wof:name":"Stadtgemeindeamt Rottenmann",
    "wof:placetype":"venue"
},
  "geometry": {"coordinates":[14.3580436707,47.5254974365],"type":"Point"}
}