{
  "type": "Feature",
  "properties": {
    "addr:full":"M\u00fcnchenstr 18 Wien Wien 1120",
    "addr:housenumber":"18",
    "addr:postcode":"1120",
    "addr:street":"Muenchenstr",
    "iso:country":"AT",
    "sg:address":"M\u00fcnchenstr 18",
    "sg:city":"Wien",
    "sg:orig_category":"Druckereien",
    "sg:phone":"+43 4318 042812",
    "sg:postcode":"1120",
    "sg:province":"Wien",
    "wof:name":"GRAPHIA - TOMA DRUCK KEG",
    "wof:placetype":"venue"
},
  "geometry": {"coordinates":[16.3290939331,48.1824874878],"type":"Point"}
}