{
  "type": "Feature",
  "properties": {
    "addr:full":"Nr 42 Niederru\u00dfbach Nieder\u00f6sterreich 3702",
    "addr:postcode":"3702",
    "addr:street":"Nr;Niederoesterreich",
    "iso:country":"AT",
    "sg:address":"Nr 42",
    "sg:city":"Niederru\u00dfbach",
    "sg:orig_category":"Feuerwehren",
    "sg:phone":"+43 4329 5430488",
    "sg:postcode":"3702",
    "sg:province":"Nieder\u00f6sterreich",
    "wof:name":"Freiwillige Feuerwehr Stranzendorf",
    "wof:placetype":"venue"
},
  "geometry": {"coordinates":[16.0376472473,48.4505691528],"type":"Point"}
}