{
  "type": "Feature",
  "properties": {
    "addr:full":"Friedrich-Schiller-Str 2 Traiskirchen Nieder\u00f6sterreich 2514",
    "addr:housenumber":"2",
    "addr:postcode":"2514",
    "addr:street":"Friedrich-Schiller-Str;Niederoesterreich",
    "iso:country":"AT",
    "sg:address":"Friedrich-Schiller-Str 2",
    "sg:city":"Traiskirchen",
    "sg:orig_category":"Tabaktrafiken",
    "sg:phone":"+43 4322 5253119",
    "sg:postcode":"2514",
    "sg:province":"Nieder\u00f6sterreich",
    "wof:name":"Hronek Margarete",
    "wof:placetype":"venue"
},
  "geometry": {"coordinates":[16.2868213654,48.0218963623],"type":"Point"}
}