{
  "type": "Feature",
  "properties": {
    "addr:full":"Bahng 4 Breitenau am Hochlantsch Steiermark 8614",
    "addr:housenumber":"4",
    "addr:postcode":"8614",
    "addr:street":"Bahng",
    "iso:country":"AT",
    "sg:address":"Bahng 4",
    "sg:city":"Breitenau am Hochlantsch",
    "sg:orig_category":"Tischlereien",
    "sg:phone":"+43 3866 2297",
    "sg:postcode":"8614",
    "sg:province":"Steiermark",
    "wof:name":"Eibl Mario",
    "wof:placetype":"venue"
},
  "geometry": {"coordinates":[16.1454391479,47.7346572876],"type":"Point"}
}