{
  "type": "Feature",
  "properties": {
    "iso:country":"AT",
    "sg:address":"Hauptstrasse 73",
    "sg:city":"Grafendorf",
    "sg:classifiers":[
        {
            "category":"Building & Trades",
            "subcategory":"Plumbing",
            "type":"Services"
        }
    ],
    "sg:phone":"+43 3338 2528",
    "sg:postcode":"8232",
    "sg:province":"Steiermark",
    "sg:tags":[
        "tub",
        "bath"
    ],
    "wof:name":"Ing. Herbert Kopper",
    "wof:placetype":"venue"
},
  "geometry": {"coordinates":[15.9579706192,47.3341445923],"type":"Point"}
}