{
  "type": "Feature",
  "properties": {
    "iso:country":"AT",
    "sg:address":"Siezenheimer Strasse 64",
    "sg:city":"Salzburg",
    "sg:classifiers":[
        {
            "category":"Building & Trades",
            "subcategory":"Plumbing",
            "type":"Services"
        }
    ],
    "sg:phone":"+43 662 439222",
    "sg:postcode":"5020",
    "sg:province":"Salzburg",
    "sg:tags":[
        "tub",
        "bath"
    ],
    "wof:name":"Josef Modl Ges.m.b.H",
    "wof:placetype":"venue"
},
  "geometry": {"coordinates":[13.0010728836,47.8075218201],"type":"Point"}
}