{
  "type": "Feature",
  "properties": {
    "addr:full":"Wiedner Hauptstr 64/9 Wien Wien 1040",
    "addr:housenumber":"64 / 9",
    "addr:postcode":"1040",
    "addr:street":"Hauptstr",
    "iso:country":"AT",
    "sg:address":"Wiedner Hauptstr 64/9",
    "sg:city":"Wien",
    "sg:orig_category":"Institute",
    "sg:phone":"+43 1 5850473",
    "sg:postcode":"1040",
    "sg:province":"Wien",
    "wof:name":"\u00f6sterreichisches Institut f Ged\u00e4chtnistraining",
    "wof:placetype":"venue"
},
  "geometry": {"coordinates":[16.3661518097,48.1905632019],"type":"Point"}
}