{
  "type": "Feature",
  "properties": {
    "addr:full":"Untergro\u00dfau 210/Gewerbepark Sinabelkirchen Steiermark 8261",
    "addr:housenumber":"210 /",
    "addr:postcode":"8261",
    "addr:street":"Untergrossau;Gewerbepark Sinabelkirchen Steiermark",
    "iso:country":"AT",
    "sg:address":"Untergro\u00dfau 210/Gewerbepark",
    "sg:city":"Sinabelkirchen",
    "sg:orig_category":"Maschinenbau",
    "sg:phone":"+43 3118 50055",
    "sg:postcode":"8261",
    "sg:province":"Steiermark",
    "wof:name":"Hajek Othmar Ing",
    "wof:placetype":"venue"
},
  "geometry": {"coordinates":[15.8282032013,47.1025505066],"type":"Point"}
}