{
  "type": "Feature",
  "properties": {
    "iso:country":"AT",
    "sg:address":"Bahnhofstr 3",
    "sg:city":"Hohenems",
    "sg:orig_category":"Physiotherapie",
    "sg:phone":"+43 5576 7351622",
    "sg:postcode":"6845",
    "sg:province":"Vorarlberg",
    "wof:name":"Amann Karin Dipl-PT",
    "wof:placetype":"venue"
},
  "geometry": {"coordinates":[9.6869001389,47.361415863],"type":"Point"}
}