{
  "type": "Feature",
  "properties": {
    "addr:full":"Lengdorfer Str 8 Niedernsill Salzburg 5722",
    "addr:housenumber":"8",
    "addr:postcode":"5722",
    "addr:street":"Str;Salzburg",
    "iso:country":"AT",
    "sg:address":"Lengdorfer Str 8",
    "sg:city":"Niedernsill",
    "sg:orig_category":"Transportunternehmen",
    "sg:phone":"+43 6548 85200",
    "sg:postcode":"5722",
    "sg:province":"Salzburg",
    "wof:name":"Steiner Transport GmbH",
    "wof:placetype":"venue"
},
  "geometry": {"coordinates":[12.6270446777,47.2833709717],"type":"Point"}
}