{
  "type": "Feature",
  "properties": {
    "addr:full":"Marktpl 37 Langschlag Nieder\u00f6sterreich 3921",
    "addr:housenumber":"37",
    "addr:postcode":"3921",
    "addr:street":"Marktpl",
    "iso:country":"AT",
    "sg:address":"Marktpl 37",
    "sg:city":"Langschlag",
    "sg:orig_category":"Gemeinden",
    "sg:phone":"+43 2814 8218",
    "sg:postcode":"3921",
    "sg:province":"Nieder\u00f6sterreich",
    "wof:name":"Gemeindeamt Langschlag",
    "wof:placetype":"venue"
},
  "geometry": {"coordinates":[14.8837966919,48.5754699707],"type":"Point"}
}