{
  "type": "Feature",
  "properties": {
    "addr:full":"Engerthstr 237 Wien Wien 1020",
    "addr:housenumber":"237",
    "addr:postcode":"1020",
    "iso:country":"AT",
    "sg:address":"Engerthstr 237",
    "sg:city":"Wien",
    "sg:orig_category":"Restaurants: Chinesisch",
    "sg:phone":"+43 1 7283715",
    "sg:postcode":"1020",
    "sg:province":"Wien",
    "wof:name":"China-Restaurant Gedeihen",
    "wof:placetype":"venue"
},
  "geometry": {"coordinates":[16.4132328033,48.2174720764],"type":"Point"}
}