{
  "type": "Feature",
  "properties": {
    "addr:full":"Alpenstr 95-97 Salzburg Salzburg 5020",
    "addr:postcode":"95-97;5020",
    "addr:street":"Salzburg",
    "iso:country":"AT",
    "sg:address":"Alpenstr 95-97",
    "sg:city":"Salzburg",
    "sg:orig_category":"Fitnesscenter",
    "sg:phone":"+43 662 6250850",
    "sg:postcode":"5020",
    "sg:province":"Salzburg",
    "sg:website":"vitaclub.at",
    "wof:name":"VITA CLUB S\u00dcD - Vita-Club VC-Fitness GmbH",
    "wof:placetype":"venue"
},
  "geometry": {"coordinates":[13.0690374374,47.7761573792],"type":"Point"}
}