{
  "type": "Feature",
  "properties": {
    "addr:full":"Hauptstr 24 Sigmundsherberg Nieder\u00f6sterreich 3751",
    "addr:housenumber":"24",
    "addr:postcode":"3751",
    "addr:street":"Hauptstr",
    "iso:country":"AT",
    "sg:address":"Hauptstr 24",
    "sg:city":"Sigmundsherberg",
    "sg:orig_category":"Friseure U Frisiersalons",
    "sg:phone":"+43 2983 2471",
    "sg:postcode":"3751",
    "sg:province":"Nieder\u00f6sterreich",
    "wof:name":"Frisierstube D\u00f6lcher",
    "wof:placetype":"venue"
},
  "geometry": {"coordinates":[15.7471237183,48.686164856],"type":"Point"}
}