{
  "type": "Feature",
  "properties": {
    "addr:full":"Enge 1 Hollabrunn Nieder\u00f6sterreich 2020",
    "addr:housenumber":"1",
    "addr:postcode":"2020",
    "addr:street":"Enge",
    "iso:country":"AT",
    "sg:address":"Enge 1",
    "sg:city":"Hollabrunn",
    "sg:classifiers":[
        {
            "category":"Banks & Credit Unions",
            "subcategory":"Investment Brokerage",
            "type":"Services"
        }
    ],
    "sg:phone":"+43 4329 525772",
    "sg:postcode":"2020",
    "sg:province":"Nieder\u00f6sterreich",
    "sg:tags":[
        "management",
        "facility"
    ],
    "wof:name":"SEITEC GesmbH - Facility Management",
    "wof:placetype":"venue"
},
  "geometry": {"coordinates":[16.0820178986,48.5658721924],"type":"Point"}
}