{
  "type": "Feature",
  "properties": {
    "addr:full":"Gagering 35 F\u00fcgen Tirol 6263",
    "addr:housenumber":"35",
    "addr:postcode":"6263",
    "addr:street":"Gagering;Tirol",
    "iso:country":"AT",
    "sg:address":"Gagering 35",
    "sg:city":"F\u00fcgen",
    "sg:classifiers":[
        {
            "category":"Home & Garden",
            "subcategory":"Building Materials",
            "type":"Retail Goods"
        }
    ],
    "sg:phone":"+43 5288 64147",
    "sg:postcode":"6263",
    "sg:province":"Tirol",
    "sg:tags":[
        "bonding",
        "plaster"
    ],
    "sg:website":"eberharter-gruber.at",
    "wof:name":"Eberharter-Gruber Ges.m.b.H.",
    "wof:placetype":"venue"
},
  "geometry": {"coordinates":[11.8522386551,47.3594703674],"type":"Point"}
}