{
  "type": "Feature",
  "properties": {
    "addr:full":"Landrichterstrasse 5 Rankweil Vorarlberg 6830",
    "addr:housenumber":"5",
    "addr:postcode":"6830",
    "addr:street":"Landrichterstrasse",
    "iso:country":"AT",
    "sg:address":"Landrichterstrasse 5",
    "sg:city":"Rankweil",
    "sg:classifiers":[
        {
            "category":"Home & Garden",
            "subcategory":"Carpets & Floor Coverings",
            "type":"Retail Goods"
        }
    ],
    "sg:phone":"+43 5522 44602",
    "sg:postcode":"6830",
    "sg:province":"Vorarlberg",
    "sg:tags":[
        "carpeting"
    ],
    "wof:name":"M. SCHERRER Der Raumausstatter Ges.m.b.H.",
    "wof:placetype":"venue"
},
  "geometry": {"coordinates":[9.6502017975,47.2763137817],"type":"Point"}
}