{
  "type": "Feature",
  "properties": {
    "addr:full":"Sobieskig 37/(im Hof) Wien Wien 1090",
    "addr:housenumber":"37 / im hof",
    "addr:postcode":"1090",
    "addr:street":"Sobieskig",
    "iso:country":"AT",
    "sg:address":"Sobieskig 37/(im Hof)",
    "sg:city":"Wien",
    "sg:orig_category":"Fotografen",
    "sg:phone":"+43 4366 43945254",
    "sg:postcode":"1090",
    "sg:province":"Wien",
    "wof:name":"Sazel Michael",
    "wof:placetype":"venue"
},
  "geometry": {"coordinates":[16.3528862,48.230682373],"type":"Point"}
}