{
  "type": "Feature",
  "properties": {
    "addr:full":"Canisiusg 25 Wien Wien 1090",
    "addr:housenumber":"25",
    "addr:postcode":"1090",
    "addr:street":"Canisiusg",
    "iso:country":"AT",
    "sg:address":"Canisiusg 25",
    "sg:city":"Wien",
    "sg:orig_category":"Friseure U Frisiersalons",
    "sg:phone":"+43 1 3176121",
    "sg:postcode":"1090",
    "sg:province":"Wien",
    "wof:name":"Renner Gertrude",
    "wof:placetype":"venue"
},
  "geometry": {"coordinates":[16.3512496948,48.2279930115],"type":"Point"}
}