{
  "type": "Feature",
  "properties": {
    "addr:full":"Maxglaner Hauptstr 50 Salzburg Salzburg 5020",
    "addr:housenumber":"50",
    "addr:postcode":"5020",
    "addr:street":"Maxglaner Hauptstr;Salzburg",
    "iso:country":"AT",
    "sg:address":"Maxglaner Hauptstr 50",
    "sg:city":"Salzburg",
    "sg:classifiers":[
        {
            "category":"Professional",
            "subcategory":"Computer Services",
            "type":"Services"
        }
    ],
    "sg:phone":"+43 662 832232",
    "sg:postcode":"5020",
    "sg:province":"Salzburg",
    "sg:tags":[
        "software"
    ],
    "wof:name":"CCS GmbH",
    "wof:placetype":"venue"
},
  "geometry": {"coordinates":[13.019197464,47.7987861633],"type":"Point"}
}