{
  "type": "Feature",
  "properties": {
    "iso:country":"AT",
    "sg:address":"Paracelsusstr 4",
    "sg:city":"Salzburg",
    "sg:classifiers":[
        {
            "category":"Organizations",
            "subcategory":"Community Association",
            "type":"Services"
        }
    ],
    "sg:phone":"+43 662 6202420",
    "sg:postcode":"5020",
    "sg:province":"Salzburg",
    "sg:tags":[
        "relation",
        "public"
    ],
    "wof:name":"Publico ECC Salzburg Public Relations GesmbH",
    "wof:placetype":"venue"
},
  "geometry": {"coordinates":[13.0470285416,47.8075485229],"type":"Point"}
}