{
  "type": "Feature",
  "properties": {
    "iso:country":"AT",
    "sg:address":"Gro\u00df Enzersdorfer Str 59",
    "sg:city":"Wien",
    "sg:classifiers":[
        {
            "category":"Government",
            "subcategory":"Post Office",
            "type":"Public Place"
        }
    ],
    "sg:phone":"+43 4312 88660",
    "sg:postcode":"1220",
    "sg:province":"Wien",
    "sg:tags":[
        "motorenbestandteile",
        "-material",
        "u"
    ],
    "wof:name":"Delphi Automotive Systems Vienna GmbH",
    "wof:placetype":"venue"
},
  "geometry": {"coordinates":[16.4999141693,48.2181396484],"type":"Point"}
}