{
  "type": "Feature",
  "properties": {
    "iso:country":"AT",
    "sg:address":"Osterwiese 2 ",
    "sg:city":"Eisenstadt",
    "sg:classifiers":[
        {
            "category":"Banks & Credit Unions",
            "subcategory":"Financial Services",
            "type":"Services"
        }
    ],
    "sg:phone":"+43 4326 82625310",
    "sg:postcode":"7000",
    "sg:province":"Burgenland",
    "sg:tags":[
        "banking",
        "finance",
        "insurance"
    ],
    "wof:name":"SOZIALVERSICHERUNGSANSTALT DER GERWERBLICHEN WIRTSCHAFT",
    "wof:placetype":"venue"
},
  "geometry": {"coordinates":[16.5295543671,47.8472709656],"type":"Point"}
}