{
  "type": "Feature",
  "properties": {
    "addr:full":"Goethestr 4 St. Valentin Nieder\u00f6sterreich 4300",
    "addr:housenumber":"4",
    "addr:postcode":"4300",
    "addr:street":"Goethestr",
    "iso:country":"AT",
    "sg:address":"Goethestr 4",
    "sg:city":"St. Valentin",
    "sg:orig_category":"Maler, Anstreicher U Lackierer",
    "sg:phone":"+43 4374 3554230",
    "sg:postcode":"4300",
    "sg:province":"Nieder\u00f6sterreich",
    "wof:name":"Kleindl Franz",
    "wof:placetype":"venue"
},
  "geometry": {"coordinates":[14.5132226944,48.1606521606],"type":"Point"}
}