{
  "type": "Feature",
  "properties": {
    "iso:country":"AT",
    "sg:address":"K\u00f6stenbaumg 17",
    "sg:city":"Graz",
    "sg:orig_category":"Fenster",
    "sg:phone":"+43 316 721550",
    "sg:postcode":"8020",
    "sg:province":"Steiermark",
    "sg:website":"newline.at",
    "wof:name":"Newline HandelsgesmbH",
    "wof:placetype":"venue"
},
  "geometry": {"coordinates":[15.4284543991,47.0614852905],"type":"Point"}
}