{
  "type": "Feature",
  "properties": {
    "iso:country":"AT",
    "sg:address":"Welser Str 35-39",
    "sg:city":"Leonding",
    "sg:orig_category":"Lebensmittel / Einzelhandel",
    "sg:phone":"+43 4373 2602666",
    "sg:postcode":"4060",
    "sg:province":"Ober\u00f6sterreich",
    "wof:name":"Asien Shop",
    "wof:placetype":"venue"
},
  "geometry": {"coordinates":[14.2662982941,48.2683563232],"type":"Point"}
}