{
  "type": "Feature",
  "properties": {
    "addr:full":"Schiemerstr 2 Hallein Salzburg 5400",
    "addr:housenumber":"2",
    "addr:postcode":"5400",
    "addr:street":"Schiemerstr;Salzburg",
    "iso:country":"AT",
    "sg:address":"Schiemerstr 2",
    "sg:city":"Hallein",
    "sg:orig_category":"Diskotheken",
    "sg:phone":"+43 664 5264631",
    "sg:postcode":"5400",
    "sg:province":"Salzburg",
    "wof:name":"Tanzbar Disco Papillon",
    "wof:placetype":"venue"
},
  "geometry": {"coordinates":[13.0921401978,47.6836204529],"type":"Point"}
}