{
  "type": "Feature",
  "properties": {
    "addr:full":"P\u00f6ttschinger Str 7 Lichtenw\u00f6rth Nieder\u00f6sterreich 2493",
    "addr:housenumber":"7",
    "addr:postcode":"2493",
    "addr:street":"Str;Niederoesterreich",
    "iso:country":"AT",
    "sg:address":"P\u00f6ttschinger Str 7",
    "sg:city":"Lichtenw\u00f6rth",
    "sg:orig_category":"Erdarbeiten",
    "sg:phone":"+43 2622 75459",
    "sg:postcode":"2493",
    "sg:province":"Nieder\u00f6sterreich",
    "wof:name":"Lehner Alois GmbH",
    "wof:placetype":"venue"
},
  "geometry": {"coordinates":[9.1929798126,48.6895484924],"type":"Point"}
}