{
  "type": "Feature",
  "properties": {
    "addr:full":"Sonnenstr 2a Wolfurt Vorarlberg 6922",
    "addr:housenumber":"2a",
    "addr:postcode":"6922",
    "addr:street":"Sonnenstr",
    "iso:country":"AT",
    "sg:address":"Sonnenstr 2a",
    "sg:city":"Wolfurt",
    "sg:classifiers":[
        {
            "category":"Professional",
            "subcategory":"Management & Consulting",
            "type":"Services"
        }
    ],
    "sg:phone":"+43 664 5425447",
    "sg:postcode":"6922",
    "sg:province":"Vorarlberg",
    "sg:tags":[
        "supervision"
    ],
    "wof:name":"Deimel Jutta Dipl-Psych",
    "wof:placetype":"venue"
},
  "geometry": {"coordinates":[9.7451677322,47.4683532715],"type":"Point"}
}