{
  "type": "Feature",
  "properties": {
    "addr:full":"Ghegastr 24 Knittelfeld Steiermark 8720",
    "addr:housenumber":"24",
    "addr:postcode":"8720",
    "addr:street":"Ghegastr",
    "iso:country":"AT",
    "sg:address":"Ghegastr 24",
    "sg:city":"Knittelfeld",
    "sg:orig_category":"Torantriebe",
    "sg:phone":"+43 3512 74204",
    "sg:postcode":"8720",
    "sg:province":"Steiermark",
    "wof:name":"Moitzi Guttomat-Torprofi",
    "wof:placetype":"venue"
},
  "geometry": {"coordinates":[14.8144140244,47.2105941772],"type":"Point"}
}