{
  "type": "Feature",
  "properties": {
    "iso:country":"AT",
    "sg:address":"Nr 70",
    "sg:city":"Sirnitz",
    "sg:classifiers":[
        {
            "category":"Travel",
            "subcategory":"Hotels & Motels",
            "type":"Entertainment"
        }
    ],
    "sg:phone":"+43 4279 7352",
    "sg:postcode":"9571",
    "sg:province":"K\u00e4rnten",
    "wof:name":"Alpenhotel Ludwig",
    "wof:placetype":"venue"
},
  "geometry": {"coordinates":[14.0589342117,46.8222122192],"type":"Point"}
}