{
  "type": "Feature",
  "properties": {
    "iso:country":"AT",
    "sg:address":"Hauptstr 76",
    "sg:city":"Frankenmarkt",
    "sg:orig_category":"Bars-Cafes",
    "sg:phone":"+43 76846455",
    "sg:postcode":"4890",
    "sg:province":"Ober\u00f6sterreich",
    "wof:name":"Milla's Bar",
    "wof:placetype":"venue"
},
  "geometry": {"coordinates":[13.4210300446,47.9857597351],"type":"Point"}
}