{
  "type": "Feature",
  "properties": {
    "addr:full":"Museumstr 8 Innsbruck Tirol 6020",
    "addr:housenumber":"8",
    "addr:postcode":"6020",
    "addr:street":"Museumstr;Tirol",
    "iso:country":"AT",
    "sg:address":"Museumstr 8",
    "sg:city":"Innsbruck",
    "sg:orig_category":"Nachhilfe U Lernbetreuung",
    "sg:phone":"+43 512 582620",
    "sg:postcode":"6020",
    "sg:province":"Tirol",
    "wof:name":"Nachhilfeschule Eureka",
    "wof:placetype":"venue"
},
  "geometry": {"coordinates":[11.3958692551,47.2671012878],"type":"Point"}
}