{
  "type": "Feature",
  "properties": {
    "iso:country":"AT",
    "sg:address":"Wenzelberg 1",
    "sg:city":"Vichtenstein",
    "sg:orig_category":"Bergbahnen",
    "sg:phone":"+43 7714 80550",
    "sg:postcode":"4091",
    "sg:province":"Ober\u00f6sterreich",
    "wof:name":"Haugstein Lifte GesmbH",
    "wof:placetype":"venue"
},
  "geometry": {"coordinates":[13.6780786514,48.5164260864],"type":"Point"}
}