{
  "type": "Feature",
  "properties": {
    "addr:full":"Salzburger Str 24 Hall in Tirol Tirol 6060",
    "addr:housenumber":"24",
    "addr:postcode":"6060",
    "addr:street":"Salzburger Str;Tirol",
    "iso:country":"AT",
    "sg:address":"Salzburger Str 24",
    "sg:city":"Hall in Tirol",
    "sg:orig_category":"Armaturen / Erzeugung U Gro\u00c3\u0178handel",
    "sg:phone":"+43 4352 23577110",
    "sg:postcode":"6060",
    "sg:province":"Tirol",
    "wof:name":"Schmiedl Gustav Armaturenfabrik GesmbH & Co KG",
    "wof:placetype":"venue"
},
  "geometry": {"coordinates":[11.51633358,47.2803726196],"type":"Point"}
}