{
  "type": "Feature",
  "properties": {
    "addr:full":"Petersgasse 45 Graz Steiermark 8010",
    "addr:housenumber":"45",
    "addr:postcode":"8010",
    "addr:street":"Petersgasse",
    "iso:country":"AT",
    "sg:address":"Petersgasse 45",
    "sg:city":"Graz",
    "sg:classifiers":[
        {
            "category":"Structure",
            "subcategory":"Office Building",
            "type":"Public Place"
        }
    ],
    "sg:phone":"+43 316 80890",
    "sg:postcode":"8010",
    "sg:province":"Steiermark",
    "sg:tags":[
        "compact",
        "systems",
        "air conditioning"
    ],
    "sg:website":"air-cond.com",
    "wof:name":"Air-Cond Klimaanlagen Handelsges.m.b.H. Toshiba Vertriebsorganisation \u00d6sterreich, Osteuropa",
    "wof:placetype":"venue"
},
  "geometry": {"coordinates":[15.4566545486,47.0632133484],"type":"Point"}
}