{
  "type": "Feature",
  "properties": {
    "iso:country":"AT",
    "sg:address":"Lassallestr 30",
    "sg:city":"Wien",
    "sg:orig_category":"Erdarbeiten",
    "sg:phone":"+43 1 7263514",
    "sg:postcode":"1020",
    "sg:province":"Wien",
    "wof:name":"Bulduk Ahmet GesmbH",
    "wof:placetype":"venue"
},
  "geometry": {"coordinates":[16.3996124268,48.2225837708],"type":"Point"}
}