{
  "type": "Feature",
  "properties": {
    "iso:country":"AT",
    "sg:address":"L v Hildebrandt-G 5",
    "sg:city":"Parndorf",
    "sg:orig_category":"Entsorgungen",
    "sg:phone":"+43 2166 20817",
    "sg:postcode":"7111",
    "sg:province":"Burgenland",
    "wof:name":"ROFA FASTL EDV Verwertungs- und Vertriebs-KEG",
    "wof:placetype":"venue"
},
  "geometry": {"coordinates":[16.8575897217,47.9981613159],"type":"Point"}
}