{
  "type": "Feature",
  "properties": {
    "addr:full":"Industriezentrum N\u00f6 S\u00fcd Stra\u00dfe 3 Obj 6 Wiener Neudorf Nieder\u00f6sterreich 2351",
    "addr:housenumber":"3 obj 6",
    "addr:postcode":"2351",
    "addr:street":"Industriezentrum Noe Sued Strasse",
    "iso:country":"AT",
    "sg:address":"Industriezentrum N\u00f6 S\u00fcd Stra\u00dfe 3 Obj 6",
    "sg:city":"Wiener Neudorf",
    "sg:orig_category":"Gabelstapler",
    "sg:phone":"+43 4322 36615010",
    "sg:postcode":"2351",
    "sg:province":"Nieder\u00f6sterreich",
    "wof:name":"STILL GESELLSCHAFT M.B.H.",
    "wof:placetype":"venue"
},
  "geometry": {"coordinates":[16.3183326721,48.0863113403],"type":"Point"}
}