{
  "type": "Feature",
  "properties": {
    "addr:full":"Floridusgasse 60  Wien Wien 1210",
    "addr:housenumber":"60",
    "addr:postcode":"1210",
    "addr:street":"Floridusgasse",
    "iso:country":"AT",
    "sg:address":"Floridusgasse 60 ",
    "sg:city":"Wien",
    "sg:orig_category":"Caps Headwear",
    "sg:phone":"+43 1 2568616",
    "sg:postcode":"1210",
    "sg:province":"Wien",
    "wof:name":"Vienna Hutfabrik Ges.m.b.H.",
    "wof:placetype":"venue"
},
  "geometry": {"coordinates":[16.4142036438,48.248790741],"type":"Point"}
}