{
  "type": "Feature",
  "properties": {
    "addr:full":"Schwarzstr 46 Salzburg Salzburg 5020",
    "addr:housenumber":"46",
    "addr:postcode":"5020",
    "addr:street":"Schwarzstr;Salzburg",
    "iso:country":"AT",
    "sg:address":"Schwarzstr 46",
    "sg:city":"Salzburg",
    "sg:orig_category":"Werbeagenturen",
    "sg:phone":"+43 662 8763210",
    "sg:postcode":"5020",
    "sg:province":"Salzburg",
    "wof:name":"Agentur Team 2 WerbegesmbH",
    "wof:placetype":"venue"
},
  "geometry": {"coordinates":[13.0385942459,47.8082427979],"type":"Point"}
}