{
  "type": "Feature",
  "properties": {
    "addr:full":"Nr 12 Kitzeck im Sausal Steiermark 8442",
    "addr:postcode":"8442",
    "addr:street":"Nr",
    "iso:country":"AT",
    "sg:address":"Nr 12",
    "sg:city":"Kitzeck im Sausal",
    "sg:orig_category":"Non-Classified Establishments",
    "sg:phone":"+43 3456 2420",
    "sg:postcode":"8442",
    "sg:province":"Steiermark",
    "wof:name":"Pfarramt",
    "wof:placetype":"venue"
},
  "geometry": {"coordinates":[15.4540109634,46.7809333801],"type":"Point"}
}