{
  "type": "Feature",
  "properties": {
    "addr:full":"Weidlinger Str 39 Klosterneuburg Nieder\u00f6sterreich 3400",
    "addr:housenumber":"39",
    "addr:postcode":"3400",
    "addr:street":"Str;Niederoesterreich",
    "iso:country":"AT",
    "sg:address":"Weidlinger Str 39",
    "sg:city":"Klosterneuburg",
    "sg:classifiers":[
        {
            "category":"Restaurant",
            "type":"Food & Drink"
        }
    ],
    "sg:phone":"+43 2243 20610",
    "sg:postcode":"3400",
    "sg:province":"Nieder\u00f6sterreich",
    "sg:tags":[
        "pizzeria"
    ],
    "wof:name":"Pizzeria Trattoria Castelnuovo",
    "wof:placetype":"venue"
},
  "geometry": {"coordinates":[16.3283348083,48.2948646545],"type":"Point"}
}