{
  "type": "Feature",
  "properties": {
    "addr:full":"Anglerweg 18 Salzburg Salzburg 5020",
    "addr:housenumber":"18",
    "addr:postcode":"5020",
    "addr:street":"Anglerweg;Salzburg",
    "iso:country":"AT",
    "sg:address":"Anglerweg 18",
    "sg:city":"Salzburg",
    "sg:orig_category":"Bildhauer",
    "sg:phone":"+43 662 436311",
    "sg:postcode":"5020",
    "sg:province":"Salzburg",
    "wof:name":"Macala Stephan",
    "wof:placetype":"venue"
},
  "geometry": {"coordinates":[13.008515358,47.8297996521],"type":"Point"}
}