{
  "type": "Feature",
  "properties": {
    "addr:full":"Wollingerg 5 Jennersdorf Burgenland 8380",
    "addr:housenumber":"5",
    "addr:postcode":"8380",
    "addr:street":"Wollingerg",
    "iso:country":"AT",
    "sg:address":"Wollingerg 5",
    "sg:city":"Jennersdorf",
    "sg:orig_category":"Feuerwehren",
    "sg:phone":"+43 3329 45055",
    "sg:postcode":"8380",
    "sg:province":"Burgenland",
    "wof:name":"Stadtfeuerwehr Jennersdorf",
    "wof:placetype":"venue"
},
  "geometry": {"coordinates":[16.1458854675,46.936000824],"type":"Point"}
}