{
  "type": "Feature",
  "properties": {
    "addr:full":"Dr.-Karl-Renner-Pl 1 Traiskirchen Nieder\u00f6sterreich 2514",
    "addr:housenumber":"1",
    "addr:postcode":"2514",
    "addr:street":"Dr.-Karl-Renner-Pl;Niederoesterreich",
    "iso:country":"AT",
    "sg:address":"Dr.-Karl-Renner-Pl 1",
    "sg:city":"Traiskirchen",
    "sg:orig_category":"Raumausstattung",
    "sg:phone":"+43 2252 524410",
    "sg:postcode":"2514",
    "sg:province":"Nieder\u00f6sterreich",
    "wof:name":"Gaster GesmbH",
    "wof:placetype":"venue"
},
  "geometry": {"coordinates":[16.2931632996,48.0151863098],"type":"Point"}
}