{
  "type": "Feature",
  "properties": {
    "addr:full":"Rudolfinerg 16-18 Wien Wien 1190",
    "addr:postcode":"16-18;1190",
    "iso:country":"AT",
    "sg:address":"Rudolfinerg 16-18",
    "sg:city":"Wien",
    "sg:orig_category":"Botschaften",
    "sg:phone":"+43 1 36988530",
    "sg:postcode":"1190",
    "sg:province":"Wien",
    "wof:name":"Botschaft der Demokratischen Volksrepublik Algerien",
    "wof:placetype":"venue"
},
  "geometry": {"coordinates":[16.3468532562,48.2443389893],"type":"Point"}
}