{
  "type": "Feature",
  "properties": {
    "addr:full":"Marktpl 21 Ottensheim Ober\u00f6sterreich 4100",
    "addr:housenumber":"21",
    "addr:postcode":"4100",
    "addr:street":"Marktpl",
    "iso:country":"AT",
    "sg:address":"Marktpl 21",
    "sg:city":"Ottensheim",
    "sg:classifiers":[
        {
            "category":"Restaurant",
            "type":"Food & Drink"
        }
    ],
    "sg:phone":"+43 7234 85055",
    "sg:postcode":"4100",
    "sg:province":"Ober\u00f6sterreich",
    "sg:tags":[
        "pizzeria"
    ],
    "wof:name":"Pizzeria Casa Vecchia",
    "wof:placetype":"venue"
},
  "geometry": {"coordinates":[14.1759681702,48.3315391541],"type":"Point"}
}