{
  "type": "Feature",
  "properties": {
    "iso:country":"AT",
    "sg:address":"Nr 26",
    "sg:city":"F\u00fcrstenfeld",
    "sg:orig_category":"Bankomat-Standorte",
    "sg:phone":"+43 3382 527120",
    "sg:postcode":"8280",
    "sg:province":"Steiermark",
    "wof:name":"Bankomat d Raiffeisenbank F\u00fcrstenfeld",
    "wof:placetype":"venue"
},
  "geometry": {"coordinates":[16.0748786926,47.0515441895],"type":"Point"}
}