{
  "type": "Feature",
  "properties": {
    "addr:full":"Mitterhofen 85 Maishofen Salzburg 5751",
    "addr:housenumber":"85",
    "addr:postcode":"5751",
    "addr:street":"Mitterhofen;Salzburg",
    "iso:country":"AT",
    "sg:address":"Mitterhofen 85",
    "sg:city":"Maishofen",
    "sg:orig_category":"Brandschutz",
    "sg:phone":"+43 6542 689840",
    "sg:postcode":"5751",
    "sg:province":"Salzburg",
    "wof:name":"Moser Ferdinand",
    "wof:placetype":"venue"
},
  "geometry": {"coordinates":[12.8200283051,47.3817634583],"type":"Point"}
}