{
  "type": "Feature",
  "properties": {
    "iso:country":"AT",
    "sg:address":"Am Salcher 5",
    "sg:city":"Gresten",
    "sg:orig_category":"Zimmereien",
    "sg:phone":"+43 4367 65379778",
    "sg:postcode":"3264",
    "sg:province":"Nieder\u00f6sterreich",
    "wof:name":"Harreither Rudolf Zimmermeister",
    "wof:placetype":"venue"
},
  "geometry": {"coordinates":[15.0246610641,47.9799003601],"type":"Point"}
}