{
  "type": "Feature",
  "properties": {
    "addr:full":"Priesterhausg 5 Klagenfurt K\u00e4rnten 9020",
    "addr:housenumber":"5",
    "addr:postcode":"9020",
    "addr:street":"Priesterhausg;Kaernten",
    "iso:country":"AT",
    "sg:address":"Priesterhausg 5",
    "sg:city":"Klagenfurt",
    "sg:classifiers":[
        {
            "category":"Travel",
            "subcategory":"Hotels & Motels",
            "type":"Entertainment"
        }
    ],
    "sg:phone":"+43 463 578860",
    "sg:postcode":"9020",
    "sg:province":"K\u00e4rnten",
    "sg:website":"hotelgeyer.com",
    "wof:name":"Hotel Geyer",
    "wof:placetype":"venue"
},
  "geometry": {"coordinates":[14.3121328354,46.6258621216],"type":"Point"}
}