{
  "type": "Feature",
  "properties": {
    "addr:full":"Unionstrasse 97 Linz Ober\u00f6sterreich 4020",
    "addr:housenumber":"97",
    "addr:postcode":"4020",
    "addr:street":"Unionstrasse",
    "iso:country":"AT",
    "sg:address":"Unionstrasse 97",
    "sg:city":"Linz",
    "sg:classifiers":[
        {
            "category":"Building & Trades",
            "subcategory":"Electrical",
            "type":"Services"
        }
    ],
    "sg:phone":"+43 732 671325",
    "sg:postcode":"4020",
    "sg:province":"Ober\u00f6sterreich",
    "sg:tags":[
        "installation"
    ],
    "wof:name":"Dumfart & Co Gas- und Wasserleitungs Installationsges.m.b.H. & Co KG",
    "wof:placetype":"venue"
},
  "geometry": {"coordinates":[14.2824344635,48.2805976868],"type":"Point"}
}