{
  "type": "Feature",
  "properties": {
    "iso:country":"AT",
    "sg:address":"Birkfelder Str 40",
    "sg:city":"Weiz",
    "sg:orig_category":"Lebensmittel / Einzelhandel",
    "sg:phone":"+43 3172 42406",
    "sg:postcode":"8160",
    "sg:province":"Steiermark",
    "wof:name":"Billa AG",
    "wof:placetype":"venue"
},
  "geometry": {"coordinates":[15.6315937042,47.2187843323],"type":"Point"}
}