{
  "type": "Feature",
  "properties": {
    "addr:full":"Salzweg 47 Wals Salzburg 5071",
    "addr:housenumber":"47",
    "addr:postcode":"5071",
    "addr:street":"Salzweg;Salzburg",
    "iso:country":"AT",
    "sg:address":"Salzweg 47",
    "sg:city":"Wals",
    "sg:classifiers":[
        {
            "category":"Taxi",
            "type":"Transportation"
        }
    ],
    "sg:phone":"+43 662 853151",
    "sg:postcode":"5071",
    "sg:province":"Salzburg",
    "sg:tags":[
        "personentransporte",
        "u"
    ],
    "wof:name":"Suppik Erwin",
    "wof:placetype":"venue"
},
  "geometry": {"coordinates":[12.9720182419,47.7737541199],"type":"Point"}
}