{
  "type": "Feature",
  "properties": {
    "iso:country":"AT",
    "sg:address":"Markgraf R\u00fcdiger-Str 8",
    "sg:city":"Wien",
    "sg:classifiers":[
        {
            "category":"Organizations",
            "subcategory":"Community Association",
            "type":"Services"
        }
    ],
    "sg:phone":"+43 1 87679560",
    "sg:postcode":"1150",
    "sg:province":"Wien",
    "sg:tags":[
        "relation",
        "public"
    ],
    "wof:name":"Universimed International Publications GmbH",
    "wof:placetype":"venue"
},
  "geometry": {"coordinates":[16.3320903778,48.2006416321],"type":"Point"}
}