{
  "type": "Feature",
  "properties": {
    "addr:full":"Schillerstr 4 Innsbruck Tirol 6020",
    "addr:housenumber":"4",
    "addr:postcode":"6020",
    "addr:street":"Schillerstr;Tirol",
    "iso:country":"AT",
    "sg:address":"Schillerstr 4",
    "sg:city":"Innsbruck",
    "sg:orig_category":"Elektroinstallationsunternehmen",
    "sg:phone":"+43 512 580880",
    "sg:postcode":"6020",
    "sg:province":"Tirol",
    "wof:name":"Ghedina Dino",
    "wof:placetype":"venue"
},
  "geometry": {"coordinates":[11.405714035,47.2752876282],"type":"Point"}
}