{
  "type": "Feature",
  "properties": {
    "addr:full":"Kaiser F Josef-Str 15 Bad Ischl Ober\u00f6sterreich 4820",
    "addr:housenumber":"15",
    "addr:postcode":"4820",
    "addr:street":"Josef-Str",
    "iso:country":"AT",
    "sg:address":"Kaiser F Josef-Str 15",
    "sg:city":"Bad Ischl",
    "sg:orig_category":"Steuerberatung",
    "sg:phone":"+43 6132 236200",
    "sg:postcode":"4820",
    "sg:province":"Ober\u00f6sterreich",
    "wof:name":"Egelkraut Otto Dr iur",
    "wof:placetype":"venue"
},
  "geometry": {"coordinates":[13.6257123947,47.711971283],"type":"Point"}
}