{
  "type": "Feature",
  "properties": {
    "iso:country":"AT",
    "sg:address":"Kaiserbergstr 17",
    "sg:city":"Ebbs",
    "sg:classifiers":[
        {
            "category":"Farming",
            "subcategory":"Livestock Farm",
            "type":"Manufacturing & Wholesale Goods"
        }
    ],
    "sg:phone":"+43 5373 42735",
    "sg:postcode":"6341",
    "sg:province":"Tirol",
    "sg:tags":[
        "-handel",
        "viehzucht",
        "u"
    ],
    "wof:name":"Wildauer Otto K\u00e4lbermastbetrieb",
    "wof:placetype":"venue"
},
  "geometry": {"coordinates":[12.2182273865,47.630027771],"type":"Point"}
}