{
  "type": "Feature",
  "properties": {
    "addr:full":"J\u00e4gerwirtstr 835 Puch Salzburg 5412",
    "addr:housenumber":"835",
    "addr:postcode":"5412",
    "addr:street":"Salzburg",
    "iso:country":"AT",
    "sg:address":"J\u00e4gerwirtstr 835",
    "sg:city":"Puch",
    "sg:orig_category":"Natursteine U -Platten",
    "sg:phone":"+43 4366 44642752",
    "sg:postcode":"5412",
    "sg:province":"Salzburg",
    "wof:name":"Macola L & M Naturstein KEG",
    "wof:placetype":"venue"
},
  "geometry": {"coordinates":[13.0917205811,47.7106323242],"type":"Point"}
}