{
  "type": "Feature",
  "properties": {
    "iso:country":"AT",
    "sg:address":"Lindenstr 4",
    "sg:city":"Reutte",
    "sg:orig_category":"Hobbyvereine",
    "sg:phone":"+43 4356 7271401",
    "sg:postcode":"6600",
    "sg:province":"Tirol",
    "wof:name":"Fu\u00dfball- Freizeit- u Hilfsverein",
    "wof:placetype":"venue"
},
  "geometry": {"coordinates":[10.71733284,47.4888381958],"type":"Point"}
}