{
  "type": "Feature",
  "properties": {
    "addr:full":"Nr 4 Hippach Tirol 6283",
    "addr:postcode":"6283",
    "addr:street":"Nr;Hippach Tirol",
    "iso:country":"AT",
    "sg:address":"Nr 4",
    "sg:city":"Hippach",
    "sg:orig_category":"Lebensmittel / Einzelhandel",
    "sg:phone":"+43 5282 40040",
    "sg:postcode":"6283",
    "sg:province":"Tirol",
    "wof:name":"ADEG Contra Markt",
    "wof:placetype":"venue"
},
  "geometry": {"coordinates":[11.8661670685,47.2039108276],"type":"Point"}
}