{
  "type": "Feature",
  "properties": {
    "iso:country":"AT",
    "sg:address":"Eintrachtg 1",
    "sg:city":"Liebenau",
    "sg:orig_category":"\u00c3\u201erzte- U Spitalsbedarf",
    "sg:phone":"+43 316 403209",
    "sg:postcode":"8041",
    "sg:province":"Steiermark",
    "wof:name":"Bischof Dental",
    "wof:placetype":"venue"
},
  "geometry": {"coordinates":[15.4569787979,47.0226707458],"type":"Point"}
}