{
  "type": "Feature",
  "properties": {
    "addr:full":"Lindeng 5 Wien Wien 1070",
    "addr:housenumber":"5",
    "addr:postcode":"1070",
    "addr:street":"Lindeng",
    "iso:country":"AT",
    "sg:address":"Lindeng 5",
    "sg:city":"Wien",
    "sg:orig_category":"Architekten",
    "sg:phone":"+43 1 5231037",
    "sg:postcode":"1070",
    "sg:province":"Wien",
    "wof:name":"Loidl-Reisch Cordula Dipl-Ing",
    "wof:placetype":"venue"
},
  "geometry": {"coordinates":[16.3546123505,48.2011909485],"type":"Point"}
}