{
  "type": "Feature",
  "properties": {
    "addr:full":"Riedlingsdorf Burgenland 7422",
    "addr:postcode":"7422",
    "iso:country":"AT",
    "sg:city":"Riedlingsdorf",
    "sg:orig_category":"Dienstleistungen, Messen U Veranstaltungen",
    "sg:postcode":"7422",
    "sg:province":"Burgenland",
    "sg:website":"http://www.ronny-net.com/juergen",
    "wof:name":"Showproduktionen J\u00fcrgen Marcus",
    "wof:placetype":"venue"
},
  "geometry": {"coordinates":[16.1364059448,47.3453216553],"type":"Point"}
}