{
  "type": "Feature",
  "properties": {
    "addr:full":"Kehlerstr 56 Dornbirn Vorarlberg 6850",
    "addr:housenumber":"56",
    "addr:postcode":"6850",
    "addr:street":"Kehlerstr",
    "iso:country":"AT",
    "sg:address":"Kehlerstr 56",
    "sg:city":"Dornbirn",
    "sg:orig_category":"Installationsunternehmen",
    "sg:phone":"+43 5572 34421",
    "sg:postcode":"6850",
    "sg:province":"Vorarlberg",
    "wof:name":"Liema - Manfred Liesinger",
    "wof:placetype":"venue"
},
  "geometry": {"coordinates":[9.7559137344,47.4230613708],"type":"Point"}
}