{
  "type": "Feature",
  "properties": {
    "iso:country":"AT",
    "sg:address":"Hietzinger Hauptstr 10",
    "sg:city":"Wien",
    "sg:orig_category":"Boutiquen",
    "sg:phone":"+43 1 8770279",
    "sg:postcode":"1130",
    "sg:province":"Wien",
    "wof:name":"SISLEY in Hietzing",
    "wof:placetype":"venue"
},
  "geometry": {"coordinates":[16.3023529053,48.1866569519],"type":"Point"}
}