{
  "type": "Feature",
  "properties": {
    "iso:country":"AT",
    "sg:address":"Sperberegg",
    "sg:city":"Lans",
    "sg:classifiers":[
        {
            "category":"Restaurant",
            "type":"Food & Drink"
        }
    ],
    "sg:phone":"+43 512 378816",
    "sg:postcode":"6072",
    "sg:province":"Tirol",
    "wof:name":"Golfrestaurant Walter Steirer",
    "wof:placetype":"venue"
},
  "geometry": {"coordinates":[11.4270954132,47.2437286377],"type":"Point"}
}