{
  "type": "Feature",
  "properties": {
    "addr:full":"Feldbacher Str 28 St. Stefan im Rosental Steiermark 8083",
    "addr:housenumber":"28",
    "addr:postcode":"8083",
    "addr:street":"Str",
    "iso:country":"AT",
    "sg:address":"Feldbacher Str 28",
    "sg:city":"St. Stefan im Rosental",
    "sg:orig_category":"Tischlereien",
    "sg:phone":"+43 4331 1682280",
    "sg:postcode":"8083",
    "sg:province":"Steiermark",
    "wof:name":"Ladenstein GesmbH",
    "wof:placetype":"venue"
},
  "geometry": {"coordinates":[15.7120189667,46.9067306519],"type":"Point"}
}