{
  "type": "Feature",
  "properties": {
    "addr:full":"Linke Hauptzeile 29 Hornstein Burgenland 7053",
    "addr:housenumber":"29",
    "addr:postcode":"7053",
    "addr:street":"Linke Hauptzeile",
    "iso:country":"AT",
    "sg:address":"Linke Hauptzeile 29",
    "sg:city":"Hornstein",
    "sg:orig_category":"Gutsverwaltungen",
    "sg:phone":"+43 2689 22010",
    "sg:postcode":"7053",
    "sg:province":"Burgenland",
    "wof:name":"Dworzak Stefan Dipl-Ing",
    "wof:placetype":"venue"
},
  "geometry": {"coordinates":[16.4441337585,47.8807106018],"type":"Point"}
}