{
  "type": "Feature",
  "properties": {
    "addr:full":"Breinberg Nord 63 Neumarkt am Wallersee Salzburg 5202",
    "addr:housenumber":"63",
    "addr:postcode":"5202",
    "addr:street":"Breinberg Nord;Salzburg",
    "iso:country":"AT",
    "sg:address":"Breinberg Nord 63",
    "sg:city":"Neumarkt am Wallersee",
    "sg:classifiers":[
        {
            "category":"Professional",
            "subcategory":"Computer Services",
            "type":"Services"
        }
    ],
    "sg:phone":"+43 6216 402138",
    "sg:postcode":"5202",
    "sg:province":"Salzburg",
    "sg:tags":[
        "software"
    ],
    "wof:name":"Haslauer Hermann Dipl-Ing",
    "wof:placetype":"venue"
},
  "geometry": {"coordinates":[13.2245721817,47.9449386597],"type":"Point"}
}