{
  "type": "Feature",
  "properties": {
    "addr:full":"Jordang 7/7/3a Wien Wien 1010",
    "addr:housenumber":"7 / 7 / 3a",
    "addr:postcode":"1010",
    "addr:street":"Jordang",
    "iso:country":"AT",
    "sg:address":"Jordang 7/7/3a",
    "sg:city":"Wien",
    "sg:orig_category":"Fitnesscenter",
    "sg:phone":"+43 1 5325589",
    "sg:postcode":"1010",
    "sg:province":"Wien",
    "wof:name":"Pilates Akademie",
    "wof:placetype":"venue"
},
  "geometry": {"coordinates":[16.3688049316,48.2025489807],"type":"Point"}
}