{
  "type": "Feature",
  "properties": {
    "iso:country":"AT",
    "sg:address":"Nr. 207 ",
    "sg:city":"\u00d6blarn",
    "sg:classifiers":[
        {
            "category":"Professional",
            "subcategory":"Engineering",
            "type":"Services"
        }
    ],
    "sg:phone":"+43 4336 842836",
    "sg:postcode":"8960",
    "sg:province":"Steiermark",
    "sg:tags":[
        "machine",
        "-",
        "mechanical"
    ],
    "wof:name":"SCHORKMAYR GESMBH",
    "wof:placetype":"venue"
},
  "geometry": {"coordinates":[166.9221496582,-0.5282999873],"type":"Point"}
}