{
  "type": "Feature",
  "properties": {
    "iso:country":"AT",
    "sg:address":"Nr 42",
    "sg:city":"G\u00fcssing",
    "sg:orig_category":"Autoreparatur",
    "sg:phone":"+43 3325 20080",
    "sg:postcode":"7540",
    "sg:province":"Burgenland",
    "wof:name":"Mex Motos-Jost Rainer",
    "wof:placetype":"venue"
},
  "geometry": {"coordinates":[16.2575492859,47.0234718323],"type":"Point"}
}