{
  "type": "Feature",
  "properties": {
    "addr:full":"Langenlebarner Str 58 Tulln an der Donau Nieder\u00f6sterreich 3430",
    "addr:postcode":"3430",
    "addr:street":"Str 58",
    "iso:country":"AT",
    "sg:address":"Langenlebarner Str 58",
    "sg:city":"Tulln an der Donau",
    "sg:orig_category":"Blumeneinzelhandel",
    "sg:phone":"+43 4322 7262359",
    "sg:postcode":"3430",
    "sg:province":"Nieder\u00f6sterreich",
    "wof:name":"Blumen Susi Zoubek",
    "wof:placetype":"venue"
},
  "geometry": {"coordinates":[16.0689907074,48.3296203613],"type":"Point"}
}