{
  "type": "Feature",
  "properties": {
    "addr:full":"Stadtpl 20 Braunau am Inn Ober\u00f6sterreich 5280",
    "addr:housenumber":"20",
    "addr:postcode":"5280",
    "addr:street":"Stadtpl",
    "iso:country":"AT",
    "sg:address":"Stadtpl 20",
    "sg:city":"Braunau am Inn",
    "sg:orig_category":"Friseure U Frisiersalons",
    "sg:phone":"+43 4377 2264655",
    "sg:postcode":"5280",
    "sg:province":"Ober\u00f6sterreich",
    "wof:name":"Hohensinn Walter",
    "wof:placetype":"venue"
},
  "geometry": {"coordinates":[13.0349960327,48.257976532],"type":"Point"}
}