{
  "type": "Feature",
  "properties": {
    "iso:country":"AT",
    "sg:address":"Erdbergstr 189-193",
    "sg:city":"Wien",
    "sg:orig_category":"Autohandel",
    "sg:phone":"+43 4317 40200",
    "sg:postcode":"1110",
    "sg:province":"Wien",
    "wof:name":"DENZEL Kundencenter Erdberg",
    "wof:placetype":"venue"
},
  "geometry": {"coordinates":[16.4309158325,48.1858291626],"type":"Point"}
}