{
  "type": "Feature",
  "properties": {
    "addr:full":"Kaufpark 11 St. Valentin Nieder\u00f6sterreich 4300",
    "addr:housenumber":"11",
    "addr:postcode":"4300",
    "addr:street":"Kaufpark",
    "iso:country":"AT",
    "sg:address":"Kaufpark 11",
    "sg:city":"St. Valentin",
    "sg:orig_category":"Handarbeiten",
    "sg:phone":"+43 7435 52123",
    "sg:postcode":"4300",
    "sg:province":"Nieder\u00f6sterreich",
    "wof:name":"Ediths Handarbeiten - Buchmayr Edith",
    "wof:placetype":"venue"
},
  "geometry": {"coordinates":[14.5193338394,48.1912651062],"type":"Point"}
}