{
  "type": "Feature",
  "properties": {
    "iso:country":"AT",
    "sg:address":"Dorfstr 172",
    "sg:city":"Flachau",
    "sg:orig_category":"Tourismusinformation U -Organisationen",
    "sg:phone":"+43 4364 5722140",
    "sg:postcode":"5542",
    "sg:province":"Salzburg",
    "wof:name":"Tourismusverband Flachau",
    "wof:placetype":"venue"
},
  "geometry": {"coordinates":[13.3921222687,47.3435821533],"type":"Point"}
}