{
  "type": "Feature",
  "properties": {
    "addr:full":"Linzer Str 255 Wien Wien 1140",
    "addr:housenumber":"255",
    "addr:postcode":"1140",
    "addr:street":"Linzer Str",
    "iso:country":"AT",
    "sg:address":"Linzer Str 255",
    "sg:city":"Wien",
    "sg:orig_category":"Pelze U Pelzwaren",
    "sg:phone":"+43 4314 197717",
    "sg:postcode":"1140",
    "sg:province":"Wien",
    "wof:name":"Pelzhandel Butka",
    "wof:placetype":"venue"
},
  "geometry": {"coordinates":[16.2842826843,48.19480896],"type":"Point"}
}