{
  "type": "Feature",
  "properties": {
    "addr:full":"Dalaas 102 Dalaas Vorarlberg 6752",
    "addr:housenumber":"102",
    "addr:postcode":"6752",
    "addr:street":"Dalaas",
    "iso:country":"AT",
    "sg:address":"Dalaas 102",
    "sg:city":"Dalaas",
    "sg:orig_category":"ChildrenS Furniture",
    "sg:phone":"+43 5585 72190",
    "sg:postcode":"6752",
    "sg:province":"Vorarlberg",
    "sg:website":"tischlerei-engstler.at",
    "wof:name":"Klaus Engstler",
    "wof:placetype":"venue"
},
  "geometry": {"coordinates":[10.0052509308,47.1233291626],"type":"Point"}
}