{
  "type": "Feature",
  "properties": {
    "addr:full":"Simmeringer Hauptstr 171 Wien Wien 1110",
    "addr:housenumber":"171",
    "addr:postcode":"1110",
    "addr:street":"Simmeringer Hauptstr",
    "iso:country":"AT",
    "sg:address":"Simmeringer Hauptstr 171",
    "sg:city":"Wien",
    "sg:orig_category":"Garagen Parkgaragen",
    "sg:phone":"+43 1 7685606",
    "sg:postcode":"1110",
    "sg:province":"Wien",
    "wof:name":"APCOA Parking Austria AG",
    "wof:placetype":"venue"
},
  "geometry": {"coordinates":[16.4222202301,48.1688194275],"type":"Point"}
}