{
  "type": "Feature",
  "properties": {
    "iso:country":"AT",
    "sg:address":"Loferer Bundesstr 11",
    "sg:city":"Zell am See",
    "sg:orig_category":"Autovermietung",
    "sg:phone":"+43 4365 4273225",
    "sg:postcode":"5700",
    "sg:province":"Salzburg",
    "wof:name":"Autoverleih Buchbinder",
    "wof:placetype":"venue"
},
  "geometry": {"coordinates":[12.7963485718,47.3255386353],"type":"Point"}
}