{
  "type": "Feature",
  "properties": {
    "addr:full":"Marktpl 26 Rabenstein an der Pielach Nieder\u00f6sterreich 3203",
    "addr:housenumber":"26",
    "addr:postcode":"3203",
    "addr:street":"Marktpl",
    "iso:country":"AT",
    "sg:address":"Marktpl 26",
    "sg:city":"Rabenstein an der Pielach",
    "sg:orig_category":"Tabaktrafiken",
    "sg:phone":"+43 4327 232301",
    "sg:postcode":"3203",
    "sg:province":"Nieder\u00f6sterreich",
    "wof:name":"Parg Elfriede",
    "wof:placetype":"venue"
},
  "geometry": {"coordinates":[15.4670085907,48.0650482178],"type":"Point"}
}