{
  "type": "Feature",
  "properties": {
    "iso:country":"AT",
    "sg:address":"Technikerstr 34",
    "sg:city":"Innsbruck",
    "sg:orig_category":"Banken U Sparkassen",
    "sg:phone":"+43 512 284191",
    "sg:postcode":"6020",
    "sg:province":"Tirol",
    "wof:name":"Tiroler Sparkasse Bank AG Innsbruck",
    "wof:placetype":"venue"
},
  "geometry": {"coordinates":[11.3475646973,47.265247345],"type":"Point"}
}