{
  "type": "Feature",
  "properties": {
    "addr:full":"Bergg 8 Rohrbach in Ober\u00f6sterreich Ober\u00f6sterreich 4150",
    "addr:housenumber":"8",
    "addr:postcode":"4150",
    "addr:street":"Bergg",
    "iso:country":"AT",
    "sg:address":"Bergg 8",
    "sg:city":"Rohrbach in Ober\u00f6sterreich",
    "sg:orig_category":"Fenster",
    "sg:phone":"+43 4372 8940083",
    "sg:postcode":"4150",
    "sg:province":"Ober\u00f6sterreich",
    "wof:name":"Actual Eilmannsberger",
    "wof:placetype":"venue"
},
  "geometry": {"coordinates":[13.9951534271,48.5746955872],"type":"Point"}
}