{
  "type": "Feature",
  "properties": {
    "addr:full":"Erzherzog Karl-Str 57 Wien Wien 1220",
    "addr:housenumber":"57",
    "addr:postcode":"1220",
    "iso:country":"AT",
    "sg:address":"Erzherzog Karl-Str 57",
    "sg:city":"Wien",
    "sg:orig_category":"Lebensmittel / Einzelhandel",
    "sg:phone":"+43 1 2025770",
    "sg:postcode":"1220",
    "sg:province":"Wien",
    "wof:name":"MONDO Lebensmitteldiskonter",
    "wof:placetype":"venue"
},
  "geometry": {"coordinates":[16.4421405792,48.2346038818],"type":"Point"}
}