{
  "type": "Feature",
  "properties": {
    "addr:full":"Annaberg Annaberg Salzburg 5524",
    "addr:postcode":"5524",
    "iso:country":"AT",
    "sg:address":"Annaberg",
    "sg:city":"Annaberg",
    "sg:orig_category":"Musikgruppen",
    "sg:phone":"+43 6463 8608",
    "sg:postcode":"5524",
    "sg:province":"Salzburg",
    "wof:name":"Musikkapelle Annaberg",
    "wof:placetype":"venue"
},
  "geometry": {"coordinates":[13.4311275482,47.5239715576],"type":"Point"}
}