{
  "type": "Feature",
  "properties": {
    "addr:full":"Linzer Str 85 Gablitz Nieder\u00f6sterreich 3003",
    "addr:housenumber":"85",
    "addr:postcode":"3003",
    "addr:street":"Linzer Str",
    "iso:country":"AT",
    "sg:address":"Linzer Str 85",
    "sg:city":"Gablitz",
    "sg:classifiers":[
        {
            "category":"Restaurant",
            "type":"Food & Drink"
        }
    ],
    "sg:phone":"+43 2231 61171",
    "sg:postcode":"3003",
    "sg:province":"Nieder\u00f6sterreich",
    "sg:tags":[
        "pizzeria"
    ],
    "wof:name":"Pizzeria Antonello",
    "wof:placetype":"venue"
},
  "geometry": {"coordinates":[16.1562328339,48.2276496887],"type":"Point"}
}