{
  "type": "Feature",
  "properties": {
    "iso:country":"AT",
    "sg:address":"Liesinger Str 3C",
    "sg:city":"Wolfsgraben",
    "sg:orig_category":"Exporteure U Importeure",
    "sg:phone":"+43 2233 56801",
    "sg:postcode":"3012",
    "sg:province":"Nieder\u00f6sterreich",
    "wof:name":"HM Maschinenbau- und Bahntechnik GmbH",
    "wof:placetype":"venue"
},
  "geometry": {"coordinates":[16.121011734,48.1576805115],"type":"Point"}
}