{
  "type": "Feature",
  "properties": {
    "addr:full":"Belruptstr 21 Bregenz Vorarlberg 6900",
    "addr:housenumber":"21",
    "addr:postcode":"6900",
    "addr:street":"Belruptstr",
    "iso:country":"AT",
    "sg:address":"Belruptstr 21",
    "sg:city":"Bregenz",
    "sg:orig_category":"Non-Classified Establishments",
    "sg:phone":"+43 5574 45396",
    "sg:postcode":"6900",
    "sg:province":"Vorarlberg",
    "wof:name":"Kirchenbeitragsstelle",
    "wof:placetype":"venue"
},
  "geometry": {"coordinates":[9.7507629395,47.5039978027],"type":"Point"}
}