{
  "type": "Feature",
  "properties": {
    "addr:full":"Gasser Pl 8 Hermagor K\u00e4rnten 9620",
    "addr:housenumber":"8",
    "addr:postcode":"9620",
    "addr:street":"Gasser Pl;Kaernten",
    "iso:country":"AT",
    "sg:address":"Gasser Pl 8",
    "sg:city":"Hermagor",
    "sg:orig_category":"Versicherungsunternehmen",
    "sg:phone":"+43 4282 23600",
    "sg:postcode":"9620",
    "sg:province":"K\u00e4rnten",
    "wof:name":"Allianz Elementar Versicherungs-AG",
    "wof:placetype":"venue"
},
  "geometry": {"coordinates":[13.3717746735,46.627620697],"type":"Point"}
}