{
  "type": "Feature",
  "properties": {
    "addr:full":"Nr 504 Jenbach Tirol 6200",
    "addr:postcode":"6200",
    "addr:street":"Nr 504;Tirol",
    "iso:country":"AT",
    "sg:address":"Nr 504",
    "sg:city":"Jenbach",
    "sg:orig_category":"Musikgruppen",
    "sg:phone":"+43 5244 63804",
    "sg:postcode":"6200",
    "sg:province":"Tirol",
    "wof:name":"Mader Alfred",
    "wof:placetype":"venue"
},
  "geometry": {"coordinates":[11.7709331512,47.3917541504],"type":"Point"}
}