{
  "type": "Feature",
  "properties": {
    "iso:country":"AT",
    "sg:address":"Hauptstr 157",
    "sg:city":"Bad Mitterndorf",
    "sg:orig_category":"Bekleidung / Einzelhandel",
    "sg:phone":"+43 4336 233950",
    "sg:postcode":"8983",
    "sg:province":"Steiermark",
    "wof:name":"Vergud Klaus",
    "wof:placetype":"venue"
},
  "geometry": {"coordinates":[13.9318876266,47.5550498962],"type":"Point"}
}