{
  "type": "Feature",
  "properties": {
    "iso:country":"AT",
    "sg:address":"Satoristr 5",
    "sg:city":"Gmunden",
    "sg:orig_category":"Immobilienmakler",
    "sg:phone":"+43 4376 12649500",
    "sg:postcode":"4810",
    "sg:province":"Ober\u00f6sterreich",
    "wof:name":"Immobilienb\u00fcro Kaiser Ernst",
    "wof:placetype":"venue"
},
  "geometry": {"coordinates":[13.7981462479,47.918598175],"type":"Point"}
}