{
  "type": "Feature",
  "properties": {
    "addr:full":"Am Hartboden 23 Gratkorn Steiermark 8101",
    "addr:housenumber":"23",
    "addr:postcode":"8101",
    "addr:street":"Am Hartboden",
    "iso:country":"AT",
    "sg:address":"Am Hartboden 23",
    "sg:city":"Gratkorn",
    "sg:orig_category":"Unterhaltungselektronik / Einzelhandel",
    "sg:phone":"+43 4331 2423675",
    "sg:postcode":"8101",
    "sg:province":"Steiermark",
    "wof:name":"Wei\u00df Gerhard",
    "wof:placetype":"venue"
},
  "geometry": {"coordinates":[15.3662929535,47.1206321716],"type":"Point"}
}