{
  "type": "Feature",
  "properties": {
    "addr:full":"Triester Str 1 Wiener Neudorf Nieder\u00f6sterreich 2351",
    "addr:postcode":"2351",
    "addr:street":"Str",
    "iso:country":"AT",
    "sg:address":"Triester Str 1",
    "sg:city":"Wiener Neudorf",
    "sg:orig_category":"Blumeneinzelhandel",
    "sg:phone":"+43 2236 61283",
    "sg:postcode":"2351",
    "sg:province":"Nieder\u00f6sterreich",
    "wof:name":"Blumen B & B R Bigl GesmbH",
    "wof:placetype":"venue"
},
  "geometry": {"coordinates":[16.3141651154,48.0828285217],"type":"Point"}
}