{
  "type": "Feature",
  "properties": {
    "addr:full":"Hardegg 64 Wien Wien 1220",
    "addr:housenumber":"64",
    "addr:postcode":"1220",
    "addr:street":"Hardegg",
    "iso:country":"AT",
    "sg:address":"Hardegg 64",
    "sg:city":"Wien",
    "sg:orig_category":"Genossenschaften",
    "sg:phone":"+43 1 2809955",
    "sg:postcode":"1220",
    "sg:province":"Wien",
    "wof:name":"Wogem Gemeinn\u00fctzige Wohn-, Bau- und Siedlungsges f Gemeindebedienstete GesmbH",
    "wof:placetype":"venue"
},
  "geometry": {"coordinates":[16.4582176208,48.2195396423],"type":"Point"}
}