{
  "type": "Feature",
  "properties": {
    "iso:country":"AT",
    "sg:address":"J und G Rainer-Str 4",
    "sg:city":"W\u00f6rgl",
    "sg:orig_category":"Weiterbildungsinstitute M Allg U Berufl Bildungsangebot",
    "sg:phone":"+43 5332 23070",
    "sg:postcode":"6300",
    "sg:province":"Tirol",
    "wof:name":"ibis acam - Privates Institut f berufsbezogene Information und Schulung GmbH",
    "wof:placetype":"venue"
},
  "geometry": {"coordinates":[-69.3131027222,-51.6091995239],"type":"Point"}
}