{
  "type": "Feature",
  "properties": {
    "addr:full":"Nr 63 Birkfeld Steiermark 8190",
    "addr:postcode":"8190",
    "addr:street":"Nr 63",
    "iso:country":"AT",
    "sg:address":"Nr 63",
    "sg:city":"Birkfeld",
    "sg:orig_category":"Fischzucht",
    "sg:phone":"+43 4331 7444630",
    "sg:postcode":"8190",
    "sg:province":"Steiermark",
    "wof:name":"Forellengasthaus Kulmer",
    "wof:placetype":"venue"
},
  "geometry": {"coordinates":[15.6830863953,47.3945388794],"type":"Point"}
}