{
  "type": "Feature",
  "properties": {
    "addr:full":"Salurner Str Kufstein Tirol 6330",
    "addr:postcode":"6330",
    "addr:street":"Str Kufstein",
    "iso:country":"AT",
    "sg:address":"Salurner Str",
    "sg:city":"Kufstein",
    "sg:orig_category":"Rettungsdienste",
    "sg:phone":"+43 5372 63040",
    "sg:postcode":"6330",
    "sg:province":"Tirol",
    "wof:name":"\u00f6sterreichischer Bergrettungsdienst",
    "wof:placetype":"venue"
},
  "geometry": {"coordinates":[12.1639757156,47.5779495239],"type":"Point"}
}