{
  "type": "Feature",
  "properties": {
    "iso:country":"AT",
    "sg:address":"Hutfabrikweg 20",
    "sg:city":"Ebreichsdorf",
    "sg:orig_category":"Waagen / Reparatur U Service",
    "sg:phone":"+43 2254 75863",
    "sg:postcode":"2483",
    "sg:province":"Nieder\u00f6sterreich",
    "wof:name":"Bizerba Waagen GesmbH & Co KG",
    "wof:placetype":"venue"
},
  "geometry": {"coordinates":[16.3989486694,47.9752578735],"type":"Point"}
}