{
  "type": "Feature",
  "properties": {
    "addr:full":"Nr 45 Markt Piesting Nieder\u00f6sterreich 2753",
    "addr:postcode":"2753",
    "addr:street":"Nr;Markt",
    "iso:country":"AT",
    "sg:address":"Nr 45",
    "sg:city":"Markt Piesting",
    "sg:orig_category":"Automatisierungstechnik",
    "sg:phone":"+43 2633 458340",
    "sg:postcode":"2753",
    "sg:province":"Nieder\u00f6sterreich",
    "sg:website":"www.mitterhofer.com",
    "wof:name":"Mitterhofer Automatisierungstechnik GmbH",
    "wof:placetype":"venue"
},
  "geometry": {"coordinates":[16.1277275085,47.8729743958],"type":"Point"}
}