{
  "type": "Feature",
  "properties": {
    "addr:full":"Kriegwald 62 Julbach Ober\u00f6sterreich 4162",
    "addr:housenumber":"62",
    "addr:postcode":"4162",
    "addr:street":"Kriegwald",
    "iso:country":"AT",
    "sg:address":"Kriegwald 62",
    "sg:city":"Julbach",
    "sg:orig_category":"Landwirtschaftliche Produkte",
    "sg:phone":"+43 7288 71024",
    "sg:postcode":"4162",
    "sg:province":"Ober\u00f6sterreich",
    "wof:name":"Grenzlandmilchhof GmbH & Co KG",
    "wof:placetype":"venue"
},
  "geometry": {"coordinates":[13.8183069229,48.6607627869],"type":"Point"}
}