{
  "type": "Feature",
  "properties": {
    "iso:country":"AT",
    "sg:address":"Hauptpl 1",
    "sg:city":"Bad Leonfelden",
    "sg:orig_category":"Gemeinden",
    "sg:phone":"+43 7213 65650",
    "sg:postcode":"4190",
    "sg:province":"Ober\u00f6sterreich",
    "wof:name":"Stadtgemeindeamt Bad Leonfelden",
    "wof:placetype":"venue"
},
  "geometry": {"coordinates":[14.2928991318,48.5226554871],"type":"Point"}
}