{
  "type": "Feature",
  "properties": {
    "addr:full":"Warmbader Str 72 Villach K\u00e4rnten 9500",
    "addr:housenumber":"72",
    "addr:postcode":"9500",
    "addr:street":"Str;Kaernten",
    "iso:country":"AT",
    "sg:address":"Warmbader Str 72",
    "sg:city":"Villach",
    "sg:orig_category":"Elektroinstallationsunternehmen",
    "sg:phone":"+43 4242 35535",
    "sg:postcode":"9500",
    "sg:province":"K\u00e4rnten",
    "wof:name":"Gasser Erwin",
    "wof:placetype":"venue"
},
  "geometry": {"coordinates":[13.8314199448,46.5956802368],"type":"Point"}
}