{
  "type": "Feature",
  "properties": {
    "addr:full":"Vischerstr 1 Natternbach Ober\u00f6sterreich 4723",
    "addr:housenumber":"1",
    "addr:postcode":"4723",
    "addr:street":"Vischerstr",
    "iso:country":"AT",
    "sg:address":"Vischerstr 1",
    "sg:city":"Natternbach",
    "sg:orig_category":"Tourismusinformation U -Organisationen",
    "sg:phone":"+43 4372 788258",
    "sg:postcode":"4723",
    "sg:province":"Ober\u00f6sterreich",
    "wof:name":"Tourismusverband",
    "wof:placetype":"venue"
},
  "geometry": {"coordinates":[13.7493953705,48.396736145],"type":"Point"}
}