{
  "type": "Feature",
  "properties": {
    "addr:full":"Alszeile 118/9 Wien Wien 1170",
    "addr:housenumber":"118 / 9",
    "addr:postcode":"1170",
    "addr:street":"Alszeile",
    "iso:country":"AT",
    "sg:address":"Alszeile 118/9",
    "sg:city":"Wien",
    "sg:orig_category":"Architekten",
    "sg:phone":"+43 660 4117388",
    "sg:postcode":"1170",
    "sg:province":"Wien",
    "wof:name":"Kratschmar Bernhard Dipl-Ing",
    "wof:placetype":"venue"
},
  "geometry": {"coordinates":[16.2971553802,48.2305297852],"type":"Point"}
}