{
  "type": "Feature",
  "properties": {
    "iso:country":"AT",
    "sg:address":"Blaiken 111",
    "sg:city":"St. Andr\u00e4",
    "sg:orig_category":"Autohandel",
    "sg:phone":"+43 4358 2364",
    "sg:postcode":"9433",
    "sg:province":"K\u00e4rnten",
    "wof:name":"Steinwender Bernhard",
    "wof:placetype":"venue"
},
  "geometry": {"coordinates":[14.8266181946,46.7652778625],"type":"Point"}
}