{
  "type": "Feature",
  "properties": {
    "iso:country":"AT",
    "sg:address":"Humboldtgasse 18",
    "sg:city":"Wien",
    "sg:orig_category":"Freizeit, Sport",
    "sg:phone":"+43 664",
    "sg:postcode":"1100",
    "sg:province":"Wien",
    "sg:website":"http://www.dart-master-liga.co.at",
    "wof:name":"Dart - Master - Liga",
    "wof:placetype":"venue"
},
  "geometry": {"coordinates":[16.3771572113,48.1811103821],"type":"Point"}
}