{
  "type": "Feature",
  "properties": {
    "addr:full":"Feuerwehrpl 4 Bad V\u00f6slau Nieder\u00f6sterreich 2540",
    "addr:housenumber":"4",
    "addr:postcode":"2540",
    "addr:street":"Feuerwehrpl",
    "iso:country":"AT",
    "sg:address":"Feuerwehrpl 4",
    "sg:city":"Bad V\u00f6slau",
    "sg:orig_category":"Tischlereien",
    "sg:phone":"+43 2252 790531",
    "sg:postcode":"2540",
    "sg:province":"Nieder\u00f6sterreich",
    "wof:name":"Wallner Reinhard",
    "wof:placetype":"venue"
},
  "geometry": {"coordinates":[16.1958618164,47.9619674683],"type":"Point"}
}