{
  "type": "Feature",
  "properties": {
    "iso:country":"AT",
    "sg:address":"Bambergstr 11",
    "sg:city":"Kirchdorf an der Krems",
    "sg:orig_category":"Restaurants: Chinesisch",
    "sg:phone":"+43 4375 8251111",
    "sg:postcode":"4560",
    "sg:province":"Ober\u00f6sterreich",
    "wof:name":"China-Restaurant",
    "wof:placetype":"venue"
},
  "geometry": {"coordinates":[14.1194696426,47.9070472717],"type":"Point"}
}