{
  "type": "Feature",
  "properties": {
    "addr:full":"Amselweg 7 Attnang-Puchheim Ober\u00f6sterreich 4800",
    "addr:housenumber":"7",
    "addr:postcode":"4800",
    "addr:street":"Amselweg",
    "iso:country":"AT",
    "sg:address":"Amselweg 7",
    "sg:city":"Attnang-Puchheim",
    "sg:classifiers":[
        {
            "category":"Parking",
            "subcategory":"Lot",
            "type":"Transportation"
        }
    ],
    "sg:phone":"+43 4376 7462471",
    "sg:postcode":"4800",
    "sg:province":"Ober\u00f6sterreich",
    "sg:tags":[
        "transport",
        "road"
    ],
    "wof:name":"F. ZAUNRIETH GESMBH",
    "wof:placetype":"venue"
},
  "geometry": {"coordinates":[13.7328577042,48.0183372498],"type":"Point"}
}