{
  "type": "Feature",
  "properties": {
    "addr:full":"Ubellstrasse 5 Linz Ober\u00f6sterreich 4020",
    "addr:housenumber":"5",
    "addr:postcode":"4020",
    "addr:street":"Ubellstrasse",
    "iso:country":"AT",
    "sg:address":"Ubellstrasse 5",
    "sg:city":"Linz",
    "sg:classifiers":[
        {
            "category":"Shopping",
            "subcategory":"Stationery & Office Supplies",
            "type":"Retail Goods"
        }
    ],
    "sg:phone":"+43 732 346214",
    "sg:postcode":"4020",
    "sg:province":"Ober\u00f6sterreich",
    "sg:tags":[
        "uninterruptible",
        "unit",
        "ups",
        "power"
    ],
    "sg:website":"gps-usv.at",
    "wof:name":"GPS Gr\u00fcnauer Power Solutions",
    "wof:placetype":"venue"
},
  "geometry": {"coordinates":[14.2917165756,48.2659034729],"type":"Point"}
}