{
  "type": "Feature",
  "properties": {
    "addr:full":"Wiener Str. 338 G\u00f6sting Steiermark 8051",
    "addr:housenumber":"338",
    "addr:postcode":"8051",
    "addr:street":"Goesting Steiermark",
    "iso:country":"AT",
    "sg:address":"Wiener Str. 338",
    "sg:city":"G\u00f6sting",
    "sg:classifiers":[
        {
            "category":"Professional",
            "subcategory":"Engineering",
            "type":"Services"
        }
    ],
    "sg:phone":"+43 4331 660060",
    "sg:postcode":"8051",
    "sg:province":"Steiermark",
    "sg:tags":[
        "machine",
        "-",
        "mechanical"
    ],
    "wof:name":"KLG AUSTRIA K\u00dcHLM\u00d6BEL & LADENBAU GMBH",
    "wof:placetype":"venue"
},
  "geometry": {"coordinates":[15.4030056,47.1024093628],"type":"Point"}
}