{
  "type": "Feature",
  "properties": {
    "addr:full":"Flie\u00dferau 394c Landeck Tirol 6500",
    "addr:housenumber":"394c",
    "addr:postcode":"6500",
    "addr:street":"Fliesserau;Tirol",
    "iso:country":"AT",
    "sg:address":"Flie\u00dferau 394c",
    "sg:city":"Landeck",
    "sg:classifiers":[
        {
            "category":"Banks & Credit Unions",
            "subcategory":"Bank",
            "type":"Services"
        }
    ],
    "sg:phone":"+43 5442 670070",
    "sg:postcode":"6500",
    "sg:province":"Tirol",
    "sg:tags":[
        "services",
        "energy",
        "saving",
        "consulting"
    ],
    "sg:website":"beachcomberhottubs.at",
    "wof:name":"Beachcomber Austria",
    "wof:placetype":"venue"
},
  "geometry": {"coordinates":[10.5670547485,47.1368560791],"type":"Point"}
}