{
  "type": "Feature",
  "properties": {
    "addr:full":"Schumanng 56/16 Wien Wien 1170",
    "addr:housenumber":"56 / 16",
    "addr:postcode":"1170",
    "addr:street":"Schumanng",
    "iso:country":"AT",
    "sg:address":"Schumanng 56/16",
    "sg:city":"Wien",
    "sg:orig_category":"Webdesign",
    "sg:phone":"+43 4369 911884460",
    "sg:postcode":"1170",
    "sg:province":"Wien",
    "wof:name":"Scheidegger Markus",
    "wof:placetype":"venue"
},
  "geometry": {"coordinates":[16.3359279633,48.2221794128],"type":"Point"}
}