{
  "type": "Feature",
  "properties": {
    "addr:full":"Kematen an der Ybbs Nieder\u00f6sterreich 3331",
    "addr:postcode":"3331",
    "addr:street":"Niederoesterreich",
    "iso:country":"AT",
    "sg:city":"Kematen an der Ybbs",
    "sg:orig_category":"Feuerwehren",
    "sg:phone":"+43 7448 26080",
    "sg:postcode":"3331",
    "sg:province":"Nieder\u00f6sterreich",
    "wof:name":"Freiwillige Feuerwehr Niederhausleiten-H\u00f6fing",
    "wof:placetype":"venue"
},
  "geometry": {"coordinates":[-97.7891540527,46.7603759766],"type":"Point"}
}