{
  "type": "Feature",
  "properties": {
    "addr:full":"Robert Hamerling-G 9 Wien Wien 1150",
    "addr:housenumber":"9",
    "addr:postcode":"1150",
    "iso:country":"AT",
    "sg:address":"Robert Hamerling-G 9",
    "sg:city":"Wien",
    "sg:orig_category":"Immobilienverwaltungen",
    "sg:phone":"+43 1 8923869",
    "sg:postcode":"1150",
    "sg:province":"Wien",
    "wof:name":"Tula Realit\u00e4ten Verwaltungs- und Vermittlungs GesmbH",
    "wof:placetype":"venue"
},
  "geometry": {"coordinates":[16.3367862701,48.1939811707],"type":"Point"}
}