{
  "type": "Feature",
  "properties": {
    "addr:full":"M\u00fchlbach 64 Traunkirchen Ober\u00f6sterreich 4801",
    "addr:housenumber":"64",
    "addr:postcode":"4801",
    "addr:street":"Muehlbach",
    "iso:country":"AT",
    "sg:address":"M\u00fchlbach 64",
    "sg:city":"Traunkirchen",
    "sg:orig_category":"Volkshochschulen",
    "sg:phone":"+43 4376 173315",
    "sg:postcode":"4801",
    "sg:province":"Ober\u00f6sterreich",
    "wof:name":"Volkshochschule Altm\u00fcnster",
    "wof:placetype":"venue"
},
  "geometry": {"coordinates":[13.7895488739,47.8446311951],"type":"Point"}
}