{
  "type": "Feature",
  "properties": {
    "iso:country":"AT",
    "sg:address":"Natalis-Obwexer-Str 15",
    "sg:city":"Matrei in Osttirol",
    "sg:orig_category":"Freizeit- U Sportbekleidung",
    "sg:phone":"+43 4348 7567960",
    "sg:postcode":"9971",
    "sg:province":"Tirol",
    "wof:name":"Anita Dr Helbig GesmbH",
    "wof:placetype":"venue"
},
  "geometry": {"coordinates":[12.5347900391,46.9970588684],"type":"Point"}
}