{
  "type": "Feature",
  "properties": {
    "addr:full":"Kampl Kapellenweg 27 Neustift im Stubaital Tirol 6167",
    "addr:housenumber":"27",
    "addr:postcode":"6167",
    "addr:street":"Kapellenweg;Tirol",
    "iso:country":"AT",
    "sg:address":"Kampl Kapellenweg 27",
    "sg:city":"Neustift im Stubaital",
    "sg:orig_category":"Maler, Anstreicher U Lackierer",
    "sg:phone":"+43 4352 263108",
    "sg:postcode":"6167",
    "sg:province":"Tirol",
    "wof:name":"Mairhofer Robert",
    "wof:placetype":"venue"
},
  "geometry": {"coordinates":[11.3075504303,47.1104850769],"type":"Point"}
}