{
  "type": "Feature",
  "properties": {
    "addr:full":"Dresdner Str 81-85 Wien Wien 1200",
    "addr:postcode":"81-85;1200",
    "addr:street":"Str",
    "iso:country":"AT",
    "sg:address":"Dresdner Str 81-85",
    "sg:city":"Wien",
    "sg:orig_category":"Datenverarbeitung",
    "sg:phone":"+43 4313 37330",
    "sg:postcode":"1200",
    "sg:province":"Wien",
    "sg:website":"travi.com",
    "wof:name":"TRAVIAUSTRIA Datenservice f Reise u Touristik GmbH & Co. Nfg. KG",
    "wof:placetype":"venue"
},
  "geometry": {"coordinates":[16.3831443787,48.2340354919],"type":"Point"}
}