{
  "type": "Feature",
  "properties": {
    "addr:full":"Hauptpl 21 Perg Ober\u00f6sterreich 4320",
    "addr:housenumber":"21",
    "addr:postcode":"4320",
    "addr:street":"Hauptpl",
    "iso:country":"AT",
    "sg:address":"Hauptpl 21",
    "sg:city":"Perg",
    "sg:orig_category":"Lederwaren / Einzelhandel",
    "sg:phone":"+43 7262 52507",
    "sg:postcode":"4320",
    "sg:province":"Ober\u00f6sterreich",
    "wof:name":"Hofer Anneliese",
    "wof:placetype":"venue"
},
  "geometry": {"coordinates":[14.6327676773,48.2499656677],"type":"Point"}
}