{
  "type": "Feature",
  "properties": {
    "addr:full":"Pyhrnstr 15 Windischgarsten Ober\u00f6sterreich 4580",
    "addr:housenumber":"15",
    "addr:postcode":"4580",
    "addr:street":"Pyhrnstr",
    "iso:country":"AT",
    "sg:address":"Pyhrnstr 15",
    "sg:city":"Windischgarsten",
    "sg:orig_category":"Fleischhauereien",
    "sg:phone":"+43 7562 53100",
    "sg:postcode":"4580",
    "sg:province":"Ober\u00f6sterreich",
    "wof:name":"Moser Adolf",
    "wof:placetype":"venue"
},
  "geometry": {"coordinates":[14.3352098465,47.7160835266],"type":"Point"}
}