{
  "type": "Feature",
  "properties": {
    "addr:full":"Euratsfelder Str 6 Amstetten Nieder\u00f6sterreich 3300",
    "addr:housenumber":"6",
    "addr:postcode":"3300",
    "addr:street":"Str;Niederoesterreich",
    "iso:country":"AT",
    "sg:address":"Euratsfelder Str 6",
    "sg:city":"Amstetten",
    "sg:orig_category":"Blumeneinzelhandel",
    "sg:phone":"+43 7472 65778",
    "sg:postcode":"3300",
    "sg:province":"Nieder\u00f6sterreich",
    "wof:name":"Blumenst\u00fcberl Marianne",
    "wof:placetype":"venue"
},
  "geometry": {"coordinates":[14.8706607819,48.1244812012],"type":"Point"}
}