{
  "type": "Feature",
  "properties": {
    "iso:country":"AT",
    "sg:address":"Andling 2",
    "sg:city":"Waizenkirchen",
    "sg:orig_category":"Maler, Anstreicher U Lackierer",
    "sg:phone":"+43 7277 7159",
    "sg:postcode":"4730",
    "sg:province":"Ober\u00f6sterreich",
    "wof:name":"Sch\u00fctzeneder Norbert",
    "wof:placetype":"venue"
},
  "geometry": {"coordinates":[13.8088312149,48.3689842224],"type":"Point"}
}