{
  "type": "Feature",
  "properties": {
    "addr:full":"Krugerstr 9 Wien Wien 1010",
    "addr:housenumber":"9",
    "addr:postcode":"1010",
    "addr:street":"Krugerstr",
    "iso:country":"AT",
    "sg:address":"Krugerstr 9",
    "sg:city":"Wien",
    "sg:orig_category":"Tabaktrafiken",
    "sg:phone":"+43 1 5135720",
    "sg:postcode":"1010",
    "sg:province":"Wien",
    "wof:name":"Ghassemi Djalil Ing",
    "wof:placetype":"venue"
},
  "geometry": {"coordinates":[16.3715782166,48.2040252686],"type":"Point"}
}