{
  "type": "Feature",
  "properties": {
    "addr:full":"Koschatstr 6 Br\u00fcckl K\u00e4rnten 9371",
    "addr:housenumber":"6",
    "addr:postcode":"9371",
    "addr:street":"Koschatstr;Kaernten",
    "iso:country":"AT",
    "sg:address":"Koschatstr 6",
    "sg:city":"Br\u00fcckl",
    "sg:classifiers":[
        {
            "category":"Restaurant",
            "type":"Food & Drink"
        }
    ],
    "sg:phone":"+43 4214 2003",
    "sg:postcode":"9371",
    "sg:province":"K\u00e4rnten",
    "sg:tags":[
        "pizzeria"
    ],
    "wof:name":"Pizzeria El Piggo",
    "wof:placetype":"venue"
},
  "geometry": {"coordinates":[14.5287446976,46.7512664795],"type":"Point"}
}