{
  "type": "Feature",
  "properties": {
    "addr:full":"Herzog-Bernhard-Pl 10 St. Veit an der Glan K\u00e4rnten 9300",
    "addr:housenumber":"10",
    "addr:postcode":"9300",
    "addr:street":"Herzog-Bernhard-Pl;Kaernten",
    "iso:country":"AT",
    "sg:address":"Herzog-Bernhard-Pl 10",
    "sg:city":"St. Veit an der Glan",
    "sg:orig_category":"Glasereien",
    "sg:phone":"+43 4342 1235070",
    "sg:postcode":"9300",
    "sg:province":"K\u00e4rnten",
    "wof:name":"Glas Puppitz u Systemtechnik GmbH",
    "wof:placetype":"venue"
},
  "geometry": {"coordinates":[14.3596448898,46.7668190002],"type":"Point"}
}