{
  "type": "Feature",
  "properties": {
    "addr:full":"Schalchham 13 Regau Ober\u00f6sterreich 4844",
    "addr:housenumber":"13",
    "addr:postcode":"4844",
    "addr:street":"Schalchham;Oberoesterreich",
    "iso:country":"AT",
    "sg:address":"Schalchham 13",
    "sg:city":"Regau",
    "sg:orig_category":"Reinigungsservice",
    "sg:phone":"+43 767220621",
    "sg:postcode":"4844",
    "sg:province":"Ober\u00f6sterreich",
    "wof:name":"STP Reinigungsservice",
    "wof:placetype":"venue"
},
  "geometry": {"coordinates":[13.6820735931,47.9977684021],"type":"Point"}
}