{
  "type": "Feature",
  "properties": {
    "iso:country":"AT",
    "sg:address":"R\u00fcstorf 116",
    "sg:city":"Schwanenstadt",
    "sg:orig_category":"Playground Equipment And Installations",
    "sg:phone":"+43 699 10879755",
    "sg:postcode":"4690",
    "sg:province":"Ober\u00f6sterreich",
    "sg:website":"saunabau.at",
    "wof:name":"Sauna + Spielplatzbau Ges.m.b.H.",
    "wof:placetype":"venue"
},
  "geometry": {"coordinates":[13.7731847763,48.0545158386],"type":"Point"}
}