{
  "type": "Feature",
  "properties": {
    "iso:country":"AT",
    "sg:address":"Eizendorf",
    "sg:city":"Saxen",
    "sg:orig_category":"Feuerwehren",
    "sg:phone":"+43 7269 320",
    "sg:postcode":"4351",
    "sg:province":"Ober\u00f6sterreich",
    "wof:name":"Freiwillige Feuerwehr Eizendorf",
    "wof:placetype":"venue"
},
  "geometry": {"coordinates":[14.7672395706,48.190372467],"type":"Point"}
}