{
  "type": "Feature",
  "properties": {
    "addr:full":"Bahnhofstr 3 Traun Ober\u00f6sterreich 4050",
    "addr:housenumber":"3",
    "addr:postcode":"4050",
    "addr:street":"Bahnhofstr",
    "iso:country":"AT",
    "sg:address":"Bahnhofstr 3",
    "sg:city":"Traun",
    "sg:orig_category":"Banken U Sparkassen",
    "sg:phone":"+43 5 050531480",
    "sg:postcode":"4050",
    "sg:province":"Ober\u00f6sterreich",
    "wof:name":"Bank Austria Creditanstalt AG",
    "wof:placetype":"venue"
},
  "geometry": {"coordinates":[14.2399921417,48.2205238342],"type":"Point"}
}