{
  "type": "Feature",
  "properties": {
    "addr:full":"Saalfeldner Str 19 Zell am See Salzburg 5700",
    "addr:housenumber":"19",
    "addr:postcode":"5700",
    "addr:street":"Str;Salzburg",
    "iso:country":"AT",
    "sg:address":"Saalfeldner Str 19",
    "sg:city":"Zell am See",
    "sg:classifiers":[
        {
            "category":"Wholesale",
            "subcategory":"Stationery",
            "type":"Manufacturing & Wholesale Goods"
        }
    ],
    "sg:phone":"+43 4365 42473200",
    "sg:postcode":"5700",
    "sg:province":"Salzburg",
    "sg:tags":[
        "sport-",
        "u",
        "sponsoring-agenturen"
    ],
    "wof:name":"Pinsport Sportagentur Golf Events",
    "wof:placetype":"venue"
},
  "geometry": {"coordinates":[12.7972803116,47.3273735046],"type":"Point"}
}