{
  "type": "Feature",
  "properties": {
    "iso:country":"AT",
    "sg:address":"Pfeilg 10-12/2",
    "sg:city":"Wien",
    "sg:orig_category":"Medienbeobachtung",
    "sg:phone":"+43 4367 65356000",
    "sg:postcode":"1080",
    "sg:province":"Wien",
    "wof:name":"CHILLI Verein f\u00fcr freie und unabh\u00e4ngige Medienarbeit",
    "wof:placetype":"venue"
},
  "geometry": {"coordinates":[16.3430690765,48.2106552124],"type":"Point"}
}