{
  "type": "Feature",
  "properties": {
    "addr:full":"Wiener Str 10 Korneuburg Nieder\u00f6sterreich 2100",
    "addr:postcode":"2100",
    "addr:street":"Niederoesterreich",
    "iso:country":"AT",
    "sg:address":"Wiener Str 10",
    "sg:city":"Korneuburg",
    "sg:orig_category":"Fotografen",
    "sg:phone":"+43 2262 74038",
    "sg:postcode":"2100",
    "sg:province":"Nieder\u00f6sterreich",
    "wof:name":"Schellack Werner - Portraitfotograf",
    "wof:placetype":"venue"
},
  "geometry": {"coordinates":[16.3341712952,48.3426399231],"type":"Point"}
}