{
  "type": "Feature",
  "properties": {
    "addr:full":"Grazer Str 69 Judendorf-Stra\u00dfengel Steiermark 8111",
    "addr:housenumber":"69",
    "addr:postcode":"8111",
    "addr:street":"Str",
    "iso:country":"AT",
    "sg:address":"Grazer Str 69",
    "sg:city":"Judendorf-Stra\u00dfengel",
    "sg:orig_category":"Restaurants: Chinesisch",
    "sg:phone":"+43 3124 54897",
    "sg:postcode":"8111",
    "sg:province":"Steiermark",
    "wof:name":"China-Restaurant Zhang Yong GmbH",
    "wof:placetype":"venue"
},
  "geometry": {"coordinates":[15.3487844467,47.1154441833],"type":"Point"}
}