{
  "type": "Feature",
  "properties": {
    "addr:full":"Ziegeleistrasse 12 Sattledt Ober\u00f6sterreich 4642",
    "addr:housenumber":"12",
    "addr:postcode":"4642",
    "addr:street":"Ziegeleistrasse",
    "iso:country":"AT",
    "sg:address":"Ziegeleistrasse 12",
    "sg:city":"Sattledt",
    "sg:classifiers":[
        {
            "category":"Building & Trades",
            "subcategory":"Plumbing",
            "type":"Services"
        }
    ],
    "sg:phone":"+43 7244 8770",
    "sg:postcode":"4642",
    "sg:province":"Ober\u00f6sterreich",
    "sg:tags":[
        "supraregional",
        "gas"
    ],
    "wof:name":"Walter Bichlbauer Ges.m.b.H.",
    "wof:placetype":"venue"
},
  "geometry": {"coordinates":[14.0584201813,48.0667877197],"type":"Point"}
}