{
  "type": "Feature",
  "properties": {
    "iso:country":"AT",
    "sg:address":"Dorotheergasse 7/12",
    "sg:city":"Wien",
    "sg:classifiers":[
        {
            "category":"Professional",
            "subcategory":"Credit Reporting & Collection",
            "type":"Services"
        }
    ],
    "sg:phone":"+43 1 5134415",
    "sg:postcode":"1010",
    "sg:province":"Wien",
    "sg:tags":[
        "processing",
        "data"
    ],
    "sg:website":"surfcontrol.at",
    "wof:name":"SurfControl GmbH",
    "wof:placetype":"venue"
},
  "geometry": {"coordinates":[16.369884491,48.2077102661],"type":"Point"}
}