{
  "type": "Feature",
  "properties": {
    "addr:full":"Liechtensteinstr 94 Wien Wien 1090",
    "addr:housenumber":"94",
    "addr:postcode":"1090",
    "addr:street":"Liechtensteinstr",
    "iso:country":"AT",
    "sg:address":"Liechtensteinstr 94",
    "sg:city":"Wien",
    "sg:classifiers":[
        {
            "category":"Restaurant",
            "type":"Food & Drink"
        }
    ],
    "sg:phone":"+43 1 3106446",
    "sg:postcode":"1090",
    "sg:province":"Wien",
    "wof:name":"Restaurant Edelschmankerl",
    "wof:placetype":"venue"
},
  "geometry": {"coordinates":[16.3563041687,48.2287216187],"type":"Point"}
}