{
  "type": "Feature",
  "properties": {
    "addr:full":"Tiroler Str 56 Greifenburg K\u00e4rnten 9761",
    "addr:housenumber":"56",
    "addr:postcode":"9761",
    "addr:street":"Str;Kaernten",
    "iso:country":"AT",
    "sg:address":"Tiroler Str 56",
    "sg:city":"Greifenburg",
    "sg:orig_category":"Papier- U Schreibwaren / Einzelhandel",
    "sg:phone":"+43 4347 12320",
    "sg:postcode":"9761",
    "sg:province":"K\u00e4rnten",
    "wof:name":"Rieper Heidemarie",
    "wof:placetype":"venue"
},
  "geometry": {"coordinates":[13.1800174713,46.7509651184],"type":"Point"}
}