{
  "type": "Feature",
  "properties": {
    "iso:country":"AT",
    "sg:address":"Unterer Stadtpl 11",
    "sg:city":"Kufstein",
    "sg:orig_category":"Papier- U Schreibwaren / Einzelhandel",
    "sg:phone":"+43 5372 62737",
    "sg:postcode":"6330",
    "sg:province":"Tirol",
    "wof:name":"\u00d6gg Erich",
    "wof:placetype":"venue"
},
  "geometry": {"coordinates":[12.1687803268,47.583026886],"type":"Point"}
}