{
  "type": "Feature",
  "properties": {
    "addr:full":"Lindenstr 12 K\u00fchnsdorf K\u00e4rnten 9125",
    "addr:housenumber":"12",
    "addr:postcode":"9125",
    "addr:street":"Lindenstr;Kaernten",
    "iso:country":"AT",
    "sg:address":"Lindenstr 12",
    "sg:city":"K\u00fchnsdorf",
    "sg:orig_category":"Friseure U Frisiersalons",
    "sg:phone":"+43 4342 326142",
    "sg:postcode":"9125",
    "sg:province":"K\u00e4rnten",
    "wof:name":"Schmidt Renate",
    "wof:placetype":"venue"
},
  "geometry": {"coordinates":[14.7210216522,46.6057701111],"type":"Point"}
}