{
  "type": "Feature",
  "properties": {
    "addr:full":"Hauptstr 43 Henndorf am Wallersee Salzburg 5302",
    "addr:housenumber":"43",
    "addr:postcode":"5302",
    "addr:street":"Hauptstr",
    "iso:country":"AT",
    "sg:address":"Hauptstr 43",
    "sg:city":"Henndorf am Wallersee",
    "sg:orig_category":"Fleischhauereien",
    "sg:phone":"+43 4362 148236",
    "sg:postcode":"5302",
    "sg:province":"Salzburg",
    "wof:name":"Andessner Franz",
    "wof:placetype":"venue"
},
  "geometry": {"coordinates":[13.1871995926,47.8982391357],"type":"Point"}
}