{
  "type": "Feature",
  "properties": {
    "addr:full":"Wiener Strasse 35a Kapfenberg Steiermark 8605",
    "addr:housenumber":"35a",
    "addr:postcode":"8605",
    "addr:street":"Wiener Strasse",
    "iso:country":"AT",
    "sg:address":"Wiener Strasse 35a",
    "sg:city":"Kapfenberg",
    "sg:classifiers":[
        {
            "category":"Health Services",
            "subcategory":"Dentist",
            "type":"Services"
        }
    ],
    "sg:phone":"+43 3862 26404",
    "sg:postcode":"8605",
    "sg:province":"Steiermark",
    "sg:tags":[
        "dental",
        "implant"
    ],
    "wof:name":"BHM Dental Labor Ges.m.b.H.",
    "wof:placetype":"venue"
},
  "geometry": {"coordinates":[15.2915935516,47.4441223145],"type":"Point"}
}