{
  "type": "Feature",
  "properties": {
    "addr:full":"Obere Klaus 97 Schladming Steiermark 8970",
    "addr:housenumber":"97",
    "addr:postcode":"8970",
    "addr:street":"Obere Klaus",
    "iso:country":"AT",
    "sg:address":"Obere Klaus 97",
    "sg:city":"Schladming",
    "sg:orig_category":"Tischlereien",
    "sg:phone":"+43 3687 22416",
    "sg:postcode":"8970",
    "sg:province":"Steiermark",
    "wof:name":"Wohlfahrter Einrichtungshaus",
    "wof:placetype":"venue"
},
  "geometry": {"coordinates":[13.7011709213,47.4016685486],"type":"Point"}
}