{
  "type": "Feature",
  "properties": {
    "addr:full":"Liebenstein 6 Liebenau Ober\u00f6sterreich 4252",
    "addr:housenumber":"6",
    "addr:postcode":"4252",
    "addr:street":"Liebenstein",
    "iso:country":"AT",
    "sg:address":"Liebenstein 6",
    "sg:city":"Liebenau",
    "sg:orig_category":"Schlossereien",
    "sg:phone":"+43 7953 431",
    "sg:postcode":"4252",
    "sg:province":"Ober\u00f6sterreich",
    "wof:name":"Puchner Engelbert",
    "wof:placetype":"venue"
},
  "geometry": {"coordinates":[14.7807722092,48.5123023987],"type":"Point"}
}