{
  "type": "Feature",
  "properties": {
    "addr:full":"Schulg 12 Donnerskirchen Burgenland 7082",
    "addr:housenumber":"12",
    "addr:postcode":"7082",
    "addr:street":"Schulg",
    "iso:country":"AT",
    "sg:address":"Schulg 12",
    "sg:city":"Donnerskirchen",
    "sg:orig_category":"Volksschulen",
    "sg:phone":"+43 2683 8664",
    "sg:postcode":"7082",
    "sg:province":"Burgenland",
    "wof:name":"Volksschule",
    "wof:placetype":"venue"
},
  "geometry": {"coordinates":[16.6425132751,47.8994026184],"type":"Point"}
}