{
  "type": "Feature",
  "properties": {
    "iso:country":"AT",
    "sg:address":"Dr.-Glatz-Str 2",
    "sg:city":"Innsbruck",
    "sg:orig_category":"Telekommunikation",
    "sg:phone":"+43 512 934355",
    "sg:postcode":"6020",
    "sg:province":"Tirol",
    "wof:name":"TELE ROLL Telekommunikationshandels GmbH",
    "wof:placetype":"venue"
},
  "geometry": {"coordinates":[11.4129009247,47.2622337341],"type":"Point"}
}