{
  "type": "Feature",
  "properties": {
    "iso:country":"AT",
    "sg:address":"Gartengasse 10",
    "sg:city":"Siegendorf im Burgenland",
    "sg:classifiers":[
        {
            "category":"Home & Garden",
            "subcategory":"Building Materials",
            "type":"Retail Goods"
        }
    ],
    "sg:phone":"+43 2687 48103",
    "sg:postcode":"7011",
    "sg:province":"Burgenland",
    "sg:tags":[
        "steel",
        "balcony"
    ],
    "wof:name":"Stefan Steiner",
    "wof:placetype":"venue"
},
  "geometry": {"coordinates":[16.5390625,47.7827568054],"type":"Point"}
}