{
  "type": "Feature",
  "properties": {
    "addr:full":"Kaiser-Franz-Josef-Str 14 Bad Ischl Ober\u00f6sterreich 4820",
    "addr:housenumber":"14",
    "addr:postcode":"4820",
    "addr:street":"Kaiser-Franz-Josef-Str",
    "iso:country":"AT",
    "sg:address":"Kaiser-Franz-Josef-Str 14",
    "sg:city":"Bad Ischl",
    "sg:orig_category":"Mineralien",
    "sg:phone":"+43 4361 3225736",
    "sg:postcode":"4820",
    "sg:province":"Ober\u00f6sterreich",
    "wof:name":"NAYAB Mineralien",
    "wof:placetype":"venue"
},
  "geometry": {"coordinates":[13.6230154037,47.7128410339],"type":"Point"}
}