{
  "type": "Feature",
  "properties": {
    "addr:full":"Leiserg 15 Rohrendorf Nieder\u00f6sterreich 3495",
    "addr:housenumber":"15",
    "addr:postcode":"3495",
    "addr:street":"Leiserg",
    "iso:country":"AT",
    "sg:address":"Leiserg 15",
    "sg:city":"Rohrendorf",
    "sg:orig_category":"Reinigungsbedarf U Reinigungsmittel",
    "sg:phone":"+43 4327 3273465",
    "sg:postcode":"3495",
    "sg:province":"Nieder\u00f6sterreich",
    "wof:name":"Berger Karl",
    "wof:placetype":"venue"
},
  "geometry": {"coordinates":[15.6505870819,48.4210090637],"type":"Point"}
}