{
  "type": "Feature",
  "properties": {
    "addr:full":"Felixstr. 24  Mattersburg Burgenland 7210",
    "addr:housenumber":"24",
    "addr:postcode":"7210",
    "addr:street":"Felixstr.",
    "iso:country":"AT",
    "sg:address":"Felixstr. 24 ",
    "sg:city":"Mattersburg",
    "sg:classifiers":[
        {
            "category":"Farming",
            "subcategory":"Livestock Farm",
            "type":"Manufacturing & Wholesale Goods"
        }
    ],
    "sg:phone":"+43 4326 26610",
    "sg:postcode":"7210",
    "sg:province":"Burgenland",
    "sg:tags":[
        "agriculture"
    ],
    "wof:name":"FELIX AUSTRIA GESMBH",
    "wof:placetype":"venue"
},
  "geometry": {"coordinates":[16.4101905823,47.7331848145],"type":"Point"}
}