{
  "type": "Feature",
  "properties": {
    "addr:full":"Heinrich-von-Schullern-Weg 21 Natters Tirol 6161",
    "addr:housenumber":"21",
    "addr:postcode":"6161",
    "addr:street":"Heinrich-Von-Schullern-Weg;Tirol",
    "iso:country":"AT",
    "sg:address":"Heinrich-von-Schullern-Weg 21",
    "sg:city":"Natters",
    "sg:classifiers":[
        {
            "category":"Taxi",
            "type":"Transportation"
        }
    ],
    "sg:phone":"+43 4351 2546692",
    "sg:postcode":"6161",
    "sg:province":"Tirol",
    "sg:tags":[
        "personentransporte",
        "u"
    ],
    "wof:name":"Hubmann Herwig",
    "wof:placetype":"venue"
},
  "geometry": {"coordinates":[11.3703355789,47.2341499329],"type":"Point"}
}