{
  "type": "Feature",
  "properties": {
    "addr:full":"K. H. Waggerl Strasse 49 Wagrain Salzburg 5602",
    "addr:housenumber":"49",
    "addr:postcode":"5602",
    "addr:street":"K.;Waggerl Strasse;Salzburg",
    "iso:country":"AT",
    "sg:address":"K. H. Waggerl Strasse 49",
    "sg:city":"Wagrain",
    "sg:classifiers":[
        {
            "category":"Professional",
            "subcategory":"Advertising",
            "type":"Services"
        }
    ],
    "sg:phone":"+43 664 1411514",
    "sg:postcode":"5602",
    "sg:province":"Salzburg",
    "sg:tags":[
        "cosmetic"
    ],
    "sg:website":"loop8.at",
    "wof:name":"loop cosmetics",
    "wof:placetype":"venue"
},
  "geometry": {"coordinates":[13.3045568466,47.3348236084],"type":"Point"}
}