{
  "type": "Feature",
  "properties": {
    "iso:country":"AT",
    "sg:address":"E\u00dfreithweg 578",
    "sg:city":"Kaprun",
    "sg:orig_category":"Appartements / Ferienwohnungen",
    "sg:phone":"+43 6547 7434",
    "sg:postcode":"5710",
    "sg:province":"Salzburg",
    "wof:name":"Appartementhaus",
    "wof:placetype":"venue"
},
  "geometry": {"coordinates":[12.7575788498,47.2708206177],"type":"Point"}
}