{
  "type": "Feature",
  "properties": {
    "addr:full":"Auf der Bleich 2 Oberneukirchen Ober\u00f6sterreich 4181",
    "addr:housenumber":"2",
    "addr:postcode":"4181",
    "addr:street":"Auf Der Bleich",
    "iso:country":"AT",
    "sg:address":"Auf der Bleich 2",
    "sg:city":"Oberneukirchen",
    "sg:orig_category":"Non-Classified Establishments",
    "sg:phone":"+43 7212 21131",
    "sg:postcode":"4181",
    "sg:province":"Ober\u00f6sterreich",
    "wof:name":"Evangelisches Diakoniewerk",
    "wof:placetype":"venue"
},
  "geometry": {"coordinates":[14.2268648148,48.4645423889],"type":"Point"}
}