{
  "type": "Feature",
  "properties": {
    "iso:country":"AT",
    "sg:address":"Dechant Thaller-Str 34",
    "sg:city":"Leibnitz",
    "sg:orig_category":"Lebensmittel / Einzelhandel",
    "sg:phone":"+43 3452 756060",
    "sg:postcode":"8430",
    "sg:province":"Steiermark",
    "wof:name":"MERKUR Markt",
    "wof:placetype":"venue"
},
  "geometry": {"coordinates":[15.5404529572,46.7885818481],"type":"Point"}
}