{
  "type": "Feature",
  "properties": {
    "iso:country":"AT",
    "sg:address":"Tober 26",
    "sg:city":"Fladnitz an der Teichalm",
    "sg:orig_category":"Schmieden U Schmiedeeisenelemente",
    "sg:phone":"+43 4331 7927525",
    "sg:postcode":"8163",
    "sg:province":"Steiermark",
    "wof:name":"Feldgrill Karl",
    "wof:placetype":"venue"
},
  "geometry": {"coordinates":[15.4943723679,47.2979393005],"type":"Point"}
}