{
  "type": "Feature",
  "properties": {
    "addr:full":"H\u00f6rstorf 23 Mitterkirchen Ober\u00f6sterreich 4343",
    "addr:housenumber":"23",
    "addr:postcode":"4343",
    "addr:street":"Hoerstorf",
    "iso:country":"AT",
    "sg:address":"H\u00f6rstorf 23",
    "sg:city":"Mitterkirchen",
    "sg:classifiers":[
        {
            "category":"Home & Garden",
            "subcategory":"Building Materials",
            "type":"Retail Goods"
        }
    ],
    "sg:phone":"+43 7269 8176",
    "sg:postcode":"4343",
    "sg:province":"Ober\u00f6sterreich",
    "sg:tags":[
        "baustoffe",
        "-material",
        "u"
    ],
    "wof:name":"Datterl Maria",
    "wof:placetype":"venue"
},
  "geometry": {"coordinates":[14.7093400955,48.1854057312],"type":"Point"}
}