{
  "type": "Feature",
  "properties": {
    "addr:full":"Nr 146 Weitensfeld K\u00e4rnten 9344",
    "addr:postcode":"9344",
    "addr:street":"Nr 146 Weitensfeld Kaernten",
    "iso:country":"AT",
    "sg:address":"Nr 146",
    "sg:city":"Weitensfeld",
    "sg:orig_category":"Feuerwehren",
    "sg:phone":"+43 4265 244",
    "sg:postcode":"9344",
    "sg:province":"K\u00e4rnten",
    "wof:name":"Feuerwache Weitensfeld",
    "wof:placetype":"venue"
},
  "geometry": {"coordinates":[14.193403244,46.8474197388],"type":"Point"}
}