{
  "type": "Feature",
  "properties": {
    "addr:full":"Stadtpl 7 Grieskirchen Ober\u00f6sterreich 4710",
    "addr:housenumber":"7",
    "addr:postcode":"4710",
    "addr:street":"Stadtpl",
    "iso:country":"AT",
    "sg:address":"Stadtpl 7",
    "sg:city":"Grieskirchen",
    "sg:orig_category":"Elektronische Bauelemente U Bauteile",
    "sg:phone":"+43 4372 4862917",
    "sg:postcode":"4710",
    "sg:province":"Ober\u00f6sterreich",
    "wof:name":"METCOMP Elektronik GmbH",
    "wof:placetype":"venue"
},
  "geometry": {"coordinates":[13.830447197,48.2348518372],"type":"Point"}
}