{
  "type": "Feature",
  "properties": {
    "addr:full":"Eferdinger Str 6 Wels Ober\u00f6sterreich 4600",
    "addr:housenumber":"6",
    "addr:postcode":"4600",
    "addr:street":"Str;Oberoesterreich",
    "iso:country":"AT",
    "sg:address":"Eferdinger Str 6",
    "sg:city":"Wels",
    "sg:orig_category":"Pizzazustellungen",
    "sg:phone":"+43 4372 4243777",
    "sg:postcode":"4600",
    "sg:province":"Ober\u00f6sterreich",
    "wof:name":"PIZZA SALAD MARINA",
    "wof:placetype":"venue"
},
  "geometry": {"coordinates":[14.0249090195,48.1674537659],"type":"Point"}
}