{
  "type": "Feature",
  "properties": {
    "iso:country":"AT",
    "sg:address":"Hochstr 139",
    "sg:city":"Perchtoldsdorf",
    "sg:orig_category":"Finanz- U Wirtschaftsberatung",
    "sg:phone":"+43 1 8697025",
    "sg:postcode":"2380",
    "sg:province":"Nieder\u00f6sterreich",
    "wof:name":"Wirtschaftsberater - Mag P Kerekes",
    "wof:placetype":"venue"
},
  "geometry": {"coordinates":[16.2583560944,48.1291160583],"type":"Point"}
}