{
  "type": "Feature",
  "properties": {
    "addr:full":"Kreuzfeld 6 Micheldorf in Ober\u00f6sterreich Ober\u00f6sterreich 4563",
    "addr:housenumber":"6",
    "addr:postcode":"4563",
    "addr:street":"Kreuzfeld",
    "iso:country":"AT",
    "sg:address":"Kreuzfeld 6",
    "sg:city":"Micheldorf in Ober\u00f6sterreich",
    "sg:orig_category":"Immobilienmakler",
    "sg:phone":"+43 4366 48396762",
    "sg:postcode":"4563",
    "sg:province":"Ober\u00f6sterreich",
    "wof:name":"Pechmann Harald - Schalk Consulting Immobilien",
    "wof:placetype":"venue"
},
  "geometry": {"coordinates":[14.1249046326,47.8824768066],"type":"Point"}
}