{
  "type": "Feature",
  "properties": {
    "addr:full":"Taugl 64 St. Koloman Salzburg 5423",
    "addr:housenumber":"64",
    "addr:postcode":"5423",
    "addr:street":"Taugl",
    "iso:country":"AT",
    "sg:address":"Taugl 64",
    "sg:city":"St. Koloman",
    "sg:orig_category":"Gartenarchitekten",
    "sg:phone":"+43 4362 41258",
    "sg:postcode":"5423",
    "sg:province":"Salzburg",
    "wof:name":"Ridky Erich Dipl-Ing",
    "wof:placetype":"venue"
},
  "geometry": {"coordinates":[13.2200908661,47.6502151489],"type":"Point"}
}