{
  "type": "Feature",
  "properties": {
    "addr:full":"Hauptstr 74 St. Radegund Steiermark 8061",
    "addr:housenumber":"74",
    "addr:postcode":"8061",
    "addr:street":"Hauptstr",
    "iso:country":"AT",
    "sg:address":"Hauptstr 74",
    "sg:city":"St. Radegund",
    "sg:orig_category":"Unternehmensberatung",
    "sg:phone":"+43 4331 3221699",
    "sg:postcode":"8061",
    "sg:province":"Steiermark",
    "wof:name":"bocons.net Managementberatung - Dipl Ing Thomas Bogensperger",
    "wof:placetype":"venue"
},
  "geometry": {"coordinates":[15.4929771423,47.1764640808],"type":"Point"}
}