{
  "type": "Feature",
  "properties": {
    "addr:full":"Unionstr 21 Linz Ober\u00f6sterreich 4020",
    "addr:housenumber":"21",
    "addr:postcode":"4020",
    "addr:street":"Unionstr",
    "iso:country":"AT",
    "sg:address":"Unionstr 21",
    "sg:city":"Linz",
    "sg:orig_category":"Schmiermittel",
    "sg:phone":"+43 732 600626",
    "sg:postcode":"4020",
    "sg:province":"Ober\u00f6sterreich",
    "sg:website":"high-low.at",
    "wof:name":"High & Low Trading T Hochholdinger",
    "wof:placetype":"venue"
},
  "geometry": {"coordinates":[14.2956991196,48.287940979],"type":"Point"}
}