{
  "type": "Feature",
  "properties": {
    "addr:full":"Pieslwang Gr\u00fcnburg Ober\u00f6sterreich 4594",
    "addr:postcode":"4594",
    "addr:street":"Oberoesterreich",
    "iso:country":"AT",
    "sg:address":"Pieslwang",
    "sg:city":"Gr\u00fcnburg",
    "sg:orig_category":"Feuerwehren",
    "sg:phone":"+43 7257 8423",
    "sg:postcode":"4594",
    "sg:province":"Ober\u00f6sterreich",
    "wof:name":"Freiwillige Feuerwehr Pieslwang",
    "wof:placetype":"venue"
},
  "geometry": {"coordinates":[14.3039684296,47.9784622192],"type":"Point"}
}