{
  "type": "Feature",
  "properties": {
    "addr:full":"Mettersdorf 109 Mettersdorf am Sa\u00dfbach Steiermark 8092",
    "addr:housenumber":"109",
    "addr:postcode":"8092",
    "addr:street":"Mettersdorf",
    "iso:country":"AT",
    "sg:address":"Mettersdorf 109",
    "sg:city":"Mettersdorf am Sa\u00dfbach",
    "sg:classifiers":[
        {
            "category":"Structure",
            "subcategory":"Office Building",
            "type":"Public Place"
        }
    ],
    "sg:phone":"+43 3477 3445",
    "sg:postcode":"8092",
    "sg:province":"Steiermark",
    "sg:tags":[
        "assemblies",
        "erecting",
        "skeleton"
    ],
    "sg:website":"gera.at",
    "wof:name":"Montagen f\u00fcr Tischlereiprodukte Ges.m.b.H.",
    "wof:placetype":"venue"
},
  "geometry": {"coordinates":[15.7083749771,46.8062095642],"type":"Point"}
}