{
  "type": "Feature",
  "properties": {
    "iso:country":"AT",
    "sg:address":"Karlingerstrasse 8",
    "sg:city":"Hartkirchen",
    "sg:orig_category":"Apparatus, Containers, Tanks, Vessels, And Boilers Of Stainless Steel",
    "sg:phone":"+43 7273 63360",
    "sg:postcode":"4081",
    "sg:province":"Ober\u00f6sterreich",
    "sg:website":"bremstaller.at",
    "wof:name":"Bremstaller GmbH & Co KG",
    "wof:placetype":"venue"
},
  "geometry": {"coordinates":[14.0031843185,48.3606872559],"type":"Point"}
}