{
  "type": "Feature",
  "properties": {
    "iso:country":"AT",
    "sg:address":"Wiener Str 484",
    "sg:city":"Linz",
    "sg:orig_category":"Unterhaltungselektronik / Einzelhandel",
    "sg:phone":"+43 732 308999",
    "sg:postcode":"4030",
    "sg:province":"Ober\u00f6sterreich",
    "wof:name":"Nirnberger Carmen",
    "wof:placetype":"venue"
},
  "geometry": {"coordinates":[14.3288955688,48.2448158264],"type":"Point"}
}