{
  "type": "Feature",
  "properties": {
    "iso:country":"AT",
    "sg:address":"Nr 35",
    "sg:city":"St. Nikolai im Sausal",
    "sg:orig_category":"Volksschulen",
    "sg:phone":"+43 4331 8523773",
    "sg:postcode":"8505",
    "sg:province":"Steiermark",
    "wof:name":"Volksschule",
    "wof:placetype":"venue"
},
  "geometry": {"coordinates":[15.4494228363,46.821395874],"type":"Point"}
}