{
  "type": "Feature",
  "properties": {
    "addr:full":"Tiroler Str 29 Silz Tirol 6424",
    "addr:postcode":"6424",
    "addr:street":"Str 29;Tirol",
    "iso:country":"AT",
    "sg:address":"Tiroler Str 29",
    "sg:city":"Silz",
    "sg:orig_category":"Physiotherapie",
    "sg:phone":"+43 650 7497461",
    "sg:postcode":"6424",
    "sg:province":"Tirol",
    "wof:name":"Weisiele Karoline Dipl-PT",
    "wof:placetype":"venue"
},
  "geometry": {"coordinates":[10.935256958,47.2679595947],"type":"Point"}
}