{
  "type": "Feature",
  "properties": {
    "iso:country":"AT",
    "sg:address":"Nr 7",
    "sg:city":"Kottes",
    "sg:orig_category":"Schlossereien",
    "sg:phone":"+43 2873 7248",
    "sg:postcode":"3623",
    "sg:province":"Nieder\u00f6sterreich",
    "wof:name":"Karl Herbert",
    "wof:placetype":"venue"
},
  "geometry": {"coordinates":[15.3013572693,48.4425735474],"type":"Point"}
}