{
  "type": "Feature",
  "properties": {
    "iso:country":"AT",
    "sg:address":"Bachviertelstr 3",
    "sg:city":"St. Peter in der Au",
    "sg:orig_category":"Installationsunternehmen",
    "sg:phone":"+43 7477 423420",
    "sg:postcode":"3352",
    "sg:province":"Nieder\u00f6sterreich",
    "wof:name":"Br\u00e4u Rudolf",
    "wof:placetype":"venue"
},
  "geometry": {"coordinates":[14.6241970062,48.044216156],"type":"Point"}
}