{
  "type": "Feature",
  "properties": {
    "addr:full":"Bachviertelstr 3 St. Peter in der Au Nieder\u00f6sterreich 3352",
    "addr:housenumber":"3",
    "addr:postcode":"3352",
    "addr:street":"Bachviertelstr",
    "iso:country":"AT",
    "sg:address":"Bachviertelstr 3",
    "sg:city":"St. Peter in der Au",
    "sg:orig_category":"Installationsunternehmen",
    "sg:phone":"+43 7477 423420",
    "sg:postcode":"3352",
    "sg:province":"Nieder\u00f6sterreich",
    "wof:name":"Br\u00e4u Rudolf",
    "wof:placetype":"venue"
},
  "geometry": {"coordinates":[14.6241970062,48.044216156],"type":"Point"}
}