{
  "type": "Feature",
  "properties": {
    "addr:full":"Hauptstrasse 71  Neumarkt am Wallersee Salzburg 5202",
    "addr:housenumber":"71",
    "addr:postcode":"5202",
    "addr:street":"Hauptstrasse;Salzburg",
    "iso:country":"AT",
    "sg:address":"Hauptstrasse 71 ",
    "sg:city":"Neumarkt am Wallersee",
    "sg:classifiers":[
        {
            "category":"Building & Trades",
            "subcategory":"Plumbing",
            "type":"Services"
        }
    ],
    "sg:phone":"+43 6216 20029",
    "sg:postcode":"5202",
    "sg:province":"Salzburg",
    "sg:tags":[
        "supraregional",
        "gas"
    ],
    "wof:name":"Gerhard Imser",
    "wof:placetype":"venue"
},
  "geometry": {"coordinates":[13.2254390717,47.9481658936],"type":"Point"}
}