{
  "type": "Feature",
  "properties": {
    "addr:full":"Reiterkreuzweg 13 Rohrmoos-Untertal Steiermark 8971",
    "addr:housenumber":"13",
    "addr:postcode":"8971",
    "addr:street":"Reiterkreuzweg",
    "iso:country":"AT",
    "sg:address":"Reiterkreuzweg 13",
    "sg:city":"Rohrmoos-Untertal",
    "sg:orig_category":"Pensionen / Privatzimmer",
    "sg:phone":"+43 3687 61475",
    "sg:postcode":"8971",
    "sg:province":"Steiermark",
    "wof:name":"H\u00f6flehner Franz",
    "wof:placetype":"venue"
},
  "geometry": {"coordinates":[13.6526470184,47.3824653625],"type":"Point"}
}