{
  "type": "Feature",
  "properties": {
    "iso:country":"AT",
    "sg:address":"Dobersberger Str 14",
    "sg:city":"Karlstein an der Thaya",
    "sg:orig_category":"Unternehmensberatung",
    "sg:phone":"+43 2844 7008",
    "sg:postcode":"3822",
    "sg:province":"Nieder\u00f6sterreich",
    "wof:name":"Consent Betriebsberatung GesmbH",
    "wof:placetype":"venue"
},
  "geometry": {"coordinates":[15.3973560333,48.8860855103],"type":"Point"}
}