{
  "type": "Feature",
  "properties": {
    "addr:full":"Nr 24 St. Lorenzen Steiermark 8715",
    "addr:postcode":"8715",
    "addr:street":"Nr 24",
    "iso:country":"AT",
    "sg:address":"Nr 24",
    "sg:city":"St. Lorenzen",
    "sg:classifiers":[
        {
            "category":"Organizations",
            "subcategory":"Community Association",
            "type":"Services"
        }
    ],
    "sg:phone":"+43 3512 73506",
    "sg:postcode":"8715",
    "sg:province":"Steiermark",
    "sg:tags":[
        "relation",
        "public"
    ],
    "wof:name":"Dimi PR-Service",
    "wof:placetype":"venue"
},
  "geometry": {"coordinates":[14.8935403824,47.2492713928],"type":"Point"}
}