{
  "type": "Feature",
  "properties": {
    "addr:full":"Loferer Str 22 Saalfelden am Steinernen Meer Salzburg 5760",
    "addr:postcode":"5760",
    "addr:street":"Str 22;Salzburg",
    "iso:country":"AT",
    "sg:address":"Loferer Str 22",
    "sg:city":"Saalfelden am Steinernen Meer",
    "sg:orig_category":"Trachtenbekleidung",
    "sg:phone":"+43 4365 82726560",
    "sg:postcode":"5760",
    "sg:province":"Salzburg",
    "wof:name":"M\u00fchringer Mode u Tracht KG",
    "wof:placetype":"venue"
},
  "geometry": {"coordinates":[12.8492765427,47.4265823364],"type":"Point"}
}