{
  "type": "Feature",
  "properties": {
    "iso:country":"AT",
    "sg:address":"Franz-Michael-Felder-Strasse 28",
    "sg:city":"Hohenems",
    "sg:classifiers":[
        {
            "category":"Professional",
            "subcategory":"Art Services",
            "type":"Services"
        }
    ],
    "sg:phone":"+43 5576 78990",
    "sg:postcode":"6845",
    "sg:province":"Vorarlberg",
    "sg:tags":[
        "agency",
        "artist"
    ],
    "sg:website":"festivals.cc",
    "wof:name":"Veranstaltungsservice Peter",
    "wof:placetype":"venue"
},
  "geometry": {"coordinates":[9.6850309372,47.3596611023],"type":"Point"}
}