{
  "type": "Feature",
  "properties": {
    "addr:full":"K\u00e4rntner Str 501 Graz Steiermark 8020",
    "addr:housenumber":"501",
    "addr:postcode":"8020",
    "addr:street":"Str",
    "iso:country":"AT",
    "sg:address":"K\u00e4rntner Str 501",
    "sg:city":"Graz",
    "sg:orig_category":"Farben U Lacke / Erzeugung U Gro\u00c3\u0178handel",
    "sg:phone":"+43 4331 6713206",
    "sg:postcode":"8020",
    "sg:province":"Steiermark",
    "wof:name":"Christ Ludwig & Co GesmbH",
    "wof:placetype":"venue"
},
  "geometry": {"coordinates":[15.4111499786,47.0689201355],"type":"Point"}
}