{
  "type": "Feature",
  "properties": {
    "addr:full":"Wittgensteinstr 122 Wien Wien 1130",
    "addr:housenumber":"122",
    "addr:postcode":"1130",
    "iso:country":"AT",
    "sg:address":"Wittgensteinstr 122",
    "sg:city":"Wien",
    "sg:orig_category":"Werbeagenturen",
    "sg:phone":"+43 1 8881037",
    "sg:postcode":"1130",
    "sg:province":"Wien",
    "wof:name":"Marketing Spezial Paudler Philipp Dagmar Mag",
    "wof:placetype":"venue"
},
  "geometry": {"coordinates":[16.2628135681,48.1601028442],"type":"Point"}
}