{
  "type": "Feature",
  "properties": {
    "addr:full":"Josefst\u00e4dter Str 9 Wien Wien 1080",
    "addr:housenumber":"9",
    "addr:postcode":"1080",
    "addr:street":"Str",
    "iso:country":"AT",
    "sg:address":"Josefst\u00e4dter Str 9",
    "sg:city":"Wien",
    "sg:orig_category":"Juweliere, Gold- U Silberschmiede",
    "sg:phone":"+43 1 4069043",
    "sg:postcode":"1080",
    "sg:province":"Wien",
    "wof:name":"Celand Helmut",
    "wof:placetype":"venue"
},
  "geometry": {"coordinates":[16.3430690765,48.2106552124],"type":"Point"}
}