{
  "type": "Feature",
  "properties": {
    "addr:full":"Wipplingerstr 5 Wien Wien 1010",
    "addr:housenumber":"5",
    "addr:postcode":"1010",
    "addr:street":"Wipplingerstr",
    "iso:country":"AT",
    "sg:address":"Wipplingerstr 5",
    "sg:city":"Wien",
    "sg:orig_category":"Antiquariate",
    "sg:phone":"+43 1 5337149",
    "sg:postcode":"1010",
    "sg:province":"Wien",
    "wof:name":"Bourcy & Paulusch",
    "wof:placetype":"venue"
},
  "geometry": {"coordinates":[16.3712882996,48.2114601135],"type":"Point"}
}