{
  "type": "Feature",
  "properties": {
    "addr:full":"Dorfstr 34 Lans Tirol 6072",
    "addr:housenumber":"34",
    "addr:postcode":"6072",
    "addr:street":"Dorfstr;Tirol",
    "iso:country":"AT",
    "sg:address":"Dorfstr 34",
    "sg:city":"Lans",
    "sg:orig_category":"Tourismusinformation U -Organisationen",
    "sg:phone":"+43 4351 2378178",
    "sg:postcode":"6072",
    "sg:province":"Tirol",
    "wof:name":"Tourismusb\u00fcro Lans",
    "wof:placetype":"venue"
},
  "geometry": {"coordinates":[11.4289102554,47.2383346558],"type":"Point"}
}