{
  "type": "Feature",
  "properties": {
    "addr:full":"Bergg 101 Neusiedl am See Burgenland 7100",
    "addr:housenumber":"101",
    "addr:postcode":"7100",
    "iso:country":"AT",
    "sg:address":"Bergg 101",
    "sg:city":"Neusiedl am See",
    "sg:orig_category":"Hafnereien",
    "sg:phone":"+43 2167 24440",
    "sg:postcode":"7100",
    "sg:province":"Burgenland",
    "wof:name":"Horvath Ernst",
    "wof:placetype":"venue"
},
  "geometry": {"coordinates":[16.834569931,47.9593582153],"type":"Point"}
}