{
  "type": "Feature",
  "properties": {
    "addr:full":"Oberdorf 14 Kematen in Tirol Tirol 6175",
    "addr:housenumber":"14",
    "addr:postcode":"6175",
    "addr:street":"Oberdorf;Tirol",
    "iso:country":"AT",
    "sg:address":"Oberdorf 14",
    "sg:city":"Kematen in Tirol",
    "sg:orig_category":"Gemeinden",
    "sg:phone":"+43 5232 771770",
    "sg:postcode":"6175",
    "sg:province":"Tirol",
    "wof:name":"Gemeindeamt Ranggen",
    "wof:placetype":"venue"
},
  "geometry": {"coordinates":[11.2120819092,47.2574043274],"type":"Point"}
}