{
  "type": "Feature",
  "properties": {
    "addr:full":"Goldschlagstr 126/38 Wien Wien 1150",
    "addr:housenumber":"126 / 38",
    "addr:postcode":"1150",
    "iso:country":"AT",
    "sg:address":"Goldschlagstr 126/38",
    "sg:city":"Wien",
    "sg:orig_category":"Telefonmarketing",
    "sg:phone":"+43 1 3199900",
    "sg:postcode":"1150",
    "sg:province":"Wien",
    "sg:website":"www.teleprofi.at",
    "wof:name":"Teleprofi Eva Maria Akkaya KEG",
    "wof:placetype":"venue"
},
  "geometry": {"coordinates":[16.3135967255,48.1954116821],"type":"Point"}
}