{
  "type": "Feature",
  "properties": {
    "addr:full":"Liechtensteinstrasse 13 Mistelbach Nieder\u00f6sterreich 2130",
    "addr:housenumber":"13",
    "addr:postcode":"2130",
    "addr:street":"Liechtensteinstrasse;Niederoesterreich",
    "iso:country":"AT",
    "sg:address":"Liechtensteinstrasse 13",
    "sg:city":"Mistelbach",
    "sg:classifiers":[
        {
            "category":"Home & Garden",
            "subcategory":"Building Materials",
            "type":"Retail Goods"
        }
    ],
    "sg:phone":"+43 2572 2458",
    "sg:postcode":"2130",
    "sg:province":"Nieder\u00f6sterreich",
    "sg:tags":[
        "installation",
        "electric"
    ],
    "wof:name":"Ing. Josef Zodtl",
    "wof:placetype":"venue"
},
  "geometry": {"coordinates":[16.5773239136,48.5675048828],"type":"Point"}
}