{
  "type": "Feature",
  "properties": {
    "iso:country":"AT",
    "sg:address":"Richterg 8",
    "sg:city":"Wien",
    "sg:orig_category":"\u00c3\u201erzte / F Allgemeinmedizin",
    "sg:phone":"+43 1 5234310",
    "sg:postcode":"1070",
    "sg:province":"Wien",
    "wof:name":"Gehl Isolde Dr",
    "wof:placetype":"venue"
},
  "geometry": {"coordinates":[16.3483161926,48.1994247437],"type":"Point"}
}