{
  "type": "Feature",
  "properties": {
    "addr:full":"Florianig 17 Wien Wien 1080",
    "addr:housenumber":"17",
    "addr:postcode":"1080",
    "addr:street":"Florianig",
    "iso:country":"AT",
    "sg:address":"Florianig 17",
    "sg:city":"Wien",
    "sg:orig_category":"Textilreinigung",
    "sg:phone":"+43 4314 029808",
    "sg:postcode":"1080",
    "sg:province":"Wien",
    "wof:name":"Harter M OEG",
    "wof:placetype":"venue"
},
  "geometry": {"coordinates":[16.3516292572,48.211769104],"type":"Point"}
}