{
  "type": "Feature",
  "properties": {
    "addr:full":"Dirmhirng 126 Wien Wien 1230",
    "addr:housenumber":"126",
    "addr:postcode":"1230",
    "iso:country":"AT",
    "sg:address":"Dirmhirng 126",
    "sg:city":"Wien",
    "sg:orig_category":"Bauunternehmen",
    "sg:phone":"+43 1 88912100",
    "sg:postcode":"1230",
    "sg:province":"Wien",
    "wof:name":"Ofner Bruno GesmbH",
    "wof:placetype":"venue"
},
  "geometry": {"coordinates":[16.284029007,48.1381454468],"type":"Point"}
}