{
  "type": "Feature",
  "properties": {
    "addr:full":"Niederranna Hofkirchen im M\u00fchlkreis Ober\u00f6sterreich 4142",
    "addr:postcode":"4142",
    "addr:street":"Niederranna",
    "iso:country":"AT",
    "sg:address":"Niederranna",
    "sg:city":"Hofkirchen im M\u00fchlkreis",
    "sg:orig_category":"Feuerwehren",
    "sg:phone":"+43 7285 516",
    "sg:postcode":"4142",
    "sg:province":"Ober\u00f6sterreich",
    "wof:name":"Freiwillige Feuerwehr Niederranna",
    "wof:placetype":"venue"
},
  "geometry": {"coordinates":[13.7992286682,48.4669265747],"type":"Point"}
}