{
  "type": "Feature",
  "properties": {
    "addr:full":"D\u00f6llacher Str 1 Liezen Steiermark 8940",
    "addr:housenumber":"1",
    "addr:postcode":"8940",
    "addr:street":"Str",
    "iso:country":"AT",
    "sg:address":"D\u00f6llacher Str 1",
    "sg:city":"Liezen",
    "sg:orig_category":"Psychotherapie",
    "sg:phone":"+43 676 4189098",
    "sg:postcode":"8940",
    "sg:province":"Steiermark",
    "wof:name":"Preis Roswitha Viktoria",
    "wof:placetype":"venue"
},
  "geometry": {"coordinates":[14.2413349152,47.5672111511],"type":"Point"}
}