{
  "type": "Feature",
  "properties": {
    "addr:full":"K\u00e4rntner Str. 4 Graz Steiermark 8020",
    "addr:housenumber":"4",
    "addr:postcode":"8020",
    "addr:street":"Str.",
    "iso:country":"AT",
    "sg:address":"K\u00e4rntner Str. 4",
    "sg:city":"Graz",
    "sg:classifiers":[
        {
            "category":"Wholesale",
            "subcategory":"Drugs",
            "type":"Manufacturing & Wholesale Goods"
        }
    ],
    "sg:phone":"+43 4331 6293000",
    "sg:postcode":"8020",
    "sg:province":"Steiermark",
    "sg:tags":[
        "chemical",
        "pharmaceutical"
    ],
    "wof:name":"FRANZ LEITNER BRENNSTOFF U. MINERAL\u00d6LHANDELS GMBH",
    "wof:placetype":"venue"
},
  "geometry": {"coordinates":[15.4111499786,47.0689201355],"type":"Point"}
}