{
  "type": "Feature",
  "properties": {
    "addr:full":"Neunkirchner Strasse 37 Wiener Neustadt Nieder\u00f6sterreich 2700",
    "addr:housenumber":"37",
    "addr:postcode":"2700",
    "addr:street":"Neunkirchner Strasse",
    "iso:country":"AT",
    "sg:address":"Neunkirchner Strasse 37",
    "sg:city":"Wiener Neustadt",
    "sg:classifiers":[
        {
            "category":"Food & Beverages",
            "subcategory":"Groceries & Convenience Stores",
            "type":"Retail Goods"
        }
    ],
    "sg:phone":"+43 2622 85956",
    "sg:postcode":"2700",
    "sg:province":"Nieder\u00f6sterreich",
    "sg:tags":[
        "dietetic",
        "foodstuff"
    ],
    "sg:website":"vitacan.com",
    "wof:name":"MEDOSAN Handelsges.m.b.H.",
    "wof:placetype":"venue"
},
  "geometry": {"coordinates":[16.2420806885,47.8073005676],"type":"Point"}
}