{
  "type": "Feature",
  "properties": {
    "addr:full":"Linzer Strasse 143a Gablitz Nieder\u00f6sterreich 3003",
    "addr:housenumber":"143a",
    "addr:postcode":"3003",
    "addr:street":"Linzer Strasse",
    "iso:country":"AT",
    "sg:address":"Linzer Strasse 143a",
    "sg:city":"Gablitz",
    "sg:classifiers":[
        {
            "category":"Home & Garden",
            "subcategory":"Building Materials",
            "type":"Retail Goods"
        }
    ],
    "sg:phone":"+43 2231 65620",
    "sg:postcode":"3003",
    "sg:province":"Nieder\u00f6sterreich",
    "sg:tags":[
        "gravel",
        "crushed"
    ],
    "wof:name":"Leopold Ring",
    "wof:placetype":"venue"
},
  "geometry": {"coordinates":[16.1450634003,48.2330131531],"type":"Point"}
}