{
  "type": "Feature",
  "properties": {
    "iso:country":"AT",
    "sg:address":"Sebastian Kneipp-Weg 17/III",
    "sg:city":"Innsbruck",
    "sg:orig_category":"Physiotherapie",
    "sg:phone":"+43 512 272999",
    "sg:postcode":"6020",
    "sg:province":"Tirol",
    "wof:name":"Margreiter Wolfgang Dipl-PT",
    "wof:placetype":"venue"
},
  "geometry": {"coordinates":[11.3913040161,47.2679977417],"type":"Point"}
}