{
  "type": "Feature",
  "properties": {
    "iso:country":"AT",
    "sg:address":"Ringstr 25",
    "sg:city":"Feldbach",
    "sg:orig_category":"Zahngesundheitsvorsorge",
    "sg:phone":"+43 4331 52250920",
    "sg:postcode":"8330",
    "sg:province":"Steiermark",
    "wof:name":"Zahnambulatorium d Stmk Gebietskrankenkasse",
    "wof:placetype":"venue"
},
  "geometry": {"coordinates":[15.8853473663,46.9521026611],"type":"Point"}
}