{
  "type": "Feature",
  "properties": {
    "addr:full":"Wilhelm-Leibl-G 12-14 Wien Wien 1130",
    "addr:postcode":"12-14;1130",
    "iso:country":"AT",
    "sg:address":"Wilhelm-Leibl-G 12-14",
    "sg:city":"Wien",
    "sg:orig_category":"Immobilienverwaltungen",
    "sg:phone":"+43 1 80415610",
    "sg:postcode":"1130",
    "sg:province":"Wien",
    "wof:name":"Familienhilfe WohnungseigentumsverwaltungsgesmbH",
    "wof:placetype":"venue"
},
  "geometry": {"coordinates":[16.2765312195,48.1765708923],"type":"Point"}
}