{
  "type": "Feature",
  "properties": {
    "addr:full":"Edlbacherstr 10 Linz Ober\u00f6sterreich 4020",
    "addr:housenumber":"10",
    "addr:postcode":"4020",
    "addr:street":"Edlbacherstr",
    "iso:country":"AT",
    "sg:address":"Edlbacherstr 10",
    "sg:city":"Linz",
    "sg:orig_category":"Bauunternehmen",
    "sg:phone":"+43 732 69710",
    "sg:postcode":"4020",
    "sg:province":"Ober\u00f6sterreich",
    "sg:website":"swietelsky.com",
    "wof:name":"Swietelsky Baugesellschaft mbH",
    "wof:placetype":"venue"
},
  "geometry": {"coordinates":[14.2954435349,48.2864685059],"type":"Point"}
}