{
  "type": "Feature",
  "properties": {
    "addr:full":"Feldstrasse 2 Ennsdorf Nieder\u00f6sterreich 4482",
    "addr:housenumber":"2",
    "addr:postcode":"4482",
    "addr:street":"Feldstrasse",
    "iso:country":"AT",
    "sg:address":"Feldstrasse 2",
    "sg:city":"Ennsdorf",
    "sg:classifiers":[
        {
            "category":"Utilities",
            "subcategory":"Fuel Oil & Lpg",
            "type":"Services"
        }
    ],
    "sg:phone":"+43 7223 838180",
    "sg:postcode":"4482",
    "sg:province":"Nieder\u00f6sterreich",
    "sg:tags":[
        "water",
        "coal",
        "ore",
        "drilling",
        "deep"
    ],
    "sg:website":"reisinger.net",
    "wof:name":"Reisinger Gesellschaft m.b.H. Bohrungen - Brunnenbau Spezialtiefbau - Installationen",
    "wof:placetype":"venue"
},
  "geometry": {"coordinates":[14.50187397,48.2132301331],"type":"Point"}
}