{
  "type": "Feature",
  "properties": {
    "addr:full":"Batloggstr 97 Schruns Vorarlberg 6780",
    "addr:housenumber":"97",
    "addr:postcode":"6780",
    "addr:street":"Batloggstr",
    "iso:country":"AT",
    "sg:address":"Batloggstr 97",
    "sg:city":"Schruns",
    "sg:orig_category":"Steuerberatung",
    "sg:phone":"+43 5556 733270",
    "sg:postcode":"6780",
    "sg:province":"Vorarlberg",
    "wof:name":"RTG R\u00e4tikon Treuhand GmbH - Wirtschaftspr\u00fcfungs- und Steuerberatungsgesellschaft",
    "wof:placetype":"venue"
},
  "geometry": {"coordinates":[9.9053888321,47.078163147],"type":"Point"}
}