{
  "type": "Feature",
  "properties": {
    "addr:full":"Nr 127 Eberschwang Ober\u00f6sterreich 4906",
    "addr:postcode":"4906",
    "addr:street":"Nr 127",
    "iso:country":"AT",
    "sg:address":"Nr 127",
    "sg:city":"Eberschwang",
    "sg:orig_category":"Holzwaren",
    "sg:phone":"+43 7753 2108",
    "sg:postcode":"4906",
    "sg:province":"Ober\u00f6sterreich",
    "wof:name":"Fisecker G\u00fcnther - Holzwaren",
    "wof:placetype":"venue"
},
  "geometry": {"coordinates":[13.5620698929,48.154460907],"type":"Point"}
}