{
  "type": "Feature",
  "properties": {
    "addr:full":"V\u00f6lkermarkter Str 38 St. Veit an der Glan K\u00e4rnten 9300",
    "addr:housenumber":"38",
    "addr:postcode":"9300",
    "addr:street":"Str;Kaernten",
    "iso:country":"AT",
    "sg:address":"V\u00f6lkermarkter Str 38",
    "sg:city":"St. Veit an der Glan",
    "sg:orig_category":"Friseure U Frisiersalons",
    "sg:phone":"+43 4342 122596",
    "sg:postcode":"9300",
    "sg:province":"K\u00e4rnten",
    "wof:name":"Frisiersalon Belivia",
    "wof:placetype":"venue"
},
  "geometry": {"coordinates":[14.3717489243,46.7659492493],"type":"Point"}
}