{
  "type": "Feature",
  "properties": {
    "addr:full":"Rinnholzpl 1 Gmunden Ober\u00f6sterreich 4810",
    "addr:housenumber":"1",
    "addr:postcode":"4810",
    "addr:street":"Rinnholzpl;Oberoesterreich",
    "iso:country":"AT",
    "sg:address":"Rinnholzpl 1",
    "sg:city":"Gmunden",
    "sg:orig_category":"Handarbeiten",
    "sg:phone":"+43 761265609",
    "sg:postcode":"4810",
    "sg:province":"Ober\u00f6sterreich",
    "wof:name":"Forstinger Monika",
    "wof:placetype":"venue"
},
  "geometry": {"coordinates":[13.7987136841,47.9193229675],"type":"Point"}
}