{
  "type": "Feature",
  "properties": {
    "addr:full":"Mitterweg 37 Pinsdorf Ober\u00f6sterreich 4812",
    "addr:housenumber":"37",
    "addr:postcode":"4812",
    "addr:street":"Mitterweg",
    "iso:country":"AT",
    "sg:address":"Mitterweg 37",
    "sg:city":"Pinsdorf",
    "sg:classifiers":[
        {
            "category":"Home & Garden",
            "subcategory":"Building Materials",
            "type":"Retail Goods"
        }
    ],
    "sg:phone":"+43 7612639730",
    "sg:postcode":"4812",
    "sg:province":"Ober\u00f6sterreich",
    "sg:tags":[
        "baustoffe",
        "-material",
        "u"
    ],
    "wof:name":"Nu\u00dfbaumer Baustoff GmbH",
    "wof:placetype":"venue"
},
  "geometry": {"coordinates":[13.7738981247,47.933303833],"type":"Point"}
}