{
  "type": "Feature",
  "properties": {
    "addr:full":"Unterwei\u00dfenbach 101 Kuchl Salzburg 5431",
    "addr:housenumber":"101",
    "addr:postcode":"5431",
    "addr:street":"Unterweissenbach;Salzburg",
    "iso:country":"AT",
    "sg:address":"Unterwei\u00dfenbach 101",
    "sg:city":"Kuchl",
    "sg:orig_category":"Schneidereien",
    "sg:phone":"+43 6244 7743",
    "sg:postcode":"5431",
    "sg:province":"Salzburg",
    "wof:name":"Trachtenschneiderei Struber",
    "wof:placetype":"venue"
},
  "geometry": {"coordinates":[13.1438808441,47.625667572],"type":"Point"}
}