{
  "type": "Feature",
  "properties": {
    "addr:full":"Brunecker Str 2 Innsbruck Tirol 6020",
    "addr:housenumber":"2",
    "addr:postcode":"6020",
    "addr:street":"Str;Tirol",
    "iso:country":"AT",
    "sg:address":"Brunecker Str 2",
    "sg:city":"Innsbruck",
    "sg:orig_category":"Sonnenstudios",
    "sg:phone":"+43 512 564444",
    "sg:postcode":"6020",
    "sg:province":"Tirol",
    "wof:name":"Sonnenstudio Braunb\u00e4r",
    "wof:placetype":"venue"
},
  "geometry": {"coordinates":[11.4009437561,47.2663726807],"type":"Point"}
}