{
  "type": "Feature",
  "properties": {
    "addr:full":"Stanislausg 13 Wien Wien 1030",
    "addr:housenumber":"13",
    "addr:postcode":"1030",
    "addr:street":"Stanislausg",
    "iso:country":"AT",
    "sg:address":"Stanislausg 13",
    "sg:city":"Wien",
    "sg:orig_category":"Werbegrafik- U Grafik-Design",
    "sg:phone":"+43 4317 981653",
    "sg:postcode":"1030",
    "sg:province":"Wien",
    "wof:name":"Meixner Eva-Maria",
    "wof:placetype":"venue"
},
  "geometry": {"coordinates":[16.3885917664,48.1937294006],"type":"Point"}
}