{
  "type": "Feature",
  "properties": {
    "iso:country":"AT",
    "sg:address":"Amraser Str 1",
    "sg:city":"Innsbruck",
    "sg:orig_category":"Friseure U Frisiersalons",
    "sg:phone":"+43 4351 2574112",
    "sg:postcode":"6020",
    "sg:province":"Tirol",
    "wof:name":"Frisiersalon Innsbrucker Kamplstub'n",
    "wof:placetype":"venue"
},
  "geometry": {"coordinates":[11.4039592743,47.2652206421],"type":"Point"}
}