{
  "type": "Feature",
  "properties": {
    "iso:country":"AT",
    "sg:address":"Josef Kr\u00e4nzl-Str 20",
    "sg:city":"Ried im Innkreis",
    "sg:orig_category":"Non-Classified Establishments",
    "sg:phone":"+43 7752 826260",
    "sg:postcode":"4910",
    "sg:province":"Ober\u00f6sterreich",
    "wof:name":"BEV-Vermessungsamt",
    "wof:placetype":"venue"
},
  "geometry": {"coordinates":[13.4865703583,48.2032585144],"type":"Point"}
}