{
  "type": "Feature",
  "properties": {
    "addr:full":"Nr 30 Pernersdorf-Pfaffendorf Nieder\u00f6sterreich 2052",
    "addr:postcode":"2052",
    "addr:street":"Nr 30 Pernersdorf-Pfaffendorf",
    "iso:country":"AT",
    "sg:address":"Nr 30",
    "sg:city":"Pernersdorf-Pfaffendorf",
    "sg:orig_category":"Brandschutz",
    "sg:phone":"+43 2944 86520",
    "sg:postcode":"2052",
    "sg:province":"Nieder\u00f6sterreich",
    "wof:name":"Zemann Walter",
    "wof:placetype":"venue"
},
  "geometry": {"coordinates":[16.0126857758,48.6999816895],"type":"Point"}
}