{
  "type": "Feature",
  "properties": {
    "addr:full":"F\u00fcrbergstr 47 Salzburg Salzburg 5020",
    "addr:housenumber":"47",
    "addr:postcode":"5020",
    "addr:street":"Fuerbergstr;Salzburg",
    "iso:country":"AT",
    "sg:address":"F\u00fcrbergstr 47",
    "sg:city":"Salzburg",
    "sg:orig_category":"Lebensmittel / Einzelhandel",
    "sg:phone":"+43 662 650570",
    "sg:postcode":"5020",
    "sg:province":"Salzburg",
    "wof:name":"SPAR \u00f6sterreichische Warenhandels-AG",
    "wof:placetype":"venue"
},
  "geometry": {"coordinates":[13.0433769226,47.8006744385],"type":"Point"}
}