{
  "type": "Feature",
  "properties": {
    "addr:full":"Industriestr 2 Vomp Tirol 6134",
    "addr:housenumber":"2",
    "addr:postcode":"6134",
    "addr:street":"Industriestr;Tirol",
    "iso:country":"AT",
    "sg:address":"Industriestr 2",
    "sg:city":"Vomp",
    "sg:classifiers":[
        {
            "category":"Home & Garden",
            "subcategory":"Garden Supply",
            "type":"Retail Goods"
        }
    ],
    "sg:phone":"+43 5242 69890",
    "sg:postcode":"6134",
    "sg:province":"Tirol",
    "sg:tags":[
        "schotter",
        "sand",
        "u"
    ],
    "wof:name":"Derfeser Ernst GmbH",
    "wof:placetype":"venue"
},
  "geometry": {"coordinates":[11.6994972229,47.3513221741],"type":"Point"}
}