{
  "type": "Feature",
  "properties": {
    "addr:full":"Auerweg 8 Rohrmoos-Untertal Steiermark 8971",
    "addr:housenumber":"8",
    "addr:postcode":"8971",
    "addr:street":"Auerweg",
    "iso:country":"AT",
    "sg:address":"Auerweg 8",
    "sg:city":"Rohrmoos-Untertal",
    "sg:orig_category":"Pensionen / Privatzimmer",
    "sg:phone":"+43 3687 614370",
    "sg:postcode":"8971",
    "sg:province":"Steiermark",
    "wof:name":"Hutegger Hans und Erika",
    "wof:placetype":"venue"
},
  "geometry": {"coordinates":[13.6774463654,47.3723106384],"type":"Point"}
}