{
  "type": "Feature",
  "properties": {
    "addr:full":"Kronburg 103 Zams Tirol 6511",
    "addr:housenumber":"103",
    "addr:postcode":"6511",
    "addr:street":"Kronburg;Tirol",
    "iso:country":"AT",
    "sg:address":"Kronburg 103",
    "sg:city":"Zams",
    "sg:orig_category":"Non-Classified Establishments",
    "sg:phone":"+43 5442 65778",
    "sg:postcode":"6511",
    "sg:province":"Tirol",
    "wof:name":"Kloster Kronburg",
    "wof:placetype":"venue"
},
  "geometry": {"coordinates":[10.6258029938,47.1770019531],"type":"Point"}
}