{
  "type": "Feature",
  "properties": {
    "addr:full":"Deutschordenstrasse 6 Wien Wien 1140",
    "addr:housenumber":"6",
    "addr:postcode":"1140",
    "addr:street":"Deutschordenstrasse",
    "iso:country":"AT",
    "sg:address":"Deutschordenstrasse 6",
    "sg:city":"Wien",
    "sg:classifiers":[
        {
            "category":"Manufacturing",
            "subcategory":"Rubber & Plastics",
            "type":"Manufacturing & Wholesale Goods"
        }
    ],
    "sg:phone":"+43 1 9118550",
    "sg:postcode":"1140",
    "sg:province":"Wien",
    "sg:tags":[
        "high-performance"
    ],
    "sg:website":"ahlborn-kunststoffe.at",
    "wof:name":"Ahlborn Kunststoffe",
    "wof:placetype":"venue"
},
  "geometry": {"coordinates":[16.2666931152,48.19556427],"type":"Point"}
}