{
  "type": "Feature",
  "properties": {
    "addr:full":"Paracelsusstr 20 Wels Ober\u00f6sterreich 4600",
    "addr:housenumber":"20",
    "addr:postcode":"4600",
    "addr:street":"Paracelsusstr;Oberoesterreich",
    "iso:country":"AT",
    "sg:address":"Paracelsusstr 20",
    "sg:city":"Wels",
    "sg:orig_category":"Technische Bedarfsartikel",
    "sg:phone":"+43 7242 46291",
    "sg:postcode":"4600",
    "sg:province":"Ober\u00f6sterreich",
    "wof:name":"St\u00f6ffl Rudolf GmbH",
    "wof:placetype":"venue"
},
  "geometry": {"coordinates":[14.005654335,48.1591300964],"type":"Point"}
}