{
  "type": "Feature",
  "properties": {
    "iso:country":"AT",
    "sg:address":"Kapellenstr 1",
    "sg:city":"Lustenau",
    "sg:orig_category":"Lebensmittel / Einzelhandel",
    "sg:phone":"+43 5577 86658",
    "sg:postcode":"6890",
    "sg:province":"Vorarlberg",
    "wof:name":"SPAR \u00f6sterr Warenhandels-AG - Rheincenter",
    "wof:placetype":"venue"
},
  "geometry": {"coordinates":[9.660279274,47.4307098389],"type":"Point"}
}