{
  "type": "Feature",
  "properties": {
    "addr:full":"Edmund-Hofbauer-Str 1 Krems an der Donau Nieder\u00f6sterreich 3500",
    "addr:housenumber":"1",
    "addr:postcode":"3500",
    "addr:street":"Edmund-Hofbauer-Str",
    "iso:country":"AT",
    "sg:address":"Edmund-Hofbauer-Str 1",
    "sg:city":"Krems an der Donau",
    "sg:orig_category":"Steuerberatung",
    "sg:phone":"+43 4327 32831300",
    "sg:postcode":"3500",
    "sg:province":"Nieder\u00f6sterreich",
    "wof:name":"Astoria Wirtschaftstreuhand GesmbH Steuerberatungsgesellschaft",
    "wof:placetype":"venue"
},
  "geometry": {"coordinates":[15.6022901535,48.4082679749],"type":"Point"}
}