{
  "type": "Feature",
  "properties": {
    "addr:full":"Nr 64 Eben im Pongau Salzburg 5531",
    "addr:postcode":"5531",
    "addr:street":"Nr",
    "iso:country":"AT",
    "sg:address":"Nr 64",
    "sg:city":"Eben im Pongau",
    "sg:orig_category":"Holzhandel",
    "sg:phone":"+43 6458 85600",
    "sg:postcode":"5531",
    "sg:province":"Salzburg",
    "wof:name":"HGS Holzteam Hochleitner-Gr\u00fcnwald-Stadler OHG",
    "wof:placetype":"venue"
},
  "geometry": {"coordinates":[13.3952989578,47.4079742432],"type":"Point"}
}