{
  "type": "Feature",
  "properties": {
    "addr:full":"Harter Str 28 Gratkorn Steiermark 8101",
    "addr:postcode":"8101",
    "addr:street":"Str 28",
    "iso:country":"AT",
    "sg:address":"Harter Str 28",
    "sg:city":"Gratkorn",
    "sg:orig_category":"Autobusse / Service U Vertrieb",
    "sg:phone":"+43 3124 22945",
    "sg:postcode":"8101",
    "sg:province":"Steiermark",
    "wof:name":"Noge Autobus Imp-u Export GmbH",
    "wof:placetype":"venue"
},
  "geometry": {"coordinates":[15.3663949966,47.1216468811],"type":"Point"}
}