{
  "type": "Feature",
  "properties": {
    "addr:full":"Frauenwiese 12 Kapfenberg Steiermark 8605",
    "addr:housenumber":"12",
    "addr:postcode":"8605",
    "addr:street":"Frauenwiese",
    "iso:country":"AT",
    "sg:address":"Frauenwiese 12",
    "sg:city":"Kapfenberg",
    "sg:orig_category":"Rauchfangkehrer",
    "sg:phone":"+43 3862 32146",
    "sg:postcode":"8605",
    "sg:province":"Steiermark",
    "wof:name":"Weigand Siegfried",
    "wof:placetype":"venue"
},
  "geometry": {"coordinates":[15.319111824,47.4534835815],"type":"Point"}
}