{
  "type": "Feature",
  "properties": {
    "addr:full":"Wiedner Hauptstr 19 Wien Wien 1040",
    "addr:housenumber":"19",
    "addr:postcode":"1040",
    "addr:street":"Hauptstr",
    "iso:country":"AT",
    "sg:address":"Wiedner Hauptstr 19",
    "sg:city":"Wien",
    "sg:orig_category":"Ingenieurkonsulenten / Zivilingenieure",
    "sg:phone":"+43 1 50519840",
    "sg:postcode":"1040",
    "sg:province":"Wien",
    "wof:name":"Gruppe Wasser Ziviltechniker Gesellschaft f Wasserwirtschaft GmbH",
    "wof:placetype":"venue"
},
  "geometry": {"coordinates":[16.3676967621,48.1964988708],"type":"Point"}
}