{
  "type": "Feature",
  "properties": {
    "addr:full":"Hauptstr 1a Klosterneuburg Nieder\u00f6sterreich 3400",
    "addr:housenumber":"1a",
    "addr:postcode":"3400",
    "addr:street":"Hauptstr;Niederoesterreich",
    "iso:country":"AT",
    "sg:address":"Hauptstr 1a",
    "sg:city":"Klosterneuburg",
    "sg:orig_category":"Betonbohr- U -Schneidedienst",
    "sg:phone":"+43 2243 34902",
    "sg:postcode":"3400",
    "sg:province":"Nieder\u00f6sterreich",
    "wof:name":"Liska GmbH",
    "wof:placetype":"venue"
},
  "geometry": {"coordinates":[16.3111228943,48.2904663086],"type":"Point"}
}