{
  "type": "Feature",
  "properties": {
    "iso:country":"AT",
    "sg:address":"Scholzg 7",
    "sg:city":"Wien",
    "sg:orig_category":"Stra\u00c3\u0178enmarkierungen, Bodenmarkierungen",
    "sg:phone":"+43 1 3340011",
    "sg:postcode":"1020",
    "sg:province":"Wien",
    "sg:website":"www.parkline.at",
    "wof:name":"PARKLINE - Bodenmarkierung + Industriemalerei",
    "wof:placetype":"venue"
},
  "geometry": {"coordinates":[16.3701782227,48.2247619629],"type":"Point"}
}