{
  "type": "Feature",
  "properties": {
    "addr:full":"Nr 177 Stans Tirol 6135",
    "addr:postcode":"6135",
    "addr:street":"Nr 177;Tirol",
    "iso:country":"AT",
    "sg:address":"Nr 177",
    "sg:city":"Stans",
    "sg:orig_category":"Psychotherapie",
    "sg:phone":"+43 5242 71314",
    "sg:postcode":"6135",
    "sg:province":"Tirol",
    "wof:name":"Plattner Karl L",
    "wof:placetype":"venue"
},
  "geometry": {"coordinates":[11.7170000076,47.36977005],"type":"Point"}
}