{
  "type": "Feature",
  "properties": {
    "iso:country":"AT",
    "sg:address":"Marienbadg 24",
    "sg:city":"Klagenfurt-Viktring",
    "sg:orig_category":"Unternehmensberatung",
    "sg:phone":"+43 463 292737",
    "sg:postcode":"9073",
    "sg:province":"K\u00e4rnten",
    "wof:name":"China-Consulting Dr Yang KEG",
    "wof:placetype":"venue"
},
  "geometry": {"coordinates":[14.2808742523,46.5874633789],"type":"Point"}
}