{
  "type": "Feature",
  "properties": {
    "addr:full":"Lumplgraben 123 Gro\u00dframing Ober\u00f6sterreich 4463",
    "addr:housenumber":"123",
    "addr:postcode":"4463",
    "addr:street":"Lumplgraben",
    "iso:country":"AT",
    "sg:address":"Lumplgraben 123",
    "sg:city":"Gro\u00dframing",
    "sg:orig_category":"Transportunternehmen",
    "sg:phone":"+43 7254 8212",
    "sg:postcode":"4463",
    "sg:province":"Ober\u00f6sterreich",
    "wof:name":"Garstenauer Peter",
    "wof:placetype":"venue"
},
  "geometry": {"coordinates":[14.5318183899,47.8597755432],"type":"Point"}
}