{
  "type": "Feature",
  "properties": {
    "iso:country":"AT",
    "sg:address":"Harter Strasse 29",
    "sg:city":"Gratkorn",
    "sg:orig_category":"Banknote, Coin, Coin-Rolls, Chip And Money Changers",
    "sg:phone":"+43 3124 23844",
    "sg:postcode":"8101",
    "sg:province":"Steiermark",
    "sg:website":"gbs-moneysys.com",
    "wof:name":"GBS-Geldbearbeitungssysteme GmbH",
    "wof:placetype":"venue"
},
  "geometry": {"coordinates":[15.3607091904,47.1223564148],"type":"Point"}
}