{
  "type": "Feature",
  "properties": {
    "addr:full":"Nr 14 Thernberg Nieder\u00f6sterreich 2832",
    "addr:postcode":"2832",
    "addr:street":"Nr 14 Thernberg",
    "iso:country":"AT",
    "sg:address":"Nr 14",
    "sg:city":"Thernberg",
    "sg:orig_category":"Botendienste",
    "sg:phone":"+43 699 19417524",
    "sg:postcode":"2832",
    "sg:province":"Nieder\u00f6sterreich",
    "wof:name":"Scherleitner Josef",
    "wof:placetype":"venue"
},
  "geometry": {"coordinates":[16.1604804993,47.6599655151],"type":"Point"}
}