{
  "type": "Feature",
  "properties": {
    "iso:country":"AT",
    "sg:address":"Amraser-See-Str 56a",
    "sg:city":"Innsbruck",
    "sg:orig_category":"Boutiquen",
    "sg:phone":"+43 512 325311",
    "sg:postcode":"6020",
    "sg:province":"Tirol",
    "wof:name":"Treff 17",
    "wof:placetype":"venue"
},
  "geometry": {"coordinates":[11.4283132553,47.2627105713],"type":"Point"}
}