{
  "type": "Feature",
  "properties": {
    "iso:country":"AT",
    "sg:address":"Millst\u00e4tter Str 10",
    "sg:city":"Radenthein",
    "sg:classifiers":[
        {
            "category":"Restaurant",
            "type":"Food & Drink"
        }
    ],
    "sg:phone":"+43 699 11399497",
    "sg:postcode":"9545",
    "sg:province":"K\u00e4rnten",
    "wof:name":"Werksrestaurant Flaschberger Leopold",
    "wof:placetype":"venue"
},
  "geometry": {"coordinates":[13.696931839,46.7985038757],"type":"Point"}
}