{
  "type": "Feature",
  "properties": {
    "addr:full":"Nr 1 Millstatt K\u00e4rnten 9872",
    "addr:postcode":"9872",
    "addr:street":"Nr;Kaernten",
    "iso:country":"AT",
    "sg:address":"Nr 1",
    "sg:city":"Millstatt",
    "sg:orig_category":"Appartements / Ferienwohnungen",
    "sg:phone":"+43 4766 2222",
    "sg:postcode":"9872",
    "sg:province":"K\u00e4rnten",
    "wof:name":"Fremdenpension Burgstaller",
    "wof:placetype":"venue"
},
  "geometry": {"coordinates":[13.5716075897,46.8050041199],"type":"Point"}
}