{
  "type": "Feature",
  "properties": {
    "addr:full":"Langg 37 Bad Radkersburg Steiermark 8490",
    "addr:housenumber":"37",
    "addr:postcode":"8490",
    "addr:street":"Langg",
    "iso:country":"AT",
    "sg:address":"Langg 37",
    "sg:city":"Bad Radkersburg",
    "sg:orig_category":"Waren Aller Art",
    "sg:phone":"+43 3476 2349",
    "sg:postcode":"8490",
    "sg:province":"Steiermark",
    "wof:name":"Bazar Mir Inh Adolf Heinz Mir",
    "wof:placetype":"venue"
},
  "geometry": {"coordinates":[15.9888820648,46.6908340454],"type":"Point"}
}