{
  "type": "Feature",
  "properties": {
    "addr:full":"Langenharter Strasse 1 St. Valentin Nieder\u00f6sterreich 4300",
    "addr:housenumber":"1",
    "addr:postcode":"4300",
    "addr:street":"Langenharter Strasse",
    "iso:country":"AT",
    "sg:address":"Langenharter Strasse 1",
    "sg:city":"St. Valentin",
    "sg:classifiers":[
        {
            "category":"Building & Trades",
            "subcategory":"Plumbing",
            "type":"Services"
        }
    ],
    "sg:phone":"+43 7435 53158",
    "sg:postcode":"4300",
    "sg:province":"Nieder\u00f6sterreich",
    "sg:tags":[
        "supraregional",
        "gas"
    ],
    "wof:name":"Karl Raindl Ges.m.b.H.",
    "wof:placetype":"venue"
},
  "geometry": {"coordinates":[14.5245199203,48.1742362976],"type":"Point"}
}