{
  "type": "Feature",
  "properties": {
    "iso:country":"AT",
    "sg:city":"Wernberg",
    "sg:orig_category":"Feuerwehren",
    "sg:phone":"+43 4252 2766",
    "sg:postcode":"9241",
    "sg:province":"K\u00e4rnten",
    "wof:name":"Freiwillige Feuerwehr Wernberg",
    "wof:placetype":"venue"
},
  "geometry": {"coordinates":[13.9396600723,46.6228561401],"type":"Point"}
}