{
  "type": "Feature",
  "properties": {
    "iso:country":"AT",
    "sg:address":"Untereisendorf 12",
    "sg:city":"Pabneukirchen",
    "sg:orig_category":"Erdarbeiten",
    "sg:phone":"+43 4372 6553300",
    "sg:postcode":"4363",
    "sg:province":"Ober\u00f6sterreich",
    "wof:name":"Lindner Josef",
    "wof:placetype":"venue"
},
  "geometry": {"coordinates":[14.8445329666,48.3224868774],"type":"Point"}
}