{
  "type": "Feature",
  "properties": {
    "addr:full":"Leusb\u00fcndtweg 49a Feldkirch Vorarlberg 6800",
    "addr:housenumber":"49a",
    "addr:postcode":"6800",
    "addr:street":"Leusbuendtweg",
    "iso:country":"AT",
    "sg:address":"Leusb\u00fcndtweg 49a",
    "sg:city":"Feldkirch",
    "sg:orig_category":"Energieberatung U -Untersuchung",
    "sg:phone":"+43 5522 34213410",
    "sg:postcode":"6800",
    "sg:province":"Vorarlberg",
    "wof:name":"Arbeitsgemeinschaft Erneuerbare Energie Vorarlberg",
    "wof:placetype":"venue"
},
  "geometry": {"coordinates":[9.5967845917,47.2381515503],"type":"Point"}
}