{
  "type": "Feature",
  "properties": {
    "addr:full":"Durisolstr 7 Wels Ober\u00f6sterreich 4600",
    "addr:housenumber":"7",
    "addr:postcode":"4600",
    "addr:street":"Durisolstr;Oberoesterreich",
    "iso:country":"AT",
    "sg:address":"Durisolstr 7",
    "sg:city":"Wels",
    "sg:classifiers":[
        {
            "category":"Home & Garden",
            "subcategory":"Building Materials",
            "type":"Retail Goods"
        }
    ],
    "sg:phone":"+43 7242 206424",
    "sg:postcode":"4600",
    "sg:province":"Ober\u00f6sterreich",
    "sg:tags":[
        "baustoffe",
        "-material",
        "u"
    ],
    "wof:name":"SAB Systeme am Bau VertriebsgmbH",
    "wof:placetype":"venue"
},
  "geometry": {"coordinates":[14.0079917908,48.1509475708],"type":"Point"}
}