{
  "type": "Feature",
  "properties": {
    "addr:full":"Roseng 14 Maria Lanzendorf Nieder\u00f6sterreich 2326",
    "addr:housenumber":"14",
    "addr:postcode":"2326",
    "addr:street":"Roseng",
    "iso:country":"AT",
    "sg:address":"Roseng 14",
    "sg:city":"Maria Lanzendorf",
    "sg:orig_category":"Friseure U Frisiersalons",
    "sg:phone":"+43 4322 3542690",
    "sg:postcode":"2326",
    "sg:province":"Nieder\u00f6sterreich",
    "wof:name":"Friseursalon Schranz",
    "wof:placetype":"venue"
},
  "geometry": {"coordinates":[16.4194316864,48.1003990173],"type":"Point"}
}