{
  "type": "Feature",
  "properties": {
    "iso:country":"AT",
    "sg:address":"Alois Ebner-Str 3",
    "sg:city":"Wilhelmsburg an der Traisen",
    "sg:orig_category":"Autohandel",
    "sg:phone":"+43 2746 6086",
    "sg:postcode":"3150",
    "sg:province":"Nieder\u00f6sterreich",
    "wof:name":"Autocenter Wilhelmsburg Inh M Haiderer",
    "wof:placetype":"venue"
},
  "geometry": {"coordinates":[15.6558494568,48.0672073364],"type":"Point"}
}