{
  "type": "Feature",
  "properties": {
    "addr:full":"Hausruckstr 18 Ampflwang im Hausruckwald Ober\u00f6sterreich 4843",
    "addr:housenumber":"18",
    "addr:postcode":"4843",
    "addr:street":"Hausruckstr",
    "iso:country":"AT",
    "sg:address":"Hausruckstr 18",
    "sg:city":"Ampflwang im Hausruckwald",
    "sg:orig_category":"Musikunterricht",
    "sg:phone":"+43 4376 7539286",
    "sg:postcode":"4843",
    "sg:province":"Ober\u00f6sterreich",
    "wof:name":"Landesmusikschule Ottnang",
    "wof:placetype":"venue"
},
  "geometry": {"coordinates":[13.5678243637,48.0939941406],"type":"Point"}
}