{
  "type": "Feature",
  "properties": {
    "iso:country":"AT",
    "sg:address":"Mitterndorfer Strasse 2",
    "sg:city":"Gramatneusiedl",
    "sg:classifiers":[
        {
            "category":"Manufacturing",
            "subcategory":"Wood Products",
            "type":"Manufacturing & Wholesale Goods"
        }
    ],
    "sg:phone":"+43 2234 73053",
    "sg:postcode":"2440",
    "sg:province":"Nieder\u00f6sterreich",
    "sg:tags":[
        "gate",
        "made",
        "door"
    ],
    "sg:website":"optima-haas.at",
    "wof:name":"Optima - Haas",
    "wof:placetype":"venue"
},
  "geometry": {"coordinates":[16.4949169159,48.0185394287],"type":"Point"}
}