{
  "type": "Feature",
  "properties": {
    "addr:full":"Nr 5 Floing Steiermark 8183",
    "addr:postcode":"8183",
    "addr:street":"Nr",
    "iso:country":"AT",
    "sg:address":"Nr 5",
    "sg:city":"Floing",
    "sg:orig_category":"Gemeinden",
    "sg:phone":"+43 3177 22340",
    "sg:postcode":"8183",
    "sg:province":"Steiermark",
    "wof:name":"Gemeindeamt Floing",
    "wof:placetype":"venue"
},
  "geometry": {"coordinates":[15.7296800613,47.2485237122],"type":"Point"}
}