{
  "type": "Feature",
  "properties": {
    "addr:full":"Hauptpl 8 Neuberg an der M\u00fcrz Steiermark 8692",
    "addr:housenumber":"8;8692",
    "addr:street":"Hauptpl",
    "iso:country":"AT",
    "sg:address":"Hauptpl 8",
    "sg:city":"Neuberg an der M\u00fcrz",
    "sg:orig_category":"Datenverarbeitung",
    "sg:phone":"+43 3857 20133",
    "sg:postcode":"8692",
    "sg:province":"Steiermark",
    "wof:name":"Steinacher Christian",
    "wof:placetype":"venue"
},
  "geometry": {"coordinates":[15.5736713409,47.666973114],"type":"Point"}
}