{
  "type": "Feature",
  "properties": {
    "iso:country":"AT",
    "sg:city":"Maria Saal",
    "sg:orig_category":"Freizeit, Musik",
    "sg:postcode":"9063",
    "sg:province":"K\u00e4rnten",
    "sg:website":"http://listen.to/newmotion",
    "wof:name":"The New Motion",
    "wof:placetype":"venue"
},
  "geometry": {"coordinates":[14.3471212387,46.6808509827],"type":"Point"}
}