{
  "type": "Feature",
  "properties": {
    "addr:full":"Dr.-Kofler-Str 4 Fulpmes Tirol 6166",
    "addr:housenumber":"4",
    "addr:postcode":"6166",
    "addr:street":"Dr.-Kofler-Str;Tirol",
    "iso:country":"AT",
    "sg:address":"Dr.-Kofler-Str 4",
    "sg:city":"Fulpmes",
    "sg:classifiers":[
        {
            "category":"Restaurant",
            "type":"Food & Drink"
        }
    ],
    "sg:phone":"+43 5225 63120",
    "sg:postcode":"6166",
    "sg:province":"Tirol",
    "sg:tags":[
        "pizzeria"
    ],
    "wof:name":"Pizzeria Bel Ami",
    "wof:placetype":"venue"
},
  "geometry": {"coordinates":[11.3510808945,47.1532783508],"type":"Point"}
}