{
  "type": "Feature",
  "properties": {
    "iso:country":"AT",
    "sg:address":"Alter Markt 8",
    "sg:city":"Kilb",
    "sg:orig_category":"Gemeinden",
    "sg:phone":"+43 2748 73210",
    "sg:postcode":"3233",
    "sg:province":"Nieder\u00f6sterreich",
    "wof:name":"Gemeindeamt Kilb",
    "wof:placetype":"venue"
},
  "geometry": {"coordinates":[15.406580925,48.1009712219],"type":"Point"}
}