{
  "type": "Feature",
  "properties": {
    "addr:full":"Sparkassenpl. 1  Bludenz Vorarlberg 6700",
    "addr:housenumber":"1",
    "addr:postcode":"6700",
    "addr:street":"Sparkassenpl.",
    "iso:country":"AT",
    "sg:address":"Sparkassenpl. 1 ",
    "sg:city":"Bludenz",
    "sg:classifiers":[
        {
            "category":"Banks & Credit Unions",
            "subcategory":"Bank",
            "type":"Services"
        }
    ],
    "sg:phone":"+43 4355 52636810",
    "sg:postcode":"6700",
    "sg:province":"Vorarlberg",
    "sg:tags":[
        "banking",
        "institution"
    ],
    "wof:name":"SPARKASSE DER STADT BLUDENZ",
    "wof:placetype":"venue"
},
  "geometry": {"coordinates":[9.8208379745,47.155380249],"type":"Point"}
}