{
  "type": "Feature",
  "properties": {
    "addr:full":"Thurnhofg 22 Horn Nieder\u00f6sterreich 3580",
    "addr:housenumber":"22",
    "addr:postcode":"3580",
    "addr:street":"Thurnhofg",
    "iso:country":"AT",
    "sg:address":"Thurnhofg 22",
    "sg:city":"Horn",
    "sg:classifiers":[
        {
            "category":"Restaurant",
            "type":"Food & Drink"
        }
    ],
    "sg:phone":"+43 2982 30182",
    "sg:postcode":"3580",
    "sg:province":"Nieder\u00f6sterreich",
    "sg:tags":[
        "pizzeria"
    ],
    "wof:name":"Pizzaria Giovanni",
    "wof:placetype":"venue"
},
  "geometry": {"coordinates":[15.6574287415,48.6637763977],"type":"Point"}
}