{
  "type": "Feature",
  "properties": {
    "iso:country":"AT",
    "sg:address":"Thalbachg 4",
    "sg:city":"Bregenz",
    "sg:orig_category":"Arbeitsvermittlung",
    "sg:phone":"+43 5574 54254",
    "sg:postcode":"6900",
    "sg:province":"Vorarlberg",
    "wof:name":"ARB-Arbeitsinitiative Regio Bodensee",
    "wof:placetype":"venue"
},
  "geometry": {"coordinates":[9.7469997406,47.5002975464],"type":"Point"}
}