{
  "type": "Feature",
  "properties": {
    "iso:country":"AT",
    "sg:address":"Strozzig 1",
    "sg:city":"Wien",
    "sg:orig_category":"Restaurants: Chinesisch",
    "sg:phone":"+43 1 4050348",
    "sg:postcode":"1080",
    "sg:province":"Wien",
    "wof:name":"China-Restaurant Paradise",
    "wof:placetype":"venue"
},
  "geometry": {"coordinates":[16.3491401672,48.2065887451],"type":"Point"}
}