{
  "type": "Feature",
  "properties": {
    "addr:full":"Nr 51 Tauplitz Steiermark 8982",
    "addr:postcode":"8982",
    "addr:street":"Nr",
    "iso:country":"AT",
    "sg:address":"Nr 51",
    "sg:city":"Tauplitz",
    "sg:classifiers":[
        {
            "category":"Park",
            "subcategory":"Provincial",
            "type":"Public Place"
        }
    ],
    "sg:phone":"+43 3688 2337",
    "sg:postcode":"8982",
    "sg:province":"Steiermark",
    "sg:tags":[
        "u",
        "ski-",
        "snowboardschulen"
    ],
    "wof:name":"Schischule & Schiverleih Vasold",
    "wof:placetype":"venue"
},
  "geometry": {"coordinates":[14.0155315399,47.5634117126],"type":"Point"}
}