{
  "type": "Feature",
  "properties": {
    "iso:country":"AT",
    "sg:address":"Schlatten 22",
    "sg:city":"Bromberg",
    "sg:orig_category":"Zimmereien",
    "sg:phone":"+43 2629 8602",
    "sg:postcode":"2833",
    "sg:province":"Nieder\u00f6sterreich",
    "wof:name":"Neum\u00fcller Anton",
    "wof:placetype":"venue"
},
  "geometry": {"coordinates":[16.2377872467,47.6548614502],"type":"Point"}
}