{
  "type": "Feature",
  "properties": {
    "iso:country":"AT",
    "sg:address":"Rablern 16",
    "sg:city":"Andorf",
    "sg:orig_category":"Innenarchitekten",
    "sg:phone":"+43 7766 3848",
    "sg:postcode":"4770",
    "sg:province":"Ober\u00f6sterreich",
    "wof:name":"Probst Josef Wohn-Atelier",
    "wof:placetype":"venue"
},
  "geometry": {"coordinates":[13.5565109253,48.3342971802],"type":"Point"}
}