{
  "type": "Feature",
  "properties": {
    "addr:full":"Julius-Meinl-G 15 Wien Wien 1170",
    "addr:housenumber":"15",
    "addr:postcode":"1170",
    "addr:street":"Julius-Meinl-G",
    "iso:country":"AT",
    "sg:address":"Julius-Meinl-G 15",
    "sg:city":"Wien",
    "sg:orig_category":"Psychotherapie",
    "sg:phone":"+43 1 4892548",
    "sg:postcode":"1170",
    "sg:province":"Wien",
    "wof:name":"Badelt Irmgard",
    "wof:placetype":"venue"
},
  "geometry": {"coordinates":[16.3140964508,48.2236557007],"type":"Point"}
}