{
  "type": "Feature",
  "properties": {
    "addr:full":"Angernstr 6 Garsten Ober\u00f6sterreich 4451",
    "addr:housenumber":"6",
    "addr:postcode":"4451",
    "addr:street":"Angernstr",
    "iso:country":"AT",
    "sg:address":"Angernstr 6",
    "sg:city":"Garsten",
    "sg:orig_category":"Pensionen / Privatzimmer",
    "sg:phone":"+43 7252 53114",
    "sg:postcode":"4451",
    "sg:province":"Ober\u00f6sterreich",
    "wof:name":"Pension Ennstal",
    "wof:placetype":"venue"
},
  "geometry": {"coordinates":[14.3768959045,47.9880981445],"type":"Point"}
}