{
  "type": "Feature",
  "properties": {
    "iso:country":"AT",
    "sg:address":"Bismarckg 16",
    "sg:city":"Weiz",
    "sg:orig_category":"Friseure U Frisiersalons",
    "sg:phone":"+43 4331 7241146",
    "sg:postcode":"8160",
    "sg:province":"Steiermark",
    "sg:website":"lisbeth.at",
    "wof:name":"Friseur Lisbeth",
    "wof:placetype":"venue"
},
  "geometry": {"coordinates":[15.6239976883,47.2184333801],"type":"Point"}
}