{
  "type": "Feature",
  "properties": {
    "iso:country":"AT",
    "sg:address":"Mollardgasse 85a/1/14",
    "sg:city":"Wien",
    "sg:classifiers":[
        {
            "category":"Real Estate",
            "subcategory":"Real Estate Services",
            "type":"Services"
        }
    ],
    "sg:phone":"+43 1 5970117",
    "sg:postcode":"1060",
    "sg:province":"Wien",
    "sg:tags":[
        "decoration",
        "rustic",
        "articles"
    ],
    "wof:name":"Karl Binder Ges.m.b.H.",
    "wof:placetype":"venue"
},
  "geometry": {"coordinates":[16.3504657745,48.1947135925],"type":"Point"}
}