{
  "type": "Feature",
  "properties": {
    "addr:full":"Ascheter Str 3 Wels Ober\u00f6sterreich 4600",
    "addr:housenumber":"3",
    "addr:postcode":"4600",
    "addr:street":"Str;Oberoesterreich",
    "iso:country":"AT",
    "sg:address":"Ascheter Str 3",
    "sg:city":"Wels",
    "sg:orig_category":"Befestigungstechnik",
    "sg:phone":"+43 7242 63270",
    "sg:postcode":"4600",
    "sg:province":"Ober\u00f6sterreich",
    "wof:name":"Bero Gro\u00dfhandel",
    "wof:placetype":"venue"
},
  "geometry": {"coordinates":[14.0264501572,48.1520652771],"type":"Point"}
}