{
  "type": "Feature",
  "properties": {
    "iso:country":"AT",
    "sg:address":"Am Sonnenlehen 392",
    "sg:city":"Gro\u00dfgmain",
    "sg:orig_category":"Unterhaltungselektronik / Erzeugung U Gro\u00c3\u0178handel",
    "sg:phone":"+43 4362 478363",
    "sg:postcode":"5084",
    "sg:province":"Salzburg",
    "wof:name":"Tr\u00f6zm\u00fcller Jimmy",
    "wof:placetype":"venue"
},
  "geometry": {"coordinates":[12.0809497833,48.0439414978],"type":"Point"}
}