{
  "type": "Feature",
  "properties": {
    "iso:country":"AT",
    "sg:address":"Defreggerstr 28",
    "sg:city":"Hohenems",
    "sg:orig_category":"Hypnose",
    "sg:phone":"+43 5576 77737",
    "sg:postcode":"6845",
    "sg:province":"Vorarlberg",
    "wof:name":"Bechter Hermann Dipl Mentaltrainer",
    "wof:placetype":"venue"
},
  "geometry": {"coordinates":[9.6805753708,47.3564338684],"type":"Point"}
}