{
  "type": "Feature",
  "properties": {
    "addr:full":"Meidlinger Hauptstr 72 Wien Wien 1120",
    "addr:housenumber":"72",
    "addr:postcode":"1120",
    "addr:street":"Meidlinger Hauptstr",
    "iso:country":"AT",
    "sg:address":"Meidlinger Hauptstr 72",
    "sg:city":"Wien",
    "sg:orig_category":"Berufsbekleidung / Einzelhandel",
    "sg:phone":"+43 1 8154159",
    "sg:postcode":"1120",
    "sg:province":"Wien",
    "wof:name":"Sterba Adalbert Ing",
    "wof:placetype":"venue"
},
  "geometry": {"coordinates":[16.3299922943,48.1760673523],"type":"Point"}
}