{
  "type": "Feature",
  "properties": {
    "addr:full":"Engerthstr 257 Wien Wien 1020",
    "addr:housenumber":"257",
    "addr:postcode":"1020",
    "iso:country":"AT",
    "sg:address":"Engerthstr 257",
    "sg:city":"Wien",
    "sg:orig_category":"Behinderungen / Leben Mit Behinderungen",
    "sg:phone":"+43 1 7261682",
    "sg:postcode":"1020",
    "sg:province":"Wien",
    "wof:name":"Jugend am Werk Wohnverbundb\u00fcro",
    "wof:placetype":"venue"
},
  "geometry": {"coordinates":[16.4195842743,48.2129440308],"type":"Point"}
}