{
  "type": "Feature",
  "properties": {
    "addr:full":"Nr 24 Pernegg an der Mur Steiermark 8132",
    "addr:postcode":"8132",
    "addr:street":"Nr",
    "iso:country":"AT",
    "sg:address":"Nr 24",
    "sg:city":"Pernegg an der Mur",
    "sg:orig_category":"Elektroinstallationsunternehmen",
    "sg:phone":"+43 3867 50410",
    "sg:postcode":"8132",
    "sg:province":"Steiermark",
    "wof:name":"Hofbauer Peter",
    "wof:placetype":"venue"
},
  "geometry": {"coordinates":[15.3446798325,47.3590660095],"type":"Point"}
}