{
  "type": "Feature",
  "properties": {
    "addr:full":"Triester Str 67 Neunkirchen Nieder\u00f6sterreich 2620",
    "addr:housenumber":"67",
    "addr:postcode":"2620",
    "addr:street":"Str",
    "iso:country":"AT",
    "sg:address":"Triester Str 67",
    "sg:city":"Neunkirchen",
    "sg:orig_category":"Berufsschulen",
    "sg:phone":"+43 4326 35653860",
    "sg:postcode":"2620",
    "sg:province":"Nieder\u00f6sterreich",
    "wof:name":"Landesberufsschule - Technologiezentrum f\u00fcr Metalltechnik",
    "wof:placetype":"venue"
},
  "geometry": {"coordinates":[16.0980548859,47.7119560242],"type":"Point"}
}