{
  "type": "Feature",
  "properties": {
    "addr:full":"Nr 31 St. Katharein an der Laming Steiermark 8611",
    "addr:postcode":"8611",
    "addr:street":"Nr 31",
    "iso:country":"AT",
    "sg:address":"Nr 31",
    "sg:city":"St. Katharein an der Laming",
    "sg:orig_category":"Gemeinden",
    "sg:phone":"+43 4338 6922420",
    "sg:postcode":"8611",
    "sg:province":"Steiermark",
    "wof:name":"Gemeindeamt St Katharein an der Laming",
    "wof:placetype":"venue"
},
  "geometry": {"coordinates":[15.1625738144,47.4715538025],"type":"Point"}
}