{
  "type": "Feature",
  "properties": {
    "iso:country":"AT",
    "sg:address":"Guntherstr 10",
    "sg:city":"Wien",
    "sg:orig_category":"Terrassen, Gartenanlagen, Natursteinarbeiten, Pflaster U Pflasterungen",
    "sg:phone":"+43 1 77462620",
    "sg:postcode":"1220",
    "sg:province":"Wien",
    "sg:website":"www.sgd.at",
    "wof:name":"1 A-Au\u00dfengestaltung Stein und Gartendesign PflasterungsgesmbH",
    "wof:placetype":"venue"
},
  "geometry": {"coordinates":[16.5467796326,48.2189941406],"type":"Point"}
}