{
  "type": "Feature",
  "properties": {
    "addr:full":"Bahnhofstr 55 Klagenfurt K\u00e4rnten 9020",
    "addr:housenumber":"55",
    "addr:postcode":"9020",
    "addr:street":"Bahnhofstr;Kaernten",
    "iso:country":"AT",
    "sg:address":"Bahnhofstr 55",
    "sg:city":"Klagenfurt",
    "sg:orig_category":"Versicherungsunternehmen",
    "sg:phone":"+43 463 3102250",
    "sg:postcode":"9020",
    "sg:province":"K\u00e4rnten",
    "sg:website":"arag.at",
    "wof:name":"ARAG \u00f6sterreich Allgemeine Rechtsschutzversicherungs-Aktiengesellschaft",
    "wof:placetype":"venue"
},
  "geometry": {"coordinates":[14.3126869202,46.6177787781],"type":"Point"}
}