{
  "type": "Feature",
  "properties": {
    "iso:country":"AT",
    "sg:address":"Dambach 35",
    "sg:city":"Neuhofen an der Krems",
    "sg:orig_category":"Ziegeleien",
    "sg:phone":"+43 4372 274272",
    "sg:postcode":"4501",
    "sg:province":"Ober\u00f6sterreich",
    "wof:name":"Ziegelwerk Neuhofen K F u Dipl-Ing H Obermair GesmbH & Co KG",
    "wof:placetype":"venue"
},
  "geometry": {"coordinates":[14.2117948532,48.147605896],"type":"Point"}
}