{
  "type": "Feature",
  "properties": {
    "addr:full":"Roseng 4 Traismauer Nieder\u00f6sterreich 3133",
    "addr:housenumber":"4",
    "addr:postcode":"3133",
    "addr:street":"Roseng",
    "iso:country":"AT",
    "sg:address":"Roseng 4",
    "sg:city":"Traismauer",
    "sg:orig_category":"Tischlereien",
    "sg:phone":"+43 2783 8557",
    "sg:postcode":"3133",
    "sg:province":"Nieder\u00f6sterreich",
    "wof:name":"Zimmer Rudolf",
    "wof:placetype":"venue"
},
  "geometry": {"coordinates":[15.7403230667,48.3550109863],"type":"Point"}
}