{
  "type": "Feature",
  "properties": {
    "addr:full":"Ortsstr 73 Biedermannsdorf Nieder\u00f6sterreich 2362",
    "addr:housenumber":"73",
    "addr:postcode":"2362",
    "addr:street":"Ortsstr",
    "iso:country":"AT",
    "sg:address":"Ortsstr 73",
    "sg:city":"Biedermannsdorf",
    "sg:orig_category":"Landwirtschaftliche Produkte",
    "sg:phone":"+43 2236 71147",
    "sg:postcode":"2362",
    "sg:province":"Nieder\u00f6sterreich",
    "wof:name":"Presolly GmbH",
    "wof:placetype":"venue"
},
  "geometry": {"coordinates":[16.3416938782,48.0839538574],"type":"Point"}
}