{
  "type": "Feature",
  "properties": {
    "addr:full":"S\u00fcdweg 11 St. Stefan im Lavanttal K\u00e4rnten 9431",
    "addr:housenumber":"11",
    "addr:postcode":"9431",
    "addr:street":"Suedweg",
    "iso:country":"AT",
    "sg:address":"S\u00fcdweg 11",
    "sg:city":"St. Stefan im Lavanttal",
    "sg:orig_category":"Industrieanlagenbau U -Planung",
    "sg:phone":"+43 4343 5251621",
    "sg:postcode":"9431",
    "sg:province":"K\u00e4rnten",
    "wof:name":"Industrieanlagenbau GesmbH",
    "wof:placetype":"venue"
},
  "geometry": {"coordinates":[14.832036972,46.8094558716],"type":"Point"}
}