{
  "type": "Feature",
  "properties": {
    "addr:full":"Hermann-Sander-Str 14/1 Bludenz Vorarlberg 6700",
    "addr:housenumber":"14 / 1",
    "addr:postcode":"6700",
    "addr:street":"Hermann-Sander-Str",
    "iso:country":"AT",
    "sg:address":"Hermann-Sander-Str 14/1",
    "sg:city":"Bludenz",
    "sg:orig_category":"Industrieanlagenbau U -Planung",
    "sg:phone":"+43 4365 03402401",
    "sg:postcode":"6700",
    "sg:province":"Vorarlberg",
    "wof:name":"Optisolution - Ing Reinhard Sauerwein",
    "wof:placetype":"venue"
},
  "geometry": {"coordinates":[9.8185157776,47.1528663635],"type":"Point"}
}