{
  "type": "Feature",
  "properties": {
    "addr:full":"Dorf 13 Hohenweiler Vorarlberg 6914",
    "addr:housenumber":"13",
    "addr:postcode":"6914",
    "addr:street":"Dorf",
    "iso:country":"AT",
    "sg:address":"Dorf 13",
    "sg:city":"Hohenweiler",
    "sg:orig_category":"Volksschulen",
    "sg:phone":"+43 5573 83313",
    "sg:postcode":"6914",
    "sg:province":"Vorarlberg",
    "wof:name":"Volksschule",
    "wof:placetype":"venue"
},
  "geometry": {"coordinates":[9.7815361023,47.5886077881],"type":"Point"}
}