{
  "type": "Feature",
  "properties": {
    "addr:full":"Schumanng 72 Wien Wien 1170",
    "addr:housenumber":"72",
    "addr:postcode":"1170",
    "addr:street":"Schumanng",
    "iso:country":"AT",
    "sg:address":"Schumanng 72",
    "sg:city":"Wien",
    "sg:orig_category":"Friseure U Frisiersalons",
    "sg:phone":"+43 1 4069151",
    "sg:postcode":"1170",
    "sg:province":"Wien",
    "wof:name":"B\u00fcchinger Gertrude",
    "wof:placetype":"venue"
},
  "geometry": {"coordinates":[16.3339328766,48.2231636047],"type":"Point"}
}