{
  "type": "Feature",
  "properties": {
    "addr:full":"Grenzackerstr 17 Wien Wien 1100",
    "addr:housenumber":"17",
    "addr:postcode":"1100",
    "addr:street":"Grenzackerstr",
    "iso:country":"AT",
    "sg:address":"Grenzackerstr 17",
    "sg:city":"Wien",
    "sg:classifiers":[
        {
            "category":"Taxi",
            "type":"Transportation"
        }
    ],
    "sg:phone":"+43 4366 42016488",
    "sg:postcode":"1100",
    "sg:province":"Wien",
    "sg:tags":[
        "personentransporte",
        "u"
    ],
    "wof:name":"Toffel Gerald - Taxi u Mietwagen",
    "wof:placetype":"venue"
},
  "geometry": {"coordinates":[16.3765125275,48.1630897522],"type":"Point"}
}