{
  "type": "Feature",
  "properties": {
    "addr:full":"Braunhirscheng 28 Wien Wien 1150",
    "addr:housenumber":"28",
    "addr:postcode":"1150",
    "addr:street":"Braunhirscheng",
    "iso:country":"AT",
    "sg:address":"Braunhirscheng 28",
    "sg:city":"Wien",
    "sg:orig_category":"Reinigungsbedarf U Reinigungsmittel",
    "sg:phone":"+43 4318 9208000",
    "sg:postcode":"1150",
    "sg:province":"Wien",
    "wof:name":"Ray-Werk Helmut Schellenberger & Co GesmbH",
    "wof:placetype":"venue"
},
  "geometry": {"coordinates":[16.3268680573,48.1883010864],"type":"Point"}
}