{
  "type": "Feature",
  "properties": {
    "iso:country":"AT",
    "sg:address":"Am Nordsaum 12",
    "sg:city":"Traun",
    "sg:orig_category":"Musikgruppen",
    "sg:phone":"+43 7229 70168",
    "sg:postcode":"4050",
    "sg:province":"Ober\u00f6sterreich",
    "wof:name":"Stadtkapelle Traun",
    "wof:placetype":"venue"
},
  "geometry": {"coordinates":[14.236451149,48.2297973633],"type":"Point"}
}