{
  "type": "Feature",
  "properties": {
    "addr:full":"Pfalzauer Str 42 Pressbaum Nieder\u00f6sterreich 3021",
    "addr:postcode":"3021",
    "addr:street":"Str 42",
    "iso:country":"AT",
    "sg:address":"Pfalzauer Str 42",
    "sg:city":"Pressbaum",
    "sg:orig_category":"Tonstudios",
    "sg:phone":"+43 664 3848969",
    "sg:postcode":"3021",
    "sg:province":"Nieder\u00f6sterreich",
    "wof:name":"TC Electronic in \u00d6sterreich",
    "wof:placetype":"venue"
},
  "geometry": {"coordinates":[16.0749931335,48.1702651978],"type":"Point"}
}