{
  "type": "Feature",
  "properties": {
    "addr:full":"Bahnhofstr 24 Schruns Vorarlberg 6780",
    "addr:housenumber":"24",
    "addr:postcode":"6780",
    "addr:street":"Bahnhofstr",
    "iso:country":"AT",
    "sg:address":"Bahnhofstr 24",
    "sg:city":"Schruns",
    "sg:orig_category":"Spielwaren U Spiele",
    "sg:phone":"+43 4355 5671030",
    "sg:postcode":"6780",
    "sg:province":"Vorarlberg",
    "wof:name":"Silvretta Center der Konsumgenossenschaft Montafon regGenmbH",
    "wof:placetype":"venue"
},
  "geometry": {"coordinates":[9.9185714722,47.0795402527],"type":"Point"}
}