{
  "type": "Feature",
  "properties": {
    "addr:full":"Papagenopl 3 Salzburg Salzburg 5020",
    "addr:housenumber":"3",
    "addr:postcode":"5020",
    "addr:street":"Papagenopl;Salzburg",
    "iso:country":"AT",
    "sg:address":"Papagenopl 3",
    "sg:city":"Salzburg",
    "sg:orig_category":"Friseure U Frisiersalons",
    "sg:phone":"+43 4366 2845323",
    "sg:postcode":"5020",
    "sg:province":"Salzburg",
    "wof:name":"Hlawa Haar-Creation",
    "wof:placetype":"venue"
},
  "geometry": {"coordinates":[13.0497159958,47.7982292175],"type":"Point"}
}