{
  "type": "Feature",
  "properties": {
    "addr:full":"Billrothstrasse 54 Wien Wien 1190",
    "addr:housenumber":"54",
    "addr:postcode":"1190",
    "addr:street":"Billrothstrasse",
    "iso:country":"AT",
    "sg:address":"Billrothstrasse 54",
    "sg:city":"Wien",
    "sg:classifiers":[
        {
            "category":"Building & Trades",
            "subcategory":"Construction",
            "type":"Services"
        }
    ],
    "sg:phone":"+43 1 3699690",
    "sg:postcode":"1190",
    "sg:province":"Wien",
    "sg:tags":[
        "door",
        "renovation",
        "renewal"
    ],
    "wof:name":"Alois Linsbichler",
    "wof:placetype":"venue"
},
  "geometry": {"coordinates":[16.3491172791,48.2402305603],"type":"Point"}
}