{
  "type": "Feature",
  "properties": {
    "addr:full":"Bahnstr 13 Pottendorf Nieder\u00f6sterreich 2486",
    "addr:housenumber":"13",
    "addr:postcode":"2486",
    "addr:street":"Bahnstr",
    "iso:country":"AT",
    "sg:address":"Bahnstr 13",
    "sg:city":"Pottendorf",
    "sg:orig_category":"Fotografen",
    "sg:phone":"+43 699 10852203",
    "sg:postcode":"2486",
    "sg:province":"Nieder\u00f6sterreich",
    "wof:name":"Madzulis Ronald",
    "wof:placetype":"venue"
},
  "geometry": {"coordinates":[16.3899097443,47.9059295654],"type":"Point"}
}