{
  "type": "Feature",
  "properties": {
    "iso:country":"AT",
    "sg:address":"Untere Feldstr 270",
    "sg:city":"Pitten",
    "sg:orig_category":"Autoreparatur",
    "sg:phone":"+43 2627 822400",
    "sg:postcode":"2823",
    "sg:province":"Nieder\u00f6sterreich",
    "wof:name":"Gruber Alexander",
    "wof:placetype":"venue"
},
  "geometry": {"coordinates":[16.1824245453,47.7175598145],"type":"Point"}
}