{
  "type": "Feature",
  "properties": {
    "iso:country":"AT",
    "sg:address":"Prager Strasse 70",
    "sg:city":"Wien",
    "sg:classifiers":[
        {
            "category":"Building & Trades",
            "subcategory":"Plumbing",
            "type":"Services"
        }
    ],
    "sg:phone":"+43 1 2711374",
    "sg:postcode":"1210",
    "sg:province":"Wien",
    "sg:tags":[
        "supraregional",
        "gas"
    ],
    "wof:name":"G\u00fcnther Weber Installationsges.m.b.H.",
    "wof:placetype":"venue"
},
  "geometry": {"coordinates":[16.3923625946,48.2685661316],"type":"Point"}
}