{
  "type": "Feature",
  "properties": {
    "addr:full":"Ackerg 31 Wiener Neustadt Nieder\u00f6sterreich 2700",
    "addr:housenumber":"31",
    "addr:postcode":"2700",
    "addr:street":"Ackerg",
    "iso:country":"AT",
    "sg:address":"Ackerg 31",
    "sg:city":"Wiener Neustadt",
    "sg:orig_category":"Erdarbeiten",
    "sg:phone":"+43 664 2415643",
    "sg:postcode":"2700",
    "sg:province":"Nieder\u00f6sterreich",
    "wof:name":"M\u00fcller Franz",
    "wof:placetype":"venue"
},
  "geometry": {"coordinates":[16.2614021301,47.8343467712],"type":"Point"}
}