{
  "type": "Feature",
  "properties": {
    "addr:full":"Ludwig-Binder-Str 11 Gleisdorf Steiermark 8200",
    "addr:housenumber":"11",
    "addr:postcode":"8200",
    "addr:street":"Ludwig-Binder-Str",
    "iso:country":"AT",
    "sg:address":"Ludwig-Binder-Str 11",
    "sg:city":"Gleisdorf",
    "sg:orig_category":"Elektroinstallationsunternehmen",
    "sg:phone":"+43 4331 122159",
    "sg:postcode":"8200",
    "sg:province":"Steiermark",
    "wof:name":"PICHLERwerke",
    "wof:placetype":"venue"
},
  "geometry": {"coordinates":[15.7071838379,47.1059379578],"type":"Point"}
}