{
  "type": "Feature",
  "properties": {
    "addr:full":"Siebensterng 2 Wien Wien 1070",
    "addr:housenumber":"2",
    "addr:postcode":"1070",
    "addr:street":"Siebensterng",
    "iso:country":"AT",
    "sg:address":"Siebensterng 2",
    "sg:city":"Wien",
    "sg:orig_category":"Fliesen U Platten",
    "sg:phone":"+43 1 5241204",
    "sg:postcode":"1070",
    "sg:province":"Wien",
    "sg:website":"www.devon-devon.at",
    "wof:name":"Devon & Devon",
    "wof:placetype":"venue"
},
  "geometry": {"coordinates":[16.356918335,48.2029724121],"type":"Point"}
}