{
  "type": "Feature",
  "properties": {
    "addr:full":"Leonfeldner Str 300a Linz Ober\u00f6sterreich 4040",
    "addr:postcode":"4040",
    "addr:street":"Str 300A",
    "iso:country":"AT",
    "sg:address":"Leonfeldner Str 300a",
    "sg:city":"Linz",
    "sg:orig_category":"Unternehmensberatung",
    "sg:phone":"+43 732 250150",
    "sg:postcode":"4040",
    "sg:province":"Ober\u00f6sterreich",
    "wof:name":"Dawari Heidemarie Mag",
    "wof:placetype":"venue"
},
  "geometry": {"coordinates":[14.2932596207,48.3472290039],"type":"Point"}
}