{
  "type": "Feature",
  "properties": {
    "addr:full":"Karl-Mayer-G 32 Ebreichsdorf Nieder\u00f6sterreich 2483",
    "addr:housenumber":"32",
    "addr:postcode":"2483",
    "addr:street":"Karl-Mayer-G",
    "iso:country":"AT",
    "sg:address":"Karl-Mayer-G 32",
    "sg:city":"Ebreichsdorf",
    "sg:orig_category":"Tischlereien",
    "sg:phone":"+43 2254 72385",
    "sg:postcode":"2483",
    "sg:province":"Nieder\u00f6sterreich",
    "wof:name":"Handstanger Karl",
    "wof:placetype":"venue"
},
  "geometry": {"coordinates":[16.4085693359,47.958530426],"type":"Point"}
}