{
  "type": "Feature",
  "properties": {
    "addr:full":"Schulstr 49 Wallsee Nieder\u00f6sterreich 3313",
    "addr:housenumber":"49",
    "addr:postcode":"3313",
    "addr:street":"Schulstr",
    "iso:country":"AT",
    "sg:address":"Schulstr 49",
    "sg:city":"Wallsee",
    "sg:orig_category":"Pensionen / Privatzimmer",
    "sg:phone":"+43 7433 2223",
    "sg:postcode":"3313",
    "sg:province":"Nieder\u00f6sterreich",
    "wof:name":"Gasthaus Pension Wallseerhof",
    "wof:placetype":"venue"
},
  "geometry": {"coordinates":[14.7188100815,48.1655082703],"type":"Point"}
}