{
  "type": "Feature",
  "properties": {
    "addr:full":"Hauptstr 178 Seeboden K\u00e4rnten 9871",
    "addr:housenumber":"178",
    "addr:postcode":"9871",
    "addr:street":"Hauptstr;Kaernten",
    "iso:country":"AT",
    "sg:address":"Hauptstr 178",
    "sg:city":"Seeboden",
    "sg:classifiers":[
        {
            "category":"Restaurant",
            "type":"Food & Drink"
        }
    ],
    "sg:phone":"+43 4762 82030",
    "sg:postcode":"9871",
    "sg:province":"K\u00e4rnten",
    "sg:tags":[
        "pizzeria"
    ],
    "wof:name":"Pizzeria Ristorante Napoli",
    "wof:placetype":"venue"
},
  "geometry": {"coordinates":[13.5302324295,46.8164253235],"type":"Point"}
}