{
  "type": "Feature",
  "properties": {
    "addr:full":"Brixentaler Str 7 Brixen im Thale Tirol 6364",
    "addr:housenumber":"7",
    "addr:postcode":"6364",
    "addr:street":"Str;Tirol",
    "iso:country":"AT",
    "sg:address":"Brixentaler Str 7",
    "sg:city":"Brixen im Thale",
    "sg:orig_category":"Installationsunternehmen",
    "sg:phone":"+43 5334 8613",
    "sg:postcode":"6364",
    "sg:province":"Tirol",
    "wof:name":"Eisenmann Johann",
    "wof:placetype":"venue"
},
  "geometry": {"coordinates":[12.2363033295,47.4457817078],"type":"Point"}
}