{
  "type": "Feature",
  "properties": {
    "iso:country":"AT",
    "sg:address":"Taglieberstr 6",
    "sg:city":"Wien",
    "sg:orig_category":"Elektroinstallationsunternehmen",
    "sg:phone":"+43 1 8891283",
    "sg:postcode":"1230",
    "sg:province":"Wien",
    "wof:name":"Novak Friedrich",
    "wof:placetype":"venue"
},
  "geometry": {"coordinates":[16.2876052856,48.1490325928],"type":"Point"}
}