{
  "type": "Feature",
  "properties": {
    "addr:full":"Nr 194 Preding Steiermark 8504",
    "addr:postcode":"8504",
    "addr:street":"Nr 194",
    "iso:country":"AT",
    "sg:address":"Nr 194",
    "sg:city":"Preding",
    "sg:orig_category":"Bauunternehmen",
    "sg:phone":"+43 3185 306000",
    "sg:postcode":"8504",
    "sg:province":"Steiermark",
    "wof:name":"Powoden Bau GmbH Hoch- und Tiefbau",
    "wof:placetype":"venue"
},
  "geometry": {"coordinates":[15.4067401886,46.8597869873],"type":"Point"}
}