{
  "type": "Feature",
  "properties": {
    "addr:full":"Bahnhofstr 15 Zell am Ziller Tirol 6280",
    "addr:housenumber":"15",
    "addr:postcode":"6280",
    "addr:street":"Bahnhofstr;Tirol",
    "iso:country":"AT",
    "sg:address":"Bahnhofstr 15",
    "sg:city":"Zell am Ziller",
    "sg:classifiers":[
        {
            "category":"Travel",
            "subcategory":"Hotels & Motels",
            "type":"Entertainment"
        }
    ],
    "sg:phone":"+43 4352 8222860",
    "sg:postcode":"6280",
    "sg:province":"Tirol",
    "wof:name":"Sporthotel Theresa",
    "wof:placetype":"venue"
},
  "geometry": {"coordinates":[11.8807945251,47.2301979065],"type":"Point"}
}