{
  "type": "Feature",
  "properties": {
    "addr:full":"Augustinerg 20 Salzburg Salzburg 5020",
    "addr:housenumber":"20",
    "addr:postcode":"5020",
    "addr:street":"Augustinerg;Salzburg",
    "iso:country":"AT",
    "sg:address":"Augustinerg 20",
    "sg:city":"Salzburg",
    "sg:orig_category":"Appartements / Ferienwohnungen",
    "sg:phone":"+43 662 8461930",
    "sg:postcode":"5020",
    "sg:province":"Salzburg",
    "wof:name":"Imhof Peter",
    "wof:placetype":"venue"
},
  "geometry": {"coordinates":[13.0317001343,47.8025741577],"type":"Point"}
}