{
  "type": "Feature",
  "properties": {
    "addr:full":"Freimoosstr 1 Neumarkt in Steiermark Steiermark 8820",
    "addr:housenumber":"1",
    "addr:postcode":"8820",
    "addr:street":"Freimoosstr",
    "iso:country":"AT",
    "sg:address":"Freimoosstr 1",
    "sg:city":"Neumarkt in Steiermark",
    "sg:orig_category":"Installationsunternehmen",
    "sg:phone":"+43 4335 8421340",
    "sg:postcode":"8820",
    "sg:province":"Steiermark",
    "wof:name":"Griedl Klaus",
    "wof:placetype":"venue"
},
  "geometry": {"coordinates":[14.4274482727,47.0716934204],"type":"Point"}
}