{
  "type": "Feature",
  "properties": {
    "iso:country":"AT",
    "sg:address":"Kinopl 10",
    "sg:city":"Radenthein",
    "sg:orig_category":"Versicherungsunternehmen",
    "sg:phone":"+43 4342 462415",
    "sg:postcode":"9545",
    "sg:province":"K\u00e4rnten",
    "wof:name":"Generali Versicherung AG",
    "wof:placetype":"venue"
},
  "geometry": {"coordinates":[13.7024116516,46.7985076904],"type":"Point"}
}