{
  "type": "Feature",
  "properties": {
    "addr:full":"Herberthstr 1 Wolfsberg K\u00e4rnten 9400",
    "addr:housenumber":"1;kaernten",
    "addr:postcode":"9400",
    "addr:street":"Herberthstr",
    "iso:country":"AT",
    "sg:address":"Herberthstr 1",
    "sg:city":"Wolfsberg",
    "sg:orig_category":"Telekommunikation",
    "sg:phone":"+43 800 100100",
    "sg:postcode":"9400",
    "sg:province":"K\u00e4rnten",
    "wof:name":"Telekom Shop",
    "wof:placetype":"venue"
},
  "geometry": {"coordinates":[14.8397493362,46.8404045105],"type":"Point"}
}