{
  "type": "Feature",
  "properties": {
    "addr:full":"Steinachg 15 Wien Wien 1220",
    "addr:housenumber":"15",
    "addr:postcode":"1220",
    "addr:street":"Steinachg",
    "iso:country":"AT",
    "sg:address":"Steinachg 15",
    "sg:city":"Wien",
    "sg:orig_category":"Technische Bedarfsartikel",
    "sg:phone":"+43 1 7744866",
    "sg:postcode":"1220",
    "sg:province":"Wien",
    "wof:name":"Klug Margot",
    "wof:placetype":"venue"
},
  "geometry": {"coordinates":[16.5359764099,48.2075157166],"type":"Point"}
}