{
  "type": "Feature",
  "properties": {
    "addr:full":"Hauptpl 14b Knittelfeld Steiermark 8720",
    "addr:housenumber":"14b",
    "addr:postcode":"8720",
    "addr:street":"Hauptpl",
    "iso:country":"AT",
    "sg:address":"Hauptpl 14b",
    "sg:city":"Knittelfeld",
    "sg:orig_category":"Psychotherapie",
    "sg:phone":"+43 3512 71722",
    "sg:postcode":"8720",
    "sg:province":"Steiermark",
    "wof:name":"Trattnig Dagmar",
    "wof:placetype":"venue"
},
  "geometry": {"coordinates":[14.8293638229,47.2147941589],"type":"Point"}
}