{
  "type": "Feature",
  "properties": {
    "addr:full":"Hausbergstr 65 Walchsee Tirol 6344",
    "addr:housenumber":"65",
    "addr:postcode":"6344",
    "addr:street":"Hausbergstr;Tirol",
    "iso:country":"AT",
    "sg:address":"Hausbergstr 65",
    "sg:city":"Walchsee",
    "sg:orig_category":"Appartements / Ferienwohnungen",
    "sg:phone":"+43 5374 5630",
    "sg:postcode":"6344",
    "sg:province":"Tirol",
    "wof:name":"Appartementhaus Montana",
    "wof:placetype":"venue"
},
  "geometry": {"coordinates":[12.3191843033,47.6572875977],"type":"Point"}
}