{
  "type": "Feature",
  "properties": {
    "iso:country":"AT",
    "sg:address":"Bolgenach 40",
    "sg:city":"Hittisau",
    "sg:orig_category":"Pensionen / Privatzimmer",
    "sg:phone":"+43 5513 6529",
    "sg:postcode":"6952",
    "sg:province":"Vorarlberg",
    "wof:name":"Bilgeri Hanspeter und Marianne",
    "wof:placetype":"venue"
},
  "geometry": {"coordinates":[9.9612169266,47.4672966003],"type":"Point"}
}