{
  "type": "Feature",
  "properties": {
    "iso:country":"AT",
    "sg:address":"Eduard-Bodem-G 4",
    "sg:city":"Innsbruck",
    "sg:orig_category":"Wasserbetten",
    "sg:phone":"+43 512 262690",
    "sg:postcode":"6020",
    "sg:province":"Tirol",
    "wof:name":"W\u00fcrz Wasserbetten",
    "wof:placetype":"venue"
},
  "geometry": {"coordinates":[11.4356327057,47.2650794983],"type":"Point"}
}