{
  "type": "Feature",
  "properties": {
    "iso:country":"AT",
    "sg:address":"Klosterstr 2",
    "sg:city":"Amstetten",
    "sg:orig_category":"Politische Parteien",
    "sg:phone":"+43 7472 625640",
    "sg:postcode":"3300",
    "sg:province":"Nieder\u00f6sterreich",
    "wof:name":"\u00f6sterreichische Volkspartei (\u00f6VP)",
    "wof:placetype":"venue"
},
  "geometry": {"coordinates":[14.8681297302,48.1230583191],"type":"Point"}
}