{
  "type": "Feature",
  "properties": {
    "addr:full":"In Schiffeln 30 Langenzersdorf Nieder\u00f6sterreich 2103",
    "addr:housenumber":"30",
    "addr:postcode":"2103",
    "iso:country":"AT",
    "sg:address":"In Schiffeln 30",
    "sg:city":"Langenzersdorf",
    "sg:orig_category":"Maler, Anstreicher U Lackierer",
    "sg:phone":"+43 2244 2770",
    "sg:postcode":"2103",
    "sg:province":"Nieder\u00f6sterreich",
    "wof:name":"G\u00f6rlich Manfred",
    "wof:placetype":"venue"
},
  "geometry": {"coordinates":[16.359796524,48.3105888367],"type":"Point"}
}