{
  "type": "Feature",
  "properties": {
    "addr:full":"Friensdorf 68 Wartberg ob der Aist Ober\u00f6sterreich 4224",
    "addr:housenumber":"68",
    "addr:postcode":"4224",
    "addr:street":"Friensdorf",
    "iso:country":"AT",
    "sg:address":"Friensdorf 68",
    "sg:city":"Wartberg ob der Aist",
    "sg:orig_category":"Umwelttechnik",
    "sg:phone":"+43 7236 7194",
    "sg:postcode":"4224",
    "sg:province":"Ober\u00f6sterreich",
    "wof:name":"Europhat Umwelttechnik Johann Schwabegger",
    "wof:placetype":"venue"
},
  "geometry": {"coordinates":[14.5195941925,48.359539032],"type":"Point"}
}