{
  "type": "Feature",
  "properties": {
    "addr:full":"Edelsbachstr 93 Eggersdorf Steiermark 8063",
    "addr:housenumber":"93",
    "addr:postcode":"8063",
    "addr:street":"Edelsbachstr",
    "iso:country":"AT",
    "sg:address":"Edelsbachstr 93",
    "sg:city":"Eggersdorf",
    "sg:orig_category":"Bodenverlegung",
    "sg:phone":"+43 4331 173381",
    "sg:postcode":"8063",
    "sg:province":"Steiermark",
    "wof:name":"Manninger Peter",
    "wof:placetype":"venue"
},
  "geometry": {"coordinates":[15.5624141693,47.1169166565],"type":"Point"}
}