{
  "type": "Feature",
  "properties": {
    "addr:full":"Oberst-Lepperdingerstra\u00dfe 1 Wals Salzburg 5071",
    "addr:housenumber":"1",
    "addr:postcode":"5071",
    "addr:street":"Oberst-Lepperdingerstrasse;Salzburg",
    "iso:country":"AT",
    "sg:address":"Oberst-Lepperdingerstra\u00dfe 1",
    "sg:city":"Wals",
    "sg:classifiers":[
        {
            "category":"Building & Trades",
            "subcategory":"Electrical",
            "type":"Services"
        }
    ],
    "sg:phone":"+43 662 4348000",
    "sg:postcode":"5071",
    "sg:province":"Salzburg",
    "sg:tags":[
        "engineering",
        "construction",
        "architectural",
        "software"
    ],
    "sg:website":"nemetschek.at",
    "wof:name":"NEMETSCHEK Ges.m.b.H.",
    "wof:placetype":"venue"
},
  "geometry": {"coordinates":[12.9693145752,47.7897644043],"type":"Point"}
}