{
  "type": "Feature",
  "properties": {
    "iso:country":"AT",
    "sg:address":"Gschwendter Str 41",
    "sg:city":"Kumberg",
    "sg:orig_category":"Werbeagenturen",
    "sg:phone":"+43 3132 2327",
    "sg:postcode":"8062",
    "sg:province":"Steiermark",
    "wof:name":"Print-Verlag",
    "wof:placetype":"venue"
},
  "geometry": {"coordinates":[15.5573501587,47.172958374],"type":"Point"}
}