{
  "type": "Feature",
  "properties": {
    "addr:full":"Kapruner Str 3 Zell am See Salzburg 5700",
    "addr:housenumber":"3",
    "addr:postcode":"5700",
    "addr:street":"Str;Salzburg",
    "iso:country":"AT",
    "sg:address":"Kapruner Str 3",
    "sg:city":"Zell am See",
    "sg:orig_category":"Fleischhauereien",
    "sg:phone":"+43 6542 56832",
    "sg:postcode":"5700",
    "sg:province":"Salzburg",
    "wof:name":"Schirnhofer-Breisler GesmbH - Shop in Shop",
    "wof:placetype":"venue"
},
  "geometry": {"coordinates":[12.7844161987,47.2824211121],"type":"Point"}
}