{
  "type": "Feature",
  "properties": {
    "addr:full":"Hauptstr 56 Hennersdorf Nieder\u00f6sterreich 2332",
    "addr:housenumber":"56",
    "addr:postcode":"2332",
    "addr:street":"Hauptstr",
    "iso:country":"AT",
    "sg:address":"Hauptstr 56",
    "sg:city":"Hennersdorf",
    "sg:orig_category":"\u00c3\u201erzte / F Allgemeinmedizin",
    "sg:phone":"+43 2235 818670",
    "sg:postcode":"2332",
    "sg:province":"Nieder\u00f6sterreich",
    "wof:name":"Krause Franklin Dr",
    "wof:placetype":"venue"
},
  "geometry": {"coordinates":[16.3673229218,48.1104545593],"type":"Point"}
}