{
  "type": "Feature",
  "properties": {
    "addr:full":"B\u00fcngenstr 6 Lustenau Vorarlberg 6890",
    "addr:housenumber":"6",
    "addr:postcode":"6890",
    "addr:street":"Buengenstr",
    "iso:country":"AT",
    "sg:address":"B\u00fcngenstr 6",
    "sg:city":"Lustenau",
    "sg:orig_category":"Stickereien",
    "sg:phone":"+43 5577 84717",
    "sg:postcode":"6890",
    "sg:province":"Vorarlberg",
    "wof:name":"Hagen Werner",
    "wof:placetype":"venue"
},
  "geometry": {"coordinates":[9.6590452194,47.4262237549],"type":"Point"}
}