{
  "type": "Feature",
  "properties": {
    "addr:full":"Bairbach 6a Telfs Tirol 6410",
    "addr:housenumber":"6a",
    "addr:postcode":"6410",
    "addr:street":"Bairbach;Tirol",
    "iso:country":"AT",
    "sg:address":"Bairbach 6a",
    "sg:city":"Telfs",
    "sg:classifiers":[
        {
            "category":"Restaurant",
            "type":"Food & Drink"
        }
    ],
    "sg:phone":"+43 5262 63260",
    "sg:postcode":"6410",
    "sg:province":"Tirol",
    "wof:name":"Cafe-Restaurant Stefan",
    "wof:placetype":"venue"
},
  "geometry": {"coordinates":[11.1191558838,47.3166770935],"type":"Point"}
}