{
  "type": "Feature",
  "properties": {
    "iso:country":"AT",
    "sg:address":"Hauptpl 92",
    "sg:city":"Gars am Kamp",
    "sg:orig_category":"Fleischhauereien",
    "sg:phone":"+43 2985 2227",
    "sg:postcode":"3571",
    "sg:province":"Nieder\u00f6sterreich",
    "wof:name":"Kolobratnik Richard GesmbH",
    "wof:placetype":"venue"
},
  "geometry": {"coordinates":[15.6593770981,48.5983085632],"type":"Point"}
}