{
  "type": "Feature",
  "properties": {
    "addr:full":"Liebknechtg 36/36 Wien Wien 1160",
    "addr:housenumber":"36 / 36",
    "addr:postcode":"1160",
    "addr:street":"Liebknechtg",
    "iso:country":"AT",
    "sg:address":"Liebknechtg 36/36",
    "sg:city":"Wien",
    "sg:orig_category":"Psychotherapie",
    "sg:phone":"+43 1 9532940",
    "sg:postcode":"1160",
    "sg:province":"Wien",
    "wof:name":"Tinhof Andrea Mag",
    "wof:placetype":"venue"
},
  "geometry": {"coordinates":[16.3040904999,48.2225990295],"type":"Point"}
}