{
  "type": "Feature",
  "properties": {
    "iso:country":"AT",
    "sg:address":"Johannag 36/21",
    "sg:city":"Wien",
    "sg:classifiers":[
        {
            "category":"Organizations",
            "subcategory":"Community Association",
            "type":"Services"
        }
    ],
    "sg:phone":"+43 4319 610843",
    "sg:postcode":"1050",
    "sg:province":"Wien",
    "sg:tags":[
        "relation",
        "public"
    ],
    "wof:name":"no.sugar marketing.pr",
    "wof:placetype":"venue"
},
  "geometry": {"coordinates":[16.3584918976,48.19165802],"type":"Point"}
}