{
  "type": "Feature",
  "properties": {
    "iso:country":"AT",
    "sg:address":"Franz-M.-Felder-Str 10",
    "sg:city":"Dornbirn",
    "sg:orig_category":"Bestattungsunternehmen",
    "sg:phone":"+43 5572 206300",
    "sg:postcode":"6850",
    "sg:province":"Vorarlberg",
    "wof:name":"Bestattung Oberhauser GesmbH",
    "wof:placetype":"venue"
},
  "geometry": {"coordinates":[9.7399597168,47.4172821045],"type":"Point"}
}