{
  "type": "Feature",
  "properties": {
    "addr:full":"Auf der Matte 19 Bregenz Vorarlberg 6900",
    "addr:housenumber":"19",
    "addr:postcode":"6900",
    "addr:street":"Auf Der Matte",
    "iso:country":"AT",
    "sg:address":"Auf der Matte 19",
    "sg:city":"Bregenz",
    "sg:classifiers":[
        {
            "category":"Wholesale",
            "subcategory":"Stationery",
            "type":"Manufacturing & Wholesale Goods"
        }
    ],
    "sg:phone":"+43 650 4004441",
    "sg:postcode":"6900",
    "sg:province":"Vorarlberg",
    "sg:tags":[
        "sport-",
        "u",
        "sponsoring-agenturen"
    ],
    "wof:name":"Sponsoring-Team Spo.t. Bilgeri Ettinger OEG",
    "wof:placetype":"venue"
},
  "geometry": {"coordinates":[9.7278661728,47.4990463257],"type":"Point"}
}