{
  "type": "Feature",
  "properties": {
    "addr:full":"Rennweg 94 Wien Wien 1030",
    "addr:housenumber":"94",
    "addr:postcode":"1030",
    "addr:street":"Rennweg",
    "iso:country":"AT",
    "sg:address":"Rennweg 94",
    "sg:city":"Wien",
    "sg:orig_category":"Installationsunternehmen",
    "sg:phone":"+43 1 797190",
    "sg:postcode":"1030",
    "sg:province":"Wien",
    "wof:name":"Siegl Ing InstallationsgesmbH",
    "wof:placetype":"venue"
},
  "geometry": {"coordinates":[16.398399353,48.1895523071],"type":"Point"}
}