{
  "type": "Feature",
  "properties": {
    "addr:full":"Klagbaumg 17 Wien Wien 1040",
    "addr:housenumber":"17",
    "addr:postcode":"1040",
    "addr:street":"Klagbaumg",
    "iso:country":"AT",
    "sg:address":"Klagbaumg 17",
    "sg:city":"Wien",
    "sg:orig_category":"Maler, Anstreicher U Lackierer",
    "sg:phone":"+43 1 5818086",
    "sg:postcode":"1040",
    "sg:province":"Wien",
    "wof:name":"R & A Raumausstattungs GesmbH",
    "wof:placetype":"venue"
},
  "geometry": {"coordinates":[16.3640022278,48.1918983459],"type":"Point"}
}