{
  "type": "Feature",
  "properties": {
    "addr:full":"Wiener Str 8 Wolkersdorf im Weinviertel Nieder\u00f6sterreich 2120",
    "addr:housenumber":"8",
    "addr:postcode":"2120",
    "iso:country":"AT",
    "sg:address":"Wiener Str 8",
    "sg:city":"Wolkersdorf im Weinviertel",
    "sg:orig_category":"Bauunternehmen",
    "sg:phone":"+43 2245 3997",
    "sg:postcode":"2120",
    "sg:province":"Nieder\u00f6sterreich",
    "wof:name":"Mayer & Beinhart BaugesmbH",
    "wof:placetype":"venue"
},
  "geometry": {"coordinates":[16.5141849518,48.3840026855],"type":"Point"}
}