{
  "type": "Feature",
  "properties": {
    "addr:full":"Julius Raab-Str 17 Linz Ober\u00f6sterreich 4040",
    "addr:housenumber":"17",
    "addr:postcode":"4040",
    "iso:country":"AT",
    "sg:address":"Julius Raab-Str 17",
    "sg:city":"Linz",
    "sg:classifiers":[
        {
            "category":"Retail",
            "subcategory":"Event Space",
            "type":"Services"
        }
    ],
    "sg:phone":"+43 732 757862",
    "sg:postcode":"4040",
    "sg:province":"Ober\u00f6sterreich",
    "sg:tags":[
        "hand-",
        "u",
        "fu\u00c3\u0178pflege"
    ],
    "wof:name":"Zauner Heidemarie",
    "wof:placetype":"venue"
},
  "geometry": {"coordinates":[14.3217058182,48.3301544189],"type":"Point"}
}