{
  "type": "Feature",
  "properties": {
    "addr:full":"Windhof 150 Semriach Steiermark 8102",
    "addr:housenumber":"150",
    "addr:postcode":"8102",
    "addr:street":"Windhof",
    "iso:country":"AT",
    "sg:address":"Windhof 150",
    "sg:city":"Semriach",
    "sg:orig_category":"\u00c3\u201erzte / F Allgemeinmedizin",
    "sg:phone":"+43 3127 888880",
    "sg:postcode":"8102",
    "sg:province":"Steiermark",
    "wof:name":"Semmelrock Harald Dr",
    "wof:placetype":"venue"
},
  "geometry": {"coordinates":[15.4145851135,47.2089958191],"type":"Point"}
}