{
  "type": "Feature",
  "properties": {
    "addr:full":"Salzburger Str 57 Lambach Ober\u00f6sterreich 4650",
    "addr:housenumber":"57",
    "addr:postcode":"4650",
    "addr:street":"Salzburger Str",
    "iso:country":"AT",
    "sg:address":"Salzburger Str 57",
    "sg:city":"Lambach",
    "sg:orig_category":"Elektroinstallationsunternehmen",
    "sg:phone":"+43 7245 21120",
    "sg:postcode":"4650",
    "sg:province":"Ober\u00f6sterreich",
    "wof:name":"Huber Johann Elektrotechnik",
    "wof:placetype":"venue"
},
  "geometry": {"coordinates":[13.8621149063,48.0905647278],"type":"Point"}
}