{
  "type": "Feature",
  "properties": {
    "addr:full":"Freist\u00e4dter Str 317 Linz Ober\u00f6sterreich 4040",
    "addr:housenumber":"317",
    "addr:postcode":"4040",
    "addr:street":"Str",
    "iso:country":"AT",
    "sg:address":"Freist\u00e4dter Str 317",
    "sg:city":"Linz",
    "sg:orig_category":"Non-Classified Establishments",
    "sg:phone":"+43 732 248640",
    "sg:postcode":"4040",
    "sg:province":"Ober\u00f6sterreich",
    "wof:name":"Christengemeinde Linz-Dornach",
    "wof:placetype":"venue"
},
  "geometry": {"coordinates":[14.3207416534,48.3290481567],"type":"Point"}
}