{
  "type": "Feature",
  "properties": {
    "iso:country":"AT",
    "sg:address":"Amalienstr 14",
    "sg:city":"Wien",
    "sg:orig_category":"Spenglereien",
    "sg:phone":"+43 4366 41035130",
    "sg:postcode":"1130",
    "sg:province":"Wien",
    "wof:name":"Giesinger Werner",
    "wof:placetype":"venue"
},
  "geometry": {"coordinates":[16.2724933624,48.1914329529],"type":"Point"}
}