{
  "type": "Feature",
  "properties": {
    "addr:full":"Vois 12 Schwarzau im Gebirge Nieder\u00f6sterreich 2662",
    "addr:housenumber":"12",
    "addr:postcode":"2662",
    "addr:street":"Vois",
    "iso:country":"AT",
    "sg:address":"Vois 12",
    "sg:city":"Schwarzau im Gebirge",
    "sg:classifiers":[
        {
            "category":"Manufacturing",
            "subcategory":"Wood Products",
            "type":"Manufacturing & Wholesale Goods"
        }
    ],
    "sg:phone":"+43 2667 213",
    "sg:postcode":"2662",
    "sg:province":"Nieder\u00f6sterreich",
    "sg:tags":[
        "firewood"
    ],
    "sg:website":"kienbink.at",
    "wof:name":"F. Kienbink Ges.m.b.H.",
    "wof:placetype":"venue"
},
  "geometry": {"coordinates":[15.7523612976,47.8087348938],"type":"Point"}
}