{
  "type": "Feature",
  "properties": {
    "iso:country":"AT",
    "sg:address":"Wiener Str 9",
    "sg:city":"Waidhofen an der Thaya",
    "sg:orig_category":"Institute",
    "sg:phone":"+43 4328 4252955",
    "sg:postcode":"3830",
    "sg:province":"Nieder\u00f6sterreich",
    "wof:name":"Theater an der Mauer (TAM)",
    "wof:placetype":"venue"
},
  "geometry": {"coordinates":[15.2887153625,48.8155593872],"type":"Point"}
}