{
  "type": "Feature",
  "properties": {
    "iso:country":"AT",
    "sg:address":"Otto-Loewi-G 18/3",
    "sg:city":"St. Peter",
    "sg:orig_category":"Architekten",
    "sg:phone":"+43 316 425942",
    "sg:postcode":"8042",
    "sg:province":"Steiermark",
    "wof:name":"Mitterberger Gerhard Arch Dipl-Ing",
    "wof:placetype":"venue"
},
  "geometry": {"coordinates":[15.4680547714,47.0580101013],"type":"Point"}
}