{
  "type": "Feature",
  "properties": {
    "addr:full":"Nr 53 Unterpremst\u00e4tten Steiermark 8141",
    "addr:postcode":"8141",
    "addr:street":"Nr 53 Unterpremstaetten Steiermark",
    "iso:country":"AT",
    "sg:address":"Nr 53",
    "sg:city":"Unterpremst\u00e4tten",
    "sg:orig_category":"Gutsverwaltungen",
    "sg:phone":"+43 3135 52212",
    "sg:postcode":"8141",
    "sg:province":"Steiermark",
    "wof:name":"Mader'sche Gutsverwaltung",
    "wof:placetype":"venue"
},
  "geometry": {"coordinates":[15.4021930695,46.9679298401],"type":"Point"}
}