{
  "type": "Feature",
  "properties": {
    "addr:full":"Hauptstr 81 Frankenmarkt Ober\u00f6sterreich 4890",
    "addr:housenumber":"81",
    "addr:postcode":"4890",
    "addr:street":"Hauptstr;Oberoesterreich",
    "iso:country":"AT",
    "sg:address":"Hauptstr 81",
    "sg:city":"Frankenmarkt",
    "sg:orig_category":"Musikunterricht",
    "sg:phone":"+43 76848759",
    "sg:postcode":"4890",
    "sg:province":"Ober\u00f6sterreich",
    "wof:name":"Landesmusikschule",
    "wof:placetype":"venue"
},
  "geometry": {"coordinates":[13.4184246063,47.9852561951],"type":"Point"}
}