{
  "type": "Feature",
  "properties": {
    "iso:country":"AT",
    "sg:address":"Erzherzog-Rainer-Ring 18",
    "sg:city":"Baden",
    "sg:orig_category":"Boutiquen",
    "sg:phone":"+43 4322 5245373",
    "sg:postcode":"2500",
    "sg:province":"Nieder\u00f6sterreich",
    "wof:name":"Sigmund Helga",
    "wof:placetype":"venue"
},
  "geometry": {"coordinates":[16.2319316864,48.0086784363],"type":"Point"}
}