{
  "type": "Feature",
  "properties": {
    "addr:full":"Schulweg 3 F\u00fcrnitz K\u00e4rnten 9586",
    "addr:housenumber":"3",
    "addr:postcode":"9586",
    "addr:street":"Schulweg;Kaernten",
    "iso:country":"AT",
    "sg:address":"Schulweg 3",
    "sg:city":"F\u00fcrnitz",
    "sg:orig_category":"Volksschulen",
    "sg:phone":"+43 4342 573539",
    "sg:postcode":"9586",
    "sg:province":"K\u00e4rnten",
    "wof:name":"Volksschule",
    "wof:placetype":"venue"
},
  "geometry": {"coordinates":[13.813246727,46.5601997375],"type":"Point"}
}