{
  "type": "Feature",
  "properties": {
    "addr:full":"Raiffeisenstr 2 Wolfern Ober\u00f6sterreich 4493",
    "addr:housenumber":"2",
    "addr:postcode":"4493",
    "addr:street":"Raiffeisenstr",
    "iso:country":"AT",
    "sg:address":"Raiffeisenstr 2",
    "sg:city":"Wolfern",
    "sg:orig_category":"Tischlereien",
    "sg:phone":"+43 7253 71110",
    "sg:postcode":"4493",
    "sg:province":"Ober\u00f6sterreich",
    "wof:name":"FEWI-Holztechnik GmbH",
    "wof:placetype":"venue"
},
  "geometry": {"coordinates":[14.3755607605,48.0804290771],"type":"Point"}
}