{
  "type": "Feature",
  "properties": {
    "addr:full":"Hauptstr 26 Scheibbs Nieder\u00f6sterreich 3270",
    "addr:housenumber":"26",
    "addr:postcode":"3270",
    "addr:street":"Hauptstr",
    "iso:country":"AT",
    "sg:address":"Hauptstr 26",
    "sg:city":"Scheibbs",
    "sg:orig_category":"Fleischhauereien",
    "sg:phone":"+43 7482 42454",
    "sg:postcode":"3270",
    "sg:province":"Nieder\u00f6sterreich",
    "wof:name":"Lechner Herbert",
    "wof:placetype":"venue"
},
  "geometry": {"coordinates":[15.166642189,48.0056610107],"type":"Point"}
}