{
  "type": "Feature",
  "properties": {
    "addr:full":"Radlpa\u00dfstr 30 Lannach Steiermark 8502",
    "addr:housenumber":"30",
    "addr:postcode":"8502",
    "addr:street":"Radlpassstr",
    "iso:country":"AT",
    "sg:address":"Radlpa\u00dfstr 30",
    "sg:city":"Lannach",
    "sg:orig_category":"Bauunternehmen",
    "sg:phone":"+43 4331 3681891",
    "sg:postcode":"8502",
    "sg:province":"Steiermark",
    "wof:name":"Hoch- u Tiefbau Egger GesmbH",
    "wof:placetype":"venue"
},
  "geometry": {"coordinates":[15.3365068436,46.9475708008],"type":"Point"}
}