{
  "type": "Feature",
  "properties": {
    "addr:full":"Gm\u00fcnder Str 201 Weitra Nieder\u00f6sterreich 3970",
    "addr:housenumber":"201",
    "addr:postcode":"3970",
    "addr:street":"Str",
    "iso:country":"AT",
    "sg:address":"Gm\u00fcnder Str 201",
    "sg:city":"Weitra",
    "sg:orig_category":"Damenmoden",
    "sg:phone":"+43 2856 3221",
    "sg:postcode":"3970",
    "sg:province":"Nieder\u00f6sterreich",
    "wof:name":"Maisetschl\u00e4ger Elfriede",
    "wof:placetype":"venue"
},
  "geometry": {"coordinates":[14.8928060532,48.7005844116],"type":"Point"}
}