{
  "type": "Feature",
  "properties": {
    "addr:full":"Leibnizgasse 61 Wien Wien 1100",
    "addr:housenumber":"61",
    "addr:postcode":"1100",
    "addr:street":"Leibnizgasse",
    "iso:country":"AT",
    "sg:address":"Leibnizgasse 61",
    "sg:city":"Wien",
    "sg:classifiers":[
        {
            "category":"Professional",
            "subcategory":"Art Services",
            "type":"Services"
        }
    ],
    "sg:phone":"+43 1 60263920",
    "sg:postcode":"1100",
    "sg:province":"Wien",
    "sg:tags":[
        "stand",
        "construction",
        "exhibition",
        "fair",
        "trade"
    ],
    "sg:website":"members.chello.at/ing.pessl",
    "wof:name":"Ing. Pessl Kunststofftechnik GmbH",
    "wof:placetype":"venue"
},
  "geometry": {"coordinates":[16.3747158051,48.1697769165],"type":"Point"}
}