{
  "type": "Feature",
  "properties": {
    "addr:full":"Gewerbeparkstrasse 25 Krems an der Donau Nieder\u00f6sterreich 3500",
    "addr:housenumber":"25",
    "addr:postcode":"3500",
    "addr:street":"Gewerbeparkstrasse",
    "iso:country":"AT",
    "sg:address":"Gewerbeparkstrasse 25",
    "sg:city":"Krems an der Donau",
    "sg:classifiers":[
        {
            "category":"Manufacturing",
            "subcategory":"Rubber & Plastics",
            "type":"Manufacturing & Wholesale Goods"
        }
    ],
    "sg:phone":"+43 2732 73501",
    "sg:postcode":"3500",
    "sg:province":"Nieder\u00f6sterreich",
    "sg:tags":[
        "barrel"
    ],
    "sg:website":"strapex.co.at",
    "wof:name":"Strapex Austria GmbH",
    "wof:placetype":"venue"
},
  "geometry": {"coordinates":[15.6645803452,48.4080886841],"type":"Point"}
}