{
  "type": "Feature",
  "properties": {
    "iso:country":"AT",
    "sg:address":"Meidlinger Hauptstr 36",
    "sg:city":"Wien",
    "sg:classifiers":[
        {
            "category":"Restaurant",
            "type":"Food & Drink"
        }
    ],
    "sg:phone":"+43 1 8177084",
    "sg:postcode":"1120",
    "sg:province":"Wien",
    "wof:name":"Nordsee GesmbH",
    "wof:placetype":"venue"
},
  "geometry": {"coordinates":[16.3296508789,48.1793746948],"type":"Point"}
}