{
  "type": "Feature",
  "properties": {
    "addr:full":"Harhagen 3 Sattledt Ober\u00f6sterreich 4642",
    "addr:housenumber":"3",
    "addr:postcode":"4642",
    "addr:street":"Harhagen",
    "iso:country":"AT",
    "sg:address":"Harhagen 3",
    "sg:city":"Sattledt",
    "sg:orig_category":"Autohandel",
    "sg:phone":"+43 7244 8244",
    "sg:postcode":"4642",
    "sg:province":"Ober\u00f6sterreich",
    "wof:name":"Denk Anna Maria",
    "wof:placetype":"venue"
},
  "geometry": {"coordinates":[14.0453586578,48.0672149658],"type":"Point"}
}