{
  "type": "Feature",
  "properties": {
    "iso:country":"AT",
    "sg:address":"Villacher Str 1A",
    "sg:city":"Klagenfurt",
    "sg:orig_category":"Plakatierungsunternehmen",
    "sg:phone":"+43 463 50690",
    "sg:postcode":"9020",
    "sg:province":"K\u00e4rnten",
    "wof:name":"Ank\u00fcnder Ges f Au\u00dfenwerbung mbH",
    "wof:placetype":"venue"
},
  "geometry": {"coordinates":[14.30356884,46.623336792],"type":"Point"}
}