{
  "type": "Feature",
  "properties": {
    "addr:full":"Bro\u00dfwaldeng 8 Bregenz Vorarlberg 6900",
    "addr:housenumber":"8",
    "addr:postcode":"6900",
    "addr:street":"Brosswaldeng",
    "iso:country":"AT",
    "sg:address":"Bro\u00dfwaldeng 8",
    "sg:city":"Bregenz",
    "sg:orig_category":"Interessensvertretungen",
    "sg:phone":"+43 5574 487870",
    "sg:postcode":"6900",
    "sg:province":"Vorarlberg",
    "wof:name":"Institut f Gesundheits- und Krankenpflege",
    "wof:placetype":"venue"
},
  "geometry": {"coordinates":[9.7339878082,47.5010604858],"type":"Point"}
}