{
  "type": "Feature",
  "properties": {
    "addr:full":"Hofsteigstr 21 Lustenau Vorarlberg 6890",
    "addr:housenumber":"21",
    "addr:postcode":"6890",
    "addr:street":"Hofsteigstr",
    "iso:country":"AT",
    "sg:address":"Hofsteigstr 21",
    "sg:city":"Lustenau",
    "sg:orig_category":"Stickereien",
    "sg:phone":"+43 4355 7783313",
    "sg:postcode":"6890",
    "sg:province":"Vorarlberg",
    "wof:name":"Grabher Ferdinand",
    "wof:placetype":"venue"
},
  "geometry": {"coordinates":[9.6621990204,47.4361991882],"type":"Point"}
}