{
  "type": "Feature",
  "properties": {
    "addr:full":"Bahnhofstr 14 Spittal an der Drau K\u00e4rnten 9800",
    "addr:housenumber":"14",
    "addr:postcode":"9800",
    "addr:street":"Bahnhofstr;Kaernten",
    "iso:country":"AT",
    "sg:address":"Bahnhofstr 14",
    "sg:city":"Spittal an der Drau",
    "sg:orig_category":"Spielwaren U Spiele",
    "sg:phone":"+43 4347 623097",
    "sg:postcode":"9800",
    "sg:province":"K\u00e4rnten",
    "wof:name":"Spiel-Box Inh Ewald Faullant",
    "wof:placetype":"venue"
},
  "geometry": {"coordinates":[13.491358757,46.797744751],"type":"Point"}
}