{
  "type": "Feature",
  "properties": {
    "iso:country":"AT",
    "sg:address":"Leystr 34",
    "sg:city":"Wien",
    "sg:orig_category":"Volksschulen",
    "sg:phone":"+43 1 3328552",
    "sg:postcode":"1200",
    "sg:province":"Wien",
    "wof:name":"Schulen d Stadt Wien",
    "wof:placetype":"venue"
},
  "geometry": {"coordinates":[16.3774032593,48.2433128357],"type":"Point"}
}