{
  "type": "Feature",
  "properties": {
    "addr:full":"Hauptpl 8 Ybbs an der Donau Nieder\u00f6sterreich 3370",
    "addr:housenumber":"8",
    "addr:postcode":"3370",
    "addr:street":"Hauptpl",
    "iso:country":"AT",
    "sg:address":"Hauptpl 8",
    "sg:city":"Ybbs an der Donau",
    "sg:orig_category":"Tabaktrafiken",
    "sg:phone":"+43 7412 54173",
    "sg:postcode":"3370",
    "sg:province":"Nieder\u00f6sterreich",
    "wof:name":"Stadler Josef",
    "wof:placetype":"venue"
},
  "geometry": {"coordinates":[15.0856771469,48.177280426],"type":"Point"}
}