{
  "type": "Feature",
  "properties": {
    "addr:full":"Bundesstr. 110 Haus Steiermark 8967",
    "addr:housenumber":"110",
    "addr:postcode":"8967",
    "addr:street":"Haus",
    "iso:country":"AT",
    "sg:address":"Bundesstr. 110",
    "sg:city":"Haus",
    "sg:classifiers":[
        {
            "category":"Professional",
            "subcategory":"Engineering",
            "type":"Services"
        }
    ],
    "sg:phone":"+43 4336 8641280",
    "sg:postcode":"8967",
    "sg:province":"Steiermark",
    "sg:tags":[
        "machine",
        "-",
        "mechanical"
    ],
    "wof:name":"SANIT\u00c4R-ELEMENTBAU GESMBH",
    "wof:placetype":"venue"
},
  "geometry": {"coordinates":[13.7485494614,47.4063148499],"type":"Point"}
}