{
  "type": "Feature",
  "properties": {
    "addr:full":"Kesselbodeng 10 Zwettl Nieder\u00f6sterreich 3910",
    "addr:housenumber":"10",
    "addr:postcode":"3910",
    "addr:street":"Kesselbodeng;Niederoesterreich",
    "iso:country":"AT",
    "sg:address":"Kesselbodeng 10",
    "sg:city":"Zwettl",
    "sg:orig_category":"Tischlereimaschinen U -Bedarf",
    "sg:phone":"+43 4328 22525210",
    "sg:postcode":"3910",
    "sg:province":"Nieder\u00f6sterreich",
    "wof:name":"Aschauer Tischlereibedarf GmbH",
    "wof:placetype":"venue"
},
  "geometry": {"coordinates":[15.1681003571,48.6041564941],"type":"Point"}
}