{
  "type": "Feature",
  "properties": {
    "addr:full":"Nr 1 Oberkappel Ober\u00f6sterreich 4144",
    "addr:postcode":"4144",
    "addr:street":"Nr;Oberoesterreich",
    "iso:country":"AT",
    "sg:address":"Nr 1",
    "sg:city":"Oberkappel",
    "sg:orig_category":"Non-Classified Establishments",
    "sg:phone":"+43 7284 206",
    "sg:postcode":"4144",
    "sg:province":"Ober\u00f6sterreich",
    "wof:name":"Pfarramt Oberkappel",
    "wof:placetype":"venue"
},
  "geometry": {"coordinates":[13.7711467743,48.5525512695],"type":"Point"}
}