{
  "type": "Feature",
  "properties": {
    "iso:country":"AT",
    "sg:address":"Erdbergstr 176-178",
    "sg:city":"Wien",
    "sg:orig_category":"Autoreparatur, Autohandel",
    "sg:phone":"+43 1 7988139",
    "sg:postcode":"1030",
    "sg:province":"Wien",
    "wof:name":"Frantes & Tabor GesmbH",
    "wof:placetype":"venue"
},
  "geometry": {"coordinates":[16.4099121094,48.1935768127],"type":"Point"}
}