{
  "type": "Feature",
  "properties": {
    "addr:full":"Hauptstr 46 Unterrabnitz Burgenland 7371",
    "addr:housenumber":"46",
    "addr:postcode":"7371",
    "addr:street":"Hauptstr",
    "iso:country":"AT",
    "sg:address":"Hauptstr 46",
    "sg:city":"Unterrabnitz",
    "sg:orig_category":"Banken U Sparkassen",
    "sg:phone":"+43 4326 168514",
    "sg:postcode":"7371",
    "sg:province":"Burgenland",
    "wof:name":"Raiffeisenbank Dra\u00dfmarkt-Kobersdorf- St. Martin regGenmbH",
    "wof:placetype":"venue"
},
  "geometry": {"coordinates":[16.3759250641,47.4554786682],"type":"Point"}
}