{
  "type": "Feature",
  "properties": {
    "iso:country":"AT",
    "sg:address":"Landstr 7",
    "sg:city":"Hainburg an der Donau",
    "sg:orig_category":"Optiker",
    "sg:phone":"+43 4321 65624310",
    "sg:postcode":"2410",
    "sg:province":"Nieder\u00f6sterreich",
    "wof:name":"Alschinger Franz GesmbH",
    "wof:placetype":"venue"
},
  "geometry": {"coordinates":[16.9370231628,48.1451950073],"type":"Point"}
}