{
  "type": "Feature",
  "properties": {
    "iso:country":"AT",
    "sg:address":"Nr 8",
    "sg:city":"Ruden",
    "sg:orig_category":"Landwirtschaftliche Produkte",
    "sg:phone":"+43 4234 336",
    "sg:postcode":"9113",
    "sg:province":"K\u00e4rnten",
    "wof:name":"Spieler Stanislaus",
    "wof:placetype":"venue"
},
  "geometry": {"coordinates":[14.7703266144,46.6569061279],"type":"Point"}
}