{
  "type": "Feature",
  "properties": {
    "iso:country":"AT",
    "sg:address":"Gmundner Str 14",
    "sg:city":"Sch\u00f6rfling am Attersee",
    "sg:orig_category":"Fleisch-, Wurst- U Selchwaren / Erzeugung U Gro\u00c3\u0178handel",
    "sg:phone":"+43 4376 622225",
    "sg:postcode":"4861",
    "sg:province":"Ober\u00f6sterreich",
    "wof:name":"Haidinger Hansj\u00f6rg",
    "wof:placetype":"venue"
},
  "geometry": {"coordinates":[13.6109857559,47.9497947693],"type":"Point"}
}