{
  "type": "Feature",
  "properties": {
    "addr:full":"Hauptstr 11 Stockerau Nieder\u00f6sterreich 2000",
    "addr:housenumber":"11",
    "addr:postcode":"2000",
    "addr:street":"Hauptstr",
    "iso:country":"AT",
    "sg:address":"Hauptstr 11",
    "sg:city":"Stockerau",
    "sg:orig_category":"Immobilienmakler",
    "sg:phone":"+43 2266 72454",
    "sg:postcode":"2000",
    "sg:province":"Nieder\u00f6sterreich",
    "wof:name":"IMMO-CONTRACT MaklergesmbH",
    "wof:placetype":"venue"
},
  "geometry": {"coordinates":[16.2096843719,48.3852539062],"type":"Point"}
}