{
  "type": "Feature",
  "properties": {
    "addr:full":"Ledererg 3 Sch\u00f6rfling am Attersee Ober\u00f6sterreich 4861",
    "addr:housenumber":"3",
    "addr:postcode":"4861",
    "addr:street":"Ledererg;Am",
    "iso:country":"AT",
    "sg:address":"Ledererg 3",
    "sg:city":"Sch\u00f6rfling am Attersee",
    "sg:orig_category":"Unternehmensberatung",
    "sg:phone":"+43 4376 62484824",
    "sg:postcode":"4861",
    "sg:province":"Ober\u00f6sterreich",
    "wof:name":"Commercial Assistance Daten u Informationsverarbeitung GmbH",
    "wof:placetype":"venue"
},
  "geometry": {"coordinates":[13.599439621,47.947807312],"type":"Point"}
}