{
  "type": "Feature",
  "properties": {
    "addr:full":"Alte Mattseer Strasse 3 Bergheim Salzburg 5101",
    "addr:housenumber":"3",
    "addr:postcode":"5101",
    "addr:street":"Alte Mattseer Strasse;Salzburg",
    "iso:country":"AT",
    "sg:address":"Alte Mattseer Strasse 3",
    "sg:city":"Bergheim",
    "sg:classifiers":[
        {
            "category":"Shopping",
            "subcategory":"Clothing, Apparel, & Fashions",
            "type":"Retail Goods"
        }
    ],
    "sg:phone":"+43 662 21400",
    "sg:postcode":"5101",
    "sg:province":"Salzburg",
    "sg:tags":[
        "image",
        "clothing",
        "basic"
    ],
    "sg:website":"levi.com",
    "wof:name":"Levi Strauss Germany GmbH",
    "wof:placetype":"venue"
},
  "geometry": {"coordinates":[13.0567703247,47.8402709961],"type":"Point"}
}