{
  "type": "Feature",
  "properties": {
    "addr:full":"Pestalozzistr. 3  Waidhofen an der Ybbs Nieder\u00f6sterreich 3340",
    "addr:housenumber":"3",
    "addr:postcode":"3340",
    "addr:street":"Pestalozzistr.",
    "iso:country":"AT",
    "sg:address":"Pestalozzistr. 3 ",
    "sg:city":"Waidhofen an der Ybbs",
    "sg:classifiers":[
        {
            "category":"Manufacturing",
            "subcategory":"Metals",
            "type":"Manufacturing & Wholesale Goods"
        }
    ],
    "sg:phone":"+43 4374 42555080",
    "sg:postcode":"3340",
    "sg:province":"Nieder\u00f6sterreich",
    "sg:tags":[
        "processing"
    ],
    "wof:name":"FILTERBAU GES.MBH",
    "wof:placetype":"venue"
},
  "geometry": {"coordinates":[14.7903633118,47.9502754211],"type":"Point"}
}