{
  "type": "Feature",
  "properties": {
    "addr:full":"Nr 77 Dimbach Ober\u00f6sterreich 4371",
    "addr:postcode":"4371",
    "addr:street":"Nr;Dimbach",
    "iso:country":"AT",
    "sg:address":"Nr 77",
    "sg:city":"Dimbach",
    "sg:orig_category":"Forstverwaltungen",
    "sg:phone":"+43 7260 4957",
    "sg:postcode":"4371",
    "sg:province":"Ober\u00f6sterreich",
    "wof:name":"Domkapitelsche G\u00fcterverwaltung Revierleitung Schwarzenberg",
    "wof:placetype":"venue"
},
  "geometry": {"coordinates":[14.9078550339,48.3062705994],"type":"Point"}
}