{
  "type": "Feature",
  "properties": {
    "addr:full":"Ungargasse 46 Wien Wien 1030",
    "addr:housenumber":"46",
    "addr:postcode":"1030",
    "addr:street":"Ungargasse",
    "iso:country":"AT",
    "sg:address":"Ungargasse 46",
    "sg:city":"Wien",
    "sg:classifiers":[
        {
            "category":"Professional",
            "subcategory":"Engineering",
            "type":"Services"
        }
    ],
    "sg:phone":"+43 4317 133783",
    "sg:postcode":"1030",
    "sg:province":"Wien",
    "sg:tags":[
        "machine",
        "-",
        "mechanical"
    ],
    "wof:name":"MECKE KLIMA GES.MBH",
    "wof:placetype":"venue"
},
  "geometry": {"coordinates":[16.3872261047,48.1995620728],"type":"Point"}
}