{
  "type": "Feature",
  "properties": {
    "addr:full":"Einsiedlerg 2 Wien Wien 1050",
    "addr:housenumber":"2",
    "addr:postcode":"1050",
    "addr:street":"Einsiedlerg",
    "iso:country":"AT",
    "sg:address":"Einsiedlerg 2",
    "sg:city":"Wien",
    "sg:classifiers":[
        {
            "category":"Professional",
            "subcategory":"Testing Lab",
            "type":"Services"
        }
    ],
    "sg:phone":"+43 1 588170",
    "sg:postcode":"1050",
    "sg:province":"Wien",
    "sg:tags":[
        "magistrate"
    ],
    "wof:name":"Magistrat d Stadt Wien - MA 48 - Stadtreinigung",
    "wof:placetype":"venue"
},
  "geometry": {"coordinates":[16.3528518677,48.1811218262],"type":"Point"}
}