{
  "type": "Feature",
  "properties": {
    "iso:country":"AT",
    "sg:address":"Elbigenalp-Dorf 91 ",
    "sg:city":"Elbigenalp",
    "sg:classifiers":[
        {
            "category":"Communications",
            "subcategory":"Television Station",
            "type":"Services"
        }
    ],
    "sg:phone":"+43 4356 34500",
    "sg:postcode":"6652",
    "sg:province":"Tirol",
    "sg:tags":[
        "electronic",
        "publishing"
    ],
    "wof:name":"KDG MEDIATECH AG",
    "wof:placetype":"venue"
},
  "geometry": {"coordinates":[10.4359750748,47.2906074524],"type":"Point"}
}