{
  "type": "Feature",
  "properties": {
    "iso:country":"AT",
    "sg:address":"Ing Etzel-Str 71",
    "sg:city":"Innsbruck",
    "sg:orig_category":"Sonderschulen",
    "sg:phone":"+43 512 933561",
    "sg:postcode":"6020",
    "sg:province":"Tirol",
    "wof:name":"SPZ d Landes Tirol f blinde und sehbehinderte Kinder",
    "wof:placetype":"venue"
},
  "geometry": {"coordinates":[11.413564682,47.2776679993],"type":"Point"}
}