{
  "type": "Feature",
  "properties": {
    "addr:full":"Heide, 25. Strasse 1 Kematen an der Ybbs Nieder\u00f6sterreich 3331",
    "addr:housenumber":"1",
    "addr:postcode":"3331",
    "addr:street":"Heide;Strasse",
    "iso:country":"AT",
    "sg:address":"Heide, 25. Strasse 1",
    "sg:city":"Kematen an der Ybbs",
    "sg:classifiers":[
        {
            "category":"Manufacturing",
            "subcategory":"Wood Products",
            "type":"Manufacturing & Wholesale Goods"
        }
    ],
    "sg:phone":"+43 7448 21780",
    "sg:postcode":"3331",
    "sg:province":"Nieder\u00f6sterreich",
    "sg:tags":[
        "lumber"
    ],
    "sg:website":"stoeckl.com",
    "wof:name":"St\u00f6ckl Ges.m.b.H.",
    "wof:placetype":"venue"
},
  "geometry": {"coordinates":[14.7576198578,48.0224990845],"type":"Point"}
}