{
  "type": "Feature",
  "properties": {
    "iso:country":"AT",
    "sg:address":"Waldeggstr 16",
    "sg:city":"Linz",
    "sg:orig_category":"Inkassoinstitute",
    "sg:phone":"+43 732 656242",
    "sg:postcode":"4020",
    "sg:province":"Ober\u00f6sterreich",
    "sg:website":"oko-inkasso.co.at",
    "wof:name":"Ausk\u00fcnfte - Inkasso OKO GmbH & Co KG",
    "wof:placetype":"venue"
},
  "geometry": {"coordinates":[14.2851266861,48.2931747437],"type":"Point"}
}