{
  "type": "Feature",
  "properties": {
    "addr:full":"Spittelwiese 4/1 Linz Ober\u00f6sterreich 4020",
    "addr:housenumber":"4 / 1",
    "addr:postcode":"4020",
    "addr:street":"Spittelwiese",
    "iso:country":"AT",
    "sg:address":"Spittelwiese 4/1",
    "sg:city":"Linz",
    "sg:orig_category":"Institute",
    "sg:phone":"+43 732 77200",
    "sg:postcode":"4020",
    "sg:province":"Ober\u00f6sterreich",
    "wof:name":"Amt d O\u00d6 Landesregierung - Institut f Kulturf\u00f6rderung",
    "wof:placetype":"venue"
},
  "geometry": {"coordinates":[14.2883386612,48.3028793335],"type":"Point"}
}