{
  "type": "Feature",
  "properties": {
    "iso:country":"AT",
    "sg:address":"Nr 5",
    "sg:city":"Filzmoos",
    "sg:orig_category":"Pensionen / Privatzimmer",
    "sg:phone":"+43 6453 8298",
    "sg:postcode":"5532",
    "sg:province":"Salzburg",
    "wof:name":"Fr\u00fchst\u00fcckspension Raingut",
    "wof:placetype":"venue"
},
  "geometry": {"coordinates":[13.5202980042,47.4332199097],"type":"Point"}
}