{
  "type": "Feature",
  "properties": {
    "addr:full":"Nr 64 Blindenmarkt Nieder\u00f6sterreich 3372",
    "addr:postcode":"3372",
    "addr:street":"Nr 64",
    "iso:country":"AT",
    "sg:address":"Nr 64",
    "sg:city":"Blindenmarkt",
    "sg:orig_category":"Tankstellen",
    "sg:phone":"+43 7412 58927",
    "sg:postcode":"3372",
    "sg:province":"Nieder\u00f6sterreich",
    "wof:name":"IQ- Diskont Tankstelle Betreiber Lindner",
    "wof:placetype":"venue"
},
  "geometry": {"coordinates":[14.9881477356,48.1284942627],"type":"Point"}
}