{
  "type": "Feature",
  "properties": {
    "addr:full":"Keimlgutg 50 Linz Ober\u00f6sterreich 4040",
    "addr:housenumber":"50",
    "addr:postcode":"4040",
    "addr:street":"Keimlgutg",
    "iso:country":"AT",
    "sg:address":"Keimlgutg 50",
    "sg:city":"Linz",
    "sg:orig_category":"Webdesign",
    "sg:phone":"+43 676 5045050",
    "sg:postcode":"4040",
    "sg:province":"Ober\u00f6sterreich",
    "wof:name":"Design & Grips",
    "wof:placetype":"venue"
},
  "geometry": {"coordinates":[14.2610778809,48.3168678284],"type":"Point"}
}