{
  "type": "Feature",
  "properties": {
    "addr:full":"Schmidgunstg 12 Wien Wien 1110",
    "addr:housenumber":"12",
    "addr:postcode":"1110",
    "addr:street":"Schmidgunstg",
    "iso:country":"AT",
    "sg:address":"Schmidgunstg 12",
    "sg:city":"Wien",
    "sg:orig_category":"Autohandel",
    "sg:phone":"+43 1 7698228",
    "sg:postcode":"1110",
    "sg:province":"Wien",
    "wof:name":"Czeczil GesmbH",
    "wof:placetype":"venue"
},
  "geometry": {"coordinates":[16.4618682861,48.1607284546],"type":"Point"}
}