{
  "type": "Feature",
  "properties": {
    "addr:full":"Holzriedstr 33 Wolfurt Vorarlberg 6922",
    "addr:housenumber":"33",
    "addr:postcode":"6922",
    "addr:street":"Holzriedstr",
    "iso:country":"AT",
    "sg:address":"Holzriedstr 33",
    "sg:city":"Wolfurt",
    "sg:orig_category":"Dichtungsmassen U -Materialien",
    "sg:phone":"+43 4355 746950",
    "sg:postcode":"6922",
    "sg:province":"Vorarlberg",
    "sg:website":"haberkorn.com",
    "wof:name":"Haberkorn Abdichtungssysteme GmbH",
    "wof:placetype":"venue"
},
  "geometry": {"coordinates":[9.7430038452,47.4543457031],"type":"Point"}
}