{
  "type": "Feature",
  "properties": {
    "addr:full":"Berg 102 Gaschurn Vorarlberg 6793",
    "addr:housenumber":"102",
    "addr:postcode":"6793",
    "addr:street":"Berg",
    "iso:country":"AT",
    "sg:address":"Berg 102",
    "sg:city":"Gaschurn",
    "sg:orig_category":"Pensionen / Privatzimmer",
    "sg:phone":"+43 4355 588321",
    "sg:postcode":"6793",
    "sg:province":"Vorarlberg",
    "wof:name":"Maderer Pension",
    "wof:placetype":"venue"
},
  "geometry": {"coordinates":[10.0160560608,46.9878997803],"type":"Point"}
}