{
  "type": "Feature",
  "properties": {
    "addr:full":"PF 35 Wien Wien 1200",
    "addr:postcode":"1200",
    "iso:country":"AT",
    "sg:address":"PF 35",
    "sg:city":"Wien",
    "sg:orig_category":"Internet, Webseiten U -Systeme",
    "sg:phone":"+43 676 3775366",
    "sg:postcode":"1200",
    "sg:province":"Wien",
    "sg:website":"fellner.at",
    "wof:name":"Fellner Webservice",
    "wof:placetype":"venue"
},
  "geometry": {"coordinates":[16.3734645844,48.2306060791],"type":"Point"}
}