{
  "type": "Feature",
  "properties": {
    "iso:country":"AT",
    "sg:address":"Bahnhofstr 50",
    "sg:city":"Stra\u00dfgang",
    "sg:orig_category":"Personalbereitstellung",
    "sg:phone":"+43 4331 6287373",
    "sg:postcode":"8054",
    "sg:province":"Steiermark",
    "wof:name":"VAPS Personalservice Donawitz GmbH & Co KG",
    "wof:placetype":"venue"
},
  "geometry": {"coordinates":[15.405134201,47.0198287964],"type":"Point"}
}