{
  "type": "Feature",
  "properties": {
    "addr:full":"Unterschnadter Str 29 Pucking Ober\u00f6sterreich 4055",
    "addr:postcode":"4055",
    "addr:street":"Str 29",
    "iso:country":"AT",
    "sg:address":"Unterschnadter Str 29",
    "sg:city":"Pucking",
    "sg:classifiers":[
        {
            "category":"Professional",
            "subcategory":"Art Services",
            "type":"Services"
        }
    ],
    "sg:phone":"+43 7229 80500",
    "sg:postcode":"4055",
    "sg:province":"Ober\u00f6sterreich",
    "sg:tags":[
        "designer"
    ],
    "wof:name":"Balder Gerhard",
    "wof:placetype":"venue"
},
  "geometry": {"coordinates":[14.2350301743,48.1770401001],"type":"Point"}
}