{
  "type": "Feature",
  "properties": {
    "addr:full":"H\u00f6ggenstr 4C Radstadt Salzburg 5550",
    "addr:housenumber":"4c",
    "addr:postcode":"5550",
    "addr:street":"Hoeggenstr;Salzburg",
    "iso:country":"AT",
    "sg:address":"H\u00f6ggenstr 4C",
    "sg:city":"Radstadt",
    "sg:orig_category":"Industrievertretungen",
    "sg:phone":"+43 6452 6312",
    "sg:postcode":"5550",
    "sg:province":"Salzburg",
    "wof:name":"Industrievertretungen Schaidreiter",
    "wof:placetype":"venue"
},
  "geometry": {"coordinates":[13.4728040695,47.3774414062],"type":"Point"}
}