{
  "type": "Feature",
  "properties": {
    "iso:country":"AT",
    "sg:address":"Paben 3",
    "sg:city":"Lasberg",
    "sg:orig_category":"Biologische Produkte",
    "sg:phone":"+43 7947 6797",
    "sg:postcode":"4291",
    "sg:province":"Ober\u00f6sterreich",
    "wof:name":"M\u00fchlviertler Bio-Lieferservice",
    "wof:placetype":"venue"
},
  "geometry": {"coordinates":[14.5936126709,48.4505500793],"type":"Point"}
}