{
  "type": "Feature",
  "properties": {
    "addr:full":"Paben 3 Lasberg Ober\u00f6sterreich 4291",
    "addr:housenumber":"3",
    "addr:postcode":"4291",
    "addr:street":"Paben",
    "iso:country":"AT",
    "sg:address":"Paben 3",
    "sg:city":"Lasberg",
    "sg:orig_category":"Biologische Produkte",
    "sg:phone":"+43 7947 6797",
    "sg:postcode":"4291",
    "sg:province":"Ober\u00f6sterreich",
    "wof:name":"M\u00fchlviertler Bio-Lieferservice",
    "wof:placetype":"venue"
},
  "geometry": {"coordinates":[14.5936126709,48.4505500793],"type":"Point"}
}