{
  "type": "Feature",
  "properties": {
    "addr:full":"Pre\u00dfbaumer Strasse 4 Sieghartskirchen Nieder\u00f6sterreich 3443",
    "addr:housenumber":"4",
    "addr:postcode":"3443",
    "addr:street":"Pressbaumer Strasse;Niederoesterreich",
    "iso:country":"AT",
    "sg:address":"Pre\u00dfbaumer Strasse 4",
    "sg:city":"Sieghartskirchen",
    "sg:classifiers":[
        {
            "category":"Manufacturing",
            "subcategory":"Glass & Minerals",
            "type":"Manufacturing & Wholesale Goods"
        }
    ],
    "sg:phone":"+43 2274 2252",
    "sg:postcode":"3443",
    "sg:province":"Nieder\u00f6sterreich",
    "sg:tags":[
        "design"
    ],
    "wof:name":"Franz Geiger",
    "wof:placetype":"venue"
},
  "geometry": {"coordinates":[16.0134525299,48.2544212341],"type":"Point"}
}