{
  "type": "Feature",
  "properties": {
    "addr:full":"Marktplatz 8 Pregarten Ober\u00f6sterreich 4230",
    "addr:housenumber":"8",
    "addr:postcode":"4230",
    "addr:street":"Marktplatz",
    "iso:country":"AT",
    "sg:address":"Marktplatz 8",
    "sg:city":"Pregarten",
    "sg:classifiers":[
        {
            "category":"Home & Garden",
            "subcategory":"Household Appliances",
            "type":"Retail Goods"
        }
    ],
    "sg:phone":"+43 7236 22740",
    "sg:postcode":"4230",
    "sg:province":"Ober\u00f6sterreich",
    "sg:tags":[
        "electric"
    ],
    "wof:name":"LEITNER Elektrotechnik- und Handel GmbH",
    "wof:placetype":"venue"
},
  "geometry": {"coordinates":[14.5305480957,48.3551979065],"type":"Point"}
}