{
  "type": "Feature",
  "properties": {
    "addr:full":"Dorfstrasse 55 Westendorf Tirol 6363",
    "addr:housenumber":"55",
    "addr:postcode":"6363",
    "addr:street":"Dorfstrasse;Tirol",
    "iso:country":"AT",
    "sg:address":"Dorfstrasse 55",
    "sg:city":"Westendorf",
    "sg:classifiers":[
        {
            "category":"Building & Trades",
            "subcategory":"Plumbing",
            "type":"Services"
        }
    ],
    "sg:phone":"+43 5334 6277",
    "sg:postcode":"6363",
    "sg:province":"Tirol",
    "sg:tags":[
        "tub",
        "bath"
    ],
    "wof:name":"Richard Treichl",
    "wof:placetype":"venue"
},
  "geometry": {"coordinates":[12.2163496017,47.4355201721],"type":"Point"}
}