{
  "type": "Feature",
  "properties": {
    "addr:full":"Alte Landstr 6a Schwaz Tirol 6130",
    "addr:housenumber":"6a",
    "addr:postcode":"6130",
    "addr:street":"Alte Landstr;Tirol",
    "iso:country":"AT",
    "sg:address":"Alte Landstr 6a",
    "sg:city":"Schwaz",
    "sg:orig_category":"Physiotherapie",
    "sg:phone":"+43 5242 64297",
    "sg:postcode":"6130",
    "sg:province":"Tirol",
    "wof:name":"P\u00f6hl Constanze Dipl-PT",
    "wof:placetype":"venue"
},
  "geometry": {"coordinates":[11.7228660583,47.3523139954],"type":"Point"}
}