{
  "type": "Feature",
  "properties": {
    "addr:full":"Schweizer Str 87 Hohenems Vorarlberg 6845",
    "addr:postcode":"6845",
    "addr:street":"Str 87",
    "iso:country":"AT",
    "sg:address":"Schweizer Str 87",
    "sg:city":"Hohenems",
    "sg:orig_category":"Damenmoden",
    "sg:phone":"+43 5576 42787",
    "sg:postcode":"6845",
    "sg:province":"Vorarlberg",
    "wof:name":"NEW YORKER - NYer Hansen & Knapp KG",
    "wof:placetype":"venue"
},
  "geometry": {"coordinates":[9.6757268906,47.3748703003],"type":"Point"}
}