{
  "type": "Feature",
  "properties": {
    "addr:full":"Rehmen 91 Au Vorarlberg 6883",
    "addr:housenumber":"91",
    "addr:postcode":"6883",
    "addr:street":"Rehmen",
    "iso:country":"AT",
    "sg:address":"Rehmen 91",
    "sg:city":"Au",
    "sg:classifiers":[
        {
            "category":"Travel",
            "subcategory":"Hotels & Motels",
            "type":"Entertainment"
        }
    ],
    "sg:phone":"+43 5515 2247",
    "sg:postcode":"6883",
    "sg:province":"Vorarlberg",
    "wof:name":"Hotel Alpenrose",
    "wof:placetype":"venue"
},
  "geometry": {"coordinates":[9.9826622009,47.3227767944],"type":"Point"}
}