{
  "type": "Feature",
  "properties": {
    "iso:country":"AT",
    "sg:address":"Schotteng 2",
    "sg:city":"Wien",
    "sg:orig_category":"Kontaktlinsenoptiker, Fernrohre U Feldstecher, Optiker",
    "sg:phone":"+43 4315 3363150",
    "sg:postcode":"1010",
    "sg:province":"Wien",
    "sg:website":"optikhaus-binder.at",
    "wof:name":"Binder Gerhard",
    "wof:placetype":"venue"
},
  "geometry": {"coordinates":[16.3640403748,48.2125282288],"type":"Point"}
}