{
  "type": "Feature",
  "properties": {
    "addr:full":"Nr 20 Emmersdorf an der Donau Nieder\u00f6sterreich 3644",
    "addr:postcode":"3644",
    "addr:street":"Nr;Emmersdorf An Der Donau",
    "iso:country":"AT",
    "sg:address":"Nr 20",
    "sg:city":"Emmersdorf an der Donau",
    "sg:classifiers":[
        {
            "category":"Travel",
            "subcategory":"Hotels & Motels",
            "type":"Entertainment"
        }
    ],
    "sg:phone":"+43 2752 72572",
    "sg:postcode":"3644",
    "sg:province":"Nieder\u00f6sterreich",
    "wof:name":"Best Western Landhotel Wachau",
    "wof:placetype":"venue"
},
  "geometry": {"coordinates":[166.9221496582,-0.5282999873],"type":"Point"}
}