{
  "type": "Feature",
  "properties": {
    "iso:country":"AT",
    "sg:address":"Grabeng 8",
    "sg:city":"Hermagor",
    "sg:orig_category":"Spenglereien",
    "sg:phone":"+43 4282 38700",
    "sg:postcode":"9620",
    "sg:province":"K\u00e4rnten",
    "wof:name":"Moser Hansj\u00f6rg",
    "wof:placetype":"venue"
},
  "geometry": {"coordinates":[13.3656196594,46.6284103394],"type":"Point"}
}