{
  "type": "Feature",
  "properties": {
    "addr:full":"Conrad-von-H\u00f6tzendorf-Str 29 Voitsberg Steiermark 8570",
    "addr:housenumber":"29",
    "addr:postcode":"8570",
    "addr:street":"Conrad-Von-Hoetzendorf-Str",
    "iso:country":"AT",
    "sg:address":"Conrad-von-H\u00f6tzendorf-Str 29",
    "sg:city":"Voitsberg",
    "sg:orig_category":"Politische Parteien",
    "sg:phone":"+43 4331 4222421",
    "sg:postcode":"8570",
    "sg:province":"Steiermark",
    "wof:name":"Kommunistische Partei \u00f6sterreichs",
    "wof:placetype":"venue"
},
  "geometry": {"coordinates":[15.1419010162,47.0523033142],"type":"Point"}
}