{
  "type": "Feature",
  "properties": {
    "addr:full":"Ruflinger Strasse 97 Leonding Ober\u00f6sterreich 4060",
    "addr:housenumber":"97",
    "addr:postcode":"4060",
    "addr:street":"Ruflinger Strasse",
    "iso:country":"AT",
    "sg:address":"Ruflinger Strasse 97",
    "sg:city":"Leonding",
    "sg:orig_category":"Anti-Mould Coatings",
    "sg:phone":"+43 732 670668",
    "sg:postcode":"4060",
    "sg:province":"Ober\u00f6sterreich",
    "sg:website":"malerei-kutsam.at",
    "wof:name":"KUTSAM Malereibetrieb GmbH",
    "wof:placetype":"venue"
},
  "geometry": {"coordinates":[14.2425699234,48.2767105103],"type":"Point"}
}