{
  "type": "Feature",
  "properties": {
    "iso:country":"AT",
    "sg:address":"Ufer 3/2/2",
    "sg:city":"Wallsee",
    "sg:orig_category":"Friseure U Frisiersalons",
    "sg:phone":"+43 664 5246902",
    "sg:postcode":"3313",
    "sg:province":"Nieder\u00f6sterreich",
    "wof:name":"Wieser Manuela",
    "wof:placetype":"venue"
},
  "geometry": {"coordinates":[14.7188100815,48.1655082703],"type":"Point"}
}