{
  "type": "Feature",
  "properties": {
    "addr:full":"Nr 53 St. Jodok am Brenner Tirol 6154",
    "addr:postcode":"6154",
    "addr:street":"Nr 53;Tirol",
    "iso:country":"AT",
    "sg:address":"Nr 53",
    "sg:city":"St. Jodok am Brenner",
    "sg:orig_category":"Volksschulen",
    "sg:phone":"+43 5279 5467",
    "sg:postcode":"6154",
    "sg:province":"Tirol",
    "wof:name":"Volksschule",
    "wof:placetype":"venue"
},
  "geometry": {"coordinates":[11.5639219284,47.079044342],"type":"Point"}
}