{
  "type": "Feature",
  "properties": {
    "addr:full":"Aspanger Str 252 Pitten Nieder\u00f6sterreich 2823",
    "addr:housenumber":"252",
    "addr:postcode":"2823",
    "iso:country":"AT",
    "sg:address":"Aspanger Str 252",
    "sg:city":"Pitten",
    "sg:orig_category":"Papier / Erzeugung U Gro\u00c3\u0178handel",
    "sg:phone":"+43 4326 278000",
    "sg:postcode":"2823",
    "sg:province":"Nieder\u00f6sterreich",
    "wof:name":"Hamburger W AG",
    "wof:placetype":"venue"
},
  "geometry": {"coordinates":[16.1872062683,47.7157440186],"type":"Point"}
}