{
  "type": "Feature",
  "properties": {
    "iso:country":"AT",
    "sg:address":"Eberschwanger Str 74",
    "sg:city":"Ried im Innkreis",
    "sg:orig_category":"Massagen",
    "sg:phone":"+43 7752 81446",
    "sg:postcode":"4910",
    "sg:province":"Ober\u00f6sterreich",
    "wof:name":"Gr\u00fcndl Erika - Standort Neuhofen 25",
    "wof:placetype":"venue"
},
  "geometry": {"coordinates":[13.5049648285,48.1930847168],"type":"Point"}
}