{
  "type": "Feature",
  "properties": {
    "addr:full":"Schlosserstr 6 Gr\u00f6dig Salzburg 5082",
    "addr:housenumber":"6",
    "addr:postcode":"5082",
    "addr:street":"Schlosserstr;Salzburg",
    "iso:country":"AT",
    "sg:address":"Schlosserstr 6",
    "sg:city":"Gr\u00f6dig",
    "sg:classifiers":[
        {
            "category":"Building & Trades",
            "subcategory":"Construction",
            "type":"Services"
        }
    ],
    "sg:phone":"+43 6246 75775",
    "sg:postcode":"5082",
    "sg:province":"Salzburg",
    "sg:tags":[
        "aggregate"
    ],
    "wof:name":"MAG-Motoren GesmbH",
    "wof:placetype":"venue"
},
  "geometry": {"coordinates":[-76.2684555054,37.4373283386],"type":"Point"}
}