{
  "type": "Feature",
  "properties": {
    "iso:country":"AT",
    "sg:address":"Siebenbrunnenfeldg 1d",
    "sg:city":"Wien",
    "sg:orig_category":"\u00c3\u201erzte / F Allgemeinmedizin",
    "sg:phone":"+43 1 5441375",
    "sg:postcode":"1050",
    "sg:province":"Wien",
    "wof:name":"Korsh Oleh Dr",
    "wof:placetype":"venue"
},
  "geometry": {"coordinates":[16.3560905457,48.1825828552],"type":"Point"}
}