{
  "type": "Feature",
  "properties": {
    "addr:full":"Zwettler Str 30 Oberneukirchen Ober\u00f6sterreich 4181",
    "addr:housenumber":"30",
    "addr:postcode":"4181",
    "addr:street":"Str",
    "iso:country":"AT",
    "sg:address":"Zwettler Str 30",
    "sg:city":"Oberneukirchen",
    "sg:orig_category":"Reifen U Reifendienste",
    "sg:phone":"+43 7212 7449",
    "sg:postcode":"4181",
    "sg:province":"Ober\u00f6sterreich",
    "wof:name":"Hartl Reifen- Kfz- und Zubeh\u00f6r",
    "wof:placetype":"venue"
},
  "geometry": {"coordinates":[14.2414617538,48.4657745361],"type":"Point"}
}