{
  "type": "Feature",
  "properties": {
    "addr:full":"Nesselweg 16  Dornbirn Vorarlberg 6850",
    "addr:housenumber":"16",
    "addr:postcode":"6850",
    "addr:street":"Nesselweg",
    "iso:country":"AT",
    "sg:address":"Nesselweg 16 ",
    "sg:city":"Dornbirn",
    "sg:classifiers":[
        {
            "category":"Building & Trades",
            "subcategory":"Plumbing",
            "type":"Services"
        }
    ],
    "sg:phone":"+43 5572 29169",
    "sg:postcode":"6850",
    "sg:province":"Vorarlberg",
    "sg:tags":[
        "supraregional",
        "gas"
    ],
    "wof:name":"Zortea Dornbirn",
    "wof:placetype":"venue"
},
  "geometry": {"coordinates":[9.7505264282,47.4255332947],"type":"Point"}
}