{
  "type": "Feature",
  "properties": {
    "addr:full":"Lindnerfeld 1 Kitzb\u00fchel Tirol 6370",
    "addr:housenumber":"1",
    "addr:postcode":"6370",
    "addr:street":"Lindnerfeld;Tirol",
    "iso:country":"AT",
    "sg:address":"Lindnerfeld 1",
    "sg:city":"Kitzb\u00fchel",
    "sg:orig_category":"Gesundheitsvorsorge",
    "sg:phone":"+43 5356 75337",
    "sg:postcode":"6370",
    "sg:province":"Tirol",
    "wof:name":"Winkler Walter",
    "wof:placetype":"venue"
},
  "geometry": {"coordinates":[12.4082660675,47.4381866455],"type":"Point"}
}