{
  "type": "Feature",
  "properties": {
    "addr:full":"Klafterreith 44 St. Johann am Walde Ober\u00f6sterreich 5242",
    "addr:housenumber":"44",
    "addr:postcode":"5242",
    "addr:street":"Klafterreith",
    "iso:country":"AT",
    "sg:address":"Klafterreith 44",
    "sg:city":"St. Johann am Walde",
    "sg:orig_category":"Isolierungen",
    "sg:phone":"+43 4377 4320022",
    "sg:postcode":"5242",
    "sg:province":"Ober\u00f6sterreich",
    "wof:name":"Fertigputze Haslinger GmbH",
    "wof:placetype":"venue"
},
  "geometry": {"coordinates":[13.3101940155,48.1161422729],"type":"Point"}
}