{
  "type": "Feature",
  "properties": {
    "addr:full":"Glaserg 4 A Wien Wien 1090",
    "addr:housenumber":"4 a",
    "addr:postcode":"1090",
    "addr:street":"Glaserg",
    "iso:country":"AT",
    "sg:address":"Glaserg 4 A",
    "sg:city":"Wien",
    "sg:orig_category":"Webereien U Spinnereien",
    "sg:phone":"+43 1 3199227",
    "sg:postcode":"1090",
    "sg:province":"Wien",
    "wof:name":"Atelier Vertico",
    "wof:placetype":"venue"
},
  "geometry": {"coordinates":[16.3624610901,48.2241249084],"type":"Point"}
}