{
  "type": "Feature",
  "properties": {
    "iso:country":"AT",
    "sg:address":"Reitschulg 2",
    "sg:city":"Graz",
    "sg:orig_category":"Waren Aller Art",
    "sg:phone":"+43 316 817717",
    "sg:postcode":"8010",
    "sg:province":"Steiermark",
    "sg:website":"www.ein-euro-shop.com",
    "wof:name":"Ein Euro Shop",
    "wof:placetype":"venue"
},
  "geometry": {"coordinates":[15.4438056946,47.0669822693],"type":"Point"}
}