{
  "type": "Feature",
  "properties": {
    "addr:full":"Alter Pl 6-7 Klagenfurt K\u00e4rnten 9020",
    "addr:housenumber":"6-7",
    "addr:postcode":"9020",
    "addr:street":"Alter Pl;Kaernten",
    "iso:country":"AT",
    "sg:address":"Alter Pl 6-7",
    "sg:city":"Klagenfurt",
    "sg:orig_category":"Drogerien",
    "sg:phone":"+43 463 5134770",
    "sg:postcode":"9020",
    "sg:province":"K\u00e4rnten",
    "wof:name":"dm drogerie markt GmbH",
    "wof:placetype":"venue"
},
  "geometry": {"coordinates":[14.3087682724,46.6254501343],"type":"Point"}
}