{
  "type": "Feature",
  "properties": {
    "iso:country":"AT",
    "sg:address":"Nr 46",
    "sg:city":"Geretsberg",
    "sg:orig_category":"Installationsunternehmen",
    "sg:phone":"+43 4377 487606",
    "sg:postcode":"5132",
    "sg:province":"Ober\u00f6sterreich",
    "sg:website":"zoeschg.com",
    "wof:name":"Z\u00f6schg Markus jun",
    "wof:placetype":"venue"
},
  "geometry": {"coordinates":[12.9375829697,48.0898628235],"type":"Point"}
}