{
  "type": "Feature",
  "properties": {
    "addr:full":"Hoher Nu\u00dfbaumweg 12 Eisenstadt Burgenland 7000",
    "addr:housenumber":"12",
    "addr:postcode":"7000",
    "addr:street":"Hoher Nussbaumweg",
    "iso:country":"AT",
    "sg:address":"Hoher Nu\u00dfbaumweg 12",
    "sg:city":"Eisenstadt",
    "sg:orig_category":"Exporteure U Importeure",
    "sg:phone":"+43 2682 72785",
    "sg:postcode":"7000",
    "sg:province":"Burgenland",
    "wof:name":"Contact Export-Import WarenhandelsgesmbH",
    "wof:placetype":"venue"
},
  "geometry": {"coordinates":[16.5288715363,47.8536567688],"type":"Point"}
}