{
  "type": "Feature",
  "properties": {
    "addr:full":"Rotensterng 22 Wien Wien 1020",
    "addr:housenumber":"22",
    "addr:postcode":"1020",
    "addr:street":"Rotensterng",
    "iso:country":"AT",
    "sg:address":"Rotensterng 22",
    "sg:city":"Wien",
    "sg:orig_category":"Bauunternehmen",
    "sg:phone":"+43 1 2128095",
    "sg:postcode":"1020",
    "sg:province":"Wien",
    "wof:name":"Newis Bau GmbH",
    "wof:placetype":"venue"
},
  "geometry": {"coordinates":[16.3839168549,48.2171783447],"type":"Point"}
}