{
  "type": "Feature",
  "properties": {
    "iso:country":"AT",
    "sg:address":"Nr 20",
    "sg:city":"Gastern",
    "sg:orig_category":"Webereien U Spinnereien",
    "sg:phone":"+43 2864 2221",
    "sg:postcode":"3852",
    "sg:province":"Nieder\u00f6sterreich",
    "wof:name":"Hirsch Gerhard",
    "wof:placetype":"venue"
},
  "geometry": {"coordinates":[147.14059448239999,-38.1040687561],"type":"Point"}
}