{
  "type": "Feature",
  "properties": {
    "iso:country":"AT",
    "sg:address":"Hauptstr 53",
    "sg:city":"Gaspoltshofen",
    "sg:orig_category":"Non-Classified Establishments",
    "sg:phone":"+43 5 91334232",
    "sg:postcode":"4673",
    "sg:province":"Ober\u00f6sterreich",
    "wof:name":"Gendarmerieposten",
    "wof:placetype":"venue"
},
  "geometry": {"coordinates":[13.735874176,48.1400299072],"type":"Point"}
}