{
  "type": "Feature",
  "properties": {
    "addr:full":"Rastenfeld 169 Rastenfeld Nieder\u00f6sterreich 3532",
    "addr:housenumber":"169",
    "addr:postcode":"3532",
    "addr:street":"Rastenfeld",
    "iso:country":"AT",
    "sg:address":"Rastenfeld 169",
    "sg:city":"Rastenfeld",
    "sg:classifiers":[
        {
            "category":"Train Station",
            "subcategory":"Light Rail",
            "type":"Transportation"
        }
    ],
    "sg:phone":"+43 2826 7726",
    "sg:postcode":"3532",
    "sg:province":"Nieder\u00f6sterreich",
    "sg:tags":[
        "twine",
        "baler"
    ],
    "sg:website":"waldland.at",
    "wof:name":"WALDLAND Faserproduktions GmbH",
    "wof:placetype":"venue"
},
  "geometry": {"coordinates":[15.3253240585,48.5598526001],"type":"Point"}
}