{
  "type": "Feature",
  "properties": {
    "addr:full":"Hauptpl 22 Frohnleiten Steiermark 8130",
    "addr:housenumber":"22",
    "addr:postcode":"8130",
    "addr:street":"Hauptpl",
    "iso:country":"AT",
    "sg:address":"Hauptpl 22",
    "sg:city":"Frohnleiten",
    "sg:orig_category":"Banken U Sparkassen",
    "sg:phone":"+43 4331 2625040",
    "sg:postcode":"8130",
    "sg:province":"Steiermark",
    "wof:name":"Volksbank Graz-Bruck regGenmbH",
    "wof:placetype":"venue"
},
  "geometry": {"coordinates":[15.3262786865,47.270816803],"type":"Point"}
}