{
  "type": "Feature",
  "properties": {
    "addr:full":"Hegerg 7 Wien Wien 1030",
    "addr:housenumber":"7",
    "addr:postcode":"1030",
    "addr:street":"Hegerg",
    "iso:country":"AT",
    "sg:address":"Hegerg 7",
    "sg:city":"Wien",
    "sg:orig_category":"Installationsunternehmen",
    "sg:phone":"+43 1 79861510",
    "sg:postcode":"1030",
    "sg:province":"Wien",
    "wof:name":"Air Medical Gase- und Apparate-VertriebsgesmbH",
    "wof:placetype":"venue"
},
  "geometry": {"coordinates":[16.3870811462,48.1918029785],"type":"Point"}
}