{
  "type": "Feature",
  "properties": {
    "addr:full":"Schwabenlandl 10 Ostermiething Ober\u00f6sterreich 5121",
    "addr:housenumber":"10",
    "addr:postcode":"5121",
    "addr:street":"Schwabenlandl",
    "iso:country":"AT",
    "sg:address":"Schwabenlandl 10",
    "sg:city":"Ostermiething",
    "sg:orig_category":"Pensionen / Privatzimmer",
    "sg:phone":"+43 4362 7885170",
    "sg:postcode":"5121",
    "sg:province":"Ober\u00f6sterreich",
    "sg:website":"reithof-piber.at",
    "wof:name":"Islandpferde Reithof Piber KEG",
    "wof:placetype":"venue"
},
  "geometry": {"coordinates":[12.7718238831,48.1021499634],"type":"Point"}
}