{
  "type": "Feature",
  "properties": {
    "addr:full":"Alois-Auer-Str 15 Wels Ober\u00f6sterreich 4600",
    "addr:housenumber":"15",
    "addr:postcode":"4600",
    "addr:street":"Alois-Auer-Str;Oberoesterreich",
    "iso:country":"AT",
    "sg:address":"Alois-Auer-Str 15",
    "sg:city":"Wels",
    "sg:orig_category":"Immobilienmakler",
    "sg:phone":"+43 664 1200030",
    "sg:postcode":"4600",
    "sg:province":"Ober\u00f6sterreich",
    "wof:name":"TOP-REAL ImmobilienprojektegesmbH",
    "wof:placetype":"venue"
},
  "geometry": {"coordinates":[14.0272483826,48.1629486084],"type":"Point"}
}