{
  "type": "Feature",
  "properties": {
    "iso:country":"AT",
    "sg:address":"Mayrhansenstrasse 6",
    "sg:city":"Leonding",
    "sg:classifiers":[
        {
            "category":"Building & Trades",
            "subcategory":"Electrical",
            "type":"Services"
        }
    ],
    "sg:phone":"+43 732 6707970",
    "sg:postcode":"4060",
    "sg:province":"Ober\u00f6sterreich",
    "sg:tags":[
        "installation"
    ],
    "sg:website":"nopp.at",
    "wof:name":"Josef Nopp KG",
    "wof:placetype":"venue"
},
  "geometry": {"coordinates":[14.2490587234,48.2785797119],"type":"Point"}
}