{
  "type": "Feature",
  "properties": {
    "iso:country":"AT",
    "sg:address":"Hohenstaufeng 6",
    "sg:city":"Graz",
    "sg:orig_category":"Autobusunternehmen",
    "sg:phone":"+43 316 72810",
    "sg:postcode":"8020",
    "sg:province":"Steiermark",
    "sg:website":"www.postbus.at",
    "wof:name":"\u00d6sterreichische Postbus AG",
    "wof:placetype":"venue"
},
  "geometry": {"coordinates":[15.4245414734,47.059425354],"type":"Point"}
}