{
  "type": "Feature",
  "properties": {
    "addr:full":"Neuberg 39 Filzmoos Salzburg 5532",
    "addr:housenumber":"39",
    "addr:postcode":"5532",
    "addr:street":"Neuberg;Salzburg",
    "iso:country":"AT",
    "sg:address":"Neuberg 39",
    "sg:city":"Filzmoos",
    "sg:orig_category":"Appartements / Ferienwohnungen",
    "sg:phone":"+43 6453 8543",
    "sg:postcode":"5532",
    "sg:province":"Salzburg",
    "wof:name":"Appartements Landhaus Kainhof",
    "wof:placetype":"venue"
},
  "geometry": {"coordinates":[13.5203046799,47.4333534241],"type":"Point"}
}