{
  "type": "Feature",
  "properties": {
    "addr:full":"Nr 291 Gleisdorf Steiermark 8200",
    "addr:postcode":"8200",
    "addr:street":"Nr 291",
    "iso:country":"AT",
    "sg:address":"Nr 291",
    "sg:city":"Gleisdorf",
    "sg:orig_category":"Innenarchitekten",
    "sg:phone":"+43 4331 123686310",
    "sg:postcode":"8200",
    "sg:province":"Steiermark",
    "wof:name":"Atelier Xaver - Farb- u Lichtgestaltung - Wintergarten",
    "wof:placetype":"venue"
},
  "geometry": {"coordinates":[15.6912050247,47.103477478],"type":"Point"}
}