{
  "type": "Feature",
  "properties": {
    "addr:full":"Nr 95 Strem Burgenland 7522",
    "addr:postcode":"7522",
    "addr:street":"Nr",
    "iso:country":"AT",
    "sg:address":"Nr 95",
    "sg:city":"Strem",
    "sg:orig_category":"Spenglereien",
    "sg:phone":"+43 3324 6508",
    "sg:postcode":"7522",
    "sg:province":"Burgenland",
    "wof:name":"Knasar Eduard",
    "wof:placetype":"venue"
},
  "geometry": {"coordinates":[16.4142494202,47.0441932678],"type":"Point"}
}