{
  "type": "Feature",
  "properties": {
    "addr:full":"Hauptstr 47 Petronell Nieder\u00f6sterreich 2404",
    "addr:housenumber":"47",
    "addr:postcode":"2404",
    "addr:street":"Hauptstr;Niederoesterreich",
    "iso:country":"AT",
    "sg:address":"Hauptstr 47",
    "sg:city":"Petronell",
    "sg:orig_category":"Weine / Einzelhandel",
    "sg:phone":"+43 2163 2818",
    "sg:postcode":"2404",
    "sg:province":"Nieder\u00f6sterreich",
    "wof:name":"Johann Dietrich",
    "wof:placetype":"venue"
},
  "geometry": {"coordinates":[16.869638443,48.113735199],"type":"Point"}
}