{
  "type": "Feature",
  "properties": {
    "addr:full":"Hochk\u00f6nig Bundesstr 223 M\u00fchlbach am Hochk\u00f6nig Salzburg 5505",
    "addr:housenumber":"223",
    "addr:postcode":"5505",
    "addr:street":"Muehlbach Am Hochkoenig Salzburg",
    "iso:country":"AT",
    "sg:address":"Hochk\u00f6nig Bundesstr 223",
    "sg:city":"M\u00fchlbach am Hochk\u00f6nig",
    "sg:orig_category":"Sonnenstudios",
    "sg:phone":"+43 6467 7748",
    "sg:postcode":"5505",
    "sg:province":"Salzburg",
    "wof:name":"Sparber Marion",
    "wof:placetype":"venue"
},
  "geometry": {"coordinates":[-82.265586853,37.4296951294],"type":"Point"}
}