{
  "type": "Feature",
  "properties": {
    "iso:country":"AT",
    "sg:address":"Ro\u00dfmarkt 11",
    "sg:city":"Grieskirchen",
    "sg:orig_category":"Tabaktrafiken",
    "sg:phone":"+43 7248 62525",
    "sg:postcode":"4710",
    "sg:province":"Ober\u00f6sterreich",
    "wof:name":"Pointl Josef",
    "wof:placetype":"venue"
},
  "geometry": {"coordinates":[13.8257322311,48.2358856201],"type":"Point"}
}