{
  "type": "Feature",
  "properties": {
    "addr:full":"Churer Str 12 Hohenems Vorarlberg 6845",
    "addr:postcode":"6845",
    "addr:street":"Str 12",
    "iso:country":"AT",
    "sg:address":"Churer Str 12",
    "sg:city":"Hohenems",
    "sg:orig_category":"Fenster",
    "sg:phone":"+43 5576 42142",
    "sg:postcode":"6845",
    "sg:province":"Vorarlberg",
    "wof:name":"K\u00f6rver Fenstertechnik",
    "wof:placetype":"venue"
},
  "geometry": {"coordinates":[9.6647949219,47.3556594849],"type":"Point"}
}