{
  "type": "Feature",
  "properties": {
    "addr:full":"Posthofstr 50 Linz Ober\u00f6sterreich 4020",
    "addr:housenumber":"50",
    "addr:postcode":"4020",
    "addr:street":"Posthofstr",
    "iso:country":"AT",
    "sg:address":"Posthofstr 50",
    "sg:city":"Linz",
    "sg:orig_category":"Politische Parteien",
    "sg:phone":"+43 732 778355",
    "sg:postcode":"4020",
    "sg:province":"Ober\u00f6sterreich",
    "wof:name":"Sozialdemokratische Partei \u00f6sterreichs -Sektion Schiffswerft",
    "wof:placetype":"venue"
},
  "geometry": {"coordinates":[14.3113126755,48.3114128113],"type":"Point"}
}