{
  "type": "Feature",
  "properties": {
    "addr:full":"Nr 152 Nappersdorf Nieder\u00f6sterreich 2023",
    "addr:postcode":"2023",
    "addr:street":"Nr 152 Nappersdorf",
    "iso:country":"AT",
    "sg:address":"Nr 152",
    "sg:city":"Nappersdorf",
    "sg:orig_category":"Volksschulen",
    "sg:phone":"+43 2953 26300",
    "sg:postcode":"2023",
    "sg:province":"Nieder\u00f6sterreich",
    "wof:name":"Volksschule",
    "wof:placetype":"venue"
},
  "geometry": {"coordinates":[16.1849422455,48.6285476685],"type":"Point"}
}