{
  "type": "Feature",
  "properties": {
    "addr:full":"Leopold-Scheel-Weg 1 Feldkirch Vorarlberg 6800",
    "addr:housenumber":"1",
    "addr:postcode":"6800",
    "addr:street":"Leopold-Scheel-Weg",
    "iso:country":"AT",
    "sg:address":"Leopold-Scheel-Weg 1",
    "sg:city":"Feldkirch",
    "sg:classifiers":[
        {
            "category":"Shopping",
            "subcategory":"Thrift Store",
            "type":"Retail Goods"
        }
    ],
    "sg:phone":"+43 5522 35230",
    "sg:postcode":"6800",
    "sg:province":"Vorarlberg",
    "sg:tags":[
        "second-hand-shops"
    ],
    "wof:name":"Sec and Boutique & B\u00fcgelservice",
    "wof:placetype":"venue"
},
  "geometry": {"coordinates":[9.5864992142,47.2312431335],"type":"Point"}
}