{
  "type": "Feature",
  "properties": {
    "addr:full":"Donaustadtstr 1 Wien Wien 1220",
    "addr:housenumber":"1",
    "addr:postcode":"1220",
    "addr:street":"Donaustadtstr",
    "iso:country":"AT",
    "sg:address":"Donaustadtstr 1",
    "sg:city":"Wien",
    "sg:orig_category":"Textilreinigung",
    "sg:phone":"+43 1 2034728",
    "sg:postcode":"1220",
    "sg:province":"Wien",
    "wof:name":"Putzerei und Textilpflege GesmbH",
    "wof:placetype":"venue"
},
  "geometry": {"coordinates":[16.4354743958,48.2415313721],"type":"Point"}
}