{
  "type": "Feature",
  "properties": {
    "iso:country":"AT",
    "sg:address":"Rokitanskygasse 3",
    "sg:city":"Wien",
    "sg:classifiers":[
        {
            "category":"Military Area",
            "subcategory":"Air Force Base",
            "type":"Public Place"
        }
    ],
    "sg:phone":"+43 1 4862235",
    "sg:postcode":"1170",
    "sg:province":"Wien",
    "sg:tags":[
        "assembly",
        "furniture"
    ],
    "wof:name":"Rudolf Huber",
    "wof:placetype":"venue"
},
  "geometry": {"coordinates":[16.3281269073,48.2207794189],"type":"Point"}
}