{
  "type": "Feature",
  "properties": {
    "addr:full":"Wipfing 30 Eberstalzell Ober\u00f6sterreich 4653",
    "addr:housenumber":"30",
    "addr:postcode":"4653",
    "addr:street":"Wipfing",
    "iso:country":"AT",
    "sg:address":"Wipfing 30",
    "sg:city":"Eberstalzell",
    "sg:orig_category":"Bauunternehmen",
    "sg:phone":"+43 7241 28029",
    "sg:postcode":"4653",
    "sg:province":"Ober\u00f6sterreich",
    "wof:name":"ANHO Bau GesmbH",
    "wof:placetype":"venue"
},
  "geometry": {"coordinates":[14.0055446625,48.0433311462],"type":"Point"}
}