{
  "type": "Feature",
  "properties": {
    "iso:country":"AT",
    "sg:address":"Nr 6",
    "sg:city":"Liezen",
    "sg:orig_category":"Abwassertechnik",
    "sg:phone":"+43 3612 30284",
    "sg:postcode":"8940",
    "sg:province":"Steiermark",
    "wof:name":"KSA Anlagenbau GmbH",
    "wof:placetype":"venue"
},
  "geometry": {"coordinates":[14.2413349152,47.5672111511],"type":"Point"}
}