{
  "type": "Feature",
  "properties": {
    "iso:country":"AT",
    "sg:address":"Wolkersdorfer Str 51",
    "sg:city":"Pillichsdorf",
    "sg:orig_category":"Telekommunikation",
    "sg:phone":"+43 2245 838900",
    "sg:postcode":"2211",
    "sg:province":"Nieder\u00f6sterreich",
    "wof:name":"hoc.it TK & IT Consulting",
    "wof:placetype":"venue"
},
  "geometry": {"coordinates":[16.527973175,48.3664741516],"type":"Point"}
}