{
  "type": "Feature",
  "properties": {
    "iso:country":"AT",
    "sg:address":"Nr 111",
    "sg:city":"Radstadt",
    "sg:orig_category":"Natursteine U -Platten",
    "sg:phone":"+43 6454 8406",
    "sg:postcode":"5550",
    "sg:province":"Salzburg",
    "wof:name":"R E S Com Edith Schmidt",
    "wof:placetype":"venue"
},
  "geometry": {"coordinates":[13.4658269882,47.3852462769],"type":"Point"}
}