{
  "type": "Feature",
  "properties": {
    "addr:full":"Schulg 19 Horitschon Burgenland 7312",
    "addr:housenumber":"19",
    "addr:postcode":"7312",
    "addr:street":"Schulg",
    "iso:country":"AT",
    "sg:address":"Schulg 19",
    "sg:city":"Horitschon",
    "sg:orig_category":"Volksschulen",
    "sg:phone":"+43 2610 42341",
    "sg:postcode":"7312",
    "sg:province":"Burgenland",
    "wof:name":"Volksschule",
    "wof:placetype":"venue"
},
  "geometry": {"coordinates":[16.5458145142,47.5875015259],"type":"Point"}
}