{
  "type": "Feature",
  "properties": {
    "addr:full":"Leobner Str 18 Niklasdorf Steiermark 8712",
    "addr:housenumber":"18",
    "addr:postcode":"8712",
    "addr:street":"Str",
    "iso:country":"AT",
    "sg:address":"Leobner Str 18",
    "sg:city":"Niklasdorf",
    "sg:orig_category":"Schlossereien",
    "sg:phone":"+43 3842 813220",
    "sg:postcode":"8712",
    "sg:province":"Steiermark",
    "wof:name":"Buchebner Adolf",
    "wof:placetype":"venue"
},
  "geometry": {"coordinates":[15.1640434265,47.3968086243],"type":"Point"}
}