{
  "type": "Feature",
  "properties": {
    "iso:country":"AT",
    "sg:address":"Feldanger 9",
    "sg:city":"Neuzeug",
    "sg:classifiers":[
        {
            "category":"Taxi",
            "type":"Transportation"
        }
    ],
    "sg:phone":"+43 4372 592792",
    "sg:postcode":"4523",
    "sg:province":"Ober\u00f6sterreich",
    "sg:tags":[
        "personentransporte",
        "u"
    ],
    "wof:name":"Raab-Taxi",
    "wof:placetype":"venue"
},
  "geometry": {"coordinates":[14.3221750259,48.0261383057],"type":"Point"}
}