{
  "type": "Feature",
  "properties": {
    "addr:full":"Schweglerstr 10 Wien Wien 1150",
    "addr:housenumber":"10",
    "addr:postcode":"1150",
    "addr:street":"Schweglerstr",
    "iso:country":"AT",
    "sg:address":"Schweglerstr 10",
    "sg:city":"Wien",
    "sg:orig_category":"Installationsunternehmen",
    "sg:phone":"+43 1 98233400",
    "sg:postcode":"1150",
    "sg:province":"Wien",
    "wof:name":"Braunb\u00f6ck GmbH & Co KG",
    "wof:placetype":"venue"
},
  "geometry": {"coordinates":[16.3293151855,48.1969795227],"type":"Point"}
}