{
  "type": "Feature",
  "properties": {
    "addr:full":"Alte Str 21 Oberwart Burgenland 7400",
    "addr:housenumber":"21",
    "addr:postcode":"7400",
    "addr:street":"Alte Str",
    "iso:country":"AT",
    "sg:address":"Alte Str 21",
    "sg:city":"Oberwart",
    "sg:orig_category":"Steinmetzbetriebe",
    "sg:phone":"+43 3352 38415",
    "sg:postcode":"7400",
    "sg:province":"Burgenland",
    "wof:name":"Jandl Stein",
    "wof:placetype":"venue"
},
  "geometry": {"coordinates":[16.2131557465,47.2876167297],"type":"Point"}
}