{
  "type": "Feature",
  "properties": {
    "iso:country":"AT",
    "sg:address":"Bahnstr 5",
    "sg:city":"Brunn am Gebirge",
    "sg:orig_category":"Steuerberatung",
    "sg:phone":"+43 4322 36317820",
    "sg:postcode":"2345",
    "sg:province":"Nieder\u00f6sterreich",
    "wof:name":"Morak Julius & Mag Franz Harrand Wirtschaftstreuhand GmbH & Co KEG Steuerberatungsgesell.",
    "wof:placetype":"venue"
},
  "geometry": {"coordinates":[16.286239624,48.1052818298],"type":"Point"}
}