{
  "type": "Feature",
  "properties": {
    "addr:full":"Marktpl 18 Heiligenkreuz am Waasen Steiermark 8081",
    "addr:housenumber":"18",
    "addr:postcode":"8081",
    "addr:street":"Marktpl",
    "iso:country":"AT",
    "sg:address":"Marktpl 18",
    "sg:city":"Heiligenkreuz am Waasen",
    "sg:orig_category":"Friseure U Frisiersalons",
    "sg:phone":"+43 4331 342264",
    "sg:postcode":"8081",
    "sg:province":"Steiermark",
    "wof:name":"Hofer Karin",
    "wof:placetype":"venue"
},
  "geometry": {"coordinates":[15.5848884583,46.9565734863],"type":"Point"}
}