{
  "type": "Feature",
  "properties": {
    "iso:country":"AT",
    "sg:city":"Geiersberg",
    "sg:orig_category":"Feuerwehren",
    "sg:phone":"+43 7732 3459",
    "sg:postcode":"4922",
    "sg:province":"Ober\u00f6sterreich",
    "wof:name":"Freiwillige Feuerwehr Pramerdorf",
    "wof:placetype":"venue"
},
  "geometry": {"coordinates":[13.6053323746,48.1988792419],"type":"Point"}
}