{
  "type": "Feature",
  "properties": {
    "addr:full":"Linzer Bundesstr 40-42 Gnigl Salzburg 5023",
    "addr:housenumber":"40-42",
    "addr:postcode":"5023",
    "iso:country":"AT",
    "sg:address":"Linzer Bundesstr 40-42",
    "sg:city":"Gnigl",
    "sg:orig_category":"Immobilienverwaltungen",
    "sg:phone":"+43 662 641422",
    "sg:postcode":"5023",
    "sg:province":"Salzburg",
    "wof:name":"Haas & Haas Immobilien GesmbH",
    "wof:placetype":"venue"
},
  "geometry": {"coordinates":[13.0690135956,47.8144760132],"type":"Point"}
}