{
  "type": "Feature",
  "properties": {
    "addr:full":"G\u00e4rtnerg 12 Wien Wien 1030",
    "addr:housenumber":"12",
    "addr:postcode":"1030",
    "addr:street":"Gaertnerg",
    "iso:country":"AT",
    "sg:address":"G\u00e4rtnerg 12",
    "sg:city":"Wien",
    "sg:orig_category":"Waschmaschinen / Einzelhandel",
    "sg:phone":"+43 1 7136335",
    "sg:postcode":"1030",
    "sg:province":"Wien",
    "wof:name":"Waitzinger GesmbH - Eudora Ansicht und Vertrieb",
    "wof:placetype":"venue"
},
  "geometry": {"coordinates":[16.3876190186,48.2055892944],"type":"Point"}
}