{
  "type": "Feature",
  "properties": {
    "addr:full":"Wegscheide 3 Weiz Steiermark 8160",
    "addr:housenumber":"3",
    "addr:postcode":"8160",
    "addr:street":"Wegscheide",
    "iso:country":"AT",
    "sg:address":"Wegscheide 3",
    "sg:city":"Weiz",
    "sg:orig_category":"Politische Parteien",
    "sg:phone":"+43 3172 38710",
    "sg:postcode":"8160",
    "sg:province":"Steiermark",
    "wof:name":"Freiheitliche Partei \u00f6sterreichs (FP\u00f6)",
    "wof:placetype":"venue"
},
  "geometry": {"coordinates":[15.6394491196,47.2208366394],"type":"Point"}
}