{
  "type": "Feature",
  "properties": {
    "addr:full":"Untere Hauptstrasse 30 Maria Lanzendorf Nieder\u00f6sterreich 2326",
    "addr:housenumber":"30",
    "addr:postcode":"2326",
    "addr:street":"Untere Hauptstrasse",
    "iso:country":"AT",
    "sg:address":"Untere Hauptstrasse 30",
    "sg:city":"Maria Lanzendorf",
    "sg:classifiers":[
        {
            "category":"Manufacturing",
            "subcategory":"Motor Vehicles & Parts",
            "type":"Manufacturing & Wholesale Goods"
        }
    ],
    "sg:phone":"+43 2235 42676",
    "sg:postcode":"2326",
    "sg:province":"Nieder\u00f6sterreich",
    "sg:tags":[
        "metal",
        "sheet",
        "bent"
    ],
    "wof:name":"Franz Lipkovics",
    "wof:placetype":"venue"
},
  "geometry": {"coordinates":[16.4461288452,48.1123199463],"type":"Point"}
}