{
  "type": "Feature",
  "properties": {
    "addr:full":"Makartstr 51 Traun Ober\u00f6sterreich 4050",
    "addr:housenumber":"51",
    "addr:postcode":"4050",
    "addr:street":"Makartstr",
    "iso:country":"AT",
    "sg:address":"Makartstr 51",
    "sg:city":"Traun",
    "sg:classifiers":[
        {
            "category":"Taxi",
            "type":"Transportation"
        }
    ],
    "sg:phone":"+43 4372 2962266",
    "sg:postcode":"4050",
    "sg:province":"Ober\u00f6sterreich",
    "sg:tags":[
        "personentransporte",
        "u"
    ],
    "wof:name":"Schaufler Emil",
    "wof:placetype":"venue"
},
  "geometry": {"coordinates":[14.2737350464,48.2342224121],"type":"Point"}
}