{
  "type": "Feature",
  "properties": {
    "addr:full":"Hartkirchen Ober\u00f6sterreich 4081",
    "addr:postcode":"4081",
    "iso:country":"AT",
    "sg:city":"Hartkirchen",
    "sg:orig_category":"Feuerwehren",
    "sg:phone":"+43 7273 8438",
    "sg:postcode":"4081",
    "sg:province":"Ober\u00f6sterreich",
    "wof:name":"Freiwillige Feuerwehr Hilkering Hachlham",
    "wof:placetype":"venue"
},
  "geometry": {"coordinates":[13.9747800827,48.3721885681],"type":"Point"}
}