{
  "type": "Feature",
  "properties": {
    "addr:full":"Industriestr 1 Sollenau Nieder\u00f6sterreich 2601",
    "addr:housenumber":"1",
    "addr:postcode":"2601",
    "addr:street":"Industriestr",
    "iso:country":"AT",
    "sg:address":"Industriestr 1",
    "sg:city":"Sollenau",
    "sg:orig_category":"Lastkraftwagen",
    "sg:phone":"+43 2628 47465",
    "sg:postcode":"2601",
    "sg:province":"Nieder\u00f6sterreich",
    "wof:name":"TRANS-TECH HandelsgmbH",
    "wof:placetype":"venue"
},
  "geometry": {"coordinates":[16.2550983429,47.9067878723],"type":"Point"}
}