{
  "type": "Feature",
  "properties": {
    "addr:full":"Altmannsdorfer Str 249 Wien Wien 1230",
    "addr:housenumber":"249",
    "addr:postcode":"1230",
    "addr:street":"Str",
    "iso:country":"AT",
    "sg:address":"Altmannsdorfer Str 249",
    "sg:city":"Wien",
    "sg:orig_category":"Elektroinstallationsunternehmen",
    "sg:phone":"+43 4366 49829587",
    "sg:postcode":"1230",
    "sg:province":"Wien",
    "wof:name":"Heindl Johann",
    "wof:placetype":"venue"
},
  "geometry": {"coordinates":[16.3225498199,48.1464118958],"type":"Point"}
}