{
  "type": "Feature",
  "properties": {
    "addr:full":"Rohrbacher Str 10 Korneuburg Nieder\u00f6sterreich 2100",
    "addr:postcode":"2100",
    "addr:street":"Str 10",
    "iso:country":"AT",
    "sg:address":"Rohrbacher Str 10",
    "sg:city":"Korneuburg",
    "sg:orig_category":"Banken U Sparkassen",
    "sg:phone":"+43 4322 62662310",
    "sg:postcode":"2100",
    "sg:province":"Nieder\u00f6sterreich",
    "wof:name":"Sparkasse der Stadt Korneuburg",
    "wof:placetype":"venue"
},
  "geometry": {"coordinates":[16.3210144043,48.3787841797],"type":"Point"}
}