{
  "type": "Feature",
  "properties": {
    "iso:country":"AT",
    "sg:address":"Radetzkystr 31",
    "sg:city":"Wien",
    "sg:orig_category":"Ambulatorien",
    "sg:phone":"+43 1 7133788",
    "sg:postcode":"1030",
    "sg:province":"Wien",
    "wof:name":"Anton Proksch Institut",
    "wof:placetype":"venue"
},
  "geometry": {"coordinates":[16.3908023834,48.2125320435],"type":"Point"}
}