{
  "type": "Feature",
  "properties": {
    "addr:full":"Lange Str 364 Langegg Nieder\u00f6sterreich 3872",
    "addr:housenumber":"364",
    "addr:postcode":"3872",
    "addr:street":"Lange Str;Langegg Niederoesterreich",
    "iso:country":"AT",
    "sg:address":"Lange Str 364",
    "sg:city":"Langegg",
    "sg:classifiers":[
        {
            "category":"Professional",
            "subcategory":"Computer Services",
            "type":"Services"
        }
    ],
    "sg:phone":"+43 2862 5367121",
    "sg:postcode":"3872",
    "sg:province":"Nieder\u00f6sterreich",
    "sg:tags":[
        "software"
    ],
    "wof:name":"RZA Rechenzentrum Amaliendorf GmbH",
    "wof:placetype":"venue"
},
  "geometry": {"coordinates":[15.085814476,48.8351364136],"type":"Point"}
}