{
  "type": "Feature",
  "properties": {
    "addr:full":"Uferstr 32 Innsbruck Tirol 6020",
    "addr:housenumber":"32",
    "addr:postcode":"6020",
    "addr:street":"Uferstr;Tirol",
    "iso:country":"AT",
    "sg:address":"Uferstr 32",
    "sg:city":"Innsbruck",
    "sg:orig_category":"Tonstudios",
    "sg:phone":"+43 512 285119",
    "sg:postcode":"6020",
    "sg:province":"Tirol",
    "wof:name":"Str\u00f6her Hanno",
    "wof:placetype":"venue"
},
  "geometry": {"coordinates":[11.3729028702,47.2553100586],"type":"Point"}
}