{
  "type": "Feature",
  "properties": {
    "addr:full":"Fesslers 17 Hohenweiler Vorarlberg 6914",
    "addr:housenumber":"17",
    "addr:postcode":"6914",
    "addr:street":"Fesslers",
    "iso:country":"AT",
    "sg:address":"Fesslers 17",
    "sg:city":"Hohenweiler",
    "sg:orig_category":"Handelsagenturen",
    "sg:phone":"+43 5573 84695",
    "sg:postcode":"6914",
    "sg:province":"Vorarlberg",
    "wof:name":"Bocek Ingrid",
    "wof:placetype":"venue"
},
  "geometry": {"coordinates":[9.7717657089,47.5731887817],"type":"Point"}
}