{
  "type": "Feature",
  "properties": {
    "addr:full":"Nr 106 St. Nikolai im Sausal Steiermark 8505",
    "addr:postcode":"8505",
    "addr:street":"Nr 106",
    "iso:country":"AT",
    "sg:address":"Nr 106",
    "sg:city":"St. Nikolai im Sausal",
    "sg:orig_category":"Appartements / Ferienwohnungen",
    "sg:phone":"+43 4331 842756",
    "sg:postcode":"8505",
    "sg:province":"Steiermark",
    "wof:name":"Schaden Franz u Klaudia",
    "wof:placetype":"venue"
},
  "geometry": {"coordinates":[-103.11498260499999,33.7812652588],"type":"Point"}
}