{
  "type": "Feature",
  "properties": {
    "addr:full":"Bahnhofstr 47 Hausmening Nieder\u00f6sterreich 3363",
    "addr:housenumber":"47",
    "addr:postcode":"3363",
    "addr:street":"Bahnhofstr",
    "iso:country":"AT",
    "sg:address":"Bahnhofstr 47",
    "sg:city":"Hausmening",
    "sg:orig_category":"Dachdeckereien",
    "sg:phone":"+43 4374 7553010",
    "sg:postcode":"3363",
    "sg:province":"Nieder\u00f6sterreich",
    "wof:name":"Bruckner Erwin",
    "wof:placetype":"venue"
},
  "geometry": {"coordinates":[14.8153438568,48.0717124939],"type":"Point"}
}