{
  "type": "Feature",
  "properties": {
    "addr:full":"Schleipfweg 23 Rankweil Vorarlberg 6830",
    "addr:housenumber":"23",
    "addr:postcode":"6830",
    "addr:street":"Schleipfweg",
    "iso:country":"AT",
    "sg:address":"Schleipfweg 23",
    "sg:city":"Rankweil",
    "sg:orig_category":"Bastelbedarf",
    "sg:phone":"+43 5522 47240",
    "sg:postcode":"6830",
    "sg:province":"Vorarlberg",
    "wof:name":"BASTELBOX - Scheier Manuela",
    "wof:placetype":"venue"
},
  "geometry": {"coordinates":[9.632976532,47.2737464905],"type":"Point"}
}