{
  "type": "Feature",
  "properties": {
    "iso:country":"AT",
    "sg:address":"Ludwig-Walter-Str 29",
    "sg:city":"Villach",
    "sg:orig_category":"Politische Parteien",
    "sg:phone":"+43 4242 34275",
    "sg:postcode":"9500",
    "sg:province":"K\u00e4rnten",
    "wof:name":"KP\u00f6 Villach-Sankt Agathen BezLtg Villach",
    "wof:placetype":"venue"
},
  "geometry": {"coordinates":[13.8528003693,46.6078720093],"type":"Point"}
}