{
  "type": "Feature",
  "properties": {
    "addr:full":"Untere Augartenstr 37/6 Wien Wien 1020",
    "addr:housenumber":"37 / 6",
    "addr:postcode":"1020",
    "addr:street":"Untere Augartenstr",
    "iso:country":"AT",
    "sg:address":"Untere Augartenstr 37/6",
    "sg:city":"Wien",
    "sg:orig_category":"\u00c3\u201erzte / F Allgemeinmedizin",
    "sg:phone":"+43 1 3323684",
    "sg:postcode":"1020",
    "sg:province":"Wien",
    "wof:name":"Sedlacek Gabriela Dr",
    "wof:placetype":"venue"
},
  "geometry": {"coordinates":[16.3746299744,48.2224235535],"type":"Point"}
}