{
  "type": "Feature",
  "properties": {
    "addr:full":"Himberger Strasse 17-19 Wien Wien 1100",
    "addr:postcode":"17-19;1100",
    "addr:street":"Himberger Strasse",
    "iso:country":"AT",
    "sg:address":"Himberger Strasse 17-19",
    "sg:city":"Wien",
    "sg:classifiers":[
        {
            "category":"Utilities",
            "subcategory":"Natural Gas",
            "type":"Services"
        }
    ],
    "sg:phone":"+43 1 68851960",
    "sg:postcode":"1100",
    "sg:province":"Wien",
    "sg:tags":[
        "bathroom",
        "cock",
        "fitting"
    ],
    "sg:website":"janacek.at",
    "wof:name":"Janacek Ges.m.b.H.",
    "wof:placetype":"venue"
},
  "geometry": {"coordinates":[16.382774353,48.1437492371],"type":"Point"}
}