{
  "type": "Feature",
  "properties": {
    "addr:full":"Linzer Str 61 Freistadt Ober\u00f6sterreich 4240",
    "addr:housenumber":"61",
    "addr:postcode":"4240",
    "addr:street":"Linzer Str",
    "iso:country":"AT",
    "sg:address":"Linzer Str 61",
    "sg:city":"Freistadt",
    "sg:classifiers":[
        {
            "category":"Taxi",
            "type":"Transportation"
        }
    ],
    "sg:phone":"+43 4366 45132324",
    "sg:postcode":"4240",
    "sg:province":"Ober\u00f6sterreich",
    "sg:tags":[
        "personentransporte",
        "u"
    ],
    "wof:name":"Kastl Gerhard Taxi-Mietwagen u Krankentransporte",
    "wof:placetype":"venue"
},
  "geometry": {"coordinates":[14.5034446716,48.4974594116],"type":"Point"}
}