{
  "type": "Feature",
  "properties": {
    "addr:full":"Nr 4 Erlauf Nieder\u00f6sterreich 3253",
    "addr:postcode":"3253",
    "addr:street":"Nr;Erlauf",
    "iso:country":"AT",
    "sg:address":"Nr 4",
    "sg:city":"Erlauf",
    "sg:orig_category":"Transportunternehmen",
    "sg:phone":"+43 2757 54188",
    "sg:postcode":"3253",
    "sg:province":"Nieder\u00f6sterreich",
    "wof:name":"Preitensteiner & H\u00f6rhan Transport GmbH",
    "wof:placetype":"venue"
},
  "geometry": {"coordinates":[15.1851453781,48.1843452454],"type":"Point"}
}