{
  "type": "Feature",
  "properties": {
    "iso:country":"AT",
    "sg:address":"Sengsschmiedstrasse 4",
    "sg:city":"Kirchdorf an der Krems",
    "sg:classifiers":[
        {
            "category":"Building & Trades",
            "subcategory":"Plumbing",
            "type":"Services"
        }
    ],
    "sg:phone":"+43 7582 612110",
    "sg:postcode":"4560",
    "sg:province":"Ober\u00f6sterreich",
    "sg:tags":[
        "tub",
        "bath"
    ],
    "wof:name":"Ing. Dietmar WASER GmbH",
    "wof:placetype":"venue"
},
  "geometry": {"coordinates":[14.0811481476,47.927116394],"type":"Point"}
}