{
  "type": "Feature",
  "properties": {
    "iso:country":"AT",
    "sg:address":"K\u00e4rntner Str 58",
    "sg:city":"Knittelfeld",
    "sg:orig_category":"Tankstellen",
    "sg:phone":"+43 3512 71939",
    "sg:postcode":"8720",
    "sg:province":"Steiermark",
    "wof:name":"JET Tankstelle",
    "wof:placetype":"venue"
},
  "geometry": {"coordinates":[14.8291902542,47.2139434814],"type":"Point"}
}