{
  "type": "Feature",
  "properties": {
    "addr:full":"Leonsteiner Str 12 Leonstein Ober\u00f6sterreich 4592",
    "addr:postcode":"4592",
    "addr:street":"Str;Oberoesterreich",
    "iso:country":"AT",
    "sg:address":"Leonsteiner Str 12",
    "sg:city":"Leonstein",
    "sg:orig_category":"Banken U Sparkassen",
    "sg:phone":"+43 4375 842771",
    "sg:postcode":"4592",
    "sg:province":"Ober\u00f6sterreich",
    "wof:name":"Raiffeisenbank Molln-Leonstein regGenmbH",
    "wof:placetype":"venue"
},
  "geometry": {"coordinates":[14.23117733,47.8949661255],"type":"Point"}
}