{
  "type": "Feature",
  "properties": {
    "addr:full":"Flachauwinkel 265 Flachau Salzburg 5542",
    "addr:housenumber":"265",
    "addr:postcode":"5542",
    "addr:street":"Flachau Salzburg",
    "iso:country":"AT",
    "sg:address":"Flachauwinkel 265",
    "sg:city":"Flachau",
    "sg:classifiers":[
        {
            "category":"Restaurant",
            "type":"Food & Drink"
        }
    ],
    "sg:phone":"+43 6457 3076",
    "sg:postcode":"5542",
    "sg:province":"Salzburg",
    "wof:name":"Restaurant Ofent\u00fcrl",
    "wof:placetype":"venue"
},
  "geometry": {"coordinates":[13.3902196884,47.3616104126],"type":"Point"}
}