{
  "type": "Feature",
  "properties": {
    "addr:full":"Hauptstr 12a Lockenhaus Burgenland 7442",
    "addr:housenumber":"12a",
    "addr:postcode":"7442",
    "addr:street":"Hauptstr",
    "iso:country":"AT",
    "sg:address":"Hauptstr 12a",
    "sg:city":"Lockenhaus",
    "sg:orig_category":"Tabaktrafiken",
    "sg:phone":"+43 2616 2910",
    "sg:postcode":"7442",
    "sg:province":"Burgenland",
    "wof:name":"Gilschwert Franz",
    "wof:placetype":"venue"
},
  "geometry": {"coordinates":[16.4181118011,47.4077033997],"type":"Point"}
}