{
  "type": "Feature",
  "properties": {
    "iso:country":"AT",
    "sg:address":"Kirschentalg 10b",
    "sg:city":"Innsbruck",
    "sg:classifiers":[
        {
            "category":"Professional",
            "subcategory":"Computer Services",
            "type":"Services"
        }
    ],
    "sg:phone":"+43 4351 229475820",
    "sg:postcode":"6020",
    "sg:province":"Tirol",
    "sg:tags":[
        "software"
    ],
    "wof:name":"Wizzical Wolf & Partner OEG Techkommunikation & IT",
    "wof:placetype":"venue"
},
  "geometry": {"coordinates":[11.3874559402,47.2687034607],"type":"Point"}
}