{
  "type": "Feature",
  "properties": {
    "addr:full":"Gatterburgg 14 Wien Wien 1190",
    "addr:housenumber":"14",
    "addr:postcode":"1190",
    "addr:street":"Gatterburgg",
    "iso:country":"AT",
    "sg:address":"Gatterburgg 14",
    "sg:city":"Wien",
    "sg:orig_category":"Non-Classified Establishments",
    "sg:phone":"+43 1 360340",
    "sg:postcode":"1190",
    "sg:province":"Wien",
    "wof:name":"Magistratisches Bezirksamt f d 19. Bezirk",
    "wof:placetype":"venue"
},
  "geometry": {"coordinates":[16.3535461426,48.2388801575],"type":"Point"}
}