{
  "type": "Feature",
  "properties": {
    "addr:full":"Nr 17 Minihof-Liebau Burgenland 8384",
    "addr:postcode":"8384",
    "addr:street":"Nr;Minihof-Liebau",
    "iso:country":"AT",
    "sg:address":"Nr 17",
    "sg:city":"Minihof-Liebau",
    "sg:orig_category":"Fleischhauereien",
    "sg:phone":"+43 3329 2118",
    "sg:postcode":"8384",
    "sg:province":"Burgenland",
    "wof:name":"Brunner Alois",
    "wof:placetype":"venue"
},
  "geometry": {"coordinates":[16.0747261047,46.8825569153],"type":"Point"}
}