{
  "type": "Feature",
  "properties": {
    "addr:full":"Nr 182 Grafendorf Steiermark 8232",
    "addr:postcode":"8232",
    "addr:street":"Nr 182",
    "iso:country":"AT",
    "sg:address":"Nr 182",
    "sg:city":"Grafendorf",
    "sg:orig_category":"Lebensmittel / Einzelhandel",
    "sg:phone":"+43 4333 3820200",
    "sg:postcode":"8232",
    "sg:province":"Steiermark",
    "wof:name":"ADEG - Kogler Franz HandelsgesmbH",
    "wof:placetype":"venue"
},
  "geometry": {"coordinates":[15.9579706192,47.3341445923],"type":"Point"}
}