{
  "type": "Feature",
  "properties": {
    "addr:full":"Kirschentalg 30 Innsbruck Tirol 6020",
    "addr:housenumber":"30",
    "addr:postcode":"6020",
    "addr:street":"Kirschentalg;Tirol",
    "iso:country":"AT",
    "sg:address":"Kirschentalg 30",
    "sg:city":"Innsbruck",
    "sg:orig_category":"Appartements / Ferienwohnungen",
    "sg:phone":"+43 4351 2272070",
    "sg:postcode":"6020",
    "sg:province":"Tirol",
    "wof:name":"Albrecht Ferienwohnung",
    "wof:placetype":"venue"
},
  "geometry": {"coordinates":[11.3856687546,47.2708320618],"type":"Point"}
}