{
  "type": "Feature",
  "properties": {
    "addr:full":"Grammeallee 1 Schwanenstadt Ober\u00f6sterreich 4690",
    "addr:housenumber":"1",
    "addr:postcode":"4690",
    "addr:street":"Grammeallee",
    "iso:country":"AT",
    "sg:address":"Grammeallee 1",
    "sg:city":"Schwanenstadt",
    "sg:orig_category":"Innenarchitekten",
    "sg:phone":"+43 76735169",
    "sg:postcode":"4690",
    "sg:province":"Ober\u00f6sterreich",
    "wof:name":"Pillichshammer Hermann Ing",
    "wof:placetype":"venue"
},
  "geometry": {"coordinates":[13.7747154236,48.0598106384],"type":"Point"}
}