{
  "type": "Feature",
  "properties": {
    "addr:full":"Hinterhaus 179 Persenbeug Nieder\u00f6sterreich 3680",
    "addr:housenumber":"179",
    "addr:postcode":"3680",
    "addr:street":"Hinterhaus",
    "iso:country":"AT",
    "sg:address":"Hinterhaus 179",
    "sg:city":"Persenbeug",
    "sg:orig_category":"Polizei U Gendarmerie",
    "sg:phone":"+43 4374 12526800",
    "sg:postcode":"3680",
    "sg:province":"Nieder\u00f6sterreich",
    "wof:name":"Schiffahrtspolizei Strom- u Schleusenaufsicht Persenbeug",
    "wof:placetype":"venue"
},
  "geometry": {"coordinates":[15.0718517303,48.1921768188],"type":"Point"}
}