{
  "type": "Feature",
  "properties": {
    "addr:full":"Kaltschacher Strasse 32 Wernberg K\u00e4rnten 9241",
    "addr:housenumber":"32",
    "addr:postcode":"9241",
    "addr:street":"Kaltschacher Strasse;Kaernten",
    "iso:country":"AT",
    "sg:address":"Kaltschacher Strasse 32",
    "sg:city":"Wernberg",
    "sg:classifiers":[
        {
            "category":"Food & Beverages",
            "subcategory":"Fruits & Vegetables",
            "type":"Retail Goods"
        }
    ],
    "sg:phone":"+43 4252 24522",
    "sg:postcode":"9241",
    "sg:province":"K\u00e4rnten",
    "sg:tags":[
        "flower",
        "seed"
    ],
    "sg:website":"eurosaat.com",
    "wof:name":"Samen Dostall",
    "wof:placetype":"venue"
},
  "geometry": {"coordinates":[13.9505081177,46.621547699],"type":"Point"}
}