{
  "type": "Feature",
  "properties": {
    "iso:country":"AT",
    "sg:address":"Burgg 33",
    "sg:city":"Wien",
    "sg:orig_category":"Immobilienmakler",
    "sg:phone":"+43 1 5266767",
    "sg:postcode":"1070",
    "sg:province":"Wien",
    "wof:name":"Intex-Danubia Realit\u00e4ten GesmbH",
    "wof:placetype":"venue"
},
  "geometry": {"coordinates":[16.3526382446,48.2042579651],"type":"Point"}
}