{
  "type": "Feature",
  "properties": {
    "addr:full":"Sportplatzstr 13 Ebreichsdorf Nieder\u00f6sterreich 2483",
    "addr:housenumber":"13",
    "addr:postcode":"2483",
    "addr:street":"Sportplatzstr",
    "iso:country":"AT",
    "sg:address":"Sportplatzstr 13",
    "sg:city":"Ebreichsdorf",
    "sg:orig_category":"Spirituosen / Erzeugung U Gro\u00c3\u0178handel",
    "sg:phone":"+43 2254 725560",
    "sg:postcode":"2483",
    "sg:province":"Nieder\u00f6sterreich",
    "wof:name":"Lehar GesmbH",
    "wof:placetype":"venue"
},
  "geometry": {"coordinates":[16.3987903595,47.9594802856],"type":"Point"}
}