{
  "type": "Feature",
  "properties": {
    "addr:full":"Bahnstr 2B Gramatneusiedl Nieder\u00f6sterreich 2440",
    "addr:housenumber":"2b",
    "addr:postcode":"2440",
    "addr:street":"Bahnstr",
    "iso:country":"AT",
    "sg:address":"Bahnstr 2B",
    "sg:city":"Gramatneusiedl",
    "sg:orig_category":"Non-Classified Establishments",
    "sg:phone":"+43 5 91333225",
    "sg:postcode":"2440",
    "sg:province":"Nieder\u00f6sterreich",
    "wof:name":"Gendarmerie",
    "wof:placetype":"venue"
},
  "geometry": {"coordinates":[16.4901771545,48.0292549133],"type":"Point"}
}