{
  "type": "Feature",
  "properties": {
    "addr:full":"Palvenstr 2 Saalfelden am Steinernen Meer Salzburg 5760",
    "addr:housenumber":"2",
    "addr:postcode":"5760",
    "addr:street":"Palvenstr",
    "iso:country":"AT",
    "sg:address":"Palvenstr 2",
    "sg:city":"Saalfelden am Steinernen Meer",
    "sg:orig_category":"Non-Classified Establishments",
    "sg:phone":"+43 6582 741630",
    "sg:postcode":"5760",
    "sg:province":"Salzburg",
    "wof:name":"Evangelisches Pfarramt",
    "wof:placetype":"venue"
},
  "geometry": {"coordinates":[12.8512868881,47.4327087402],"type":"Point"}
}