{
  "type": "Feature",
  "properties": {
    "addr:full":"Alpenblick 5 Gallneukirchen Ober\u00f6sterreich 4210",
    "addr:housenumber":"5",
    "addr:postcode":"4210",
    "addr:street":"Alpenblick;Oberoesterreich",
    "iso:country":"AT",
    "sg:address":"Alpenblick 5",
    "sg:city":"Gallneukirchen",
    "sg:orig_category":"Handelsagenturen",
    "sg:phone":"+43 7235 67248",
    "sg:postcode":"4210",
    "sg:province":"Ober\u00f6sterreich",
    "wof:name":"Sigl Andreas - Objektberatung-T\u00fcrbeschl\u00e4ge",
    "wof:placetype":"venue"
},
  "geometry": {"coordinates":[14.4756259918,48.3673629761],"type":"Point"}
}