{
  "type": "Feature",
  "properties": {
    "addr:full":"Wiener Str 24 Amstetten Nieder\u00f6sterreich 3300",
    "addr:postcode":"3300",
    "addr:street":"Niederoesterreich",
    "iso:country":"AT",
    "sg:address":"Wiener Str 24",
    "sg:city":"Amstetten",
    "sg:orig_category":"Textilreinigung",
    "sg:phone":"+43 7472 62852",
    "sg:postcode":"3300",
    "sg:province":"Nieder\u00f6sterreich",
    "wof:name":"Putzerei Kuttner Andrea",
    "wof:placetype":"venue"
},
  "geometry": {"coordinates":[14.8774280548,48.1226272583],"type":"Point"}
}