{
  "type": "Feature",
  "properties": {
    "addr:full":"Puchberger Str 51 Wels Ober\u00f6sterreich 4600",
    "addr:housenumber":"51",
    "addr:postcode":"4600",
    "addr:street":"Str;Oberoesterreich",
    "iso:country":"AT",
    "sg:address":"Puchberger Str 51",
    "sg:city":"Wels",
    "sg:classifiers":[
        {
            "category":"Professional",
            "subcategory":"Computer Services",
            "type":"Services"
        }
    ],
    "sg:phone":"+43 7242 45541",
    "sg:postcode":"4600",
    "sg:province":"Ober\u00f6sterreich",
    "sg:tags":[
        "software"
    ],
    "wof:name":"dpw H R Software GmbH",
    "wof:placetype":"venue"
},
  "geometry": {"coordinates":[14.0232906342,48.1809692383],"type":"Point"}
}