{
  "type": "Feature",
  "properties": {
    "addr:full":"Heiligenkreuz 14 Kremsm\u00fcnster Ober\u00f6sterreich 4550",
    "addr:housenumber":"14",
    "addr:postcode":"4550",
    "addr:street":"Heiligenkreuz;Oberoesterreich",
    "iso:country":"AT",
    "sg:address":"Heiligenkreuz 14",
    "sg:city":"Kremsm\u00fcnster",
    "sg:orig_category":"Feuerwehren",
    "sg:phone":"+43 7583 20017",
    "sg:postcode":"4550",
    "sg:province":"Ober\u00f6sterreich",
    "wof:name":"Freiwillige Feuerwehr Irndorf",
    "wof:placetype":"venue"
},
  "geometry": {"coordinates":[14.0936422348,48.0659790039],"type":"Point"}
}