{
  "type": "Feature",
  "properties": {
    "addr:full":"Schulweg 1 Stockerau Nieder\u00f6sterreich 2000",
    "addr:housenumber":"1",
    "addr:postcode":"2000",
    "addr:street":"Schulweg",
    "iso:country":"AT",
    "sg:address":"Schulweg 1",
    "sg:city":"Stockerau",
    "sg:orig_category":"Hauptschulen",
    "sg:phone":"+43 2266 62228",
    "sg:postcode":"2000",
    "sg:province":"Nieder\u00f6sterreich",
    "wof:name":"Hauptschule Ost",
    "wof:placetype":"venue"
},
  "geometry": {"coordinates":[16.2117786407,48.388381958],"type":"Point"}
}