{
  "type": "Feature",
  "properties": {
    "iso:country":"AT",
    "sg:address":"St Veiter Str 6-8",
    "sg:city":"Andritz",
    "sg:orig_category":"\u00c3\u201enderungsschneidereien",
    "sg:phone":"+43 316 697734",
    "sg:postcode":"8045",
    "sg:province":"Steiermark",
    "wof:name":"Kupsa Rosemarie",
    "wof:placetype":"venue"
},
  "geometry": {"coordinates":[15.4145069122,47.11170578],"type":"Point"}
}