{
  "type": "Feature",
  "properties": {
    "iso:country":"AT",
    "sg:address":"Eitnerg. 19 ",
    "sg:city":"Wien",
    "sg:classifiers":[
        {
            "category":"Shopping",
            "subcategory":"Computers & Home Electronics",
            "type":"Retail Goods"
        }
    ],
    "sg:phone":"+43 4318 65045",
    "sg:postcode":"1230",
    "sg:province":"Wien",
    "sg:tags":[
        "electronic",
        "electrical",
        "equipment"
    ],
    "wof:name":"B\u00c4REN BATTERIE GES.MBH",
    "wof:placetype":"venue"
},
  "geometry": {"coordinates":[16.3047771454,48.1390838623],"type":"Point"}
}