{
  "type": "Feature",
  "properties": {
    "addr:full":"Ortenburger Str 12 Spittal an der Drau K\u00e4rnten 9800",
    "addr:housenumber":"12",
    "addr:postcode":"9800",
    "addr:street":"Str;Kaernten",
    "iso:country":"AT",
    "sg:address":"Ortenburger Str 12",
    "sg:city":"Spittal an der Drau",
    "sg:classifiers":[
        {
            "category":"Shopping",
            "subcategory":"Bicycles & Sporting Goods",
            "type":"Retail Goods"
        }
    ],
    "sg:phone":"+43 4347 624888",
    "sg:postcode":"9800",
    "sg:province":"K\u00e4rnten",
    "sg:tags":[
        "munition",
        "u",
        "waffen"
    ],
    "wof:name":"Ebenberger Peter",
    "wof:placetype":"venue"
},
  "geometry": {"coordinates":[13.4935388565,46.7955322266],"type":"Point"}
}