{
  "type": "Feature",
  "properties": {
    "addr:full":"Nr 34 Rohrbach an der Lafnitz Steiermark 8234",
    "addr:postcode":"8234",
    "addr:street":"Nr 34",
    "iso:country":"AT",
    "sg:address":"Nr 34",
    "sg:city":"Rohrbach an der Lafnitz",
    "sg:orig_category":"Volksschulen",
    "sg:phone":"+43 4333 383720",
    "sg:postcode":"8234",
    "sg:province":"Steiermark",
    "wof:name":"Volksschule",
    "wof:placetype":"venue"
},
  "geometry": {"coordinates":[15.9732465744,47.3812446594],"type":"Point"}
}