{
  "type": "Feature",
  "properties": {
    "addr:full":"Nr 321 Nauders Tirol 6543",
    "addr:postcode":"6543",
    "addr:street":"Nr 321;Tirol",
    "iso:country":"AT",
    "sg:address":"Nr 321",
    "sg:city":"Nauders",
    "sg:orig_category":"Pensionen / Privatzimmer",
    "sg:phone":"+43 5473 87365",
    "sg:postcode":"6543",
    "sg:province":"Tirol",
    "wof:name":"Pension Haus Panorama",
    "wof:placetype":"venue"
},
  "geometry": {"coordinates":[10.4996595383,46.8896980286],"type":"Point"}
}