{
  "type": "Feature",
  "properties": {
    "addr:full":"Billrothstr 83/17 Wien Wien 1190",
    "addr:housenumber":"83 / 17",
    "addr:postcode":"1190",
    "addr:street":"Billrothstr",
    "iso:country":"AT",
    "sg:address":"Billrothstr 83/17",
    "sg:city":"Wien",
    "sg:orig_category":"Elektrotechnik",
    "sg:phone":"+43 1 32042510",
    "sg:postcode":"1190",
    "sg:province":"Wien",
    "wof:name":"GTG Dipl-Ing Georg Tauchner GmbH",
    "wof:placetype":"venue"
},
  "geometry": {"coordinates":[16.3429355621,48.2454948425],"type":"Point"}
}