{
  "type": "Feature",
  "properties": {
    "iso:country":"AT",
    "sg:address":"Bahnhofstr 30",
    "sg:city":"Dornbirn",
    "sg:orig_category":"Massagen",
    "sg:phone":"+43 699 10187743",
    "sg:postcode":"6850",
    "sg:province":"Vorarlberg",
    "wof:name":"Resch Grete Shiatsu",
    "wof:placetype":"venue"
},
  "geometry": {"coordinates":[9.7392473221,47.4171905518],"type":"Point"}
}