{
  "type": "Feature",
  "properties": {
    "addr:full":"K\u00fchnsdorf Mitte 18 K\u00fchnsdorf K\u00e4rnten 9125",
    "addr:housenumber":"18",
    "addr:postcode":"9125",
    "addr:street":"Mitte;Kaernten",
    "iso:country":"AT",
    "sg:address":"K\u00fchnsdorf Mitte 18",
    "sg:city":"K\u00fchnsdorf",
    "sg:classifiers":[
        {
            "category":"Restaurant",
            "type":"Food & Drink"
        }
    ],
    "sg:phone":"+43 4342 3289329",
    "sg:postcode":"9125",
    "sg:province":"K\u00e4rnten",
    "wof:name":"Park Cafe",
    "wof:placetype":"venue"
},
  "geometry": {"coordinates":[14.6350193024,46.6194801331],"type":"Point"}
}