{
  "type": "Feature",
  "properties": {
    "addr:full":"Hofferpl 11 Wien Wien 1160",
    "addr:housenumber":"11",
    "addr:postcode":"1160",
    "addr:street":"Hofferpl",
    "iso:country":"AT",
    "sg:address":"Hofferpl 11",
    "sg:city":"Wien",
    "sg:classifiers":[
        {
            "category":"Taxi",
            "type":"Transportation"
        }
    ],
    "sg:phone":"+43 4369 912005624",
    "sg:postcode":"1160",
    "sg:province":"Wien",
    "sg:tags":[
        "personentransporte",
        "u"
    ],
    "wof:name":"FAXI das Fahrradtaxi",
    "wof:placetype":"venue"
},
  "geometry": {"coordinates":[16.3337478638,48.2094268799],"type":"Point"}
}