{
  "type": "Feature",
  "properties": {
    "addr:full":"Nr 114 Obsteig Tirol 6416",
    "addr:postcode":"6416",
    "addr:street":"Nr 114;Tirol",
    "iso:country":"AT",
    "sg:address":"Nr 114",
    "sg:city":"Obsteig",
    "sg:orig_category":"Appartements / Ferienwohnungen",
    "sg:phone":"+43 4352 648394",
    "sg:postcode":"6416",
    "sg:province":"Tirol",
    "wof:name":"Alpenblick Landhaus",
    "wof:placetype":"venue"
},
  "geometry": {"coordinates":[10.9270277023,47.2980957031],"type":"Point"}
}