{
  "type": "Feature",
  "properties": {
    "addr:full":"Erdbergstr 26 Wien Wien 1030",
    "addr:housenumber":"26",
    "addr:postcode":"1030",
    "addr:street":"Erdbergstr",
    "iso:country":"AT",
    "sg:address":"Erdbergstr 26",
    "sg:city":"Wien",
    "sg:orig_category":"Maler, Anstreicher U Lackierer",
    "sg:phone":"+43 1 71262590",
    "sg:postcode":"1030",
    "sg:province":"Wien",
    "wof:name":"Lampl Rudolf",
    "wof:placetype":"venue"
},
  "geometry": {"coordinates":[16.3945922852,48.202331543],"type":"Point"}
}