{
  "type": "Feature",
  "properties": {
    "addr:full":"Wasagasse 12 Wien Wien 1090",
    "addr:housenumber":"12",
    "addr:postcode":"1090",
    "addr:street":"Wasagasse",
    "iso:country":"AT",
    "sg:address":"Wasagasse 12",
    "sg:city":"Wien",
    "sg:classifiers":[
        {
            "category":"Banks & Credit Unions",
            "subcategory":"Investment Brokerage",
            "type":"Services"
        }
    ],
    "sg:phone":"+43 1 3191406",
    "sg:postcode":"1090",
    "sg:province":"Wien",
    "sg:tags":[
        "impression",
        "dental",
        "compound"
    ],
    "sg:website":"dentalstudio.at",
    "wof:name":"Dentalstudio Rudolf M\u00fcller",
    "wof:placetype":"venue"
},
  "geometry": {"coordinates":[16.361164093,48.2172050476],"type":"Point"}
}