{
  "type": "Feature",
  "properties": {
    "addr:full":"Nr 125 Feistritz am Wechsel Nieder\u00f6sterreich 2873",
    "addr:postcode":"2873",
    "addr:street":"Nr;Feistritz;Wechsel",
    "iso:country":"AT",
    "sg:address":"Nr 125",
    "sg:city":"Feistritz am Wechsel",
    "sg:orig_category":"Volksschulen",
    "sg:phone":"+43 4326 412167",
    "sg:postcode":"2873",
    "sg:province":"Nieder\u00f6sterreich",
    "wof:name":"Volksschule",
    "wof:placetype":"venue"
},
  "geometry": {"coordinates":[16.0537948608,47.5992774963],"type":"Point"}
}