{
  "type": "Feature",
  "properties": {
    "addr:full":"Aichberg 54 Eibiswald Steiermark 8552",
    "addr:housenumber":"54",
    "addr:postcode":"8552",
    "addr:street":"Aichberg",
    "iso:country":"AT",
    "sg:address":"Aichberg 54",
    "sg:city":"Eibiswald",
    "sg:orig_category":"Erdbau",
    "sg:phone":"+43 676 4070000",
    "sg:postcode":"8552",
    "sg:province":"Steiermark",
    "wof:name":"Schmuck Johann",
    "wof:placetype":"venue"
},
  "geometry": {"coordinates":[15.2274599075,46.6824150085],"type":"Point"}
}