{
  "type": "Feature",
  "properties": {
    "addr:full":"Michl-Felder-Str 10 Bregenz Vorarlberg 6900",
    "addr:housenumber":"10",
    "addr:postcode":"6900",
    "addr:street":"Michl-Felder-Str",
    "iso:country":"AT",
    "sg:address":"Michl-Felder-Str 10",
    "sg:city":"Bregenz",
    "sg:orig_category":"Schlossereien",
    "sg:phone":"+43 5574 45762",
    "sg:postcode":"6900",
    "sg:province":"Vorarlberg",
    "wof:name":"Kofler Wilfried",
    "wof:placetype":"venue"
},
  "geometry": {"coordinates":[9.7530632019,47.5070838928],"type":"Point"}
}