{
  "type": "Feature",
  "properties": {
    "addr:full":"Reichenauer Str 35 Altenberg Ober\u00f6sterreich 4203",
    "addr:housenumber":"35",
    "addr:postcode":"4203",
    "addr:street":"Str",
    "iso:country":"AT",
    "sg:address":"Reichenauer Str 35",
    "sg:city":"Altenberg",
    "sg:orig_category":"Teppiche / Erzeugung U Gro\u00c3\u0178handel",
    "sg:phone":"+43 4372 307228",
    "sg:postcode":"4203",
    "sg:province":"Ober\u00f6sterreich",
    "wof:name":"H\u00f6rezeder Maximilian",
    "wof:placetype":"venue"
},
  "geometry": {"coordinates":[14.3420610428,48.3761177063],"type":"Point"}
}