{
  "type": "Feature",
  "properties": {
    "iso:country":"AT",
    "sg:address":"Steglandweg 2",
    "sg:city":"Hallein",
    "sg:orig_category":"Appartements / Ferienwohnungen",
    "sg:phone":"+43 4362 4581343",
    "sg:postcode":"5400",
    "sg:province":"Salzburg",
    "sg:website":"interrest.at",
    "wof:name":"A&D INTERREST WERBEAGENTUR R. SALZBURG",
    "wof:placetype":"venue"
},
  "geometry": {"coordinates":[13.0963840485,47.6794967651],"type":"Point"}
}