{
  "type": "Feature",
  "properties": {
    "addr:full":"Maria Rekker Gasse 1/39 Wien Wien 1100",
    "addr:housenumber":"1 / 39",
    "addr:postcode":"1100",
    "addr:street":"Gasse",
    "iso:country":"AT",
    "sg:address":"Maria Rekker Gasse 1/39",
    "sg:city":"Wien",
    "sg:classifiers":[
        {
            "category":"Professional",
            "subcategory":"Advertising",
            "type":"Services"
        }
    ],
    "sg:phone":"+43 699 19542772",
    "sg:postcode":"1100",
    "sg:province":"Wien",
    "sg:tags":[
        "agency",
        "internet"
    ],
    "sg:website":"space-factory.at",
    "wof:name":"Space-Factory",
    "wof:placetype":"venue"
},
  "geometry": {"coordinates":[16.383108139,48.1645927429],"type":"Point"}
}