{
  "type": "Feature",
  "properties": {
    "addr:full":"Jagdbergstr 65 Satteins Vorarlberg 6822",
    "addr:housenumber":"65",
    "addr:postcode":"6822",
    "addr:street":"Jagdbergstr",
    "iso:country":"AT",
    "sg:address":"Jagdbergstr 65",
    "sg:city":"Satteins",
    "sg:orig_category":"Non-Classified Establishments",
    "sg:phone":"+43 5524 8505",
    "sg:postcode":"6822",
    "sg:province":"Vorarlberg",
    "wof:name":"Pfarramt Schnifis",
    "wof:placetype":"venue"
},
  "geometry": {"coordinates":[9.7249898911,47.2143745422],"type":"Point"}
}