{
  "type": "Feature",
  "properties": {
    "addr:full":"Eisenst\u00e4dter Str 32a Breitenbrunn Burgenland 7091",
    "addr:housenumber":"32a",
    "addr:postcode":"7091",
    "addr:street":"Str",
    "iso:country":"AT",
    "sg:address":"Eisenst\u00e4dter Str 32a",
    "sg:city":"Breitenbrunn",
    "sg:orig_category":"Banken U Sparkassen",
    "sg:phone":"+43 4326 8352650",
    "sg:postcode":"7091",
    "sg:province":"Burgenland",
    "wof:name":"Raiffeisenlandesbank Burgenland Waren- & Revisionsverband regGenmbH",
    "wof:placetype":"venue"
},
  "geometry": {"coordinates":[16.7305927277,47.9435577393],"type":"Point"}
}