{
  "type": "Feature",
  "properties": {
    "addr:full":"Wiener Str 32 Eugendorf Salzburg 5301",
    "addr:postcode":"5301",
    "addr:street":"32 Eugendorf",
    "iso:country":"AT",
    "sg:address":"Wiener Str 32",
    "sg:city":"Eugendorf",
    "sg:orig_category":"Telefonanlagen",
    "sg:phone":"+43 664 4311115",
    "sg:postcode":"5301",
    "sg:province":"Salzburg",
    "wof:name":"Elektro & Kommunikationstechnik Klaus Hohenwarter",
    "wof:placetype":"venue"
},
  "geometry": {"coordinates":[13.1632022858,47.8782424927],"type":"Point"}
}