{
  "type": "Feature",
  "properties": {
    "iso:country":"AT",
    "sg:address":"Karfreitstrasse 24",
    "sg:city":"Klagenfurt",
    "sg:classifiers":[
        {
            "category":"Home & Garden",
            "subcategory":"Building Materials",
            "type":"Retail Goods"
        }
    ],
    "sg:phone":"+43 463 516342",
    "sg:postcode":"9020",
    "sg:province":"K\u00e4rnten",
    "sg:tags":[
        "gravel",
        "crushed"
    ],
    "wof:name":"Bleiburger Dolomitwerk GesmbH",
    "wof:placetype":"venue"
},
  "geometry": {"coordinates":[14.3085947037,46.6215133667],"type":"Point"}
}