{
  "type": "Feature",
  "properties": {
    "addr:full":"Obachgasse 2 Wien Wien 1220",
    "addr:housenumber":"2",
    "addr:postcode":"1220",
    "addr:street":"Obachgasse",
    "iso:country":"AT",
    "sg:address":"Obachgasse 2",
    "sg:city":"Wien",
    "sg:classifiers":[
        {
            "category":"Banks & Credit Unions",
            "subcategory":"Bank",
            "type":"Services"
        }
    ],
    "sg:phone":"+43 1 250210",
    "sg:postcode":"1220",
    "sg:province":"Wien",
    "sg:tags":[
        "chain",
        "systems",
        "cable",
        "guide"
    ],
    "sg:website":"vangeel.at",
    "wof:name":"Van Geel Austria GmbH",
    "wof:placetype":"venue"
},
  "geometry": {"coordinates":[16.4597759247,48.2545204163],"type":"Point"}
}