{
  "type": "Feature",
  "properties": {
    "addr:full":"Schlachthausgasse 9 Karlstetten Nieder\u00f6sterreich 3121",
    "addr:housenumber":"9",
    "addr:postcode":"3121",
    "addr:street":"Schlachthausgasse",
    "iso:country":"AT",
    "sg:address":"Schlachthausgasse 9",
    "sg:city":"Karlstetten",
    "sg:orig_category":"Non-Classified Establishments",
    "sg:phone":"+43 2741 82930",
    "sg:postcode":"3121",
    "sg:province":"Nieder\u00f6sterreich",
    "sg:website":"schlachthof.at",
    "wof:name":"Julius Kloiber Schlachthof Ges.m.b.H.",
    "wof:placetype":"venue"
},
  "geometry": {"coordinates":[15.5655174255,48.2571868896],"type":"Point"}
}