{
  "type": "Feature",
  "properties": {
    "addr:full":"Knappenweg 1 Oberzeiring Steiermark 8762",
    "addr:housenumber":"1",
    "addr:postcode":"8762",
    "addr:street":"Knappenweg",
    "iso:country":"AT",
    "sg:address":"Knappenweg 1",
    "sg:city":"Oberzeiring",
    "sg:orig_category":"\u00c3\u201erzte / F Allgemeinmedizin",
    "sg:phone":"+43 3571 2276",
    "sg:postcode":"8762",
    "sg:province":"Steiermark",
    "wof:name":"Heschl Klaus Dr",
    "wof:placetype":"venue"
},
  "geometry": {"coordinates":[14.48640728,47.2521209717],"type":"Point"}
}