{
  "type": "Feature",
  "properties": {
    "iso:country":"AT",
    "sg:address":"Universit\u00e4tsstr 6",
    "sg:city":"Graz",
    "sg:orig_category":"Institute",
    "sg:phone":"+43 316 3804398",
    "sg:postcode":"8010",
    "sg:province":"Steiermark",
    "wof:name":"Inst f Sozialmedizin Karl Franzens Universit\u00e4t",
    "wof:placetype":"venue"
},
  "geometry": {"coordinates":[15.449634552,47.0789413452],"type":"Point"}
}