{
  "type": "Feature",
  "properties": {
    "addr:full":"Hausham 10 V\u00f6cklamarkt Ober\u00f6sterreich 4870",
    "addr:housenumber":"10",
    "addr:postcode":"4870",
    "addr:street":"Hausham;Oberoesterreich",
    "iso:country":"AT",
    "sg:address":"Hausham 10",
    "sg:city":"V\u00f6cklamarkt",
    "sg:orig_category":"Tischlereien",
    "sg:phone":"+43 768262920",
    "sg:postcode":"4870",
    "sg:province":"Ober\u00f6sterreich",
    "wof:name":"Lehner Christian Innenausbau und Planung",
    "wof:placetype":"venue"
},
  "geometry": {"coordinates":[13.4818000793,48.0179595947],"type":"Point"}
}