{
  "type": "Feature",
  "properties": {
    "addr:full":"Eduard-Kittenberger-G 99 Wien Wien 1230",
    "addr:housenumber":"99",
    "addr:postcode":"1230",
    "addr:street":"Eduard-Kittenberger-G",
    "iso:country":"AT",
    "sg:address":"Eduard-Kittenberger-G 99",
    "sg:city":"Wien",
    "sg:orig_category":"Beschichtungen",
    "sg:phone":"+43 4318 6542520",
    "sg:postcode":"1230",
    "sg:province":"Wien",
    "sg:website":"terolabservices.com",
    "wof:name":"Terolab Services Austria GmbH",
    "wof:placetype":"venue"
},
  "geometry": {"coordinates":[16.3036975861,48.1373062134],"type":"Point"}
}