{
  "type": "Feature",
  "properties": {
    "addr:full":"Hauptstr 1A Seekirchen am Wallersee Salzburg 5201",
    "addr:housenumber":"1a",
    "addr:postcode":"5201",
    "addr:street":"Hauptstr;Salzburg",
    "iso:country":"AT",
    "sg:address":"Hauptstr 1A",
    "sg:city":"Seekirchen am Wallersee",
    "sg:orig_category":"Bauunternehmen",
    "sg:phone":"+43 6212 28400",
    "sg:postcode":"5201",
    "sg:province":"Salzburg",
    "wof:name":"Voglreiter Markus Ing",
    "wof:placetype":"venue"
},
  "geometry": {"coordinates":[13.1264476776,47.8912162781],"type":"Point"}
}