{
  "type": "Feature",
  "properties": {
    "addr:full":"Archeng 48 Schwaz Tirol 6130",
    "addr:housenumber":"48",
    "addr:postcode":"6130",
    "addr:street":"Archeng;Tirol",
    "iso:country":"AT",
    "sg:address":"Archeng 48",
    "sg:city":"Schwaz",
    "sg:orig_category":"Rauchfangkehrer",
    "sg:phone":"+43 5242 62391",
    "sg:postcode":"6130",
    "sg:province":"Tirol",
    "wof:name":"Druckm\u00fcller Reinhard",
    "wof:placetype":"venue"
},
  "geometry": {"coordinates":[11.7098970413,47.3582649231],"type":"Point"}
}