{
  "type": "Feature",
  "properties": {
    "addr:full":"Haferfeldweg 19 Neuhart Steiermark 8053",
    "addr:housenumber":"19",
    "addr:postcode":"8053",
    "addr:street":"Haferfeldweg",
    "iso:country":"AT",
    "sg:address":"Haferfeldweg 19",
    "sg:city":"Neuhart",
    "sg:orig_category":"Anti-Mould Coatings",
    "sg:phone":"+43 316 284271",
    "sg:postcode":"8053",
    "sg:province":"Steiermark",
    "wof:name":"Strohmeier Malerbetrieb KEG",
    "wof:placetype":"venue"
},
  "geometry": {"coordinates":[15.3994274139,47.0426063538],"type":"Point"}
}