{
  "type": "Feature",
  "properties": {
    "addr:full":"Albertvilleg 15 Klagenfurt K\u00e4rnten 9020",
    "addr:housenumber":"15",
    "addr:postcode":"9020",
    "addr:street":"Albertvilleg;Kaernten",
    "iso:country":"AT",
    "sg:address":"Albertvilleg 15",
    "sg:city":"Klagenfurt",
    "sg:orig_category":"Medizintechnik",
    "sg:phone":"+43 463 420333",
    "sg:postcode":"9020",
    "sg:province":"K\u00e4rnten",
    "wof:name":"Leupamed Medizintechnik Ger\u00e4te GesmbH",
    "wof:placetype":"venue"
},
  "geometry": {"coordinates":[14.349653244,46.6355857849],"type":"Point"}
}