{
  "type": "Feature",
  "properties": {
    "addr:full":"Regensburger Str 25 P\u00f6chlarn Nieder\u00f6sterreich 3380",
    "addr:postcode":"3380",
    "addr:street":"Str 25 Poechlarn",
    "iso:country":"AT",
    "sg:address":"Regensburger Str 25",
    "sg:city":"P\u00f6chlarn",
    "sg:orig_category":"Banken U Sparkassen",
    "sg:phone":"+43 4327 5726260",
    "sg:postcode":"3380",
    "sg:province":"Nieder\u00f6sterreich",
    "wof:name":"Raiffeisenbank Region Melk regGenmbH",
    "wof:placetype":"venue"
},
  "geometry": {"coordinates":[-79.38526153559999,41.2145881653],"type":"Point"}
}