{
  "type": "Feature",
  "properties": {
    "addr:full":"Hauptstr 11 Himberg Nieder\u00f6sterreich 2325",
    "addr:housenumber":"11",
    "addr:postcode":"2325",
    "addr:street":"Hauptstr",
    "iso:country":"AT",
    "sg:address":"Hauptstr 11",
    "sg:city":"Himberg",
    "sg:orig_category":"Botendienste",
    "sg:phone":"+43 2235 87088",
    "sg:postcode":"2325",
    "sg:province":"Nieder\u00f6sterreich",
    "wof:name":"Botendienst Himberg Inh Irene Teinitzer",
    "wof:placetype":"venue"
},
  "geometry": {"coordinates":[16.4401054382,48.0862236023],"type":"Point"}
}