{
  "type": "Feature",
  "properties": {
    "addr:full":"Platz 61 Mellau Vorarlberg 6881",
    "addr:housenumber":"61",
    "addr:postcode":"6881",
    "addr:street":"Platz",
    "iso:country":"AT",
    "sg:address":"Platz 61",
    "sg:city":"Mellau",
    "sg:orig_category":"Non-Classified Establishments",
    "sg:phone":"+43 5518 2218",
    "sg:postcode":"6881",
    "sg:province":"Vorarlberg",
    "wof:name":"Pfarramt",
    "wof:placetype":"venue"
},
  "geometry": {"coordinates":[9.881570816,47.3503112793],"type":"Point"}
}