{
  "type": "Feature",
  "properties": {
    "addr:full":"Oberlaaer Str 191 Wien Wien 1100",
    "addr:housenumber":"191",
    "addr:postcode":"1100",
    "iso:country":"AT",
    "sg:address":"Oberlaaer Str 191",
    "sg:city":"Wien",
    "sg:orig_category":"Schlossereien",
    "sg:phone":"+43 1 6886531",
    "sg:postcode":"1100",
    "sg:province":"Wien",
    "wof:name":"Zehetner Leopold GesmbH",
    "wof:placetype":"venue"
},
  "geometry": {"coordinates":[16.3873538971,48.1413879395],"type":"Point"}
}