{
  "type": "Feature",
  "properties": {
    "addr:full":"Weinstr 47 Langenlois Nieder\u00f6sterreich 3550",
    "addr:housenumber":"47",
    "addr:postcode":"3550",
    "addr:street":"Weinstr",
    "iso:country":"AT",
    "sg:address":"Weinstr 47",
    "sg:city":"Langenlois",
    "sg:orig_category":"Architekten",
    "sg:phone":"+43 4327 342052",
    "sg:postcode":"3550",
    "sg:province":"Nieder\u00f6sterreich",
    "wof:name":"Schmid Franz Arch Prof Dipl-Ing",
    "wof:placetype":"venue"
},
  "geometry": {"coordinates":[15.6911230087,48.4593887329],"type":"Point"}
}