{
  "type": "Feature",
  "properties": {
    "addr:full":"B\u00fcrgeraustr. 29  Lienz Tirol 9900",
    "addr:housenumber":"29",
    "addr:postcode":"9900",
    "addr:street":"Buergeraustr.;Tirol",
    "iso:country":"AT",
    "sg:address":"B\u00fcrgeraustr. 29 ",
    "sg:city":"Lienz",
    "sg:classifiers":[
        {
            "category":"Shopping",
            "subcategory":"Stationery & Office Supplies",
            "type":"Retail Goods"
        }
    ],
    "sg:phone":"+43 4348 52658330",
    "sg:postcode":"9900",
    "sg:province":"Tirol",
    "sg:tags":[
        "professional"
    ],
    "wof:name":"GABRIEL FORCHER TISCHLEREI GESMBH",
    "wof:placetype":"venue"
},
  "geometry": {"coordinates":[12.7684783936,46.8281173706],"type":"Point"}
}