{
  "type": "Feature",
  "properties": {
    "addr:full":"Archleweg 5 Serfaus Tirol 6534",
    "addr:housenumber":"5",
    "addr:postcode":"6534",
    "addr:street":"Archleweg;Tirol",
    "iso:country":"AT",
    "sg:address":"Archleweg 5",
    "sg:city":"Serfaus",
    "sg:orig_category":"Pensionen / Privatzimmer",
    "sg:phone":"+43 5476 6223",
    "sg:postcode":"6534",
    "sg:province":"Tirol",
    "wof:name":"Pension Edelwei\u00df",
    "wof:placetype":"venue"
},
  "geometry": {"coordinates":[10.6064329147,47.0369377136],"type":"Point"}
}