{
  "type": "Feature",
  "properties": {
    "addr:full":"Rumersbachstr 6a Niederndorf Tirol 6342",
    "addr:housenumber":"6a",
    "addr:postcode":"6342",
    "addr:street":"Rumersbachstr",
    "iso:country":"AT",
    "sg:address":"Rumersbachstr 6a",
    "sg:city":"Niederndorf",
    "sg:orig_category":"Hafnereien",
    "sg:phone":"+43 5373 61025",
    "sg:postcode":"6342",
    "sg:province":"Tirol",
    "wof:name":"Achorner Thomas",
    "wof:placetype":"venue"
},
  "geometry": {"coordinates":[12.2144412994,47.6521568298],"type":"Point"}
}