{
  "type": "Feature",
  "properties": {
    "iso:country":"AT",
    "sg:address":"Jormannsdorfer Str 20",
    "sg:city":"Bad Tatzmannsdorf",
    "sg:classifiers":[
        {
            "category":"Travel",
            "subcategory":"Hotels & Motels",
            "type":"Entertainment"
        }
    ],
    "sg:phone":"+43 3353 8373",
    "sg:postcode":"7431",
    "sg:province":"Burgenland",
    "wof:name":"Hotel-Pension Weiss Manfred",
    "wof:placetype":"venue"
},
  "geometry": {"coordinates":[16.224029541,47.3465042114],"type":"Point"}
}