{
  "type": "Feature",
  "properties": {
    "addr:full":"Wiener Str 229 Linz Ober\u00f6sterreich 4020",
    "addr:housenumber":"229",
    "addr:postcode":"4020",
    "iso:country":"AT",
    "sg:address":"Wiener Str 229",
    "sg:city":"Linz",
    "sg:orig_category":"Rohrverbinder U -Verschraubungen",
    "sg:phone":"+43 4373 2341933",
    "sg:postcode":"4020",
    "sg:province":"Ober\u00f6sterreich",
    "wof:name":"Schwer Fittings GesmbH",
    "wof:placetype":"venue"
},
  "geometry": {"coordinates":[14.3142852783,48.2742156982],"type":"Point"}
}