{
  "type": "Feature",
  "properties": {
    "iso:country":"AT",
    "sg:address":"Werk-VI-Strasse 57",
    "sg:city":"Kapfenberg",
    "sg:classifiers":[
        {
            "category":"Manufacturing",
            "subcategory":"Tools & Machinery",
            "type":"Manufacturing & Wholesale Goods"
        }
    ],
    "sg:phone":"+43 3862 33400",
    "sg:postcode":"8605",
    "sg:province":"Steiermark",
    "sg:tags":[
        "construction",
        "container",
        "apparatus"
    ],
    "sg:website":"kroisenbrunner.at",
    "wof:name":"Kroisenbrunner Fertigungs- und Schweisstechnik GmbH",
    "wof:placetype":"venue"
},
  "geometry": {"coordinates":[15.33411026,47.4523010254],"type":"Point"}
}