{
  "type": "Feature",
  "properties": {
    "iso:country":"AT",
    "sg:address":"Singerstr 11a",
    "sg:city":"Wien",
    "sg:orig_category":"Restaurants: Chinesisch",
    "sg:phone":"+43 1 5122804",
    "sg:postcode":"1010",
    "sg:province":"Wien",
    "wof:name":"China-Restaurant Mandarin",
    "wof:placetype":"venue"
},
  "geometry": {"coordinates":[16.3742733002,48.207233429],"type":"Point"}
}