{
  "type": "Feature",
  "properties": {
    "addr:full":"Friedrichg 31 Graz Steiermark 8010",
    "addr:housenumber":"31",
    "addr:postcode":"8010",
    "addr:street":"Friedrichg",
    "iso:country":"AT",
    "sg:address":"Friedrichg 31",
    "sg:city":"Graz",
    "sg:orig_category":"Internet-Provider, Internet",
    "sg:phone":"+43 316 57553020",
    "sg:postcode":"8010",
    "sg:province":"Steiermark",
    "sg:website":"webteam.at",
    "wof:name":"Webteam Schimantz & Hampel OEG",
    "wof:placetype":"venue"
},
  "geometry": {"coordinates":[15.4369163513,47.0634422302],"type":"Point"}
}