{
  "type": "Feature",
  "properties": {
    "addr:full":"Stefan-Fechter-Weg 2 Linz Ober\u00f6sterreich 4020",
    "addr:housenumber":"2",
    "addr:postcode":"4020",
    "addr:street":"Stefan-Fechter-Weg",
    "iso:country":"AT",
    "sg:address":"Stefan-Fechter-Weg 2",
    "sg:city":"Linz",
    "sg:orig_category":"Massagen",
    "sg:phone":"+43 732 784661",
    "sg:postcode":"4020",
    "sg:province":"Ober\u00f6sterreich",
    "wof:name":"Massageinstitut Unterbrunner",
    "wof:placetype":"venue"
},
  "geometry": {"coordinates":[14.2935152054,48.306930542],"type":"Point"}
}