{
  "type": "Feature",
  "properties": {
    "addr:full":"Johnstr 29 Wien Wien 1150",
    "addr:housenumber":"29",
    "addr:postcode":"1150",
    "addr:street":"Johnstr",
    "iso:country":"AT",
    "sg:address":"Johnstr 29",
    "sg:city":"Wien",
    "sg:orig_category":"Stoffe / Erzeugung U Gro\u00c3\u0178handel",
    "sg:phone":"+43 1 7864012",
    "sg:postcode":"1150",
    "sg:province":"Wien",
    "wof:name":"R & R Textil-Design GmbH",
    "wof:placetype":"venue"
},
  "geometry": {"coordinates":[16.3177967072,48.195476532],"type":"Point"}
}