{
  "type": "Feature",
  "properties": {
    "addr:full":"Neue Heimat-Str 15 Hallein Salzburg 5400",
    "addr:housenumber":"15",
    "addr:postcode":"5400",
    "addr:street":"Salzburg",
    "iso:country":"AT",
    "sg:address":"Neue Heimat-Str 15",
    "sg:city":"Hallein",
    "sg:orig_category":"Erdarbeiten",
    "sg:phone":"+43 676 9096844",
    "sg:postcode":"5400",
    "sg:province":"Salzburg",
    "sg:website":"s-guide.at/pisarnik",
    "wof:name":"Pisarnik Christian",
    "wof:placetype":"venue"
},
  "geometry": {"coordinates":[13.1030750275,47.6759796143],"type":"Point"}
}