{
  "type": "Feature",
  "properties": {
    "addr:full":"Gutheil-Schoder-G 9 Wien Wien 1100",
    "addr:housenumber":"9",
    "addr:postcode":"1100",
    "addr:street":"Gutheil-Schoder-G",
    "iso:country":"AT",
    "sg:address":"Gutheil-Schoder-G 9",
    "sg:city":"Wien",
    "sg:classifiers":[
        {
            "category":"Restaurant",
            "type":"Food & Drink"
        }
    ],
    "sg:phone":"+43 1 661237081",
    "sg:postcode":"1100",
    "sg:province":"Wien",
    "wof:name":"Restaurant Fairway",
    "wof:placetype":"venue"
},
  "geometry": {"coordinates":[16.3394031525,48.1629943848],"type":"Point"}
}