{
  "type": "Feature",
  "properties": {
    "addr:full":"Bruckdorf 177 Mariapfarr Salzburg 5571",
    "addr:housenumber":"177",
    "addr:postcode":"5571",
    "addr:street":"Bruckdorf;Salzburg",
    "iso:country":"AT",
    "sg:address":"Bruckdorf 177",
    "sg:city":"Mariapfarr",
    "sg:orig_category":"Tischlereien",
    "sg:phone":"+43 4364 7373500",
    "sg:postcode":"5571",
    "sg:province":"Salzburg",
    "wof:name":"Grabner - G u A Moser Tischlerei u M\u00f6belhandel GnbR",
    "wof:placetype":"venue"
},
  "geometry": {"coordinates":[13.7240209579,47.153678894],"type":"Point"}
}