{
  "type": "Feature",
  "properties": {
    "addr:full":"Leo Slezak-G 6/2/1 Wien Wien 1180",
    "addr:housenumber":"6 / 2 / 1",
    "addr:postcode":"1180",
    "iso:country":"AT",
    "sg:address":"Leo Slezak-G 6/2/1",
    "sg:city":"Wien",
    "sg:orig_category":"Waren Aller Art",
    "sg:phone":"+43 1 4796746",
    "sg:postcode":"1180",
    "sg:province":"Wien",
    "wof:name":"PEEX HandelsgesmbH",
    "wof:placetype":"venue"
},
  "geometry": {"coordinates":[16.3445625305,48.2262420654],"type":"Point"}
}