{
  "type": "Feature",
  "properties": {
    "addr:full":"Georgiweg 270 Ehrenhausen Steiermark 8461",
    "addr:housenumber":"270",
    "addr:postcode":"8461",
    "addr:street":"Georgiweg",
    "iso:country":"AT",
    "sg:address":"Georgiweg 270",
    "sg:city":"Ehrenhausen",
    "sg:orig_category":"Hauptschulen",
    "sg:phone":"+43 3453 2669",
    "sg:postcode":"8461",
    "sg:province":"Steiermark",
    "wof:name":"Hauptschule",
    "wof:placetype":"venue"
},
  "geometry": {"coordinates":[15.5827035904,46.7275924683],"type":"Point"}
}