{
  "type": "Feature",
  "properties": {
    "addr:full":"Markt 39 Kuchl Salzburg 5431",
    "addr:housenumber":"39",
    "addr:postcode":"5431",
    "addr:street":"Markt;Salzburg",
    "iso:country":"AT",
    "sg:address":"Markt 39",
    "sg:city":"Kuchl",
    "sg:classifiers":[
        {
            "category":"Home & Garden",
            "subcategory":"Carpets & Floor Coverings",
            "type":"Retail Goods"
        }
    ],
    "sg:phone":"+43 6244 6476",
    "sg:postcode":"5431",
    "sg:province":"Salzburg",
    "sg:tags":[
        "carpeting"
    ],
    "wof:name":"Josef Rettenbacher",
    "wof:placetype":"venue"
},
  "geometry": {"coordinates":[13.1438016891,47.6257591248],"type":"Point"}
}