{
  "type": "Feature",
  "properties": {
    "iso:country":"AT",
    "sg:address":"Seilerst\u00e4tte 8",
    "sg:city":"Wien",
    "sg:orig_category":"Tonstudios",
    "sg:phone":"+43 1 9681237",
    "sg:postcode":"1010",
    "sg:province":"Wien",
    "wof:name":"Porsch Manfred - Tonstudio",
    "wof:placetype":"venue"
},
  "geometry": {"coordinates":[16.3761539459,48.2060623169],"type":"Point"}
}