{
  "type": "Feature",
  "properties": {
    "addr:full":"Montfortg 11 Feldkirch Vorarlberg 6800",
    "addr:housenumber":"11",
    "addr:postcode":"6800",
    "addr:street":"Montfortg",
    "iso:country":"AT",
    "sg:address":"Montfortg 11",
    "sg:city":"Feldkirch",
    "sg:orig_category":"Friseure U Frisiersalons",
    "sg:phone":"+43 4355 2231808",
    "sg:postcode":"6800",
    "sg:province":"Vorarlberg",
    "wof:name":"Frisiersalon Max Headroom",
    "wof:placetype":"venue"
},
  "geometry": {"coordinates":[9.5940933228,47.2373657227],"type":"Point"}
}