{
  "type": "Feature",
  "properties": {
    "addr:full":"Herrgottschnitzerg 8 Maria Enzersdorf Nieder\u00f6sterreich 2344",
    "addr:housenumber":"8",
    "addr:postcode":"2344",
    "addr:street":"Herrgottschnitzerg",
    "iso:country":"AT",
    "sg:address":"Herrgottschnitzerg 8",
    "sg:city":"Maria Enzersdorf",
    "sg:orig_category":"Elektroinstallationsunternehmen",
    "sg:phone":"+43 2236 421830",
    "sg:postcode":"2344",
    "sg:province":"Nieder\u00f6sterreich",
    "wof:name":"Elektro Stickler GesmbH",
    "wof:placetype":"venue"
},
  "geometry": {"coordinates":[16.2834415436,48.0998268127],"type":"Point"}
}