{
  "type": "Feature",
  "properties": {
    "addr:full":"Marktpl 8 Bad Zell Ober\u00f6sterreich 4283",
    "addr:housenumber":"8",
    "addr:postcode":"4283",
    "addr:street":"Marktpl",
    "iso:country":"AT",
    "sg:address":"Marktpl 8",
    "sg:city":"Bad Zell",
    "sg:orig_category":"Rettungsdienste",
    "sg:phone":"+43 7263 72440",
    "sg:postcode":"4283",
    "sg:province":"Ober\u00f6sterreich",
    "wof:name":"Rotes Kreuz \u00d6sterreichisches",
    "wof:placetype":"venue"
},
  "geometry": {"coordinates":[14.6695432663,48.3499679565],"type":"Point"}
}