{
  "type": "Feature",
  "properties": {
    "addr:full":"Dr.-Derfler-Str 2 Wolfern Ober\u00f6sterreich 4493",
    "addr:housenumber":"2",
    "addr:postcode":"4493",
    "addr:street":"Dr.-Derfler-Str",
    "iso:country":"AT",
    "sg:address":"Dr.-Derfler-Str 2",
    "sg:city":"Wolfern",
    "sg:orig_category":"Friseure U Frisiersalons",
    "sg:phone":"+43 4372 538293",
    "sg:postcode":"4493",
    "sg:province":"Ober\u00f6sterreich",
    "wof:name":"Hauser Rainer",
    "wof:placetype":"venue"
},
  "geometry": {"coordinates":[14.3795137405,48.082195282],"type":"Point"}
}