{
  "type": "Feature",
  "properties": {
    "addr:full":"Nr 3a Hausmannst\u00e4tten Steiermark 8071",
    "addr:housenumber":"3a",
    "addr:postcode":"8071",
    "addr:street":"Nr",
    "iso:country":"AT",
    "sg:address":"Nr 3a",
    "sg:city":"Hausmannst\u00e4tten",
    "sg:orig_category":"Schleifereien",
    "sg:phone":"+43 3135 47033",
    "sg:postcode":"8071",
    "sg:province":"Steiermark",
    "wof:name":"Salmhofer Franz - Sch\u00e4rfservice",
    "wof:placetype":"venue"
},
  "geometry": {"coordinates":[15.5542373657,47.0130844116],"type":"Point"}
}