{
  "type": "Feature",
  "properties": {
    "addr:full":"Nr 170 Ried im Oberinntal Tirol 6531",
    "addr:postcode":"6531",
    "addr:street":"Nr 170;Tirol",
    "iso:country":"AT",
    "sg:address":"Nr 170",
    "sg:city":"Ried im Oberinntal",
    "sg:orig_category":"Weiterbildungsinstitute M Allg U Berufl Bildungsangebot",
    "sg:phone":"+43 4354 72639624",
    "sg:postcode":"6531",
    "sg:province":"Tirol",
    "wof:name":"Erwachsenenschule Prutz-Ried u Umgebung",
    "wof:placetype":"venue"
},
  "geometry": {"coordinates":[10.654545784,47.0553817749],"type":"Point"}
}