{
  "type": "Feature",
  "properties": {
    "addr:full":"Obermarktstr 48 Telfs Tirol 6410",
    "addr:housenumber":"48",
    "addr:postcode":"6410",
    "addr:street":"Obermarktstr;Tirol",
    "iso:country":"AT",
    "sg:address":"Obermarktstr 48",
    "sg:city":"Telfs",
    "sg:orig_category":"Aluminiumbe- U -Verarbeitung",
    "sg:phone":"+43 4352 6269030",
    "sg:postcode":"6410",
    "sg:province":"Tirol",
    "wof:name":"Th\u00f6ni Industriebetriebe GmbH",
    "wof:placetype":"venue"
},
  "geometry": {"coordinates":[11.0669794083,47.3087043762],"type":"Point"}
}