{
  "type": "Feature",
  "properties": {
    "iso:country":"AT",
    "sg:address":"Nr 198",
    "sg:city":"Preding",
    "sg:orig_category":"Bestattungsunternehmen",
    "sg:phone":"+43 3185 31961",
    "sg:postcode":"8504",
    "sg:province":"Steiermark",
    "wof:name":"Pinter GesmbH",
    "wof:placetype":"venue"
},
  "geometry": {"coordinates":[15.4067401886,46.8597869873],"type":"Point"}
}