{
  "type": "Feature",
  "properties": {
    "addr:full":"Posthofplatz 1 Wels Ober\u00f6sterreich 4600",
    "addr:housenumber":"1",
    "addr:postcode":"4600",
    "addr:street":"Posthofplatz;Oberoesterreich",
    "iso:country":"AT",
    "sg:address":"Posthofplatz 1",
    "sg:city":"Wels",
    "sg:classifiers":[
        {
            "category":"Organizations",
            "subcategory":"Community Association",
            "type":"Services"
        }
    ],
    "sg:phone":"+43 7242 41691",
    "sg:postcode":"4600",
    "sg:province":"Ober\u00f6sterreich",
    "sg:tags":[
        "personnel",
        "placement"
    ],
    "sg:website":"go.to/elpa.at",
    "wof:name":"ELPA Personaldienstleistungs GmbH",
    "wof:placetype":"venue"
},
  "geometry": {"coordinates":[14.0147256851,48.1634750366],"type":"Point"}
}