{
  "type": "Feature",
  "properties": {
    "iso:country":"AT",
    "sg:address":"Kurze G 3",
    "sg:city":"Leobersdorf",
    "sg:orig_category":"Automatisierungstechnik",
    "sg:phone":"+43 2256 620700",
    "sg:postcode":"2544",
    "sg:province":"Nieder\u00f6sterreich",
    "wof:name":"Bernstein GmbH",
    "wof:placetype":"venue"
},
  "geometry": {"coordinates":[16.2136859894,47.9224739075],"type":"Point"}
}