{
  "type": "Feature",
  "properties": {
    "iso:country":"AT",
    "sg:address":"Salzburger Str 292",
    "sg:city":"Linz",
    "sg:orig_category":"Finanz- U Wirtschaftsberatung",
    "sg:phone":"+43 732 3759000",
    "sg:postcode":"4020",
    "sg:province":"Ober\u00f6sterreich",
    "wof:name":"AWD Beratungszentrum Linz",
    "wof:placetype":"venue"
},
  "geometry": {"coordinates":[14.2831678391,48.2542762756],"type":"Point"}
}