{
  "type": "Feature",
  "properties": {
    "addr:full":"Liechtensteinklammstr 11/1 St. Johann im Pongau Salzburg 5600",
    "addr:housenumber":"11 / 1",
    "addr:postcode":"5600",
    "addr:street":"Liechtensteinklammstr;Salzburg",
    "iso:country":"AT",
    "sg:address":"Liechtensteinklammstr 11/1",
    "sg:city":"St. Johann im Pongau",
    "sg:orig_category":"Werbeagenturen",
    "sg:phone":"+43 4364 1220091",
    "sg:postcode":"5600",
    "sg:province":"Salzburg",
    "sg:website":"ccom.at",
    "wof:name":"ccom Werbeagentur",
    "wof:placetype":"venue"
},
  "geometry": {"coordinates":[13.1998291016,47.3439102173],"type":"Point"}
}