{
  "type": "Feature",
  "properties": {
    "addr:full":"Salzburger Str 16 St. Johann in Tirol Tirol 6380",
    "addr:housenumber":"16",
    "addr:postcode":"6380",
    "addr:street":"Salzburger Str;Tirol",
    "iso:country":"AT",
    "sg:address":"Salzburger Str 16",
    "sg:city":"St. Johann in Tirol",
    "sg:orig_category":"Polizei U Gendarmerie",
    "sg:phone":"+43 4359 1337208",
    "sg:postcode":"6380",
    "sg:province":"Tirol",
    "wof:name":"Gendarmerieposten",
    "wof:placetype":"venue"
},
  "geometry": {"coordinates":[12.4231290817,47.5246162415],"type":"Point"}
}