{
  "type": "Feature",
  "properties": {
    "addr:full":"Vorstadt 2 Geras Nieder\u00f6sterreich 2093",
    "addr:housenumber":"2",
    "addr:postcode":"2093",
    "addr:street":"Vorstadt",
    "iso:country":"AT",
    "sg:address":"Vorstadt 2",
    "sg:city":"Geras",
    "sg:orig_category":"Architekten",
    "sg:phone":"+43 2912 4440",
    "sg:postcode":"2093",
    "sg:province":"Nieder\u00f6sterreich",
    "wof:name":"Trudak Christian Mag",
    "wof:placetype":"venue"
},
  "geometry": {"coordinates":[15.6725149155,48.8012733459],"type":"Point"}
}