{
  "type": "Feature",
  "properties": {
    "iso:country":"AT",
    "sg:address":"Nordbahnstr 6",
    "sg:city":"Laa an der Thaya",
    "sg:orig_category":"Geschenkartikel",
    "sg:phone":"+43 2522 2318",
    "sg:postcode":"2136",
    "sg:province":"Nieder\u00f6sterreich",
    "wof:name":"Pokorny Reinhard",
    "wof:placetype":"venue"
},
  "geometry": {"coordinates":[16.3843402863,48.7197380066],"type":"Point"}
}