{
  "type": "Feature",
  "properties": {
    "addr:full":"Schmiedingerstr 26 Salzburg Salzburg 5020",
    "addr:housenumber":"26",
    "addr:postcode":"5020",
    "addr:street":"Schmiedingerstr;Salzburg",
    "iso:country":"AT",
    "sg:address":"Schmiedingerstr 26",
    "sg:city":"Salzburg",
    "sg:orig_category":"Fenster",
    "sg:phone":"+43 4366 2421629",
    "sg:postcode":"5020",
    "sg:province":"Salzburg",
    "wof:name":"Savanovic Fenster & Fassaden KEG",
    "wof:placetype":"venue"
},
  "geometry": {"coordinates":[13.0052061081,47.8264694214],"type":"Point"}
}