{
  "type": "Feature",
  "properties": {
    "iso:country":"AT",
    "sg:address":"Abst\u00e4tten 21",
    "sg:city":"Mehrnbach",
    "sg:orig_category":"Haushaltsartikel",
    "sg:phone":"+43 7752 81128",
    "sg:postcode":"4941",
    "sg:province":"Ober\u00f6sterreich",
    "wof:name":"D\u00fcrnberger Elisabeth",
    "wof:placetype":"venue"
},
  "geometry": {"coordinates":[13.4231748581,48.2017440796],"type":"Point"}
}