{
  "type": "Feature",
  "properties": {
    "addr:full":"Suttnerstr 18 Wels Ober\u00f6sterreich 4600",
    "addr:housenumber":"18",
    "addr:postcode":"4600",
    "addr:street":"Suttnerstr;Oberoesterreich",
    "iso:country":"AT",
    "sg:address":"Suttnerstr 18",
    "sg:city":"Wels",
    "sg:orig_category":"Elektroinstallationsunternehmen",
    "sg:phone":"+43 7242 29082",
    "sg:postcode":"4600",
    "sg:province":"Ober\u00f6sterreich",
    "wof:name":"Elektrotechnik m System - Stangl Christian",
    "wof:placetype":"venue"
},
  "geometry": {"coordinates":[14.0541658401,48.1774101257],"type":"Point"}
}