{
  "type": "Feature",
  "properties": {
    "addr:full":"Pretul 6 Langenwang Steiermark 8665",
    "addr:housenumber":"6",
    "addr:postcode":"8665",
    "addr:street":"Pretul",
    "iso:country":"AT",
    "sg:address":"Pretul 6",
    "sg:city":"Langenwang",
    "sg:orig_category":"Schmieden U Schmiedeeisenelemente",
    "sg:phone":"+43 4338 5423380",
    "sg:postcode":"8665",
    "sg:province":"Steiermark",
    "wof:name":"Feiner GmbH",
    "wof:placetype":"venue"
},
  "geometry": {"coordinates":[15.6778564453,47.5606155396],"type":"Point"}
}