{
  "type": "Feature",
  "properties": {
    "addr:full":"Schlo\u00dfstr 26 Rohrbach an der G\u00f6lsen Nieder\u00f6sterreich 3163",
    "addr:housenumber":"26",
    "addr:postcode":"3163",
    "addr:street":"Schlossstr;Niederoesterreich",
    "iso:country":"AT",
    "sg:address":"Schlo\u00dfstr 26",
    "sg:city":"Rohrbach an der G\u00f6lsen",
    "sg:orig_category":"Transportunternehmen",
    "sg:phone":"+43 4327 642879",
    "sg:postcode":"3163",
    "sg:province":"Nieder\u00f6sterreich",
    "wof:name":"Gruber Franz",
    "wof:placetype":"venue"
},
  "geometry": {"coordinates":[15.7399196625,48.047454834],"type":"Point"}
}