{
  "type": "Feature",
  "properties": {
    "addr:full":"Mautner-Markhof-G 50/Top 4 Wien Wien 1110",
    "addr:housenumber":"50 / top 4",
    "addr:postcode":"1110",
    "addr:street":"Mautner-Markhof-G",
    "iso:country":"AT",
    "sg:address":"Mautner-Markhof-G 50/Top 4",
    "sg:city":"Wien",
    "sg:orig_category":"Reinigungsservice",
    "sg:phone":"+43 4317 187050",
    "sg:postcode":"1110",
    "sg:province":"Wien",
    "wof:name":"ABZ Hygiene-Service u HandelsgesmbH",
    "wof:placetype":"venue"
},
  "geometry": {"coordinates":[16.4197444916,48.1709709167],"type":"Point"}
}