{
  "type": "Feature",
  "properties": {
    "addr:full":"Klosterg 3 Dornbirn Vorarlberg 6850",
    "addr:housenumber":"3",
    "addr:postcode":"6850",
    "addr:street":"Klosterg",
    "iso:country":"AT",
    "sg:address":"Klosterg 3",
    "sg:city":"Dornbirn",
    "sg:orig_category":"Damenmoden",
    "sg:phone":"+43 4355 72372161",
    "sg:postcode":"6850",
    "sg:province":"Vorarlberg",
    "wof:name":"k.you - mode & dinge f\u00fcrs leben",
    "wof:placetype":"venue"
},
  "geometry": {"coordinates":[9.7410335541,47.4152793884],"type":"Point"}
}