{
  "type": "Feature",
  "properties": {
    "addr:full":"Frein 29 Frankenburg am Hausruck Ober\u00f6sterreich 4873",
    "addr:housenumber":"29",
    "addr:postcode":"4873",
    "addr:street":"Frein",
    "iso:country":"AT",
    "sg:address":"Frein 29",
    "sg:city":"Frankenburg am Hausruck",
    "sg:classifiers":[
        {
            "category":"Home & Garden",
            "subcategory":"Building Materials",
            "type":"Retail Goods"
        }
    ],
    "sg:phone":"+43 76838285",
    "sg:postcode":"4873",
    "sg:province":"Ober\u00f6sterreich",
    "sg:tags":[
        "railing",
        "balcony"
    ],
    "wof:name":"Hausruckschmiede H. Streicher",
    "wof:placetype":"venue"
},
  "geometry": {"coordinates":[13.4651069641,48.0878677368],"type":"Point"}
}