{
  "type": "Feature",
  "properties": {
    "addr:full":"Seestr 5 Hard Vorarlberg 6971",
    "addr:housenumber":"5",
    "addr:postcode":"6971",
    "addr:street":"Seestr",
    "iso:country":"AT",
    "sg:address":"Seestr 5",
    "sg:city":"Hard",
    "sg:orig_category":"Schablonen",
    "sg:phone":"+43 4355 7472301",
    "sg:postcode":"6971",
    "sg:province":"Vorarlberg",
    "wof:name":"Schw\u00e4rzler GmbH",
    "wof:placetype":"venue"
},
  "geometry": {"coordinates":[9.6879072189,47.4885406494],"type":"Point"}
}