{
  "type": "Feature",
  "properties": {
    "addr:full":"Grazbachgasse 21-23 Graz Steiermark 8010",
    "addr:postcode":"21-23;8010",
    "addr:street":"Grazbachgasse",
    "iso:country":"AT",
    "sg:address":"Grazbachgasse 21-23",
    "sg:city":"Graz",
    "sg:classifiers":[
        {
            "category":"Professional",
            "subcategory":"Printing & Photocopies",
            "type":"Services"
        }
    ],
    "sg:phone":"+43 316 8217170",
    "sg:postcode":"8010",
    "sg:province":"Steiermark",
    "sg:tags":[
        "shop",
        "digital"
    ],
    "wof:name":"repro r\u00f6gner Rabitsch Ges.m.b.H",
    "wof:placetype":"venue"
},
  "geometry": {"coordinates":[15.4449825287,47.065788269],"type":"Point"}
}