{
  "type": "Feature",
  "properties": {
    "iso:country":"AT",
    "sg:address":"Gewerbehof 1",
    "sg:city":"Kufstein",
    "sg:orig_category":"Glasgraveure U -\u00c3\u201etzereien",
    "sg:phone":"+43 4353 7263826",
    "sg:postcode":"6330",
    "sg:province":"Tirol",
    "wof:name":"Peckl Rene - Glasgravuren",
    "wof:placetype":"venue"
},
  "geometry": {"coordinates":[12.1711168289,47.5845909119],"type":"Point"}
}