{
  "type": "Feature",
  "properties": {
    "addr:full":"Oberdorf 11 Lermoos Tirol 6631",
    "addr:housenumber":"11",
    "addr:postcode":"6631",
    "addr:street":"Oberdorf;Tirol",
    "iso:country":"AT",
    "sg:address":"Oberdorf 11",
    "sg:city":"Lermoos",
    "sg:orig_category":"Appartements / Ferienwohnungen",
    "sg:phone":"+43 4356 732264",
    "sg:postcode":"6631",
    "sg:province":"Tirol",
    "wof:name":"Brida-Hofherr Susanna Drmedvet Sonnenhof",
    "wof:placetype":"venue"
},
  "geometry": {"coordinates":[10.8852329254,47.397808075],"type":"Point"}
}