{
  "type": "Feature",
  "properties": {
    "addr:full":"Fl\u00f6\u00dferstr 1 Scharnstein Ober\u00f6sterreich 4644",
    "addr:housenumber":"1",
    "addr:postcode":"4644",
    "addr:street":"Floesserstr",
    "iso:country":"AT",
    "sg:address":"Fl\u00f6\u00dferstr 1",
    "sg:city":"Scharnstein",
    "sg:orig_category":"Appartements / Ferienwohnungen",
    "sg:phone":"+43 76157555",
    "sg:postcode":"4644",
    "sg:province":"Ober\u00f6sterreich",
    "wof:name":"Lohner Peter",
    "wof:placetype":"venue"
},
  "geometry": {"coordinates":[13.962269783,47.9045448303],"type":"Point"}
}