{
  "type": "Feature",
  "properties": {
    "addr:full":"Haider Str 38 Ansfelden Ober\u00f6sterreich 4052",
    "addr:postcode":"4052",
    "addr:street":"Str 38",
    "iso:country":"AT",
    "sg:address":"Haider Str 38",
    "sg:city":"Ansfelden",
    "sg:orig_category":"Fleischereimaschinen U -Einrichtungen",
    "sg:phone":"+43 7229 82175",
    "sg:postcode":"4052",
    "sg:province":"Ober\u00f6sterreich",
    "wof:name":"Toperczer - Linz",
    "wof:placetype":"venue"
},
  "geometry": {"coordinates":[14.2810564041,48.2113647461],"type":"Point"}
}