{
  "type": "Feature",
  "properties": {
    "addr:full":"Industriestr 25 Haid Ober\u00f6sterreich 4053",
    "addr:housenumber":"25",
    "addr:postcode":"4053",
    "addr:street":"Industriestr",
    "iso:country":"AT",
    "sg:address":"Industriestr 25",
    "sg:city":"Haid",
    "sg:classifiers":[
        {
            "category":"Recreation",
            "subcategory":"Theme Park",
            "type":"Entertainment"
        }
    ],
    "sg:phone":"+43 7229 887010",
    "sg:postcode":"4053",
    "sg:province":"Ober\u00f6sterreich",
    "sg:tags":[
        "stahl"
    ],
    "wof:name":"BEST Baueisen- und StahlbearbeitungsgesmbH",
    "wof:placetype":"venue"
},
  "geometry": {"coordinates":[14.2602996826,48.2097244263],"type":"Point"}
}