{
  "type": "Feature",
  "properties": {
    "addr:full":"Rathauspl 51 Wolfsberg K\u00e4rnten 9400",
    "addr:housenumber":"51;kaernten",
    "addr:postcode":"9400",
    "addr:street":"Rathauspl",
    "iso:country":"AT",
    "sg:address":"Rathauspl 51",
    "sg:city":"Wolfsberg",
    "sg:orig_category":"Bestattungsunternehmen",
    "sg:phone":"+43 4352 2792",
    "sg:postcode":"9400",
    "sg:province":"K\u00e4rnten",
    "wof:name":"St\u00e4dtische Bestattung Wolfsberg- Zweigstelle Wolfsberg",
    "wof:placetype":"venue"
},
  "geometry": {"coordinates":[14.8440828323,46.8405952454],"type":"Point"}
}