{
  "type": "Feature",
  "properties": {
    "addr:full":"Hauptpl 2 Bleiburg K\u00e4rnten 9150",
    "addr:housenumber":"2",
    "addr:postcode":"9150",
    "addr:street":"Hauptpl;Kaernten",
    "iso:country":"AT",
    "sg:address":"Hauptpl 2",
    "sg:city":"Bleiburg",
    "sg:orig_category":"Apotheken",
    "sg:phone":"+43 4235 2036",
    "sg:postcode":"9150",
    "sg:province":"K\u00e4rnten",
    "wof:name":"Apotheke Bleiburg Mag pharm Heidi Kreiner",
    "wof:placetype":"venue"
},
  "geometry": {"coordinates":[14.7994699478,46.590045929],"type":"Point"}
}