{
  "type": "Feature",
  "properties": {
    "addr:full":"Wexstr 24 Wien Wien 1200",
    "addr:housenumber":"24",
    "addr:postcode":"1200",
    "addr:street":"Wexstr",
    "iso:country":"AT",
    "sg:address":"Wexstr 24",
    "sg:city":"Wien",
    "sg:orig_category":"Ingenieurkonsulenten / Zivilingenieure",
    "sg:phone":"+43 1 3507363",
    "sg:postcode":"1200",
    "sg:province":"Wien",
    "wof:name":"B\u00f6sm\u00fcller Helmut Dipl-Ing Ziviltechniker GmbH",
    "wof:placetype":"venue"
},
  "geometry": {"coordinates":[16.368888855,48.2359428406],"type":"Point"}
}