{
  "type": "Feature",
  "properties": {
    "addr:full":"Lagerg 98a Graz Steiermark 8020",
    "addr:housenumber":"98a",
    "addr:postcode":"8020",
    "addr:street":"Lagerg",
    "iso:country":"AT",
    "sg:address":"Lagerg 98a",
    "sg:city":"Graz",
    "sg:orig_category":"Politische Parteien",
    "sg:phone":"+43 316 712436",
    "sg:postcode":"8020",
    "sg:province":"Steiermark",
    "wof:name":"Kommunistische Partei \u00f6sterreichs (KP\u00f6)",
    "wof:placetype":"venue"
},
  "geometry": {"coordinates":[15.43318367,47.0587005615],"type":"Point"}
}