{
  "type": "Feature",
  "properties": {
    "addr:full":"Viller Steig 2 Innsbruck-Igls Tirol 6080",
    "addr:housenumber":"2",
    "addr:postcode":"6080",
    "addr:street":"Viller Steig",
    "iso:country":"AT",
    "sg:address":"Viller Steig 2",
    "sg:city":"Innsbruck-Igls",
    "sg:classifiers":[
        {
            "category":"Travel",
            "subcategory":"Hotels & Motels",
            "type":"Entertainment"
        }
    ],
    "sg:phone":"+43 512 3772170",
    "sg:postcode":"6080",
    "sg:province":"Tirol",
    "wof:name":"Schlo\u00dfhotel Igls",
    "wof:placetype":"venue"
},
  "geometry": {"coordinates":[11.4072217941,47.2324409485],"type":"Point"}
}