{
  "type": "Feature",
  "properties": {
    "addr:full":"Untergasse 8 Serfaus Tirol 6534",
    "addr:housenumber":"8",
    "addr:postcode":"6534",
    "addr:street":"Untergasse;Tirol",
    "iso:country":"AT",
    "sg:address":"Untergasse 8",
    "sg:city":"Serfaus",
    "sg:orig_category":"Pensionen / Privatzimmer",
    "sg:phone":"+43 5476 62660",
    "sg:postcode":"6534",
    "sg:province":"Tirol",
    "wof:name":"Pension Geiger",
    "wof:placetype":"venue"
},
  "geometry": {"coordinates":[10.607629776,47.0369186401],"type":"Point"}
}