{
  "type": "Feature",
  "properties": {
    "iso:country":"AT",
    "sg:address":"Niederndorf 19",
    "sg:city":"Gallspach",
    "sg:classifiers":[
        {
            "category":"Manufacturing",
            "subcategory":"Wood Products",
            "type":"Manufacturing & Wholesale Goods"
        }
    ],
    "sg:phone":"+43 7248 62384",
    "sg:postcode":"4713",
    "sg:province":"Ober\u00f6sterreich",
    "sg:tags":[
        "lumber"
    ],
    "wof:name":"Johann M\u00fchlberger S\u00e4ge- und Hobelwerk",
    "wof:placetype":"venue"
},
  "geometry": {"coordinates":[13.817152977,48.2125015259],"type":"Point"}
}