{
  "type": "Feature",
  "properties": {
    "addr:full":"Grazer Strasse 12 Fernitz Steiermark 8072",
    "addr:housenumber":"12",
    "addr:postcode":"8072",
    "addr:street":"Grazer Strasse",
    "iso:country":"AT",
    "sg:address":"Grazer Strasse 12",
    "sg:city":"Fernitz",
    "sg:classifiers":[
        {
            "category":"Food & Beverages",
            "subcategory":"Bakery",
            "type":"Retail Goods"
        }
    ],
    "sg:phone":"+43 3135 52853",
    "sg:postcode":"8072",
    "sg:province":"Steiermark",
    "sg:tags":[
        "dough",
        "dumpling"
    ],
    "wof:name":"Il Pastaio Teigwarenerzeugung Zinner KG",
    "wof:placetype":"venue"
},
  "geometry": {"coordinates":[15.4990787506,46.9737854004],"type":"Point"}
}