{
  "type": "Feature",
  "properties": {
    "addr:full":"Quellenstr 131 Wien Wien 1100",
    "addr:housenumber":"131",
    "addr:postcode":"1100",
    "iso:country":"AT",
    "sg:address":"Quellenstr 131",
    "sg:city":"Wien",
    "sg:orig_category":"Juwelen, Gold- U Silberwaren / Einzelhandel",
    "sg:phone":"+43 4316 045131",
    "sg:postcode":"1100",
    "sg:province":"Wien",
    "wof:name":"Waiglein Christine",
    "wof:placetype":"venue"
},
  "geometry": {"coordinates":[16.3746032715,48.1754493713],"type":"Point"}
}