{
  "type": "Feature",
  "properties": {
    "addr:full":"Ernst-Vogel-Str 2 Stockerau Nieder\u00f6sterreich 2000",
    "addr:housenumber":"2",
    "addr:postcode":"2000",
    "addr:street":"Ernst-Vogel-Str",
    "iso:country":"AT",
    "sg:address":"Ernst-Vogel-Str 2",
    "sg:city":"Stockerau",
    "sg:orig_category":"Pumpen",
    "sg:phone":"+43 2266 6040",
    "sg:postcode":"2000",
    "sg:province":"Nieder\u00f6sterreich",
    "sg:website":"vogel-pumpen.com",
    "wof:name":"Pumpenfabrik Ernst Vogel GmbH",
    "wof:placetype":"venue"
},
  "geometry": {"coordinates":[16.1973304749,48.3883018494],"type":"Point"}
}