{
  "type": "Feature",
  "properties": {
    "addr:full":"Horner Str 16 Ziersdorf Nieder\u00f6sterreich 3710",
    "addr:housenumber":"16",
    "addr:postcode":"3710",
    "addr:street":"Str",
    "iso:country":"AT",
    "sg:address":"Horner Str 16",
    "sg:city":"Ziersdorf",
    "sg:orig_category":"Fleischhauereien",
    "sg:phone":"+43 2956 22180",
    "sg:postcode":"3710",
    "sg:province":"Nieder\u00f6sterreich",
    "wof:name":"Lembacher Harald",
    "wof:placetype":"venue"
},
  "geometry": {"coordinates":[15.9252710342,48.5286140442],"type":"Point"}
}