{
  "type": "Feature",
  "properties": {
    "iso:country":"AT",
    "sg:address":"Nockhofweg 47",
    "sg:city":"Mutters",
    "sg:orig_category":"Pensionen / Privatzimmer",
    "sg:phone":"+43 512 548582",
    "sg:postcode":"6162",
    "sg:province":"Tirol",
    "wof:name":"Nockhof",
    "wof:placetype":"venue"
},
  "geometry": {"coordinates":[11.371014595,47.2226905823],"type":"Point"}
}