{
  "type": "Feature",
  "properties": {
    "addr:full":"St. Pantaleon Ober\u00f6sterreich 5120",
    "addr:postcode":"5120",
    "addr:street":"Oberoesterreich",
    "iso:country":"AT",
    "sg:city":"St. Pantaleon",
    "sg:orig_category":"Feuerwehren",
    "sg:phone":"+43 664 6309883",
    "sg:postcode":"5120",
    "sg:province":"Ober\u00f6sterreich",
    "wof:name":"Freiwillige Feuerwehr Wildshut",
    "wof:placetype":"venue"
},
  "geometry": {"coordinates":[12.8668022156,48.0077934265],"type":"Point"}
}