{
  "type": "Feature",
  "properties": {
    "addr:full":"Hietzinger Hauptstr 38b Wien Wien 1130",
    "addr:housenumber":"38b",
    "addr:postcode":"1130",
    "addr:street":"Hietzinger Hauptstr",
    "iso:country":"AT",
    "sg:address":"Hietzinger Hauptstr 38b",
    "sg:city":"Wien",
    "sg:orig_category":"Tapezierer U Dekorateure",
    "sg:phone":"+43 4318 775564",
    "sg:postcode":"1130",
    "sg:province":"Wien",
    "wof:name":"Mayer Johann Josef Inh Ernst Schmidt",
    "wof:placetype":"venue"
},
  "geometry": {"coordinates":[16.2954311371,48.1870613098],"type":"Point"}
}