{
  "type": "Feature",
  "properties": {
    "iso:country":"AT",
    "sg:address":"Tiroler Strasse 53",
    "sg:city":"Villach",
    "sg:classifiers":[
        {
            "category":"Government",
            "subcategory":"Fire Station",
            "type":"Public Place"
        }
    ],
    "sg:phone":"+43 4242 536750",
    "sg:postcode":"9500",
    "sg:province":"K\u00e4rnten",
    "sg:tags":[
        "alloy",
        "light",
        "aluminium",
        "processing"
    ],
    "wof:name":"Metallbau Franz Weinstich",
    "wof:placetype":"venue"
},
  "geometry": {"coordinates":[13.8302326202,46.6141662598],"type":"Point"}
}