{
  "type": "Feature",
  "properties": {
    "iso:country":"AT",
    "sg:address":"Obtarrenzer Str 2",
    "sg:city":"Tarrenz",
    "sg:orig_category":"Appartements / Ferienwohnungen",
    "sg:phone":"+43 4354 1265711",
    "sg:postcode":"6464",
    "sg:province":"Tirol",
    "wof:name":"Chalet Elisabeth - Fam Tangl",
    "wof:placetype":"venue"
},
  "geometry": {"coordinates":[10.7692327499,47.2716827393],"type":"Point"}
}