{
  "type": "Feature",
  "properties": {
    "addr:full":"Roseggerstr 30 Innsbruck Tirol 6020",
    "addr:housenumber":"30",
    "addr:postcode":"6020",
    "addr:street":"Roseggerstr;Tirol",
    "iso:country":"AT",
    "sg:address":"Roseggerstr 30",
    "sg:city":"Innsbruck",
    "sg:orig_category":"Installationsunternehmen",
    "sg:phone":"+43 512 344322",
    "sg:postcode":"6020",
    "sg:province":"Tirol",
    "wof:name":"Nikosan - Nikolaus Scharnagl",
    "wof:placetype":"venue"
},
  "geometry": {"coordinates":[11.4118528366,47.2604179382],"type":"Point"}
}