{
  "type": "Feature",
  "properties": {
    "addr:full":"Hauptstr 4 Wolkersdorf im Weinviertel Nieder\u00f6sterreich 2120",
    "addr:housenumber":"4",
    "addr:postcode":"2120",
    "addr:street":"Hauptstr",
    "iso:country":"AT",
    "sg:address":"Hauptstr 4",
    "sg:city":"Wolkersdorf im Weinviertel",
    "sg:orig_category":"Friseure U Frisiersalons",
    "sg:phone":"+43 2245 5566",
    "sg:postcode":"2120",
    "sg:province":"Nieder\u00f6sterreich",
    "wof:name":"Frisiersalon Dana",
    "wof:placetype":"venue"
},
  "geometry": {"coordinates":[16.52684021,48.367023468],"type":"Point"}
}