{
  "type": "Feature",
  "properties": {
    "addr:full":"Burgg 93 Wien Wien 1070",
    "addr:housenumber":"93",
    "addr:postcode":"1070",
    "addr:street":"Burgg",
    "iso:country":"AT",
    "sg:address":"Burgg 93",
    "sg:city":"Wien",
    "sg:orig_category":"Versicherungsunternehmen",
    "sg:phone":"+43 1 5237430",
    "sg:postcode":"1070",
    "sg:province":"Wien",
    "wof:name":"AXA Nordstern-Colonia Versicherungs AG",
    "wof:placetype":"venue"
},
  "geometry": {"coordinates":[16.3426418304,48.204284668],"type":"Point"}
}