{
  "type": "Feature",
  "properties": {
    "iso:country":"AT",
    "sg:address":"Sackstr 14",
    "sg:city":"Mooskirchen",
    "sg:orig_category":"Tischlereien",
    "sg:phone":"+43 4331 3722260",
    "sg:postcode":"8562",
    "sg:province":"Steiermark",
    "wof:name":"Ulrych Hubert",
    "wof:placetype":"venue"
},
  "geometry": {"coordinates":[15.283370018,46.981967926],"type":"Point"}
}