{
  "type": "Feature",
  "properties": {
    "addr:full":"Wernhardtstr 24 Wien Wien 1160",
    "addr:housenumber":"24",
    "addr:postcode":"1160",
    "addr:street":"Wernhardtstr",
    "iso:country":"AT",
    "sg:address":"Wernhardtstr 24",
    "sg:city":"Wien",
    "sg:orig_category":"Lebensmittel / Einzelhandel",
    "sg:phone":"+43 1 9291628",
    "sg:postcode":"1160",
    "sg:province":"Wien",
    "wof:name":"Billa AG",
    "wof:placetype":"venue"
},
  "geometry": {"coordinates":[16.30509758,48.2085037231],"type":"Point"}
}