{
  "type": "Feature",
  "properties": {
    "iso:country":"AT",
    "sg:address":"Gumpendorfer Str 109",
    "sg:city":"Wien",
    "sg:orig_category":"Friseure U Frisiersalons",
    "sg:phone":"+43 4315 976807",
    "sg:postcode":"1060",
    "sg:province":"Wien",
    "wof:name":"Sz\u00f6ts Rosemarie",
    "wof:placetype":"venue"
},
  "geometry": {"coordinates":[16.3470897675,48.1909828186],"type":"Point"}
}