{
  "type": "Feature",
  "properties": {
    "iso:country":"AT",
    "sg:address":"Erzherzog-Karl-Str 21",
    "sg:city":"Wien",
    "sg:orig_category":"Autohandel",
    "sg:phone":"+43 1 2606625",
    "sg:postcode":"1220",
    "sg:province":"Wien",
    "wof:name":"Seat Schwandl",
    "wof:placetype":"venue"
},
  "geometry": {"coordinates":[16.4356498718,48.237285614],"type":"Point"}
}