{
  "type": "Feature",
  "properties": {
    "iso:country":"AT",
    "sg:address":"Leitermayerg 6",
    "sg:city":"Wien",
    "sg:orig_category":"Siebdruckereien",
    "sg:phone":"+43 1 4084982",
    "sg:postcode":"1170",
    "sg:province":"Wien",
    "wof:name":"Prodecor Werbebedarf",
    "wof:placetype":"venue"
},
  "geometry": {"coordinates":[16.3354434967,48.2210464478],"type":"Point"}
}