{
  "type": "Feature",
  "properties": {
    "iso:country":"AT",
    "sg:address":"Nelkenstr 56",
    "sg:city":"Kottingbrunn",
    "sg:orig_category":"Medizintechnik",
    "sg:phone":"+43 2252 77111",
    "sg:postcode":"2542",
    "sg:province":"Nieder\u00f6sterreich",
    "wof:name":"Meddiscount Handels-GmbH",
    "wof:placetype":"venue"
},
  "geometry": {"coordinates":[16.2265396118,47.9402542114],"type":"Point"}
}