{
  "type": "Feature",
  "properties": {
    "iso:country":"AT",
    "sg:address":"Harrachg 5",
    "sg:city":"Wien",
    "sg:classifiers":[
        {
            "category":"Taxi",
            "type":"Transportation"
        }
    ],
    "sg:phone":"+43 1 2699034",
    "sg:postcode":"1220",
    "sg:province":"Wien",
    "sg:tags":[
        "personentransporte",
        "u"
    ],
    "wof:name":"Hurban G\u00fcnther",
    "wof:placetype":"venue"
},
  "geometry": {"coordinates":[16.4264278412,48.2232704163],"type":"Point"}
}