{
  "type": "Feature",
  "properties": {
    "addr:full":"Gartenstadt 1 Sigmundsherberg Nieder\u00f6sterreich 3751",
    "addr:housenumber":"1",
    "addr:postcode":"3751",
    "addr:street":"Gartenstadt",
    "iso:country":"AT",
    "sg:address":"Gartenstadt 1",
    "sg:city":"Sigmundsherberg",
    "sg:orig_category":"Banken U Sparkassen",
    "sg:phone":"+43 4350 10026590",
    "sg:postcode":"3751",
    "sg:province":"Nieder\u00f6sterreich",
    "wof:name":"Weinviertler Sparkasse AG",
    "wof:placetype":"venue"
},
  "geometry": {"coordinates":[15.7457838058,48.6873321533],"type":"Point"}
}