{
  "type": "Feature",
  "properties": {
    "addr:full":"Anton-Schneider-Str 16 Bregenz Vorarlberg 6900",
    "addr:housenumber":"16",
    "addr:postcode":"6900",
    "addr:street":"Anton-Schneider-Str",
    "iso:country":"AT",
    "sg:address":"Anton-Schneider-Str 16",
    "sg:city":"Bregenz",
    "sg:orig_category":"Immobilienmakler",
    "sg:phone":"+43 5574 77553",
    "sg:postcode":"6900",
    "sg:province":"Vorarlberg",
    "wof:name":"Immobilien Stocker KEG",
    "wof:placetype":"venue"
},
  "geometry": {"coordinates":[9.7482004166,47.5037574768],"type":"Point"}
}