{
  "type": "Feature",
  "properties": {
    "iso:country":"AT",
    "sg:address":"Alois Orth-Allee 12",
    "sg:city":"Gloggnitz",
    "sg:orig_category":"Ingenieurkonsulenten / Zivilingenieure",
    "sg:phone":"+43 2662 44387",
    "sg:postcode":"2640",
    "sg:province":"Nieder\u00f6sterreich",
    "wof:name":"Zisser Helmut Dipl-Ing",
    "wof:placetype":"venue"
},
  "geometry": {"coordinates":[15.96276474,47.6773414612],"type":"Point"}
}