{
  "type": "Feature",
  "properties": {
    "addr:full":"Hoveng 3/4/9 Korneuburg Nieder\u00f6sterreich 2100",
    "addr:housenumber":"3 / 4 / 9",
    "addr:postcode":"2100",
    "addr:street":"Hoveng;Niederoesterreich",
    "iso:country":"AT",
    "sg:address":"Hoveng 3/4/9",
    "sg:city":"Korneuburg",
    "sg:classifiers":[
        {
            "category":"Organizations",
            "subcategory":"Community Association",
            "type":"Services"
        }
    ],
    "sg:phone":"+43 4366 45409157",
    "sg:postcode":"2100",
    "sg:province":"Nieder\u00f6sterreich",
    "sg:tags":[
        "relation",
        "public"
    ],
    "wof:name":"Melzer Helmut",
    "wof:placetype":"venue"
},
  "geometry": {"coordinates":[16.3329143524,48.3437843323],"type":"Point"}
}