{
  "type": "Feature",
  "properties": {
    "iso:country":"AT",
    "sg:address":"8.Mai-Str 2",
    "sg:city":"Klagenfurt",
    "sg:orig_category":"Massagen",
    "sg:phone":"+43 4346 355390",
    "sg:postcode":"9020",
    "sg:province":"K\u00e4rnten",
    "wof:name":"Buchacher Massage",
    "wof:placetype":"venue"
},
  "geometry": {"coordinates":[14.3069906235,46.6229820251],"type":"Point"}
}