{
  "type": "Feature",
  "properties": {
    "addr:full":"Nr 1 H\u00fcttenberg K\u00e4rnten 9375",
    "addr:postcode":"9375",
    "addr:street":"Nr;Huettenberg",
    "iso:country":"AT",
    "sg:address":"Nr 1",
    "sg:city":"H\u00fcttenberg",
    "sg:orig_category":"Werbeagenturen",
    "sg:phone":"+43 4263 8522",
    "sg:postcode":"9375",
    "sg:province":"K\u00e4rnten",
    "wof:name":"Rachle Werbeagentur",
    "wof:placetype":"venue"
},
  "geometry": {"coordinates":[14.5481901169,46.9406700134],"type":"Point"}
}