{
  "type": "Feature",
  "properties": {
    "addr:full":"Nr 161 Edelschrott Steiermark 8583",
    "addr:postcode":"8583",
    "addr:street":"Nr;Edelschrott",
    "iso:country":"AT",
    "sg:address":"Nr 161",
    "sg:city":"Edelschrott",
    "sg:orig_category":"Hauskrankenpflege / Heimhilfe",
    "sg:phone":"+43 3145 657",
    "sg:postcode":"8583",
    "sg:province":"Steiermark",
    "wof:name":"Hauskrankenpflege Edelschrott",
    "wof:placetype":"venue"
},
  "geometry": {"coordinates":[15.0517597198,47.0216178894],"type":"Point"}
}