{
  "type": "Feature",
  "properties": {
    "iso:country":"AT",
    "sg:address":"Tiergartenstr 125",
    "sg:city":"Innsbruck",
    "sg:classifiers":[
        {
            "category":"Utilities",
            "subcategory":"Refuse",
            "type":"Services"
        }
    ],
    "sg:phone":"+43 4351 22720010",
    "sg:postcode":"6020",
    "sg:province":"Tirol",
    "sg:tags":[
        "catering"
    ],
    "wof:name":"CATERING Services GmbH",
    "wof:placetype":"venue"
},
  "geometry": {"coordinates":[11.3616609573,47.256893158],"type":"Point"}
}