{
  "type": "Feature",
  "properties": {
    "addr:full":"Vituspl 1 Kritzendorf Nieder\u00f6sterreich 3420",
    "addr:housenumber":"1",
    "addr:postcode":"3420",
    "addr:street":"Vituspl",
    "iso:country":"AT",
    "sg:address":"Vituspl 1",
    "sg:city":"Kritzendorf",
    "sg:orig_category":"Non-Classified Establishments",
    "sg:phone":"+43 2243 244670",
    "sg:postcode":"3420",
    "sg:province":"Nieder\u00f6sterreich",
    "wof:name":"Pfarramt Kritzendorf",
    "wof:placetype":"venue"
},
  "geometry": {"coordinates":[16.3026752472,48.3274993896],"type":"Point"}
}