{
  "type": "Feature",
  "properties": {
    "addr:full":"Budweiser Str 1 Schrems Nieder\u00f6sterreich 3943",
    "addr:housenumber":"1",
    "addr:postcode":"3943",
    "addr:street":"Str",
    "iso:country":"AT",
    "sg:address":"Budweiser Str 1",
    "sg:city":"Schrems",
    "sg:orig_category":"Handarbeiten",
    "sg:phone":"+43 2853 76074",
    "sg:postcode":"3943",
    "sg:province":"Nieder\u00f6sterreich",
    "wof:name":"Hobbiger Handarbeiten",
    "wof:placetype":"venue"
},
  "geometry": {"coordinates":[15.0658893585,48.7939529419],"type":"Point"}
}