{
  "type": "Feature",
  "properties": {
    "addr:full":"Hainburger Str. 34/1/13 Wien Wien 1030",
    "addr:housenumber":"34 / 1 / 13",
    "addr:postcode":"1030",
    "addr:street":"Str.",
    "iso:country":"AT",
    "sg:address":"Hainburger Str. 34/1/13",
    "sg:city":"Wien",
    "sg:orig_category":"Miscellaneous Products",
    "sg:phone":"+43 4317 109267",
    "sg:postcode":"1030",
    "sg:province":"Wien",
    "sg:website":"altesse.at",
    "wof:name":"ALTESSE ZIGARETTENH\u00dcLLENERZEUGUNG UND PAPIERVERARBEITUNG GESMBH",
    "wof:placetype":"venue"
},
  "geometry": {"coordinates":[16.4025096893,48.1936683655],"type":"Point"}
}