{
  "type": "Feature",
  "properties": {
    "iso:country":"AT",
    "sg:address":"Fernkorng 88",
    "sg:city":"Wien",
    "sg:orig_category":"Bauunternehmen",
    "sg:phone":"+43 1 6005073",
    "sg:postcode":"1100",
    "sg:province":"Wien",
    "wof:name":"MTB Grausam KEG",
    "wof:placetype":"venue"
},
  "geometry": {"coordinates":[16.361951828,48.1685600281],"type":"Point"}
}