{
  "type": "Feature",
  "properties": {
    "iso:country":"AT",
    "sg:address":"Nr 285",
    "sg:city":"Vorau",
    "sg:orig_category":"Autoreparatur",
    "sg:phone":"+43 3337 2284",
    "sg:postcode":"8250",
    "sg:province":"Steiermark",
    "sg:website":"autohaus-kremnitzer.at",
    "wof:name":"Kremnitzer F GesmbH & Co KG",
    "wof:placetype":"venue"
},
  "geometry": {"coordinates":[15.8873929977,47.4056854248],"type":"Point"}
}