{
  "type": "Feature",
  "properties": {
    "addr:full":"Eckberger Weinstr 94 Gamlitz Steiermark 8462",
    "addr:housenumber":"94",
    "addr:postcode":"8462",
    "addr:street":"Weinstr",
    "iso:country":"AT",
    "sg:address":"Eckberger Weinstr 94",
    "sg:city":"Gamlitz",
    "sg:orig_category":"Rettungsdienste",
    "sg:phone":"+43 3453 20440",
    "sg:postcode":"8462",
    "sg:province":"Steiermark",
    "wof:name":"\u00f6sterreichisches Rotes Kreuz",
    "wof:placetype":"venue"
},
  "geometry": {"coordinates":[15.5502300262,46.716293335],"type":"Point"}
}