{
  "type": "Feature",
  "properties": {
    "iso:country":"AT",
    "sg:address":"Mitterweg 58a",
    "sg:city":"Innsbruck",
    "sg:orig_category":"Apotheken",
    "sg:phone":"+43 512 2922990",
    "sg:postcode":"6020",
    "sg:province":"Tirol",
    "wof:name":"Apotheke am Mitterweg Mag pharm Dr Ignaz Moser",
    "wof:placetype":"venue"
},
  "geometry": {"coordinates":[11.3699016571,47.2578887939],"type":"Point"}
}