{
  "type": "Feature",
  "properties": {
    "addr:full":"Matzling 164 Gr\u00f6bming Steiermark 8962",
    "addr:housenumber":"164",
    "addr:postcode":"8962",
    "addr:street":"Matzling",
    "iso:country":"AT",
    "sg:address":"Matzling 164",
    "sg:city":"Gr\u00f6bming",
    "sg:orig_category":"Lichttechnik",
    "sg:phone":"+43 3684 30066",
    "sg:postcode":"8962",
    "sg:province":"Steiermark",
    "wof:name":"VEDDER LICHTMANAGEMENT - Dipl-Ing Reinhard Vedder",
    "wof:placetype":"venue"
},
  "geometry": {"coordinates":[13.9442605972,47.4664154053],"type":"Point"}
}