{
  "type": "Feature",
  "properties": {
    "addr:full":"Nr 4 Sch\u00f6nau im M\u00fchlkreis Ober\u00f6sterreich 4274",
    "addr:postcode":"4274",
    "addr:street":"Nr;Im Muehlkreis Oberoesterreich",
    "iso:country":"AT",
    "sg:address":"Nr 4",
    "sg:city":"Sch\u00f6nau im M\u00fchlkreis",
    "sg:orig_category":"Banken U Sparkassen",
    "sg:phone":"+43 4372 6173710",
    "sg:postcode":"4274",
    "sg:province":"Ober\u00f6sterreich",
    "wof:name":"Raiffeisenbank Sch\u00f6nau i M regGenmbH",
    "wof:placetype":"venue"
},
  "geometry": {"coordinates":[166.9221496582,-0.5282999873],"type":"Point"}
}