{
  "type": "Feature",
  "properties": {
    "addr:full":"Forchtensteinweg 3 Marz Burgenland 7221",
    "addr:housenumber":"3",
    "addr:postcode":"7221",
    "addr:street":"Forchtensteinweg",
    "iso:country":"AT",
    "sg:address":"Forchtensteinweg 3",
    "sg:city":"Marz",
    "sg:orig_category":"Elektroinstallationsunternehmen",
    "sg:phone":"+43 4326 2662387",
    "sg:postcode":"7221",
    "sg:province":"Burgenland",
    "wof:name":"Grafl Josef",
    "wof:placetype":"venue"
},
  "geometry": {"coordinates":[16.410194397,47.7152786255],"type":"Point"}
}