{
  "type": "Feature",
  "properties": {
    "addr:full":"Hauptpl 1 Judenburg Steiermark 8750",
    "addr:housenumber":"1",
    "addr:postcode":"8750",
    "addr:street":"Hauptpl",
    "iso:country":"AT",
    "sg:address":"Hauptpl 1",
    "sg:city":"Judenburg",
    "sg:orig_category":"Gemeinden",
    "sg:phone":"+43 3572 831410",
    "sg:postcode":"8750",
    "sg:province":"Steiermark",
    "wof:name":"Stadtgemeinde Judenburg",
    "wof:placetype":"venue"
},
  "geometry": {"coordinates":[14.6604309082,47.1687469482],"type":"Point"}
}