{
  "type": "Feature",
  "properties": {
    "iso:country":"AT",
    "sg:address":"Genotteallee 12",
    "sg:city":"Villach",
    "sg:orig_category":"Videotheken",
    "sg:phone":"+43 4242 22115",
    "sg:postcode":"9500",
    "sg:province":"K\u00e4rnten",
    "wof:name":"Star Videothek GesmbH",
    "wof:placetype":"venue"
},
  "geometry": {"coordinates":[13.8430671692,46.6203308105],"type":"Point"}
}