{
  "type": "Feature",
  "properties": {
    "iso:country":"AT",
    "sg:address":"Hauptstr 52",
    "sg:city":"Wolfsthal",
    "sg:orig_category":"Banken U Sparkassen",
    "sg:phone":"+43 4321 6562118",
    "sg:postcode":"2412",
    "sg:province":"Nieder\u00f6sterreich",
    "wof:name":"Raiffeisenbank Carnuntum regGenmbH",
    "wof:placetype":"venue"
},
  "geometry": {"coordinates":[17.0111942291,48.1347618103],"type":"Point"}
}