{
  "type": "Feature",
  "properties": {
    "addr:full":"Bahnhofstr 12 Ybbs an der Donau Nieder\u00f6sterreich 3370",
    "addr:housenumber":"12",
    "addr:postcode":"3370",
    "addr:street":"Bahnhofstr",
    "iso:country":"AT",
    "sg:address":"Bahnhofstr 12",
    "sg:city":"Ybbs an der Donau",
    "sg:orig_category":"Feuerwehren",
    "sg:phone":"+43 7412 525930",
    "sg:postcode":"3370",
    "sg:province":"Nieder\u00f6sterreich",
    "wof:name":"Freiwillige Feuerwehr Ybbs a d Donau",
    "wof:placetype":"venue"
},
  "geometry": {"coordinates":[15.0838356018,48.1729812622],"type":"Point"}
}