{
  "type": "Feature",
  "properties": {
    "iso:country":"AT",
    "sg:address":"Stuben 37",
    "sg:city":"Pfunds",
    "sg:orig_category":"Polizei U Gendarmerie",
    "sg:phone":"+43 4359 1337146",
    "sg:postcode":"6542",
    "sg:province":"Tirol",
    "wof:name":"Gendarmerie",
    "wof:placetype":"venue"
},
  "geometry": {"coordinates":[10.5360202789,46.9683799744],"type":"Point"}
}