{
  "type": "Feature",
  "properties": {
    "addr:full":"Lidmanskyg 39 Klagenfurt K\u00e4rnten 9020",
    "addr:housenumber":"39",
    "addr:postcode":"9020",
    "addr:street":"Lidmanskyg;Kaernten",
    "iso:country":"AT",
    "sg:address":"Lidmanskyg 39",
    "sg:city":"Klagenfurt",
    "sg:classifiers":[
        {
            "category":"Personal",
            "subcategory":"Adult",
            "type":"Services"
        }
    ],
    "sg:phone":"+43 4366 41350438",
    "sg:postcode":"9020",
    "sg:province":"K\u00e4rnten",
    "sg:tags":[
        "sex-shops"
    ],
    "wof:name":"Sex Shop Suppanz KEG",
    "wof:placetype":"venue"
},
  "geometry": {"coordinates":[14.3112707138,46.6226844788],"type":"Point"}
}