{
  "type": "Feature",
  "properties": {
    "addr:full":"Schalchham 108/5 Regau Ober\u00f6sterreich 4844",
    "addr:housenumber":"108 / 5",
    "addr:postcode":"4844",
    "addr:street":"Oberoesterreich",
    "iso:country":"AT",
    "sg:address":"Schalchham 108/5",
    "sg:city":"Regau",
    "sg:orig_category":"Personalbereitstellung",
    "sg:phone":"+43 4376 72754520",
    "sg:postcode":"4844",
    "sg:province":"Ober\u00f6sterreich",
    "wof:name":"Sch\u00f6nberg Christian Ing - Konstruktionsb\u00fcro & Personalleasing",
    "wof:placetype":"venue"
},
  "geometry": {"coordinates":[13.6820735931,47.9977684021],"type":"Point"}
}