{
  "type": "Feature",
  "properties": {
    "iso:country":"AT",
    "sg:address":"M\u00fchltal 30",
    "sg:city":"Westendorf",
    "sg:orig_category":"Rettungsdienste",
    "sg:phone":"+43 4353 3464000",
    "sg:postcode":"6363",
    "sg:province":"Tirol",
    "wof:name":"Rotes Kreuz \u00f6sterr Ortsstelle Brixental",
    "wof:placetype":"venue"
},
  "geometry": {"coordinates":[12.2147397995,47.4321594238],"type":"Point"}
}