{
  "type": "Feature",
  "properties": {
    "addr:full":"Noppendorf 20 Statzendorf Nieder\u00f6sterreich 3125",
    "addr:housenumber":"20",
    "addr:postcode":"3125",
    "addr:street":"Noppendorf",
    "iso:country":"AT",
    "sg:address":"Noppendorf 20",
    "sg:city":"Statzendorf",
    "sg:orig_category":"Autoreparatur",
    "sg:phone":"+43 4327 862635",
    "sg:postcode":"3125",
    "sg:province":"Nieder\u00f6sterreich",
    "wof:name":"Pachschw\u00f6ll Gerhard",
    "wof:placetype":"venue"
},
  "geometry": {"coordinates":[15.6410522461,48.3081512451],"type":"Point"}
}