{
  "type": "Feature",
  "properties": {
    "addr:full":"Steyrtalstr 116 Neuzeug Ober\u00f6sterreich 4523",
    "addr:housenumber":"116",
    "addr:postcode":"4523",
    "iso:country":"AT",
    "sg:address":"Steyrtalstr 116",
    "sg:city":"Neuzeug",
    "sg:orig_category":"Sonnenstudios",
    "sg:phone":"+43 7259 5634",
    "sg:postcode":"4523",
    "sg:province":"Ober\u00f6sterreich",
    "wof:name":"Rauchfuss Anita",
    "wof:placetype":"venue"
},
  "geometry": {"coordinates":[14.329791069,48.0438766479],"type":"Point"}
}