{
  "type": "Feature",
  "properties": {
    "addr:full":"Uferstr 17 Maishofen Salzburg 5751",
    "addr:housenumber":"17",
    "addr:postcode":"5751",
    "addr:street":"Uferstr;Salzburg",
    "iso:country":"AT",
    "sg:address":"Uferstr 17",
    "sg:city":"Maishofen",
    "sg:orig_category":"Gastronomie- U Hotelbedarf",
    "sg:phone":"+43 6542 683230",
    "sg:postcode":"5751",
    "sg:province":"Salzburg",
    "wof:name":"Langegger Elfriede",
    "wof:placetype":"venue"
},
  "geometry": {"coordinates":[12.825761795,47.380355835],"type":"Point"}
}