{
  "type": "Feature",
  "properties": {
    "addr:full":"Buchenweg 7 Ansfelden Ober\u00f6sterreich 4052",
    "addr:housenumber":"7",
    "addr:postcode":"4052",
    "addr:street":"Buchenweg",
    "iso:country":"AT",
    "sg:address":"Buchenweg 7",
    "sg:city":"Ansfelden",
    "sg:orig_category":"Reinigungsbedarf U Reinigungsmittel",
    "sg:phone":"+43 4373 2302089",
    "sg:postcode":"4052",
    "sg:province":"Ober\u00f6sterreich",
    "wof:name":"Clean Power - Haertl",
    "wof:placetype":"venue"
},
  "geometry": {"coordinates":[14.2881498337,48.2219696045],"type":"Point"}
}