{
  "type": "Feature",
  "properties": {
    "iso:country":"AT",
    "sg:address":"Schattau 64",
    "sg:city":"Ru\u00dfbach am Pa\u00df Gsch\u00fctt",
    "sg:classifiers":[
        {
            "category":"Professional",
            "subcategory":"Engineering",
            "type":"Services"
        }
    ],
    "sg:phone":"+43 4362 425400",
    "sg:postcode":"5442",
    "sg:province":"Salzburg",
    "sg:tags":[
        "machine",
        "-",
        "mechanical"
    ],
    "wof:name":"ING JOSEF BRANDAUER",
    "wof:placetype":"venue"
},
  "geometry": {"coordinates":[13.4646062851,47.5897712708],"type":"Point"}
}