{
  "type": "Feature",
  "properties": {
    "addr:full":"Johann Schorsch-G 4 Wien Wien 1140",
    "addr:housenumber":"4",
    "addr:postcode":"1140",
    "iso:country":"AT",
    "sg:address":"Johann Schorsch-G 4",
    "sg:city":"Wien",
    "sg:orig_category":"Hygieneartikel / Erzeugung U Gro\u00c3\u0178handel",
    "sg:phone":"+43 1 576700",
    "sg:postcode":"1140",
    "sg:province":"Wien",
    "wof:name":"Rauscher Consumer Products GmbH",
    "wof:placetype":"venue"
},
  "geometry": {"coordinates":[16.2195205688,48.2052345276],"type":"Point"}
}