{
  "type": "Feature",
  "properties": {
    "addr:full":"Sillian 3 Sillian Tirol 9920",
    "addr:housenumber":"3",
    "addr:postcode":"9920",
    "addr:street":"Sillian;Tirol",
    "iso:country":"AT",
    "sg:address":"Sillian 3",
    "sg:city":"Sillian",
    "sg:classifiers":[
        {
            "category":"Home & Garden",
            "subcategory":"Building Materials",
            "type":"Retail Goods"
        }
    ],
    "sg:phone":"+43 4842 6187",
    "sg:postcode":"9920",
    "sg:province":"Tirol",
    "sg:tags":[
        "tile",
        "granite"
    ],
    "wof:name":"Harald Fuchs",
    "wof:placetype":"venue"
},
  "geometry": {"coordinates":[12.4253540039,46.7489280701],"type":"Point"}
}