{
  "type": "Feature",
  "properties": {
    "iso:country":"AT",
    "sg:address":"Alte Landstr 4",
    "sg:city":"Th\u00fcringen",
    "sg:orig_category":"Handarbeiten",
    "sg:phone":"+43 5550 20062",
    "sg:postcode":"6712",
    "sg:province":"Vorarlberg",
    "wof:name":"Erna's L\u00e4dele",
    "wof:placetype":"venue"
},
  "geometry": {"coordinates":[9.7661762238,47.2000160217],"type":"Point"}
}