{
  "type": "Feature",
  "properties": {
    "iso:country":"AT",
    "sg:address":"Fischer-Villa-Str 2",
    "sg:city":"Oberalm",
    "sg:orig_category":"Versicherungsunternehmen",
    "sg:phone":"+43 4362 45843500",
    "sg:postcode":"5411",
    "sg:province":"Salzburg",
    "wof:name":"Grazer Wechselseitige Versicherung AG",
    "wof:placetype":"venue"
},
  "geometry": {"coordinates":[13.1007862091,47.6931724548],"type":"Point"}
}