{
  "type": "Feature",
  "properties": {
    "iso:country":"AT",
    "sg:address":"Nr 274c",
    "sg:city":"Preding",
    "sg:orig_category":"Textilwaren / Einzelhandel",
    "sg:phone":"+43 3185 30088",
    "sg:postcode":"8504",
    "sg:province":"Steiermark",
    "wof:name":"Modezentrum Aum\u00fcller GesmbH",
    "wof:placetype":"venue"
},
  "geometry": {"coordinates":[15.4067401886,46.8597869873],"type":"Point"}
}