{
  "type": "Feature",
  "properties": {
    "addr:full":"Streicherg 4/4 Wien Wien 1030",
    "addr:housenumber":"4 / 4",
    "addr:postcode":"1030",
    "addr:street":"Streicherg",
    "iso:country":"AT",
    "sg:address":"Streicherg 4/4",
    "sg:city":"Wien",
    "sg:orig_category":"Suchtberatung / Alkohol, Drogen, Zigaretten",
    "sg:phone":"+43 4317 1492180",
    "sg:postcode":"1030",
    "sg:province":"Wien",
    "wof:name":"Pass - Hilfe b Suchtproblemen Beratung u Therapie f betroffene u Angeh\u00f6rige",
    "wof:placetype":"venue"
},
  "geometry": {"coordinates":[16.3866958618,48.1978683472],"type":"Point"}
}