{
  "type": "Feature",
  "properties": {
    "iso:country":"AT",
    "sg:address":"Kirchstetterng 56",
    "sg:city":"Wien",
    "sg:orig_category":"Werbeartikel U -Geschenke",
    "sg:phone":"+43 4319 904487",
    "sg:postcode":"1160",
    "sg:province":"Wien",
    "sg:website":"promusen.at",
    "wof:name":"promuseum Hofst\u00e4tter KEG",
    "wof:placetype":"venue"
},
  "geometry": {"coordinates":[16.3338031769,48.211566925],"type":"Point"}
}