{
  "type": "Feature",
  "properties": {
    "iso:country":"AT",
    "sg:address":"Ried 28 ",
    "sg:city":"Wallsee",
    "sg:classifiers":[
        {
            "category":"Building & Trades",
            "subcategory":"Plumbing",
            "type":"Services"
        }
    ],
    "sg:phone":"+43 7433 2232",
    "sg:postcode":"3313",
    "sg:province":"Nieder\u00f6sterreich",
    "sg:tags":[
        "supraregional",
        "gas"
    ],
    "wof:name":"Lanzinger Installationen GmbH",
    "wof:placetype":"venue"
},
  "geometry": {"coordinates":[14.7188100815,48.1655082703],"type":"Point"}
}