{
  "type": "Feature",
  "properties": {
    "addr:full":"Bundesstr 13 St. Johann im Pongau Salzburg 5600",
    "addr:housenumber":"13",
    "addr:postcode":"5600",
    "addr:street":"Bundesstr;Salzburg",
    "iso:country":"AT",
    "sg:address":"Bundesstr 13",
    "sg:city":"St. Johann im Pongau",
    "sg:orig_category":"Tankstellen",
    "sg:phone":"+43 6412 6707",
    "sg:postcode":"5600",
    "sg:province":"Salzburg",
    "wof:name":"JET Tankstelle",
    "wof:placetype":"venue"
},
  "geometry": {"coordinates":[13.1920166016,47.3437385559],"type":"Point"}
}