{
  "type": "Feature",
  "properties": {
    "addr:full":"Holzhauser Str 63 St. Georgen Salzburg 5113",
    "addr:housenumber":"63",
    "addr:postcode":"5113",
    "addr:street":"Str",
    "iso:country":"AT",
    "sg:address":"Holzhauser Str 63",
    "sg:city":"St. Georgen",
    "sg:orig_category":"Betonbohr- U -Schneidedienst",
    "sg:phone":"+43 4362 7474190",
    "sg:postcode":"5113",
    "sg:province":"Salzburg",
    "sg:website":"amerhauser.at",
    "wof:name":"Amerhauser GmbH",
    "wof:placetype":"venue"
},
  "geometry": {"coordinates":[12.9354429245,48.0119476318],"type":"Point"}
}