{
  "type": "Feature",
  "properties": {
    "iso:country":"AT",
    "sg:address":"Vogelf\u00e4ngerweg 17",
    "sg:city":"Linz",
    "sg:orig_category":"Banken U Sparkassen",
    "sg:phone":"+43 5 010040004",
    "sg:postcode":"4030",
    "sg:province":"Ober\u00f6sterreich",
    "wof:name":"Allgemeine Sparkasse Ober\u00f6sterreich Bank AG",
    "wof:placetype":"venue"
},
  "geometry": {"coordinates":[14.2885398865,48.250995636],"type":"Point"}
}