{
  "type": "Feature",
  "properties": {
    "addr:full":"Herrengutg 10/10 Lauterach Vorarlberg 6923",
    "addr:housenumber":"10 / 10",
    "addr:postcode":"6923",
    "addr:street":"Herrengutg",
    "iso:country":"AT",
    "sg:address":"Herrengutg 10/10",
    "sg:city":"Lauterach",
    "sg:orig_category":"Kosmetische Produkte / Einzelhandel",
    "sg:phone":"+43 5574 62126",
    "sg:postcode":"6923",
    "sg:province":"Vorarlberg",
    "wof:name":"Lombagine Cosmetics - Rusch Doris",
    "wof:placetype":"venue"
},
  "geometry": {"coordinates":[9.7332382202,47.4757347107],"type":"Point"}
}