{
  "type": "Feature",
  "properties": {
    "iso:country":"AT",
    "sg:address":"Otto-von-Lilienthal-Str 7",
    "sg:city":"Salzburg",
    "sg:orig_category":"Friseure U Frisiersalons",
    "sg:phone":"+43 4366 2428901",
    "sg:postcode":"5020",
    "sg:province":"Salzburg",
    "wof:name":"Frisiersalon Berger",
    "wof:placetype":"venue"
},
  "geometry": {"coordinates":[13.0050601959,47.80991745],"type":"Point"}
}