{
  "type": "Feature",
  "properties": {
    "addr:full":"Hebenstreitstr 3 Linz Ober\u00f6sterreich 4020",
    "addr:housenumber":"3",
    "addr:postcode":"4020",
    "addr:street":"Hebenstreitstr",
    "iso:country":"AT",
    "sg:address":"Hebenstreitstr 3",
    "sg:city":"Linz",
    "sg:orig_category":"Physiotherapie",
    "sg:phone":"+43 732 673367",
    "sg:postcode":"4020",
    "sg:province":"Ober\u00f6sterreich",
    "wof:name":"Janetschko-K\u00f6llinger Constanze Dipl-PT",
    "wof:placetype":"venue"
},
  "geometry": {"coordinates":[14.2852096558,48.2758903503],"type":"Point"}
}