{
  "type": "Feature",
  "properties": {
    "addr:full":"Josef-Kollmann-Str 47 Baden Nieder\u00f6sterreich 2500",
    "addr:housenumber":"47",
    "addr:postcode":"2500",
    "addr:street":"Josef-Kollmann-Str;Niederoesterreich",
    "iso:country":"AT",
    "sg:address":"Josef-Kollmann-Str 47",
    "sg:city":"Baden",
    "sg:orig_category":"Papier / Erzeugung U Gro\u00c3\u0178handel",
    "sg:phone":"+43 4322 5221519",
    "sg:postcode":"2500",
    "sg:province":"Nieder\u00f6sterreich",
    "wof:name":"T.P.B. - Technische Papiere Binder GmbH",
    "wof:placetype":"venue"
},
  "geometry": {"coordinates":[16.2576274872,48.0064048767],"type":"Point"}
}