{
  "type": "Feature",
  "properties": {
    "iso:country":"AT",
    "sg:address":"Postg 6",
    "sg:city":"Bad Sauerbrunn",
    "sg:orig_category":"Textilwaren / Einzelhandel",
    "sg:phone":"+43 2625 32051",
    "sg:postcode":"7202",
    "sg:province":"Burgenland",
    "wof:name":"Sissy Moden Elisabeth Stasch",
    "wof:placetype":"venue"
},
  "geometry": {"coordinates":[16.3250465393,47.7747840881],"type":"Point"}
}