{
  "type": "Feature",
  "properties": {
    "addr:full":"Hauptstr. 31 Eisenstadt Burgenland 7000",
    "addr:housenumber":"31",
    "addr:postcode":"7000",
    "addr:street":"Hauptstr.",
    "iso:country":"AT",
    "sg:address":"Hauptstr. 31",
    "sg:city":"Eisenstadt",
    "sg:classifiers":[
        {
            "category":"Banks & Credit Unions",
            "subcategory":"Bank",
            "type":"Services"
        }
    ],
    "sg:phone":"+43 4326 826050",
    "sg:postcode":"7000",
    "sg:province":"Burgenland",
    "sg:tags":[
        "banking",
        "institution"
    ],
    "wof:name":"EB U. HYPOBANK BURGENLAND AG",
    "wof:placetype":"venue"
},
  "geometry": {"coordinates":[16.5236377716,47.8465194702],"type":"Point"}
}