{
  "type": "Feature",
  "properties": {
    "addr:full":"Nr 44 Kematen am Innbach Ober\u00f6sterreich 4633",
    "addr:postcode":"4633",
    "addr:street":"Nr 44",
    "iso:country":"AT",
    "sg:address":"Nr 44",
    "sg:city":"Kematen am Innbach",
    "sg:orig_category":"Tankstellen",
    "sg:phone":"+43 7247 6631",
    "sg:postcode":"4633",
    "sg:province":"Ober\u00f6sterreich",
    "wof:name":"Daxl Gottfried",
    "wof:placetype":"venue"
},
  "geometry": {"coordinates":[13.8624019623,48.1767082214],"type":"Point"}
}