{
  "type": "Feature",
  "properties": {
    "addr:full":"Weyringerg 9/15 Wien Wien 1040",
    "addr:housenumber":"9 / 15",
    "addr:postcode":"1040",
    "addr:street":"Weyringerg",
    "iso:country":"AT",
    "sg:address":"Weyringerg 9/15",
    "sg:city":"Wien",
    "sg:orig_category":"Architekten",
    "sg:phone":"+43 1 5050339",
    "sg:postcode":"1040",
    "sg:province":"Wien",
    "wof:name":"B\u00fcrgermeister Josef Arch Dipl-Ing",
    "wof:placetype":"venue"
},
  "geometry": {"coordinates":[16.3790683746,48.1886444092],"type":"Point"}
}