{
  "type": "Feature",
  "properties": {
    "addr:full":"Zugallistr 12 Salzburg Salzburg 5020",
    "addr:housenumber":"12",
    "addr:postcode":"5020",
    "addr:street":"Zugallistr;Salzburg",
    "iso:country":"AT",
    "sg:address":"Zugallistr 12",
    "sg:city":"Salzburg",
    "sg:orig_category":"Musikgruppen",
    "sg:phone":"+43 4366 280422614",
    "sg:postcode":"5020",
    "sg:province":"Salzburg",
    "wof:name":"Salzburger Blasmusikverband",
    "wof:placetype":"venue"
},
  "geometry": {"coordinates":[13.0512428284,47.7935943604],"type":"Point"}
}