{
  "type": "Feature",
  "properties": {
    "addr:full":"Industriezeile 2 Linz Ober\u00f6sterreich 4020",
    "addr:housenumber":"2",
    "addr:postcode":"4020",
    "addr:street":"Industriezeile",
    "iso:country":"AT",
    "sg:address":"Industriezeile 2",
    "sg:city":"Linz",
    "sg:orig_category":"Tischlereien",
    "sg:phone":"+43 732 796144",
    "sg:postcode":"4020",
    "sg:province":"Ober\u00f6sterreich",
    "wof:name":"Wurm Tischlerei",
    "wof:placetype":"venue"
},
  "geometry": {"coordinates":[14.3098268509,48.3180351257],"type":"Point"}
}