{
  "type": "Feature",
  "properties": {
    "addr:full":"Wei\u00dfenbach 106 Kuchl Salzburg 5431",
    "addr:housenumber":"106",
    "addr:postcode":"5431",
    "addr:street":"Weissenbach;Salzburg",
    "iso:country":"AT",
    "sg:address":"Wei\u00dfenbach 106",
    "sg:city":"Kuchl",
    "sg:orig_category":"Tiefbau",
    "sg:phone":"+43 6244 20325",
    "sg:postcode":"5431",
    "sg:province":"Salzburg",
    "wof:name":"Trumer Schutzbauten GesmbH",
    "wof:placetype":"venue"
},
  "geometry": {"coordinates":[13.1438808441,47.625667572],"type":"Point"}
}