{
  "type": "Feature",
  "properties": {
    "addr:full":"Universit\u00e4tspl 1 Salzburg Salzburg 5020",
    "addr:housenumber":"1",
    "addr:postcode":"5020",
    "addr:street":"Universitaetspl;Salzburg",
    "iso:country":"AT",
    "sg:address":"Universit\u00e4tspl 1",
    "sg:city":"Salzburg",
    "sg:orig_category":"Institute",
    "sg:phone":"+43 4366 280442753",
    "sg:postcode":"5020",
    "sg:province":"Salzburg",
    "wof:name":"Fachbreich praktische Theologie",
    "wof:placetype":"venue"
},
  "geometry": {"coordinates":[13.0418138504,47.7994232178],"type":"Point"}
}