{
  "type": "Feature",
  "properties": {
    "addr:full":"Wiener Str 24 Knittelfeld Steiermark 8720",
    "addr:postcode":"8720",
    "iso:country":"AT",
    "sg:address":"Wiener Str 24",
    "sg:city":"Knittelfeld",
    "sg:orig_category":"Autohandel",
    "sg:phone":"+43 4335 12822750",
    "sg:postcode":"8720",
    "sg:province":"Steiermark",
    "wof:name":"Grasser Alois GesmbH",
    "wof:placetype":"venue"
},
  "geometry": {"coordinates":[14.8278942108,47.2173881531],"type":"Point"}
}