{
  "type": "Feature",
  "properties": {
    "iso:country":"AT",
    "sg:address":"Kaiserebersdorferstr 263",
    "sg:city":"Wien",
    "sg:orig_category":"Autohandel",
    "sg:phone":"+43 4317 6969030",
    "sg:postcode":"1110",
    "sg:province":"Wien",
    "wof:name":"Haller Franz KFZ Reparaturwerkst\u00e4tte KG",
    "wof:placetype":"venue"
},
  "geometry": {"coordinates":[16.4643135071,48.1601371765],"type":"Point"}
}