{
  "type": "Feature",
  "properties": {
    "addr:full":"Gersthofer Str 77 Wien Wien 1180",
    "addr:postcode":"1180",
    "addr:street":"Str 77",
    "iso:country":"AT",
    "sg:address":"Gersthofer Str 77",
    "sg:city":"Wien",
    "sg:orig_category":"Friseure U Frisiersalons",
    "sg:phone":"+43 4314 786337",
    "sg:postcode":"1180",
    "sg:province":"Wien",
    "wof:name":"Waldmann Helmuth",
    "wof:placetype":"venue"
},
  "geometry": {"coordinates":[16.3272037506,48.2346992493],"type":"Point"}
}