{
  "type": "Feature",
  "properties": {
    "addr:full":"Johannesg 2 Haag Nieder\u00f6sterreich 3350",
    "addr:housenumber":"2",
    "addr:postcode":"3350",
    "addr:street":"Johannesg",
    "iso:country":"AT",
    "sg:address":"Johannesg 2",
    "sg:city":"Haag",
    "sg:orig_category":"Versicherungsunternehmen",
    "sg:phone":"+43 7434 440120",
    "sg:postcode":"3350",
    "sg:province":"Nieder\u00f6sterreich",
    "wof:name":"Generali Versicherung AG",
    "wof:placetype":"venue"
},
  "geometry": {"coordinates":[14.5653495789,48.1121902466],"type":"Point"}
}