{
  "type": "Feature",
  "properties": {
    "addr:full":"Am Stadtgraben 3/C4 St. Egyden am Steinfeld Nieder\u00f6sterreich 2731",
    "addr:housenumber":"3 / c4",
    "addr:postcode":"2731",
    "addr:street":"Am Stadtgraben",
    "iso:country":"AT",
    "sg:address":"Am Stadtgraben 3/C4",
    "sg:city":"St. Egyden am Steinfeld",
    "sg:orig_category":"Handelsagenturen",
    "sg:phone":"+43 4326 3877168",
    "sg:postcode":"2731",
    "sg:province":"Nieder\u00f6sterreich",
    "wof:name":"Prudic Martin",
    "wof:placetype":"venue"
},
  "geometry": {"coordinates":[16.1024875641,47.7818527222],"type":"Point"}
}