{
  "type": "Feature",
  "properties": {
    "iso:country":"AT",
    "sg:address":"Laabstr. 105 ",
    "sg:city":"Braunau am Inn",
    "sg:classifiers":[
        {
            "category":"Manufacturing",
            "subcategory":"Metals",
            "type":"Manufacturing & Wholesale Goods"
        }
    ],
    "sg:phone":"+43 4377 2281500",
    "sg:postcode":"5280",
    "sg:province":"Ober\u00f6sterreich",
    "sg:tags":[
        "metallurgy",
        "metalworking"
    ],
    "wof:name":"MONTEX MONTAGE & VERBINDUNGSTECHNIK GMBH",
    "wof:placetype":"venue"
},
  "geometry": {"coordinates":[13.0641965866,48.2566299438],"type":"Point"}
}