{
  "type": "Feature",
  "properties": {
    "addr:full":"Graumanng 3-5 Wien Wien 1150",
    "addr:housenumber":"3-5",
    "addr:postcode":"1150",
    "addr:street":"Graumanng",
    "iso:country":"AT",
    "sg:address":"Graumanng 3-5",
    "sg:city":"Wien",
    "sg:classifiers":[
        {
            "category":"Travel",
            "subcategory":"Hotels & Motels",
            "type":"Entertainment"
        }
    ],
    "sg:phone":"+43 1 8930010",
    "sg:postcode":"1150",
    "sg:province":"Wien",
    "wof:name":"Hotel Bauer GesmbH",
    "wof:placetype":"venue"
},
  "geometry": {"coordinates":[16.3382034302,48.1885528564],"type":"Point"}
}