{
  "type": "Feature",
  "properties": {
    "addr:full":"Reith 29 Geretsberg Ober\u00f6sterreich 5132",
    "addr:housenumber":"29",
    "addr:postcode":"5132",
    "addr:street":"Reith",
    "iso:country":"AT",
    "sg:address":"Reith 29",
    "sg:city":"Geretsberg",
    "sg:orig_category":"Handelsagenturen",
    "sg:phone":"+43 676 7006044",
    "sg:postcode":"5132",
    "sg:province":"Ober\u00f6sterreich",
    "wof:name":"Pernegger Gastro KEG",
    "wof:placetype":"venue"
},
  "geometry": {"coordinates":[12.9445333481,48.1030349731],"type":"Point"}
}