{
  "type": "Feature",
  "properties": {
    "addr:full":"Rottalgasse 16a Graz Steiermark 8010",
    "addr:housenumber":"16a",
    "addr:postcode":"8010",
    "addr:street":"Rottalgasse",
    "iso:country":"AT",
    "sg:address":"Rottalgasse 16a",
    "sg:city":"Graz",
    "sg:classifiers":[
        {
            "category":"Manufacturing",
            "subcategory":"Paper Products",
            "type":"Manufacturing & Wholesale Goods"
        }
    ],
    "sg:phone":"+43 316 673868",
    "sg:postcode":"8010",
    "sg:province":"Steiermark",
    "sg:tags":[
        "cardboard",
        "package"
    ],
    "sg:website":"ideenundwerk.at",
    "wof:name":"Idee & Werk Inh. Reinhard Tauder",
    "wof:placetype":"venue"
},
  "geometry": {"coordinates":[15.4279203415,47.0846710205],"type":"Point"}
}