{
  "type": "Feature",
  "properties": {
    "addr:full":"Hauserstr 5 Neukirchen am Walde Ober\u00f6sterreich 4724",
    "addr:housenumber":"5",
    "addr:postcode":"4724",
    "addr:street":"Hauserstr",
    "iso:country":"AT",
    "sg:address":"Hauserstr 5",
    "sg:city":"Neukirchen am Walde",
    "sg:orig_category":"Maler, Anstreicher U Lackierer",
    "sg:phone":"+43 4372 783303",
    "sg:postcode":"4724",
    "sg:province":"Ober\u00f6sterreich",
    "wof:name":"Schachner Manfred",
    "wof:placetype":"venue"
},
  "geometry": {"coordinates":[13.7754535675,48.4073638916],"type":"Point"}
}