{
  "type": "Feature",
  "properties": {
    "addr:full":"Johann-Strau\u00df-Str 15 Bad Hall Ober\u00f6sterreich 4540",
    "addr:housenumber":"15",
    "addr:postcode":"4540",
    "addr:street":"Johann-Strauss-Str",
    "iso:country":"AT",
    "sg:address":"Johann-Strau\u00df-Str 15",
    "sg:city":"Bad Hall",
    "sg:orig_category":"Handelsagenturen",
    "sg:phone":"+43 7258 26070",
    "sg:postcode":"4540",
    "sg:province":"Ober\u00f6sterreich",
    "wof:name":"Reisinger J\u00fcrgen",
    "wof:placetype":"venue"
},
  "geometry": {"coordinates":[14.2183408737,48.0310974121],"type":"Point"}
}