{
  "type": "Feature",
  "properties": {
    "iso:country":"AT",
    "sg:address":"Peter-Jordan-Strasse 19",
    "sg:city":"Wien",
    "sg:classifiers":[
        {
            "category":"Shopping",
            "subcategory":"Clothing, Apparel, & Fashions",
            "type":"Retail Goods"
        }
    ],
    "sg:phone":"+43 1 3687951",
    "sg:postcode":"1190",
    "sg:province":"Wien",
    "sg:tags":[
        "garment",
        "fur"
    ],
    "wof:name":"Horst Br\u00e4utigam, Grosshandel mit Fellen u. Rauhwaren",
    "wof:placetype":"venue"
},
  "geometry": {"coordinates":[16.3458766937,48.2369804382],"type":"Point"}
}