{
  "type": "Feature",
  "properties": {
    "addr:full":"Schuhfabrikg 17 Wien Wien 1230",
    "addr:housenumber":"17",
    "addr:postcode":"1230",
    "addr:street":"Schuhfabrikg",
    "iso:country":"AT",
    "sg:address":"Schuhfabrikg 17",
    "sg:city":"Wien",
    "sg:orig_category":"Direktmarketing",
    "sg:phone":"+43 1 8955910",
    "sg:postcode":"1230",
    "sg:province":"Wien",
    "wof:name":"Octopus - Gerhard Brodnik",
    "wof:placetype":"venue"
},
  "geometry": {"coordinates":[16.303314209,48.1583595276],"type":"Point"}
}