{
  "type": "Feature",
  "properties": {
    "addr:full":"R\u00f6tzer Str 11 Judendorf-Stra\u00dfengel Steiermark 8111",
    "addr:housenumber":"11",
    "addr:postcode":"8111",
    "addr:street":"Str",
    "iso:country":"AT",
    "sg:address":"R\u00f6tzer Str 11",
    "sg:city":"Judendorf-Stra\u00dfengel",
    "sg:orig_category":"Hobbyvereine",
    "sg:phone":"+43 3124 52089",
    "sg:postcode":"8111",
    "sg:province":"Steiermark",
    "wof:name":"Pfadfindergruppe Judendorf",
    "wof:placetype":"venue"
},
  "geometry": {"coordinates":[15.3350353241,47.1136360168],"type":"Point"}
}