{
  "type": "Feature",
  "properties": {
    "iso:country":"AT",
    "sg:address":"A1/Westautob.",
    "sg:city":"Ansfelden",
    "sg:orig_category":"Tankstellen",
    "sg:phone":"+43 7229 87115",
    "sg:postcode":"4052",
    "sg:province":"Ober\u00f6sterreich",
    "wof:name":"BP Austria Marketing GmbH",
    "wof:placetype":"venue"
},
  "geometry": {"coordinates":[14.3075647354,48.2254638672],"type":"Point"}
}