{
  "type": "Feature",
  "properties": {
    "addr:full":"Nr 744 Hitzendorf Steiermark 8151",
    "addr:postcode":"8151",
    "addr:street":"Nr 744",
    "iso:country":"AT",
    "sg:address":"Nr 744",
    "sg:city":"Hitzendorf",
    "sg:orig_category":"Waren Aller Art",
    "sg:phone":"+43 316 576648",
    "sg:postcode":"8151",
    "sg:province":"Steiermark",
    "wof:name":"Plail-Herzog Silvia",
    "wof:placetype":"venue"
},
  "geometry": {"coordinates":[15.2999134064,47.0351600647],"type":"Point"}
}