{
  "type": "Feature",
  "properties": {
    "addr:full":"Angerweg 26 Feld am See K\u00e4rnten 9544",
    "addr:housenumber":"26",
    "addr:postcode":"9544",
    "addr:street":"Angerweg;Kaernten",
    "iso:country":"AT",
    "sg:address":"Angerweg 26",
    "sg:city":"Feld am See",
    "sg:orig_category":"Friseure U Frisiersalons",
    "sg:phone":"+43 4342 462089",
    "sg:postcode":"9544",
    "sg:province":"K\u00e4rnten",
    "wof:name":"ACP - Ihr Friseur GesmbH",
    "wof:placetype":"venue"
},
  "geometry": {"coordinates":[13.7432546616,46.7830619812],"type":"Point"}
}