{
  "type": "Feature",
  "properties": {
    "addr:full":"Gr\u00e4sslplatz 5/2 Wien Wien 1110",
    "addr:housenumber":"5 / 2",
    "addr:postcode":"1110",
    "addr:street":"Graesslplatz",
    "iso:country":"AT",
    "sg:address":"Gr\u00e4sslplatz 5/2",
    "sg:city":"Wien",
    "sg:classifiers":[
        {
            "category":"Building & Trades",
            "subcategory":"Construction",
            "type":"Services"
        }
    ],
    "sg:phone":"+43 699 19554002",
    "sg:postcode":"1110",
    "sg:province":"Wien",
    "sg:tags":[
        "roofing"
    ],
    "wof:name":"Ak\u00fclke & Uyar OEG",
    "wof:placetype":"venue"
},
  "geometry": {"coordinates":[16.3974151611,48.1752357483],"type":"Point"}
}