{
  "type": "Feature",
  "properties": {
    "addr:full":"Leondinger Str 71 Traun Ober\u00f6sterreich 4050",
    "addr:postcode":"4050",
    "addr:street":"Str 71",
    "iso:country":"AT",
    "sg:address":"Leondinger Str 71",
    "sg:city":"Traun",
    "sg:orig_category":"Banken U Sparkassen",
    "sg:phone":"+43 4373 265967883",
    "sg:postcode":"4050",
    "sg:province":"Ober\u00f6sterreich",
    "wof:name":"Raiffeisenlandesbank Ober\u00f6sterreich Aktiengesellschaft",
    "wof:placetype":"venue"
},
  "geometry": {"coordinates":[14.2384881973,48.221572876],"type":"Point"}
}