{
  "type": "Feature",
  "properties": {
    "addr:full":"Montfortstr 13 Bregenz Vorarlberg 6900",
    "addr:housenumber":"13",
    "addr:postcode":"6900",
    "addr:street":"Montfortstr",
    "iso:country":"AT",
    "sg:address":"Montfortstr 13",
    "sg:city":"Bregenz",
    "sg:orig_category":"Damenmoden",
    "sg:phone":"+43 5574 42379",
    "sg:postcode":"6900",
    "sg:province":"Vorarlberg",
    "wof:name":"Studio 70 - Wenk Max",
    "wof:placetype":"venue"
},
  "geometry": {"coordinates":[9.7444534302,47.5026626587],"type":"Point"}
}