{
  "type": "Feature",
  "properties": {
    "addr:full":"Welser Str 5 Neuhofen an der Krems Ober\u00f6sterreich 4501",
    "addr:housenumber":"5",
    "addr:postcode":"4501",
    "addr:street":"Str",
    "iso:country":"AT",
    "sg:address":"Welser Str 5",
    "sg:city":"Neuhofen an der Krems",
    "sg:orig_category":"Steinmetzbetriebe",
    "sg:phone":"+43 4372 274366",
    "sg:postcode":"4501",
    "sg:province":"Ober\u00f6sterreich",
    "wof:name":"Scheibl Steinmetz KEG",
    "wof:placetype":"venue"
},
  "geometry": {"coordinates":[14.2275562286,48.1410675049],"type":"Point"}
}