{
  "type": "Feature",
  "properties": {
    "addr:full":"Widmanng 8 Villach K\u00e4rnten 9500",
    "addr:housenumber":"8",
    "addr:postcode":"9500",
    "addr:street":"Widmanng;Kaernten",
    "iso:country":"AT",
    "sg:address":"Widmanng 8",
    "sg:city":"Villach",
    "sg:orig_category":"Galerien",
    "sg:phone":"+43 4366 42026754",
    "sg:postcode":"9500",
    "sg:province":"K\u00e4rnten",
    "wof:name":"Galerie white8",
    "wof:placetype":"venue"
},
  "geometry": {"coordinates":[13.8445720673,46.6155052185],"type":"Point"}
}