{
  "type": "Feature",
  "properties": {
    "addr:full":"Stadtpl 46 Steyr Ober\u00f6sterreich 4400",
    "addr:housenumber":"46",
    "addr:postcode":"4400",
    "addr:street":"Stadtpl;Oberoesterreich",
    "iso:country":"AT",
    "sg:address":"Stadtpl 46",
    "sg:city":"Steyr",
    "sg:orig_category":"Banken U Sparkassen",
    "sg:phone":"+43 4372 524848420",
    "sg:postcode":"4400",
    "sg:province":"Ober\u00f6sterreich",
    "wof:name":"Bankomat d Raiffeisenbank Region Steyr regGenmbH",
    "wof:placetype":"venue"
},
  "geometry": {"coordinates":[14.4185619354,48.0382118225],"type":"Point"}
}