{
  "type": "Feature",
  "properties": {
    "addr:full":"Wiesstr 12 Wolfern Ober\u00f6sterreich 4493",
    "addr:housenumber":"12",
    "addr:postcode":"4493",
    "addr:street":"Wiesstr",
    "iso:country":"AT",
    "sg:address":"Wiesstr 12",
    "sg:city":"Wolfern",
    "sg:orig_category":"Futtermittel",
    "sg:phone":"+43 7253 8203",
    "sg:postcode":"4493",
    "sg:province":"Ober\u00f6sterreich",
    "wof:name":"Sch\u00f6llerbacher GmbH",
    "wof:placetype":"venue"
},
  "geometry": {"coordinates":[14.3678865433,48.11926651],"type":"Point"}
}