{
  "type": "Feature",
  "properties": {
    "addr:full":"Marktstr 30 Klein St. Paul K\u00e4rnten 9373",
    "addr:housenumber":"30",
    "addr:postcode":"9373",
    "addr:street":"Marktstr",
    "iso:country":"AT",
    "sg:address":"Marktstr 30",
    "sg:city":"Klein St. Paul",
    "sg:orig_category":"Volksschulen",
    "sg:phone":"+43 4264 2356",
    "sg:postcode":"9373",
    "sg:province":"K\u00e4rnten",
    "wof:name":"Volksschule",
    "wof:placetype":"venue"
},
  "geometry": {"coordinates":[14.5408658981,46.834400177],"type":"Point"}
}