{
  "type": "Feature",
  "properties": {
    "addr:full":"Mauttorpromenade 1 Hallein Salzburg 5400",
    "addr:housenumber":"1",
    "addr:postcode":"5400",
    "addr:street":"Mauttorpromenade;Salzburg",
    "iso:country":"AT",
    "sg:address":"Mauttorpromenade 1",
    "sg:city":"Hallein",
    "sg:orig_category":"Lebensmittel / Einzelhandel",
    "sg:phone":"+43 6245 80042",
    "sg:postcode":"5400",
    "sg:province":"Salzburg",
    "wof:name":"Billa AG",
    "wof:placetype":"venue"
},
  "geometry": {"coordinates":[13.0954637527,47.6837234497],"type":"Point"}
}