{
  "type": "Feature",
  "properties": {
    "addr:full":"Steinamangerstr 21 Pinggau Steiermark 8243",
    "addr:housenumber":"21",
    "addr:postcode":"8243",
    "addr:street":"Steinamangerstr",
    "iso:country":"AT",
    "sg:address":"Steinamangerstr 21",
    "sg:city":"Pinggau",
    "sg:orig_category":"\u00c3\u201erzte / F Allgemeinmedizin",
    "sg:phone":"+43 3339 222570",
    "sg:postcode":"8243",
    "sg:province":"Steiermark",
    "wof:name":"Koller Winfried Dr",
    "wof:placetype":"venue"
},
  "geometry": {"coordinates":[16.0700244904,47.4409065247],"type":"Point"}
}