{
  "type": "Feature",
  "properties": {
    "addr:full":"Andlersdorfer Str 9 Orth an der Donau Nieder\u00f6sterreich 2304",
    "addr:housenumber":"9",
    "addr:postcode":"2304",
    "addr:street":"Str",
    "iso:country":"AT",
    "sg:address":"Andlersdorfer Str 9",
    "sg:city":"Orth an der Donau",
    "sg:orig_category":"Innenausbau",
    "sg:phone":"+43 2212 2291",
    "sg:postcode":"2304",
    "sg:province":"Nieder\u00f6sterreich",
    "wof:name":"Greiner Helmuth",
    "wof:placetype":"venue"
},
  "geometry": {"coordinates":[16.6923618317,48.1507949829],"type":"Point"}
}