{
  "type": "Feature",
  "properties": {
    "iso:country":"AT",
    "sg:address":"Marktpl 10",
    "sg:city":"Obernberg am Inn",
    "sg:orig_category":"Notare",
    "sg:phone":"+43 7758 40020",
    "sg:postcode":"4982",
    "sg:province":"Ober\u00f6sterreich",
    "wof:name":"Wild Manfred Dr",
    "wof:placetype":"venue"
},
  "geometry": {"coordinates":[13.3355798721,48.3223381042],"type":"Point"}
}