{
  "type": "Feature",
  "properties": {
    "iso:country":"AT",
    "sg:address":"Pernerstorfer Str 43",
    "sg:city":"Neunkirchen",
    "sg:orig_category":"Tapezierer U Dekorateure",
    "sg:phone":"+43 4326 3562337",
    "sg:postcode":"2620",
    "sg:province":"Nieder\u00f6sterreich",
    "wof:name":"Weninger Erich u Wolfgang",
    "wof:placetype":"venue"
},
  "geometry": {"coordinates":[16.0980548859,47.7119560242],"type":"Point"}
}