{
  "type": "Feature",
  "properties": {
    "addr:full":"Nr 17 Kirnberg an der Mank Nieder\u00f6sterreich 3241",
    "addr:postcode":"3241",
    "addr:street":"Nr;Kirnberg An Der Mank",
    "iso:country":"AT",
    "sg:address":"Nr 17",
    "sg:city":"Kirnberg an der Mank",
    "sg:orig_category":"Pensionen / Privatzimmer",
    "sg:phone":"+43 2755 8664",
    "sg:postcode":"3241",
    "sg:province":"Nieder\u00f6sterreich",
    "wof:name":"Schmutzer Hermann",
    "wof:placetype":"venue"
},
  "geometry": {"coordinates":[15.3218803406,48.0697402954],"type":"Point"}
}