{
  "type": "Feature",
  "properties": {
    "addr:full":"Nr 201 Gosdorf Steiermark 8482",
    "addr:postcode":"8482",
    "addr:street":"Nr 201",
    "iso:country":"AT",
    "sg:address":"Nr 201",
    "sg:city":"Gosdorf",
    "sg:orig_category":"Autoreparatur",
    "sg:phone":"+43 3472 3446",
    "sg:postcode":"8482",
    "sg:province":"Steiermark",
    "wof:name":"Zacharias Josef",
    "wof:placetype":"venue"
},
  "geometry": {"coordinates":[15.7965946198,46.7270584106],"type":"Point"}
}