{
  "type": "Feature",
  "properties": {
    "iso:country":"AT",
    "sg:address":"Molkereistr 6",
    "sg:city":"Wiener Neustadt",
    "sg:orig_category":"Maler, Anstreicher U Lackierer",
    "sg:phone":"+43 4326 2226438",
    "sg:postcode":"2700",
    "sg:province":"Nieder\u00f6sterreich",
    "wof:name":"Neugebauer Werner",
    "wof:placetype":"venue"
},
  "geometry": {"coordinates":[16.2227592468,47.7944145203],"type":"Point"}
}