{
  "type": "Feature",
  "properties": {
    "addr:full":"Dorf 24 Dobl Steiermark 8143",
    "addr:housenumber":"24",
    "addr:postcode":"8143",
    "addr:street":"Dorf",
    "iso:country":"AT",
    "sg:address":"Dorf 24",
    "sg:city":"Dobl",
    "sg:orig_category":"Rettungsdienste",
    "sg:phone":"+43 4331 3663306",
    "sg:postcode":"8143",
    "sg:province":"Steiermark",
    "wof:name":"Gr\u00fcnes Kreuz Ambulanz - Fleischhacker Bernhard",
    "wof:placetype":"venue"
},
  "geometry": {"coordinates":[15.3764295578,46.9467048645],"type":"Point"}
}