{
  "type": "Feature",
  "properties": {
    "addr:full":"Pfarrg. 58 Wien Wien 1230",
    "addr:housenumber":"58",
    "addr:postcode":"1230",
    "addr:street":"Pfarrg.",
    "iso:country":"AT",
    "sg:address":"Pfarrg. 58",
    "sg:city":"Wien",
    "sg:classifiers":[
        {
            "category":"Shopping",
            "subcategory":"Computers & Home Electronics",
            "type":"Retail Goods"
        }
    ],
    "sg:phone":"+43 4316 1007",
    "sg:postcode":"1230",
    "sg:province":"Wien",
    "sg:tags":[
        "electronic",
        "electrical",
        "equipment"
    ],
    "wof:name":"BROTHER INTERNATIONAL GES. MBH",
    "wof:placetype":"venue"
},
  "geometry": {"coordinates":[16.3414840698,48.1392669678],"type":"Point"}
}