{
  "type": "Feature",
  "properties": {
    "iso:country":"AT",
    "sg:address":"J W v Goethe-Str 6-8",
    "sg:city":"Traiskirchen",
    "sg:orig_category":"Hauptschulen",
    "sg:phone":"+43 2252 526440",
    "sg:postcode":"2514",
    "sg:province":"Nieder\u00f6sterreich",
    "wof:name":"Hauptschule",
    "wof:placetype":"venue"
},
  "geometry": {"coordinates":[16.2946777344,48.0138092041],"type":"Point"}
}