{
  "type": "Feature",
  "properties": {
    "addr:full":"Johannesstr 20 Walchsee Tirol 6344",
    "addr:housenumber":"20",
    "addr:postcode":"6344",
    "addr:street":"Johannesstr;Tirol",
    "iso:country":"AT",
    "sg:address":"Johannesstr 20",
    "sg:city":"Walchsee",
    "sg:classifiers":[
        {
            "category":"Travel",
            "subcategory":"Hotels & Motels",
            "type":"Entertainment"
        }
    ],
    "sg:phone":"+43 5374 57310",
    "sg:postcode":"6344",
    "sg:province":"Tirol",
    "wof:name":"Walchsee Hotel GesmbH & Co KG",
    "wof:placetype":"venue"
},
  "geometry": {"coordinates":[12.3269033432,47.6512413025],"type":"Point"}
}