{
  "type": "Feature",
  "properties": {
    "addr:full":"Unterdorf 16 Lermoos Tirol 6631",
    "addr:housenumber":"16",
    "addr:postcode":"6631",
    "addr:street":"Unterdorf;Tirol",
    "iso:country":"AT",
    "sg:address":"Unterdorf 16",
    "sg:city":"Lermoos",
    "sg:orig_category":"Friseure U Frisiersalons",
    "sg:phone":"+43 4356 732162",
    "sg:postcode":"6631",
    "sg:province":"Tirol",
    "wof:name":"Frisiersalon Moser",
    "wof:placetype":"venue"
},
  "geometry": {"coordinates":[10.882019043,47.4016952515],"type":"Point"}
}