{
  "type": "Feature",
  "properties": {
    "addr:full":"Hessenberg 1  Traunkirchen Ober\u00f6sterreich 4801",
    "addr:housenumber":"1",
    "addr:postcode":"4801",
    "addr:street":"Hessenberg",
    "iso:country":"AT",
    "sg:address":"Hessenberg 1 ",
    "sg:city":"Traunkirchen",
    "sg:classifiers":[
        {
            "category":"Professional",
            "subcategory":"Engineering",
            "type":"Services"
        }
    ],
    "sg:phone":"+43 4376 173304",
    "sg:postcode":"4801",
    "sg:province":"Ober\u00f6sterreich",
    "sg:tags":[
        "machine",
        "-",
        "mechanical"
    ],
    "wof:name":"SEMA MASCHINENBAU GMBH",
    "wof:placetype":"venue"
},
  "geometry": {"coordinates":[13.7895488739,47.8446311951],"type":"Point"}
}