{
  "type": "Feature",
  "properties": {
    "iso:country":"AT",
    "sg:address":"Postg 14",
    "sg:city":"Gm\u00fcnd",
    "sg:classifiers":[
        {
            "category":"Taxi",
            "type":"Transportation"
        }
    ],
    "sg:phone":"+43 4328 5252331",
    "sg:postcode":"3950",
    "sg:province":"Nieder\u00f6sterreich",
    "sg:tags":[
        "personentransporte",
        "u"
    ],
    "wof:name":"Klaban Elfriede",
    "wof:placetype":"venue"
},
  "geometry": {"coordinates":[14.972287178,48.7624893188],"type":"Point"}
}