{
  "type": "Feature",
  "properties": {
    "addr:full":"Erlauf Nieder\u00f6sterreich 3253",
    "addr:postcode":"3253",
    "addr:street":"Niederoesterreich",
    "iso:country":"AT",
    "sg:city":"Erlauf",
    "sg:orig_category":"Feuerwehren",
    "sg:phone":"+43 2757 6100",
    "sg:postcode":"3253",
    "sg:province":"Nieder\u00f6sterreich",
    "wof:name":"Feuerwehr Knocking",
    "wof:placetype":"venue"
},
  "geometry": {"coordinates":[15.2113208771,48.1801528931],"type":"Point"}
}