{
  "type": "Feature",
  "properties": {
    "iso:country":"AT",
    "sg:address":"Markt 17",
    "sg:city":"Ulrichsberg",
    "sg:orig_category":"Banken U Sparkassen",
    "sg:phone":"+43 7288 22260",
    "sg:postcode":"4161",
    "sg:province":"Ober\u00f6sterreich",
    "wof:name":"Sparkasse M\u00fchlviertel-West Bank AG",
    "wof:placetype":"venue"
},
  "geometry": {"coordinates":[13.9123306274,48.67445755],"type":"Point"}
}