{
  "type": "Feature",
  "properties": {
    "iso:country":"AT",
    "sg:address":"Steyrer Str 13",
    "sg:city":"Enns",
    "sg:orig_category":"Juweliere, Gold- U Silberschmiede",
    "sg:phone":"+43 7223 82592",
    "sg:postcode":"4470",
    "sg:province":"Ober\u00f6sterreich",
    "wof:name":"Langer Erich",
    "wof:placetype":"venue"
},
  "geometry": {"coordinates":[14.4745988846,48.1993751526],"type":"Point"}
}