{
  "type": "Feature",
  "properties": {
    "addr:full":"Laudong 55 Wien Wien 1080",
    "addr:housenumber":"55",
    "addr:postcode":"1080",
    "addr:street":"Laudong",
    "iso:country":"AT",
    "sg:address":"Laudong 55",
    "sg:city":"Wien",
    "sg:orig_category":"Exporteure U Importeure",
    "sg:phone":"+43 4314 054583",
    "sg:postcode":"1080",
    "sg:province":"Wien",
    "wof:name":"J & B Air Service Import Export",
    "wof:placetype":"venue"
},
  "geometry": {"coordinates":[16.3434448242,48.2130088806],"type":"Point"}
}