{
  "type": "Feature",
  "properties": {
    "addr:full":"Dr.-Felix-Bunzl-Str 1 Wattens Tirol 6112",
    "addr:housenumber":"1",
    "addr:postcode":"6112",
    "addr:street":"Dr.-Felix-Bunzl-Str;Tirol",
    "iso:country":"AT",
    "sg:address":"Dr.-Felix-Bunzl-Str 1",
    "sg:city":"Wattens",
    "sg:orig_category":"Damenmoden",
    "sg:phone":"+43 4352 2453590",
    "sg:postcode":"6112",
    "sg:province":"Tirol",
    "wof:name":"Elviro Fantur KEG",
    "wof:placetype":"venue"
},
  "geometry": {"coordinates":[11.592045784,47.2928924561],"type":"Point"}
}