{
  "type": "Feature",
  "properties": {
    "iso:country":"AT",
    "sg:address":"W\u00e4hringer G\u00fcrtel 107",
    "sg:city":"Wien",
    "sg:classifiers":[
        {
            "category":"Retail",
            "subcategory":"Event Space",
            "type":"Services"
        }
    ],
    "sg:phone":"+43 1 4795422",
    "sg:postcode":"1180",
    "sg:province":"Wien",
    "sg:tags":[
        "hand-",
        "u",
        "fu\u00c3\u0178pflege"
    ],
    "wof:name":"Salon Margret",
    "wof:placetype":"venue"
},
  "geometry": {"coordinates":[16.3445625305,48.2262420654],"type":"Point"}
}