{
  "type": "Feature",
  "properties": {
    "addr:full":"Porzellang 26 Wien Wien 1090",
    "addr:housenumber":"26",
    "addr:postcode":"1090",
    "addr:street":"Porzellang",
    "iso:country":"AT",
    "sg:address":"Porzellang 26",
    "sg:city":"Wien",
    "sg:orig_category":"Psychotherapie",
    "sg:phone":"+43 1 3195947",
    "sg:postcode":"1090",
    "sg:province":"Wien",
    "wof:name":"Rothe Claudia",
    "wof:placetype":"venue"
},
  "geometry": {"coordinates":[16.3608341217,48.2211952209],"type":"Point"}
}