{
  "type": "Feature",
  "properties": {
    "addr:full":"Rainer Str 15 Wels Ober\u00f6sterreich 4600",
    "addr:housenumber":"15",
    "addr:postcode":"4600",
    "addr:street":"Oberoesterreich",
    "iso:country":"AT",
    "sg:address":"Rainer Str 15",
    "sg:city":"Wels",
    "sg:orig_category":"Tankstellen",
    "sg:phone":"+43 7242 473460",
    "sg:postcode":"4600",
    "sg:province":"Ober\u00f6sterreich",
    "wof:name":"Stadlbauer A gegr 1845 Immobilien und Holding GmbH",
    "wof:placetype":"venue"
},
  "geometry": {"coordinates":[14.0212287903,48.1623382568],"type":"Point"}
}