{
  "type": "Feature",
  "properties": {
    "addr:full":"Obere Neusiedlstr 4 St. Leonhard am Forst Nieder\u00f6sterreich 3243",
    "addr:housenumber":"4",
    "addr:postcode":"3243",
    "addr:street":"Obere Neusiedlstr",
    "iso:country":"AT",
    "sg:address":"Obere Neusiedlstr 4",
    "sg:city":"St. Leonhard am Forst",
    "sg:orig_category":"Rauchfangkehrer",
    "sg:phone":"+43 4327 562153",
    "sg:postcode":"3243",
    "sg:province":"Nieder\u00f6sterreich",
    "wof:name":"Bartunek Ferdinand",
    "wof:placetype":"venue"
},
  "geometry": {"coordinates":[15.2900810242,48.1445007324],"type":"Point"}
}