{
  "type": "Feature",
  "properties": {
    "addr:full":"Bad Gams 13 Bad Gams Steiermark 8524",
    "addr:housenumber":"13",
    "addr:postcode":"8524",
    "addr:street":"Bad Gams",
    "iso:country":"AT",
    "sg:address":"Bad Gams 13",
    "sg:city":"Bad Gams",
    "sg:classifiers":[
        {
            "category":"Retail",
            "subcategory":"Repair Shop",
            "type":"Services"
        }
    ],
    "sg:phone":"+43 3463 2321",
    "sg:postcode":"8524",
    "sg:province":"Steiermark",
    "sg:tags":[
        "agricultural",
        "machinery"
    ],
    "sg:website":"horvath.cc",
    "wof:name":"Franz Horvath Ges.m.b.H. & Co KG",
    "wof:placetype":"venue"
},
  "geometry": {"coordinates":[15.2194385529,46.8684654236],"type":"Point"}
}