{
  "type": "Feature",
  "properties": {
    "iso:country":"AT",
    "sg:address":"Obermarkt 30",
    "sg:city":"Reutte",
    "sg:orig_category":"Drogerien",
    "sg:phone":"+43 5672 62469",
    "sg:postcode":"6600",
    "sg:province":"Tirol",
    "wof:name":"Drogerie Parf\u00fcmerie Reformhaus Sorg",
    "wof:placetype":"venue"
},
  "geometry": {"coordinates":[10.7199401855,47.4859542847],"type":"Point"}
}