{
  "type": "Feature",
  "properties": {
    "iso:country":"AT",
    "sg:address":"Koloman-Wallisch-Pl 20",
    "sg:city":"Bruck an der Mur",
    "sg:orig_category":"Boutiquen",
    "sg:phone":"+43 3862 55916",
    "sg:postcode":"8600",
    "sg:province":"Steiermark",
    "wof:name":"Boutique Femina",
    "wof:placetype":"venue"
},
  "geometry": {"coordinates":[15.269908905,47.4101829529],"type":"Point"}
}