{
  "type": "Feature",
  "properties": {
    "iso:country":"AT",
    "sg:address":"Adalbert-Stifter-Str. 65",
    "sg:city":"Wien",
    "sg:classifiers":[
        {
            "category":"Banks & Credit Unions",
            "subcategory":"Financial Services",
            "type":"Services"
        }
    ],
    "sg:phone":"+43 4313 31110",
    "sg:postcode":"1200",
    "sg:province":"Wien",
    "sg:tags":[
        "banking",
        "finance",
        "insurance"
    ],
    "wof:name":"ALLG. UNFALLVERSICHERUNGSANSTALT",
    "wof:placetype":"venue"
},
  "geometry": {"coordinates":[16.3744544983,48.2426986694],"type":"Point"}
}