{
  "type": "Feature",
  "properties": {
    "addr:full":"S\u00fcdtiroler Pl 1 Salzburg Salzburg 5020",
    "addr:housenumber":"1",
    "addr:postcode":"5020",
    "addr:street":"Suedtiroler Pl;Salzburg",
    "iso:country":"AT",
    "sg:address":"S\u00fcdtiroler Pl 1",
    "sg:city":"Salzburg",
    "sg:orig_category":"Friseure U Frisiersalons",
    "sg:phone":"+43 4366 2881381",
    "sg:postcode":"5020",
    "sg:province":"Salzburg",
    "wof:name":"Kr\u00f6ll Peter Bahnhoffriseur",
    "wof:placetype":"venue"
},
  "geometry": {"coordinates":[13.0433769226,47.8006744385],"type":"Point"}
}