{
  "type": "Feature",
  "properties": {
    "addr:full":"Sittendorf Parz 69 Haitzendorf Nieder\u00f6sterreich 3485",
    "addr:housenumber":"69",
    "addr:postcode":"3485",
    "addr:street":"Parz",
    "iso:country":"AT",
    "sg:address":"Sittendorf Parz 69",
    "sg:city":"Haitzendorf",
    "sg:orig_category":"Feuerwehren",
    "sg:phone":"+43 2735 2776",
    "sg:postcode":"3485",
    "sg:province":"Nieder\u00f6sterreich",
    "wof:name":"Freiwillige Feuerwehr Sittendorf",
    "wof:placetype":"venue"
},
  "geometry": {"coordinates":[15.7485160828,48.4298973083],"type":"Point"}
}