{
  "type": "Feature",
  "properties": {
    "iso:country":"AT",
    "sg:address":"Eichelhofweg 505",
    "sg:city":"Wien",
    "sg:orig_category":"Botendienste",
    "sg:phone":"+43 1 3188065",
    "sg:postcode":"1190",
    "sg:province":"Wien",
    "wof:name":"Botendienst TENline logistics - Wolfgang Tenschert",
    "wof:placetype":"venue"
},
  "geometry": {"coordinates":[16.3575344086,48.2663917542],"type":"Point"}
}