{
  "type": "Feature",
  "properties": {
    "addr:full":"Schlo\u00dfstr 19 Hof Salzburg 5322",
    "addr:housenumber":"19",
    "addr:postcode":"5322",
    "addr:street":"Schlossstr;Salzburg",
    "iso:country":"AT",
    "sg:address":"Schlo\u00dfstr 19",
    "sg:city":"Hof",
    "sg:orig_category":"Lebens- U Sozialberatung",
    "sg:phone":"+43 4362 292253235",
    "sg:postcode":"5322",
    "sg:province":"Salzburg",
    "wof:name":"Institut f\u00fcr ganzheitliche Therapie Brigitte Knei\u00dfl Feldenkrais-P\u00e4dagogin",
    "wof:placetype":"venue"
},
  "geometry": {"coordinates":[13.2487602234,47.8084716797],"type":"Point"}
}