{
  "type": "Feature",
  "properties": {
    "addr:full":"Salzacht Bdstr Nord 103 Hallein Salzburg 5400",
    "addr:housenumber":"103",
    "addr:postcode":"5400",
    "addr:street":"Salzburg",
    "iso:country":"AT",
    "sg:address":"Salzacht Bdstr Nord 103",
    "sg:city":"Hallein",
    "sg:orig_category":"Lebensmittel / Einzelhandel",
    "sg:phone":"+43 6245 738380",
    "sg:postcode":"5400",
    "sg:province":"Salzburg",
    "wof:name":"ADEG Contra Markt",
    "wof:placetype":"venue"
},
  "geometry": {"coordinates":[13.0599098206,47.7173194885],"type":"Point"}
}