{
  "type": "Feature",
  "properties": {
    "addr:full":"Gudrunstrasse 90 Wien Wien 1100",
    "addr:housenumber":"90",
    "addr:postcode":"1100",
    "addr:street":"Gudrunstrasse",
    "iso:country":"AT",
    "sg:address":"Gudrunstrasse 90",
    "sg:city":"Wien",
    "sg:classifiers":[
        {
            "category":"Building & Trades",
            "subcategory":"Construction",
            "type":"Services"
        }
    ],
    "sg:phone":"+43 1 60083010",
    "sg:postcode":"1100",
    "sg:province":"Wien",
    "sg:tags":[
        "flat",
        "steep",
        "roof",
        "waterproofing"
    ],
    "sg:website":"isolit.at",
    "wof:name":"Isolit-Isolier GmbH",
    "wof:placetype":"venue"
},
  "geometry": {"coordinates":[16.3842964172,48.1774940491],"type":"Point"}
}