{
  "type": "Feature",
  "properties": {
    "addr:full":"Ohlsdorf Ober\u00f6sterreich 4694",
    "addr:postcode":"4694",
    "iso:country":"AT",
    "sg:city":"Ohlsdorf",
    "sg:orig_category":"Feuerwehren",
    "sg:phone":"+43 761247212",
    "sg:postcode":"4694",
    "sg:province":"Ober\u00f6sterreich",
    "wof:name":"Freiwillige Feuerwehr Ohlsdorf",
    "wof:placetype":"venue"
},
  "geometry": {"coordinates":[13.7921009064,47.960735321],"type":"Point"}
}