{
  "type": "Feature",
  "properties": {
    "addr:full":"Kindergartenweg 10 Kalsdorf Steiermark 8401",
    "addr:housenumber":"10",
    "addr:postcode":"8401",
    "addr:street":"Kindergartenweg",
    "iso:country":"AT",
    "sg:address":"Kindergartenweg 10",
    "sg:city":"Kalsdorf",
    "sg:orig_category":"Friseure U Frisiersalons",
    "sg:phone":"+43 4331 3552620",
    "sg:postcode":"8401",
    "sg:province":"Steiermark",
    "wof:name":"Dworacek Herta",
    "wof:placetype":"venue"
},
  "geometry": {"coordinates":[15.4804553986,46.9617004395],"type":"Point"}
}