{
  "type": "Feature",
  "properties": {
    "addr:full":"Haidestr 35 Wels Ober\u00f6sterreich 4600",
    "addr:housenumber":"35",
    "addr:postcode":"4600",
    "addr:street":"Haidestr;Oberoesterreich",
    "iso:country":"AT",
    "sg:address":"Haidestr 35",
    "sg:city":"Wels",
    "sg:orig_category":"Paletten / Erzeugung U Gro\u00c3\u0178handel",
    "sg:phone":"+43 4367 65508300",
    "sg:postcode":"4600",
    "sg:province":"Ober\u00f6sterreich",
    "wof:name":"Lugmair Walter",
    "wof:placetype":"venue"
},
  "geometry": {"coordinates":[14.0197248459,48.1671104431],"type":"Point"}
}