{
  "type": "Feature",
  "properties": {
    "addr:full":"Hainburger Str 47 Wien Wien 1030",
    "addr:postcode":"1030",
    "addr:street":"Str 47",
    "iso:country":"AT",
    "sg:address":"Hainburger Str 47",
    "sg:city":"Wien",
    "sg:classifiers":[
        {
            "category":"Retail",
            "subcategory":"Event Space",
            "type":"Services"
        }
    ],
    "sg:phone":"+43 4317 182563",
    "sg:postcode":"1030",
    "sg:province":"Wien",
    "sg:tags":[
        "hand-",
        "u",
        "fu\u00c3\u0178pflege"
    ],
    "wof:name":"M\u00fcller Heinrich",
    "wof:placetype":"venue"
},
  "geometry": {"coordinates":[16.3999233246,48.1977233887],"type":"Point"}
}