{
  "type": "Feature",
  "properties": {
    "addr:full":"Drautalstr 14 Feistritz an der Drau K\u00e4rnten 9710",
    "addr:housenumber":"14",
    "addr:postcode":"9710",
    "addr:street":"Drautalstr",
    "iso:country":"AT",
    "sg:address":"Drautalstr 14",
    "sg:city":"Feistritz an der Drau",
    "sg:orig_category":"Tankstellen",
    "sg:phone":"+43 4342 452644",
    "sg:postcode":"9710",
    "sg:province":"K\u00e4rnten",
    "wof:name":"AVANTI TankstellenbetriebsgesmbH",
    "wof:placetype":"venue"
},
  "geometry": {"coordinates":[13.6840639114,46.6893539429],"type":"Point"}
}