{
  "type": "Feature",
  "properties": {
    "addr:full":"Etrichg 15 Innsbruck Tirol 6020",
    "addr:housenumber":"15",
    "addr:postcode":"6020",
    "addr:street":"Etrichg;Tirol",
    "iso:country":"AT",
    "sg:address":"Etrichg 15",
    "sg:city":"Innsbruck",
    "sg:orig_category":"Autohandel",
    "sg:phone":"+43 664 3423737",
    "sg:postcode":"6020",
    "sg:province":"Tirol",
    "wof:name":"Cabrioclassics Inh R\u00fcdiger Pickelmann",
    "wof:placetype":"venue"
},
  "geometry": {"coordinates":[11.4317350388,47.2665290833],"type":"Point"}
}