{
  "type": "Feature",
  "properties": {
    "iso:country":"AT",
    "sg:address":"Bodingbachstr 61",
    "sg:city":"Lunz am See",
    "sg:orig_category":"Messe- U Ausstellungsbau U -Gestaltung",
    "sg:phone":"+43 4374 868648",
    "sg:postcode":"3293",
    "sg:province":"Nieder\u00f6sterreich",
    "sg:website":"messebau-th.info",
    "wof:name":"Theuretzbacher Messebau",
    "wof:placetype":"venue"
},
  "geometry": {"coordinates":[15.0052785873,47.8856086731],"type":"Point"}
}