{
  "type": "Feature",
  "properties": {
    "addr:full":"Nr 16a Mooskirchen Steiermark 8562",
    "addr:postcode":"8562",
    "addr:street":"Nr",
    "iso:country":"AT",
    "sg:address":"Nr 16a",
    "sg:city":"Mooskirchen",
    "sg:orig_category":"Garten- U Landschaftsgestaltung",
    "sg:phone":"+43 4331 373620",
    "sg:postcode":"8562",
    "sg:province":"Steiermark",
    "wof:name":"Brenner Johannes",
    "wof:placetype":"venue"
},
  "geometry": {"coordinates":[15.2820587158,46.9887542725],"type":"Point"}
}