{
  "type": "Feature",
  "properties": {
    "iso:country":"AT",
    "sg:address":"El\u00dflergasse 24",
    "sg:city":"Wien",
    "sg:classifiers":[
        {
            "category":"Structure",
            "subcategory":"Tunnel",
            "type":"Public Place"
        }
    ],
    "sg:phone":"+43 1 8767600",
    "sg:postcode":"1130",
    "sg:province":"Wien",
    "sg:tags":[
        "catheter"
    ],
    "sg:website":"amex-vienna.at",
    "wof:name":"Amex-Export-Import Ges.m.b.H.",
    "wof:placetype":"venue"
},
  "geometry": {"coordinates":[16.3013801575,48.18592453],"type":"Point"}
}