{
  "type": "Feature",
  "properties": {
    "addr:full":"Kleinreith Gewerbepark 2 Ohlsdorf Ober\u00f6sterreich 4694",
    "addr:housenumber":"2",
    "addr:postcode":"4694",
    "addr:street":"Gewerbepark",
    "iso:country":"AT",
    "sg:address":"Kleinreith Gewerbepark 2",
    "sg:city":"Ohlsdorf",
    "sg:orig_category":"Installationsunternehmen",
    "sg:phone":"+43 4376 1264813",
    "sg:postcode":"4694",
    "sg:province":"Ober\u00f6sterreich",
    "sg:website":"wellnessbau.at",
    "wof:name":"Schiller Installations GesmbH & Co KG",
    "wof:placetype":"venue"
},
  "geometry": {"coordinates":[13.7924604416,47.9412612915],"type":"Point"}
}