{
  "type": "Feature",
  "properties": {
    "iso:country":"AT",
    "sg:address":"Industriegebiet 4",
    "sg:city":"Losenstein",
    "sg:classifiers":[
        {
            "category":"Manufacturing",
            "subcategory":"Motor Vehicles & Parts",
            "type":"Manufacturing & Wholesale Goods"
        }
    ],
    "sg:phone":"+43 7255 62370",
    "sg:postcode":"4460",
    "sg:province":"Ober\u00f6sterreich",
    "sg:tags":[
        "component",
        "hydraulic"
    ],
    "sg:website":"weber-hydraulik.at",
    "wof:name":"WEBER-HYDRAULIK GmbH",
    "wof:placetype":"venue"
},
  "geometry": {"coordinates":[14.4064121246,47.9311256409],"type":"Point"}
}