{
  "type": "Feature",
  "properties": {
    "addr:full":"Vordernebelberg 33 Kollerschlag Ober\u00f6sterreich 4154",
    "addr:housenumber":"33",
    "addr:postcode":"4154",
    "addr:street":"Vordernebelberg",
    "iso:country":"AT",
    "sg:address":"Vordernebelberg 33",
    "sg:city":"Kollerschlag",
    "sg:orig_category":"Pensionen / Privatzimmer",
    "sg:phone":"+43 7287 72370",
    "sg:postcode":"4154",
    "sg:province":"Ober\u00f6sterreich",
    "wof:name":"Ramlhof Sportpension Hotel - Fam Kasper",
    "wof:placetype":"venue"
},
  "geometry": {"coordinates":[13.8414564133,48.6052284241],"type":"Point"}
}