{
  "type": "Feature",
  "properties": {
    "addr:full":"Kaiser-Franz-Josef-Str 17 Bad Gastein Salzburg 5640",
    "addr:housenumber":"17",
    "addr:postcode":"5640",
    "addr:street":"Kaiser-Franz-Josef-Str;Salzburg",
    "iso:country":"AT",
    "sg:address":"Kaiser-Franz-Josef-Str 17",
    "sg:city":"Bad Gastein",
    "sg:orig_category":"Schneidereien",
    "sg:phone":"+43 4364 346405",
    "sg:postcode":"5640",
    "sg:province":"Salzburg",
    "wof:name":"Hermi's N\u00e4hstube",
    "wof:placetype":"venue"
},
  "geometry": {"coordinates":[13.1343851089,47.1161842346],"type":"Point"}
}