{
  "type": "Feature",
  "properties": {
    "addr:full":"Tobersbachstr 50 Uttendorf Salzburg 5723",
    "addr:housenumber":"50",
    "addr:postcode":"5723",
    "addr:street":"Tobersbachstr;Salzburg",
    "iso:country":"AT",
    "sg:address":"Tobersbachstr 50",
    "sg:city":"Uttendorf",
    "sg:orig_category":"Blumeneinzelhandel",
    "sg:phone":"+43 6563 8843",
    "sg:postcode":"5723",
    "sg:province":"Salzburg",
    "wof:name":"Blumen Germann - Inh Hans Peter Rettenmoser",
    "wof:placetype":"venue"
},
  "geometry": {"coordinates":[12.5809793472,47.2856864929],"type":"Point"}
}