{
  "type": "Feature",
  "properties": {
    "iso:country":"AT",
    "sg:city":"Haslach an der M\u00fchl",
    "sg:orig_category":"Reisen, Tourismusinfo",
    "sg:postcode":"4170",
    "sg:province":"Ober\u00f6sterreich",
    "sg:website":"http://www.romantik.at",
    "wof:name":"BERGERGUT Romantik Hotel",
    "wof:placetype":"venue"
},
  "geometry": {"coordinates":[14.0414218903,48.5752792358],"type":"Point"}
}