{
  "type": "Feature",
  "properties": {
    "addr:full":"Wolkensteing 24 Graz Steiermark 8020",
    "addr:housenumber":"24",
    "addr:postcode":"8020",
    "addr:street":"Wolkensteing",
    "iso:country":"AT",
    "sg:address":"Wolkensteing 24",
    "sg:city":"Graz",
    "sg:orig_category":"Schmieden U Schmiedeeisenelemente",
    "sg:phone":"+43 316 574919",
    "sg:postcode":"8020",
    "sg:province":"Steiermark",
    "wof:name":"Posarnig Erwin Mag Ing - K\u00fcnstler - Schlosser - Schmiedemeister",
    "wof:placetype":"venue"
},
  "geometry": {"coordinates":[15.4077711105,47.0804748535],"type":"Point"}
}