{
  "type": "Feature",
  "properties": {
    "addr:full":"Nordbahnstr 18 Wien Wien 1020",
    "addr:housenumber":"18",
    "addr:postcode":"1020",
    "addr:street":"Nordbahnstr",
    "iso:country":"AT",
    "sg:address":"Nordbahnstr 18",
    "sg:city":"Wien",
    "sg:orig_category":"Chemikalien",
    "sg:phone":"+43 4312 1223310",
    "sg:postcode":"1020",
    "sg:province":"Wien",
    "wof:name":"Nova Chemie GesmbH & Co KG Erz u Vertrieb v chem Produkten",
    "wof:placetype":"venue"
},
  "geometry": {"coordinates":[16.3885097504,48.2258491516],"type":"Point"}
}