{
  "type": "Feature",
  "properties": {
    "addr:full":"Enterwinkl 53 Maria Alm am Steinernen Meer Salzburg 5761",
    "addr:housenumber":"53",
    "addr:postcode":"5761",
    "addr:street":"Enterwinkl",
    "iso:country":"AT",
    "sg:address":"Enterwinkl 53",
    "sg:city":"Maria Alm am Steinernen Meer",
    "sg:orig_category":"Reinigungsbedarf U Reinigungsmittel",
    "sg:phone":"+43 4366 43414697",
    "sg:postcode":"5761",
    "sg:province":"Salzburg",
    "wof:name":"Eder Wilfried",
    "wof:placetype":"venue"
},
  "geometry": {"coordinates":[12.9207572937,47.4088439941],"type":"Point"}
}