{
  "type": "Feature",
  "properties": {
    "addr:full":"Garteng 8 Ferlach K\u00e4rnten 9170",
    "addr:housenumber":"8",
    "addr:postcode":"9170",
    "addr:street":"Garteng;Kaernten",
    "iso:country":"AT",
    "sg:address":"Garteng 8",
    "sg:city":"Ferlach",
    "sg:orig_category":"Musikgruppen",
    "sg:phone":"+43 4227 2831",
    "sg:postcode":"9170",
    "sg:province":"K\u00e4rnten",
    "wof:name":"Mobile Disco Trampmusik Inh Robert Moser",
    "wof:placetype":"venue"
},
  "geometry": {"coordinates":[14.3032522202,46.5286026001],"type":"Point"}
}