{
  "type": "Feature",
  "properties": {
    "iso:country":"AT",
    "sg:address":"Am Rauchkogel 7",
    "sg:city":"Maria Enzersdorf",
    "sg:orig_category":"Geschenkartikel",
    "sg:phone":"+43 2236 46366",
    "sg:postcode":"2344",
    "sg:province":"Nieder\u00f6sterreich",
    "wof:name":"ROWE Robert Weber",
    "wof:placetype":"venue"
},
  "geometry": {"coordinates":[16.2671756744,48.0970535278],"type":"Point"}
}