{
  "type": "Feature",
  "properties": {
    "addr:full":"Millst\u00e4tter Str 77 Feld am See K\u00e4rnten 9544",
    "addr:postcode":"9544",
    "addr:street":"Str 77;Kaernten",
    "iso:country":"AT",
    "sg:address":"Millst\u00e4tter Str 77",
    "sg:city":"Feld am See",
    "sg:orig_category":"Fischzucht",
    "sg:phone":"+43 4246 2345",
    "sg:postcode":"9544",
    "sg:province":"K\u00e4rnten",
    "wof:name":"Fischzucht Feld am See - K\u00e4rntenfisch",
    "wof:placetype":"venue"
},
  "geometry": {"coordinates":[13.7401294708,46.780456543],"type":"Point"}
}