{
  "type": "Feature",
  "properties": {
    "addr:full":"Innerberger Str. 13 Schwechat Nieder\u00f6sterreich 2320",
    "addr:postcode":"2320",
    "addr:street":"Str. 13 Schwechat Niederoesterreich",
    "iso:country":"AT",
    "sg:address":"Innerberger Str. 13",
    "sg:city":"Schwechat",
    "sg:classifiers":[
        {
            "category":"Parking",
            "subcategory":"Lot",
            "type":"Transportation"
        }
    ],
    "sg:phone":"+43 4317 078135",
    "sg:postcode":"2320",
    "sg:province":"Nieder\u00f6sterreich",
    "sg:tags":[
        "transport",
        "road"
    ],
    "wof:name":"F. F. GSCHWENDT OHG",
    "wof:placetype":"venue"
},
  "geometry": {"coordinates":[16.4743232727,48.15102005],"type":"Point"}
}