{
  "type": "Feature",
  "properties": {
    "iso:country":"AT",
    "sg:address":"Nr 11",
    "sg:city":"Gampern",
    "sg:orig_category":"Transportunternehmen",
    "sg:phone":"+43 768280030",
    "sg:postcode":"4851",
    "sg:province":"Ober\u00f6sterreich",
    "wof:name":"Reiter Transport GmbH & Co KG",
    "wof:placetype":"venue"
},
  "geometry": {"coordinates":[13.5552349091,47.989364624],"type":"Point"}
}