{
  "type": "Feature",
  "properties": {
    "addr:full":"Nestelbachberg 34 Nestelbach Steiermark 8302",
    "addr:housenumber":"34",
    "addr:postcode":"8302",
    "addr:street":"Nestelbachberg",
    "iso:country":"AT",
    "sg:address":"Nestelbachberg 34",
    "sg:city":"Nestelbach",
    "sg:classifiers":[
        {
            "category":"Professional",
            "subcategory":"Management & Consulting",
            "type":"Services"
        }
    ],
    "sg:phone":"+43 4366 41012218",
    "sg:postcode":"8302",
    "sg:province":"Steiermark",
    "sg:tags":[
        "supervision"
    ],
    "wof:name":"Weiss Wolfgang",
    "wof:placetype":"venue"
},
  "geometry": {"coordinates":[15.6123256683,47.0734291077],"type":"Point"}
}