{
  "type": "Feature",
  "properties": {
    "addr:full":"Nr 195 Heimschuh Steiermark 8451",
    "addr:postcode":"8451",
    "addr:street":"Nr",
    "iso:country":"AT",
    "sg:address":"Nr 195",
    "sg:city":"Heimschuh",
    "sg:orig_category":"Tischlereien",
    "sg:phone":"+43 4334 5282481",
    "sg:postcode":"8451",
    "sg:province":"Steiermark",
    "wof:name":"Hartner Franz",
    "wof:placetype":"venue"
},
  "geometry": {"coordinates":[15.4879951477,46.7589645386],"type":"Point"}
}