{
  "type": "Feature",
  "properties": {
    "addr:full":"Heinrichstr 2 Graz Steiermark 8010",
    "addr:housenumber":"2",
    "addr:postcode":"8010",
    "addr:street":"Heinrichstr",
    "iso:country":"AT",
    "sg:address":"Heinrichstr 2",
    "sg:city":"Graz",
    "sg:orig_category":"Lebensmittel / Einzelhandel",
    "sg:phone":"+43 316 324773",
    "sg:postcode":"8010",
    "sg:province":"Steiermark",
    "wof:name":"Hornig J GmbH",
    "wof:placetype":"venue"
},
  "geometry": {"coordinates":[15.4437236786,47.0778274536],"type":"Point"}
}