{
  "type": "Feature",
  "properties": {
    "addr:full":"Keplerstr 8 Sattledt Ober\u00f6sterreich 4642",
    "addr:housenumber":"8",
    "addr:postcode":"4642",
    "addr:street":"Keplerstr",
    "iso:country":"AT",
    "sg:address":"Keplerstr 8",
    "sg:city":"Sattledt",
    "sg:orig_category":"\u00c3\u201erzte / F Allgemeinmedizin",
    "sg:phone":"+43 7244 8762",
    "sg:postcode":"4642",
    "sg:province":"Ober\u00f6sterreich",
    "wof:name":"Schmidinger Josef Dr",
    "wof:placetype":"venue"
},
  "geometry": {"coordinates":[14.0597286224,48.0716705322],"type":"Point"}
}