{
  "type": "Feature",
  "properties": {
    "addr:full":"Hauptstr 26 Peuerbach Ober\u00f6sterreich 4722",
    "addr:housenumber":"26",
    "addr:postcode":"4722",
    "addr:street":"Hauptstr",
    "iso:country":"AT",
    "sg:address":"Hauptstr 26",
    "sg:city":"Peuerbach",
    "sg:orig_category":"Banken U Sparkassen",
    "sg:phone":"+43 4372 7624050",
    "sg:postcode":"4722",
    "sg:province":"Ober\u00f6sterreich",
    "wof:name":"Sparkasse Eferding-Peuerbach-Waizenkirchen",
    "wof:placetype":"venue"
},
  "geometry": {"coordinates":[13.7707490921,48.3450775146],"type":"Point"}
}