{
  "type": "Feature",
  "properties": {
    "addr:full":"Schlo\u00df 1 P\u00f6llau Steiermark 8225",
    "addr:housenumber":"1",
    "addr:postcode":"8225",
    "addr:street":"Schloss",
    "iso:country":"AT",
    "sg:address":"Schlo\u00df 1",
    "sg:city":"P\u00f6llau",
    "sg:orig_category":"Friseure U Frisiersalons",
    "sg:phone":"+43 4333 352334",
    "sg:postcode":"8225",
    "sg:province":"Steiermark",
    "wof:name":"Schlo\u00dffriseur Hirschegger",
    "wof:placetype":"venue"
},
  "geometry": {"coordinates":[15.8337945938,47.301990509],"type":"Point"}
}