{
  "type": "Feature",
  "properties": {
    "iso:country":"AT",
    "sg:address":"Fabriksstr 2",
    "sg:city":"Enzesfeld-Lindabrunn",
    "sg:orig_category":"Metalle U -Halbfabrikate",
    "sg:phone":"+43 2256 811450",
    "sg:postcode":"2551",
    "sg:province":"Nieder\u00f6sterreich",
    "wof:name":"Enzesfeld-Caro Metallwerke AG",
    "wof:placetype":"venue"
},
  "geometry": {"coordinates":[16.1926345825,47.9217224121],"type":"Point"}
}