{
  "type": "Feature",
  "properties": {
    "iso:country":"AT",
    "sg:address":"Leystr 114",
    "sg:city":"Wien",
    "sg:orig_category":"Lebensmittel / Einzelhandel",
    "sg:phone":"+43 4313 337401",
    "sg:postcode":"1200",
    "sg:province":"Wien",
    "wof:name":"EGETUERK YASAR VURAL KEG",
    "wof:placetype":"venue"
},
  "geometry": {"coordinates":[16.3876781464,48.2338905334],"type":"Point"}
}