{
  "type": "Feature",
  "properties": {
    "addr:full":"Gartenstrasse 10 Wartberg an der Krems Ober\u00f6sterreich 4552",
    "addr:housenumber":"10",
    "addr:postcode":"4552",
    "addr:street":"Gartenstrasse",
    "iso:country":"AT",
    "sg:address":"Gartenstrasse 10",
    "sg:city":"Wartberg an der Krems",
    "sg:classifiers":[
        {
            "category":"Banks & Credit Unions",
            "subcategory":"Atm",
            "type":"Services"
        }
    ],
    "sg:phone":"+43 7587 7362",
    "sg:postcode":"4552",
    "sg:province":"Ober\u00f6sterreich",
    "sg:tags":[
        "dispersion",
        "cast"
    ],
    "wof:name":"Gernot Grall",
    "wof:placetype":"venue"
},
  "geometry": {"coordinates":[14.1145029068,47.9866294861],"type":"Point"}
}