{
  "type": "Feature",
  "properties": {
    "addr:full":"Carlbergerg 45 Wien Wien 1230",
    "addr:housenumber":"45",
    "addr:postcode":"1230",
    "addr:street":"Carlbergerg",
    "iso:country":"AT",
    "sg:address":"Carlbergerg 45",
    "sg:city":"Wien",
    "sg:orig_category":"Druckluftanlagen U -Maschinen",
    "sg:phone":"+43 1 8698766",
    "sg:postcode":"1230",
    "sg:province":"Wien",
    "wof:name":"AMERSIN Olschinsky GmbH",
    "wof:placetype":"venue"
},
  "geometry": {"coordinates":[16.296831131,48.1412811279],"type":"Point"}
}