{
  "type": "Feature",
  "properties": {
    "iso:country":"AT",
    "sg:address":"Krugerstr 12",
    "sg:city":"Wien",
    "sg:orig_category":"Friseure U Frisiersalons",
    "sg:phone":"+43 4315 443434",
    "sg:postcode":"1010",
    "sg:province":"Wien",
    "wof:name":"Botanik Natur- u Revitalfris\u00f6r",
    "wof:placetype":"venue"
},
  "geometry": {"coordinates":[16.3722763062,48.2036399841],"type":"Point"}
}