{
  "type": "Feature",
  "properties": {
    "addr:full":"Laxenburger Str 99 Wien Wien 1100",
    "addr:housenumber":"99",
    "addr:postcode":"1100",
    "addr:street":"Laxenburger Str",
    "iso:country":"AT",
    "sg:address":"Laxenburger Str 99",
    "sg:city":"Wien",
    "sg:orig_category":"Installationsunternehmen",
    "sg:phone":"+43 1 6043487",
    "sg:postcode":"1100",
    "sg:province":"Wien",
    "sg:website":"scheder.at",
    "wof:name":"Scheder Johann",
    "wof:placetype":"venue"
},
  "geometry": {"coordinates":[16.3721466064,48.1716308594],"type":"Point"}
}