{
  "type": "Feature",
  "properties": {
    "iso:country":"AT",
    "sg:address":"Wiener Str 52",
    "sg:city":"Schwechat",
    "sg:orig_category":"Satellitenempfangsanlagen",
    "sg:phone":"+43 4317 064466",
    "sg:postcode":"2320",
    "sg:province":"Nieder\u00f6sterreich",
    "wof:name":"B & R Elektrobau GesmbH",
    "wof:placetype":"venue"
},
  "geometry": {"coordinates":[16.4683704376,48.1460342407],"type":"Point"}
}