{
  "type": "Feature",
  "properties": {
    "addr:full":"Nr 43 Taufkirchen an der Pram Ober\u00f6sterreich 4775",
    "addr:postcode":"4775",
    "addr:street":"Nr 43",
    "iso:country":"AT",
    "sg:address":"Nr 43",
    "sg:city":"Taufkirchen an der Pram",
    "sg:orig_category":"Kosmetikanwendungsberatung",
    "sg:phone":"+43 4377 198309",
    "sg:postcode":"4775",
    "sg:province":"Ober\u00f6sterreich",
    "wof:name":"Channoine u Nobusan-Fachberatung - Elfriede u Rudolf Schmiedseder",
    "wof:placetype":"venue"
},
  "geometry": {"coordinates":[13.5362701416,48.4104499817],"type":"Point"}
}