{
  "type": "Feature",
  "properties": {
    "addr:full":"M\u00fctzens 5 Matrei am Brenner Tirol 6143",
    "addr:housenumber":"5",
    "addr:postcode":"6143",
    "addr:street":"Muetzens;Brenner",
    "iso:country":"AT",
    "sg:address":"M\u00fctzens 5",
    "sg:city":"Matrei am Brenner",
    "sg:orig_category":"Pensionen / Privatzimmer",
    "sg:phone":"+43 5273 6159",
    "sg:postcode":"6143",
    "sg:province":"Tirol",
    "wof:name":"Ferienhof Staacher",
    "wof:placetype":"venue"
},
  "geometry": {"coordinates":[11.4604654312,47.1421813965],"type":"Point"}
}