{
  "type": "Feature",
  "properties": {
    "iso:country":"AT",
    "sg:address":"Brauhausstrasse 67",
    "sg:city":"Schwechat",
    "sg:classifiers":[
        {
            "category":"Structure",
            "subcategory":"Bridge",
            "type":"Public Place"
        }
    ],
    "sg:phone":"+43 1 70766220",
    "sg:postcode":"2320",
    "sg:province":"Nieder\u00f6sterreich",
    "sg:tags":[
        "automation"
    ],
    "sg:website":"baumeister.cc",
    "wof:name":"Ing. Manfred Leiner Baumeister und Bautr\u00e4ger GmbH",
    "wof:placetype":"venue"
},
  "geometry": {"coordinates":[16.4624958038,48.125743866],"type":"Point"}
}