{
  "type": "Feature",
  "properties": {
    "addr:full":"Sackstrasse 8  Stainz Steiermark 8510",
    "addr:housenumber":"8",
    "addr:postcode":"8510",
    "addr:street":"Sackstrasse",
    "iso:country":"AT",
    "sg:address":"Sackstrasse 8 ",
    "sg:city":"Stainz",
    "sg:classifiers":[
        {
            "category":"Government",
            "subcategory":"Fire Station",
            "type":"Public Place"
        }
    ],
    "sg:phone":"+43 3463 2307",
    "sg:postcode":"8510",
    "sg:province":"Steiermark",
    "sg:tags":[
        "supraregional",
        "plant",
        "installation",
        "heating"
    ],
    "sg:website":"www.lsi.at",
    "wof:name":"Karl Flanyek Ges.m.b.H.",
    "wof:placetype":"venue"
},
  "geometry": {"coordinates":[15.2630853653,46.8932342529],"type":"Point"}
}