{
  "type": "Feature",
  "properties": {
    "addr:full":"Dr.-Kasimir-Graff-G 4 Breitenfurt Nieder\u00f6sterreich 2384",
    "addr:housenumber":"4",
    "addr:postcode":"2384",
    "addr:street":"Dr.-Kasimir-Graff-G",
    "iso:country":"AT",
    "sg:address":"Dr.-Kasimir-Graff-G 4",
    "sg:city":"Breitenfurt",
    "sg:orig_category":"\u00c3\u201erzte / F Allgemeinmedizin",
    "sg:phone":"+43 2239 33220",
    "sg:postcode":"2384",
    "sg:province":"Nieder\u00f6sterreich",
    "wof:name":"Hahn Franz Dr",
    "wof:placetype":"venue"
},
  "geometry": {"coordinates":[16.195520401,48.1339645386],"type":"Point"}
}