{
  "type": "Feature",
  "properties": {
    "iso:country":"AT",
    "sg:address":"Bahnhofstr 15",
    "sg:city":"Dornbirn",
    "sg:orig_category":"Bankomat-Standorte",
    "sg:phone":"+43 4350 5333",
    "sg:postcode":"6850",
    "sg:province":"Vorarlberg",
    "wof:name":"Bankomat d BTV - Bank f\u00fcr Tirol und Vorarlberg AG",
    "wof:placetype":"venue"
},
  "geometry": {"coordinates":[9.7395143509,47.4156074524],"type":"Point"}
}