{
  "type": "Feature",
  "properties": {
    "addr:full":"Unterdorf 1 Wenns Tirol 6473",
    "addr:housenumber":"1",
    "addr:postcode":"6473",
    "addr:street":"Unterdorf;Tirol",
    "iso:country":"AT",
    "sg:address":"Unterdorf 1",
    "sg:city":"Wenns",
    "sg:orig_category":"Fleischhauereien",
    "sg:phone":"+43 5414 87264",
    "sg:postcode":"6473",
    "sg:province":"Tirol",
    "wof:name":"Krug Rudolf",
    "wof:placetype":"venue"
},
  "geometry": {"coordinates":[10.7312002182,47.1684265137],"type":"Point"}
}