{
  "type": "Feature",
  "properties": {
    "addr:full":"Sch\u00f6nburgstrasse 26 Wien Wien 1040",
    "addr:housenumber":"26",
    "addr:postcode":"1040",
    "addr:street":"Schoenburgstrasse",
    "iso:country":"AT",
    "sg:address":"Sch\u00f6nburgstrasse 26",
    "sg:city":"Wien",
    "sg:classifiers":[
        {
            "category":"Arts & Performance",
            "subcategory":"Arts Center",
            "type":"Entertainment"
        }
    ],
    "sg:phone":"+43 1 50598530",
    "sg:postcode":"1040",
    "sg:province":"Wien",
    "sg:tags":[
        "print",
        "photographic",
        "digital"
    ],
    "sg:website":"grandits-team.at",
    "wof:name":"Grandits-Team Reprografie Ges.m.b.H.",
    "wof:placetype":"venue"
},
  "geometry": {"coordinates":[16.3683853149,48.188117981],"type":"Point"}
}