{
  "type": "Feature",
  "properties": {
    "iso:country":"AT",
    "sg:address":"Bahnhofallee 34",
    "sg:city":"Bad Schallerbach",
    "sg:orig_category":"Massagen",
    "sg:phone":"+43 7249 48531",
    "sg:postcode":"4701",
    "sg:province":"Ober\u00f6sterreich",
    "wof:name":"Waltenberger Gerda",
    "wof:placetype":"venue"
},
  "geometry": {"coordinates":[13.9185314178,48.2297859192],"type":"Point"}
}