{
  "type": "Feature",
  "properties": {
    "iso:country":"AT",
    "sg:address":"Felix-Ennemoser-Weg 17",
    "sg:city":"Elsbethen-Glasenbach",
    "sg:orig_category":"Rauchfangkehrer",
    "sg:phone":"+43 662 625793",
    "sg:postcode":"5061",
    "sg:province":"Salzburg",
    "wof:name":"Abfalter Helmut",
    "wof:placetype":"venue"
},
  "geometry": {"coordinates":[13.0803852081,47.7644462585],"type":"Point"}
}