{
  "type": "Feature",
  "properties": {
    "addr:full":"A\u00dfmayergasse 54 Wien Wien 1120",
    "addr:housenumber":"54",
    "addr:postcode":"1120",
    "addr:street":"Assmayergasse",
    "iso:country":"AT",
    "sg:address":"A\u00dfmayergasse 54",
    "sg:city":"Wien",
    "sg:classifiers":[
        {
            "category":"Wholesale",
            "subcategory":"Construction Materials",
            "type":"Manufacturing & Wholesale Goods"
        }
    ],
    "sg:phone":"+43 1 8151555",
    "sg:postcode":"1120",
    "sg:province":"Wien",
    "sg:tags":[
        "bridge",
        "temporary",
        "materials",
        "crown"
    ],
    "wof:name":"Dentallabor Norbert Derbl",
    "wof:placetype":"venue"
},
  "geometry": {"coordinates":[16.3290939331,48.1824874878],"type":"Point"}
}