{
  "type": "Feature",
  "properties": {
    "iso:country":"AT",
    "sg:address":"Brixner Str 3",
    "sg:city":"Innsbruck",
    "sg:orig_category":"Briefmarken Philatelie",
    "sg:phone":"+43 4351 2587972",
    "sg:postcode":"6020",
    "sg:province":"Tirol",
    "wof:name":"Poettinger Toni",
    "wof:placetype":"venue"
},
  "geometry": {"coordinates":[11.3997220993,47.264957428],"type":"Point"}
}