{
  "type": "Feature",
  "properties": {
    "iso:country":"AT",
    "sg:address":"Nr 7",
    "sg:city":"Obritzberg",
    "sg:orig_category":"Wasseraufbereitung U -Reinigung",
    "sg:phone":"+43 4327 866422",
    "sg:postcode":"3123",
    "sg:province":"Nieder\u00f6sterreich",
    "wof:name":"Higer Rudolf - Fachberatung & Verkauf f GRANDER-TECHNOLOGIE",
    "wof:placetype":"venue"
},
  "geometry": {"coordinates":[15.5941095352,48.2923965454],"type":"Point"}
}