{
  "type": "Feature",
  "properties": {
    "addr:full":"Pestalozzistr 75 Leoben Steiermark 8700",
    "addr:housenumber":"75",
    "addr:postcode":"8700",
    "addr:street":"Pestalozzistr",
    "iso:country":"AT",
    "sg:address":"Pestalozzistr 75",
    "sg:city":"Leoben",
    "sg:orig_category":"Tabaktrafiken",
    "sg:phone":"+43 3842 216330",
    "sg:postcode":"8700",
    "sg:province":"Steiermark",
    "wof:name":"Kern Ewald",
    "wof:placetype":"venue"
},
  "geometry": {"coordinates":[15.0734157562,47.3759498596],"type":"Point"}
}