{
  "type": "Feature",
  "properties": {
    "iso:country":"AT",
    "sg:address":"H\u00f6henweg 7",
    "sg:city":"Micheldorf",
    "sg:orig_category":"Sonnenschutzanlagen",
    "sg:phone":"+43 4366 44105719",
    "sg:postcode":"9322",
    "sg:province":"K\u00e4rnten",
    "wof:name":"ZEBO-Tec Zerz u Bolcevic OEG",
    "wof:placetype":"venue"
},
  "geometry": {"coordinates":[14.4270496368,46.9146881104],"type":"Point"}
}