{
  "type": "Feature",
  "properties": {
    "addr:full":"Mitterhofer Str 6 Wels Ober\u00f6sterreich 4600",
    "addr:housenumber":"6",
    "addr:postcode":"4600",
    "addr:street":"Str;Oberoesterreich",
    "iso:country":"AT",
    "sg:address":"Mitterhofer Str 6",
    "sg:city":"Wels",
    "sg:orig_category":"Autohandel",
    "sg:phone":"+43 7242 474620",
    "sg:postcode":"4600",
    "sg:province":"Ober\u00f6sterreich",
    "wof:name":"Riehs Hermann GesmbH & Co KG",
    "wof:placetype":"venue"
},
  "geometry": {"coordinates":[14.0649232864,48.1778450012],"type":"Point"}
}