{
  "type": "Feature",
  "properties": {
    "addr:full":"Kaiser-Josef-Str 25 Wolkersdorf im Weinviertel Nieder\u00f6sterreich 2120",
    "addr:housenumber":"25",
    "addr:postcode":"2120",
    "addr:street":"Kaiser-Josef-Str",
    "iso:country":"AT",
    "sg:address":"Kaiser-Josef-Str 25",
    "sg:city":"Wolkersdorf im Weinviertel",
    "sg:orig_category":"Tischlereien",
    "sg:phone":"+43 4322 452392",
    "sg:postcode":"2120",
    "sg:province":"Nieder\u00f6sterreich",
    "wof:name":"Wei\u00df Friedrich",
    "wof:placetype":"venue"
},
  "geometry": {"coordinates":[16.5189704895,48.3852653503],"type":"Point"}
}