{
  "type": "Feature",
  "properties": {
    "addr:full":"Gehrenstr 31 Klaus-Weiler Vorarlberg 6833",
    "addr:housenumber":"31",
    "addr:postcode":"6833",
    "addr:street":"Gehrenstr",
    "iso:country":"AT",
    "sg:address":"Gehrenstr 31",
    "sg:city":"Klaus-Weiler",
    "sg:orig_category":"Stickereien",
    "sg:phone":"+43 5523 62649",
    "sg:postcode":"6833",
    "sg:province":"Vorarlberg",
    "wof:name":"Loacker Ulrich",
    "wof:placetype":"venue"
},
  "geometry": {"coordinates":[9.6490316391,47.2999267578],"type":"Point"}
}