{
  "type": "Feature",
  "properties": {
    "addr:full":"Mitterkleinarl 194 Wagrain Salzburg 5602",
    "addr:housenumber":"194",
    "addr:postcode":"5602",
    "addr:street":"Mitterkleinarl;Salzburg",
    "iso:country":"AT",
    "sg:address":"Mitterkleinarl 194",
    "sg:city":"Wagrain",
    "sg:orig_category":"Pensionen / Privatzimmer",
    "sg:phone":"+43 6418 342",
    "sg:postcode":"5602",
    "sg:province":"Salzburg",
    "wof:name":"Viehhauser Rupert",
    "wof:placetype":"venue"
},
  "geometry": {"coordinates":[13.2964773178,47.3332366943],"type":"Point"}
}