{
  "type": "Feature",
  "properties": {
    "iso:country":"AT",
    "sg:address":"Langenloiser Str 71",
    "sg:city":"Gf\u00f6hl",
    "sg:orig_category":"Bauunternehmen",
    "sg:phone":"+43 2716 20070",
    "sg:postcode":"3542",
    "sg:province":"Nieder\u00f6sterreich",
    "wof:name":"Eckl A BauGmbH",
    "wof:placetype":"venue"
},
  "geometry": {"coordinates":[-71.7024688721,43.5195732117],"type":"Point"}
}