{
  "type": "Feature",
  "properties": {
    "iso:country":"AT",
    "sg:address":"Brauhausstr 40",
    "sg:city":"Schwechat",
    "sg:orig_category":"Friseure U Frisiersalons",
    "sg:phone":"+43 4317 072288",
    "sg:postcode":"2320",
    "sg:province":"Nieder\u00f6sterreich",
    "wof:name":"Salon Inge Inh Zrunek Ingeborg GesmbH",
    "wof:placetype":"venue"
},
  "geometry": {"coordinates":[16.4657611847,48.1300468445],"type":"Point"}
}