{
  "type": "Feature",
  "properties": {
    "addr:full":"Hauptstr 146 Klosterneuburg Nieder\u00f6sterreich 3400",
    "addr:housenumber":"146",
    "addr:postcode":"3400",
    "addr:street":"Hauptstr;Niederoesterreich",
    "iso:country":"AT",
    "sg:address":"Hauptstr 146",
    "sg:city":"Klosterneuburg",
    "sg:classifiers":[
        {
            "category":"Restaurant",
            "type":"Food & Drink"
        }
    ],
    "sg:phone":"+43 2243 83180",
    "sg:postcode":"3400",
    "sg:province":"Nieder\u00f6sterreich",
    "wof:name":"Strasser Oskar",
    "wof:placetype":"venue"
},
  "geometry": {"coordinates":[16.2743206024,48.3091201782],"type":"Point"}
}