{
  "type": "Feature",
  "properties": {
    "addr:full":"Ebentaler Str 249 Klagenfurt K\u00e4rnten 9020",
    "addr:housenumber":"249",
    "addr:postcode":"9020",
    "addr:street":"Kaernten",
    "iso:country":"AT",
    "sg:address":"Ebentaler Str 249",
    "sg:city":"Klagenfurt",
    "sg:orig_category":"Fenster",
    "sg:phone":"+43 463 3203300",
    "sg:postcode":"9020",
    "sg:province":"K\u00e4rnten",
    "wof:name":"Fenster und T\u00fcren Handels- Bau- und Montage GmbH",
    "wof:placetype":"venue"
},
  "geometry": {"coordinates":[14.3510303497,46.609664917],"type":"Point"}
}