{
  "type": "Feature",
  "properties": {
    "iso:country":"AT",
    "sg:address":"Sauldorf 39",
    "sg:city":"Kirchberg",
    "sg:orig_category":"Molkereien U Molkereiprodukte",
    "sg:phone":"+43 4377 475205",
    "sg:postcode":"5232",
    "sg:province":"Ober\u00f6sterreich",
    "wof:name":"Mendler Elfriede",
    "wof:placetype":"venue"
},
  "geometry": {"coordinates":[13.1004400253,48.0395202637],"type":"Point"}
}