{
  "type": "Feature",
  "properties": {
    "iso:country":"AT",
    "sg:address":"Richard Strauss Str. 39 ",
    "sg:city":"Wien",
    "sg:classifiers":[
        {
            "category":"Utilities",
            "subcategory":"Electric",
            "type":"Services"
        }
    ],
    "sg:phone":"+43 4316 10960",
    "sg:postcode":"1230",
    "sg:province":"Wien",
    "sg:tags":[
        "component",
        "electronic"
    ],
    "wof:name":"KSI KONTAKT SYSTEME INTER GESMBH",
    "wof:placetype":"venue"
},
  "geometry": {"coordinates":[16.336681366,48.1393814087],"type":"Point"}
}