{
  "type": "Feature",
  "properties": {
    "addr:full":"Passauer Pl 5/3 Wien Wien 1010",
    "addr:housenumber":"5 / 3",
    "addr:postcode":"1010",
    "addr:street":"Passauer Pl",
    "iso:country":"AT",
    "sg:address":"Passauer Pl 5/3",
    "sg:city":"Wien",
    "sg:orig_category":"Stahl / Gro\u00c3\u0178handel",
    "sg:phone":"+43 1 5332967",
    "sg:postcode":"1010",
    "sg:province":"Wien",
    "wof:name":"GTI Export-Import GmbH",
    "wof:placetype":"venue"
},
  "geometry": {"coordinates":[16.3688049316,48.2025489807],"type":"Point"}
}