{
  "type": "Feature",
  "properties": {
    "addr:full":"Bahnhofstr 10 Zell am See Salzburg 5700",
    "addr:housenumber":"10",
    "addr:postcode":"5700",
    "addr:street":"Bahnhofstr;Salzburg",
    "iso:country":"AT",
    "sg:address":"Bahnhofstr 10",
    "sg:city":"Zell am See",
    "sg:orig_category":"Beratungsstellen",
    "sg:phone":"+43 6542 73242",
    "sg:postcode":"5700",
    "sg:province":"Salzburg",
    "wof:name":"Schulpsychologische Beratungsstelle Zell am See",
    "wof:placetype":"venue"
},
  "geometry": {"coordinates":[12.797290802,47.3218765259],"type":"Point"}
}