{
  "type": "Feature",
  "properties": {
    "addr:full":"Baumg 29-41 Wien Wien 1030",
    "addr:postcode":"29-41;1030",
    "iso:country":"AT",
    "sg:address":"Baumg 29-41",
    "sg:city":"Wien",
    "sg:orig_category":"Politische Parteien",
    "sg:phone":"+43 1 7188494",
    "sg:postcode":"1030",
    "sg:province":"Wien",
    "wof:name":"Sozialdemokratische Partei \u00d6sterreichs Sektion 15",
    "wof:placetype":"venue"
},
  "geometry": {"coordinates":[16.3986206055,48.1958084106],"type":"Point"}
}