{
  "type": "Feature",
  "properties": {
    "addr:full":"Lambacher Str 11a Gunskirchen Ober\u00f6sterreich 4623",
    "addr:postcode":"4623",
    "addr:street":"Str 11A",
    "iso:country":"AT",
    "sg:address":"Lambacher Str 11a",
    "sg:city":"Gunskirchen",
    "sg:classifiers":[
        {
            "category":"Restaurant",
            "type":"Food & Drink"
        }
    ],
    "sg:phone":"+43 7246 20242",
    "sg:postcode":"4623",
    "sg:province":"Ober\u00f6sterreich",
    "sg:tags":[
        "pizzeria"
    ],
    "wof:name":"Pizzeria La Gondola",
    "wof:placetype":"venue"
},
  "geometry": {"coordinates":[13.9425258636,48.1311645508],"type":"Point"}
}