{
  "type": "Feature",
  "properties": {
    "addr:full":"R\u00f6merstr 57 Wels Ober\u00f6sterreich 4600",
    "addr:housenumber":"57",
    "addr:postcode":"4600",
    "addr:street":"Roemerstr;Oberoesterreich",
    "iso:country":"AT",
    "sg:address":"R\u00f6merstr 57",
    "sg:city":"Wels",
    "sg:orig_category":"Elektroinstallationsunternehmen",
    "sg:phone":"+43 7242 72788",
    "sg:postcode":"4600",
    "sg:province":"Ober\u00f6sterreich",
    "wof:name":"Elektrotechnik Plus Inh Christian Panic",
    "wof:placetype":"venue"
},
  "geometry": {"coordinates":[14.0178833008,48.172542572],"type":"Point"}
}