{
  "type": "Feature",
  "properties": {
    "iso:country":"AT",
    "sg:address":"Schulg 1",
    "sg:city":"Volders",
    "sg:orig_category":"Friseure U Frisiersalons",
    "sg:phone":"+43 5224 56256",
    "sg:postcode":"6111",
    "sg:province":"Tirol",
    "wof:name":"Fris\u00f6r Relly",
    "wof:placetype":"venue"
},
  "geometry": {"coordinates":[11.5657997131,47.287109375],"type":"Point"}
}