{
  "type": "Feature",
  "properties": {
    "addr:full":"In der Au 6 Stockerau Nieder\u00f6sterreich 2000",
    "addr:housenumber":"6",
    "addr:postcode":"2000",
    "addr:street":"In Der Au",
    "iso:country":"AT",
    "sg:address":"In der Au 6",
    "sg:city":"Stockerau",
    "sg:orig_category":"Forstverwaltungen",
    "sg:phone":"+43 2266 69562",
    "sg:postcode":"2000",
    "sg:province":"Nieder\u00f6sterreich",
    "wof:name":"Forstverwaltung der Stadt Stockerau",
    "wof:placetype":"venue"
},
  "geometry": {"coordinates":[16.2074947357,48.3848304749],"type":"Point"}
}