{
  "type": "Feature",
  "properties": {
    "iso:country":"AT",
    "sg:address":"Schubertstr 13",
    "sg:city":"Korneuburg",
    "sg:orig_category":"\u00c3\u201erzte / F Allgemeinmedizin",
    "sg:phone":"+43 4367 67892281",
    "sg:postcode":"2100",
    "sg:province":"Nieder\u00f6sterreich",
    "wof:name":"Kurz Karin Dr",
    "wof:placetype":"venue"
},
  "geometry": {"coordinates":[16.3369522095,48.3414916992],"type":"Point"}
}