{
  "type": "Feature",
  "properties": {
    "addr:full":"Seeblickstrasse 157 Drobollach am Faaker See K\u00e4rnten 9580",
    "addr:housenumber":"157",
    "addr:postcode":"9580",
    "addr:street":"Seeblickstrasse",
    "iso:country":"AT",
    "sg:address":"Seeblickstrasse 157",
    "sg:city":"Drobollach am Faaker See",
    "sg:classifiers":[
        {
            "category":"Home & Garden",
            "subcategory":"Building Materials",
            "type":"Retail Goods"
        }
    ],
    "sg:phone":"+43 4254 22190",
    "sg:postcode":"9580",
    "sg:province":"K\u00e4rnten",
    "sg:tags":[
        "installation",
        "electric"
    ],
    "sg:website":"elektro-gailer.or.at",
    "wof:name":"Rudolf Gailer Elektroinstallationstechnik GmbH",
    "wof:placetype":"venue"
},
  "geometry": {"coordinates":[13.927570343,46.5896492004],"type":"Point"}
}