{
  "type": "Feature",
  "properties": {
    "addr:full":"Fischerstr 13 Ried im Innkreis Ober\u00f6sterreich 4910",
    "addr:housenumber":"13",
    "addr:postcode":"4910",
    "addr:street":"Fischerstr",
    "iso:country":"AT",
    "sg:address":"Fischerstr 13",
    "sg:city":"Ried im Innkreis",
    "sg:orig_category":"Lebensmittel / Einzelhandel",
    "sg:phone":"+43 4377 5226575",
    "sg:postcode":"4910",
    "sg:province":"Ober\u00f6sterreich",
    "wof:name":"Penny Markt",
    "wof:placetype":"venue"
},
  "geometry": {"coordinates":[13.4735622406,48.1990776062],"type":"Point"}
}