{
  "type": "Feature",
  "properties": {
    "iso:country":"AT",
    "sg:address":"Bundesstr 6",
    "sg:city":"Koblach",
    "sg:orig_category":"Lebensmittel / Einzelhandel",
    "sg:phone":"+43 4355 2355206",
    "sg:postcode":"6842",
    "sg:province":"Vorarlberg",
    "wof:name":"Hofer KG",
    "wof:placetype":"venue"
},
  "geometry": {"coordinates":[9.6302700043,47.3260688782],"type":"Point"}
}