{
  "type": "Feature",
  "properties": {
    "addr:full":"Edelwei\u00dfstr 14 Asten Ober\u00f6sterreich 4481",
    "addr:housenumber":"14",
    "addr:postcode":"4481",
    "addr:street":"Edelweissstr",
    "iso:country":"AT",
    "sg:address":"Edelwei\u00dfstr 14",
    "sg:city":"Asten",
    "sg:orig_category":"Feuerwehren",
    "sg:phone":"+43 7224 68307",
    "sg:postcode":"4481",
    "sg:province":"Ober\u00f6sterreich",
    "wof:name":"Freiwillige Feuerwehr Asten",
    "wof:placetype":"venue"
},
  "geometry": {"coordinates":[14.4112443924,48.2195396423],"type":"Point"}
}