{
  "type": "Feature",
  "properties": {
    "iso:country":"AT",
    "sg:address":"M\u00fchlg 1",
    "sg:city":"Kollerschlag",
    "sg:orig_category":"Appartements / Ferienwohnungen",
    "sg:phone":"+43 7287 8553",
    "sg:postcode":"4154",
    "sg:province":"Ober\u00f6sterreich",
    "wof:name":"Ferienhof Querschmied Fam Hofmann",
    "wof:placetype":"venue"
},
  "geometry": {"coordinates":[13.8414564133,48.6052284241],"type":"Point"}
}