{
  "type": "Feature",
  "properties": {
    "iso:country":"AT",
    "sg:address":"Tullner Str 2",
    "sg:city":"Asperhofen",
    "sg:orig_category":"Autohandel",
    "sg:phone":"+43 2772 582660",
    "sg:postcode":"3041",
    "sg:province":"Nieder\u00f6sterreich",
    "wof:name":"Steinhauser Michael",
    "wof:placetype":"venue"
},
  "geometry": {"coordinates":[15.9261484146,48.2423858643],"type":"Point"}
}