{
  "type": "Feature",
  "properties": {
    "addr:full":"Ottakringer Str 147 Wien Wien 1160",
    "addr:housenumber":"147",
    "addr:postcode":"1160",
    "iso:country":"AT",
    "sg:address":"Ottakringer Str 147",
    "sg:city":"Wien",
    "sg:orig_category":"Fitnesscenter",
    "sg:phone":"+43 1 4817571",
    "sg:postcode":"1160",
    "sg:province":"Wien",
    "wof:name":"Shape Line",
    "wof:placetype":"venue"
},
  "geometry": {"coordinates":[16.3156070709,48.2131385803],"type":"Point"}
}