{
  "type": "Feature",
  "properties": {
    "addr:full":"Nr 253 Strallegg Steiermark 8192",
    "addr:postcode":"8192",
    "addr:street":"Nr 253",
    "iso:country":"AT",
    "sg:address":"Nr 253",
    "sg:city":"Strallegg",
    "sg:orig_category":"Feuerwehren",
    "sg:phone":"+43 3174 22300",
    "sg:postcode":"8192",
    "sg:province":"Steiermark",
    "wof:name":"Freiwillige Feuerwehr Strallegg",
    "wof:placetype":"venue"
},
  "geometry": {"coordinates":[15.7248001099,47.4109153748],"type":"Point"}
}