{
  "type": "Feature",
  "properties": {
    "addr:full":"Wickenburgg 12 Graz Steiermark 8010",
    "addr:housenumber":"12",
    "addr:postcode":"8010",
    "addr:street":"Wickenburgg",
    "iso:country":"AT",
    "sg:address":"Wickenburgg 12",
    "sg:city":"Graz",
    "sg:orig_category":"Architekten",
    "sg:phone":"+43 316 682690",
    "sg:postcode":"8010",
    "sg:province":"Steiermark",
    "wof:name":"arcitectural operation system",
    "wof:placetype":"venue"
},
  "geometry": {"coordinates":[15.4371938705,47.0790138245],"type":"Point"}
}