{
  "type": "Feature",
  "properties": {
    "addr:full":"Prinz-Eugen-Str 32 Wien Wien 1040",
    "addr:housenumber":"32",
    "addr:postcode":"1040",
    "addr:street":"Prinz-Eugen-Str",
    "iso:country":"AT",
    "sg:address":"Prinz-Eugen-Str 32",
    "sg:city":"Wien",
    "sg:orig_category":"Banken U Sparkassen",
    "sg:phone":"+43 4315 06950",
    "sg:postcode":"1040",
    "sg:province":"Wien",
    "wof:name":"SOCIETE GENERALE",
    "wof:placetype":"venue"
},
  "geometry": {"coordinates":[16.3776283264,48.1936607361],"type":"Point"}
}