{
  "type": "Feature",
  "properties": {
    "addr:full":"Breitenseer Str 20-22 Wien Wien 1140",
    "addr:postcode":"20-22;1140",
    "addr:street":"Str",
    "iso:country":"AT",
    "sg:address":"Breitenseer Str 20-22",
    "sg:city":"Wien",
    "sg:orig_category":"Elektronik",
    "sg:phone":"+43 1 52219740",
    "sg:postcode":"1140",
    "sg:province":"Wien",
    "wof:name":"Saia-Burgess \u00f6sterreich GmbH",
    "wof:placetype":"venue"
},
  "geometry": {"coordinates":[16.3110656738,48.2003517151],"type":"Point"}
}