{
  "type": "Feature",
  "properties": {
    "addr:full":"Hauptstrasse 11-13 Schleinbach Nieder\u00f6sterreich 2123",
    "addr:postcode":"11-13;2123",
    "addr:street":"Hauptstrasse",
    "iso:country":"AT",
    "sg:address":"Hauptstrasse 11-13",
    "sg:city":"Schleinbach",
    "sg:classifiers":[
        {
            "category":"Manufacturing",
            "subcategory":"Wood Products",
            "type":"Manufacturing & Wholesale Goods"
        }
    ],
    "sg:phone":"+43 2245 89169",
    "sg:postcode":"2123",
    "sg:province":"Nieder\u00f6sterreich",
    "sg:tags":[
        "gate",
        "made",
        "door"
    ],
    "sg:website":"senger-tischlerei.at",
    "wof:name":"Senger Tischlerwerkst\u00e4tte",
    "wof:placetype":"venue"
},
  "geometry": {"coordinates":[16.4764461517,48.4196128845],"type":"Point"}
}