{
  "type": "Feature",
  "properties": {
    "addr:full":"Ziegeleistr 1 Salzburg Salzburg 5020",
    "addr:housenumber":"1",
    "addr:postcode":"5020",
    "addr:street":"Ziegeleistr;Salzburg",
    "iso:country":"AT",
    "sg:address":"Ziegeleistr 1",
    "sg:city":"Salzburg",
    "sg:orig_category":"Pumpen",
    "sg:phone":"+43 662 875289",
    "sg:postcode":"5020",
    "sg:province":"Salzburg",
    "wof:name":"NOVOTERM Handels GmbH",
    "wof:placetype":"venue"
},
  "geometry": {"coordinates":[13.0598201752,47.8231544495],"type":"Point"}
}