{
  "type": "Feature",
  "properties": {
    "addr:full":"Franziskanerpl 1 G\u00fcssing Burgenland 7540",
    "addr:housenumber":"1",
    "addr:postcode":"7540",
    "addr:street":"Franziskanerpl",
    "iso:country":"AT",
    "sg:address":"Franziskanerpl 1",
    "sg:city":"G\u00fcssing",
    "sg:orig_category":"Non-Classified Establishments",
    "sg:phone":"+43 3322 43067",
    "sg:postcode":"7540",
    "sg:province":"Burgenland",
    "wof:name":"Franziskanerkloster",
    "wof:placetype":"venue"
},
  "geometry": {"coordinates":[16.3234901428,47.0595207214],"type":"Point"}
}