{
  "type": "Feature",
  "properties": {
    "addr:full":"J\u00e4gerstr 43 Wien Wien 1200",
    "addr:housenumber":"43",
    "addr:postcode":"1200",
    "addr:street":"Jaegerstr",
    "iso:country":"AT",
    "sg:address":"J\u00e4gerstr 43",
    "sg:city":"Wien",
    "sg:orig_category":"Sonnenstudios",
    "sg:phone":"+43 1 3324088",
    "sg:postcode":"1200",
    "sg:province":"Wien",
    "wof:name":"Quick Sun Sonnenstudio",
    "wof:placetype":"venue"
},
  "geometry": {"coordinates":[16.370470047,48.2311706543],"type":"Point"}
}