{
  "type": "Feature",
  "properties": {
    "addr:full":"Au 59 Gro\u00dfarl Salzburg 5611",
    "addr:housenumber":"59",
    "addr:postcode":"5611",
    "addr:street":"Au;Salzburg",
    "iso:country":"AT",
    "sg:address":"Au 59",
    "sg:city":"Gro\u00dfarl",
    "sg:orig_category":"Pensionen / Privatzimmer",
    "sg:phone":"+43 6414 3340",
    "sg:postcode":"5611",
    "sg:province":"Salzburg",
    "wof:name":"Pension Dorfer-Aichhorn",
    "wof:placetype":"venue"
},
  "geometry": {"coordinates":[-114.0853424072,47.1626281738],"type":"Point"}
}