{
  "type": "Feature",
  "properties": {
    "addr:full":"Sackstr 40 Graz Steiermark 8010",
    "addr:housenumber":"40",
    "addr:postcode":"8010",
    "addr:street":"Sackstr",
    "iso:country":"AT",
    "sg:address":"Sackstr 40",
    "sg:city":"Graz",
    "sg:orig_category":"Bars-Cafes",
    "sg:phone":"+43 316 829756",
    "sg:postcode":"8010",
    "sg:province":"Steiermark",
    "wof:name":"Blue Moon",
    "wof:placetype":"venue"
},
  "geometry": {"coordinates":[15.4348449707,47.0753707886],"type":"Point"}
}