{
  "type": "Feature",
  "properties": {
    "addr:full":"Otto Wagner-Pl Wien Wien 1090",
    "addr:postcode":"1090",
    "iso:country":"AT",
    "sg:address":"Otto Wagner-Pl",
    "sg:city":"Wien",
    "sg:orig_category":"Garagen Parkgaragen",
    "sg:phone":"+43 1 4052241",
    "sg:postcode":"1090",
    "sg:province":"Wien",
    "wof:name":"Otto Wagner Platz Tiefgarage Bau- und BetriebsgesmbH und Co KG",
    "wof:placetype":"venue"
},
  "geometry": {"coordinates":[16.3545455933,48.2160644531],"type":"Point"}
}