{
  "type": "Feature",
  "properties": {
    "addr:full":"Stadthallestr 4 Amstetten Nieder\u00f6sterreich 3300",
    "addr:housenumber":"4",
    "addr:postcode":"3300",
    "addr:street":"Stadthallestr;Niederoesterreich",
    "iso:country":"AT",
    "sg:address":"Stadthallestr 4",
    "sg:city":"Amstetten",
    "sg:orig_category":"Rohrleitungen U Rohrleitungsbau",
    "sg:phone":"+43 4374 7228225",
    "sg:postcode":"3300",
    "sg:province":"Nieder\u00f6sterreich",
    "wof:name":"Unistahl Bau- u Rohrleitungsbau GesmbH",
    "wof:placetype":"venue"
},
  "geometry": {"coordinates":[14.876540184,48.1154403687],"type":"Point"}
}