{
  "type": "Feature",
  "properties": {
    "iso:country":"AT",
    "sg:address":"Gutauer Str 49",
    "sg:city":"Bad Zell",
    "sg:orig_category":"Sportanlagen",
    "sg:phone":"+43 4372 6320097",
    "sg:postcode":"4283",
    "sg:province":"Ober\u00f6sterreich",
    "wof:name":"ARENA Wirt",
    "wof:placetype":"venue"
},
  "geometry": {"coordinates":[14.6650753021,48.3535041809],"type":"Point"}
}