{
  "type": "Feature",
  "properties": {
    "addr:full":"Bahnhofstr 63 Ried im Innkreis Ober\u00f6sterreich 4910",
    "addr:housenumber":"63",
    "addr:postcode":"4910",
    "addr:street":"Bahnhofstr",
    "iso:country":"AT",
    "sg:address":"Bahnhofstr 63",
    "sg:city":"Ried im Innkreis",
    "sg:orig_category":"Steuerberatung",
    "sg:phone":"+43 4377 526150",
    "sg:postcode":"4910",
    "sg:province":"Ober\u00f6sterreich",
    "wof:name":"Fusseis Karl",
    "wof:placetype":"venue"
},
  "geometry": {"coordinates":[13.489364624,48.2018432617],"type":"Point"}
}