{
  "type": "Feature",
  "properties": {
    "addr:full":"Unterkreuschlach 1 Gm\u00fcnd K\u00e4rnten 9853",
    "addr:housenumber":"1",
    "addr:postcode":"9853",
    "addr:street":"Unterkreuschlach;Kaernten",
    "iso:country":"AT",
    "sg:address":"Unterkreuschlach 1",
    "sg:city":"Gm\u00fcnd",
    "sg:classifiers":[
        {
            "category":"Home & Garden",
            "subcategory":"Garden Supply",
            "type":"Retail Goods"
        }
    ],
    "sg:phone":"+43 4347 322453",
    "sg:postcode":"9853",
    "sg:province":"K\u00e4rnten",
    "sg:tags":[
        "schotter",
        "sand",
        "u"
    ],
    "wof:name":"M\u00f6ssler Franz",
    "wof:placetype":"venue"
},
  "geometry": {"coordinates":[13.5422592163,46.9127044678],"type":"Point"}
}