{
  "type": "Feature",
  "properties": {
    "iso:country":"AT",
    "sg:address":"Nr 71",
    "sg:city":"Admont",
    "sg:orig_category":"Autohandel",
    "sg:phone":"+43 3612 7573",
    "sg:postcode":"8911",
    "sg:province":"Steiermark",
    "wof:name":"Lemmerer jun Hubert",
    "wof:placetype":"venue"
},
  "geometry": {"coordinates":[14.4609088898,47.5760040283],"type":"Point"}
}