{
  "type": "Feature",
  "properties": {
    "addr:full":"Siedlungsstr NB Haiming Tirol 6425",
    "addr:postcode":"6425",
    "addr:street":"Tirol",
    "iso:country":"AT",
    "sg:address":"Siedlungsstr NB",
    "sg:city":"Haiming",
    "sg:orig_category":"Lebensmittel / Einzelhandel",
    "sg:phone":"+43 5266 87235",
    "sg:postcode":"6425",
    "sg:province":"Tirol",
    "wof:name":"Billa AG",
    "wof:placetype":"venue"
},
  "geometry": {"coordinates":[10.8829202652,47.2561302185],"type":"Point"}
}