{
  "type": "Feature",
  "properties": {
    "addr:full":"Pappelstr 2 Langenzersdorf Nieder\u00f6sterreich 2103",
    "addr:housenumber":"2",
    "addr:postcode":"2103",
    "addr:street":"Pappelstr",
    "iso:country":"AT",
    "sg:address":"Pappelstr 2",
    "sg:city":"Langenzersdorf",
    "sg:orig_category":"Transportunternehmen",
    "sg:phone":"+43 2244 22920",
    "sg:postcode":"2103",
    "sg:province":"Nieder\u00f6sterreich",
    "wof:name":"B\u00f6hm Leonhard TransportgesmbH & Co KG",
    "wof:placetype":"venue"
},
  "geometry": {"coordinates":[16.363073349,48.2865447998],"type":"Point"}
}