{
  "type": "Feature",
  "properties": {
    "addr:full":"Gnies 85 Sinabelkirchen Steiermark 8261",
    "addr:housenumber":"85",
    "addr:postcode":"8261",
    "addr:street":"Gnies",
    "iso:country":"AT",
    "sg:address":"Gnies 85",
    "sg:city":"Sinabelkirchen",
    "sg:orig_category":"Pumpen / Reparatur",
    "sg:phone":"+43 3118 2253",
    "sg:postcode":"8261",
    "sg:province":"Steiermark",
    "wof:name":"Garvens Service GesmbH",
    "wof:placetype":"venue"
},
  "geometry": {"coordinates":[15.8534994125,47.099193573],"type":"Point"}
}