{
  "type": "Feature",
  "properties": {
    "iso:country":"AT",
    "sg:address":"Hof 37/38",
    "sg:city":"Kl\u00f6sterle",
    "sg:orig_category":"Tischlereien",
    "sg:phone":"+43 4355 825880",
    "sg:postcode":"6754",
    "sg:province":"Vorarlberg",
    "wof:name":"Walch Arthur",
    "wof:placetype":"venue"
},
  "geometry": {"coordinates":[-101.40701293950001,34.2146606445],"type":"Point"}
}