{
  "type": "Feature",
  "properties": {
    "iso:country":"AT",
    "sg:address":"Bahnhofstr 2",
    "sg:city":"Rosental an der Kainach",
    "sg:orig_category":"Tankstellen",
    "sg:phone":"+43 4331 4228279",
    "sg:postcode":"8582",
    "sg:province":"Steiermark",
    "wof:name":"JET Tankstelle",
    "wof:placetype":"venue"
},
  "geometry": {"coordinates":[15.125544548,47.0531272888],"type":"Point"}
}