{
  "type": "Feature",
  "properties": {
    "addr:full":"Nr 17b Pertisau Tirol 6213",
    "addr:postcode":"6213",
    "addr:street":"Nr;Pertisau",
    "iso:country":"AT",
    "sg:address":"Nr 17b",
    "sg:city":"Pertisau",
    "sg:orig_category":"Pensionen / Privatzimmer",
    "sg:phone":"+43 5243 5376",
    "sg:postcode":"6213",
    "sg:province":"Tirol",
    "wof:name":"W\u00f6ll Josef",
    "wof:placetype":"venue"
},
  "geometry": {"coordinates":[11.6961479187,47.4396896362],"type":"Point"}
}