{
  "type": "Feature",
  "properties": {
    "addr:full":"Steigenteschg 73 Wien Wien 1220",
    "addr:housenumber":"73",
    "addr:postcode":"1220",
    "addr:street":"Steigenteschg",
    "iso:country":"AT",
    "sg:address":"Steigenteschg 73",
    "sg:city":"Wien",
    "sg:classifiers":[
        {
            "category":"Internet Cafe",
            "subcategory":"None",
            "type":"Food & Drink"
        }
    ],
    "sg:phone":"+43 664 3556644",
    "sg:postcode":"1220",
    "sg:province":"Wien",
    "wof:name":"Pixmess Multimedia und Corporate Webbing",
    "wof:placetype":"venue"
},
  "geometry": {"coordinates":[16.445432663,48.2439880371],"type":"Point"}
}