{
  "type": "Feature",
  "properties": {
    "iso:country":"AT",
    "sg:address":"Mo\u00dfbacherg 18",
    "sg:city":"Wien",
    "sg:orig_category":"Elektronische Bauelemente U Bauteile",
    "sg:phone":"+43 1 91428300",
    "sg:postcode":"1140",
    "sg:province":"Wien",
    "wof:name":"Eltrona-RKT Rottenmanner Kabeltechnik GmbH",
    "wof:placetype":"venue"
},
  "geometry": {"coordinates":[16.2696990967,48.1994247437],"type":"Point"}
}