{
  "type": "Feature",
  "properties": {
    "addr:full":"Erentrudisstr 28 Salzburg Salzburg 5020",
    "addr:housenumber":"28",
    "addr:postcode":"5020",
    "addr:street":"Erentrudisstr;Salzburg",
    "iso:country":"AT",
    "sg:address":"Erentrudisstr 28",
    "sg:city":"Salzburg",
    "sg:orig_category":"Transportunternehmen",
    "sg:phone":"+43 4366 2620523",
    "sg:postcode":"5020",
    "sg:province":"Salzburg",
    "wof:name":"Ratzinger Wolfgang",
    "wof:placetype":"venue"
},
  "geometry": {"coordinates":[13.064499855,47.7823181152],"type":"Point"}
}