{
  "type": "Feature",
  "properties": {
    "addr:full":"Magazing 5 Linz Ober\u00f6sterreich 4020",
    "addr:housenumber":"5",
    "addr:postcode":"4020",
    "addr:street":"Magazing",
    "iso:country":"AT",
    "sg:address":"Magazing 5",
    "sg:city":"Linz",
    "sg:orig_category":"Bandagen U Bandagisten",
    "sg:phone":"+43 732 770340",
    "sg:postcode":"4020",
    "sg:province":"Ober\u00f6sterreich",
    "wof:name":"Bandagist Heindl GesmbH",
    "wof:placetype":"venue"
},
  "geometry": {"coordinates":[14.2904663086,48.2997436523],"type":"Point"}
}