{
  "type": "Feature",
  "properties": {
    "iso:country":"AT",
    "sg:address":"Pacassistrasse 26",
    "sg:city":"Wien",
    "sg:classifiers":[
        {
            "category":"Home & Garden",
            "subcategory":"Carpets & Floor Coverings",
            "type":"Retail Goods"
        }
    ],
    "sg:phone":"+43 1 80481510",
    "sg:postcode":"1130",
    "sg:province":"Wien",
    "sg:tags":[
        "screed",
        "floating"
    ],
    "wof:name":"Ing. Paul Bosak Ges.m.b.H.",
    "wof:placetype":"venue"
},
  "geometry": {"coordinates":[16.2887496948,48.1752815247],"type":"Point"}
}