{
  "type": "Feature",
  "properties": {
    "addr:full":"M\u00fchlbachstr 14 Wilhering Ober\u00f6sterreich 4073",
    "addr:housenumber":"14",
    "addr:postcode":"4073",
    "addr:street":"Muehlbachstr",
    "iso:country":"AT",
    "sg:address":"M\u00fchlbachstr 14",
    "sg:city":"Wilhering",
    "sg:orig_category":"Steuerungstechnik",
    "sg:phone":"+43 4372 2623580",
    "sg:postcode":"4073",
    "sg:province":"Ober\u00f6sterreich",
    "wof:name":"SST Stadler Steuerungstechnik GesmbH",
    "wof:placetype":"venue"
},
  "geometry": {"coordinates":[14.1893806458,48.3233795166],"type":"Point"}
}