{
  "type": "Feature",
  "properties": {
    "iso:country":"AT",
    "sg:address":"Nr 88",
    "sg:city":"Griffen",
    "sg:orig_category":"Tabaktrafiken",
    "sg:phone":"+43 4233 25036",
    "sg:postcode":"9112",
    "sg:province":"K\u00e4rnten",
    "wof:name":"Kupferschmied Andrea",
    "wof:placetype":"venue"
},
  "geometry": {"coordinates":[14.7313051224,46.7036705017],"type":"Point"}
}