{
  "type": "Feature",
  "properties": {
    "addr:full":"Margaretenstr 21 Wien Wien 1040",
    "addr:housenumber":"21",
    "addr:postcode":"1040",
    "addr:street":"Margaretenstr",
    "iso:country":"AT",
    "sg:address":"Margaretenstr 21",
    "sg:city":"Wien",
    "sg:orig_category":"Fleischhauereien",
    "sg:phone":"+43 1 5853790",
    "sg:postcode":"1040",
    "sg:province":"Wien",
    "wof:name":"Schirnhofer-Breisler GesmbH - Shop in Shop",
    "wof:placetype":"venue"
},
  "geometry": {"coordinates":[16.3649406433,48.1959686279],"type":"Point"}
}