{
  "type": "Feature",
  "properties": {
    "iso:country":"AT",
    "sg:address":"Unterg 5",
    "sg:city":"Fiss",
    "sg:orig_category":"Banken U Sparkassen",
    "sg:phone":"+43 4354 7665750",
    "sg:postcode":"6533",
    "sg:province":"Tirol",
    "wof:name":"Volksbank Landeck regGenmbH",
    "wof:placetype":"venue"
},
  "geometry": {"coordinates":[10.6193056107,47.0555839539],"type":"Point"}
}