{
  "type": "Feature",
  "properties": {
    "iso:country":"AT",
    "sg:address":"Welser Str 17-19",
    "sg:city":"Leonding",
    "sg:orig_category":"Lebensmittel / Einzelhandel",
    "sg:phone":"+43 732 671974",
    "sg:postcode":"4060",
    "sg:province":"Ober\u00f6sterreich",
    "wof:name":"MONDO Lebensmitteldiskonter",
    "wof:placetype":"venue"
},
  "geometry": {"coordinates":[14.269949913,48.2715606689],"type":"Point"}
}