{
  "type": "Feature",
  "properties": {
    "addr:full":"Dammstr 13 Wien Wien 1200",
    "addr:housenumber":"13",
    "addr:postcode":"1200",
    "addr:street":"Dammstr",
    "iso:country":"AT",
    "sg:address":"Dammstr 13",
    "sg:city":"Wien",
    "sg:orig_category":"Friseure U Frisiersalons",
    "sg:phone":"+43 4313 300197",
    "sg:postcode":"1200",
    "sg:province":"Wien",
    "wof:name":"Herdegen-Sziber Veronika",
    "wof:placetype":"venue"
},
  "geometry": {"coordinates":[16.3746070862,48.2322349548],"type":"Point"}
}