{
  "type": "Feature",
  "properties": {
    "addr:full":"S\u00e4uleng 17 Wien Wien 1090",
    "addr:housenumber":"17",
    "addr:postcode":"1090",
    "addr:street":"Saeuleng",
    "iso:country":"AT",
    "sg:address":"S\u00e4uleng 17",
    "sg:city":"Wien",
    "sg:classifiers":[
        {
            "category":"Professional",
            "subcategory":"Computer Services",
            "type":"Services"
        }
    ],
    "sg:phone":"+43 1 3102439",
    "sg:postcode":"1090",
    "sg:province":"Wien",
    "sg:tags":[
        "software"
    ],
    "wof:name":"Graf Peter Mag KEG",
    "wof:placetype":"venue"
},
  "geometry": {"coordinates":[16.351474762,48.2234115601],"type":"Point"}
}