{
  "type": "Feature",
  "properties": {
    "addr:full":"Linzer Str 13 Bad Zell Ober\u00f6sterreich 4283",
    "addr:housenumber":"13",
    "addr:postcode":"4283",
    "addr:street":"Linzer Str",
    "iso:country":"AT",
    "sg:address":"Linzer Str 13",
    "sg:city":"Bad Zell",
    "sg:orig_category":"Autohandel",
    "sg:phone":"+43 7263 72290",
    "sg:postcode":"4283",
    "sg:province":"Ober\u00f6sterreich",
    "wof:name":"Pilz GesmbH",
    "wof:placetype":"venue"
},
  "geometry": {"coordinates":[14.6652641296,48.3468093872],"type":"Point"}
}