{
  "type": "Feature",
  "properties": {
    "addr:full":"Nr 138 Flachau Salzburg 5542",
    "addr:postcode":"5542",
    "addr:street":"Nr 138;Salzburg",
    "iso:country":"AT",
    "sg:address":"Nr 138",
    "sg:city":"Flachau",
    "sg:classifiers":[
        {
            "category":"Travel",
            "subcategory":"Hotels & Motels",
            "type":"Entertainment"
        }
    ],
    "sg:phone":"+43 6457 22420",
    "sg:postcode":"5542",
    "sg:province":"Salzburg",
    "wof:name":"Hotel Pongauerhof",
    "wof:placetype":"venue"
},
  "geometry": {"coordinates":[13.3921222687,47.3435821533],"type":"Point"}
}