{
  "type": "Feature",
  "properties": {
    "iso:country":"AT",
    "sg:address":"Alte Poststr 46",
    "sg:city":"Hainburg an der Donau",
    "sg:classifiers":[
        {
            "category":"Shopping",
            "subcategory":"Bicycles & Sporting Goods",
            "type":"Retail Goods"
        }
    ],
    "sg:phone":"+43 4321 65628480",
    "sg:postcode":"2410",
    "sg:province":"Nieder\u00f6sterreich",
    "sg:tags":[
        "munition",
        "u",
        "waffen"
    ],
    "wof:name":"Petronics G\u00fcnter",
    "wof:placetype":"venue"
},
  "geometry": {"coordinates":[16.9454479218,48.1470413208],"type":"Point"}
}