{
  "type": "Feature",
  "properties": {
    "addr:full":"Waldbrunnerstr 13 Ansfelden Ober\u00f6sterreich 4052",
    "addr:housenumber":"13",
    "addr:postcode":"4052",
    "addr:street":"Waldbrunnerstr",
    "iso:country":"AT",
    "sg:address":"Waldbrunnerstr 13",
    "sg:city":"Ansfelden",
    "sg:orig_category":"Autoersatzteile",
    "sg:phone":"+43 7229 82332",
    "sg:postcode":"4052",
    "sg:province":"Ober\u00f6sterreich",
    "wof:name":"IHF Lehofer",
    "wof:placetype":"venue"
},
  "geometry": {"coordinates":[14.2757234573,48.2092895508],"type":"Point"}
}