{
  "type": "Feature",
  "properties": {
    "addr:full":"Pochendorf 64 Kremsm\u00fcnster Ober\u00f6sterreich 4550",
    "addr:housenumber":"64",
    "addr:postcode":"4550",
    "addr:street":"Pochendorf;Oberoesterreich",
    "iso:country":"AT",
    "sg:address":"Pochendorf 64",
    "sg:city":"Kremsm\u00fcnster",
    "sg:orig_category":"Autospenglereien",
    "sg:phone":"+43 4375 8350550",
    "sg:postcode":"4550",
    "sg:province":"Ober\u00f6sterreich",
    "wof:name":"K\u00f6nigseder Karosseriefachwerkst\u00e4tte u Tuning",
    "wof:placetype":"venue"
},
  "geometry": {"coordinates":[14.0918645859,48.066444397],"type":"Point"}
}