{
  "type": "Feature",
  "properties": {
    "addr:full":"Perfektastrasse 11 Wien Wien 1230",
    "addr:housenumber":"11",
    "addr:postcode":"1230",
    "addr:street":"Perfektastrasse",
    "iso:country":"AT",
    "sg:address":"Perfektastrasse 11",
    "sg:city":"Wien",
    "sg:classifiers":[
        {
            "category":"Shopping",
            "subcategory":"Crafts & Fabrics",
            "type":"Retail Goods"
        }
    ],
    "sg:phone":"+43 1 60945360",
    "sg:postcode":"1230",
    "sg:province":"Wien",
    "sg:tags":[
        "polishing",
        "cloth",
        "cleaning"
    ],
    "sg:website":"enjo.at",
    "wof:name":"Enjo Vertriebs GmbH",
    "wof:placetype":"venue"
},
  "geometry": {"coordinates":[16.3229827881,48.1377182007],"type":"Point"}
}