{
  "type": "Feature",
  "properties": {
    "iso:country":"AT",
    "sg:address":"Zieglerg 31",
    "sg:city":"Wien",
    "sg:classifiers":[
        {
            "category":"Arts & Performance",
            "subcategory":"Theater",
            "type":"Entertainment"
        }
    ],
    "sg:phone":"+43 1 5231833",
    "sg:postcode":"1070",
    "sg:province":"Wien",
    "wof:name":"Theater mbH",
    "wof:placetype":"venue"
},
  "geometry": {"coordinates":[16.344865799,48.2012367249],"type":"Point"}
}