{
  "type": "Feature",
  "properties": {
    "iso:country":"AT",
    "sg:address":"Kirchstetterng 25",
    "sg:city":"Wien",
    "sg:orig_category":"Tabaktrafiken",
    "sg:phone":"+43 1 4925587",
    "sg:postcode":"1160",
    "sg:province":"Wien",
    "wof:name":"Kammerer Manfred",
    "wof:placetype":"venue"
},
  "geometry": {"coordinates":[16.3320064545,48.2071113586],"type":"Point"}
}