{
  "type": "Feature",
  "properties": {
    "addr:full":"Karl Gattermayer-Weg 1 Sierning Ober\u00f6sterreich 4522",
    "addr:housenumber":"1",
    "addr:postcode":"4522",
    "addr:street":"Gattermayer-Weg",
    "iso:country":"AT",
    "sg:address":"Karl Gattermayer-Weg 1",
    "sg:city":"Sierning",
    "sg:orig_category":"Bekleidung / Einzelhandel",
    "sg:phone":"+43 7259 3130",
    "sg:postcode":"4522",
    "sg:province":"Ober\u00f6sterreich",
    "wof:name":"H\u00dcLLE-FARBE-LINIE Bekleidungs und Farbatelier",
    "wof:placetype":"venue"
},
  "geometry": {"coordinates":[14.313290596,48.0542907715],"type":"Point"}
}