{
  "type": "Feature",
  "properties": {
    "addr:full":"Eichberger Str 2 Gm\u00fcnd Nieder\u00f6sterreich 3950",
    "addr:housenumber":"2",
    "addr:postcode":"3950",
    "addr:street":"Str;Niederoesterreich",
    "iso:country":"AT",
    "sg:address":"Eichberger Str 2",
    "sg:city":"Gm\u00fcnd",
    "sg:orig_category":"Autohandel",
    "sg:phone":"+43 4328 5283106",
    "sg:postcode":"3950",
    "sg:province":"Nieder\u00f6sterreich",
    "wof:name":"Sch\u00f6nsgibl Erwin",
    "wof:placetype":"venue"
},
  "geometry": {"coordinates":[14.9417819977,48.7470626831],"type":"Point"}
}