{
  "type": "Feature",
  "properties": {
    "addr:full":"F\u00fcrbergstr 18-20 Salzburg Salzburg 5020",
    "addr:postcode":"18-20;5020",
    "addr:street":"Salzburg",
    "iso:country":"AT",
    "sg:address":"F\u00fcrbergstr 18-20",
    "sg:city":"Salzburg",
    "sg:orig_category":"Restaurants: Griechisch",
    "sg:phone":"+43 662 645943",
    "sg:postcode":"5020",
    "sg:province":"Salzburg",
    "wof:name":"Akropolis",
    "wof:placetype":"venue"
},
  "geometry": {"coordinates":[13.0433769226,47.8006744385],"type":"Point"}
}