{
  "type": "Feature",
  "properties": {
    "addr:full":"Treustrasse 68 Wien Wien 1200",
    "addr:housenumber":"68",
    "addr:postcode":"1200",
    "addr:street":"Treustrasse",
    "iso:country":"AT",
    "sg:address":"Treustrasse 68",
    "sg:city":"Wien",
    "sg:classifiers":[
        {
            "category":"Manufacturing",
            "subcategory":"Signs",
            "type":"Manufacturing & Wholesale Goods"
        }
    ],
    "sg:phone":"+43 1 3328210",
    "sg:postcode":"1200",
    "sg:province":"Wien",
    "sg:tags":[
        "car",
        "lettering"
    ],
    "sg:website":"impresa.at",
    "wof:name":"Impresa Druckerei GmbH",
    "wof:placetype":"venue"
},
  "geometry": {"coordinates":[16.3640556335,48.2324447632],"type":"Point"}
}