{
  "type": "Feature",
  "properties": {
    "addr:full":"Schumanng 21 Klagenfurt K\u00e4rnten 9020",
    "addr:housenumber":"21",
    "addr:postcode":"9020",
    "addr:street":"Schumanng;Kaernten",
    "iso:country":"AT",
    "sg:address":"Schumanng 21",
    "sg:city":"Klagenfurt",
    "sg:orig_category":"Betriebseinrichtungen",
    "sg:phone":"+43 463 230730",
    "sg:postcode":"9020",
    "sg:province":"K\u00e4rnten",
    "wof:name":"Werdinig Heinrich Lagertechnik",
    "wof:placetype":"venue"
},
  "geometry": {"coordinates":[14.2761745453,46.6166000366],"type":"Point"}
}