{
  "type": "Feature",
  "properties": {
    "addr:full":"Nr 40 Thiersee Tirol 6335",
    "addr:postcode":"6335",
    "addr:street":"Nr 40;Tirol",
    "iso:country":"AT",
    "sg:address":"Nr 40",
    "sg:city":"Thiersee",
    "sg:orig_category":"Banken U Sparkassen",
    "sg:phone":"+43 5376 5209",
    "sg:postcode":"6335",
    "sg:province":"Tirol",
    "wof:name":"Raiffeisenbank Thiersee regGenmbH",
    "wof:placetype":"venue"
},
  "geometry": {"coordinates":[12.1183481216,47.5942153931],"type":"Point"}
}