{
  "type": "Feature",
  "properties": {
    "iso:country":"AT",
    "sg:address":"Marktpl 7",
    "sg:city":"Leobersdorf",
    "sg:orig_category":"Bibliotheken",
    "sg:phone":"+43 2256 62323",
    "sg:postcode":"2544",
    "sg:province":"Nieder\u00f6sterreich",
    "wof:name":"B\u00fccherei der Marktgemeinde",
    "wof:placetype":"venue"
},
  "geometry": {"coordinates":[16.2159976959,47.9254493713],"type":"Point"}
}