{
  "type": "Feature",
  "properties": {
    "iso:country":"AT",
    "sg:address":"Heiligenst\u00e4dter Str 143/6",
    "sg:city":"Wien",
    "sg:orig_category":"\u00c3\u201erzte / F Allgemeinmedizin",
    "sg:phone":"+43 1 3186643",
    "sg:postcode":"1190",
    "sg:province":"Wien",
    "wof:name":"Khely Manfred Dr",
    "wof:placetype":"venue"
},
  "geometry": {"coordinates":[16.364112854,48.2530708313],"type":"Point"}
}