{
  "type": "Feature",
  "properties": {
    "addr:full":"Markt 144 Kaumberg Nieder\u00f6sterreich 2572",
    "addr:housenumber":"144",
    "addr:postcode":"2572",
    "addr:street":"Markt",
    "iso:country":"AT",
    "sg:address":"Markt 144",
    "sg:city":"Kaumberg",
    "sg:orig_category":"Filmproduktionen",
    "sg:phone":"+43 2765 8003",
    "sg:postcode":"2572",
    "sg:province":"Nieder\u00f6sterreich",
    "wof:name":"MITTERM\u00dcLLER KEG",
    "wof:placetype":"venue"
},
  "geometry": {"coordinates":[15.8847465515,48.0337104797],"type":"Point"}
}