{
  "type": "Feature",
  "properties": {
    "iso:country":"AT",
    "sg:address":"Afritschweg 18",
    "sg:city":"Linz",
    "sg:orig_category":"Biologische Produkte",
    "sg:phone":"+43 732 916755",
    "sg:postcode":"4030",
    "sg:province":"Ober\u00f6sterreich",
    "wof:name":"Breitenfellner Peter",
    "wof:placetype":"venue"
},
  "geometry": {"coordinates":[14.333521843,48.2388038635],"type":"Point"}
}