{
  "type": "Feature",
  "properties": {
    "addr:full":"Afritschweg 18 Linz Ober\u00f6sterreich 4030",
    "addr:housenumber":"18",
    "addr:postcode":"4030",
    "addr:street":"Afritschweg",
    "iso:country":"AT",
    "sg:address":"Afritschweg 18",
    "sg:city":"Linz",
    "sg:orig_category":"Biologische Produkte",
    "sg:phone":"+43 732 916755",
    "sg:postcode":"4030",
    "sg:province":"Ober\u00f6sterreich",
    "wof:name":"Breitenfellner Peter",
    "wof:placetype":"venue"
},
  "geometry": {"coordinates":[14.333521843,48.2388038635],"type":"Point"}
}