{
  "type": "Feature",
  "properties": {
    "addr:full":"Neustadt 41 Feldkirch Vorarlberg 6800",
    "addr:housenumber":"41",
    "addr:postcode":"6800",
    "addr:street":"Neustadt",
    "iso:country":"AT",
    "sg:address":"Neustadt 41",
    "sg:city":"Feldkirch",
    "sg:orig_category":"Schneidereien",
    "sg:phone":"+43 5522 70856",
    "sg:postcode":"6800",
    "sg:province":"Vorarlberg",
    "wof:name":"Riegler Barbara",
    "wof:placetype":"venue"
},
  "geometry": {"coordinates":[9.5988550186,47.2364387512],"type":"Point"}
}