{
  "type": "Feature",
  "properties": {
    "addr:full":"Engerthstr 141 Wien Wien 1020",
    "addr:housenumber":"141",
    "addr:postcode":"1020",
    "iso:country":"AT",
    "sg:address":"Engerthstr 141",
    "sg:city":"Wien",
    "sg:orig_category":"Leitern",
    "sg:phone":"+43 1 2148275",
    "sg:postcode":"1020",
    "sg:province":"Wien",
    "wof:name":"H\u00f6dl Silvia",
    "wof:placetype":"venue"
},
  "geometry": {"coordinates":[16.3949699402,48.2316665649],"type":"Point"}
}