{
  "type": "Feature",
  "properties": {
    "iso:country":"AT",
    "sg:address":"Salzburger Str 30",
    "sg:city":"Ried im Innkreis",
    "sg:orig_category":"Spenglereien",
    "sg:phone":"+43 4377 5284666",
    "sg:postcode":"4910",
    "sg:province":"Ober\u00f6sterreich",
    "wof:name":"Haslinger Josef",
    "wof:placetype":"venue"
},
  "geometry": {"coordinates":[13.4766931534,48.2024841309],"type":"Point"}
}