{
  "type": "Feature",
  "properties": {
    "addr:full":"Salzburger Str 30 Ried im Innkreis Ober\u00f6sterreich 4910",
    "addr:housenumber":"30",
    "addr:postcode":"4910",
    "addr:street":"Salzburger Str",
    "iso:country":"AT",
    "sg:address":"Salzburger Str 30",
    "sg:city":"Ried im Innkreis",
    "sg:orig_category":"Spenglereien",
    "sg:phone":"+43 4377 5284666",
    "sg:postcode":"4910",
    "sg:province":"Ober\u00f6sterreich",
    "wof:name":"Haslinger Josef",
    "wof:placetype":"venue"
},
  "geometry": {"coordinates":[13.4766931534,48.2024841309],"type":"Point"}
}