{
  "type": "Feature",
  "properties": {
    "addr:full":"Pernerstorferg 31 Wien Wien 1100",
    "addr:housenumber":"31",
    "addr:postcode":"1100",
    "addr:street":"Pernerstorferg",
    "iso:country":"AT",
    "sg:address":"Pernerstorferg 31",
    "sg:city":"Wien",
    "sg:orig_category":"Haushaltsartikel",
    "sg:phone":"+43 4316 075571",
    "sg:postcode":"1100",
    "sg:province":"Wien",
    "wof:name":"Motaev Benjamin KEG",
    "wof:placetype":"venue"
},
  "geometry": {"coordinates":[16.3750572205,48.1764144897],"type":"Point"}
}