{
  "type": "Feature",
  "properties": {
    "addr:full":"Wiener Strasse 13 Haag Nieder\u00f6sterreich 3350",
    "addr:housenumber":"13",
    "addr:postcode":"3350",
    "addr:street":"Wiener Strasse",
    "iso:country":"AT",
    "sg:address":"Wiener Strasse 13",
    "sg:city":"Haag",
    "sg:classifiers":[
        {
            "category":"Shopping",
            "subcategory":"Photographic Equipment",
            "type":"Retail Goods"
        }
    ],
    "sg:phone":"+43 7434 42222",
    "sg:postcode":"3350",
    "sg:province":"Nieder\u00f6sterreich",
    "sg:tags":[
        "camera",
        "digital"
    ],
    "sg:website":"cisar.at",
    "wof:name":"Cisar Foto",
    "wof:placetype":"venue"
},
  "geometry": {"coordinates":[14.5672397614,48.1127815247],"type":"Point"}
}