{
  "type": "Feature",
  "properties": {
    "addr:full":"Dorf 123 Schnepfau Vorarlberg 6882",
    "addr:housenumber":"123",
    "addr:postcode":"6882",
    "addr:street":"Dorf",
    "iso:country":"AT",
    "sg:address":"Dorf 123",
    "sg:city":"Schnepfau",
    "sg:orig_category":"Molkereien U Molkereiprodukte",
    "sg:phone":"+43 4355 182820",
    "sg:postcode":"6882",
    "sg:province":"Vorarlberg",
    "wof:name":"Sennerei Schnepfau regGenmbH",
    "wof:placetype":"venue"
},
  "geometry": {"coordinates":[9.9455270767,47.3522415161],"type":"Point"}
}