{
  "type": "Feature",
  "properties": {
    "addr:full":"Wiener Str 24 Hainfeld Nieder\u00f6sterreich 3170",
    "addr:postcode":"3170",
    "addr:street":"Niederoesterreich",
    "iso:country":"AT",
    "sg:address":"Wiener Str 24",
    "sg:city":"Hainfeld",
    "sg:orig_category":"Tankstellen",
    "sg:phone":"+43 2764 2222",
    "sg:postcode":"3170",
    "sg:province":"Nieder\u00f6sterreich",
    "wof:name":"OMV AG",
    "wof:placetype":"venue"
},
  "geometry": {"coordinates":[15.7788772583,48.0337600708],"type":"Point"}
}