{
  "type": "Feature",
  "properties": {
    "iso:country":"AT",
    "sg:address":"Dorfstr 12",
    "sg:city":"Fieberbrunn",
    "sg:orig_category":"Polizei U Gendarmerie",
    "sg:phone":"+43 4359 1337202",
    "sg:postcode":"6391",
    "sg:province":"Tirol",
    "wof:name":"Gendarmerie",
    "wof:placetype":"venue"
},
  "geometry": {"coordinates":[12.5428876877,47.4773178101],"type":"Point"}
}