{
  "type": "Feature",
  "properties": {
    "addr:full":"Haselgraben 37 Ybbsitz Nieder\u00f6sterreich 3341",
    "addr:housenumber":"37",
    "addr:postcode":"3341",
    "addr:street":"Haselgraben",
    "iso:country":"AT",
    "sg:address":"Haselgraben 37",
    "sg:city":"Ybbsitz",
    "sg:orig_category":"Sandstrahlarbeiten",
    "sg:phone":"+43 7443 88200",
    "sg:postcode":"3341",
    "sg:province":"Nieder\u00f6sterreich",
    "wof:name":"FAHRNGRUBER Erich - Sandstrahlen",
    "wof:placetype":"venue"
},
  "geometry": {"coordinates":[14.9104032516,47.9511413574],"type":"Point"}
}