{
  "type": "Feature",
  "properties": {
    "iso:country":"AT",
    "sg:address":"Marbachstr 7",
    "sg:city":"Rudersdorf",
    "sg:orig_category":"Transportunternehmen",
    "sg:phone":"+43 3382 73002",
    "sg:postcode":"7571",
    "sg:province":"Burgenland",
    "wof:name":"Tonweber KG",
    "wof:placetype":"venue"
},
  "geometry": {"coordinates":[16.138885498,47.0481071472],"type":"Point"}
}