{
  "type": "Feature",
  "properties": {
    "addr:full":"Stegg 30 Bischofshofen Salzburg 5500",
    "addr:housenumber":"30",
    "addr:postcode":"5500",
    "addr:street":"Stegg;Salzburg",
    "iso:country":"AT",
    "sg:address":"Stegg 30",
    "sg:city":"Bischofshofen",
    "sg:orig_category":"Textilwaren / Einzelhandel",
    "sg:phone":"+43 6462 4393",
    "sg:postcode":"5500",
    "sg:province":"Salzburg",
    "wof:name":"Mayer Waltraud",
    "wof:placetype":"venue"
},
  "geometry": {"coordinates":[13.2236328125,47.4171562195],"type":"Point"}
}