{
  "type": "Feature",
  "properties": {
    "addr:full":"D\u00f6blinger Hauptstr 79/11 Wien Wien 1190",
    "addr:housenumber":"79 / 11",
    "addr:postcode":"1190",
    "addr:street":"Hauptstr",
    "iso:country":"AT",
    "sg:address":"D\u00f6blinger Hauptstr 79/11",
    "sg:city":"Wien",
    "sg:orig_category":"\u00c3\u201erzte / F Allgemeinmedizin",
    "sg:phone":"+43 1 3670720",
    "sg:postcode":"1190",
    "sg:province":"Wien",
    "wof:name":"Schweitzer Michael Dr med",
    "wof:placetype":"venue"
},
  "geometry": {"coordinates":[16.3553390503,48.2420043945],"type":"Point"}
}