{
  "type": "Feature",
  "properties": {
    "iso:country":"AT",
    "sg:address":"Vogelweider Str 43",
    "sg:city":"Wels",
    "sg:orig_category":"Friseure U Frisiersalons",
    "sg:phone":"+43 7242 43392",
    "sg:postcode":"4600",
    "sg:province":"Ober\u00f6sterreich",
    "wof:name":"Pr\u00f6mer Gottlieb",
    "wof:placetype":"venue"
},
  "geometry": {"coordinates":[14.0117397308,48.1631355286],"type":"Point"}
}