{
  "type": "Feature",
  "properties": {
    "addr:full":"Stegweg 3 Elsbethen-Glasenbach Salzburg 5061",
    "addr:housenumber":"3",
    "addr:postcode":"5061",
    "addr:street":"Stegweg;Salzburg",
    "iso:country":"AT",
    "sg:address":"Stegweg 3",
    "sg:city":"Elsbethen-Glasenbach",
    "sg:orig_category":"Elektroinstallationsunternehmen",
    "sg:phone":"+43 662 635421",
    "sg:postcode":"5061",
    "sg:province":"Salzburg",
    "wof:name":"Helminger Josef",
    "wof:placetype":"venue"
},
  "geometry": {"coordinates":[13.0799589157,47.767665863],"type":"Point"}
}