{
  "type": "Feature",
  "properties": {
    "addr:full":"Meidlinger Hauptstr 6 Wien Wien 1120",
    "addr:housenumber":"6",
    "addr:postcode":"1120",
    "addr:street":"Meidlinger Hauptstr",
    "iso:country":"AT",
    "sg:address":"Meidlinger Hauptstr 6",
    "sg:city":"Wien",
    "sg:orig_category":"Eissalons",
    "sg:phone":"+43 1 8159030",
    "sg:postcode":"1120",
    "sg:province":"Wien",
    "wof:name":"Zampolli",
    "wof:placetype":"venue"
},
  "geometry": {"coordinates":[16.3297748566,48.1820373535],"type":"Point"}
}