{
  "type": "Feature",
  "properties": {
    "iso:country":"AT",
    "sg:address":"Leiten 111",
    "sg:city":"Ramsau am Dachstein",
    "sg:orig_category":"Holzhandel",
    "sg:phone":"+43 4336 8781197",
    "sg:postcode":"8972",
    "sg:province":"Steiermark",
    "wof:name":"Walcher Holzhandel Profil- u Schnittholz",
    "wof:placetype":"venue"
},
  "geometry": {"coordinates":[13.6792354584,47.4065246582],"type":"Point"}
}