{
  "type": "Feature",
  "properties": {
    "addr:full":"Hansalg 4 Wien Wien 1030",
    "addr:housenumber":"4",
    "addr:postcode":"1030",
    "addr:street":"Hansalg",
    "iso:country":"AT",
    "sg:address":"Hansalg 4",
    "sg:city":"Wien",
    "sg:orig_category":"Tabaktrafiken",
    "sg:phone":"+43 1 7146078",
    "sg:postcode":"1030",
    "sg:province":"Wien",
    "wof:name":"Mosm\u00fcller Robert",
    "wof:placetype":"venue"
},
  "geometry": {"coordinates":[16.3881587982,48.2074279785],"type":"Point"}
}