{
  "type": "Feature",
  "properties": {
    "addr:full":"Ledererstr 1 Oberneukirchen Ober\u00f6sterreich 4181",
    "addr:housenumber":"1",
    "addr:postcode":"4181",
    "addr:street":"Ledererstr",
    "iso:country":"AT",
    "sg:address":"Ledererstr 1",
    "sg:city":"Oberneukirchen",
    "sg:orig_category":"Gemeinden",
    "sg:phone":"+43 7212 70550",
    "sg:postcode":"4181",
    "sg:province":"Ober\u00f6sterreich",
    "wof:name":"Marktgemeinde Oberneukirchen",
    "wof:placetype":"venue"
},
  "geometry": {"coordinates":[14.2256660461,48.4633598328],"type":"Point"}
}