{
  "type": "Feature",
  "properties": {
    "addr:full":"Widmanng 42 Villach K\u00e4rnten 9500",
    "addr:housenumber":"42",
    "addr:postcode":"9500",
    "addr:street":"Widmanng;Kaernten",
    "iso:country":"AT",
    "sg:address":"Widmanng 42",
    "sg:city":"Villach",
    "sg:orig_category":"Juweliere, Gold- U Silberschmiede",
    "sg:phone":"+43 4342 4227372",
    "sg:postcode":"9500",
    "sg:province":"K\u00e4rnten",
    "wof:name":"Juwelier Sch\u00fctzlhoffer GmbH & Co KG",
    "wof:placetype":"venue"
},
  "geometry": {"coordinates":[13.8442993164,46.61277771],"type":"Point"}
}