{
  "type": "Feature",
  "properties": {
    "addr:full":"Fraueng 1 (Ecke/Hauptpl) Baden Nieder\u00f6sterreich 2500",
    "addr:housenumber":"1",
    "addr:postcode":"2500",
    "addr:street":"Fraueng;Ecke;Niederoesterreich",
    "iso:country":"AT",
    "sg:address":"Fraueng 1 (Ecke/Hauptpl)",
    "sg:city":"Baden",
    "sg:orig_category":"\u00c3\u201erzte / F Allgemeinmedizin",
    "sg:phone":"+43 4365 05830997",
    "sg:postcode":"2500",
    "sg:province":"Nieder\u00f6sterreich",
    "wof:name":"Jenisch Michaela Dr",
    "wof:placetype":"venue"
},
  "geometry": {"coordinates":[16.2344455719,48.0071411133],"type":"Point"}
}