{
  "type": "Feature",
  "properties": {
    "addr:full":"Gastgebg 27 Wien Wien 1230",
    "addr:housenumber":"27",
    "addr:postcode":"1230",
    "addr:street":"Gastgebg",
    "iso:country":"AT",
    "sg:address":"Gastgebg 27",
    "sg:city":"Wien",
    "sg:orig_category":"Industrievertretungen",
    "sg:phone":"+43 4318 038055",
    "sg:postcode":"1230",
    "sg:province":"Wien",
    "wof:name":"HTC Textile Application Consulting GmbH",
    "wof:placetype":"venue"
},
  "geometry": {"coordinates":[16.2954158783,48.1524505615],"type":"Point"}
}