{
  "type": "Feature",
  "properties": {
    "addr:full":"Schottenring 35 Wien Wien 1010",
    "addr:housenumber":"35",
    "addr:postcode":"1010",
    "addr:street":"Schottenring",
    "iso:country":"AT",
    "sg:address":"Schottenring 35",
    "sg:city":"Wien",
    "sg:orig_category":"Non-Classified Establishments",
    "sg:phone":"+43 1 31051590",
    "sg:postcode":"1010",
    "sg:province":"Wien",
    "wof:name":"Katholische Sozialakademie \u00d6sterreichs",
    "wof:placetype":"venue"
},
  "geometry": {"coordinates":[16.3695926666,48.2175216675],"type":"Point"}
}