{
  "type": "Feature",
  "properties": {
    "addr:full":"Nr 22 Steinfeld K\u00e4rnten 9754",
    "addr:postcode":"9754",
    "addr:street":"Nr;Steinfeld",
    "iso:country":"AT",
    "sg:address":"Nr 22",
    "sg:city":"Steinfeld",
    "sg:orig_category":"Tischlereien",
    "sg:phone":"+43 4717 20055",
    "sg:postcode":"9754",
    "sg:province":"K\u00e4rnten",
    "wof:name":"Hartlieb Egon",
    "wof:placetype":"venue"
},
  "geometry": {"coordinates":[13.2483673096,46.7575645447],"type":"Point"}
}