{
  "type": "Feature",
  "properties": {
    "addr:full":"Stockhofstrasse 6 Linz Ober\u00f6sterreich 4020",
    "addr:housenumber":"6",
    "addr:postcode":"4020",
    "addr:street":"Stockhofstrasse",
    "iso:country":"AT",
    "sg:address":"Stockhofstrasse 6",
    "sg:city":"Linz",
    "sg:classifiers":[
        {
            "category":"Health Services",
            "subcategory":"Optometrist",
            "type":"Services"
        }
    ],
    "sg:phone":"+43 732 663474",
    "sg:postcode":"4020",
    "sg:province":"Ober\u00f6sterreich",
    "sg:tags":[
        "opt",
        "glass",
        "chain"
    ],
    "wof:name":"Karl Wildmann",
    "wof:placetype":"venue"
},
  "geometry": {"coordinates":[14.2874116898,48.2971763611],"type":"Point"}
}