{
  "type": "Feature",
  "properties": {
    "iso:country":"AT",
    "sg:address":"Glantschach 19",
    "sg:city":"Liebenfels",
    "sg:classifiers":[
        {
            "category":"Utilities",
            "subcategory":"Electric",
            "type":"Services"
        }
    ],
    "sg:phone":"+43 4215 3160",
    "sg:postcode":"9556",
    "sg:province":"K\u00e4rnten",
    "sg:tags":[
        "planing",
        "metal"
    ],
    "wof:name":"Harald Heckenbichler - Bauholz S\u00e4gewerk",
    "wof:placetype":"venue"
},
  "geometry": {"coordinates":[14.25806427,46.749168396],"type":"Point"}
}