{
  "type": "Feature",
  "properties": {
    "addr:full":"Stadtpl 7 Schwanenstadt Ober\u00f6sterreich 4690",
    "addr:housenumber":"7",
    "addr:postcode":"4690",
    "addr:street":"Stadtpl",
    "iso:country":"AT",
    "sg:address":"Stadtpl 7",
    "sg:city":"Schwanenstadt",
    "sg:orig_category":"Elektroinstallationsunternehmen",
    "sg:phone":"+43 767323340",
    "sg:postcode":"4690",
    "sg:province":"Ober\u00f6sterreich",
    "wof:name":"Schobesberger KG",
    "wof:placetype":"venue"
},
  "geometry": {"coordinates":[13.7730979919,48.0546379089],"type":"Point"}
}