{
  "type": "Feature",
  "properties": {
    "addr:full":"Bahnhofstrasse 17 Tulln an der Donau Nieder\u00f6sterreich 3430",
    "addr:housenumber":"17",
    "addr:postcode":"3430",
    "addr:street":"Bahnhofstrasse",
    "iso:country":"AT",
    "sg:address":"Bahnhofstrasse 17",
    "sg:city":"Tulln an der Donau",
    "sg:classifiers":[
        {
            "category":"Health Services",
            "subcategory":"Nursing And Care Facility",
            "type":"Services"
        }
    ],
    "sg:phone":"+43 2272 64763",
    "sg:postcode":"3430",
    "sg:province":"Nieder\u00f6sterreich",
    "sg:tags":[
        "battery",
        "aid",
        "hearing"
    ],
    "wof:name":"Martin Tscherny GesmbH",
    "wof:placetype":"venue"
},
  "geometry": {"coordinates":[16.0539512634,48.3297691345],"type":"Point"}
}