{
  "type": "Feature",
  "properties": {
    "addr:full":"Augasse 19 Wien Wien 1090",
    "addr:housenumber":"19",
    "addr:postcode":"1090",
    "addr:street":"Augasse",
    "iso:country":"AT",
    "sg:address":"Augasse 19",
    "sg:city":"Wien",
    "sg:classifiers":[
        {
            "category":"Professional",
            "subcategory":"Advertising",
            "type":"Services"
        }
    ],
    "sg:phone":"+43 1 3105919",
    "sg:postcode":"1090",
    "sg:province":"Wien",
    "sg:tags":[
        "poster"
    ],
    "sg:website":"kopierkeller.at",
    "wof:name":"Fanta & Posch GmbH & Co KG",
    "wof:placetype":"venue"
},
  "geometry": {"coordinates":[16.356502533,48.232383728],"type":"Point"}
}