{
  "type": "Feature",
  "properties": {
    "addr:full":"Nr 368 Hohenruppersdorf Nieder\u00f6sterreich 2223",
    "addr:postcode":"2223",
    "addr:street":"Nr 368",
    "iso:country":"AT",
    "sg:address":"Nr 368",
    "sg:city":"Hohenruppersdorf",
    "sg:orig_category":"Autoverwertung",
    "sg:phone":"+43 2574 8366",
    "sg:postcode":"2223",
    "sg:province":"Nieder\u00f6sterreich",
    "wof:name":"Seidl Karl",
    "wof:placetype":"venue"
},
  "geometry": {"coordinates":[16.6530265808,48.4634246826],"type":"Point"}
}