{
  "type": "Feature",
  "properties": {
    "iso:country":"AT",
    "sg:address":"Obern 42",
    "sg:city":"Leutasch",
    "sg:classifiers":[
        {
            "category":"Travel",
            "subcategory":"Hotels & Motels",
            "type":"Entertainment"
        }
    ],
    "sg:phone":"+43 4352 146253",
    "sg:postcode":"6105",
    "sg:province":"Tirol",
    "sg:website":"jodlerwirt.at",
    "wof:name":"Hotel Bergland",
    "wof:placetype":"venue"
},
  "geometry": {"coordinates":[11.1238269806,47.3604240417],"type":"Point"}
}