{
  "type": "Feature",
  "properties": {
    "addr:full":"Steiner Landstr 80 Krems an der Donau Nieder\u00f6sterreich 3500",
    "addr:housenumber":"80",
    "addr:postcode":"3500",
    "addr:street":"Steiner Landstr",
    "iso:country":"AT",
    "sg:address":"Steiner Landstr 80",
    "sg:city":"Krems an der Donau",
    "sg:orig_category":"Apotheken",
    "sg:phone":"+43 2732 845670",
    "sg:postcode":"3500",
    "sg:province":"Nieder\u00f6sterreich",
    "wof:name":"Apotheke Zum Engel Mag pharm Walter Riedl KG",
    "wof:placetype":"venue"
},
  "geometry": {"coordinates":[15.580206871,48.4016151428],"type":"Point"}
}