{
  "type": "Feature",
  "properties": {
    "addr:full":"Nr 127 Unterkohlst\u00e4tten Burgenland 7435",
    "addr:postcode":"7435",
    "addr:street":"Nr 127 Unterkohlstaetten",
    "iso:country":"AT",
    "sg:address":"Nr 127",
    "sg:city":"Unterkohlst\u00e4tten",
    "sg:orig_category":"Transportunternehmen",
    "sg:phone":"+43 4366 44014646",
    "sg:postcode":"7435",
    "sg:province":"Burgenland",
    "wof:name":"Klein Unlimited GmbH",
    "wof:placetype":"venue"
},
  "geometry": {"coordinates":[16.3263683319,47.3749008179],"type":"Point"}
}