{
  "type": "Feature",
  "properties": {
    "addr:full":"Steiner Landstrasse 70 Krems an der Donau Nieder\u00f6sterreich 3500",
    "addr:housenumber":"70",
    "addr:postcode":"3500",
    "addr:street":"Steiner Landstrasse",
    "iso:country":"AT",
    "sg:address":"Steiner Landstrasse 70",
    "sg:city":"Krems an der Donau",
    "sg:classifiers":[
        {
            "category":"Home & Garden",
            "subcategory":"Household Appliances",
            "type":"Retail Goods"
        }
    ],
    "sg:phone":"+43 2732 82312",
    "sg:postcode":"3500",
    "sg:province":"Nieder\u00f6sterreich",
    "sg:tags":[
        "stove",
        "chimney"
    ],
    "sg:website":"waldviertlerwohnwelten.com",
    "wof:name":"Pani & Kovar GmbH",
    "wof:placetype":"venue"
},
  "geometry": {"coordinates":[15.5814323425,48.4019622803],"type":"Point"}
}