{
  "type": "Feature",
  "properties": {
    "iso:country":"AT",
    "sg:address":"Am Scheern 10",
    "sg:city":"Wald",
    "sg:orig_category":"Fenster",
    "sg:phone":"+43 4327 452143",
    "sg:postcode":"3144",
    "sg:province":"Nieder\u00f6sterreich",
    "wof:name":"Zeller Christine - Stabil Fenster u T\u00fcren",
    "wof:placetype":"venue"
},
  "geometry": {"coordinates":[-94.49806976319999,47.8722839355],"type":"Point"}
}