{
  "type": "Feature",
  "properties": {
    "addr:full":"Rathauspl 2 Kirchdorf an der Krems Ober\u00f6sterreich 4560",
    "addr:housenumber":"2",
    "addr:postcode":"4560",
    "addr:street":"Rathauspl",
    "iso:country":"AT",
    "sg:address":"Rathauspl 2",
    "sg:city":"Kirchdorf an der Krems",
    "sg:orig_category":"Juweliere, Gold- U Silberschmiede",
    "sg:phone":"+43 4375 8264298",
    "sg:postcode":"4560",
    "sg:province":"Ober\u00f6sterreich",
    "wof:name":"Sch\u00f6ffmann Sonja",
    "wof:placetype":"venue"
},
  "geometry": {"coordinates":[14.1226139069,47.9059028625],"type":"Point"}
}