{
  "type": "Feature",
  "properties": {
    "addr:full":"Im Moos 2 Absam Tirol 6067",
    "addr:housenumber":"2",
    "addr:postcode":"6067",
    "addr:street":"Im Moos;Tirol",
    "iso:country":"AT",
    "sg:address":"Im Moos 2",
    "sg:city":"Absam",
    "sg:orig_category":"Feuerwehren",
    "sg:phone":"+43 5223 57540",
    "sg:postcode":"6067",
    "sg:province":"Tirol",
    "wof:name":"Freiwillige Feuerwehr Absam",
    "wof:placetype":"venue"
},
  "geometry": {"coordinates":[11.5084981918,47.2953338623],"type":"Point"}
}