{
  "type": "Feature",
  "properties": {
    "addr:full":"Grazer G 73 Leibnitz Steiermark 8430",
    "addr:housenumber":"73",
    "addr:postcode":"8430",
    "addr:street":"Grazer G;Steiermark",
    "iso:country":"AT",
    "sg:address":"Grazer G 73",
    "sg:city":"Leibnitz",
    "sg:orig_category":"Papier- U Schreibwaren / Einzelhandel",
    "sg:phone":"+43 3452 83166",
    "sg:postcode":"8430",
    "sg:province":"Steiermark",
    "wof:name":"Hofbauer Jutta",
    "wof:placetype":"venue"
},
  "geometry": {"coordinates":[15.5385303497,46.7871894836],"type":"Point"}
}