{
  "type": "Feature",
  "properties": {
    "addr:full":"Griesfeldstr. 1 Wiener Neudorf Nieder\u00f6sterreich 2351",
    "addr:housenumber":"1",
    "addr:postcode":"2351",
    "addr:street":"Griesfeldstr.",
    "iso:country":"AT",
    "sg:address":"Griesfeldstr. 1",
    "sg:city":"Wiener Neudorf",
    "sg:classifiers":[
        {
            "category":"Autos & Motor Vehicles",
            "subcategory":"Boat Sales",
            "type":"Retail Goods"
        }
    ],
    "sg:phone":"+43 4322 3664676",
    "sg:postcode":"2351",
    "sg:province":"Nieder\u00f6sterreich",
    "wof:name":"ALLTECHNIK GMBH",
    "wof:placetype":"venue"
},
  "geometry": {"coordinates":[16.3246364594,48.0795936584],"type":"Point"}
}