{
  "type": "Feature",
  "properties": {
    "iso:country":"AT",
    "sg:address":"Nr 165a",
    "sg:city":"Gaschurn",
    "sg:orig_category":"Pensionen / Privatzimmer",
    "sg:phone":"+43 4355 588630",
    "sg:postcode":"6793",
    "sg:province":"Vorarlberg",
    "wof:name":"Pension Alpenrose",
    "wof:placetype":"venue"
},
  "geometry": {"coordinates":[10.0248842239,46.9886512756],"type":"Point"}
}