{
  "type": "Feature",
  "properties": {
    "iso:country":"AT",
    "sg:address":"Hauptpl 14/1",
    "sg:city":"Villach",
    "sg:orig_category":"Restaurants: Chinesisch",
    "sg:phone":"+43 4242 250149",
    "sg:postcode":"9500",
    "sg:province":"K\u00e4rnten",
    "wof:name":"China-Restaurant goldenes Paradies",
    "wof:placetype":"venue"
},
  "geometry": {"coordinates":[13.8468465805,46.6143875122],"type":"Point"}
}