{
  "type": "Feature",
  "properties": {
    "iso:country":"AT",
    "sg:address":"Haidestr. 53",
    "sg:city":"Wels",
    "sg:classifiers":[
        {
            "category":"Parking",
            "subcategory":"Lot",
            "type":"Transportation"
        }
    ],
    "sg:phone":"+43 4372 42669310",
    "sg:postcode":"4600",
    "sg:province":"Ober\u00f6sterreich",
    "sg:tags":[
        "transport",
        "road"
    ],
    "wof:name":"KARL AUGUSTIN GES. MBH",
    "wof:placetype":"venue"
},
  "geometry": {"coordinates":[14.0164899826,48.1660118103],"type":"Point"}
}