{
  "type": "Feature",
  "properties": {
    "addr:full":"Pfarrgasse 3 Horn Nieder\u00f6sterreich 3580",
    "addr:housenumber":"3",
    "addr:postcode":"3580",
    "addr:street":"Pfarrgasse;Niederoesterreich",
    "iso:country":"AT",
    "sg:address":"Pfarrgasse 3",
    "sg:city":"Horn",
    "sg:orig_category":"Chains, Necklaces",
    "sg:phone":"+43 2982 2421",
    "sg:postcode":"3580",
    "sg:province":"Nieder\u00f6sterreich",
    "sg:website":"strassberger.horn.at",
    "wof:name":"Stra\u00dfberger KG",
    "wof:placetype":"venue"
},
  "geometry": {"coordinates":[15.6582746506,48.6647720337],"type":"Point"}
}