{
  "type": "Feature",
  "properties": {
    "addr:full":"Europastr. 1 Vitis Nieder\u00f6sterreich 3902",
    "addr:housenumber":"1",
    "addr:postcode":"3902",
    "addr:street":"Europastr.",
    "iso:country":"AT",
    "sg:address":"Europastr. 1",
    "sg:city":"Vitis",
    "sg:classifiers":[
        {
            "category":"Professional",
            "subcategory":"Engineering",
            "type":"Services"
        }
    ],
    "sg:phone":"+43 4328 418685",
    "sg:postcode":"3902",
    "sg:province":"Nieder\u00f6sterreich",
    "sg:tags":[
        "machine",
        "-",
        "mechanical"
    ],
    "wof:name":"FIDA INSTALLATIONEN GMBH",
    "wof:placetype":"venue"
},
  "geometry": {"coordinates":[15.1932916641,48.7570075989],"type":"Point"}
}