{
  "type": "Feature",
  "properties": {
    "addr:full":"Ledererg 521 Kaprun Salzburg 5710",
    "addr:housenumber":"521",
    "addr:postcode":"5710",
    "addr:street":"Kaprun Salzburg",
    "iso:country":"AT",
    "sg:address":"Ledererg 521",
    "sg:city":"Kaprun",
    "sg:orig_category":"Appartements / Ferienwohnungen",
    "sg:phone":"+43 6547 74050",
    "sg:postcode":"5710",
    "sg:province":"Salzburg",
    "wof:name":"Fischer Susanne",
    "wof:placetype":"venue"
},
  "geometry": {"coordinates":[12.7575788498,47.2708206177],"type":"Point"}
}