{
  "type": "Feature",
  "properties": {
    "addr:full":"Flurstrasse 1 Rum Tirol 6063",
    "addr:housenumber":"1",
    "addr:postcode":"6063",
    "addr:street":"Flurstrasse;Tirol",
    "iso:country":"AT",
    "sg:address":"Flurstrasse 1",
    "sg:city":"Rum",
    "sg:classifiers":[
        {
            "category":"Commercial Area",
            "type":"Public Place"
        }
    ],
    "sg:phone":"+43 512 264488",
    "sg:postcode":"6063",
    "sg:province":"Tirol",
    "sg:tags":[
        "equipping",
        "kitchen"
    ],
    "sg:website":"fuco.at",
    "wof:name":"FUCO maschinen handels service gmbh",
    "wof:placetype":"venue"
},
  "geometry": {"coordinates":[11.4533004761,47.2756156921],"type":"Point"}
}