{
  "type": "Feature",
  "properties": {
    "addr:full":"Neustr 238 Kaprun Salzburg 5710",
    "addr:housenumber":"238",
    "addr:postcode":"5710",
    "addr:street":"Kaprun Salzburg",
    "iso:country":"AT",
    "sg:address":"Neustr 238",
    "sg:city":"Kaprun",
    "sg:orig_category":"Pensionen / Privatzimmer",
    "sg:phone":"+43 6547 82490",
    "sg:postcode":"5710",
    "sg:province":"Salzburg",
    "wof:name":"Pension Eichkatzerl",
    "wof:placetype":"venue"
},
  "geometry": {"coordinates":[12.7612609863,47.2721252441],"type":"Point"}
}