{
  "type": "Feature",
  "properties": {
    "iso:country":"AT",
    "sg:address":"Grillgasse 46",
    "sg:city":"Wien",
    "sg:classifiers":[
        {
            "category":"Military Area",
            "subcategory":"Coast Guard Base",
            "type":"Public Place"
        }
    ],
    "sg:phone":"+43 1 7435525",
    "sg:postcode":"1110",
    "sg:province":"Wien",
    "sg:tags":[
        "regulator",
        "flow",
        "air"
    ],
    "sg:website":"gp-airsystems.com",
    "wof:name":"G & P AIR SYSTEMS VertriebsgmbH",
    "wof:placetype":"venue"
},
  "geometry": {"coordinates":[16.409362793,48.1694641113],"type":"Point"}
}