{
  "type": "Feature",
  "properties": {
    "addr:full":"Kindermanng 20 Graz Steiermark 8020",
    "addr:housenumber":"20",
    "addr:postcode":"8020",
    "addr:street":"Kindermanng",
    "iso:country":"AT",
    "sg:address":"Kindermanng 20",
    "sg:city":"Graz",
    "sg:orig_category":"Immobilienverwaltungen",
    "sg:phone":"+43 316 716830",
    "sg:postcode":"8020",
    "sg:province":"Steiermark",
    "wof:name":"Fellner Paula",
    "wof:placetype":"venue"
},
  "geometry": {"coordinates":[15.4251337051,47.0668373108],"type":"Point"}
}