{
  "type": "Feature",
  "properties": {
    "addr:full":"Haidestr. 4 Wien Wien 1110",
    "addr:housenumber":"4",
    "addr:postcode":"1110",
    "addr:street":"Haidestr.",
    "iso:country":"AT",
    "sg:address":"Haidestr. 4",
    "sg:city":"Wien",
    "sg:classifiers":[
        {
            "category":"Wholesale",
            "subcategory":"Drugs",
            "type":"Manufacturing & Wholesale Goods"
        }
    ],
    "sg:phone":"+43 4318 01040",
    "sg:postcode":"1110",
    "sg:province":"Wien",
    "sg:tags":[
        "chemical",
        "pharmaceutical"
    ],
    "wof:name":"SANOVA PHARMA GES.MBH",
    "wof:placetype":"venue"
},
  "geometry": {"coordinates":[16.42852211,48.1786346436],"type":"Point"}
}