{
  "type": "Feature",
  "properties": {
    "addr:full":"Radetzkystr 7 Graz Steiermark 8010",
    "addr:housenumber":"7",
    "addr:postcode":"8010",
    "addr:street":"Radetzkystr",
    "iso:country":"AT",
    "sg:address":"Radetzkystr 7",
    "sg:city":"Graz",
    "sg:orig_category":"Tabaktrafiken",
    "sg:phone":"+43 316 829387",
    "sg:postcode":"8010",
    "sg:province":"Steiermark",
    "wof:name":"Weiss Eva",
    "wof:placetype":"venue"
},
  "geometry": {"coordinates":[15.4401845932,47.0664482117],"type":"Point"}
}