{
  "type": "Feature",
  "properties": {
    "iso:country":"AT",
    "sg:address":"Radetzkystr 7",
    "sg:city":"Graz",
    "sg:orig_category":"Tabaktrafiken",
    "sg:phone":"+43 316 829387",
    "sg:postcode":"8010",
    "sg:province":"Steiermark",
    "wof:name":"Weiss Eva",
    "wof:placetype":"venue"
},
  "geometry": {"coordinates":[15.4401845932,47.0664482117],"type":"Point"}
}