{
  "type": "Feature",
  "properties": {
    "addr:full":"Raffaltplatz 19-23 Murau Steiermark 8850",
    "addr:postcode":"19-23;8850",
    "addr:street":"Raffaltplatz",
    "iso:country":"AT",
    "sg:address":"Raffaltplatz 19-23",
    "sg:city":"Murau",
    "sg:classifiers":[
        {
            "category":"Wholesale",
            "subcategory":"Beer",
            "type":"Manufacturing & Wholesale Goods"
        }
    ],
    "sg:phone":"+43 3532 32660",
    "sg:postcode":"8850",
    "sg:province":"Steiermark",
    "sg:website":"murauerbier.at",
    "wof:name":"1. Obermurtaler Brauereigenossen- schaft in Murau reg. Gen.m.b.H.",
    "wof:placetype":"venue"
},
  "geometry": {"coordinates":[14.1655950546,47.1111183167],"type":"Point"}
}