{
  "type": "Feature",
  "properties": {
    "addr:full":"B\u00fcrgerg 21-23/13/1-2 Wien Wien 1100",
    "addr:housenumber":"21-23 / 13 / 1-2",
    "addr:postcode":"1100",
    "iso:country":"AT",
    "sg:address":"B\u00fcrgerg 21-23/13/1-2",
    "sg:city":"Wien",
    "sg:orig_category":"\u00c3\u201erzte / F Allgemeinmedizin",
    "sg:phone":"+43 1 6026206",
    "sg:postcode":"1100",
    "sg:province":"Wien",
    "wof:name":"Abou-Harb Ayman MedR Dr",
    "wof:placetype":"venue"
},
  "geometry": {"coordinates":[16.3744049072,48.1782684326],"type":"Point"}
}