{
  "type": "Feature",
  "properties": {
    "iso:country":"AT",
    "sg:address":"Unterstra\u00df 251",
    "sg:city":"Obsteig",
    "sg:orig_category":"Lebensmittel / Einzelhandel",
    "sg:phone":"+43 5264 20417",
    "sg:postcode":"6416",
    "sg:province":"Tirol",
    "wof:name":"SPAR \u00f6sterreichische Warenhandels-AG",
    "wof:placetype":"venue"
},
  "geometry": {"coordinates":[10.9278440475,47.2978858948],"type":"Point"}
}