{
  "type": "Feature",
  "properties": {
    "addr:full":"Schenkenstr 8 Wien Wien 1010",
    "addr:housenumber":"8",
    "addr:postcode":"1010",
    "addr:street":"Schenkenstr",
    "iso:country":"AT",
    "sg:address":"Schenkenstr 8",
    "sg:city":"Wien",
    "sg:orig_category":"Politische Parteien",
    "sg:phone":"+43 1 401105897",
    "sg:postcode":"1010",
    "sg:province":"Wien",
    "wof:name":"Freiheitliches EU B\u00fcro",
    "wof:placetype":"venue"
},
  "geometry": {"coordinates":[16.3629970551,48.2109184265],"type":"Point"}
}