{
  "type": "Feature",
  "properties": {
    "addr:full":"Schmiedwiese 170 Mayrhofen Tirol 6290",
    "addr:housenumber":"170",
    "addr:postcode":"6290",
    "addr:street":"Schmiedwiese;Tirol",
    "iso:country":"AT",
    "sg:address":"Schmiedwiese 170",
    "sg:city":"Mayrhofen",
    "sg:orig_category":"Pensionen / Privatzimmer",
    "sg:phone":"+43 5285 62359",
    "sg:postcode":"6290",
    "sg:province":"Tirol",
    "wof:name":"Frankhauser Astrid",
    "wof:placetype":"venue"
},
  "geometry": {"coordinates":[11.8637199402,47.1727714539],"type":"Point"}
}