{
  "type": "Feature",
  "properties": {
    "iso:country":"AT",
    "sg:address":"Markt 18",
    "sg:city":"Ulrichsberg",
    "sg:classifiers":[
        {
            "category":"Utilities",
            "subcategory":"Natural Gas",
            "type":"Services"
        }
    ],
    "sg:phone":"+43 7288 70100",
    "sg:postcode":"4161",
    "sg:province":"Ober\u00f6sterreich",
    "sg:tags":[
        "heater",
        "direct",
        "electric"
    ],
    "sg:website":"redzac-gabriel.at",
    "wof:name":"Elektrohaus Gabriel Ges.m.b.H.",
    "wof:placetype":"venue"
},
  "geometry": {"coordinates":[13.9126300812,48.6745605469],"type":"Point"}
}