{
  "type": "Feature",
  "properties": {
    "addr:full":"Platzl 109 Leutasch Tirol 6105",
    "addr:housenumber":"109",
    "addr:postcode":"6105",
    "addr:street":"Platzl;Tirol",
    "iso:country":"AT",
    "sg:address":"Platzl 109",
    "sg:city":"Leutasch",
    "sg:orig_category":"Pensionen / Privatzimmer",
    "sg:phone":"+43 5214 6365",
    "sg:postcode":"6105",
    "sg:province":"Tirol",
    "wof:name":"Thoamlhof",
    "wof:placetype":"venue"
},
  "geometry": {"coordinates":[11.1376609802,47.3619270325],"type":"Point"}
}