{
  "type": "Feature",
  "properties": {
    "iso:country":"AT",
    "sg:address":"Nr 20",
    "sg:city":"Kapelln",
    "sg:orig_category":"Landwirtschaftliche Hilfsdienste",
    "sg:phone":"+43 4327 842254",
    "sg:postcode":"3141",
    "sg:province":"Nieder\u00f6sterreich",
    "wof:name":"Schulz Hermann",
    "wof:placetype":"venue"
},
  "geometry": {"coordinates":[15.7556753159,48.2581596375],"type":"Point"}
}