{
  "type": "Feature",
  "properties": {
    "iso:country":"AT",
    "sg:address":"Sch\u00fctzeng 12",
    "sg:city":"St. Andr\u00e4-W\u00f6rdern",
    "sg:orig_category":"Baumeister",
    "sg:phone":"+43 2242 31052",
    "sg:postcode":"3423",
    "sg:province":"Nieder\u00f6sterreich",
    "wof:name":"Gei\u00dfler Manfred Bmstr Ing",
    "wof:placetype":"venue"
},
  "geometry": {"coordinates":[16.2101764679,48.3275222778],"type":"Point"}
}