{
  "type": "Feature",
  "properties": {
    "iso:country":"AT",
    "sg:address":"Kindergartenweg 13",
    "sg:city":"Kalsdorf",
    "sg:orig_category":"Musikgruppen",
    "sg:phone":"+43 3135 51551",
    "sg:postcode":"8401",
    "sg:province":"Steiermark",
    "wof:name":"Musikkapelle der Roto-Frank AG",
    "wof:placetype":"venue"
},
  "geometry": {"coordinates":[15.4809989929,46.962097168],"type":"Point"}
}