{
  "type": "Feature",
  "properties": {
    "iso:country":"AT",
    "sg:address":"Nr 246",
    "sg:city":"St. Martin am Tennengebirge",
    "sg:orig_category":"Bauunternehmen",
    "sg:phone":"+43 6463 74150",
    "sg:postcode":"5522",
    "sg:province":"Salzburg",
    "wof:name":"Martin Bau-GesmbH",
    "wof:placetype":"venue"
},
  "geometry": {"coordinates":[-83.1848602295,34.4854125977],"type":"Point"}
}