{
  "type": "Feature",
  "properties": {
    "addr:full":"Rosenthalg 9 Perchtoldsdorf Nieder\u00f6sterreich 2380",
    "addr:housenumber":"9",
    "addr:postcode":"2380",
    "addr:street":"Rosenthalg",
    "iso:country":"AT",
    "sg:address":"Rosenthalg 9",
    "sg:city":"Perchtoldsdorf",
    "sg:orig_category":"Entsorgungen, Abfallentsorgung U -Verwertung",
    "sg:phone":"+43 4318 650000",
    "sg:postcode":"2380",
    "sg:province":"Nieder\u00f6sterreich",
    "wof:name":"ACS Abfall- & Containerservice GmbH",
    "wof:placetype":"venue"
},
  "geometry": {"coordinates":[16.2813396454,48.1309204102],"type":"Point"}
}