{
  "type": "Feature",
  "properties": {
    "iso:country":"AT",
    "sg:address":"Teilenstr 10b",
    "sg:city":"Lustenau",
    "sg:orig_category":"Stickereien",
    "sg:phone":"+43 5577 86794",
    "sg:postcode":"6890",
    "sg:province":"Vorarlberg",
    "wof:name":"Hagen Edwin",
    "wof:placetype":"venue"
},
  "geometry": {"coordinates":[9.6659498215,47.4288101196],"type":"Point"}
}