{
  "type": "Feature",
  "properties": {
    "addr:full":"Vorstadtg 6 Stadtschlaining Burgenland 7461",
    "addr:housenumber":"6",
    "addr:postcode":"7461",
    "addr:street":"Vorstadtg",
    "iso:country":"AT",
    "sg:address":"Vorstadtg 6",
    "sg:city":"Stadtschlaining",
    "sg:orig_category":"Non-Classified Establishments",
    "sg:phone":"+43 3355 2231",
    "sg:postcode":"7461",
    "sg:province":"Burgenland",
    "wof:name":"Pfarramt",
    "wof:placetype":"venue"
},
  "geometry": {"coordinates":[16.2792205811,47.3237075806],"type":"Point"}
}