{
  "type": "Feature",
  "properties": {
    "iso:country":"AT",
    "sg:address":"Haider Strasse 7",
    "sg:city":"Bad Leonfelden",
    "sg:classifiers":[
        {
            "category":"Communications",
            "subcategory":"Film & Video Production",
            "type":"Services"
        }
    ],
    "sg:phone":"+43 7213 81980",
    "sg:postcode":"4190",
    "sg:province":"Ober\u00f6sterreich",
    "sg:tags":[
        "printers",
        "printer",
        "data",
        "digital"
    ],
    "wof:name":"Engelbert Panholzer",
    "wof:placetype":"venue"
},
  "geometry": {"coordinates":[14.2989168167,48.5176239014],"type":"Point"}
}