{
  "type": "Feature",
  "properties": {
    "addr:full":"Stauraczg 6 Wien Wien 1050",
    "addr:housenumber":"6",
    "addr:postcode":"1050",
    "addr:street":"Stauraczg",
    "iso:country":"AT",
    "sg:address":"Stauraczg 6",
    "sg:city":"Wien",
    "sg:orig_category":"Bauunternehmen",
    "sg:phone":"+43 664 2022928",
    "sg:postcode":"1050",
    "sg:province":"Wien",
    "wof:name":"Kallos Handels- & Bau GmbH",
    "wof:placetype":"venue"
},
  "geometry": {"coordinates":[16.3584518433,48.1824951172],"type":"Point"}
}