{
  "type": "Feature",
  "properties": {
    "addr:full":"Vilzbach 2 Neukirchen am Walde Ober\u00f6sterreich 4724",
    "addr:housenumber":"2",
    "addr:postcode":"4724",
    "addr:street":"Vilzbach",
    "iso:country":"AT",
    "sg:address":"Vilzbach 2",
    "sg:city":"Neukirchen am Walde",
    "sg:orig_category":"Reinigungsservice",
    "sg:phone":"+43 4372 7833400",
    "sg:postcode":"4724",
    "sg:province":"Ober\u00f6sterreich",
    "wof:name":"B\u00fcro- u Industriereinigung GesmbH",
    "wof:placetype":"venue"
},
  "geometry": {"coordinates":[13.7808732986,48.4049911499],"type":"Point"}
}