{
  "type": "Feature",
  "properties": {
    "iso:country":"AT",
    "sg:address":"Aurachtalstr 28",
    "sg:city":"Pinsdorf",
    "sg:orig_category":"\u00c3\u201erzte / F Allgemeinmedizin",
    "sg:phone":"+43 761273888",
    "sg:postcode":"4812",
    "sg:province":"Ober\u00f6sterreich",
    "wof:name":"Seidl Peter Dr",
    "wof:placetype":"venue"
},
  "geometry": {"coordinates":[13.7422580719,47.9226722717],"type":"Point"}
}