{
  "type": "Feature",
  "properties": {
    "addr:full":"Schiffm\u00fchlenstr 98/7 Wien Wien 1220",
    "addr:housenumber":"98 / 7",
    "addr:postcode":"1220",
    "addr:street":"Schiffmuehlenstr",
    "iso:country":"AT",
    "sg:address":"Schiffm\u00fchlenstr 98/7",
    "sg:city":"Wien",
    "sg:orig_category":"Genossenschaften",
    "sg:phone":"+43 4312 633728",
    "sg:postcode":"1220",
    "sg:province":"Wien",
    "wof:name":"Gemeinn\u00fctzige Siedlungs-Genossenschaft Altmannsdorf u Hetzendorf regGenmbH",
    "wof:placetype":"venue"
},
  "geometry": {"coordinates":[16.444606781,48.2497138977],"type":"Point"}
}