{
  "type": "Feature",
  "properties": {
    "addr:full":"Beethoveng 4-6 Baden Nieder\u00f6sterreich 2500",
    "addr:housenumber":"4-6",
    "addr:postcode":"2500",
    "addr:street":"Beethoveng;Niederoesterreich",
    "iso:country":"AT",
    "sg:address":"Beethoveng 4-6",
    "sg:city":"Baden",
    "sg:orig_category":"Finanz- U Wirtschaftsberatung",
    "sg:phone":"+43 4322 52209090",
    "sg:postcode":"2500",
    "sg:province":"Nieder\u00f6sterreich",
    "wof:name":"AWD Beratungszentrum Baden",
    "wof:placetype":"venue"
},
  "geometry": {"coordinates":[16.2330741882,48.0082397461],"type":"Point"}
}