{
  "type": "Feature",
  "properties": {
    "iso:country":"AT",
    "sg:address":"Nr 43",
    "sg:city":"Nappersdorf",
    "sg:orig_category":"Rebschulen",
    "sg:phone":"+43 2953 2339",
    "sg:postcode":"2023",
    "sg:province":"Nieder\u00f6sterreich",
    "wof:name":"Seifried Josef",
    "wof:placetype":"venue"
},
  "geometry": {"coordinates":[16.1849422455,48.6285476685],"type":"Point"}
}