{
  "type": "Feature",
  "properties": {
    "addr:full":"Nr 6 St. Georgen im Attergau Ober\u00f6sterreich 4880",
    "addr:housenumber":"6",
    "addr:postcode":"4880",
    "addr:street":"Nr",
    "iso:country":"AT",
    "sg:address":"Nr 6",
    "sg:city":"St. Georgen im Attergau",
    "sg:orig_category":"Spirituosen / Erzeugung U Gro\u00c3\u0178handel",
    "sg:phone":"+43 4376 676493",
    "sg:postcode":"4880",
    "sg:province":"Ober\u00f6sterreich",
    "wof:name":"Ablinger G\u00fcnther",
    "wof:placetype":"venue"
},
  "geometry": {"coordinates":[13.4907569885,47.9334526062],"type":"Point"}
}