{
  "type": "Feature",
  "properties": {
    "addr:full":"Eisenst\u00e4dter Strasse 1a Breitenbrunn Burgenland 7091",
    "addr:housenumber":"1a",
    "addr:postcode":"7091",
    "addr:street":"Eisenstaedter Strasse",
    "iso:country":"AT",
    "sg:address":"Eisenst\u00e4dter Strasse 1a",
    "sg:city":"Breitenbrunn",
    "sg:classifiers":[
        {
            "category":"Manufacturing",
            "subcategory":"Textiles",
            "type":"Manufacturing & Wholesale Goods"
        }
    ],
    "sg:phone":"+43 2683 5293",
    "sg:postcode":"7091",
    "sg:province":"Burgenland",
    "sg:tags":[
        "curtain",
        "fabric"
    ],
    "wof:name":"Harald Frischmann",
    "wof:placetype":"venue"
},
  "geometry": {"coordinates":[16.7319335938,47.9443626404],"type":"Point"}
}