{
  "type": "Feature",
  "properties": {
    "addr:full":"Oberort 11 Trag\u00f6\u00df-Oberort Steiermark 8612",
    "addr:housenumber":"11",
    "addr:postcode":"8612",
    "addr:street":"Oberort",
    "iso:country":"AT",
    "sg:address":"Oberort 11",
    "sg:city":"Trag\u00f6\u00df-Oberort",
    "sg:orig_category":"Tabaktrafiken",
    "sg:phone":"+43 3868 8670",
    "sg:postcode":"8612",
    "sg:province":"Steiermark",
    "wof:name":"Nicht Franz",
    "wof:placetype":"venue"
},
  "geometry": {"coordinates":[15.0801753998,47.4979553223],"type":"Point"}
}