{
  "type": "Feature",
  "properties": {
    "addr:full":"Hauptstr 108 Trautmannsdorf an der Leitha Nieder\u00f6sterreich 2454",
    "addr:housenumber":"108",
    "addr:postcode":"2454",
    "addr:street":"Hauptstr",
    "iso:country":"AT",
    "sg:address":"Hauptstr 108",
    "sg:city":"Trautmannsdorf an der Leitha",
    "sg:orig_category":"Installationsunternehmen",
    "sg:phone":"+43 2169 22410",
    "sg:postcode":"2454",
    "sg:province":"Nieder\u00f6sterreich",
    "wof:name":"Meran GesmbH",
    "wof:placetype":"venue"
},
  "geometry": {"coordinates":[16.6700134277,48.021068573],"type":"Point"}
}