{
  "type": "Feature",
  "properties": {
    "addr:full":"Binderg 12 Gols Burgenland 7122",
    "addr:housenumber":"12",
    "addr:postcode":"7122",
    "addr:street":"Binderg",
    "iso:country":"AT",
    "sg:address":"Binderg 12",
    "sg:city":"Gols",
    "sg:orig_category":"Friseure U Frisiersalons",
    "sg:phone":"+43 2173 2144",
    "sg:postcode":"7122",
    "sg:province":"Burgenland",
    "wof:name":"M\u00fcller Heinz",
    "wof:placetype":"venue"
},
  "geometry": {"coordinates":[16.9117469788,47.8984069824],"type":"Point"}
}