{
  "type": "Feature",
  "properties": {
    "iso:country":"AT",
    "sg:address":"Nr 6",
    "sg:city":"Oberzeiring",
    "sg:orig_category":"Ingenieurkonsulenten / Zivilingenieure",
    "sg:phone":"+43 4335 7123240",
    "sg:postcode":"8762",
    "sg:province":"Steiermark",
    "wof:name":"Neuber & Co Dipl-Ing",
    "wof:placetype":"venue"
},
  "geometry": {"coordinates":[14.5115098953,47.2576713562],"type":"Point"}
}