{
  "type": "Feature",
  "properties": {
    "addr:full":"Sonnbichl 1 Haiming Tirol 6425",
    "addr:housenumber":"1",
    "addr:postcode":"6425",
    "addr:street":"Sonnbichl;Tirol",
    "iso:country":"AT",
    "sg:address":"Sonnbichl 1",
    "sg:city":"Haiming",
    "sg:orig_category":"Fenster, Fensterrenovierung U -Reparatur",
    "sg:phone":"+43 4352 6688564",
    "sg:postcode":"6425",
    "sg:province":"Tirol",
    "wof:name":"Zoller-Prantl GesmbH & Co KG",
    "wof:placetype":"venue"
},
  "geometry": {"coordinates":[10.8793411255,47.2497138977],"type":"Point"}
}