{
  "type": "Feature",
  "properties": {
    "addr:full":"Percostr 17 Wien Wien 1220",
    "addr:housenumber":"17",
    "addr:postcode":"1220",
    "addr:street":"Percostr",
    "iso:country":"AT",
    "sg:address":"Percostr 17",
    "sg:city":"Wien",
    "sg:classifiers":[
        {
            "category":"Home & Garden",
            "subcategory":"Garden Supply",
            "type":"Retail Goods"
        }
    ],
    "sg:phone":"+43 4312 593600",
    "sg:postcode":"1220",
    "sg:province":"Wien",
    "sg:tags":[
        "schotter",
        "sand",
        "u"
    ],
    "wof:name":"JKI Sand u Kies Deponiebetrieb GesmbH",
    "wof:placetype":"venue"
},
  "geometry": {"coordinates":[16.4667205811,48.2657814026],"type":"Point"}
}