{
  "type": "Feature",
  "properties": {
    "addr:full":"Untermarktstr 17 Telfs Tirol 6410",
    "addr:housenumber":"17",
    "addr:postcode":"6410",
    "addr:street":"Untermarktstr;Tirol",
    "iso:country":"AT",
    "sg:address":"Untermarktstr 17",
    "sg:city":"Telfs",
    "sg:classifiers":[
        {
            "category":"Professional",
            "subcategory":"Computer Services",
            "type":"Services"
        }
    ],
    "sg:phone":"+43 5262 66988",
    "sg:postcode":"6410",
    "sg:province":"Tirol",
    "sg:tags":[
        "software"
    ],
    "wof:name":"H\u00e4rting Rainer Mag",
    "wof:placetype":"venue"
},
  "geometry": {"coordinates":[11.0730829239,47.3069915771],"type":"Point"}
}