{
  "type": "Feature",
  "properties": {
    "addr:full":"Grazer Str 26 Mariazell Steiermark 8630",
    "addr:postcode":"8630",
    "addr:street":"Str 26",
    "iso:country":"AT",
    "sg:address":"Grazer Str 26",
    "sg:city":"Mariazell",
    "sg:orig_category":"Autobusunternehmen",
    "sg:phone":"+43 3882 2550",
    "sg:postcode":"8630",
    "sg:province":"Steiermark",
    "wof:name":"Verkehrsstelle Mariazell",
    "wof:placetype":"venue"
},
  "geometry": {"coordinates":[15.3150787354,47.7707519531],"type":"Point"}
}