{
  "type": "Feature",
  "properties": {
    "addr:full":"Am Kaiserm\u00fchlendamm 2 Wien Wien 1220",
    "addr:housenumber":"2",
    "addr:postcode":"1220",
    "addr:street":"Am Kaisermuehlendamm",
    "iso:country":"AT",
    "sg:address":"Am Kaiserm\u00fchlendamm 2",
    "sg:city":"Wien",
    "sg:orig_category":"Hauptschulen",
    "sg:phone":"+43 1 2636990211",
    "sg:postcode":"1220",
    "sg:province":"Wien",
    "wof:name":"Schulen d Stadt Wien Sportmittelschule",
    "wof:placetype":"venue"
},
  "geometry": {"coordinates":[16.444606781,48.2497138977],"type":"Point"}
}