{
  "type": "Feature",
  "properties": {
    "addr:full":"Nr 1 Kainisch Steiermark 8984",
    "addr:postcode":"8984",
    "addr:street":"Nr",
    "iso:country":"AT",
    "sg:address":"Nr 1",
    "sg:city":"Kainisch",
    "sg:orig_category":"Holzhandel",
    "sg:phone":"+43 4336 242190",
    "sg:postcode":"8984",
    "sg:province":"Steiermark",
    "wof:name":"Grieshofer Friedrich",
    "wof:placetype":"venue"
},
  "geometry": {"coordinates":[13.8338899612,47.5548400879],"type":"Point"}
}