{
  "type": "Feature",
  "properties": {
    "addr:full":"Bahnhofstr 13 Feldkirch Vorarlberg 6800",
    "addr:postcode":"6800",
    "addr:street":"Bahnhofstr 13",
    "iso:country":"AT",
    "sg:address":"Bahnhofstr 13",
    "sg:city":"Feldkirch",
    "sg:orig_category":"Non-Classified Establishments",
    "sg:phone":"+43 5522 3485306",
    "sg:postcode":"6800",
    "sg:province":"Vorarlberg",
    "wof:name":"Schulamt der Di\u00f6zese Feldkirch",
    "wof:placetype":"venue"
},
  "geometry": {"coordinates":[9.5994977951,47.2399330139],"type":"Point"}
}