{
  "type": "Feature",
  "properties": {
    "iso:country":"AT",
    "sg:address":"Rafaltenstrasse 8",
    "sg:city":"Bludenz",
    "sg:classifiers":[
        {
            "category":"Building & Trades",
            "subcategory":"Plumbing",
            "type":"Services"
        }
    ],
    "sg:phone":"+43 5552 69253",
    "sg:postcode":"6700",
    "sg:province":"Vorarlberg",
    "sg:tags":[
        "supraregional",
        "gas"
    ],
    "sg:website":"warum-peter.at",
    "wof:name":"Peter Warum Installationen KEG",
    "wof:placetype":"venue"
},
  "geometry": {"coordinates":[9.8090400696,47.1617584229],"type":"Point"}
}