{
  "type": "Feature",
  "properties": {
    "iso:country":"AT",
    "sg:address":"Brown-Boveri-Str 8",
    "sg:city":"Wiener Neudorf",
    "sg:orig_category":"Ingenieurkonsulenten / Zivilingenieure",
    "sg:phone":"+43 2236 28144",
    "sg:postcode":"2351",
    "sg:province":"Nieder\u00f6sterreich",
    "wof:name":"Begusch Walter Dipl-Ing",
    "wof:placetype":"venue"
},
  "geometry": {"coordinates":[16.3103790283,48.0747413635],"type":"Point"}
}