{
  "type": "Feature",
  "properties": {
    "iso:country":"AT",
    "sg:address":"Bahnsteggasse 5/3",
    "sg:city":"Wien",
    "sg:classifiers":[
        {
            "category":"Home & Garden",
            "subcategory":"Building Materials",
            "type":"Retail Goods"
        }
    ],
    "sg:phone":"+43 1 2857436",
    "sg:postcode":"1210",
    "sg:province":"Wien",
    "sg:tags":[
        "appraisal",
        "damage"
    ],
    "sg:website":"members.aon.at/a.lipa",
    "wof:name":"Ing. Andreas Lipa",
    "wof:placetype":"venue"
},
  "geometry": {"coordinates":[16.3974456787,48.2651557922],"type":"Point"}
}