{
  "type": "Feature",
  "properties": {
    "iso:country":"AT",
    "sg:address":"Stelzhamer Str. 25",
    "sg:city":"Ampflwang im Hausruckwald",
    "sg:classifiers":[
        {
            "category":"Home & Garden",
            "subcategory":"Home Furnishings",
            "type":"Retail Goods"
        }
    ],
    "sg:phone":"+43 4376 752265",
    "sg:postcode":"4843",
    "sg:province":"Ober\u00f6sterreich",
    "sg:tags":[
        "household"
    ],
    "wof:name":"RUDOLF PRENNEIS GMBH & CO KG",
    "wof:placetype":"venue"
},
  "geometry": {"coordinates":[13.5607681274,48.0945701599],"type":"Point"}
}