{
  "type": "Feature",
  "properties": {
    "iso:country":"AT",
    "sg:address":"Tattendorfer Gasse 19",
    "sg:city":"Tribuswinkel",
    "sg:classifiers":[
        {
            "category":"Parking",
            "subcategory":"Lot",
            "type":"Transportation"
        }
    ],
    "sg:phone":"+43 4322 52805500",
    "sg:postcode":"2512",
    "sg:province":"Nieder\u00f6sterreich",
    "sg:tags":[
        "transport",
        "road"
    ],
    "wof:name":"SCHWINGENSCHL\u00d6GEL GES.MBH",
    "wof:placetype":"venue"
},
  "geometry": {"coordinates":[16.2946853638,47.9884490967],"type":"Point"}
}