{
  "type": "Feature",
  "properties": {
    "iso:country":"AT",
    "sg:address":"Wiedner Hauptstr 114/18",
    "sg:city":"Wien",
    "sg:orig_category":"Psychotherapie",
    "sg:phone":"+43 1 5455127",
    "sg:postcode":"1050",
    "sg:province":"Wien",
    "wof:name":"Till Wolfgang DDr",
    "wof:placetype":"venue"
},
  "geometry": {"coordinates":[16.3621711731,48.1851539612],"type":"Point"}
}