{
  "type": "Feature",
  "properties": {
    "addr:full":"Ableidingerstr 19 Enzersfeld Nieder\u00f6sterreich 2202",
    "addr:housenumber":"19",
    "addr:postcode":"2202",
    "addr:street":"Ableidingerstr",
    "iso:country":"AT",
    "sg:address":"Ableidingerstr 19",
    "sg:city":"Enzersfeld",
    "sg:orig_category":"Banken U Sparkassen",
    "sg:phone":"+43 2262 673131",
    "sg:postcode":"2202",
    "sg:province":"Nieder\u00f6sterreich",
    "wof:name":"Raiffeisenbank Korneuburg regGenmbH",
    "wof:placetype":"venue"
},
  "geometry": {"coordinates":[16.4259529114,48.3625793457],"type":"Point"}
}