{
  "type": "Feature",
  "properties": {
    "addr:full":"Robert-Bach-G 51 Mauerbach Nieder\u00f6sterreich 3001",
    "addr:housenumber":"51",
    "addr:postcode":"3001",
    "addr:street":"Robert-Bach-G",
    "iso:country":"AT",
    "sg:address":"Robert-Bach-G 51",
    "sg:city":"Mauerbach",
    "sg:orig_category":"Musikgruppen",
    "sg:phone":"+43 676 5348129",
    "sg:postcode":"3001",
    "sg:province":"Nieder\u00f6sterreich",
    "wof:name":"Bach Katharina-live an der Hammondorgel-spielt auf Ihren Festen",
    "wof:placetype":"venue"
},
  "geometry": {"coordinates":[16.1870937347,48.2357025146],"type":"Point"}
}