{
  "type": "Feature",
  "properties": {
    "addr:full":"Gebhard-Wei\u00df-G 3 Bregenz Vorarlberg 6900",
    "addr:housenumber":"3",
    "addr:postcode":"6900",
    "addr:street":"Gebhard-Weiss-G",
    "iso:country":"AT",
    "sg:address":"Gebhard-Wei\u00df-G 3",
    "sg:city":"Bregenz",
    "sg:orig_category":"Friseure U Frisiersalons",
    "sg:phone":"+43 4355 7444884",
    "sg:postcode":"6900",
    "sg:province":"Vorarlberg",
    "wof:name":"Christian",
    "wof:placetype":"venue"
},
  "geometry": {"coordinates":[9.7476921082,47.5038032532],"type":"Point"}
}