{
  "type": "Feature",
  "properties": {
    "iso:country":"AT",
    "sg:address":"Kreuzwirtg 2",
    "sg:city":"Klagenfurt",
    "sg:orig_category":"Zimmereien",
    "sg:phone":"+43 463 413030",
    "sg:postcode":"9020",
    "sg:province":"K\u00e4rnten",
    "wof:name":"Ebner Zimmerei Holzbau KG",
    "wof:placetype":"venue"
},
  "geometry": {"coordinates":[14.3151407242,46.641494751],"type":"Point"}
}