{
  "type": "Feature",
  "properties": {
    "iso:country":"AT",
    "sg:address":"Liechtensteiner Str 137a",
    "sg:city":"Feldkirch",
    "sg:orig_category":"Wechselstuben",
    "sg:phone":"+43 5522 72752",
    "sg:postcode":"6800",
    "sg:province":"Vorarlberg",
    "wof:name":"\u00f6AMTC-Wechselstube Tisis - Grenzstation",
    "wof:placetype":"venue"
},
  "geometry": {"coordinates":[9.5967845917,47.2381515503],"type":"Point"}
}