{
  "type": "Feature",
  "properties": {
    "addr:full":"Pfarrgasse 5a Wels Ober\u00f6sterreich 4600",
    "addr:housenumber":"5a",
    "addr:postcode":"4600",
    "addr:street":"Pfarrgasse;Oberoesterreich",
    "iso:country":"AT",
    "sg:address":"Pfarrgasse 5a",
    "sg:city":"Wels",
    "sg:classifiers":[
        {
            "category":"Home & Garden",
            "subcategory":"Furniture",
            "type":"Retail Goods"
        }
    ],
    "sg:phone":"+43 7242 47230",
    "sg:postcode":"4600",
    "sg:province":"Ober\u00f6sterreich",
    "sg:tags":[
        "designer"
    ],
    "sg:website":"wohnform-schuerz.at",
    "wof:name":"Wohnform Sch\u00fcrz - Marschner Ges.m.b.H. & Co KG",
    "wof:placetype":"venue"
},
  "geometry": {"coordinates":[14.0261945724,48.1597747803],"type":"Point"}
}