{
  "type": "Feature",
  "properties": {
    "addr:full":"Trujeg 13A Tarrenz Tirol 6464",
    "addr:housenumber":"13a",
    "addr:postcode":"6464",
    "addr:street":"Trujeg;Tirol",
    "iso:country":"AT",
    "sg:address":"Trujeg 13A",
    "sg:city":"Tarrenz",
    "sg:orig_category":"Volksschulen",
    "sg:phone":"+43 5412 66085",
    "sg:postcode":"6464",
    "sg:province":"Tirol",
    "wof:name":"Volksschule",
    "wof:placetype":"venue"
},
  "geometry": {"coordinates":[10.7621488571,47.26537323],"type":"Point"}
}