{
  "type": "Feature",
  "properties": {
    "addr:full":"Linzer Str 260 Wels Ober\u00f6sterreich 4600",
    "addr:housenumber":"260",
    "addr:postcode":"4600",
    "addr:street":"Linzer Str;Oberoesterreich",
    "iso:country":"AT",
    "sg:address":"Linzer Str 260",
    "sg:city":"Wels",
    "sg:orig_category":"Metallbe- U -Verarbeitung",
    "sg:phone":"+43 4372 42930930",
    "sg:postcode":"4600",
    "sg:province":"Ober\u00f6sterreich",
    "wof:name":"LASER & more Edelstahl KomponentenfertigungsgesmbH",
    "wof:placetype":"venue"
},
  "geometry": {"coordinates":[14.0672092438,48.1810493469],"type":"Point"}
}