{
  "type": "Feature",
  "properties": {
    "addr:full":"Escheng 3 Leopoldsdorf Nieder\u00f6sterreich 2333",
    "addr:housenumber":"3",
    "addr:postcode":"2333",
    "addr:street":"Escheng",
    "iso:country":"AT",
    "sg:address":"Escheng 3",
    "sg:city":"Leopoldsdorf",
    "sg:orig_category":"Zahntechnische Laboratorien",
    "sg:phone":"+43 4322 3543633",
    "sg:postcode":"2333",
    "sg:province":"Nieder\u00f6sterreich",
    "wof:name":"Steinbach Gerhard",
    "wof:placetype":"venue"
},
  "geometry": {"coordinates":[16.3903770447,48.1123313904],"type":"Point"}
}