{
  "type": "Feature",
  "properties": {
    "addr:full":"Nr 90 Gro\u00dfarl Salzburg 5611",
    "addr:postcode":"5611",
    "addr:street":"Nr 90;Salzburg",
    "iso:country":"AT",
    "sg:address":"Nr 90",
    "sg:city":"Gro\u00dfarl",
    "sg:orig_category":"Banken U Sparkassen",
    "sg:phone":"+43 6414 2390",
    "sg:postcode":"5611",
    "sg:province":"Salzburg",
    "wof:name":"Raiffeisenbank Gro\u00dfarl H\u00fcttschlag regGenmbH",
    "wof:placetype":"venue"
},
  "geometry": {"coordinates":[-114.0853424072,47.1626281738],"type":"Point"}
}