{
  "type": "Feature",
  "properties": {
    "addr:full":"Bernsteinstrasse 40 St. Georgen an der Gusen Ober\u00f6sterreich 4222",
    "addr:housenumber":"40",
    "addr:postcode":"4222",
    "addr:street":"Bernsteinstrasse",
    "iso:country":"AT",
    "sg:address":"Bernsteinstrasse 40",
    "sg:city":"St. Georgen an der Gusen",
    "sg:classifiers":[
        {
            "category":"Personal",
            "subcategory":"Hair Removal",
            "type":"Services"
        }
    ],
    "sg:phone":"+43 7237 2333",
    "sg:postcode":"4222",
    "sg:province":"Ober\u00f6sterreich",
    "sg:tags":[
        "brush"
    ],
    "wof:name":"HAGON Import-Export-Handelsges.m.b.H.",
    "wof:placetype":"venue"
},
  "geometry": {"coordinates":[14.4150066376,48.273021698],"type":"Point"}
}