{
  "type": "Feature",
  "properties": {
    "addr:full":"Bauhofpl 2 Mureck Steiermark 8480",
    "addr:housenumber":"2",
    "addr:postcode":"8480",
    "addr:street":"Bauhofpl",
    "iso:country":"AT",
    "sg:address":"Bauhofpl 2",
    "sg:city":"Mureck",
    "sg:orig_category":"Non-Classified Establishments",
    "sg:phone":"+43 3472 2435",
    "sg:postcode":"8480",
    "sg:province":"Steiermark",
    "wof:name":"Stra\u00dfenmeisterei Mureck Bundes- und Landesstra\u00dfenverwaltung",
    "wof:placetype":"venue"
},
  "geometry": {"coordinates":[15.7788009644,46.7085800171],"type":"Point"}
}