{
  "type": "Feature",
  "properties": {
    "iso:country":"AT",
    "sg:address":"Universit\u00e4tsstr 24",
    "sg:city":"Innsbruck",
    "sg:orig_category":"Physiotherapie",
    "sg:phone":"+43 512 575320",
    "sg:postcode":"6020",
    "sg:province":"Tirol",
    "wof:name":"Scharfetter Barbara Dipl-PT",
    "wof:placetype":"venue"
},
  "geometry": {"coordinates":[11.4003133774,47.2689437866],"type":"Point"}
}