{
  "type": "Feature",
  "properties": {
    "addr:full":"Augustinerg 9a Salzburg Salzburg 5020",
    "addr:housenumber":"9a",
    "addr:postcode":"5020",
    "addr:street":"Augustinerg;Salzburg",
    "iso:country":"AT",
    "sg:address":"Augustinerg 9a",
    "sg:city":"Salzburg",
    "sg:orig_category":"Psychologen",
    "sg:phone":"+43 664 4010019",
    "sg:postcode":"5020",
    "sg:province":"Salzburg",
    "wof:name":"Hutterer Astrid Mag",
    "wof:placetype":"venue"
},
  "geometry": {"coordinates":[13.0320749283,47.8028182983],"type":"Point"}
}