{
  "type": "Feature",
  "properties": {
    "addr:full":"Gerichtsg 24-26 Wien Wien 1210",
    "addr:postcode":"24-26;1210",
    "iso:country":"AT",
    "sg:address":"Gerichtsg 24-26",
    "sg:city":"Wien",
    "sg:orig_category":"Werbegestalter",
    "sg:phone":"+43 1 4090862",
    "sg:postcode":"1210",
    "sg:province":"Wien",
    "wof:name":"Dittrich Manfred",
    "wof:placetype":"venue"
},
  "geometry": {"coordinates":[16.3998813629,48.2637786865],"type":"Point"}
}