{
  "type": "Feature",
  "properties": {
    "addr:full":"Hornweg 17 Kitzb\u00fchel Tirol 6370",
    "addr:housenumber":"17",
    "addr:postcode":"6370",
    "addr:street":"Hornweg;Tirol",
    "iso:country":"AT",
    "sg:address":"Hornweg 17",
    "sg:city":"Kitzb\u00fchel",
    "sg:orig_category":"Pensionen / Privatzimmer",
    "sg:phone":"+43 5356 62312",
    "sg:postcode":"6370",
    "sg:province":"Tirol",
    "wof:name":"Pension Rainhof",
    "wof:placetype":"venue"
},
  "geometry": {"coordinates":[12.3932504654,47.4495735168],"type":"Point"}
}