{
  "type": "Feature",
  "properties": {
    "iso:country":"AT",
    "sg:address":"Hauptstr 10",
    "sg:city":"Linz",
    "sg:orig_category":"Architekten",
    "sg:phone":"+43 732 717191",
    "sg:postcode":"4040",
    "sg:province":"Ober\u00f6sterreich",
    "wof:name":"Hagenauer Klaus Dipl-Ing Arch - Moser Herbert Dipl-Ing",
    "wof:placetype":"venue"
},
  "geometry": {"coordinates":[14.283741951,48.310295105],"type":"Point"}
}