{
  "type": "Feature",
  "properties": {
    "addr:full":"Arlbergstr 57 St. Anton am Arlberg Tirol 6580",
    "addr:housenumber":"57",
    "addr:postcode":"6580",
    "addr:street":"Arlbergstr",
    "iso:country":"AT",
    "sg:address":"Arlbergstr 57",
    "sg:city":"St. Anton am Arlberg",
    "sg:orig_category":"Appartements / Ferienwohnungen",
    "sg:phone":"+43 5446 3407",
    "sg:postcode":"6580",
    "sg:province":"Tirol",
    "wof:name":"Landhaus Klimmer",
    "wof:placetype":"venue"
},
  "geometry": {"coordinates":[10.2654380798,47.1276283264],"type":"Point"}
}