{
  "type": "Feature",
  "properties": {
    "addr:full":"Vorderstadt 33 Kitzb\u00fchel Tirol 6370",
    "addr:housenumber":"33",
    "addr:postcode":"6370",
    "addr:street":"Vorderstadt;Tirol",
    "iso:country":"AT",
    "sg:address":"Vorderstadt 33",
    "sg:city":"Kitzb\u00fchel",
    "sg:orig_category":"Drogerien",
    "sg:phone":"+43 5356 62796",
    "sg:postcode":"6370",
    "sg:province":"Tirol",
    "wof:name":"Drogerie im Pfleghof Feinparfumerie Hubert Bodner GesmbH",
    "wof:placetype":"venue"
},
  "geometry": {"coordinates":[12.3917331696,47.4459991455],"type":"Point"}
}