{
  "type": "Feature",
  "properties": {
    "addr:full":"Hauptstr 34 Gr\u00fcnburg Ober\u00f6sterreich 4594",
    "addr:housenumber":"34",
    "addr:postcode":"4594",
    "addr:street":"Hauptstr;Oberoesterreich",
    "iso:country":"AT",
    "sg:address":"Hauptstr 34",
    "sg:city":"Gr\u00fcnburg",
    "sg:orig_category":"Gemeinden",
    "sg:phone":"+43 7257 72550",
    "sg:postcode":"4594",
    "sg:province":"Ober\u00f6sterreich",
    "wof:name":"Gemeindeamt Gr\u00fcnburg",
    "wof:placetype":"venue"
},
  "geometry": {"coordinates":[14.2626285553,47.9700469971],"type":"Point"}
}