{
  "type": "Feature",
  "properties": {
    "addr:full":"Flughafen Wien Schwechat Obj 263/Zimmer 232 Wien Wien 1300",
    "addr:housenumber":"263 / zimmer 232",
    "addr:postcode":"1300",
    "addr:street":"Obj",
    "iso:country":"AT",
    "sg:address":"Flughafen Wien Schwechat Obj 263/Zimmer 232",
    "sg:city":"Wien",
    "sg:orig_category":"Speditionen",
    "sg:phone":"+43 4317 0073541",
    "sg:postcode":"1300",
    "sg:province":"Wien",
    "wof:name":"Nippon Express GmbH",
    "wof:placetype":"venue"
},
  "geometry": {"coordinates":[16.5561008453,48.1137504578],"type":"Point"}
}