{
  "type": "Feature",
  "properties": {
    "addr:full":"Hauptschulstr 5 Bad Gastein Salzburg 5640",
    "addr:housenumber":"5",
    "addr:postcode":"5640",
    "addr:street":"Hauptschulstr;Salzburg",
    "iso:country":"AT",
    "sg:address":"Hauptschulstr 5",
    "sg:city":"Bad Gastein",
    "sg:orig_category":"Musikunterricht",
    "sg:phone":"+43 6434 2912",
    "sg:postcode":"5640",
    "sg:province":"Salzburg",
    "wof:name":"Salzburger Musikschulwerk",
    "wof:placetype":"venue"
},
  "geometry": {"coordinates":[13.1328420639,47.1075248718],"type":"Point"}
}