{
  "type": "Feature",
  "properties": {
    "addr:full":"Fachschulstrasse 6 Fulpmes Tirol 6166",
    "addr:housenumber":"6",
    "addr:postcode":"6166",
    "addr:street":"Fachschulstrasse;Tirol",
    "iso:country":"AT",
    "sg:address":"Fachschulstrasse 6",
    "sg:city":"Fulpmes",
    "sg:orig_category":"Glass-Fibre Reinforced Plastic Grp Mouldings",
    "sg:phone":"+43 5225 623790",
    "sg:postcode":"6166",
    "sg:province":"Tirol",
    "sg:website":"brandauer.at",
    "wof:name":"Ing. Raimund Brandauer GmbH Tirol-Tools Werkzeuge und Kunststoffteile",
    "wof:placetype":"venue"
},
  "geometry": {"coordinates":[11.3477258682,47.1557846069],"type":"Point"}
}