{
  "type": "Feature",
  "properties": {
    "addr:full":"Hauptstr 13 Lutzmannsburg Burgenland 7361",
    "addr:housenumber":"13",
    "addr:postcode":"7361",
    "addr:street":"Hauptstr",
    "iso:country":"AT",
    "sg:address":"Hauptstr 13",
    "sg:city":"Lutzmannsburg",
    "sg:orig_category":"Autobusunternehmen",
    "sg:phone":"+43 4326 1587231",
    "sg:postcode":"7361",
    "sg:province":"Burgenland",
    "wof:name":"Mersich Emmerich, Rudolf Mersich u Peter Mersich GesbR",
    "wof:placetype":"venue"
},
  "geometry": {"coordinates":[16.6337928772,47.4634628296],"type":"Point"}
}