{
  "type": "Feature",
  "properties": {
    "addr:full":"Franz-Josef-Str 21 Maria Enzersdorf Nieder\u00f6sterreich 2344",
    "addr:housenumber":"21",
    "addr:postcode":"2344",
    "addr:street":"Franz-Josef-Str",
    "iso:country":"AT",
    "sg:address":"Franz-Josef-Str 21",
    "sg:city":"Maria Enzersdorf",
    "sg:orig_category":"Autohandel",
    "sg:phone":"+43 2236 425200",
    "sg:postcode":"2344",
    "sg:province":"Nieder\u00f6sterreich",
    "wof:name":"Autohaus Robert Stipschitz GmbH",
    "wof:placetype":"venue"
},
  "geometry": {"coordinates":[16.2867641449,48.0972518921],"type":"Point"}
}