{
  "type": "Feature",
  "properties": {
    "addr:full":"Kanalg 7 Dornbirn Vorarlberg 6850",
    "addr:housenumber":"7",
    "addr:postcode":"6850",
    "addr:street":"Kanalg",
    "iso:country":"AT",
    "sg:address":"Kanalg 7",
    "sg:city":"Dornbirn",
    "sg:orig_category":"Automatisierungstechnik",
    "sg:phone":"+43 5572 206050",
    "sg:postcode":"6850",
    "sg:province":"Vorarlberg",
    "wof:name":"Octa development group Schmedler KEG",
    "wof:placetype":"venue"
},
  "geometry": {"coordinates":[9.7437801361,47.4131889343],"type":"Point"}
}