{
  "type": "Feature",
  "properties": {
    "iso:country":"AT",
    "sg:address":"Burgg 121/17",
    "sg:city":"Wien",
    "sg:classifiers":[
        {
            "category":"Government",
            "subcategory":"Post Office",
            "type":"Public Place"
        }
    ],
    "sg:phone":"+43 4315 232970",
    "sg:postcode":"1070",
    "sg:province":"Wien",
    "sg:tags":[
        "yoga"
    ],
    "wof:name":"Yoga nach B.K.S. Iyengar - Yoga Zentrum - Mag. Klaus Neyer",
    "wof:placetype":"venue"
},
  "geometry": {"coordinates":[16.3382225037,48.204082489],"type":"Point"}
}