{
  "type": "Feature",
  "properties": {
    "addr:full":"Linzer Str 23 Braunau am Inn Ober\u00f6sterreich 5280",
    "addr:housenumber":"23",
    "addr:postcode":"5280",
    "addr:street":"Linzer Str",
    "iso:country":"AT",
    "sg:address":"Linzer Str 23",
    "sg:city":"Braunau am Inn",
    "sg:orig_category":"Friseure U Frisiersalons",
    "sg:phone":"+43 4377 2263041",
    "sg:postcode":"5280",
    "sg:province":"Ober\u00f6sterreich",
    "wof:name":"Dunhofer Johannes",
    "wof:placetype":"venue"
},
  "geometry": {"coordinates":[13.0372142792,48.2594413757],"type":"Point"}
}