{
  "type": "Feature",
  "properties": {
    "iso:country":"AT",
    "sg:address":"Biberweg 24",
    "sg:city":"Linz",
    "sg:orig_category":"Bibliotheken",
    "sg:phone":"+43 732 321173",
    "sg:postcode":"4030",
    "sg:province":"Ober\u00f6sterreich",
    "wof:name":"Stadtbibliothek Linz - Pichling",
    "wof:placetype":"venue"
},
  "geometry": {"coordinates":[14.3660707474,48.2509803772],"type":"Point"}
}