{
  "type": "Feature",
  "properties": {
    "addr:full":"K\u00f6nigsb\u00fchelstr 33 Breitenfurt Nieder\u00f6sterreich 2384",
    "addr:housenumber":"33",
    "addr:postcode":"2384",
    "addr:street":"Koenigsbuehelstr",
    "iso:country":"AT",
    "sg:address":"K\u00f6nigsb\u00fchelstr 33",
    "sg:city":"Breitenfurt",
    "sg:orig_category":"Forstverwaltungen",
    "sg:phone":"+43 2239 2266",
    "sg:postcode":"2384",
    "sg:province":"Nieder\u00f6sterreich",
    "wof:name":"\u00d6sterreichische Bundesforste AG - Forstbetrieb",
    "wof:placetype":"venue"
},
  "geometry": {"coordinates":[16.2043056488,48.1380386353],"type":"Point"}
}