{
  "type": "Feature",
  "properties": {
    "addr:full":"Colloredog 24 Wien Wien 1180",
    "addr:housenumber":"24",
    "addr:postcode":"1180",
    "addr:street":"Colloredog",
    "iso:country":"AT",
    "sg:address":"Colloredog 24",
    "sg:city":"Wien",
    "sg:orig_category":"Ingenieurkonsulenten / Zivilingenieure",
    "sg:phone":"+43 1 47047210",
    "sg:postcode":"1180",
    "sg:province":"Wien",
    "wof:name":"Meisterhofer Hermann G Dr",
    "wof:placetype":"venue"
},
  "geometry": {"coordinates":[16.3422737122,48.2328605652],"type":"Point"}
}