{
  "type": "Feature",
  "properties": {
    "addr:full":"Itzlinger Hauptstr 57 Salzburg Salzburg 5020",
    "addr:housenumber":"57",
    "addr:postcode":"5020",
    "addr:street":"Itzlinger Hauptstr;Salzburg",
    "iso:country":"AT",
    "sg:address":"Itzlinger Hauptstr 57",
    "sg:city":"Salzburg",
    "sg:orig_category":"Personalbereitstellung",
    "sg:phone":"+43 662 451080",
    "sg:postcode":"5020",
    "sg:province":"Salzburg",
    "sg:website":"www.fachkraefte.net",
    "wof:name":"team flexibel Fachkr\u00e4fteservice GmbH",
    "wof:placetype":"venue"
},
  "geometry": {"coordinates":[13.0413255692,47.8240623474],"type":"Point"}
}