{
  "type": "Feature",
  "properties": {
    "addr:full":"Antonsg 16 Baden Nieder\u00f6sterreich 2500",
    "addr:housenumber":"16",
    "addr:postcode":"2500",
    "addr:street":"Antonsg;Niederoesterreich",
    "iso:country":"AT",
    "sg:address":"Antonsg 16",
    "sg:city":"Baden",
    "sg:orig_category":"Chemikalien",
    "sg:phone":"+43 2252 224660",
    "sg:postcode":"2500",
    "sg:province":"Nieder\u00f6sterreich",
    "wof:name":"Kuntner & Co KG",
    "wof:placetype":"venue"
},
  "geometry": {"coordinates":[16.2394504547,48.0093841553],"type":"Point"}
}