{
  "type": "Feature",
  "properties": {
    "iso:country":"AT",
    "sg:address":"Gewerbepark 28",
    "sg:city":"F\u00fcgen",
    "sg:orig_category":"Installationsunternehmen",
    "sg:phone":"+43 5288 623430",
    "sg:postcode":"6263",
    "sg:province":"Tirol",
    "wof:name":"Baumann Johann GmbH & Co KG",
    "wof:placetype":"venue"
},
  "geometry": {"coordinates":[11.8676013947,47.3273391724],"type":"Point"}
}