{
  "type": "Feature",
  "properties": {
    "iso:country":"AT",
    "sg:address":"Innerfahrafeld 1",
    "sg:city":"Hohenberg",
    "sg:classifiers":[
        {
            "category":"Utilities",
            "subcategory":"Electric",
            "type":"Services"
        }
    ],
    "sg:phone":"+43 2767 73570",
    "sg:postcode":"3192",
    "sg:province":"Nieder\u00f6sterreich",
    "sg:tags":[
        "engineering",
        "hydraulic"
    ],
    "wof:name":"Andreas Wiesbauer GmbH",
    "wof:placetype":"venue"
},
  "geometry": {"coordinates":[15.6023874283,47.93409729],"type":"Point"}
}