{
  "type": "Feature",
  "properties": {
    "iso:country":"AT",
    "sg:address":"Kogl 14",
    "sg:city":"Kirchham",
    "sg:orig_category":"Transportunternehmen",
    "sg:phone":"+43 76192331",
    "sg:postcode":"4656",
    "sg:province":"Ober\u00f6sterreich",
    "wof:name":"Starzinger Anton Intern G\u00fcter Ferntransporte GesmbH",
    "wof:placetype":"venue"
},
  "geometry": {"coordinates":[13.9046440125,47.9466972351],"type":"Point"}
}