{
  "type": "Feature",
  "properties": {
    "addr:full":"Anna-Neumann-Str 24 Murau Steiermark 8850",
    "addr:housenumber":"24",
    "addr:postcode":"8850",
    "addr:street":"Anna-Neumann-Str",
    "iso:country":"AT",
    "sg:address":"Anna-Neumann-Str 24",
    "sg:city":"Murau",
    "sg:classifiers":[
        {
            "category":"Retail",
            "subcategory":"Event Space",
            "type":"Services"
        }
    ],
    "sg:phone":"+43 4335 322127",
    "sg:postcode":"8850",
    "sg:province":"Steiermark",
    "sg:tags":[
        "hand-",
        "u",
        "fu\u00c3\u0178pflege"
    ],
    "wof:name":"Karner Christine",
    "wof:placetype":"venue"
},
  "geometry": {"coordinates":[14.1683692932,47.1103401184],"type":"Point"}
}