{
  "type": "Feature",
  "properties": {
    "addr:full":"Paradeiserg 18/1 Klagenfurt K\u00e4rnten 9020",
    "addr:housenumber":"18 / 1",
    "addr:postcode":"9020",
    "addr:street":"Paradeiserg;Kaernten",
    "iso:country":"AT",
    "sg:address":"Paradeiserg 18/1",
    "sg:city":"Klagenfurt",
    "sg:orig_category":"Friseure U Frisiersalons",
    "sg:phone":"+43 463 515952",
    "sg:postcode":"9020",
    "sg:province":"K\u00e4rnten",
    "wof:name":"Frisiersalon Heidi",
    "wof:placetype":"venue"
},
  "geometry": {"coordinates":[14.3111276627,46.6235313416],"type":"Point"}
}