{
  "type": "Feature",
  "properties": {
    "iso:country":"AT",
    "sg:address":"Hauptstr. 28",
    "sg:city":"Admont",
    "sg:classifiers":[
        {
            "category":"Farming",
            "subcategory":"Livestock Farm",
            "type":"Manufacturing & Wholesale Goods"
        }
    ],
    "sg:phone":"+43 4336 132403",
    "sg:postcode":"8911",
    "sg:province":"Steiermark",
    "sg:tags":[
        "agriculture"
    ],
    "wof:name":"STEIERM.LANDESFORSTE FORSTDIREKTION ADMONT",
    "wof:placetype":"venue"
},
  "geometry": {"coordinates":[14.4607601166,47.5766487122],"type":"Point"}
}