{
  "type": "Feature",
  "properties": {
    "addr:full":"Siebenbrunneng 48 Wien Wien 1050",
    "addr:housenumber":"48",
    "addr:postcode":"1050",
    "addr:street":"Siebenbrunneng",
    "iso:country":"AT",
    "sg:address":"Siebenbrunneng 48",
    "sg:city":"Wien",
    "sg:orig_category":"Fenster",
    "sg:phone":"+43 4367 65052190",
    "sg:postcode":"1050",
    "sg:province":"Wien",
    "wof:name":"Fensterreinigung Kellermayr",
    "wof:placetype":"venue"
},
  "geometry": {"coordinates":[16.354549408,48.1859703064],"type":"Point"}
}