{
  "type": "Feature",
  "properties": {
    "addr:full":"Neuhofenstr 37 Gmunden Ober\u00f6sterreich 4810",
    "addr:housenumber":"37",
    "addr:postcode":"4810",
    "addr:street":"Neuhofenstr;Oberoesterreich",
    "iso:country":"AT",
    "sg:address":"Neuhofenstr 37",
    "sg:city":"Gmunden",
    "sg:orig_category":"Forstbedarf",
    "sg:phone":"+43 761277464",
    "sg:postcode":"4810",
    "sg:province":"Ober\u00f6sterreich",
    "wof:name":"Interforst HandelsgesmbH",
    "wof:placetype":"venue"
},
  "geometry": {"coordinates":[13.7851696014,47.9310188293],"type":"Point"}
}