{
  "type": "Feature",
  "properties": {
    "iso:country":"AT",
    "sg:address":"Nr 210",
    "sg:city":"Bad Eisenkappel",
    "sg:orig_category":"Zimmereien",
    "sg:phone":"+43 4238 2150",
    "sg:postcode":"9135",
    "sg:province":"K\u00e4rnten",
    "wof:name":"Klaura Holzbau GesmbH Nfg KG",
    "wof:placetype":"venue"
},
  "geometry": {"coordinates":[14.5931138992,46.4872512817],"type":"Point"}
}