{
  "type": "Feature",
  "properties": {
    "iso:country":"AT",
    "sg:address":"Goldschlagstr 103/2",
    "sg:city":"Wien",
    "sg:orig_category":"Tauschvermittler",
    "sg:phone":"+43 1 9245105",
    "sg:postcode":"1150",
    "sg:province":"Wien",
    "wof:name":"Gally Roman Tauschzentrale",
    "wof:placetype":"venue"
},
  "geometry": {"coordinates":[16.3170642853,48.1942939758],"type":"Point"}
}