{
  "type": "Feature",
  "properties": {
    "addr:full":"Rohrerstr 43 Zell am Ziller Tirol 6280",
    "addr:housenumber":"43",
    "addr:postcode":"6280",
    "addr:street":"Rohrerstr;Tirol",
    "iso:country":"AT",
    "sg:address":"Rohrerstr 43",
    "sg:city":"Zell am Ziller",
    "sg:orig_category":"Pensionen / Privatzimmer",
    "sg:phone":"+43 5282 7131",
    "sg:postcode":"6280",
    "sg:province":"Tirol",
    "wof:name":"Fremdenpension Daum",
    "wof:placetype":"venue"
},
  "geometry": {"coordinates":[11.8924589157,47.2361869812],"type":"Point"}
}