{
  "type": "Feature",
  "properties": {
    "iso:country":"AT",
    "sg:address":"Bernhardtg 4",
    "sg:city":"Spittal an der Drau",
    "sg:orig_category":"Blumeneinzelhandel",
    "sg:phone":"+43 4347 6233988",
    "sg:postcode":"9800",
    "sg:province":"K\u00e4rnten",
    "wof:name":"Stranner Angelika Blumenboutique",
    "wof:placetype":"venue"
},
  "geometry": {"coordinates":[13.4968900681,46.7977409363],"type":"Point"}
}