{
  "type": "Feature",
  "properties": {
    "iso:country":"AT",
    "sg:address":"Hilprechtsham 5",
    "sg:city":"Kirchberg",
    "sg:orig_category":"Werbegrafik- U Grafik-Design",
    "sg:phone":"+43 7747 40101",
    "sg:postcode":"5232",
    "sg:province":"Ober\u00f6sterreich",
    "wof:name":"Atelier Dennis de Kort",
    "wof:placetype":"venue"
},
  "geometry": {"coordinates":[13.1004400253,48.0395202637],"type":"Point"}
}