{
  "type": "Feature",
  "properties": {
    "addr:full":"Salzburger Str 67 Wels Ober\u00f6sterreich 4600",
    "addr:housenumber":"67",
    "addr:postcode":"4600",
    "addr:street":"Salzburger Str;Oberoesterreich",
    "iso:country":"AT",
    "sg:address":"Salzburger Str 67",
    "sg:city":"Wels",
    "sg:orig_category":"Restaurants: Italienisch",
    "sg:phone":"+43 7242 51114",
    "sg:postcode":"4600",
    "sg:province":"Ober\u00f6sterreich",
    "wof:name":"Pizzeria - Rimi",
    "wof:placetype":"venue"
},
  "geometry": {"coordinates":[14.0060491562,48.1567306519],"type":"Point"}
}