{
  "type": "Feature",
  "properties": {
    "addr:full":"M\u00fchlg 11 Berndorf Nieder\u00f6sterreich 2560",
    "addr:housenumber":"11",
    "addr:postcode":"2560",
    "addr:street":"Muehlg",
    "iso:country":"AT",
    "sg:address":"M\u00fchlg 11",
    "sg:city":"Berndorf",
    "sg:orig_category":"Erdarbeiten",
    "sg:phone":"+43 2672 83347",
    "sg:postcode":"2560",
    "sg:province":"Nieder\u00f6sterreich",
    "wof:name":"Birbamer Gerald",
    "wof:placetype":"venue"
},
  "geometry": {"coordinates":[16.1051998138,47.8947486877],"type":"Point"}
}