{
  "type": "Feature",
  "properties": {
    "addr:full":"Brown-Boveri-Str 6 Wiener Neudorf Nieder\u00f6sterreich 2351",
    "addr:housenumber":"6",
    "addr:postcode":"2351",
    "addr:street":"Brown-Boveri-Str",
    "iso:country":"AT",
    "sg:address":"Brown-Boveri-Str 6",
    "sg:city":"Wiener Neudorf",
    "sg:orig_category":"Finanz- U Wirtschaftsberatung",
    "sg:phone":"+43 4322 36869494",
    "sg:postcode":"2351",
    "sg:province":"Nieder\u00f6sterreich",
    "wof:name":"Lehner B\u00fcrobetriebs KEG",
    "wof:placetype":"venue"
},
  "geometry": {"coordinates":[16.3105869293,48.0755271912],"type":"Point"}
}