{
  "type": "Feature",
  "properties": {
    "iso:country":"AT",
    "sg:address":"Badg 6",
    "sg:city":"Kritzendorf",
    "sg:orig_category":"Transportunternehmen",
    "sg:phone":"+43 4322 4330323",
    "sg:postcode":"3420",
    "sg:province":"Nieder\u00f6sterreich",
    "wof:name":"PONZER Transport- u Transportvermittlung GmbH",
    "wof:placetype":"venue"
},
  "geometry": {"coordinates":[16.3018398285,48.3276901245],"type":"Point"}
}