{
  "type": "Feature",
  "properties": {
    "addr:full":"Brucker Str. 21  Gratkorn Steiermark 8101",
    "addr:postcode":"8101",
    "addr:street":"Str. 21",
    "iso:country":"AT",
    "sg:address":"Brucker Str. 21 ",
    "sg:city":"Gratkorn",
    "sg:classifiers":[
        {
            "category":"Manufacturing",
            "subcategory":"Paper Products",
            "type":"Manufacturing & Wholesale Goods"
        }
    ],
    "sg:phone":"+43 4331 242010",
    "sg:postcode":"8101",
    "sg:province":"Steiermark",
    "sg:tags":[
        "cardboard"
    ],
    "wof:name":"SAPPI PAPIERHOLDING AG",
    "wof:placetype":"venue"
},
  "geometry": {"coordinates":[15.3357152939,47.1350021362],"type":"Point"}
}