{
  "type": "Feature",
  "properties": {
    "iso:country":"AT",
    "sg:address":"Vordernberger Str 74",
    "sg:city":"Eisenerz",
    "sg:orig_category":"Autoreparatur",
    "sg:phone":"+43 3848 60002",
    "sg:postcode":"8790",
    "sg:province":"Steiermark",
    "wof:name":"AUTO Ritzinger",
    "wof:placetype":"venue"
},
  "geometry": {"coordinates":[14.9070196152,47.5415344238],"type":"Point"}
}