{
  "type": "Feature",
  "properties": {
    "addr:full":"Im Markt 7 Gaming Nieder\u00f6sterreich 3292",
    "addr:housenumber":"7",
    "addr:postcode":"3292",
    "addr:street":"Im Markt",
    "iso:country":"AT",
    "sg:address":"Im Markt 7",
    "sg:city":"Gaming",
    "sg:orig_category":"Banken U Sparkassen",
    "sg:phone":"+43 5 010025426",
    "sg:postcode":"3292",
    "sg:province":"Nieder\u00f6sterreich",
    "wof:name":"Sparkasse der Stadt Amstetten",
    "wof:placetype":"venue"
},
  "geometry": {"coordinates":[15.0878705978,47.9290084839],"type":"Point"}
}