{
  "type": "Feature",
  "properties": {
    "iso:country":"AT",
    "sg:address":"Bahnhofstr 279",
    "sg:city":"Schladming",
    "sg:orig_category":"Tabaktrafiken",
    "sg:phone":"+43 3687 22811",
    "sg:postcode":"8970",
    "sg:province":"Steiermark",
    "wof:name":"Bachler Matthias jun",
    "wof:placetype":"venue"
},
  "geometry": {"coordinates":[13.6805505753,47.393573761],"type":"Point"}
}