{
  "type": "Feature",
  "properties": {
    "addr:full":"Liebeneggstr 12 Innsbruck Tirol 6020",
    "addr:housenumber":"12",
    "addr:postcode":"6020",
    "addr:street":"Liebeneggstr;Tirol",
    "iso:country":"AT",
    "sg:address":"Liebeneggstr 12",
    "sg:city":"Innsbruck",
    "sg:orig_category":"Werbegrafik- U Grafik-Design",
    "sg:phone":"+43 4351 2560526",
    "sg:postcode":"6020",
    "sg:province":"Tirol",
    "wof:name":"C-Grafik Clemens Lackner",
    "wof:placetype":"venue"
},
  "geometry": {"coordinates":[11.3986406326,47.2589073181],"type":"Point"}
}