{
  "type": "Feature",
  "properties": {
    "addr:full":"Hauptstr 19 Ober-Grafendorf Nieder\u00f6sterreich 3200",
    "addr:housenumber":"19",
    "addr:postcode":"3200",
    "addr:street":"Hauptstr",
    "iso:country":"AT",
    "sg:address":"Hauptstr 19",
    "sg:city":"Ober-Grafendorf",
    "sg:orig_category":"Elektroinstallationsunternehmen",
    "sg:phone":"+43 2747 22000",
    "sg:postcode":"3200",
    "sg:province":"Nieder\u00f6sterreich",
    "wof:name":"ElektroinstallationsgesmbH",
    "wof:placetype":"venue"
},
  "geometry": {"coordinates":[15.5482788086,48.1503295898],"type":"Point"}
}