{
  "type": "Feature",
  "properties": {
    "addr:full":"Industriezeile 56 Linz Ober\u00f6sterreich 4020",
    "addr:housenumber":"56",
    "addr:postcode":"4020",
    "addr:street":"Industriezeile",
    "iso:country":"AT",
    "sg:address":"Industriezeile 56",
    "sg:city":"Linz",
    "sg:orig_category":"Hydraulik",
    "sg:phone":"+43 4373 278920",
    "sg:postcode":"4020",
    "sg:province":"Ober\u00f6sterreich",
    "wof:name":"Hainzl Industriesysteme GesmbH",
    "wof:placetype":"venue"
},
  "geometry": {"coordinates":[14.3152198792,48.3072242737],"type":"Point"}
}