{
  "type": "Feature",
  "properties": {
    "addr:full":"Badstr 17 Offenhausen Ober\u00f6sterreich 4625",
    "addr:housenumber":"17",
    "addr:postcode":"4625",
    "addr:street":"Badstr",
    "iso:country":"AT",
    "sg:address":"Badstr 17",
    "sg:city":"Offenhausen",
    "sg:orig_category":"\u00c3\u201erzte / F Allgemeinmedizin",
    "sg:phone":"+43 7247 6246",
    "sg:postcode":"4625",
    "sg:province":"Ober\u00f6sterreich",
    "wof:name":"Baudraxler Walter MedR Dr",
    "wof:placetype":"venue"
},
  "geometry": {"coordinates":[13.839764595,48.1584777832],"type":"Point"}
}