{
  "type": "Feature",
  "properties": {
    "addr:full":"Innerbachstrasse 17u. 19 Vandans Vorarlberg 6773",
    "addr:housenumber":"17u 19",
    "addr:postcode":"6773",
    "addr:street":"Innerbachstrasse",
    "iso:country":"AT",
    "sg:address":"Innerbachstrasse 17u. 19",
    "sg:city":"Vandans",
    "sg:classifiers":[
        {
            "category":"Museum",
            "subcategory":"Botanical Garden",
            "type":"Entertainment"
        }
    ],
    "sg:phone":"+43 5556 72722",
    "sg:postcode":"6773",
    "sg:province":"Vorarlberg",
    "sg:tags":[
        "vegetable",
        "choppers",
        "cabbage",
        "slicer"
    ],
    "wof:name":"Gebr\u00fcder Dietrich, Hobel- und S\u00e4gewerk, Krauthobelerzeugung",
    "wof:placetype":"venue"
},
  "geometry": {"coordinates":[9.8655061722,47.0882530212],"type":"Point"}
}