{
  "type": "Feature",
  "properties": {
    "iso:country":"AT",
    "sg:address":"Schulstr 211",
    "sg:city":"Greifenburg",
    "sg:orig_category":"Hauptschulen",
    "sg:phone":"+43 4347 123400",
    "sg:postcode":"9761",
    "sg:province":"K\u00e4rnten",
    "wof:name":"Hauptschule",
    "wof:placetype":"venue"
},
  "geometry": {"coordinates":[13.1779022217,46.749710083],"type":"Point"}
}