{
  "type": "Feature",
  "properties": {
    "addr:full":"Alexanderhofstr 15 Millstatt K\u00e4rnten 9872",
    "addr:housenumber":"15",
    "addr:postcode":"9872",
    "addr:street":"Alexanderhofstr;Kaernten",
    "iso:country":"AT",
    "sg:address":"Alexanderhofstr 15",
    "sg:city":"Millstatt",
    "sg:orig_category":"Tischlereien",
    "sg:phone":"+43 4766 2194",
    "sg:postcode":"9872",
    "sg:province":"K\u00e4rnten",
    "wof:name":"Klinar Tischlerei GmbH",
    "wof:placetype":"venue"
},
  "geometry": {"coordinates":[13.5624103546,46.809261322],"type":"Point"}
}