{
  "type": "Feature",
  "properties": {
    "iso:country":"AT",
    "sg:address":"Hauptstr 11",
    "sg:city":"Peuerbach",
    "sg:orig_category":"Handarbeiten",
    "sg:phone":"+43 664 1636204",
    "sg:postcode":"4722",
    "sg:province":"Ober\u00f6sterreich",
    "wof:name":"Sallaberger Elisabeth",
    "wof:placetype":"venue"
},
  "geometry": {"coordinates":[13.7719364166,48.3437576294],"type":"Point"}
}