{
  "type": "Feature",
  "properties": {
    "addr:full":"Seitenstettner Str 13 Steyr Ober\u00f6sterreich 4400",
    "addr:postcode":"4400",
    "addr:street":"Str 13",
    "iso:country":"AT",
    "sg:address":"Seitenstettner Str 13",
    "sg:city":"Steyr",
    "sg:orig_category":"Massagen",
    "sg:phone":"+43 7252 82602",
    "sg:postcode":"4400",
    "sg:province":"Ober\u00f6sterreich",
    "wof:name":"Massage-Institut-Glaser",
    "wof:placetype":"venue"
},
  "geometry": {"coordinates":[14.447687149,48.0452957153],"type":"Point"}
}