{
  "type": "Feature",
  "properties": {
    "addr:full":"Irenentalstr 30 Untertullnerbach Nieder\u00f6sterreich 3011",
    "addr:housenumber":"30",
    "addr:postcode":"3011",
    "addr:street":"Irenentalstr",
    "iso:country":"AT",
    "sg:address":"Irenentalstr 30",
    "sg:city":"Untertullnerbach",
    "sg:orig_category":"Non-Classified Establishments",
    "sg:phone":"+43 2233 53147",
    "sg:postcode":"3011",
    "sg:province":"Nieder\u00f6sterreich",
    "wof:name":"Pfarramt",
    "wof:placetype":"venue"
},
  "geometry": {"coordinates":[16.1310539246,48.1915588379],"type":"Point"}
}