{
  "type": "Feature",
  "properties": {
    "addr:full":"Markt 24 Werfen Salzburg 5450",
    "addr:housenumber":"24",
    "addr:postcode":"5450",
    "addr:street":"Markt;Salzburg",
    "iso:country":"AT",
    "sg:address":"Markt 24",
    "sg:city":"Werfen",
    "sg:orig_category":"Tourismusinformation U -Organisationen",
    "sg:phone":"+43 4364 685388",
    "sg:postcode":"5450",
    "sg:province":"Salzburg",
    "wof:name":"Tourismusverband Werfen",
    "wof:placetype":"venue"
},
  "geometry": {"coordinates":[13.1883678436,47.477306366],"type":"Point"}
}