{
  "type": "Feature",
  "properties": {
    "addr:full":"Nordstrasse 3 Eugendorf Salzburg 5301",
    "addr:housenumber":"3",
    "addr:postcode":"5301",
    "addr:street":"Nordstrasse;Salzburg",
    "iso:country":"AT",
    "sg:address":"Nordstrasse 3",
    "sg:city":"Eugendorf",
    "sg:classifiers":[
        {
            "category":"Government",
            "subcategory":"Court House",
            "type":"Public Place"
        }
    ],
    "sg:phone":"+43 6225 85410",
    "sg:postcode":"5301",
    "sg:province":"Salzburg",
    "sg:tags":[
        "vice",
        "bench"
    ],
    "sg:website":"muellnertools.at",
    "wof:name":"Herbert M\u00fcllner",
    "wof:placetype":"venue"
},
  "geometry": {"coordinates":[13.1253881454,47.8693237305],"type":"Point"}
}