{
  "type": "Feature",
  "properties": {
    "addr:full":"Schottenpassage 9 Wien Wien 1010",
    "addr:housenumber":"9",
    "addr:postcode":"1010",
    "addr:street":"Schottenpassage",
    "iso:country":"AT",
    "sg:address":"Schottenpassage 9",
    "sg:city":"Wien",
    "sg:orig_category":"Fleischhauereien",
    "sg:phone":"+43 4314 027531",
    "sg:postcode":"1010",
    "sg:province":"Wien",
    "wof:name":"Tr\u00fcnkel Leopold GmbH",
    "wof:placetype":"venue"
},
  "geometry": {"coordinates":[16.3627605438,48.2133369446],"type":"Point"}
}