{
  "type": "Feature",
  "properties": {
    "addr:full":"Steindorf 251 Stra\u00dfwalchen Salzburg 5204",
    "addr:housenumber":"251",
    "addr:postcode":"5204",
    "addr:street":"Steindorf;Salzburg",
    "iso:country":"AT",
    "sg:address":"Steindorf 251",
    "sg:city":"Stra\u00dfwalchen",
    "sg:orig_category":"Tankstellen",
    "sg:phone":"+43 6215 5921",
    "sg:postcode":"5204",
    "sg:province":"Salzburg",
    "wof:name":"JET Tankstelle",
    "wof:placetype":"venue"
},
  "geometry": {"coordinates":[13.2366724014,47.9572868347],"type":"Point"}
}