{
  "type": "Feature",
  "properties": {
    "addr:full":"Maria-Theresien-Str 11 Innsbruck Tirol 6020",
    "addr:housenumber":"11",
    "addr:postcode":"6020",
    "addr:street":"Maria-Theresien-Str;Tirol",
    "iso:country":"AT",
    "sg:address":"Maria-Theresien-Str 11",
    "sg:city":"Innsbruck",
    "sg:classifiers":[
        {
            "category":"Restaurant",
            "type":"Food & Drink"
        }
    ],
    "sg:phone":"+43 512 572881",
    "sg:postcode":"6020",
    "sg:province":"Tirol",
    "wof:name":"Nordsee GesmbH",
    "wof:placetype":"venue"
},
  "geometry": {"coordinates":[11.3939056396,47.2665672302],"type":"Point"}
}