{
  "type": "Feature",
  "properties": {
    "addr:full":"Friedelstr 20 Klagenfurt K\u00e4rnten 9020",
    "addr:housenumber":"20",
    "addr:postcode":"9020",
    "addr:street":"Friedelstr;Kaernten",
    "iso:country":"AT",
    "sg:address":"Friedelstr 20",
    "sg:city":"Klagenfurt",
    "sg:orig_category":"Werbeagenturen",
    "sg:phone":"+43 4367 67461808",
    "sg:postcode":"9020",
    "sg:province":"K\u00e4rnten",
    "wof:name":"sidonie purpur",
    "wof:placetype":"venue"
},
  "geometry": {"coordinates":[14.2934904099,46.6201515198],"type":"Point"}
}