{
  "type": "Feature",
  "properties": {
    "addr:full":"Parkstr 53 Wiener Neudorf Nieder\u00f6sterreich 2351",
    "addr:housenumber":"53",
    "addr:postcode":"2351",
    "addr:street":"Parkstr",
    "iso:country":"AT",
    "sg:address":"Parkstr 53",
    "sg:city":"Wiener Neudorf",
    "sg:orig_category":"Autohandel",
    "sg:phone":"+43 4322 3661745",
    "sg:postcode":"2351",
    "sg:province":"Nieder\u00f6sterreich",
    "wof:name":"Adam Richard",
    "wof:placetype":"venue"
},
  "geometry": {"coordinates":[16.3188819885,48.0830154419],"type":"Point"}
}