{
  "type": "Feature",
  "properties": {
    "addr:full":"Amerling 33 Kramsach Tirol 6233",
    "addr:housenumber":"33",
    "addr:postcode":"6233",
    "addr:street":"Amerling;Tirol",
    "iso:country":"AT",
    "sg:address":"Amerling 33",
    "sg:city":"Kramsach",
    "sg:orig_category":"Schmieden U Schmiedeeisenelemente",
    "sg:phone":"+43 4353 3764258",
    "sg:postcode":"6233",
    "sg:province":"Tirol",
    "wof:name":"Schmiedeeisen Wolfsgruber",
    "wof:placetype":"venue"
},
  "geometry": {"coordinates":[11.8814840317,47.443359375],"type":"Point"}
}