{
  "type": "Feature",
  "properties": {
    "iso:country":"AT",
    "sg:address":"Nr 49",
    "sg:city":"Kukmirn",
    "sg:orig_category":"Feuerwehren",
    "sg:phone":"+43 3328 32940",
    "sg:postcode":"7543",
    "sg:province":"Burgenland",
    "wof:name":"Freiwillige Feuerwehr Eisenh\u00fcttl",
    "wof:placetype":"venue"
},
  "geometry": {"coordinates":[172.21682739260001,-43.5008888245],"type":"Point"}
}