{
  "type": "Feature",
  "properties": {
    "addr:full":"Landstra\u00dfer Hauptstr 117 Wien Wien 1030",
    "addr:housenumber":"117",
    "addr:postcode":"1030",
    "addr:street":"Landstrasser Hauptstr",
    "iso:country":"AT",
    "sg:address":"Landstra\u00dfer Hauptstr 117",
    "sg:city":"Wien",
    "sg:orig_category":"Tabaktrafiken",
    "sg:phone":"+43 1 7129765",
    "sg:postcode":"1030",
    "sg:province":"Wien",
    "wof:name":"Rubner Robert",
    "wof:placetype":"venue"
},
  "geometry": {"coordinates":[16.3963661194,48.1962738037],"type":"Point"}
}