{
  "type": "Feature",
  "properties": {
    "addr:full":"Grubeng 10a Eggendorf Nieder\u00f6sterreich 2492",
    "addr:housenumber":"10a",
    "addr:postcode":"2492",
    "addr:street":"Grubeng",
    "iso:country":"AT",
    "sg:address":"Grubeng 10a",
    "sg:city":"Eggendorf",
    "sg:classifiers":[
        {
            "category":"Professional",
            "subcategory":"Management & Consulting",
            "type":"Services"
        }
    ],
    "sg:phone":"+43 4326 2273054",
    "sg:postcode":"2492",
    "sg:province":"Nieder\u00f6sterreich",
    "wof:name":"Leitner Walter",
    "wof:placetype":"venue"
},
  "geometry": {"coordinates":[8.1344404221,49.3539199829],"type":"Point"}
}