{
  "type": "Feature",
  "properties": {
    "addr:full":"Meggenhofen Ober\u00f6sterreich 4714",
    "addr:postcode":"4714",
    "addr:street":"Oberoesterreich",
    "iso:country":"AT",
    "sg:city":"Meggenhofen",
    "sg:orig_category":"Feuerwehren",
    "sg:phone":"+43 7247 7269",
    "sg:postcode":"4714",
    "sg:province":"Ober\u00f6sterreich",
    "wof:name":"Freiwillige Feuerwehr Meggenhofen",
    "wof:placetype":"venue"
},
  "geometry": {"coordinates":[13.7969532013,48.1803016663],"type":"Point"}
}