{
  "type": "Feature",
  "properties": {
    "addr:full":"Neutorg 26 Graz Steiermark 8010",
    "addr:housenumber":"26",
    "addr:postcode":"8010",
    "addr:street":"Neutorg",
    "iso:country":"AT",
    "sg:address":"Neutorg 26",
    "sg:city":"Graz",
    "sg:orig_category":"Offsetdruckereien",
    "sg:phone":"+43 316 8292070",
    "sg:postcode":"8010",
    "sg:province":"Steiermark",
    "wof:name":"Druckerei Khil GesmbH",
    "wof:placetype":"venue"
},
  "geometry": {"coordinates":[15.4359331131,47.0699195862],"type":"Point"}
}