{
  "type": "Feature",
  "properties": {
    "iso:country":"AT",
    "sg:address":"Augustinerstr 3",
    "sg:city":"Wien",
    "sg:orig_category":"Non-Classified Establishments",
    "sg:phone":"+43 1 53370990",
    "sg:postcode":"1010",
    "sg:province":"Wien",
    "wof:name":"Pfarramt St Augustin",
    "wof:placetype":"venue"
},
  "geometry": {"coordinates":[16.367975235,48.205291748],"type":"Point"}
}