{
  "type": "Feature",
  "properties": {
    "addr:full":"Gellertg 28/22 Wien Wien 1100",
    "addr:housenumber":"28 / 22",
    "addr:postcode":"1100",
    "addr:street":"Gellertg",
    "iso:country":"AT",
    "sg:address":"Gellertg 28/22",
    "sg:city":"Wien",
    "sg:orig_category":"Transportunternehmen",
    "sg:phone":"+43 1 6004809",
    "sg:postcode":"1100",
    "sg:province":"Wien",
    "wof:name":"SALE Transport GesmbH",
    "wof:placetype":"venue"
},
  "geometry": {"coordinates":[16.3744049072,48.1782684326],"type":"Point"}
}