{
  "type": "Feature",
  "properties": {
    "addr:full":"Neubauzeile 116 Linz Ober\u00f6sterreich 4030",
    "addr:housenumber":"116",
    "addr:postcode":"4030",
    "addr:street":"Neubauzeile",
    "iso:country":"AT",
    "sg:address":"Neubauzeile 116",
    "sg:city":"Linz",
    "sg:orig_category":"Blanking, Punching, Stamping, Embossing And Drawing Dies, Progressive Dies",
    "sg:phone":"+43 732 382031",
    "sg:postcode":"4030",
    "sg:province":"Ober\u00f6sterreich",
    "sg:website":"oswt.at",
    "wof:name":"Oswald Werkzeugtechnik GmbH",
    "wof:placetype":"venue"
},
  "geometry": {"coordinates":[14.2768592834,48.2405090332],"type":"Point"}
}