{
  "type": "Feature",
  "properties": {
    "addr:full":"Klosterneuburger Str 49 Wien Wien 1200",
    "addr:postcode":"1200",
    "addr:street":"Str 49",
    "iso:country":"AT",
    "sg:address":"Klosterneuburger Str 49",
    "sg:city":"Wien",
    "sg:orig_category":"Sonnenstudios",
    "sg:phone":"+43 1 2760000",
    "sg:postcode":"1200",
    "sg:province":"Wien",
    "wof:name":"Go2Sun",
    "wof:placetype":"venue"
},
  "geometry": {"coordinates":[16.3665370941,48.2309951782],"type":"Point"}
}