{
  "type": "Feature",
  "properties": {
    "addr:full":"Nr 80 Langkampfen Tirol 6336",
    "addr:postcode":"6336",
    "addr:street":"Nr 80;Tirol",
    "iso:country":"AT",
    "sg:address":"Nr 80",
    "sg:city":"Langkampfen",
    "sg:orig_category":"Anlagenbau U -Technik",
    "sg:phone":"+43 5372 63390",
    "sg:postcode":"6336",
    "sg:province":"Tirol",
    "wof:name":"MAB Anlagenbau Austria GmbH & Co KG",
    "wof:placetype":"venue"
},
  "geometry": {"coordinates":[12.0865154266,47.5244979858],"type":"Point"}
}