{
  "type": "Feature",
  "properties": {
    "addr:full":"Nr 69 Pettneu am Arlberg Tirol 6574",
    "addr:postcode":"6574",
    "addr:street":"Nr;Pettneu;Arlberg",
    "iso:country":"AT",
    "sg:address":"Nr 69",
    "sg:city":"Pettneu am Arlberg",
    "sg:orig_category":"Volksschulen",
    "sg:phone":"+43 5447 5662",
    "sg:postcode":"6574",
    "sg:province":"Tirol",
    "wof:name":"Volksschule",
    "wof:placetype":"venue"
},
  "geometry": {"coordinates":[10.3418588638,47.148349762],"type":"Point"}
}