{
  "type": "Feature",
  "properties": {
    "addr:full":"Raaber-Bahn-G 10 Wien Wien 1100",
    "addr:housenumber":"10",
    "addr:postcode":"1100",
    "addr:street":"Raaber-Bahn-G",
    "iso:country":"AT",
    "sg:address":"Raaber-Bahn-G 10",
    "sg:city":"Wien",
    "sg:classifiers":[
        {
            "category":"Restaurant",
            "type":"Food & Drink"
        }
    ],
    "sg:phone":"+43 4316 032827",
    "sg:postcode":"1100",
    "sg:province":"Wien",
    "wof:name":"Cafe-Restaurant Zum Sockerl",
    "wof:placetype":"venue"
},
  "geometry": {"coordinates":[16.3771858215,48.1805953979],"type":"Point"}
}