{
  "type": "Feature",
  "properties": {
    "addr:full":"Wirlsdorfer Str 11 Seeboden K\u00e4rnten 9871",
    "addr:housenumber":"11",
    "addr:postcode":"9871",
    "addr:street":"Str;Kaernten",
    "iso:country":"AT",
    "sg:address":"Wirlsdorfer Str 11",
    "sg:city":"Seeboden",
    "sg:orig_category":"Pensionen / Privatzimmer",
    "sg:phone":"+43 4762 81190",
    "sg:postcode":"9871",
    "sg:province":"K\u00e4rnten",
    "wof:name":"Haus B\u00f6hm",
    "wof:placetype":"venue"
},
  "geometry": {"coordinates":[13.5133428574,46.8165092468],"type":"Point"}
}