{
  "type": "Feature",
  "properties": {
    "addr:full":"Bradl 319 Jenbach Tirol 6200",
    "addr:housenumber":"319",
    "addr:postcode":"6200",
    "addr:street":"Bradl;Tirol",
    "iso:country":"AT",
    "sg:address":"Bradl 319",
    "sg:city":"Jenbach",
    "sg:orig_category":"Strick- U Wirkwaren / Erzeugung U Gro\u00c3\u0178handel",
    "sg:phone":"+43 5244 62030",
    "sg:postcode":"6200",
    "sg:province":"Tirol",
    "wof:name":"Giesswein Isabella Strick- und Walkdesign GmbH",
    "wof:placetype":"venue"
},
  "geometry": {"coordinates":[11.8194198608,47.4034042358],"type":"Point"}
}