{
  "type": "Feature",
  "properties": {
    "addr:full":"Hauptpl 2 Neuberg an der M\u00fcrz Steiermark 8692",
    "addr:housenumber":"2;8692",
    "addr:street":"Hauptpl",
    "iso:country":"AT",
    "sg:address":"Hauptpl 2",
    "sg:city":"Neuberg an der M\u00fcrz",
    "sg:orig_category":"Maler, Anstreicher U Lackierer",
    "sg:phone":"+43 4338 5782780",
    "sg:postcode":"8692",
    "sg:province":"Steiermark",
    "wof:name":"Plotzer KG",
    "wof:placetype":"venue"
},
  "geometry": {"coordinates":[15.574886322,47.6668281555],"type":"Point"}
}