{
  "type": "Feature",
  "properties": {
    "addr:full":"Bundesstrasse 114 Lauterach Vorarlberg 6923",
    "addr:housenumber":"114",
    "addr:postcode":"6923",
    "addr:street":"Bundesstrasse",
    "iso:country":"AT",
    "sg:address":"Bundesstrasse 114",
    "sg:city":"Lauterach",
    "sg:orig_category":"Freizeit, Hobbies U Vereine",
    "sg:phone":"+43 664",
    "sg:postcode":"6923",
    "sg:province":"Vorarlberg",
    "sg:website":"http://www.vrz.net/tauchschule/",
    "wof:name":"TAUCHSCHULE Lauterach",
    "wof:placetype":"venue"
},
  "geometry": {"coordinates":[9.7280712128,47.4670715332],"type":"Point"}
}