{
  "type": "Feature",
  "properties": {
    "addr:full":"Taubstummeng 15 Wien Wien 1040",
    "addr:housenumber":"15",
    "addr:postcode":"1040",
    "addr:street":"Taubstummeng",
    "iso:country":"AT",
    "sg:address":"Taubstummeng 15",
    "sg:city":"Wien",
    "sg:orig_category":"Fotografen",
    "sg:phone":"+43 1 5057301",
    "sg:postcode":"1040",
    "sg:province":"Wien",
    "wof:name":"Schoeller Nora Studio f Fotographie",
    "wof:placetype":"venue"
},
  "geometry": {"coordinates":[16.3706207275,48.1947784424],"type":"Point"}
}