{
  "type": "Feature",
  "properties": {
    "addr:full":"Kirchenstr 11 Bad Tatzmannsdorf Burgenland 7431",
    "addr:housenumber":"11",
    "addr:postcode":"7431",
    "addr:street":"Kirchenstr",
    "iso:country":"AT",
    "sg:address":"Kirchenstr 11",
    "sg:city":"Bad Tatzmannsdorf",
    "sg:orig_category":"Volksschulen",
    "sg:phone":"+43 3353 82460",
    "sg:postcode":"7431",
    "sg:province":"Burgenland",
    "wof:name":"Volksschule",
    "wof:placetype":"venue"
},
  "geometry": {"coordinates":[16.2273788452,47.3338317871],"type":"Point"}
}