{
  "type": "Feature",
  "properties": {
    "addr:full":"Reinprechtsdorf Str 9 Wien Wien 1050",
    "addr:housenumber":"9",
    "addr:postcode":"1050",
    "addr:street":"Reinprechtsdorf Str",
    "iso:country":"AT",
    "sg:address":"Reinprechtsdorf Str 9",
    "sg:city":"Wien",
    "sg:orig_category":"Damenmoden",
    "sg:phone":"+43 1 5451016",
    "sg:postcode":"1050",
    "sg:province":"Wien",
    "wof:name":"Fraczek-Moden GesmbH",
    "wof:placetype":"venue"
},
  "geometry": {"coordinates":[16.3558158875,48.1837501526],"type":"Point"}
}