{
  "type": "Feature",
  "properties": {
    "addr:full":"Matroseng 3 Wien Wien 1060",
    "addr:housenumber":"3",
    "addr:postcode":"1060",
    "addr:street":"Matroseng",
    "iso:country":"AT",
    "sg:address":"Matroseng 3",
    "sg:city":"Wien",
    "sg:orig_category":"Hydrokulturen",
    "sg:phone":"+43 1 5962198",
    "sg:postcode":"1060",
    "sg:province":"Wien",
    "wof:name":"Eckl Hans Dipl-Ing",
    "wof:placetype":"venue"
},
  "geometry": {"coordinates":[16.3414916992,48.1947135925],"type":"Point"}
}