{
  "type": "Feature",
  "properties": {
    "iso:country":"AT",
    "sg:address":"Lerchenfelder Str 63",
    "sg:city":"Wien",
    "sg:orig_category":"Steuerungstechnik",
    "sg:phone":"+43 1 5229152",
    "sg:postcode":"1070",
    "sg:province":"Wien",
    "wof:name":"KEBA AG",
    "wof:placetype":"venue"
},
  "geometry": {"coordinates":[16.3469352722,48.2066879272],"type":"Point"}
}