{
  "type": "Feature",
  "properties": {
    "addr:full":"Schallmooser Hauptstr 50 Salzburg Salzburg 5020",
    "addr:housenumber":"50",
    "addr:postcode":"5020",
    "addr:street":"Schallmooser Hauptstr;Salzburg",
    "iso:country":"AT",
    "sg:address":"Schallmooser Hauptstr 50",
    "sg:city":"Salzburg",
    "sg:classifiers":[
        {
            "category":"Restaurant",
            "type":"Food & Drink"
        }
    ],
    "sg:phone":"+43 4366 2870894",
    "sg:postcode":"5020",
    "sg:province":"Salzburg",
    "wof:name":"Urban-Keller",
    "wof:placetype":"venue"
},
  "geometry": {"coordinates":[13.0608968735,47.8073272705],"type":"Point"}
}