{
  "type": "Feature",
  "properties": {
    "addr:full":"Khevenh\u00fcllerg 16 Villach K\u00e4rnten 9500",
    "addr:housenumber":"16",
    "addr:postcode":"9500",
    "addr:street":"Khevenhuellerg;Kaernten",
    "iso:country":"AT",
    "sg:address":"Khevenh\u00fcllerg 16",
    "sg:city":"Villach",
    "sg:orig_category":"Volksschulen",
    "sg:phone":"+43 4242 2053300",
    "sg:postcode":"9500",
    "sg:province":"K\u00e4rnten",
    "wof:name":"Khevenh\u00fcllerschule",
    "wof:placetype":"venue"
},
  "geometry": {"coordinates":[13.8491945267,46.618106842],"type":"Point"}
}