{
  "type": "Feature",
  "properties": {
    "addr:full":"VOEST-ALPINE-Str 3 Linz Ober\u00f6sterreich 4020",
    "addr:housenumber":"3",
    "addr:postcode":"4020",
    "addr:street":"Voest-Alpine-Str",
    "iso:country":"AT",
    "sg:address":"VOEST-ALPINE-Str 3",
    "sg:city":"Linz",
    "sg:orig_category":"Bleche U Blechwaren",
    "sg:phone":"+43 4373 265850",
    "sg:postcode":"4020",
    "sg:province":"Ober\u00f6sterreich",
    "wof:name":"Voest-Alpine Giesserei Linz GmbH",
    "wof:placetype":"venue"
},
  "geometry": {"coordinates":[14.3199720383,48.2774925232],"type":"Point"}
}