{
  "type": "Feature",
  "properties": {
    "addr:full":"Schlo\u00dfstr 50 Alkoven Ober\u00f6sterreich 4072",
    "addr:housenumber":"50",
    "addr:postcode":"4072",
    "addr:street":"Schlossstr",
    "iso:country":"AT",
    "sg:address":"Schlo\u00dfstr 50",
    "sg:city":"Alkoven",
    "sg:orig_category":"Metallbau",
    "sg:phone":"+43 4372 7476110",
    "sg:postcode":"4072",
    "sg:province":"Ober\u00f6sterreich",
    "wof:name":"Schlenhardt GesmbH",
    "wof:placetype":"venue"
},
  "geometry": {"coordinates":[14.1170854568,48.2879104614],"type":"Point"}
}