{
  "type": "Feature",
  "properties": {
    "iso:country":"AT",
    "sg:address":"Prager Str 64",
    "sg:city":"Wien",
    "sg:classifiers":[
        {
            "category":"Wholesale",
            "subcategory":"Motor Vehicles",
            "type":"Manufacturing & Wholesale Goods"
        }
    ],
    "sg:phone":"+43 1 2705180",
    "sg:postcode":"1210",
    "sg:province":"Wien",
    "sg:tags":[
        "moped"
    ],
    "wof:name":"Wonisch Gerhard",
    "wof:placetype":"venue"
},
  "geometry": {"coordinates":[16.3926696777,48.2677192688],"type":"Point"}
}