{
  "type": "Feature",
  "properties": {
    "iso:country":"AT",
    "sg:address":"Erzherzog-Johann-Str 2",
    "sg:city":"Stainz",
    "sg:orig_category":"Tabaktrafiken",
    "sg:phone":"+43 3463 2692",
    "sg:postcode":"8510",
    "sg:province":"Steiermark",
    "wof:name":"Spari Melanie",
    "wof:placetype":"venue"
},
  "geometry": {"coordinates":[15.2631244659,46.8938331604],"type":"Point"}
}