{
  "type": "Feature",
  "properties": {
    "addr:full":"Haferg 2 Wels Ober\u00f6sterreich 4600",
    "addr:housenumber":"2",
    "addr:postcode":"4600",
    "addr:street":"Haferg;Oberoesterreich",
    "iso:country":"AT",
    "sg:address":"Haferg 2",
    "sg:city":"Wels",
    "sg:orig_category":"Friseure U Frisiersalons",
    "sg:phone":"+43 4372 4243501",
    "sg:postcode":"4600",
    "sg:province":"Ober\u00f6sterreich",
    "wof:name":"Marquant Edith",
    "wof:placetype":"venue"
},
  "geometry": {"coordinates":[14.0257425308,48.1570167542],"type":"Point"}
}