{
  "type": "Feature",
  "properties": {
    "addr:full":"Silbertaler Str 1 Schruns Vorarlberg 6780",
    "addr:housenumber":"1",
    "addr:postcode":"6780",
    "addr:street":"Str",
    "iso:country":"AT",
    "sg:address":"Silbertaler Str 1",
    "sg:city":"Schruns",
    "sg:orig_category":"Juwelen, Gold- U Silberwaren / Einzelhandel",
    "sg:phone":"+43 4355 5672565",
    "sg:postcode":"6780",
    "sg:province":"Vorarlberg",
    "wof:name":"Montafoner Schmuckk\u00e4stli",
    "wof:placetype":"venue"
},
  "geometry": {"coordinates":[9.9179954529,47.0808944702],"type":"Point"}
}