{
  "type": "Feature",
  "properties": {
    "addr:full":"Sch\u00f6pfgasse 4 Gnigl Salzburg 5023",
    "addr:housenumber":"4",
    "addr:postcode":"5023",
    "addr:street":"Schoepfgasse",
    "iso:country":"AT",
    "sg:address":"Sch\u00f6pfgasse 4",
    "sg:city":"Gnigl",
    "sg:classifiers":[
        {
            "category":"Manufacturing",
            "subcategory":"Motor Vehicles & Parts",
            "type":"Manufacturing & Wholesale Goods"
        }
    ],
    "sg:phone":"+43 662 640078",
    "sg:postcode":"5023",
    "sg:province":"Salzburg",
    "sg:tags":[
        "body",
        "car",
        "accessory"
    ],
    "sg:website":"karosserie-wallner.at",
    "wof:name":"Thomas Wallner",
    "wof:placetype":"venue"
},
  "geometry": {"coordinates":[13.0684871674,47.8145217896],"type":"Point"}
}