{
  "type": "Feature",
  "properties": {
    "addr:full":"Willerg 27 Wien Wien 1230",
    "addr:housenumber":"27",
    "addr:postcode":"1230",
    "addr:street":"Willerg",
    "iso:country":"AT",
    "sg:address":"Willerg 27",
    "sg:city":"Wien",
    "sg:orig_category":"Handelsagenturen",
    "sg:phone":"+43 1 8884278",
    "sg:postcode":"1230",
    "sg:province":"Wien",
    "wof:name":"Sch\u00fctzenhofer - Zerspanungstechnologie",
    "wof:placetype":"venue"
},
  "geometry": {"coordinates":[16.2580490112,48.1357307434],"type":"Point"}
}