{
  "type": "Feature",
  "properties": {
    "addr:full":"Niederthalheim Ober\u00f6sterreich 4692",
    "addr:postcode":"4692",
    "iso:country":"AT",
    "sg:city":"Niederthalheim",
    "sg:orig_category":"Feuerwehren",
    "sg:phone":"+43 76737182",
    "sg:postcode":"4692",
    "sg:province":"Ober\u00f6sterreich",
    "wof:name":"Freiwillige Feuerwehr Penetzdorf",
    "wof:placetype":"venue"
},
  "geometry": {"coordinates":[13.729385376,48.1072387695],"type":"Point"}
}