{
  "type": "Feature",
  "properties": {
    "addr:full":"Gymnasiumstr 4 Waidhofen an der Thaya Nieder\u00f6sterreich 3830",
    "addr:housenumber":"4",
    "addr:postcode":"3830",
    "addr:street":"Gymnasiumstr",
    "iso:country":"AT",
    "sg:address":"Gymnasiumstr 4",
    "sg:city":"Waidhofen an der Thaya",
    "sg:orig_category":"Polytechnische Schulen",
    "sg:phone":"+43 4328 4252447",
    "sg:postcode":"3830",
    "sg:province":"Nieder\u00f6sterreich",
    "wof:name":"Polytechnische Schule",
    "wof:placetype":"venue"
},
  "geometry": {"coordinates":[15.2824468613,48.8127593994],"type":"Point"}
}