{
  "type": "Feature",
  "properties": {
    "addr:full":"Leondinger Str 74 Traun Ober\u00f6sterreich 4050",
    "addr:postcode":"4050",
    "addr:street":"Str 74",
    "iso:country":"AT",
    "sg:address":"Leondinger Str 74",
    "sg:city":"Traun",
    "sg:orig_category":"Montagen U Montagetechnik",
    "sg:phone":"+43 7229 75055",
    "sg:postcode":"4050",
    "sg:province":"Ober\u00f6sterreich",
    "wof:name":"HMF Montage GmbH",
    "wof:placetype":"venue"
},
  "geometry": {"coordinates":[14.2639389038,48.2369613647],"type":"Point"}
}