{
  "type": "Feature",
  "properties": {
    "iso:country":"AT",
    "sg:address":"Gartenheimstr 47",
    "sg:city":"Wien",
    "sg:orig_category":"Tabaktrafiken",
    "sg:phone":"+43 1 77474190",
    "sg:postcode":"1220",
    "sg:province":"Wien",
    "wof:name":"Hussl Alfred",
    "wof:placetype":"venue"
},
  "geometry": {"coordinates":[16.5341434479,48.2159576416],"type":"Point"}
}