{
  "type": "Feature",
  "properties": {
    "addr:full":"Hauptpl 28 Wiener Neustadt Nieder\u00f6sterreich 2700",
    "addr:housenumber":"28",
    "addr:postcode":"2700",
    "addr:street":"Hauptpl",
    "iso:country":"AT",
    "sg:address":"Hauptpl 28",
    "sg:city":"Wiener Neustadt",
    "sg:orig_category":"Banken U Sparkassen",
    "sg:phone":"+43 4326 22274510",
    "sg:postcode":"2700",
    "sg:province":"Nieder\u00f6sterreich",
    "wof:name":"Bankomat d Raiffeisenregionalbank Wr Neustadt regGenmbH",
    "wof:placetype":"venue"
},
  "geometry": {"coordinates":[16.2441043854,47.8126983643],"type":"Point"}
}