{
  "type": "Feature",
  "properties": {
    "addr:full":"Nr 147 St. Pantaleon Ober\u00f6sterreich 5120",
    "addr:postcode":"5120",
    "addr:street":"Nr 147",
    "iso:country":"AT",
    "sg:address":"Nr 147",
    "sg:city":"St. Pantaleon",
    "sg:orig_category":"\u00c3\u201erzte / F Allgemeinmedizin",
    "sg:phone":"+43 6277 7665",
    "sg:postcode":"5120",
    "sg:province":"Ober\u00f6sterreich",
    "wof:name":"Binder Helmut Dr",
    "wof:placetype":"venue"
},
  "geometry": {"coordinates":[166.9221496582,-0.5282999873],"type":"Point"}
}