{
  "type": "Feature",
  "properties": {
    "iso:country":"AT",
    "sg:address":"Franz-Liszt-G 9",
    "sg:city":"Neusiedl am See",
    "sg:orig_category":"Psychotherapie",
    "sg:phone":"+43 2167 20874",
    "sg:postcode":"7100",
    "sg:province":"Burgenland",
    "wof:name":"Psychotherapie Institut Neusiedl",
    "wof:placetype":"venue"
},
  "geometry": {"coordinates":[16.8485794067,47.946685791],"type":"Point"}
}