{
  "type": "Feature",
  "properties": {
    "addr:full":"Gewerbestr 4 Bruck an der Gro\u00dfglocknerstra\u00dfe Salzburg 5671",
    "addr:housenumber":"4",
    "addr:postcode":"5671",
    "addr:street":"Gewerbestr;Grossglocknerstrasse Salzburg",
    "iso:country":"AT",
    "sg:address":"Gewerbestr 4",
    "sg:city":"Bruck an der Gro\u00dfglocknerstra\u00dfe",
    "sg:orig_category":"Befestigungstechnik",
    "sg:phone":"+43 4365 4560640",
    "sg:postcode":"5671",
    "sg:province":"Salzburg",
    "wof:name":"Hilti Austria GesmbH",
    "wof:placetype":"venue"
},
  "geometry": {"coordinates":[12.8262853622,47.2858848572],"type":"Point"}
}