{
  "type": "Feature",
  "properties": {
    "addr:full":"Franziskanerpl 14 Graz Steiermark 8010",
    "addr:housenumber":"14",
    "addr:postcode":"8010",
    "addr:street":"Franziskanerpl",
    "iso:country":"AT",
    "sg:address":"Franziskanerpl 14",
    "sg:city":"Graz",
    "sg:orig_category":"Non-Classified Establishments",
    "sg:phone":"+43 316 8291890",
    "sg:postcode":"8010",
    "sg:province":"Steiermark",
    "wof:name":"Franziskanerkloster",
    "wof:placetype":"venue"
},
  "geometry": {"coordinates":[15.4368495941,47.0705032349],"type":"Point"}
}