{
  "type": "Feature",
  "properties": {
    "addr:full":"Huttenstr 10 Eichgraben Nieder\u00f6sterreich 3032",
    "addr:housenumber":"10",
    "addr:postcode":"3032",
    "addr:street":"Huttenstr",
    "iso:country":"AT",
    "sg:address":"Huttenstr 10",
    "sg:city":"Eichgraben",
    "sg:orig_category":"Garten- U Landschaftsgestaltung",
    "sg:phone":"+43 4327 7342046",
    "sg:postcode":"3032",
    "sg:province":"Nieder\u00f6sterreich",
    "wof:name":"Malecek Michael",
    "wof:placetype":"venue"
},
  "geometry": {"coordinates":[15.9871454239,48.1761322021],"type":"Point"}
}