{
  "type": "Feature",
  "properties": {
    "addr:full":"Tannberg 152 Lech Vorarlberg 6764",
    "addr:housenumber":"152",
    "addr:postcode":"6764",
    "addr:street":"Tannberg",
    "iso:country":"AT",
    "sg:address":"Tannberg 152",
    "sg:city":"Lech",
    "sg:orig_category":"Appartements / Ferienwohnungen",
    "sg:phone":"+43 4355 832241",
    "sg:postcode":"6764",
    "sg:province":"Vorarlberg",
    "wof:name":"Haus Ganahl",
    "wof:placetype":"venue"
},
  "geometry": {"coordinates":[10.1382112503,47.2056884766],"type":"Point"}
}