{
  "type": "Feature",
  "properties": {
    "addr:full":"Innrain 95 Innsbruck Tirol 6020",
    "addr:housenumber":"95",
    "addr:postcode":"6020",
    "addr:street":"Innrain;Tirol",
    "iso:country":"AT",
    "sg:address":"Innrain 95",
    "sg:city":"Innsbruck",
    "sg:orig_category":"Genossenschaften",
    "sg:phone":"+43 512 520610",
    "sg:postcode":"6020",
    "sg:province":"Tirol",
    "wof:name":"Gemeinn\u00fctzige Hauptgen d Siedlerbundes regGenmbH",
    "wof:placetype":"venue"
},
  "geometry": {"coordinates":[11.3807582855,47.258846283],"type":"Point"}
}