{
  "type": "Feature",
  "properties": {
    "addr:full":"Hochstr 75 Perchtoldsdorf Nieder\u00f6sterreich 2380",
    "addr:housenumber":"75",
    "addr:postcode":"2380",
    "addr:street":"Hochstr",
    "iso:country":"AT",
    "sg:address":"Hochstr 75",
    "sg:city":"Perchtoldsdorf",
    "sg:orig_category":"Heurigen / Buschenschank",
    "sg:phone":"+43 1 8659102",
    "sg:postcode":"2380",
    "sg:province":"Nieder\u00f6sterreich",
    "wof:name":"Spiegelhofer Ludwig",
    "wof:placetype":"venue"
},
  "geometry": {"coordinates":[16.2620124817,48.1246681213],"type":"Point"}
}