{
  "type": "Feature",
  "properties": {
    "addr:full":"P Mitterbauer-Str 3 Roitham Ober\u00f6sterreich 4661",
    "addr:housenumber":"3",
    "addr:postcode":"4661",
    "addr:street":"P Mitterbauer-Str",
    "iso:country":"AT",
    "sg:address":"P Mitterbauer-Str 3",
    "sg:city":"Roitham",
    "sg:orig_category":"Drehereien",
    "sg:phone":"+43 761324460",
    "sg:postcode":"4661",
    "sg:province":"Ober\u00f6sterreich",
    "wof:name":"Brandner GmbH",
    "wof:placetype":"venue"
},
  "geometry": {"coordinates":[13.8473854065,48.0069618225],"type":"Point"}
}