{
  "type": "Feature",
  "properties": {
    "addr:full":"Aschacher Str 1 Ottensheim Ober\u00f6sterreich 4100",
    "addr:housenumber":"1",
    "addr:postcode":"4100",
    "addr:street":"Str",
    "iso:country":"AT",
    "sg:address":"Aschacher Str 1",
    "sg:city":"Ottensheim",
    "sg:orig_category":"Brauereianlagen U -Bedarf",
    "sg:phone":"+43 4373 2772306",
    "sg:postcode":"4100",
    "sg:province":"Ober\u00f6sterreich",
    "wof:name":"Thor - Br\u00e4u Laska KEG",
    "wof:placetype":"venue"
},
  "geometry": {"coordinates":[14.1651754379,48.3382034302],"type":"Point"}
}