{
  "type": "Feature",
  "properties": {
    "addr:full":"Schmalzhofg 13/3 Wien Wien 1060",
    "addr:housenumber":"13 / 3",
    "addr:postcode":"1060",
    "addr:street":"Schmalzhofg",
    "iso:country":"AT",
    "sg:address":"Schmalzhofg 13/3",
    "sg:city":"Wien",
    "sg:orig_category":"Galerien",
    "sg:phone":"+43 1 9134458",
    "sg:postcode":"1060",
    "sg:province":"Wien",
    "sg:website":"www.galerie-lindner.at",
    "wof:name":"Galerie Lindner",
    "wof:placetype":"venue"
},
  "geometry": {"coordinates":[16.3459300995,48.1949691772],"type":"Point"}
}