{
  "type": "Feature",
  "properties": {
    "addr:full":"Nr 70 Markgrafneusiedl Nieder\u00f6sterreich 2282",
    "addr:postcode":"2282",
    "addr:street":"Nr;Niederoesterreich",
    "iso:country":"AT",
    "sg:address":"Nr 70",
    "sg:city":"Markgrafneusiedl",
    "sg:orig_category":"Gemeinden",
    "sg:phone":"+43 2248 2585",
    "sg:postcode":"2282",
    "sg:province":"Nieder\u00f6sterreich",
    "wof:name":"Gemeinde Glinzendorf",
    "wof:placetype":"venue"
},
  "geometry": {"coordinates":[16.6323261261,48.2674369812],"type":"Point"}
}