{
  "type": "Feature",
  "properties": {
    "iso:country":"AT",
    "sg:address":"Don-Bosco-G 15",
    "sg:city":"Wien",
    "sg:orig_category":"Behinderungen / Leben Mit Behinderungen",
    "sg:phone":"+43 4316 672159",
    "sg:postcode":"1230",
    "sg:province":"Wien",
    "wof:name":"Lebenshilfe Wien Verein f Menschen m geistiger u mehrfacher Behinderung",
    "wof:placetype":"venue"
},
  "geometry": {"coordinates":[16.329870224,48.1481437683],"type":"Point"}
}