{
  "type": "Feature",
  "properties": {
    "iso:country":"AT",
    "sg:address":"Gadenweith 9",
    "sg:city":"Neuhaus",
    "sg:orig_category":"Bauunternehmen",
    "sg:phone":"+43 2674 86358",
    "sg:postcode":"2565",
    "sg:province":"Nieder\u00f6sterreich",
    "wof:name":"Sch\u00f6ner J M Bau GmbH",
    "wof:placetype":"venue"
},
  "geometry": {"coordinates":[16.0705070496,47.989818573],"type":"Point"}
}