{
  "type": "Feature",
  "properties": {
    "addr:full":"Nr 20 Hinterstoder Ober\u00f6sterreich 4573",
    "addr:postcode":"4573",
    "addr:street":"Nr;Hinterstoder Oberoesterreich",
    "iso:country":"AT",
    "sg:address":"Nr 20",
    "sg:city":"Hinterstoder",
    "sg:classifiers":[
        {
            "category":"Park",
            "subcategory":"Provincial",
            "type":"Public Place"
        }
    ],
    "sg:phone":"+43 7564 5050",
    "sg:postcode":"4573",
    "sg:province":"Ober\u00f6sterreich",
    "sg:tags":[
        "u",
        "ski-",
        "snowboardschulen"
    ],
    "wof:name":"Schischule Stodertal",
    "wof:placetype":"venue"
},
  "geometry": {"coordinates":[14.1566810608,47.7001152039],"type":"Point"}
}