{
  "type": "Feature",
  "properties": {
    "addr:full":"Nr 330 Drasenhofen Nieder\u00f6sterreich 2165",
    "addr:postcode":"2165",
    "addr:street":"Nr;Drasenhofen Niederoesterreich",
    "iso:country":"AT",
    "sg:address":"Nr 330",
    "sg:city":"Drasenhofen",
    "sg:orig_category":"Autoreparatur",
    "sg:phone":"+43 4325 5485226",
    "sg:postcode":"2165",
    "sg:province":"Nieder\u00f6sterreich",
    "wof:name":"Braunstingl Helmut Ing",
    "wof:placetype":"venue"
},
  "geometry": {"coordinates":[16.6465511322,48.7561454773],"type":"Point"}
}