{
  "type": "Feature",
  "properties": {
    "addr:full":"Atterseestr 13 Seewalchen am Attersee Ober\u00f6sterreich 4863",
    "addr:housenumber":"13",
    "addr:postcode":"4863",
    "addr:street":"Atterseestr",
    "iso:country":"AT",
    "sg:address":"Atterseestr 13",
    "sg:city":"Seewalchen am Attersee",
    "sg:classifiers":[
        {
            "category":"Restaurant",
            "type":"Food & Drink"
        }
    ],
    "sg:phone":"+43 4376 626214",
    "sg:postcode":"4863",
    "sg:province":"Ober\u00f6sterreich",
    "wof:name":"Restaurant Bootshaus",
    "wof:placetype":"venue"
},
  "geometry": {"coordinates":[13.5963468552,47.9494590759],"type":"Point"}
}