{
  "type": "Feature",
  "properties": {
    "addr:full":"Lilienthalg 20 Graz Steiermark 8020",
    "addr:housenumber":"20",
    "addr:postcode":"8020",
    "addr:street":"Lilienthalg",
    "iso:country":"AT",
    "sg:address":"Lilienthalg 20",
    "sg:city":"Graz",
    "sg:orig_category":"Lebens- U Sozialberatung",
    "sg:phone":"+43 316 585800",
    "sg:postcode":"8020",
    "sg:province":"Steiermark",
    "wof:name":"Vinzi Haus - Soziale Beratungstelle",
    "wof:placetype":"venue"
},
  "geometry": {"coordinates":[15.4071121216,47.0743904114],"type":"Point"}
}