{
  "type": "Feature",
  "properties": {
    "addr:full":"Kirchenpl 3 Weissenbach an der Triesting Nieder\u00f6sterreich 2564",
    "addr:housenumber":"3",
    "addr:postcode":"2564",
    "addr:street":"Kirchenpl;Niederoesterreich",
    "iso:country":"AT",
    "sg:address":"Kirchenpl 3",
    "sg:city":"Weissenbach an der Triesting",
    "sg:orig_category":"Messen U Ausstellungen",
    "sg:phone":"+43 4326 7487822",
    "sg:postcode":"2564",
    "sg:province":"Nieder\u00f6sterreich",
    "wof:name":"Triestingtaler Heimatmuseum d Marktgemeinde Weissenbach/Triesting",
    "wof:placetype":"venue"
},
  "geometry": {"coordinates":[16.0378684998,47.9819908142],"type":"Point"}
}