{
  "type": "Feature",
  "properties": {
    "addr:full":"Bundesstr 15 Wernberg K\u00e4rnten 9241",
    "addr:housenumber":"15",
    "addr:postcode":"9241",
    "addr:street":"Bundesstr;Kaernten",
    "iso:country":"AT",
    "sg:address":"Bundesstr 15",
    "sg:city":"Wernberg",
    "sg:orig_category":"Banken U Sparkassen",
    "sg:phone":"+43 4252 22230",
    "sg:postcode":"9241",
    "sg:province":"K\u00e4rnten",
    "wof:name":"Raiffeisenbank Wernberg regGenmbH",
    "wof:placetype":"venue"
},
  "geometry": {"coordinates":[13.9393587112,46.6230888367],"type":"Point"}
}