{
  "type": "Feature",
  "properties": {
    "iso:country":"AT",
    "sg:address":"N\u00f6ckhamstr 16",
    "sg:city":"Gleink",
    "sg:classifiers":[
        {
            "category":"Professional",
            "subcategory":"Computer Services",
            "type":"Services"
        }
    ],
    "sg:phone":"+43 7252 81533",
    "sg:postcode":"4407",
    "sg:province":"Ober\u00f6sterreich",
    "sg:tags":[
        "software"
    ],
    "wof:name":"Palette CAD-Systeme GmbH",
    "wof:placetype":"venue"
},
  "geometry": {"coordinates":[14.4159860611,48.0908508301],"type":"Point"}
}