{
  "type": "Feature",
  "properties": {
    "addr:full":"Hauptstr 19 Laab im Walde Nieder\u00f6sterreich 2381",
    "addr:housenumber":"19",
    "addr:postcode":"2381",
    "addr:street":"Hauptstr",
    "iso:country":"AT",
    "sg:address":"Hauptstr 19",
    "sg:city":"Laab im Walde",
    "sg:orig_category":"Molkereien U Molkereiprodukte",
    "sg:phone":"+43 4322 394121",
    "sg:postcode":"2381",
    "sg:province":"Nieder\u00f6sterreich",
    "wof:name":"Gebr Aschauer GnbR - Die Milch v Bauernhof",
    "wof:placetype":"venue"
},
  "geometry": {"coordinates":[16.1766681671,48.1551551819],"type":"Point"}
}