{
  "type": "Feature",
  "properties": {
    "addr:full":"Vogelweiderstr 44a Salzburg Salzburg 5020",
    "addr:housenumber":"44a",
    "addr:postcode":"5020",
    "addr:street":"Vogelweiderstr;Salzburg",
    "iso:country":"AT",
    "sg:address":"Vogelweiderstr 44a",
    "sg:city":"Salzburg",
    "sg:orig_category":"Telekommunikation, Computernetzwerke, Telefonanlagen",
    "sg:phone":"+43 5 08110",
    "sg:postcode":"5020",
    "sg:province":"Salzburg",
    "wof:name":"Kapsch BusinessCom AG",
    "wof:placetype":"venue"
},
  "geometry": {"coordinates":[13.0544376373,47.812461853],"type":"Point"}
}