{
  "type": "Feature",
  "properties": {
    "iso:country":"AT",
    "sg:address":"Lechtaler Str 89",
    "sg:city":"Bach",
    "sg:orig_category":"Autoreparatur",
    "sg:phone":"+43 5634 6384",
    "sg:postcode":"6653",
    "sg:province":"Tirol",
    "wof:name":"Wolf Ferdinand",
    "wof:placetype":"venue"
},
  "geometry": {"coordinates":[10.403676033,47.270198822],"type":"Point"}
}