{
  "type": "Feature",
  "properties": {
    "addr:full":"Friesachstr 15 St\u00fcbing Steiermark 8114",
    "addr:housenumber":"15",
    "addr:postcode":"8114",
    "addr:street":"Friesachstr",
    "iso:country":"AT",
    "sg:address":"Friesachstr 15",
    "sg:city":"St\u00fcbing",
    "sg:orig_category":"Anlagenbau U -Technik",
    "sg:phone":"+43 3127 2000",
    "sg:postcode":"8114",
    "sg:province":"Steiermark",
    "wof:name":"Salomon Automation GmbH",
    "wof:placetype":"venue"
},
  "geometry": {"coordinates":[15.3342876434,47.1734199524],"type":"Point"}
}