{
  "type": "Feature",
  "properties": {
    "addr:full":"Rathauspl 1 Peuerbach Ober\u00f6sterreich 4722",
    "addr:housenumber":"1",
    "addr:postcode":"4722",
    "addr:street":"Rathauspl",
    "iso:country":"AT",
    "sg:address":"Rathauspl 1",
    "sg:city":"Peuerbach",
    "sg:orig_category":"Museen / Ausstellungen",
    "sg:phone":"+43 7276 2014",
    "sg:postcode":"4722",
    "sg:province":"Ober\u00f6sterreich",
    "wof:name":"Museum Bauernkrieg und O\u00f6 Landeskrippe",
    "wof:placetype":"venue"
},
  "geometry": {"coordinates":[13.7706737518,48.3435134888],"type":"Point"}
}