{
  "type": "Feature",
  "properties": {
    "addr:full":"Kandaharweg 10 St. Anton am Arlberg Tirol 6580",
    "addr:housenumber":"10",
    "addr:postcode":"6580",
    "addr:street":"Kandaharweg;Tirol",
    "iso:country":"AT",
    "sg:address":"Kandaharweg 10",
    "sg:city":"St. Anton am Arlberg",
    "sg:classifiers":[
        {
            "category":"Park",
            "subcategory":"Provincial",
            "type":"Public Place"
        }
    ],
    "sg:phone":"+43 4354 463563",
    "sg:postcode":"6580",
    "sg:province":"Tirol",
    "sg:tags":[
        "u",
        "ski-",
        "snowboardschulen"
    ],
    "wof:name":"Skischule St Anton",
    "wof:placetype":"venue"
},
  "geometry": {"coordinates":[10.2642011642,47.128944397],"type":"Point"}
}