{
  "type": "Feature",
  "properties": {
    "addr:full":"Am Dorfpl 115 Liezen Steiermark 8940",
    "addr:housenumber":"115",
    "addr:postcode":"8940",
    "addr:street":"Am Dorfpl",
    "iso:country":"AT",
    "sg:address":"Am Dorfpl 115",
    "sg:city":"Liezen",
    "sg:orig_category":"Volksschulen",
    "sg:phone":"+43 4336 1222432",
    "sg:postcode":"8940",
    "sg:province":"Steiermark",
    "wof:name":"Volksschule",
    "wof:placetype":"venue"
},
  "geometry": {"coordinates":[14.2039728165,47.5710678101],"type":"Point"}
}