{
  "type": "Feature",
  "properties": {
    "iso:country":"AT",
    "sg:address":"Hirteng 24A",
    "sg:city":"Mattersburg",
    "sg:orig_category":"Fleischhauereien",
    "sg:phone":"+43 2626 62293",
    "sg:postcode":"7210",
    "sg:province":"Burgenland",
    "wof:name":"Ivancsich Otto",
    "wof:placetype":"venue"
},
  "geometry": {"coordinates":[16.3976287842,47.7394790649],"type":"Point"}
}