{
  "type": "Feature",
  "properties": {
    "addr:full":"Strau\u00dfstr 11 Waidhofen an der Thaya Nieder\u00f6sterreich 3830",
    "addr:housenumber":"11",
    "addr:postcode":"3830",
    "addr:street":"Straussstr",
    "iso:country":"AT",
    "sg:address":"Strau\u00dfstr 11",
    "sg:city":"Waidhofen an der Thaya",
    "sg:orig_category":"Maler, Anstreicher U Lackierer",
    "sg:phone":"+43 4365 02502561",
    "sg:postcode":"3830",
    "sg:province":"Nieder\u00f6sterreich",
    "wof:name":"Wurth Martin",
    "wof:placetype":"venue"
},
  "geometry": {"coordinates":[15.2785387039,48.8059768677],"type":"Point"}
}