{
  "type": "Feature",
  "properties": {
    "addr:full":"Dieselstr 9a Mauer-\u00d6hling Nieder\u00f6sterreich 3362",
    "addr:housenumber":"9a",
    "addr:postcode":"3362",
    "addr:street":"Dieselstr;Niederoesterreich",
    "iso:country":"AT",
    "sg:address":"Dieselstr 9a",
    "sg:city":"Mauer-\u00d6hling",
    "sg:orig_category":"Dachdeckereien",
    "sg:phone":"+43 7472 62838",
    "sg:postcode":"3362",
    "sg:province":"Nieder\u00f6sterreich",
    "wof:name":"Haberhauer Wolfgang",
    "wof:placetype":"venue"
},
  "geometry": {"coordinates":[14.7985095978,48.1009559631],"type":"Point"}
}