{
  "type": "Feature",
  "properties": {
    "addr:full":"Friedensstr 6 Salzburg Salzburg 5020",
    "addr:housenumber":"6",
    "addr:postcode":"5020",
    "addr:street":"Friedensstr;Salzburg",
    "iso:country":"AT",
    "sg:address":"Friedensstr 6",
    "sg:city":"Salzburg",
    "sg:orig_category":"Textilreinigung",
    "sg:phone":"+43 650 4431745",
    "sg:postcode":"5020",
    "sg:province":"Salzburg",
    "wof:name":"Exclusiv Spezialreinigung",
    "wof:placetype":"venue"
},
  "geometry": {"coordinates":[13.0649986267,47.7859954834],"type":"Point"}
}