{
  "type": "Feature",
  "properties": {
    "iso:country":"AT",
    "sg:address":"Altenrieder Str 2",
    "sg:city":"Ried im Innkreis",
    "sg:orig_category":"Steuerberatung",
    "sg:phone":"+43 4377 52832170",
    "sg:postcode":"4910",
    "sg:province":"Ober\u00f6sterreich",
    "wof:name":"Z\u00f6dl Walter",
    "wof:placetype":"venue"
},
  "geometry": {"coordinates":[13.4811849594,48.2182426453],"type":"Point"}
}