{
  "type": "Feature",
  "properties": {
    "addr:full":"Schubertstr 30 Wels Ober\u00f6sterreich 4600",
    "addr:housenumber":"30",
    "addr:postcode":"4600",
    "addr:street":"Schubertstr;Oberoesterreich",
    "iso:country":"AT",
    "sg:address":"Schubertstr 30",
    "sg:city":"Wels",
    "sg:orig_category":"Molkereien U Molkereiprodukte",
    "sg:phone":"+43 4372 42469960",
    "sg:postcode":"4600",
    "sg:province":"Ober\u00f6sterreich",
    "wof:name":"Landfrisch Molkerei regGenmbH",
    "wof:placetype":"venue"
},
  "geometry": {"coordinates":[14.0191411972,48.1626815796],"type":"Point"}
}