{
  "type": "Feature",
  "properties": {
    "iso:country":"AT",
    "sg:address":"Schubertstr 30",
    "sg:city":"Wels",
    "sg:orig_category":"Molkereien U Molkereiprodukte",
    "sg:phone":"+43 4372 42469960",
    "sg:postcode":"4600",
    "sg:province":"Ober\u00f6sterreich",
    "wof:name":"Landfrisch Molkerei regGenmbH",
    "wof:placetype":"venue"
},
  "geometry": {"coordinates":[14.0191411972,48.1626815796],"type":"Point"}
}