{
  "type": "Feature",
  "properties": {
    "iso:country":"AT",
    "sg:address":"Arbesg 15",
    "sg:city":"Hall in Tirol",
    "sg:orig_category":"Damenmoden",
    "sg:phone":"+43 5223 57128",
    "sg:postcode":"6060",
    "sg:province":"Tirol",
    "wof:name":"Halbedel GmbH & Co KG",
    "wof:placetype":"venue"
},
  "geometry": {"coordinates":[11.5065698624,47.2818107605],"type":"Point"}
}