{
  "type": "Feature",
  "properties": {
    "addr:full":"Handelszentrum 7 Bergheim Salzburg 5101",
    "addr:housenumber":"7",
    "addr:postcode":"5101",
    "addr:street":"Handelszentrum;Salzburg",
    "iso:country":"AT",
    "sg:address":"Handelszentrum 7",
    "sg:city":"Bergheim",
    "sg:classifiers":[
        {
            "category":"Professional",
            "subcategory":"Detective & Security Services",
            "type":"Services"
        }
    ],
    "sg:phone":"+43 662 452460",
    "sg:postcode":"5101",
    "sg:province":"Salzburg",
    "sg:tags":[
        "access",
        "control",
        "ac",
        "system"
    ],
    "sg:website":"sensormatic.com",
    "wof:name":"ADT-Sensormatic Ges.m.b.H.",
    "wof:placetype":"venue"
},
  "geometry": {"coordinates":[13.0413331985,47.8418159485],"type":"Point"}
}