{
  "type": "Feature",
  "properties": {
    "addr:full":"Krappfelder Str 24 Treibach-Althofen K\u00e4rnten 9330",
    "addr:postcode":"9330",
    "addr:street":"Str 24 Treibach-Althofen Kaernten",
    "iso:country":"AT",
    "sg:address":"Krappfelder Str 24",
    "sg:city":"Treibach-Althofen",
    "sg:orig_category":"Autohandel",
    "sg:phone":"+43 4262 47770",
    "sg:postcode":"9330",
    "sg:province":"K\u00e4rnten",
    "wof:name":"Autohaus Hofst\u00e4tter GmbH",
    "wof:placetype":"venue"
},
  "geometry": {"coordinates":[14.4634714127,46.8656959534],"type":"Point"}
}