{
  "type": "Feature",
  "properties": {
    "addr:full":"Parzweg 2 Alkoven Ober\u00f6sterreich 4072",
    "addr:housenumber":"2",
    "addr:postcode":"4072",
    "addr:street":"Parzweg",
    "iso:country":"AT",
    "sg:address":"Parzweg 2",
    "sg:city":"Alkoven",
    "sg:orig_category":"ChildrenS Furniture",
    "sg:phone":"+43 7274 6374",
    "sg:postcode":"4072",
    "sg:province":"Ober\u00f6sterreich",
    "sg:website":"max-niedermayr.at",
    "wof:name":"Tischlereiwerkst\u00e4tte Maximilian Niedermayr",
    "wof:placetype":"venue"
},
  "geometry": {"coordinates":[14.115275383,48.2825241089],"type":"Point"}
}