{
  "type": "Feature",
  "properties": {
    "iso:country":"AT",
    "sg:address":"Annastr 12",
    "sg:city":"Gmunden",
    "sg:orig_category":"Bauunternehmen",
    "sg:phone":"+43 761263869",
    "sg:postcode":"4810",
    "sg:province":"Ober\u00f6sterreich",
    "wof:name":"CH Wohnbau GesmbH Erdbau Kraschansky",
    "wof:placetype":"venue"
},
  "geometry": {"coordinates":[13.8074188232,47.9160804749],"type":"Point"}
}