{
  "type": "Feature",
  "properties": {
    "iso:country":"AT",
    "sg:address":"Wr Neust\u00e4dter Str 112",
    "sg:city":"Kottingbrunn",
    "sg:classifiers":[
        {
            "category":"Professional",
            "subcategory":"Computer Services",
            "type":"Services"
        }
    ],
    "sg:phone":"+43 2252 746260",
    "sg:postcode":"2542",
    "sg:province":"Nieder\u00f6sterreich",
    "sg:tags":[
        "software"
    ],
    "sg:website":"isap.at",
    "wof:name":"Isap Datenverarbeitungs GesmbH",
    "wof:placetype":"venue"
},
  "geometry": {"coordinates":[16.2285327911,47.9514656067],"type":"Point"}
}