{
  "type": "Feature",
  "properties": {
    "addr:full":"Raiffeisenstr 2 Elsbethen-Glasenbach Salzburg 5061",
    "addr:housenumber":"2",
    "addr:postcode":"5061",
    "addr:street":"Raiffeisenstr;Salzburg",
    "iso:country":"AT",
    "sg:address":"Raiffeisenstr 2",
    "sg:city":"Elsbethen-Glasenbach",
    "sg:orig_category":"Weiterbildungsinstitute M Allg U Berufl Bildungsangebot",
    "sg:phone":"+43 662 80477520",
    "sg:postcode":"5061",
    "sg:province":"Salzburg",
    "wof:name":"Katholisches Bildungswerk Salzburg",
    "wof:placetype":"venue"
},
  "geometry": {"coordinates":[13.0922317505,47.769405365],"type":"Point"}
}