{
  "type": "Feature",
  "properties": {
    "iso:country":"AT",
    "sg:address":"Obergreutschach 32",
    "sg:city":"Griffen",
    "sg:orig_category":"Pensionen / Privatzimmer",
    "sg:phone":"+43 4233 2380",
    "sg:postcode":"9112",
    "sg:province":"K\u00e4rnten",
    "wof:name":"Bauernhof Juritsch",
    "wof:placetype":"venue"
},
  "geometry": {"coordinates":[14.6839551926,46.7536659241],"type":"Point"}
}