{
  "type": "Feature",
  "properties": {
    "addr:full":"Schnettraweg 5 Gr\u00e4n Tirol 6673",
    "addr:housenumber":"5",
    "addr:postcode":"6673",
    "addr:street":"Schnettraweg;Tirol",
    "iso:country":"AT",
    "sg:address":"Schnettraweg 5",
    "sg:city":"Gr\u00e4n",
    "sg:orig_category":"Pensionen / Privatzimmer",
    "sg:phone":"+43 4356 756495",
    "sg:postcode":"6673",
    "sg:province":"Tirol",
    "wof:name":"Landhaus Schnettra",
    "wof:placetype":"venue"
},
  "geometry": {"coordinates":[10.5586223602,47.4935417175],"type":"Point"}
}