{
  "type": "Feature",
  "properties": {
    "iso:country":"AT",
    "sg:address":"Mittelbergeramt 19 ",
    "sg:city":"Gf\u00f6hl",
    "sg:classifiers":[
        {
            "category":"Sports & Exercise",
            "subcategory":"Playing Field",
            "type":"Entertainment"
        }
    ],
    "sg:phone":"+43 4327 1686840",
    "sg:postcode":"3542",
    "sg:province":"Nieder\u00f6sterreich",
    "sg:tags":[
        "game"
    ],
    "wof:name":"PETER KOCH",
    "wof:placetype":"venue"
},
  "geometry": {"coordinates":[15.484869957,48.5275497437],"type":"Point"}
}