{
  "type": "Feature",
  "properties": {
    "addr:full":"Nr 7 Geinberg Ober\u00f6sterreich 4943",
    "addr:postcode":"4943",
    "addr:street":"Nr;Geinberg",
    "iso:country":"AT",
    "sg:address":"Nr 7",
    "sg:city":"Geinberg",
    "sg:orig_category":"Estriche",
    "sg:phone":"+43 7723 83010",
    "sg:postcode":"4943",
    "sg:province":"Ober\u00f6sterreich",
    "wof:name":"Penzenstadler Estrichb\u00f6rse GmbH & Co KG",
    "wof:placetype":"venue"
},
  "geometry": {"coordinates":[13.2941713333,48.2649269104],"type":"Point"}
}