{
  "type": "Feature",
  "properties": {
    "addr:full":"Bl\u00fctenweg 5 Wels Ober\u00f6sterreich 4600",
    "addr:housenumber":"5",
    "addr:postcode":"4600",
    "addr:street":"Bluetenweg;Oberoesterreich",
    "iso:country":"AT",
    "sg:address":"Bl\u00fctenweg 5",
    "sg:city":"Wels",
    "sg:classifiers":[
        {
            "category":"Taxi",
            "type":"Transportation"
        }
    ],
    "sg:phone":"+43 7242 46005",
    "sg:postcode":"4600",
    "sg:province":"Ober\u00f6sterreich",
    "sg:tags":[
        "personentransporte",
        "u"
    ],
    "wof:name":"Weiss Elisabeth",
    "wof:placetype":"venue"
},
  "geometry": {"coordinates":[13.6517000198,52.3689498901],"type":"Point"}
}