{
  "type": "Feature",
  "properties": {
    "addr:full":"Kirchenpl 6 Schrattenberg Nieder\u00f6sterreich 2172",
    "addr:housenumber":"6",
    "addr:postcode":"2172",
    "addr:street":"Kirchenpl",
    "iso:country":"AT",
    "sg:address":"Kirchenpl 6",
    "sg:city":"Schrattenberg",
    "sg:orig_category":"Fleischhauereien",
    "sg:phone":"+43 2555 2334",
    "sg:postcode":"2172",
    "sg:province":"Nieder\u00f6sterreich",
    "wof:name":"Zesch Franz",
    "wof:placetype":"venue"
},
  "geometry": {"coordinates":[16.7222423553,48.7244186401],"type":"Point"}
}