{
  "type": "Feature",
  "properties": {
    "addr:full":"Frimmelgasse 4 Wien Wien 1190",
    "addr:housenumber":"4",
    "addr:postcode":"1190",
    "addr:street":"Frimmelgasse",
    "iso:country":"AT",
    "sg:address":"Frimmelgasse 4",
    "sg:city":"Wien",
    "sg:classifiers":[
        {
            "category":"Manufacturing",
            "subcategory":"Petroleum Products",
            "type":"Manufacturing & Wholesale Goods"
        }
    ],
    "sg:phone":"+43 1 37045060",
    "sg:postcode":"1190",
    "sg:province":"Wien",
    "sg:tags":[
        "measuring",
        "equipment"
    ],
    "sg:website":"gammaoil.at",
    "wof:name":"Gamma Mineral\u00f6lhandelsges.m.b.H.",
    "wof:placetype":"venue"
},
  "geometry": {"coordinates":[16.3572788239,48.2599105835],"type":"Point"}
}