{
  "type": "Feature",
  "properties": {
    "addr:full":"Eggenberg 4 Vorchdorf Ober\u00f6sterreich 4655",
    "addr:housenumber":"4",
    "addr:postcode":"4655",
    "addr:street":"Eggenberg",
    "iso:country":"AT",
    "sg:address":"Eggenberg 4",
    "sg:city":"Vorchdorf",
    "sg:orig_category":"Pensionen / Privatzimmer",
    "sg:phone":"+43 76146465",
    "sg:postcode":"4655",
    "sg:province":"Ober\u00f6sterreich",
    "wof:name":"Pesendorfer Franz",
    "wof:placetype":"venue"
},
  "geometry": {"coordinates":[13.9262447357,47.9914703369],"type":"Point"}
}