{
  "type": "Feature",
  "properties": {
    "addr:full":"Herrengasse 19 Th\u00fcringen Vorarlberg 6712",
    "addr:housenumber":"19",
    "addr:postcode":"6712",
    "addr:street":"Herrengasse",
    "iso:country":"AT",
    "sg:address":"Herrengasse 19",
    "sg:city":"Th\u00fcringen",
    "sg:classifiers":[
        {
            "category":"Retail",
            "subcategory":"Portrait Studio",
            "type":"Services"
        }
    ],
    "sg:phone":"+43 5550 24200",
    "sg:postcode":"6712",
    "sg:province":"Vorarlberg",
    "sg:tags":[
        "bathroom",
        "renovation"
    ],
    "sg:website":"kueng-installationen.at",
    "wof:name":"K\u00fcng Installationen GmbH",
    "wof:placetype":"venue"
},
  "geometry": {"coordinates":[9.7624731064,47.2006607056],"type":"Point"}
}