{
  "type": "Feature",
  "properties": {
    "addr:full":"Nr 4 Kirchbach in Steiermark Steiermark 8082",
    "addr:postcode":"8082",
    "addr:street":"Nr",
    "iso:country":"AT",
    "sg:address":"Nr 4",
    "sg:city":"Kirchbach in Steiermark",
    "sg:orig_category":"Fahrschulen",
    "sg:phone":"+43 3116 2371",
    "sg:postcode":"8082",
    "sg:province":"Steiermark",
    "sg:website":"fahrschule-kirchbach.com",
    "wof:name":"Fahrschule Kirchbach Logistik GesmbH",
    "wof:placetype":"venue"
},
  "geometry": {"coordinates":[15.6588878632,46.937297821],"type":"Point"}
}