{
  "type": "Feature",
  "properties": {
    "addr:full":"L\u00f6wensteinstr 62/1 Wien Wien 1220",
    "addr:housenumber":"62 / 1",
    "addr:postcode":"1220",
    "addr:street":"Loewensteinstr",
    "iso:country":"AT",
    "sg:address":"L\u00f6wensteinstr 62/1",
    "sg:city":"Wien",
    "sg:orig_category":"Massagen",
    "sg:phone":"+43 4317 743494",
    "sg:postcode":"1220",
    "sg:province":"Wien",
    "wof:name":"Hellmann Christian",
    "wof:placetype":"venue"
},
  "geometry": {"coordinates":[16.5138549805,48.2047348022],"type":"Point"}
}