{
  "type": "Feature",
  "properties": {
    "addr:full":"Friedhofg 25 Judenburg Steiermark 8750",
    "addr:housenumber":"25",
    "addr:postcode":"8750",
    "addr:street":"Friedhofg",
    "iso:country":"AT",
    "sg:address":"Friedhofg 25",
    "sg:city":"Judenburg",
    "sg:orig_category":"Maler, Anstreicher U Lackierer",
    "sg:phone":"+43 4335 7282068",
    "sg:postcode":"8750",
    "sg:province":"Steiermark",
    "wof:name":"Poharec Walter",
    "wof:placetype":"venue"
},
  "geometry": {"coordinates":[14.653881073,47.1664772034],"type":"Point"}
}