{
  "type": "Feature",
  "properties": {
    "addr:full":"Schillerpl 2 Feldkirchen in K\u00e4rnten K\u00e4rnten 9560",
    "addr:housenumber":"2",
    "addr:postcode":"9560",
    "addr:street":"Schillerpl;Kaernten",
    "iso:country":"AT",
    "sg:address":"Schillerpl 2",
    "sg:city":"Feldkirchen in K\u00e4rnten",
    "sg:orig_category":"Immobilienverwaltungen",
    "sg:phone":"+43 4342 763132",
    "sg:postcode":"9560",
    "sg:province":"K\u00e4rnten",
    "wof:name":"Nindler-Moser Erich Immobilien KEG",
    "wof:placetype":"venue"
},
  "geometry": {"coordinates":[14.0921669006,46.7245788574],"type":"Point"}
}