{
  "type": "Feature",
  "properties": {
    "addr:full":"Hauptstr 27 Mannersdorf am Leithagebirge Nieder\u00f6sterreich 2452",
    "addr:housenumber":"27",
    "addr:postcode":"2452",
    "addr:street":"Hauptstr",
    "iso:country":"AT",
    "sg:address":"Hauptstr 27",
    "sg:city":"Mannersdorf am Leithagebirge",
    "sg:orig_category":"Steinmetzbetriebe",
    "sg:phone":"+43 2168 623850",
    "sg:postcode":"2452",
    "sg:province":"Nieder\u00f6sterreich",
    "wof:name":"Opferkuh Friedrich GesmbH",
    "wof:placetype":"venue"
},
  "geometry": {"coordinates":[16.6009368896,47.9732055664],"type":"Point"}
}