{
  "type": "Feature",
  "properties": {
    "iso:country":"AT",
    "sg:address":"Hauptstr 53",
    "sg:city":"Rudersdorf",
    "sg:orig_category":"Raumausstattung",
    "sg:phone":"+43 3382 71777",
    "sg:postcode":"7571",
    "sg:province":"Burgenland",
    "wof:name":"Raumausstattung Weber",
    "wof:placetype":"venue"
},
  "geometry": {"coordinates":[16.1237163544,47.0470352173],"type":"Point"}
}