{
  "type": "Feature",
  "properties": {
    "iso:country":"AT",
    "sg:address":"Framrach 21",
    "sg:city":"St. Andr\u00e4",
    "sg:orig_category":"Transportunternehmen",
    "sg:phone":"+43 4358 2595",
    "sg:postcode":"9433",
    "sg:province":"K\u00e4rnten",
    "wof:name":"Watl Josef",
    "wof:placetype":"venue"
},
  "geometry": {"coordinates":[14.818479538,46.7410507202],"type":"Point"}
}