{
  "type": "Feature",
  "properties": {
    "addr:full":"Klosterg 7a Mautern in Steiermark Steiermark 8774",
    "addr:housenumber":"7a",
    "addr:postcode":"8774",
    "addr:street":"Klosterg",
    "iso:country":"AT",
    "sg:address":"Klosterg 7a",
    "sg:city":"Mautern in Steiermark",
    "sg:orig_category":"Hauptschulen",
    "sg:phone":"+43 4338 453112",
    "sg:postcode":"8774",
    "sg:province":"Steiermark",
    "wof:name":"Musikhauptschule",
    "wof:placetype":"venue"
},
  "geometry": {"coordinates":[14.8243312836,47.3990478516],"type":"Point"}
}