{
  "type": "Feature",
  "properties": {
    "addr:full":"Heizerg 1 Wiener Neustadt Nieder\u00f6sterreich 2700",
    "addr:housenumber":"1",
    "addr:postcode":"2700",
    "addr:street":"Heizerg",
    "iso:country":"AT",
    "sg:address":"Heizerg 1",
    "sg:city":"Wiener Neustadt",
    "sg:orig_category":"Genossenschaften",
    "sg:phone":"+43 4326 22226890",
    "sg:postcode":"2700",
    "sg:province":"Nieder\u00f6sterreich",
    "wof:name":"Neue Heimat Gemeinn\u00fctzige Wohnungs- u SiedlungsgesmbH",
    "wof:placetype":"venue"
},
  "geometry": {"coordinates":[16.2641448975,47.8318862915],"type":"Point"}
}