{
  "type": "Feature",
  "properties": {
    "iso:country":"AT",
    "sg:address":"Trauttmansdorffgasse 28",
    "sg:city":"Wien",
    "sg:classifiers":[
        {
            "category":"Professional",
            "subcategory":"Advertising",
            "type":"Services"
        }
    ],
    "sg:phone":"+43 1 8795900",
    "sg:postcode":"1130",
    "sg:province":"Wien",
    "sg:tags":[
        "space"
    ],
    "sg:website":"containad.com",
    "wof:name":"contain:ad Containerwerbung GmbH",
    "wof:placetype":"venue"
},
  "geometry": {"coordinates":[16.2962627411,48.1844863892],"type":"Point"}
}