{
  "type": "Feature",
  "properties": {
    "iso:country":"AT",
    "sg:address":"Walfischg 1",
    "sg:city":"Wien",
    "sg:classifiers":[
        {
            "category":"Restaurant",
            "type":"Food & Drink"
        }
    ],
    "sg:phone":"+43 4315 122939",
    "sg:postcode":"1010",
    "sg:province":"Wien",
    "wof:name":"Kaspar Gerald Prof Mag",
    "wof:placetype":"venue"
},
  "geometry": {"coordinates":[16.3705673218,48.2036895752],"type":"Point"}
}