{
  "type": "Feature",
  "properties": {
    "addr:full":"Nr 166 Gurten Ober\u00f6sterreich 4942",
    "addr:postcode":"4942",
    "addr:street":"Nr 166",
    "iso:country":"AT",
    "sg:address":"Nr 166",
    "sg:city":"Gurten",
    "sg:orig_category":"Cad/Cae/Cam/Cim-Systeme",
    "sg:phone":"+43 7757 70030",
    "sg:postcode":"4942",
    "sg:province":"Ober\u00f6sterreich",
    "wof:name":"Duft Reinhold Computer-Dienstleistungs-Center",
    "wof:placetype":"venue"
},
  "geometry": {"coordinates":[13.3448448181,48.2405700684],"type":"Point"}
}