{
  "type": "Feature",
  "properties": {
    "iso:country":"AT",
    "sg:address":"Pfaffing 24",
    "sg:city":"Saalfelden am Steinernen Meer",
    "sg:orig_category":"Transportunternehmen",
    "sg:phone":"+43 6582 723280",
    "sg:postcode":"5760",
    "sg:province":"Salzburg",
    "wof:name":"Jung-Trans-Transport und HandelsgesmbH",
    "wof:placetype":"venue"
},
  "geometry": {"coordinates":[12.8589010239,47.4167938232],"type":"Point"}
}