{
  "type": "Feature",
  "properties": {
    "addr:full":"Pfaffing 24 Saalfelden am Steinernen Meer Salzburg 5760",
    "addr:housenumber":"24",
    "addr:postcode":"5760",
    "addr:street":"Pfaffing;Salzburg",
    "iso:country":"AT",
    "sg:address":"Pfaffing 24",
    "sg:city":"Saalfelden am Steinernen Meer",
    "sg:orig_category":"Transportunternehmen",
    "sg:phone":"+43 6582 723280",
    "sg:postcode":"5760",
    "sg:province":"Salzburg",
    "wof:name":"Jung-Trans-Transport und HandelsgesmbH",
    "wof:placetype":"venue"
},
  "geometry": {"coordinates":[12.8589010239,47.4167938232],"type":"Point"}
}