{
  "type": "Feature",
  "properties": {
    "addr:full":"Schwarzstr 35 Salzburg Salzburg 5020",
    "addr:housenumber":"35",
    "addr:postcode":"5020",
    "addr:street":"Schwarzstr;Salzburg",
    "iso:country":"AT",
    "sg:address":"Schwarzstr 35",
    "sg:city":"Salzburg",
    "sg:orig_category":"Volksschulen",
    "sg:phone":"+43 662 8740160",
    "sg:postcode":"5020",
    "sg:province":"Salzburg",
    "wof:name":"Private Volksschule f M\u00e4dchen d Schulschwestern",
    "wof:placetype":"venue"
},
  "geometry": {"coordinates":[13.0389308929,47.8063049316],"type":"Point"}
}