{
  "type": "Feature",
  "properties": {
    "addr:full":"Nr 22 Hausleiten Nieder\u00f6sterreich 3464",
    "addr:postcode":"3464",
    "addr:street":"Nr;Niederoesterreich",
    "iso:country":"AT",
    "sg:address":"Nr 22",
    "sg:city":"Hausleiten",
    "sg:orig_category":"Transportunternehmen",
    "sg:phone":"+43 2265 6923",
    "sg:postcode":"3464",
    "sg:province":"Nieder\u00f6sterreich",
    "wof:name":"Pisecker Josef",
    "wof:placetype":"venue"
},
  "geometry": {"coordinates":[16.1025238037,48.393989563],"type":"Point"}
}