{
  "type": "Feature",
  "properties": {
    "addr:full":"Schikanederg 12 Wien Wien 1040",
    "addr:housenumber":"12",
    "addr:postcode":"1040",
    "addr:street":"Schikanederg",
    "iso:country":"AT",
    "sg:address":"Schikanederg 12",
    "sg:city":"Wien",
    "sg:orig_category":"Kontaktlinsenoptiker",
    "sg:phone":"+43 1 5861399",
    "sg:postcode":"1040",
    "sg:province":"Wien",
    "wof:name":"Koller Anton",
    "wof:placetype":"venue"
},
  "geometry": {"coordinates":[16.3635234833,48.1977157593],"type":"Point"}
}