{
  "type": "Feature",
  "properties": {
    "addr:full":"Hauptpl 13 Korneuburg Nieder\u00f6sterreich 2100",
    "addr:housenumber":"13",
    "addr:postcode":"2100",
    "addr:street":"Hauptpl;Niederoesterreich",
    "iso:country":"AT",
    "sg:address":"Hauptpl 13",
    "sg:city":"Korneuburg",
    "sg:orig_category":"Fleischhauereien",
    "sg:phone":"+43 2262 72104",
    "sg:postcode":"2100",
    "sg:province":"Nieder\u00f6sterreich",
    "wof:name":"Pfennigbauer Rudolf",
    "wof:placetype":"venue"
},
  "geometry": {"coordinates":[16.3342723846,48.3442306519],"type":"Point"}
}