{
  "type": "Feature",
  "properties": {
    "iso:country":"AT",
    "sg:address":"Hauptpl 13",
    "sg:city":"Korneuburg",
    "sg:orig_category":"Fleischhauereien",
    "sg:phone":"+43 2262 72104",
    "sg:postcode":"2100",
    "sg:province":"Nieder\u00f6sterreich",
    "wof:name":"Pfennigbauer Rudolf",
    "wof:placetype":"venue"
},
  "geometry": {"coordinates":[16.3342723846,48.3442306519],"type":"Point"}
}