{
  "type": "Feature",
  "properties": {
    "addr:full":"Hauptstr 21 Thaya Nieder\u00f6sterreich 3842",
    "addr:housenumber":"21",
    "addr:postcode":"3842",
    "addr:street":"Hauptstr",
    "iso:country":"AT",
    "sg:address":"Hauptstr 21",
    "sg:city":"Thaya",
    "sg:orig_category":"Tischlereien",
    "sg:phone":"+43 2842 526730",
    "sg:postcode":"3842",
    "sg:province":"Nieder\u00f6sterreich",
    "wof:name":"Bayer Helmut",
    "wof:placetype":"venue"
},
  "geometry": {"coordinates":[15.2785825729,48.8556289673],"type":"Point"}
}