{
  "type": "Feature",
  "properties": {
    "addr:full":"Nr 65 Pertisau Tirol 6213",
    "addr:postcode":"6213",
    "addr:street":"Nr;Pertisau",
    "iso:country":"AT",
    "sg:address":"Nr 65",
    "sg:city":"Pertisau",
    "sg:orig_category":"Bootsvermietung",
    "sg:phone":"+43 5243 5989",
    "sg:postcode":"6213",
    "sg:province":"Tirol",
    "wof:name":"Bootsvermietung Pertisau",
    "wof:placetype":"venue"
},
  "geometry": {"coordinates":[11.6961479187,47.4396896362],"type":"Point"}
}