{
  "type": "Feature",
  "properties": {
    "addr:full":"Anger 384 Lech Vorarlberg 6764",
    "addr:housenumber":"384",
    "addr:postcode":"6764",
    "addr:street":"Anger",
    "iso:country":"AT",
    "sg:address":"Anger 384",
    "sg:city":"Lech",
    "sg:orig_category":"Pensionen / Privatzimmer",
    "sg:phone":"+43 4355 8324240",
    "sg:postcode":"6764",
    "sg:province":"Vorarlberg",
    "wof:name":"Fortuna Haus Anger",
    "wof:placetype":"venue"
},
  "geometry": {"coordinates":[10.1481189728,47.2123756409],"type":"Point"}
}