{
  "type": "Feature",
  "properties": {
    "addr:full":"Weineckg 19 Stockerau Nieder\u00f6sterreich 2000",
    "addr:housenumber":"19",
    "addr:postcode":"2000",
    "addr:street":"Weineckg",
    "iso:country":"AT",
    "sg:address":"Weineckg 19",
    "sg:city":"Stockerau",
    "sg:orig_category":"Dachdeckereien",
    "sg:phone":"+43 2266 62345",
    "sg:postcode":"2000",
    "sg:province":"Nieder\u00f6sterreich",
    "wof:name":"Zickbauer Dachdeckerei-Spenglerei GmbH",
    "wof:placetype":"venue"
},
  "geometry": {"coordinates":[16.2241325378,48.3833274841],"type":"Point"}
}