{
  "type": "Feature",
  "properties": {
    "addr:full":"Am Sonnenhang 25 Leoben Steiermark 8700",
    "addr:housenumber":"25",
    "addr:postcode":"8700",
    "addr:street":"Am Sonnenhang",
    "iso:country":"AT",
    "sg:address":"Am Sonnenhang 25",
    "sg:city":"Leoben",
    "sg:orig_category":"Musikgruppen",
    "sg:phone":"+43 676 3980968",
    "sg:postcode":"8700",
    "sg:province":"Steiermark",
    "wof:name":"Die Seegrabner",
    "wof:placetype":"venue"
},
  "geometry": {"coordinates":[15.0758085251,47.3628883362],"type":"Point"}
}