{
  "type": "Feature",
  "properties": {
    "addr:full":"Wasserzeile 3 Apetlon Burgenland 7143",
    "addr:housenumber":"3",
    "addr:postcode":"7143",
    "addr:street":"Wasserzeile",
    "iso:country":"AT",
    "sg:address":"Wasserzeile 3",
    "sg:city":"Apetlon",
    "sg:orig_category":"Heurigen / Buschenschank",
    "sg:phone":"+43 4321 752375",
    "sg:postcode":"7143",
    "sg:province":"Burgenland",
    "wof:name":"Dorfheuriger Klinger",
    "wof:placetype":"venue"
},
  "geometry": {"coordinates":[16.8293952942,47.7421035767],"type":"Point"}
}