{
  "type": "Feature",
  "properties": {
    "addr:full":"Mariahilfer Str 120 Wien Wien 1070",
    "addr:housenumber":"120",
    "addr:postcode":"1070",
    "iso:country":"AT",
    "sg:address":"Mariahilfer Str 120",
    "sg:city":"Wien",
    "sg:orig_category":"Juwelen, Gold- U Silberwaren / Einzelhandel",
    "sg:phone":"+43 4315 240889",
    "sg:postcode":"1070",
    "sg:province":"Wien",
    "wof:name":"Navarro Juwelier",
    "wof:placetype":"venue"
},
  "geometry": {"coordinates":[16.3420772552,48.1964912415],"type":"Point"}
}