{
  "type": "Feature",
  "properties": {
    "iso:country":"AT",
    "sg:address":"Dr.-Arming-Strasse 5",
    "sg:city":"Wels",
    "sg:classifiers":[
        {
            "category":"Government",
            "subcategory":"Post Office",
            "type":"Public Place"
        }
    ],
    "sg:phone":"+43 7242 661040",
    "sg:postcode":"4600",
    "sg:province":"Ober\u00f6sterreich",
    "sg:tags":[
        "date",
        "stamp"
    ],
    "sg:website":"colop.com/",
    "wof:name":"COLOP Stempelerzeugung Skopek Ges.m.b.H. & Co KG",
    "wof:placetype":"venue"
},
  "geometry": {"coordinates":[14.0143976212,48.1674156189],"type":"Point"}
}