{
  "type": "Feature",
  "properties": {
    "addr:full":"Luna 75 Kundl Tirol 6250",
    "addr:housenumber":"75",
    "addr:postcode":"6250",
    "addr:street":"Luna;Tirol",
    "iso:country":"AT",
    "sg:address":"Luna 75",
    "sg:city":"Kundl",
    "sg:orig_category":"Putze",
    "sg:phone":"+43 5338 73140",
    "sg:postcode":"6250",
    "sg:province":"Tirol",
    "wof:name":"Quarzolith Putz- und M\u00f6rtelerzeugung Kundl GesmbH",
    "wof:placetype":"venue"
},
  "geometry": {"coordinates":[12.0143556595,47.471408844],"type":"Point"}
}