{
  "type": "Feature",
  "properties": {
    "iso:country":"AT",
    "sg:address":"Nr 116",
    "sg:city":"Strallegg",
    "sg:orig_category":"Lebensmittel / Einzelhandel",
    "sg:phone":"+43 3174 22240",
    "sg:postcode":"8192",
    "sg:province":"Steiermark",
    "wof:name":"Riegler Harald",
    "wof:placetype":"venue"
},
  "geometry": {"coordinates":[15.7248001099,47.4109153748],"type":"Point"}
}