{
  "type": "Feature",
  "properties": {
    "iso:country":"AT",
    "sg:address":"Piaristeng 13/1",
    "sg:city":"Wien",
    "sg:orig_category":"Baumeister",
    "sg:phone":"+43 1 52363980",
    "sg:postcode":"1080",
    "sg:province":"Wien",
    "wof:name":"Fuchs Roland Ing GmbH",
    "wof:placetype":"venue"
},
  "geometry": {"coordinates":[16.3508644104,48.2075119019],"type":"Point"}
}