{
  "type": "Feature",
  "properties": {
    "addr:full":"Wolfersbachweg 2 Kraubath an der Mur Steiermark 8714",
    "addr:housenumber":"2",
    "addr:postcode":"8714",
    "addr:street":"Wolfersbachweg",
    "iso:country":"AT",
    "sg:address":"Wolfersbachweg 2",
    "sg:city":"Kraubath an der Mur",
    "sg:orig_category":"Baumschulen",
    "sg:phone":"+43 3832 2410",
    "sg:postcode":"8714",
    "sg:province":"Steiermark",
    "wof:name":"Steirische Landesforstg\u00e4rten, Au\u00dfenstelle-Kraubath",
    "wof:placetype":"venue"
},
  "geometry": {"coordinates":[14.9521245956,47.3170852661],"type":"Point"}
}