{
  "type": "Feature",
  "properties": {
    "iso:country":"AT",
    "sg:address":"Sylvester-Jordan-Str 5",
    "sg:city":"Axams",
    "sg:orig_category":"Fu\u00c3\u0178pflege U Fu\u00c3\u0178pflegesalons",
    "sg:phone":"+43 4366 44453337",
    "sg:postcode":"6094",
    "sg:province":"Tirol",
    "wof:name":"Fuss Fit Praxmarer Christiane",
    "wof:placetype":"venue"
},
  "geometry": {"coordinates":[11.2793731689,47.2312889099],"type":"Point"}
}