{
  "type": "Feature",
  "properties": {
    "iso:country":"AT",
    "sg:address":"Rathausstr 4",
    "sg:city":"Amstetten",
    "sg:orig_category":"Blumeneinzelhandel",
    "sg:phone":"+43 7472 62450",
    "sg:postcode":"3300",
    "sg:province":"Nieder\u00f6sterreich",
    "wof:name":"Lindlbauer Renate",
    "wof:placetype":"venue"
},
  "geometry": {"coordinates":[14.8710279465,48.1229171753],"type":"Point"}
}