{
  "type": "Feature",
  "properties": {
    "addr:full":"Arbeiterg 52 Wien Wien 1050",
    "addr:housenumber":"52",
    "addr:postcode":"1050",
    "addr:street":"Arbeiterg",
    "iso:country":"AT",
    "sg:address":"Arbeiterg 52",
    "sg:city":"Wien",
    "sg:classifiers":[
        {
            "category":"Shopping",
            "subcategory":"Thrift Store",
            "type":"Retail Goods"
        }
    ],
    "sg:phone":"+43 1 5449701",
    "sg:postcode":"1050",
    "sg:province":"Wien",
    "sg:tags":[
        "second-hand-shops"
    ],
    "wof:name":"Kinderfundgrube",
    "wof:placetype":"venue"
},
  "geometry": {"coordinates":[16.3462657928,48.1843299866],"type":"Point"}
}