{
  "type": "Feature",
  "properties": {
    "addr:full":"Voitg 2 Wien Wien 1220",
    "addr:housenumber":"2",
    "addr:postcode":"1220",
    "addr:street":"Voitg",
    "iso:country":"AT",
    "sg:address":"Voitg 2",
    "sg:city":"Wien",
    "sg:orig_category":"Druckereien",
    "sg:phone":"+43 1 25945060",
    "sg:postcode":"1220",
    "sg:province":"Wien",
    "wof:name":"S.PRINT R. Sporr GmbH & Co KG",
    "wof:placetype":"venue"
},
  "geometry": {"coordinates":[16.444606781,48.2497138977],"type":"Point"}
}