{
  "type": "Feature",
  "properties": {
    "addr:full":"Nr 37 G\u00fcssing Burgenland 7540",
    "addr:postcode":"7540",
    "addr:street":"Nr 37 Guessing",
    "iso:country":"AT",
    "sg:address":"Nr 37",
    "sg:city":"G\u00fcssing",
    "sg:orig_category":"Autoreparatur",
    "sg:phone":"+43 3328 32764",
    "sg:postcode":"7540",
    "sg:province":"Burgenland",
    "wof:name":"Scherner Wolfgang",
    "wof:placetype":"venue"
},
  "geometry": {"coordinates":[16.8418807983,47.9491081238],"type":"Point"}
}