{
  "type": "Feature",
  "properties": {
    "addr:full":"Hamplpl 2 Bad Hofgastein Salzburg 5630",
    "addr:housenumber":"2",
    "addr:postcode":"5630",
    "addr:street":"Hamplpl;Salzburg",
    "iso:country":"AT",
    "sg:address":"Hamplpl 2",
    "sg:city":"Bad Hofgastein",
    "sg:classifiers":[
        {
            "category":"Travel",
            "subcategory":"Hotels & Motels",
            "type":"Entertainment"
        }
    ],
    "sg:phone":"+43 6432 67590",
    "sg:postcode":"5630",
    "sg:province":"Salzburg",
    "wof:name":"Panorama Appartementhotel",
    "wof:placetype":"venue"
},
  "geometry": {"coordinates":[13.1052074432,47.1707801819],"type":"Point"}
}