{
  "type": "Feature",
  "properties": {
    "iso:country":"AT",
    "sg:address":"Nr 46",
    "sg:city":"Eibiswald",
    "sg:orig_category":"Fotografen",
    "sg:phone":"+43 3466 42304",
    "sg:postcode":"8552",
    "sg:province":"Steiermark",
    "wof:name":"Foto Strametz",
    "wof:placetype":"venue"
},
  "geometry": {"coordinates":[15.2274599075,46.6824150085],"type":"Point"}
}