{
  "type": "Feature",
  "properties": {
    "addr:full":"H\u00f6henstr 13 Linz Ober\u00f6sterreich 4040",
    "addr:housenumber":"13",
    "addr:postcode":"4040",
    "addr:street":"Hoehenstr",
    "iso:country":"AT",
    "sg:address":"H\u00f6henstr 13",
    "sg:city":"Linz",
    "sg:orig_category":"Personalbereitstellung",
    "sg:phone":"+43 732 222740",
    "sg:postcode":"4040",
    "sg:province":"Ober\u00f6sterreich",
    "wof:name":"ACE consulting & engineering GesmbH",
    "wof:placetype":"venue"
},
  "geometry": {"coordinates":[14.2578554153,48.3602561951],"type":"Point"}
}