{
  "type": "Feature",
  "properties": {
    "iso:country":"AT",
    "sg:address":"Hauptstr 19",
    "sg:city":"Krummnu\u00dfbaum",
    "sg:classifiers":[
        {
            "category":"Restaurant",
            "type":"Food & Drink"
        }
    ],
    "sg:phone":"+43 2757 8792",
    "sg:postcode":"3375",
    "sg:province":"Nieder\u00f6sterreich",
    "sg:tags":[
        "pizzeria"
    ],
    "wof:name":"Cicuara Mihajlo",
    "wof:placetype":"venue"
},
  "geometry": {"coordinates":[-90.31578063960001,39.3304100037],"type":"Point"}
}