{
  "type": "Feature",
  "properties": {
    "addr:full":"Wildbachfeld 87 Deutschlandsberg Steiermark 8530",
    "addr:housenumber":"87",
    "addr:postcode":"8530",
    "addr:street":"Wildbachfeld",
    "iso:country":"AT",
    "sg:address":"Wildbachfeld 87",
    "sg:city":"Deutschlandsberg",
    "sg:orig_category":"Werbeagenturen",
    "sg:phone":"+43 3462 7175",
    "sg:postcode":"8530",
    "sg:province":"Steiermark",
    "wof:name":"schenk media",
    "wof:placetype":"venue"
},
  "geometry": {"coordinates":[15.200466156,46.8503570557],"type":"Point"}
}