{
  "type": "Feature",
  "properties": {
    "addr:full":"Rosentaler Strasse 207 Klagenfurt K\u00e4rnten 9020",
    "addr:housenumber":"207",
    "addr:postcode":"9020",
    "addr:street":"Rosentaler Strasse;Kaernten",
    "iso:country":"AT",
    "sg:address":"Rosentaler Strasse 207",
    "sg:city":"Klagenfurt",
    "sg:classifiers":[
        {
            "category":"Health Services",
            "subcategory":"Nursing And Care Facility",
            "type":"Services"
        }
    ],
    "sg:phone":"+43 463 298500",
    "sg:postcode":"9020",
    "sg:province":"K\u00e4rnten",
    "sg:tags":[
        "battery",
        "aid",
        "hearing"
    ],
    "sg:website":"europower-austria.at",
    "wof:name":"EUROPOWER AUSTRIA BATTERIE GmbH",
    "wof:placetype":"venue"
},
  "geometry": {"coordinates":[14.3274202347,46.6254196167],"type":"Point"}
}