{
  "type": "Feature",
  "properties": {
    "addr:full":"Forstweg 2 Eggersdorf Steiermark 8063",
    "addr:housenumber":"2",
    "addr:postcode":"8063",
    "addr:street":"Forstweg",
    "iso:country":"AT",
    "sg:address":"Forstweg 2",
    "sg:city":"Eggersdorf",
    "sg:orig_category":"Physiotherapie",
    "sg:phone":"+43 3117 3393",
    "sg:postcode":"8063",
    "sg:province":"Steiermark",
    "wof:name":"Binder Alexandra Dipl-PT",
    "wof:placetype":"venue"
},
  "geometry": {"coordinates":[15.608048439,47.1257858276],"type":"Point"}
}