{
  "type": "Feature",
  "properties": {
    "addr:full":"Mannsw\u00f6rther Str 65 Schwechat Nieder\u00f6sterreich 2320",
    "addr:postcode":"2320",
    "addr:street":"Str 65 Schwechat Niederoesterreich",
    "iso:country":"AT",
    "sg:address":"Mannsw\u00f6rther Str 65",
    "sg:city":"Schwechat",
    "sg:orig_category":"\u00c3\u201erzte / F Allgemeinmedizin",
    "sg:phone":"+43 1 7068600",
    "sg:postcode":"2320",
    "sg:province":"Nieder\u00f6sterreich",
    "wof:name":"Kanfer-Steinhauer Denise Dr",
    "wof:placetype":"venue"
},
  "geometry": {"coordinates":[16.5133953094,48.147808075],"type":"Point"}
}