{
  "type": "Feature",
  "properties": {
    "addr:full":"Schulstrasse 6 Perg Ober\u00f6sterreich 4320",
    "addr:housenumber":"6",
    "addr:postcode":"4320",
    "addr:street":"Schulstrasse",
    "iso:country":"AT",
    "sg:address":"Schulstrasse 6",
    "sg:city":"Perg",
    "sg:classifiers":[
        {
            "category":"Community Center",
            "subcategory":"Youth",
            "type":"Public Place"
        }
    ],
    "sg:phone":"+43 7262 58080",
    "sg:postcode":"4320",
    "sg:province":"Ober\u00f6sterreich",
    "sg:tags":[
        "tile",
        "border"
    ],
    "wof:name":"Franz Ehrentraut",
    "wof:placetype":"venue"
},
  "geometry": {"coordinates":[14.6306629181,48.2500419617],"type":"Point"}
}