{
  "type": "Feature",
  "properties": {
    "addr:full":"Grieskirchner Str 4 Wels Ober\u00f6sterreich 4600",
    "addr:housenumber":"4",
    "addr:postcode":"4600",
    "addr:street":"Str;Oberoesterreich",
    "iso:country":"AT",
    "sg:address":"Grieskirchner Str 4",
    "sg:city":"Wels",
    "sg:orig_category":"Tankstellen",
    "sg:phone":"+43 7242 41273",
    "sg:postcode":"4600",
    "sg:province":"Ober\u00f6sterreich",
    "wof:name":"Shell Austria GmbH",
    "wof:placetype":"venue"
},
  "geometry": {"coordinates":[14.0248537064,48.1690711975],"type":"Point"}
}