{
  "type": "Feature",
  "properties": {
    "addr:full":"Millerg 29 Wien Wien 1060",
    "addr:housenumber":"29",
    "addr:postcode":"1060",
    "addr:street":"Millerg",
    "iso:country":"AT",
    "sg:address":"Millerg 29",
    "sg:city":"Wien",
    "sg:orig_category":"Elektroinstallationsunternehmen",
    "sg:phone":"+43 1 59759370",
    "sg:postcode":"1060",
    "sg:province":"Wien",
    "sg:website":"itg-gartner.at",
    "wof:name":"Gartner GmbH",
    "wof:placetype":"venue"
},
  "geometry": {"coordinates":[16.34258461,48.1937141418],"type":"Point"}
}