{
  "type": "Feature",
  "properties": {
    "addr:full":"Hauptstr 117a Pressbaum Nieder\u00f6sterreich 3021",
    "addr:housenumber":"117a",
    "addr:postcode":"3021",
    "addr:street":"Hauptstr;Niederoesterreich",
    "iso:country":"AT",
    "sg:address":"Hauptstr 117a",
    "sg:city":"Pressbaum",
    "sg:orig_category":"Lebensmittel / Einzelhandel",
    "sg:phone":"+43 2233 53978",
    "sg:postcode":"3021",
    "sg:province":"Nieder\u00f6sterreich",
    "wof:name":"MONDO Lebensmitteldiskonter",
    "wof:placetype":"venue"
},
  "geometry": {"coordinates":[16.0636100769,48.1778793335],"type":"Point"}
}