{
  "type": "Feature",
  "properties": {
    "iso:country":"AT",
    "sg:address":"Draschestr 56",
    "sg:city":"Wien",
    "sg:orig_category":"Autoreparatur, Autohandel",
    "sg:phone":"+43 1 61668480",
    "sg:postcode":"1230",
    "sg:province":"Wien",
    "sg:website":"www.alfaromeo-borka.at",
    "wof:name":"BORKA Autoreparaturen, Tuning, Verkauf und Havariedienst GesmbH",
    "wof:placetype":"venue"
},
  "geometry": {"coordinates":[16.3549385071,48.1476783752],"type":"Point"}
}