{
  "type": "Feature",
  "properties": {
    "addr:full":"Nr 103 Ried im Oberinntal Tirol 6531",
    "addr:postcode":"6531",
    "addr:street":"Nr 103;Tirol",
    "iso:country":"AT",
    "sg:address":"Nr 103",
    "sg:city":"Ried im Oberinntal",
    "sg:classifiers":[
        {
            "category":"Travel",
            "subcategory":"Hotels & Motels",
            "type":"Entertainment"
        }
    ],
    "sg:phone":"+43 5472 6622",
    "sg:postcode":"6531",
    "sg:province":"Tirol",
    "wof:name":"Hotel Forer",
    "wof:placetype":"venue"
},
  "geometry": {"coordinates":[10.654545784,47.0553817749],"type":"Point"}
}