{
  "type": "Feature",
  "properties": {
    "iso:country":"AT",
    "sg:address":"Industriestrasse 26",
    "sg:city":"Wolfsberg",
    "sg:classifiers":[
        {
            "category":"Professional",
            "subcategory":"Engineering",
            "type":"Services"
        }
    ],
    "sg:phone":"+43 4352 37246",
    "sg:postcode":"9400",
    "sg:province":"K\u00e4rnten",
    "wof:name":"GEZET-Industrietechnik Ing. G\u00fcnther Zweibrot",
    "wof:placetype":"venue"
},
  "geometry": {"coordinates":[14.8413476944,46.82006073],"type":"Point"}
}