{
  "type": "Feature",
  "properties": {
    "addr:full":"Tesma Allee 1 Sinabelkirchen Steiermark 8261",
    "addr:housenumber":"1",
    "addr:postcode":"8261",
    "addr:street":"Tesma Allee",
    "iso:country":"AT",
    "sg:address":"Tesma Allee 1",
    "sg:city":"Sinabelkirchen",
    "sg:classifiers":[
        {
            "category":"Professional",
            "subcategory":"Engineering",
            "type":"Services"
        }
    ],
    "sg:phone":"+43 3118 2055",
    "sg:postcode":"8261",
    "sg:province":"Steiermark",
    "sg:website":"tesma.com",
    "wof:name":"Tesma Fuel-Tec Zweigniederlassung der Tesma GmbH",
    "wof:placetype":"venue"
},
  "geometry": {"coordinates":[15.8282032013,47.1025505066],"type":"Point"}
}