{
  "type": "Feature",
  "properties": {
    "addr:full":"Hochstr 1 Sierning Ober\u00f6sterreich 4522",
    "addr:housenumber":"1",
    "addr:postcode":"4522",
    "addr:street":"Hochstr",
    "iso:country":"AT",
    "sg:address":"Hochstr 1",
    "sg:city":"Sierning",
    "sg:orig_category":"Drogerien",
    "sg:phone":"+43 7259 2205",
    "sg:postcode":"4522",
    "sg:province":"Ober\u00f6sterreich",
    "wof:name":"Antonius-Drogerie",
    "wof:placetype":"venue"
},
  "geometry": {"coordinates":[14.3088636398,48.0443000793],"type":"Point"}
}