{
  "type": "Feature",
  "properties": {
    "addr:full":"Landstr 22 Linz Ober\u00f6sterreich 4020",
    "addr:housenumber":"22",
    "addr:postcode":"4020",
    "addr:street":"Landstr",
    "iso:country":"AT",
    "sg:address":"Landstr 22",
    "sg:city":"Linz",
    "sg:orig_category":"Trachtenbekleidung",
    "sg:phone":"+43 732 7753440",
    "sg:postcode":"4020",
    "sg:province":"Ober\u00f6sterreich",
    "wof:name":"Thalbauer Harriette Lieb KG",
    "wof:placetype":"venue"
},
  "geometry": {"coordinates":[14.2879867554,48.3040122986],"type":"Point"}
}