{
  "type": "Feature",
  "properties": {
    "addr:full":"Vorderstadt 15 Kitzb\u00fchel Tirol 6370",
    "addr:housenumber":"15",
    "addr:postcode":"6370",
    "addr:street":"Vorderstadt;Tirol",
    "iso:country":"AT",
    "sg:address":"Vorderstadt 15",
    "sg:city":"Kitzb\u00fchel",
    "sg:orig_category":"Apotheken",
    "sg:phone":"+43 5356 62415",
    "sg:postcode":"6370",
    "sg:province":"Tirol",
    "wof:name":"Stadt-Apotheke Zum Tiroler Adler Magpharm Johann Riedmann KG",
    "wof:placetype":"venue"
},
  "geometry": {"coordinates":[12.3910579681,47.4468078613],"type":"Point"}
}