{
  "type": "Feature",
  "properties": {
    "addr:full":"Sebastian Kelch-G 1-3 Wien Wien 1140",
    "addr:housenumber":"1-3",
    "addr:postcode":"1140",
    "iso:country":"AT",
    "sg:address":"Sebastian Kelch-G 1-3",
    "sg:city":"Wien",
    "sg:orig_category":"Friseure U Frisiersalons",
    "sg:phone":"+43 1 9839889",
    "sg:postcode":"1140",
    "sg:province":"Wien",
    "wof:name":"Dotter Karl",
    "wof:placetype":"venue"
},
  "geometry": {"coordinates":[16.3077220917,48.1972923279],"type":"Point"}
}