{
  "type": "Feature",
  "properties": {
    "addr:full":"Cobenzlg 68 Wien Wien 1190",
    "addr:housenumber":"68",
    "addr:postcode":"1190",
    "addr:street":"Cobenzlg",
    "iso:country":"AT",
    "sg:address":"Cobenzlg 68",
    "sg:city":"Wien",
    "sg:orig_category":"Farben U Lacke / Erzeugung U Gro\u00c3\u0178handel",
    "sg:phone":"+43 4313 205577",
    "sg:postcode":"1190",
    "sg:province":"Wien",
    "wof:name":"Lack Klintens HandelsgesmbH",
    "wof:placetype":"venue"
},
  "geometry": {"coordinates":[16.3350429535,48.2599411011],"type":"Point"}
}