{
  "type": "Feature",
  "properties": {
    "addr:full":"Bsuch 201 Saalfelden am Steinernen Meer Salzburg 5760",
    "addr:housenumber":"201",
    "addr:postcode":"5760",
    "addr:street":"Saalfelden;Salzburg",
    "iso:country":"AT",
    "sg:address":"Bsuch 201",
    "sg:city":"Saalfelden am Steinernen Meer",
    "sg:orig_category":"Massagen",
    "sg:phone":"+43 4366 45364288",
    "sg:postcode":"5760",
    "sg:province":"Salzburg",
    "wof:name":"Massagefachinstitut Herzog Elisabeth",
    "wof:placetype":"venue"
},
  "geometry": {"coordinates":[12.8474750519,47.426410675],"type":"Point"}
}