{
  "type": "Feature",
  "properties": {
    "addr:full":"K\u00f6rblerstr 108 Ramingstein Salzburg 5591",
    "addr:housenumber":"108",
    "addr:postcode":"5591",
    "addr:street":"Ramingstein Salzburg",
    "iso:country":"AT",
    "sg:address":"K\u00f6rblerstr 108",
    "sg:city":"Ramingstein",
    "sg:orig_category":"Autoreparatur",
    "sg:phone":"+43 6475 525",
    "sg:postcode":"5591",
    "sg:province":"Salzburg",
    "wof:name":"Pritz Karl",
    "wof:placetype":"venue"
},
  "geometry": {"coordinates":[13.8369922638,47.0755195618],"type":"Point"}
}