{
  "type": "Feature",
  "properties": {
    "addr:full":"Kaiser Josef-Pl 1 4601",
    "addr:housenumber":"1",
    "addr:postcode":"4601",
    "addr:street":"Josef-Pl",
    "iso:country":"AT",
    "sg:address":"Kaiser Josef-Pl 1",
    "sg:orig_category":"Non-Classified Establishments",
    "sg:phone":"+43 7242 235341",
    "sg:postcode":"4601",
    "wof:name":"Magistrat der Stadt Wels Standesamt",
    "wof:placetype":"venue"
},
  "geometry": {"coordinates":[14.0255756378,48.1601982117],"type":"Point"}
}