{
  "type": "Feature",
  "properties": {
    "iso:country":"AT",
    "sg:address":"Marienhofg 7",
    "sg:city":"Baden",
    "sg:orig_category":"Beschichtungen",
    "sg:phone":"+43 2252 44092",
    "sg:postcode":"2500",
    "sg:province":"Nieder\u00f6sterreich",
    "wof:name":"Fabiankowitsch Michael",
    "wof:placetype":"venue"
},
  "geometry": {"coordinates":[16.2184791565,47.9991455078],"type":"Point"}
}