{
  "type": "Feature",
  "properties": {
    "addr:full":"Grafenstein K\u00e4rnten 9131",
    "addr:postcode":"9131",
    "addr:street":"Kaernten",
    "iso:country":"AT",
    "sg:city":"Grafenstein",
    "sg:orig_category":"Fischzucht",
    "sg:phone":"+43 4221 2800",
    "sg:postcode":"9131",
    "sg:province":"K\u00e4rnten",
    "wof:name":"Iridea Forellenzucht GesmbH",
    "wof:placetype":"venue"
},
  "geometry": {"coordinates":[-109.5989074707,38.9482917786],"type":"Point"}
}