{
  "type": "Feature",
  "properties": {
    "addr:full":"Lustenauer Str 20 Linz Ober\u00f6sterreich 4020",
    "addr:postcode":"4020",
    "addr:street":"Str 20",
    "iso:country":"AT",
    "sg:address":"Lustenauer Str 20",
    "sg:city":"Linz",
    "sg:orig_category":"Werbegrafik- U Grafik-Design",
    "sg:phone":"+43 732 796572",
    "sg:postcode":"4020",
    "sg:province":"Ober\u00f6sterreich",
    "wof:name":"Haslinger Hermann Mag",
    "wof:placetype":"venue"
},
  "geometry": {"coordinates":[14.2975273132,48.30078125],"type":"Point"}
}