{
  "type": "Feature",
  "properties": {
    "addr:full":"Baumg 62 Wien Wien 1030",
    "addr:housenumber":"62",
    "addr:postcode":"1030",
    "addr:street":"Baumg",
    "iso:country":"AT",
    "sg:address":"Baumg 62",
    "sg:city":"Wien",
    "sg:orig_category":"Hydraulik",
    "sg:phone":"+43 1 79659300",
    "sg:postcode":"1030",
    "sg:province":"Wien",
    "sg:website":"hansa-flex.com",
    "wof:name":"Hansa-Flex Hydraulik GmbH",
    "wof:placetype":"venue"
},
  "geometry": {"coordinates":[16.408197403,48.1906509399],"type":"Point"}
}