{
  "type": "Feature",
  "properties": {
    "addr:full":"Weinheimerg 2 Wien Wien 1160",
    "addr:housenumber":"2",
    "addr:postcode":"1160",
    "addr:street":"Weinheimerg",
    "iso:country":"AT",
    "sg:address":"Weinheimerg 2",
    "sg:city":"Wien",
    "sg:orig_category":"Beratungsstellen",
    "sg:phone":"+43 4314 919616845",
    "sg:postcode":"1160",
    "sg:province":"Wien",
    "wof:name":"Geriatrisches Tageszentrum - Fonds Soziales Wien - GTZ - Ottakring/Hernals",
    "wof:placetype":"venue"
},
  "geometry": {"coordinates":[16.3116874695,48.2128944397],"type":"Point"}
}