{
  "type": "Feature",
  "properties": {
    "iso:country":"AT",
    "sg:address":"Nr 9",
    "sg:city":"Wilhelmsburg an der Traisen",
    "sg:orig_category":"Molkereien U Molkereiprodukte",
    "sg:phone":"+43 2746 4876",
    "sg:postcode":"3150",
    "sg:province":"Nieder\u00f6sterreich",
    "wof:name":"Wilhelmsburger Hoflieferanten",
    "wof:placetype":"venue"
},
  "geometry": {"coordinates":[15.6558494568,48.0672073364],"type":"Point"}
}