{
  "type": "Feature",
  "properties": {
    "addr:full":"Kle\u00dfheimer Allee 102 Salzburg Salzburg 5020",
    "addr:housenumber":"102",
    "addr:postcode":"5020",
    "addr:street":"Klessheimer Allee;Salzburg",
    "iso:country":"AT",
    "sg:address":"Kle\u00dfheimer Allee 102",
    "sg:city":"Salzburg",
    "sg:orig_category":"Biologische Produkte",
    "sg:phone":"+43 662 424380",
    "sg:postcode":"5020",
    "sg:province":"Salzburg",
    "wof:name":"Bauernk\u00f6rberl",
    "wof:placetype":"venue"
},
  "geometry": {"coordinates":[13.00481987,47.8120079041],"type":"Point"}
}