{
  "type": "Feature",
  "properties": {
    "addr:full":"Innsbrucker Str 28 Hall in Tirol Tirol 6060",
    "addr:housenumber":"28",
    "addr:postcode":"6060",
    "addr:street":"Str;Tirol",
    "iso:country":"AT",
    "sg:address":"Innsbrucker Str 28",
    "sg:city":"Hall in Tirol",
    "sg:orig_category":"Tankstellen",
    "sg:phone":"+43 5223 57242",
    "sg:postcode":"6060",
    "sg:province":"Tirol",
    "wof:name":"Agip-Tankstelle Hen\u00f6kl",
    "wof:placetype":"venue"
},
  "geometry": {"coordinates":[11.4946174622,47.2782478333],"type":"Point"}
}