{
  "type": "Feature",
  "properties": {
    "addr:full":"Nr 126 Weistrach Nieder\u00f6sterreich 3351",
    "addr:postcode":"3351",
    "addr:street":"Nr 126",
    "iso:country":"AT",
    "sg:address":"Nr 126",
    "sg:city":"Weistrach",
    "sg:orig_category":"Tischlereien",
    "sg:phone":"+43 7477 421240",
    "sg:postcode":"3351",
    "sg:province":"Nieder\u00f6sterreich",
    "wof:name":"Donner Karl",
    "wof:placetype":"venue"
},
  "geometry": {"coordinates":[14.5837316513,48.0553855896],"type":"Point"}
}