{
  "type": "Feature",
  "properties": {
    "addr:full":"R\u00fcthenenstr 15 Meiningen Vorarlberg 6812",
    "addr:housenumber":"15",
    "addr:postcode":"6812",
    "addr:street":"Ruethenenstr",
    "iso:country":"AT",
    "sg:address":"R\u00fcthenenstr 15",
    "sg:city":"Meiningen",
    "sg:orig_category":"Reinigungsservice",
    "sg:phone":"+43 4367 69384028",
    "sg:postcode":"6812",
    "sg:province":"Vorarlberg",
    "wof:name":"Marco Putzengel Barjamovic Dragan",
    "wof:placetype":"venue"
},
  "geometry": {"coordinates":[9.5787162781,47.2983360291],"type":"Point"}
}