{
  "type": "Feature",
  "properties": {
    "addr:full":"Koednitz 49 Kals am Gro\u00dfglockner Tirol 9981",
    "addr:housenumber":"49",
    "addr:postcode":"9981",
    "addr:street":"Koednitz;Grossglockner",
    "iso:country":"AT",
    "sg:address":"Koednitz 49",
    "sg:city":"Kals am Gro\u00dfglockner",
    "sg:orig_category":"Bildung And Forschung, Schulen",
    "sg:phone":"+43 4876 8810",
    "sg:postcode":"9981",
    "sg:province":"Tirol",
    "sg:website":"http://www.bnet.at/hs-kals/index.htm",
    "wof:name":"HS Kals",
    "wof:placetype":"venue"
},
  "geometry": {"coordinates":[12.6448354721,47.0012321472],"type":"Point"}
}