{
  "type": "Feature",
  "properties": {
    "addr:full":"Nr 24/1 Weitra Nieder\u00f6sterreich 3970",
    "addr:housenumber":"1",
    "addr:postcode":"3970",
    "addr:street":"Nr 24 /",
    "iso:country":"AT",
    "sg:address":"Nr 24/1",
    "sg:city":"Weitra",
    "sg:orig_category":"Physiotherapie",
    "sg:phone":"+43 664 3706839",
    "sg:postcode":"3970",
    "sg:province":"Nieder\u00f6sterreich",
    "wof:name":"Klonner Gabriele",
    "wof:placetype":"venue"
},
  "geometry": {"coordinates":[14.8928060532,48.7005844116],"type":"Point"}
}