{
  "type": "Feature",
  "properties": {
    "iso:country":"AT",
    "sg:address":"Nr 96",
    "sg:city":"Ramsau am Dachstein",
    "sg:orig_category":"Elektroinstallationsunternehmen",
    "sg:phone":"+43 3687 810160",
    "sg:postcode":"8972",
    "sg:province":"Steiermark",
    "wof:name":"Reiter Johann",
    "wof:placetype":"venue"
},
  "geometry": {"coordinates":[13.6525297165,47.4214515686],"type":"Point"}
}