{
  "type": "Feature",
  "properties": {
    "iso:country":"AT",
    "sg:address":"Thalmannsbach 8",
    "sg:city":"Sigharting",
    "sg:orig_category":"Unternehmensberatung",
    "sg:phone":"+43 7766 4011",
    "sg:postcode":"4771",
    "sg:province":"Ober\u00f6sterreich",
    "wof:name":"Buchinger Walter Mag",
    "wof:placetype":"venue"
},
  "geometry": {"coordinates":[13.6096372604,48.3891143799],"type":"Point"}
}