{
  "type": "Feature",
  "properties": {
    "iso:country":"AT",
    "sg:city":"Schlierbach",
    "sg:orig_category":"Feuerwehren",
    "sg:phone":"+43 7582 81222",
    "sg:postcode":"4553",
    "sg:province":"Ober\u00f6sterreich",
    "wof:name":"Freiwillige Feuerwehr Schlierbach",
    "wof:placetype":"venue"
},
  "geometry": {"coordinates":[14.1261034012,47.9373321533],"type":"Point"}
}