{
  "type": "Feature",
  "properties": {
    "addr:full":"Georg-Sigl-Str 16 Breitenfurt Nieder\u00f6sterreich 2384",
    "addr:housenumber":"16",
    "addr:postcode":"2384",
    "addr:street":"Georg-Sigl-Str",
    "iso:country":"AT",
    "sg:address":"Georg-Sigl-Str 16",
    "sg:city":"Breitenfurt",
    "sg:orig_category":"Werbeagenturen",
    "sg:phone":"+43 4322 394277",
    "sg:postcode":"2384",
    "sg:province":"Nieder\u00f6sterreich",
    "wof:name":"Atelier Tintifax Ing Michael Trimmel",
    "wof:placetype":"venue"
},
  "geometry": {"coordinates":[16.1917991638,48.1364402771],"type":"Point"}
}