{
  "type": "Feature",
  "properties": {
    "addr:full":"Promeggen 4 Maria Luggau K\u00e4rnten 9655",
    "addr:housenumber":"4",
    "addr:postcode":"9655",
    "addr:street":"Promeggen",
    "iso:country":"AT",
    "sg:address":"Promeggen 4",
    "sg:city":"Maria Luggau",
    "sg:orig_category":"Appartements / Ferienwohnungen",
    "sg:phone":"+43 4716 301",
    "sg:postcode":"9655",
    "sg:province":"K\u00e4rnten",
    "wof:name":"Salcher Lorenz",
    "wof:placetype":"venue"
},
  "geometry": {"coordinates":[12.7352161407,46.7049674988],"type":"Point"}
}