{
  "type": "Feature",
  "properties": {
    "addr:full":"Linden 51 Keutschach K\u00e4rnten 9074",
    "addr:housenumber":"51",
    "addr:postcode":"9074",
    "addr:street":"Linden;Kaernten",
    "iso:country":"AT",
    "sg:address":"Linden 51",
    "sg:city":"Keutschach",
    "sg:orig_category":"Osteopathie",
    "sg:phone":"+43 4273 2041",
    "sg:postcode":"9074",
    "sg:province":"K\u00e4rnten",
    "wof:name":"Ha\u00dfler Florian",
    "wof:placetype":"venue"
},
  "geometry": {"coordinates":[14.152762413,46.6049957275],"type":"Point"}
}