{
  "type": "Feature",
  "properties": {
    "addr:full":"Auenstr 8 Hohenems Vorarlberg 6845",
    "addr:housenumber":"8",
    "addr:postcode":"6845",
    "addr:street":"Auenstr",
    "iso:country":"AT",
    "sg:address":"Auenstr 8",
    "sg:city":"Hohenems",
    "sg:orig_category":"Pensionen / Privatzimmer",
    "sg:phone":"+43 4355 7679696",
    "sg:postcode":"6845",
    "sg:province":"Vorarlberg",
    "wof:name":"Mathis Norbert",
    "wof:placetype":"venue"
},
  "geometry": {"coordinates":[9.7118253708,47.3678970337],"type":"Point"}
}