{
  "type": "Feature",
  "properties": {
    "addr:full":"Braunhirscheng 7 Wien Wien 1150",
    "addr:housenumber":"7",
    "addr:postcode":"1150",
    "addr:street":"Braunhirscheng",
    "iso:country":"AT",
    "sg:address":"Braunhirscheng 7",
    "sg:city":"Wien",
    "sg:orig_category":"Baumeister",
    "sg:phone":"+43 1 89399660",
    "sg:postcode":"1150",
    "sg:province":"Wien",
    "wof:name":"Petsch Gerhard Ing GesmbH",
    "wof:placetype":"venue"
},
  "geometry": {"coordinates":[16.3265991211,48.1873817444],"type":"Point"}
}