{
  "type": "Feature",
  "properties": {
    "addr:full":"Dorfstr 2 Afritz am See K\u00e4rnten 9542",
    "addr:housenumber":"2",
    "addr:postcode":"9542",
    "addr:street":"Dorfstr;Kaernten",
    "iso:country":"AT",
    "sg:address":"Dorfstr 2",
    "sg:city":"Afritz am See",
    "sg:orig_category":"Tourismusinformation U -Organisationen",
    "sg:phone":"+43 4342 4721260",
    "sg:postcode":"9542",
    "sg:province":"K\u00e4rnten",
    "wof:name":"Tourismusinformation",
    "wof:placetype":"venue"
},
  "geometry": {"coordinates":[13.8003778458,46.7254753113],"type":"Point"}
}