{
  "type": "Feature",
  "properties": {
    "iso:country":"AT",
    "sg:address":"Bergstr 9",
    "sg:city":"Lackenbach",
    "sg:orig_category":"Hafnereien",
    "sg:phone":"+43 2619 8646",
    "sg:postcode":"7322",
    "sg:province":"Burgenland",
    "wof:name":"Horvath Franz",
    "wof:placetype":"venue"
},
  "geometry": {"coordinates":[16.4656867981,47.5889396667],"type":"Point"}
}