{
  "type": "Feature",
  "properties": {
    "iso:country":"AT",
    "sg:address":"Kardinalpl 6",
    "sg:city":"Klagenfurt",
    "sg:orig_category":"Partnervermittlung",
    "sg:phone":"+43 4346 3502876",
    "sg:postcode":"9020",
    "sg:province":"K\u00e4rnten",
    "wof:name":"Kontakt die Partnervermittlungen - Inh Elisabeth Barasits",
    "wof:placetype":"venue"
},
  "geometry": {"coordinates":[14.3117637634,46.6238021851],"type":"Point"}
}