{
  "type": "Feature",
  "properties": {
    "addr:full":"Nr 288 Vorau Steiermark 8250",
    "addr:postcode":"8250",
    "addr:street":"Nr",
    "iso:country":"AT",
    "sg:address":"Nr 288",
    "sg:city":"Vorau",
    "sg:orig_category":"Fenster",
    "sg:phone":"+43 3337 2448",
    "sg:postcode":"8250",
    "sg:province":"Steiermark",
    "wof:name":"Kager Josef GesmbH",
    "wof:placetype":"venue"
},
  "geometry": {"coordinates":[15.8873929977,47.4056854248],"type":"Point"}
}