{
  "type": "Feature",
  "properties": {
    "iso:country":"AT",
    "sg:address":"Ziegeleigasse 10",
    "sg:city":"Hartberg",
    "sg:classifiers":[
        {
            "category":"Retail",
            "subcategory":"Repair Shop",
            "type":"Services"
        }
    ],
    "sg:phone":"+43 3332 62478",
    "sg:postcode":"8230",
    "sg:province":"Steiermark",
    "sg:tags":[
        "agricultural",
        "machinery"
    ],
    "sg:website":"stahlbau-grabner.at",
    "wof:name":"Stahlbau Grabner GmbH",
    "wof:placetype":"venue"
},
  "geometry": {"coordinates":[15.9674787521,47.2630157471],"type":"Point"}
}