{
  "type": "Feature",
  "properties": {
    "addr:full":"Corvinusring 24-26 Wiener Neustadt Nieder\u00f6sterreich 2700",
    "addr:postcode":"24-26;2700",
    "addr:street":"Corvinusring;Niederoesterreich",
    "iso:country":"AT",
    "sg:address":"Corvinusring 24-26",
    "sg:city":"Wiener Neustadt",
    "sg:orig_category":"Tabaktrafiken",
    "sg:phone":"+43 2622 20793",
    "sg:postcode":"2700",
    "sg:province":"Nieder\u00f6sterreich",
    "wof:name":"Kessler Kiosk",
    "wof:placetype":"venue"
},
  "geometry": {"coordinates":[16.2475223541,47.8163795471],"type":"Point"}
}