{
  "type": "Feature",
  "properties": {
    "addr:full":"Rosentalstr 16 Heiligenkreuz am Waasen Steiermark 8081",
    "addr:housenumber":"16",
    "addr:postcode":"8081",
    "addr:street":"Rosentalstr",
    "iso:country":"AT",
    "sg:address":"Rosentalstr 16",
    "sg:city":"Heiligenkreuz am Waasen",
    "sg:orig_category":"Schlossereien",
    "sg:phone":"+43 4331 3425590",
    "sg:postcode":"8081",
    "sg:province":"Steiermark",
    "wof:name":"Stradner Hans Ing",
    "wof:placetype":"venue"
},
  "geometry": {"coordinates":[15.5789060593,46.9579200745],"type":"Point"}
}