{
  "type": "Feature",
  "properties": {
    "iso:country":"AT",
    "sg:address":"Gartengasse 17",
    "sg:city":"Wien",
    "sg:classifiers":[
        {
            "category":"Government",
            "subcategory":"City Hall",
            "type":"Public Place"
        }
    ],
    "sg:phone":"+43 1 5454921",
    "sg:postcode":"1050",
    "sg:province":"Wien",
    "sg:tags":[
        "interior",
        "painting"
    ],
    "wof:name":"Erich Hackl",
    "wof:placetype":"venue"
},
  "geometry": {"coordinates":[16.3584308624,48.1899032593],"type":"Point"}
}