{
  "type": "Feature",
  "properties": {
    "addr:full":"Dorfweg 2 Ansfelden Ober\u00f6sterreich 4052",
    "addr:housenumber":"2",
    "addr:postcode":"4052",
    "addr:street":"Dorfweg",
    "iso:country":"AT",
    "sg:address":"Dorfweg 2",
    "sg:city":"Ansfelden",
    "sg:orig_category":"Personalberatung",
    "sg:phone":"+43 7229 51710",
    "sg:postcode":"4052",
    "sg:province":"Ober\u00f6sterreich",
    "wof:name":"Motiv Personal Consulting GmbH",
    "wof:placetype":"venue"
},
  "geometry": {"coordinates":[14.291633606,48.2108650208],"type":"Point"}
}