{
  "type": "Feature",
  "properties": {
    "addr:full":"Kienburg 14 9953",
    "addr:housenumber":"14",
    "addr:postcode":"9953",
    "addr:street":"Kienburg",
    "iso:country":"AT",
    "sg:address":"Kienburg 14",
    "sg:orig_category":"Appartements / Ferienwohnungen",
    "sg:phone":"+43 4348 725254",
    "sg:postcode":"9953",
    "wof:name":"Blasen - Markus Putzhuber",
    "wof:placetype":"venue"
},
  "geometry": {"coordinates":[12.5931282043,46.9352073669],"type":"Point"}
}