{
  "type": "Feature",
  "properties": {
    "iso:country":"AT",
    "sg:address":"Winkelweg 29",
    "sg:city":"Bludenz",
    "sg:orig_category":"Tischlereien",
    "sg:phone":"+43 4355 52631910",
    "sg:postcode":"6700",
    "sg:province":"Vorarlberg",
    "wof:name":"Neyer Otto",
    "wof:placetype":"venue"
},
  "geometry": {"coordinates":[9.8223991394,47.1638221741],"type":"Point"}
}