{
  "type": "Feature",
  "properties": {
    "iso:country":"AT",
    "sg:address":"Hauptstr 43",
    "sg:city":"Gro\u00dfpetersdorf",
    "sg:orig_category":"Bankomat-Standorte",
    "sg:phone":"+43 3362 40160",
    "sg:postcode":"7503",
    "sg:province":"Burgenland",
    "wof:name":"Bankomat d Volksbank S\u00fcdburgenland regGenmbH",
    "wof:placetype":"venue"
},
  "geometry": {"coordinates":[8.0355539322,53.0033073425],"type":"Point"}
}