{
  "type": "Feature",
  "properties": {
    "addr:full":"Im Hatric 6 Hartberg Steiermark 8230",
    "addr:housenumber":"6",
    "addr:postcode":"8230",
    "addr:street":"Im Hatric",
    "iso:country":"AT",
    "sg:address":"Im Hatric 6",
    "sg:city":"Hartberg",
    "sg:orig_category":"Bekleidung / Einzelhandel",
    "sg:phone":"+43 4333 3262032",
    "sg:postcode":"8230",
    "sg:province":"Steiermark",
    "wof:name":"Takko ModeMarkt GmbH",
    "wof:placetype":"venue"
},
  "geometry": {"coordinates":[15.9913454056,47.2823791504],"type":"Point"}
}