{
  "type": "Feature",
  "properties": {
    "addr:full":"Wienerbergstr 11/12/Vienna/Twintower Wien Wien 1100",
    "addr:housenumber":"11 / 12 / vienna",
    "addr:postcode":"1100",
    "addr:street":"Wienerbergstr",
    "iso:country":"AT",
    "sg:address":"Wienerbergstr 11/12/Vienna/Twintower",
    "sg:city":"Wien",
    "sg:orig_category":"Telefonanlagen",
    "sg:phone":"+43 1 331530",
    "sg:postcode":"1100",
    "sg:province":"Wien",
    "wof:name":"AVAYA Austria GmbH",
    "wof:placetype":"venue"
},
  "geometry": {"coordinates":[16.3744049072,48.1782684326],"type":"Point"}
}