{
  "type": "Feature",
  "properties": {
    "addr:full":"Forstgartenweg 1 Hausmannst\u00e4tten Steiermark 8071",
    "addr:housenumber":"1",
    "addr:postcode":"8071",
    "addr:street":"Forstgartenweg",
    "iso:country":"AT",
    "sg:address":"Forstgartenweg 1",
    "sg:city":"Hausmannst\u00e4tten",
    "sg:orig_category":"Baumschulen",
    "sg:phone":"+43 4331 6401162",
    "sg:postcode":"8071",
    "sg:province":"Steiermark",
    "wof:name":"Forstgartenbetrieb des Landes Steiermark",
    "wof:placetype":"venue"
},
  "geometry": {"coordinates":[15.5542373657,47.0130844116],"type":"Point"}
}