{
  "type": "Feature",
  "properties": {
    "iso:country":"AT",
    "sg:address":"Scheiblberg 42",
    "sg:city":"Rohrbach in Ober\u00f6sterreich",
    "sg:orig_category":"Rauchfangkehrer",
    "sg:phone":"+43 4372 895333",
    "sg:postcode":"4150",
    "sg:province":"Ober\u00f6sterreich",
    "wof:name":"Ignis Feuer-Energie- u Umwelttechnik GmbH",
    "wof:placetype":"venue"
},
  "geometry": {"coordinates":[13.9875669479,48.5582351685],"type":"Point"}
}