{
  "type": "Feature",
  "properties": {
    "addr:full":"Steiner Landstr 97 Krems an der Donau Nieder\u00f6sterreich 3500",
    "addr:housenumber":"97",
    "addr:postcode":"3500",
    "addr:street":"Steiner Landstr",
    "iso:country":"AT",
    "sg:address":"Steiner Landstr 97",
    "sg:city":"Krems an der Donau",
    "sg:orig_category":"Bilderrahmen",
    "sg:phone":"+43 676 5253635",
    "sg:postcode":"3500",
    "sg:province":"Nieder\u00f6sterreich",
    "wof:name":"Bauer Andreas - Art & Frame",
    "wof:placetype":"venue"
},
  "geometry": {"coordinates":[15.5781822205,48.4006843567],"type":"Point"}
}