{
  "type": "Feature",
  "properties": {
    "addr:full":"Tassilostr 7 Salzburg Salzburg 5020",
    "addr:housenumber":"7",
    "addr:postcode":"5020",
    "addr:street":"Tassilostr;Salzburg",
    "iso:country":"AT",
    "sg:address":"Tassilostr 7",
    "sg:city":"Salzburg",
    "sg:orig_category":"Umweltschutz",
    "sg:phone":"+43 662 427085",
    "sg:postcode":"5020",
    "sg:province":"Salzburg",
    "wof:name":"Neff Reinhold Ing",
    "wof:placetype":"venue"
},
  "geometry": {"coordinates":[13.0174798965,47.8293228149],"type":"Point"}
}