{
  "type": "Feature",
  "properties": {
    "addr:full":"Schillerstr 28 Feldbach Steiermark 8330",
    "addr:housenumber":"28",
    "addr:postcode":"8330",
    "addr:street":"Schillerstr",
    "iso:country":"AT",
    "sg:address":"Schillerstr 28",
    "sg:city":"Feldbach",
    "sg:orig_category":"Nachhilfe U Lernbetreuung",
    "sg:phone":"+43 676 4135077",
    "sg:postcode":"8330",
    "sg:province":"Steiermark",
    "wof:name":"Nachhilfeinstitut LSZ Colong Anne-Benedicte",
    "wof:placetype":"venue"
},
  "geometry": {"coordinates":[15.8847103119,46.9509544373],"type":"Point"}
}