{
  "type": "Feature",
  "properties": {
    "addr:full":"Mockenstr 81 Hard Vorarlberg 6971",
    "addr:housenumber":"81",
    "addr:postcode":"6971",
    "addr:street":"Mockenstr",
    "iso:country":"AT",
    "sg:address":"Mockenstr 81",
    "sg:city":"Hard",
    "sg:classifiers":[
        {
            "category":"Professional",
            "subcategory":"Engineering",
            "type":"Services"
        }
    ],
    "sg:phone":"+43 4355 74741770",
    "sg:postcode":"6971",
    "sg:province":"Vorarlberg",
    "sg:tags":[
        "machine",
        "-",
        "mechanical"
    ],
    "wof:name":"HELMUT GOLL GMBH",
    "wof:placetype":"venue"
},
  "geometry": {"coordinates":[9.6783895493,47.4848709106],"type":"Point"}
}