{
  "type": "Feature",
  "properties": {
    "iso:country":"AT",
    "sg:address":"Nr 1",
    "sg:city":"Markt Neuhodis",
    "sg:orig_category":"Bildhauer",
    "sg:phone":"+43 3363 79379",
    "sg:postcode":"7464",
    "sg:province":"Burgenland",
    "wof:name":"Kedl Christine",
    "wof:placetype":"venue"
},
  "geometry": {"coordinates":[16.3952350616,47.2961273193],"type":"Point"}
}