{
  "type": "Feature",
  "properties": {
    "iso:country":"AT",
    "sg:address":"Pichlhofstr 604",
    "sg:city":"Kaprun",
    "sg:orig_category":"Schlossereien",
    "sg:phone":"+43 4365 478390",
    "sg:postcode":"5710",
    "sg:province":"Salzburg",
    "wof:name":"J\u00e4ger Hans Schlosserei GmbH",
    "wof:placetype":"venue"
},
  "geometry": {"coordinates":[12.749671936,47.2690162659],"type":"Point"}
}