{
  "type": "Feature",
  "properties": {
    "addr:full":"Kandaharweg 15 St. Anton am Arlberg Tirol 6580",
    "addr:housenumber":"15",
    "addr:postcode":"6580",
    "addr:street":"Kandaharweg;Tirol",
    "iso:country":"AT",
    "sg:address":"Kandaharweg 15",
    "sg:city":"St. Anton am Arlberg",
    "sg:classifiers":[
        {
            "category":"Park",
            "subcategory":"Provincial",
            "type":"Public Place"
        }
    ],
    "sg:phone":"+43 4354 4634110",
    "sg:postcode":"6580",
    "sg:province":"Tirol",
    "sg:tags":[
        "u",
        "ski-",
        "snowboardschulen"
    ],
    "sg:website":"skischool-arlberg.com",
    "wof:name":"Schischule Arlberg - ski-snowboardschule arlberg",
    "wof:placetype":"venue"
},
  "geometry": {"coordinates":[10.2638263702,47.129032135],"type":"Point"}
}