{
  "type": "Feature",
  "properties": {
    "iso:country":"AT",
    "sg:address":"Stadtweg 10",
    "sg:city":"Wiesmath",
    "sg:orig_category":"Zimmereien",
    "sg:phone":"+43 4326 4522760",
    "sg:postcode":"2811",
    "sg:province":"Nieder\u00f6sterreich",
    "wof:name":"Kleinrad ZimmereibetriebsgesmbH",
    "wof:placetype":"venue"
},
  "geometry": {"coordinates":[16.269329071,47.6361503601],"type":"Point"}
}