{
  "type": "Feature",
  "properties": {
    "addr:full":"Riedweg 9a Inzing Tirol 6401",
    "addr:housenumber":"9a",
    "addr:postcode":"6401",
    "addr:street":"Riedweg;Tirol",
    "iso:country":"AT",
    "sg:address":"Riedweg 9a",
    "sg:city":"Inzing",
    "sg:orig_category":"Geschenkartikel",
    "sg:phone":"+43 5238 87877",
    "sg:postcode":"6401",
    "sg:province":"Tirol",
    "wof:name":"HIAS Handels GmbH",
    "wof:placetype":"venue"
},
  "geometry": {"coordinates":[11.1963224411,47.2760429382],"type":"Point"}
}