{
  "type": "Feature",
  "properties": {
    "addr:full":"Sieglangerufer 133a Innsbruck Tirol 6020",
    "addr:housenumber":"133a",
    "addr:postcode":"6020",
    "addr:street":"Sieglangerufer;Tirol",
    "iso:country":"AT",
    "sg:address":"Sieglangerufer 133a",
    "sg:city":"Innsbruck",
    "sg:classifiers":[
        {
            "category":"Home & Garden",
            "subcategory":"Building Materials",
            "type":"Retail Goods"
        }
    ],
    "sg:phone":"+43 4351 2341545",
    "sg:postcode":"6020",
    "sg:province":"Tirol",
    "sg:tags":[
        "baustoffe",
        "-material",
        "u"
    ],
    "wof:name":"Gutwenger Roland",
    "wof:placetype":"venue"
},
  "geometry": {"coordinates":[11.359087944,47.2535514832],"type":"Point"}
}