{
  "type": "Feature",
  "properties": {
    "iso:country":"AT",
    "sg:address":"Unterdorf 154",
    "sg:city":"Thalgau",
    "sg:orig_category":"Musikgruppen",
    "sg:phone":"+43 6235 6934",
    "sg:postcode":"5303",
    "sg:province":"Salzburg",
    "wof:name":"Die Thalgauer",
    "wof:placetype":"venue"
},
  "geometry": {"coordinates":[13.2410392761,47.8438072205],"type":"Point"}
}