{
  "type": "Feature",
  "properties": {
    "addr:full":"Alte Schwendestr 16 Riezlern Vorarlberg 6991",
    "addr:housenumber":"16",
    "addr:postcode":"6991",
    "iso:country":"AT",
    "sg:address":"Alte Schwendestr 16",
    "sg:city":"Riezlern",
    "sg:orig_category":"Appartements / Ferienwohnungen",
    "sg:phone":"+43 4355 175443",
    "sg:postcode":"6991",
    "sg:province":"Vorarlberg",
    "wof:name":"Ferienwohnungen Haus Peter-Paul",
    "wof:placetype":"venue"
},
  "geometry": {"coordinates":[10.1874399185,47.3604393005],"type":"Point"}
}