{
  "type": "Feature",
  "properties": {
    "addr:full":"Welser Str 91-93 Leonding Ober\u00f6sterreich 4060",
    "addr:postcode":"91-93;4060",
    "addr:street":"Str;Oberoesterreich",
    "iso:country":"AT",
    "sg:address":"Welser Str 91-93",
    "sg:city":"Leonding",
    "sg:orig_category":"Autohandel",
    "sg:phone":"+43 4373 26700270",
    "sg:postcode":"4060",
    "sg:province":"Ober\u00f6sterreich",
    "wof:name":"Autohaus Seipl GmbH",
    "wof:placetype":"venue"
},
  "geometry": {"coordinates":[14.2490816116,48.2543869019],"type":"Point"}
}