{
  "type": "Feature",
  "properties": {
    "addr:full":"Siebensterngasse 16A Wien Wien 1070",
    "addr:housenumber":"16a",
    "addr:postcode":"1070",
    "addr:street":"Siebensterngasse",
    "iso:country":"AT",
    "sg:address":"Siebensterngasse 16A",
    "sg:city":"Wien",
    "sg:classifiers":[
        {
            "category":"Professional",
            "subcategory":"Detective & Security Services",
            "type":"Services"
        }
    ],
    "sg:phone":"+43 1 5235233",
    "sg:postcode":"1070",
    "sg:province":"Wien",
    "sg:tags":[
        "access",
        "control",
        "ac",
        "system"
    ],
    "sg:website":"helason.at",
    "wof:name":"HELASON Sicherheitstechnik GesmbH",
    "wof:placetype":"venue"
},
  "geometry": {"coordinates":[16.3551826477,48.2026481628],"type":"Point"}
}