{
  "type": "Feature",
  "properties": {
    "addr:full":"Adalbert-Stifter-Strasse 1 Braunau am Inn Ober\u00f6sterreich 5280",
    "addr:housenumber":"1",
    "addr:postcode":"5280",
    "addr:street":"Adalbert-Stifter-Strasse",
    "iso:country":"AT",
    "sg:address":"Adalbert-Stifter-Strasse 1",
    "sg:city":"Braunau am Inn",
    "sg:classifiers":[
        {
            "category":"Building & Trades",
            "subcategory":"Electrical",
            "type":"Services"
        }
    ],
    "sg:phone":"+43 7722 62689",
    "sg:postcode":"5280",
    "sg:province":"Ober\u00f6sterreich",
    "sg:tags":[
        "work",
        "installation"
    ],
    "wof:name":"Elektro Blum Inh. Martin Blum",
    "wof:placetype":"venue"
},
  "geometry": {"coordinates":[13.0355997086,48.2509040833],"type":"Point"}
}