{
  "type": "Feature",
  "properties": {
    "iso:country":"AT",
    "sg:address":"Postgasse 6 ",
    "sg:city":"Wien",
    "sg:classifiers":[
        {
            "category":"Bars & Pubs",
            "type":"Food & Drink"
        }
    ],
    "sg:phone":"+43 1 5133802",
    "sg:postcode":"1010",
    "sg:province":"Wien",
    "sg:tags":[
        "acrylic",
        "lamp",
        "luminaires"
    ],
    "sg:website":"www.thomasleuchten.at",
    "wof:name":"Thomas-Leuchten, Inhaber Dolores Gruber",
    "wof:placetype":"venue"
},
  "geometry": {"coordinates":[16.3791179657,48.2092933655],"type":"Point"}
}