{
  "type": "Feature",
  "properties": {
    "addr:full":"Bergg 11 Wien Wien 1090",
    "addr:housenumber":"11",
    "addr:postcode":"1090",
    "addr:street":"Bergg",
    "iso:country":"AT",
    "sg:address":"Bergg 11",
    "sg:city":"Wien",
    "sg:orig_category":"Institute",
    "sg:phone":"+43 1 427741701",
    "sg:postcode":"1090",
    "sg:province":"Wien",
    "wof:name":"Institut f Sprachwissenschaft d Universit\u00e4t Wien",
    "wof:placetype":"venue"
},
  "geometry": {"coordinates":[16.3613567352,48.218082428],"type":"Point"}
}