{
  "type": "Feature",
  "properties": {
    "addr:full":"Zur Schleuse 1 Stockerau Nieder\u00f6sterreich 2000",
    "addr:housenumber":"1",
    "addr:postcode":"2000",
    "addr:street":"Zur Schleuse",
    "iso:country":"AT",
    "sg:address":"Zur Schleuse 1",
    "sg:city":"Stockerau",
    "sg:orig_category":"Matratzen",
    "sg:phone":"+43 2266 67026",
    "sg:postcode":"2000",
    "sg:province":"Nieder\u00f6sterreich",
    "wof:name":"BETTEN MAX GmbH",
    "wof:placetype":"venue"
},
  "geometry": {"coordinates":[16.1869792938,48.3876571655],"type":"Point"}
}