{
  "type": "Feature",
  "properties": {
    "addr:full":"Stuwerstr 27 Wien Wien 1020",
    "addr:housenumber":"27",
    "addr:postcode":"1020",
    "addr:street":"Stuwerstr",
    "iso:country":"AT",
    "sg:address":"Stuwerstr 27",
    "sg:city":"Wien",
    "sg:orig_category":"Farben U Lacke / Einzelhandel",
    "sg:phone":"+43 1 7280509",
    "sg:postcode":"1020",
    "sg:province":"Wien",
    "wof:name":"Farbenkaiser",
    "wof:placetype":"venue"
},
  "geometry": {"coordinates":[16.4028606415,48.2189331055],"type":"Point"}
}