{
  "type": "Feature",
  "properties": {
    "addr:full":"Traiseng 17 Wien Wien 1200",
    "addr:housenumber":"17",
    "addr:postcode":"1200",
    "addr:street":"Traiseng",
    "iso:country":"AT",
    "sg:address":"Traiseng 17",
    "sg:city":"Wien",
    "sg:orig_category":"Friseure U Frisiersalons",
    "sg:phone":"+43 1 3328659",
    "sg:postcode":"1200",
    "sg:province":"Wien",
    "wof:name":"Harmer Brigitte",
    "wof:placetype":"venue"
},
  "geometry": {"coordinates":[16.3881492615,48.2359886169],"type":"Point"}
}