{
  "type": "Feature",
  "properties": {
    "iso:country":"AT",
    "sg:address":"Marschallpl 4",
    "sg:city":"Wien",
    "sg:orig_category":"Handschuhe",
    "sg:phone":"+43 1 5055101",
    "sg:postcode":"1120",
    "sg:province":"Wien",
    "wof:name":"Br\u00fcder Oehring KG",
    "wof:placetype":"venue"
},
  "geometry": {"coordinates":[16.3043994904,48.165348053],"type":"Point"}
}