{
  "type": "Feature",
  "properties": {
    "iso:country":"AT",
    "sg:address":"Nr 168",
    "sg:city":"Semriach",
    "sg:orig_category":"Friseure U Frisiersalons",
    "sg:phone":"+43 4331 278297",
    "sg:postcode":"8102",
    "sg:province":"Steiermark",
    "wof:name":"Feldgrill Erika",
    "wof:placetype":"venue"
},
  "geometry": {"coordinates":[15.4031257629,47.217502594],"type":"Point"}
}