{
  "type": "Feature",
  "properties": {
    "addr:full":"Bahnhofpl 18 Krems an der Donau Nieder\u00f6sterreich 3500",
    "addr:housenumber":"18",
    "addr:postcode":"3500",
    "addr:street":"Bahnhofpl",
    "iso:country":"AT",
    "sg:address":"Bahnhofpl 18",
    "sg:city":"Krems an der Donau",
    "sg:orig_category":"\u00c3\u201enderungsschneidereien",
    "sg:phone":"+43 2732 70660",
    "sg:postcode":"3500",
    "sg:province":"Nieder\u00f6sterreich",
    "wof:name":"\u00e4nderungsschneiderei Brigitte Spindler",
    "wof:placetype":"venue"
},
  "geometry": {"coordinates":[15.6051111221,48.4096374512],"type":"Point"}
}