{
  "type": "Feature",
  "properties": {
    "iso:country":"AT",
    "sg:address":"Oldenburgg 49",
    "sg:city":"Wien",
    "sg:classifiers":[
        {
            "category":"Organizations",
            "subcategory":"Community Association",
            "type":"Services"
        }
    ],
    "sg:phone":"+43 1 66732840",
    "sg:postcode":"1230",
    "sg:province":"Wien",
    "sg:tags":[
        "relation",
        "public"
    ],
    "wof:name":"Wachta Hansj\u00f6rg Dr GesmbH Public Affairs",
    "wof:placetype":"venue"
},
  "geometry": {"coordinates":[16.3295269012,48.146484375],"type":"Point"}
}