{
  "type": "Feature",
  "properties": {
    "addr:full":"Deutschstr 19 Wien Wien 1230",
    "addr:housenumber":"19",
    "addr:postcode":"1230",
    "addr:street":"Deutschstr",
    "iso:country":"AT",
    "sg:address":"Deutschstr 19",
    "sg:city":"Wien",
    "sg:orig_category":"Reifen U Reifendienste",
    "sg:phone":"+43 4316 1631500",
    "sg:postcode":"1230",
    "sg:province":"Wien",
    "sg:website":"yokohama.at",
    "wof:name":"Yokohama (Austria) GmbH",
    "wof:placetype":"venue"
},
  "geometry": {"coordinates":[16.3586006165,48.1418037415],"type":"Point"}
}