{
  "type": "Feature",
  "properties": {
    "addr:full":"Ketzerg 212 Wien Wien 1230",
    "addr:housenumber":"212",
    "addr:postcode":"1230",
    "iso:country":"AT",
    "sg:address":"Ketzerg 212",
    "sg:city":"Wien",
    "sg:orig_category":"Gefahrguttransporte",
    "sg:phone":"+43 1 86593160",
    "sg:postcode":"1230",
    "sg:province":"Wien",
    "wof:name":"Klacska Paul GesmbH",
    "wof:placetype":"venue"
},
  "geometry": {"coordinates":[16.2887153625,48.1308631897],"type":"Point"}
}