{
  "type": "Feature",
  "properties": {
    "iso:country":"AT",
    "sg:address":"Hauptstr 18",
    "sg:city":"Prambachkirchen",
    "sg:orig_category":"Non-Classified Establishments",
    "sg:phone":"+43 5 91334223",
    "sg:postcode":"4731",
    "sg:province":"Ober\u00f6sterreich",
    "wof:name":"Gendarmerieposten",
    "wof:placetype":"venue"
},
  "geometry": {"coordinates":[13.9045629501,48.3148040771],"type":"Point"}
}