{
  "type": "Feature",
  "properties": {
    "addr:full":"Neue Landstr 82 M\u00e4der Vorarlberg 6841",
    "addr:housenumber":"82",
    "addr:postcode":"6841",
    "addr:street":"Neue Landstr",
    "iso:country":"AT",
    "sg:address":"Neue Landstr 82",
    "sg:city":"M\u00e4der",
    "sg:orig_category":"Autohandel",
    "sg:phone":"+43 5523 51261",
    "sg:postcode":"6841",
    "sg:province":"Vorarlberg",
    "wof:name":"Auto Schranz",
    "wof:placetype":"venue"
},
  "geometry": {"coordinates":[-72.1268081665,44.9376831055],"type":"Point"}
}