{
  "type": "Feature",
  "properties": {
    "addr:full":"Pirquetg 5a Wien Wien 1220",
    "addr:housenumber":"5a",
    "addr:postcode":"1220",
    "addr:street":"Pirquetg",
    "iso:country":"AT",
    "sg:address":"Pirquetg 5a",
    "sg:city":"Wien",
    "sg:orig_category":"Tabaktrafiken",
    "sg:phone":"+43 1 2821285",
    "sg:postcode":"1220",
    "sg:province":"Wien",
    "wof:name":"Fachberger Peter",
    "wof:placetype":"venue"
},
  "geometry": {"coordinates":[16.444606781,48.2497138977],"type":"Point"}
}