{
  "type": "Feature",
  "properties": {
    "addr:full":"Glanfeldg 29 St. Veit an der Glan K\u00e4rnten 9300",
    "addr:housenumber":"29",
    "addr:postcode":"9300",
    "addr:street":"Glanfeldg;Kaernten",
    "iso:country":"AT",
    "sg:address":"Glanfeldg 29",
    "sg:city":"St. Veit an der Glan",
    "sg:orig_category":"Lebens- U Sozialberatung",
    "sg:phone":"+43 4342 1228346",
    "sg:postcode":"9300",
    "sg:province":"K\u00e4rnten",
    "wof:name":"Lebens- u Sozialberatung H\u00fcbler Heimo Mag",
    "wof:placetype":"venue"
},
  "geometry": {"coordinates":[14.3818540573,46.7568817139],"type":"Point"}
}