{
  "type": "Feature",
  "properties": {
    "addr:full":"R\u00f6merpark 1 Frohnleiten Steiermark 8130",
    "addr:housenumber":"1",
    "addr:postcode":"8130",
    "addr:street":"Roemerpark",
    "iso:country":"AT",
    "sg:address":"R\u00f6merpark 1",
    "sg:city":"Frohnleiten",
    "sg:orig_category":"Friseure U Frisiersalons",
    "sg:phone":"+43 4331 264471",
    "sg:postcode":"8130",
    "sg:province":"Steiermark",
    "wof:name":"Haarstudio Dagmar Jantscher",
    "wof:placetype":"venue"
},
  "geometry": {"coordinates":[15.3268537521,47.271068573],"type":"Point"}
}