{
  "type": "Feature",
  "properties": {
    "iso:country":"AT",
    "sg:address":"Schubertstr 27",
    "sg:city":"Kufstein",
    "sg:orig_category":"Autohandel",
    "sg:phone":"+43 5372 647400",
    "sg:postcode":"6330",
    "sg:province":"Tirol",
    "wof:name":"Autozentrum Kufstein-Zell - Auto-Service GesmbH",
    "wof:placetype":"venue"
},
  "geometry": {"coordinates":[12.1618709564,47.5857849121],"type":"Point"}
}