{
  "type": "Feature",
  "properties": {
    "addr:full":"Kraihammerstr 43 Eugendorf Salzburg 5301",
    "addr:housenumber":"43",
    "addr:postcode":"5301",
    "addr:street":"Kraihammerstr;Salzburg",
    "iso:country":"AT",
    "sg:address":"Kraihammerstr 43",
    "sg:city":"Eugendorf",
    "sg:orig_category":"Tabaktrafiken",
    "sg:phone":"+43 6225 7273",
    "sg:postcode":"5301",
    "sg:province":"Salzburg",
    "wof:name":"Weichenberger Eva",
    "wof:placetype":"venue"
},
  "geometry": {"coordinates":[13.1303033829,47.8658866882],"type":"Point"}
}