{
  "type": "Feature",
  "properties": {
    "addr:full":"Nr 148 Teufenbach Steiermark 8833",
    "addr:postcode":"8833",
    "addr:street":"Nr 148",
    "iso:country":"AT",
    "sg:address":"Nr 148",
    "sg:city":"Teufenbach",
    "sg:orig_category":"\u00c3\u201erzte / F Allgemeinmedizin",
    "sg:phone":"+43 3582 81750",
    "sg:postcode":"8833",
    "sg:province":"Steiermark",
    "wof:name":"Geigl Horst Dr",
    "wof:placetype":"venue"
},
  "geometry": {"coordinates":[14.3591108322,47.1285476685],"type":"Point"}
}