{
  "type": "Feature",
  "properties": {
    "addr:full":"Wagramer Stra\u00dfe Donauzentrum 81 Wien Wien 1220",
    "addr:housenumber":"81",
    "addr:postcode":"1220",
    "addr:street":"Wagramer Strasse Donauzentrum",
    "iso:country":"AT",
    "sg:address":"Wagramer Stra\u00dfe Donauzentrum 81",
    "sg:city":"Wien",
    "sg:orig_category":"Lederbekleidung",
    "sg:phone":"+43 4312 036497",
    "sg:postcode":"1220",
    "sg:province":"Wien",
    "wof:name":"INDIAN DREAMS",
    "wof:placetype":"venue"
},
  "geometry": {"coordinates":[16.444606781,48.2497138977],"type":"Point"}
}