{
  "type": "Feature",
  "properties": {
    "addr:full":"Brandberg 12a Mayrhofen Tirol 6290",
    "addr:housenumber":"12a",
    "addr:postcode":"6290",
    "addr:street":"Brandberg;Tirol",
    "iso:country":"AT",
    "sg:address":"Brandberg 12a",
    "sg:city":"Mayrhofen",
    "sg:classifiers":[
        {
            "category":"Home & Garden",
            "subcategory":"Carpets & Floor Coverings",
            "type":"Retail Goods"
        }
    ],
    "sg:phone":"+43 5285 641520",
    "sg:postcode":"6290",
    "sg:province":"Tirol",
    "sg:tags":[
        "screed",
        "steel",
        "stainless",
        "grating"
    ],
    "sg:website":"estrichtechnik.at",
    "wof:name":"Estrich-Technik Dengg & Tasser GmbH",
    "wof:placetype":"venue"
},
  "geometry": {"coordinates":[11.8984899521,47.167301178],"type":"Point"}
}