{
  "type": "Feature",
  "properties": {
    "addr:full":"Nr 114 Feistritz an der Drau K\u00e4rnten 9710",
    "addr:postcode":"9710",
    "addr:street":"Nr",
    "iso:country":"AT",
    "sg:address":"Nr 114",
    "sg:city":"Feistritz an der Drau",
    "sg:orig_category":"Hauptschulen",
    "sg:phone":"+43 4342 452350",
    "sg:postcode":"9710",
    "sg:province":"K\u00e4rnten",
    "wof:name":"Hauptschule 1 - Schihauptschule",
    "wof:placetype":"venue"
},
  "geometry": {"coordinates":[13.66314888,46.7018623352],"type":"Point"}
}