{
  "type": "Feature",
  "properties": {
    "iso:country":"AT",
    "sg:address":"Prinz-Eugen-Str 47",
    "sg:city":"Pasching",
    "sg:orig_category":"Sauna U Dampfbad / Bau U Ausstattung",
    "sg:phone":"+43 4372 2973115",
    "sg:postcode":"4061",
    "sg:province":"Ober\u00f6sterreich",
    "wof:name":"Kreczi Hartwig - Schwimmb\u00e4der-Sauna-Lehmklimakammer-Dampfb\u00e4der",
    "wof:placetype":"venue"
},
  "geometry": {"coordinates":[14.2432098389,48.2437896729],"type":"Point"}
}