{
  "type": "Feature",
  "properties": {
    "addr:full":"Schie\u00dfstand 24 Inzing Tirol 6401",
    "addr:housenumber":"24",
    "addr:postcode":"6401",
    "addr:street":"Schiessstand;Tirol",
    "iso:country":"AT",
    "sg:address":"Schie\u00dfstand 24",
    "sg:city":"Inzing",
    "sg:orig_category":"Tischlereien",
    "sg:phone":"+43 5238 53903",
    "sg:postcode":"6401",
    "sg:province":"Tirol",
    "wof:name":"Gruber Johann",
    "wof:placetype":"venue"
},
  "geometry": {"coordinates":[11.2182235718,47.2662582397],"type":"Point"}
}