{
  "type": "Feature",
  "properties": {
    "addr:full":"Anton-Adlgasser-Weg 22 Salzburg Salzburg 5020",
    "addr:housenumber":"22",
    "addr:postcode":"5020",
    "addr:street":"Anton-Adlgasser-Weg;Salzburg",
    "iso:country":"AT",
    "sg:address":"Anton-Adlgasser-Weg 22",
    "sg:city":"Salzburg",
    "sg:orig_category":"Schifffahrt",
    "sg:phone":"+43 662 825858",
    "sg:postcode":"5020",
    "sg:province":"Salzburg",
    "wof:name":"Salzburg Stadt Schiff-Fahrt GmbH & Co KG",
    "wof:placetype":"venue"
},
  "geometry": {"coordinates":[13.0365161896,47.7820549011],"type":"Point"}
}