{
  "type": "Feature",
  "properties": {
    "iso:country":"AT",
    "sg:address":"Dorfstr 60",
    "sg:city":"St. Anton am Arlberg",
    "sg:orig_category":"Bars-Cafes",
    "sg:phone":"+43 5446 271454",
    "sg:postcode":"6580",
    "sg:province":"Tirol",
    "wof:name":"Bobo's Bar-Restaurant",
    "wof:placetype":"venue"
},
  "geometry": {"coordinates":[10.266576767,47.1296043396],"type":"Point"}
}