{
  "type": "Feature",
  "properties": {
    "iso:country":"AT",
    "sg:address":"Untermarkt 18",
    "sg:city":"Reutte",
    "sg:orig_category":"Friseure U Frisiersalons",
    "sg:phone":"+43 4356 7262643",
    "sg:postcode":"6600",
    "sg:province":"Tirol",
    "wof:name":"Frisiersalon Singer",
    "wof:placetype":"venue"
},
  "geometry": {"coordinates":[10.7178153992,47.4905891418],"type":"Point"}
}