{
  "type": "Feature",
  "properties": {
    "addr:full":"Hauptstr 57 Reichenau an der Rax Nieder\u00f6sterreich 2651",
    "addr:housenumber":"57",
    "addr:postcode":"2651",
    "addr:street":"Hauptstr",
    "iso:country":"AT",
    "sg:address":"Hauptstr 57",
    "sg:city":"Reichenau an der Rax",
    "sg:orig_category":"Bauunternehmen",
    "sg:phone":"+43 2666 536090",
    "sg:postcode":"2651",
    "sg:province":"Nieder\u00f6sterreich",
    "wof:name":"Gruber & Seebacher Hoch- Tief- Stahlbetonbau GesmbH",
    "wof:placetype":"venue"
},
  "geometry": {"coordinates":[15.844581604,47.6953468323],"type":"Point"}
}