{
  "type": "Feature",
  "properties": {
    "addr:full":"Nr 7 Irnfritz Nieder\u00f6sterreich 3754",
    "addr:housenumber":"3754",
    "addr:street":"Nr;Irnfritz Niederoesterreich",
    "iso:country":"AT",
    "sg:address":"Nr 7",
    "sg:city":"Irnfritz",
    "sg:orig_category":"Transportunternehmen",
    "sg:phone":"+43 2986 6266",
    "sg:postcode":"3754",
    "sg:province":"Nieder\u00f6sterreich",
    "wof:name":"Rudolf Franz",
    "wof:placetype":"venue"
},
  "geometry": {"coordinates":[15.5585279465,48.7394676208],"type":"Point"}
}