{
  "type": "Feature",
  "properties": {
    "addr:full":"Conrad-von-H\u00f6tzendorf-Str 104 Graz Steiermark 8010",
    "addr:housenumber":"104",
    "addr:postcode":"8010",
    "iso:country":"AT",
    "sg:address":"Conrad-von-H\u00f6tzendorf-Str 104",
    "sg:city":"Graz",
    "sg:orig_category":"Non-Classified Establishments",
    "sg:phone":"+43 4331 64634390",
    "sg:postcode":"8010",
    "sg:province":"Steiermark",
    "wof:name":"Magistrat Graz - Bezirksamt 6. Bezirk Jakomini",
    "wof:placetype":"venue"
},
  "geometry": {"coordinates":[15.4499788284,47.0519447327],"type":"Point"}
}