{
  "type": "Feature",
  "properties": {
    "addr:full":"St. Marienkirchen Ober\u00f6sterreich 4774",
    "addr:postcode":"4774",
    "iso:country":"AT",
    "sg:city":"St. Marienkirchen",
    "sg:orig_category":"Feuerwehren",
    "sg:phone":"+43 4377 112136",
    "sg:postcode":"4774",
    "sg:province":"Ober\u00f6sterreich",
    "wof:name":"Freiwillige Feuerwehr Hackenbuch",
    "wof:placetype":"venue"
},
  "geometry": {"coordinates":[13.4707736969,48.3878173828],"type":"Point"}
}