{
  "type": "Feature",
  "properties": {
    "addr:full":"Dresdner Str 6 Wien Wien 1200",
    "addr:housenumber":"6",
    "addr:postcode":"1200",
    "addr:street":"Str",
    "iso:country":"AT",
    "sg:address":"Dresdner Str 6",
    "sg:city":"Wien",
    "sg:orig_category":"Baumeister",
    "sg:phone":"+43 1 3323399",
    "sg:postcode":"1200",
    "sg:province":"Wien",
    "wof:name":"Warenits Karl Stefan Ing",
    "wof:placetype":"venue"
},
  "geometry": {"coordinates":[16.3747215271,48.2413482666],"type":"Point"}
}