{
  "type": "Feature",
  "properties": {
    "addr:full":"Bundesstr. 74 Rankweil Vorarlberg 6830",
    "addr:housenumber":"74",
    "addr:postcode":"6830",
    "addr:street":"Bundesstr.",
    "iso:country":"AT",
    "sg:address":"Bundesstr. 74",
    "sg:city":"Rankweil",
    "sg:classifiers":[
        {
            "category":"Autos & Motor Vehicles",
            "subcategory":"Automobile Sales",
            "type":"Retail Goods"
        }
    ],
    "sg:phone":"+43 4355 2277290",
    "sg:postcode":"6830",
    "sg:province":"Vorarlberg",
    "sg:tags":[
        "industrial"
    ],
    "wof:name":"WALSER GMBH",
    "wof:placetype":"venue"
},
  "geometry": {"coordinates":[9.6189241409,47.2827110291],"type":"Point"}
}