{
  "type": "Feature",
  "properties": {
    "addr:full":"Rathauspl 3 Gmunden Ober\u00f6sterreich 4810",
    "addr:housenumber":"3",
    "addr:postcode":"4810",
    "addr:street":"Rathauspl;Oberoesterreich",
    "iso:country":"AT",
    "sg:address":"Rathauspl 3",
    "sg:city":"Gmunden",
    "sg:orig_category":"Juwelen, Gold- U Silberwaren / Einzelhandel",
    "sg:phone":"+43 4376 1264040",
    "sg:postcode":"4810",
    "sg:province":"Ober\u00f6sterreich",
    "wof:name":"Reiter Juwelier",
    "wof:placetype":"venue"
},
  "geometry": {"coordinates":[13.7993888855,47.91847229],"type":"Point"}
}