{
  "type": "Feature",
  "properties": {
    "addr:full":"Brucker Bundesstr 6 Zell am See Salzburg 5700",
    "addr:housenumber":"6",
    "addr:postcode":"5700",
    "addr:street":"Salzburg",
    "iso:country":"AT",
    "sg:address":"Brucker Bundesstr 6",
    "sg:city":"Zell am See",
    "sg:orig_category":"Gerichte",
    "sg:phone":"+43 6542 736780",
    "sg:postcode":"5700",
    "sg:province":"Salzburg",
    "wof:name":"Bezirksgericht Zell am See",
    "wof:placetype":"venue"
},
  "geometry": {"coordinates":[12.7962656021,47.3225097656],"type":"Point"}
}