{
  "type": "Feature",
  "properties": {
    "addr:full":"Salzburger Str 92 Oberndorf Salzburg 5110",
    "addr:housenumber":"92",
    "addr:postcode":"5110",
    "addr:street":"Salzburger Str",
    "iso:country":"AT",
    "sg:address":"Salzburger Str 92",
    "sg:city":"Oberndorf",
    "sg:orig_category":"Textilreinigung",
    "sg:phone":"+43 4362 724236",
    "sg:postcode":"5110",
    "sg:province":"Salzburg",
    "wof:name":"Wacht Franz GesmbH & Co KG",
    "wof:placetype":"venue"
},
  "geometry": {"coordinates":[12.9352703094,47.9464683533],"type":"Point"}
}