{
  "type": "Feature",
  "properties": {
    "addr:full":"Nr 37 Galt\u00fcr Tirol 6563",
    "addr:postcode":"6563",
    "addr:street":"Nr 37 Galtuer Tirol",
    "iso:country":"AT",
    "sg:address":"Nr 37",
    "sg:city":"Galt\u00fcr",
    "sg:orig_category":"Non-Classified Establishments",
    "sg:phone":"+43 5443 8236",
    "sg:postcode":"6563",
    "sg:province":"Tirol",
    "wof:name":"Pfarramt",
    "wof:placetype":"venue"
},
  "geometry": {"coordinates":[9.2292995453,46.4031715393],"type":"Point"}
}