{
  "type": "Feature",
  "properties": {
    "addr:full":"Jahnstr 16 Langenlois Nieder\u00f6sterreich 3550",
    "addr:housenumber":"16",
    "addr:postcode":"3550",
    "addr:street":"Jahnstr",
    "iso:country":"AT",
    "sg:address":"Jahnstr 16",
    "sg:city":"Langenlois",
    "sg:orig_category":"Maler, Anstreicher U Lackierer",
    "sg:phone":"+43 2734 2311",
    "sg:postcode":"3550",
    "sg:province":"Nieder\u00f6sterreich",
    "wof:name":"Mayerhofer Helmut",
    "wof:placetype":"venue"
},
  "geometry": {"coordinates":[15.6882963181,48.4767532349],"type":"Point"}
}