{
  "type": "Feature",
  "properties": {
    "addr:full":"Marktstr 30 Haus Steiermark 8967",
    "addr:housenumber":"30",
    "addr:postcode":"8967",
    "addr:street":"Marktstr",
    "iso:country":"AT",
    "sg:address":"Marktstr 30",
    "sg:city":"Haus",
    "sg:orig_category":"Banken U Sparkassen",
    "sg:phone":"+43 4336 8623210",
    "sg:postcode":"8967",
    "sg:province":"Steiermark",
    "wof:name":"Steierm\u00e4rkische Bank u Sparkassen AG",
    "wof:placetype":"venue"
},
  "geometry": {"coordinates":[13.7689466476,47.4106216431],"type":"Point"}
}