{
  "type": "Feature",
  "properties": {
    "iso:country":"AT",
    "sg:address":"Eisenst\u00e4dter Str 3",
    "sg:city":"Kittsee",
    "sg:orig_category":"Tankstellen",
    "sg:phone":"+43 4321 432224",
    "sg:postcode":"2421",
    "sg:province":"Burgenland",
    "wof:name":"AVANTI-Tankstelle",
    "wof:placetype":"venue"
},
  "geometry": {"coordinates":[17.0591754913,48.0927963257],"type":"Point"}
}