{
  "type": "Feature",
  "properties": {
    "addr:full":"Mitterwei\u00dfenbach 47 Bad Ischl Ober\u00f6sterreich 4820",
    "addr:housenumber":"47",
    "addr:postcode":"4820",
    "addr:street":"Mitterweissenbach",
    "iso:country":"AT",
    "sg:address":"Mitterwei\u00dfenbach 47",
    "sg:city":"Bad Ischl",
    "sg:orig_category":"Feuerwehren",
    "sg:phone":"+43 6132 29110",
    "sg:postcode":"4820",
    "sg:province":"Ober\u00f6sterreich",
    "wof:name":"Freiwillige Feuerwehr Mitterwei\u00dfenbach",
    "wof:placetype":"venue"
},
  "geometry": {"coordinates":[13.6257123947,47.711971283],"type":"Point"}
}