{
  "type": "Feature",
  "properties": {
    "addr:full":"Hollabrunner Str 44 Breitenwaida Nieder\u00f6sterreich 2014",
    "addr:housenumber":"44",
    "addr:postcode":"2014",
    "addr:street":"Str",
    "iso:country":"AT",
    "sg:address":"Hollabrunner Str 44",
    "sg:city":"Breitenwaida",
    "sg:orig_category":"Immobilienmakler",
    "sg:phone":"+43 4329 542057",
    "sg:postcode":"2014",
    "sg:province":"Nieder\u00f6sterreich",
    "wof:name":"Zlabinger Immobilien",
    "wof:placetype":"venue"
},
  "geometry": {"coordinates":[16.0707645416,48.5177497864],"type":"Point"}
}