{
  "type": "Feature",
  "properties": {
    "addr:full":"Grabenweg 72 Innsbruck Tirol 6020",
    "addr:housenumber":"72",
    "addr:postcode":"6020",
    "addr:street":"Grabenweg;Tirol",
    "iso:country":"AT",
    "sg:address":"Grabenweg 72",
    "sg:city":"Innsbruck",
    "sg:orig_category":"Datenverarbeitung",
    "sg:phone":"+43 4351 2334400",
    "sg:postcode":"6020",
    "sg:province":"Tirol",
    "wof:name":"Schranz Gernot",
    "wof:placetype":"venue"
},
  "geometry": {"coordinates":[11.4403610229,47.2649726868],"type":"Point"}
}