{
  "type": "Feature",
  "properties": {
    "addr:full":"Ernst Grein-Str 33 Aigen Salzburg 5026",
    "addr:housenumber":"33",
    "addr:postcode":"5026",
    "addr:street":"Aigen Salzburg",
    "iso:country":"AT",
    "sg:address":"Ernst Grein-Str 33",
    "sg:city":"Aigen",
    "sg:classifiers":[
        {
            "category":"Internet Cafe",
            "subcategory":"None",
            "type":"Food & Drink"
        }
    ],
    "sg:phone":"+43 699 11342158",
    "sg:postcode":"5026",
    "sg:province":"Salzburg",
    "wof:name":"Next Generation Software Gerhard Kittel",
    "wof:placetype":"venue"
},
  "geometry": {"coordinates":[13.0795679092,47.7950172424],"type":"Point"}
}