{
  "type": "Feature",
  "properties": {
    "addr:full":"Industriestr 13-15 Eisenstadt Burgenland 7000",
    "addr:postcode":"7000",
    "iso:country":"AT",
    "sg:address":"Industriestr 13-15",
    "sg:city":"Eisenstadt",
    "sg:orig_category":"Pokale, Automaten, Kaffeeautomaten",
    "sg:phone":"+43 2682 661110",
    "sg:postcode":"7000",
    "sg:province":"Burgenland",
    "sg:website":"www.gastromatic.at",
    "wof:name":"Gastromatic Gastro und Automatentechnik GmbH",
    "wof:placetype":"venue"
},
  "geometry": {"coordinates":[16.5342311859,47.8325157166],"type":"Point"}
}