{
  "type": "Feature",
  "properties": {
    "addr:full":"Steirerg 147 Schladming Steiermark 8970",
    "addr:housenumber":"147",
    "addr:postcode":"8970",
    "iso:country":"AT",
    "sg:address":"Steirerg 147",
    "sg:city":"Schladming",
    "sg:orig_category":"Tabaktrafiken",
    "sg:phone":"+43 4336 8722931",
    "sg:postcode":"8970",
    "sg:province":"Steiermark",
    "wof:name":"Pilz Sigrid",
    "wof:placetype":"venue"
},
  "geometry": {"coordinates":[13.6887073517,47.3919563293],"type":"Point"}
}