{
  "type": "Feature",
  "properties": {
    "addr:full":"Rosaliastr 250 Bad Erlach Nieder\u00f6sterreich 2822",
    "addr:housenumber":"250",
    "addr:postcode":"2822",
    "iso:country":"AT",
    "sg:address":"Rosaliastr 250",
    "sg:city":"Bad Erlach",
    "sg:orig_category":"Transportunternehmen",
    "sg:phone":"+43 2627 45899",
    "sg:postcode":"2822",
    "sg:province":"Nieder\u00f6sterreich",
    "wof:name":"Waldherr Transporte GesmbH & Co KG",
    "wof:placetype":"venue"
},
  "geometry": {"coordinates":[16.2261257172,47.7260856628],"type":"Point"}
}