{
  "type": "Feature",
  "properties": {
    "addr:full":"Grazer Str 35 Feldbach Steiermark 8330",
    "addr:postcode":"8330",
    "addr:street":"Str 35",
    "iso:country":"AT",
    "sg:address":"Grazer Str 35",
    "sg:city":"Feldbach",
    "sg:orig_category":"Immobilienverwaltungen",
    "sg:phone":"+43 4331 522813",
    "sg:postcode":"8330",
    "sg:province":"Steiermark",
    "wof:name":"Allegro GesmbH",
    "wof:placetype":"venue"
},
  "geometry": {"coordinates":[15.8805446625,46.9573783875],"type":"Point"}
}