{
  "type": "Feature",
  "properties": {
    "iso:country":"AT",
    "sg:address":"Roan 1",
    "sg:city":"Terfens",
    "sg:orig_category":"Garten- U Landschaftsgestaltung",
    "sg:phone":"+43 4352 2468675",
    "sg:postcode":"6123",
    "sg:province":"Tirol",
    "wof:name":"Piccinini Richard",
    "wof:placetype":"venue"
},
  "geometry": {"coordinates":[11.6425056458,47.3191947937],"type":"Point"}
}