{
  "type": "Feature",
  "properties": {
    "iso:country":"AT",
    "sg:address":"Ritzenseestr 35",
    "sg:city":"Saalfelden am Steinernen Meer",
    "sg:classifiers":[
        {
            "category":"Restaurant",
            "type":"Food & Drink"
        }
    ],
    "sg:phone":"+43 4365 82723540",
    "sg:postcode":"5760",
    "sg:province":"Salzburg",
    "wof:name":"Restaurant Ritzen",
    "wof:placetype":"venue"
},
  "geometry": {"coordinates":[12.8472290039,47.4207077026],"type":"Point"}
}