{
  "type": "Feature",
  "properties": {
    "addr:full":"Kircheng 112 Stainach Steiermark 8950",
    "addr:housenumber":"112",
    "addr:postcode":"8950",
    "iso:country":"AT",
    "sg:address":"Kircheng 112",
    "sg:city":"Stainach",
    "sg:orig_category":"Volksschulen",
    "sg:phone":"+43 3682 22353",
    "sg:postcode":"8950",
    "sg:province":"Steiermark",
    "wof:name":"Volksschule",
    "wof:placetype":"venue"
},
  "geometry": {"coordinates":[14.1094732285,47.5300216675],"type":"Point"}
}