{
  "type": "Feature",
  "properties": {
    "addr:full":"Lechaschau, Lechtaler Str. 45 A  Reutte Tirol 6600",
    "addr:housenumber":"45 a",
    "addr:postcode":"6600",
    "addr:street":"Str.;Tirol",
    "iso:country":"AT",
    "sg:address":"Lechaschau, Lechtaler Str. 45 A ",
    "sg:city":"Reutte",
    "sg:classifiers":[
        {
            "category":"Manufacturing",
            "subcategory":"Metals",
            "type":"Manufacturing & Wholesale Goods"
        }
    ],
    "sg:phone":"+43 4356 7263055",
    "sg:postcode":"6600",
    "sg:province":"Tirol",
    "sg:tags":[
        "metallurgy",
        "metalworking"
    ],
    "wof:name":"MULTIVAC-MASCHINENBAU GES.MBH & CO KG",
    "wof:placetype":"venue"
},
  "geometry": {"coordinates":[10.7185935974,47.4889183044],"type":"Point"}
}