{
  "type": "Feature",
  "properties": {
    "addr:full":"R\u00f6tzbachg 28 Trofaiach Steiermark 8793",
    "addr:housenumber":"28",
    "addr:postcode":"8793",
    "addr:street":"Roetzbachg",
    "iso:country":"AT",
    "sg:address":"R\u00f6tzbachg 28",
    "sg:city":"Trofaiach",
    "sg:orig_category":"Transportunternehmen",
    "sg:phone":"+43 4338 4723850",
    "sg:postcode":"8793",
    "sg:province":"Steiermark",
    "wof:name":"Gep Transport GmbH",
    "wof:placetype":"venue"
},
  "geometry": {"coordinates":[15.0105581284,47.4325637817],"type":"Point"}
}