{
  "type": "Feature",
  "properties": {
    "iso:country":"AT",
    "sg:address":"Gewerbepark Urfahr 6",
    "sg:city":"Linz",
    "sg:classifiers":[
        {
            "category":"Professional",
            "subcategory":"Computer Services",
            "type":"Services"
        }
    ],
    "sg:phone":"+43 4373 2700425",
    "sg:postcode":"4040",
    "sg:province":"Ober\u00f6sterreich",
    "sg:tags":[
        "information",
        "technology"
    ],
    "wof:name":"HAPRA HARD- UND SOFTWARE F\u00dcR GRAFIK UND DESIGN GESELLSCHAFT MBH",
    "wof:placetype":"venue"
},
  "geometry": {"coordinates":[14.2872982025,48.3173866272],"type":"Point"}
}