{
  "type": "Feature",
  "properties": {
    "addr:full":"Pachersdorfstr 1 St. Marien Ober\u00f6sterreich 4502",
    "addr:housenumber":"1",
    "addr:postcode":"4502",
    "addr:street":"Pachersdorfstr;Oberoesterreich",
    "iso:country":"AT",
    "sg:address":"Pachersdorfstr 1",
    "sg:city":"St. Marien",
    "sg:orig_category":"Fassbindereien",
    "sg:phone":"+43 4372 274548",
    "sg:postcode":"4502",
    "sg:province":"Ober\u00f6sterreich",
    "wof:name":"Hagm\u00fcller Florian",
    "wof:placetype":"venue"
},
  "geometry": {"coordinates":[14.2385015488,48.1637611389],"type":"Point"}
}