{
  "type": "Feature",
  "properties": {
    "addr:full":"Georg-Coch-Pl 3/8 Wien Wien 1010",
    "addr:housenumber":"3 / 8",
    "addr:postcode":"1010",
    "addr:street":"Georg-Coch-Pl",
    "iso:country":"AT",
    "sg:address":"Georg-Coch-Pl 3/8",
    "sg:city":"Wien",
    "sg:orig_category":"Architekten",
    "sg:phone":"+43 1 5127142",
    "sg:postcode":"1010",
    "sg:province":"Wien",
    "wof:name":"Hoppe Diether S Arch Prof DI Dr techn",
    "wof:placetype":"venue"
},
  "geometry": {"coordinates":[16.3816261292,48.2100791931],"type":"Point"}
}