{
  "type": "Feature",
  "properties": {
    "addr:full":"Ledochovskastr 4 Loosdorf Nieder\u00f6sterreich 3382",
    "addr:housenumber":"4",
    "addr:postcode":"3382",
    "addr:street":"Ledochovskastr",
    "iso:country":"AT",
    "sg:address":"Ledochovskastr 4",
    "sg:city":"Loosdorf",
    "sg:orig_category":"Non-Classified Establishments",
    "sg:phone":"+43 2754 6257",
    "sg:postcode":"3382",
    "sg:province":"Nieder\u00f6sterreich",
    "wof:name":"Pfarramt",
    "wof:placetype":"venue"
},
  "geometry": {"coordinates":[15.3811845779,48.1837120056],"type":"Point"}
}