{
  "type": "Feature",
  "properties": {
    "addr:full":"Hauptpl 2 Ober-Grafendorf Nieder\u00f6sterreich 3200",
    "addr:housenumber":"2",
    "addr:postcode":"3200",
    "addr:street":"Hauptpl",
    "iso:country":"AT",
    "sg:address":"Hauptpl 2",
    "sg:city":"Ober-Grafendorf",
    "sg:orig_category":"Gemeinden",
    "sg:phone":"+43 2747 23130",
    "sg:postcode":"3200",
    "sg:province":"Nieder\u00f6sterreich",
    "wof:name":"Gemeindeamt Ober-Grafendorf",
    "wof:placetype":"venue"
},
  "geometry": {"coordinates":[15.5442972183,48.1507644653],"type":"Point"}
}