{
  "type": "Feature",
  "properties": {
    "addr:full":"Gro\u00dfsulzer Strasse 15 Wundschuh Steiermark 8142",
    "addr:housenumber":"15",
    "addr:postcode":"8142",
    "addr:street":"Grosssulzer Strasse",
    "iso:country":"AT",
    "sg:address":"Gro\u00dfsulzer Strasse 15",
    "sg:city":"Wundschuh",
    "sg:classifiers":[
        {
            "category":"Building & Trades",
            "subcategory":"Construction",
            "type":"Services"
        }
    ],
    "sg:phone":"+43 3135 54330",
    "sg:postcode":"8142",
    "sg:province":"Steiermark",
    "sg:tags":[
        "bitumen",
        "road"
    ],
    "sg:website":"bitubau.com",
    "wof:name":"BITUBAU Bitumin\u00f6se Baustoffe und Strassensanierung GmbH",
    "wof:placetype":"venue"
},
  "geometry": {"coordinates":[15.4557409286,46.9290847778],"type":"Point"}
}