{
  "type": "Feature",
  "properties": {
    "addr:full":"Nr 46 H\u00fcrm Nieder\u00f6sterreich 3383",
    "addr:postcode":"3383",
    "addr:street":"Nr 46 Huerm",
    "iso:country":"AT",
    "sg:address":"Nr 46",
    "sg:city":"H\u00fcrm",
    "sg:orig_category":"Feuerwehren",
    "sg:phone":"+43 2754 6006",
    "sg:postcode":"3383",
    "sg:province":"Nieder\u00f6sterreich",
    "wof:name":"Freiwillige Feuerwehr Inning",
    "wof:placetype":"venue"
},
  "geometry": {"coordinates":[15.4132108688,48.1561889648],"type":"Point"}
}