{
  "type": "Feature",
  "properties": {
    "addr:full":"Unterberg 32 Alpbach Tirol 6236",
    "addr:housenumber":"32",
    "addr:postcode":"6236",
    "addr:street":"Unterberg;Tirol",
    "iso:country":"AT",
    "sg:address":"Unterberg 32",
    "sg:city":"Alpbach",
    "sg:orig_category":"Erdarbeiten",
    "sg:phone":"+43 699 10017974",
    "sg:postcode":"6236",
    "sg:province":"Tirol",
    "wof:name":"Moser Hans",
    "wof:placetype":"venue"
},
  "geometry": {"coordinates":[11.9435110092,47.3986091614],"type":"Point"}
}