{
  "type": "Feature",
  "properties": {
    "addr:full":"Roseggerstr 4 Marchtrenk Ober\u00f6sterreich 4614",
    "addr:housenumber":"4",
    "addr:postcode":"4614",
    "addr:street":"Roseggerstr",
    "iso:country":"AT",
    "sg:address":"Roseggerstr 4",
    "sg:city":"Marchtrenk",
    "sg:orig_category":"Stahl / Gro\u00c3\u0178handel",
    "sg:phone":"+43 4372 4358558",
    "sg:postcode":"4614",
    "sg:province":"Ober\u00f6sterreich",
    "wof:name":"Mitter G\u00fcnther",
    "wof:placetype":"venue"
},
  "geometry": {"coordinates":[14.1167697906,48.1955947876],"type":"Point"}
}