{
  "type": "Feature",
  "properties": {
    "iso:country":"AT",
    "sg:address":"Eichstr 54",
    "sg:city":"Gnigl",
    "sg:classifiers":[
        {
            "category":"Restaurant",
            "type":"Food & Drink"
        }
    ],
    "sg:phone":"+43 662 640438",
    "sg:postcode":"5023",
    "sg:province":"Salzburg",
    "wof:name":"Restaurant Pomodoro",
    "wof:placetype":"venue"
},
  "geometry": {"coordinates":[13.0746841431,47.8116226196],"type":"Point"}
}