{
  "type": "Feature",
  "properties": {
    "addr:full":"Gaaler Str 38 Knittelfeld Steiermark 8720",
    "addr:housenumber":"38",
    "addr:postcode":"8720",
    "addr:street":"Str",
    "iso:country":"AT",
    "sg:address":"Gaaler Str 38",
    "sg:city":"Knittelfeld",
    "sg:orig_category":"Massagen",
    "sg:phone":"+43 676 848432101",
    "sg:postcode":"8720",
    "sg:province":"Steiermark",
    "wof:name":"Weber Rene'",
    "wof:placetype":"venue"
},
  "geometry": {"coordinates":[14.8141460419,47.2133293152],"type":"Point"}
}