{
  "type": "Feature",
  "properties": {
    "addr:full":"Donaustr 7 Stockerau Nieder\u00f6sterreich 2000",
    "addr:housenumber":"7",
    "addr:postcode":"2000",
    "addr:street":"Donaustr",
    "iso:country":"AT",
    "sg:address":"Donaustr 7",
    "sg:city":"Stockerau",
    "sg:orig_category":"Rauchfangkehrer",
    "sg:phone":"+43 2266 62642",
    "sg:postcode":"2000",
    "sg:province":"Nieder\u00f6sterreich",
    "wof:name":"Juza Josef",
    "wof:placetype":"venue"
},
  "geometry": {"coordinates":[16.2061958313,48.383895874],"type":"Point"}
}