{
  "type": "Feature",
  "properties": {
    "addr:full":"Stadtpl 39 Gm\u00fcnd Nieder\u00f6sterreich 3950",
    "addr:housenumber":"39",
    "addr:postcode":"3950",
    "addr:street":"Stadtpl;Niederoesterreich",
    "iso:country":"AT",
    "sg:address":"Stadtpl 39",
    "sg:city":"Gm\u00fcnd",
    "sg:orig_category":"Notare",
    "sg:phone":"+43 2852 52376",
    "sg:postcode":"3950",
    "sg:province":"Nieder\u00f6sterreich",
    "wof:name":"Wagner Viktoria Dr iur",
    "wof:placetype":"venue"
},
  "geometry": {"coordinates":[14.9868202209,48.7731819153],"type":"Point"}
}