{
  "type": "Feature",
  "properties": {
    "addr:full":"Markt 14 Waldhausen im Strudengau Ober\u00f6sterreich 4391",
    "addr:housenumber":"14",
    "addr:postcode":"4391",
    "addr:street":"Markt",
    "iso:country":"AT",
    "sg:address":"Markt 14",
    "sg:city":"Waldhausen im Strudengau",
    "sg:orig_category":"Tourismusinformation U -Organisationen",
    "sg:phone":"+43 4372 604505",
    "sg:postcode":"4391",
    "sg:province":"Ober\u00f6sterreich",
    "wof:name":"Tourismusverband Waldhausen im Strudengau",
    "wof:placetype":"venue"
},
  "geometry": {"coordinates":[14.9469547272,48.2740745544],"type":"Point"}
}