{
  "type": "Feature",
  "properties": {
    "addr:full":"Nr 26 Eggendorf im Thale Nieder\u00f6sterreich 2031",
    "addr:postcode":"2031",
    "addr:street":"Nr 26",
    "iso:country":"AT",
    "sg:address":"Nr 26",
    "sg:city":"Eggendorf im Thale",
    "sg:orig_category":"Forstverwaltungen",
    "sg:phone":"+43 2953 8221",
    "sg:postcode":"2031",
    "sg:province":"Nieder\u00f6sterreich",
    "wof:name":"Sch\u00f6nborn-Buchheim'sche Georg Revierleitung",
    "wof:placetype":"venue"
},
  "geometry": {"coordinates":[16.1729030609,48.5815963745],"type":"Point"}
}