{
  "type": "Feature",
  "properties": {
    "addr:full":"Leopoldsdorfer Str 33 Maria Lanzendorf Nieder\u00f6sterreich 2326",
    "addr:housenumber":"33",
    "addr:postcode":"2326",
    "addr:street":"Str",
    "iso:country":"AT",
    "sg:address":"Leopoldsdorfer Str 33",
    "sg:city":"Maria Lanzendorf",
    "sg:orig_category":"Personalbereitstellung",
    "sg:phone":"+43 2235 44088",
    "sg:postcode":"2326",
    "sg:province":"Nieder\u00f6sterreich",
    "wof:name":"part personalleasing",
    "wof:placetype":"venue"
},
  "geometry": {"coordinates":[16.4144134521,48.0999565125],"type":"Point"}
}