{
  "type": "Feature",
  "properties": {
    "iso:country":"AT",
    "sg:city":"Drasenhofen",
    "sg:orig_category":"Non-Classified Establishments",
    "sg:phone":"+43 2554 85315",
    "sg:postcode":"2165",
    "sg:province":"Nieder\u00f6sterreich",
    "wof:name":"Pfarramt",
    "wof:placetype":"venue"
},
  "geometry": {"coordinates":[16.6036434174,48.7538299561],"type":"Point"}
}