{
  "type": "Feature",
  "properties": {
    "addr:full":"Huban 226 Doren Vorarlberg 6933",
    "addr:housenumber":"226",
    "addr:postcode":"6933",
    "addr:street":"Huban",
    "iso:country":"AT",
    "sg:address":"Huban 226",
    "sg:city":"Doren",
    "sg:orig_category":"Zimmereien",
    "sg:phone":"+43 5516 2260",
    "sg:postcode":"6933",
    "sg:province":"Vorarlberg",
    "wof:name":"\u00f6sterle Artur",
    "wof:placetype":"venue"
},
  "geometry": {"coordinates":[9.8966245651,47.4967956543],"type":"Point"}
}