{
  "type": "Feature",
  "properties": {
    "addr:full":"Gaswerkgasse 12  Salzburg Salzburg 5020",
    "addr:housenumber":"12",
    "addr:postcode":"5020",
    "addr:street":"Gaswerkgasse;Salzburg",
    "iso:country":"AT",
    "sg:address":"Gaswerkgasse 12 ",
    "sg:city":"Salzburg",
    "sg:classifiers":[
        {
            "category":"Professional",
            "subcategory":"Computer Services",
            "type":"Services"
        }
    ],
    "sg:phone":"+43 4366 24344140",
    "sg:postcode":"5020",
    "sg:province":"Salzburg",
    "sg:tags":[
        "information",
        "technology"
    ],
    "wof:name":"KOPIERTECHNIK GES.MBH",
    "wof:placetype":"venue"
},
  "geometry": {"coordinates":[13.0331916809,47.8095741272],"type":"Point"}
}