{
  "type": "Feature",
  "properties": {
    "addr:full":"Sch\u00f6nbrunner Str 222-228 Wien Wien 1120",
    "addr:housenumber":"222-228",
    "addr:postcode":"1120",
    "addr:street":"Str",
    "iso:country":"AT",
    "sg:address":"Sch\u00f6nbrunner Str 222-228",
    "sg:city":"Wien",
    "sg:orig_category":"Massagen",
    "sg:phone":"+43 1 8139314",
    "sg:postcode":"1120",
    "sg:province":"Wien",
    "wof:name":"Massagefachinstitut Gabriele Lauder und Walter Kuri OEG",
    "wof:placetype":"venue"
},
  "geometry": {"coordinates":[16.3290939331,48.1824874878],"type":"Point"}
}