{
  "type": "Feature",
  "properties": {
    "addr:full":"Gersthofer Str 16 Wien Wien 1180",
    "addr:postcode":"1180",
    "addr:street":"Str 16",
    "iso:country":"AT",
    "sg:address":"Gersthofer Str 16",
    "sg:city":"Wien",
    "sg:orig_category":"Drogerien",
    "sg:phone":"+43 1 4784240",
    "sg:postcode":"1180",
    "sg:province":"Wien",
    "wof:name":"dm drogerie markt GmbH",
    "wof:placetype":"venue"
},
  "geometry": {"coordinates":[16.3281478882,48.2333679199],"type":"Point"}
}