{
  "type": "Feature",
  "properties": {
    "addr:full":"Roterdstr 24 Wien Wien 1160",
    "addr:housenumber":"24",
    "addr:postcode":"1160",
    "addr:street":"Roterdstr",
    "iso:country":"AT",
    "sg:address":"Roterdstr 24",
    "sg:city":"Wien",
    "sg:orig_category":"Umwelttechnik",
    "sg:phone":"+43 1 89498550",
    "sg:postcode":"1160",
    "sg:province":"Wien",
    "wof:name":"Enviroplan Umwelttechnik GesmbH",
    "wof:placetype":"venue"
},
  "geometry": {"coordinates":[16.302488327,48.21925354],"type":"Point"}
}