{
  "type": "Feature",
  "properties": {
    "addr:full":"Titus-Appel-Strasse 1 Vitis Nieder\u00f6sterreich 3902",
    "addr:housenumber":"1",
    "addr:postcode":"3902",
    "addr:street":"Titus-Appel-Strasse",
    "iso:country":"AT",
    "sg:address":"Titus-Appel-Strasse 1",
    "sg:city":"Vitis",
    "sg:classifiers":[
        {
            "category":"Building & Trades",
            "subcategory":"Plumbing",
            "type":"Services"
        }
    ],
    "sg:phone":"+43 2841 9001",
    "sg:postcode":"3902",
    "sg:province":"Nieder\u00f6sterreich",
    "sg:tags":[
        "tub",
        "bath"
    ],
    "sg:website":"appel.at",
    "wof:name":"Appel Ges.m.b.H.",
    "wof:placetype":"venue"
},
  "geometry": {"coordinates":[15.1848993301,48.7555580139],"type":"Point"}
}