{
  "type": "Feature",
  "properties": {
    "iso:country":"AT",
    "sg:address":"Zwerggrabeng 11",
    "sg:city":"Andau",
    "sg:orig_category":"Blumeneinzelhandel",
    "sg:phone":"+43 2176 3429",
    "sg:postcode":"7163",
    "sg:province":"Burgenland",
    "wof:name":"Sattler Katharina",
    "wof:placetype":"venue"
},
  "geometry": {"coordinates":[17.0308761597,47.7778396606],"type":"Point"}
}