{
  "type": "Feature",
  "properties": {
    "addr:full":"Hauptpl 11 Fels am Wagram Nieder\u00f6sterreich 3481",
    "addr:housenumber":"11",
    "addr:postcode":"3481",
    "addr:street":"Hauptpl;Niederoesterreich",
    "iso:country":"AT",
    "sg:address":"Hauptpl 11",
    "sg:city":"Fels am Wagram",
    "sg:orig_category":"Weine / Einzelhandel",
    "sg:phone":"+43 676 7515084",
    "sg:postcode":"3481",
    "sg:province":"Nieder\u00f6sterreich",
    "wof:name":"Pauser Josef - Weinbau",
    "wof:placetype":"venue"
},
  "geometry": {"coordinates":[15.8186273575,48.4383049011],"type":"Point"}
}