{
  "type": "Feature",
  "properties": {
    "addr:full":"Feldweg 18 Flaurling Tirol 6403",
    "addr:housenumber":"18",
    "addr:postcode":"6403",
    "addr:street":"Feldweg;Tirol",
    "iso:country":"AT",
    "sg:address":"Feldweg 18",
    "sg:city":"Flaurling",
    "sg:orig_category":"Weiterbildungsinstitute M Allg U Berufl Bildungsangebot",
    "sg:phone":"+43 4352 6261889",
    "sg:postcode":"6403",
    "sg:province":"Tirol",
    "wof:name":"Erwachsenenschule Flaurling",
    "wof:placetype":"venue"
},
  "geometry": {"coordinates":[11.1233005524,47.2923927307],"type":"Point"}
}