{
  "type": "Feature",
  "properties": {
    "addr:full":"Hauptstr 22 St. Radegund Steiermark 8061",
    "addr:housenumber":"22",
    "addr:postcode":"8061",
    "addr:street":"Hauptstr",
    "iso:country":"AT",
    "sg:address":"Hauptstr 22",
    "sg:city":"St. Radegund",
    "sg:orig_category":"Fleischhauereien",
    "sg:phone":"+43 4331 322234",
    "sg:postcode":"8061",
    "sg:province":"Steiermark",
    "wof:name":"Pichler Franz",
    "wof:placetype":"venue"
},
  "geometry": {"coordinates":[15.4898443222,47.1804084778],"type":"Point"}
}