{
  "type": "Feature",
  "properties": {
    "addr:full":"Lacknerg 106 Wien Wien 1180",
    "addr:housenumber":"106",
    "addr:postcode":"1180",
    "iso:country":"AT",
    "sg:address":"Lacknerg 106",
    "sg:city":"Wien",
    "sg:orig_category":"Feuerfestbau U -Materialien",
    "sg:phone":"+43 4314 706236",
    "sg:postcode":"1180",
    "sg:province":"Wien",
    "wof:name":"Technokeram HandelsgesmbH & Co KG",
    "wof:placetype":"venue"
},
  "geometry": {"coordinates":[16.3340530396,48.2279472351],"type":"Point"}
}