{
  "type": "Feature",
  "properties": {
    "addr:full":"Hauptpl 1 Voitsberg Steiermark 8570",
    "addr:housenumber":"1",
    "addr:postcode":"8570",
    "addr:street":"Hauptpl",
    "iso:country":"AT",
    "sg:address":"Hauptpl 1",
    "sg:city":"Voitsberg",
    "sg:orig_category":"Versicherungsunternehmen",
    "sg:phone":"+43 3142 224670",
    "sg:postcode":"8570",
    "sg:province":"Steiermark",
    "wof:name":"Wiener St\u00e4dtische Allgemeine Versicherung AG",
    "wof:placetype":"venue"
},
  "geometry": {"coordinates":[15.1500577927,47.0493392944],"type":"Point"}
}