{
  "type": "Feature",
  "properties": {
    "addr:full":"Wolfernstr 17 Steyr Ober\u00f6sterreich 4400",
    "addr:housenumber":"17",
    "addr:postcode":"4400",
    "addr:street":"Wolfernstr;Oberoesterreich",
    "iso:country":"AT",
    "sg:address":"Wolfernstr 17",
    "sg:city":"Steyr",
    "sg:classifiers":[
        {
            "category":"Restaurant",
            "type":"Food & Drink"
        }
    ],
    "sg:phone":"+43 7252 72408",
    "sg:postcode":"4400",
    "sg:province":"Ober\u00f6sterreich",
    "wof:name":"Aldo - Restaurant Pizzeria - Kern Walter",
    "wof:placetype":"venue"
},
  "geometry": {"coordinates":[14.4078083038,48.0476875305],"type":"Point"}
}