{
  "type": "Feature",
  "properties": {
    "iso:country":"AT",
    "sg:address":"Forst 193",
    "sg:city":"Mariahof",
    "sg:orig_category":"ChildrenS Furniture",
    "sg:phone":"+43 3584 2067",
    "sg:postcode":"8812",
    "sg:province":"Steiermark",
    "wof:name":"Gerhard Skiber",
    "wof:placetype":"venue"
},
  "geometry": {"coordinates":[-82.6173629761,42.5609474182],"type":"Point"}
}