{
  "type": "Feature",
  "properties": {
    "addr:full":"Nr. 102  Gro\u00dfwilfersdorf Steiermark 8263",
    "addr:postcode":"8263",
    "addr:street":"Nr. 102",
    "iso:country":"AT",
    "sg:address":"Nr. 102 ",
    "sg:city":"Gro\u00dfwilfersdorf",
    "sg:classifiers":[
        {
            "category":"Food & Beverages",
            "subcategory":"Groceries & Convenience Stores",
            "type":"Retail Goods"
        }
    ],
    "sg:phone":"+43 4333 8578010",
    "sg:postcode":"8263",
    "sg:province":"Steiermark",
    "sg:tags":[
        "product",
        "related"
    ],
    "wof:name":"LANDWIRTSCHAFTLICHE EIN-U. VERKAUFSGENOSSENSCHAFT REG.GEN.MBH",
    "wof:placetype":"venue"
},
  "geometry": {"coordinates":[15.9948101044,47.0773239136],"type":"Point"}
}