{
  "type": "Feature",
  "properties": {
    "iso:country":"AT",
    "sg:address":"Fugbachg 12",
    "sg:city":"Wien",
    "sg:orig_category":"Tischlereien",
    "sg:phone":"+43 1 2125417",
    "sg:postcode":"1020",
    "sg:province":"Wien",
    "wof:name":"Pale&#269;ek Karl",
    "wof:placetype":"venue"
},
  "geometry": {"coordinates":[16.3882083893,48.2207794189],"type":"Point"}
}