{
  "type": "Feature",
  "properties": {
    "iso:country":"AT",
    "sg:address":"Herbeckstr 45",
    "sg:city":"Wien",
    "sg:orig_category":"Physiotherapie",
    "sg:phone":"+43 1 4709577",
    "sg:postcode":"1180",
    "sg:province":"Wien",
    "wof:name":"Morawec Gertrude Dipl-PT",
    "wof:placetype":"venue"
},
  "geometry": {"coordinates":[16.3222351074,48.2318534851],"type":"Point"}
}