{
  "type": "Feature",
  "properties": {
    "iso:country":"AT",
    "sg:address":"Hauptstr 6",
    "sg:city":"Frauenkirchen",
    "sg:orig_category":"Damenmoden",
    "sg:phone":"+43 2172 2228",
    "sg:postcode":"7132",
    "sg:province":"Burgenland",
    "wof:name":"Lass Paula KG",
    "wof:placetype":"venue"
},
  "geometry": {"coordinates":[16.9260997772,47.8362083435],"type":"Point"}
}