{
  "type": "Feature",
  "properties": {
    "addr:full":"Griesg 31 Salzburg Salzburg 5020",
    "addr:housenumber":"31",
    "addr:postcode":"5020",
    "addr:street":"Griesg;Salzburg",
    "iso:country":"AT",
    "sg:address":"Griesg 31",
    "sg:city":"Salzburg",
    "sg:classifiers":[
        {
            "category":"Restaurant",
            "type":"Food & Drink"
        }
    ],
    "sg:phone":"+43 662 8434700",
    "sg:postcode":"5020",
    "sg:province":"Salzburg",
    "wof:name":"Wienerwald Restaurants GesmbH",
    "wof:placetype":"venue"
},
  "geometry": {"coordinates":[13.0433769226,47.8006744385],"type":"Point"}
}