{
  "type": "Feature",
  "properties": {
    "addr:full":"Oberradin 52-54 Braz Vorarlberg 6751",
    "addr:housenumber":"52-54",
    "addr:postcode":"6751",
    "addr:street":"Oberradin",
    "iso:country":"AT",
    "sg:address":"Oberradin 52-54",
    "sg:city":"Braz",
    "sg:classifiers":[
        {
            "category":"Government",
            "subcategory":"Post Office",
            "type":"Public Place"
        }
    ],
    "sg:phone":"+43 4355 5266163",
    "sg:postcode":"6751",
    "sg:province":"Vorarlberg",
    "sg:tags":[
        "u",
        "-material",
        "dachdeckereibedarf"
    ],
    "wof:name":"B & H Handels- u ProduktionsgesmbH",
    "wof:placetype":"venue"
},
  "geometry": {"coordinates":[9.9180688858,47.144695282],"type":"Point"}
}