{
  "type": "Feature",
  "properties": {
    "iso:country":"AT",
    "sg:address":"Landstra\u00dfer Hauptstr 28",
    "sg:city":"Wien",
    "sg:classifiers":[
        {
            "category":"Travel",
            "subcategory":"Hotels & Motels",
            "type":"Entertainment"
        }
    ],
    "sg:phone":"+43 1 716710",
    "sg:postcode":"1030",
    "sg:province":"Wien",
    "wof:name":"Mercure Grand Hotel Biedermeier Wien",
    "wof:placetype":"venue"
},
  "geometry": {"coordinates":[16.3889656067,48.2037696838],"type":"Point"}
}