{
  "type": "Feature",
  "properties": {
    "addr:full":"Josef Kohl-G 53 Knittelfeld Steiermark 8720",
    "addr:housenumber":"53",
    "addr:postcode":"8720",
    "iso:country":"AT",
    "sg:address":"Josef Kohl-G 53",
    "sg:city":"Knittelfeld",
    "sg:orig_category":"Hygienepapiere",
    "sg:phone":"+43 664 2410122",
    "sg:postcode":"8720",
    "sg:province":"Steiermark",
    "wof:name":"Schachner Harald - Papier- und Hygienebedarf",
    "wof:placetype":"venue"
},
  "geometry": {"coordinates":[14.8068819046,47.2146682739],"type":"Point"}
}