{
  "type": "Feature",
  "properties": {
    "addr:full":"Plainbergweg 7 Salzburg Salzburg 5020",
    "addr:housenumber":"7",
    "addr:postcode":"5020",
    "addr:street":"Plainbergweg;Salzburg",
    "iso:country":"AT",
    "sg:address":"Plainbergweg 7",
    "sg:city":"Salzburg",
    "sg:orig_category":"Nachhilfe U Lernbetreuung",
    "sg:phone":"+43 4366 2453905",
    "sg:postcode":"5020",
    "sg:province":"Salzburg",
    "sg:website":"abisz-lernstudio.at",
    "wof:name":"A bis Z - Lernstudio",
    "wof:placetype":"venue"
},
  "geometry": {"coordinates":[13.0403060913,47.8098602295],"type":"Point"}
}