{
  "type": "Feature",
  "properties": {
    "addr:full":"Universit\u00e4tsplatz 8 Salzburg Salzburg 5020",
    "addr:housenumber":"8",
    "addr:postcode":"5020",
    "addr:street":"Universitaetsplatz;Salzburg",
    "iso:country":"AT",
    "sg:address":"Universit\u00e4tsplatz 8",
    "sg:city":"Salzburg",
    "sg:orig_category":"Chains, Necklaces",
    "sg:phone":"+43 662 842150",
    "sg:postcode":"5020",
    "sg:province":"Salzburg",
    "sg:website":"uhren-juwelen-kalteis.at",
    "wof:name":"Kalteis Ges.m.b.H. & Co KG",
    "wof:placetype":"venue"
},
  "geometry": {"coordinates":[13.0421600342,47.7996635437],"type":"Point"}
}