{
  "type": "Feature",
  "properties": {
    "addr:full":"Hauptpl 4 Hollabrunn Nieder\u00f6sterreich 2020",
    "addr:housenumber":"4",
    "addr:postcode":"2020",
    "addr:street":"Hauptpl",
    "iso:country":"AT",
    "sg:address":"Hauptpl 4",
    "sg:city":"Hollabrunn",
    "sg:orig_category":"Blumeneinzelhandel",
    "sg:phone":"+43 2952 4030",
    "sg:postcode":"2020",
    "sg:province":"Nieder\u00f6sterreich",
    "wof:name":"Bauer Blumen",
    "wof:placetype":"venue"
},
  "geometry": {"coordinates":[16.0957965851,48.5829963684],"type":"Point"}
}