{
  "type": "Feature",
  "properties": {
    "iso:country":"AT",
    "sg:address":"Rudolf-Zeller-G 71",
    "sg:city":"Wien",
    "sg:classifiers":[
        {
            "category":"Restaurant",
            "type":"Food & Drink"
        }
    ],
    "sg:phone":"+43 1 8881968",
    "sg:postcode":"1230",
    "sg:province":"Wien",
    "sg:tags":[
        "pizzeria"
    ],
    "wof:name":"Bella Vienna Pizza & Pasta",
    "wof:placetype":"venue"
},
  "geometry": {"coordinates":[16.2806129456,48.1412239075],"type":"Point"}
}