{
  "type": "Feature",
  "properties": {
    "addr:full":"Hasnerstr 36 Linz Ober\u00f6sterreich 4020",
    "addr:housenumber":"36",
    "addr:postcode":"4020",
    "addr:street":"Hasnerstr",
    "iso:country":"AT",
    "sg:address":"Hasnerstr 36",
    "sg:city":"Linz",
    "sg:orig_category":"Werbeagenturen",
    "sg:phone":"+43 4373 2245306",
    "sg:postcode":"4020",
    "sg:province":"Ober\u00f6sterreich",
    "wof:name":"TOP-AD Werbeagentur",
    "wof:placetype":"venue"
},
  "geometry": {"coordinates":[14.2946472168,48.2855110168],"type":"Point"}
}