{
  "type": "Feature",
  "properties": {
    "addr:full":"Straucherg 16 Graz Steiermark 8020",
    "addr:housenumber":"16",
    "addr:postcode":"8020",
    "addr:street":"Straucherg",
    "iso:country":"AT",
    "sg:address":"Straucherg 16",
    "sg:city":"Graz",
    "sg:orig_category":"Steuerberatung",
    "sg:phone":"+43 316 7129450",
    "sg:postcode":"8020",
    "sg:province":"Steiermark",
    "wof:name":"Slawitsch Hans-Michael Dr iur",
    "wof:placetype":"venue"
},
  "geometry": {"coordinates":[15.4270372391,47.0720405579],"type":"Point"}
}