{
  "type": "Feature",
  "properties": {
    "addr:full":"Grieshof 147A Strengen Tirol 6571",
    "addr:housenumber":"147a",
    "addr:postcode":"6571",
    "addr:street":"Grieshof",
    "iso:country":"AT",
    "sg:address":"Grieshof 147A",
    "sg:city":"Strengen",
    "sg:orig_category":"Fotografen",
    "sg:phone":"+43 4354 475911",
    "sg:postcode":"6571",
    "sg:province":"Tirol",
    "wof:name":"Mallaun Josef",
    "wof:placetype":"venue"
},
  "geometry": {"coordinates":[10.461810112,47.1273727417],"type":"Point"}
}