{
  "type": "Feature",
  "properties": {
    "addr:full":"Salzburger Str 1 Bischofshofen Salzburg 5500",
    "addr:housenumber":"1",
    "addr:postcode":"5500",
    "addr:street":"Salzburger Str;Salzburg",
    "iso:country":"AT",
    "sg:address":"Salzburger Str 1",
    "sg:city":"Bischofshofen",
    "sg:orig_category":"Tourismusinformation U -Organisationen",
    "sg:phone":"+43 4364 622471",
    "sg:postcode":"5500",
    "sg:province":"Salzburg",
    "wof:name":"Tourismusverband Bischofshofen",
    "wof:placetype":"venue"
},
  "geometry": {"coordinates":[13.2186841965,47.4179267883],"type":"Point"}
}