{
  "type": "Feature",
  "properties": {
    "addr:full":"Nr 95 Gnas Steiermark 8342",
    "addr:postcode":"8342",
    "addr:street":"Nr",
    "iso:country":"AT",
    "sg:address":"Nr 95",
    "sg:city":"Gnas",
    "sg:orig_category":"Mietautos",
    "sg:phone":"+43 3151 8394",
    "sg:postcode":"8342",
    "sg:province":"Steiermark",
    "wof:name":"Schwarz Rudolf",
    "wof:placetype":"venue"
},
  "geometry": {"coordinates":[15.8265724182,46.8743095398],"type":"Point"}
}