{
  "type": "Feature",
  "properties": {
    "addr:full":"Linzer Str 32 Wien Wien 1140",
    "addr:housenumber":"32",
    "addr:postcode":"1140",
    "addr:street":"Linzer Str",
    "iso:country":"AT",
    "sg:address":"Linzer Str 32",
    "sg:city":"Wien",
    "sg:orig_category":"Friseure U Frisiersalons",
    "sg:phone":"+43 1 982815715",
    "sg:postcode":"1140",
    "sg:province":"Wien",
    "wof:name":"Ihr dm Friseur Studio",
    "wof:placetype":"venue"
},
  "geometry": {"coordinates":[16.312702179,48.1932449341],"type":"Point"}
}