{
  "type": "Feature",
  "properties": {
    "iso:country":"AT",
    "sg:address":"Andreas Hofer-Str 2",
    "sg:city":"Kufstein",
    "sg:classifiers":[
        {
            "category":"Professional",
            "subcategory":"Computer Services",
            "type":"Services"
        }
    ],
    "sg:phone":"+43 5372 62044",
    "sg:postcode":"6330",
    "sg:province":"Tirol",
    "sg:tags":[
        "software"
    ],
    "wof:name":"Ciutura-Oberlechner KEG - Knowledge Architects",
    "wof:placetype":"venue"
},
  "geometry": {"coordinates":[12.1734447479,47.5827178955],"type":"Point"}
}