{
  "type": "Feature",
  "properties": {
    "addr:full":"Wilhelminenstrasse 91 Wien Wien 1160",
    "addr:housenumber":"91",
    "addr:postcode":"1160",
    "addr:street":"Wilhelminenstrasse",
    "iso:country":"AT",
    "sg:address":"Wilhelminenstrasse 91",
    "sg:city":"Wien",
    "sg:classifiers":[
        {
            "category":"Home & Garden",
            "subcategory":"Hardware",
            "type":"Retail Goods"
        }
    ],
    "sg:phone":"+43 1 4869097",
    "sg:postcode":"1160",
    "sg:province":"Wien",
    "sg:tags":[
        "component",
        "electronic"
    ],
    "wof:name":"Deltron Austria GmbH",
    "wof:placetype":"venue"
},
  "geometry": {"coordinates":[16.3067741394,48.2177619934],"type":"Point"}
}