{
  "type": "Feature",
  "properties": {
    "addr:full":"Andr\u00e4-Lackner-Weg 2 Hallein Salzburg 5400",
    "addr:housenumber":"2",
    "addr:postcode":"5400",
    "addr:street":"Andrae-Lackner-Weg;Salzburg",
    "iso:country":"AT",
    "sg:address":"Andr\u00e4-Lackner-Weg 2",
    "sg:city":"Hallein",
    "sg:orig_category":"Fleischhauereien",
    "sg:phone":"+43 6245 804960",
    "sg:postcode":"5400",
    "sg:province":"Salzburg",
    "wof:name":"Lindlbauer Leopold",
    "wof:placetype":"venue"
},
  "geometry": {"coordinates":[13.0993995667,47.6837730408],"type":"Point"}
}