{
  "type": "Feature",
  "properties": {
    "iso:country":"AT",
    "sg:address":"Ascherstrasse 10",
    "sg:city":"Puchberg am Schneeberg",
    "sg:classifiers":[
        {
            "category":"Government",
            "subcategory":"Fire Station",
            "type":"Public Place"
        }
    ],
    "sg:phone":"+43 2636 2303",
    "sg:postcode":"2734",
    "sg:province":"Nieder\u00f6sterreich",
    "sg:tags":[
        "alloy",
        "light",
        "aluminium",
        "processing"
    ],
    "wof:name":"Stefan Bock",
    "wof:placetype":"venue"
},
  "geometry": {"coordinates":[15.927816391,47.7974090576],"type":"Point"}
}