{
  "type": "Feature",
  "properties": {
    "addr:full":"Linzer Bundesstr 13 Salzburg Salzburg 5020",
    "addr:housenumber":"13",
    "addr:postcode":"5020",
    "addr:street":"Salzburg",
    "iso:country":"AT",
    "sg:address":"Linzer Bundesstr 13",
    "sg:city":"Salzburg",
    "sg:orig_category":"Psychotherapie",
    "sg:phone":"+43 4366 2834261",
    "sg:postcode":"5020",
    "sg:province":"Salzburg",
    "wof:name":"Schellenbacher Manfred Dr",
    "wof:placetype":"venue"
},
  "geometry": {"coordinates":[13.065331459,47.8108711243],"type":"Point"}
}