{
  "type": "Feature",
  "properties": {
    "addr:full":"Lastenstr 6A Salzburg Salzburg 5020",
    "addr:housenumber":"6a",
    "addr:postcode":"5020",
    "addr:street":"Lastenstr;Salzburg",
    "iso:country":"AT",
    "sg:address":"Lastenstr 6A",
    "sg:city":"Salzburg",
    "sg:orig_category":"Pensionen / Privatzimmer",
    "sg:phone":"+43 662 874351",
    "sg:postcode":"5020",
    "sg:province":"Salzburg",
    "wof:name":"Pension Sandwirt",
    "wof:placetype":"venue"
},
  "geometry": {"coordinates":[13.0470285416,47.8117332458],"type":"Point"}
}