{
  "type": "Feature",
  "properties": {
    "iso:country":"AT",
    "sg:address":"Bahnhofstr 11/2",
    "sg:city":"Zell am See",
    "sg:orig_category":"Architekten",
    "sg:phone":"+43 6542 728770",
    "sg:postcode":"5700",
    "sg:province":"Salzburg",
    "wof:name":"Glaninger Helmut Arch Dipl-Ing",
    "wof:placetype":"venue"
},
  "geometry": {"coordinates":[12.7976989746,47.3218154907],"type":"Point"}
}