{
  "type": "Feature",
  "properties": {
    "iso:country":"AT",
    "sg:address":"Franz-Josef-Pl 1",
    "sg:city":"Gmunden",
    "sg:classifiers":[
        {
            "category":"Shopping",
            "subcategory":"Gifts & Souvenirs",
            "type":"Retail Goods"
        }
    ],
    "sg:phone":"+43 761272172",
    "sg:postcode":"4810",
    "sg:province":"Ober\u00f6sterreich",
    "wof:name":"H\u00f6rak Leopold",
    "wof:placetype":"venue"
},
  "geometry": {"coordinates":[13.7979297638,47.9178886414],"type":"Point"}
}