{
  "type": "Feature",
  "properties": {
    "addr:full":"Nr 100 K\u00f6flach Steiermark 8580",
    "addr:postcode":"8580",
    "addr:street":"Nr 100",
    "iso:country":"AT",
    "sg:address":"Nr 100",
    "sg:city":"K\u00f6flach",
    "sg:orig_category":"Baumeister",
    "sg:phone":"+43 4331 4020913",
    "sg:postcode":"8580",
    "sg:province":"Steiermark",
    "wof:name":"Kastner Bauplanung, Bauleitung GmbH & CoKEG",
    "wof:placetype":"venue"
},
  "geometry": {"coordinates":[15.0835552216,47.0640258789],"type":"Point"}
}