{
  "type": "Feature",
  "properties": {
    "addr:full":"Ginsterweg 7 Gunskirchen Ober\u00f6sterreich 4623",
    "addr:housenumber":"7",
    "addr:postcode":"4623",
    "addr:street":"Ginsterweg",
    "iso:country":"AT",
    "sg:address":"Ginsterweg 7",
    "sg:city":"Gunskirchen",
    "sg:orig_category":"Zahntechnische Laboratorien",
    "sg:phone":"+43 7246 7653",
    "sg:postcode":"4623",
    "sg:province":"Ober\u00f6sterreich",
    "wof:name":"M\u00f6seneder Erich",
    "wof:placetype":"venue"
},
  "geometry": {"coordinates":[13.9410123825,48.1263656616],"type":"Point"}
}