{
  "type": "Feature",
  "properties": {
    "addr:full":"Kierlinger Str 4 Klosterneuburg Nieder\u00f6sterreich 3400",
    "addr:housenumber":"4",
    "addr:postcode":"3400",
    "addr:street":"Str;Niederoesterreich",
    "iso:country":"AT",
    "sg:address":"Kierlinger Str 4",
    "sg:city":"Klosterneuburg",
    "sg:orig_category":"Bausparkassen",
    "sg:phone":"+43 2243 37736",
    "sg:postcode":"3400",
    "sg:province":"Nieder\u00f6sterreich",
    "wof:name":"W\u00fcstenrot Beratungsstelle - Brudny Klaus & Co KEG",
    "wof:placetype":"venue"
},
  "geometry": {"coordinates":[16.3215293884,48.307964325],"type":"Point"}
}