{
  "type": "Feature",
  "properties": {
    "addr:full":"Wei\u00dfgerberg 13 Bad Hofgastein Salzburg 5630",
    "addr:housenumber":"13",
    "addr:postcode":"5630",
    "addr:street":"Weissgerberg;Salzburg",
    "iso:country":"AT",
    "sg:address":"Wei\u00dfgerberg 13",
    "sg:city":"Bad Hofgastein",
    "sg:orig_category":"Massagen",
    "sg:phone":"+43 6432 7191",
    "sg:postcode":"5630",
    "sg:province":"Salzburg",
    "wof:name":"Fachinstitut Gastuna - Heilmassage - R\u00f6ck Thomas",
    "wof:placetype":"venue"
},
  "geometry": {"coordinates":[13.1028347015,47.1707115173],"type":"Point"}
}