{
  "type": "Feature",
  "properties": {
    "addr:full":"Kle\u00dfheimer Allee 29A Salzburg Salzburg 5020",
    "addr:housenumber":"29a",
    "addr:postcode":"5020",
    "addr:street":"Klessheimer Allee;Salzburg",
    "iso:country":"AT",
    "sg:address":"Kle\u00dfheimer Allee 29A",
    "sg:city":"Salzburg",
    "sg:orig_category":"\u00c3\u201enderungsschneidereien",
    "sg:phone":"+43 662 434090",
    "sg:postcode":"5020",
    "sg:province":"Salzburg",
    "wof:name":"Demir Nazim",
    "wof:placetype":"venue"
},
  "geometry": {"coordinates":[13.016494751,47.8079376221],"type":"Point"}
}