{
  "type": "Feature",
  "properties": {
    "addr:full":"Lauterbrunn 2 Andorf Ober\u00f6sterreich 4770",
    "addr:housenumber":"2",
    "addr:postcode":"4770",
    "addr:street":"Lauterbrunn",
    "iso:country":"AT",
    "sg:address":"Lauterbrunn 2",
    "sg:city":"Andorf",
    "sg:orig_category":"Landwirtschaftliche Produkte",
    "sg:phone":"+43 7766 36100",
    "sg:postcode":"4770",
    "sg:province":"Ober\u00f6sterreich",
    "wof:name":"Andorfer AgrarhandelsgmbH",
    "wof:placetype":"venue"
},
  "geometry": {"coordinates":[13.5965967178,48.3779945374],"type":"Point"}
}