{
  "type": "Feature",
  "properties": {
    "addr:full":"Haager Str 54 Steyr Ober\u00f6sterreich 4400",
    "addr:housenumber":"54",
    "addr:postcode":"4400",
    "addr:street":"Haager Str;Oberoesterreich",
    "iso:country":"AT",
    "sg:address":"Haager Str 54",
    "sg:city":"Steyr",
    "sg:orig_category":"Dachdeckereien",
    "sg:phone":"+43 7252 738480",
    "sg:postcode":"4400",
    "sg:province":"Ober\u00f6sterreich",
    "wof:name":"Lipfert Gotthard Dachdeckerei und Spenglerei GesmbH & Co KG",
    "wof:placetype":"venue"
},
  "geometry": {"coordinates":[14.4522800446,48.0596847534],"type":"Point"}
}