{
  "type": "Feature",
  "properties": {
    "iso:country":"AT",
    "sg:address":"Nr 32",
    "sg:city":"Ossiach",
    "sg:orig_category":"Lebensmittel / Einzelhandel",
    "sg:phone":"+43 4243 75115",
    "sg:postcode":"9570",
    "sg:province":"K\u00e4rnten",
    "wof:name":"Spar-Markt Inh Manfred Krappinger Dkfm",
    "wof:placetype":"venue"
},
  "geometry": {"coordinates":[13.9840993881,46.6746025085],"type":"Point"}
}