{
  "type": "Feature",
  "properties": {
    "addr:full":"Au\u00dfen 79 Kirchberg am Wechsel Nieder\u00f6sterreich 2880",
    "addr:housenumber":"79",
    "addr:postcode":"2880",
    "addr:street":"Aussen",
    "iso:country":"AT",
    "sg:address":"Au\u00dfen 79",
    "sg:city":"Kirchberg am Wechsel",
    "sg:classifiers":[
        {
            "category":"Manufacturing",
            "subcategory":"Wood Products",
            "type":"Manufacturing & Wholesale Goods"
        }
    ],
    "sg:phone":"+43 2641 2112",
    "sg:postcode":"2880",
    "sg:province":"Nieder\u00f6sterreich",
    "sg:tags":[
        "lumber"
    ],
    "wof:name":"MARX Ges.m.b.H.",
    "wof:placetype":"venue"
},
  "geometry": {"coordinates":[15.9898548126,47.6096954346],"type":"Point"}
}