{
  "type": "Feature",
  "properties": {
    "addr:full":"Marktpassage 1d Knittelfeld Steiermark 8720",
    "addr:housenumber":"1d",
    "addr:postcode":"8720",
    "addr:street":"Marktpassage",
    "iso:country":"AT",
    "sg:address":"Marktpassage 1d",
    "sg:city":"Knittelfeld",
    "sg:orig_category":"Finanz- U Wirtschaftsberatung",
    "sg:phone":"+43 4335 12751060",
    "sg:postcode":"8720",
    "sg:province":"Steiermark",
    "wof:name":"FINCON Institut f private u gewerbliche Wirtschaftsberatung GesmbH",
    "wof:placetype":"venue"
},
  "geometry": {"coordinates":[14.7964105606,47.2081298828],"type":"Point"}
}