{
  "type": "Feature",
  "properties": {
    "addr:full":"Hauptstrasse 284a Kalsdorf Steiermark 8401",
    "addr:housenumber":"284a",
    "addr:postcode":"8401",
    "addr:street":"Hauptstrasse",
    "iso:country":"AT",
    "sg:address":"Hauptstrasse 284a",
    "sg:city":"Kalsdorf",
    "sg:classifiers":[
        {
            "category":"Professional",
            "type":"Services"
        }
    ],
    "sg:phone":"+43 3135 53227",
    "sg:postcode":"8401",
    "sg:province":"Steiermark",
    "sg:tags":[
        "leasing"
    ],
    "sg:website":"mls.at",
    "wof:name":"MLS Personalleasing",
    "wof:placetype":"venue"
},
  "geometry": {"coordinates":[15.4841098785,46.946975708],"type":"Point"}
}