{
  "type": "Feature",
  "properties": {
    "addr:full":"Nr 220 Eibiswald Steiermark 8552",
    "addr:postcode":"8552",
    "addr:street":"Nr",
    "iso:country":"AT",
    "sg:address":"Nr 220",
    "sg:city":"Eibiswald",
    "sg:orig_category":"Zeitungen U Zeitschriften",
    "sg:phone":"+43 3466 4702621",
    "sg:postcode":"8552",
    "sg:province":"Steiermark",
    "wof:name":"Galaxis Internetmagazin",
    "wof:placetype":"venue"
},
  "geometry": {"coordinates":[15.2274599075,46.6824150085],"type":"Point"}
}