{
  "type": "Feature",
  "properties": {
    "addr:full":"Pichlwanger Str 13 Timelkam Ober\u00f6sterreich 4850",
    "addr:postcode":"4850",
    "addr:street":"Str 13",
    "iso:country":"AT",
    "sg:address":"Pichlwanger Str 13",
    "sg:city":"Timelkam",
    "sg:orig_category":"Banken U Sparkassen",
    "sg:phone":"+43 4350 10040064",
    "sg:postcode":"4850",
    "sg:province":"Ober\u00f6sterreich",
    "wof:name":"Allgemeine Sparkasse Ober\u00f6sterreich Bank AG",
    "wof:placetype":"venue"
},
  "geometry": {"coordinates":[13.6120243073,48.0010261536],"type":"Point"}
}