{
  "type": "Feature",
  "properties": {
    "addr:full":"Wiener Str 63 Krems an der Donau Nieder\u00f6sterreich 3500",
    "addr:postcode":"3500",
    "addr:street":"63",
    "iso:country":"AT",
    "sg:address":"Wiener Str 63",
    "sg:city":"Krems an der Donau",
    "sg:orig_category":"Tankstellen",
    "sg:phone":"+43 2732 84967",
    "sg:postcode":"3500",
    "sg:province":"Nieder\u00f6sterreich",
    "wof:name":"Agip Austria GmbH",
    "wof:placetype":"venue"
},
  "geometry": {"coordinates":[15.6146831512,48.4146957397],"type":"Point"}
}