{
  "type": "Feature",
  "properties": {
    "iso:country":"AT",
    "sg:address":"Fluchtg 7/16",
    "sg:city":"Wien",
    "sg:orig_category":"Steuerberatung",
    "sg:phone":"+43 1 9257960",
    "sg:postcode":"1090",
    "sg:province":"Wien",
    "wof:name":"Kubitza Bernd Mag",
    "wof:placetype":"venue"
},
  "geometry": {"coordinates":[16.353012085,48.2241973877],"type":"Point"}
}