{
  "type": "Feature",
  "properties": {
    "iso:country":"AT",
    "sg:address":"Hauptstr 14",
    "sg:city":"St. Lambrecht",
    "sg:orig_category":"Friseure U Frisiersalons",
    "sg:phone":"+43 4335 852848",
    "sg:postcode":"8813",
    "sg:province":"Steiermark",
    "wof:name":"Gie\u00dfl Rudolf",
    "wof:placetype":"venue"
},
  "geometry": {"coordinates":[14.2990636826,47.0691986084],"type":"Point"}
}