{
  "type": "Feature",
  "properties": {
    "addr:full":"Mitterweg 1 Grafenw\u00f6rth Nieder\u00f6sterreich 3484",
    "addr:housenumber":"1",
    "addr:postcode":"3484",
    "addr:street":"Mitterweg;Niederoesterreich",
    "iso:country":"AT",
    "sg:address":"Mitterweg 1",
    "sg:city":"Grafenw\u00f6rth",
    "sg:orig_category":"Stra\u00c3\u0178enbau",
    "sg:phone":"+43 2738 77060",
    "sg:postcode":"3484",
    "sg:province":"Nieder\u00f6sterreich",
    "wof:name":"Leit Schutz Handels- und Montage GmbH",
    "wof:placetype":"venue"
},
  "geometry": {"coordinates":[15.7557210922,48.40782547],"type":"Point"}
}