{
  "type": "Feature",
  "properties": {
    "addr:full":"K\u00e4ferheimer Str 53 Wals Salzburg 5071",
    "addr:postcode":"5071",
    "addr:street":"Str 53;Salzburg",
    "iso:country":"AT",
    "sg:address":"K\u00e4ferheimer Str 53",
    "sg:city":"Wals",
    "sg:orig_category":"Autohandel",
    "sg:phone":"+43 662 850097",
    "sg:postcode":"5071",
    "sg:province":"Salzburg",
    "wof:name":"Kalcher Andreas KFZ Meisterbetrieb",
    "wof:placetype":"venue"
},
  "geometry": {"coordinates":[12.9579238892,47.7853736877],"type":"Point"}
}