{
  "type": "Feature",
  "properties": {
    "addr:full":"Glaser Str 11 Aigen Salzburg 5026",
    "addr:postcode":"5026",
    "addr:street":"Str 11;Salzburg",
    "iso:country":"AT",
    "sg:address":"Glaser Str 11",
    "sg:city":"Aigen",
    "sg:orig_category":"Chemisch-Technische Produkte",
    "sg:phone":"+43 662 6333930",
    "sg:postcode":"5026",
    "sg:province":"Salzburg",
    "wof:name":"PROTEC Trading GmbH",
    "wof:placetype":"venue"
},
  "geometry": {"coordinates":[13.0846147537,47.7786064148],"type":"Point"}
}