{
  "type": "Feature",
  "properties": {
    "addr:full":"Zauneggerstr 8 Grieskirchen Ober\u00f6sterreich 4710",
    "addr:housenumber":"8",
    "addr:postcode":"4710",
    "addr:street":"Zauneggerstr",
    "iso:country":"AT",
    "sg:address":"Zauneggerstr 8",
    "sg:city":"Grieskirchen",
    "sg:orig_category":"Steuerberatung",
    "sg:phone":"+43 4372 4864748",
    "sg:postcode":"4710",
    "sg:province":"Ober\u00f6sterreich",
    "wof:name":"Fuchshuber Johann Dkfm",
    "wof:placetype":"venue"
},
  "geometry": {"coordinates":[13.8338003159,48.2335624695],"type":"Point"}
}