{
  "type": "Feature",
  "properties": {
    "iso:country":"AT",
    "sg:address":"Dorfstrasse 105",
    "sg:city":"Ludesch",
    "sg:classifiers":[
        {
            "category":"Home & Garden",
            "subcategory":"Household Appliances",
            "type":"Retail Goods"
        }
    ],
    "sg:phone":"+43 5550 3140",
    "sg:postcode":"6713",
    "sg:province":"Vorarlberg",
    "sg:tags":[
        "electric"
    ],
    "wof:name":"Erwin M\u00fcller",
    "wof:placetype":"venue"
},
  "geometry": {"coordinates":[9.787979126,47.1919593811],"type":"Point"}
}