{
  "type": "Feature",
  "properties": {
    "iso:country":"AT",
    "sg:address":"Re\u00dfnigweg 4",
    "sg:city":"Ferlach",
    "sg:orig_category":"Handarbeiten",
    "sg:phone":"+43 4227 3733",
    "sg:postcode":"9170",
    "sg:province":"K\u00e4rnten",
    "wof:name":"Socher Anna",
    "wof:placetype":"venue"
},
  "geometry": {"coordinates":[14.297164917,46.5278625488],"type":"Point"}
}