{
  "type": "Feature",
  "properties": {
    "addr:full":"Neustiftg 83 Wien Wien 1070",
    "addr:housenumber":"83",
    "addr:postcode":"1070",
    "addr:street":"Neustiftg",
    "iso:country":"AT",
    "sg:address":"Neustiftg 83",
    "sg:city":"Wien",
    "sg:orig_category":"Studentenheime",
    "sg:phone":"+43 1 5248877",
    "sg:postcode":"1070",
    "sg:province":"Wien",
    "wof:name":"Studentenhaus des Wr. Jugendherbergwerkes",
    "wof:placetype":"venue"
},
  "geometry": {"coordinates":[16.3468780518,48.2054901123],"type":"Point"}
}