{
  "type": "Feature",
  "properties": {
    "addr:full":"Bahnhofstrasse 203 Furth Nieder\u00f6sterreich 3511",
    "addr:housenumber":"203",
    "addr:postcode":"3511",
    "addr:street":"Bahnhofstrasse",
    "iso:country":"AT",
    "sg:address":"Bahnhofstrasse 203",
    "sg:city":"Furth",
    "sg:classifiers":[
        {
            "category":"Home & Garden",
            "subcategory":"Carpets & Floor Coverings",
            "type":"Retail Goods"
        }
    ],
    "sg:phone":"+43 2732 720620",
    "sg:postcode":"3511",
    "sg:province":"Nieder\u00f6sterreich",
    "sg:tags":[
        "screed",
        "renovation"
    ],
    "sg:website":"spanny.at",
    "wof:name":"Hubert Spanny Ges.m.b.H. & Co KG",
    "wof:placetype":"venue"
},
  "geometry": {"coordinates":[15.6125049591,48.374168396],"type":"Point"}
}