{
  "type": "Feature",
  "properties": {
    "iso:country":"AT",
    "sg:address":"Hirschgraben 37",
    "sg:city":"Feldkirch",
    "sg:classifiers":[
        {
            "category":"Banks & Credit Unions",
            "subcategory":"Bureau De Change",
            "type":"Services"
        }
    ],
    "sg:phone":"+43 5522 74727",
    "sg:postcode":"6800",
    "sg:province":"Vorarlberg",
    "sg:website":"informa.at",
    "wof:name":"Informa Auskunftei und Inkasso GesmbH",
    "wof:placetype":"venue"
},
  "geometry": {"coordinates":[9.5939722061,47.2375526428],"type":"Point"}
}