{
  "type": "Feature",
  "properties": {
    "addr:full":"Grieselstein Dorf 7 Jennersdorf Burgenland 8380",
    "addr:housenumber":"7",
    "addr:postcode":"8380",
    "addr:street":"Dorf",
    "iso:country":"AT",
    "sg:address":"Grieselstein Dorf 7",
    "sg:city":"Jennersdorf",
    "sg:orig_category":"Elektroinstallationsunternehmen",
    "sg:phone":"+43 3329 45561",
    "sg:postcode":"8380",
    "sg:province":"Burgenland",
    "wof:name":"Werner Heribert Ing",
    "wof:placetype":"venue"
},
  "geometry": {"coordinates":[16.1308784485,46.9410400391],"type":"Point"}
}