{
  "type": "Feature",
  "properties": {
    "iso:country":"AT",
    "sg:address":"Sonnenweg 3",
    "sg:city":"Axams",
    "sg:orig_category":"Appartements / Ferienwohnungen",
    "sg:phone":"+43 5234 68972",
    "sg:postcode":"6094",
    "sg:province":"Tirol",
    "wof:name":"Appartement Sailer",
    "wof:placetype":"venue"
},
  "geometry": {"coordinates":[11.2815799713,47.233707428],"type":"Point"}
}