{
  "type": "Feature",
  "properties": {
    "iso:country":"AT",
    "sg:address":"Laaber Str 41",
    "sg:city":"Breitenfurt",
    "sg:orig_category":"Garten- U Landschaftsgestaltung",
    "sg:phone":"+43 4322 392488",
    "sg:postcode":"2384",
    "sg:province":"Nieder\u00f6sterreich",
    "wof:name":"Heger Manfred",
    "wof:placetype":"venue"
},
  "geometry": {"coordinates":[16.1947994232,48.1440811157],"type":"Point"}
}