{
  "type": "Feature",
  "properties": {
    "addr:full":"An der Fernstr 2 Andorf Ober\u00f6sterreich 4770",
    "addr:housenumber":"2",
    "addr:postcode":"4770",
    "addr:street":"An Der Fernstr",
    "iso:country":"AT",
    "sg:address":"An der Fernstr 2",
    "sg:city":"Andorf",
    "sg:classifiers":[
        {
            "category":"Home & Garden",
            "subcategory":"Building Materials",
            "type":"Retail Goods"
        }
    ],
    "sg:phone":"+43 4377 66412410",
    "sg:postcode":"4770",
    "sg:province":"Ober\u00f6sterreich",
    "sg:tags":[
        "baustoffe",
        "-material",
        "u"
    ],
    "wof:name":"Rothner Josef",
    "wof:placetype":"venue"
},
  "geometry": {"coordinates":[13.5776348114,48.371761322],"type":"Point"}
}