{
  "type": "Feature",
  "properties": {
    "iso:country":"AT",
    "sg:address":"Deutsch Goritz 77",
    "sg:city":"Deutsch Goritz",
    "sg:classifiers":[
        {
            "category":"Utilities",
            "subcategory":"Water",
            "type":"Services"
        }
    ],
    "sg:phone":"+43 3474 8333",
    "sg:postcode":"8483",
    "sg:province":"Steiermark",
    "sg:tags":[
        "waters",
        "natural",
        "mineral"
    ],
    "sg:website":"peterquelle.at",
    "wof:name":"Peterquelle Mineralwasser Ges.m.b.H. & Co. KG",
    "wof:placetype":"venue"
},
  "geometry": {"coordinates":[15.8311033249,46.7535629272],"type":"Point"}
}