{
  "type": "Feature",
  "properties": {
    "addr:full":"Hauptstr 12 Frankenburg am Hausruck Ober\u00f6sterreich 4873",
    "addr:housenumber":"12",
    "addr:postcode":"4873",
    "addr:street":"Hauptstr",
    "iso:country":"AT",
    "sg:address":"Hauptstr 12",
    "sg:city":"Frankenburg am Hausruck",
    "sg:orig_category":"Banken U Sparkassen",
    "sg:phone":"+43 4376 8387270",
    "sg:postcode":"4873",
    "sg:province":"Ober\u00f6sterreich",
    "wof:name":"Bankomat d Hagebank-Volksbank V\u00f6cklabruck-Traunsee regGenmbH",
    "wof:placetype":"venue"
},
  "geometry": {"coordinates":[13.4897575378,48.067855835],"type":"Point"}
}