{
  "type": "Feature",
  "properties": {
    "iso:country":"AT",
    "sg:address":"Franzosenweg 12",
    "sg:city":"Wien",
    "sg:orig_category":"Werbeagenturen",
    "sg:phone":"+43 1 68929590",
    "sg:postcode":"1100",
    "sg:province":"Wien",
    "wof:name":"Brain Power Competence - Heinreichsberger + Rada OEG",
    "wof:placetype":"venue"
},
  "geometry": {"coordinates":[16.384103775,48.1398162842],"type":"Point"}
}