{
  "type": "Feature",
  "properties": {
    "addr:full":"Herzograd 8 St. Valentin Nieder\u00f6sterreich 4300",
    "addr:housenumber":"8",
    "addr:postcode":"4300",
    "addr:street":"Herzograd",
    "iso:country":"AT",
    "sg:address":"Herzograd 8",
    "sg:city":"St. Valentin",
    "sg:orig_category":"Handelsagenturen",
    "sg:phone":"+43 7435 54065",
    "sg:postcode":"4300",
    "sg:province":"Nieder\u00f6sterreich",
    "wof:name":"Weingartner Walter",
    "wof:placetype":"venue"
},
  "geometry": {"coordinates":[14.5111665726,48.1610908508],"type":"Point"}
}