{
  "type": "Feature",
  "properties": {
    "addr:full":"Haseng 18 Wien Wien 1100",
    "addr:housenumber":"18",
    "addr:postcode":"1100",
    "addr:street":"Haseng",
    "iso:country":"AT",
    "sg:address":"Haseng 18",
    "sg:city":"Wien",
    "sg:orig_category":"Autobusunternehmen",
    "sg:phone":"+43 1 6049191",
    "sg:postcode":"1100",
    "sg:province":"Wien",
    "wof:name":"Mazur Walter",
    "wof:placetype":"venue"
},
  "geometry": {"coordinates":[16.3707141876,48.1796417236],"type":"Point"}
}