{
  "type": "Feature",
  "properties": {
    "addr:full":"Koppler Str 59 Koppl Salzburg 5321",
    "addr:postcode":"5321",
    "addr:street":"Str 59;Salzburg",
    "iso:country":"AT",
    "sg:address":"Koppler Str 59",
    "sg:city":"Koppl",
    "sg:orig_category":"Steuerberatung",
    "sg:phone":"+43 6221 20242",
    "sg:postcode":"5321",
    "sg:province":"Salzburg",
    "wof:name":"Karl Rupert Mag",
    "wof:placetype":"venue"
},
  "geometry": {"coordinates":[13.1554145813,47.8100128174],"type":"Point"}
}