{
  "type": "Feature",
  "properties": {
    "addr:full":"Lainsitzweg 4 Gm\u00fcnd Nieder\u00f6sterreich 3950",
    "addr:housenumber":"4",
    "addr:postcode":"3950",
    "addr:street":"Lainsitzweg;Niederoesterreich",
    "iso:country":"AT",
    "sg:address":"Lainsitzweg 4",
    "sg:city":"Gm\u00fcnd",
    "sg:orig_category":"Autoreparatur",
    "sg:phone":"+43 2852 52427",
    "sg:postcode":"3950",
    "sg:province":"Nieder\u00f6sterreich",
    "wof:name":"Eder Willibald",
    "wof:placetype":"venue"
},
  "geometry": {"coordinates":[14.9699907303,48.7632980347],"type":"Point"}
}