{
  "type": "Feature",
  "properties": {
    "iso:country":"AT",
    "sg:address":"Hardtmuthgasse 97",
    "sg:city":"Wien",
    "sg:classifiers":[
        {
            "category":"Arts & Performance",
            "subcategory":"Music",
            "type":"Entertainment"
        }
    ],
    "sg:phone":"+43 1 601790",
    "sg:postcode":"1100",
    "sg:province":"Wien",
    "sg:tags":[
        "brass",
        "rod",
        "section"
    ],
    "sg:website":"kuegele.com",
    "wof:name":"M.A. K\u00fcgele Ges.m.b.H.",
    "wof:placetype":"venue"
},
  "geometry": {"coordinates":[16.3612117767,48.1715164185],"type":"Point"}
}