{
  "type": "Feature",
  "properties": {
    "addr:full":"Hauergraben 1 Scharnstein Ober\u00f6sterreich 4644",
    "addr:housenumber":"1",
    "addr:postcode":"4644",
    "addr:street":"Hauergraben",
    "iso:country":"AT",
    "sg:address":"Hauergraben 1",
    "sg:city":"Scharnstein",
    "sg:orig_category":"Appartements / Ferienwohnungen",
    "sg:phone":"+43 76168541",
    "sg:postcode":"4644",
    "sg:province":"Ober\u00f6sterreich",
    "wof:name":"Roithof Theresia und Erich Sieberer",
    "wof:placetype":"venue"
},
  "geometry": {"coordinates":[13.9281139374,47.8708992004],"type":"Point"}
}