{
  "type": "Feature",
  "properties": {
    "addr:full":"Sonnseite 27 Wagrain Salzburg 5602",
    "addr:housenumber":"27",
    "addr:postcode":"5602",
    "addr:street":"Sonnseite;Salzburg",
    "iso:country":"AT",
    "sg:address":"Sonnseite 27",
    "sg:city":"Wagrain",
    "sg:orig_category":"Pensionen / Privatzimmer",
    "sg:phone":"+43 4364 138751",
    "sg:postcode":"5602",
    "sg:province":"Salzburg",
    "wof:name":"Wallner Rupert - Obered",
    "wof:placetype":"venue"
},
  "geometry": {"coordinates":[13.2851362228,47.3435516357],"type":"Point"}
}