{
  "type": "Feature",
  "properties": {
    "addr:full":"Hauptallee 124 Wien Wien 1020",
    "addr:housenumber":"124",
    "addr:postcode":"1020",
    "addr:street":"Hauptallee",
    "iso:country":"AT",
    "sg:address":"Hauptallee 124",
    "sg:city":"Wien",
    "sg:classifiers":[
        {
            "category":"Sports & Exercise",
            "subcategory":"Sports Center",
            "type":"Entertainment"
        }
    ],
    "sg:phone":"+43 1 72807090",
    "sg:postcode":"1020",
    "sg:province":"Wien",
    "sg:tags":[
        "billiards",
        "accessory"
    ],
    "wof:name":"Brunswick Ges.m.b.H.",
    "wof:placetype":"venue"
},
  "geometry": {"coordinates":[16.4042510986,48.2109603882],"type":"Point"}
}