{
  "type": "Feature",
  "properties": {
    "addr:full":"Bahnhofstr 11 Ried im Innkreis Ober\u00f6sterreich 4910",
    "addr:housenumber":"11",
    "addr:postcode":"4910",
    "addr:street":"Bahnhofstr",
    "iso:country":"AT",
    "sg:address":"Bahnhofstr 11",
    "sg:city":"Ried im Innkreis",
    "sg:orig_category":"Architekten",
    "sg:phone":"+43 7752 84555",
    "sg:postcode":"4910",
    "sg:province":"Ober\u00f6sterreich",
    "sg:website":"www.groesswang.co.at",
    "wof:name":"Gr\u00f6sswang Josef Arch Dipl-Ing",
    "wof:placetype":"venue"
},
  "geometry": {"coordinates":[13.4879302979,48.2073173523],"type":"Point"}
}