{
  "type": "Feature",
  "properties": {
    "addr:full":"M\u00fchlg 126-128 Gleisdorf Steiermark 8200",
    "addr:postcode":"126-128;8200",
    "iso:country":"AT",
    "sg:address":"M\u00fchlg 126-128",
    "sg:city":"Gleisdorf",
    "sg:orig_category":"Brillen U -Fassungen / Erzeugung U Gro\u00c3\u0178handel",
    "sg:phone":"+43 4331 1246190",
    "sg:postcode":"8200",
    "sg:province":"Steiermark",
    "wof:name":"SOLSTAR Produktions GmbH",
    "wof:placetype":"venue"
},
  "geometry": {"coordinates":[15.6912050247,47.103477478],"type":"Point"}
}