{
  "type": "Feature",
  "properties": {
    "addr:full":"Bahnhofstr 49 W\u00f6rgl Tirol 6300",
    "addr:housenumber":"49",
    "addr:postcode":"6300",
    "addr:street":"Bahnhofstr;Tirol",
    "iso:country":"AT",
    "sg:address":"Bahnhofstr 49",
    "sg:city":"W\u00f6rgl",
    "sg:orig_category":"Beratungsstellen",
    "sg:phone":"+43 4353 327051110",
    "sg:postcode":"6300",
    "sg:province":"Tirol",
    "wof:name":"BIN - Suchtberatung Alkohol, Medikamentenabh\u00e4ngigkeit, Spielsucht",
    "wof:placetype":"venue"
},
  "geometry": {"coordinates":[-69.3131027222,-51.6091995239],"type":"Point"}
}