{
  "type": "Feature",
  "properties": {
    "addr:full":"Nr 64 Markt Neuhodis Burgenland 7464",
    "addr:postcode":"7464",
    "addr:street":"Nr;Markt",
    "iso:country":"AT",
    "sg:address":"Nr 64",
    "sg:city":"Markt Neuhodis",
    "sg:orig_category":"Tapezierer U Dekorateure",
    "sg:phone":"+43 4333 6377539",
    "sg:postcode":"7464",
    "sg:province":"Burgenland",
    "wof:name":"Gr\u00fcnwald Manfred",
    "wof:placetype":"venue"
},
  "geometry": {"coordinates":[16.3952350616,47.2961273193],"type":"Point"}
}