{
  "type": "Feature",
  "properties": {
    "iso:country":"AT",
    "sg:address":"Semperstr 29",
    "sg:city":"Wien",
    "sg:orig_category":"Museen / Ausstellungen",
    "sg:phone":"+43 1 4796083",
    "sg:postcode":"1180",
    "sg:province":"Wien",
    "wof:name":"\u00f6sterreichisches Sprachinselmuseum",
    "wof:placetype":"venue"
},
  "geometry": {"coordinates":[16.3482227325,48.2268638611],"type":"Point"}
}