{
  "type": "Feature",
  "properties": {
    "addr:full":"Koschatstr 10 Br\u00fcckl K\u00e4rnten 9371",
    "addr:housenumber":"10",
    "addr:postcode":"9371",
    "addr:street":"Koschatstr;Kaernten",
    "iso:country":"AT",
    "sg:address":"Koschatstr 10",
    "sg:city":"Br\u00fcckl",
    "sg:orig_category":"Polizei U Gendarmerie",
    "sg:phone":"+43 4359 1332121",
    "sg:postcode":"9371",
    "sg:province":"K\u00e4rnten",
    "wof:name":"Gendarmerie",
    "wof:placetype":"venue"
},
  "geometry": {"coordinates":[14.5308294296,46.7510757446],"type":"Point"}
}