{
  "type": "Feature",
  "properties": {
    "addr:full":"Klosterg 1 Innsbruck Tirol 6020",
    "addr:housenumber":"1",
    "addr:postcode":"6020",
    "addr:street":"Klosterg;Tirol",
    "iso:country":"AT",
    "sg:address":"Klosterg 1",
    "sg:city":"Innsbruck",
    "sg:orig_category":"Musikgruppen",
    "sg:phone":"+43 512 581918",
    "sg:postcode":"6020",
    "sg:province":"Tirol",
    "wof:name":"Wiltener S\u00e4ngerknaben",
    "wof:placetype":"venue"
},
  "geometry": {"coordinates":[11.3996248245,47.2537460327],"type":"Point"}
}