{
  "type": "Feature",
  "properties": {
    "addr:full":"Rotensterng 8 Wien Wien 1020",
    "addr:housenumber":"8",
    "addr:postcode":"1020",
    "addr:street":"Rotensterng",
    "iso:country":"AT",
    "sg:address":"Rotensterng 8",
    "sg:city":"Wien",
    "sg:orig_category":"Bars-Cafes",
    "sg:phone":"+43 664 4602441",
    "sg:postcode":"1020",
    "sg:province":"Wien",
    "wof:name":"Shabu Kafe",
    "wof:placetype":"venue"
},
  "geometry": {"coordinates":[16.3819694519,48.2176475525],"type":"Point"}
}