{
  "type": "Feature",
  "properties": {
    "addr:full":"Burgfrieden 7 Hall in Tirol Tirol 6060",
    "addr:housenumber":"7",
    "addr:postcode":"6060",
    "addr:street":"Burgfrieden;Tirol",
    "iso:country":"AT",
    "sg:address":"Burgfrieden 7",
    "sg:city":"Hall in Tirol",
    "sg:classifiers":[
        {
            "category":"Home & Garden",
            "subcategory":"Building Materials",
            "type":"Retail Goods"
        }
    ],
    "sg:phone":"+43 4352 2352422",
    "sg:postcode":"6060",
    "sg:province":"Tirol",
    "sg:tags":[
        "baustoffe",
        "-material",
        "u"
    ],
    "wof:name":"Gstraunthaler & Rossi Bauberatung u Bauwarengro\u00dfhandel GesmbH",
    "wof:placetype":"venue"
},
  "geometry": {"coordinates":[11.4858236313,47.2778511047],"type":"Point"}
}