{
  "type": "Feature",
  "properties": {
    "addr:full":"Reithofferplatz 11 Wien Wien 1150",
    "addr:housenumber":"11",
    "addr:postcode":"1150",
    "addr:street":"Reithofferplatz",
    "iso:country":"AT",
    "sg:address":"Reithofferplatz 11",
    "sg:city":"Wien",
    "sg:classifiers":[
        {
            "category":"Home & Garden",
            "subcategory":"Building Materials",
            "type":"Retail Goods"
        }
    ],
    "sg:phone":"+43 664 1609652",
    "sg:postcode":"1150",
    "sg:province":"Wien",
    "sg:tags":[
        "installation",
        "electric"
    ],
    "wof:name":"Karl Kramar",
    "wof:placetype":"venue"
},
  "geometry": {"coordinates":[16.330286026,48.1983146667],"type":"Point"}
}