{
  "type": "Feature",
  "properties": {
    "addr:full":"Treffenberg 3 Schwanberg Steiermark 8541",
    "addr:housenumber":"3",
    "addr:postcode":"8541",
    "addr:street":"Treffenberg",
    "iso:country":"AT",
    "sg:address":"Treffenberg 3",
    "sg:city":"Schwanberg",
    "sg:classifiers":[
        {
            "category":"Home & Garden",
            "subcategory":"Furniture",
            "type":"Retail Goods"
        }
    ],
    "sg:phone":"+43 3467 8400",
    "sg:postcode":"8541",
    "sg:province":"Steiermark",
    "sg:tags":[
        "bathroom"
    ],
    "wof:name":"Johann Gegg",
    "wof:placetype":"venue"
},
  "geometry": {"coordinates":[15.2004699707,46.7570381165],"type":"Point"}
}