{
  "type": "Feature",
  "properties": {
    "addr:full":"St. Georgen 24 Obernberg am Inn Ober\u00f6sterreich 4982",
    "addr:housenumber":"24",
    "addr:postcode":"4982",
    "addr:street":"St. Georgen",
    "iso:country":"AT",
    "sg:address":"St. Georgen 24",
    "sg:city":"Obernberg am Inn",
    "sg:classifiers":[
        {
            "category":"Manufacturing",
            "subcategory":"Furniture",
            "type":"Manufacturing & Wholesale Goods"
        }
    ],
    "sg:phone":"+43 7758 2561",
    "sg:postcode":"4982",
    "sg:province":"Ober\u00f6sterreich",
    "sg:tags":[
        "bedroom"
    ],
    "sg:website":"niklas.at",
    "wof:name":"Niklas M\u00f6belwerk GesmbH",
    "wof:placetype":"venue"
},
  "geometry": {"coordinates":[13.3341207504,48.2915306091],"type":"Point"}
}