{
  "type": "Feature",
  "properties": {
    "iso:country":"AT",
    "sg:address":"Prechtlerstrasse 23",
    "sg:city":"Grieskirchen",
    "sg:classifiers":[
        {
            "category":"Home & Garden",
            "subcategory":"Home Furnishings",
            "type":"Retail Goods"
        }
    ],
    "sg:phone":"+43 7248 63713",
    "sg:postcode":"4710",
    "sg:province":"Ober\u00f6sterreich",
    "sg:tags":[
        "interior",
        "decoration"
    ],
    "wof:name":"Josef Zehetleitner",
    "wof:placetype":"venue"
},
  "geometry": {"coordinates":[13.83340168,48.2339744568],"type":"Point"}
}