{
  "type": "Feature",
  "properties": {
    "iso:country":"AT",
    "sg:address":"Hormayrg 9",
    "sg:city":"Wien",
    "sg:orig_category":"Bauunternehmen",
    "sg:phone":"+43 1 9232067",
    "sg:postcode":"1170",
    "sg:province":"Wien",
    "wof:name":"CALAS Bau GmbH",
    "wof:placetype":"venue"
},
  "geometry": {"coordinates":[16.3307209015,48.2196884155],"type":"Point"}
}