{
  "type": "Feature",
  "properties": {
    "addr:full":"Burgauer Str 21 F\u00fcrstenfeld Steiermark 8280",
    "addr:postcode":"8280",
    "addr:street":"21",
    "iso:country":"AT",
    "sg:address":"Burgauer Str 21",
    "sg:city":"F\u00fcrstenfeld",
    "sg:orig_category":"Bauunternehmen",
    "sg:phone":"+43 4333 82524680",
    "sg:postcode":"8280",
    "sg:province":"Steiermark",
    "sg:website":"domweber.at",
    "wof:name":"Domweber BaugesmbH",
    "wof:placetype":"venue"
},
  "geometry": {"coordinates":[16.076051712,47.0616722107],"type":"Point"}
}