{
  "type": "Feature",
  "properties": {
    "iso:country":"AT",
    "sg:address":"Hafnerstrasse 1",
    "sg:city":"Wallern an der Trattnach",
    "sg:classifiers":[
        {
            "category":"Home & Garden",
            "subcategory":"Carpets & Floor Coverings",
            "type":"Retail Goods"
        }
    ],
    "sg:phone":"+43 7249 49110",
    "sg:postcode":"4702",
    "sg:province":"Ober\u00f6sterreich",
    "sg:tags":[
        "grout",
        "adhesive",
        "tiles"
    ],
    "sg:website":"fliesen-renner.at",
    "wof:name":"Renner GmbH",
    "wof:placetype":"venue"
},
  "geometry": {"coordinates":[13.9601354599,48.2388572693],"type":"Point"}
}