{
  "type": "Feature",
  "properties": {
    "addr:full":"Leopoldauer Pl 13 Wien Wien 1210",
    "addr:housenumber":"13",
    "addr:postcode":"1210",
    "addr:street":"Leopoldauer Pl",
    "iso:country":"AT",
    "sg:address":"Leopoldauer Pl 13",
    "sg:city":"Wien",
    "sg:orig_category":"Tabaktrafiken",
    "sg:phone":"+43 4312 584141",
    "sg:postcode":"1210",
    "sg:province":"Wien",
    "wof:name":"Hojsa Marion",
    "wof:placetype":"venue"
},
  "geometry": {"coordinates":[16.4389667511,48.26329422],"type":"Point"}
}