{
  "type": "Feature",
  "properties": {
    "addr:full":"Kirchenpl 1 Maissau Nieder\u00f6sterreich 3712",
    "addr:housenumber":"1",
    "addr:postcode":"3712",
    "addr:street":"Kirchenpl",
    "iso:country":"AT",
    "sg:address":"Kirchenpl 1",
    "sg:city":"Maissau",
    "sg:orig_category":"Forstverwaltungen",
    "sg:phone":"+43 4329 5882273",
    "sg:postcode":"3712",
    "sg:province":"Nieder\u00f6sterreich",
    "wof:name":"Traun'sche Forst- u Gutsverwaltung",
    "wof:placetype":"venue"
},
  "geometry": {"coordinates":[15.8253116608,48.5713768005],"type":"Point"}
}