{
  "type": "Feature",
  "properties": {
    "iso:country":"AT",
    "sg:address":"Neuberg 91",
    "sg:city":"Filzmoos",
    "sg:orig_category":"Pensionen / Privatzimmer",
    "sg:phone":"+43 4364 538519",
    "sg:postcode":"5532",
    "sg:province":"Salzburg",
    "wof:name":"Berghoamat Rettenwender Michael",
    "wof:placetype":"venue"
},
  "geometry": {"coordinates":[13.5203046799,47.4333534241],"type":"Point"}
}