{
  "type": "Feature",
  "properties": {
    "addr:full":"Hauptstr 43 Wolkersdorf im Weinviertel Nieder\u00f6sterreich 2120",
    "addr:housenumber":"43",
    "addr:postcode":"2120",
    "addr:street":"Hauptstr",
    "iso:country":"AT",
    "sg:address":"Hauptstr 43",
    "sg:city":"Wolkersdorf im Weinviertel",
    "sg:orig_category":"\u00c3\u201erzte / F Allgemeinmedizin",
    "sg:phone":"+43 4322 45824840",
    "sg:postcode":"2120",
    "sg:province":"Nieder\u00f6sterreich",
    "wof:name":"Schuller-Schreib Ulrike Dr",
    "wof:placetype":"venue"
},
  "geometry": {"coordinates":[16.5185279846,48.3829917908],"type":"Point"}
}