{
  "type": "Feature",
  "properties": {
    "iso:country":"AT",
    "sg:address":"Wiener Str 92",
    "sg:city":"Kapfenberg",
    "sg:orig_category":"Textilreinigung",
    "sg:phone":"+43 3862 22024",
    "sg:postcode":"8605",
    "sg:province":"Steiermark",
    "wof:name":"Putzerei-Perfekt Viktor Dengg",
    "wof:placetype":"venue"
},
  "geometry": {"coordinates":[15.3040065765,47.447227478],"type":"Point"}
}