{
  "type": "Feature",
  "properties": {
    "addr:full":"Diesseits 174 St. Martin im Innkreis Ober\u00f6sterreich 4973",
    "addr:housenumber":"174",
    "addr:postcode":"4973",
    "addr:street":"Diesseits",
    "iso:country":"AT",
    "sg:address":"Diesseits 174",
    "sg:city":"St. Martin im Innkreis",
    "sg:orig_category":"Bankomat-Standorte",
    "sg:phone":"+43 7751 6061",
    "sg:postcode":"4973",
    "sg:province":"Ober\u00f6sterreich",
    "wof:name":"Bankomat d Raiffeisenbank Innkreis Mitte regGenmbH",
    "wof:placetype":"venue"
},
  "geometry": {"coordinates":[13.4180746078,48.261505127],"type":"Point"}
}