{
  "type": "Feature",
  "properties": {
    "iso:country":"AT",
    "sg:address":"Seestr 42",
    "sg:city":"Seeboden",
    "sg:orig_category":"Pensionen / Privatzimmer",
    "sg:phone":"+43 4762 81838",
    "sg:postcode":"9871",
    "sg:province":"K\u00e4rnten",
    "wof:name":"Feichter Johanna",
    "wof:placetype":"venue"
},
  "geometry": {"coordinates":[13.5224456787,46.8151397705],"type":"Point"}
}