{
  "type": "Feature",
  "properties": {
    "addr:full":"Nelkenstr 33 Wels Ober\u00f6sterreich 4600",
    "addr:housenumber":"33",
    "addr:postcode":"4600",
    "addr:street":"Nelkenstr;Oberoesterreich",
    "iso:country":"AT",
    "sg:address":"Nelkenstr 33",
    "sg:city":"Wels",
    "sg:orig_category":"Fliesen U Platten",
    "sg:phone":"+43 7242 450040",
    "sg:postcode":"4600",
    "sg:province":"Ober\u00f6sterreich",
    "sg:website":"www.gringinger.at",
    "wof:name":"Fliesen Gringinger Eduard GesmbH & Co KG",
    "wof:placetype":"venue"
},
  "geometry": {"coordinates":[13.9948387146,48.1538200378],"type":"Point"}
}