{
  "type": "Feature",
  "properties": {
    "addr:full":"Bairisch K\u00f6lldorf 262 Bad Gleichenberg Steiermark 8344",
    "addr:housenumber":"262",
    "addr:postcode":"8344",
    "iso:country":"AT",
    "sg:address":"Bairisch K\u00f6lldorf 262",
    "sg:city":"Bad Gleichenberg",
    "sg:classifiers":[
        {
            "category":"Structure",
            "subcategory":"Office Building",
            "type":"Public Place"
        }
    ],
    "sg:phone":"+43 3159 3367",
    "sg:postcode":"8344",
    "sg:province":"Steiermark",
    "sg:tags":[
        "industrial",
        "assembly"
    ],
    "wof:name":"R\u00f6ck Ges.m.b.H.",
    "wof:placetype":"venue"
},
  "geometry": {"coordinates":[15.923743248,46.8854370117],"type":"Point"}
}