{
  "type": "Feature",
  "properties": {
    "addr:full":"E-Werk-G 7 Ernstbrunn Nieder\u00f6sterreich 2115",
    "addr:housenumber":"7",
    "addr:postcode":"2115",
    "addr:street":"E-Werk-G",
    "iso:country":"AT",
    "sg:address":"E-Werk-G 7",
    "sg:city":"Ernstbrunn",
    "sg:orig_category":"Installationsunternehmen",
    "sg:phone":"+43 2576 2088",
    "sg:postcode":"2115",
    "sg:province":"Nieder\u00f6sterreich",
    "wof:name":"Kuderer Martin Ing",
    "wof:placetype":"venue"
},
  "geometry": {"coordinates":[16.3617553711,48.5267372131],"type":"Point"}
}