{
  "type": "Feature",
  "properties": {
    "iso:country":"AT",
    "sg:address":"Draschestr 63",
    "sg:city":"Wien",
    "sg:orig_category":"Autohandel",
    "sg:phone":"+43 1 6162515",
    "sg:postcode":"1230",
    "sg:province":"Wien",
    "wof:name":"Bohuslavek Ernestine Mag",
    "wof:placetype":"venue"
},
  "geometry": {"coordinates":[16.3533649445,48.1477737427],"type":"Point"}
}