{
  "type": "Feature",
  "properties": {
    "addr:full":"Nr 60a Leibnitz Steiermark 8430",
    "addr:postcode":"8430",
    "addr:street":"Nr 60A;Steiermark",
    "iso:country":"AT",
    "sg:address":"Nr 60a",
    "sg:city":"Leibnitz",
    "sg:orig_category":"Lebensmittel / Einzelhandel",
    "sg:phone":"+43 4334 5273516",
    "sg:postcode":"8430",
    "sg:province":"Steiermark",
    "wof:name":"Billa AG",
    "wof:placetype":"venue"
},
  "geometry": {"coordinates":[15.5377645493,46.7811355591],"type":"Point"}
}