{
  "type": "Feature",
  "properties": {
    "addr:full":"Fadleiten 11 Pichl Ober\u00f6sterreich 4632",
    "addr:housenumber":"11",
    "addr:postcode":"4632",
    "addr:street":"Fadleiten",
    "iso:country":"AT",
    "sg:address":"Fadleiten 11",
    "sg:city":"Pichl",
    "sg:orig_category":"Garten- U Landschaftsgestaltung",
    "sg:phone":"+43 4372 4942166",
    "sg:postcode":"4632",
    "sg:province":"Ober\u00f6sterreich",
    "wof:name":"Strasser Anton",
    "wof:placetype":"venue"
},
  "geometry": {"coordinates":[13.909277916,48.2058296204],"type":"Point"}
}