{
  "type": "Feature",
  "properties": {
    "iso:country":"AT",
    "sg:address":"Dreifaltigkeitspl 10",
    "sg:city":"Gars am Kamp",
    "sg:orig_category":"Fleischhauereien",
    "sg:phone":"+43 4329 852512",
    "sg:postcode":"3571",
    "sg:province":"Nieder\u00f6sterreich",
    "wof:name":"Schober GmbH - biologische Erzeugnisse",
    "wof:placetype":"venue"
},
  "geometry": {"coordinates":[15.6592264175,48.5958099365],"type":"Point"}
}