{
  "type": "Feature",
  "properties": {
    "iso:country":"AT",
    "sg:address":"J\u00e4gerstr 30/16",
    "sg:city":"Wien",
    "sg:orig_category":"Waren Aller Art",
    "sg:phone":"+43 4319 682349",
    "sg:postcode":"1200",
    "sg:province":"Wien",
    "wof:name":"cultis - Cultivating Systems - Heimo Zimmermann KEG",
    "wof:placetype":"venue"
},
  "geometry": {"coordinates":[16.3712806702,48.2291793823],"type":"Point"}
}