{
  "type": "Feature",
  "properties": {
    "addr:full":"Johann-Sackl-G 27 Leoben Steiermark 8700",
    "addr:housenumber":"27",
    "addr:postcode":"8700",
    "addr:street":"Johann-Sackl-G",
    "iso:country":"AT",
    "sg:address":"Johann-Sackl-G 27",
    "sg:city":"Leoben",
    "sg:orig_category":"Botendienste",
    "sg:phone":"+43 3842 25662",
    "sg:postcode":"8700",
    "sg:province":"Steiermark",
    "wof:name":"Stadlbauer Friedrich",
    "wof:placetype":"venue"
},
  "geometry": {"coordinates":[15.0648555756,47.3760452271],"type":"Point"}
}