{
  "type": "Feature",
  "properties": {
    "addr:full":"Hilmteichstr 118A Kroisbach Steiermark 8043",
    "addr:housenumber":"118a",
    "addr:postcode":"8043",
    "iso:country":"AT",
    "sg:address":"Hilmteichstr 118A",
    "sg:city":"Kroisbach",
    "sg:orig_category":"Ingenieurkonsulenten / Zivilingenieure",
    "sg:phone":"+43 316 3819830",
    "sg:postcode":"8043",
    "sg:province":"Steiermark",
    "wof:name":"Haberl Thomas Dr techn",
    "wof:placetype":"venue"
},
  "geometry": {"coordinates":[15.4611053467,47.0874023438],"type":"Point"}
}