{
  "type": "Feature",
  "properties": {
    "iso:country":"AT",
    "sg:address":"Kobernau\u00dfer Strasse 87",
    "sg:city":"Lohnsburg am Kobernau\u00dferwald",
    "sg:classifiers":[
        {
            "category":"Home & Garden",
            "subcategory":"Home Furnishings",
            "type":"Retail Goods"
        }
    ],
    "sg:phone":"+43 7754 3388",
    "sg:postcode":"4923",
    "sg:province":"Ober\u00f6sterreich",
    "sg:tags":[
        "covering",
        "furniture"
    ],
    "wof:name":"Georg Litzlbauer",
    "wof:placetype":"venue"
},
  "geometry": {"coordinates":[13.4070711136,48.142906189],"type":"Point"}
}