{
  "type": "Feature",
  "properties": {
    "addr:full":"Vogelweidplatz 10 Wien Wien 1150",
    "addr:housenumber":"10",
    "addr:postcode":"1150",
    "addr:street":"Vogelweidplatz",
    "iso:country":"AT",
    "sg:address":"Vogelweidplatz 10",
    "sg:city":"Wien",
    "sg:classifiers":[
        {
            "category":"Banks & Credit Unions",
            "subcategory":"Investment Brokerage",
            "type":"Services"
        }
    ],
    "sg:phone":"+43 1 9822188",
    "sg:postcode":"1150",
    "sg:province":"Wien",
    "sg:tags":[
        "bench"
    ],
    "sg:website":"fuhrmann.cc",
    "wof:name":"Rolf Benz \u00d6sterreich",
    "wof:placetype":"venue"
},
  "geometry": {"coordinates":[16.3311729431,48.2034797668],"type":"Point"}
}