{
  "type": "Feature",
  "properties": {
    "addr:full":"Nr 220 Tux Tirol 6293",
    "addr:postcode":"6293",
    "addr:street":"Nr 220;Tirol",
    "iso:country":"AT",
    "sg:address":"Nr 220",
    "sg:city":"Tux",
    "sg:orig_category":"Appartements / Ferienwohnungen",
    "sg:phone":"+43 5287 87604",
    "sg:postcode":"6293",
    "sg:province":"Tirol",
    "wof:name":"Ferienhof Ausserbrente - Willy Geisler",
    "wof:placetype":"venue"
},
  "geometry": {"coordinates":[11.6970243454,47.1270294189],"type":"Point"}
}