{
  "type": "Feature",
  "properties": {
    "iso:country":"AT",
    "sg:address":"Stammg 7",
    "sg:city":"Wien",
    "sg:orig_category":"Psychotherapie",
    "sg:phone":"+43 1 7187788",
    "sg:postcode":"1030",
    "sg:province":"Wien",
    "wof:name":"Planyavsky Stefan Mag",
    "wof:placetype":"venue"
},
  "geometry": {"coordinates":[16.3923892975,48.2070999146],"type":"Point"}
}