{
  "type": "Feature",
  "properties": {
    "addr:full":"Marktpl 1 Asten Ober\u00f6sterreich 4481",
    "addr:housenumber":"1",
    "addr:postcode":"4481",
    "addr:street":"Marktpl",
    "iso:country":"AT",
    "sg:address":"Marktpl 1",
    "sg:city":"Asten",
    "sg:orig_category":"Non-Classified Establishments",
    "sg:phone":"+43 7224 65516",
    "sg:postcode":"4481",
    "sg:province":"Ober\u00f6sterreich",
    "wof:name":"Pfarramt",
    "wof:placetype":"venue"
},
  "geometry": {"coordinates":[14.4221611023,48.2195129395],"type":"Point"}
}