{
  "type": "Feature",
  "properties": {
    "addr:full":"Bodingbachstr 69 Lunz am See Nieder\u00f6sterreich 3293",
    "addr:housenumber":"69",
    "addr:postcode":"3293",
    "addr:street":"Bodingbachstr",
    "iso:country":"AT",
    "sg:address":"Bodingbachstr 69",
    "sg:city":"Lunz am See",
    "sg:orig_category":"Erdarbeiten",
    "sg:phone":"+43 7486 8225",
    "sg:postcode":"3293",
    "sg:province":"Nieder\u00f6sterreich",
    "wof:name":"Wurzer Peter",
    "wof:placetype":"venue"
},
  "geometry": {"coordinates":[15.0050354004,47.8864135742],"type":"Point"}
}