{
  "type": "Feature",
  "properties": {
    "addr:full":"Nr 245/3 Heimschuh Steiermark 8451",
    "addr:housenumber":"3",
    "addr:postcode":"8451",
    "addr:street":"Nr 245 /",
    "iso:country":"AT",
    "sg:address":"Nr 245/3",
    "sg:city":"Heimschuh",
    "sg:orig_category":"Friseure U Frisiersalons",
    "sg:phone":"+43 3452 72273",
    "sg:postcode":"8451",
    "sg:province":"Steiermark",
    "wof:name":"Gabi's Haarstudio",
    "wof:placetype":"venue"
},
  "geometry": {"coordinates":[15.4879951477,46.7589645386],"type":"Point"}
}