{
  "type": "Feature",
  "properties": {
    "iso:country":"AT",
    "sg:address":"Ybbsstr 10",
    "sg:city":"Wien",
    "sg:orig_category":"Installationsunternehmen",
    "sg:phone":"+43 1 7280127",
    "sg:postcode":"1020",
    "sg:province":"Wien",
    "wof:name":"Raich Paul",
    "wof:placetype":"venue"
},
  "geometry": {"coordinates":[16.397644043,48.2205543518],"type":"Point"}
}