{
  "type": "Feature",
  "properties": {
    "addr:full":"Kreuzg 53 Wien Wien 1180",
    "addr:housenumber":"53",
    "addr:postcode":"1180",
    "addr:street":"Kreuzg",
    "iso:country":"AT",
    "sg:address":"Kreuzg 53",
    "sg:city":"Wien",
    "sg:orig_category":"Bodenverlegung",
    "sg:phone":"+43 1 4067179",
    "sg:postcode":"1180",
    "sg:province":"Wien",
    "wof:name":"Graf W.F. Raumgestaltung",
    "wof:placetype":"venue"
},
  "geometry": {"coordinates":[16.335477829,48.2243118286],"type":"Point"}
}