{
  "type": "Feature",
  "properties": {
    "addr:full":"Ebendorfer Hauptstr 2 Mistelbach Nieder\u00f6sterreich 2130",
    "addr:housenumber":"2",
    "addr:postcode":"2130",
    "addr:street":"Hauptstr;Niederoesterreich",
    "iso:country":"AT",
    "sg:address":"Ebendorfer Hauptstr 2",
    "sg:city":"Mistelbach",
    "sg:orig_category":"Forstverwaltungen",
    "sg:phone":"+43 2572 5858",
    "sg:postcode":"2130",
    "sg:province":"Nieder\u00f6sterreich",
    "wof:name":"Mitscha-M\u00e4rheim'sche Hermann Gutsverwaltung",
    "wof:placetype":"venue"
},
  "geometry": {"coordinates":[16.5766372681,48.5606117249],"type":"Point"}
}