{
  "type": "Feature",
  "properties": {
    "iso:country":"AT",
    "sg:address":"Unt Schirmleitenstr 28",
    "sg:city":"St. Veit",
    "sg:orig_category":"Gartenpflege",
    "sg:phone":"+43 664 3930003",
    "sg:postcode":"8046",
    "sg:province":"Steiermark",
    "wof:name":"Liegenschaftsbetreuung men@work",
    "wof:placetype":"venue"
},
  "geometry": {"coordinates":[15.410733223,47.1314620972],"type":"Point"}
}