{
  "type": "Feature",
  "properties": {
    "addr:full":"F\u00f6hrenstr 7 Eisenerz Steiermark 8790",
    "addr:housenumber":"7",
    "addr:postcode":"8790",
    "addr:street":"Foehrenstr",
    "iso:country":"AT",
    "sg:address":"F\u00f6hrenstr 7",
    "sg:city":"Eisenerz",
    "sg:orig_category":"Holzhandel",
    "sg:phone":"+43 4338 482521",
    "sg:postcode":"8790",
    "sg:province":"Steiermark",
    "wof:name":"Peyrlberger Hubert",
    "wof:placetype":"venue"
},
  "geometry": {"coordinates":[14.8931617737,47.5438537598],"type":"Point"}
}