{
  "type": "Feature",
  "properties": {
    "addr:full":"Bachstr 22 Steinerkirchen an der Traun Ober\u00f6sterreich 4652",
    "addr:housenumber":"22",
    "addr:postcode":"4652",
    "addr:street":"Bachstr",
    "iso:country":"AT",
    "sg:address":"Bachstr 22",
    "sg:city":"Steinerkirchen an der Traun",
    "sg:classifiers":[
        {
            "category":"Restaurant",
            "type":"Food & Drink"
        }
    ],
    "sg:phone":"+43 7241 2139",
    "sg:postcode":"4652",
    "sg:province":"Ober\u00f6sterreich",
    "wof:name":"Hofinger Andreas",
    "wof:placetype":"venue"
},
  "geometry": {"coordinates":[13.9564161301,48.0752906799],"type":"Point"}
}