{
  "type": "Feature",
  "properties": {
    "addr:full":"Ruster Str 138 Eisenstadt Burgenland 7000",
    "addr:housenumber":"138",
    "addr:postcode":"7000",
    "iso:country":"AT",
    "sg:address":"Ruster Str 138",
    "sg:city":"Eisenstadt",
    "sg:orig_category":"Bauunternehmen",
    "sg:phone":"+43 2682 660210",
    "sg:postcode":"7000",
    "sg:province":"Burgenland",
    "wof:name":"Lauggas Baugesellschaft GmbH",
    "wof:placetype":"venue"
},
  "geometry": {"coordinates":[16.5309066772,47.8279914856],"type":"Point"}
}