{
  "type": "Feature",
  "properties": {
    "addr:full":"Nr 65 Johnsbach Steiermark 8912",
    "addr:postcode":"8912",
    "addr:street":"Nr",
    "iso:country":"AT",
    "sg:address":"Nr 65",
    "sg:city":"Johnsbach",
    "sg:classifiers":[
        {
            "category":"Taxi",
            "type":"Transportation"
        }
    ],
    "sg:phone":"+43 3611 2150",
    "sg:postcode":"8912",
    "sg:province":"Steiermark",
    "sg:tags":[
        "personentransporte",
        "u"
    ],
    "wof:name":"Zeiringer Johann",
    "wof:placetype":"venue"
},
  "geometry": {"coordinates":[14.584236145,47.5398178101],"type":"Point"}
}