{
  "type": "Feature",
  "properties": {
    "addr:full":"Schetteregg 898 Egg Vorarlberg 6863",
    "addr:housenumber":"898",
    "addr:postcode":"6863",
    "iso:country":"AT",
    "sg:address":"Schetteregg 898",
    "sg:city":"Egg",
    "sg:classifiers":[
        {
            "category":"Travel",
            "subcategory":"Hotels & Motels",
            "type":"Entertainment"
        }
    ],
    "sg:phone":"+43 5512 3220",
    "sg:postcode":"6863",
    "sg:province":"Vorarlberg",
    "wof:name":"Schetteregger Hof",
    "wof:placetype":"venue"
},
  "geometry": {"coordinates":[9.9694261551,47.4123420715],"type":"Point"}
}