{
  "type": "Feature",
  "properties": {
    "addr:full":"Oberham 1 Hohenzell Ober\u00f6sterreich 4921",
    "addr:housenumber":"1",
    "addr:postcode":"4921",
    "addr:street":"Oberham",
    "iso:country":"AT",
    "sg:address":"Oberham 1",
    "sg:city":"Hohenzell",
    "sg:orig_category":"Personalbereitstellung",
    "sg:phone":"+43 7752 86236",
    "sg:postcode":"4921",
    "sg:province":"Ober\u00f6sterreich",
    "wof:name":"D\u00fcrnberger Josef",
    "wof:placetype":"venue"
},
  "geometry": {"coordinates":[13.5528678894,48.19373703],"type":"Point"}
}