{
  "type": "Feature",
  "properties": {
    "iso:country":"AT",
    "sg:address":"Industriestrasse 6",
    "sg:city":"Bruck an der Leitha",
    "sg:classifiers":[
        {
            "category":"Home & Garden",
            "subcategory":"Building Materials",
            "type":"Retail Goods"
        }
    ],
    "sg:phone":"+43 2162 62156",
    "sg:postcode":"2460",
    "sg:province":"Nieder\u00f6sterreich",
    "sg:tags":[
        "aluminium",
        "gutter"
    ],
    "wof:name":"Ing. Franz Weber",
    "wof:placetype":"venue"
},
  "geometry": {"coordinates":[16.7857990265,48.0332717896],"type":"Point"}
}