{
  "type": "Feature",
  "properties": {
    "addr:full":"Hainfelder Str 14 Berndorf Nieder\u00f6sterreich 2560",
    "addr:postcode":"2560",
    "addr:street":"Str 14",
    "iso:country":"AT",
    "sg:address":"Hainfelder Str 14",
    "sg:city":"Berndorf",
    "sg:orig_category":"Apotheken",
    "sg:phone":"+43 4326 72822240",
    "sg:postcode":"2560",
    "sg:province":"Nieder\u00f6sterreich",
    "wof:name":"Apotheke Zur heiligen Dreifaltigkeit Dr Tschochner KEG - P\u00e4chterin Mag Heidi WURZINGER",
    "wof:placetype":"venue"
},
  "geometry": {"coordinates":[16.1096954346,47.9470367432],"type":"Point"}
}