{
  "type": "Feature",
  "properties": {
    "addr:full":"Landstr 20 Steinerkirchen an der Traun Ober\u00f6sterreich 4652",
    "addr:housenumber":"20",
    "addr:postcode":"4652",
    "addr:street":"Landstr",
    "iso:country":"AT",
    "sg:address":"Landstr 20",
    "sg:city":"Steinerkirchen an der Traun",
    "sg:orig_category":"Volksschulen",
    "sg:phone":"+43 4372 412226",
    "sg:postcode":"4652",
    "sg:province":"Ober\u00f6sterreich",
    "wof:name":"Volksschule",
    "wof:placetype":"venue"
},
  "geometry": {"coordinates":[13.9602184296,48.0788421631],"type":"Point"}
}