{
  "type": "Feature",
  "properties": {
    "addr:full":"Marktpl 30 Bad Zell Ober\u00f6sterreich 4283",
    "addr:housenumber":"30",
    "addr:postcode":"4283",
    "addr:street":"Marktpl",
    "iso:country":"AT",
    "sg:address":"Marktpl 30",
    "sg:city":"Bad Zell",
    "sg:orig_category":"\u00c3\u201enderungsschneidereien",
    "sg:phone":"+43 7263 20081",
    "sg:postcode":"4283",
    "sg:province":"Ober\u00f6sterreich",
    "wof:name":"Tischberger Rosina",
    "wof:placetype":"venue"
},
  "geometry": {"coordinates":[14.6695308685,48.3493347168],"type":"Point"}
}