{
  "type": "Feature",
  "properties": {
    "addr:full":"Im Martinsfeld 17 Rankweil Vorarlberg 6830",
    "addr:housenumber":"17",
    "addr:postcode":"6830",
    "addr:street":"Im Martinsfeld",
    "iso:country":"AT",
    "sg:address":"Im Martinsfeld 17",
    "sg:city":"Rankweil",
    "sg:orig_category":"Babyausstattung",
    "sg:phone":"+43 5522 73201",
    "sg:postcode":"6830",
    "sg:province":"Vorarlberg",
    "wof:name":"Purzelb\u00e4r",
    "wof:placetype":"venue"
},
  "geometry": {"coordinates":[9.6431694031,47.2692146301],"type":"Point"}
}