{
  "type": "Feature",
  "properties": {
    "addr:full":"Unterer Stadtpl Hall in Tirol Tirol 6060",
    "addr:postcode":"6060",
    "addr:street":"Unterer;Hall;Tirol",
    "iso:country":"AT",
    "sg:address":"Unterer Stadtpl",
    "sg:city":"Hall in Tirol",
    "sg:orig_category":"Damenmoden",
    "sg:phone":"+43 5223 5393074",
    "sg:postcode":"6060",
    "sg:province":"Tirol",
    "wof:name":"Mode von Feucht",
    "wof:placetype":"venue"
},
  "geometry": {"coordinates":[11.5044460297,47.280834198],"type":"Point"}
}