{
  "type": "Feature",
  "properties": {
    "addr:full":"Schlo\u00dfpl 3 Staatz-Kautendorf Nieder\u00f6sterreich 2134",
    "addr:housenumber":"3",
    "addr:postcode":"2134",
    "addr:street":"Schlosspl;Niederoesterreich",
    "iso:country":"AT",
    "sg:address":"Schlo\u00dfpl 3",
    "sg:city":"Staatz-Kautendorf",
    "sg:orig_category":"Volksschulen",
    "sg:phone":"+43 2524 3530",
    "sg:postcode":"2134",
    "sg:province":"Nieder\u00f6sterreich",
    "wof:name":"Volksschule",
    "wof:placetype":"venue"
},
  "geometry": {"coordinates":[16.4909744263,48.6764755249],"type":"Point"}
}