{
  "type": "Feature",
  "properties": {
    "addr:full":"Salzburger Str 40 Wattens Tirol 6112",
    "addr:housenumber":"40",
    "addr:postcode":"6112",
    "addr:street":"Salzburger Str;Tirol",
    "iso:country":"AT",
    "sg:address":"Salzburger Str 40",
    "sg:city":"Wattens",
    "sg:orig_category":"Bauunternehmen",
    "sg:phone":"+43 4352 24529400",
    "sg:postcode":"6112",
    "sg:province":"Tirol",
    "wof:name":"Goidinger H Dipl-Ing Bau- u Leichtbeton GesmbH",
    "wof:placetype":"venue"
},
  "geometry": {"coordinates":[11.60247612,47.2925949097],"type":"Point"}
}