{
  "type": "Feature",
  "properties": {
    "addr:full":"Sandstrasse 29 Lustenau Vorarlberg 6890",
    "addr:housenumber":"29",
    "addr:postcode":"6890",
    "addr:street":"Sandstrasse",
    "iso:country":"AT",
    "sg:address":"Sandstrasse 29",
    "sg:city":"Lustenau",
    "sg:orig_category":"Inventors Offices, Inventions",
    "sg:phone":"+43 5577 82674",
    "sg:postcode":"6890",
    "sg:province":"Vorarlberg",
    "sg:website":"vseworld.com",
    "wof:name":"VSE Vakuumtechnik Hubert B\u00f6sch",
    "wof:placetype":"venue"
},
  "geometry": {"coordinates":[9.6544561386,47.439655304],"type":"Point"}
}