{
  "type": "Feature",
  "properties": {
    "addr:full":"Bahnhofstr 25 Hartberg Steiermark 8230",
    "addr:housenumber":"25",
    "addr:postcode":"8230",
    "addr:street":"Bahnhofstr",
    "iso:country":"AT",
    "sg:address":"Bahnhofstr 25",
    "sg:city":"Hartberg",
    "sg:orig_category":"Banken U Sparkassen",
    "sg:phone":"+43 3332 650650",
    "sg:postcode":"8230",
    "sg:province":"Steiermark",
    "wof:name":"Bank f Arbeit und Wirtschaft AG",
    "wof:placetype":"venue"
},
  "geometry": {"coordinates":[15.978146553,47.2829780579],"type":"Point"}
}