{
  "type": "Feature",
  "properties": {
    "addr:full":"Schulstr 2 Gaweinstal Nieder\u00f6sterreich 2191",
    "addr:housenumber":"2",
    "addr:postcode":"2191",
    "addr:street":"Schulstr",
    "iso:country":"AT",
    "sg:address":"Schulstr 2",
    "sg:city":"Gaweinstal",
    "sg:orig_category":"Hauptschulen",
    "sg:phone":"+43 2574 29500",
    "sg:postcode":"2191",
    "sg:province":"Nieder\u00f6sterreich",
    "wof:name":"Hauptschule",
    "wof:placetype":"venue"
},
  "geometry": {"coordinates":[16.585641861,48.4787445068],"type":"Point"}
}