{
  "type": "Feature",
  "properties": {
    "iso:country":"AT",
    "sg:address":"Aug 81",
    "sg:city":"G\u00f6sting",
    "sg:orig_category":"Volksschulen",
    "sg:phone":"+43 316 684929",
    "sg:postcode":"8051",
    "sg:province":"Steiermark",
    "wof:name":"Volksschule",
    "wof:placetype":"venue"
},
  "geometry": {"coordinates":[15.3543653488,47.0787315369],"type":"Point"}
}