{
  "type": "Feature",
  "properties": {
    "addr:full":"St. Veiter Str 179 Klagenfurt K\u00e4rnten 9020",
    "addr:housenumber":"179",
    "addr:postcode":"9020",
    "addr:street":"St. Veiter Str;Kaernten",
    "iso:country":"AT",
    "sg:address":"St. Veiter Str 179",
    "sg:city":"Klagenfurt",
    "sg:orig_category":"Autoreparatur",
    "sg:phone":"+43 463 418145",
    "sg:postcode":"9020",
    "sg:province":"K\u00e4rnten",
    "wof:name":"Lepuch & Perko GmbH",
    "wof:placetype":"venue"
},
  "geometry": {"coordinates":[14.3138780594,46.6499938965],"type":"Point"}
}