{
  "type": "Feature",
  "properties": {
    "iso:country":"AT",
    "sg:address":"Paulinengasse 13",
    "sg:city":"Wien",
    "sg:classifiers":[
        {
            "category":"Structure",
            "subcategory":"Building",
            "type":"Public Place"
        }
    ],
    "sg:phone":"+43 1 4704180",
    "sg:postcode":"1180",
    "sg:province":"Wien",
    "sg:tags":[
        "apartment"
    ],
    "sg:website":"tromayerbau.at",
    "wof:name":"TROMAYER BAU Ges.m.b.H.",
    "wof:placetype":"venue"
},
  "geometry": {"coordinates":[16.3314304352,48.2277755737],"type":"Point"}
}