{
  "type": "Feature",
  "properties": {
    "addr:full":"Dorf 231 Flie\u00df Tirol 6521",
    "addr:housenumber":"231",
    "addr:postcode":"6521",
    "addr:street":"Dorf;Tirol",
    "iso:country":"AT",
    "sg:address":"Dorf 231",
    "sg:city":"Flie\u00df",
    "sg:orig_category":"Appartements / Ferienwohnungen",
    "sg:phone":"+43 5449 5312",
    "sg:postcode":"6521",
    "sg:province":"Tirol",
    "wof:name":"Geiger Wilfried",
    "wof:placetype":"venue"
},
  "geometry": {"coordinates":[10.6277103424,47.1199989319],"type":"Point"}
}