{
  "type": "Feature",
  "properties": {
    "iso:country":"AT",
    "sg:address":"Sturzg 8",
    "sg:city":"Graz",
    "sg:orig_category":"Abfallentsorgung U -Verwertung",
    "sg:phone":"+43 316 2958980",
    "sg:postcode":"8020",
    "sg:province":"Steiermark",
    "wof:name":"AEVG Abfall Entsorgungs und VerwertungsgmbH",
    "wof:placetype":"venue"
},
  "geometry": {"coordinates":[15.438996315,47.0460128784],"type":"Point"}
}