{
  "type": "Feature",
  "properties": {
    "iso:country":"AT",
    "sg:address":"Rennsteiner Str 7",
    "sg:city":"Villach",
    "sg:orig_category":"Telefonmarketing",
    "sg:phone":"+43 4242 24422",
    "sg:postcode":"9500",
    "sg:province":"K\u00e4rnten",
    "wof:name":"TELEPOWER - Herrgesell Elfriede",
    "wof:placetype":"venue"
},
  "geometry": {"coordinates":[13.8459596634,46.6200294495],"type":"Point"}
}