{
  "type": "Feature",
  "properties": {
    "addr:full":"Bergg 7 Langenzersdorf Nieder\u00f6sterreich 2103",
    "addr:housenumber":"7",
    "addr:postcode":"2103",
    "addr:street":"Bergg",
    "iso:country":"AT",
    "sg:address":"Bergg 7",
    "sg:city":"Langenzersdorf",
    "sg:orig_category":"Elektronik",
    "sg:phone":"+43 2244 48600",
    "sg:postcode":"2103",
    "sg:province":"Nieder\u00f6sterreich",
    "wof:name":"Offenbeck Industrial Electronics",
    "wof:placetype":"venue"
},
  "geometry": {"coordinates":[16.3559913635,48.3127746582],"type":"Point"}
}