{
  "type": "Feature",
  "properties": {
    "addr:full":"Kr\u00e4utlerweg 40-42 Salzburg Salzburg 5020",
    "addr:postcode":"40-42;5020",
    "addr:street":"Salzburg",
    "iso:country":"AT",
    "sg:address":"Kr\u00e4utlerweg 40-42",
    "sg:city":"Salzburg",
    "sg:orig_category":"Gastronomie- U Hotelbedarf",
    "sg:phone":"+43 662 8249630",
    "sg:postcode":"5020",
    "sg:province":"Salzburg",
    "sg:website":"www.holzmann.at",
    "wof:name":"Holzmann Rudolf OHG - Gastro",
    "wof:placetype":"venue"
},
  "geometry": {"coordinates":[13.0073747635,47.7780723572],"type":"Point"}
}