{
  "type": "Feature",
  "properties": {
    "iso:country":"AT",
    "sg:address":"W\u00e4hringer Str 80-82",
    "sg:city":"Wien",
    "sg:orig_category":"Boutiquen",
    "sg:phone":"+43 1 4708089",
    "sg:postcode":"1180",
    "sg:province":"Wien",
    "wof:name":"Francoise",
    "wof:placetype":"venue"
},
  "geometry": {"coordinates":[16.3488674164,48.2253036499],"type":"Point"}
}