{
  "type": "Feature",
  "properties": {
    "iso:country":"AT",
    "sg:address":"Jakominipl 12",
    "sg:city":"Graz",
    "sg:orig_category":"Friseurbedarf",
    "sg:phone":"+43 316 815472",
    "sg:postcode":"8010",
    "sg:province":"Steiermark",
    "wof:name":"Maurer Robert GmbH",
    "wof:placetype":"venue"
},
  "geometry": {"coordinates":[15.4439430237,47.0674858093],"type":"Point"}
}