{
  "type": "Feature",
  "properties": {
    "addr:full":"Reichsstr 133a Feldkirch Vorarlberg 6800",
    "addr:housenumber":"133a",
    "addr:postcode":"6800",
    "iso:country":"AT",
    "sg:address":"Reichsstr 133a",
    "sg:city":"Feldkirch",
    "sg:orig_category":"Tankstellen",
    "sg:phone":"+43 5522 73061",
    "sg:postcode":"6800",
    "sg:province":"Vorarlberg",
    "wof:name":"JET Tankstelle",
    "wof:placetype":"venue"
},
  "geometry": {"coordinates":[9.6100912094,47.2471427917],"type":"Point"}
}