{
  "type": "Feature",
  "properties": {
    "addr:full":"Schulg 189 Schladming Steiermark 8970",
    "addr:housenumber":"189",
    "addr:postcode":"8970",
    "iso:country":"AT",
    "sg:address":"Schulg 189",
    "sg:city":"Schladming",
    "sg:orig_category":"Banken U Sparkassen",
    "sg:phone":"+43 4336 87225210",
    "sg:postcode":"8970",
    "sg:province":"Steiermark",
    "wof:name":"Raiffeisenbank Schladming regGenmbH",
    "wof:placetype":"venue"
},
  "geometry": {"coordinates":[13.6925163269,47.3930587769],"type":"Point"}
}