{
  "type": "Feature",
  "properties": {
    "addr:full":"Hauptstr 42a St. Johann im Pongau Salzburg 5600",
    "addr:housenumber":"42a",
    "addr:postcode":"5600",
    "addr:street":"Hauptstr;Salzburg",
    "iso:country":"AT",
    "sg:address":"Hauptstr 42a",
    "sg:city":"St. Johann im Pongau",
    "sg:orig_category":"Lebensmittel / Einzelhandel",
    "sg:phone":"+43 6412 7239",
    "sg:postcode":"5600",
    "sg:province":"Salzburg",
    "wof:name":"Billa AG",
    "wof:placetype":"venue"
},
  "geometry": {"coordinates":[13.201210022,47.3472290039],"type":"Point"}
}