{
  "type": "Feature",
  "properties": {
    "addr:full":"Nr 20 Friedersbach Nieder\u00f6sterreich 3533",
    "addr:postcode":"3533",
    "addr:street":"Nr 20 Friedersbach",
    "iso:country":"AT",
    "sg:address":"Nr 20",
    "sg:city":"Friedersbach",
    "sg:classifiers":[
        {
            "category":"Home & Garden",
            "subcategory":"Building Materials",
            "type":"Retail Goods"
        }
    ],
    "sg:phone":"+43 4328 2276294",
    "sg:postcode":"3533",
    "sg:province":"Nieder\u00f6sterreich",
    "sg:tags":[
        "baustoffe",
        "-material",
        "u"
    ],
    "wof:name":"Hanni Elfriede u Franz OHG",
    "wof:placetype":"venue"
},
  "geometry": {"coordinates":[15.2693529129,48.5901679993],"type":"Point"}
}