{
  "type": "Feature",
  "properties": {
    "addr:full":"Kreuzstr 15 Schlins Vorarlberg 6824",
    "addr:housenumber":"15",
    "addr:postcode":"6824",
    "addr:street":"Kreuzstr",
    "iso:country":"AT",
    "sg:address":"Kreuzstr 15",
    "sg:city":"Schlins",
    "sg:orig_category":"Tischlereien",
    "sg:phone":"+43 5524 83210",
    "sg:postcode":"6824",
    "sg:province":"Vorarlberg",
    "sg:website":"faktor8.at/hartmann",
    "wof:name":"Hartmann Albert",
    "wof:placetype":"venue"
},
  "geometry": {"coordinates":[9.6972312927,47.2064437866],"type":"Point"}
}