{
  "type": "Feature",
  "properties": {
    "iso:country":"AT",
    "sg:address":"Herrschaftsweg 2",
    "sg:city":"Stegersbach",
    "sg:orig_category":"Zimmereien",
    "sg:phone":"+43 3326 52243",
    "sg:postcode":"7551",
    "sg:province":"Burgenland",
    "wof:name":"Oswald GmbH",
    "wof:placetype":"venue"
},
  "geometry": {"coordinates":[16.170835495,47.1555252075],"type":"Point"}
}