{
  "type": "Feature",
  "properties": {
    "addr:full":"Schranneng 2 Salzburg Salzburg 5020",
    "addr:housenumber":"2",
    "addr:postcode":"5020",
    "addr:street":"Schranneng;Salzburg",
    "iso:country":"AT",
    "sg:address":"Schranneng 2",
    "sg:city":"Salzburg",
    "sg:orig_category":"Osteopathie",
    "sg:phone":"+43 662 872912",
    "sg:postcode":"5020",
    "sg:province":"Salzburg",
    "wof:name":"Huber Bernhard",
    "wof:placetype":"venue"
},
  "geometry": {"coordinates":[13.0437173843,47.8051223755],"type":"Point"}
}