{
  "type": "Feature",
  "properties": {
    "iso:country":"AT",
    "sg:address":"Nr 65",
    "sg:city":"Holzgau",
    "sg:orig_category":"Lebensmittel / Einzelhandel",
    "sg:phone":"+43 5633 5278",
    "sg:postcode":"6654",
    "sg:province":"Tirol",
    "wof:name":"Nah & Frisch Markt - Fam Knitel",
    "wof:placetype":"venue"
},
  "geometry": {"coordinates":[10.3436069489,47.2595977783],"type":"Point"}
}