{
  "type": "Feature",
  "properties": {
    "addr:full":"Thermenpl 2 Laa an der Thaya Nieder\u00f6sterreich 2136",
    "addr:housenumber":"2",
    "addr:postcode":"2136",
    "addr:street":"Thermenpl",
    "iso:country":"AT",
    "sg:address":"Thermenpl 2",
    "sg:city":"Laa an der Thaya",
    "sg:orig_category":"Gesundheit / Allgemeine Informationsstellen",
    "sg:phone":"+43 4325 2284084",
    "sg:postcode":"2136",
    "sg:province":"Nieder\u00f6sterreich",
    "wof:name":"Gesundheits- u Vitalzentrum Laa",
    "wof:placetype":"venue"
},
  "geometry": {"coordinates":[16.3999576569,48.7243537903],"type":"Point"}
}