{
  "type": "Feature",
  "properties": {
    "addr:full":"Hockeg 87 Wien Wien 1180",
    "addr:housenumber":"87",
    "addr:postcode":"1180",
    "addr:street":"Hockeg",
    "iso:country":"AT",
    "sg:address":"Hockeg 87",
    "sg:city":"Wien",
    "sg:orig_category":"Chemikalien",
    "sg:phone":"+43 4314 7915400",
    "sg:postcode":"1180",
    "sg:province":"Wien",
    "wof:name":"Pompe Julius Dr OHG & Co Nahrungsmittel-Rohstoffe-HandelsgesmbH",
    "wof:placetype":"venue"
},
  "geometry": {"coordinates":[16.3104076385,48.2390441895],"type":"Point"}
}