{
  "type": "Feature",
  "properties": {
    "addr:full":"Stuben Ferndorfer Str 44 Feistritz an der Drau K\u00e4rnten 9710",
    "addr:housenumber":"44",
    "addr:postcode":"9710",
    "addr:street":"Stuben Ferndorfer Str",
    "iso:country":"AT",
    "sg:address":"Stuben Ferndorfer Str 44",
    "sg:city":"Feistritz an der Drau",
    "sg:classifiers":[
        {
            "category":"Restaurant",
            "type":"Food & Drink"
        }
    ],
    "sg:phone":"+43 4342 452218",
    "sg:postcode":"9710",
    "sg:province":"K\u00e4rnten",
    "wof:name":"Bahnhofrestaurant",
    "wof:placetype":"venue"
},
  "geometry": {"coordinates":[13.66314888,46.7018623352],"type":"Point"}
}