{
  "type": "Feature",
  "properties": {
    "addr:full":"Wiener Str 51 G\u00fcssing Burgenland 7540",
    "addr:postcode":"7540",
    "addr:street":"51 Guessing",
    "iso:country":"AT",
    "sg:address":"Wiener Str 51",
    "sg:city":"G\u00fcssing",
    "sg:orig_category":"Umwelttechnik",
    "sg:phone":"+43 4333 2243011",
    "sg:postcode":"7540",
    "sg:province":"Burgenland",
    "wof:name":"Biomasse-Kraftwerk G\u00fcssing GmbH & Co KG - Werk",
    "wof:placetype":"venue"
},
  "geometry": {"coordinates":[16.3196105957,47.0746688843],"type":"Point"}
}