{
  "type": "Feature",
  "properties": {
    "addr:full":"M\u00fchlbachring 14 Spielberg Steiermark 8724",
    "addr:housenumber":"14",
    "addr:postcode":"8724",
    "addr:street":"Muehlbachring",
    "iso:country":"AT",
    "sg:address":"M\u00fchlbachring 14",
    "sg:city":"Spielberg",
    "sg:orig_category":"Elektroinstallationsunternehmen",
    "sg:phone":"+43 4335 12490740",
    "sg:postcode":"8724",
    "sg:province":"Steiermark",
    "wof:name":"Elektro Angerer",
    "wof:placetype":"venue"
},
  "geometry": {"coordinates":[14.7973117828,47.2074241638],"type":"Point"}
}