{
  "type": "Feature",
  "properties": {
    "addr:full":"Hauptstr 66 Henndorf am Wallersee Salzburg 5302",
    "addr:housenumber":"66",
    "addr:postcode":"5302",
    "addr:street":"Hauptstr",
    "iso:country":"AT",
    "sg:address":"Hauptstr 66",
    "sg:city":"Henndorf am Wallersee",
    "sg:orig_category":"Fenster",
    "sg:phone":"+43 4362 146381",
    "sg:postcode":"5302",
    "sg:province":"Salzburg",
    "wof:name":"Moser Engelbert",
    "wof:placetype":"venue"
},
  "geometry": {"coordinates":[13.1896276474,47.9003448486],"type":"Point"}
}