{
  "type": "Feature",
  "properties": {
    "iso:country":"AT",
    "sg:address":"Neudorf 41",
    "sg:city":"Hermagor",
    "sg:orig_category":"Tonanlagen / Vermietung",
    "sg:phone":"+43 4282 3000",
    "sg:postcode":"9620",
    "sg:province":"K\u00e4rnten",
    "wof:name":"Rauscher Werner",
    "wof:placetype":"venue"
},
  "geometry": {"coordinates":[13.3710899353,46.6263885498],"type":"Point"}
}