{
  "type": "Feature",
  "properties": {
    "addr:full":"Dr.-Hans-Kloepfer-Str 22 Fernitz Steiermark 8072",
    "addr:housenumber":"22",
    "addr:postcode":"8072",
    "addr:street":"Dr.-Hans-Kloepfer-Str",
    "iso:country":"AT",
    "sg:address":"Dr.-Hans-Kloepfer-Str 22",
    "sg:city":"Fernitz",
    "sg:orig_category":"Baumeister",
    "sg:phone":"+43 3135 51641",
    "sg:postcode":"8072",
    "sg:province":"Steiermark",
    "sg:website":"planender-baumeister.at",
    "wof:name":"Baumeister Ing Harald Posch Bauleitung-PlanungsgesmbH",
    "wof:placetype":"venue"
},
  "geometry": {"coordinates":[15.5014839172,46.9781799316],"type":"Point"}
}