{
  "type": "Feature",
  "properties": {
    "iso:country":"AT",
    "sg:address":"Hauptstr 145",
    "sg:city":"Golling an der Erlauf",
    "sg:orig_category":"Berufsbekleidung / Einzelhandel",
    "sg:phone":"+43 4327 577533",
    "sg:postcode":"3381",
    "sg:province":"Nieder\u00f6sterreich",
    "wof:name":"Hartmann-Versand f\u00fcr's Handwerk - Eva Hartmann",
    "wof:placetype":"venue"
},
  "geometry": {"coordinates":[15.174331665,48.1880073547],"type":"Point"}
}