{
  "type": "Feature",
  "properties": {
    "addr:full":"Richard-Strauss-Str 34 Wien Wien 1230",
    "addr:housenumber":"34",
    "addr:postcode":"1230",
    "addr:street":"Richard-Strauss-Str",
    "iso:country":"AT",
    "sg:address":"Richard-Strauss-Str 34",
    "sg:city":"Wien",
    "sg:orig_category":"Autoreparatur",
    "sg:phone":"+43 1 610040",
    "sg:postcode":"1230",
    "sg:province":"Wien",
    "wof:name":"Frey Ernst OHG",
    "wof:placetype":"venue"
},
  "geometry": {"coordinates":[16.3348484039,48.1380691528],"type":"Point"}
}