{
  "type": "Feature",
  "properties": {
    "addr:full":"Bahnstr 24 Wolkersdorf im Weinviertel Nieder\u00f6sterreich 2120",
    "addr:housenumber":"24",
    "addr:postcode":"2120",
    "addr:street":"Bahnstr",
    "iso:country":"AT",
    "sg:address":"Bahnstr 24",
    "sg:city":"Wolkersdorf im Weinviertel",
    "sg:orig_category":"Notare",
    "sg:phone":"+43 2245 22310",
    "sg:postcode":"2120",
    "sg:province":"Nieder\u00f6sterreich",
    "wof:name":"Friedschr\u00f6der Johann Dr",
    "wof:placetype":"venue"
},
  "geometry": {"coordinates":[16.5192546844,48.3726654053],"type":"Point"}
}