{
  "type": "Feature",
  "properties": {
    "addr:full":"Leopold-Werndl-Str 11 Steyr Ober\u00f6sterreich 4400",
    "addr:housenumber":"11",
    "addr:postcode":"4400",
    "addr:street":"Leopold-Werndl-Str;Oberoesterreich",
    "iso:country":"AT",
    "sg:address":"Leopold-Werndl-Str 11",
    "sg:city":"Steyr",
    "sg:orig_category":"Handelsagenturen",
    "sg:phone":"+43 7252 48482",
    "sg:postcode":"4400",
    "sg:province":"Ober\u00f6sterreich",
    "wof:name":"Dimitrov Wladimir Dipl-Ing",
    "wof:placetype":"venue"
},
  "geometry": {"coordinates":[14.4131011963,48.0345344543],"type":"Point"}
}