{
  "type": "Feature",
  "properties": {
    "addr:full":"Algersdorfer Str 31 Graz Steiermark 8020",
    "addr:housenumber":"31",
    "addr:postcode":"8020",
    "addr:street":"Str",
    "iso:country":"AT",
    "sg:address":"Algersdorfer Str 31",
    "sg:city":"Graz",
    "sg:orig_category":"Behinderungen / Leben Mit Behinderungen",
    "sg:phone":"+43 316 586855",
    "sg:postcode":"8020",
    "sg:province":"Steiermark",
    "wof:name":"Verein zur Erhaltung d Wohn- und Arbeitsgemeinschaft Behinderter",
    "wof:placetype":"venue"
},
  "geometry": {"coordinates":[15.4016571045,47.0761489868],"type":"Point"}
}