{
  "type": "Feature",
  "properties": {
    "addr:full":"Salzburger Str 44 Bad Hofgastein Salzburg 5630",
    "addr:housenumber":"44",
    "addr:postcode":"5630",
    "addr:street":"Salzburger Str;Salzburg",
    "iso:country":"AT",
    "sg:address":"Salzburger Str 44",
    "sg:city":"Bad Hofgastein",
    "sg:orig_category":"Autobusunternehmen",
    "sg:phone":"+43 4364 326344",
    "sg:postcode":"5630",
    "sg:province":"Salzburg",
    "wof:name":"\u00f6BB-Postbus GmbH Verkehrsstelle Bad Hofgastein",
    "wof:placetype":"venue"
},
  "geometry": {"coordinates":[13.104352951,47.1777839661],"type":"Point"}
}