{
  "type": "Feature",
  "properties": {
    "addr:full":"Heimst\u00e4ttenhof 4 Haid Ober\u00f6sterreich 4053",
    "addr:housenumber":"4",
    "addr:postcode":"4053",
    "addr:street":"Heimstaettenhof",
    "iso:country":"AT",
    "sg:address":"Heimst\u00e4ttenhof 4",
    "sg:city":"Haid",
    "sg:orig_category":"Magnetfeldtherapie",
    "sg:phone":"+43 4369 911052062",
    "sg:postcode":"4053",
    "sg:province":"Ober\u00f6sterreich",
    "wof:name":"magnetfeldtherapie",
    "wof:placetype":"venue"
},
  "geometry": {"coordinates":[14.2519388199,48.2016868591],"type":"Point"}
}