{
  "type": "Feature",
  "properties": {
    "addr:full":"Hauptstr 29 Grein Ober\u00f6sterreich 4360",
    "addr:housenumber":"29",
    "addr:postcode":"4360",
    "addr:street":"Hauptstr",
    "iso:country":"AT",
    "sg:address":"Hauptstr 29",
    "sg:city":"Grein",
    "sg:orig_category":"Textilwaren / Einzelhandel",
    "sg:phone":"+43 7268 323",
    "sg:postcode":"4360",
    "sg:province":"Ober\u00f6sterreich",
    "wof:name":"Ziegler Kurt",
    "wof:placetype":"venue"
},
  "geometry": {"coordinates":[14.8559904099,48.2282791138],"type":"Point"}
}