{
  "type": "Feature",
  "properties": {
    "iso:country":"AT",
    "sg:address":"Nr 55",
    "sg:city":"Kematen in Tirol",
    "sg:classifiers":[
        {
            "category":"Professional",
            "subcategory":"Computer Services",
            "type":"Services"
        }
    ],
    "sg:phone":"+43 5232 210210",
    "sg:postcode":"6175",
    "sg:province":"Tirol",
    "sg:tags":[
        "software"
    ],
    "wof:name":"proALPHA Software Austria GesmbH",
    "wof:placetype":"venue"
},
  "geometry": {"coordinates":[11.2721157074,47.2541809082],"type":"Point"}
}