{
  "type": "Feature",
  "properties": {
    "iso:country":"AT",
    "sg:address":"Widumg 3",
    "sg:city":"Silz",
    "sg:orig_category":"Tourismusinformation U -Organisationen",
    "sg:phone":"+43 4352 636552",
    "sg:postcode":"6424",
    "sg:province":"Tirol",
    "wof:name":"Tourismusverband Silz",
    "wof:placetype":"venue"
},
  "geometry": {"coordinates":[10.9259881973,47.2672538757],"type":"Point"}
}