{
  "type": "Feature",
  "properties": {
    "addr:full":"Hannesgrub 10 Ried im Innkreis Ober\u00f6sterreich 4910",
    "addr:housenumber":"10",
    "addr:postcode":"4910",
    "addr:street":"Hannesgrub",
    "iso:country":"AT",
    "sg:address":"Hannesgrub 10",
    "sg:city":"Ried im Innkreis",
    "sg:orig_category":"Autoreparatur",
    "sg:phone":"+43 4377 5280424",
    "sg:postcode":"4910",
    "sg:province":"Ober\u00f6sterreich",
    "wof:name":"Auto Bramer",
    "wof:placetype":"venue"
},
  "geometry": {"coordinates":[13.4977397919,48.2174835205],"type":"Point"}
}