{
  "type": "Feature",
  "properties": {
    "addr:full":"Hof 69 Kirchberg an der Raab Steiermark 8324",
    "addr:housenumber":"69",
    "addr:postcode":"8324",
    "addr:street":"Hof",
    "iso:country":"AT",
    "sg:address":"Hof 69",
    "sg:city":"Kirchberg an der Raab",
    "sg:orig_category":"Fenster",
    "sg:phone":"+43 4331 153090",
    "sg:postcode":"8324",
    "sg:province":"Steiermark",
    "wof:name":"Actual-Fenster Leitgeb",
    "wof:placetype":"venue"
},
  "geometry": {"coordinates":[15.7469596863,46.9772911072],"type":"Point"}
}