{
  "type": "Feature",
  "properties": {
    "addr:full":"Poschacherstr 6 Mauthausen Ober\u00f6sterreich 4310",
    "addr:housenumber":"6",
    "addr:postcode":"4310",
    "addr:street":"Poschacherstr",
    "iso:country":"AT",
    "sg:address":"Poschacherstr 6",
    "sg:city":"Mauthausen",
    "sg:orig_category":"Textilwaren / Einzelhandel",
    "sg:phone":"+43 7238 5448",
    "sg:postcode":"4310",
    "sg:province":"Ober\u00f6sterreich",
    "wof:name":"TPS",
    "wof:placetype":"venue"
},
  "geometry": {"coordinates":[14.5265808105,48.2401733398],"type":"Point"}
}