{
  "type": "Feature",
  "properties": {
    "iso:country":"AT",
    "sg:address":"Winten 29",
    "sg:city":"Geinberg",
    "sg:orig_category":"Appartements / Ferienwohnungen",
    "sg:phone":"+43 664 2135181",
    "sg:postcode":"4943",
    "sg:province":"Ober\u00f6sterreich",
    "wof:name":"Ferienhaus In der Winten",
    "wof:placetype":"venue"
},
  "geometry": {"coordinates":[13.3019104004,48.265171051],"type":"Point"}
}