{
  "type": "Feature",
  "properties": {
    "iso:country":"AT",
    "sg:address":"Brockmanng 69",
    "sg:city":"Graz",
    "sg:orig_category":"Schneidereien",
    "sg:phone":"+43 650 3209810",
    "sg:postcode":"8010",
    "sg:province":"Steiermark",
    "wof:name":"Peserl Eduard",
    "wof:placetype":"venue"
},
  "geometry": {"coordinates":[15.4458665848,47.0625839233],"type":"Point"}
}