{
  "type": "Feature",
  "properties": {
    "addr:full":"Burgweg 1 Hausmening Nieder\u00f6sterreich 3363",
    "addr:housenumber":"1",
    "addr:postcode":"3363",
    "addr:street":"Burgweg",
    "iso:country":"AT",
    "sg:address":"Burgweg 1",
    "sg:city":"Hausmening",
    "sg:orig_category":"Museen / Ausstellungen",
    "sg:phone":"+43 7475 54037",
    "sg:postcode":"3363",
    "sg:province":"Nieder\u00f6sterreich",
    "wof:name":"Schlo\u00df Ulmerfeld",
    "wof:placetype":"venue"
},
  "geometry": {"coordinates":[14.816365242,48.0766716003],"type":"Point"}
}