{
  "type": "Feature",
  "properties": {
    "addr:full":"M\u00f6\u00dflg 5 Innsbruck Tirol 6020",
    "addr:housenumber":"5",
    "addr:postcode":"6020",
    "addr:street":"Moesslg;Tirol",
    "iso:country":"AT",
    "sg:address":"M\u00f6\u00dflg 5",
    "sg:city":"Innsbruck",
    "sg:orig_category":"Architekten",
    "sg:phone":"+43 512 342035",
    "sg:postcode":"6020",
    "sg:province":"Tirol",
    "wof:name":"Neubauer Thomas Dipl-Ing",
    "wof:placetype":"venue"
},
  "geometry": {"coordinates":[11.3913040161,47.2679977417],"type":"Point"}
}