{
  "type": "Feature",
  "properties": {
    "addr:full":"Peter Rosegger-Str 212 Stainach Steiermark 8950",
    "addr:housenumber":"212",
    "addr:postcode":"8950",
    "iso:country":"AT",
    "sg:address":"Peter Rosegger-Str 212",
    "sg:city":"Stainach",
    "sg:orig_category":"Bauunternehmen",
    "sg:phone":"+43 4336 82222650",
    "sg:postcode":"8950",
    "sg:province":"Steiermark",
    "wof:name":"Wildbach- u Lawinenverbauung Gebietsbaultg Oberes Ennstal",
    "wof:placetype":"venue"
},
  "geometry": {"coordinates":[14.1162147522,47.5335426331],"type":"Point"}
}