{
  "type": "Feature",
  "properties": {
    "iso:country":"AT",
    "sg:address":"Friedhofstr 10",
    "sg:city":"Braunau am Inn",
    "sg:orig_category":"Blumeneinzelhandel",
    "sg:phone":"+43 7722 63326",
    "sg:postcode":"5280",
    "sg:province":"Ober\u00f6sterreich",
    "wof:name":"Blumen Felber",
    "wof:placetype":"venue"
},
  "geometry": {"coordinates":[13.0328931808,48.252620697],"type":"Point"}
}