{
  "type": "Feature",
  "properties": {
    "addr:full":"Eferdinger Str 17 Wilhering Ober\u00f6sterreich 4073",
    "addr:housenumber":"17",
    "addr:postcode":"4073",
    "addr:street":"Str",
    "iso:country":"AT",
    "sg:address":"Eferdinger Str 17",
    "sg:city":"Wilhering",
    "sg:classifiers":[
        {
            "category":"Internet Cafe",
            "subcategory":"None",
            "type":"Food & Drink"
        }
    ],
    "sg:phone":"+43 7226 20569",
    "sg:postcode":"4073",
    "sg:province":"Ober\u00f6sterreich",
    "wof:name":"x-technik IT & Medien GmbH",
    "wof:placetype":"venue"
},
  "geometry": {"coordinates":[14.1717643738,48.3103752136],"type":"Point"}
}