{
  "type": "Feature",
  "properties": {
    "addr:full":"Dietmar v Aist-Str 4 Schwertberg Ober\u00f6sterreich 4311",
    "addr:housenumber":"4",
    "addr:postcode":"4311",
    "addr:street":"Aist-Str",
    "iso:country":"AT",
    "sg:address":"Dietmar v Aist-Str 4",
    "sg:city":"Schwertberg",
    "sg:orig_category":"Bekleidung / Einzelhandel",
    "sg:phone":"+43 7262 61230",
    "sg:postcode":"4311",
    "sg:province":"Ober\u00f6sterreich",
    "wof:name":"Kutsam GesmbH & Co KG",
    "wof:placetype":"venue"
},
  "geometry": {"coordinates":[14.5817127228,48.2739906311],"type":"Point"}
}