{
  "type": "Feature",
  "properties": {
    "addr:full":"Schulg 3 Andau Burgenland 7163",
    "addr:housenumber":"3",
    "addr:postcode":"7163",
    "addr:street":"Schulg",
    "iso:country":"AT",
    "sg:address":"Schulg 3",
    "sg:city":"Andau",
    "sg:orig_category":"Volksschulen",
    "sg:phone":"+43 4321 762963",
    "sg:postcode":"7163",
    "sg:province":"Burgenland",
    "wof:name":"Volksschule",
    "wof:placetype":"venue"
},
  "geometry": {"coordinates":[17.0308303833,47.7739295959],"type":"Point"}
}