{
  "type": "Feature",
  "properties": {
    "iso:country":"AT",
    "sg:address":"Pfarrg 677",
    "sg:city":"Schladming",
    "sg:orig_category":"Apotheken",
    "sg:phone":"+43 4336 87225770",
    "sg:postcode":"8970",
    "sg:province":"Steiermark",
    "wof:name":"Edelwei\u00df-Apotheke Magpharm Vera Ottowitz",
    "wof:placetype":"venue"
},
  "geometry": {"coordinates":[13.6869354248,47.3917236328],"type":"Point"}
}