{
  "type": "Feature",
  "properties": {
    "addr:full":"Klaus-Weiler Vorarlberg 6833",
    "addr:postcode":"6833",
    "iso:country":"AT",
    "sg:city":"Klaus-Weiler",
    "sg:orig_category":"Feuerwehren",
    "sg:phone":"+43 5523 576600",
    "sg:postcode":"6833",
    "sg:province":"Vorarlberg",
    "wof:name":"Feuerwehr Klaus",
    "wof:placetype":"venue"
},
  "geometry": {"coordinates":[9.6465816498,47.3089485168],"type":"Point"}
}