{
  "type": "Feature",
  "properties": {
    "addr:full":"Schwarzenbergpl 10 Wien Wien 1040",
    "addr:housenumber":"10",
    "addr:postcode":"1040",
    "addr:street":"Schwarzenbergpl",
    "iso:country":"AT",
    "sg:address":"Schwarzenbergpl 10",
    "sg:city":"Wien",
    "sg:orig_category":"Unternehmensberatung",
    "sg:phone":"+43 4315 055708",
    "sg:postcode":"1040",
    "sg:province":"Wien",
    "wof:name":"I.T.P.S. International Trade Promotion Services GmbH",
    "wof:placetype":"venue"
},
  "geometry": {"coordinates":[16.3749294281,48.1976585388],"type":"Point"}
}