{
  "type": "Feature",
  "properties": {
    "addr:full":"Kehlerm\u00e4hder 2 Dornbirn Vorarlberg 6850",
    "addr:housenumber":"2",
    "addr:postcode":"6850",
    "addr:street":"Kehlermaehder",
    "iso:country":"AT",
    "sg:address":"Kehlerm\u00e4hder 2",
    "sg:city":"Dornbirn",
    "sg:orig_category":"Behinderungen / Leben Mit Behinderungen",
    "sg:phone":"+43 5572 238550",
    "sg:postcode":"6850",
    "sg:province":"Vorarlberg",
    "wof:name":"Lebenshilfe Dornbirn - Werkst\u00e4tten",
    "wof:placetype":"venue"
},
  "geometry": {"coordinates":[9.7503166199,47.4241600037],"type":"Point"}
}