{
  "type": "Feature",
  "properties": {
    "addr:full":"Peterspl. 1  Wien Wien 1010",
    "addr:housenumber":"1",
    "addr:postcode":"1010",
    "addr:street":"Peterspl.",
    "iso:country":"AT",
    "sg:address":"Peterspl. 1 ",
    "sg:city":"Wien",
    "sg:classifiers":[
        {
            "category":"Food & Beverages",
            "subcategory":"Dairy",
            "type":"Retail Goods"
        }
    ],
    "sg:phone":"+43 4315 339096",
    "sg:postcode":"1010",
    "sg:province":"Wien",
    "sg:tags":[
        "product"
    ],
    "wof:name":"WEISSHAPPEL KG",
    "wof:placetype":"venue"
},
  "geometry": {"coordinates":[16.3701019287,48.2091903687],"type":"Point"}
}