{
  "type": "Feature",
  "properties": {
    "addr:full":"Nu\u00dfdorfer Strasse 3/15 Wien Wien 1090",
    "addr:housenumber":"3 / 15",
    "addr:postcode":"1090",
    "addr:street":"Nussdorfer Strasse",
    "iso:country":"AT",
    "sg:address":"Nu\u00dfdorfer Strasse 3/15",
    "sg:city":"Wien",
    "sg:classifiers":[
        {
            "category":"Professional",
            "subcategory":"Art Services",
            "type":"Services"
        }
    ],
    "sg:phone":"+43 1 3194864",
    "sg:postcode":"1090",
    "sg:province":"Wien",
    "sg:tags":[
        "stand",
        "construction",
        "exhibition",
        "fair",
        "trade"
    ],
    "sg:website":"hsinnovation.com",
    "wof:name":"HS Innovation Public Relations Consulting GmbH",
    "wof:placetype":"venue"
},
  "geometry": {"coordinates":[16.3531532288,48.2225227356],"type":"Point"}
}