{
  "type": "Feature",
  "properties": {
    "addr:full":"Kreuzg 2 Kufstein Tirol 6330",
    "addr:housenumber":"2",
    "addr:postcode":"6330",
    "addr:street":"Kreuzg;Tirol",
    "iso:country":"AT",
    "sg:address":"Kreuzg 2",
    "sg:city":"Kufstein",
    "sg:orig_category":"Notare",
    "sg:phone":"+43 5372 62363",
    "sg:postcode":"6330",
    "sg:province":"Tirol",
    "wof:name":"Mader Helmut Dr",
    "wof:placetype":"venue"
},
  "geometry": {"coordinates":[12.171872139,47.5832099915],"type":"Point"}
}