{
  "type": "Feature",
  "properties": {
    "addr:full":"Kroneng 6 Schruns Vorarlberg 6780",
    "addr:housenumber":"6",
    "addr:postcode":"6780",
    "addr:street":"Kroneng",
    "iso:country":"AT",
    "sg:address":"Kroneng 6",
    "sg:city":"Schruns",
    "sg:orig_category":"Ingenieurkonsulenten / Zivilingenieure",
    "sg:phone":"+43 5556 720020",
    "sg:postcode":"6780",
    "sg:province":"Vorarlberg",
    "wof:name":"GEOGNOS Bertle Technische Geologie Ziviltechniker GmbH",
    "wof:placetype":"venue"
},
  "geometry": {"coordinates":[9.9184808731,47.0812530518],"type":"Point"}
}