{
  "type": "Feature",
  "properties": {
    "addr:full":"Hauptstr 11 Ried im Traunkreis Ober\u00f6sterreich 4551",
    "addr:housenumber":"11",
    "addr:postcode":"4551",
    "addr:street":"Hauptstr",
    "iso:country":"AT",
    "sg:address":"Hauptstr 11",
    "sg:city":"Ried im Traunkreis",
    "sg:orig_category":"Autoreparatur",
    "sg:phone":"+43 7588 7231",
    "sg:postcode":"4551",
    "sg:province":"Ober\u00f6sterreich",
    "wof:name":"Kammerhuber Fritz",
    "wof:placetype":"venue"
},
  "geometry": {"coordinates":[14.0745429993,48.0232276917],"type":"Point"}
}