{
  "type": "Feature",
  "properties": {
    "addr:full":"Michael-Pacher-Str 36 Salzburg Salzburg 5020",
    "addr:housenumber":"36",
    "addr:postcode":"5020",
    "addr:street":"Michael-Pacher-Str;Salzburg",
    "iso:country":"AT",
    "sg:address":"Michael-Pacher-Str 36",
    "sg:city":"Salzburg",
    "sg:orig_category":"Non-Classified Establishments",
    "sg:phone":"+43 662 80420",
    "sg:postcode":"5020",
    "sg:province":"Salzburg",
    "wof:name":"Landesregierung Salzburg - Fachabteilung Hochbau",
    "wof:placetype":"venue"
},
  "geometry": {"coordinates":[13.0635061264,47.7887992859],"type":"Point"}
}