{
  "type": "Feature",
  "properties": {
    "iso:country":"AT",
    "sg:address":"Gumpendorfer Str 88",
    "sg:city":"Wien",
    "sg:orig_category":"Friseure U Frisiersalons",
    "sg:phone":"+43 4315 955147",
    "sg:postcode":"1060",
    "sg:province":"Wien",
    "wof:name":"Jederman Friseur GmbH",
    "wof:placetype":"venue"
},
  "geometry": {"coordinates":[16.3483963013,48.192401886],"type":"Point"}
}