{
  "type": "Feature",
  "properties": {
    "addr:full":"St. Martin 13 Hall in Tirol Tirol 6060",
    "addr:housenumber":"13",
    "addr:postcode":"6060",
    "addr:street":"St. Martin;Tirol",
    "iso:country":"AT",
    "sg:address":"St. Martin 13",
    "sg:city":"Hall in Tirol",
    "sg:orig_category":"Tischlereien",
    "sg:phone":"+43 5223 42281",
    "sg:postcode":"6060",
    "sg:province":"Tirol",
    "wof:name":"Unterberger Albert",
    "wof:placetype":"venue"
},
  "geometry": {"coordinates":[11.5566759109,47.3188285828],"type":"Point"}
}