{
  "type": "Feature",
  "properties": {
    "iso:country":"AT",
    "sg:address":"St. Martin 13",
    "sg:city":"Hall in Tirol",
    "sg:orig_category":"Tischlereien",
    "sg:phone":"+43 5223 42281",
    "sg:postcode":"6060",
    "sg:province":"Tirol",
    "wof:name":"Unterberger Albert",
    "wof:placetype":"venue"
},
  "geometry": {"coordinates":[11.5566759109,47.3188285828],"type":"Point"}
}