{
  "type": "Feature",
  "properties": {
    "addr:full":"Thalheimer Str 59 Thalheim Steiermark 8754",
    "addr:postcode":"8754",
    "addr:street":"Str 59",
    "iso:country":"AT",
    "sg:address":"Thalheimer Str 59",
    "sg:city":"Thalheim",
    "sg:orig_category":"Elektroinstallationsunternehmen",
    "sg:phone":"+43 3579 20500",
    "sg:postcode":"8754",
    "sg:province":"Steiermark",
    "wof:name":"Moder Elektrotechnik",
    "wof:placetype":"venue"
},
  "geometry": {"coordinates":[14.5945138931,47.1941795349],"type":"Point"}
}