{
  "type": "Feature",
  "properties": {
    "addr:full":"Walgaustr 48 Bludesch Vorarlberg 6719",
    "addr:housenumber":"48",
    "addr:postcode":"6719",
    "addr:street":"Walgaustr",
    "iso:country":"AT",
    "sg:address":"Walgaustr 48",
    "sg:city":"Bludesch",
    "sg:orig_category":"Automaten",
    "sg:phone":"+43 5525 63355",
    "sg:postcode":"6719",
    "sg:province":"Vorarlberg",
    "wof:name":"H\u00e4mmerle Kaffee GmbH",
    "wof:placetype":"venue"
},
  "geometry": {"coordinates":[9.726064682,47.197479248],"type":"Point"}
}