{
  "type": "Feature",
  "properties": {
    "addr:full":"Reichenauer Str 80 Innsbruck Tirol 6020",
    "addr:postcode":"6020",
    "addr:street":"Str 80;Tirol",
    "iso:country":"AT",
    "sg:address":"Reichenauer Str 80",
    "sg:city":"Innsbruck",
    "sg:classifiers":[
        {
            "category":"Shopping",
            "subcategory":"Thrift Store",
            "type":"Retail Goods"
        }
    ],
    "sg:phone":"+43 512 391559",
    "sg:postcode":"6020",
    "sg:province":"Tirol",
    "sg:tags":[
        "second-hand-shops"
    ],
    "wof:name":"KLAMOTTE Second-Hand-Sammelstelle",
    "wof:placetype":"venue"
},
  "geometry": {"coordinates":[11.4180145264,47.2742347717],"type":"Point"}
}