{
  "type": "Feature",
  "properties": {
    "addr:full":"Bahnhofstr 27 Rankweil Vorarlberg 6830",
    "addr:postcode":"6830",
    "addr:street":"Bahnhofstr 27",
    "iso:country":"AT",
    "sg:address":"Bahnhofstr 27",
    "sg:city":"Rankweil",
    "sg:orig_category":"Bars-Cafes",
    "sg:phone":"+43 5522 46272",
    "sg:postcode":"6830",
    "sg:province":"Vorarlberg",
    "wof:name":"Bar-Bistro-Gw\u00f6lb H\u00f6rnlingen",
    "wof:placetype":"venue"
},
  "geometry": {"coordinates":[9.6386470795,47.2715377808],"type":"Point"}
}