{
  "type": "Feature",
  "properties": {
    "addr:full":"Wiener Str 13 Korneuburg Nieder\u00f6sterreich 2100",
    "addr:postcode":"2100",
    "addr:street":"Niederoesterreich",
    "iso:country":"AT",
    "sg:address":"Wiener Str 13",
    "sg:city":"Korneuburg",
    "sg:orig_category":"Restaurants: Chinesisch",
    "sg:phone":"+43 2262 61486",
    "sg:postcode":"2100",
    "sg:province":"Nieder\u00f6sterreich",
    "wof:name":"China-Restaurant z Mandarin",
    "wof:placetype":"venue"
},
  "geometry": {"coordinates":[16.3363609314,48.3411102295],"type":"Point"}
}