{
  "type": "Feature",
  "properties": {
    "addr:full":"Naaffgasse 6 Wien Wien 1180",
    "addr:housenumber":"6",
    "addr:postcode":"1180",
    "addr:street":"Naaffgasse",
    "iso:country":"AT",
    "sg:address":"Naaffgasse 6",
    "sg:city":"Wien",
    "sg:classifiers":[
        {
            "category":"Wholesale",
            "subcategory":"Durable Goods & Equipment",
            "type":"Manufacturing & Wholesale Goods"
        }
    ],
    "sg:phone":"+43 1 47933650",
    "sg:postcode":"1180",
    "sg:province":"Wien",
    "sg:tags":[
        "silencer",
        "industrial"
    ],
    "wof:name":"Dipl.-Ing. N. Buch GmbH",
    "wof:placetype":"venue"
},
  "geometry": {"coordinates":[16.3133811951,48.2327575684],"type":"Point"}
}