{
  "type": "Feature",
  "properties": {
    "iso:country":"AT",
    "sg:address":"Klosterneuburger Str 58",
    "sg:city":"Wien",
    "sg:orig_category":"Unterhaltungselektronik / Reparatur",
    "sg:phone":"+43 1 3303684",
    "sg:postcode":"1200",
    "sg:province":"Wien",
    "wof:name":"Unel Service Johann Pulker",
    "wof:placetype":"venue"
},
  "geometry": {"coordinates":[16.3663921356,48.2321205139],"type":"Point"}
}