{
  "type": "Feature",
  "properties": {
    "addr:full":"Goldegg 26 Wien Wien 1040",
    "addr:housenumber":"26",
    "addr:postcode":"1040",
    "addr:street":"Goldegg",
    "iso:country":"AT",
    "sg:address":"Goldegg 26",
    "sg:city":"Wien",
    "sg:orig_category":"Handelsagenturen",
    "sg:phone":"+43 664 1607669",
    "sg:postcode":"1040",
    "sg:province":"Wien",
    "wof:name":"Gisch G\u00fcnter",
    "wof:placetype":"venue"
},
  "geometry": {"coordinates":[16.3754348755,48.1895599365],"type":"Point"}
}