{
  "type": "Feature",
  "properties": {
    "iso:country":"AT",
    "sg:address":"Deniflestr 7",
    "sg:city":"Fulpmes",
    "sg:classifiers":[
        {
            "category":"Travel",
            "subcategory":"Hotels & Motels",
            "type":"Entertainment"
        }
    ],
    "sg:phone":"+43 5225 63774",
    "sg:postcode":"6166",
    "sg:province":"Tirol",
    "wof:name":"Hotel-Cafe-Restaurant Medrazerhof",
    "wof:placetype":"venue"
},
  "geometry": {"coordinates":[11.3423585892,47.1420440674],"type":"Point"}
}