{
  "type": "Feature",
  "properties": {
    "iso:country":"AT",
    "sg:address":"Lassallestrasse 30",
    "sg:city":"Wien",
    "sg:orig_category":"Canalisation",
    "sg:phone":"+43 1 7263514",
    "sg:postcode":"1020",
    "sg:province":"Wien",
    "sg:website":"members.chello.at/ahmet.bulduk",
    "wof:name":"Ahmet Bulduk Ges.m.b.H.",
    "wof:placetype":"venue"
},
  "geometry": {"coordinates":[16.3996124268,48.2225837708],"type":"Point"}
}