{
  "type": "Feature",
  "properties": {
    "iso:country":"AT",
    "sg:address":"Hauptstr 36",
    "sg:city":"Nikitsch",
    "sg:orig_category":"Banken U Sparkassen",
    "sg:phone":"+43 4326 148252",
    "sg:postcode":"7302",
    "sg:province":"Burgenland",
    "wof:name":"Raiffeisenkasse Deutschkreutz-Nikitsch regGenmbH",
    "wof:placetype":"venue"
},
  "geometry": {"coordinates":[16.6446266174,47.5252189636],"type":"Point"}
}