{
  "type": "Feature",
  "properties": {
    "addr:full":"Leharg 1 Wien Wien 1060",
    "addr:housenumber":"1",
    "addr:postcode":"1060",
    "addr:street":"Leharg",
    "iso:country":"AT",
    "sg:address":"Leharg 1",
    "sg:city":"Wien",
    "sg:classifiers":[
        {
            "category":"Restaurant",
            "type":"Food & Drink"
        }
    ],
    "sg:phone":"+43 1 5856395",
    "sg:postcode":"1060",
    "sg:province":"Wien",
    "wof:name":"Saigon",
    "wof:placetype":"venue"
},
  "geometry": {"coordinates":[16.3643302917,48.2006187439],"type":"Point"}
}