{
  "type": "Feature",
  "properties": {
    "addr:full":"Druckereistr 12 Gmunden Ober\u00f6sterreich 4810",
    "addr:housenumber":"12",
    "addr:postcode":"4810",
    "addr:street":"Druckereistr;Oberoesterreich",
    "iso:country":"AT",
    "sg:address":"Druckereistr 12",
    "sg:city":"Gmunden",
    "sg:orig_category":"Blumeneinzelhandel",
    "sg:phone":"+43 4366 41411941",
    "sg:postcode":"4810",
    "sg:province":"Ober\u00f6sterreich",
    "wof:name":"Michaela's Rosenshop",
    "wof:placetype":"venue"
},
  "geometry": {"coordinates":[13.7895030975,47.9257774353],"type":"Point"}
}