{
  "type": "Feature",
  "properties": {
    "addr:full":"Simmeringstr 10 Silz Tirol 6424",
    "addr:housenumber":"10",
    "addr:postcode":"6424",
    "addr:street":"Simmeringstr;Tirol",
    "iso:country":"AT",
    "sg:address":"Simmeringstr 10",
    "sg:city":"Silz",
    "sg:classifiers":[
        {
            "category":"Restaurant",
            "type":"Food & Drink"
        }
    ],
    "sg:phone":"+43 4352 635583",
    "sg:postcode":"6424",
    "sg:province":"Tirol",
    "sg:website":"crazy-eddy.com",
    "wof:name":"Crazy Eddy Gastro GmbH",
    "wof:placetype":"venue"
},
  "geometry": {"coordinates":[10.9191551208,47.2708358765],"type":"Point"}
}