{
  "type": "Feature",
  "properties": {
    "addr:full":"Mariahilfstr 22b/11 Innsbruck Tirol 6020",
    "addr:housenumber":"22b / 11",
    "addr:postcode":"6020",
    "addr:street":"Mariahilfstr;Tirol",
    "iso:country":"AT",
    "sg:address":"Mariahilfstr 22b/11",
    "sg:city":"Innsbruck",
    "sg:orig_category":"Werbeagenturen",
    "sg:phone":"+43 512 940251",
    "sg:postcode":"6020",
    "sg:province":"Tirol",
    "wof:name":"factoryEC Kaltenhuber Kaufmann OEG - Marketing-Consulting - eBusiness",
    "wof:placetype":"venue"
},
  "geometry": {"coordinates":[11.3893289566,47.2684020996],"type":"Point"}
}