{
  "type": "Feature",
  "properties": {
    "addr:full":"Stadtpl 1 Radstadt Salzburg 5550",
    "addr:housenumber":"1",
    "addr:postcode":"5550",
    "addr:street":"Stadtpl;Salzburg",
    "iso:country":"AT",
    "sg:address":"Stadtpl 1",
    "sg:city":"Radstadt",
    "sg:orig_category":"Polizei U Gendarmerie",
    "sg:phone":"+43 4359 1335151",
    "sg:postcode":"5550",
    "sg:province":"Salzburg",
    "wof:name":"Gendarmerieposten Radtstadt",
    "wof:placetype":"venue"
},
  "geometry": {"coordinates":[13.4624633789,47.3849639893],"type":"Point"}
}