{
  "type": "Feature",
  "properties": {
    "iso:country":"AT",
    "sg:address":"Nr 280",
    "sg:city":"Bad Waltersdorf",
    "sg:orig_category":"Pensionen / Privatzimmer",
    "sg:phone":"+43 4333 333100",
    "sg:postcode":"8271",
    "sg:province":"Steiermark",
    "wof:name":"G\u00e4stehaus Lind",
    "wof:placetype":"venue"
},
  "geometry": {"coordinates":[16.0086784363,47.1696166992],"type":"Point"}
}