{
  "type": "Feature",
  "properties": {
    "addr:full":"Winklern 9 Winklern K\u00e4rnten 9841",
    "addr:housenumber":"9",
    "addr:postcode":"9841",
    "addr:street":"Winklern;Kaernten",
    "iso:country":"AT",
    "sg:address":"Winklern 9",
    "sg:city":"Winklern",
    "sg:orig_category":"Reisen, Tourismusinfo",
    "sg:phone":"+43 4822",
    "sg:postcode":"9841",
    "sg:province":"K\u00e4rnten",
    "sg:website":"http://tiscover.com/winklern",
    "wof:name":"Fremdenverkehrsamt Winklern",
    "wof:placetype":"venue"
},
  "geometry": {"coordinates":[12.876115799,46.8697662354],"type":"Point"}
}