{
  "type": "Feature",
  "properties": {
    "addr:full":"Am Weiher 3 Wolfsberg K\u00e4rnten 9400",
    "addr:housenumber":"3;kaernten",
    "addr:postcode":"9400",
    "addr:street":"Am Weiher",
    "iso:country":"AT",
    "sg:address":"Am Weiher 3",
    "sg:city":"Wolfsberg",
    "sg:orig_category":"Fleischhauereien",
    "sg:phone":"+43 4343 522612",
    "sg:postcode":"9400",
    "sg:province":"K\u00e4rnten",
    "wof:name":"Trettenbrein Fleischhauerei GesmbH & Co KG",
    "wof:placetype":"venue"
},
  "geometry": {"coordinates":[14.8406019211,46.8403167725],"type":"Point"}
}