{
  "type": "Feature",
  "properties": {
    "addr:full":"Obere L\u00e4nde 7 Frastanz Vorarlberg 6820",
    "addr:housenumber":"7",
    "addr:postcode":"6820",
    "addr:street":"Obere Laende",
    "iso:country":"AT",
    "sg:address":"Obere L\u00e4nde 7",
    "sg:city":"Frastanz",
    "sg:orig_category":"Betten",
    "sg:phone":"+43 4355 22535000",
    "sg:postcode":"6820",
    "sg:province":"Vorarlberg",
    "sg:website":"samina.at",
    "wof:name":"SAMINA Produktions- u Handels GmbH",
    "wof:placetype":"venue"
},
  "geometry": {"coordinates":[9.6292104721,47.2186813354],"type":"Point"}
}