{
  "type": "Feature",
  "properties": {
    "addr:full":"Prinz-Eugen-Str 72 Innsbruck Tirol 6020",
    "addr:housenumber":"72",
    "addr:postcode":"6020",
    "addr:street":"Prinz-Eugen-Str;Tirol",
    "iso:country":"AT",
    "sg:address":"Prinz-Eugen-Str 72",
    "sg:city":"Innsbruck",
    "sg:orig_category":"Freizeit- U Sportbekleidung",
    "sg:phone":"+43 4351 2344378",
    "sg:postcode":"6020",
    "sg:province":"Tirol",
    "wof:name":"California Shop",
    "wof:placetype":"venue"
},
  "geometry": {"coordinates":[11.4135074615,47.272693634],"type":"Point"}
}