{
  "type": "Feature",
  "properties": {
    "addr:full":"Gaisbachstr 23 Rauris Salzburg 5661",
    "addr:housenumber":"23",
    "addr:postcode":"5661",
    "addr:street":"Gaisbachstr;Salzburg",
    "iso:country":"AT",
    "sg:address":"Gaisbachstr 23",
    "sg:city":"Rauris",
    "sg:orig_category":"Pensionen / Privatzimmer",
    "sg:phone":"+43 4365 446315",
    "sg:postcode":"5661",
    "sg:province":"Salzburg",
    "wof:name":"Moser-Meiling Pension",
    "wof:placetype":"venue"
},
  "geometry": {"coordinates":[12.9976863861,47.2297096252],"type":"Point"}
}