{
  "type": "Feature",
  "properties": {
    "iso:country":"AT",
    "sg:address":"Hermann-Gebauer-Str 18",
    "sg:city":"Wien",
    "sg:orig_category":"Fische U Fischwaren / Erzeugung U Gro\u00c3\u0178handel",
    "sg:phone":"+43 4317 32130",
    "sg:postcode":"1220",
    "sg:province":"Wien",
    "wof:name":"Nordsee GesmbH",
    "wof:placetype":"venue"
},
  "geometry": {"coordinates":[16.4737262726,48.2652931213],"type":"Point"}
}