{
  "type": "Feature",
  "properties": {
    "addr:full":"Porzellang 14-16 Wien Wien 1090",
    "addr:postcode":"14-16;1090",
    "addr:street":"Porzellang",
    "iso:country":"AT",
    "sg:address":"Porzellang 14-16",
    "sg:city":"Wien",
    "sg:orig_category":"Lebensmittelmaschinen",
    "sg:phone":"+43 1 3176170",
    "sg:postcode":"1090",
    "sg:province":"Wien",
    "wof:name":"Vogel Ernst",
    "wof:placetype":"venue"
},
  "geometry": {"coordinates":[16.3618984222,48.2199478149],"type":"Point"}
}