{
  "type": "Feature",
  "properties": {
    "iso:country":"AT",
    "sg:address":"Millennium Park 4",
    "sg:city":"Lustenau",
    "sg:orig_category":"Marketingberatung",
    "sg:phone":"+43 4355 7762359",
    "sg:postcode":"6890",
    "sg:province":"Vorarlberg",
    "wof:name":"Spo.nsoring-T.eam Spo.T.Bilgeri & Ettinger OEG",
    "wof:placetype":"venue"
},
  "geometry": {"coordinates":[9.6712684631,47.4202842712],"type":"Point"}
}