{
  "type": "Feature",
  "properties": {
    "addr:full":"Dornauberg 38 Ginzling Tirol 6295",
    "addr:housenumber":"38",
    "addr:postcode":"6295",
    "addr:street":"Dornauberg",
    "iso:country":"AT",
    "sg:address":"Dornauberg 38",
    "sg:city":"Ginzling",
    "sg:orig_category":"Mietautos",
    "sg:phone":"+43 4366 41029354",
    "sg:postcode":"6295",
    "sg:province":"Tirol",
    "wof:name":"Fankhauser Max",
    "wof:placetype":"venue"
},
  "geometry": {"coordinates":[11.8085803986,47.1002845764],"type":"Point"}
}