{
  "type": "Feature",
  "properties": {
    "addr:full":"Ga\u00dfl 2 Friedburg Ober\u00f6sterreich 5211",
    "addr:housenumber":"2",
    "addr:postcode":"5211",
    "addr:street":"Gassl",
    "iso:country":"AT",
    "sg:address":"Ga\u00dfl 2",
    "sg:city":"Friedburg",
    "sg:orig_category":"Autohandel",
    "sg:phone":"+43 7746 22890",
    "sg:postcode":"5211",
    "sg:province":"Ober\u00f6sterreich",
    "wof:name":"Toyota Karrer GmbH",
    "wof:placetype":"venue"
},
  "geometry": {"coordinates":[13.2165813446,48.0067062378],"type":"Point"}
}