{
  "type": "Feature",
  "properties": {
    "iso:country":"AT",
    "sg:address":"Walzeng 29/2",
    "sg:city":"Perchtoldsdorf",
    "sg:orig_category":"Physiotherapie",
    "sg:phone":"+43 1 8659956",
    "sg:postcode":"2380",
    "sg:province":"Nieder\u00f6sterreich",
    "wof:name":"Team G S B Gerald Gretzl",
    "wof:placetype":"venue"
},
  "geometry": {"coordinates":[16.2604122162,48.1220245361],"type":"Point"}
}