{
  "type": "Feature",
  "properties": {
    "iso:country":"AT",
    "sg:address":"Radfeld 12a Rettenbach ",
    "sg:city":"Kundl",
    "sg:classifiers":[
        {
            "category":"Banks & Credit Unions",
            "subcategory":"Investment Brokerage",
            "type":"Services"
        }
    ],
    "sg:phone":"+43 4353 388421",
    "sg:postcode":"6250",
    "sg:province":"Tirol",
    "sg:tags":[
        "-",
        "transport",
        "related"
    ],
    "wof:name":"EUROPATRANS TRANSPORTGES. MBH",
    "wof:placetype":"venue"
},
  "geometry": {"coordinates":[11.9853544235,47.4697036743],"type":"Point"}
}