{
  "type": "Feature",
  "properties": {
    "addr:full":"Kogler Str 8 Sieghartskirchen Nieder\u00f6sterreich 3443",
    "addr:housenumber":"8",
    "addr:postcode":"3443",
    "addr:street":"Str;Niederoesterreich",
    "iso:country":"AT",
    "sg:address":"Kogler Str 8",
    "sg:city":"Sieghartskirchen",
    "sg:orig_category":"Fleischhauereien",
    "sg:phone":"+43 2274 60810",
    "sg:postcode":"3443",
    "sg:province":"Nieder\u00f6sterreich",
    "wof:name":"Berger Fleischwaren GesmbH & Co KG",
    "wof:placetype":"venue"
},
  "geometry": {"coordinates":[16.0098209381,48.2445907593],"type":"Point"}
}