{
  "type": "Feature",
  "properties": {
    "addr:full":"Schererstr 6 Wetzelsdorf Steiermark 8052",
    "addr:housenumber":"6",
    "addr:postcode":"8052",
    "addr:street":"Schererstr",
    "iso:country":"AT",
    "sg:address":"Schererstr 6",
    "sg:city":"Wetzelsdorf",
    "sg:orig_category":"Werbeagenturen",
    "sg:phone":"+43 316 5740600",
    "sg:postcode":"8052",
    "sg:province":"Steiermark",
    "wof:name":"TR - Creativ",
    "wof:placetype":"venue"
},
  "geometry": {"coordinates":[15.3966712952,47.0565299988],"type":"Point"}
}