{
  "type": "Feature",
  "properties": {
    "addr:full":"Seitenbergg 25 Wien Wien 1160",
    "addr:housenumber":"25",
    "addr:postcode":"1160",
    "addr:street":"Seitenbergg",
    "iso:country":"AT",
    "sg:address":"Seitenbergg 25",
    "sg:city":"Wien",
    "sg:classifiers":[
        {
            "category":"Communications",
            "subcategory":"Film & Video Production",
            "type":"Services"
        }
    ],
    "sg:phone":"+43 4314 805588",
    "sg:postcode":"1160",
    "sg:province":"Wien",
    "sg:tags":[
        "multimedia"
    ],
    "wof:name":"Metalogic",
    "wof:placetype":"venue"
},
  "geometry": {"coordinates":[16.3122406006,48.2167510986],"type":"Point"}
}