{
  "type": "Feature",
  "properties": {
    "iso:country":"AT",
    "sg:address":"Dr Neumann-G 1/1",
    "sg:city":"Wien",
    "sg:orig_category":"\u00c3\u201erzte / F Allgemeinmedizin",
    "sg:phone":"+43 664 1228121",
    "sg:postcode":"1230",
    "sg:province":"Wien",
    "wof:name":"Kopta Hannelore Dr",
    "wof:placetype":"venue"
},
  "geometry": {"coordinates":[16.287612915,48.1379470825],"type":"Point"}
}