{
  "type": "Feature",
  "properties": {
    "addr:full":"Breitenfurter Str 338 Wien Wien 1230",
    "addr:housenumber":"338",
    "addr:postcode":"1230",
    "addr:street":"Str",
    "iso:country":"AT",
    "sg:address":"Breitenfurter Str 338",
    "sg:city":"Wien",
    "sg:orig_category":"Bandagen U Bandagisten",
    "sg:phone":"+43 1 86594540",
    "sg:postcode":"1230",
    "sg:province":"Wien",
    "wof:name":"S.O.B. - Kerkoc Sanit\u00e4tsfachgesch\u00e4ft Orthop\u00e4die Bandagist GesmbH",
    "wof:placetype":"venue"
},
  "geometry": {"coordinates":[16.2875766754,48.1379051208],"type":"Point"}
}