{
  "type": "Feature",
  "properties": {
    "addr:full":"Industriegel\u00e4nde 8/Zone A Fulpmes Tirol 6166",
    "addr:housenumber":"8 / zone",
    "addr:postcode":"6166",
    "addr:street":"Industriegelaende;A Fulpmes",
    "iso:country":"AT",
    "sg:address":"Industriegel\u00e4nde 8/Zone A",
    "sg:city":"Fulpmes",
    "sg:orig_category":"Glasereien",
    "sg:phone":"+43 5225 626120",
    "sg:postcode":"6166",
    "sg:province":"Tirol",
    "wof:name":"REFI Reinhard Fiechtl Glaserei Spenglerei GmbH",
    "wof:placetype":"venue"
},
  "geometry": {"coordinates":[11.3487129211,47.1532936096],"type":"Point"}
}