{
  "type": "Feature",
  "properties": {
    "addr:full":"Kampl Gewerbezone 10 Neustift im Stubaital Tirol 6167",
    "addr:housenumber":"10",
    "addr:postcode":"6167",
    "addr:street":"Gewerbezone;Tirol",
    "iso:country":"AT",
    "sg:address":"Kampl Gewerbezone 10",
    "sg:city":"Neustift im Stubaital",
    "sg:orig_category":"Autoreparatur",
    "sg:phone":"+43 4352 262661",
    "sg:postcode":"6167",
    "sg:province":"Tirol",
    "wof:name":"Auto-Hofer GmbH",
    "wof:placetype":"venue"
},
  "geometry": {"coordinates":[11.3075504303,47.1104850769],"type":"Point"}
}