{
  "type": "Feature",
  "properties": {
    "addr:full":"W\u00e4hringer Str 87 Wien Wien 1180",
    "addr:postcode":"1180",
    "addr:street":"Str 87",
    "iso:country":"AT",
    "sg:address":"W\u00e4hringer Str 87",
    "sg:city":"Wien",
    "sg:orig_category":"Optiker",
    "sg:phone":"+43 1 4038550",
    "sg:postcode":"1180",
    "sg:province":"Wien",
    "wof:name":"Optik Bauer",
    "wof:placetype":"venue"
},
  "geometry": {"coordinates":[16.3461914062,48.2254829407],"type":"Point"}
}