{
  "type": "Feature",
  "properties": {
    "addr:full":"Zdarskystr 12 St. P\u00f6lten Nieder\u00f6sterreich 3100",
    "addr:housenumber":"12",
    "addr:postcode":"3100",
    "addr:street":"Zdarskystr",
    "iso:country":"AT",
    "sg:address":"Zdarskystr 12",
    "sg:city":"St. P\u00f6lten",
    "sg:orig_category":"Matten U Mattenvermietung",
    "sg:phone":"+43 2742 8818130",
    "sg:postcode":"3100",
    "sg:province":"Nieder\u00f6sterreich",
    "wof:name":"Salesianer Textilservice GmbH",
    "wof:placetype":"venue"
},
  "geometry": {"coordinates":[15.6240940094,48.2076377869],"type":"Point"}
}