{
  "type": "Feature",
  "properties": {
    "iso:country":"AT",
    "sg:address":"R\u00f6merstr 134",
    "sg:city":"Wels",
    "sg:classifiers":[
        {
            "category":"Taxi",
            "type":"Transportation"
        }
    ],
    "sg:phone":"+43 4372 42207200",
    "sg:postcode":"4600",
    "sg:province":"Ober\u00f6sterreich",
    "sg:tags":[
        "personentransporte",
        "u"
    ],
    "wof:name":"Taxi Stiefm\u00fcller",
    "wof:placetype":"venue"
},
  "geometry": {"coordinates":[13.9685125351,48.1398696899],"type":"Point"}
}