{
  "type": "Feature",
  "properties": {
    "addr:full":"Friedenssdlg 11 Pottenstein Nieder\u00f6sterreich 2563",
    "addr:housenumber":"11",
    "addr:postcode":"2563",
    "addr:street":"Friedenssdlg",
    "iso:country":"AT",
    "sg:address":"Friedenssdlg 11",
    "sg:city":"Pottenstein",
    "sg:orig_category":"Solartechnik",
    "sg:phone":"+43 4326 7282895",
    "sg:postcode":"2563",
    "sg:province":"Nieder\u00f6sterreich",
    "wof:name":"Bartu Christian",
    "wof:placetype":"venue"
},
  "geometry": {"coordinates":[16.3519897461,48.0015106201],"type":"Point"}
}