{
  "type": "Feature",
  "properties": {
    "addr:full":"Himmelstr 7 Wien Wien 1190",
    "addr:housenumber":"7",
    "addr:postcode":"1190",
    "addr:street":"Himmelstr",
    "iso:country":"AT",
    "sg:address":"Himmelstr 7",
    "sg:city":"Wien",
    "sg:orig_category":"Werbeartikel U -Geschenke",
    "sg:phone":"+43 4313 2091510",
    "sg:postcode":"1190",
    "sg:province":"Wien",
    "sg:website":"mitraco.com",
    "wof:name":"Mitraco Geschenkartikelvertrieb GesmbH",
    "wof:placetype":"venue"
},
  "geometry": {"coordinates":[16.3415145874,48.2557106018],"type":"Point"}
}