{
  "type": "Feature",
  "properties": {
    "addr:full":"Fasanstr 7 Maria Rain K\u00e4rnten 9161",
    "addr:housenumber":"7",
    "addr:postcode":"9161",
    "addr:street":"Fasanstr;Kaernten",
    "iso:country":"AT",
    "sg:address":"Fasanstr 7",
    "sg:city":"Maria Rain",
    "sg:orig_category":"Waren Aller Art",
    "sg:phone":"+43 664 2209905",
    "sg:postcode":"9161",
    "sg:province":"K\u00e4rnten",
    "wof:name":"PAROPA HandelsgesmbH",
    "wof:placetype":"venue"
},
  "geometry": {"coordinates":[14.2888050079,46.5651283264],"type":"Point"}
}