{
  "type": "Feature",
  "properties": {
    "addr:full":"Am Bergl 8 Imst Tirol 6460",
    "addr:housenumber":"8",
    "addr:postcode":"6460",
    "addr:street":"Am Bergl;Tirol",
    "iso:country":"AT",
    "sg:address":"Am Bergl 8",
    "sg:city":"Imst",
    "sg:orig_category":"Appartements / Ferienwohnungen",
    "sg:phone":"+43 5412 67298",
    "sg:postcode":"6460",
    "sg:province":"Tirol",
    "wof:name":"Falkner Anni",
    "wof:placetype":"venue"
},
  "geometry": {"coordinates":[10.7359685898,47.2447090149],"type":"Point"}
}