{
  "type": "Feature",
  "properties": {
    "iso:country":"AT",
    "sg:address":"Pottendorfer Str 144",
    "sg:city":"Wiener Neustadt",
    "sg:orig_category":"Waren Aller Art",
    "sg:phone":"+43 2622 82572",
    "sg:postcode":"2700",
    "sg:province":"Nieder\u00f6sterreich",
    "wof:name":"Birtalan OEG",
    "wof:placetype":"venue"
},
  "geometry": {"coordinates":[16.2650032043,47.8316993713],"type":"Point"}
}