{
  "type": "Feature",
  "properties": {
    "addr:full":"Leisnitzg 294 Tamsweg Salzburg 5580",
    "addr:housenumber":"294",
    "addr:postcode":"5580",
    "addr:street":"Tamsweg Salzburg",
    "iso:country":"AT",
    "sg:address":"Leisnitzg 294",
    "sg:city":"Tamsweg",
    "sg:orig_category":"Eisenwaren",
    "sg:phone":"+43 6474 22370",
    "sg:postcode":"5580",
    "sg:province":"Salzburg",
    "wof:name":"Hutegger & Co KG",
    "wof:placetype":"venue"
},
  "geometry": {"coordinates":[13.8090353012,47.1275100708],"type":"Point"}
}