{
  "type": "Feature",
  "properties": {
    "addr:full":"Wiener Str 159A Gumpoldskirchen Nieder\u00f6sterreich 2352",
    "addr:postcode":"2352",
    "addr:street":"Str 159A",
    "iso:country":"AT",
    "sg:address":"Wiener Str 159A",
    "sg:city":"Gumpoldskirchen",
    "sg:orig_category":"Garten- U Landschaftsgestaltung",
    "sg:phone":"+43 4365 06607269",
    "sg:postcode":"2352",
    "sg:province":"Nieder\u00f6sterreich",
    "wof:name":"Gosch Michael F. Dipl Ing - Permakultur-Beratung",
    "wof:placetype":"venue"
},
  "geometry": {"coordinates":[16.2916469574,48.039100647],"type":"Point"}
}