{
  "type": "Feature",
  "properties": {
    "iso:country":"AT",
    "sg:address":"Zinsgasse 503",
    "sg:city":"Tamsweg",
    "sg:classifiers":[
        {
            "category":"Transit Center",
            "subcategory":"Freight",
            "type":"Transportation"
        }
    ],
    "sg:phone":"+43 6474 2228",
    "sg:postcode":"5580",
    "sg:province":"Salzburg",
    "sg:tags":[
        "wood",
        "cnc-machining"
    ],
    "wof:name":"L\u00fcftenegger GmbH & Co KG",
    "wof:placetype":"venue"
},
  "geometry": {"coordinates":[13.803853035,47.133518219],"type":"Point"}
}