{
  "type": "Feature",
  "properties": {
    "addr:full":"M Eduard Angerer-Weg 52 St. Johann in Tirol Tirol 6380",
    "addr:housenumber":"52",
    "addr:postcode":"johann;6380",
    "addr:street":"Angerer-Weg;Tirol",
    "iso:country":"AT",
    "sg:address":"M Eduard Angerer-Weg 52",
    "sg:city":"St. Johann in Tirol",
    "sg:orig_category":"Pensionen / Privatzimmer",
    "sg:phone":"+43 5352 64306",
    "sg:postcode":"6380",
    "sg:province":"Tirol",
    "wof:name":"Pension Christl am Horn",
    "wof:placetype":"venue"
},
  "geometry": {"coordinates":[12.4375476837,47.5140724182],"type":"Point"}
}