{
  "type": "Feature",
  "properties": {
    "addr:full":"Wiener Str 3 Eugendorf Salzburg 5301",
    "addr:housenumber":"3",
    "addr:postcode":"5301",
    "addr:street":"Eugendorf Salzburg",
    "iso:country":"AT",
    "sg:address":"Wiener Str 3",
    "sg:city":"Eugendorf",
    "sg:orig_category":"Blumeneinzelhandel",
    "sg:phone":"+43 6225 7279",
    "sg:postcode":"5301",
    "sg:province":"Salzburg",
    "wof:name":"Feichtner Birgit",
    "wof:placetype":"venue"
},
  "geometry": {"coordinates":[13.1297674179,47.8652076721],"type":"Point"}
}