{
  "type": "Feature",
  "properties": {
    "addr:full":"Ossiacher Zeile 39 Villach K\u00e4rnten 9500",
    "addr:housenumber":"39",
    "addr:postcode":"9500",
    "addr:street":"Ossiacher Zeile;Kaernten",
    "iso:country":"AT",
    "sg:address":"Ossiacher Zeile 39",
    "sg:city":"Villach",
    "sg:orig_category":"Garagen Parkgaragen",
    "sg:phone":"+43 4242 22887",
    "sg:postcode":"9500",
    "sg:province":"K\u00e4rnten",
    "wof:name":"APCOA Parking Austria AG",
    "wof:placetype":"venue"
},
  "geometry": {"coordinates":[13.8509550095,46.6089515686],"type":"Point"}
}