{
  "type": "Feature",
  "properties": {
    "iso:country":"AT",
    "sg:address":"Nr 10",
    "sg:city":"Werfenweng",
    "sg:orig_category":"Pensionen / Privatzimmer",
    "sg:phone":"+43 6466 403",
    "sg:postcode":"5453",
    "sg:province":"Salzburg",
    "wof:name":"Leiweinhof - Alexander Rettensteiner",
    "wof:placetype":"venue"
},
  "geometry": {"coordinates":[13.2578277588,47.46144104],"type":"Point"}
}