{
  "type": "Feature",
  "properties": {
    "addr:full":"Pestalozzistr 40 Leoben Steiermark 8700",
    "addr:housenumber":"40",
    "addr:postcode":"8700",
    "addr:street":"Pestalozzistr",
    "iso:country":"AT",
    "sg:address":"Pestalozzistr 40",
    "sg:city":"Leoben",
    "sg:orig_category":"Tanzschulen",
    "sg:phone":"+43 3842 81816",
    "sg:postcode":"8700",
    "sg:province":"Steiermark",
    "sg:website":"www.tanzschule-glauninger.at",
    "wof:name":"Treffpunkt Tanzschule - Glauninger & Wassner",
    "wof:placetype":"venue"
},
  "geometry": {"coordinates":[15.0789079666,47.3754043579],"type":"Point"}
}