{
  "type": "Feature",
  "properties": {
    "addr:full":"Grazer Str 18 Kapfenberg Steiermark 8605",
    "addr:postcode":"8605",
    "addr:street":"Str 18",
    "iso:country":"AT",
    "sg:address":"Grazer Str 18",
    "sg:city":"Kapfenberg",
    "sg:orig_category":"Tabaktrafiken",
    "sg:phone":"+43 3862 23355",
    "sg:postcode":"8605",
    "sg:province":"Steiermark",
    "wof:name":"Schneidhofer Renate",
    "wof:placetype":"venue"
},
  "geometry": {"coordinates":[15.2875833511,47.4386100769],"type":"Point"}
}