{
  "type": "Feature",
  "properties": {
    "addr:full":"Brunntalstrasse 25 Steyrerm\u00fchl Ober\u00f6sterreich 4662",
    "addr:housenumber":"25",
    "addr:postcode":"4662",
    "addr:street":"Brunntalstrasse;Oberoesterreich",
    "iso:country":"AT",
    "sg:address":"Brunntalstrasse 25",
    "sg:city":"Steyrerm\u00fchl",
    "sg:classifiers":[
        {
            "category":"Manufacturing",
            "subcategory":"Furniture",
            "type":"Manufacturing & Wholesale Goods"
        }
    ],
    "sg:phone":"+43 76138640",
    "sg:postcode":"4662",
    "sg:province":"Ober\u00f6sterreich",
    "sg:tags":[
        "design"
    ],
    "wof:name":"Gottfried Atzlinger",
    "wof:placetype":"venue"
},
  "geometry": {"coordinates":[13.8106050491,47.9919090271],"type":"Point"}
}