{
  "type": "Feature",
  "properties": {
    "iso:country":"AT",
    "sg:address":"Oberstein 67",
    "sg:city":"St. Martin am Tennengebirge",
    "sg:orig_category":"Pensionen / Privatzimmer",
    "sg:phone":"+43 4364 6373660",
    "sg:postcode":"5522",
    "sg:province":"Salzburg",
    "wof:name":"Pension Waldheim",
    "wof:placetype":"venue"
},
  "geometry": {"coordinates":[13.3807420731,47.4529037476],"type":"Point"}
}