{
  "type": "Feature",
  "properties": {
    "iso:country":"AT",
    "sg:address":"Bundesstr 23",
    "sg:city":"Kemeten",
    "sg:orig_category":"Elektrotechnik",
    "sg:phone":"+43 4333 525210",
    "sg:postcode":"7531",
    "sg:province":"Burgenland",
    "wof:name":"ELEKTROTECHNIK E-TEC PAUL",
    "wof:placetype":"venue"
},
  "geometry": {"coordinates":[16.1526527405,47.2488288879],"type":"Point"}
}