{
  "type": "Feature",
  "properties": {
    "addr:full":"Bahnhofstr 59 Gm\u00fcnd Nieder\u00f6sterreich 3950",
    "addr:housenumber":"59",
    "addr:postcode":"3950",
    "addr:street":"Bahnhofstr;Niederoesterreich",
    "iso:country":"AT",
    "sg:address":"Bahnhofstr 59",
    "sg:city":"Gm\u00fcnd",
    "sg:orig_category":"Fahrschulen",
    "sg:phone":"+43 2852 52248",
    "sg:postcode":"3950",
    "sg:province":"Nieder\u00f6sterreich",
    "wof:name":"1.Gm\u00fcnder Autofahrschule Friedrich Zischka",
    "wof:placetype":"venue"
},
  "geometry": {"coordinates":[14.985490799,48.7661590576],"type":"Point"}
}