{
  "type": "Feature",
  "properties": {
    "addr:full":"Nr 6 Stra\u00dfburg K\u00e4rnten 9341",
    "addr:postcode":"9341",
    "addr:street":"Nr;Strassburg Kaernten",
    "iso:country":"AT",
    "sg:address":"Nr 6",
    "sg:city":"Stra\u00dfburg",
    "sg:orig_category":"Metallbau",
    "sg:phone":"+43 4266 3166",
    "sg:postcode":"9341",
    "sg:province":"K\u00e4rnten",
    "wof:name":"Selinger Metallbau GmbH",
    "wof:placetype":"venue"
},
  "geometry": {"coordinates":[14.3311347961,46.8950157166],"type":"Point"}
}