{
  "type": "Feature",
  "properties": {
    "addr:full":"Nr 85 Friedersbach Nieder\u00f6sterreich 3533",
    "addr:postcode":"3533",
    "addr:street":"Nr 85 Friedersbach",
    "iso:country":"AT",
    "sg:address":"Nr 85",
    "sg:city":"Friedersbach",
    "sg:orig_category":"Tischlereien",
    "sg:phone":"+43 4328 2277230",
    "sg:postcode":"3533",
    "sg:province":"Nieder\u00f6sterreich",
    "wof:name":"Brunner Claudia - Bau- u M\u00f6beltischlerei",
    "wof:placetype":"venue"
},
  "geometry": {"coordinates":[15.2693529129,48.5901679993],"type":"Point"}
}