{
  "type": "Feature",
  "properties": {
    "addr:full":"Hauptstr 35 St. Johann im Pongau Salzburg 5600",
    "addr:housenumber":"35",
    "addr:postcode":"5600",
    "addr:street":"Hauptstr;Salzburg",
    "iso:country":"AT",
    "sg:address":"Hauptstr 35",
    "sg:city":"St. Johann im Pongau",
    "sg:orig_category":"Politische Parteien",
    "sg:phone":"+43 6412 43460",
    "sg:postcode":"5600",
    "sg:province":"Salzburg",
    "wof:name":"\u00f6sterreichische Volkspartei (\u00f6VP) Bezirksleitung Pongau",
    "wof:placetype":"venue"
},
  "geometry": {"coordinates":[13.2026529312,47.3491134644],"type":"Point"}
}