{
  "type": "Feature",
  "properties": {
    "addr:full":"Pfarrstr 276 Mariapfarr Salzburg 5571",
    "addr:housenumber":"276",
    "addr:postcode":"5571",
    "addr:street":"Mariapfarr Salzburg",
    "iso:country":"AT",
    "sg:address":"Pfarrstr 276",
    "sg:city":"Mariapfarr",
    "sg:orig_category":"Lebensmittel / Einzelhandel",
    "sg:phone":"+43 6473 74410",
    "sg:postcode":"5571",
    "sg:province":"Salzburg",
    "wof:name":"ADEG Aktiv Markt",
    "wof:placetype":"venue"
},
  "geometry": {"coordinates":[13.7457036972,47.1497344971],"type":"Point"}
}