{
  "type": "Feature",
  "properties": {
    "addr:full":"Pfarrweg 3 Bergheim Salzburg 5101",
    "addr:housenumber":"3",
    "addr:postcode":"5101",
    "addr:street":"Pfarrweg;Salzburg",
    "iso:country":"AT",
    "sg:address":"Pfarrweg 3",
    "sg:city":"Bergheim",
    "sg:orig_category":"Non-Classified Establishments",
    "sg:phone":"+43 662 4520940",
    "sg:postcode":"5101",
    "sg:province":"Salzburg",
    "wof:name":"Pfarramt",
    "wof:placetype":"venue"
},
  "geometry": {"coordinates":[13.0248041153,47.840133667],"type":"Point"}
}