{
  "type": "Feature",
  "properties": {
    "addr:full":"Rosengartenweg 11 Zell am Ziller Tirol 6280",
    "addr:housenumber":"11",
    "addr:postcode":"6280",
    "addr:street":"Rosengartenweg;Tirol",
    "iso:country":"AT",
    "sg:address":"Rosengartenweg 11",
    "sg:city":"Zell am Ziller",
    "sg:orig_category":"Installationsunternehmen",
    "sg:phone":"+43 5282 2133",
    "sg:postcode":"6280",
    "sg:province":"Tirol",
    "wof:name":"Fankhauser Josef",
    "wof:placetype":"venue"
},
  "geometry": {"coordinates":[11.8868932724,47.2344970703],"type":"Point"}
}