{
  "type": "Feature",
  "properties": {
    "addr:full":"Wiener Str 1a Langenzersdorf Nieder\u00f6sterreich 2103",
    "addr:postcode":"2103",
    "addr:street":"Str 1A",
    "iso:country":"AT",
    "sg:address":"Wiener Str 1a",
    "sg:city":"Langenzersdorf",
    "sg:orig_category":"Bekleidung / Einzelhandel",
    "sg:phone":"+43 2244 4023",
    "sg:postcode":"2103",
    "sg:province":"Nieder\u00f6sterreich",
    "wof:name":"Modestube Hilde Habek",
    "wof:placetype":"venue"
},
  "geometry": {"coordinates":[16.3582172394,48.3091316223],"type":"Point"}
}