{
  "type": "Feature",
  "properties": {
    "addr:full":"Grazer Str 59 Leibnitz Steiermark 8430",
    "addr:postcode":"8430",
    "addr:street":"Str 59;Steiermark",
    "iso:country":"AT",
    "sg:address":"Grazer Str 59",
    "sg:city":"Leibnitz",
    "sg:orig_category":"Autoverwertung",
    "sg:phone":"+43 4334 5283851",
    "sg:postcode":"8430",
    "sg:province":"Steiermark",
    "wof:name":"Zirngast KFZ GesmbH Nfg KEG",
    "wof:placetype":"venue"
},
  "geometry": {"coordinates":[15.5424547195,46.8274726868],"type":"Point"}
}