{
  "type": "Feature",
  "properties": {
    "addr:full":"Schlo\u00dfpl 2 Vorchdorf Ober\u00f6sterreich 4655",
    "addr:housenumber":"2",
    "addr:postcode":"4655",
    "addr:street":"Schlosspl",
    "iso:country":"AT",
    "sg:address":"Schlo\u00dfpl 2",
    "sg:city":"Vorchdorf",
    "sg:orig_category":"Waren Aller Art",
    "sg:phone":"+43 4376 145322",
    "sg:postcode":"4655",
    "sg:province":"Ober\u00f6sterreich",
    "wof:name":"Weltladen",
    "wof:placetype":"venue"
},
  "geometry": {"coordinates":[13.9226665497,48.0034179688],"type":"Point"}
}