{
  "type": "Feature",
  "properties": {
    "iso:country":"AT",
    "sg:address":"Bergerbr\u00e4uhofstr. 33",
    "sg:city":"Salzburg",
    "sg:classifiers":[
        {
            "category":"Professional",
            "subcategory":"Advertising",
            "type":"Services"
        }
    ],
    "sg:phone":"+43 4366 29390",
    "sg:postcode":"5020",
    "sg:province":"Salzburg",
    "sg:tags":[
        "communication",
        "medium"
    ],
    "wof:name":"IDC GMBH",
    "wof:placetype":"venue"
},
  "geometry": {"coordinates":[13.0559549332,47.818271637],"type":"Point"}
}