{
  "type": "Feature",
  "properties": {
    "iso:country":"AT",
    "sg:address":"Sportplatzstr 9",
    "sg:city":"Enns",
    "sg:orig_category":"\u00c3\u201erzte / F Allgemeinmedizin",
    "sg:phone":"+43 7223 82640",
    "sg:postcode":"4470",
    "sg:province":"Ober\u00f6sterreich",
    "wof:name":"Hockl Wolfgang Dr",
    "wof:placetype":"venue"
},
  "geometry": {"coordinates":[14.4746131897,48.2114601135],"type":"Point"}
}