{
  "type": "Feature",
  "properties": {
    "iso:country":"AT",
    "sg:address":"Billrothstrasse 63",
    "sg:city":"Wien",
    "sg:classifiers":[
        {
            "category":"Personal",
            "subcategory":"Skin Care",
            "type":"Services"
        }
    ],
    "sg:phone":"+43 1 3694763",
    "sg:postcode":"1190",
    "sg:province":"Wien",
    "sg:tags":[
        "clips",
        "earrings",
        "ear",
        "stud"
    ],
    "wof:name":"Peter Ternes",
    "wof:placetype":"venue"
},
  "geometry": {"coordinates":[16.3486557007,48.2407188416],"type":"Point"}
}