{
  "type": "Feature",
  "properties": {
    "addr:full":"Pfarrg 12 Hollabrunn Nieder\u00f6sterreich 2020",
    "addr:housenumber":"12",
    "addr:postcode":"2020",
    "addr:street":"Pfarrg",
    "iso:country":"AT",
    "sg:address":"Pfarrg 12",
    "sg:city":"Hollabrunn",
    "sg:orig_category":"Modellbau",
    "sg:phone":"+43 664 4504105",
    "sg:postcode":"2020",
    "sg:province":"Nieder\u00f6sterreich",
    "wof:name":"Gruber Modellbau OEG",
    "wof:placetype":"venue"
},
  "geometry": {"coordinates":[16.0788230896,48.5610847473],"type":"Point"}
}