{
  "type": "Feature",
  "properties": {
    "addr:full":"Theresienthalstrasse 11-13 Hausmening Nieder\u00f6sterreich 3363",
    "addr:postcode":"11-13;3363",
    "addr:street":"Theresienthalstrasse;Niederoesterreich",
    "iso:country":"AT",
    "sg:address":"Theresienthalstrasse 11-13",
    "sg:city":"Hausmening",
    "sg:classifiers":[
        {
            "category":"Shopping",
            "subcategory":"Computers & Home Electronics",
            "type":"Retail Goods"
        }
    ],
    "sg:phone":"+43 7475 541000",
    "sg:postcode":"3363",
    "sg:province":"Nieder\u00f6sterreich",
    "sg:tags":[
        "system",
        "automation"
    ],
    "sg:website":"tb-eas.com",
    "wof:name":"E.A.S. Automatisierungstechnik Beratungs Ges.m.b.H.",
    "wof:placetype":"venue"
},
  "geometry": {"coordinates":[14.813949585,48.076133728],"type":"Point"}
}