{
  "type": "Feature",
  "properties": {
    "addr:full":"Museumstr 22 Linz Ober\u00f6sterreich 4020",
    "addr:housenumber":"22",
    "addr:postcode":"4020",
    "addr:street":"Museumstr",
    "iso:country":"AT",
    "sg:address":"Museumstr 22",
    "sg:city":"Linz",
    "sg:orig_category":"Autoreparatur",
    "sg:phone":"+43 732 781198",
    "sg:postcode":"4020",
    "sg:province":"Ober\u00f6sterreich",
    "wof:name":"Tanackovic Peter",
    "wof:placetype":"venue"
},
  "geometry": {"coordinates":[14.2954721451,48.3062591553],"type":"Point"}
}