{
  "type": "Feature",
  "properties": {
    "addr:full":"Pofelweg 10 G\u00f6fis Vorarlberg 6811",
    "addr:housenumber":"10",
    "addr:postcode":"6811",
    "addr:street":"Pofelweg",
    "iso:country":"AT",
    "sg:address":"Pofelweg 10",
    "sg:city":"G\u00f6fis",
    "sg:orig_category":"Musikgruppen",
    "sg:phone":"+43 5522 75418",
    "sg:postcode":"6811",
    "sg:province":"Vorarlberg",
    "wof:name":"DIDI - Alleinunterhalter",
    "wof:placetype":"venue"
},
  "geometry": {"coordinates":[-90.20757293699999,36.779548645],"type":"Point"}
}