{
  "type": "Feature",
  "properties": {
    "iso:country":"AT",
    "sg:address":"Bahnhofstr 5",
    "sg:city":"Bregenz",
    "sg:orig_category":"Papier- U Schreibwaren / Einzelhandel",
    "sg:phone":"+43 4355 744222013",
    "sg:postcode":"6900",
    "sg:province":"Vorarlberg",
    "wof:name":"LU & MO Papeterie GmbH",
    "wof:placetype":"venue"
},
  "geometry": {"coordinates":[9.7450666428,47.5037727356],"type":"Point"}
}