{
  "type": "Feature",
  "properties": {
    "addr:full":"Neusiedlerstrasse 15-19 Gloggnitz Nieder\u00f6sterreich 2640",
    "addr:postcode":"15-19;2640",
    "addr:street":"Neusiedlerstrasse;Niederoesterreich",
    "iso:country":"AT",
    "sg:address":"Neusiedlerstrasse 15-19",
    "sg:city":"Gloggnitz",
    "sg:classifiers":[
        {
            "category":"Manufacturing",
            "subcategory":"Tools & Machinery",
            "type":"Manufacturing & Wholesale Goods"
        }
    ],
    "sg:phone":"+43 2662 42780",
    "sg:postcode":"2640",
    "sg:province":"Nieder\u00f6sterreich",
    "sg:tags":[
        "construction",
        "container",
        "apparatus"
    ],
    "sg:website":"karasekgroup.at",
    "wof:name":"Norbert Karasek Ges.m.b.H. Beh\u00e4lter- und Anlagenbau",
    "wof:placetype":"venue"
},
  "geometry": {"coordinates":[15.9505224228,47.6688461304],"type":"Point"}
}