{
  "type": "Feature",
  "properties": {
    "addr:full":"Bozner Pl 5 Innsbruck Tirol 6020",
    "addr:housenumber":"5",
    "addr:postcode":"6020",
    "addr:street":"Bozner Pl;Tirol",
    "iso:country":"AT",
    "sg:address":"Bozner Pl 5",
    "sg:city":"Innsbruck",
    "sg:classifiers":[
        {
            "category":"Professional",
            "type":"Services"
        }
    ],
    "sg:phone":"+43 512 59110",
    "sg:postcode":"6020",
    "sg:province":"Tirol",
    "sg:tags":[
        "leasing"
    ],
    "wof:name":"Tiroler Landesprojekte Grundverwertungs-GmbH",
    "wof:placetype":"venue"
},
  "geometry": {"coordinates":[11.3980951309,47.2647972107],"type":"Point"}
}