{
  "type": "Feature",
  "properties": {
    "iso:country":"AT",
    "sg:address":"Breitenfelder G 2",
    "sg:city":"Wien",
    "sg:orig_category":"Pensionen / Privatzimmer",
    "sg:phone":"+43 1 4083308",
    "sg:postcode":"1080",
    "sg:province":"Wien",
    "wof:name":"Pension Gaber",
    "wof:placetype":"venue"
},
  "geometry": {"coordinates":[16.3452968597,48.2143211365],"type":"Point"}
}