{
  "type": "Feature",
  "properties": {
    "iso:country":"AT",
    "sg:address":"Nordbahnstr 22",
    "sg:city":"Wien",
    "sg:orig_category":"Lebens- U Sozialberatung",
    "sg:phone":"+43 1 2821109",
    "sg:postcode":"1020",
    "sg:province":"Wien",
    "wof:name":"Smazinka J\u00f6rg Mag",
    "wof:placetype":"venue"
},
  "geometry": {"coordinates":[16.3886356354,48.2252731323],"type":"Point"}
}