{
  "type": "Feature",
  "properties": {
    "addr:full":"Wiener Str 2 Maria Lanzendorf Nieder\u00f6sterreich 2326",
    "addr:housenumber":"2",
    "addr:postcode":"2326",
    "iso:country":"AT",
    "sg:address":"Wiener Str 2",
    "sg:city":"Maria Lanzendorf",
    "sg:orig_category":"Fleischhauereien",
    "sg:phone":"+43 4322 3544046",
    "sg:postcode":"2326",
    "sg:province":"Nieder\u00f6sterreich",
    "wof:name":"Schirnhofer-Breisler GesmbH - Shop in Shop",
    "wof:placetype":"venue"
},
  "geometry": {"coordinates":[16.4185371399,48.0991172791],"type":"Point"}
}