{
  "type": "Feature",
  "properties": {
    "iso:country":"AT",
    "sg:address":"Gadollaweg 26",
    "sg:city":"Puntigam",
    "sg:orig_category":"Modellagenturen",
    "sg:phone":"+43 316 261091",
    "sg:postcode":"8055",
    "sg:province":"Steiermark",
    "wof:name":"TEAM f\u00fcr MODE",
    "wof:placetype":"venue"
},
  "geometry": {"coordinates":[15.4413890839,47.0218849182],"type":"Point"}
}