{
  "type": "Feature",
  "properties": {
    "addr:full":"Ehrenbrunngasse 1  Schwechat Nieder\u00f6sterreich 2320",
    "addr:housenumber":"1",
    "addr:postcode":"2320",
    "addr:street":"Ehrenbrunngasse;Niederoesterreich",
    "iso:country":"AT",
    "sg:address":"Ehrenbrunngasse 1 ",
    "sg:city":"Schwechat",
    "sg:classifiers":[
        {
            "category":"Government",
            "subcategory":"Fire Station",
            "type":"Public Place"
        }
    ],
    "sg:phone":"+43 1 7076510",
    "sg:postcode":"2320",
    "sg:province":"Nieder\u00f6sterreich",
    "sg:tags":[
        "supraregional",
        "plant",
        "installation",
        "heating"
    ],
    "wof:name":"Alois Ruck",
    "wof:placetype":"venue"
},
  "geometry": {"coordinates":[16.4801883698,48.1403617859],"type":"Point"}
}