{
  "type": "Feature",
  "properties": {
    "addr:full":"Resselg 1 Gerasdorf Nieder\u00f6sterreich 2201",
    "addr:housenumber":"1",
    "addr:postcode":"2201",
    "addr:street":"Resselg",
    "iso:country":"AT",
    "sg:address":"Resselg 1",
    "sg:city":"Gerasdorf",
    "sg:orig_category":"Hydraulik",
    "sg:phone":"+43 4317 342496",
    "sg:postcode":"2201",
    "sg:province":"Nieder\u00f6sterreich",
    "wof:name":"Hansa-Flex Hydraulik GmbH",
    "wof:placetype":"venue"
},
  "geometry": {"coordinates":[16.4793205261,48.2821655273],"type":"Point"}
}