{
  "type": "Feature",
  "properties": {
    "iso:country":"AT",
    "sg:address":"Nr 19",
    "sg:city":"Pernegg an der Mur",
    "sg:orig_category":"Lebensmittel / Einzelhandel",
    "sg:phone":"+43 3867 8012",
    "sg:postcode":"8132",
    "sg:province":"Steiermark",
    "wof:name":"Freidorfer Romana",
    "wof:placetype":"venue"
},
  "geometry": {"coordinates":[15.3446798325,47.3590660095],"type":"Point"}
}