{
  "type": "Feature",
  "properties": {
    "addr:full":"Klosterbergg 8 Vorau Steiermark 8250",
    "addr:housenumber":"8",
    "addr:postcode":"8250",
    "addr:street":"Klosterbergg",
    "iso:country":"AT",
    "sg:address":"Klosterbergg 8",
    "sg:city":"Vorau",
    "sg:orig_category":"Lebensmittel / Einzelhandel",
    "sg:phone":"+43 3337 30005",
    "sg:postcode":"8250",
    "sg:province":"Steiermark",
    "wof:name":"A & O Markt Nah & Frisch",
    "wof:placetype":"venue"
},
  "geometry": {"coordinates":[15.8871173859,47.4051055908],"type":"Point"}
}