{
  "type": "Feature",
  "properties": {
    "addr:full":"Industriestrasse 2 Heidenreichstein Nieder\u00f6sterreich 3860",
    "addr:housenumber":"2",
    "addr:postcode":"3860",
    "addr:street":"Industriestrasse",
    "iso:country":"AT",
    "sg:address":"Industriestrasse 2",
    "sg:city":"Heidenreichstein",
    "sg:classifiers":[
        {
            "category":"Military Area",
            "subcategory":"Air Force Base",
            "type":"Public Place"
        }
    ],
    "sg:phone":"+43 2862 581610",
    "sg:postcode":"3860",
    "sg:province":"Nieder\u00f6sterreich",
    "sg:tags":[
        "window",
        "skylight",
        "dormer"
    ],
    "wof:name":"WAKU-Fenster G.m.b.H.",
    "wof:placetype":"venue"
},
  "geometry": {"coordinates":[15.1045942307,48.8551483154],"type":"Point"}
}