{
  "type": "Feature",
  "properties": {
    "iso:country":"AT",
    "sg:address":"Nasen 246",
    "sg:city":"W\u00f6rgl",
    "sg:orig_category":"Autovermietung",
    "sg:phone":"+43 650 2705777",
    "sg:postcode":"6300",
    "sg:province":"Tirol",
    "wof:name":"Magic Limousines",
    "wof:placetype":"venue"
},
  "geometry": {"coordinates":[-69.3131027222,-51.6091995239],"type":"Point"}
}