{
  "type": "Feature",
  "properties": {
    "addr:full":"Nr 19 Mandling Steiermark 8974",
    "addr:postcode":"8974",
    "addr:street":"Nr 19 Mandling Steiermark",
    "iso:country":"AT",
    "sg:address":"Nr 19",
    "sg:city":"Mandling",
    "sg:orig_category":"Appartements / Ferienwohnungen",
    "sg:phone":"+43 6454 7261",
    "sg:postcode":"8974",
    "sg:province":"Steiermark",
    "wof:name":"Bergbauernhof Irxner",
    "wof:placetype":"venue"
},
  "geometry": {"coordinates":[13.5746250153,47.4045944214],"type":"Point"}
}