{
  "type": "Feature",
  "properties": {
    "addr:full":"Hauptstrasse 37 Gaspoltshofen Ober\u00f6sterreich 4673",
    "addr:housenumber":"37",
    "addr:postcode":"4673",
    "addr:street":"Hauptstrasse",
    "iso:country":"AT",
    "sg:address":"Hauptstrasse 37",
    "sg:city":"Gaspoltshofen",
    "sg:classifiers":[
        {
            "category":"Wholesale",
            "subcategory":"Plants",
            "type":"Manufacturing & Wholesale Goods"
        }
    ],
    "sg:phone":"+43 7735 69370",
    "sg:postcode":"4673",
    "sg:province":"Ober\u00f6sterreich",
    "sg:tags":[
        "machine",
        "industrial",
        "automation"
    ],
    "sg:website":"baum-autom.at",
    "wof:name":"Baumgartner GmbH & Co KG",
    "wof:placetype":"venue"
},
  "geometry": {"coordinates":[13.7368011475,48.1409721375],"type":"Point"}
}