{
  "type": "Feature",
  "properties": {
    "addr:full":"Hofg 11 St. Peter in der Au Nieder\u00f6sterreich 3352",
    "addr:housenumber":"11",
    "addr:postcode":"3352",
    "addr:street":"Hofg",
    "iso:country":"AT",
    "sg:address":"Hofg 11",
    "sg:city":"St. Peter in der Au",
    "sg:orig_category":"Eisenwaren",
    "sg:phone":"+43 7477 423220",
    "sg:postcode":"3352",
    "sg:province":"Nieder\u00f6sterreich",
    "wof:name":"Klein KG",
    "wof:placetype":"venue"
},
  "geometry": {"coordinates":[14.6215419769,48.0450401306],"type":"Point"}
}