{
  "type": "Feature",
  "properties": {
    "addr:full":"Pfeilgasse 35 Wien Wien 1080",
    "addr:housenumber":"35",
    "addr:postcode":"1080",
    "addr:street":"Pfeilgasse",
    "iso:country":"AT",
    "sg:address":"Pfeilgasse 35",
    "sg:city":"Wien",
    "sg:classifiers":[
        {
            "category":"Government",
            "subcategory":"Post Office",
            "type":"Public Place"
        }
    ],
    "sg:phone":"+43 1 40575140",
    "sg:postcode":"1080",
    "sg:province":"Wien",
    "sg:tags":[
        "assembly",
        "furniture"
    ],
    "sg:website":"vitra.com",
    "wof:name":"Vitra Ges.m.b.H. Austria",
    "wof:placetype":"venue"
},
  "geometry": {"coordinates":[16.3424530029,48.2090454102],"type":"Point"}
}