{
  "type": "Feature",
  "properties": {
    "addr:full":"Eisenst\u00e4dter Str 10 Oberpullendorf Burgenland 7350",
    "addr:housenumber":"10",
    "addr:postcode":"7350",
    "addr:street":"Str",
    "iso:country":"AT",
    "sg:address":"Eisenst\u00e4dter Str 10",
    "sg:city":"Oberpullendorf",
    "sg:orig_category":"Gastronomie- U Hoteleinrichtungen",
    "sg:phone":"+43 2612 43337",
    "sg:postcode":"7350",
    "sg:province":"Burgenland",
    "wof:name":"May Way Fachmarkt f Gastrotechnik",
    "wof:placetype":"venue"
},
  "geometry": {"coordinates":[16.5114440918,47.4970207214],"type":"Point"}
}