{
  "type": "Feature",
  "properties": {
    "iso:country":"AT",
    "sg:address":"Nr 14",
    "sg:city":"Gosdorf",
    "sg:orig_category":"Feuerwehren",
    "sg:phone":"+43 664 5427799",
    "sg:postcode":"8482",
    "sg:province":"Steiermark",
    "wof:name":"Freiwillige Feuerwehr Misselsdorf",
    "wof:placetype":"venue"
},
  "geometry": {"coordinates":[15.7965946198,46.7270584106],"type":"Point"}
}