{
  "type": "Feature",
  "properties": {
    "addr:full":"Aspergasse 16 Salzburg Salzburg 5020",
    "addr:housenumber":"16",
    "addr:postcode":"5020",
    "addr:street":"Aspergasse;Salzburg",
    "iso:country":"AT",
    "sg:address":"Aspergasse 16",
    "sg:city":"Salzburg",
    "sg:classifiers":[
        {
            "category":"Manufacturing",
            "subcategory":"Metals",
            "type":"Manufacturing & Wholesale Goods"
        }
    ],
    "sg:phone":"+43 662 628400",
    "sg:postcode":"5020",
    "sg:province":"Salzburg",
    "sg:tags":[
        "precious",
        "banister"
    ],
    "wof:name":"HEINDL Metallbau GmbH",
    "wof:placetype":"venue"
},
  "geometry": {"coordinates":[13.0620336533,47.7908287048],"type":"Point"}
}