{
  "type": "Feature",
  "properties": {
    "addr:full":"Frauenfelderstr 6/11 Wien Wien 1170",
    "addr:housenumber":"6 / 11",
    "addr:postcode":"1170",
    "addr:street":"Frauenfelderstr",
    "iso:country":"AT",
    "sg:address":"Frauenfelderstr 6/11",
    "sg:city":"Wien",
    "sg:orig_category":"Psychotherapie",
    "sg:phone":"+43 664 1422299",
    "sg:postcode":"1170",
    "sg:province":"Wien",
    "wof:name":"Berchtold Marcel Mag",
    "wof:placetype":"venue"
},
  "geometry": {"coordinates":[16.3130931854,48.2255935669],"type":"Point"}
}