{
  "type": "Feature",
  "properties": {
    "addr:full":"Nr 34 Hochneukirchen Nieder\u00f6sterreich 2852",
    "addr:postcode":"2852",
    "addr:street":"Nr;Niederoesterreich",
    "iso:country":"AT",
    "sg:address":"Nr 34",
    "sg:city":"Hochneukirchen",
    "sg:orig_category":"Tankstellen",
    "sg:phone":"+43 2648 280",
    "sg:postcode":"2852",
    "sg:province":"Nieder\u00f6sterreich",
    "wof:name":"Diskont Tanstelle",
    "wof:placetype":"venue"
},
  "geometry": {"coordinates":[16.1997680664,47.4575958252],"type":"Point"}
}