{
  "type": "Feature",
  "properties": {
    "addr:full":"Arlbergstr 7/1 Dornbirn Vorarlberg 6850",
    "addr:housenumber":"7 / 1",
    "addr:postcode":"6850",
    "addr:street":"Arlbergstr",
    "iso:country":"AT",
    "sg:address":"Arlbergstr 7/1",
    "sg:city":"Dornbirn",
    "sg:orig_category":"Werbeagenturen",
    "sg:phone":"+43 4355 72207060",
    "sg:postcode":"6850",
    "sg:province":"Vorarlberg",
    "wof:name":"Hagen Werbung GmbH",
    "wof:placetype":"venue"
},
  "geometry": {"coordinates":[9.736038208,47.3996086121],"type":"Point"}
}