{
  "type": "Feature",
  "properties": {
    "iso:country":"AT",
    "sg:address":"Unterwagramer Str 31",
    "sg:city":"St. P\u00f6lten",
    "sg:orig_category":"Fleischhauereien",
    "sg:phone":"+43 2742 252189",
    "sg:postcode":"3100",
    "sg:province":"Nieder\u00f6sterreich",
    "wof:name":"Bogner Karl-Michael",
    "wof:placetype":"venue"
},
  "geometry": {"coordinates":[-79.3644332886,34.8895263672],"type":"Point"}
}