{
  "type": "Feature",
  "properties": {
    "addr:full":"Hauptpl 5 Bruck an der Mur Steiermark 8600",
    "addr:housenumber":"5",
    "addr:postcode":"8600",
    "addr:street":"Hauptpl",
    "iso:country":"AT",
    "sg:address":"Hauptpl 5",
    "sg:city":"Bruck an der Mur",
    "sg:orig_category":"Fotoapparate U -Artikel / Einzelhandel",
    "sg:phone":"+43 4338 62513750",
    "sg:postcode":"8600",
    "sg:province":"Steiermark",
    "wof:name":"Remele Hans",
    "wof:placetype":"venue"
},
  "geometry": {"coordinates":[15.2685451508,47.4100990295],"type":"Point"}
}