{
  "type": "Feature",
  "properties": {
    "addr:full":"Hauptstr 18 St. Johann im Pongau Salzburg 5600",
    "addr:housenumber":"18",
    "addr:postcode":"5600",
    "addr:street":"Hauptstr;Salzburg",
    "iso:country":"AT",
    "sg:address":"Hauptstr 18",
    "sg:city":"St. Johann im Pongau",
    "sg:orig_category":"Gemeinden",
    "sg:phone":"+43 4364 1280010",
    "sg:postcode":"5600",
    "sg:province":"Salzburg",
    "wof:name":"Stadtgemeinde St Johann im Pongau",
    "wof:placetype":"venue"
},
  "geometry": {"coordinates":[13.2038621902,47.3493804932],"type":"Point"}
}