{
  "type": "Feature",
  "properties": {
    "addr:full":"Nr 10 Rohr im Gebirge Nieder\u00f6sterreich 2663",
    "addr:postcode":"2663",
    "addr:street":"Nr",
    "iso:country":"AT",
    "sg:address":"Nr 10",
    "sg:city":"Rohr im Gebirge",
    "sg:orig_category":"Volksschulen",
    "sg:phone":"+43 4326 678249",
    "sg:postcode":"2663",
    "sg:province":"Nieder\u00f6sterreich",
    "wof:name":"Volksschule",
    "wof:placetype":"venue"
},
  "geometry": {"coordinates":[15.7363061905,47.8951377869],"type":"Point"}
}