{
  "type": "Feature",
  "properties": {
    "addr:full":"Unterdorf 18 Rietz Tirol 6421",
    "addr:housenumber":"18",
    "addr:postcode":"6421",
    "addr:street":"Unterdorf;Tirol",
    "iso:country":"AT",
    "sg:address":"Unterdorf 18",
    "sg:city":"Rietz",
    "sg:orig_category":"Pensionen / Privatzimmer",
    "sg:phone":"+43 4352 6262619",
    "sg:postcode":"6421",
    "sg:province":"Tirol",
    "wof:name":"Bio-Form Bau u M\u00f6beltischlerei",
    "wof:placetype":"venue"
},
  "geometry": {"coordinates":[11.0285491943,47.2882385254],"type":"Point"}
}