{
  "type": "Feature",
  "properties": {
    "addr:full":"Wollzeile 15 Wien Wien 1010",
    "addr:housenumber":"15",
    "addr:postcode":"1010",
    "addr:street":"Wollzeile",
    "iso:country":"AT",
    "sg:address":"Wollzeile 15",
    "sg:city":"Wien",
    "sg:orig_category":"Bankomat-Standorte",
    "sg:phone":"+43 5 010020012",
    "sg:postcode":"1010",
    "sg:province":"Wien",
    "wof:name":"Bankomat d Erste Bank d oesterreichischen Sparkassen AG",
    "wof:placetype":"venue"
},
  "geometry": {"coordinates":[16.3759593964,48.2086448669],"type":"Point"}
}