{
  "type": "Feature",
  "properties": {
    "addr:full":"Kurhausstr 29 Bad Pirawarth Nieder\u00f6sterreich 2222",
    "addr:housenumber":"29",
    "addr:postcode":"2222",
    "addr:street":"Kurhausstr;Niederoesterreich",
    "iso:country":"AT",
    "sg:address":"Kurhausstr 29",
    "sg:city":"Bad Pirawarth",
    "sg:orig_category":"Friseure U Frisiersalons",
    "sg:phone":"+43 4325 742363",
    "sg:postcode":"2222",
    "sg:province":"Nieder\u00f6sterreich",
    "wof:name":"Graf Gabriela",
    "wof:placetype":"venue"
},
  "geometry": {"coordinates":[16.6016788483,48.4527893066],"type":"Point"}
}