{
  "type": "Feature",
  "properties": {
    "iso:country":"AT",
    "sg:address":"Kurhausstr 29",
    "sg:city":"Bad Pirawarth",
    "sg:orig_category":"Friseure U Frisiersalons",
    "sg:phone":"+43 4325 742363",
    "sg:postcode":"2222",
    "sg:province":"Nieder\u00f6sterreich",
    "wof:name":"Graf Gabriela",
    "wof:placetype":"venue"
},
  "geometry": {"coordinates":[16.6016788483,48.4527893066],"type":"Point"}
}