{
  "type": "Feature",
  "properties": {
    "iso:country":"AT",
    "sg:address":"Margaretenstr 119",
    "sg:city":"Wien",
    "sg:orig_category":"Textilwaren / Einzelhandel",
    "sg:phone":"+43 1 5456568",
    "sg:postcode":"1050",
    "sg:province":"Wien",
    "wof:name":"HERZ HandelsgesmbH & Co KG",
    "wof:placetype":"venue"
},
  "geometry": {"coordinates":[16.3532371521,48.1881103516],"type":"Point"}
}