{
  "type": "Feature",
  "properties": {
    "addr:full":"Ossiacher Str 6 St. Veit an der Glan K\u00e4rnten 9300",
    "addr:housenumber":"6",
    "addr:postcode":"9300",
    "addr:street":"Str;Kaernten",
    "iso:country":"AT",
    "sg:address":"Ossiacher Str 6",
    "sg:city":"St. Veit an der Glan",
    "sg:orig_category":"Bankomat-Standorte",
    "sg:phone":"+43 4342 12533311",
    "sg:postcode":"9300",
    "sg:province":"K\u00e4rnten",
    "wof:name":"Bankomat d PSK St Veit an der Glan",
    "wof:placetype":"venue"
},
  "geometry": {"coordinates":[14.3584947586,46.7659645081],"type":"Point"}
}