{
  "type": "Feature",
  "properties": {
    "addr:full":"Hauptstr 96 Frankenmarkt Ober\u00f6sterreich 4890",
    "addr:housenumber":"96",
    "addr:postcode":"4890",
    "addr:street":"Hauptstr;Oberoesterreich",
    "iso:country":"AT",
    "sg:address":"Hauptstr 96",
    "sg:city":"Frankenmarkt",
    "sg:orig_category":"Juweliere, Gold- U Silberschmiede",
    "sg:phone":"+43 76846421",
    "sg:postcode":"4890",
    "sg:province":"Ober\u00f6sterreich",
    "wof:name":"Pichler Engelbert",
    "wof:placetype":"venue"
},
  "geometry": {"coordinates":[13.4191627502,47.9855537415],"type":"Point"}
}