{
  "type": "Feature",
  "properties": {
    "addr:full":"Linzer Str 2 Attnang-Puchheim Ober\u00f6sterreich 4800",
    "addr:housenumber":"2",
    "addr:postcode":"4800",
    "addr:street":"Linzer Str",
    "iso:country":"AT",
    "sg:address":"Linzer Str 2",
    "sg:city":"Attnang-Puchheim",
    "sg:orig_category":"Elektroinstallationsunternehmen",
    "sg:phone":"+43 767466510",
    "sg:postcode":"4800",
    "sg:province":"Ober\u00f6sterreich",
    "wof:name":"Elektro Diehs",
    "wof:placetype":"venue"
},
  "geometry": {"coordinates":[13.7242603302,48.0216712952],"type":"Point"}
}