{
  "type": "Feature",
  "properties": {
    "addr:full":"Ramsau 126e Hippach Tirol 6283",
    "addr:housenumber":"126e",
    "addr:postcode":"6283",
    "addr:street":"Ramsau;Tirol",
    "iso:country":"AT",
    "sg:address":"Ramsau 126e",
    "sg:city":"Hippach",
    "sg:orig_category":"Appartements / Ferienwohnungen",
    "sg:phone":"+43 4352 823523",
    "sg:postcode":"6283",
    "sg:province":"Tirol",
    "wof:name":"Ferienwohnungen Huamatl",
    "wof:placetype":"venue"
},
  "geometry": {"coordinates":[11.8709201813,47.2054481506],"type":"Point"}
}