{
  "type": "Feature",
  "properties": {
    "addr:full":"Alfred-Kubin-Pl 4/1A Wien Wien 1220",
    "addr:housenumber":"4 / 1a",
    "addr:postcode":"1220",
    "addr:street":"Alfred-Kubin-Pl",
    "iso:country":"AT",
    "sg:address":"Alfred-Kubin-Pl 4/1A",
    "sg:city":"Wien",
    "sg:orig_category":"Tabaktrafiken",
    "sg:phone":"+43 1 2583188",
    "sg:postcode":"1220",
    "sg:province":"Wien",
    "wof:name":"Edtmaier Susanne",
    "wof:placetype":"venue"
},
  "geometry": {"coordinates":[16.4412593842,48.2603034973],"type":"Point"}
}