{
  "type": "Feature",
  "properties": {
    "addr:full":"Grazer Strasse 87 Deutschlandsberg Steiermark 8530",
    "addr:housenumber":"87",
    "addr:postcode":"8530",
    "addr:street":"Grazer Strasse",
    "iso:country":"AT",
    "sg:address":"Grazer Strasse 87",
    "sg:city":"Deutschlandsberg",
    "sg:classifiers":[
        {
            "category":"Autos & Motor Vehicles",
            "subcategory":"Auto Supplies",
            "type":"Retail Goods"
        }
    ],
    "sg:phone":"+43 3462 2369",
    "sg:postcode":"8530",
    "sg:province":"Steiermark",
    "sg:tags":[
        "automobile",
        "painting"
    ],
    "wof:name":"Autohaus Resch Ges.m.b.H. & Co KG",
    "wof:placetype":"venue"
},
  "geometry": {"coordinates":[15.2344808578,46.8162765503],"type":"Point"}
}