{
  "type": "Feature",
  "properties": {
    "addr:full":"F\u00e4rberg 15 Dornbirn Vorarlberg 6850",
    "addr:housenumber":"15",
    "addr:postcode":"6850",
    "addr:street":"Faerberg",
    "iso:country":"AT",
    "sg:address":"F\u00e4rberg 15",
    "sg:city":"Dornbirn",
    "sg:classifiers":[
        {
            "category":"Food & Beverages",
            "subcategory":"Bakery",
            "type":"Retail Goods"
        }
    ],
    "sg:phone":"+43 5572 22593",
    "sg:postcode":"6850",
    "sg:province":"Vorarlberg",
    "sg:tags":[
        "sandwich"
    ],
    "wof:name":"Fago's Brot & Sandwich",
    "wof:placetype":"venue"
},
  "geometry": {"coordinates":[9.7437801361,47.4131889343],"type":"Point"}
}