{
  "type": "Feature",
  "properties": {
    "addr:full":"Altausseer Str 353 Bad Aussee Steiermark 8990",
    "addr:postcode":"8990",
    "iso:country":"AT",
    "sg:address":"Altausseer Str 353",
    "sg:city":"Bad Aussee",
    "sg:orig_category":"Autoreparatur",
    "sg:phone":"+43 4336 22520850",
    "sg:postcode":"8990",
    "sg:province":"Steiermark",
    "wof:name":"Bathelt Autohaus Handels- u Werkst\u00e4tten GesmbH",
    "wof:placetype":"venue"
},
  "geometry": {"coordinates":[13.7810258865,47.6105957031],"type":"Point"}
}