{
  "type": "Feature",
  "properties": {
    "addr:full":"Waidmannsdorfer Str 73 Klagenfurt K\u00e4rnten 9020",
    "addr:housenumber":"73",
    "addr:postcode":"9020",
    "addr:street":"Waidmannsdorfer Str;Kaernten",
    "iso:country":"AT",
    "sg:address":"Waidmannsdorfer Str 73",
    "sg:city":"Klagenfurt",
    "sg:orig_category":"Tabaktrafiken",
    "sg:phone":"+43 463 22571",
    "sg:postcode":"9020",
    "sg:province":"K\u00e4rnten",
    "wof:name":"Kotschnig Ingrid",
    "wof:placetype":"venue"
},
  "geometry": {"coordinates":[14.293047905,46.61485672],"type":"Point"}
}