{
  "type": "Feature",
  "properties": {
    "iso:country":"AT",
    "sg:address":"Franz-Liszt-G 25-27",
    "sg:city":"Neusiedl am See",
    "sg:orig_category":"Lebensmittel / Einzelhandel",
    "sg:phone":"+43 4321 672495",
    "sg:postcode":"7100",
    "sg:province":"Burgenland",
    "wof:name":"Optifood HandelsgmbH",
    "wof:placetype":"venue"
},
  "geometry": {"coordinates":[16.8480415344,47.9473114014],"type":"Point"}
}