{
  "type": "Feature",
  "properties": {
    "addr:full":"Achleit 91 W\u00f6rgl Tirol 6300",
    "addr:housenumber":"91",
    "addr:postcode":"6300",
    "addr:street":"Achleit;Tirol",
    "iso:country":"AT",
    "sg:address":"Achleit 91",
    "sg:city":"W\u00f6rgl",
    "sg:orig_category":"Steuerberatung",
    "sg:phone":"+43 5332 56647",
    "sg:postcode":"6300",
    "sg:province":"Tirol",
    "wof:name":"Hausberger Ernst",
    "wof:placetype":"venue"
},
  "geometry": {"coordinates":[12.0299119949,47.4921302795],"type":"Point"}
}