{
  "type": "Feature",
  "properties": {
    "addr:full":"Waidach 32 Nu\u00dfdorf am Haunsberg Salzburg 5151",
    "addr:housenumber":"32",
    "addr:postcode":"5151",
    "addr:street":"Waidach;Salzburg",
    "iso:country":"AT",
    "sg:address":"Waidach 32",
    "sg:city":"Nu\u00dfdorf am Haunsberg",
    "sg:orig_category":"Offsetdruckereien",
    "sg:phone":"+43 6276 395",
    "sg:postcode":"5151",
    "sg:province":"Salzburg",
    "wof:name":"Schmidinger Helmut",
    "wof:placetype":"venue"
},
  "geometry": {"coordinates":[13.0012874603,47.9578895569],"type":"Point"}
}