{
  "type": "Feature",
  "properties": {
    "addr:full":"Schrankg 4 Wien Wien 1070",
    "addr:housenumber":"4",
    "addr:postcode":"1070",
    "addr:street":"Schrankg",
    "iso:country":"AT",
    "sg:address":"Schrankg 4",
    "sg:city":"Wien",
    "sg:classifiers":[
        {
            "category":"Restaurant",
            "type":"Food & Drink"
        }
    ],
    "sg:phone":"+43 1 5269491",
    "sg:postcode":"1070",
    "sg:province":"Wien",
    "wof:name":"Restaurant Lux",
    "wof:placetype":"venue"
},
  "geometry": {"coordinates":[16.354757309,48.202835083],"type":"Point"}
}