{
  "type": "Feature",
  "properties": {
    "addr:full":"Nr 13 Kapelln Nieder\u00f6sterreich 3141",
    "addr:postcode":"3141",
    "addr:street":"Nr;Kapelln",
    "iso:country":"AT",
    "sg:address":"Nr 13",
    "sg:city":"Kapelln",
    "sg:orig_category":"Schrauben, Muttern U Nieten",
    "sg:phone":"+43 4327 842385",
    "sg:postcode":"3141",
    "sg:province":"Nieder\u00f6sterreich",
    "wof:name":"Bayer Johann GesmbH",
    "wof:placetype":"venue"
},
  "geometry": {"coordinates":[15.7556753159,48.2581596375],"type":"Point"}
}