{
  "type": "Feature",
  "properties": {
    "addr:full":"Kirchpl 6 Bad Hofgastein Salzburg 5630",
    "addr:housenumber":"6",
    "addr:postcode":"5630",
    "addr:street":"Kirchpl;Salzburg",
    "iso:country":"AT",
    "sg:address":"Kirchpl 6",
    "sg:city":"Bad Hofgastein",
    "sg:orig_category":"Optiker",
    "sg:phone":"+43 6432 2595",
    "sg:postcode":"5630",
    "sg:province":"Salzburg",
    "wof:name":"Optik Perendi",
    "wof:placetype":"venue"
},
  "geometry": {"coordinates":[13.1071233749,47.1708984375],"type":"Point"}
}