{
  "type": "Feature",
  "properties": {
    "addr:full":"Nr 37 Unterpremst\u00e4tten Steiermark 8141",
    "addr:postcode":"8141",
    "addr:street":"Nr 37 Unterpremstaetten Steiermark",
    "iso:country":"AT",
    "sg:address":"Nr 37",
    "sg:city":"Unterpremst\u00e4tten",
    "sg:orig_category":"Gemeinden",
    "sg:phone":"+43 3135 524350",
    "sg:postcode":"8141",
    "sg:province":"Steiermark",
    "wof:name":"Gemeindeamt Zettling",
    "wof:placetype":"venue"
},
  "geometry": {"coordinates":[-91.5072937012,32.9921264648],"type":"Point"}
}