{
  "type": "Feature",
  "properties": {
    "iso:country":"AT",
    "sg:address":"Burggasse 110/Halbgasse 18",
    "sg:city":"Wien",
    "sg:classifiers":[
        {
            "category":"Organizations",
            "subcategory":"Membership Organization",
            "type":"Services"
        }
    ],
    "sg:phone":"+43 1 5263884",
    "sg:postcode":"1070",
    "sg:province":"Wien",
    "sg:tags":[
        "clothing",
        "mountaineering"
    ],
    "sg:website":"alpenfritz.at",
    "wof:name":"Michael Milz KG",
    "wof:placetype":"venue"
},
  "geometry": {"coordinates":[16.3383293152,48.2016792297],"type":"Point"}
}