{
  "type": "Feature",
  "properties": {
    "iso:country":"AT",
    "sg:address":"Eisenst\u00e4dter Str Parz/1115",
    "sg:city":"Breitenbrunn",
    "sg:orig_category":"Autoreparatur",
    "sg:phone":"+43 2683 5296",
    "sg:postcode":"7091",
    "sg:province":"Burgenland",
    "wof:name":"Hofbauer Josef",
    "wof:placetype":"venue"
},
  "geometry": {"coordinates":[16.7329368591,47.9457244873],"type":"Point"}
}