{
  "type": "Feature",
  "properties": {
    "addr:full":"Markt Allhau 437 Markt Allhau Burgenland 7411",
    "addr:housenumber":"437",
    "addr:postcode":"7411",
    "addr:street":"Markt Allhau",
    "iso:country":"AT",
    "sg:address":"Markt Allhau 437",
    "sg:city":"Markt Allhau",
    "sg:classifiers":[
        {
            "category":"Community Center",
            "subcategory":"Senior",
            "type":"Public Place"
        }
    ],
    "sg:phone":"+43 3356 8275",
    "sg:postcode":"7411",
    "sg:province":"Burgenland",
    "sg:tags":[
        "tile",
        "wall",
        "ceramic"
    ],
    "wof:name":"G\u00fcnter Loppauer",
    "wof:placetype":"venue"
},
  "geometry": {"coordinates":[16.0903167725,47.285610199],"type":"Point"}
}