{
  "type": "Feature",
  "properties": {
    "addr:full":"Siedlung 21 Ampflwang im Hausruckwald Ober\u00f6sterreich 4843",
    "addr:housenumber":"21",
    "addr:postcode":"4843",
    "addr:street":"Siedlung",
    "iso:country":"AT",
    "sg:address":"Siedlung 21",
    "sg:city":"Ampflwang im Hausruckwald",
    "sg:orig_category":"Baumaschinenverleih",
    "sg:phone":"+43 4376 752935",
    "sg:postcode":"4843",
    "sg:province":"Ober\u00f6sterreich",
    "wof:name":"Bauger\u00e4teverleih Josef St\u00fcbler",
    "wof:placetype":"venue"
},
  "geometry": {"coordinates":[13.5624303818,48.0847206116],"type":"Point"}
}