{
  "type": "Feature",
  "properties": {
    "addr:full":"Nr 15 Grafenschlag Nieder\u00f6sterreich 3912",
    "addr:postcode":"3912",
    "addr:street":"Nr;Grafenschlag",
    "iso:country":"AT",
    "sg:address":"Nr 15",
    "sg:city":"Grafenschlag",
    "sg:orig_category":"Waren Aller Art",
    "sg:phone":"+43 2875 8382",
    "sg:postcode":"3912",
    "sg:province":"Nieder\u00f6sterreich",
    "wof:name":"Logistik - Service HandelsgmbH",
    "wof:placetype":"venue"
},
  "geometry": {"coordinates":[15.1739721298,48.4707336426],"type":"Point"}
}