{
  "type": "Feature",
  "properties": {
    "addr:full":"Lassallestr 11 Wien Wien 1020",
    "addr:housenumber":"11",
    "addr:postcode":"1020",
    "addr:street":"Lassallestr",
    "iso:country":"AT",
    "sg:address":"Lassallestr 11",
    "sg:city":"Wien",
    "sg:orig_category":"Fahrschulen",
    "sg:phone":"+43 1 2144361",
    "sg:postcode":"1020",
    "sg:province":"Wien",
    "sg:website":"fahrschule-columbus.at",
    "wof:name":"Fahrschule Columbus",
    "wof:placetype":"venue"
},
  "geometry": {"coordinates":[16.4003639221,48.2235221863],"type":"Point"}
}