{
  "type": "Feature",
  "properties": {
    "iso:country":"AT",
    "sg:address":"Alte Landstr 8",
    "sg:city":"Bludenz",
    "sg:orig_category":"Versicherungsunternehmen",
    "sg:phone":"+43 5552 63322",
    "sg:postcode":"6700",
    "sg:province":"Vorarlberg",
    "wof:name":"Donau Versicherung",
    "wof:placetype":"venue"
},
  "geometry": {"coordinates":[9.8188285828,47.1582756042],"type":"Point"}
}