{
  "type": "Feature",
  "properties": {
    "addr:full":"Augartenstr 39 Lustenau Vorarlberg 6890",
    "addr:housenumber":"39",
    "addr:postcode":"6890",
    "addr:street":"Augartenstr",
    "iso:country":"AT",
    "sg:address":"Augartenstr 39",
    "sg:city":"Lustenau",
    "sg:orig_category":"Schlossereien",
    "sg:phone":"+43 5577 88116",
    "sg:postcode":"6890",
    "sg:province":"Vorarlberg",
    "wof:name":"Kreativ-Metall",
    "wof:placetype":"venue"
},
  "geometry": {"coordinates":[9.65376091,47.4423065186],"type":"Point"}
}