{
  "type": "Feature",
  "properties": {
    "addr:full":"Bundesstr 41 Rum Tirol 6063",
    "addr:housenumber":"41",
    "addr:postcode":"6063",
    "addr:street":"Bundesstr;Tirol",
    "iso:country":"AT",
    "sg:address":"Bundesstr 41",
    "sg:city":"Rum",
    "sg:orig_category":"Eisenwaren",
    "sg:phone":"+43 512 2611170",
    "sg:postcode":"6063",
    "sg:province":"Tirol",
    "wof:name":"Hofmann Josef",
    "wof:placetype":"venue"
},
  "geometry": {"coordinates":[11.446395874,47.2773971558],"type":"Point"}
}