{
  "type": "Feature",
  "properties": {
    "iso:country":"AT",
    "sg:address":"Hietzinger Hauptstr 148",
    "sg:city":"Wien",
    "sg:orig_category":"Textilreinigung",
    "sg:phone":"+43 1 8795016",
    "sg:postcode":"1130",
    "sg:province":"Wien",
    "wof:name":"Alphaclean Textilreinigung Pertich & Co OHG",
    "wof:placetype":"venue"
},
  "geometry": {"coordinates":[16.2705879211,48.187953949],"type":"Point"}
}