{
  "type": "Feature",
  "properties": {
    "addr:full":"Hosla 11 Unterrabnitz Burgenland 7371",
    "addr:housenumber":"11",
    "addr:postcode":"7371",
    "addr:street":"Hosla",
    "iso:country":"AT",
    "sg:address":"Hosla 11",
    "sg:city":"Unterrabnitz",
    "sg:orig_category":"Messe- U Ausstellungsbau U -Gestaltung",
    "sg:phone":"+43 4326 1630089",
    "sg:postcode":"7371",
    "sg:province":"Burgenland",
    "wof:name":"Hellmer Messebau - Eventdesign",
    "wof:placetype":"venue"
},
  "geometry": {"coordinates":[16.408952713,47.4443092346],"type":"Point"}
}