{
  "type": "Feature",
  "properties": {
    "addr:full":"Wickenburgg 8 Graz Steiermark 8010",
    "addr:housenumber":"8",
    "addr:postcode":"8010",
    "addr:street":"Wickenburgg",
    "iso:country":"AT",
    "sg:address":"Wickenburgg 8",
    "sg:city":"Graz",
    "sg:orig_category":"Automatisierungstechnik",
    "sg:phone":"+43 316 6766770",
    "sg:postcode":"8010",
    "sg:province":"Steiermark",
    "wof:name":"ATEG Automation Technology Engineering Group",
    "wof:placetype":"venue"
},
  "geometry": {"coordinates":[15.4385757446,47.0791625977],"type":"Point"}
}