{
  "type": "Feature",
  "properties": {
    "addr:full":"Landstr 113 Linz Ober\u00f6sterreich 4020",
    "addr:housenumber":"113",
    "addr:postcode":"4020",
    "addr:street":"Landstr",
    "iso:country":"AT",
    "sg:address":"Landstr 113",
    "sg:city":"Linz",
    "sg:orig_category":"Textilwaren / Einzelhandel",
    "sg:phone":"+43 732 656164",
    "sg:postcode":"4020",
    "sg:province":"Ober\u00f6sterreich",
    "wof:name":"Reiter Betten & Vorh\u00e4nge GmbH",
    "wof:placetype":"venue"
},
  "geometry": {"coordinates":[14.2924585342,48.2959251404],"type":"Point"}
}