{
  "type": "Feature",
  "properties": {
    "addr:full":"Rosental 4 Neukirchen am Gro\u00dfvenediger Salzburg 5741",
    "addr:housenumber":"4",
    "addr:postcode":"5741",
    "addr:street":"Rosental;Salzburg",
    "iso:country":"AT",
    "sg:address":"Rosental 4",
    "sg:city":"Neukirchen am Gro\u00dfvenediger",
    "sg:orig_category":"Transportunternehmen",
    "sg:phone":"+43 6565 6322",
    "sg:postcode":"5741",
    "sg:province":"Salzburg",
    "wof:name":"St\u00f6ckl Peter",
    "wof:placetype":"venue"
},
  "geometry": {"coordinates":[12.3227596283,47.261390686],"type":"Point"}
}