{
  "type": "Feature",
  "properties": {
    "addr:full":"Kaserng. 25 Judenburg Steiermark 8750",
    "addr:housenumber":"25",
    "addr:postcode":"8750",
    "addr:street":"Kaserng.",
    "iso:country":"AT",
    "sg:address":"Kaserng. 25",
    "sg:city":"Judenburg",
    "sg:classifiers":[
        {
            "category":"Sports & Exercise",
            "subcategory":"Playing Field",
            "type":"Entertainment"
        }
    ],
    "sg:phone":"+43 4335 7285419",
    "sg:postcode":"8750",
    "sg:province":"Steiermark",
    "sg:tags":[
        "game"
    ],
    "wof:name":"ING GERD ELTNER",
    "wof:placetype":"venue"
},
  "geometry": {"coordinates":[14.6633453369,47.1692123413],"type":"Point"}
}