{
  "type": "Feature",
  "properties": {
    "addr:full":"Offenhausener Str 12 Gunskirchen Ober\u00f6sterreich 4623",
    "addr:postcode":"4623",
    "addr:street":"Str 12",
    "iso:country":"AT",
    "sg:address":"Offenhausener Str 12",
    "sg:city":"Gunskirchen",
    "sg:orig_category":"Autoreparatur",
    "sg:phone":"+43 7246 202020",
    "sg:postcode":"4623",
    "sg:province":"Ober\u00f6sterreich",
    "wof:name":"TRUCK & TRAILER SERVICE Neumayer",
    "wof:placetype":"venue"
},
  "geometry": {"coordinates":[13.9350166321,48.1329345703],"type":"Point"}
}