{
  "type": "Feature",
  "properties": {
    "addr:full":"Klienstr 7 Hohenems Vorarlberg 6845",
    "addr:housenumber":"7",
    "addr:postcode":"6845",
    "addr:street":"Klienstr",
    "iso:country":"AT",
    "sg:address":"Klienstr 7",
    "sg:city":"Hohenems",
    "sg:orig_category":"Garagentore U -Antriebe",
    "sg:phone":"+43 5576 732300",
    "sg:postcode":"6845",
    "sg:province":"Vorarlberg",
    "wof:name":"Ermato Handels GmbH & Co",
    "wof:placetype":"venue"
},
  "geometry": {"coordinates":[9.6785011292,47.3623504639],"type":"Point"}
}