{
  "type": "Feature",
  "properties": {
    "iso:country":"AT",
    "sg:address":"Hauptstr 25",
    "sg:city":"Zwentendorf an der Donau",
    "sg:orig_category":"Friseure U Frisiersalons",
    "sg:phone":"+43 4322 772248",
    "sg:postcode":"3435",
    "sg:province":"Nieder\u00f6sterreich",
    "wof:name":"Frank Walter",
    "wof:placetype":"venue"
},
  "geometry": {"coordinates":[15.9102058411,48.3458557129],"type":"Point"}
}