{
  "type": "Feature",
  "properties": {
    "iso:country":"AT",
    "sg:address":"Thullin 16",
    "sg:city":"Turnau",
    "sg:orig_category":"Sand U Schotter, Erdarbeiten",
    "sg:phone":"+43 3863 22760",
    "sg:postcode":"8625",
    "sg:province":"Steiermark",
    "sg:website":"www.wurzenberger.at",
    "wof:name":"Wurzenberger Br\u00fcder",
    "wof:placetype":"venue"
},
  "geometry": {"coordinates":[15.3370742798,47.5582237244],"type":"Point"}
}