{
  "type": "Feature",
  "properties": {
    "iso:country":"AT",
    "sg:address":"Markt Allhau 86",
    "sg:city":"Markt Allhau",
    "sg:classifiers":[
        {
            "category":"Arts & Performance",
            "subcategory":"Art Gallery",
            "type":"Entertainment"
        }
    ],
    "sg:phone":"+43 3356 7908",
    "sg:postcode":"7411",
    "sg:province":"Burgenland",
    "sg:tags":[
        "painting"
    ],
    "wof:name":"Alfred Ringbauer",
    "wof:placetype":"venue"
},
  "geometry": {"coordinates":[16.0812625885,47.2892875671],"type":"Point"}
}