{
  "type": "Feature",
  "properties": {
    "iso:country":"AT",
    "sg:address":"Siedlung 154C",
    "sg:city":"Rattenberg",
    "sg:orig_category":"Tonstudios",
    "sg:phone":"+43 5337 93217",
    "sg:postcode":"6240",
    "sg:province":"Tirol",
    "wof:name":"Cox John Patrick",
    "wof:placetype":"venue"
},
  "geometry": {"coordinates":[11.8964691162,47.4384994507],"type":"Point"}
}