{
  "type": "Feature",
  "properties": {
    "addr:full":"Theodor-K\u00f6rner-Str 127 Graz Steiermark 8010",
    "addr:housenumber":"127",
    "addr:postcode":"8010",
    "iso:country":"AT",
    "sg:address":"Theodor-K\u00f6rner-Str 127",
    "sg:city":"Graz",
    "sg:orig_category":"Marketingberatung",
    "sg:phone":"+43 316 684148",
    "sg:postcode":"8010",
    "sg:province":"Steiermark",
    "sg:website":"bestservice4you.at",
    "wof:name":"Best Service for you",
    "wof:placetype":"venue"
},
  "geometry": {"coordinates":[15.4281082153,47.0891647339],"type":"Point"}
}