{
  "type": "Feature",
  "properties": {
    "addr:full":"Esterhazyg 30 Wien Wien 1060",
    "addr:housenumber":"30",
    "addr:postcode":"1060",
    "addr:street":"Esterhazyg",
    "iso:country":"AT",
    "sg:address":"Esterhazyg 30",
    "sg:city":"Wien",
    "sg:classifiers":[
        {
            "category":"Government",
            "subcategory":"Post Office",
            "type":"Public Place"
        }
    ],
    "sg:phone":"+43 1 7490785",
    "sg:postcode":"1060",
    "sg:province":"Wien",
    "sg:tags":[
        "yoga"
    ],
    "wof:name":"Vogler Elisabeth",
    "wof:placetype":"venue"
},
  "geometry": {"coordinates":[16.349237442,48.1972312927],"type":"Point"}
}