{
  "type": "Feature",
  "properties": {
    "iso:country":"AT",
    "sg:address":"Steggasse 33",
    "sg:city":"Bischofshofen",
    "sg:classifiers":[
        {
            "category":"Home & Garden",
            "subcategory":"Home Furnishings",
            "type":"Retail Goods"
        }
    ],
    "sg:phone":"+43 6462 8040",
    "sg:postcode":"5500",
    "sg:province":"Salzburg",
    "sg:tags":[
        "fixture",
        "lighting"
    ],
    "sg:website":"metallart.at",
    "wof:name":"Atelier Herbert Gahr",
    "wof:placetype":"venue"
},
  "geometry": {"coordinates":[13.2227163315,47.4172973633],"type":"Point"}
}