{
  "type": "Feature",
  "properties": {
    "addr:full":"Ziegeleistr 27 Klagenfurt K\u00e4rnten 9020",
    "addr:housenumber":"27",
    "addr:postcode":"9020",
    "addr:street":"Ziegeleistr;Kaernten",
    "iso:country":"AT",
    "sg:address":"Ziegeleistr 27",
    "sg:city":"Klagenfurt",
    "sg:orig_category":"Paketdienste, Kurierdienste",
    "sg:phone":"+43 810 810010",
    "sg:postcode":"9020",
    "sg:province":"K\u00e4rnten",
    "wof:name":"DHL Worldwide Express DHL International GesmbH",
    "wof:placetype":"venue"
},
  "geometry": {"coordinates":[14.3755226135,46.6330795288],"type":"Point"}
}