{
  "type": "Feature",
  "properties": {
    "addr:full":"Winklarner Str 5 Amstetten Nieder\u00f6sterreich 3300",
    "addr:housenumber":"5",
    "addr:postcode":"3300",
    "addr:street":"Str;Niederoesterreich",
    "iso:country":"AT",
    "sg:address":"Winklarner Str 5",
    "sg:city":"Amstetten",
    "sg:orig_category":"Tankstellen",
    "sg:phone":"+43 7472 62409",
    "sg:postcode":"3300",
    "sg:province":"Nieder\u00f6sterreich",
    "wof:name":"AVANTI TankstellenbetriebsgesmbH",
    "wof:placetype":"venue"
},
  "geometry": {"coordinates":[14.8715791702,48.1119918823],"type":"Point"}
}