{
  "type": "Feature",
  "properties": {
    "addr:full":"Hauptstr 27 Bernstein Burgenland 7434",
    "addr:housenumber":"27",
    "addr:postcode":"7434",
    "addr:street":"Hauptstr",
    "iso:country":"AT",
    "sg:address":"Hauptstr 27",
    "sg:city":"Bernstein",
    "sg:orig_category":"\u00c3\u201erzte / F Allgemeinmedizin",
    "sg:phone":"+43 3354 63230",
    "sg:postcode":"7434",
    "sg:province":"Burgenland",
    "wof:name":"Kraus Andreas Dr",
    "wof:placetype":"venue"
},
  "geometry": {"coordinates":[16.2557125092,47.4043693542],"type":"Point"}
}