{
  "type": "Feature",
  "properties": {
    "addr:full":"Obere Augartenstr 70 Wien Wien 1020",
    "addr:housenumber":"70",
    "addr:postcode":"1020",
    "addr:street":"Obere Augartenstr",
    "iso:country":"AT",
    "sg:address":"Obere Augartenstr 70",
    "sg:city":"Wien",
    "sg:orig_category":"Elektroinstallationsunternehmen",
    "sg:phone":"+43 1 2143797",
    "sg:postcode":"1020",
    "sg:province":"Wien",
    "wof:name":"Lenk Elektro GmbH",
    "wof:placetype":"venue"
},
  "geometry": {"coordinates":[16.3796691895,48.2195472717],"type":"Point"}
}