{
  "type": "Feature",
  "properties": {
    "addr:full":"Robert-Schumann-G. 59  Perchtoldsdorf Nieder\u00f6sterreich 2380",
    "addr:housenumber":"59",
    "addr:postcode":"2380",
    "addr:street":"Robert-Schumann-G.",
    "iso:country":"AT",
    "sg:address":"Robert-Schumann-G. 59 ",
    "sg:city":"Perchtoldsdorf",
    "sg:classifiers":[
        {
            "category":"Home & Garden",
            "subcategory":"Home Furnishings",
            "type":"Retail Goods"
        }
    ],
    "sg:phone":"+43 4318 698173",
    "sg:postcode":"2380",
    "sg:province":"Nieder\u00f6sterreich",
    "sg:tags":[
        "household"
    ],
    "wof:name":"PAUL PRESENT HANDELSGESMBH",
    "wof:placetype":"venue"
},
  "geometry": {"coordinates":[16.2854633331,48.1164016724],"type":"Point"}
}