{
  "type": "Feature",
  "properties": {
    "addr:full":"Lehenstr 1 Scharnstein Ober\u00f6sterreich 4644",
    "addr:housenumber":"1",
    "addr:postcode":"4644",
    "addr:street":"Lehenstr",
    "iso:country":"AT",
    "sg:address":"Lehenstr 1",
    "sg:city":"Scharnstein",
    "sg:orig_category":"Biologische Produkte",
    "sg:phone":"+43 76152985",
    "sg:postcode":"4644",
    "sg:province":"Ober\u00f6sterreich",
    "wof:name":"Naturladen Heidi Buchegger",
    "wof:placetype":"venue"
},
  "geometry": {"coordinates":[13.9541721344,47.902305603],"type":"Point"}
}