{
  "type": "Feature",
  "properties": {
    "iso:country":"AT",
    "sg:address":"Hamburger Str 14",
    "sg:city":"Wien",
    "sg:classifiers":[
        {
            "category":"Arts & Performance",
            "subcategory":"Theater",
            "type":"Entertainment"
        }
    ],
    "sg:phone":"+43 1 5870653",
    "sg:postcode":"1050",
    "sg:province":"Wien",
    "wof:name":"Spektakel",
    "wof:placetype":"venue"
},
  "geometry": {"coordinates":[16.3560848236,48.1957550049],"type":"Point"}
}