{
  "type": "Feature",
  "properties": {
    "iso:country":"AT",
    "sg:address":"Steindorf 12",
    "sg:city":"Seewalchen am Attersee",
    "sg:orig_category":"Estriche",
    "sg:phone":"+43 76623682",
    "sg:postcode":"4863",
    "sg:province":"Ober\u00f6sterreich",
    "wof:name":"Kr\u00f6pfel Margit",
    "wof:placetype":"venue"
},
  "geometry": {"coordinates":[13.565779686,47.9647941589],"type":"Point"}
}