{
  "type": "Feature",
  "properties": {
    "addr:full":"Salzstr 12 Zirl Tirol 6170",
    "addr:housenumber":"12",
    "addr:postcode":"6170",
    "addr:street":"Salzstr;Tirol",
    "iso:country":"AT",
    "sg:address":"Salzstr 12",
    "sg:city":"Zirl",
    "sg:orig_category":"Estriche",
    "sg:phone":"+43 5238 5100",
    "sg:postcode":"6170",
    "sg:province":"Tirol",
    "sg:website":"roefix.com",
    "wof:name":"R\u00f6fix AG",
    "wof:placetype":"venue"
},
  "geometry": {"coordinates":[11.2332544327,47.2641334534],"type":"Point"}
}