{
  "type": "Feature",
  "properties": {
    "addr:full":"Nisselg 4-6 Wien Wien 1140",
    "addr:housenumber":"4-6",
    "addr:postcode":"1140",
    "addr:street":"Nisselg",
    "iso:country":"AT",
    "sg:address":"Nisselg 4-6",
    "sg:city":"Wien",
    "sg:orig_category":"Lebensmittel / Einzelhandel",
    "sg:phone":"+43 4318 975438",
    "sg:postcode":"1140",
    "sg:province":"Wien",
    "wof:name":"Billa AG",
    "wof:placetype":"venue"
},
  "geometry": {"coordinates":[16.3043079376,48.1884994507],"type":"Point"}
}