{
  "type": "Feature",
  "properties": {
    "addr:full":"Villacher Strasse 122 Feistritz an der Drau K\u00e4rnten 9710",
    "addr:housenumber":"122",
    "addr:postcode":"9710",
    "addr:street":"Villacher Strasse",
    "iso:country":"AT",
    "sg:address":"Villacher Strasse 122",
    "sg:city":"Feistritz an der Drau",
    "sg:classifiers":[
        {
            "category":"Juice Bar",
            "subcategory":"None",
            "type":"Food & Drink"
        }
    ],
    "sg:phone":"+43 4245 2307",
    "sg:postcode":"9710",
    "sg:province":"K\u00e4rnten",
    "sg:tags":[
        "granite",
        "slab"
    ],
    "sg:website":"hoeher.at",
    "wof:name":"G. H\u00f6her Steinmetzbetrieb Ges.m.b.H. & Co KG",
    "wof:placetype":"venue"
},
  "geometry": {"coordinates":[13.6812143326,46.6893577576],"type":"Point"}
}