{
  "type": "Feature",
  "properties": {
    "iso:country":"AT",
    "sg:address":"Kufsteiner Str 7",
    "sg:city":"Kirchbichl",
    "sg:orig_category":"Friseure U Frisiersalons",
    "sg:phone":"+43 5332 88290",
    "sg:postcode":"6322",
    "sg:province":"Tirol",
    "wof:name":"Haar Design - Heidi Steiner",
    "wof:placetype":"venue"
},
  "geometry": {"coordinates":[12.0986890793,47.5194740295],"type":"Point"}
}