{
  "type": "Feature",
  "properties": {
    "iso:country":"AT",
    "sg:address":"Grazer Str 1",
    "sg:city":"Lebring",
    "sg:orig_category":"Gemeinden",
    "sg:phone":"+43 3182 24710",
    "sg:postcode":"8403",
    "sg:province":"Steiermark",
    "wof:name":"Marktgemeinde Lebring-St. Margarethen",
    "wof:placetype":"venue"
},
  "geometry": {"coordinates":[15.5358200073,46.8576393127],"type":"Point"}
}