{
  "type": "Feature",
  "properties": {
    "addr:full":"Hauptstr 31 Deutsch Wagram Nieder\u00f6sterreich 2232",
    "addr:housenumber":"31",
    "addr:postcode":"2232",
    "addr:street":"Hauptstr",
    "iso:country":"AT",
    "sg:address":"Hauptstr 31",
    "sg:city":"Deutsch Wagram",
    "sg:orig_category":"Tapezierer U Dekorateure",
    "sg:phone":"+43 4322 472417",
    "sg:postcode":"2232",
    "sg:province":"Nieder\u00f6sterreich",
    "wof:name":"Weiss Markus",
    "wof:placetype":"venue"
},
  "geometry": {"coordinates":[16.5615596771,48.2972145081],"type":"Point"}
}