{
  "type": "Feature",
  "properties": {
    "addr:full":"Hauptpl 1 Liezen Steiermark 8940",
    "addr:housenumber":"1",
    "addr:postcode":"8940",
    "addr:street":"Hauptpl",
    "iso:country":"AT",
    "sg:address":"Hauptpl 1",
    "sg:city":"Liezen",
    "sg:orig_category":"Versicherungsunternehmen",
    "sg:phone":"+43 3612 222380",
    "sg:postcode":"8940",
    "sg:province":"Steiermark",
    "wof:name":"Wiener St\u00e4dtische Allgemeine Versicherung AG",
    "wof:placetype":"venue"
},
  "geometry": {"coordinates":[14.2427711487,47.5670013428],"type":"Point"}
}