{
  "type": "Feature",
  "properties": {
    "addr:full":"Sebastian-Stief-Strasse 18 Seekirchen am Wallersee Salzburg 5201",
    "addr:housenumber":"18",
    "addr:postcode":"5201",
    "addr:street":"Sebastian-Stief-Strasse;Salzburg",
    "iso:country":"AT",
    "sg:address":"Sebastian-Stief-Strasse 18",
    "sg:city":"Seekirchen am Wallersee",
    "sg:classifiers":[
        {
            "category":"Structure",
            "subcategory":"Restrooms",
            "type":"Public Place"
        }
    ],
    "sg:phone":"+43 6212 75410",
    "sg:postcode":"5201",
    "sg:province":"Salzburg",
    "sg:tags":[
        "handicapped",
        "accessible",
        "toilet"
    ],
    "sg:website":"selmer.at",
    "wof:name":"Selmer Ges.m.b.H.",
    "wof:placetype":"venue"
},
  "geometry": {"coordinates":[13.1253252029,47.8960342407],"type":"Point"}
}