{
  "type": "Feature",
  "properties": {
    "addr:full":"Hauptpl 22 Deutsch Brodersdorf Nieder\u00f6sterreich 2443",
    "addr:housenumber":"22",
    "addr:postcode":"2443",
    "addr:street":"Hauptpl",
    "iso:country":"AT",
    "sg:address":"Hauptpl 22",
    "sg:city":"Deutsch Brodersdorf",
    "sg:orig_category":"Non-Classified Establishments",
    "sg:phone":"+43 2255 8256",
    "sg:postcode":"2443",
    "sg:province":"Nieder\u00f6sterreich",
    "wof:name":"Pfarramt",
    "wof:placetype":"venue"
},
  "geometry": {"coordinates":[16.516784668,47.9162826538],"type":"Point"}
}