{
  "type": "Feature",
  "properties": {
    "addr:full":"Klopstockg 52 Wien Wien 1170",
    "addr:housenumber":"52",
    "addr:postcode":"1170",
    "addr:street":"Klopstockg",
    "iso:country":"AT",
    "sg:address":"Klopstockg 52",
    "sg:city":"Wien",
    "sg:orig_category":"Autohandel",
    "sg:phone":"+43 1 4806089",
    "sg:postcode":"1170",
    "sg:province":"Wien",
    "wof:name":"Petrovic Autohandels KEG",
    "wof:placetype":"venue"
},
  "geometry": {"coordinates":[16.32396698,48.2195129395],"type":"Point"}
}