{
  "type": "Feature",
  "properties": {
    "iso:country":"AT",
    "sg:address":"Rechte Wienzeile 83",
    "sg:city":"Wien",
    "sg:classifiers":[
        {
            "category":"Manufacturing",
            "subcategory":"Jewelry",
            "type":"Manufacturing & Wholesale Goods"
        }
    ],
    "sg:phone":"+43 1 5875550",
    "sg:postcode":"1050",
    "sg:province":"Wien",
    "sg:tags":[
        "bangle",
        "bracelet"
    ],
    "sg:website":"perlen-poell.com",
    "wof:name":"Perlen-P\u00f6ll Handels GmbH",
    "wof:placetype":"venue"
},
  "geometry": {"coordinates":[16.3551235199,48.1933631897],"type":"Point"}
}