{
  "type": "Feature",
  "properties": {
    "addr:full":"Friedhofg NB Michelhausen Nieder\u00f6sterreich 3451",
    "addr:postcode":"3451",
    "addr:street":"Niederoesterreich",
    "iso:country":"AT",
    "sg:address":"Friedhofg NB",
    "sg:city":"Michelhausen",
    "sg:orig_category":"Feuerwehren",
    "sg:phone":"+43 2275 5555",
    "sg:postcode":"3451",
    "sg:province":"Nieder\u00f6sterreich",
    "wof:name":"Freiwillige Feuerwehr Michelhausen",
    "wof:placetype":"venue"
},
  "geometry": {"coordinates":[15.9415197372,48.2898597717],"type":"Point"}
}