{
  "type": "Feature",
  "properties": {
    "addr:full":"Wohlfahrterstr 6 St. P\u00f6lten Nieder\u00f6sterreich 3100",
    "addr:housenumber":"6",
    "addr:postcode":"3100",
    "addr:street":"Wohlfahrterstr",
    "iso:country":"AT",
    "sg:address":"Wohlfahrterstr 6",
    "sg:city":"St. P\u00f6lten",
    "sg:orig_category":"Autohandel",
    "sg:phone":"+43 2742 253584",
    "sg:postcode":"3100",
    "sg:province":"Nieder\u00f6sterreich",
    "wof:name":"Le Cars Inh Walter Ebner",
    "wof:placetype":"venue"
},
  "geometry": {"coordinates":[15.6360301971,48.1864356995],"type":"Point"}
}