{
  "type": "Feature",
  "properties": {
    "addr:full":"Flirsch 185 Flirsch Tirol 6572",
    "addr:housenumber":"185",
    "addr:postcode":"6572",
    "addr:street":"Flirsch;Tirol",
    "iso:country":"AT",
    "sg:address":"Flirsch 185",
    "sg:city":"Flirsch",
    "sg:classifiers":[
        {
            "category":"Manufacturing",
            "subcategory":"Wood Products",
            "type":"Manufacturing & Wholesale Goods"
        }
    ],
    "sg:phone":"+43 5447 5710",
    "sg:postcode":"6572",
    "sg:province":"Tirol",
    "sg:tags":[
        "gate",
        "made",
        "door"
    ],
    "wof:name":"Hubert Matt",
    "wof:placetype":"venue"
},
  "geometry": {"coordinates":[10.4204397202,47.1362228394],"type":"Point"}
}