{
  "type": "Feature",
  "properties": {
    "addr:full":"Marktg 1 Mattersburg Burgenland 7210",
    "addr:housenumber":"1",
    "addr:postcode":"7210",
    "addr:street":"Marktg",
    "iso:country":"AT",
    "sg:address":"Marktg 1",
    "sg:city":"Mattersburg",
    "sg:orig_category":"Bezirkshauptmannschaften",
    "sg:phone":"+43 2626 622520",
    "sg:postcode":"7210",
    "sg:province":"Burgenland",
    "wof:name":"Bezirkshauptmannschaft Mattersburg",
    "wof:placetype":"venue"
},
  "geometry": {"coordinates":[16.4006614685,47.7379341125],"type":"Point"}
}