{
  "type": "Feature",
  "properties": {
    "addr:full":"Kremstalstr 28 Haid Ober\u00f6sterreich 4053",
    "addr:housenumber":"28",
    "addr:postcode":"4053",
    "addr:street":"Kremstalstr",
    "iso:country":"AT",
    "sg:address":"Kremstalstr 28",
    "sg:city":"Haid",
    "sg:orig_category":"Autoreparatur",
    "sg:phone":"+43 7229 87525",
    "sg:postcode":"4053",
    "sg:province":"Ober\u00f6sterreich",
    "wof:name":"B\u00f6hm Johann GesmbH",
    "wof:placetype":"venue"
},
  "geometry": {"coordinates":[14.2470970154,48.2041664124],"type":"Point"}
}