{
  "type": "Feature",
  "properties": {
    "iso:country":"AT",
    "sg:address":"Tiefenbachstr 19",
    "sg:city":"Elixhausen",
    "sg:orig_category":"Massagen",
    "sg:phone":"+43 662 480116",
    "sg:postcode":"5161",
    "sg:province":"Salzburg",
    "wof:name":"Zangerle Lukas - Akupunkt-Massage nach Penzel",
    "wof:placetype":"venue"
},
  "geometry": {"coordinates":[13.0696659088,47.8676223755],"type":"Point"}
}