{
  "type": "Feature",
  "properties": {
    "iso:country":"AT",
    "sg:address":"Nr 17",
    "sg:city":"F\u00fcrstenfeld",
    "sg:classifiers":[
        {
            "category":"Restaurant",
            "type":"Food & Drink"
        }
    ],
    "sg:phone":"+43 3382 55936",
    "sg:postcode":"8280",
    "sg:province":"Steiermark",
    "wof:name":"Alizadeh Saboor Ghadir - Steinrestaurator",
    "wof:placetype":"venue"
},
  "geometry": {"coordinates":[16.0748786926,47.0515441895],"type":"Point"}
}