{
  "type": "Feature",
  "properties": {
    "addr:full":"Kaiserstr 7 St. Johann in Tirol Tirol 6380",
    "addr:housenumber":"7",
    "addr:postcode":"6380",
    "addr:street":"Kaiserstr;Tirol",
    "iso:country":"AT",
    "sg:address":"Kaiserstr 7",
    "sg:city":"St. Johann in Tirol",
    "sg:orig_category":"Damenmoden",
    "sg:phone":"+43 5352 622490",
    "sg:postcode":"6380",
    "sg:province":"Tirol",
    "wof:name":"Modenhaus Johanna Feller - Inh Friedrich Randl",
    "wof:placetype":"venue"
},
  "geometry": {"coordinates":[12.4261932373,47.5221290588],"type":"Point"}
}