{
  "type": "Feature",
  "properties": {
    "iso:country":"AT",
    "sg:address":"Federnberg 16",
    "sg:city":"Kirchheim im Innkreis",
    "sg:orig_category":"Elektroinstallationsunternehmen",
    "sg:phone":"+43 4377 557923",
    "sg:postcode":"4932",
    "sg:province":"Ober\u00f6sterreich",
    "wof:name":"Piereder Ludwig",
    "wof:placetype":"venue"
},
  "geometry": {"coordinates":[13.3853540421,48.2042732239],"type":"Point"}
}