{
  "type": "Feature",
  "properties": {
    "addr:full":"Hausmeninger Str 74 Mauer-\u00d6hling Nieder\u00f6sterreich 3362",
    "addr:postcode":"3362",
    "addr:street":"Str 74 Mauer-Oehling",
    "iso:country":"AT",
    "sg:address":"Hausmeninger Str 74",
    "sg:city":"Mauer-\u00d6hling",
    "sg:orig_category":"Tankstellen",
    "sg:phone":"+43 7475 52619",
    "sg:postcode":"3362",
    "sg:province":"Nieder\u00f6sterreich",
    "wof:name":"OMV Tankstelle - Wagner E GesmbH",
    "wof:placetype":"venue"
},
  "geometry": {"coordinates":[14.7991437912,48.0934944153],"type":"Point"}
}