{
  "type": "Feature",
  "properties": {
    "iso:country":"AT",
    "sg:address":"W\u00e4hringer Str 149",
    "sg:city":"Wien",
    "sg:orig_category":"Apotheken",
    "sg:phone":"+43 1 47933200",
    "sg:postcode":"1180",
    "sg:province":"Wien",
    "wof:name":"Adler Apotheke Mag pharm Hans Jakesz KG",
    "wof:placetype":"venue"
},
  "geometry": {"coordinates":[16.3354701996,48.2281341553],"type":"Point"}
}