{
  "type": "Feature",
  "properties": {
    "addr:full":"Obere Str 45 Schiltern Nieder\u00f6sterreich 3553",
    "addr:housenumber":"45",
    "addr:postcode":"3553",
    "addr:street":"Obere Str;Niederoesterreich",
    "iso:country":"AT",
    "sg:address":"Obere Str 45",
    "sg:city":"Schiltern",
    "sg:classifiers":[
        {
            "category":"Health Services",
            "subcategory":"Nursing And Care Facility",
            "type":"Services"
        }
    ],
    "sg:phone":"+43 2734 82220",
    "sg:postcode":"3553",
    "sg:province":"Nieder\u00f6sterreich",
    "sg:tags":[
        "rehabilitation"
    ],
    "wof:name":"Psychosoziales Zentrum Schiltern GesmbH",
    "wof:placetype":"venue"
},
  "geometry": {"coordinates":[15.617143631,48.5187683105],"type":"Point"}
}