{
  "type": "Feature",
  "properties": {
    "addr:full":"Nobilegasse 22 Wien Wien 1150",
    "addr:housenumber":"22",
    "addr:postcode":"1150",
    "addr:street":"Nobilegasse",
    "iso:country":"AT",
    "sg:address":"Nobilegasse 22",
    "sg:city":"Wien",
    "sg:classifiers":[
        {
            "category":"Home & Garden",
            "subcategory":"Building Materials",
            "type":"Retail Goods"
        }
    ],
    "sg:phone":"+43 1 98237450",
    "sg:postcode":"1150",
    "sg:province":"Wien",
    "sg:tags":[
        "cutting",
        "laser",
        "cnc"
    ],
    "sg:website":"hermes-novak.at",
    "wof:name":"Hermes Novak Ges.m.b.H.",
    "wof:placetype":"venue"
},
  "geometry": {"coordinates":[16.3156147003,48.1952362061],"type":"Point"}
}