{
  "type": "Feature",
  "properties": {
    "addr:full":"Unterhart 36 Steinhaus Ober\u00f6sterreich 4641",
    "addr:housenumber":"36",
    "addr:postcode":"4641",
    "addr:street":"Unterhart;Oberoesterreich",
    "iso:country":"AT",
    "sg:address":"Unterhart 36",
    "sg:city":"Steinhaus",
    "sg:orig_category":"Stahl / Gro\u00c3\u0178handel",
    "sg:phone":"+43 7242 210017",
    "sg:postcode":"4641",
    "sg:province":"Ober\u00f6sterreich",
    "wof:name":"MAXX-STAHL GmbH",
    "wof:placetype":"venue"
},
  "geometry": {"coordinates":[14.0389623642,48.1120834351],"type":"Point"}
}