{
  "type": "Feature",
  "properties": {
    "addr:full":"Hauptstr 54 Stixneusiedl Nieder\u00f6sterreich 2463",
    "addr:housenumber":"54",
    "addr:postcode":"2463",
    "addr:street":"Hauptstr;Niederoesterreich",
    "iso:country":"AT",
    "sg:address":"Hauptstr 54",
    "sg:city":"Stixneusiedl",
    "sg:orig_category":"Lebensmittel / Einzelhandel",
    "sg:phone":"+43 2230 2709",
    "sg:postcode":"2463",
    "sg:province":"Nieder\u00f6sterreich",
    "wof:name":"Karl Christine",
    "wof:placetype":"venue"
},
  "geometry": {"coordinates":[16.6425819397,48.0535964966],"type":"Point"}
}