{
  "type": "Feature",
  "properties": {
    "addr:full":"Gmundner Str 16 Pinsdorf Ober\u00f6sterreich 4812",
    "addr:housenumber":"16",
    "addr:postcode":"4812",
    "addr:street":"Str",
    "iso:country":"AT",
    "sg:address":"Gmundner Str 16",
    "sg:city":"Pinsdorf",
    "sg:orig_category":"Wasseraufbereitung U -Reinigung",
    "sg:phone":"+43 4376 1266359",
    "sg:postcode":"4812",
    "sg:province":"Ober\u00f6sterreich",
    "wof:name":"Lindsay Austria Pf\u00e4ffle Wasserenth\u00e4rtungsgesmbH",
    "wof:placetype":"venue"
},
  "geometry": {"coordinates":[13.7723789215,47.9292869568],"type":"Point"}
}