{
  "type": "Feature",
  "properties": {
    "addr:full":"F\u00fchrichg 6 Wien Wien 1010",
    "addr:housenumber":"6",
    "addr:postcode":"1010",
    "addr:street":"Fuehrichg",
    "iso:country":"AT",
    "sg:address":"F\u00fchrichg 6",
    "sg:city":"Wien",
    "sg:orig_category":"Steuerberatung",
    "sg:phone":"+43 1 51258630",
    "sg:postcode":"1010",
    "sg:province":"Wien",
    "wof:name":"Akzente WirtschaftstreuhandgesmbH Steuerberatungsges",
    "wof:placetype":"venue"
},
  "geometry": {"coordinates":[16.3688049316,48.2025489807],"type":"Point"}
}