{
  "type": "Feature",
  "properties": {
    "addr:full":"Hauptstr 195-197 Strasshof an der Nordbahn Nieder\u00f6sterreich 2231",
    "addr:housenumber":"195-197",
    "addr:postcode":"2231",
    "addr:street":"Hauptstr",
    "iso:country":"AT",
    "sg:address":"Hauptstr 195-197",
    "sg:city":"Strasshof an der Nordbahn",
    "sg:orig_category":"Lebensmittel / Einzelhandel",
    "sg:phone":"+43 4322 872366",
    "sg:postcode":"2231",
    "sg:province":"Nieder\u00f6sterreich",
    "wof:name":"Zielpunkt Warenhandel GmbH & Co KG",
    "wof:placetype":"venue"
},
  "geometry": {"coordinates":[16.6347618103,48.315990448],"type":"Point"}
}