{
  "type": "Feature",
  "properties": {
    "addr:full":"Triester Str 14 Wiener Neudorf Nieder\u00f6sterreich 2351",
    "addr:postcode":"2351",
    "addr:street":"Str 14",
    "iso:country":"AT",
    "sg:address":"Triester Str 14",
    "sg:city":"Wiener Neudorf",
    "sg:orig_category":"Arbeitsvermittlung",
    "sg:phone":"+43 4322 368050",
    "sg:postcode":"2351",
    "sg:province":"Nieder\u00f6sterreich",
    "wof:name":"Arbeitsmarktservice M\u00f6dling",
    "wof:placetype":"venue"
},
  "geometry": {"coordinates":[16.3118152618,48.0709877014],"type":"Point"}
}