{
  "type": "Feature",
  "properties": {
    "addr:full":"Feldg 55 Deutschfeistritz Steiermark 8121",
    "addr:housenumber":"55",
    "addr:postcode":"8121",
    "addr:street":"Feldg",
    "iso:country":"AT",
    "sg:address":"Feldg 55",
    "sg:city":"Deutschfeistritz",
    "sg:orig_category":"Schneidereien",
    "sg:phone":"+43 4331 2741218",
    "sg:postcode":"8121",
    "sg:province":"Steiermark",
    "wof:name":"Kapfer Johann",
    "wof:placetype":"venue"
},
  "geometry": {"coordinates":[15.3357686996,47.1987991333],"type":"Point"}
}