{
  "type": "Feature",
  "properties": {
    "addr:full":"Ketzerg 411 Wien Wien 1230",
    "addr:housenumber":"411",
    "addr:postcode":"1230",
    "iso:country":"AT",
    "sg:address":"Ketzerg 411",
    "sg:city":"Wien",
    "sg:orig_category":"Restaurants: Chinesisch",
    "sg:phone":"+43 1 8899308",
    "sg:postcode":"1230",
    "sg:province":"Wien",
    "wof:name":"China-Restaurant Lotosblume",
    "wof:placetype":"venue"
},
  "geometry": {"coordinates":[16.2664394379,48.1338272095],"type":"Point"}
}