{
  "type": "Feature",
  "properties": {
    "addr:full":"Moosstr 6 Seekirchen am Wallersee Salzburg 5201",
    "addr:housenumber":"6",
    "addr:postcode":"5201",
    "addr:street":"Moosstr;Salzburg",
    "iso:country":"AT",
    "sg:address":"Moosstr 6",
    "sg:city":"Seekirchen am Wallersee",
    "sg:orig_category":"Handelsagenturen",
    "sg:phone":"+43 6212 7465",
    "sg:postcode":"5201",
    "sg:province":"Salzburg",
    "wof:name":"M\u00f6ssler Franz",
    "wof:placetype":"venue"
},
  "geometry": {"coordinates":[13.1268911362,47.8928718567],"type":"Point"}
}