{
  "type": "Feature",
  "properties": {
    "iso:country":"AT",
    "sg:address":"Siedlungsweg 14",
    "sg:city":"Jochberg",
    "sg:classifiers":[
        {
            "category":"Restaurant",
            "type":"Food & Drink"
        }
    ],
    "sg:phone":"+43 5355 5343",
    "sg:postcode":"6373",
    "sg:province":"Tirol",
    "wof:name":"J\u00fcnger Friedrich",
    "wof:placetype":"venue"
},
  "geometry": {"coordinates":[12.418469429,47.373298645],"type":"Point"}
}