{
  "type": "Feature",
  "properties": {
    "addr:full":"Hauptpl 26-27 Korneuburg Nieder\u00f6sterreich 2100",
    "addr:postcode":"26-27;2100",
    "addr:street":"Niederoesterreich",
    "iso:country":"AT",
    "sg:address":"Hauptpl 26-27",
    "sg:city":"Korneuburg",
    "sg:orig_category":"Apotheken",
    "sg:phone":"+43 4322 62725010",
    "sg:postcode":"2100",
    "sg:province":"Nieder\u00f6sterreich",
    "wof:name":"Kreisapotheke Zum schwarzen Adler Magpharm Richard Kwizda KG",
    "wof:placetype":"venue"
},
  "geometry": {"coordinates":[16.3324928284,48.3438796997],"type":"Point"}
}