{
  "type": "Feature",
  "properties": {
    "addr:full":"Mariahilfer Str 70 Wien Wien 1070",
    "addr:postcode":"1070",
    "addr:street":"Str 70",
    "iso:country":"AT",
    "sg:address":"Mariahilfer Str 70",
    "sg:city":"Wien",
    "sg:orig_category":"Bankomat-Standorte",
    "sg:phone":"+43 5 050557010",
    "sg:postcode":"1070",
    "sg:province":"Wien",
    "wof:name":"Bankomat d Bank Austria Creditanstalt AG",
    "wof:placetype":"venue"
},
  "geometry": {"coordinates":[16.3497219086,48.1983184814],"type":"Point"}
}