{
  "type": "Feature",
  "properties": {
    "addr:full":"Pramerg 6 Wien Wien 1090",
    "addr:housenumber":"6",
    "addr:postcode":"1090",
    "addr:street":"Pramerg",
    "iso:country":"AT",
    "sg:address":"Pramerg 6",
    "sg:city":"Wien",
    "sg:orig_category":"Galerien",
    "sg:phone":"+43 1 3103930",
    "sg:postcode":"1090",
    "sg:province":"Wien",
    "wof:name":"Galerie Heinrich Steinek",
    "wof:placetype":"venue"
},
  "geometry": {"coordinates":[16.3619155884,48.222328186],"type":"Point"}
}