{
  "type": "Feature",
  "properties": {
    "iso:country":"AT",
    "sg:address":"Obdacher Str 577",
    "sg:city":"Bad St. Leonhard im Lavanttal",
    "sg:orig_category":"Autoreparatur",
    "sg:phone":"+43 4343 5022310",
    "sg:postcode":"9462",
    "sg:province":"K\u00e4rnten",
    "wof:name":"Tripolt Peter GmbH",
    "wof:placetype":"venue"
},
  "geometry": {"coordinates":[14.7835092545,46.9707107544],"type":"Point"}
}