{
  "type": "Feature",
  "properties": {
    "iso:country":"AT",
    "sg:address":"Hauptstr 78c",
    "sg:city":"Arzl im Pitztal",
    "sg:classifiers":[
        {
            "category":"Taxi",
            "type":"Transportation"
        }
    ],
    "sg:phone":"+43 4354 1265400",
    "sg:postcode":"6471",
    "sg:province":"Tirol",
    "sg:tags":[
        "personentransporte",
        "u"
    ],
    "wof:name":"Pitztal Reisen - Taxi Walch GesmbH",
    "wof:placetype":"venue"
},
  "geometry": {"coordinates":[10.7617301941,47.2069854736],"type":"Point"}
}