{
  "type": "Feature",
  "properties": {
    "iso:country":"AT",
    "sg:address":"An der Bundesstr",
    "sg:city":"Steinberg-D\u00f6rfl",
    "sg:orig_category":"Raumausstattung",
    "sg:phone":"+43 2612 8498",
    "sg:postcode":"7453",
    "sg:province":"Burgenland",
    "wof:name":"Leidl & Emmer Raumausstatter GesmbH",
    "wof:placetype":"venue"
},
  "geometry": {"coordinates":[16.4869441986,47.4750709534],"type":"Point"}
}