{
  "type": "Feature",
  "properties": {
    "iso:country":"AT",
    "sg:address":"Dampfschiffstr 14",
    "sg:city":"Wien",
    "sg:orig_category":"Schilder",
    "sg:phone":"+43 4317 126219",
    "sg:postcode":"1030",
    "sg:province":"Wien",
    "sg:website":"reitmaier.at/",
    "wof:name":"Reitmaier Stempel & Schilder GesmbH",
    "wof:placetype":"venue"
},
  "geometry": {"coordinates":[16.3902511597,48.2127304077],"type":"Point"}
}