{
  "type": "Feature",
  "properties": {
    "iso:country":"AT",
    "sg:address":"Wiener Str 10",
    "sg:city":"Hainfeld",
    "sg:orig_category":"Schneidereien",
    "sg:phone":"+43 2764 3174",
    "sg:postcode":"3170",
    "sg:province":"Nieder\u00f6sterreich",
    "wof:name":"Schildb\u00f6ck Elfriede",
    "wof:placetype":"venue"
},
  "geometry": {"coordinates":[15.775390625,48.0340576172],"type":"Point"}
}