{
  "type": "Feature",
  "properties": {
    "addr:full":"Weideng 3 G\u00fcssing Burgenland 7540",
    "addr:housenumber":"3",
    "addr:postcode":"7540",
    "addr:street":"Weideng",
    "iso:country":"AT",
    "sg:address":"Weideng 3",
    "sg:city":"G\u00fcssing",
    "sg:classifiers":[
        {
            "category":"Organizations",
            "subcategory":"Community Association",
            "type":"Services"
        }
    ],
    "sg:phone":"+43 4366 41918034",
    "sg:postcode":"7540",
    "sg:province":"Burgenland",
    "sg:tags":[
        "relation",
        "public"
    ],
    "wof:name":"Public Suxess",
    "wof:placetype":"venue"
},
  "geometry": {"coordinates":[16.3329257965,47.0626983643],"type":"Point"}
}