{
  "type": "Feature",
  "properties": {
    "addr:full":"Weissenbach Bachstr 30 Gloggnitz Nieder\u00f6sterreich 2640",
    "addr:housenumber":"30",
    "addr:postcode":"2640",
    "addr:street":"Weissenbach Bachstr",
    "iso:country":"AT",
    "sg:address":"Weissenbach Bachstr 30",
    "sg:city":"Gloggnitz",
    "sg:orig_category":"Baumschulen",
    "sg:phone":"+43 4326 6244316",
    "sg:postcode":"2640",
    "sg:province":"Nieder\u00f6sterreich",
    "wof:name":"Baumschule Schwarz",
    "wof:placetype":"venue"
},
  "geometry": {"coordinates":[15.9231367111,47.6624641418],"type":"Point"}
}