{
  "type": "Feature",
  "properties": {
    "iso:country":"AT",
    "sg:address":"Andreas-Hofer-Str 21a",
    "sg:city":"Salzburg",
    "sg:classifiers":[
        {
            "category":"Personal",
            "subcategory":"Sauna",
            "type":"Services"
        }
    ],
    "sg:phone":"+43 4366 2459598",
    "sg:postcode":"5020",
    "sg:province":"Salzburg",
    "sg:tags":[
        "u",
        "dampfbad"
    ],
    "wof:name":"Sporrer Birgit",
    "wof:placetype":"venue"
},
  "geometry": {"coordinates":[13.0429019928,47.8207550049],"type":"Point"}
}