{
  "type": "Feature",
  "properties": {
    "addr:full":"G\u00fcrtelstr Traiskirchen Nieder\u00f6sterreich 2514",
    "addr:postcode":"2514",
    "addr:street":"Niederoesterreich",
    "iso:country":"AT",
    "sg:address":"G\u00fcrtelstr",
    "sg:city":"Traiskirchen",
    "sg:orig_category":"Tabaktrafiken",
    "sg:phone":"+43 2252 54208",
    "sg:postcode":"2514",
    "sg:province":"Nieder\u00f6sterreich",
    "wof:name":"Imber Erna",
    "wof:placetype":"venue"
},
  "geometry": {"coordinates":[16.2946777344,48.0138092041],"type":"Point"}
}