{
  "type": "Feature",
  "properties": {
    "addr:full":"Am Arlandgrund 45 Andritz Steiermark 8045",
    "addr:housenumber":"45",
    "addr:postcode":"8045",
    "addr:street":"Am Arlandgrund",
    "iso:country":"AT",
    "sg:address":"Am Arlandgrund 45",
    "sg:city":"Andritz",
    "sg:orig_category":"Psychologen",
    "sg:phone":"+43 316 688365",
    "sg:postcode":"8045",
    "sg:province":"Steiermark",
    "wof:name":"Graf Iris Mag",
    "wof:placetype":"venue"
},
  "geometry": {"coordinates":[15.4150390625,47.0995178223],"type":"Point"}
}