{
  "type": "Feature",
  "properties": {
    "addr:full":"Adalbert Stifter-Str 68 Pasching Ober\u00f6sterreich 4061",
    "addr:housenumber":"68",
    "addr:postcode":"4061",
    "addr:street":"Adalbert;Oberoesterreich",
    "iso:country":"AT",
    "sg:address":"Adalbert Stifter-Str 68",
    "sg:city":"Pasching",
    "sg:orig_category":"Banken U Sparkassen",
    "sg:phone":"+43 7229 618770",
    "sg:postcode":"4061",
    "sg:province":"Ober\u00f6sterreich",
    "wof:name":"VKB-Bank Volkskreditbank AG",
    "wof:placetype":"venue"
},
  "geometry": {"coordinates":[14.2412853241,48.2426490784],"type":"Point"}
}