{
  "type": "Feature",
  "properties": {
    "addr:full":"Grenzweg 162 Gro\u00dfgmain Salzburg 5084",
    "addr:housenumber":"162",
    "addr:postcode":"5084",
    "addr:street":"Grenzweg;Salzburg",
    "iso:country":"AT",
    "sg:address":"Grenzweg 162",
    "sg:city":"Gro\u00dfgmain",
    "sg:classifiers":[
        {
            "category":"Professional",
            "subcategory":"Computer Services",
            "type":"Services"
        }
    ],
    "sg:phone":"+43 6247 8798",
    "sg:postcode":"5084",
    "sg:province":"Salzburg",
    "sg:tags":[
        "software"
    ],
    "wof:name":"DVC Computing Software Service GmbH",
    "wof:placetype":"venue"
},
  "geometry": {"coordinates":[12.0809497833,48.0439414978],"type":"Point"}
}