{
  "type": "Feature",
  "properties": {
    "iso:country":"AT",
    "sg:address":"Marktplatz 4",
    "sg:city":"Feldkirchen an der Donau",
    "sg:classifiers":[
        {
            "category":"Home & Garden",
            "subcategory":"Building Materials",
            "type":"Retail Goods"
        }
    ],
    "sg:phone":"+43 7233 7263",
    "sg:postcode":"4101",
    "sg:province":"Ober\u00f6sterreich",
    "sg:tags":[
        "gravel",
        "crushed"
    ],
    "wof:name":"Georg Sprengseis Ges.m.b.H. & Co KG",
    "wof:placetype":"venue"
},
  "geometry": {"coordinates":[14.0522880554,48.3452720642],"type":"Point"}
}