{
  "type": "Feature",
  "properties": {
    "addr:full":"Greiner Str. 70 Kremsm\u00fcnster Ober\u00f6sterreich 4550",
    "addr:postcode":"4550",
    "addr:street":"Str. 70 Kremsmuenster Oberoesterreich",
    "iso:country":"AT",
    "sg:address":"Greiner Str. 70",
    "sg:city":"Kremsm\u00fcnster",
    "sg:classifiers":[
        {
            "category":"Manufacturing",
            "subcategory":"Paper Products",
            "type":"Manufacturing & Wholesale Goods"
        }
    ],
    "sg:phone":"+43 4375 837251",
    "sg:postcode":"4550",
    "sg:province":"Ober\u00f6sterreich",
    "sg:tags":[
        "cardboard"
    ],
    "wof:name":"GREINER VERPACKUNGEN GMBH",
    "wof:placetype":"venue"
},
  "geometry": {"coordinates":[14.120349884,48.0394210815],"type":"Point"}
}