{
  "type": "Feature",
  "properties": {
    "addr:full":"Salvatorg 3/18 Wien Wien 1010",
    "addr:housenumber":"3 / 18",
    "addr:postcode":"1010",
    "addr:street":"Salvatorg",
    "iso:country":"AT",
    "sg:address":"Salvatorg 3/18",
    "sg:city":"Wien",
    "sg:orig_category":"Steuerberatung",
    "sg:phone":"+43 1 5355238",
    "sg:postcode":"1010",
    "sg:province":"Wien",
    "wof:name":"Knipp Andreas Mag",
    "wof:placetype":"venue"
},
  "geometry": {"coordinates":[16.3719463348,48.2116851807],"type":"Point"}
}