{
  "type": "Feature",
  "properties": {
    "addr:full":"Nr 78 St. Peter im Sulmtal Steiermark 8542",
    "addr:postcode":"8542",
    "addr:street":"Nr 78",
    "iso:country":"AT",
    "sg:address":"Nr 78",
    "sg:city":"St. Peter im Sulmtal",
    "sg:orig_category":"Feuerwehren",
    "sg:phone":"+43 3467 7100",
    "sg:postcode":"8542",
    "sg:province":"Steiermark",
    "wof:name":"Freiwillige Feuerwehr St Peter i Sulmtal",
    "wof:placetype":"venue"
},
  "geometry": {"coordinates":[15.2506084442,46.7571640015],"type":"Point"}
}