{
  "type": "Feature",
  "properties": {
    "iso:country":"AT",
    "sg:address":"Villacher Str 53",
    "sg:city":"Klagenfurt",
    "sg:orig_category":"Textilreinigung",
    "sg:phone":"+43 463 25666",
    "sg:postcode":"9020",
    "sg:province":"K\u00e4rnten",
    "wof:name":"Benda Berta",
    "wof:placetype":"venue"
},
  "geometry": {"coordinates":[14.3019475937,46.6270751953],"type":"Point"}
}