{
  "type": "Feature",
  "properties": {
    "iso:country":"AT",
    "sg:address":"Tokiostr 10",
    "sg:city":"Wien",
    "sg:classifiers":[
        {
            "category":"Taxi",
            "type":"Transportation"
        }
    ],
    "sg:phone":"+43 4366 41337650",
    "sg:postcode":"1220",
    "sg:province":"Wien",
    "sg:tags":[
        "personentransporte",
        "u"
    ],
    "wof:name":"Mikhail Sameh GesmbH",
    "wof:placetype":"venue"
},
  "geometry": {"coordinates":[16.4304027557,48.2487335205],"type":"Point"}
}