{
  "type": "Feature",
  "properties": {
    "addr:full":"Wahringerstr 36 Linz Ober\u00f6sterreich 4030",
    "addr:housenumber":"36",
    "addr:postcode":"4030",
    "addr:street":"Wahringerstr",
    "iso:country":"AT",
    "sg:address":"Wahringerstr 36",
    "sg:city":"Linz",
    "sg:orig_category":"Maschinenbestand- U Ersatzteile",
    "sg:phone":"+43 732 65858414",
    "sg:postcode":"4030",
    "sg:province":"Ober\u00f6sterreich",
    "wof:name":"HOTECH GesmbH",
    "wof:placetype":"venue"
},
  "geometry": {"coordinates":[14.3224287033,48.2645149231],"type":"Point"}
}