{
  "type": "Feature",
  "properties": {
    "iso:country":"AT",
    "sg:address":"Moosmahdstr. 39 ",
    "sg:city":"Dornbirn",
    "sg:classifiers":[
        {
            "category":"Professional",
            "subcategory":"Printing & Photocopies",
            "type":"Services"
        }
    ],
    "sg:phone":"+43 4355 7222213",
    "sg:postcode":"6850",
    "sg:province":"Vorarlberg",
    "wof:name":"HUGO MAYER GES.MBH & CO KG",
    "wof:placetype":"venue"
},
  "geometry": {"coordinates":[9.7339839935,47.4105873108],"type":"Point"}
}