{
  "type": "Feature",
  "properties": {
    "addr:full":"Reinprechtsdorf Str 48 Wien Wien 1050",
    "addr:housenumber":"48",
    "addr:postcode":"1050",
    "addr:street":"Reinprechtsdorf Str",
    "iso:country":"AT",
    "sg:address":"Reinprechtsdorf Str 48",
    "sg:city":"Wien",
    "sg:orig_category":"Zahntechnische Laboratorien",
    "sg:phone":"+43 1 5457272",
    "sg:postcode":"1050",
    "sg:province":"Wien",
    "wof:name":"Frommherz Peter Dentaltechnik",
    "wof:placetype":"venue"
},
  "geometry": {"coordinates":[16.3534927368,48.1864547729],"type":"Point"}
}