{
  "type": "Feature",
  "properties": {
    "iso:country":"AT",
    "sg:address":"Karl-Punzer-Str 16",
    "sg:city":"Steyr",
    "sg:orig_category":"Drogerien",
    "sg:phone":"+43 4372 52869860",
    "sg:postcode":"4400",
    "sg:province":"Ober\u00f6sterreich",
    "wof:name":"Drogerie Pfeiffer",
    "wof:placetype":"venue"
},
  "geometry": {"coordinates":[14.4423770905,48.0511894226],"type":"Point"}
}