{
  "type": "Feature",
  "properties": {
    "addr:full":"Salzburger Str 34 Radstadt Salzburg 5550",
    "addr:housenumber":"34",
    "addr:postcode":"5550",
    "addr:street":"Salzburger Str;Salzburg",
    "iso:country":"AT",
    "sg:address":"Salzburger Str 34",
    "sg:city":"Radstadt",
    "sg:orig_category":"Tankstellen",
    "sg:phone":"+43 6452 4382",
    "sg:postcode":"5550",
    "sg:province":"Salzburg",
    "wof:name":"Agip Austria GmbH",
    "wof:placetype":"venue"
},
  "geometry": {"coordinates":[13.4505805969,47.3868141174],"type":"Point"}
}