{
  "type": "Feature",
  "properties": {
    "addr:full":"Bahnhofstr 288 Zell am See Salzburg 5700",
    "addr:housenumber":"288",
    "addr:postcode":"5700",
    "addr:street":"Bahnhofstr;Salzburg",
    "iso:country":"AT",
    "sg:address":"Bahnhofstr 288",
    "sg:city":"Zell am See",
    "sg:orig_category":"Drogerien",
    "sg:phone":"+43 6542 72081",
    "sg:postcode":"5700",
    "sg:province":"Salzburg",
    "wof:name":"dm drogerie markt GmbH",
    "wof:placetype":"venue"
},
  "geometry": {"coordinates":[12.7968139648,47.3213348389],"type":"Point"}
}