{
  "type": "Feature",
  "properties": {
    "addr:full":"Nr 94 Strass im Zillertal Tirol 6261",
    "addr:postcode":"6261",
    "addr:street":"Nr;Strass;Zillertal Tirol",
    "iso:country":"AT",
    "sg:address":"Nr 94",
    "sg:city":"Strass im Zillertal",
    "sg:orig_category":"Polizei U Gendarmerie",
    "sg:phone":"+43 4359 1337255",
    "sg:postcode":"6261",
    "sg:province":"Tirol",
    "wof:name":"Gendarmerie",
    "wof:placetype":"venue"
},
  "geometry": {"coordinates":[11.8219985962,47.3957252502],"type":"Point"}
}