{
  "type": "Feature",
  "properties": {
    "addr:full":"Nr 92 Sigharting Ober\u00f6sterreich 4771",
    "addr:postcode":"4771",
    "addr:street":"Nr 92",
    "iso:country":"AT",
    "sg:address":"Nr 92",
    "sg:city":"Sigharting",
    "sg:orig_category":"Abfallentsorgung U -Verwertung",
    "sg:phone":"+43 7766 22200",
    "sg:postcode":"4771",
    "sg:province":"Ober\u00f6sterreich",
    "wof:name":"Bezirksabfallverband Sch\u00e4rding",
    "wof:placetype":"venue"
},
  "geometry": {"coordinates":[13.5986776352,48.3950500488],"type":"Point"}
}