{
  "type": "Feature",
  "properties": {
    "addr:full":"Mariahilfstr 30 Innsbruck Tirol 6020",
    "addr:housenumber":"30",
    "addr:postcode":"6020",
    "addr:street":"Mariahilfstr;Tirol",
    "iso:country":"AT",
    "sg:address":"Mariahilfstr 30",
    "sg:city":"Innsbruck",
    "sg:orig_category":"Autohandel",
    "sg:phone":"+43 512 283998",
    "sg:postcode":"6020",
    "sg:province":"Tirol",
    "wof:name":"Balta & Co OEG",
    "wof:placetype":"venue"
},
  "geometry": {"coordinates":[11.3889894485,47.2682342529],"type":"Point"}
}