{
  "type": "Feature",
  "properties": {
    "addr:full":"Kircheng 2 Knittelfeld Steiermark 8720",
    "addr:housenumber":"2",
    "addr:postcode":"8720",
    "addr:street":"Kircheng",
    "iso:country":"AT",
    "sg:address":"Kircheng 2",
    "sg:city":"Knittelfeld",
    "sg:orig_category":"Textilreinigung",
    "sg:phone":"+43 4335 1283073",
    "sg:postcode":"8720",
    "sg:province":"Steiermark",
    "wof:name":"Textilreinigung Proprentner",
    "wof:placetype":"venue"
},
  "geometry": {"coordinates":[14.8295679092,47.2136764526],"type":"Point"}
}