{
  "type": "Feature",
  "properties": {
    "addr:full":"Claudiastr 205 Seefeld in Tirol Tirol 6100",
    "addr:housenumber":"205",
    "addr:postcode":"6100",
    "addr:street":"Seefeld;Tirol",
    "iso:country":"AT",
    "sg:address":"Claudiastr 205",
    "sg:city":"Seefeld in Tirol",
    "sg:orig_category":"Appartements / Ferienwohnungen",
    "sg:phone":"+43 4352 122038",
    "sg:postcode":"6100",
    "sg:province":"Tirol",
    "wof:name":"Appartementhaus Max Liebl",
    "wof:placetype":"venue"
},
  "geometry": {"coordinates":[11.192278862,47.3305969238],"type":"Point"}
}