{
  "type": "Feature",
  "properties": {
    "addr:full":"Laurschweg 23 Fiss Tirol 6533",
    "addr:housenumber":"23",
    "addr:postcode":"6533",
    "addr:street":"Laurschweg;Tirol",
    "iso:country":"AT",
    "sg:address":"Laurschweg 23",
    "sg:city":"Fiss",
    "sg:classifiers":[
        {
            "category":"Travel",
            "subcategory":"Hotels & Motels",
            "type":"Entertainment"
        }
    ],
    "sg:phone":"+43 5476 67140",
    "sg:postcode":"6533",
    "sg:province":"Tirol",
    "wof:name":"Familienhotel St.Laurentius",
    "wof:placetype":"venue"
},
  "geometry": {"coordinates":[10.6111803055,47.0548439026],"type":"Point"}
}