{
  "type": "Feature",
  "properties": {
    "addr:full":"Hauptstr 5 Aspang-Markt Nieder\u00f6sterreich 2870",
    "addr:housenumber":"5",
    "addr:postcode":"2870",
    "addr:street":"Hauptstr;Niederoesterreich",
    "iso:country":"AT",
    "sg:address":"Hauptstr 5",
    "sg:city":"Aspang-Markt",
    "sg:orig_category":"Tabaktrafiken",
    "sg:phone":"+43 2642 52635",
    "sg:postcode":"2870",
    "sg:province":"Nieder\u00f6sterreich",
    "wof:name":"Rauscher Walter",
    "wof:placetype":"venue"
},
  "geometry": {"coordinates":[16.0897388458,47.5535697937],"type":"Point"}
}