{
  "type": "Feature",
  "properties": {
    "iso:country":"AT",
    "sg:address":"Hauptstrasse 2a",
    "sg:city":"Strasshof an der Nordbahn",
    "sg:classifiers":[
        {
            "category":"Banks & Credit Unions",
            "subcategory":"Investment Brokerage",
            "type":"Services"
        }
    ],
    "sg:phone":"+43 2287 2468",
    "sg:postcode":"2231",
    "sg:province":"Nieder\u00f6sterreich",
    "sg:tags":[
        "work",
        "bituminous",
        "surfacing"
    ],
    "wof:name":"Josef Wagner Ges.m.b.H",
    "wof:placetype":"venue"
},
  "geometry": {"coordinates":[16.6106395721,48.3223457336],"type":"Point"}
}