{
  "type": "Feature",
  "properties": {
    "iso:country":"AT",
    "sg:address":"Kaplanstr 9",
    "sg:city":"Freistadt",
    "sg:orig_category":"Holzhandel",
    "sg:phone":"+43 4379 4274166",
    "sg:postcode":"4240",
    "sg:province":"Ober\u00f6sterreich",
    "wof:name":"Max's Holzfachmarkt u Montagetischlerei Markus Gattringer",
    "wof:placetype":"venue"
},
  "geometry": {"coordinates":[14.5037755966,48.4941596985],"type":"Point"}
}