{
  "type": "Feature",
  "properties": {
    "iso:country":"AT",
    "sg:address":"Prof.-Franz-Spath-Ring 55",
    "sg:city":"St. Peter",
    "sg:orig_category":"Massagen",
    "sg:phone":"+43 4331 6462798",
    "sg:postcode":"8042",
    "sg:province":"Steiermark",
    "wof:name":"Tropper Maria",
    "wof:placetype":"venue"
},
  "geometry": {"coordinates":[15.4764499664,47.0591583252],"type":"Point"}
}