{
  "type": "Feature",
  "properties": {
    "addr:full":"Heimsdlg 47 Kapfenberg Steiermark 8605",
    "addr:housenumber":"47",
    "addr:postcode":"8605",
    "addr:street":"Heimsdlg",
    "iso:country":"AT",
    "sg:address":"Heimsdlg 47",
    "sg:city":"Kapfenberg",
    "sg:orig_category":"Blumenbinder",
    "sg:phone":"+43 3862 32266",
    "sg:postcode":"8605",
    "sg:province":"Steiermark",
    "wof:name":"Knau\u00df G\u00fcnter",
    "wof:placetype":"venue"
},
  "geometry": {"coordinates":[15.2912454605,47.4438438416],"type":"Point"}
}