{
  "type": "Feature",
  "properties": {
    "addr:full":"Weilhartstrasse 42  Ostermiething Ober\u00f6sterreich 5121",
    "addr:housenumber":"42",
    "addr:postcode":"5121",
    "addr:street":"Weilhartstrasse",
    "iso:country":"AT",
    "sg:address":"Weilhartstrasse 42 ",
    "sg:city":"Ostermiething",
    "sg:classifiers":[
        {
            "category":"Building & Trades",
            "subcategory":"Plumbing",
            "type":"Services"
        }
    ],
    "sg:phone":"+43 6278 6315",
    "sg:postcode":"5121",
    "sg:province":"Ober\u00f6sterreich",
    "sg:tags":[
        "supraregional",
        "gas"
    ],
    "wof:name":"Georg H\u00e4usler",
    "wof:placetype":"venue"
},
  "geometry": {"coordinates":[12.8303232193,48.045589447],"type":"Point"}
}