{
  "type": "Feature",
  "properties": {
    "iso:country":"AT",
    "sg:address":"Eitnerg. 5a",
    "sg:city":"Wien",
    "sg:classifiers":[
        {
            "category":"Professional",
            "subcategory":"Engineering",
            "type":"Services"
        }
    ],
    "sg:phone":"+43 4318 6595360",
    "sg:postcode":"1230",
    "sg:province":"Wien",
    "sg:tags":[
        "machine",
        "-",
        "mechanical"
    ],
    "wof:name":"HEIZB\u00d6SCH KG W. B\u00d6SCH",
    "wof:placetype":"venue"
},
  "geometry": {"coordinates":[16.3102607727,48.1388282776],"type":"Point"}
}