{
  "type": "Feature",
  "properties": {
    "addr:full":"Leystr Wien Wien 1200",
    "addr:postcode":"1200",
    "iso:country":"AT",
    "sg:address":"Leystr",
    "sg:city":"Wien",
    "sg:orig_category":"Non-Classified Establishments",
    "sg:phone":"+43 1 3324928",
    "sg:postcode":"1200",
    "sg:province":"Wien",
    "wof:name":"TAXI-TEL Standplatztelefon Betriebs GmbH",
    "wof:placetype":"venue"
},
  "geometry": {"coordinates":[16.3749446869,48.2473907471],"type":"Point"}
}