{
  "type": "Feature",
  "properties": {
    "addr:full":"Zaillachweg 16 Kammern im Liesingtal Steiermark 8773",
    "addr:housenumber":"16",
    "addr:postcode":"8773",
    "addr:street":"Zaillachweg",
    "iso:country":"AT",
    "sg:address":"Zaillachweg 16",
    "sg:city":"Kammern im Liesingtal",
    "sg:orig_category":"Tischlereien",
    "sg:phone":"+43 4338 448756",
    "sg:postcode":"8773",
    "sg:province":"Steiermark",
    "wof:name":"Graf Martin",
    "wof:placetype":"venue"
},
  "geometry": {"coordinates":[14.8898515701,47.3926887512],"type":"Point"}
}