{
  "type": "Feature",
  "properties": {
    "addr:full":"Hauptstr 30 Mannersdorf am Leithagebirge Nieder\u00f6sterreich 2452",
    "addr:housenumber":"30",
    "addr:postcode":"2452",
    "addr:street":"Hauptstr",
    "iso:country":"AT",
    "sg:address":"Hauptstr 30",
    "sg:city":"Mannersdorf am Leithagebirge",
    "sg:orig_category":"Lebensmittel / Einzelhandel",
    "sg:phone":"+43 2168 62489",
    "sg:postcode":"2452",
    "sg:province":"Nieder\u00f6sterreich",
    "wof:name":"METIN DOGAN KEG",
    "wof:placetype":"venue"
},
  "geometry": {"coordinates":[16.6016521454,47.9732055664],"type":"Point"}
}