{
  "type": "Feature",
  "properties": {
    "iso:country":"AT",
    "sg:address":"Seitenstettner Str 28",
    "sg:city":"Steyr",
    "sg:orig_category":"Estriche",
    "sg:phone":"+43 7252 76458",
    "sg:postcode":"4400",
    "sg:province":"Ober\u00f6sterreich",
    "wof:name":"Belags-Technik GesmbH",
    "wof:placetype":"venue"
},
  "geometry": {"coordinates":[14.4473514557,48.0449943542],"type":"Point"}
}