{
  "type": "Feature",
  "properties": {
    "addr:full":"Rauhensteing 7 Wien Wien 1010",
    "addr:housenumber":"7",
    "addr:postcode":"1010",
    "addr:street":"Rauhensteing",
    "iso:country":"AT",
    "sg:address":"Rauhensteing 7",
    "sg:city":"Wien",
    "sg:classifiers":[
        {
            "category":"Taxi",
            "type":"Transportation"
        }
    ],
    "sg:phone":"+43 4366 49122548",
    "sg:postcode":"1010",
    "sg:province":"Wien",
    "sg:tags":[
        "personentransporte",
        "u"
    ],
    "wof:name":"Frey Rosita",
    "wof:placetype":"venue"
},
  "geometry": {"coordinates":[16.3726139069,48.2059059143],"type":"Point"}
}