{
  "type": "Feature",
  "properties": {
    "addr:full":"Hochfeldstr 1 Alkoven Ober\u00f6sterreich 4072",
    "addr:housenumber":"1",
    "addr:postcode":"4072",
    "addr:street":"Hochfeldstr",
    "iso:country":"AT",
    "sg:address":"Hochfeldstr 1",
    "sg:city":"Alkoven",
    "sg:orig_category":"Apotheken",
    "sg:phone":"+43 7274 8920",
    "sg:postcode":"4072",
    "sg:province":"Ober\u00f6sterreich",
    "wof:name":"Apotheke Mag pharm Anton Past",
    "wof:placetype":"venue"
},
  "geometry": {"coordinates":[14.1184053421,48.288860321],"type":"Point"}
}