{
  "type": "Feature",
  "properties": {
    "iso:country":"AT",
    "sg:address":"Kirchenpl 4",
    "sg:city":"Gro\u00df-Enzersdorf",
    "sg:orig_category":"Fleischhauereien",
    "sg:phone":"+43 2249 2321",
    "sg:postcode":"2301",
    "sg:province":"Nieder\u00f6sterreich",
    "wof:name":"Neumayer GesmbH",
    "wof:placetype":"venue"
},
  "geometry": {"coordinates":[16.5499267578,48.2031364441],"type":"Point"}
}