{
  "type": "Feature",
  "properties": {
    "addr:full":"Koflergasse 4 Wien Wien 1120",
    "addr:housenumber":"4",
    "addr:postcode":"1120",
    "addr:street":"Koflergasse",
    "iso:country":"AT",
    "sg:address":"Koflergasse 4",
    "sg:city":"Wien",
    "sg:classifiers":[
        {
            "category":"Professional",
            "subcategory":"Accounting & Tax Preparation",
            "type":"Services"
        }
    ],
    "sg:phone":"+43 1 8159370",
    "sg:postcode":"1120",
    "sg:province":"Wien",
    "sg:tags":[
        "book-keeping"
    ],
    "wof:name":"Peter Burgmann",
    "wof:placetype":"venue"
},
  "geometry": {"coordinates":[16.3449478149,48.1819076538],"type":"Point"}
}