{
  "type": "Feature",
  "properties": {
    "addr:full":"Riedstr 6 Lauterach Vorarlberg 6923",
    "addr:housenumber":"6",
    "addr:postcode":"6923",
    "addr:street":"Riedstr",
    "iso:country":"AT",
    "sg:address":"Riedstr 6",
    "sg:city":"Lauterach",
    "sg:orig_category":"Installationsunternehmen",
    "sg:phone":"+43 4355 7476492",
    "sg:postcode":"6923",
    "sg:province":"Vorarlberg",
    "wof:name":"W\u00e4rme & Wassertechnik Raimund Grabher",
    "wof:placetype":"venue"
},
  "geometry": {"coordinates":[9.7212667465,47.473991394],"type":"Point"}
}