{
  "type": "Feature",
  "properties": {
    "addr:full":"Gaudergasse 21a Zell am Ziller Tirol 6280",
    "addr:housenumber":"21a",
    "addr:postcode":"6280",
    "addr:street":"Gaudergasse;Tirol",
    "iso:country":"AT",
    "sg:address":"Gaudergasse 21a",
    "sg:city":"Zell am Ziller",
    "sg:orig_category":"Cnc Cutting, Cnc Chip Removal",
    "sg:phone":"+43 5282 22450",
    "sg:postcode":"6280",
    "sg:province":"Tirol",
    "sg:website":"langesee.at",
    "wof:name":"Hans Langesee Ges.m.b.H. Antriebselemente - CNC-Zerspanungstechnik",
    "wof:placetype":"venue"
},
  "geometry": {"coordinates":[11.8876190186,47.2299766541],"type":"Point"}
}