{
  "type": "Feature",
  "properties": {
    "addr:full":"Loitzendorf 19 Alberndorf in der Riedmark Ober\u00f6sterreich 4211",
    "addr:housenumber":"19",
    "addr:postcode":"4211",
    "addr:street":"Loitzendorf",
    "iso:country":"AT",
    "sg:address":"Loitzendorf 19",
    "sg:city":"Alberndorf in der Riedmark",
    "sg:orig_category":"Installationsunternehmen",
    "sg:phone":"+43 4372 357490",
    "sg:postcode":"4211",
    "sg:province":"Ober\u00f6sterreich",
    "wof:name":"Ganglberger Herbert",
    "wof:placetype":"venue"
},
  "geometry": {"coordinates":[14.4462718964,48.4022903442],"type":"Point"}
}