{
  "type": "Feature",
  "properties": {
    "addr:full":"K\u00f6chelstr 10 Salzburg Salzburg 5020",
    "addr:housenumber":"10",
    "addr:postcode":"5020",
    "addr:street":"Koechelstr;Salzburg",
    "iso:country":"AT",
    "sg:address":"K\u00f6chelstr 10",
    "sg:city":"Salzburg",
    "sg:orig_category":"Handelsagenturen",
    "sg:phone":"+43 662 820985",
    "sg:postcode":"5020",
    "sg:province":"Salzburg",
    "wof:name":"Berger Herbert",
    "wof:placetype":"venue"
},
  "geometry": {"coordinates":[13.0342178345,47.7768783569],"type":"Point"}
}