{
  "type": "Feature",
  "properties": {
    "addr:full":"Burgg 105/9 Wien Wien 1070",
    "addr:housenumber":"105 / 9",
    "addr:postcode":"1070",
    "iso:country":"AT",
    "sg:address":"Burgg 105/9",
    "sg:city":"Wien",
    "sg:orig_category":"Musikgruppen",
    "sg:phone":"+43 664 3012818",
    "sg:postcode":"1070",
    "sg:province":"Wien",
    "wof:name":"Ninic Slavko Mag",
    "wof:placetype":"venue"
},
  "geometry": {"coordinates":[16.3409252167,48.2042732239],"type":"Point"}
}