{
  "type": "Feature",
  "properties": {
    "addr:full":"Feldkirchenstr 50 Kalsdorf Steiermark 8401",
    "addr:housenumber":"50",
    "addr:postcode":"8401",
    "addr:street":"Feldkirchenstr",
    "iso:country":"AT",
    "sg:address":"Feldkirchenstr 50",
    "sg:city":"Kalsdorf",
    "sg:orig_category":"Transportunternehmen",
    "sg:phone":"+43 3135 544320",
    "sg:postcode":"8401",
    "sg:province":"Steiermark",
    "wof:name":"Drei-S Transport GesmbH",
    "wof:placetype":"venue"
},
  "geometry": {"coordinates":[15.4587478638,46.9721832275],"type":"Point"}
}