{
  "type": "Feature",
  "properties": {
    "addr:full":"Eggenstall 150 St. Leonhard im Pitztal Tirol 6481",
    "addr:housenumber":"150",
    "addr:postcode":"6481",
    "addr:street":"Eggenstall;Tirol",
    "iso:country":"AT",
    "sg:address":"Eggenstall 150",
    "sg:city":"St. Leonhard im Pitztal",
    "sg:orig_category":"Tischlereien",
    "sg:phone":"+43 4354 1387228",
    "sg:postcode":"6481",
    "sg:province":"Tirol",
    "wof:name":"Eiter Herbert",
    "wof:placetype":"venue"
},
  "geometry": {"coordinates":[10.843211174,47.0711975098],"type":"Point"}
}