{
  "type": "Feature",
  "properties": {
    "addr:full":"Eisenst\u00e4dter Str 55 Breitenbrunn Burgenland 7091",
    "addr:postcode":"7091",
    "addr:street":"Str 55",
    "iso:country":"AT",
    "sg:address":"Eisenst\u00e4dter Str 55",
    "sg:city":"Breitenbrunn",
    "sg:orig_category":"Ingenieurkonsulenten / Zivilingenieure",
    "sg:phone":"+43 2683 70170",
    "sg:postcode":"7091",
    "sg:province":"Burgenland",
    "wof:name":"Fuchs Philipp Dipl-Ing",
    "wof:placetype":"venue"
},
  "geometry": {"coordinates":[16.7291240692,47.940990448],"type":"Point"}
}