{
  "type": "Feature",
  "properties": {
    "iso:country":"AT",
    "sg:city":"Altm\u00fcnster",
    "sg:classifiers":[
        {
            "category":"Taxi",
            "type":"Transportation"
        }
    ],
    "sg:phone":"+43 4376 121713",
    "sg:postcode":"4813",
    "sg:province":"Ober\u00f6sterreich",
    "sg:tags":[
        "personentransporte",
        "u"
    ],
    "wof:name":"Holzleitner Friedrich",
    "wof:placetype":"venue"
},
  "geometry": {"coordinates":[146.77166748050001,-19.2821292877],"type":"Point"}
}