{
  "type": "Feature",
  "properties": {
    "iso:country":"AT",
    "sg:address":"Stubnerkogel",
    "sg:city":"Bad Gastein",
    "sg:classifiers":[
        {
            "category":"Restaurant",
            "type":"Food & Drink"
        }
    ],
    "sg:phone":"+43 6432 7314",
    "sg:postcode":"5640",
    "sg:province":"Salzburg",
    "wof:name":"Restaurant Stubneralm - Skih\u00fctte Hans Buchner",
    "wof:placetype":"venue"
},
  "geometry": {"coordinates":[13.098818779,47.1247749329],"type":"Point"}
}