{
  "type": "Feature",
  "properties": {
    "addr:full":"Mozartstr 26 Linz Ober\u00f6sterreich 4020",
    "addr:housenumber":"26",
    "addr:postcode":"4020",
    "addr:street":"Mozartstr",
    "iso:country":"AT",
    "sg:address":"Mozartstr 26",
    "sg:city":"Linz",
    "sg:orig_category":"Raumausstattung",
    "sg:phone":"+43 4373 2770541",
    "sg:postcode":"4020",
    "sg:province":"Ober\u00f6sterreich",
    "wof:name":"HERZOG Raumausstattung",
    "wof:placetype":"venue"
},
  "geometry": {"coordinates":[14.2951602936,48.3018836975],"type":"Point"}
}