{
  "type": "Feature",
  "properties": {
    "addr:full":"Sechshauser Str 83 Wien Wien 1150",
    "addr:postcode":"1150",
    "addr:street":"83",
    "iso:country":"AT",
    "sg:address":"Sechshauser Str 83",
    "sg:city":"Wien",
    "sg:orig_category":"Abfallentsorgung U -Verwertung",
    "sg:phone":"+43 1 89208140",
    "sg:postcode":"1150",
    "sg:province":"Wien",
    "wof:name":"GUA Gesellschaft f umfassende Analysen GesmbH",
    "wof:placetype":"venue"
},
  "geometry": {"coordinates":[16.3247890472,48.1862335205],"type":"Point"}
}