{
  "type": "Feature",
  "properties": {
    "iso:country":"AT",
    "sg:address":"Ossiacher Str 7",
    "sg:city":"Feldkirchen in K\u00e4rnten",
    "sg:orig_category":"Lebensmittel / Erzeugung U Gro\u00c3\u0178handel",
    "sg:phone":"+43 4342 7649940",
    "sg:postcode":"9560",
    "sg:province":"K\u00e4rnten",
    "wof:name":"SONNTHURN PRODUKTIONSGmbH",
    "wof:placetype":"venue"
},
  "geometry": {"coordinates":[14.0889129639,46.7190361023],"type":"Point"}
}