{
  "type": "Feature",
  "properties": {
    "addr:full":"Kefergutstr 3 Linz Ober\u00f6sterreich 4020",
    "addr:housenumber":"3",
    "addr:postcode":"4020",
    "addr:street":"Kefergutstr",
    "iso:country":"AT",
    "sg:address":"Kefergutstr 3",
    "sg:city":"Linz",
    "sg:orig_category":"Friseure U Frisiersalons",
    "sg:phone":"+43 4373 2672528",
    "sg:postcode":"4020",
    "sg:province":"Ober\u00f6sterreich",
    "wof:name":"Wolfsteiner Oliver",
    "wof:placetype":"venue"
},
  "geometry": {"coordinates":[14.2816915512,48.2794303894],"type":"Point"}
}