{
  "type": "Feature",
  "properties": {
    "addr:full":"Pausing 3 Raab Ober\u00f6sterreich 4760",
    "addr:housenumber":"3",
    "addr:postcode":"4760",
    "addr:street":"Pausing;Oberoesterreich",
    "iso:country":"AT",
    "sg:address":"Pausing 3",
    "sg:city":"Raab",
    "sg:orig_category":"Autohandel",
    "sg:phone":"+43 7762 2901",
    "sg:postcode":"4760",
    "sg:province":"Ober\u00f6sterreich",
    "wof:name":"Brettbacher GesmbH",
    "wof:placetype":"venue"
},
  "geometry": {"coordinates":[13.6600999832,48.3453674316],"type":"Point"}
}