{
  "type": "Feature",
  "properties": {
    "addr:full":"Marktpl 13 Wolfsegg am Hausruck Ober\u00f6sterreich 4902",
    "addr:housenumber":"13",
    "addr:postcode":"4902",
    "addr:street":"Marktpl",
    "iso:country":"AT",
    "sg:address":"Marktpl 13",
    "sg:city":"Wolfsegg am Hausruck",
    "sg:orig_category":"Banken U Sparkassen",
    "sg:phone":"+43 4376 7673910",
    "sg:postcode":"4902",
    "sg:province":"Ober\u00f6sterreich",
    "wof:name":"Raiffeisenbank Ottnang-Wolfsegg regGenmbH",
    "wof:placetype":"venue"
},
  "geometry": {"coordinates":[13.6743898392,48.1068496704],"type":"Point"}
}