{
  "type": "Feature",
  "properties": {
    "addr:full":"K\u00fchschelmg 5 Hollabrunn Nieder\u00f6sterreich 2020",
    "addr:housenumber":"5",
    "addr:postcode":"2020",
    "addr:street":"Kuehschelmg",
    "iso:country":"AT",
    "sg:address":"K\u00fchschelmg 5",
    "sg:city":"Hollabrunn",
    "sg:orig_category":"Architekten",
    "sg:phone":"+43 2952 3965",
    "sg:postcode":"2020",
    "sg:province":"Nieder\u00f6sterreich",
    "wof:name":"Maurer Ernst Arch Dipl-Ing",
    "wof:placetype":"venue"
},
  "geometry": {"coordinates":[16.0783004761,48.5624580383],"type":"Point"}
}