{
  "type": "Feature",
  "properties": {
    "addr:full":"Hauptstr 17 Kottingbrunn Nieder\u00f6sterreich 2542",
    "addr:housenumber":"17",
    "addr:postcode":"2542",
    "addr:street":"Hauptstr",
    "iso:country":"AT",
    "sg:address":"Hauptstr 17",
    "sg:city":"Kottingbrunn",
    "sg:orig_category":"Rebschulen",
    "sg:phone":"+43 2252 76118",
    "sg:postcode":"2542",
    "sg:province":"Nieder\u00f6sterreich",
    "wof:name":"Kober & Kohlf\u00fcrst Reben Inh Dipl-Ing Gerd Ohrenberger",
    "wof:placetype":"venue"
},
  "geometry": {"coordinates":[16.2291431427,47.9524688721],"type":"Point"}
}