{
  "type": "Feature",
  "properties": {
    "addr:full":"Donau-City-Str. 6 Wien Wien 1220",
    "addr:housenumber":"6",
    "addr:postcode":"1220",
    "addr:street":"Donau-City-Str.",
    "iso:country":"AT",
    "sg:address":"Donau-City-Str. 6",
    "sg:city":"Wien",
    "sg:classifiers":[
        {
            "category":"Banks & Credit Unions",
            "subcategory":"Bank",
            "type":"Services"
        }
    ],
    "sg:phone":"+43 4312 60700",
    "sg:postcode":"1220",
    "sg:province":"Wien",
    "sg:tags":[
        "banking",
        "institution"
    ],
    "wof:name":"CAPITAL BANK GMBH",
    "wof:placetype":"venue"
},
  "geometry": {"coordinates":[16.4142074585,48.2327766418],"type":"Point"}
}