{
  "type": "Feature",
  "properties": {
    "iso:country":"AT",
    "sg:address":"Hetmanekg. 13",
    "sg:city":"Wien",
    "sg:classifiers":[
        {
            "category":"Parking",
            "subcategory":"Lot",
            "type":"Transportation"
        }
    ],
    "sg:phone":"+43 4316 90660",
    "sg:postcode":"1230",
    "sg:province":"Wien",
    "sg:tags":[
        "transport",
        "road"
    ],
    "wof:name":"HABASIT GES.MBH",
    "wof:placetype":"venue"
},
  "geometry": {"coordinates":[16.3162536621,48.1343078613],"type":"Point"}
}