{
  "type": "Feature",
  "properties": {
    "addr:full":"Fohrenburgstr. 5 Bludenz Vorarlberg 6700",
    "addr:housenumber":"5",
    "addr:postcode":"6700",
    "addr:street":"Fohrenburgstr.",
    "iso:country":"AT",
    "sg:address":"Fohrenburgstr. 5",
    "sg:city":"Bludenz",
    "sg:classifiers":[
        {
            "category":"Food & Beverages",
            "subcategory":"Groceries & Convenience Stores",
            "type":"Retail Goods"
        }
    ],
    "sg:phone":"+43 4355 52606",
    "sg:postcode":"6700",
    "sg:province":"Vorarlberg",
    "sg:tags":[
        "drink"
    ],
    "wof:name":"BIERBRAUEREI FOHRENBURG GESMBH",
    "wof:placetype":"venue"
},
  "geometry": {"coordinates":[9.8140830994,47.1578788757],"type":"Point"}
}