{
  "type": "Feature",
  "properties": {
    "addr:full":"Vorderfager 12 Elsbethen-Glasenbach Salzburg 5061",
    "addr:housenumber":"12",
    "addr:postcode":"5061",
    "addr:street":"Vorderfager",
    "iso:country":"AT",
    "sg:address":"Vorderfager 12",
    "sg:city":"Elsbethen-Glasenbach",
    "sg:orig_category":"Tischlereien",
    "sg:phone":"+43 662 620756",
    "sg:postcode":"5061",
    "sg:province":"Salzburg",
    "wof:name":"Fagerer Josef",
    "wof:placetype":"venue"
},
  "geometry": {"coordinates":[13.1189546585,47.7762641907],"type":"Point"}
}