{
  "type": "Feature",
  "properties": {
    "iso:country":"AT",
    "sg:address":"Itter 300 ",
    "sg:city":"W\u00f6rgl",
    "sg:classifiers":[
        {
            "category":"Food & Beverages",
            "subcategory":"Bakery",
            "type":"Retail Goods"
        }
    ],
    "sg:phone":"+43 4353 3275654",
    "sg:postcode":"6300",
    "sg:province":"Tirol",
    "sg:tags":[
        "grain",
        "cereal"
    ],
    "wof:name":"EP - NATURPRODUKTE AG",
    "wof:placetype":"venue"
},
  "geometry": {"coordinates":[4.2635498047,50.6487503052],"type":"Point"}
}