{
  "type": "Feature",
  "properties": {
    "addr:full":"Kremstalstr. 30 Haid Ober\u00f6sterreich 4053",
    "addr:housenumber":"30",
    "addr:postcode":"4053",
    "addr:street":"Kremstalstr.",
    "iso:country":"AT",
    "sg:address":"Kremstalstr. 30",
    "sg:city":"Haid",
    "sg:classifiers":[
        {
            "category":"Parking",
            "subcategory":"Lot",
            "type":"Transportation"
        }
    ],
    "sg:phone":"+43 4372 29816000",
    "sg:postcode":"4053",
    "sg:province":"Ober\u00f6sterreich",
    "sg:tags":[
        "transport",
        "road"
    ],
    "wof:name":"ANTON MITTER GESMBH",
    "wof:placetype":"venue"
},
  "geometry": {"coordinates":[14.2373685837,48.1676254272],"type":"Point"}
}