{
  "type": "Feature",
  "properties": {
    "addr:full":"Arnezhoferstr 10 Wien Wien 1020",
    "addr:housenumber":"10",
    "addr:postcode":"1020",
    "addr:street":"Arnezhoferstr",
    "iso:country":"AT",
    "sg:address":"Arnezhoferstr 10",
    "sg:city":"Wien",
    "sg:classifiers":[
        {
            "category":"Retail",
            "subcategory":"Event Space",
            "type":"Services"
        }
    ],
    "sg:phone":"+43 4317 268442",
    "sg:postcode":"1020",
    "sg:province":"Wien",
    "sg:tags":[
        "hand-",
        "u",
        "fu\u00c3\u0178pflege"
    ],
    "wof:name":"Petkovic Christine",
    "wof:placetype":"venue"
},
  "geometry": {"coordinates":[16.3984584808,48.2196922302],"type":"Point"}
}