{
  "type": "Feature",
  "properties": {
    "iso:country":"AT",
    "sg:address":"Dorf 138",
    "sg:city":"Finkenberg",
    "sg:orig_category":"Non-Classified Establishments",
    "sg:phone":"+43 664 2112936",
    "sg:postcode":"6292",
    "sg:province":"Tirol",
    "wof:name":"Pfarramt",
    "wof:placetype":"venue"
},
  "geometry": {"coordinates":[11.8245811462,47.1537971497],"type":"Point"}
}