{
  "type": "Feature",
  "properties": {
    "iso:country":"AT",
    "sg:address":"Kirchenpl 5",
    "sg:city":"Horn",
    "sg:orig_category":"Damenmoden",
    "sg:phone":"+43 2982 2933",
    "sg:postcode":"3580",
    "sg:province":"Nieder\u00f6sterreich",
    "wof:name":"Zimm Mode",
    "wof:placetype":"venue"
},
  "geometry": {"coordinates":[15.6574258804,48.6636314392],"type":"Point"}
}