{
  "type": "Feature",
  "properties": {
    "iso:country":"AT",
    "sg:address":"Nr 170",
    "sg:city":"Steyrling",
    "sg:orig_category":"Banken U Sparkassen",
    "sg:phone":"+43 7585 8209",
    "sg:postcode":"4571",
    "sg:province":"Ober\u00f6sterreich",
    "wof:name":"Raiffeisenkasse Steyrling regGenmbH",
    "wof:placetype":"venue"
},
  "geometry": {"coordinates":[14.1571464539,47.831653595],"type":"Point"}
}