{
  "type": "Feature",
  "properties": {
    "addr:full":"Wippenham 5 Gurten Ober\u00f6sterreich 4942",
    "addr:housenumber":"5",
    "addr:postcode":"4942",
    "addr:street":"Wippenham",
    "iso:country":"AT",
    "sg:address":"Wippenham 5",
    "sg:city":"Gurten",
    "sg:classifiers":[
        {
            "category":"Manufacturing",
            "subcategory":"Wood Products",
            "type":"Manufacturing & Wholesale Goods"
        }
    ],
    "sg:phone":"+43 7757 6601",
    "sg:postcode":"4942",
    "sg:province":"Ober\u00f6sterreich",
    "sg:tags":[
        "gate",
        "made",
        "door"
    ],
    "sg:website":"weibold.at",
    "wof:name":"Johann Weibold",
    "wof:placetype":"venue"
},
  "geometry": {"coordinates":[13.3448448181,48.2405700684],"type":"Point"}
}