{
  "type": "Feature",
  "properties": {
    "iso:country":"AT",
    "sg:address":"Innstr 23-25",
    "sg:city":"Innsbruck",
    "sg:orig_category":"Seifen",
    "sg:phone":"+43 512 2821630",
    "sg:postcode":"6020",
    "sg:province":"Tirol",
    "wof:name":"Walde Carl Alois KG",
    "wof:placetype":"venue"
},
  "geometry": {"coordinates":[11.3909864426,47.2700271606],"type":"Point"}
}