{
  "type": "Feature",
  "properties": {
    "addr:full":"Judenleiten 27 Perg Ober\u00f6sterreich 4320",
    "addr:housenumber":"27",
    "addr:postcode":"4320",
    "addr:street":"Judenleiten",
    "iso:country":"AT",
    "sg:address":"Judenleiten 27",
    "sg:city":"Perg",
    "sg:orig_category":"Werbegrafik- U Grafik-Design",
    "sg:phone":"+43 4372 6252743",
    "sg:postcode":"4320",
    "sg:province":"Ober\u00f6sterreich",
    "wof:name":"Gruber Grafik-Designer",
    "wof:placetype":"venue"
},
  "geometry": {"coordinates":[14.6340551376,48.2500610352],"type":"Point"}
}