{
  "type": "Feature",
  "properties": {
    "addr:full":"Bethlehemstr 9b Linz Ober\u00f6sterreich 4020",
    "addr:housenumber":"9b",
    "addr:postcode":"4020",
    "addr:street":"Bethlehemstr",
    "iso:country":"AT",
    "sg:address":"Bethlehemstr 9b",
    "sg:city":"Linz",
    "sg:classifiers":[
        {
            "category":"Taxi",
            "type":"Transportation"
        }
    ],
    "sg:phone":"+43 4369 914420858",
    "sg:postcode":"4020",
    "sg:province":"Ober\u00f6sterreich",
    "sg:tags":[
        "personentransporte",
        "u"
    ],
    "wof:name":"Taxi Haudum",
    "wof:placetype":"venue"
},
  "geometry": {"coordinates":[14.2917366028,48.3041572571],"type":"Point"}
}