{
  "type": "Feature",
  "properties": {
    "addr:full":"V\u00f6lkendorfer Str 92 Villach K\u00e4rnten 9500",
    "addr:housenumber":"92",
    "addr:postcode":"9500",
    "addr:street":"Str;Kaernten",
    "iso:country":"AT",
    "sg:address":"V\u00f6lkendorfer Str 92",
    "sg:city":"Villach",
    "sg:orig_category":"Unternehmensberatung",
    "sg:phone":"+43 4242 51388",
    "sg:postcode":"9500",
    "sg:province":"K\u00e4rnten",
    "wof:name":"Archimedes-Partner f Entwicklung - Lampel Dietrich Josef Dipl-Ing",
    "wof:placetype":"venue"
},
  "geometry": {"coordinates":[13.8491945267,46.618106842],"type":"Point"}
}