{
  "type": "Feature",
  "properties": {
    "iso:country":"AT",
    "sg:address":"Industriestr 35",
    "sg:city":"Guntramsdorf",
    "sg:orig_category":"Speditionen",
    "sg:phone":"+43 2236 8004",
    "sg:postcode":"2353",
    "sg:province":"Nieder\u00f6sterreich",
    "wof:name":"TVS Europaverkehre SpeditionsgesmbH",
    "wof:placetype":"venue"
},
  "geometry": {"coordinates":[16.3250808716,48.0625114441],"type":"Point"}
}