{
  "type": "Feature",
  "properties": {
    "addr:full":"Entalweg 623 Kaprun Salzburg 5710",
    "addr:housenumber":"623",
    "addr:postcode":"5710",
    "addr:street":"Kaprun Salzburg",
    "iso:country":"AT",
    "sg:address":"Entalweg 623",
    "sg:city":"Kaprun",
    "sg:orig_category":"Transportunternehmen",
    "sg:phone":"+43 6547 74030",
    "sg:postcode":"5710",
    "sg:province":"Salzburg",
    "wof:name":"Hartl Anton",
    "wof:placetype":"venue"
},
  "geometry": {"coordinates":[12.7435646057,47.262966156],"type":"Point"}
}