{
  "type": "Feature",
  "properties": {
    "iso:country":"AT",
    "sg:address":"Lichteneckerg 6",
    "sg:city":"Guntramsdorf",
    "sg:orig_category":"Pensionen / Privatzimmer",
    "sg:phone":"+43 2236 530440",
    "sg:postcode":"2353",
    "sg:province":"Nieder\u00f6sterreich",
    "wof:name":"Pension Pia",
    "wof:placetype":"venue"
},
  "geometry": {"coordinates":[16.3110542297,48.046169281],"type":"Point"}
}