{
  "type": "Feature",
  "properties": {
    "iso:country":"AT",
    "sg:address":"Archengasse 45",
    "sg:city":"Schwaz",
    "sg:classifiers":[
        {
            "category":"Home & Garden",
            "subcategory":"Home Furnishings",
            "type":"Retail Goods"
        }
    ],
    "sg:phone":"+43 5242 623000",
    "sg:postcode":"6130",
    "sg:province":"Tirol",
    "sg:tags":[
        "air-conditioners"
    ],
    "sg:website":"nesensohn.com",
    "wof:name":"Nesensohn GmbH Filiale Schwaz",
    "wof:placetype":"venue"
},
  "geometry": {"coordinates":[11.7101774216,47.3577003479],"type":"Point"}
}