{
  "type": "Feature",
  "properties": {
    "iso:country":"AT",
    "sg:address":"Schu\u00dflinie 3",
    "sg:city":"Wien",
    "sg:orig_category":"Speditionen",
    "sg:phone":"+43 1 760520",
    "sg:postcode":"1110",
    "sg:province":"Wien",
    "wof:name":"Fiege Euro-Logistics Austria GmbH",
    "wof:placetype":"venue"
},
  "geometry": {"coordinates":[16.4401950836,48.1789131165],"type":"Point"}
}