{
  "type": "Feature",
  "properties": {
    "iso:country":"AT",
    "sg:address":"Hofhaymer Allee 42/2",
    "sg:city":"Salzburg",
    "sg:orig_category":"Unternehmensberatung",
    "sg:phone":"+43 662 8238880",
    "sg:postcode":"5020",
    "sg:province":"Salzburg",
    "wof:name":"A & C Automationssystem & Consulting GmbH & Co KG",
    "wof:placetype":"venue"
},
  "geometry": {"coordinates":[13.0556983948,47.7858963013],"type":"Point"}
}