{
  "type": "Feature",
  "properties": {
    "addr:full":"Nr 1 Lanzenkirchen Nieder\u00f6sterreich 2821",
    "addr:postcode":"2821",
    "addr:street":"Nr;Lanzenkirchen",
    "iso:country":"AT",
    "sg:address":"Nr 1",
    "sg:city":"Lanzenkirchen",
    "sg:orig_category":"Non-Classified Establishments",
    "sg:phone":"+43 2627 45403",
    "sg:postcode":"2821",
    "sg:province":"Nieder\u00f6sterreich",
    "wof:name":"Pfarramt",
    "wof:placetype":"venue"
},
  "geometry": {"coordinates":[16.2391223907,47.7426261902],"type":"Point"}
}