{
  "type": "Feature",
  "properties": {
    "iso:country":"AT",
    "sg:address":"Bahnhofstrasse 27",
    "sg:city":"Klagenfurt",
    "sg:classifiers":[
        {
            "category":"Shopping",
            "subcategory":"Jewelry",
            "type":"Retail Goods"
        }
    ],
    "sg:phone":"+43 463 5117650",
    "sg:postcode":"9020",
    "sg:province":"K\u00e4rnten",
    "sg:tags":[
        "amber",
        "jewellery"
    ],
    "sg:website":"max-habenicht.at",
    "wof:name":"O. u. M. Habenicht Ges.m.b.H.",
    "wof:placetype":"venue"
},
  "geometry": {"coordinates":[14.3108596802,46.6229782104],"type":"Point"}
}