{
  "type": "Feature",
  "properties": {
    "addr:full":"Bahnhofstr 1 Wattens Tirol 6112",
    "addr:housenumber":"1",
    "addr:postcode":"6112",
    "addr:street":"Bahnhofstr;Tirol",
    "iso:country":"AT",
    "sg:address":"Bahnhofstr 1",
    "sg:city":"Wattens",
    "sg:orig_category":"Bestattungsunternehmen",
    "sg:phone":"+43 5224 52254",
    "sg:postcode":"6112",
    "sg:province":"Tirol",
    "wof:name":"Lechner Helmut & Co KEG",
    "wof:placetype":"venue"
},
  "geometry": {"coordinates":[11.5909957886,47.2905502319],"type":"Point"}
}