{
  "type": "Feature",
  "properties": {
    "iso:country":"AT",
    "sg:address":"Nr 130",
    "sg:city":"Buch",
    "sg:orig_category":"Gemeinden",
    "sg:phone":"+43 3332 62814",
    "sg:postcode":"8274",
    "sg:province":"Steiermark",
    "wof:name":"Gemeindeamt Buch-Geiseldorf",
    "wof:placetype":"venue"
},
  "geometry": {"coordinates":[15.9917430878,47.2286262512],"type":"Point"}
}