{
  "type": "Feature",
  "properties": {
    "addr:full":"Neubauzeile 106 4034",
    "addr:housenumber":"106",
    "addr:postcode":"4034",
    "addr:street":"Neubauzeile",
    "iso:country":"AT",
    "sg:address":"Neubauzeile 106",
    "sg:classifiers":[
        {
            "category":"Food & Beverages",
            "subcategory":"Groceries & Convenience Stores",
            "type":"Retail Goods"
        }
    ],
    "sg:phone":"+43 4373 2385022",
    "sg:postcode":"4034",
    "sg:tags":[
        "product",
        "related"
    ],
    "wof:name":"ROBERT SPEIGNER GESMBH",
    "wof:placetype":"venue"
},
  "geometry": {"coordinates":[14.2784862518,48.2418632507],"type":"Point"}
}