{
  "type": "Feature",
  "properties": {
    "addr:full":"C Doppler-Str 3a Salzburg Salzburg 5020",
    "addr:housenumber":"3a",
    "addr:postcode":"5020",
    "addr:street":"Salzburg",
    "iso:country":"AT",
    "sg:address":"C Doppler-Str 3a",
    "sg:city":"Salzburg",
    "sg:orig_category":"Non-Classified Establishments",
    "sg:phone":"+43 662 441071",
    "sg:postcode":"5020",
    "sg:province":"Salzburg",
    "wof:name":"Russisch orthodoxe Kirche",
    "wof:placetype":"venue"
},
  "geometry": {"coordinates":[13.0349035263,47.8098678589],"type":"Point"}
}