{
  "type": "Feature",
  "properties": {
    "iso:country":"AT",
    "sg:address":"Kastellstr 50",
    "sg:city":"Stegersbach",
    "sg:orig_category":"Stukkateure U Trockenausbauer",
    "sg:phone":"+43 3326 53288",
    "sg:postcode":"7551",
    "sg:province":"Burgenland",
    "wof:name":"WILROT & HELOP Trockenausbau GesmbH",
    "wof:placetype":"venue"
},
  "geometry": {"coordinates":[16.177362442,47.1601257324],"type":"Point"}
}