{
  "type": "Feature",
  "properties": {
    "addr:full":"Marktpl 8 Neumarkt im Hausruckkreis Ober\u00f6sterreich 4720",
    "addr:housenumber":"8",
    "addr:postcode":"4720",
    "addr:street":"Marktpl",
    "iso:country":"AT",
    "sg:address":"Marktpl 8",
    "sg:city":"Neumarkt im Hausruckkreis",
    "sg:orig_category":"Blumeneinzelhandel",
    "sg:phone":"+43 7733 7606",
    "sg:postcode":"4720",
    "sg:province":"Ober\u00f6sterreich",
    "wof:name":"Blumen-Pavilion",
    "wof:placetype":"venue"
},
  "geometry": {"coordinates":[13.7255916595,48.2733039856],"type":"Point"}
}