{
  "type": "Feature",
  "properties": {
    "addr:full":"Nr 77 H\u00fcrm Nieder\u00f6sterreich 3383",
    "addr:postcode":"3383",
    "addr:street":"Nr 77 Huerm",
    "iso:country":"AT",
    "sg:address":"Nr 77",
    "sg:city":"H\u00fcrm",
    "sg:orig_category":"Feuerwehren",
    "sg:phone":"+43 2754 8177",
    "sg:postcode":"3383",
    "sg:province":"Nieder\u00f6sterreich",
    "wof:name":"Freiwillige Feuerwehr H\u00fcrm",
    "wof:placetype":"venue"
},
  "geometry": {"coordinates":[166.9221496582,-0.5282999873],"type":"Point"}
}