{
  "type": "Feature",
  "properties": {
    "iso:country":"AT",
    "sg:address":"Senefelderg 16",
    "sg:city":"Wien",
    "sg:orig_category":"Tabaktrafiken",
    "sg:phone":"+43 1 6027401",
    "sg:postcode":"1100",
    "sg:province":"Wien",
    "wof:name":"Schanz Brigitte",
    "wof:placetype":"venue"
},
  "geometry": {"coordinates":[16.3753585815,48.1759910583],"type":"Point"}
}