{
  "type": "Feature",
  "properties": {
    "addr:full":"Fleischhackerg 9 Wien Wien 1230",
    "addr:housenumber":"9",
    "addr:postcode":"1230",
    "addr:street":"Fleischhackerg",
    "iso:country":"AT",
    "sg:address":"Fleischhackerg 9",
    "sg:city":"Wien",
    "sg:orig_category":"Auskunfteien",
    "sg:phone":"+43 1 8861555",
    "sg:postcode":"1230",
    "sg:province":"Wien",
    "wof:name":"Wirtschaftsdatendienst Atlas KEG",
    "wof:placetype":"venue"
},
  "geometry": {"coordinates":[16.2853431702,48.1565513611],"type":"Point"}
}