{
  "type": "Feature",
  "properties": {
    "addr:full":"Hietzinger Hauptstr 3 Wien Wien 1130",
    "addr:housenumber":"3",
    "addr:postcode":"1130",
    "addr:street":"Hietzinger Hauptstr",
    "iso:country":"AT",
    "sg:address":"Hietzinger Hauptstr 3",
    "sg:city":"Wien",
    "sg:orig_category":"Boutiquen",
    "sg:phone":"+43 1 8793513",
    "sg:postcode":"1130",
    "sg:province":"Wien",
    "wof:name":"Boutique Wolford",
    "wof:placetype":"venue"
},
  "geometry": {"coordinates":[16.3012905121,48.1859817505],"type":"Point"}
}