{
  "type": "Feature",
  "properties": {
    "iso:country":"AT",
    "sg:address":"Zeppelinstr 12",
    "sg:city":"Linz",
    "sg:orig_category":"Fleischhauereien",
    "sg:phone":"+43 732 305955",
    "sg:postcode":"4030",
    "sg:province":"Ober\u00f6sterreich",
    "wof:name":"Schirnhofer-Breisler GesmbH - Shop in Shop",
    "wof:placetype":"venue"
},
  "geometry": {"coordinates":[14.3201541901,48.2560691833],"type":"Point"}
}