{
  "type": "Feature",
  "properties": {
    "addr:full":"Hauptstr 18 Mannersdorf am Leithagebirge Nieder\u00f6sterreich 2452",
    "addr:housenumber":"18",
    "addr:postcode":"2452",
    "addr:street":"Hauptstr",
    "iso:country":"AT",
    "sg:address":"Hauptstr 18",
    "sg:city":"Mannersdorf am Leithagebirge",
    "sg:orig_category":"Schneidereien",
    "sg:phone":"+43 4321 6868657",
    "sg:postcode":"2452",
    "sg:province":"Nieder\u00f6sterreich",
    "wof:name":"ANGY Mode nach Ma\u00df - Inh Anna Zierfu\u00df",
    "wof:placetype":"venue"
},
  "geometry": {"coordinates":[16.6000957489,47.9720077515],"type":"Point"}
}