{
  "type": "Feature",
  "properties": {
    "iso:country":"AT",
    "sg:address":"Sigmund-Thun-Str 16",
    "sg:city":"Hallein",
    "sg:orig_category":"Lebensmittel / Einzelhandel",
    "sg:phone":"+43 6245 88609",
    "sg:postcode":"5400",
    "sg:province":"Salzburg",
    "wof:name":"Corso Gourmet",
    "wof:placetype":"venue"
},
  "geometry": {"coordinates":[13.0959501266,47.6826057434],"type":"Point"}
}