{
  "type": "Feature",
  "properties": {
    "addr:full":"Anblickweg 14 Lengenfeld Nieder\u00f6sterreich 3552",
    "addr:housenumber":"14",
    "addr:postcode":"3552",
    "addr:street":"Anblickweg",
    "iso:country":"AT",
    "sg:address":"Anblickweg 14",
    "sg:city":"Lengenfeld",
    "sg:orig_category":"Me\u00c3\u0178-, Steuer- U Regeltechnik",
    "sg:phone":"+43 2719 221622",
    "sg:postcode":"3552",
    "sg:province":"Nieder\u00f6sterreich",
    "wof:name":"RTR - Regeltechnik Riedel",
    "wof:placetype":"venue"
},
  "geometry": {"coordinates":[15.6043806076,48.4458885193],"type":"Point"}
}