{
  "type": "Feature",
  "properties": {
    "iso:country":"AT",
    "sg:address":"Bundesstr. ",
    "sg:city":"Klaus-Weiler",
    "sg:classifiers":[
        {
            "category":"Home & Garden",
            "subcategory":"Home Furnishings",
            "type":"Retail Goods"
        }
    ],
    "sg:phone":"+43 4355 2362115",
    "sg:postcode":"6833",
    "sg:province":"Vorarlberg",
    "sg:tags":[
        "household"
    ],
    "wof:name":"WEILER M\u00d6BEL TISCHLEREI GES.MBH & CO KG",
    "wof:placetype":"venue"
},
  "geometry": {"coordinates":[9.6465816498,47.3089485168],"type":"Point"}
}