{
  "type": "Feature",
  "properties": {
    "iso:country":"AT",
    "sg:address":"Spitalg 2",
    "sg:city":"Kremsm\u00fcnster",
    "sg:orig_category":"Apotheken",
    "sg:phone":"+43 7583 52500",
    "sg:postcode":"4550",
    "sg:province":"Ober\u00f6sterreich",
    "wof:name":"Apotheke z hl Benedikt",
    "wof:placetype":"venue"
},
  "geometry": {"coordinates":[14.1304092407,48.0521354675],"type":"Point"}
}