{
  "type": "Feature",
  "properties": {
    "addr:full":"Weimarer Str 24 Wien Wien 1180",
    "addr:postcode":"1180",
    "addr:street":"Str 24",
    "iso:country":"AT",
    "sg:address":"Weimarer Str 24",
    "sg:city":"Wien",
    "sg:orig_category":"Weine / Einzelhandel",
    "sg:phone":"+43 1 4703357",
    "sg:postcode":"1180",
    "sg:province":"Wien",
    "wof:name":"Salomon Dr KG",
    "wof:placetype":"venue"
},
  "geometry": {"coordinates":[16.3414134979,48.2277946472],"type":"Point"}
}