{
  "type": "Feature",
  "properties": {
    "iso:country":"AT",
    "sg:address":"Priesnegger Str 4/21",
    "sg:city":"Klagenfurt",
    "sg:orig_category":"Tauchsportschulen U -Vereine",
    "sg:phone":"+43 676 5174760",
    "sg:postcode":"9020",
    "sg:province":"K\u00e4rnten",
    "wof:name":"Tauch-Wassersportakademie",
    "wof:placetype":"venue"
},
  "geometry": {"coordinates":[14.2980804443,46.6405258179],"type":"Point"}
}