{
  "type": "Feature",
  "properties": {
    "addr:full":"Anton-Karg-Str 7 Kufstein Tirol 6330",
    "addr:housenumber":"7",
    "addr:postcode":"6330",
    "addr:street":"Anton-Karg-Str;Tirol",
    "iso:country":"AT",
    "sg:address":"Anton-Karg-Str 7",
    "sg:city":"Kufstein",
    "sg:orig_category":"Maschinenhandel",
    "sg:phone":"+43 4353 72632140",
    "sg:postcode":"6330",
    "sg:province":"Tirol",
    "sg:website":"eisele.at",
    "wof:name":"Behringer Eisele Maschinen GesmbH",
    "wof:placetype":"venue"
},
  "geometry": {"coordinates":[12.1747303009,47.5871963501],"type":"Point"}
}