{
  "type": "Feature",
  "properties": {
    "addr:full":"Grenzstr 57 St. Marein im M\u00fcrztal Steiermark 8641",
    "addr:housenumber":"57",
    "addr:postcode":"8641",
    "addr:street":"Grenzstr",
    "iso:country":"AT",
    "sg:address":"Grenzstr 57",
    "sg:city":"St. Marein im M\u00fcrztal",
    "sg:orig_category":"Elektroinstallationsunternehmen",
    "sg:phone":"+43 4338 6422340",
    "sg:postcode":"8641",
    "sg:province":"Steiermark",
    "wof:name":"Schaffer Karl Elektro Installationen u Schlossereibetrieb GesmbH",
    "wof:placetype":"venue"
},
  "geometry": {"coordinates":[15.3672542572,47.4763870239],"type":"Point"}
}