{
  "type": "Feature",
  "properties": {
    "addr:full":"Fasang 49 Wien Wien 1030",
    "addr:housenumber":"49",
    "addr:postcode":"1030",
    "addr:street":"Fasang",
    "iso:country":"AT",
    "sg:address":"Fasang 49",
    "sg:city":"Wien",
    "sg:orig_category":"Steuerberatung",
    "sg:phone":"+43 4317 9827620",
    "sg:postcode":"1030",
    "sg:province":"Wien",
    "wof:name":"Pudschedl Bruno",
    "wof:placetype":"venue"
},
  "geometry": {"coordinates":[16.3855361938,48.1893844604],"type":"Point"}
}