{
  "type": "Feature",
  "properties": {
    "iso:country":"AT",
    "sg:address":"Wiedner Hauptstr 45-47",
    "sg:city":"Wien",
    "sg:orig_category":"Ingenieurkonsulenten / Zivilingenieure",
    "sg:phone":"+43 1 5058333",
    "sg:postcode":"1040",
    "sg:province":"Wien",
    "wof:name":"Poltnigg & Klammer Diplomingenieure ZiviltechnikergesmbH",
    "wof:placetype":"venue"
},
  "geometry": {"coordinates":[16.3673553467,48.1931915283],"type":"Point"}
}