{
  "type": "Feature",
  "properties": {
    "iso:country":"AT",
    "sg:address":"Bahnhofstr 2",
    "sg:city":"Bruck an der Mur",
    "sg:classifiers":[
        {
            "category":"Recreation",
            "subcategory":"Theme Park",
            "type":"Entertainment"
        }
    ],
    "sg:phone":"+43 3862 8930",
    "sg:postcode":"8600",
    "sg:province":"Steiermark",
    "sg:tags":[
        "stahl"
    ],
    "wof:name":"voestalpine Austria Draht GmbH",
    "wof:placetype":"venue"
},
  "geometry": {"coordinates":[15.2740411758,47.4123725891],"type":"Point"}
}