{
  "type": "Feature",
  "properties": {
    "iso:country":"AT",
    "sg:address":"Griesmayrstr 19",
    "sg:city":"Linz",
    "sg:orig_category":"Fotografen",
    "sg:phone":"+43 732 248185",
    "sg:postcode":"4040",
    "sg:province":"Ober\u00f6sterreich",
    "wof:name":"Bilderprofi Strauss Fotoatelier GesmbH",
    "wof:placetype":"venue"
},
  "geometry": {"coordinates":[14.2993211746,48.3337020874],"type":"Point"}
}