{
  "type": "Feature",
  "properties": {
    "addr:full":"Dr.-Billroth-Weg 66 Leibnitz Steiermark 8430",
    "addr:housenumber":"66",
    "addr:postcode":"8430",
    "addr:street":"Dr.-Billroth-Weg;Steiermark",
    "iso:country":"AT",
    "sg:address":"Dr.-Billroth-Weg 66",
    "sg:city":"Leibnitz",
    "sg:orig_category":"\u00c3\u201erzte / F Allgemeinmedizin",
    "sg:phone":"+43 3452 744700",
    "sg:postcode":"8430",
    "sg:province":"Steiermark",
    "wof:name":"Holler Johann Dr",
    "wof:placetype":"venue"
},
  "geometry": {"coordinates":[15.5632781982,46.7806015015],"type":"Point"}
}