{
  "type": "Feature",
  "properties": {
    "addr:full":"Hunnenbrunn Bundesstr 5 St. Veit an der Glan K\u00e4rnten 9300",
    "addr:housenumber":"5",
    "addr:postcode":"9300",
    "addr:street":"Bundesstr;Kaernten",
    "iso:country":"AT",
    "sg:address":"Hunnenbrunn Bundesstr 5",
    "sg:city":"St. Veit an der Glan",
    "sg:orig_category":"Maler, Anstreicher U Lackierer",
    "sg:phone":"+43 4342 1253070",
    "sg:postcode":"9300",
    "sg:province":"K\u00e4rnten",
    "wof:name":"Pugganig Karl",
    "wof:placetype":"venue"
},
  "geometry": {"coordinates":[14.3591928482,46.7664413452],"type":"Point"}
}