{
  "type": "Feature",
  "properties": {
    "addr:full":"Kugelfangweg 25 Rum Tirol 6063",
    "addr:housenumber":"25",
    "addr:postcode":"6063",
    "addr:street":"Kugelfangweg;Tirol",
    "iso:country":"AT",
    "sg:address":"Kugelfangweg 25",
    "sg:city":"Rum",
    "sg:orig_category":"Auskunfteien",
    "sg:phone":"+43 512 369344",
    "sg:postcode":"6063",
    "sg:province":"Tirol",
    "wof:name":"Dun & Bradstreet Information Services GmbH",
    "wof:placetype":"venue"
},
  "geometry": {"coordinates":[11.4471797943,47.2704315186],"type":"Point"}
}