{
  "type": "Feature",
  "properties": {
    "addr:full":"Billrothstr 20 Wien Wien 1190",
    "addr:housenumber":"20",
    "addr:postcode":"1190",
    "addr:street":"Billrothstr",
    "iso:country":"AT",
    "sg:address":"Billrothstr 20",
    "sg:city":"Wien",
    "sg:orig_category":"Optiker",
    "sg:phone":"+43 1 3695411",
    "sg:postcode":"1190",
    "sg:province":"Wien",
    "wof:name":"Pearle \u00f6sterreich GmbH - Wyk Haus der Optik",
    "wof:placetype":"venue"
},
  "geometry": {"coordinates":[16.3494052887,48.2368392944],"type":"Point"}
}