{
  "type": "Feature",
  "properties": {
    "iso:country":"AT",
    "sg:address":"Hegig 3",
    "sg:city":"Salzburg",
    "sg:orig_category":"Ingenieurkonsulenten / Zivilingenieure",
    "sg:phone":"+43 662 829130",
    "sg:postcode":"5020",
    "sg:province":"Salzburg",
    "wof:name":"Wozak Ludwig Prof Dipl-Ing",
    "wof:placetype":"venue"
},
  "geometry": {"coordinates":[13.0344171524,47.7932510376],"type":"Point"}
}