{
  "type": "Feature",
  "properties": {
    "addr:full":"Nr 92 Wagrain Salzburg 5602",
    "addr:postcode":"5602",
    "addr:street":"Nr;Salzburg",
    "iso:country":"AT",
    "sg:address":"Nr 92",
    "sg:city":"Wagrain",
    "sg:orig_category":"Bars-Cafes",
    "sg:phone":"+43 6418 230",
    "sg:postcode":"5602",
    "sg:province":"Salzburg",
    "wof:name":"Moser Annemarie",
    "wof:placetype":"venue"
},
  "geometry": {"coordinates":[13.2964773178,47.3332366943],"type":"Point"}
}