{
  "type": "Feature",
  "properties": {
    "addr:full":"Babenbergerstr 36 Lilienfeld Nieder\u00f6sterreich 3180",
    "addr:housenumber":"36",
    "addr:postcode":"3180",
    "addr:street":"Babenbergerstr",
    "iso:country":"AT",
    "sg:address":"Babenbergerstr 36",
    "sg:city":"Lilienfeld",
    "sg:orig_category":"Versicherungsunternehmen",
    "sg:phone":"+43 2762 52450",
    "sg:postcode":"3180",
    "sg:province":"Nieder\u00f6sterreich",
    "wof:name":"Wiener St\u00e4dtische Allgemeine Versicherung AG",
    "wof:placetype":"venue"
},
  "geometry": {"coordinates":[15.5970649719,48.0176925659],"type":"Point"}
}