{
  "type": "Feature",
  "properties": {
    "iso:country":"AT",
    "sg:address":"K\u00f6nigsbachstr 7",
    "sg:city":"Rabenstein an der Pielach",
    "sg:orig_category":"Tischlereien",
    "sg:phone":"+43 4327 2324010",
    "sg:postcode":"3203",
    "sg:province":"Nieder\u00f6sterreich",
    "wof:name":"Strasser Helmut",
    "wof:placetype":"venue"
},
  "geometry": {"coordinates":[15.4633646011,48.0661888123],"type":"Point"}
}