{
  "type": "Feature",
  "properties": {
    "iso:country":"AT",
    "sg:address":"In den H\u00e4gen 3",
    "sg:city":"Hirschegg",
    "sg:classifiers":[
        {
            "category":"Travel",
            "subcategory":"Hotels & Motels",
            "type":"Entertainment"
        }
    ],
    "sg:phone":"+43 4355 1751710",
    "sg:postcode":"6992",
    "sg:province":"Vorarlberg",
    "wof:name":"Sporthotel Walliser",
    "wof:placetype":"venue"
},
  "geometry": {"coordinates":[10.171954155,47.3495864868],"type":"Point"}
}