{
  "type": "Feature",
  "properties": {
    "addr:full":"Obere Hauptstr 18 Hohenberg Nieder\u00f6sterreich 3192",
    "addr:housenumber":"18",
    "addr:postcode":"3192",
    "addr:street":"Obere Hauptstr",
    "iso:country":"AT",
    "sg:address":"Obere Hauptstr 18",
    "sg:city":"Hohenberg",
    "sg:orig_category":"Bauunternehmen",
    "sg:phone":"+43 4327 678010",
    "sg:postcode":"3192",
    "sg:province":"Nieder\u00f6sterreich",
    "wof:name":"H\u00f6lblinger u Zefferer Hoch- u Tiefbau GesmbH",
    "wof:placetype":"venue"
},
  "geometry": {"coordinates":[15.6174249649,47.9147872925],"type":"Point"}
}