{
  "type": "Feature",
  "properties": {
    "addr:full":"Derfflingerstr 12 Linz Ober\u00f6sterreich 4020",
    "addr:housenumber":"12",
    "addr:postcode":"4020",
    "addr:street":"Derfflingerstr",
    "iso:country":"AT",
    "sg:address":"Derfflingerstr 12",
    "sg:city":"Linz",
    "sg:orig_category":"Umweltschutz",
    "sg:phone":"+43 4373 2772585",
    "sg:postcode":"4020",
    "sg:province":"Ober\u00f6sterreich",
    "wof:name":"Gsellmann & Partners Consulting GmbH",
    "wof:placetype":"venue"
},
  "geometry": {"coordinates":[14.3104295731,48.3077278137],"type":"Point"}
}