{
  "type": "Feature",
  "properties": {
    "iso:country":"AT",
    "sg:address":"Segnerstrasse 7",
    "sg:city":"Wien",
    "sg:classifiers":[
        {
            "category":"Bus Stop",
            "subcategory":"None",
            "type":"Transportation"
        }
    ],
    "sg:phone":"+43 1 68836170",
    "sg:postcode":"1100",
    "sg:province":"Wien",
    "sg:tags":[
        "valve",
        "check"
    ],
    "sg:website":"richterkg.at",
    "wof:name":"Manfred Richter KG",
    "wof:placetype":"venue"
},
  "geometry": {"coordinates":[16.4068622589,48.138584137],"type":"Point"}
}