{
  "type": "Feature",
  "properties": {
    "addr:full":"Nr 140 Dalaas Vorarlberg 6752",
    "addr:postcode":"6752",
    "addr:street":"Nr 140",
    "iso:country":"AT",
    "sg:address":"Nr 140",
    "sg:city":"Dalaas",
    "sg:orig_category":"Volksschulen",
    "sg:phone":"+43 4355 857384",
    "sg:postcode":"6752",
    "sg:province":"Vorarlberg",
    "wof:name":"Volksschule",
    "wof:placetype":"venue"
},
  "geometry": {"coordinates":[9.9998960495,47.1229896545],"type":"Point"}
}