{
  "type": "Feature",
  "properties": {
    "iso:country":"AT",
    "sg:address":"Friedrich Street ",
    "sg:classifiers":[
        {
            "category":"Travel",
            "subcategory":"Travel Agent",
            "type":"Entertainment"
        }
    ],
    "sg:postcode":"7",
    "wof:name":"Osterr Verkehrsburo Ag",
    "wof:placetype":"venue"
},
  "geometry": {"coordinates":[-83.79624938960001,32.073764801],"type":"Point"}
}