{
  "type": "Feature",
  "properties": {
    "iso:country":"AT",
    "sg:address":"Harbach 59",
    "sg:city":"Bad Hofgastein",
    "sg:classifiers":[
        {
            "category":"Home & Garden",
            "subcategory":"Household Appliances",
            "type":"Retail Goods"
        }
    ],
    "sg:phone":"+43 6432 2002",
    "sg:postcode":"5630",
    "sg:province":"Salzburg",
    "sg:tags":[
        "electric"
    ],
    "wof:name":"Elektro Roland Wallner",
    "wof:placetype":"venue"
},
  "geometry": {"coordinates":[13.1119976044,47.2121734619],"type":"Point"}
}