{
  "type": "Feature",
  "properties": {
    "addr:full":"Industriestr NB Friesach K\u00e4rnten 9360",
    "addr:postcode":"9360",
    "iso:country":"AT",
    "sg:address":"Industriestr NB",
    "sg:city":"Friesach",
    "sg:orig_category":"Non-Classified Establishments",
    "sg:phone":"+43 4268 22800",
    "sg:postcode":"9360",
    "sg:province":"K\u00e4rnten",
    "wof:name":"Stra\u00dfenmeisterei Friesach",
    "wof:placetype":"venue"
},
  "geometry": {"coordinates":[14.4086351395,46.9555244446],"type":"Point"}
}