{
  "type": "Feature",
  "properties": {
    "addr:full":"Obere Augartenstrasse 32 Wien Wien 1020",
    "addr:housenumber":"32",
    "addr:postcode":"1020",
    "addr:street":"Obere Augartenstrasse",
    "iso:country":"AT",
    "sg:address":"Obere Augartenstrasse 32",
    "sg:city":"Wien",
    "sg:classifiers":[
        {
            "category":"Museum",
            "subcategory":"Art Museum",
            "type":"Entertainment"
        }
    ],
    "sg:phone":"+43 1 21470070",
    "sg:postcode":"1020",
    "sg:province":"Wien",
    "sg:tags":[
        "artwork"
    ],
    "sg:website":"boesmueller.at",
    "wof:name":"Druckerei B\u00f6sm\u00fcller Ges.m.b.H.",
    "wof:placetype":"venue"
},
  "geometry": {"coordinates":[16.3752746582,48.2223930359],"type":"Point"}
}