{
  "type": "Feature",
  "properties": {
    "addr:full":"Schweibern 9 Zell am Moos Ober\u00f6sterreich 4893",
    "addr:housenumber":"9",
    "addr:postcode":"4893",
    "addr:street":"Schweibern;Oberoesterreich",
    "iso:country":"AT",
    "sg:address":"Schweibern 9",
    "sg:city":"Zell am Moos",
    "sg:orig_category":"Handelsagenturen",
    "sg:phone":"+43 4366 45017202",
    "sg:postcode":"4893",
    "sg:province":"Ober\u00f6sterreich",
    "wof:name":"Schaurecker Herbert",
    "wof:placetype":"venue"
},
  "geometry": {"coordinates":[13.3187847137,47.9021682739],"type":"Point"}
}