{
  "type": "Feature",
  "properties": {
    "addr:full":"Putzensdlg 53 Behamberg Nieder\u00f6sterreich 4441",
    "addr:housenumber":"53",
    "addr:postcode":"4441",
    "addr:street":"Putzensdlg;Behamberg Niederoesterreich",
    "iso:country":"AT",
    "sg:address":"Putzensdlg 53",
    "sg:city":"Behamberg",
    "sg:classifiers":[
        {
            "category":"Internet Cafe",
            "subcategory":"None",
            "type":"Food & Drink"
        }
    ],
    "sg:phone":"+43 7252 30327",
    "sg:postcode":"4441",
    "sg:province":"Nieder\u00f6sterreich",
    "sg:tags":[
        "internet-provider"
    ],
    "wof:name":"Friendly-net",
    "wof:placetype":"venue"
},
  "geometry": {"coordinates":[14.4758558273,48.0333518982],"type":"Point"}
}