{
  "type": "Feature",
  "properties": {
    "addr:full":"Poysbrunner Str Herrnbaumgarten Nieder\u00f6sterreich 2171",
    "addr:postcode":"2171",
    "addr:street":"Str Herrnbaumgarten",
    "iso:country":"AT",
    "sg:address":"Poysbrunner Str",
    "sg:city":"Herrnbaumgarten",
    "sg:orig_category":"Feuerwehren",
    "sg:phone":"+43 2555 2522",
    "sg:postcode":"2171",
    "sg:province":"Nieder\u00f6sterreich",
    "wof:name":"Freiwillige Feuerwehr Herrnbaumgarten",
    "wof:placetype":"venue"
},
  "geometry": {"coordinates":[16.6804847717,48.6979598999],"type":"Point"}
}