{
  "type": "Feature",
  "properties": {
    "addr:full":"Samerg. 20 Salzburg Salzburg 5020",
    "addr:housenumber":"20",
    "addr:postcode":"5020",
    "addr:street":"Samerg.;Salzburg",
    "iso:country":"AT",
    "sg:address":"Samerg. 20",
    "sg:city":"Salzburg",
    "sg:classifiers":[
        {
            "category":"Autos & Motor Vehicles",
            "subcategory":"Automobile Sales",
            "type":"Retail Goods"
        }
    ],
    "sg:phone":"+43 4366 2889950",
    "sg:postcode":"5020",
    "sg:province":"Salzburg",
    "sg:tags":[
        "industrial"
    ],
    "wof:name":"TSCHANN NUTZFAHRZEUGE GMBH",
    "wof:placetype":"venue"
},
  "geometry": {"coordinates":[13.0570173264,47.8155441284],"type":"Point"}
}