{
  "type": "Feature",
  "properties": {
    "iso:country":"AT",
    "sg:address":"Palmersbachweg 2",
    "sg:city":"Imst",
    "sg:orig_category":"Druckereien",
    "sg:phone":"+43 5412 662390",
    "sg:postcode":"6460",
    "sg:province":"Tirol",
    "wof:name":"Eggerdruck GmbH",
    "wof:placetype":"venue"
},
  "geometry": {"coordinates":[10.7400226593,47.2333831787],"type":"Point"}
}