{
  "type": "Feature",
  "properties": {
    "addr:full":"Kalvarienberg 1 Schenkenfelden Ober\u00f6sterreich 4192",
    "addr:housenumber":"1",
    "addr:postcode":"4192",
    "addr:street":"Kalvarienberg",
    "iso:country":"AT",
    "sg:address":"Kalvarienberg 1",
    "sg:city":"Schenkenfelden",
    "sg:orig_category":"Lawn Mower Motors",
    "sg:phone":"+43 7214 46340",
    "sg:postcode":"4192",
    "sg:province":"Ober\u00f6sterreich",
    "wof:name":"Gottfried Heumader",
    "wof:placetype":"venue"
},
  "geometry": {"coordinates":[14.36693573,48.5106010437],"type":"Point"}
}