{
  "type": "Feature",
  "properties": {
    "iso:country":"AT",
    "sg:address":"Packer Str 160",
    "sg:city":"S\u00f6ding",
    "sg:orig_category":"Lebensmittel / Einzelhandel",
    "sg:phone":"+43 3137 6144",
    "sg:postcode":"8561",
    "sg:province":"Steiermark",
    "wof:name":"ADEG Contra Markt",
    "wof:placetype":"venue"
},
  "geometry": {"coordinates":[-80.9476013184,38.6538276672],"type":"Point"}
}