{
  "type": "Feature",
  "properties": {
    "iso:country":"AT",
    "sg:address":"Kinoweg 198",
    "sg:city":"F\u00fcgen",
    "sg:orig_category":"Restaurants: Chinesisch",
    "sg:phone":"+43 5288 64031",
    "sg:postcode":"6263",
    "sg:province":"Tirol",
    "wof:name":"Fu Hai China Restaurant",
    "wof:placetype":"venue"
},
  "geometry": {"coordinates":[11.8509883881,47.3460617065],"type":"Point"}
}