{
  "type": "Feature",
  "properties": {
    "addr:full":"Erlaaer Pl 1 Wien Wien 1230",
    "addr:housenumber":"1",
    "addr:postcode":"1230",
    "addr:street":"Erlaaer Pl",
    "iso:country":"AT",
    "sg:address":"Erlaaer Pl 1",
    "sg:city":"Wien",
    "sg:orig_category":"Apotheken",
    "sg:phone":"+43 1 6627300",
    "sg:postcode":"1230",
    "sg:province":"Wien",
    "sg:website":"apo-wiesen.at",
    "wof:name":"Apotheke In der Wiesen",
    "wof:placetype":"venue"
},
  "geometry": {"coordinates":[16.3099517822,48.1480407715],"type":"Point"}
}