{
  "type": "Feature",
  "properties": {
    "iso:country":"AT",
    "sg:address":"Rablstr 3",
    "sg:city":"Wels",
    "sg:classifiers":[
        {
            "category":"Travel",
            "subcategory":"Hotels & Motels",
            "type":"Entertainment"
        }
    ],
    "sg:phone":"+43 7242 35723",
    "sg:postcode":"4600",
    "sg:province":"Ober\u00f6sterreich",
    "wof:name":"Austria Classic Hotels Reservierungszentrale",
    "wof:placetype":"venue"
},
  "geometry": {"coordinates":[14.0247173309,48.1614341736],"type":"Point"}
}