{
  "type": "Feature",
  "properties": {
    "addr:full":"Br\u00e4uhausg 61 Wien Wien 1050",
    "addr:housenumber":"61",
    "addr:postcode":"1050",
    "addr:street":"Braeuhausg",
    "iso:country":"AT",
    "sg:address":"Br\u00e4uhausg 61",
    "sg:city":"Wien",
    "sg:orig_category":"\u00c3\u201erzte / F Allgemeinmedizin",
    "sg:phone":"+43 1 5451099",
    "sg:postcode":"1050",
    "sg:province":"Wien",
    "wof:name":"Binder Wilhelm Dr",
    "wof:placetype":"venue"
},
  "geometry": {"coordinates":[16.3584918976,48.19165802],"type":"Point"}
}