{
  "type": "Feature",
  "properties": {
    "addr:full":"Triester Str 45 Wiener Neudorf Nieder\u00f6sterreich 2351",
    "addr:postcode":"2351",
    "addr:street":"Str 45",
    "iso:country":"AT",
    "sg:address":"Triester Str 45",
    "sg:city":"Wiener Neudorf",
    "sg:classifiers":[
        {
            "category":"Restaurant",
            "type":"Food & Drink"
        }
    ],
    "sg:phone":"+43 2236 62829",
    "sg:postcode":"2351",
    "sg:province":"Nieder\u00f6sterreich",
    "wof:name":"Tennisanlage-Clubrestaurant SEV-Isovolta",
    "wof:placetype":"venue"
},
  "geometry": {"coordinates":[16.313419342,48.0798912048],"type":"Point"}
}