{
  "type": "Feature",
  "properties": {
    "addr:full":"Mauthausener Strasse 21 St. Georgen an der Gusen Ober\u00f6sterreich 4222",
    "addr:housenumber":"21",
    "addr:postcode":"4222",
    "addr:street":"Mauthausener Strasse",
    "iso:country":"AT",
    "sg:address":"Mauthausener Strasse 21",
    "sg:city":"St. Georgen an der Gusen",
    "sg:classifiers":[
        {
            "category":"Building & Trades",
            "subcategory":"Plumbing",
            "type":"Services"
        }
    ],
    "sg:phone":"+43 7237 2007",
    "sg:postcode":"4222",
    "sg:province":"Ober\u00f6sterreich",
    "sg:tags":[
        "tub",
        "bath"
    ],
    "wof:name":"Elkon Handelsges.m.b.H.",
    "wof:placetype":"venue"
},
  "geometry": {"coordinates":[14.4529352188,48.2704162598],"type":"Point"}
}