{
  "type": "Feature",
  "properties": {
    "addr:full":"Max-Zieger-Str 27 Ebensee Ober\u00f6sterreich 4802",
    "addr:housenumber":"27",
    "addr:postcode":"4802",
    "addr:street":"Max-Zieger-Str",
    "iso:country":"AT",
    "sg:address":"Max-Zieger-Str 27",
    "sg:city":"Ebensee",
    "sg:orig_category":"Volkshochschulen",
    "sg:phone":"+43 4361 338835",
    "sg:postcode":"4802",
    "sg:province":"Ober\u00f6sterreich",
    "wof:name":"Volkshochschule Ebensee",
    "wof:placetype":"venue"
},
  "geometry": {"coordinates":[13.7570133209,47.7868118286],"type":"Point"}
}