{
  "type": "Feature",
  "properties": {
    "iso:country":"AT",
    "sg:address":"Max-Zieger-Str 27",
    "sg:city":"Ebensee",
    "sg:orig_category":"Volkshochschulen",
    "sg:phone":"+43 4361 338835",
    "sg:postcode":"4802",
    "sg:province":"Ober\u00f6sterreich",
    "wof:name":"Volkshochschule Ebensee",
    "wof:placetype":"venue"
},
  "geometry": {"coordinates":[13.7570133209,47.7868118286],"type":"Point"}
}