{
  "type": "Feature",
  "properties": {
    "addr:full":"\u00e4u\u00dferes Hirschfeld 10 Neusiedl am See Burgenland 7100",
    "addr:housenumber":"10",
    "addr:postcode":"7100",
    "addr:street":"Aeusseres Hirschfeld",
    "iso:country":"AT",
    "sg:address":"\u00e4u\u00dferes Hirschfeld 10",
    "sg:city":"Neusiedl am See",
    "sg:orig_category":"Installationsunternehmen",
    "sg:phone":"+43 2167 85180",
    "sg:postcode":"7100",
    "sg:province":"Burgenland",
    "wof:name":"Karolyi Robert jun",
    "wof:placetype":"venue"
},
  "geometry": {"coordinates":[16.8358268738,47.9673118591],"type":"Point"}
}