{
  "type": "Feature",
  "properties": {
    "iso:country":"AT",
    "sg:address":"Weidach 370",
    "sg:city":"Leutasch",
    "sg:classifiers":[
        {
            "category":"Travel",
            "subcategory":"Hotels & Motels",
            "type":"Entertainment"
        }
    ],
    "sg:phone":"+43 5214 6402",
    "sg:postcode":"6105",
    "sg:province":"Tirol",
    "wof:name":"Hotel Schweizer-Hof",
    "wof:placetype":"venue"
},
  "geometry": {"coordinates":[11.1513023376,47.3726921082],"type":"Point"}
}