{
  "type": "Feature",
  "properties": {
    "iso:country":"AT",
    "sg:address":"Serviteng 7",
    "sg:city":"Wien",
    "sg:orig_category":"Sportschulen",
    "sg:phone":"+43 1 3104394",
    "sg:postcode":"1090",
    "sg:province":"Wien",
    "wof:name":"Nippon Budo Institut",
    "wof:placetype":"venue"
},
  "geometry": {"coordinates":[16.3640956879,48.2201461792],"type":"Point"}
}