{
  "type": "Feature",
  "properties": {
    "addr:full":"Hauptpl 17 Weiz Steiermark 8160",
    "addr:housenumber":"17",
    "addr:postcode":"8160",
    "addr:street":"Hauptpl",
    "iso:country":"AT",
    "sg:address":"Hauptpl 17",
    "sg:city":"Weiz",
    "sg:orig_category":"Friseure U Frisiersalons",
    "sg:phone":"+43 3172 2929",
    "sg:postcode":"8160",
    "sg:province":"Steiermark",
    "wof:name":"Salon Ingrid",
    "wof:placetype":"venue"
},
  "geometry": {"coordinates":[15.6224536896,47.2170829773],"type":"Point"}
}