{
  "type": "Feature",
  "properties": {
    "iso:country":"AT",
    "sg:address":"Landstra\u00dfer Hauptstr 144",
    "sg:city":"Wien",
    "sg:classifiers":[
        {
            "category":"Restaurant",
            "type":"Food & Drink"
        }
    ],
    "sg:phone":"+43 1 7184382",
    "sg:postcode":"1030",
    "sg:province":"Wien",
    "wof:name":"Kebabhaus Alanya",
    "wof:placetype":"venue"
},
  "geometry": {"coordinates":[16.3973140717,48.1941986084],"type":"Point"}
}