{
  "type": "Feature",
  "properties": {
    "iso:country":"AT",
    "sg:address":"Dr.-Guido-Salvagnini-Str 1",
    "sg:city":"Ennsdorf",
    "sg:orig_category":"Maschinenbau",
    "sg:phone":"+43 4372 238850",
    "sg:postcode":"4482",
    "sg:province":"Nieder\u00f6sterreich",
    "wof:name":"Salvagnini Maschinenbau GmbH",
    "wof:placetype":"venue"
},
  "geometry": {"coordinates":[14.5264797211,48.2271881104],"type":"Point"}
}