{
  "type": "Feature",
  "properties": {
    "addr:full":"Schelleingasse 1  Wien Wien 1040",
    "addr:housenumber":"1",
    "addr:postcode":"1040",
    "addr:street":"Schelleingasse",
    "iso:country":"AT",
    "sg:address":"Schelleingasse 1 ",
    "sg:city":"Wien",
    "sg:classifiers":[
        {
            "category":"Building & Trades",
            "subcategory":"Plumbing",
            "type":"Services"
        }
    ],
    "sg:phone":"+43 1 5059805",
    "sg:postcode":"1040",
    "sg:province":"Wien",
    "sg:tags":[
        "supraregional",
        "gas"
    ],
    "wof:name":"Leopold Dziwinski",
    "wof:placetype":"venue"
},
  "geometry": {"coordinates":[16.3768672943,48.1877670288],"type":"Point"}
}