{
  "type": "Feature",
  "properties": {
    "addr:full":"Europapl 4 Linz Ober\u00f6sterreich 4020",
    "addr:housenumber":"4",
    "addr:postcode":"4020",
    "addr:street":"Europapl",
    "iso:country":"AT",
    "sg:address":"Europapl 4",
    "sg:city":"Linz",
    "sg:orig_category":"Lebensmittel / Erzeugung U Gro\u00c3\u0178handel",
    "sg:phone":"+43 4373 269340",
    "sg:postcode":"4020",
    "sg:province":"Ober\u00f6sterreich",
    "wof:name":"Nestle \u00f6sterreich GmbH",
    "wof:placetype":"venue"
},
  "geometry": {"coordinates":[14.3035926819,48.2984733582],"type":"Point"}
}