{
  "type": "Feature",
  "properties": {
    "iso:country":"AT",
    "sg:address":"Vogelweiderstr 44A",
    "sg:city":"Salzburg",
    "sg:orig_category":"Medizintechnik",
    "sg:phone":"+43 662 645240440",
    "sg:postcode":"5020",
    "sg:province":"Salzburg",
    "wof:name":"Philips Medizinische Systeme GmbH",
    "wof:placetype":"venue"
},
  "geometry": {"coordinates":[13.0544376373,47.812461853],"type":"Point"}
}