{
  "type": "Feature",
  "properties": {
    "addr:full":"Nr 233 Kuchl Salzburg 5431",
    "addr:postcode":"5431",
    "addr:street":"Nr;Salzburg",
    "iso:country":"AT",
    "sg:address":"Nr 233",
    "sg:city":"Kuchl",
    "sg:orig_category":"Autoreparatur",
    "sg:phone":"+43 4362 447717",
    "sg:postcode":"5431",
    "sg:province":"Salzburg",
    "wof:name":"Panzenberger Robert",
    "wof:placetype":"venue"
},
  "geometry": {"coordinates":[13.1438808441,47.625667572],"type":"Point"}
}