{
  "type": "Feature",
  "properties": {
    "addr:full":"Syrnauer Str 10a Zwettl Nieder\u00f6sterreich 3910",
    "addr:postcode":"3910",
    "addr:street":"Str 10A",
    "iso:country":"AT",
    "sg:address":"Syrnauer Str 10a",
    "sg:city":"Zwettl",
    "sg:orig_category":"Tapezierer U Dekorateure",
    "sg:phone":"+43 2822 52591",
    "sg:postcode":"3910",
    "sg:province":"Nieder\u00f6sterreich",
    "wof:name":"Topf Josef Ing",
    "wof:placetype":"venue"
},
  "geometry": {"coordinates":[15.1681003571,48.6041564941],"type":"Point"}
}