{
  "type": "Feature",
  "properties": {
    "iso:country":"AT",
    "sg:address":"Herrenstr 6",
    "sg:city":"Mank",
    "sg:orig_category":"Eisenwaren",
    "sg:phone":"+43 2755 2281",
    "sg:postcode":"3240",
    "sg:province":"Nieder\u00f6sterreich",
    "wof:name":"Plamoser Wilfried",
    "wof:placetype":"venue"
},
  "geometry": {"coordinates":[15.3399629593,48.1120109558],"type":"Point"}
}