{
  "type": "Feature",
  "properties": {
    "addr:full":"Burggraben 1 Hohenau an der March Nieder\u00f6sterreich 2273",
    "addr:housenumber":"1",
    "addr:postcode":"2273",
    "addr:street":"Burggraben",
    "iso:country":"AT",
    "sg:address":"Burggraben 1",
    "sg:city":"Hohenau an der March",
    "sg:orig_category":"Feuerwehren",
    "sg:phone":"+43 2535 2332",
    "sg:postcode":"2273",
    "sg:province":"Nieder\u00f6sterreich",
    "wof:name":"Freiwillige Feuerwehr Hohenau",
    "wof:placetype":"venue"
},
  "geometry": {"coordinates":[16.9113674164,48.6065254211],"type":"Point"}
}