{
  "type": "Feature",
  "properties": {
    "addr:full":"Johnstr 32 Wien Wien 1150",
    "addr:housenumber":"32",
    "addr:postcode":"1150",
    "addr:street":"Johnstr",
    "iso:country":"AT",
    "sg:address":"Johnstr 32",
    "sg:city":"Wien",
    "sg:orig_category":"Autoverwertung",
    "sg:phone":"+43 1 9821344",
    "sg:postcode":"1150",
    "sg:province":"Wien",
    "wof:name":"Maloun Josef",
    "wof:placetype":"venue"
},
  "geometry": {"coordinates":[16.3182678223,48.1955375671],"type":"Point"}
}