{
  "type": "Feature",
  "properties": {
    "addr:full":"Stainachstr. 1 Anthering Salzburg 5102",
    "addr:housenumber":"1",
    "addr:postcode":"5102",
    "addr:street":"Stainachstr.;Salzburg",
    "iso:country":"AT",
    "sg:address":"Stainachstr. 1",
    "sg:city":"Anthering",
    "sg:classifiers":[
        {
            "category":"Food & Beverages",
            "subcategory":"Groceries & Convenience Stores",
            "type":"Retail Goods"
        }
    ],
    "sg:phone":"+43 4362 233211",
    "sg:postcode":"5102",
    "sg:province":"Salzburg",
    "sg:tags":[
        "product",
        "related"
    ],
    "wof:name":"ZALTECH GMBH & CO KG",
    "wof:placetype":"venue"
},
  "geometry": {"coordinates":[13.0159454346,47.8736572266],"type":"Point"}
}