{
  "type": "Feature",
  "properties": {
    "addr:full":"Taborstrasse 36 Wien Wien 1020",
    "addr:housenumber":"36",
    "addr:postcode":"1020",
    "addr:street":"Taborstrasse",
    "iso:country":"AT",
    "sg:address":"Taborstrasse 36",
    "sg:city":"Wien",
    "sg:classifiers":[
        {
            "category":"Professional",
            "type":"Services"
        }
    ],
    "sg:phone":"+43 1 2162373",
    "sg:postcode":"1020",
    "sg:province":"Wien",
    "sg:tags":[
        "auctioneer"
    ],
    "sg:website":"helvetiawatch.com",
    "wof:name":"Johann Forstinger Ges.m.b.H.",
    "wof:placetype":"venue"
},
  "geometry": {"coordinates":[16.3809223175,48.2185134888],"type":"Point"}
}