{
  "type": "Feature",
  "properties": {
    "addr:full":"Aigner Str 18 Salzburg Salzburg 5020",
    "addr:housenumber":"18",
    "addr:postcode":"5020",
    "addr:street":"Str;Salzburg",
    "iso:country":"AT",
    "sg:address":"Aigner Str 18",
    "sg:city":"Salzburg",
    "sg:orig_category":"Elektroinstallationsunternehmen",
    "sg:phone":"+43 662 6212640",
    "sg:postcode":"5020",
    "sg:province":"Salzburg",
    "wof:name":"Elektro Hummer Max Ing KG",
    "wof:placetype":"venue"
},
  "geometry": {"coordinates":[13.0672769547,47.7973327637],"type":"Point"}
}