{
  "type": "Feature",
  "properties": {
    "addr:full":"M\u00fchleistrasse 11 Anif Salzburg 5081",
    "addr:housenumber":"11",
    "addr:postcode":"5081",
    "addr:street":"Muehleistrasse;Salzburg",
    "iso:country":"AT",
    "sg:address":"M\u00fchleistrasse 11",
    "sg:city":"Anif",
    "sg:classifiers":[
        {
            "category":"Bars & Pubs",
            "subcategory":"Nightclub",
            "type":"Food & Drink"
        }
    ],
    "sg:phone":"+43 6246 74785",
    "sg:postcode":"5081",
    "sg:province":"Salzburg",
    "sg:tags":[
        "lamp",
        "halogen",
        "illuminant"
    ],
    "sg:website":"porzellan.at.tt",
    "wof:name":"pmf-Porzellanwerkst\u00e4tte",
    "wof:placetype":"venue"
},
  "geometry": {"coordinates":[13.0639257431,47.7499694824],"type":"Point"}
}