{
  "type": "Feature",
  "properties": {
    "addr:full":"Baumg 16 Wien Wien 1030",
    "addr:housenumber":"16",
    "addr:postcode":"1030",
    "addr:street":"Baumg",
    "iso:country":"AT",
    "sg:address":"Baumg 16",
    "sg:city":"Wien",
    "sg:orig_category":"Fleischhauereien",
    "sg:phone":"+43 1 7131190",
    "sg:postcode":"1030",
    "sg:province":"Wien",
    "wof:name":"Baidinger Wilhelm",
    "wof:placetype":"venue"
},
  "geometry": {"coordinates":[16.3971748352,48.1959533691],"type":"Point"}
}