{
  "type": "Feature",
  "properties": {
    "addr:full":"Hauptpl 35 Deutschlandsberg Steiermark 8530",
    "addr:housenumber":"35",
    "addr:postcode":"8530",
    "addr:street":"Hauptpl",
    "iso:country":"AT",
    "sg:address":"Hauptpl 35",
    "sg:city":"Deutschlandsberg",
    "sg:orig_category":"Gemeinden",
    "sg:phone":"+43 4334 6220110",
    "sg:postcode":"8530",
    "sg:province":"Steiermark",
    "wof:name":"Stadtgemeinde Deutschlandsberg",
    "wof:placetype":"venue"
},
  "geometry": {"coordinates":[15.2120914459,46.8141365051],"type":"Point"}
}