{
  "type": "Feature",
  "properties": {
    "addr:full":"Abelstr 6 Aschach an der Donau Ober\u00f6sterreich 4082",
    "addr:housenumber":"6",
    "addr:postcode":"4082",
    "addr:street":"Abelstr",
    "iso:country":"AT",
    "sg:address":"Abelstr 6",
    "sg:city":"Aschach an der Donau",
    "sg:orig_category":"Restaurants: Chinesisch",
    "sg:phone":"+43 7273 8299",
    "sg:postcode":"4082",
    "sg:province":"Ober\u00f6sterreich",
    "wof:name":"China-Restaurant Lotos",
    "wof:placetype":"venue"
},
  "geometry": {"coordinates":[14.0231714249,48.3640632629],"type":"Point"}
}