{
  "type": "Feature",
  "properties": {
    "addr:full":"Moos 8 Grieskirchen Ober\u00f6sterreich 4710",
    "addr:housenumber":"8",
    "addr:postcode":"4710",
    "addr:street":"Moos",
    "iso:country":"AT",
    "sg:address":"Moos 8",
    "sg:city":"Grieskirchen",
    "sg:orig_category":"Lebensmittel / Einzelhandel",
    "sg:phone":"+43 7248 68515",
    "sg:postcode":"4710",
    "sg:province":"Ober\u00f6sterreich",
    "wof:name":"Billa AG",
    "wof:placetype":"venue"
},
  "geometry": {"coordinates":[13.8269166946,48.2322120667],"type":"Point"}
}