{
  "type": "Feature",
  "properties": {
    "addr:full":"Industriestr 1 Enzesfeld-Lindabrunn Nieder\u00f6sterreich 2551",
    "addr:housenumber":"1",
    "addr:postcode":"2551",
    "addr:street":"Industriestr;Niederoesterreich",
    "iso:country":"AT",
    "sg:address":"Industriestr 1",
    "sg:city":"Enzesfeld-Lindabrunn",
    "sg:orig_category":"Metallbe- U -Verarbeitung",
    "sg:phone":"+43 2256 81874",
    "sg:postcode":"2551",
    "sg:province":"Nieder\u00f6sterreich",
    "wof:name":"Baustahlcenter GesmbH",
    "wof:placetype":"venue"
},
  "geometry": {"coordinates":[16.1962890625,47.9179954529],"type":"Point"}
}