{
  "type": "Feature",
  "properties": {
    "iso:country":"AT",
    "sg:address":"Schulstr 110",
    "sg:city":"Edelschrott",
    "sg:orig_category":"Hauptschulen",
    "sg:phone":"+43 3145 80120",
    "sg:postcode":"8583",
    "sg:province":"Steiermark",
    "wof:name":"Hauptschule",
    "wof:placetype":"venue"
},
  "geometry": {"coordinates":[15.0618038177,47.0246200562],"type":"Point"}
}