{
  "type": "Feature",
  "properties": {
    "addr:full":"Fasang 38 Wien Wien 1030",
    "addr:housenumber":"38",
    "addr:postcode":"1030",
    "addr:street":"Fasang",
    "iso:country":"AT",
    "sg:address":"Fasang 38",
    "sg:city":"Wien",
    "sg:orig_category":"Installationsunternehmen",
    "sg:phone":"+43 1 79833220",
    "sg:postcode":"1030",
    "sg:province":"Wien",
    "wof:name":"Cernik Aloisia & S\u00f6hne KG",
    "wof:placetype":"venue"
},
  "geometry": {"coordinates":[16.3853206635,48.1903190613],"type":"Point"}
}