{
  "type": "Feature",
  "properties": {
    "iso:country":"AT",
    "sg:address":"Kreuzstr 7",
    "sg:city":"Sulz-R\u00f6this",
    "sg:orig_category":"Autohandel",
    "sg:phone":"+43 5522 43714",
    "sg:postcode":"6832",
    "sg:province":"Vorarlberg",
    "wof:name":"Auto Export - Autohandel Sabbagh Tareg",
    "wof:placetype":"venue"
},
  "geometry": {"coordinates":[9.6576480865,47.2835121155],"type":"Point"}
}