{
  "type": "Feature",
  "properties": {
    "iso:country":"AT",
    "sg:address":"Albert-Schweitzer-Str 8",
    "sg:city":"Wels",
    "sg:orig_category":"Friseure U Frisiersalons",
    "sg:phone":"+43 4369 919262393",
    "sg:postcode":"4600",
    "sg:province":"Ober\u00f6sterreich",
    "wof:name":"Rauch Doris Mobil-Friseur",
    "wof:placetype":"venue"
},
  "geometry": {"coordinates":[13.9941301346,48.1615982056],"type":"Point"}
}