{
  "type": "Feature",
  "properties": {
    "addr:full":"Hochalmstr 10 Lunz am See Nieder\u00f6sterreich 3293",
    "addr:housenumber":"10",
    "addr:postcode":"3293",
    "addr:street":"Hochalmstr",
    "iso:country":"AT",
    "sg:address":"Hochalmstr 10",
    "sg:city":"Lunz am See",
    "sg:orig_category":"Pensionen / Privatzimmer",
    "sg:phone":"+43 4374 8597388",
    "sg:postcode":"3293",
    "sg:province":"Nieder\u00f6sterreich",
    "wof:name":"Heigl Engelbert u Maria",
    "wof:placetype":"venue"
},
  "geometry": {"coordinates":[15.0337314606,47.9156570435],"type":"Point"}
}