{
  "type": "Feature",
  "properties": {
    "addr:full":"Waldweg 30 Liezen Steiermark 8940",
    "addr:housenumber":"30",
    "addr:postcode":"8940",
    "addr:street":"Waldweg",
    "iso:country":"AT",
    "sg:address":"Waldweg 30",
    "sg:city":"Liezen",
    "sg:classifiers":[
        {
            "category":"Banks & Credit Unions",
            "subcategory":"Investment Brokerage",
            "type":"Services"
        }
    ],
    "sg:phone":"+43 3612 22167",
    "sg:postcode":"8940",
    "sg:province":"Steiermark",
    "sg:tags":[
        "collector",
        "solar"
    ],
    "wof:name":"Korbel Solar Systemtechnik Inh. Reinhold Korbel",
    "wof:placetype":"venue"
},
  "geometry": {"coordinates":[14.2319927216,47.5728340149],"type":"Point"}
}