{
  "type": "Feature",
  "properties": {
    "addr:full":"Nr 22 Ligist Steiermark 8563",
    "addr:postcode":"8563",
    "addr:street":"Nr",
    "iso:country":"AT",
    "sg:address":"Nr 22",
    "sg:city":"Ligist",
    "sg:orig_category":"Hauskrankenpflege / Heimhilfe",
    "sg:phone":"+43 3143 20422",
    "sg:postcode":"8563",
    "sg:province":"Steiermark",
    "wof:name":"Hilfswerk Steiermark GmbH",
    "wof:placetype":"venue"
},
  "geometry": {"coordinates":[15.2067432404,46.9937019348],"type":"Point"}
}