{
  "type": "Feature",
  "properties": {
    "addr:full":"Lastenstr. 10 Feldkirchen in K\u00e4rnten K\u00e4rnten 9560",
    "addr:housenumber":"10",
    "addr:postcode":"9560",
    "addr:street":"Lastenstr.;Kaernten",
    "iso:country":"AT",
    "sg:address":"Lastenstr. 10",
    "sg:city":"Feldkirchen in K\u00e4rnten",
    "sg:classifiers":[
        {
            "category":"Professional",
            "subcategory":"Computer Services",
            "type":"Services"
        }
    ],
    "sg:phone":"+43 4342 7657100",
    "sg:postcode":"9560",
    "sg:province":"K\u00e4rnten",
    "sg:tags":[
        "information",
        "technology"
    ],
    "wof:name":"EMBATEX ERZEUGUNG VON EDV-ZUBEH\u00d6R GES.MBH",
    "wof:placetype":"venue"
},
  "geometry": {"coordinates":[14.1010217667,46.7183265686],"type":"Point"}
}