{
  "type": "Feature",
  "properties": {
    "iso:country":"AT",
    "sg:address":"Sillh\u00f6fe 2",
    "sg:city":"Innsbruck",
    "sg:classifiers":[
        {
            "category":"Home & Garden",
            "subcategory":"Building Materials",
            "type":"Retail Goods"
        }
    ],
    "sg:phone":"+43 512 365747",
    "sg:postcode":"6020",
    "sg:province":"Tirol",
    "sg:tags":[
        "baustoffe",
        "-material",
        "u"
    ],
    "wof:name":"Reimond Gerhard Ing - YTONG Verkaufsberatung",
    "wof:placetype":"venue"
},
  "geometry": {"coordinates":[11.4045572281,47.2559547424],"type":"Point"}
}