{
  "type": "Feature",
  "properties": {
    "iso:country":"AT",
    "sg:address":"Pommerg 22",
    "sg:city":"Graz",
    "sg:orig_category":"Spenglereien",
    "sg:phone":"+43 4331 6712295",
    "sg:postcode":"8020",
    "sg:province":"Steiermark",
    "wof:name":"Schiftner Robert GmbH",
    "wof:placetype":"venue"
},
  "geometry": {"coordinates":[15.409406662,47.0726661682],"type":"Point"}
}