{
  "type": "Feature",
  "properties": {
    "addr:full":"Haydnweg 8 Velden am W\u00f6rther See K\u00e4rnten 9220",
    "addr:housenumber":"8",
    "addr:postcode":"9220",
    "addr:street":"Haydnweg;Kaernten",
    "iso:country":"AT",
    "sg:address":"Haydnweg 8",
    "sg:city":"Velden am W\u00f6rther See",
    "sg:orig_category":"Maler, Anstreicher U Lackierer",
    "sg:phone":"+43 4342 742557",
    "sg:postcode":"9220",
    "sg:province":"K\u00e4rnten",
    "wof:name":"Goritschnig Josef",
    "wof:placetype":"venue"
},
  "geometry": {"coordinates":[14.0429868698,46.6151618958],"type":"Point"}
}