{
  "type": "Feature",
  "properties": {
    "addr:full":"Tullner Str 38 Michelhausen Nieder\u00f6sterreich 3451",
    "addr:housenumber":"38",
    "addr:postcode":"3451",
    "addr:street":"Str",
    "iso:country":"AT",
    "sg:address":"Tullner Str 38",
    "sg:city":"Michelhausen",
    "sg:orig_category":"Transportunternehmen",
    "sg:phone":"+43 2275 5339",
    "sg:postcode":"3451",
    "sg:province":"Nieder\u00f6sterreich",
    "wof:name":"R\u00f6dl Johann",
    "wof:placetype":"venue"
},
  "geometry": {"coordinates":[15.9447984695,48.2894325256],"type":"Point"}
}