{
  "type": "Feature",
  "properties": {
    "iso:country":"AT",
    "sg:address":"Ferdinandstr 28",
    "sg:city":"Wien",
    "sg:orig_category":"Hafnereien",
    "sg:phone":"+43 1 2169961",
    "sg:postcode":"1020",
    "sg:province":"Wien",
    "wof:name":"Neuhold Anton",
    "wof:placetype":"venue"
},
  "geometry": {"coordinates":[16.3860607147,48.2134475708],"type":"Point"}
}