{
  "type": "Feature",
  "properties": {
    "addr:full":"Raiffeisenstr 61 Graz Steiermark 8010",
    "addr:housenumber":"61",
    "addr:postcode":"8010",
    "addr:street":"Raiffeisenstr",
    "iso:country":"AT",
    "sg:address":"Raiffeisenstr 61",
    "sg:city":"Graz",
    "sg:classifiers":[
        {
            "category":"Utilities",
            "subcategory":"Recycling",
            "type":"Services"
        }
    ],
    "sg:phone":"+43 4366 48264146",
    "sg:postcode":"8010",
    "sg:province":"Steiermark",
    "wof:name":"Rieger Entsorgungsbetrieb",
    "wof:placetype":"venue"
},
  "geometry": {"coordinates":[15.4483451843,47.0515289307],"type":"Point"}
}