{
  "type": "Feature",
  "properties": {
    "iso:country":"AT",
    "sg:address":"Bahnhofstrasse 4",
    "sg:city":"Lamprechtshausen",
    "sg:classifiers":[
        {
            "category":"Professional",
            "subcategory":"Printing & Photocopies",
            "type":"Services"
        }
    ],
    "sg:phone":"+43 6274 77008",
    "sg:postcode":"5112",
    "sg:province":"Salzburg",
    "sg:tags":[
        "offset"
    ],
    "sg:website":"kollermedia.com",
    "wof:name":"Koller Druck GmbH",
    "wof:placetype":"venue"
},
  "geometry": {"coordinates":[12.9525117874,47.9905433655],"type":"Point"}
}