{
  "type": "Feature",
  "properties": {
    "addr:full":"Haidgasse 8/12 Wien Wien 1020",
    "addr:housenumber":"8 / 12",
    "addr:postcode":"1020",
    "addr:street":"Haidgasse",
    "iso:country":"AT",
    "sg:address":"Haidgasse 8/12",
    "sg:city":"Wien",
    "sg:orig_category":"Freizeit, Partnerschaft",
    "sg:phone":"+43 4312 143758",
    "sg:postcode":"1020",
    "sg:province":"Wien",
    "sg:website":"http://members.teleweb.at/r.mahut",
    "wof:name":"Briefmarken stamps",
    "wof:placetype":"venue"
},
  "geometry": {"coordinates":[16.3790073395,48.217830658],"type":"Point"}
}