{
  "type": "Feature",
  "properties": {
    "iso:country":"AT",
    "sg:address":"Rainerstr 25",
    "sg:city":"Salzburg",
    "sg:orig_category":"Immobilienverwaltungen",
    "sg:phone":"+43 662 873472",
    "sg:postcode":"5020",
    "sg:province":"Salzburg",
    "wof:name":"CG DEVELOPMENT Bauobjektentwicklungs GmbH",
    "wof:placetype":"venue"
},
  "geometry": {"coordinates":[13.0431413651,47.8110580444],"type":"Point"}
}