{
  "type": "Feature",
  "properties": {
    "iso:country":"AT",
    "sg:address":"Rathauspl 2",
    "sg:city":"Salzburg",
    "sg:orig_category":"Damenmoden",
    "sg:phone":"+43 662 8445660",
    "sg:postcode":"5020",
    "sg:province":"Salzburg",
    "wof:name":"H\u00e4mmerle - Das Modehaus",
    "wof:placetype":"venue"
},
  "geometry": {"coordinates":[13.0444879532,47.7999610901],"type":"Point"}
}