{
  "type": "Feature",
  "properties": {
    "addr:full":"Neustiftg 8a Baden Nieder\u00f6sterreich 2500",
    "addr:housenumber":"8a",
    "addr:postcode":"2500",
    "addr:street":"Neustiftg;Niederoesterreich",
    "iso:country":"AT",
    "sg:address":"Neustiftg 8a",
    "sg:city":"Baden",
    "sg:orig_category":"Maler, Anstreicher U Lackierer",
    "sg:phone":"+43 4322 5248619",
    "sg:postcode":"2500",
    "sg:province":"Nieder\u00f6sterreich",
    "wof:name":"Weber Alois GesmbH & Co KG",
    "wof:placetype":"venue"
},
  "geometry": {"coordinates":[16.2374649048,48.006816864],"type":"Point"}
}