{
  "type": "Feature",
  "properties": {
    "addr:full":"Kircheng 1 Sulz im Wienerwald Nieder\u00f6sterreich 2392",
    "addr:housenumber":"1",
    "addr:postcode":"2392",
    "addr:street":"Kircheng",
    "iso:country":"AT",
    "sg:address":"Kircheng 1",
    "sg:city":"Sulz im Wienerwald",
    "sg:classifiers":[
        {
            "category":"Travel",
            "subcategory":"Hotels & Motels",
            "type":"Entertainment"
        }
    ],
    "sg:phone":"+43 2238 8113",
    "sg:postcode":"2392",
    "sg:province":"Nieder\u00f6sterreich",
    "wof:name":"Hotel-Restaurant Sulzerhof",
    "wof:placetype":"venue"
},
  "geometry": {"coordinates":[16.1373767853,48.1029205322],"type":"Point"}
}