{
  "type": "Feature",
  "properties": {
    "addr:full":"Krotenthallerg 10 Wien Wien 1080",
    "addr:housenumber":"10",
    "addr:postcode":"1080",
    "addr:street":"Krotenthallerg",
    "iso:country":"AT",
    "sg:address":"Krotenthallerg 10",
    "sg:city":"Wien",
    "sg:classifiers":[
        {
            "category":"Organizations",
            "subcategory":"Community Association",
            "type":"Services"
        }
    ],
    "sg:phone":"+43 1 40380600",
    "sg:postcode":"1080",
    "sg:province":"Wien",
    "sg:tags":[
        "relation",
        "public"
    ],
    "wof:name":"G\u00f6rner Kommunikation",
    "wof:placetype":"venue"
},
  "geometry": {"coordinates":[16.345489502,48.212097168],"type":"Point"}
}