{
  "type": "Feature",
  "properties": {
    "iso:country":"AT",
    "sg:address":"Neubauweg 5",
    "sg:city":"St. Johann in Tirol",
    "sg:orig_category":"Musikunterricht",
    "sg:phone":"+43 5352 61860",
    "sg:postcode":"6380",
    "sg:province":"Tirol",
    "wof:name":"Landesmusikschule St Johann i Tirol",
    "wof:placetype":"venue"
},
  "geometry": {"coordinates":[12.4282827377,47.5240745544],"type":"Point"}
}