{
  "type": "Feature",
  "properties": {
    "iso:country":"AT",
    "sg:address":"Fasanweg 279",
    "sg:city":"Willendorf am Steinfelde",
    "sg:orig_category":"Elektroinstallationsunternehmen",
    "sg:phone":"+43 4326 202944",
    "sg:postcode":"2732",
    "sg:province":"Nieder\u00f6sterreich",
    "wof:name":"Tampir Josef Ing",
    "wof:placetype":"venue"
},
  "geometry": {"coordinates":[16.0573596954,47.7712059021],"type":"Point"}
}