{
  "type": "Feature",
  "properties": {
    "addr:full":"Sechshauser Str 56 Wien Wien 1150",
    "addr:postcode":"1150",
    "addr:street":"56",
    "iso:country":"AT",
    "sg:address":"Sechshauser Str 56",
    "sg:city":"Wien",
    "sg:orig_category":"Religionsgesellschaften / Bekenntnisgemeinschaften",
    "sg:phone":"+43 4318 958175",
    "sg:postcode":"1150",
    "sg:province":"Wien",
    "wof:name":"Evangelisch-Methodistische Kirche in \u00f6sterreich",
    "wof:placetype":"venue"
},
  "geometry": {"coordinates":[16.3302536011,48.1874275208],"type":"Point"}
}