{
  "type": "Feature",
  "properties": {
    "iso:country":"AT",
    "sg:address":"Steinbergstr 2",
    "sg:city":"Wetzelsdorf",
    "sg:orig_category":"Pensionen / Privatzimmer",
    "sg:phone":"+43 316 584528",
    "sg:postcode":"8052",
    "sg:province":"Steiermark",
    "wof:name":"Fr\u00fchst\u00fcckspension G\u00e4stehaus Graschi",
    "wof:placetype":"venue"
},
  "geometry": {"coordinates":[15.3905611038,47.0591659546],"type":"Point"}
}