{
  "type": "Feature",
  "properties": {
    "addr:full":"Wiesenstr 34 Wels Ober\u00f6sterreich 4600",
    "addr:housenumber":"34",
    "addr:postcode":"4600",
    "addr:street":"Wiesenstr;Oberoesterreich",
    "iso:country":"AT",
    "sg:address":"Wiesenstr 34",
    "sg:city":"Wels",
    "sg:orig_category":"Lebensmittel / Einzelhandel",
    "sg:phone":"+43 7242 45601",
    "sg:postcode":"4600",
    "sg:province":"Ober\u00f6sterreich",
    "wof:name":"Spar-Markt Inh Johann Nei\u00dfl",
    "wof:placetype":"venue"
},
  "geometry": {"coordinates":[14.0376367569,48.1618461609],"type":"Point"}
}