{
  "type": "Feature",
  "properties": {
    "addr:full":"Dr.-Wilhelm-Taucher-Str 2/II F\u00fcrstenfeld Steiermark 8280",
    "addr:housenumber":"2 / ii",
    "addr:postcode":"8280",
    "addr:street":"Dr.-Wilhelm-Taucher-Str",
    "iso:country":"AT",
    "sg:address":"Dr.-Wilhelm-Taucher-Str 2/II",
    "sg:city":"F\u00fcrstenfeld",
    "sg:orig_category":"Massagen",
    "sg:phone":"+43 4333 8252762",
    "sg:postcode":"8280",
    "sg:province":"Steiermark",
    "wof:name":"Domiter Ursula",
    "wof:placetype":"venue"
},
  "geometry": {"coordinates":[16.073474884,47.0493888855],"type":"Point"}
}