{
  "type": "Feature",
  "properties": {
    "addr:full":"Dorf 16 Dienten am Hochk\u00f6nig Salzburg 5652",
    "addr:housenumber":"16",
    "addr:postcode":"5652",
    "addr:street":"Dorf;Salzburg",
    "iso:country":"AT",
    "sg:address":"Dorf 16",
    "sg:city":"Dienten am Hochk\u00f6nig",
    "sg:classifiers":[
        {
            "category":"Travel",
            "subcategory":"Hotels & Motels",
            "type":"Entertainment"
        }
    ],
    "sg:phone":"+43 6461 2040",
    "sg:postcode":"5652",
    "sg:province":"Salzburg",
    "wof:name":"Wellnesshotel Mitterwirt",
    "wof:placetype":"venue"
},
  "geometry": {"coordinates":[13.0029220581,47.3823356628],"type":"Point"}
}