{
  "type": "Feature",
  "properties": {
    "addr:full":"Burgwies 42 Stuhlfelden Salzburg 5724",
    "addr:housenumber":"42",
    "addr:postcode":"5724",
    "addr:street":"Burgwies;Salzburg",
    "iso:country":"AT",
    "sg:address":"Burgwies 42",
    "sg:city":"Stuhlfelden",
    "sg:orig_category":"Werbeagenturen",
    "sg:phone":"+43 4365 6248623",
    "sg:postcode":"5724",
    "sg:province":"Salzburg",
    "sg:website":"rc-design.at",
    "wof:name":"Werbegrafik RC-Design",
    "wof:placetype":"venue"
},
  "geometry": {"coordinates":[12.516699791,47.2867240906],"type":"Point"}
}