{
  "type": "Feature",
  "properties": {
    "iso:country":"AT",
    "sg:address":"Ziegelfeldstrasse 3",
    "sg:city":"Tulln an der Donau",
    "sg:classifiers":[
        {
            "category":"Banks & Credit Unions",
            "subcategory":"Atm",
            "type":"Services"
        }
    ],
    "sg:phone":"+43 2272 82650",
    "sg:postcode":"3430",
    "sg:province":"Nieder\u00f6sterreich",
    "sg:tags":[
        "machine",
        "teller",
        "automated"
    ],
    "sg:website":"ibt.banktech.com",
    "wof:name":"IBT Innovative Bankentechnology GmbH",
    "wof:placetype":"venue"
},
  "geometry": {"coordinates":[16.0757808685,48.320274353],"type":"Point"}
}