{
  "type": "Feature",
  "properties": {
    "addr:full":"Leharg 6-8 Oberwart Burgenland 7400",
    "addr:housenumber":"6-8",
    "addr:postcode":"7400",
    "addr:street":"Leharg",
    "iso:country":"AT",
    "sg:address":"Leharg 6-8",
    "sg:city":"Oberwart",
    "sg:orig_category":"Trachtenbekleidung",
    "sg:phone":"+43 3352 33582",
    "sg:postcode":"7400",
    "sg:province":"Burgenland",
    "wof:name":"Trachtenstadl Christina",
    "wof:placetype":"venue"
},
  "geometry": {"coordinates":[16.2077579498,47.2893943787],"type":"Point"}
}