{
  "type": "Feature",
  "properties": {
    "addr:full":"Hofmannsthalstr Zell am See Salzburg 5700",
    "addr:postcode":"5700",
    "addr:street":"Hofmannsthalstr",
    "iso:country":"AT",
    "sg:address":"Hofmannsthalstr",
    "sg:city":"Zell am See",
    "sg:classifiers":[
        {
            "category":"Travel",
            "subcategory":"Hotels & Motels",
            "type":"Entertainment"
        }
    ],
    "sg:phone":"+43 6542 726090",
    "sg:postcode":"5700",
    "sg:province":"Salzburg",
    "wof:name":"Schlo\u00df Hotel Prielau",
    "wof:placetype":"venue"
},
  "geometry": {"coordinates":[12.8053331375,47.3416099548],"type":"Point"}
}