{
  "type": "Feature",
  "properties": {
    "addr:full":"Seideng 14 Wien Wien 1070",
    "addr:housenumber":"14",
    "addr:postcode":"1070",
    "addr:street":"Seideng",
    "iso:country":"AT",
    "sg:address":"Seideng 14",
    "sg:city":"Wien",
    "sg:orig_category":"Elektrotechnik",
    "sg:phone":"+43 1 52321720",
    "sg:postcode":"1070",
    "sg:province":"Wien",
    "wof:name":"Hirt Karl",
    "wof:placetype":"venue"
},
  "geometry": {"coordinates":[16.3443012238,48.2004928589],"type":"Point"}
}