{
  "type": "Feature",
  "properties": {
    "addr:full":"Hauptstr 20 Reichenfels K\u00e4rnten 9463",
    "addr:housenumber":"20",
    "addr:postcode":"9463",
    "addr:street":"Hauptstr;Kaernten",
    "iso:country":"AT",
    "sg:address":"Hauptstr 20",
    "sg:city":"Reichenfels",
    "sg:orig_category":"Elektroinstallationsunternehmen",
    "sg:phone":"+43 4359 22380",
    "sg:postcode":"9463",
    "sg:province":"K\u00e4rnten",
    "wof:name":"Elektro Sturmer GmbH",
    "wof:placetype":"venue"
},
  "geometry": {"coordinates":[14.7435560226,47.0071182251],"type":"Point"}
}