{
  "type": "Feature",
  "properties": {
    "iso:country":"AT",
    "sg:address":"Nr 46",
    "sg:city":"Schrems",
    "sg:orig_category":"Biologische Produkte",
    "sg:phone":"+43 2853 78470",
    "sg:postcode":"3943",
    "sg:province":"Nieder\u00f6sterreich",
    "wof:name":"Bioservice Zach GmbH",
    "wof:placetype":"venue"
},
  "geometry": {"coordinates":[15.0714254379,48.7929534912],"type":"Point"}
}