{
  "type": "Feature",
  "properties": {
    "addr:full":"Europapl 2 Villach K\u00e4rnten 9500",
    "addr:housenumber":"2",
    "addr:postcode":"9500",
    "addr:street":"Europapl;Kaernten",
    "iso:country":"AT",
    "sg:address":"Europapl 2",
    "sg:city":"Villach",
    "sg:orig_category":"Forschungsinstitute",
    "sg:phone":"+43 4242 217721",
    "sg:postcode":"9500",
    "sg:province":"K\u00e4rnten",
    "wof:name":"Ludwig Boltzmann Institut f Interkulturelle Bildungsforschung",
    "wof:placetype":"venue"
},
  "geometry": {"coordinates":[13.8498430252,46.615322113],"type":"Point"}
}