{
  "type": "Feature",
  "properties": {
    "addr:full":"Sp\u00f6rlingasse 6 Wien Wien 1060",
    "addr:housenumber":"6",
    "addr:postcode":"1060",
    "addr:street":"Spoerlingasse",
    "iso:country":"AT",
    "sg:address":"Sp\u00f6rlingasse 6",
    "sg:city":"Wien",
    "sg:orig_category":"Dental Bonding Materials",
    "sg:phone":"+43 1 5870706",
    "sg:postcode":"1060",
    "sg:province":"Wien",
    "wof:name":"Mauritsch Ges.m.b.H.",
    "wof:placetype":"venue"
},
  "geometry": {"coordinates":[16.3504657745,48.1947135925],"type":"Point"}
}