{
  "type": "Feature",
  "properties": {
    "addr:full":"Furth 43 Bad Gams Steiermark 8524",
    "addr:housenumber":"43",
    "addr:postcode":"8524",
    "addr:street":"Furth",
    "iso:country":"AT",
    "sg:address":"Furth 43",
    "sg:city":"Bad Gams",
    "sg:orig_category":"Filmproduktionen",
    "sg:phone":"+43 4334 633367",
    "sg:postcode":"8524",
    "sg:province":"Steiermark",
    "wof:name":"STRUNZ FILM - Film & Video Production",
    "wof:placetype":"venue"
},
  "geometry": {"coordinates":[15.2287683487,46.8655738831],"type":"Point"}
}