{
  "type": "Feature",
  "properties": {
    "addr:full":"Eichenstr 7 Hohenems Vorarlberg 6845",
    "addr:housenumber":"7",
    "addr:postcode":"6845",
    "addr:street":"Eichenstr",
    "iso:country":"AT",
    "sg:address":"Eichenstr 7",
    "sg:city":"Hohenems",
    "sg:orig_category":"Psychotherapie",
    "sg:phone":"+43 4355 7679334",
    "sg:postcode":"6845",
    "sg:province":"Vorarlberg",
    "wof:name":"Praxis f\u00fcr Psychotherapie - Cornelia Cubasch-K\u00f6nig",
    "wof:placetype":"venue"
},
  "geometry": {"coordinates":[9.6786756516,47.3669471741],"type":"Point"}
}