{
  "type": "Feature",
  "properties": {
    "addr:full":"Nibelungenl\u00e4nde 7A Melk Nieder\u00f6sterreich 3390",
    "addr:housenumber":"7a",
    "addr:postcode":"3390",
    "addr:street":"Nibelungenlaende",
    "iso:country":"AT",
    "sg:address":"Nibelungenl\u00e4nde 7A",
    "sg:city":"Melk",
    "sg:classifiers":[
        {
            "category":"Landmark",
            "subcategory":"Square",
            "type":"Public Place"
        }
    ],
    "sg:phone":"+43 4327 5250003",
    "sg:postcode":"3390",
    "sg:province":"Nieder\u00f6sterreich",
    "sg:tags":[
        "geometer"
    ],
    "wof:name":"Jonke Rainer Dipl-Ing",
    "wof:placetype":"venue"
},
  "geometry": {"coordinates":[15.3269643784,48.2264213562],"type":"Point"}
}