{
  "type": "Feature",
  "properties": {
    "iso:country":"AT",
    "sg:address":"Sch\u00f6nbrunner Strasse 285",
    "sg:city":"Wien",
    "sg:classifiers":[
        {
            "category":"Shopping",
            "subcategory":"Crafts & Fabrics",
            "type":"Retail Goods"
        }
    ],
    "sg:phone":"+43 1 8136667",
    "sg:postcode":"1120",
    "sg:province":"Wien",
    "sg:tags":[
        "adhesive"
    ],
    "wof:name":"Minerol Industrieprodukte Handelsges.m.b.H.",
    "wof:placetype":"venue"
},
  "geometry": {"coordinates":[16.3247585297,48.1826934814],"type":"Point"}
}