{
  "type": "Feature",
  "properties": {
    "addr:full":"Untere Hauptstr 1 Jois Burgenland 7093",
    "addr:housenumber":"1",
    "addr:postcode":"7093",
    "addr:street":"Untere Hauptstr",
    "iso:country":"AT",
    "sg:address":"Untere Hauptstr 1",
    "sg:city":"Jois",
    "sg:orig_category":"Diskotheken",
    "sg:phone":"+43 4321 608335",
    "sg:postcode":"7093",
    "sg:province":"Burgenland",
    "wof:name":"Diskothek Safari",
    "wof:placetype":"venue"
},
  "geometry": {"coordinates":[16.7907962799,47.9593048096],"type":"Point"}
}