{
  "type": "Feature",
  "properties": {
    "addr:full":"Hofweid 7 Steinakirchen am Forst Nieder\u00f6sterreich 3261",
    "addr:housenumber":"7",
    "addr:postcode":"3261",
    "addr:street":"Hofweid",
    "iso:country":"AT",
    "sg:address":"Hofweid 7",
    "sg:city":"Steinakirchen am Forst",
    "sg:orig_category":"Dienstleistungen, Sonstige Dienstleistungen",
    "sg:phone":"+43 7488",
    "sg:postcode":"3261",
    "sg:province":"Nieder\u00f6sterreich",
    "sg:website":"http://members.tripod.de/studioneptun",
    "wof:name":"Studio Neptun",
    "wof:placetype":"venue"
},
  "geometry": {"coordinates":[15.0643281937,48.077457428],"type":"Point"}
}