{
  "type": "Feature",
  "properties": {
    "addr:full":"Fischauer Gasse 113b Wiener Neustadt Nieder\u00f6sterreich 2700",
    "addr:housenumber":"113b",
    "addr:postcode":"2700",
    "addr:street":"Fischauer Gasse",
    "iso:country":"AT",
    "sg:address":"Fischauer Gasse 113b",
    "sg:city":"Wiener Neustadt",
    "sg:classifiers":[
        {
            "category":"Home & Garden",
            "subcategory":"Building Materials",
            "type":"Retail Goods"
        }
    ],
    "sg:phone":"+43 2622 23364",
    "sg:postcode":"2700",
    "sg:province":"Nieder\u00f6sterreich",
    "sg:tags":[
        "central",
        "heating",
        "boiler"
    ],
    "wof:name":"Josefy Ges.m.b.H.",
    "wof:placetype":"venue"
},
  "geometry": {"coordinates":[16.2333126068,47.8214759827],"type":"Point"}
}