{
  "type": "Feature",
  "properties": {
    "addr:full":"Oberdorfstr 4 Fuschl am See Salzburg 5330",
    "addr:housenumber":"4",
    "addr:postcode":"5330",
    "addr:street":"Oberdorfstr",
    "iso:country":"AT",
    "sg:address":"Oberdorfstr 4",
    "sg:city":"Fuschl am See",
    "sg:orig_category":"Friseure U Frisiersalons",
    "sg:phone":"+43 4362 268261",
    "sg:postcode":"5330",
    "sg:province":"Salzburg",
    "wof:name":"Frisiersalon Haarstudio Andrea",
    "wof:placetype":"venue"
},
  "geometry": {"coordinates":[13.304227829,47.7966003418],"type":"Point"}
}