{
  "type": "Feature",
  "properties": {
    "addr:full":"Maurer Lange G 108-120 Wien Wien 1230",
    "addr:postcode":"108-120;1230",
    "addr:street":"Maurer Lange G",
    "iso:country":"AT",
    "sg:address":"Maurer Lange G 108-120",
    "sg:city":"Wien",
    "sg:orig_category":"Fitnesscenter",
    "sg:phone":"+43 699 10757717",
    "sg:postcode":"1230",
    "sg:province":"Wien",
    "wof:name":"Strnad Bettina",
    "wof:placetype":"venue"
},
  "geometry": {"coordinates":[16.2613925934,48.1485137939],"type":"Point"}
}