{
  "type": "Feature",
  "properties": {
    "addr:full":"Nr 123 Niederleis Nieder\u00f6sterreich 2116",
    "addr:postcode":"2116",
    "addr:street":"Nr 123",
    "iso:country":"AT",
    "sg:address":"Nr 123",
    "sg:city":"Niederleis",
    "sg:orig_category":"\u00c3\u201erzte / F Allgemeinmedizin",
    "sg:phone":"+43 2576 23120",
    "sg:postcode":"2116",
    "sg:province":"Nieder\u00f6sterreich",
    "wof:name":"Hahn Alois Dr",
    "wof:placetype":"venue"
},
  "geometry": {"coordinates":[16.3956756592,48.5561676025],"type":"Point"}
}