{
  "type": "Feature",
  "properties": {
    "iso:country":"AT",
    "sg:address":"Salzburger Str 22",
    "sg:city":"Seekirchen am Wallersee",
    "sg:orig_category":"Sonnenstudios",
    "sg:phone":"+43 4362 122074",
    "sg:postcode":"5201",
    "sg:province":"Salzburg",
    "wof:name":"Br\u00e4unungscenter Sun Star",
    "wof:placetype":"venue"
},
  "geometry": {"coordinates":[13.1235675812,47.8861465454],"type":"Point"}
}