{
  "type": "Feature",
  "properties": {
    "addr:full":"Sch\u00f6nau 101 Bad H\u00e4ring Tirol 6323",
    "addr:housenumber":"101",
    "addr:postcode":"6323",
    "addr:street":"Tirol",
    "iso:country":"AT",
    "sg:address":"Sch\u00f6nau 101",
    "sg:city":"Bad H\u00e4ring",
    "sg:classifiers":[
        {
            "category":"Recreation",
            "subcategory":"Water Park",
            "type":"Entertainment"
        }
    ],
    "sg:phone":"+43 5332 74738",
    "sg:postcode":"6323",
    "sg:province":"Tirol",
    "sg:tags":[
        "garden",
        "bench"
    ],
    "sg:website":"rechen.at",
    "wof:name":"Gerhard Winkler",
    "wof:placetype":"venue"
},
  "geometry": {"coordinates":[-88.67497253419999,43.9075889587],"type":"Point"}
}