{
  "type": "Feature",
  "properties": {
    "addr:full":"Konstantingasse 1 Wien Wien 1160",
    "addr:housenumber":"1",
    "addr:postcode":"1160",
    "addr:street":"Konstantingasse",
    "iso:country":"AT",
    "sg:address":"Konstantingasse 1",
    "sg:city":"Wien",
    "sg:classifiers":[
        {
            "category":"Structure",
            "subcategory":"Restrooms",
            "type":"Public Place"
        }
    ],
    "sg:phone":"+43 676 4283903",
    "sg:postcode":"1160",
    "sg:province":"Wien",
    "sg:tags":[
        "equipment",
        "bath"
    ],
    "wof:name":"Tischlerei Ludwig Weichinger-Hieden",
    "wof:placetype":"venue"
},
  "geometry": {"coordinates":[16.3086566925,48.2168540955],"type":"Point"}
}