{
  "type": "Feature",
  "properties": {
    "addr:full":"Krieglach Steiermark 8670",
    "addr:postcode":"8670",
    "iso:country":"AT",
    "sg:city":"Krieglach",
    "sg:orig_category":"Feuerwehren",
    "sg:phone":"+43 3855 2222",
    "sg:postcode":"8670",
    "sg:province":"Steiermark",
    "wof:name":"Freiwillige Feuerwehr Krieglach",
    "wof:placetype":"venue"
},
  "geometry": {"coordinates":[15.5594148636,47.5454101562],"type":"Point"}
}