{
  "type": "Feature",
  "properties": {
    "addr:full":"Reisnerstr 34 Wien Wien 1030",
    "addr:housenumber":"34",
    "addr:postcode":"1030",
    "addr:street":"Reisnerstr",
    "iso:country":"AT",
    "sg:address":"Reisnerstr 34",
    "sg:city":"Wien",
    "sg:orig_category":"\u00c3\u201erzte / F Allgemeinmedizin",
    "sg:phone":"+43 1 7143350",
    "sg:postcode":"1030",
    "sg:province":"Wien",
    "wof:name":"Konzett Martin Dr",
    "wof:placetype":"venue"
},
  "geometry": {"coordinates":[16.3836669922,48.1995429993],"type":"Point"}
}