{
  "type": "Feature",
  "properties": {
    "iso:country":"AT",
    "sg:address":"Christopherusstr. 9 ",
    "sg:city":"Elsbethen-Glasenbach",
    "sg:classifiers":[
        {
            "category":"Shopping",
            "type":"Retail Goods"
        }
    ],
    "sg:phone":"+43 4366 26212540",
    "sg:postcode":"5061",
    "sg:province":"Salzburg",
    "sg:tags":[
        "finished",
        "-",
        "metallic"
    ],
    "wof:name":"REITER GES.MBH & CO KG",
    "wof:placetype":"venue"
},
  "geometry": {"coordinates":[13.0815105438,47.7499275208],"type":"Point"}
}