{
  "type": "Feature",
  "properties": {
    "iso:country":"AT",
    "sg:address":"Kleinschmidg 1/14",
    "sg:city":"Wien",
    "sg:orig_category":"Architekten",
    "sg:phone":"+43 1 5861979",
    "sg:postcode":"1040",
    "sg:province":"Wien",
    "wof:name":"Szedonja Josef Arch Dipl-Ing",
    "wof:placetype":"venue"
},
  "geometry": {"coordinates":[16.365398407,48.1940956116],"type":"Point"}
}