{
  "type": "Feature",
  "properties": {
    "addr:full":"Jakoministr 30-32 Graz Steiermark 8010",
    "addr:postcode":"30-32;8010",
    "iso:country":"AT",
    "sg:address":"Jakoministr 30-32",
    "sg:city":"Graz",
    "sg:orig_category":"Schuhreparatur",
    "sg:phone":"+43 4331 6839800",
    "sg:postcode":"8010",
    "sg:province":"Steiermark",
    "wof:name":"Minuten-Service Schuh- u Schl\u00fcssel-Sofortdienst",
    "wof:placetype":"venue"
},
  "geometry": {"coordinates":[15.4423131943,47.0649452209],"type":"Point"}
}