{
  "type": "Feature",
  "properties": {
    "addr:full":"Bahnhofstr 37 St. Veit an der Glan K\u00e4rnten 9300",
    "addr:housenumber":"37",
    "addr:postcode":"9300",
    "addr:street":"Bahnhofstr;Kaernten",
    "iso:country":"AT",
    "sg:address":"Bahnhofstr 37",
    "sg:city":"St. Veit an der Glan",
    "sg:orig_category":"Fotografen",
    "sg:phone":"+43 4212 20530",
    "sg:postcode":"9300",
    "sg:province":"K\u00e4rnten",
    "wof:name":"Hammerschlag Wolfgang",
    "wof:placetype":"venue"
},
  "geometry": {"coordinates":[14.3651580811,46.7702522278],"type":"Point"}
}