{
  "type": "Feature",
  "properties": {
    "addr:full":"Marktstr 47 St. Michael im Lungau Salzburg 5582",
    "addr:housenumber":"47",
    "addr:postcode":"5582",
    "addr:street":"Marktstr;Salzburg",
    "iso:country":"AT",
    "sg:address":"Marktstr 47",
    "sg:city":"St. Michael im Lungau",
    "sg:orig_category":"Biologische Produkte",
    "sg:phone":"+43 6477 69949",
    "sg:postcode":"5582",
    "sg:province":"Salzburg",
    "wof:name":"Tinas Alternativladen",
    "wof:placetype":"venue"
},
  "geometry": {"coordinates":[13.6381587982,47.0977020264],"type":"Point"}
}