{
  "type": "Feature",
  "properties": {
    "addr:full":"Industriestrasse 39-45 Traun Ober\u00f6sterreich 4050",
    "addr:postcode":"39-45;4050",
    "addr:street":"Industriestrasse",
    "iso:country":"AT",
    "sg:address":"Industriestrasse 39-45",
    "sg:city":"Traun",
    "sg:classifiers":[
        {
            "category":"Manufacturing",
            "subcategory":"Rubber & Plastics",
            "type":"Manufacturing & Wholesale Goods"
        }
    ],
    "sg:phone":"+43 732 3814940",
    "sg:postcode":"4050",
    "sg:province":"Ober\u00f6sterreich",
    "sg:tags":[
        "film"
    ],
    "sg:website":"durabit.com",
    "wof:name":"DURABIT-BAUPLAST Ges.m.b.H. & Co KG",
    "wof:placetype":"venue"
},
  "geometry": {"coordinates":[14.2682161331,48.2442359924],"type":"Point"}
}