{
  "type": "Feature",
  "properties": {
    "addr:full":"Grubackerg 297 Gloggnitz Nieder\u00f6sterreich 2640",
    "addr:housenumber":"297",
    "addr:postcode":"2640",
    "addr:street":"Gloggnitz Niederoesterreich",
    "iso:country":"AT",
    "sg:address":"Grubackerg 297",
    "sg:city":"Gloggnitz",
    "sg:orig_category":"Werbegrafik- U Grafik-Design",
    "sg:phone":"+43 2662 44347",
    "sg:postcode":"2640",
    "sg:province":"Nieder\u00f6sterreich",
    "wof:name":"Dietrich Stefan",
    "wof:placetype":"venue"
},
  "geometry": {"coordinates":[15.9461631775,47.6663780212],"type":"Point"}
}