{
  "type": "Feature",
  "properties": {
    "addr:full":"Kirchenpl 12 Horn Nieder\u00f6sterreich 3580",
    "addr:housenumber":"12",
    "addr:postcode":"3580",
    "addr:street":"Kirchenpl",
    "iso:country":"AT",
    "sg:address":"Kirchenpl 12",
    "sg:city":"Horn",
    "sg:orig_category":"Bankomat-Standorte",
    "sg:phone":"+43 2982 3433",
    "sg:postcode":"3580",
    "sg:province":"Nieder\u00f6sterreich",
    "wof:name":"Bankomat d Sparkasse Ravelsbach-Kirchberg",
    "wof:placetype":"venue"
},
  "geometry": {"coordinates":[15.6578979492,48.6639289856],"type":"Point"}
}