{
  "type": "Feature",
  "properties": {
    "addr:full":"Lavieren 2 Tulfes Tirol 6075",
    "addr:housenumber":"2",
    "addr:postcode":"6075",
    "addr:street":"Lavieren;Tirol",
    "iso:country":"AT",
    "sg:address":"Lavieren 2",
    "sg:city":"Tulfes",
    "sg:orig_category":"Pensionen / Privatzimmer",
    "sg:phone":"+43 5223 78157",
    "sg:postcode":"6075",
    "sg:province":"Tirol",
    "wof:name":"Pfunerhof Inh Josef Geisler",
    "wof:placetype":"venue"
},
  "geometry": {"coordinates":[11.5120706558,47.2520332336],"type":"Point"}
}