{
  "type": "Feature",
  "properties": {
    "addr:full":"Buchengasse 79 Wien Wien 1100",
    "addr:housenumber":"79",
    "addr:postcode":"1100",
    "addr:street":"Buchengasse",
    "iso:country":"AT",
    "sg:address":"Buchengasse 79",
    "sg:city":"Wien",
    "sg:classifiers":[
        {
            "category":"Manufacturing",
            "subcategory":"Paper Products",
            "type":"Manufacturing & Wholesale Goods"
        }
    ],
    "sg:phone":"+43 1 60441210",
    "sg:postcode":"1100",
    "sg:province":"Wien",
    "sg:tags":[
        "brochure",
        "production"
    ],
    "wof:name":"Franz Holzer Inh. Walter Schmutzer",
    "wof:placetype":"venue"
},
  "geometry": {"coordinates":[16.374174118,48.1748085022],"type":"Point"}
}