{
  "type": "Feature",
  "properties": {
    "addr:full":"Stelzhamerstr 3 Neuhofen an der Krems Ober\u00f6sterreich 4501",
    "addr:housenumber":"3",
    "addr:postcode":"4501",
    "addr:street":"Stelzhamerstr",
    "iso:country":"AT",
    "sg:address":"Stelzhamerstr 3",
    "sg:city":"Neuhofen an der Krems",
    "sg:orig_category":"Juweliere, Gold- U Silberschmiede",
    "sg:phone":"+43 4372 275249",
    "sg:postcode":"4501",
    "sg:province":"Ober\u00f6sterreich",
    "wof:name":"Goldschmiede Beer",
    "wof:placetype":"venue"
},
  "geometry": {"coordinates":[14.2259368896,48.1333007812],"type":"Point"}
}