{
  "type": "Feature",
  "properties": {
    "iso:country":"AT",
    "sg:address":"Stelzhamerstr 3",
    "sg:city":"Neuhofen an der Krems",
    "sg:orig_category":"Juweliere, Gold- U Silberschmiede",
    "sg:phone":"+43 4372 275249",
    "sg:postcode":"4501",
    "sg:province":"Ober\u00f6sterreich",
    "wof:name":"Goldschmiede Beer",
    "wof:placetype":"venue"
},
  "geometry": {"coordinates":[14.2259368896,48.1333007812],"type":"Point"}
}