{
  "type": "Feature",
  "properties": {
    "addr:full":"Strozzig 10 Wien Wien 1080",
    "addr:housenumber":"10",
    "addr:postcode":"1080",
    "addr:street":"Strozzig",
    "iso:country":"AT",
    "sg:address":"Strozzig 10",
    "sg:city":"Wien",
    "sg:orig_category":"Botschaften",
    "sg:phone":"+43 1 4029370",
    "sg:postcode":"1080",
    "sg:province":"Wien",
    "wof:name":"Botschaft der Republik Namibia",
    "wof:placetype":"venue"
},
  "geometry": {"coordinates":[16.349439621,48.2070732117],"type":"Point"}
}