{
  "type": "Feature",
  "properties": {
    "addr:full":"Hauptpl 23 Linz Ober\u00f6sterreich 4020",
    "addr:housenumber":"23",
    "addr:postcode":"4020",
    "addr:street":"Hauptpl",
    "iso:country":"AT",
    "sg:address":"Hauptpl 23",
    "sg:city":"Linz",
    "sg:classifiers":[
        {
            "category":"Restaurant",
            "type":"Food & Drink"
        }
    ],
    "sg:phone":"+43 732 770742",
    "sg:postcode":"4020",
    "sg:province":"Ober\u00f6sterreich",
    "wof:name":"HOFArT",
    "wof:placetype":"venue"
},
  "geometry": {"coordinates":[14.2868118286,48.3048171997],"type":"Point"}
}