{
  "type": "Feature",
  "properties": {
    "iso:country":"AT",
    "sg:address":"Maroltingerg 54",
    "sg:city":"Wien",
    "sg:orig_category":"Unternehmensberatung",
    "sg:phone":"+43 1 4949394",
    "sg:postcode":"1160",
    "sg:province":"Wien",
    "wof:name":"Ambros & Zalokar OEG - Das Unternehmen f betriebliche Gesundheitsf\u00f6rderung",
    "wof:placetype":"venue"
},
  "geometry": {"coordinates":[16.3053512573,48.2090072632],"type":"Point"}
}