{
  "type": "Feature",
  "properties": {
    "addr:full":"Mittlere 576 Bezau Vorarlberg 6870",
    "addr:housenumber":"576",
    "addr:postcode":"6870",
    "addr:street":"Mittlere",
    "iso:country":"AT",
    "sg:address":"Mittlere 576",
    "sg:city":"Bezau",
    "sg:orig_category":"Spenglereien",
    "sg:phone":"+43 5514 2359",
    "sg:postcode":"6870",
    "sg:province":"Vorarlberg",
    "wof:name":"Moosbrugger Florian",
    "wof:placetype":"venue"
},
  "geometry": {"coordinates":[9.9130153656,47.3862991333],"type":"Point"}
}