{
  "type": "Feature",
  "properties": {
    "addr:full":"Herzog-Friedrich-Str 32 Innsbruck Tirol 6020",
    "addr:housenumber":"32",
    "addr:postcode":"6020",
    "addr:street":"Herzog-Friedrich-Str;Tirol",
    "iso:country":"AT",
    "sg:address":"Herzog-Friedrich-Str 32",
    "sg:city":"Innsbruck",
    "sg:classifiers":[
        {
            "category":"Shopping",
            "subcategory":"Gifts & Souvenirs",
            "type":"Retail Goods"
        }
    ],
    "sg:phone":"+43 512 581097",
    "sg:postcode":"6020",
    "sg:province":"Tirol",
    "wof:name":"Accord HandelsgesmbH & Co KG",
    "wof:placetype":"venue"
},
  "geometry": {"coordinates":[11.3932952881,47.2674789429],"type":"Point"}
}