{
  "type": "Feature",
  "properties": {
    "addr:full":"Nr 45 Artstetten Nieder\u00f6sterreich 3661",
    "addr:postcode":"3661",
    "addr:street":"Nr;Niederoesterreich",
    "iso:country":"AT",
    "sg:address":"Nr 45",
    "sg:city":"Artstetten",
    "sg:orig_category":"Psychotherapie",
    "sg:phone":"+43 4374 1381635",
    "sg:postcode":"3661",
    "sg:province":"Nieder\u00f6sterreich",
    "wof:name":"Fuchs Erika",
    "wof:placetype":"venue"
},
  "geometry": {"coordinates":[15.2035694122,48.243057251],"type":"Point"}
}