{
  "type": "Feature",
  "properties": {
    "iso:country":"AT",
    "sg:address":"H\u00f6pfnerstr 7",
    "sg:city":"Treibach-Althofen",
    "sg:orig_category":"Immobilienmakler",
    "sg:phone":"+43 4262 20830",
    "sg:postcode":"9330",
    "sg:province":"K\u00e4rnten",
    "wof:name":"Neuwirther Raimund Dr",
    "wof:placetype":"venue"
},
  "geometry": {"coordinates":[14.4745111465,46.8703041077],"type":"Point"}
}