{
  "type": "Feature",
  "properties": {
    "iso:country":"AT",
    "sg:address":"Hameaustr 39",
    "sg:city":"Wien",
    "sg:orig_category":"Waren Aller Art",
    "sg:phone":"+43 1 8775767",
    "sg:postcode":"1190",
    "sg:province":"Wien",
    "wof:name":"EPG Trading HandelsgesmbH",
    "wof:placetype":"venue"
},
  "geometry": {"coordinates":[16.2916107178,48.251739502],"type":"Point"}
}