{
  "type": "Feature",
  "properties": {
    "addr:full":"H\u00f6lzlstr 497 Wals Salzburg 5071",
    "addr:housenumber":"497",
    "addr:postcode":"5071",
    "addr:street":"Wals Salzburg",
    "iso:country":"AT",
    "sg:address":"H\u00f6lzlstr 497",
    "sg:city":"Wals",
    "sg:orig_category":"Autoersatzteile",
    "sg:phone":"+43 662 8536800",
    "sg:postcode":"5071",
    "sg:province":"Salzburg",
    "wof:name":"Forstinger Handel und Service GmbH",
    "wof:placetype":"venue"
},
  "geometry": {"coordinates":[12.9693145752,47.7897644043],"type":"Point"}
}