{
  "type": "Feature",
  "properties": {
    "iso:country":"AT",
    "sg:address":"Herzog-Ernst-G 3",
    "sg:city":"Bruck an der Mur",
    "sg:orig_category":"Bekleidung / Einzelhandel",
    "sg:phone":"+43 3862 81992",
    "sg:postcode":"8600",
    "sg:province":"Steiermark",
    "wof:name":"KBS Kleider Bauer Betriebs-GmbH",
    "wof:placetype":"venue"
},
  "geometry": {"coordinates":[15.269610405,47.4109306335],"type":"Point"}
}