{
  "type": "Feature",
  "properties": {
    "addr:full":"Nr 104 Fernitz Steiermark 8072",
    "addr:postcode":"8072",
    "addr:street":"Nr",
    "iso:country":"AT",
    "sg:address":"Nr 104",
    "sg:city":"Fernitz",
    "sg:classifiers":[
        {
            "category":"Restaurant",
            "type":"Food & Drink"
        }
    ],
    "sg:phone":"+43 3135 826770",
    "sg:postcode":"8072",
    "sg:province":"Steiermark",
    "wof:name":"Zur Stub'n am Murberg",
    "wof:placetype":"venue"
},
  "geometry": {"coordinates":[15.4987697601,46.9728660583],"type":"Point"}
}