{
  "type": "Feature",
  "properties": {
    "iso:country":"AT",
    "sg:address":"Nr 66",
    "sg:city":"G\u00fcssing",
    "sg:orig_category":"Wassertechnik",
    "sg:phone":"+43 3322 42100",
    "sg:postcode":"7540",
    "sg:province":"Burgenland",
    "wof:name":"Pientsch GmbH",
    "wof:placetype":"venue"
},
  "geometry": {"coordinates":[16.3241195679,47.0592803955],"type":"Point"}
}