{
  "type": "Feature",
  "properties": {
    "addr:full":"Wolf 42 Steinach am Brenner Tirol 6150",
    "addr:housenumber":"42",
    "addr:postcode":"6150",
    "addr:street":"Wolf;Tirol",
    "iso:country":"AT",
    "sg:address":"Wolf 42",
    "sg:city":"Steinach am Brenner",
    "sg:orig_category":"Autoreparatur",
    "sg:phone":"+43 5279 20077",
    "sg:postcode":"6150",
    "sg:province":"Tirol",
    "wof:name":"Felder Johannes",
    "wof:placetype":"venue"
},
  "geometry": {"coordinates":[11.4859523773,47.0685691833],"type":"Point"}
}