{
  "type": "Feature",
  "properties": {
    "iso:country":"AT",
    "sg:address":"Belruptstr 44",
    "sg:city":"Bregenz",
    "sg:orig_category":"Ingenieurkonsulenten / Zivilingenieure",
    "sg:phone":"+43 5574 441290",
    "sg:postcode":"6900",
    "sg:province":"Vorarlberg",
    "wof:name":"Mader & Flatz Ziviltechniker GmbH",
    "wof:placetype":"venue"
},
  "geometry": {"coordinates":[9.7534151077,47.5063285828],"type":"Point"}
}