{
  "type": "Feature",
  "properties": {
    "iso:country":"AT",
    "sg:address":"Zinzendorfg 19",
    "sg:city":"Graz",
    "sg:orig_category":"Architekturmodellbau",
    "sg:phone":"+43 316 349151",
    "sg:postcode":"8010",
    "sg:province":"Steiermark",
    "wof:name":"Wiedemscheck Lech Ing",
    "wof:placetype":"venue"
},
  "geometry": {"coordinates":[15.4485588074,47.0757751465],"type":"Point"}
}