{
  "type": "Feature",
  "properties": {
    "addr:full":"Eichelau 535 Admont Steiermark 8911",
    "addr:housenumber":"535",
    "addr:postcode":"8911",
    "iso:country":"AT",
    "sg:address":"Eichelau 535",
    "sg:city":"Admont",
    "sg:classifiers":[
        {
            "category":"Professional",
            "subcategory":"Art Services",
            "type":"Services"
        }
    ],
    "sg:phone":"+43 664 4223783",
    "sg:postcode":"8911",
    "sg:province":"Steiermark",
    "sg:tags":[
        "designer"
    ],
    "wof:name":"Remschak Doris - print-und kommunikations-design",
    "wof:placetype":"venue"
},
  "geometry": {"coordinates":[14.4635324478,47.5796051025],"type":"Point"}
}