{
  "type": "Feature",
  "properties": {
    "addr:full":"Waagstr 1 St. Veit an der Glan K\u00e4rnten 9300",
    "addr:housenumber":"1",
    "addr:postcode":"9300",
    "addr:street":"Waagstr;Kaernten",
    "iso:country":"AT",
    "sg:address":"Waagstr 1",
    "sg:city":"St. Veit an der Glan",
    "sg:orig_category":"Telekommunikation",
    "sg:phone":"+43 4342 1271499",
    "sg:postcode":"9300",
    "sg:province":"K\u00e4rnten",
    "wof:name":"Multimediacenter GmbH",
    "wof:placetype":"venue"
},
  "geometry": {"coordinates":[14.3550777435,46.7662239075],"type":"Point"}
}