{
  "type": "Feature",
  "properties": {
    "addr:full":"Windern 379 Hittisau Vorarlberg 6952",
    "addr:housenumber":"379",
    "addr:postcode":"6952",
    "addr:street":"Windern",
    "iso:country":"AT",
    "sg:address":"Windern 379",
    "sg:city":"Hittisau",
    "sg:orig_category":"Tankstellen",
    "sg:phone":"+43 4355 136357",
    "sg:postcode":"6952",
    "sg:province":"Vorarlberg",
    "wof:name":"OMV AG",
    "wof:placetype":"venue"
},
  "geometry": {"coordinates":[9.957034111,47.4576873779],"type":"Point"}
}