{
  "type": "Feature",
  "properties": {
    "addr:full":"Meidlinger Hauptstr 34 Wien Wien 1120",
    "addr:housenumber":"34",
    "addr:postcode":"1120",
    "addr:street":"Meidlinger Hauptstr",
    "iso:country":"AT",
    "sg:address":"Meidlinger Hauptstr 34",
    "sg:city":"Wien",
    "sg:orig_category":"Lottokollekturen",
    "sg:phone":"+43 1 8137738",
    "sg:postcode":"1120",
    "sg:province":"Wien",
    "wof:name":"Fiedler Helene",
    "wof:placetype":"venue"
},
  "geometry": {"coordinates":[16.3296337128,48.1795501709],"type":"Point"}
}