{
  "type": "Feature",
  "properties": {
    "addr:full":"Stadtgraben 25 Hall in Tirol Tirol 6060",
    "addr:housenumber":"25",
    "addr:postcode":"6060",
    "addr:street":"Stadtgraben;Tirol",
    "iso:country":"AT",
    "sg:address":"Stadtgraben 25",
    "sg:city":"Hall in Tirol",
    "sg:orig_category":"Steuerberatung",
    "sg:phone":"+43 4352 23531850",
    "sg:postcode":"6060",
    "sg:province":"Tirol",
    "sg:website":"wtmetzler.at",
    "wof:name":"Metzler Hubert",
    "wof:placetype":"venue"
},
  "geometry": {"coordinates":[11.5103597641,47.2826728821],"type":"Point"}
}