{
  "type": "Feature",
  "properties": {
    "addr:full":"Kirchenweg 11 Gramastetten Ober\u00f6sterreich 4201",
    "addr:housenumber":"11",
    "addr:postcode":"4201",
    "addr:street":"Kirchenweg",
    "iso:country":"AT",
    "sg:address":"Kirchenweg 11",
    "sg:city":"Gramastetten",
    "sg:orig_category":"Feuerwehren",
    "sg:phone":"+43 7239 577122",
    "sg:postcode":"4201",
    "sg:province":"Ober\u00f6sterreich",
    "wof:name":"Freiwillige Feuerwehr Eidenberg",
    "wof:placetype":"venue"
},
  "geometry": {"coordinates":[14.2334690094,48.3947486877],"type":"Point"}
}