{
  "type": "Feature",
  "properties": {
    "iso:country":"AT",
    "sg:address":"Waldsteingartenstr 135",
    "sg:city":"Wien",
    "sg:classifiers":[
        {
            "category":"Restaurant",
            "type":"Food & Drink"
        }
    ],
    "sg:phone":"+43 4317 2818130",
    "sg:postcode":"1020",
    "sg:province":"Wien",
    "wof:name":"Pratersauna - Th\u00f6ni Verena GesmbH",
    "wof:placetype":"venue"
},
  "geometry": {"coordinates":[16.4038543701,48.2132949829],"type":"Point"}
}