{
  "type": "Feature",
  "properties": {
    "addr:full":"Markt 39 T\u00fcrnitz Nieder\u00f6sterreich 3184",
    "addr:housenumber":"39",
    "addr:postcode":"3184",
    "addr:street":"Markt;Niederoesterreich",
    "iso:country":"AT",
    "sg:address":"Markt 39",
    "sg:city":"T\u00fcrnitz",
    "sg:orig_category":"Bekleidung / Einzelhandel",
    "sg:phone":"+43 4327 698326",
    "sg:postcode":"3184",
    "sg:province":"Nieder\u00f6sterreich",
    "wof:name":"Putz Johann GesmbH",
    "wof:placetype":"venue"
},
  "geometry": {"coordinates":[-76.4168395996,37.452419281],"type":"Point"}
}