{
  "type": "Feature",
  "properties": {
    "addr:full":"Urban-G\u00f6rtschacher-Str NB Villach K\u00e4rnten 9500",
    "addr:postcode":"9500",
    "addr:street":"Kaernten",
    "iso:country":"AT",
    "sg:address":"Urban-G\u00f6rtschacher-Str NB",
    "sg:city":"Villach",
    "sg:orig_category":"Tabaktrafiken",
    "sg:phone":"+43 4342 4256809",
    "sg:postcode":"9500",
    "sg:province":"K\u00e4rnten",
    "wof:name":"Brunner Berndt",
    "wof:placetype":"venue"
},
  "geometry": {"coordinates":[13.8330202103,46.6040687561],"type":"Point"}
}