{
  "type": "Feature",
  "properties": {
    "addr:full":"Johann-Beer-Str 3 St. Georgen im Attergau Ober\u00f6sterreich 4880",
    "addr:housenumber":"3",
    "addr:postcode":"4880",
    "addr:street":"Johann-Beer-Str",
    "iso:country":"AT",
    "sg:address":"Johann-Beer-Str 3",
    "sg:city":"St. Georgen im Attergau",
    "sg:orig_category":"Autoreparatur",
    "sg:phone":"+43 4376 676438",
    "sg:postcode":"4880",
    "sg:province":"Ober\u00f6sterreich",
    "wof:name":"Reitinger Cars & Bikes",
    "wof:placetype":"venue"
},
  "geometry": {"coordinates":[13.4903125763,47.9341850281],"type":"Point"}
}