{
  "type": "Feature",
  "properties": {
    "addr:full":"Amtspl 1 Scheifling Steiermark 8811",
    "addr:housenumber":"1",
    "addr:postcode":"8811",
    "addr:street":"Amtspl",
    "iso:country":"AT",
    "sg:address":"Amtspl 1",
    "sg:city":"Scheifling",
    "sg:orig_category":"Polizei U Gendarmerie",
    "sg:phone":"+43 4359 1336363",
    "sg:postcode":"8811",
    "sg:province":"Steiermark",
    "wof:name":"Gendarmerie",
    "wof:placetype":"venue"
},
  "geometry": {"coordinates":[14.4122743607,47.148349762],"type":"Point"}
}