{
  "type": "Feature",
  "properties": {
    "addr:full":"Invalidenstr 2 Wien Wien 1030",
    "addr:housenumber":"2",
    "addr:postcode":"1030",
    "addr:street":"Invalidenstr",
    "iso:country":"AT",
    "sg:address":"Invalidenstr 2",
    "sg:city":"Wien",
    "sg:orig_category":"Fleischhauereien",
    "sg:phone":"+43 1 7124203",
    "sg:postcode":"1030",
    "sg:province":"Wien",
    "wof:name":"Khaled Hamad",
    "wof:placetype":"venue"
},
  "geometry": {"coordinates":[16.3855266571,48.2061080933],"type":"Point"}
}