{
  "type": "Feature",
  "properties": {
    "addr:full":"Grabenweg 72 Innsbruck Tirol 6020",
    "addr:housenumber":"72",
    "addr:postcode":"6020",
    "addr:street":"Grabenweg;Tirol",
    "iso:country":"AT",
    "sg:address":"Grabenweg 72",
    "sg:city":"Innsbruck",
    "sg:classifiers":[
        {
            "category":"Professional",
            "subcategory":"Accounting & Tax Preparation",
            "type":"Services"
        }
    ],
    "sg:phone":"+43 512 334400",
    "sg:postcode":"6020",
    "sg:province":"Tirol",
    "sg:tags":[
        "financial",
        "software"
    ],
    "sg:website":"softwarestudio.at",
    "wof:name":"Software Studio Ges.m.b.H.",
    "wof:placetype":"venue"
},
  "geometry": {"coordinates":[11.4403610229,47.2649726868],"type":"Point"}
}