{
  "type": "Feature",
  "properties": {
    "iso:country":"AT",
    "sg:address":"Andritzer Reichsstr 42b",
    "sg:city":"Andritz",
    "sg:orig_category":"Restaurants: Italienisch",
    "sg:phone":"+43 316 697511",
    "sg:postcode":"8045",
    "sg:province":"Steiermark",
    "wof:name":"Trattoria - Cafe Peppino",
    "wof:placetype":"venue"
},
  "geometry": {"coordinates":[15.4209547043,47.1041755676],"type":"Point"}
}