{
  "type": "Feature",
  "properties": {
    "addr:full":"Wolf-Dietrich-Str 4 Salzburg Salzburg 5020",
    "addr:housenumber":"4",
    "addr:postcode":"5020",
    "addr:street":"Wolf-Dietrich-Str;Salzburg",
    "iso:country":"AT",
    "sg:address":"Wolf-Dietrich-Str 4",
    "sg:city":"Salzburg",
    "sg:classifiers":[
        {
            "category":"Travel",
            "subcategory":"Hotels & Motels",
            "type":"Entertainment"
        }
    ],
    "sg:phone":"+43 662 882778",
    "sg:postcode":"5020",
    "sg:province":"Salzburg",
    "wof:name":"Hotel Residenz",
    "wof:placetype":"venue"
},
  "geometry": {"coordinates":[13.048415184,47.8047027588],"type":"Point"}
}