{
  "type": "Feature",
  "properties": {
    "addr:full":"Leobersdorfer Str 28 Hirtenberg Nieder\u00f6sterreich 2552",
    "addr:housenumber":"28",
    "addr:postcode":"2552",
    "addr:street":"Str",
    "iso:country":"AT",
    "sg:address":"Leobersdorfer Str 28",
    "sg:city":"Hirtenberg",
    "sg:orig_category":"Eissalons",
    "sg:phone":"+43 2256 81820",
    "sg:postcode":"2552",
    "sg:province":"Nieder\u00f6sterreich",
    "wof:name":"Eissalon Schleckeria",
    "wof:placetype":"venue"
},
  "geometry": {"coordinates":[16.1838684082,47.9311141968],"type":"Point"}
}