{
  "type": "Feature",
  "properties": {
    "iso:country":"AT",
    "sg:address":"Lainzer Str 84",
    "sg:city":"Wien",
    "sg:orig_category":"Restaurants: Chinesisch",
    "sg:phone":"+43 4318 771705",
    "sg:postcode":"1130",
    "sg:province":"Wien",
    "wof:name":"China-Restaurant Jade City",
    "wof:placetype":"venue"
},
  "geometry": {"coordinates":[16.2851772308,48.1812477112],"type":"Point"}
}