{
  "type": "Feature",
  "properties": {
    "addr:full":"Nr 18 D\u00f6briach K\u00e4rnten 9873",
    "addr:postcode":"9873",
    "addr:street":"Nr 18 Doebriach Kaernten",
    "iso:country":"AT",
    "sg:address":"Nr 18",
    "sg:city":"D\u00f6briach",
    "sg:orig_category":"Pensionen / Privatzimmer",
    "sg:phone":"+43 4246 7237",
    "sg:postcode":"9873",
    "sg:province":"K\u00e4rnten",
    "wof:name":"Steingruber Josef",
    "wof:placetype":"venue"
},
  "geometry": {"coordinates":[13.6577301025,46.7817993164],"type":"Point"}
}