{
  "type": "Feature",
  "properties": {
    "addr:full":"Nr 273 Preding Steiermark 8504",
    "addr:postcode":"8504",
    "addr:street":"Nr 273",
    "iso:country":"AT",
    "sg:address":"Nr 273",
    "sg:city":"Preding",
    "sg:orig_category":"Fleischhauereien",
    "sg:phone":"+43 3185 30024",
    "sg:postcode":"8504",
    "sg:province":"Steiermark",
    "wof:name":"Schirnhofer-Breisler GesmbH - Shop in Shop",
    "wof:placetype":"venue"
},
  "geometry": {"coordinates":[15.4067401886,46.8597869873],"type":"Point"}
}