{
  "type": "Feature",
  "properties": {
    "addr:full":"Kaarstr 7 Linz Ober\u00f6sterreich 4040",
    "addr:housenumber":"7",
    "addr:postcode":"4040",
    "addr:street":"Kaarstr",
    "iso:country":"AT",
    "sg:address":"Kaarstr 7",
    "sg:city":"Linz",
    "sg:orig_category":"Tonstudios",
    "sg:phone":"+43 732 736688",
    "sg:postcode":"4040",
    "sg:province":"Ober\u00f6sterreich",
    "wof:name":"Klangwelt Musikproduktion",
    "wof:placetype":"venue"
},
  "geometry": {"coordinates":[14.2813081741,48.3121833801],"type":"Point"}
}