{
  "type": "Feature",
  "properties": {
    "iso:country":"AT",
    "sg:address":"Linzer Str 6",
    "sg:city":"Loosdorf",
    "sg:orig_category":"Polizei U Gendarmerie",
    "sg:phone":"+43 4359 1333134",
    "sg:postcode":"3382",
    "sg:province":"Nieder\u00f6sterreich",
    "wof:name":"Gendarmerie",
    "wof:placetype":"venue"
},
  "geometry": {"coordinates":[15.3811845779,48.1837120056],"type":"Point"}
}