{
  "type": "Feature",
  "properties": {
    "iso:country":"AT",
    "sg:address":"Nr 56",
    "sg:city":"St. Georgen an der Stiefing",
    "sg:orig_category":"Volksschulen",
    "sg:phone":"+43 4331 844027",
    "sg:postcode":"8413",
    "sg:province":"Steiermark",
    "wof:name":"Volksschule",
    "wof:placetype":"venue"
},
  "geometry": {"coordinates":[15.5929555893,46.8366584778],"type":"Point"}
}