{
  "type": "Feature",
  "properties": {
    "addr:full":"Weinitzenstr 55 Andritz Steiermark 8045",
    "addr:housenumber":"55",
    "addr:postcode":"8045",
    "addr:street":"Weinitzenstr",
    "iso:country":"AT",
    "sg:address":"Weinitzenstr 55",
    "sg:city":"Andritz",
    "sg:orig_category":"Non-Classified Establishments",
    "sg:phone":"+43 316 6917880",
    "sg:postcode":"8045",
    "sg:province":"Steiermark",
    "sg:website":"www.auertore.at",
    "wof:name":"Auer Elektrotore",
    "wof:placetype":"venue"
},
  "geometry": {"coordinates":[15.431769371,47.1184043884],"type":"Point"}
}