{
  "type": "Feature",
  "properties": {
    "addr:full":"Bauerstr 4 Linz Ober\u00f6sterreich 4030",
    "addr:housenumber":"4",
    "addr:postcode":"4030",
    "addr:street":"Bauerstr",
    "iso:country":"AT",
    "sg:address":"Bauerstr 4",
    "sg:city":"Linz",
    "sg:orig_category":"Automaten",
    "sg:phone":"+43 676 3045707",
    "sg:postcode":"4030",
    "sg:province":"Ober\u00f6sterreich",
    "wof:name":"Kneringer Christian Ing",
    "wof:placetype":"venue"
},
  "geometry": {"coordinates":[14.2903394699,48.2522315979],"type":"Point"}
}