{
  "type": "Feature",
  "properties": {
    "addr:full":"Markt 79 Abtenau Salzburg 5441",
    "addr:housenumber":"79",
    "addr:postcode":"5441",
    "addr:street":"Markt;Salzburg",
    "iso:country":"AT",
    "sg:address":"Markt 79",
    "sg:city":"Abtenau",
    "sg:orig_category":"Dekorationen",
    "sg:phone":"+43 4362 4324630",
    "sg:postcode":"5441",
    "sg:province":"Salzburg",
    "wof:name":"Dekora-Domus Inh G Katholnigg",
    "wof:placetype":"venue"
},
  "geometry": {"coordinates":[13.3462638855,47.563495636],"type":"Point"}
}