{
  "type": "Feature",
  "properties": {
    "addr:full":"Bleckmanng. 10  M\u00fcrzzuschlag Steiermark 8680",
    "addr:housenumber":"10",
    "addr:postcode":"8680",
    "addr:street":"Bleckmanng.",
    "iso:country":"AT",
    "sg:address":"Bleckmanng. 10 ",
    "sg:city":"M\u00fcrzzuschlag",
    "sg:classifiers":[
        {
            "category":"Shopping",
            "type":"Retail Goods"
        }
    ],
    "sg:phone":"+43 4338 525550",
    "sg:postcode":"8680",
    "sg:province":"Steiermark",
    "sg:tags":[
        "finished",
        "-",
        "metallic"
    ],
    "wof:name":"B\u00d6HLER BLECHE GMBH",
    "wof:placetype":"venue"
},
  "geometry": {"coordinates":[15.6684751511,47.6045417786],"type":"Point"}
}