{
  "type": "Feature",
  "properties": {
    "addr:full":"Weiherstr 3 Bregenz Vorarlberg 6900",
    "addr:housenumber":"3",
    "addr:postcode":"6900",
    "addr:street":"Weiherstr",
    "iso:country":"AT",
    "sg:address":"Weiherstr 3",
    "sg:city":"Bregenz",
    "sg:orig_category":"Unternehmensberatung",
    "sg:phone":"+43 5574 45114",
    "sg:postcode":"6900",
    "sg:province":"Vorarlberg",
    "wof:name":"forsite IT Management Consulting und Entwicklung GmbH",
    "wof:placetype":"venue"
},
  "geometry": {"coordinates":[9.7437648773,47.5024757385],"type":"Point"}
}