{
  "type": "Feature",
  "properties": {
    "addr:full":"Fernkorng 83 Wien Wien 1100",
    "addr:housenumber":"83",
    "addr:postcode":"1100",
    "addr:street":"Fernkorng",
    "iso:country":"AT",
    "sg:address":"Fernkorng 83",
    "sg:city":"Wien",
    "sg:orig_category":"Automaten",
    "sg:phone":"+43 1 2080278",
    "sg:postcode":"1100",
    "sg:province":"Wien",
    "wof:name":"Automaten Unterkofler GmbH",
    "wof:placetype":"venue"
},
  "geometry": {"coordinates":[16.3624095917,48.1687965393],"type":"Point"}
}