{
  "type": "Feature",
  "properties": {
    "addr:full":"Dorf Haus 792 Mayrhofen Tirol 6290",
    "addr:housenumber":"792",
    "addr:postcode":"6290",
    "addr:street":"Dorf Haus;Tirol",
    "iso:country":"AT",
    "sg:address":"Dorf Haus 792",
    "sg:city":"Mayrhofen",
    "sg:classifiers":[
        {
            "category":"Restaurant",
            "type":"Food & Drink"
        }
    ],
    "sg:phone":"+43 5285 8119",
    "sg:postcode":"6290",
    "sg:province":"Tirol",
    "wof:name":"Restaurant Corso",
    "wof:placetype":"venue"
},
  "geometry": {"coordinates":[11.8562803268,47.1586418152],"type":"Point"}
}