{
  "type": "Feature",
  "properties": {
    "iso:country":"AT",
    "sg:address":"Nr 53",
    "sg:city":"Altschwendt",
    "sg:orig_category":"Volksschulen",
    "sg:phone":"+43 7762 2650",
    "sg:postcode":"4721",
    "sg:province":"Ober\u00f6sterreich",
    "wof:name":"Volksschule",
    "wof:placetype":"venue"
},
  "geometry": {"coordinates":[13.6878738403,48.323551178],"type":"Point"}
}