{
  "type": "Feature",
  "properties": {
    "addr:full":"Sylvester Wagner-Str 3 Salzburg Salzburg 5020",
    "addr:housenumber":"3",
    "addr:postcode":"5020",
    "addr:street":"Wagner-Str;Salzburg",
    "iso:country":"AT",
    "sg:address":"Sylvester Wagner-Str 3",
    "sg:city":"Salzburg",
    "sg:classifiers":[
        {
            "category":"Professional",
            "subcategory":"Computer Services",
            "type":"Services"
        }
    ],
    "sg:phone":"+43 662 8794840",
    "sg:postcode":"5020",
    "sg:province":"Salzburg",
    "sg:tags":[
        "software"
    ],
    "wof:name":"ASE Automation und Softwareentwicklung GesmbH",
    "wof:placetype":"venue"
},
  "geometry": {"coordinates":[13.0525360107,47.8180999756],"type":"Point"}
}