{
  "type": "Feature",
  "properties": {
    "addr:full":"Heinrichsgasse 3 Wien Wien 1010",
    "addr:housenumber":"3",
    "addr:postcode":"1010",
    "addr:street":"Heinrichsgasse",
    "iso:country":"AT",
    "sg:address":"Heinrichsgasse 3",
    "sg:city":"Wien",
    "sg:classifiers":[
        {
            "category":"Professional",
            "subcategory":"Advertising",
            "type":"Services"
        }
    ],
    "sg:phone":"+43 1 53386970",
    "sg:postcode":"1010",
    "sg:province":"Wien",
    "sg:tags":[
        "film"
    ],
    "sg:website":"tale.at",
    "wof:name":"Tale Film Produktions GmbH",
    "wof:placetype":"venue"
},
  "geometry": {"coordinates":[16.3717784882,48.215045929],"type":"Point"}
}