{
  "type": "Feature",
  "properties": {
    "iso:country":"AT",
    "sg:address":"Neutorg 47",
    "sg:city":"Graz",
    "sg:orig_category":"Galerien",
    "sg:phone":"+43 4331 6820046",
    "sg:postcode":"8010",
    "sg:province":"Steiermark",
    "wof:name":"Tazl Galerie",
    "wof:placetype":"venue"
},
  "geometry": {"coordinates":[15.4376630783,47.067855835],"type":"Point"}
}