{
  "type": "Feature",
  "properties": {
    "addr:full":"Nr 21 Wei\u00dfenkirchen in der Wachau Nieder\u00f6sterreich 3610",
    "addr:postcode":"3610",
    "addr:street":"Nr 21",
    "iso:country":"AT",
    "sg:address":"Nr 21",
    "sg:city":"Wei\u00dfenkirchen in der Wachau",
    "sg:orig_category":"Tischlereien",
    "sg:phone":"+43 2717 8232",
    "sg:postcode":"3610",
    "sg:province":"Nieder\u00f6sterreich",
    "wof:name":"Kretschmayer Hermann",
    "wof:placetype":"venue"
},
  "geometry": {"coordinates":[15.4699258804,48.3972511292],"type":"Point"}
}