{
  "type": "Feature",
  "properties": {
    "iso:country":"AT",
    "sg:address":"Josefistr 97",
    "sg:city":"Frauenkirchen",
    "sg:orig_category":"Bauunternehmen",
    "sg:phone":"+43 2172 2351",
    "sg:postcode":"7132",
    "sg:province":"Burgenland",
    "wof:name":"Thell Dipl-Ing BaugesmbH",
    "wof:placetype":"venue"
},
  "geometry": {"coordinates":[16.9215183258,47.8434333801],"type":"Point"}
}