{
  "type": "Feature",
  "properties": {
    "addr:full":"Kircheng 3 Wei\u00dfkirchen an der Traun Ober\u00f6sterreich 4616",
    "addr:housenumber":"3",
    "addr:postcode":"4616",
    "addr:street":"Kircheng",
    "iso:country":"AT",
    "sg:address":"Kircheng 3",
    "sg:city":"Wei\u00dfkirchen an der Traun",
    "sg:orig_category":"Friseure U Frisiersalons",
    "sg:phone":"+43 4372 4356821",
    "sg:postcode":"4616",
    "sg:province":"Ober\u00f6sterreich",
    "wof:name":"Fris\u00f6r Schnitt-Stelle",
    "wof:placetype":"venue"
},
  "geometry": {"coordinates":[14.1264972687,48.16431427],"type":"Point"}
}