{
  "type": "Feature",
  "properties": {
    "iso:country":"AT",
    "sg:address":"Arzler Str 208",
    "sg:city":"Innsbruck",
    "sg:orig_category":"Bars-Cafes",
    "sg:phone":"+43 512 263108",
    "sg:postcode":"6020",
    "sg:province":"Tirol",
    "wof:name":"Onkel Toms H\u00fctte",
    "wof:placetype":"venue"
},
  "geometry": {"coordinates":[11.4340419769,47.2842140198],"type":"Point"}
}