{
  "type": "Feature",
  "properties": {
    "iso:country":"AT",
    "sg:address":"Roseng 1",
    "sg:city":"Lienz",
    "sg:orig_category":"Werbegestalter",
    "sg:phone":"+43 664 1324021",
    "sg:postcode":"9900",
    "sg:province":"Tirol",
    "wof:name":"Oberrainer Robert",
    "wof:placetype":"venue"
},
  "geometry": {"coordinates":[12.7661933899,46.829410553],"type":"Point"}
}