{
  "type": "Feature",
  "properties": {
    "iso:country":"AT",
    "sg:address":"Reithtal 6",
    "sg:city":"Liezen",
    "sg:classifiers":[
        {
            "category":"Manufacturing",
            "subcategory":"Tools & Machinery",
            "type":"Manufacturing & Wholesale Goods"
        }
    ],
    "sg:phone":"+43 664 3356547",
    "sg:postcode":"8940",
    "sg:province":"Steiermark",
    "sg:tags":[
        "construction",
        "container",
        "apparatus"
    ],
    "wof:name":"Maier Handel Produktion GmbH",
    "wof:placetype":"venue"
},
  "geometry": {"coordinates":[14.2699193954,47.5655975342],"type":"Point"}
}