{
  "type": "Feature",
  "properties": {
    "addr:full":"Parndorfer Str 10a/9 Bruck an der Leitha Nieder\u00f6sterreich 2460",
    "addr:housenumber":"10a / 9",
    "addr:postcode":"2460",
    "addr:street":"Str",
    "iso:country":"AT",
    "sg:address":"Parndorfer Str 10a/9",
    "sg:city":"Bruck an der Leitha",
    "sg:orig_category":"Fotografen",
    "sg:phone":"+43 4321 6267167",
    "sg:postcode":"2460",
    "sg:province":"Nieder\u00f6sterreich",
    "wof:name":"Matz Roman",
    "wof:placetype":"venue"
},
  "geometry": {"coordinates":[16.7843837738,48.0206565857],"type":"Point"}
}