{
  "type": "Feature",
  "properties": {
    "addr:full":"Schlo\u00dfbergstr 151 Markt Hartmannsdorf Steiermark 8311",
    "addr:housenumber":"151",
    "addr:postcode":"8311",
    "iso:country":"AT",
    "sg:address":"Schlo\u00dfbergstr 151",
    "sg:city":"Markt Hartmannsdorf",
    "sg:orig_category":"Friseure U Frisiersalons",
    "sg:phone":"+43 4331 142203",
    "sg:postcode":"8311",
    "sg:province":"Steiermark",
    "wof:name":"Schloffer Johann",
    "wof:placetype":"venue"
},
  "geometry": {"coordinates":[15.8428945541,47.0542297363],"type":"Point"}
}