{
  "type": "Feature",
  "properties": {
    "addr:full":"Theodor-K\u00f6rner-G 10 Knittelfeld Steiermark 8720",
    "addr:housenumber":"10",
    "addr:postcode":"8720",
    "addr:street":"Theodor-Koerner-G",
    "iso:country":"AT",
    "sg:address":"Theodor-K\u00f6rner-G 10",
    "sg:city":"Knittelfeld",
    "sg:orig_category":"Reitsportartikel",
    "sg:phone":"+43 4335 1282681",
    "sg:postcode":"8720",
    "sg:province":"Steiermark",
    "wof:name":"Zwerlin Reitsport Handels-GmbH",
    "wof:placetype":"venue"
},
  "geometry": {"coordinates":[14.8307199478,47.2140884399],"type":"Point"}
}