{
  "type": "Feature",
  "properties": {
    "addr:full":"Schlagturn 25 Stans Tirol 6135",
    "addr:housenumber":"25",
    "addr:postcode":"6135",
    "addr:street":"Schlagturn;Tirol",
    "iso:country":"AT",
    "sg:address":"Schlagturn 25",
    "sg:city":"Stans",
    "sg:classifiers":[
        {
            "category":"Utilities",
            "subcategory":"Cable",
            "type":"Services"
        }
    ],
    "sg:phone":"+43 5242 71062",
    "sg:postcode":"6135",
    "sg:province":"Tirol",
    "sg:tags":[
        "saw"
    ],
    "sg:website":"dia2000.info",
    "wof:name":"DIA 2000 Diamond Tool Diamantenwerkzeuge GmbH",
    "wof:placetype":"venue"
},
  "geometry": {"coordinates":[11.7170000076,47.36977005],"type":"Point"}
}