{
  "type": "Feature",
  "properties": {
    "addr:full":"Nr 13 Breitenaich Ober\u00f6sterreich 4075",
    "addr:postcode":"4075",
    "addr:street":"Nr;Breitenaich",
    "iso:country":"AT",
    "sg:address":"Nr 13",
    "sg:city":"Breitenaich",
    "sg:orig_category":"Stukkateure U Trockenausbauer",
    "sg:phone":"+43 7249 477070",
    "sg:postcode":"4075",
    "sg:province":"Ober\u00f6sterreich",
    "sg:website":"www.trockenbau.co.at",
    "wof:name":"B & M Trockenbau GmbH",
    "wof:placetype":"venue"
},
  "geometry": {"coordinates":[13.9787015915,48.2480621338],"type":"Point"}
}