{
  "type": "Feature",
  "properties": {
    "addr:full":"Wiener Str 203 Linz Ober\u00f6sterreich 4020",
    "addr:housenumber":"203",
    "addr:postcode":"4020",
    "iso:country":"AT",
    "sg:address":"Wiener Str 203",
    "sg:city":"Linz",
    "sg:orig_category":"Lebensmittel / Einzelhandel",
    "sg:phone":"+43 664 3413704",
    "sg:postcode":"4020",
    "sg:province":"Ober\u00f6sterreich",
    "wof:name":"Coskun Yasar",
    "wof:placetype":"venue"
},
  "geometry": {"coordinates":[14.3130683899,48.2762031555],"type":"Point"}
}