{
  "type": "Feature",
  "properties": {
    "addr:full":"Dr.-Leopold-H\u00fctter-Str 105 Friedberg Steiermark 8240",
    "addr:housenumber":"105",
    "addr:postcode":"8240",
    "iso:country":"AT",
    "sg:address":"Dr.-Leopold-H\u00fctter-Str 105",
    "sg:city":"Friedberg",
    "sg:orig_category":"Hauskrankenpflege / Heimhilfe",
    "sg:phone":"+43 4333 3923344",
    "sg:postcode":"8240",
    "sg:province":"Steiermark",
    "wof:name":"Hauskrankenpflege - Altenhilfe",
    "wof:placetype":"venue"
},
  "geometry": {"coordinates":[16.0580654144,47.4416236877],"type":"Point"}
}