{
  "type": "Feature",
  "properties": {
    "addr:full":"Wiener Str. 48 4024",
    "addr:postcode":"4024",
    "addr:street":"Str. 48",
    "iso:country":"AT",
    "sg:address":"Wiener Str. 48",
    "sg:classifiers":[
        {
            "category":"Banks & Credit Unions",
            "subcategory":"Financial Services",
            "type":"Services"
        }
    ],
    "sg:phone":"+43 4373 26952",
    "sg:postcode":"4024",
    "sg:tags":[
        "banking",
        "finance",
        "insurance"
    ],
    "wof:name":"Z\u00dcRICH VERSICHERUNGS AG",
    "wof:placetype":"venue"
},
  "geometry": {"coordinates":[14.3003482819,48.2865600586],"type":"Point"}
}