{
  "type": "Feature",
  "properties": {
    "addr:full":"Nr 18 Waidhofen an der Thaya Nieder\u00f6sterreich 3830",
    "addr:postcode":"3830",
    "addr:street":"Nr;An Der Thaya",
    "iso:country":"AT",
    "sg:address":"Nr 18",
    "sg:city":"Waidhofen an der Thaya",
    "sg:orig_category":"Non-Classified Establishments",
    "sg:phone":"+43 664 5040325",
    "sg:postcode":"3830",
    "sg:province":"Nieder\u00f6sterreich",
    "wof:name":"SIXM\u00dcHLE VerwaltungsGmbH",
    "wof:placetype":"venue"
},
  "geometry": {"coordinates":[15.2838354111,48.8136940002],"type":"Point"}
}