{
  "type": "Feature",
  "properties": {
    "iso:country":"AT",
    "sg:address":"Virgen 129",
    "sg:city":"Virgen",
    "sg:classifiers":[
        {
            "category":"Building & Trades",
            "subcategory":"Landscaping Services",
            "type":"Services"
        }
    ],
    "sg:phone":"+43 4874 5223",
    "sg:postcode":"9972",
    "sg:province":"Tirol",
    "sg:tags":[
        "dredging"
    ],
    "sg:website":"haus-bstieler.at",
    "wof:name":"Marian Bstieler GesmbH",
    "wof:placetype":"venue"
},
  "geometry": {"coordinates":[12.4558134079,47.0037765503],"type":"Point"}
}