{
  "type": "Feature",
  "properties": {
    "addr:full":"Neulerchenfelder Str. 35  Wien Wien 1160",
    "addr:postcode":"1160",
    "addr:street":"Str. 35",
    "iso:country":"AT",
    "sg:address":"Neulerchenfelder Str. 35 ",
    "sg:city":"Wien",
    "sg:classifiers":[
        {
            "category":"Professional",
            "subcategory":"Printing & Photocopies",
            "type":"Services"
        }
    ],
    "sg:phone":"+43 4314 0389260",
    "sg:postcode":"1160",
    "sg:province":"Wien",
    "wof:name":"REMA-PRINTDRUCK & VERLAGSGES. MBH",
    "wof:placetype":"venue"
},
  "geometry": {"coordinates":[16.3347244263,48.2110977173],"type":"Point"}
}