{
  "type": "Feature",
  "properties": {
    "addr:full":"Lacknergasse 7 Voitsberg Steiermark 8570",
    "addr:housenumber":"7",
    "addr:postcode":"8570",
    "addr:street":"Lacknergasse",
    "iso:country":"AT",
    "sg:address":"Lacknergasse 7",
    "sg:city":"Voitsberg",
    "sg:classifiers":[
        {
            "category":"Home & Garden",
            "subcategory":"Building Materials",
            "type":"Retail Goods"
        }
    ],
    "sg:phone":"+43 3142 222250",
    "sg:postcode":"8570",
    "sg:province":"Steiermark",
    "sg:tags":[
        "aluminium",
        "gutter"
    ],
    "wof:name":"Altenburger GmbH",
    "wof:placetype":"venue"
},
  "geometry": {"coordinates":[15.1411237717,47.0543251038],"type":"Point"}
}