{
  "type": "Feature",
  "properties": {
    "addr:full":"W\u00f6rthersee S\u00fcduferstr 133 Reifnitz K\u00e4rnten 9081",
    "addr:housenumber":"133",
    "addr:postcode":"9081",
    "addr:street":"Kaernten",
    "iso:country":"AT",
    "sg:address":"W\u00f6rthersee S\u00fcduferstr 133",
    "sg:city":"Reifnitz",
    "sg:orig_category":"Tankstellen",
    "sg:phone":"+43 4342 732372",
    "sg:postcode":"9081",
    "sg:province":"K\u00e4rnten",
    "wof:name":"AVANTI TankstellenbetriebsgesmbH",
    "wof:placetype":"venue"
},
  "geometry": {"coordinates":[14.1815433502,46.6068840027],"type":"Point"}
}