{
  "type": "Feature",
  "properties": {
    "addr:full":"M\u00fchltalerstr 4 Leoben Steiermark 8700",
    "addr:housenumber":"4",
    "addr:postcode":"8700",
    "addr:street":"Muehltalerstr",
    "iso:country":"AT",
    "sg:address":"M\u00fchltalerstr 4",
    "sg:city":"Leoben",
    "sg:orig_category":"Immobilienmakler",
    "sg:phone":"+43 3842 444690",
    "sg:postcode":"8700",
    "sg:province":"Steiermark",
    "wof:name":"Stengg GmbH",
    "wof:placetype":"venue"
},
  "geometry": {"coordinates":[15.0960092545,47.3813095093],"type":"Point"}
}