{
  "type": "Feature",
  "properties": {
    "addr:full":"Edelstal, Badstr. 30 Berg Nieder\u00f6sterreich 2413",
    "addr:housenumber":"30;2413",
    "addr:street":"Berg Niederoesterreich",
    "iso:country":"AT",
    "sg:address":"Edelstal, Badstr. 30",
    "sg:city":"Berg",
    "sg:classifiers":[
        {
            "category":"Food & Beverages",
            "subcategory":"Groceries & Convenience Stores",
            "type":"Retail Goods"
        }
    ],
    "sg:phone":"+43 4321 4522510",
    "sg:postcode":"2413",
    "sg:province":"Nieder\u00f6sterreich",
    "sg:tags":[
        "drink"
    ],
    "wof:name":"R\u00d6MERQUELLE GMBH",
    "wof:placetype":"venue"
},
  "geometry": {"coordinates":[17.0371341705,48.1037406921],"type":"Point"}
}