{
  "type": "Feature",
  "properties": {
    "iso:country":"AT",
    "sg:address":"Gorskistr. 16",
    "sg:city":"Wien",
    "sg:classifiers":[
        {
            "category":"Professional",
            "subcategory":"Engineering",
            "type":"Services"
        }
    ],
    "sg:phone":"+43 4316 1603030",
    "sg:postcode":"1230",
    "sg:province":"Wien",
    "sg:tags":[
        "machine",
        "-",
        "mechanical"
    ],
    "wof:name":"SED PRODUKTION GMBH",
    "wof:placetype":"venue"
},
  "geometry": {"coordinates":[16.3546867371,48.1415672302],"type":"Point"}
}