{
  "type": "Feature",
  "properties": {
    "addr:full":"Schremser Str 69 Heidenreichstein Nieder\u00f6sterreich 3860",
    "addr:housenumber":"69",
    "addr:postcode":"3860",
    "addr:street":"Str",
    "iso:country":"AT",
    "sg:address":"Schremser Str 69",
    "sg:city":"Heidenreichstein",
    "sg:orig_category":"Autoreparatur",
    "sg:phone":"+43 4328 6252382",
    "sg:postcode":"3860",
    "sg:province":"Nieder\u00f6sterreich",
    "wof:name":"F\u00fcrnweger GmbH",
    "wof:placetype":"venue"
},
  "geometry": {"coordinates":[15.1086921692,48.8568305969],"type":"Point"}
}