{
  "type": "Feature",
  "properties": {
    "addr:full":"Schlo\u00dfg 1 Poysdorf Nieder\u00f6sterreich 2170",
    "addr:housenumber":"1",
    "addr:postcode":"2170",
    "addr:street":"Schlossg",
    "iso:country":"AT",
    "sg:address":"Schlo\u00dfg 1",
    "sg:city":"Poysdorf",
    "sg:orig_category":"Gutsverwaltungen",
    "sg:phone":"+43 2552 2605",
    "sg:postcode":"2170",
    "sg:province":"Nieder\u00f6sterreich",
    "wof:name":"Sachsen-Coburg und Gotha Philipp A",
    "wof:placetype":"venue"
},
  "geometry": {"coordinates":[16.6295757294,48.668674469],"type":"Point"}
}