{
  "type": "Feature",
  "properties": {
    "addr:full":"Traunsteinstr 109 Gmunden Ober\u00f6sterreich 4810",
    "addr:housenumber":"109",
    "addr:postcode":"4810",
    "addr:street":"Oberoesterreich",
    "iso:country":"AT",
    "sg:address":"Traunsteinstr 109",
    "sg:city":"Gmunden",
    "sg:classifiers":[
        {
            "category":"Restaurant",
            "type":"Food & Drink"
        }
    ],
    "sg:phone":"+43 4376 1277700",
    "sg:postcode":"4810",
    "sg:province":"Ober\u00f6sterreich",
    "wof:name":"Landhotel Gasthof Gr\u00fcnberg am See",
    "wof:placetype":"venue"
},
  "geometry": {"coordinates":[13.8064603806,47.9039039612],"type":"Point"}
}