{
  "type": "Feature",
  "properties": {
    "addr:full":"Vbg Wirtschaftspark G\u00f6tzis Vorarlberg 6840",
    "addr:postcode":"6840",
    "iso:country":"AT",
    "sg:address":"Vbg Wirtschaftspark",
    "sg:city":"G\u00f6tzis",
    "sg:classifiers":[
        {
            "category":"Professional",
            "subcategory":"Computer Services",
            "type":"Services"
        }
    ],
    "sg:phone":"+43 5523 55266",
    "sg:postcode":"6840",
    "sg:province":"Vorarlberg",
    "sg:tags":[
        "software"
    ],
    "wof:name":"erath KEG",
    "wof:placetype":"venue"
},
  "geometry": {"coordinates":[9.665719986,47.3356399536],"type":"Point"}
}