{
  "type": "Feature",
  "properties": {
    "addr:full":"Reinprechtsdorfer Str 12 Wien Wien 1050",
    "addr:postcode":"1050",
    "addr:street":"Str 12",
    "iso:country":"AT",
    "sg:address":"Reinprechtsdorfer Str 12",
    "sg:city":"Wien",
    "sg:orig_category":"Bettwaren",
    "sg:phone":"+43 4315 443149",
    "sg:postcode":"1050",
    "sg:province":"Wien",
    "wof:name":"Ruda & Co Bettfedern u Bettwarenhandel",
    "wof:placetype":"venue"
},
  "geometry": {"coordinates":[16.3572597504,48.1827964783],"type":"Point"}
}