{
  "type": "Feature",
  "properties": {
    "addr:full":"Untere Hauptstr 31 Neusiedl am See Burgenland 7100",
    "addr:housenumber":"31",
    "addr:postcode":"7100",
    "addr:street":"Untere Hauptstr",
    "iso:country":"AT",
    "sg:address":"Untere Hauptstr 31",
    "sg:city":"Neusiedl am See",
    "sg:classifiers":[
        {
            "category":"Restaurant",
            "type":"Food & Drink"
        }
    ],
    "sg:phone":"+43 2167 2032",
    "sg:postcode":"7100",
    "sg:province":"Burgenland",
    "wof:name":"Simonutti Gastronomie GmbH",
    "wof:placetype":"venue"
},
  "geometry": {"coordinates":[16.8467121124,47.9466285706],"type":"Point"}
}