{
  "type": "Feature",
  "properties": {
    "iso:country":"AT",
    "sg:address":"Kohlgraben 2",
    "sg:city":"Lieboch",
    "sg:orig_category":"Filmproduktionen",
    "sg:phone":"+43 3136 61150",
    "sg:postcode":"8501",
    "sg:province":"Steiermark",
    "wof:name":"Posch Franz",
    "wof:placetype":"venue"
},
  "geometry": {"coordinates":[15.3286886215,46.9776763916],"type":"Point"}
}