{
  "type": "Feature",
  "properties": {
    "iso:country":"AT",
    "sg:address":"Dechant Thaller-Str 37/2",
    "sg:city":"Leibnitz",
    "sg:orig_category":"Psychotherapie",
    "sg:phone":"+43 3452 72079",
    "sg:postcode":"8430",
    "sg:province":"Steiermark",
    "wof:name":"Psychotherapeutische Praxisgemeinschaft Klug Erna und Walter OEG",
    "wof:placetype":"venue"
},
  "geometry": {"coordinates":[15.5401163101,46.7882728577],"type":"Point"}
}