{
  "type": "Feature",
  "properties": {
    "addr:full":"Anton-Krieger-G 97 Wien Wien 1230",
    "addr:housenumber":"97",
    "addr:postcode":"1230",
    "addr:street":"Anton-Krieger-G",
    "iso:country":"AT",
    "sg:address":"Anton-Krieger-G 97",
    "sg:city":"Wien",
    "sg:orig_category":"Werbeagenturen",
    "sg:phone":"+43 1 8880206",
    "sg:postcode":"1230",
    "sg:province":"Wien",
    "wof:name":"Strauss Gabriele",
    "wof:placetype":"venue"
},
  "geometry": {"coordinates":[16.2684764862,48.1428451538],"type":"Point"}
}