{
  "type": "Feature",
  "properties": {
    "addr:full":"Rauhensteing 10/12a Wien Wien 1010",
    "addr:housenumber":"10 / 12a",
    "addr:postcode":"1010",
    "addr:street":"Rauhensteing",
    "iso:country":"AT",
    "sg:address":"Rauhensteing 10/12a",
    "sg:city":"Wien",
    "sg:orig_category":"Forschungsinstitute",
    "sg:phone":"+43 1 5134084",
    "sg:postcode":"1010",
    "sg:province":"Wien",
    "wof:name":"B\u00fcro f Genealogie-Ausforschung unbekannter Erben",
    "wof:placetype":"venue"
},
  "geometry": {"coordinates":[16.3722953796,48.206111908],"type":"Point"}
}