{
  "type": "Feature",
  "properties": {
    "iso:country":"AT",
    "sg:address":"Feitscher Sdlg 25",
    "sg:city":"Timmersdorf",
    "sg:classifiers":[
        {
            "category":"Home & Garden",
            "subcategory":"Building Materials",
            "type":"Retail Goods"
        }
    ],
    "sg:phone":"+43 4338 3382260",
    "sg:postcode":"8772",
    "sg:province":"Steiermark",
    "sg:tags":[
        "baustoffe",
        "-material",
        "u"
    ],
    "wof:name":"Gruber Herbert GmbH",
    "wof:placetype":"venue"
},
  "geometry": {"coordinates":[14.9700727463,47.3805465698],"type":"Point"}
}