{
  "type": "Feature",
  "properties": {
    "addr:full":"Napplach 95 Penk K\u00e4rnten 9816",
    "addr:housenumber":"95",
    "addr:postcode":"9816",
    "addr:street":"Napplach;Kaernten",
    "iso:country":"AT",
    "sg:address":"Napplach 95",
    "sg:city":"Penk",
    "sg:orig_category":"Tankstellen",
    "sg:phone":"+43 664 1817955",
    "sg:postcode":"9816",
    "sg:province":"K\u00e4rnten",
    "wof:name":"Esso Tankstelle",
    "wof:placetype":"venue"
},
  "geometry": {"coordinates":[13.2661018372,46.8871536255],"type":"Point"}
}