{
  "type": "Feature",
  "properties": {
    "addr:full":"Tannenweg 8 Gmunden Ober\u00f6sterreich 4810",
    "addr:housenumber":"8",
    "addr:postcode":"4810",
    "addr:street":"Tannenweg;Oberoesterreich",
    "iso:country":"AT",
    "sg:address":"Tannenweg 8",
    "sg:city":"Gmunden",
    "sg:orig_category":"Bauleitung U -Betreuung",
    "sg:phone":"+43 4376 1271615",
    "sg:postcode":"4810",
    "sg:province":"Ober\u00f6sterreich",
    "wof:name":"Krakora Rudolf Ing",
    "wof:placetype":"venue"
},
  "geometry": {"coordinates":[13.7751607895,47.9120483398],"type":"Point"}
}