{
  "type": "Feature",
  "properties": {
    "iso:country":"AT",
    "sg:address":"Reichsstr 143a",
    "sg:city":"Feldkirch",
    "sg:orig_category":"Fleischhauereien",
    "sg:phone":"+43 5522 37013",
    "sg:postcode":"6800",
    "sg:province":"Vorarlberg",
    "wof:name":"Deutschmann Gubi GmbH",
    "wof:placetype":"venue"
},
  "geometry": {"coordinates":[9.6079006195,47.2452392578],"type":"Point"}
}