{
  "type": "Feature",
  "properties": {
    "iso:country":"AT",
    "sg:address":"Kapellenweg 11",
    "sg:city":"Seewalchen am Attersee",
    "sg:orig_category":"Maschinenbau",
    "sg:phone":"+43 4376 623236",
    "sg:postcode":"4863",
    "sg:province":"Ober\u00f6sterreich",
    "wof:name":"Starzinger Rudolf",
    "wof:placetype":"venue"
},
  "geometry": {"coordinates":[13.5891857147,47.9542388916],"type":"Point"}
}