{
  "type": "Feature",
  "properties": {
    "addr:full":"Hauptstr. 2 Fohnsdorf Steiermark 8753",
    "addr:housenumber":"2",
    "addr:postcode":"8753",
    "addr:street":"Hauptstr.",
    "iso:country":"AT",
    "sg:address":"Hauptstr. 2",
    "sg:city":"Fohnsdorf",
    "sg:classifiers":[
        {
            "category":"Banks & Credit Unions",
            "subcategory":"Bank",
            "type":"Services"
        }
    ],
    "sg:phone":"+43 4335 7321170",
    "sg:postcode":"8753",
    "sg:province":"Steiermark",
    "sg:tags":[
        "banking",
        "institution"
    ],
    "wof:name":"RAIFFEISENBANK P\u00d6LSTAL REG.GEN.MBH",
    "wof:placetype":"venue"
},
  "geometry": {"coordinates":[14.6773090363,47.208114624],"type":"Point"}
}