{
  "type": "Feature",
  "properties": {
    "iso:country":"AT",
    "sg:address":"Heidenreichsteiner Strasse 9",
    "sg:city":"Waidhofen an der Thaya",
    "sg:classifiers":[
        {
            "category":"Home & Garden",
            "subcategory":"Home Furnishings",
            "type":"Retail Goods"
        }
    ],
    "sg:phone":"+43 2842 54136",
    "sg:postcode":"3830",
    "sg:province":"Nieder\u00f6sterreich",
    "sg:tags":[
        "household",
        "ceramic"
    ],
    "sg:website":"pani.at",
    "wof:name":"Pani Ges.m.b.H.",
    "wof:placetype":"venue"
},
  "geometry": {"coordinates":[15.2517976761,48.7931785583],"type":"Point"}
}