{
  "type": "Feature",
  "properties": {
    "addr:full":"Hochgreith 72 St. Veit Steiermark 8046",
    "addr:housenumber":"72",
    "addr:postcode":"8046",
    "addr:street":"Hochgreith",
    "iso:country":"AT",
    "sg:address":"Hochgreith 72",
    "sg:city":"St. Veit",
    "sg:orig_category":"Psychotherapie",
    "sg:phone":"+43 316 694373",
    "sg:postcode":"8046",
    "sg:province":"Steiermark",
    "wof:name":"Kiszter Norbert",
    "wof:placetype":"venue"
},
  "geometry": {"coordinates":[15.4320335388,47.1295967102],"type":"Point"}
}