{
  "type": "Feature",
  "properties": {
    "addr:full":"Garnisong 11/13 Wien Wien 1090",
    "addr:housenumber":"11 / 13",
    "addr:postcode":"1090",
    "addr:street":"Garnisong",
    "iso:country":"AT",
    "sg:address":"Garnisong 11/13",
    "sg:city":"Wien",
    "sg:orig_category":"Marketingberatung",
    "sg:phone":"+43 1 4060480",
    "sg:postcode":"1090",
    "sg:province":"Wien",
    "wof:name":"Medien Werkzeuge Kommunikations- & Veranstaltungs- GmbH",
    "wof:placetype":"venue"
},
  "geometry": {"coordinates":[16.3563919067,48.2166290283],"type":"Point"}
}