{
  "type": "Feature",
  "properties": {
    "iso:country":"AT",
    "sg:address":"Zaubertalstr 6",
    "sg:city":"Linz",
    "sg:orig_category":"Fernseh- U Radiogesellschaften",
    "sg:phone":"+43 4373 2782342",
    "sg:postcode":"4020",
    "sg:province":"Ober\u00f6sterreich",
    "wof:name":"SOZ VerlagsgesmbH",
    "wof:placetype":"venue"
},
  "geometry": {"coordinates":[14.2581882477,48.30651474],"type":"Point"}
}