{
  "type": "Feature",
  "properties": {
    "addr:full":"Hadikgasse 72/Hoftrakt T\u00fcr 4 Wien Wien 1140",
    "addr:housenumber":"72 / hoftrakt;4",
    "addr:postcode":"1140",
    "addr:street":"Hadikgasse;Tuer",
    "iso:country":"AT",
    "sg:address":"Hadikgasse 72/Hoftrakt T\u00fcr 4",
    "sg:city":"Wien",
    "sg:classifiers":[
        {
            "category":"Building & Trades",
            "subcategory":"Construction",
            "type":"Services"
        }
    ],
    "sg:phone":"+43 1 8946262",
    "sg:postcode":"1140",
    "sg:province":"Wien",
    "sg:tags":[
        "flat",
        "steep",
        "roof",
        "waterproofing"
    ],
    "wof:name":"SKA Spenglerei A. Kranzinger Ges.m.b.H. & Co KG",
    "wof:placetype":"venue"
},
  "geometry": {"coordinates":[16.2696990967,48.1994247437],"type":"Point"}
}