{
  "type": "Feature",
  "properties": {
    "addr:full":"Maria Schmolln 9 Maria Schmolln Ober\u00f6sterreich 5241",
    "addr:housenumber":"9",
    "addr:postcode":"5241",
    "addr:street":"Maria Schmolln",
    "iso:country":"AT",
    "sg:address":"Maria Schmolln 9",
    "sg:city":"Maria Schmolln",
    "sg:classifiers":[
        {
            "category":"Manufacturing",
            "subcategory":"Wood Products",
            "type":"Manufacturing & Wholesale Goods"
        }
    ],
    "sg:phone":"+43 7743 2676",
    "sg:postcode":"5241",
    "sg:province":"Ober\u00f6sterreich",
    "sg:tags":[
        "made",
        "balcony"
    ],
    "wof:name":"Alois Winkler",
    "wof:placetype":"venue"
},
  "geometry": {"coordinates":[13.2200841904,48.1362686157],"type":"Point"}
}