{
  "type": "Feature",
  "properties": {
    "iso:country":"AT",
    "sg:address":"Alfred-Nobel-Strasse 1",
    "sg:city":"V\u00f6lkermarkt",
    "sg:classifiers":[
        {
            "category":"Health Services",
            "subcategory":"Hospital",
            "type":"Services"
        }
    ],
    "sg:phone":"+43 4232 4460850",
    "sg:postcode":"9100",
    "sg:province":"K\u00e4rnten",
    "sg:tags":[
        "tableware",
        "cardboard",
        "disposable"
    ],
    "sg:website":"muchar.at",
    "wof:name":"MAVI Verpackungen GmbH",
    "wof:placetype":"venue"
},
  "geometry": {"coordinates":[-77.7896270752,42.256149292],"type":"Point"}
}