{
  "type": "Feature",
  "properties": {
    "addr:full":"Otto-Hauberger-Str 35 Kapfenberg Steiermark 8605",
    "addr:housenumber":"35",
    "addr:postcode":"8605",
    "addr:street":"Otto-Hauberger-Str",
    "iso:country":"AT",
    "sg:address":"Otto-Hauberger-Str 35",
    "sg:city":"Kapfenberg",
    "sg:orig_category":"\u00c3\u201erzte / F Allgemeinmedizin",
    "sg:phone":"+43 3862 231350",
    "sg:postcode":"8605",
    "sg:province":"Steiermark",
    "wof:name":"Scholze Ursula Dr",
    "wof:placetype":"venue"
},
  "geometry": {"coordinates":[15.3027677536,47.450340271],"type":"Point"}
}