{
  "type": "Feature",
  "properties": {
    "iso:country":"AT",
    "sg:address":"Wolfrathpl 4",
    "sg:city":"Wien",
    "sg:orig_category":"Tabaktrafiken",
    "sg:phone":"+43 1 8778467",
    "sg:postcode":"1130",
    "sg:province":"Wien",
    "wof:name":"Kitzmantl Brigitta",
    "wof:placetype":"venue"
},
  "geometry": {"coordinates":[16.2665805817,48.1880950928],"type":"Point"}
}