{
  "type": "Feature",
  "properties": {
    "addr:full":"Wagramer Str 98 Wien Wien 1220",
    "addr:postcode":"1220",
    "addr:street":"Str 98",
    "iso:country":"AT",
    "sg:address":"Wagramer Str 98",
    "sg:city":"Wien",
    "sg:orig_category":"Boutiquen",
    "sg:phone":"+43 1 2037544",
    "sg:postcode":"1220",
    "sg:province":"Wien",
    "wof:name":"Boutique Elisabeth",
    "wof:placetype":"venue"
},
  "geometry": {"coordinates":[16.4382286072,48.2441864014],"type":"Point"}
}