{
  "type": "Feature",
  "properties": {
    "addr:full":"Traviatag Wien Wien 1230",
    "addr:postcode":"1230",
    "iso:country":"AT",
    "sg:address":"Traviatag",
    "sg:city":"Wien",
    "sg:orig_category":"Fotoausarbeitungen",
    "sg:phone":"+43 1 61626060",
    "sg:postcode":"1230",
    "sg:province":"Wien",
    "wof:name":"Fuji Film \u00d6sterreich GmbH Nfg KG",
    "wof:placetype":"venue"
},
  "geometry": {"coordinates":[16.3412895203,48.1437339783],"type":"Point"}
}