{
  "type": "Feature",
  "properties": {
    "addr:full":"Rosensteing 40 Wien Wien 1170",
    "addr:housenumber":"40",
    "addr:postcode":"1170",
    "addr:street":"Rosensteing",
    "iso:country":"AT",
    "sg:address":"Rosensteing 40",
    "sg:city":"Wien",
    "sg:orig_category":"Bandagen U Bandagisten",
    "sg:phone":"+43 4314 8624020",
    "sg:postcode":"1170",
    "sg:province":"Wien",
    "wof:name":"Sanit\u00e4tshaus Novotny u Pistora GmbH",
    "wof:placetype":"venue"
},
  "geometry": {"coordinates":[16.3264865875,48.2188568115],"type":"Point"}
}