{
  "type": "Feature",
  "properties": {
    "addr:full":"Bongat 9 Dornbirn Vorarlberg 6850",
    "addr:housenumber":"9",
    "addr:postcode":"6850",
    "addr:street":"Bongat",
    "iso:country":"AT",
    "sg:address":"Bongat 9",
    "sg:city":"Dornbirn",
    "sg:orig_category":"Innenarchitekten",
    "sg:phone":"+43 5572 26308",
    "sg:postcode":"6850",
    "sg:province":"Vorarlberg",
    "wof:name":"D\u00fcngler Manfred",
    "wof:placetype":"venue"
},
  "geometry": {"coordinates":[9.7333841324,47.4058418274],"type":"Point"}
}