{
  "type": "Feature",
  "properties": {
    "iso:country":"AT",
    "sg:address":"Europastr 1",
    "sg:city":"Langenrohr",
    "sg:orig_category":"Autohandel",
    "sg:phone":"+43 2272 668000",
    "sg:postcode":"3442",
    "sg:province":"Nieder\u00f6sterreich",
    "wof:name":"Plattner Bruno GmbH",
    "wof:placetype":"venue"
},
  "geometry": {"coordinates":[16.0182914734,48.3185043335],"type":"Point"}
}