{
  "type": "Feature",
  "properties": {
    "iso:country":"AT",
    "sg:address":"Neu Gablonz 5",
    "sg:city":"Enns",
    "sg:classifiers":[
        {
            "category":"Autos & Motor Vehicles",
            "subcategory":"Recreational Vehicle Sales",
            "type":"Retail Goods"
        }
    ],
    "sg:phone":"+43 7223 811750",
    "sg:postcode":"4470",
    "sg:province":"Ober\u00f6sterreich",
    "sg:tags":[
        "car",
        "racing",
        "tuning",
        "accessory"
    ],
    "sg:website":"pbox.cc",
    "wof:name":"PBOX Austria Kraftfahrzeugtechnik GmbH",
    "wof:placetype":"venue"
},
  "geometry": {"coordinates":[14.4792346954,48.2137947083],"type":"Point"}
}