{
  "type": "Feature",
  "properties": {
    "addr:full":"Anton-Buchalka-Str 19 Kapfenberg Steiermark 8605",
    "addr:housenumber":"19",
    "addr:postcode":"8605",
    "addr:street":"Anton-Buchalka-Str",
    "iso:country":"AT",
    "sg:address":"Anton-Buchalka-Str 19",
    "sg:city":"Kapfenberg",
    "sg:classifiers":[
        {
            "category":"Travel",
            "subcategory":"Hotels & Motels",
            "type":"Entertainment"
        }
    ],
    "sg:phone":"+43 3862 220050",
    "sg:postcode":"8605",
    "sg:province":"Steiermark",
    "sg:website":"kaiserhof-kapfenberg.at",
    "wof:name":"Belagyi Elfriede - Pension Kaiserhof",
    "wof:placetype":"venue"
},
  "geometry": {"coordinates":[15.2914381027,47.4460067749],"type":"Point"}
}