{
  "type": "Feature",
  "properties": {
    "addr:full":"Latschau Tschagguns Vorarlberg 6774",
    "addr:postcode":"6774",
    "iso:country":"AT",
    "sg:address":"Latschau",
    "sg:city":"Tschagguns",
    "sg:classifiers":[
        {
            "category":"Restaurant",
            "type":"Food & Drink"
        }
    ],
    "sg:phone":"+43 4355 5672280",
    "sg:postcode":"6774",
    "sg:province":"Vorarlberg",
    "wof:name":"Panorama-Restaurant Gr\u00fcneck",
    "wof:placetype":"venue"
},
  "geometry": {"coordinates":[9.8734397888,47.0744514465],"type":"Point"}
}