{
  "type": "Feature",
  "properties": {
    "addr:full":"K\u00fcrnbergstr. 2  Pasching Ober\u00f6sterreich 4061",
    "addr:housenumber":"2",
    "addr:postcode":"4061",
    "addr:street":"Kuernbergstr.;Oberoesterreich",
    "iso:country":"AT",
    "sg:address":"K\u00fcrnbergstr. 2 ",
    "sg:city":"Pasching",
    "sg:classifiers":[
        {
            "category":"Autos & Motor Vehicles",
            "subcategory":"Automobile Sales",
            "type":"Retail Goods"
        }
    ],
    "sg:phone":"+43 4372 2973428",
    "sg:postcode":"4061",
    "sg:province":"Ober\u00f6sterreich",
    "sg:tags":[
        "industrial"
    ],
    "wof:name":"ERNST RITTMANN",
    "wof:placetype":"venue"
},
  "geometry": {"coordinates":[14.2019853592,48.2585906982],"type":"Point"}
}