{
  "type": "Feature",
  "properties": {
    "addr:full":"Platz 30 Bezau Vorarlberg 6870",
    "addr:housenumber":"30",
    "addr:postcode":"6870",
    "addr:street":"Platz",
    "iso:country":"AT",
    "sg:address":"Platz 30",
    "sg:city":"Bezau",
    "sg:orig_category":"Haushaltsartikel",
    "sg:phone":"+43 5514 2350",
    "sg:postcode":"6870",
    "sg:province":"Vorarlberg",
    "wof:name":"Flatz Haushalt und Geschenke R\u00fcf",
    "wof:placetype":"venue"
},
  "geometry": {"coordinates":[9.9028358459,47.3854217529],"type":"Point"}
}