{
  "type": "Feature",
  "properties": {
    "iso:country":"AT",
    "sg:address":"Nr 31",
    "sg:city":"Griffen",
    "sg:orig_category":"Friseure U Frisiersalons",
    "sg:phone":"+43 4233 2781",
    "sg:postcode":"9112",
    "sg:province":"K\u00e4rnten",
    "wof:name":"Fris\u00f6r Rosi",
    "wof:placetype":"venue"
},
  "geometry": {"coordinates":[14.7313051224,46.7036705017],"type":"Point"}
}