{
  "type": "Feature",
  "properties": {
    "addr:full":"Proleber Str. 10 Niklasdorf Steiermark 8712",
    "addr:housenumber":"10",
    "addr:postcode":"8712",
    "addr:street":"Str.",
    "iso:country":"AT",
    "sg:address":"Proleber Str. 10",
    "sg:city":"Niklasdorf",
    "sg:classifiers":[
        {
            "category":"Manufacturing",
            "subcategory":"Paper Products",
            "type":"Manufacturing & Wholesale Goods"
        }
    ],
    "sg:phone":"+43 4338 428000",
    "sg:postcode":"8712",
    "sg:province":"Steiermark",
    "sg:tags":[
        "cardboard"
    ],
    "wof:name":"BRIGL & BERGMEISTER PAPIERFABRIK GES.MBH",
    "wof:placetype":"venue"
},
  "geometry": {"coordinates":[15.1486816406,47.3957176208],"type":"Point"}
}