{
  "type": "Feature",
  "properties": {
    "addr:full":"Am Hof Wien Wien 1010",
    "addr:postcode":"1010",
    "addr:street":"Am Hof",
    "iso:country":"AT",
    "sg:address":"Am Hof",
    "sg:city":"Wien",
    "sg:orig_category":"Garagen Parkgaragen",
    "sg:phone":"+43 1 53355710",
    "sg:postcode":"1010",
    "sg:province":"Wien",
    "wof:name":"Garage Am Hof GesmbH",
    "wof:placetype":"venue"
},
  "geometry": {"coordinates":[16.3682498932,48.2115516663],"type":"Point"}
}