{
  "type": "Feature",
  "properties": {
    "addr:full":"Markt 121 Gutenstein Nieder\u00f6sterreich 2770",
    "addr:housenumber":"121",
    "addr:postcode":"2770",
    "addr:street":"Markt",
    "iso:country":"AT",
    "sg:address":"Markt 121",
    "sg:city":"Gutenstein",
    "sg:orig_category":"Filmproduktionen",
    "sg:phone":"+43 664 4554600",
    "sg:postcode":"2770",
    "sg:province":"Nieder\u00f6sterreich",
    "wof:name":"Reuscher SFX",
    "wof:placetype":"venue"
},
  "geometry": {"coordinates":[15.889538765,47.875629425],"type":"Point"}
}