{
  "type": "Feature",
  "properties": {
    "addr:full":"Hauptstr 23 Wolkersdorf im Weinviertel Nieder\u00f6sterreich 2120",
    "addr:housenumber":"23",
    "addr:postcode":"2120",
    "addr:street":"Hauptstr",
    "iso:country":"AT",
    "sg:address":"Hauptstr 23",
    "sg:city":"Wolkersdorf im Weinviertel",
    "sg:orig_category":"Blumeneinzelhandel",
    "sg:phone":"+43 4322 452272",
    "sg:postcode":"2120",
    "sg:province":"Nieder\u00f6sterreich",
    "wof:name":"Knoll Helmut",
    "wof:placetype":"venue"
},
  "geometry": {"coordinates":[16.5171432495,48.3840141296],"type":"Point"}
}