{
  "type": "Feature",
  "properties": {
    "iso:country":"AT",
    "sg:address":"Himberger Str 2",
    "sg:city":"Wien",
    "sg:orig_category":"Satellitenempfangsanlagen",
    "sg:phone":"+43 4317 069898",
    "sg:postcode":"1100",
    "sg:province":"Wien",
    "wof:name":"GLOBO Electronic Handels GmbH",
    "wof:placetype":"venue"
},
  "geometry": {"coordinates":[16.3823623657,48.1455726624],"type":"Point"}
}