{
  "type": "Feature",
  "properties": {
    "iso:country":"AT",
    "sg:address":"Heiderosenstr 10",
    "sg:city":"Wels",
    "sg:orig_category":"Autohandel",
    "sg:phone":"+43 4366 43389334",
    "sg:postcode":"4600",
    "sg:province":"Ober\u00f6sterreich",
    "wof:name":"Weigl Franz Dr GesmbH",
    "wof:placetype":"venue"
},
  "geometry": {"coordinates":[14.0238056183,48.17811203],"type":"Point"}
}