{
  "type": "Feature",
  "properties": {
    "addr:full":"Postfach 71 5024",
    "addr:housenumber":"71",
    "addr:postcode":"5024",
    "addr:street":"Postfach",
    "iso:country":"AT",
    "sg:address":"Postfach 71",
    "sg:orig_category":"Dienstleistungen, Fotografie, Grafik U Design",
    "sg:postcode":"5024",
    "sg:website":"http://www.go.to/siebi",
    "wof:name":"Manfred Siebinger",
    "wof:placetype":"venue"
},
  "geometry": {"coordinates":[13.0433769226,47.8006744385],"type":"Point"}
}