{
  "type": "Feature",
  "properties": {
    "addr:full":"Perfektastrasse 83 Wien Wien 1230",
    "addr:housenumber":"83",
    "addr:postcode":"1230",
    "addr:street":"Perfektastrasse",
    "iso:country":"AT",
    "sg:address":"Perfektastrasse 83",
    "sg:city":"Wien",
    "sg:classifiers":[
        {
            "category":"Autos & Motor Vehicles",
            "subcategory":"Fuel & Gas Station",
            "type":"Retail Goods"
        }
    ],
    "sg:phone":"+43 1 8652697",
    "sg:postcode":"1230",
    "sg:province":"Wien",
    "sg:tags":[
        "carburettor"
    ],
    "sg:website":"fitscha.at",
    "wof:name":"Ernst Fitscha Ges.m.b.H.",
    "wof:placetype":"venue"
},
  "geometry": {"coordinates":[16.3013706207,48.1368103027],"type":"Point"}
}