{
  "type": "Feature",
  "properties": {
    "addr:full":"Nr 249 Sipbachzell Ober\u00f6sterreich 4621",
    "addr:postcode":"4621",
    "addr:street":"Nr 249",
    "iso:country":"AT",
    "sg:address":"Nr 249",
    "sg:city":"Sipbachzell",
    "sg:orig_category":"Handelsagenturen",
    "sg:phone":"+43 7240 8516",
    "sg:postcode":"4621",
    "sg:province":"Ober\u00f6sterreich",
    "wof:name":"Konrad Manfred",
    "wof:placetype":"venue"
},
  "geometry": {"coordinates":[14.1100311279,48.0970726013],"type":"Point"}
}