{
  "type": "Feature",
  "properties": {
    "iso:country":"AT",
    "sg:address":"Achenstr 6",
    "sg:city":"Bad Hofgastein",
    "sg:orig_category":"Pensionen / Privatzimmer",
    "sg:phone":"+43 6432 6652",
    "sg:postcode":"5630",
    "sg:province":"Salzburg",
    "wof:name":"Fr\u00fchst\u00fcckspension Angerer",
    "wof:placetype":"venue"
},
  "geometry": {"coordinates":[13.0996923447,47.1718177795],"type":"Point"}
}