{
  "type": "Feature",
  "properties": {
    "addr:full":"Siebenbrunneng 16 Wien Wien 1050",
    "addr:housenumber":"16",
    "addr:postcode":"1050",
    "addr:street":"Siebenbrunneng",
    "iso:country":"AT",
    "sg:address":"Siebenbrunneng 16",
    "sg:city":"Wien",
    "sg:orig_category":"Fleischhauereien",
    "sg:phone":"+43 1 5452319",
    "sg:postcode":"1050",
    "sg:province":"Wien",
    "wof:name":"S\u00f6llner Gertrude",
    "wof:placetype":"venue"
},
  "geometry": {"coordinates":[16.3594036102,48.1878814697],"type":"Point"}
}