{
  "type": "Feature",
  "properties": {
    "iso:country":"AT",
    "sg:address":"Heideweg 27",
    "sg:city":"Seibersdorf",
    "sg:classifiers":[
        {
            "category":"Wholesale",
            "subcategory":"Auto Parts",
            "type":"Manufacturing & Wholesale Goods"
        }
    ],
    "sg:phone":"+43 2255 72200",
    "sg:postcode":"2444",
    "sg:province":"Nieder\u00f6sterreich",
    "sg:tags":[
        "wheel",
        "car",
        "alloy",
        "rims"
    ],
    "wof:name":"Fibo Reifenhandelsges.m.b.H.",
    "wof:placetype":"venue"
},
  "geometry": {"coordinates":[16.5196266174,47.9662628174],"type":"Point"}
}