{
  "type": "Feature",
  "properties": {
    "addr:full":"Gumppstr 1 Innsbruck Tirol 6020",
    "addr:housenumber":"1",
    "addr:postcode":"6020",
    "addr:street":"Gumppstr;Tirol",
    "iso:country":"AT",
    "sg:address":"Gumppstr 1",
    "sg:city":"Innsbruck",
    "sg:orig_category":"Lebensmittel / Einzelhandel",
    "sg:phone":"+43 512 390727",
    "sg:postcode":"6020",
    "sg:province":"Tirol",
    "wof:name":"Ince Mahmut",
    "wof:placetype":"venue"
},
  "geometry": {"coordinates":[11.408372879,47.2637519836],"type":"Point"}
}