{
  "type": "Feature",
  "properties": {
    "addr:full":"Minciostr 4 Wien Wien 1150",
    "addr:housenumber":"4",
    "addr:postcode":"1150",
    "addr:street":"Minciostr",
    "iso:country":"AT",
    "sg:address":"Minciostr 4",
    "sg:city":"Wien",
    "sg:orig_category":"Reifen U Reifendienste",
    "sg:phone":"+43 1 9820205",
    "sg:postcode":"1150",
    "sg:province":"Wien",
    "sg:website":"www.reifen-muehlwisch.at",
    "wof:name":"M\u00fchlwisch Franz KG",
    "wof:placetype":"venue"
},
  "geometry": {"coordinates":[16.3132171631,48.202381134],"type":"Point"}
}