{
  "type": "Feature",
  "properties": {
    "iso:country":"AT",
    "sg:address":"Alpeilweg 4",
    "sg:city":"Tarrenz",
    "sg:orig_category":"Appartements / Ferienwohnungen",
    "sg:phone":"+43 4354 1264415",
    "sg:postcode":"6464",
    "sg:province":"Tirol",
    "wof:name":"Almhofer Rosemarie",
    "wof:placetype":"venue"
},
  "geometry": {"coordinates":[10.766251564,47.2788391113],"type":"Point"}
}