{
  "type": "Feature",
  "properties": {
    "addr:full":"Stelzhamerstr 18 St. Georgen im Attergau Ober\u00f6sterreich 4880",
    "addr:housenumber":"18",
    "addr:postcode":"4880",
    "addr:street":"Stelzhamerstr",
    "iso:country":"AT",
    "sg:address":"Stelzhamerstr 18",
    "sg:city":"St. Georgen im Attergau",
    "sg:orig_category":"Rettungsdienste",
    "sg:phone":"+43 76676244",
    "sg:postcode":"4880",
    "sg:province":"Ober\u00f6sterreich",
    "wof:name":"Rotes Kreuz \u00d6sterreichisches",
    "wof:placetype":"venue"
},
  "geometry": {"coordinates":[13.4846277237,47.9339294434],"type":"Point"}
}