{
  "type": "Feature",
  "properties": {
    "addr:full":"Arlbergstrasse 7 Dornbirn Vorarlberg 6850",
    "addr:housenumber":"7",
    "addr:postcode":"6850",
    "addr:street":"Arlbergstrasse",
    "iso:country":"AT",
    "sg:address":"Arlbergstrasse 7",
    "sg:city":"Dornbirn",
    "sg:classifiers":[
        {
            "category":"Communications",
            "subcategory":"Film & Video Production",
            "type":"Services"
        }
    ],
    "sg:phone":"+43 5572 37500",
    "sg:postcode":"6850",
    "sg:province":"Vorarlberg",
    "sg:tags":[
        "battery",
        "camera"
    ],
    "wof:name":"Heinz Winsauer Ges.m.b.H.",
    "wof:placetype":"venue"
},
  "geometry": {"coordinates":[9.736038208,47.3996086121],"type":"Point"}
}