{
  "type": "Feature",
  "properties": {
    "addr:full":"Rugierstr 38 Wien Wien 1220",
    "addr:housenumber":"38",
    "addr:postcode":"1220",
    "addr:street":"Rugierstr",
    "iso:country":"AT",
    "sg:address":"Rugierstr 38",
    "sg:city":"Wien",
    "sg:orig_category":"Chemikalien",
    "sg:phone":"+43 1 2034305",
    "sg:postcode":"1220",
    "sg:province":"Wien",
    "wof:name":"Hirsch Hertha",
    "wof:placetype":"venue"
},
  "geometry": {"coordinates":[16.4514598846,48.2381401062],"type":"Point"}
}