{
  "type": "Feature",
  "properties": {
    "addr:full":"W\u00e4hringer Str 39 Wien Wien 1090",
    "addr:postcode":"1090",
    "addr:street":"Str 39",
    "iso:country":"AT",
    "sg:address":"W\u00e4hringer Str 39",
    "sg:city":"Wien",
    "sg:orig_category":"Non-Classified Establishments",
    "sg:phone":"+43 1 400340",
    "sg:postcode":"1090",
    "sg:province":"Wien",
    "wof:name":"Magistratisches Bezirksamt f d 9. Bezirk",
    "wof:placetype":"venue"
},
  "geometry": {"coordinates":[16.3552131653,48.2206993103],"type":"Point"}
}