{
  "type": "Feature",
  "properties": {
    "addr:full":"Kienzlstr 14 Waizenkirchen Ober\u00f6sterreich 4730",
    "addr:housenumber":"14",
    "addr:postcode":"4730",
    "addr:street":"Kienzlstr",
    "iso:country":"AT",
    "sg:address":"Kienzlstr 14",
    "sg:city":"Waizenkirchen",
    "sg:orig_category":"Friseure U Frisiersalons",
    "sg:phone":"+43 7277 2287",
    "sg:postcode":"4730",
    "sg:province":"Ober\u00f6sterreich",
    "wof:name":"Haarmoden Strasser",
    "wof:placetype":"venue"
},
  "geometry": {"coordinates":[13.8563947678,48.330821991],"type":"Point"}
}