{
  "type": "Feature",
  "properties": {
    "addr:full":"Industriestr 7a M\u00e4der Vorarlberg 6841",
    "addr:housenumber":"7a",
    "addr:postcode":"maeder;6841",
    "addr:street":"Industriestr",
    "iso:country":"AT",
    "sg:address":"Industriestr 7a",
    "sg:city":"M\u00e4der",
    "sg:orig_category":"Transportunternehmen",
    "sg:phone":"+43 5523 516150",
    "sg:postcode":"6841",
    "sg:province":"Vorarlberg",
    "wof:name":"Mostegl Transporte f fl\u00fcssiger Lebensmittel",
    "wof:placetype":"venue"
},
  "geometry": {"coordinates":[-86.5726852417,37.9961738586],"type":"Point"}
}