{
  "type": "Feature",
  "properties": {
    "addr:full":"Nr 13 Hatzendorf Steiermark 8361",
    "addr:postcode":"8361",
    "addr:street":"Nr",
    "iso:country":"AT",
    "sg:address":"Nr 13",
    "sg:city":"Hatzendorf",
    "sg:orig_category":"Lebensmittel / Einzelhandel",
    "sg:phone":"+43 4331 552390",
    "sg:postcode":"8361",
    "sg:province":"Steiermark",
    "wof:name":"Spar-Markt Schober Ernst",
    "wof:placetype":"venue"
},
  "geometry": {"coordinates":[16.0021743774,46.9774932861],"type":"Point"}
}