{
  "type": "Feature",
  "properties": {
    "addr:full":"Schulg 10 Schwarzenau Nieder\u00f6sterreich 3900",
    "addr:housenumber":"10",
    "addr:postcode":"3900",
    "addr:street":"Schulg",
    "iso:country":"AT",
    "sg:address":"Schulg 10",
    "sg:city":"Schwarzenau",
    "sg:orig_category":"Volksschulen",
    "sg:phone":"+43 4328 492242",
    "sg:postcode":"3900",
    "sg:province":"Nieder\u00f6sterreich",
    "wof:name":"Volksschule",
    "wof:placetype":"venue"
},
  "geometry": {"coordinates":[15.2566137314,48.7444229126],"type":"Point"}
}