{
  "type": "Feature",
  "properties": {
    "addr:full":"Neug 8 Mank Nieder\u00f6sterreich 3240",
    "addr:housenumber":"8",
    "addr:postcode":"3240",
    "addr:street":"Neug;Niederoesterreich",
    "iso:country":"AT",
    "sg:address":"Neug 8",
    "sg:city":"Mank",
    "sg:orig_category":"Maler, Anstreicher U Lackierer",
    "sg:phone":"+43 2755 8327",
    "sg:postcode":"3240",
    "sg:province":"Nieder\u00f6sterreich",
    "wof:name":"Stelzhammer Franz",
    "wof:placetype":"venue"
},
  "geometry": {"coordinates":[15.3406190872,48.1110343933],"type":"Point"}
}