{
  "type": "Feature",
  "properties": {
    "addr:full":"Nr 10 Haag Nieder\u00f6sterreich 3350",
    "addr:postcode":"3350",
    "addr:street":"Nr;Haag Niederoesterreich",
    "iso:country":"AT",
    "sg:address":"Nr 10",
    "sg:city":"Haag",
    "sg:orig_category":"Pensionen / Privatzimmer",
    "sg:phone":"+43 7434 42829",
    "sg:postcode":"3350",
    "sg:province":"Nieder\u00f6sterreich",
    "wof:name":"Adelberger Franz",
    "wof:placetype":"venue"
},
  "geometry": {"coordinates":[14.5653553009,48.1121940613],"type":"Point"}
}