{
  "type": "Feature",
  "properties": {
    "addr:full":"Sch\u00f6rgeneck 9 Esternberg Ober\u00f6sterreich 4092",
    "addr:housenumber":"9",
    "addr:postcode":"4092",
    "addr:street":"Schoergeneck",
    "iso:country":"AT",
    "sg:address":"Sch\u00f6rgeneck 9",
    "sg:city":"Esternberg",
    "sg:orig_category":"Tischlereien",
    "sg:phone":"+43 7714 6647",
    "sg:postcode":"4092",
    "sg:province":"Ober\u00f6sterreich",
    "wof:name":"Tischlerei Reisinger KEG",
    "wof:placetype":"venue"
},
  "geometry": {"coordinates":[13.5926427841,48.5445327759],"type":"Point"}
}