{
  "type": "Feature",
  "properties": {
    "iso:country":"AT",
    "sg:address":"Dorf 16",
    "sg:city":"Neustift im Stubaital",
    "sg:orig_category":"Diskotheken",
    "sg:phone":"+43 4352 263288",
    "sg:postcode":"6167",
    "sg:province":"Tirol",
    "wof:name":"Rumpl-Disco",
    "wof:placetype":"venue"
},
  "geometry": {"coordinates":[11.3061437607,47.1105728149],"type":"Point"}
}