{
  "type": "Feature",
  "properties": {
    "iso:country":"AT",
    "sg:address":"Hauptstr 412",
    "sg:city":"Mayrhofen",
    "sg:orig_category":"Bars-Cafes",
    "sg:phone":"+43 5285 64830",
    "sg:postcode":"6290",
    "sg:province":"Tirol",
    "wof:name":"Bar-Cafe Apropos",
    "wof:placetype":"venue"
},
  "geometry": {"coordinates":[11.8634538651,47.1680030823],"type":"Point"}
}