{
  "type": "Feature",
  "properties": {
    "iso:country":"AT",
    "sg:address":"Neumarkter Str 4",
    "sg:city":"Jennersdorf",
    "sg:orig_category":"Maler, Anstreicher U Lackierer",
    "sg:phone":"+43 3329 45515",
    "sg:postcode":"8380",
    "sg:province":"Burgenland",
    "wof:name":"Neuherz Josef",
    "wof:placetype":"venue"
},
  "geometry": {"coordinates":[16.1467132568,46.9366836548],"type":"Point"}
}