{
  "type": "Feature",
  "properties": {
    "addr:full":"Theodor-Kery-Wohnpark 7/14 Neufeld an der Leitha Burgenland 2491",
    "addr:housenumber":"7 / 14",
    "addr:postcode":"2491",
    "addr:street":"Theodor-Kery-Wohnpark",
    "iso:country":"AT",
    "sg:address":"Theodor-Kery-Wohnpark 7/14",
    "sg:city":"Neufeld an der Leitha",
    "sg:orig_category":"Werbegrafik- U Grafik-Design",
    "sg:phone":"+43 4369 927994810",
    "sg:postcode":"2491",
    "sg:province":"Burgenland",
    "wof:name":"MF GraphX",
    "wof:placetype":"venue"
},
  "geometry": {"coordinates":[16.3767261505,47.8670654297],"type":"Point"}
}