{
  "type": "Feature",
  "properties": {
    "addr:full":"Rusteng. 9 Wien Wien 1150",
    "addr:housenumber":"9",
    "addr:postcode":"1150",
    "addr:street":"Rusteng.",
    "iso:country":"AT",
    "sg:address":"Rusteng. 9",
    "sg:city":"Wien",
    "sg:classifiers":[
        {
            "category":"Building & Trades",
            "subcategory":"Construction",
            "type":"Services"
        }
    ],
    "sg:phone":"+43 4318 932617",
    "sg:postcode":"1150",
    "sg:province":"Wien",
    "sg:tags":[
        "work",
        "public"
    ],
    "wof:name":"ING SCHERIAU & CO GESMBH",
    "wof:placetype":"venue"
},
  "geometry": {"coordinates":[16.3271331787,48.1925544739],"type":"Point"}
}