{
  "type": "Feature",
  "properties": {
    "addr:full":"Moserstr. 33a 5017",
    "addr:housenumber":"33a",
    "addr:postcode":"5017",
    "addr:street":"Moserstr.",
    "iso:country":"AT",
    "sg:address":"Moserstr. 33a",
    "sg:classifiers":[
        {
            "category":"Professional",
            "subcategory":"Computer Services",
            "type":"Services"
        }
    ],
    "sg:phone":"+43 4366 24348000",
    "sg:postcode":"5017",
    "sg:tags":[
        "information",
        "technology"
    ],
    "wof:name":"NEMETSCHEK \u00d6STERREICH GESMBH",
    "wof:placetype":"venue"
},
  "geometry": {"coordinates":[13.010764122,47.8013267517],"type":"Point"}
}