{
  "type": "Feature",
  "properties": {
    "addr:full":"Anna Neumann-Str 26 Murau Steiermark 8850",
    "addr:housenumber":"26",
    "addr:postcode":"8850",
    "iso:country":"AT",
    "sg:address":"Anna Neumann-Str 26",
    "sg:city":"Murau",
    "sg:orig_category":"Bildungsservice / Allgemeine Informationsstellen",
    "sg:phone":"+43 3532 44880",
    "sg:postcode":"8850",
    "sg:province":"Steiermark",
    "wof:name":"Bildungsplattform Bezirk Murau",
    "wof:placetype":"venue"
},
  "geometry": {"coordinates":[14.1681022644,47.110408783],"type":"Point"}
}