{
  "type": "Feature",
  "properties": {
    "iso:country":"AT",
    "sg:address":"Heihsweg 3",
    "sg:city":"Schwechat",
    "sg:classifiers":[
        {
            "category":"Taxi",
            "type":"Transportation"
        }
    ],
    "sg:phone":"+43 1 7072446",
    "sg:postcode":"2320",
    "sg:province":"Nieder\u00f6sterreich",
    "sg:tags":[
        "personentransporte",
        "u"
    ],
    "wof:name":"Woller Horst GesmbH",
    "wof:placetype":"venue"
},
  "geometry": {"coordinates":[16.4591255188,48.1212997437],"type":"Point"}
}