{
  "type": "Feature",
  "properties": {
    "addr:full":"Nr 64 Pichl Steiermark 8973",
    "addr:postcode":"8973",
    "addr:street":"Nr;Pichl",
    "iso:country":"AT",
    "sg:address":"Nr 64",
    "sg:city":"Pichl",
    "sg:orig_category":"Volksschulen",
    "sg:phone":"+43 4364 547302",
    "sg:postcode":"8973",
    "sg:province":"Steiermark",
    "wof:name":"Volksschule",
    "wof:placetype":"venue"
},
  "geometry": {"coordinates":[13.6136493683,47.3911323547],"type":"Point"}
}