{
  "type": "Feature",
  "properties": {
    "iso:country":"AT",
    "sg:address":"Arthaberpl 4",
    "sg:city":"Wien",
    "sg:orig_category":"Personalbereitstellung",
    "sg:phone":"+43 1 6419201",
    "sg:postcode":"1100",
    "sg:province":"Wien",
    "wof:name":"BAR-COM Beteiligungs- und Handels-GmbH",
    "wof:placetype":"venue"
},
  "geometry": {"coordinates":[16.372592926,48.1727600098],"type":"Point"}
}