{
  "type": "Feature",
  "properties": {
    "addr:full":"Himmelstrasse 7 Wien Wien 1190",
    "addr:housenumber":"7",
    "addr:postcode":"1190",
    "addr:street":"Himmelstrasse",
    "iso:country":"AT",
    "sg:address":"Himmelstrasse 7",
    "sg:city":"Wien",
    "sg:classifiers":[
        {
            "category":"Professional",
            "subcategory":"Advertising",
            "type":"Services"
        }
    ],
    "sg:phone":"+43 1 32091510",
    "sg:postcode":"1190",
    "sg:province":"Wien",
    "sg:tags":[
        "article",
        "distribution",
        "articles"
    ],
    "sg:website":"mitraco.com",
    "wof:name":"MITRACO Geschenkartikelvertrieb Ges.m.b.H.",
    "wof:placetype":"venue"
},
  "geometry": {"coordinates":[16.3415145874,48.2557106018],"type":"Point"}
}