{
  "type": "Feature",
  "properties": {
    "addr:full":"Alser Str 41 Wien Wien 1080",
    "addr:postcode":"1080",
    "addr:street":"Str 41",
    "iso:country":"AT",
    "sg:address":"Alser Str 41",
    "sg:city":"Wien",
    "sg:orig_category":"Bettwaren",
    "sg:phone":"+43 1 4026490",
    "sg:postcode":"1080",
    "sg:province":"Wien",
    "wof:name":"Betten D\u00f6rr",
    "wof:placetype":"venue"
},
  "geometry": {"coordinates":[16.3473014832,48.2151527405],"type":"Point"}
}