{
  "type": "Feature",
  "properties": {
    "addr:full":"Khekgasse 55 Wien Wien 1230",
    "addr:housenumber":"55",
    "addr:postcode":"1230",
    "addr:street":"Khekgasse",
    "iso:country":"AT",
    "sg:address":"Khekgasse 55",
    "sg:city":"Wien",
    "sg:classifiers":[
        {
            "category":"Professional",
            "subcategory":"Engineering",
            "type":"Services"
        }
    ],
    "sg:phone":"+43 1 866220",
    "sg:postcode":"1230",
    "sg:province":"Wien",
    "sg:tags":[
        "organizational",
        "information",
        "consulting",
        "technology"
    ],
    "sg:website":"sosgmbh.at",
    "wof:name":"SOS Software Service GmbH",
    "wof:placetype":"venue"
},
  "geometry": {"coordinates":[16.2729034424,48.1347961426],"type":"Point"}
}