{
  "type": "Feature",
  "properties": {
    "addr:full":"Prager Str 21 Wien Wien 1210",
    "addr:postcode":"1210",
    "addr:street":"Str 21",
    "iso:country":"AT",
    "sg:address":"Prager Str 21",
    "sg:city":"Wien",
    "sg:orig_category":"Sonnenstudios",
    "sg:phone":"+43 1 2785289",
    "sg:postcode":"1210",
    "sg:province":"Wien",
    "wof:name":"Karman Helene",
    "wof:placetype":"venue"
},
  "geometry": {"coordinates":[16.3954658508,48.2605628967],"type":"Point"}
}