{
  "type": "Feature",
  "properties": {
    "addr:full":"Ehrentaler Str 21 Klagenfurt K\u00e4rnten 9020",
    "addr:housenumber":"21",
    "addr:postcode":"9020",
    "addr:street":"Str;Kaernten",
    "iso:country":"AT",
    "sg:address":"Ehrentaler Str 21",
    "sg:city":"Klagenfurt",
    "sg:orig_category":"Edelstahl",
    "sg:phone":"+43 463 441020",
    "sg:postcode":"9020",
    "sg:province":"K\u00e4rnten",
    "wof:name":"Pfl\u00fcger-Edelstahl",
    "wof:placetype":"venue"
},
  "geometry": {"coordinates":[14.3130302429,46.6449699402],"type":"Point"}
}