{
  "type": "Feature",
  "properties": {
    "addr:full":"S\u00fcdtiroler Pl 7 Wien Wien 1040",
    "addr:housenumber":"7",
    "addr:postcode":"1040",
    "addr:street":"Suedtiroler Pl",
    "iso:country":"AT",
    "sg:address":"S\u00fcdtiroler Pl 7",
    "sg:city":"Wien",
    "sg:orig_category":"Sonnenstudios",
    "sg:phone":"+43 1 5037496",
    "sg:postcode":"1040",
    "sg:province":"Wien",
    "wof:name":"Sun Company Br\u00e4unungsstudio",
    "wof:placetype":"venue"
},
  "geometry": {"coordinates":[16.3671455383,48.1940345764],"type":"Point"}
}