{
  "type": "Feature",
  "properties": {
    "addr:full":"Traunreiterweg 5 Bad Ischl Ober\u00f6sterreich 4820",
    "addr:housenumber":"5",
    "addr:postcode":"4820",
    "addr:street":"Traunreiterweg",
    "iso:country":"AT",
    "sg:address":"Traunreiterweg 5",
    "sg:city":"Bad Ischl",
    "sg:orig_category":"Bauunternehmen",
    "sg:phone":"+43 4361 3223232",
    "sg:postcode":"4820",
    "sg:province":"Ober\u00f6sterreich",
    "wof:name":"Wildbach- u Lawinenverbauung",
    "wof:placetype":"venue"
},
  "geometry": {"coordinates":[13.6155719757,47.7058792114],"type":"Point"}
}