{
  "type": "Feature",
  "properties": {
    "addr:full":"Innsbrucker Str 29 Kirchdorf in Tirol Tirol 6382",
    "addr:housenumber":"29",
    "addr:postcode":"6382",
    "addr:street":"Str;Tirol",
    "iso:country":"AT",
    "sg:address":"Innsbrucker Str 29",
    "sg:city":"Kirchdorf in Tirol",
    "sg:classifiers":[
        {
            "category":"Travel",
            "subcategory":"Hotels & Motels",
            "type":"Entertainment"
        }
    ],
    "sg:phone":"+43 5352 61522",
    "sg:postcode":"6382",
    "sg:province":"Tirol",
    "wof:name":"Greif Hotel GesmbH",
    "wof:placetype":"venue"
},
  "geometry": {"coordinates":[12.452252388,47.551815033],"type":"Point"}
}