{
  "type": "Feature",
  "properties": {
    "addr:full":"Vesthental 201 Haidershofen Nieder\u00f6sterreich 4431",
    "addr:housenumber":"201",
    "addr:postcode":"4431",
    "addr:street":"Niederoesterreich",
    "iso:country":"AT",
    "sg:address":"Vesthental 201",
    "sg:city":"Haidershofen",
    "sg:classifiers":[
        {
            "category":"Structure",
            "subcategory":"Office Building",
            "type":"Public Place"
        }
    ],
    "sg:phone":"+43 7434 42421",
    "sg:postcode":"4431",
    "sg:province":"Nieder\u00f6sterreich",
    "sg:tags":[
        "door",
        "automatic",
        "actuator"
    ],
    "sg:website":"wartecker.at",
    "wof:name":"Wartecker GmbH",
    "wof:placetype":"venue"
},
  "geometry": {"coordinates":[14.5206050873,48.0718078613],"type":"Point"}
}