{
  "type": "Feature",
  "properties": {
    "addr:full":"Alleeg 12 Neunkirchen Nieder\u00f6sterreich 2620",
    "addr:housenumber":"12",
    "addr:postcode":"2620",
    "addr:street":"Alleeg",
    "iso:country":"AT",
    "sg:address":"Alleeg 12",
    "sg:city":"Neunkirchen",
    "sg:orig_category":"Osteopathie",
    "sg:phone":"+43 676 7502302",
    "sg:postcode":"2620",
    "sg:province":"Nieder\u00f6sterreich",
    "wof:name":"Jakusch Natascha Dipl PT - Osteopathie",
    "wof:placetype":"venue"
},
  "geometry": {"coordinates":[16.0980548859,47.7119560242],"type":"Point"}
}