{
  "type": "Feature",
  "properties": {
    "addr:full":"Hauptstr 8 G\u00f6tzendorf an der Leitha Nieder\u00f6sterreich 2434",
    "addr:housenumber":"8",
    "addr:postcode":"2434",
    "addr:street":"Hauptstr;An Der Leitha",
    "iso:country":"AT",
    "sg:address":"Hauptstr 8",
    "sg:city":"G\u00f6tzendorf an der Leitha",
    "sg:orig_category":"Fleischhauereien",
    "sg:phone":"+43 2169 2273",
    "sg:postcode":"2434",
    "sg:province":"Nieder\u00f6sterreich",
    "wof:name":"Auer Konrad",
    "wof:placetype":"venue"
},
  "geometry": {"coordinates":[-101.6332702637,46.3577537537],"type":"Point"}
}