{
  "type": "Feature",
  "properties": {
    "addr:full":"Zeillerg 7-11 Wien Wien 1170",
    "addr:housenumber":"7-11",
    "addr:postcode":"1170",
    "iso:country":"AT",
    "sg:address":"Zeillerg 7-11",
    "sg:city":"Wien",
    "sg:orig_category":"Tabaktrafiken",
    "sg:phone":"+43 1 4862492",
    "sg:postcode":"1170",
    "sg:province":"Wien",
    "wof:name":"Soukup Richard",
    "wof:placetype":"venue"
},
  "geometry": {"coordinates":[16.3123683929,48.2233734131],"type":"Point"}
}