{
  "type": "Feature",
  "properties": {
    "addr:full":"null Vielsassing St. Florian am Inn Ober\u00f6sterreich 4782",
    "addr:postcode":"4782",
    "iso:country":"AT",
    "sg:address":"null Vielsassing",
    "sg:city":"St. Florian am Inn",
    "sg:orig_category":"Non-Classified Establishments",
    "sg:phone":"+43 4377 198837",
    "sg:postcode":"4782",
    "sg:province":"Ober\u00f6sterreich",
    "wof:name":"Bundesstra\u00dfenverwaltung",
    "wof:placetype":"venue"
},
  "geometry": {"coordinates":[13.4722633362,48.4116363525],"type":"Point"}
}