{
  "type": "Feature",
  "properties": {
    "addr:full":"Baumg 29 Wien Wien 1030",
    "addr:housenumber":"29",
    "addr:postcode":"1030",
    "addr:street":"Baumg",
    "iso:country":"AT",
    "sg:address":"Baumg 29",
    "sg:city":"Wien",
    "sg:orig_category":"Raumausstattung",
    "sg:phone":"+43 1 7147731",
    "sg:postcode":"1030",
    "sg:province":"Wien",
    "wof:name":"Kleedorfer Hermann",
    "wof:placetype":"venue"
},
  "geometry": {"coordinates":[16.3986206055,48.1958084106],"type":"Point"}
}