{
  "type": "Feature",
  "properties": {
    "addr:full":"Graben 17 Opponitz Nieder\u00f6sterreich 3342",
    "addr:housenumber":"17",
    "addr:postcode":"3342",
    "addr:street":"Graben",
    "iso:country":"AT",
    "sg:address":"Graben 17",
    "sg:city":"Opponitz",
    "sg:orig_category":"Rauchfangkehrer",
    "sg:phone":"+43 7444 7527",
    "sg:postcode":"3342",
    "sg:province":"Nieder\u00f6sterreich",
    "wof:name":"Pichler Helmut",
    "wof:placetype":"venue"
},
  "geometry": {"coordinates":[14.8427619934,47.8815841675],"type":"Point"}
}