{
  "type": "Feature",
  "properties": {
    "addr:full":"Weidachstr 18b Schwarzach Vorarlberg 6858",
    "addr:housenumber":"18b",
    "addr:postcode":"6858",
    "addr:street":"Weidachstr",
    "iso:country":"AT",
    "sg:address":"Weidachstr 18b",
    "sg:city":"Schwarzach",
    "sg:orig_category":"Tischlereien",
    "sg:phone":"+43 676 3083821",
    "sg:postcode":"6858",
    "sg:province":"Vorarlberg",
    "wof:name":"Immler Edelbert",
    "wof:placetype":"venue"
},
  "geometry": {"coordinates":[9.7598800659,47.4478149414],"type":"Point"}
}