{
  "type": "Feature",
  "properties": {
    "addr:full":"Weinbergg 17 Gro\u00dfwarasdorf Burgenland 7304",
    "addr:housenumber":"17",
    "addr:postcode":"7304",
    "addr:street":"Weinbergg",
    "iso:country":"AT",
    "sg:address":"Weinbergg 17",
    "sg:city":"Gro\u00dfwarasdorf",
    "sg:orig_category":"Architekten",
    "sg:phone":"+43 2614 2689",
    "sg:postcode":"7304",
    "sg:province":"Burgenland",
    "wof:name":"Szedenik Rudolf Arch Dipl-Ing",
    "wof:placetype":"venue"
},
  "geometry": {"coordinates":[16.5901660919,47.5371513367],"type":"Point"}
}