{
  "type": "Feature",
  "properties": {
    "iso:country":"AT",
    "sg:address":"Welser Str 4",
    "sg:city":"Marchtrenk",
    "sg:orig_category":"Friseure U Frisiersalons",
    "sg:phone":"+43 7243 52278",
    "sg:postcode":"4614",
    "sg:province":"Ober\u00f6sterreich",
    "wof:name":"Friseursalon Sandler",
    "wof:placetype":"venue"
},
  "geometry": {"coordinates":[14.1108131409,48.1906433105],"type":"Point"}
}