{
  "type": "Feature",
  "properties": {
    "addr:full":"Nr 105 Kleinarl Salzburg 5603",
    "addr:postcode":"5603",
    "addr:street":"Nr;Salzburg",
    "iso:country":"AT",
    "sg:address":"Nr 105",
    "sg:city":"Kleinarl",
    "sg:orig_category":"Gemeinden",
    "sg:phone":"+43 6418 2100",
    "sg:postcode":"5603",
    "sg:province":"Salzburg",
    "wof:name":"Gemeindeamt Kleinarl",
    "wof:placetype":"venue"
},
  "geometry": {"coordinates":[13.3195962906,47.2775421143],"type":"Point"}
}