{
  "type": "Feature",
  "properties": {
    "iso:country":"AT",
    "sg:address":"Nr 70",
    "sg:city":"Donnersbach",
    "sg:orig_category":"Pensionen / Privatzimmer",
    "sg:phone":"+43 3680 252",
    "sg:postcode":"8953",
    "sg:province":"Steiermark",
    "wof:name":"Purkhardt Pius",
    "wof:placetype":"venue"
},
  "geometry": {"coordinates":[14.1177520752,47.3823890686],"type":"Point"}
}