{
  "type": "Feature",
  "properties": {
    "addr:full":"Im G\u00e4ssle 2 Schruns Vorarlberg 6780",
    "addr:housenumber":"2",
    "addr:postcode":"6780",
    "addr:street":"Im Gaessle",
    "iso:country":"AT",
    "sg:address":"Im G\u00e4ssle 2",
    "sg:city":"Schruns",
    "sg:orig_category":"Blumeneinzelhandel",
    "sg:phone":"+43 4355 5672762",
    "sg:postcode":"6780",
    "sg:province":"Vorarlberg",
    "wof:name":"Floristik Renate",
    "wof:placetype":"venue"
},
  "geometry": {"coordinates":[9.9074554443,47.0924110413],"type":"Point"}
}