{
  "type": "Feature",
  "properties": {
    "addr:full":"Stelzhamerpl 18 Ried im Innkreis Ober\u00f6sterreich 4910",
    "addr:housenumber":"18",
    "addr:postcode":"4910",
    "addr:street":"Stelzhamerpl",
    "iso:country":"AT",
    "sg:address":"Stelzhamerpl 18",
    "sg:city":"Ried im Innkreis",
    "sg:orig_category":"Optiker",
    "sg:phone":"+43 7752 831020",
    "sg:postcode":"4910",
    "sg:province":"Ober\u00f6sterreich",
    "wof:name":"Aigner Rudolf",
    "wof:placetype":"venue"
},
  "geometry": {"coordinates":[13.4871873856,48.209072113],"type":"Point"}
}