{
  "type": "Feature",
  "properties": {
    "addr:full":"Unter der Burg 1 Waidhofen an der Ybbs Nieder\u00f6sterreich 3340",
    "addr:housenumber":"1",
    "addr:postcode":"3340",
    "addr:street":"Unter Der Burg",
    "iso:country":"AT",
    "sg:address":"Unter der Burg 1",
    "sg:city":"Waidhofen an der Ybbs",
    "sg:classifiers":[
        {
            "category":"Retail",
            "subcategory":"Event Space",
            "type":"Services"
        }
    ],
    "sg:phone":"+43 4374 4252462",
    "sg:postcode":"3340",
    "sg:province":"Nieder\u00f6sterreich",
    "sg:tags":[
        "hand-",
        "u",
        "fu\u00c3\u0178pflege"
    ],
    "wof:name":"B\u00fchn Christian",
    "wof:placetype":"venue"
},
  "geometry": {"coordinates":[14.7719297409,47.9604911804],"type":"Point"}
}