{
  "type": "Feature",
  "properties": {
    "addr:full":"Ferdinand-Schoder-Str 4 Vandans Vorarlberg 6773",
    "addr:housenumber":"4",
    "addr:postcode":"6773",
    "addr:street":"Ferdinand-Schoder-Str",
    "iso:country":"AT",
    "sg:address":"Ferdinand-Schoder-Str 4",
    "sg:city":"Vandans",
    "sg:orig_category":"Estriche",
    "sg:phone":"+43 4355 5674666",
    "sg:postcode":"6773",
    "sg:province":"Vorarlberg",
    "wof:name":"Bleiner Hans",
    "wof:placetype":"venue"
},
  "geometry": {"coordinates":[9.8582811356,47.0997924805],"type":"Point"}
}