{
  "type": "Feature",
  "properties": {
    "addr:full":"Baumgartner Str 289 Mautern Nieder\u00f6sterreich 3512",
    "addr:housenumber":"289",
    "addr:postcode":"3512",
    "addr:street":"Str",
    "iso:country":"AT",
    "sg:address":"Baumgartner Str 289",
    "sg:city":"Mautern",
    "sg:orig_category":"Non-Classified Establishments",
    "sg:phone":"+43 2732 82933",
    "sg:postcode":"3512",
    "sg:province":"Nieder\u00f6sterreich",
    "wof:name":"Justizanstalt Stein Au\u00dfenstelle Mautern",
    "wof:placetype":"venue"
},
  "geometry": {"coordinates":[15.5512466431,48.3772163391],"type":"Point"}
}