{
  "type": "Feature",
  "properties": {
    "addr:full":"Leibnitzer Strasse 19 Arnfels Steiermark 8454",
    "addr:housenumber":"19",
    "addr:postcode":"8454",
    "addr:street":"Leibnitzer Strasse",
    "iso:country":"AT",
    "sg:address":"Leibnitzer Strasse 19",
    "sg:city":"Arnfels",
    "sg:classifiers":[
        {
            "category":"Home & Garden",
            "subcategory":"Household Appliances",
            "type":"Retail Goods"
        }
    ],
    "sg:phone":"+43 3455 225",
    "sg:postcode":"8454",
    "sg:province":"Steiermark",
    "sg:tags":[
        "electric"
    ],
    "wof:name":"Erich Legat Elektro",
    "wof:placetype":"venue"
},
  "geometry": {"coordinates":[15.4013643265,46.6806221008],"type":"Point"}
}