{
  "type": "Feature",
  "properties": {
    "addr:full":"Schrankg 12 Wien Wien 1070",
    "addr:housenumber":"12",
    "addr:postcode":"1070",
    "addr:street":"Schrankg",
    "iso:country":"AT",
    "sg:address":"Schrankg 12",
    "sg:city":"Wien",
    "sg:classifiers":[
        {
            "category":"Organizations",
            "subcategory":"Community Association",
            "type":"Services"
        }
    ],
    "sg:phone":"+43 1 8955611",
    "sg:postcode":"1070",
    "sg:province":"Wien",
    "sg:tags":[
        "relation",
        "public"
    ],
    "wof:name":"Cox Orange Marketing & PR GmbH",
    "wof:placetype":"venue"
},
  "geometry": {"coordinates":[16.354724884,48.203666687],"type":"Point"}
}