{
  "type": "Feature",
  "properties": {
    "addr:full":"Stegen 17 Lochau Vorarlberg 6911",
    "addr:housenumber":"17",
    "addr:postcode":"6911",
    "addr:street":"Stegen",
    "iso:country":"AT",
    "sg:address":"Stegen 17",
    "sg:city":"Lochau",
    "sg:orig_category":"Pensionen / Privatzimmer",
    "sg:phone":"+43 5573 83519",
    "sg:postcode":"6911",
    "sg:province":"Vorarlberg",
    "wof:name":"Innauer Irmagard und Alois",
    "wof:placetype":"venue"
},
  "geometry": {"coordinates":[9.7790279388,47.5505371094],"type":"Point"}
}