{
  "type": "Feature",
  "properties": {
    "iso:country":"AT",
    "sg:address":"Gewerbegebiet 685",
    "sg:city":"Pfunds",
    "sg:orig_category":"Schlossereien",
    "sg:phone":"+43 5474 52620",
    "sg:postcode":"6542",
    "sg:province":"Tirol",
    "wof:name":"Metallbau Brunner GmbH",
    "wof:placetype":"venue"
},
  "geometry": {"coordinates":[10.5467176437,46.9730453491],"type":"Point"}
}