{
  "type": "Feature",
  "properties": {
    "addr:full":"Nr 210 Trattenbach Nieder\u00f6sterreich 2881",
    "addr:postcode":"2881",
    "addr:street":"Nr 210",
    "iso:country":"AT",
    "sg:address":"Nr 210",
    "sg:city":"Trattenbach",
    "sg:orig_category":"Banken U Sparkassen",
    "sg:phone":"+43 4326 418460",
    "sg:postcode":"2881",
    "sg:province":"Nieder\u00f6sterreich",
    "wof:name":"Raiffeisenbank N\u00f6-S\u00fcd Alpin regGenmbH",
    "wof:placetype":"venue"
},
  "geometry": {"coordinates":[15.8923721313,47.6028823853],"type":"Point"}
}