{
  "type": "Feature",
  "properties": {
    "addr:full":"Kirschenweg 3/11 Biedermannsdorf Nieder\u00f6sterreich 2362",
    "addr:housenumber":"3 / 11",
    "addr:postcode":"2362",
    "addr:street":"Kirschenweg",
    "iso:country":"AT",
    "sg:address":"Kirschenweg 3/11",
    "sg:city":"Biedermannsdorf",
    "sg:orig_category":"Maler, Anstreicher U Lackierer",
    "sg:phone":"+43 2236 72202",
    "sg:postcode":"2362",
    "sg:province":"Nieder\u00f6sterreich",
    "wof:name":"Binder Peter",
    "wof:placetype":"venue"
},
  "geometry": {"coordinates":[16.3510398865,48.0848808289],"type":"Point"}
}