{
  "type": "Feature",
  "properties": {
    "addr:full":"Steinsch\u00fctzstrasse 1 Mautern Nieder\u00f6sterreich 3512",
    "addr:housenumber":"1",
    "addr:postcode":"3512",
    "addr:street":"Steinschuetzstrasse",
    "iso:country":"AT",
    "sg:address":"Steinsch\u00fctzstrasse 1",
    "sg:city":"Mautern",
    "sg:classifiers":[
        {
            "category":"Home & Garden",
            "subcategory":"Home Furnishings",
            "type":"Retail Goods"
        }
    ],
    "sg:phone":"+43 2732 855080",
    "sg:postcode":"3512",
    "sg:province":"Nieder\u00f6sterreich",
    "sg:tags":[
        "air-conditioners"
    ],
    "wof:name":"SLA Spenglerei L\u00fcftungs-, Klima- und Apparatebau Ges.m.b.H. & Co KG",
    "wof:placetype":"venue"
},
  "geometry": {"coordinates":[15.5512466431,48.3772163391],"type":"Point"}
}