{
  "type": "Feature",
  "properties": {
    "addr:full":"Saalbach 188 Saalbach Salzburg 5753",
    "addr:housenumber":"188",
    "addr:postcode":"5753",
    "addr:street":"Saalbach;Salzburg",
    "iso:country":"AT",
    "sg:address":"Saalbach 188",
    "sg:city":"Saalbach",
    "sg:classifiers":[
        {
            "category":"Home & Garden",
            "subcategory":"Building Materials",
            "type":"Retail Goods"
        }
    ],
    "sg:phone":"+43 6541 6645",
    "sg:postcode":"5753",
    "sg:province":"Salzburg",
    "sg:tags":[
        "steel",
        "balcony"
    ],
    "wof:name":"Moser GesmbH",
    "wof:placetype":"venue"
},
  "geometry": {"coordinates":[12.6301107407,47.390586853],"type":"Point"}
}