{
  "type": "Feature",
  "properties": {
    "addr:full":"Linzer Str 10 Eferding Ober\u00f6sterreich 4070",
    "addr:housenumber":"10",
    "addr:postcode":"4070",
    "addr:street":"Linzer Str",
    "iso:country":"AT",
    "sg:address":"Linzer Str 10",
    "sg:city":"Eferding",
    "sg:orig_category":"Lebensmittel / Einzelhandel",
    "sg:phone":"+43 7272 5580",
    "sg:postcode":"4070",
    "sg:province":"Ober\u00f6sterreich",
    "wof:name":"Billa AG",
    "wof:placetype":"venue"
},
  "geometry": {"coordinates":[14.0267925262,48.3045005798],"type":"Point"}
}