{
  "type": "Feature",
  "properties": {
    "addr:full":"St. Georgner Str 19 Oberndorf Salzburg 5110",
    "addr:postcode":"5110",
    "addr:street":"Str 19",
    "iso:country":"AT",
    "sg:address":"St. Georgner Str 19",
    "sg:city":"Oberndorf",
    "sg:orig_category":"Installationsunternehmen",
    "sg:phone":"+43 4362 726373",
    "sg:postcode":"5110",
    "sg:province":"Salzburg",
    "wof:name":"Mangelberger Martin GmbH",
    "wof:placetype":"venue"
},
  "geometry": {"coordinates":[12.936961174,47.9503898621],"type":"Point"}
}