{
  "type": "Feature",
  "properties": {
    "addr:full":"Akazieng 31 Apetlon Burgenland 7143",
    "addr:housenumber":"31",
    "addr:postcode":"7143",
    "addr:street":"Akazieng",
    "iso:country":"AT",
    "sg:address":"Akazieng 31",
    "sg:city":"Apetlon",
    "sg:orig_category":"Appartements / Ferienwohnungen",
    "sg:phone":"+43 2175 3088",
    "sg:postcode":"7143",
    "sg:province":"Burgenland",
    "wof:name":"H\u00e4mmerle Herbert",
    "wof:placetype":"venue"
},
  "geometry": {"coordinates":[16.8400325775,47.7418823242],"type":"Point"}
}