{
  "type": "Feature",
  "properties": {
    "addr:full":"Reichsratstr. 17 Wien Wien 1010",
    "addr:housenumber":"17",
    "addr:postcode":"1010",
    "addr:street":"Reichsratstr.",
    "iso:country":"AT",
    "sg:address":"Reichsratstr. 17",
    "sg:city":"Wien",
    "sg:classifiers":[
        {
            "category":"Banks & Credit Unions",
            "subcategory":"Bank",
            "type":"Services"
        }
    ],
    "sg:phone":"+43 4315 3131",
    "sg:postcode":"1010",
    "sg:province":"Wien",
    "sg:tags":[
        "banking",
        "institution"
    ],
    "wof:name":"BACA VERSICHERUNGSDIENST",
    "wof:placetype":"venue"
},
  "geometry": {"coordinates":[16.3589878082,48.2139053345],"type":"Point"}
}