{
  "type": "Feature",
  "properties": {
    "iso:country":"AT",
    "sg:address":"Bahnhofstr 3",
    "sg:city":"Spittal an der Drau",
    "sg:classifiers":[
        {
            "category":"Shopping",
            "subcategory":"Thrift Store",
            "type":"Retail Goods"
        }
    ],
    "sg:phone":"+43 4347 624085",
    "sg:postcode":"9800",
    "sg:province":"K\u00e4rnten",
    "sg:tags":[
        "second-hand-shops"
    ],
    "wof:name":"H\u00e4nsel u Gretel - Second-Hand-Exclusiv",
    "wof:placetype":"venue"
},
  "geometry": {"coordinates":[13.4915504456,46.7974815369],"type":"Point"}
}