{
  "type": "Feature",
  "properties": {
    "addr:full":"Hoch Imst 6 Imst Tirol 6460",
    "addr:housenumber":"6",
    "addr:postcode":"6460",
    "addr:street":"Imst Tirol",
    "iso:country":"AT",
    "sg:address":"Hoch Imst 6",
    "sg:city":"Imst",
    "sg:orig_category":"Pensionen / Privatzimmer",
    "sg:phone":"+43 5412 65496",
    "sg:postcode":"6460",
    "sg:province":"Tirol",
    "wof:name":"Chalet Just Ferienhaus",
    "wof:placetype":"venue"
},
  "geometry": {"coordinates":[10.7238712311,47.2416381836],"type":"Point"}
}