{
  "type": "Feature",
  "properties": {
    "addr:full":"Prager Str 4 Wien Wien 1210",
    "addr:housenumber":"4",
    "addr:postcode":"1210",
    "addr:street":"Str",
    "iso:country":"AT",
    "sg:address":"Prager Str 4",
    "sg:city":"Wien",
    "sg:orig_category":"Bierlokale-Pubs",
    "sg:phone":"+43 4369 917731776",
    "sg:postcode":"1210",
    "sg:province":"Wien",
    "wof:name":"Spitzweg Pub",
    "wof:placetype":"venue"
},
  "geometry": {"coordinates":[16.3965644836,48.2589988708],"type":"Point"}
}