{
  "type": "Feature",
  "properties": {
    "addr:full":"Schulstr 10 Molln Ober\u00f6sterreich 4591",
    "addr:housenumber":"10",
    "addr:postcode":"4591",
    "addr:street":"Schulstr",
    "iso:country":"AT",
    "sg:address":"Schulstr 10",
    "sg:city":"Molln",
    "sg:orig_category":"Volksschulen",
    "sg:phone":"+43 4375 8424120",
    "sg:postcode":"4591",
    "sg:province":"Ober\u00f6sterreich",
    "wof:name":"Volksschule",
    "wof:placetype":"venue"
},
  "geometry": {"coordinates":[14.2553443909,47.8865013123],"type":"Point"}
}