{
  "type": "Feature",
  "properties": {
    "iso:country":"AT",
    "sg:address":"Nr 26",
    "sg:city":"Trins",
    "sg:orig_category":"Pensionen / Privatzimmer",
    "sg:phone":"+43 5275 5338",
    "sg:postcode":"6152",
    "sg:province":"Tirol",
    "wof:name":"Hilber Franziska",
    "wof:placetype":"venue"
},
  "geometry": {"coordinates":[11.4166841507,47.0829467773],"type":"Point"}
}