{
  "type": "Feature",
  "properties": {
    "iso:country":"AT",
    "sg:address":"Bahnhofstr 106",
    "sg:city":"Saalfelden am Steinernen Meer",
    "sg:classifiers":[
        {
            "category":"Taxi",
            "type":"Transportation"
        }
    ],
    "sg:phone":"+43 4365 8271713",
    "sg:postcode":"5760",
    "sg:province":"Salzburg",
    "sg:tags":[
        "personentransporte",
        "u"
    ],
    "wof:name":"BAHNHOFTAXI",
    "wof:placetype":"venue"
},
  "geometry": {"coordinates":[12.8305635452,47.4265518188],"type":"Point"}
}