{
  "type": "Feature",
  "properties": {
    "addr:full":"Tischlerstr 13 Traun Ober\u00f6sterreich 4050",
    "addr:housenumber":"13",
    "addr:postcode":"4050",
    "addr:street":"Tischlerstr",
    "iso:country":"AT",
    "sg:address":"Tischlerstr 13",
    "sg:city":"Traun",
    "sg:orig_category":"Beratungsstellen",
    "sg:phone":"+43 7229 51574",
    "sg:postcode":"4050",
    "sg:province":"Ober\u00f6sterreich",
    "wof:name":"Pro mente Ober\u00f6sterreich - PSB Traun",
    "wof:placetype":"venue"
},
  "geometry": {"coordinates":[14.2414627075,48.2221641541],"type":"Point"}
}