{
  "type": "Feature",
  "properties": {
    "addr:full":"Nr 36 Teufenbach Steiermark 8833",
    "addr:postcode":"8833",
    "addr:street":"Nr 36",
    "iso:country":"AT",
    "sg:address":"Nr 36",
    "sg:city":"Teufenbach",
    "sg:orig_category":"Tischlereien",
    "sg:phone":"+43 3582 25490",
    "sg:postcode":"8833",
    "sg:province":"Steiermark",
    "wof:name":"Tischlerei Petautschnig GmbH",
    "wof:placetype":"venue"
},
  "geometry": {"coordinates":[14.3591108322,47.1285476685],"type":"Point"}
}