{
  "type": "Feature",
  "properties": {
    "addr:full":"Nr 39 Pfaffenschlag Nieder\u00f6sterreich 3834",
    "addr:postcode":"3834",
    "addr:street":"Nr;Pfaffenschlag",
    "iso:country":"AT",
    "sg:address":"Nr 39",
    "sg:city":"Pfaffenschlag",
    "sg:orig_category":"Lebensmittel / Einzelhandel",
    "sg:phone":"+43 4328 485091",
    "sg:postcode":"3834",
    "sg:province":"Nieder\u00f6sterreich",
    "wof:name":"Pilz' Ignaz S\u00f6hne GesmbH",
    "wof:placetype":"venue"
},
  "geometry": {"coordinates":[15.1466197968,48.8139076233],"type":"Point"}
}