{
  "type": "Feature",
  "properties": {
    "addr:full":"Wolfgang-Pauli-Gasse 5 Wien Wien 1140",
    "addr:housenumber":"5",
    "addr:postcode":"1140",
    "addr:street":"Wolfgang-Pauli-Gasse",
    "iso:country":"AT",
    "sg:address":"Wolfgang-Pauli-Gasse 5",
    "sg:city":"Wien",
    "sg:classifiers":[
        {
            "category":"Home & Garden",
            "subcategory":"Household Appliances",
            "type":"Retail Goods"
        }
    ],
    "sg:phone":"+43 1 970180",
    "sg:postcode":"1140",
    "sg:province":"Wien",
    "sg:tags":[
        "sanitary",
        "fitting"
    ],
    "sg:website":"swiag.at",
    "wof:name":"Swiag Sanit\u00e4rarmaturen GmbH",
    "wof:placetype":"venue"
},
  "geometry": {"coordinates":[16.2159557343,48.2074699402],"type":"Point"}
}