{
  "type": "Feature",
  "properties": {
    "addr:full":"Niederhofstr 23 Wien Wien 1120",
    "addr:housenumber":"23",
    "addr:postcode":"1120",
    "addr:street":"Niederhofstr",
    "iso:country":"AT",
    "sg:address":"Niederhofstr 23",
    "sg:city":"Wien",
    "sg:orig_category":"Friseure U Frisiersalons",
    "sg:phone":"+43 4318 131715",
    "sg:postcode":"1120",
    "sg:province":"Wien",
    "wof:name":"Intercoiffeur Strassl",
    "wof:placetype":"venue"
},
  "geometry": {"coordinates":[16.3315620422,48.1811637878],"type":"Point"}
}