{
  "type": "Feature",
  "properties": {
    "addr:full":"Ottogasse 1 Leopoldsdorf Nieder\u00f6sterreich 2333",
    "addr:housenumber":"1",
    "addr:postcode":"2333",
    "addr:street":"Ottogasse",
    "iso:country":"AT",
    "sg:address":"Ottogasse 1",
    "sg:city":"Leopoldsdorf",
    "sg:classifiers":[
        {
            "category":"Structure",
            "subcategory":"Tunnel",
            "type":"Public Place"
        }
    ],
    "sg:phone":"+43 2235 47712",
    "sg:postcode":"2333",
    "sg:province":"Nieder\u00f6sterreich",
    "sg:tags":[
        "canopy",
        "system"
    ],
    "wof:name":"Walter Dobmeier",
    "wof:placetype":"venue"
},
  "geometry": {"coordinates":[16.409828186,48.1077423096],"type":"Point"}
}