{
  "type": "Feature",
  "properties": {
    "addr:full":"Schulg 23 Reichenau an der Rax Nieder\u00f6sterreich 2651",
    "addr:housenumber":"23",
    "addr:postcode":"2651",
    "addr:street":"Schulg",
    "iso:country":"AT",
    "sg:address":"Schulg 23",
    "sg:city":"Reichenau an der Rax",
    "sg:orig_category":"Volksschulen",
    "sg:phone":"+43 4326 6652235",
    "sg:postcode":"2651",
    "sg:province":"Nieder\u00f6sterreich",
    "wof:name":"Volksschule",
    "wof:placetype":"venue"
},
  "geometry": {"coordinates":[15.8380889893,47.6962471008],"type":"Point"}
}