{
  "type": "Feature",
  "properties": {
    "addr:full":"Klingenbach Burgenland 7013",
    "addr:postcode":"7013",
    "iso:country":"AT",
    "sg:city":"Klingenbach",
    "sg:orig_category":"Wechselstuben",
    "sg:phone":"+43 4326 8748198",
    "sg:postcode":"7013",
    "sg:province":"Burgenland",
    "wof:name":"\u00f6AMTC Grenzstation",
    "wof:placetype":"venue"
},
  "geometry": {"coordinates":[16.5406951904,47.7519836426],"type":"Point"}
}