{
  "type": "Feature",
  "properties": {
    "addr:full":"Ludwig-Binder-Str 13 Gleisdorf Steiermark 8200",
    "addr:housenumber":"13",
    "addr:postcode":"8200",
    "addr:street":"Ludwig-Binder-Str",
    "iso:country":"AT",
    "sg:address":"Ludwig-Binder-Str 13",
    "sg:city":"Gleisdorf",
    "sg:orig_category":"Immobilienmakler",
    "sg:phone":"+43 3112 66930",
    "sg:postcode":"8200",
    "sg:province":"Steiermark",
    "sg:website":"trausner.at",
    "wof:name":"Trausner Brigitte Mag",
    "wof:placetype":"venue"
},
  "geometry": {"coordinates":[15.7068510056,47.1058273315],"type":"Point"}
}