{
  "type": "Feature",
  "properties": {
    "addr:full":"Diesterwegg 29/3 Wien Wien 1140",
    "addr:housenumber":"29 / 3",
    "addr:postcode":"1140",
    "addr:street":"Diesterwegg",
    "iso:country":"AT",
    "sg:address":"Diesterwegg 29/3",
    "sg:city":"Wien",
    "sg:orig_category":"Unternehmensberatung",
    "sg:phone":"+43 1 8922881",
    "sg:postcode":"1140",
    "sg:province":"Wien",
    "wof:name":"Auer Karl Dkfm Dr",
    "wof:placetype":"venue"
},
  "geometry": {"coordinates":[16.3054828644,48.1913337708],"type":"Point"}
}