{
  "type": "Feature",
  "properties": {
    "addr:full":"Linseng 74 Klagenfurt K\u00e4rnten 9020",
    "addr:housenumber":"74",
    "addr:postcode":"9020",
    "addr:street":"Linseng;Kaernten",
    "iso:country":"AT",
    "sg:address":"Linseng 74",
    "sg:city":"Klagenfurt",
    "sg:orig_category":"Elektronik",
    "sg:phone":"+43 699 11997687",
    "sg:postcode":"9020",
    "sg:province":"K\u00e4rnten",
    "wof:name":"Muri Martin",
    "wof:placetype":"venue"
},
  "geometry": {"coordinates":[14.2910060883,46.6232414246],"type":"Point"}
}