{
  "type": "Feature",
  "properties": {
    "iso:country":"AT",
    "sg:address":"Tsch\u00f6raner Weg 17",
    "sg:city":"Bodensdorf",
    "sg:orig_category":"Appartements / Ferienwohnungen",
    "sg:phone":"+43 4243 2145",
    "sg:postcode":"9551",
    "sg:province":"K\u00e4rnten",
    "wof:name":"Posarnig Sonja",
    "wof:placetype":"venue"
},
  "geometry": {"coordinates":[13.9662208557,46.6816902161],"type":"Point"}
}