{
  "type": "Feature",
  "properties": {
    "addr:full":"Sigmund Haffner-G 14 Salzburg Salzburg 5020",
    "addr:housenumber":"14",
    "addr:postcode":"5020",
    "addr:street":"Salzburg",
    "iso:country":"AT",
    "sg:address":"Sigmund Haffner-G 14",
    "sg:city":"Salzburg",
    "sg:orig_category":"Glasgraveure U -\u00c3\u201etzereien",
    "sg:phone":"+43 662 841323",
    "sg:postcode":"5020",
    "sg:province":"Salzburg",
    "wof:name":"Handwerkskunst in Glas",
    "wof:placetype":"venue"
},
  "geometry": {"coordinates":[13.043800354,47.7988815308],"type":"Point"}
}