{
  "type": "Feature",
  "properties": {
    "iso:country":"AT",
    "sg:address":"Fischbachg 41",
    "sg:city":"Dornbirn",
    "sg:orig_category":"Garten- U Landschaftsgestaltung",
    "sg:phone":"+43 5572 22334",
    "sg:postcode":"6850",
    "sg:province":"Vorarlberg",
    "wof:name":"Rein Markus",
    "wof:placetype":"venue"
},
  "geometry": {"coordinates":[9.7448501587,47.4245605469],"type":"Point"}
}