{
  "type": "Feature",
  "properties": {
    "addr:full":"Nr 135 Kukmirn Burgenland 7543",
    "addr:postcode":"7543",
    "addr:street":"Nr 135",
    "iso:country":"AT",
    "sg:address":"Nr 135",
    "sg:city":"Kukmirn",
    "sg:orig_category":"Spirituosen / Erzeugung U Gro\u00c3\u0178handel",
    "sg:phone":"+43 3328 32081",
    "sg:postcode":"7543",
    "sg:province":"Burgenland",
    "wof:name":"Obstgarten Nikles - Nikles Julius und Helene",
    "wof:placetype":"venue"
},
  "geometry": {"coordinates":[16.2055358887,47.072227478],"type":"Point"}
}