{
  "type": "Feature",
  "properties": {
    "addr:full":"Zentrum 18 Kramsach Tirol 6233",
    "addr:housenumber":"18",
    "addr:postcode":"6233",
    "addr:street":"Zentrum;Tirol",
    "iso:country":"AT",
    "sg:address":"Zentrum 18",
    "sg:city":"Kramsach",
    "sg:orig_category":"Lebensmittel / Erzeugung U Gro\u00c3\u0178handel",
    "sg:phone":"+43 4353 3762315",
    "sg:postcode":"6233",
    "sg:province":"Tirol",
    "wof:name":"Duftner Vinzenz KG",
    "wof:placetype":"venue"
},
  "geometry": {"coordinates":[11.883649826,47.4480018616],"type":"Point"}
}