{
  "type": "Feature",
  "properties": {
    "addr:full":"Erlastr 5 St. Pantaleon Nieder\u00f6sterreich 4303",
    "addr:housenumber":"5",
    "addr:postcode":"4303",
    "addr:street":"Erlastr",
    "iso:country":"AT",
    "sg:address":"Erlastr 5",
    "sg:city":"St. Pantaleon",
    "sg:orig_category":"Erdarbeiten",
    "sg:phone":"+43 7435 7582",
    "sg:postcode":"4303",
    "sg:province":"Nieder\u00f6sterreich",
    "wof:name":"Zeiser Franz - Gr\u00fcnfl\u00e4chenpflege - biologische \u00f6lbeseitigungmittel - Transporte",
    "wof:placetype":"venue"
},
  "geometry": {"coordinates":[14.5711803436,48.2075805664],"type":"Point"}
}