{
  "type": "Feature",
  "properties": {
    "addr:full":"Zlaner Str 9 Zlan K\u00e4rnten 9713",
    "addr:housenumber":"9",
    "addr:postcode":"9713",
    "addr:street":"Str;Kaernten",
    "iso:country":"AT",
    "sg:address":"Zlaner Str 9",
    "sg:city":"Zlan",
    "sg:orig_category":"Psychotherapie",
    "sg:phone":"+43 4761 761",
    "sg:postcode":"9713",
    "sg:province":"K\u00e4rnten",
    "wof:name":"Kelz Friederun",
    "wof:placetype":"venue"
},
  "geometry": {"coordinates":[13.5828104019,46.7292709351],"type":"Point"}
}