{
  "type": "Feature",
  "properties": {
    "addr:full":"Schafwiesenstr. 56 Wels Ober\u00f6sterreich 4600",
    "addr:housenumber":"56",
    "addr:postcode":"4600",
    "addr:street":"Schafwiesenstr.;Oberoesterreich",
    "iso:country":"AT",
    "sg:address":"Schafwiesenstr. 56",
    "sg:city":"Wels",
    "sg:classifiers":[
        {
            "category":"Manufacturing",
            "subcategory":"Metals",
            "type":"Manufacturing & Wholesale Goods"
        }
    ],
    "sg:phone":"+43 4372 42293830",
    "sg:postcode":"4600",
    "sg:province":"Ober\u00f6sterreich",
    "sg:tags":[
        "processing"
    ],
    "wof:name":"R\u00dcBIG GESMBH & CO KG",
    "wof:placetype":"venue"
},
  "geometry": {"coordinates":[14.064034462,48.1682548523],"type":"Point"}
}