{
  "type": "Feature",
  "properties": {
    "iso:country":"AT",
    "sg:address":"Leithener Wiesenweg 67",
    "sg:city":"Reith",
    "sg:orig_category":"Hausbetreuung",
    "sg:phone":"+43 5212 4479",
    "sg:postcode":"6103",
    "sg:province":"Tirol",
    "wof:name":"Hausmeisterservice Linder & Huber GmbH",
    "wof:placetype":"venue"
},
  "geometry": {"coordinates":[11.2177648544,47.2896614075],"type":"Point"}
}