{
  "type": "Feature",
  "properties": {
    "iso:country":"AT",
    "sg:address":"Sch\u00f6nfeld Kieswerkstrasse 1 T",
    "sg:city":"Lassee",
    "sg:classifiers":[
        {
            "category":"Home & Garden",
            "subcategory":"Building Materials",
            "type":"Retail Goods"
        }
    ],
    "sg:phone":"+43 2213 2953",
    "sg:postcode":"2291",
    "sg:province":"Nieder\u00f6sterreich",
    "sg:tags":[
        "gravel",
        "crushed"
    ],
    "wof:name":"Johannes Riedm\u00fcller",
    "wof:placetype":"venue"
},
  "geometry": {"coordinates":[16.8226032257,48.2252693176],"type":"Point"}
}