{
  "type": "Feature",
  "properties": {
    "addr:full":"Markt 25 St. Marein Steiermark 8323",
    "addr:housenumber":"25",
    "addr:postcode":"8323",
    "addr:street":"Markt",
    "iso:country":"AT",
    "sg:address":"Markt 25",
    "sg:city":"St. Marein",
    "sg:orig_category":"Filmproduktionen",
    "sg:phone":"+43 4331 192214",
    "sg:postcode":"8323",
    "sg:province":"Steiermark",
    "wof:name":"Stanger Helmut",
    "wof:placetype":"venue"
},
  "geometry": {"coordinates":[15.6871728897,47.0162887573],"type":"Point"}
}