{
  "type": "Feature",
  "properties": {
    "addr:full":"Lilienthalstr 10 Klagenfurt K\u00e4rnten 9020",
    "addr:housenumber":"10",
    "addr:postcode":"9020",
    "addr:street":"Lilienthalstr;Kaernten",
    "iso:country":"AT",
    "sg:address":"Lilienthalstr 10",
    "sg:city":"Klagenfurt",
    "sg:orig_category":"Massagen",
    "sg:phone":"+43 676 7318562",
    "sg:postcode":"9020",
    "sg:province":"K\u00e4rnten",
    "wof:name":"Massagepraxis Maier Johann",
    "wof:placetype":"venue"
},
  "geometry": {"coordinates":[14.2732496262,46.6186408997],"type":"Point"}
}