{
  "type": "Feature",
  "properties": {
    "addr:full":"Schrederg 4 Klosterneuburg Nieder\u00f6sterreich 3400",
    "addr:housenumber":"4",
    "addr:postcode":"3400",
    "addr:street":"Schrederg;Niederoesterreich",
    "iso:country":"AT",
    "sg:address":"Schrederg 4",
    "sg:city":"Klosterneuburg",
    "sg:orig_category":"Zelte / Vermietung",
    "sg:phone":"+43 664 2124333",
    "sg:postcode":"3400",
    "sg:province":"Nieder\u00f6sterreich",
    "wof:name":"Tom's Zeltverleih",
    "wof:placetype":"venue"
},
  "geometry": {"coordinates":[16.3113861084,48.3170661926],"type":"Point"}
}