{
  "type": "Feature",
  "properties": {
    "addr:full":"Josef-Porsch-Str 33 Obersiebenbrunn Nieder\u00f6sterreich 2283",
    "addr:housenumber":"33",
    "addr:postcode":"2283",
    "addr:street":"Josef-Porsch-Str",
    "iso:country":"AT",
    "sg:address":"Josef-Porsch-Str 33",
    "sg:city":"Obersiebenbrunn",
    "sg:orig_category":"Friseure U Frisiersalons",
    "sg:phone":"+43 4322 862607",
    "sg:postcode":"2283",
    "sg:province":"Nieder\u00f6sterreich",
    "wof:name":"Anders Michael",
    "wof:placetype":"venue"
},
  "geometry": {"coordinates":[16.7029628754,48.2638473511],"type":"Point"}
}