{
  "type": "Feature",
  "properties": {
    "addr:full":"Pregartfeld 13 Pregarten Ober\u00f6sterreich 4230",
    "addr:housenumber":"13",
    "addr:postcode":"4230",
    "addr:street":"Pregartfeld",
    "iso:country":"AT",
    "sg:address":"Pregartfeld 13",
    "sg:city":"Pregarten",
    "sg:orig_category":"Hauptschulen",
    "sg:phone":"+43 7236 23950",
    "sg:postcode":"4230",
    "sg:province":"Ober\u00f6sterreich",
    "wof:name":"Hauptschule 2",
    "wof:placetype":"venue"
},
  "geometry": {"coordinates":[14.5318202972,48.3507270813],"type":"Point"}
}