{
  "type": "Feature",
  "properties": {
    "iso:country":"AT",
    "sg:address":"Fasaneriestrasse 35",
    "sg:city":"Salzburg",
    "sg:classifiers":[
        {
            "category":"Autos & Motor Vehicles",
            "subcategory":"Auto Supplies",
            "type":"Retail Goods"
        }
    ],
    "sg:phone":"+43 662 44780",
    "sg:postcode":"5020",
    "sg:province":"Salzburg",
    "sg:tags":[
        "automobile",
        "accessory"
    ],
    "sg:website":"mercedes-benz.at",
    "wof:name":"Mercedes-Benz \u00d6sterreich Vertriebsgesellschaft m.b.H.",
    "wof:placetype":"venue"
},
  "geometry": {"coordinates":[13.0284557343,47.8170471191],"type":"Point"}
}