{
  "type": "Feature",
  "properties": {
    "addr:full":"Herzog Bernhard-Pl 3 V\u00f6lkermarkt K\u00e4rnten 9100",
    "addr:housenumber":"3",
    "addr:postcode":"9100",
    "addr:street":"Bernhard-Pl;Kaernten",
    "iso:country":"AT",
    "sg:address":"Herzog Bernhard-Pl 3",
    "sg:city":"V\u00f6lkermarkt",
    "sg:orig_category":"Friseure U Frisiersalons",
    "sg:phone":"+43 4232 2081",
    "sg:postcode":"9100",
    "sg:province":"K\u00e4rnten",
    "wof:name":"Wriessnig Kurt",
    "wof:placetype":"venue"
},
  "geometry": {"coordinates":[12.9413795471,47.6610603333],"type":"Point"}
}