{
  "type": "Feature",
  "properties": {
    "addr:full":"Ahornweg 46 Imst Tirol 6460",
    "addr:housenumber":"46",
    "addr:postcode":"6460",
    "addr:street":"Ahornweg;Tirol",
    "iso:country":"AT",
    "sg:address":"Ahornweg 46",
    "sg:city":"Imst",
    "sg:orig_category":"Appartements / Ferienwohnungen",
    "sg:phone":"+43 5412 6901",
    "sg:postcode":"6460",
    "sg:province":"Tirol",
    "wof:name":"Landhaus Bander",
    "wof:placetype":"venue"
},
  "geometry": {"coordinates":[10.7453804016,47.2481384277],"type":"Point"}
}