{
  "type": "Feature",
  "properties": {
    "addr:full":"Etrichstr 40 Wien Wien 1110",
    "addr:housenumber":"40",
    "addr:postcode":"1110",
    "addr:street":"Etrichstr",
    "iso:country":"AT",
    "sg:address":"Etrichstr 40",
    "sg:city":"Wien",
    "sg:orig_category":"Pizzazustellungen",
    "sg:phone":"+43 1 86660",
    "sg:postcode":"1110",
    "sg:province":"Wien",
    "wof:name":"Pizzamann",
    "wof:placetype":"venue"
},
  "geometry": {"coordinates":[16.4640522003,48.1522674561],"type":"Point"}
}