{
  "type": "Feature",
  "properties": {
    "iso:country":"AT",
    "sg:address":"Salztorg 5-7",
    "sg:city":"Wien",
    "sg:orig_category":"Lederbekleidung",
    "sg:phone":"+43 1 5333366",
    "sg:postcode":"1010",
    "sg:province":"Wien",
    "wof:name":"Hofst\u00e4tter Pelze",
    "wof:placetype":"venue"
},
  "geometry": {"coordinates":[16.373292923,48.2136955261],"type":"Point"}
}