{
  "type": "Feature",
  "properties": {
    "iso:country":"AT",
    "sg:address":"Mitterstr 4",
    "sg:city":"Puntigam",
    "sg:orig_category":"Friseure U Frisiersalons",
    "sg:phone":"+43 316 293536",
    "sg:postcode":"8055",
    "sg:province":"Steiermark",
    "wof:name":"Friseur Brigitte",
    "wof:placetype":"venue"
},
  "geometry": {"coordinates":[15.432469368,47.0278587341],"type":"Point"}
}