{
  "type": "Feature",
  "properties": {
    "addr:full":"Ybbsstr 28 Amstetten Nieder\u00f6sterreich 3300",
    "addr:housenumber":"28",
    "addr:postcode":"3300",
    "addr:street":"Ybbsstr;Niederoesterreich",
    "iso:country":"AT",
    "sg:address":"Ybbsstr 28",
    "sg:city":"Amstetten",
    "sg:orig_category":"Farben U Lacke / Einzelhandel",
    "sg:phone":"+43 4374 7223859",
    "sg:postcode":"3300",
    "sg:province":"Nieder\u00f6sterreich",
    "wof:name":"FARBEN WAHL GmbH",
    "wof:placetype":"venue"
},
  "geometry": {"coordinates":[14.8706903458,48.1185112],"type":"Point"}
}