{
  "type": "Feature",
  "properties": {
    "addr:full":"Anton-Baumgartner-Str 40 Wien Wien 1230",
    "addr:housenumber":"40",
    "addr:postcode":"1230",
    "addr:street":"Anton-Baumgartner-Str",
    "iso:country":"AT",
    "sg:address":"Anton-Baumgartner-Str 40",
    "sg:city":"Wien",
    "sg:orig_category":"Friseure U Frisiersalons",
    "sg:phone":"+43 4316 628083",
    "sg:postcode":"1230",
    "sg:province":"Wien",
    "wof:name":"Intercoiffeur Strassl",
    "wof:placetype":"venue"
},
  "geometry": {"coordinates":[16.3187274933,48.1516876221],"type":"Point"}
}