{
  "type": "Feature",
  "properties": {
    "addr:full":"Stubaitalstr 66 Neustift im Stubaital Tirol 6167",
    "addr:housenumber":"66",
    "addr:postcode":"6167",
    "addr:street":"Stubaitalstr;Tirol",
    "iso:country":"AT",
    "sg:address":"Stubaitalstr 66",
    "sg:city":"Neustift im Stubaital",
    "sg:classifiers":[
        {
            "category":"Travel",
            "subcategory":"Hotels & Motels",
            "type":"Entertainment"
        }
    ],
    "sg:phone":"+43 4352 2626510",
    "sg:postcode":"6167",
    "sg:province":"Tirol",
    "wof:name":"Hotel Pension Maximilian",
    "wof:placetype":"venue"
},
  "geometry": {"coordinates":[11.3106660843,47.1130409241],"type":"Point"}
}