{
  "type": "Feature",
  "properties": {
    "addr:full":"Grazer G 10 Leibnitz Steiermark 8430",
    "addr:housenumber":"10",
    "addr:postcode":"8430",
    "addr:street":"Grazer G;Steiermark",
    "iso:country":"AT",
    "sg:address":"Grazer G 10",
    "sg:city":"Leibnitz",
    "sg:orig_category":"Textilwaren / Einzelhandel",
    "sg:phone":"+43 3452 72765",
    "sg:postcode":"8430",
    "sg:province":"Steiermark",
    "wof:name":"TPS",
    "wof:placetype":"venue"
},
  "geometry": {"coordinates":[15.5391254425,46.7828941345],"type":"Point"}
}