{
  "type": "Feature",
  "properties": {
    "addr:full":"Merianstr 39/IV/54 Salzburg Salzburg 5020",
    "addr:housenumber":"39 / iv / 54",
    "addr:postcode":"5020",
    "addr:street":"Merianstr;Salzburg",
    "iso:country":"AT",
    "sg:address":"Merianstr 39/IV/54",
    "sg:city":"Salzburg",
    "sg:orig_category":"Bodenverlegung",
    "sg:phone":"+43 662 880591",
    "sg:postcode":"5020",
    "sg:province":"Salzburg",
    "wof:name":"Wiesinger Rudolf",
    "wof:placetype":"venue"
},
  "geometry": {"coordinates":[13.0433769226,47.8006744385],"type":"Point"}
}