{
  "type": "Feature",
  "properties": {
    "addr:full":"Nr 13 Stadl an der Mur Steiermark 8862",
    "addr:postcode":"8862",
    "addr:street":"Nr;An Der Mur Steiermark",
    "iso:country":"AT",
    "sg:address":"Nr 13",
    "sg:city":"Stadl an der Mur",
    "sg:orig_category":"Forstverwaltungen",
    "sg:phone":"+43 3534 22010",
    "sg:postcode":"8862",
    "sg:province":"Steiermark",
    "wof:name":"Schwarzenbergsche Forstverwaltung Paal",
    "wof:placetype":"venue"
},
  "geometry": {"coordinates":[14.0248670578,47.111530304],"type":"Point"}
}