{
  "type": "Feature",
  "properties": {
    "addr:full":"Gudrunstrasse 161 Wien Wien 1100",
    "addr:housenumber":"161",
    "addr:postcode":"1100",
    "addr:street":"Gudrunstrasse",
    "iso:country":"AT",
    "sg:address":"Gudrunstrasse 161",
    "sg:city":"Wien",
    "sg:classifiers":[
        {
            "category":"Home & Garden",
            "subcategory":"Home Furnishings",
            "type":"Retail Goods"
        }
    ],
    "sg:phone":"+43 1 6042747",
    "sg:postcode":"1100",
    "sg:province":"Wien",
    "sg:tags":[
        "bathroom",
        "wc",
        "fitting"
    ],
    "wof:name":"Gawa Sanit\u00e4r- und Heizungsinstallationen Ges.m.b.H.",
    "wof:placetype":"venue"
},
  "geometry": {"coordinates":[16.3700141907,48.1784591675],"type":"Point"}
}