{
  "type": "Feature",
  "properties": {
    "addr:full":"Hauptpl 9 Aspang-Markt Nieder\u00f6sterreich 2870",
    "addr:housenumber":"9",
    "addr:postcode":"2870",
    "addr:street":"Hauptpl;Niederoesterreich",
    "iso:country":"AT",
    "sg:address":"Hauptpl 9",
    "sg:city":"Aspang-Markt",
    "sg:orig_category":"Textilwaren / Einzelhandel",
    "sg:phone":"+43 4326 4251291",
    "sg:postcode":"2870",
    "sg:province":"Nieder\u00f6sterreich",
    "wof:name":"NKD",
    "wof:placetype":"venue"
},
  "geometry": {"coordinates":[16.0907154083,47.5547943115],"type":"Point"}
}