{
  "type": "Feature",
  "properties": {
    "iso:country":"AT",
    "sg:address":"Parkstr 6",
    "sg:city":"F\u00fcrstenfeld",
    "sg:orig_category":"Lebensmittel / Einzelhandel",
    "sg:phone":"+43 4333 8254520",
    "sg:postcode":"8280",
    "sg:province":"Steiermark",
    "wof:name":"Supermarkt Knittelfelder",
    "wof:placetype":"venue"
},
  "geometry": {"coordinates":[9.1764993668,47.6480064392],"type":"Point"}
}