{
  "type": "Feature",
  "properties": {
    "addr:full":"Nr 2 Wolfern Ober\u00f6sterreich 4493",
    "addr:postcode":"4493",
    "addr:street":"Nr;Oberoesterreich",
    "iso:country":"AT",
    "sg:address":"Nr 2",
    "sg:city":"Wolfern",
    "sg:orig_category":"Banken U Sparkassen",
    "sg:phone":"+43 7253 82200",
    "sg:postcode":"4493",
    "sg:province":"Ober\u00f6sterreich",
    "wof:name":"Raiffeisenbank Wolfern regGenmbH",
    "wof:placetype":"venue"
},
  "geometry": {"coordinates":[14.3778066635,48.0832176208],"type":"Point"}
}