{
  "type": "Feature",
  "properties": {
    "iso:country":"AT",
    "sg:address":"Mauthfeld 1",
    "sg:city":"Kirchdorf in Tirol",
    "sg:orig_category":"Biologische Produkte",
    "sg:phone":"+43 4367 63340347",
    "sg:postcode":"6382",
    "sg:province":"Tirol",
    "wof:name":"Steiner Christian",
    "wof:placetype":"venue"
},
  "geometry": {"coordinates":[12.4421815872,47.5562019348],"type":"Point"}
}