{
  "type": "Feature",
  "properties": {
    "addr:full":"Goethestr 50 Linz Ober\u00f6sterreich 4020",
    "addr:housenumber":"50",
    "addr:postcode":"4020",
    "addr:street":"Goethestr",
    "iso:country":"AT",
    "sg:address":"Goethestr 50",
    "sg:city":"Linz",
    "sg:orig_category":"Orientteppiche",
    "sg:phone":"+43 732 612122",
    "sg:postcode":"4020",
    "sg:province":"Ober\u00f6sterreich",
    "wof:name":"Dawari Farhad Mag",
    "wof:placetype":"venue"
},
  "geometry": {"coordinates":[14.2991781235,48.2979316711],"type":"Point"}
}