{
  "type": "Feature",
  "properties": {
    "addr:full":"Bahnhofstr 33-35 Kalsdorf Steiermark 8401",
    "addr:postcode":"33-35;8401",
    "addr:street":"Bahnhofstr",
    "iso:country":"AT",
    "sg:address":"Bahnhofstr 33-35",
    "sg:city":"Kalsdorf",
    "sg:orig_category":"Tischlereien",
    "sg:phone":"+43 4331 3552531",
    "sg:postcode":"8401",
    "sg:province":"Steiermark",
    "wof:name":"Botschak Monika",
    "wof:placetype":"venue"
},
  "geometry": {"coordinates":[15.4728145599,46.9647636414],"type":"Point"}
}