{
  "type": "Feature",
  "properties": {
    "iso:country":"AT",
    "sg:address":"Nr 353",
    "sg:city":"Schruns",
    "sg:orig_category":"Hufschmiede",
    "sg:phone":"+43 5556 74207",
    "sg:postcode":"6780",
    "sg:province":"Vorarlberg",
    "wof:name":"Fitsch Emil",
    "wof:placetype":"venue"
},
  "geometry": {"coordinates":[9.9074554443,47.0924110413],"type":"Point"}
}