{
  "type": "Feature",
  "properties": {
    "addr:full":"Schubertg 2 Klosterneuburg Nieder\u00f6sterreich 3400",
    "addr:housenumber":"2",
    "addr:postcode":"3400",
    "addr:street":"Schubertg;Niederoesterreich",
    "iso:country":"AT",
    "sg:address":"Schubertg 2",
    "sg:city":"Klosterneuburg",
    "sg:orig_category":"Dolmetscher",
    "sg:phone":"+43 699 11749525",
    "sg:postcode":"3400",
    "sg:province":"Nieder\u00f6sterreich",
    "wof:name":"Dieberger-Jessajan Larissa - Dolmetscher Armenisch und Russisch",
    "wof:placetype":"venue"
},
  "geometry": {"coordinates":[16.3102416992,48.3205032349],"type":"Point"}
}