{
  "type": "Feature",
  "properties": {
    "iso:country":"AT",
    "sg:address":"Leopoldauer Str 24",
    "sg:city":"Wien",
    "sg:orig_category":"Appartements / Ferienwohnungen",
    "sg:phone":"+43 664 2426630",
    "sg:postcode":"1210",
    "sg:province":"Wien",
    "sg:website":"apartment.at",
    "wof:name":"Appartements in Wien",
    "wof:placetype":"venue"
},
  "geometry": {"coordinates":[16.4079856873,48.2583198547],"type":"Point"}
}