{
  "type": "Feature",
  "properties": {
    "addr:full":"Waltend Hauptstr 5 Graz Steiermark 8010",
    "addr:housenumber":"5",
    "addr:postcode":"8010",
    "addr:street":"Hauptstr",
    "iso:country":"AT",
    "sg:address":"Waltend Hauptstr 5",
    "sg:city":"Graz",
    "sg:orig_category":"Versicherungsunternehmen",
    "sg:phone":"+43 316 4621210",
    "sg:postcode":"8010",
    "sg:province":"Steiermark",
    "wof:name":"Interunfall Versicherung-AG",
    "wof:placetype":"venue"
},
  "geometry": {"coordinates":[15.4651460648,47.065372467],"type":"Point"}
}