{
  "type": "Feature",
  "properties": {
    "iso:country":"AT",
    "sg:address":"Nr 48",
    "sg:city":"P\u00f6llau",
    "sg:orig_category":"Diskotheken",
    "sg:phone":"+43 3335 2612",
    "sg:postcode":"8225",
    "sg:province":"Steiermark",
    "wof:name":"Tanzlokal Grottenst\u00fcberl",
    "wof:placetype":"venue"
},
  "geometry": {"coordinates":[15.8337945938,47.301990509],"type":"Point"}
}