{
  "type": "Feature",
  "properties": {
    "addr:full":"Steyrer Str 1 St. Peter in der Au Nieder\u00f6sterreich 3352",
    "addr:housenumber":"1",
    "addr:postcode":"3352",
    "addr:street":"Str",
    "iso:country":"AT",
    "sg:address":"Steyrer Str 1",
    "sg:city":"St. Peter in der Au",
    "sg:orig_category":"Friseure U Frisiersalons",
    "sg:phone":"+43 4374 7749043",
    "sg:postcode":"3352",
    "sg:province":"Nieder\u00f6sterreich",
    "wof:name":"Modefriseur Carolin Holzer",
    "wof:placetype":"venue"
},
  "geometry": {"coordinates":[14.6190900803,48.0450057983],"type":"Point"}
}