{
  "type": "Feature",
  "properties": {
    "addr:full":"Tannhausen 1 Weiz Steiermark 8160",
    "addr:housenumber":"1",
    "addr:postcode":"8160",
    "addr:street":"Tannhausen",
    "iso:country":"AT",
    "sg:address":"Tannhausen 1",
    "sg:city":"Weiz",
    "sg:classifiers":[
        {
            "category":"Utilities",
            "subcategory":"Cable",
            "type":"Services"
        }
    ],
    "sg:phone":"+43 3172 2728",
    "sg:postcode":"8160",
    "sg:province":"Steiermark",
    "sg:tags":[
        "forestry"
    ],
    "wof:name":"Gudenus'sche Forst- und Gutsverwaltung",
    "wof:placetype":"venue"
},
  "geometry": {"coordinates":[15.6215696335,47.2169532776],"type":"Point"}
}