{
  "type": "Feature",
  "properties": {
    "iso:country":"AT",
    "sg:address":"Kamptalstr 3",
    "sg:city":"Langenlois",
    "sg:orig_category":"Tourismusinformation U -Organisationen",
    "sg:phone":"+43 2734 20000",
    "sg:postcode":"3550",
    "sg:province":"Nieder\u00f6sterreich",
    "wof:name":"Tourismusservice & Vinothek GmbH",
    "wof:placetype":"venue"
},
  "geometry": {"coordinates":[15.6768302917,48.4742736816],"type":"Point"}
}