{
  "type": "Feature",
  "properties": {
    "addr:full":"Hammerschmiedstr 2 Waidhofen an der Ybbs Nieder\u00f6sterreich 3340",
    "addr:housenumber":"2",
    "addr:postcode":"3340",
    "addr:street":"Hammerschmiedstr",
    "iso:country":"AT",
    "sg:address":"Hammerschmiedstr 2",
    "sg:city":"Waidhofen an der Ybbs",
    "sg:orig_category":"Apotheken",
    "sg:phone":"+43 7442 555890",
    "sg:postcode":"3340",
    "sg:province":"Nieder\u00f6sterreich",
    "wof:name":"Ybbstal-Apotheke",
    "wof:placetype":"venue"
},
  "geometry": {"coordinates":[14.7915887833,47.949005127],"type":"Point"}
}