{
  "type": "Feature",
  "properties": {
    "addr:full":"Kummerg 7/9/2 Wien Wien 1210",
    "addr:housenumber":"7 / 9 / 2",
    "addr:postcode":"1210",
    "addr:street":"Kummerg",
    "iso:country":"AT",
    "sg:address":"Kummerg 7/9/2",
    "sg:city":"Wien",
    "sg:orig_category":"Tapezierer U Dekorateure",
    "sg:phone":"+43 4312 596260",
    "sg:postcode":"1210",
    "sg:province":"Wien",
    "wof:name":"WOHN&RAUMdesign",
    "wof:placetype":"venue"
},
  "geometry": {"coordinates":[16.3978404999,48.2579994202],"type":"Point"}
}