{
  "type": "Feature",
  "properties": {
    "addr:full":"Annaberg Salzburg 5524",
    "addr:postcode":"5524",
    "addr:street":"Annaberg",
    "iso:country":"AT",
    "sg:city":"Annaberg",
    "sg:orig_category":"Feuerwehren",
    "sg:phone":"+43 6463 8230",
    "sg:postcode":"5524",
    "sg:province":"Salzburg",
    "wof:name":"Feuerwehr Annaberg",
    "wof:placetype":"venue"
},
  "geometry": {"coordinates":[13.4312047958,47.513458252],"type":"Point"}
}