{
  "type": "Feature",
  "properties": {
    "addr:full":"Rablstr 16 Wels Ober\u00f6sterreich 4600",
    "addr:housenumber":"16",
    "addr:postcode":"4600",
    "addr:street":"Rablstr;Oberoesterreich",
    "iso:country":"AT",
    "sg:address":"Rablstr 16",
    "sg:city":"Wels",
    "sg:orig_category":"Selbsthilfegruppen",
    "sg:phone":"+43 7242 67154",
    "sg:postcode":"4600",
    "sg:province":"Ober\u00f6sterreich",
    "wof:name":"Von Mensch zu Mensch - Selbsthilfegruppe",
    "wof:placetype":"venue"
},
  "geometry": {"coordinates":[14.0231933594,48.1614074707],"type":"Point"}
}