{
  "type": "Feature",
  "properties": {
    "iso:country":"AT",
    "sg:address":"Pastorstr 32",
    "sg:city":"Wien",
    "sg:orig_category":"Lebensmittel / Erzeugung U Gro\u00c3\u0178handel",
    "sg:phone":"+43 4312 557354",
    "sg:postcode":"1210",
    "sg:province":"Wien",
    "wof:name":"B.A.F. Import-Export GmbH",
    "wof:placetype":"venue"
},
  "geometry": {"coordinates":[16.4437675476,48.2748451233],"type":"Point"}
}