{
  "type": "Feature",
  "properties": {
    "addr:full":"Seilerst\u00e4tte 2 Wien Wien 1010",
    "addr:housenumber":"2",
    "addr:postcode":"1010",
    "addr:street":"Seilerstaette",
    "iso:country":"AT",
    "sg:address":"Seilerst\u00e4tte 2",
    "sg:city":"Wien",
    "sg:orig_category":"Bars-Cafes",
    "sg:phone":"+43 4315 128508",
    "sg:postcode":"1010",
    "sg:province":"Wien",
    "wof:name":"CRISTALL - BAR",
    "wof:placetype":"venue"
},
  "geometry": {"coordinates":[16.3768959045,48.2063484192],"type":"Point"}
}