{
  "type": "Feature",
  "properties": {
    "addr:full":"Nestroystr 13 Eichgraben Nieder\u00f6sterreich 3032",
    "addr:housenumber":"13",
    "addr:postcode":"3032",
    "addr:street":"Nestroystr",
    "iso:country":"AT",
    "sg:address":"Nestroystr 13",
    "sg:city":"Eichgraben",
    "sg:classifiers":[
        {
            "category":"Internet Cafe",
            "subcategory":"None",
            "type":"Food & Drink"
        }
    ],
    "sg:phone":"+43 664 2526699",
    "sg:postcode":"3032",
    "sg:province":"Nieder\u00f6sterreich",
    "wof:name":"AustrianOnlines",
    "wof:placetype":"venue"
},
  "geometry": {"coordinates":[15.979839325,48.1734657288],"type":"Point"}
}