{
  "type": "Feature",
  "properties": {
    "addr:full":"Alpenblickstr 5 Leonding Ober\u00f6sterreich 4060",
    "addr:housenumber":"5",
    "addr:postcode":"4060",
    "addr:street":"Alpenblickstr",
    "iso:country":"AT",
    "sg:address":"Alpenblickstr 5",
    "sg:city":"Leonding",
    "sg:orig_category":"Steuerberatung",
    "sg:phone":"+43 732 676367",
    "sg:postcode":"4060",
    "sg:province":"Ober\u00f6sterreich",
    "wof:name":"Mihatsch Beate Mag",
    "wof:placetype":"venue"
},
  "geometry": {"coordinates":[14.2527227402,48.2839012146],"type":"Point"}
}