{
  "type": "Feature",
  "properties": {
    "addr:full":"Wieseng 12 Weiz Steiermark 8160",
    "addr:housenumber":"12",
    "addr:postcode":"8160",
    "addr:street":"Wieseng",
    "iso:country":"AT",
    "sg:address":"Wieseng 12",
    "sg:city":"Weiz",
    "sg:orig_category":"Webdesign",
    "sg:phone":"+43 3172 4930",
    "sg:postcode":"8160",
    "sg:province":"Steiermark",
    "wof:name":"inter@ctiveaustria",
    "wof:placetype":"venue"
},
  "geometry": {"coordinates":[15.6276359558,47.212272644],"type":"Point"}
}