{
  "type": "Feature",
  "properties": {
    "iso:country":"AT",
    "sg:address":"Friedhofstr 73",
    "sg:city":"Wels",
    "sg:orig_category":"Schlankheitsinstitute",
    "sg:phone":"+43 7242 50034",
    "sg:postcode":"4600",
    "sg:province":"Ober\u00f6sterreich",
    "wof:name":"Figur Aktiv Aichhorn Gertraud",
    "wof:placetype":"venue"
},
  "geometry": {"coordinates":[14.0378866196,48.1723060608],"type":"Point"}
}