{
  "type": "Feature",
  "properties": {
    "addr:full":"Babenbergerstr Wien Wien 1010",
    "addr:postcode":"1010",
    "iso:country":"AT",
    "sg:address":"Babenbergerstr",
    "sg:city":"Wien",
    "sg:orig_category":"Non-Classified Establishments",
    "sg:phone":"+43 1 5232355",
    "sg:postcode":"1010",
    "sg:province":"Wien",
    "wof:name":"TAXI-TEL Standplatztelefon Betriebs GmbH",
    "wof:placetype":"venue"
},
  "geometry": {"coordinates":[16.3623714447,48.2031936646],"type":"Point"}
}