{
  "type": "Feature",
  "properties": {
    "iso:country":"AT",
    "sg:address":"Sendnerg 22",
    "sg:city":"Schwechat",
    "sg:orig_category":"\u00c3\u201enderungsschneidereien",
    "sg:phone":"+43 1 7073707",
    "sg:postcode":"2320",
    "sg:province":"Nieder\u00f6sterreich",
    "wof:name":"\u00e4nderungsschneiderei Mary",
    "wof:placetype":"venue"
},
  "geometry": {"coordinates":[16.4783287048,48.1437835693],"type":"Point"}
}