{
  "type": "Feature",
  "properties": {
    "iso:country":"AT",
    "sg:address":"Brunnerweg 10",
    "sg:city":"Wetzelsdorf",
    "sg:orig_category":"Psychotherapie",
    "sg:phone":"+43 316 581566",
    "sg:postcode":"8052",
    "sg:province":"Steiermark",
    "wof:name":"Stigler-Utri Magdalena Mag",
    "wof:placetype":"venue"
},
  "geometry": {"coordinates":[15.3863649368,47.0601272583],"type":"Point"}
}