{
  "type": "Feature",
  "properties": {
    "addr:full":"Thie\u00dfenbach 37 Scharnstein Ober\u00f6sterreich 4644",
    "addr:housenumber":"37",
    "addr:postcode":"4644",
    "addr:street":"Thiessenbach",
    "iso:country":"AT",
    "sg:address":"Thie\u00dfenbach 37",
    "sg:city":"Scharnstein",
    "sg:orig_category":"Glasereien",
    "sg:phone":"+43 664 2344968",
    "sg:postcode":"4644",
    "sg:province":"Ober\u00f6sterreich",
    "wof:name":"Glaserei Holzinger KEG",
    "wof:placetype":"venue"
},
  "geometry": {"coordinates":[13.962269783,47.9045448303],"type":"Point"}
}