{
  "type": "Feature",
  "properties": {
    "iso:country":"AT",
    "sg:address":"Kapuzinerstr 84",
    "sg:city":"Linz",
    "sg:orig_category":"Zeitungen U Zeitschriften",
    "sg:phone":"+43 4373 276103944",
    "sg:postcode":"4020",
    "sg:province":"Ober\u00f6sterreich",
    "wof:name":"Kirchenzeitung d Di\u00f6zese Linz",
    "wof:placetype":"venue"
},
  "geometry": {"coordinates":[14.2753095627,48.2985572815],"type":"Point"}
}