{
  "type": "Feature",
  "properties": {
    "addr:full":"Halleiner Landesstrasse 75 Puch Salzburg 5412",
    "addr:housenumber":"75",
    "addr:postcode":"5412",
    "addr:street":"Halleiner Landesstrasse;Salzburg",
    "iso:country":"AT",
    "sg:address":"Halleiner Landesstrasse 75",
    "sg:city":"Puch",
    "sg:classifiers":[
        {
            "category":"Manufacturing",
            "subcategory":"Wood Products",
            "type":"Manufacturing & Wholesale Goods"
        }
    ],
    "sg:phone":"+43 6245 80742",
    "sg:postcode":"5412",
    "sg:province":"Salzburg",
    "sg:tags":[
        "made",
        "balcony"
    ],
    "wof:name":"Christian Wei\u00df",
    "wof:placetype":"venue"
},
  "geometry": {"coordinates":[13.0854091644,47.7434120178],"type":"Point"}
}