{
  "type": "Feature",
  "properties": {
    "iso:country":"AT",
    "sg:address":"Zeihenb\u00fchl 98",
    "sg:city":"Lingenau",
    "sg:orig_category":"Rettungsdienste",
    "sg:phone":"+43 664 4609048",
    "sg:postcode":"6951",
    "sg:province":"Vorarlberg",
    "wof:name":"\u00f6sterreichische Rettungshundebrigade Landesleiter Vorarlberg",
    "wof:placetype":"venue"
},
  "geometry": {"coordinates":[9.920044899,47.4501609802],"type":"Point"}
}