{
  "type": "Feature",
  "properties": {
    "addr:full":"Alser Str 20 Wien Wien 1090",
    "addr:postcode":"1090",
    "addr:street":"Str 20",
    "iso:country":"AT",
    "sg:address":"Alser Str 20",
    "sg:city":"Wien",
    "sg:orig_category":"Chemisch-Technische Produkte",
    "sg:phone":"+43 1 4052119",
    "sg:postcode":"1090",
    "sg:province":"Wien",
    "wof:name":"Tisza Bela Dipl-Ing & Co",
    "wof:placetype":"venue"
},
  "geometry": {"coordinates":[16.3486595154,48.215385437],"type":"Point"}
}