{
  "type": "Feature",
  "properties": {
    "addr:full":"Ges\u00e4usestr 3 Liezen Steiermark 8940",
    "addr:housenumber":"3",
    "addr:postcode":"8940",
    "addr:street":"Gesaeusestr",
    "iso:country":"AT",
    "sg:address":"Ges\u00e4usestr 3",
    "sg:city":"Liezen",
    "sg:orig_category":"Lebensmittel / Einzelhandel",
    "sg:phone":"+43 3612 23101",
    "sg:postcode":"8940",
    "sg:province":"Steiermark",
    "wof:name":"Hofer KG",
    "wof:placetype":"venue"
},
  "geometry": {"coordinates":[14.248298645,47.5611305237],"type":"Point"}
}