{
  "type": "Feature",
  "properties": {
    "addr:full":"Wilbinger 483 Bezau Vorarlberg 6870",
    "addr:housenumber":"483",
    "addr:postcode":"6870",
    "iso:country":"AT",
    "sg:address":"Wilbinger 483",
    "sg:city":"Bezau",
    "sg:orig_category":"Flugschulen",
    "sg:phone":"+43 5514 3177",
    "sg:postcode":"6870",
    "sg:province":"Vorarlberg",
    "wof:name":"Flugschule Bregenzerwald - Jodok Moosbrugger GmbH",
    "wof:placetype":"venue"
},
  "geometry": {"coordinates":[9.9022083282,47.3848991394],"type":"Point"}
}