{
  "type": "Feature",
  "properties": {
    "addr:full":"Angerweg 6 Rohrbach in Ober\u00f6sterreich Ober\u00f6sterreich 4150",
    "addr:housenumber":"6",
    "addr:postcode":"4150",
    "addr:street":"Angerweg",
    "iso:country":"AT",
    "sg:address":"Angerweg 6",
    "sg:city":"Rohrbach in Ober\u00f6sterreich",
    "sg:orig_category":"Beschriftungen",
    "sg:phone":"+43 4372 8920025",
    "sg:postcode":"4150",
    "sg:province":"Ober\u00f6sterreich",
    "wof:name":"Gierlinger Markus - MEX-beschriftet u malt",
    "wof:placetype":"venue"
},
  "geometry": {"coordinates":[13.9846143723,48.5823707581],"type":"Point"}
}