{
  "type": "Feature",
  "properties": {
    "addr:full":"Dr A Schneider-Str 36a Dornbirn Vorarlberg 6850",
    "addr:housenumber":"36a",
    "addr:postcode":"6850",
    "addr:street":"Dr;Schneider-Str",
    "iso:country":"AT",
    "sg:address":"Dr A Schneider-Str 36a",
    "sg:city":"Dornbirn",
    "sg:orig_category":"Sanatorien",
    "sg:phone":"+43 5572 24314",
    "sg:postcode":"6850",
    "sg:province":"Vorarlberg",
    "wof:name":"HNO-Station Dr Kofler",
    "wof:placetype":"venue"
},
  "geometry": {"coordinates":[9.7499513626,47.4234771729],"type":"Point"}
}