{
  "type": "Feature",
  "properties": {
    "addr:full":"Wiener Str 20 Wiener Neustadt Nieder\u00f6sterreich 2700",
    "addr:postcode":"2700",
    "addr:street":"20",
    "iso:country":"AT",
    "sg:address":"Wiener Str 20",
    "sg:city":"Wiener Neustadt",
    "sg:orig_category":"Damenmoden",
    "sg:phone":"+43 2622 225700",
    "sg:postcode":"2700",
    "sg:province":"Nieder\u00f6sterreich",
    "wof:name":"Schubert Moden",
    "wof:placetype":"venue"
},
  "geometry": {"coordinates":[16.2441082001,47.8146896362],"type":"Point"}
}