{
  "type": "Feature",
  "properties": {
    "addr:full":"Nr 1 Sch\u00f6nb\u00fchel an der Donau Nieder\u00f6sterreich 3392",
    "addr:postcode":"3392",
    "addr:street":"Nr;An Der Donau",
    "iso:country":"AT",
    "sg:address":"Nr 1",
    "sg:city":"Sch\u00f6nb\u00fchel an der Donau",
    "sg:orig_category":"Non-Classified Establishments",
    "sg:phone":"+43 2752 8243",
    "sg:postcode":"3392",
    "sg:province":"Nieder\u00f6sterreich",
    "wof:name":"Pfarramt",
    "wof:placetype":"venue"
},
  "geometry": {"coordinates":[15.3738088608,48.2575492859],"type":"Point"}
}