{
  "type": "Feature",
  "properties": {
    "addr:full":"Schulstra\u00dfe 69/1 Langenzersdorf Nieder\u00f6sterreich 2103",
    "addr:housenumber":"69 / 1",
    "addr:postcode":"2103",
    "addr:street":"Schulstrasse",
    "iso:country":"AT",
    "sg:address":"Schulstra\u00dfe 69/1",
    "sg:city":"Langenzersdorf",
    "sg:orig_category":"Industrie, Sonstige Industrieunternehmungen",
    "sg:phone":"+43 2244",
    "sg:postcode":"2103",
    "sg:province":"Nieder\u00f6sterreich",
    "sg:website":"http://www.infotex.at/",
    "wof:name":"INFOTEX",
    "wof:placetype":"venue"
},
  "geometry": {"coordinates":[16.3576049805,48.3094749451],"type":"Point"}
}