{
  "type": "Feature",
  "properties": {
    "iso:country":"AT",
    "sg:address":"Kircheng 1",
    "sg:city":"Bruck an der Leitha",
    "sg:orig_category":"Friseure U Frisiersalons",
    "sg:phone":"+43 4321 6263151",
    "sg:postcode":"2460",
    "sg:province":"Nieder\u00f6sterreich",
    "wof:name":"Papp Wolfgang",
    "wof:placetype":"venue"
},
  "geometry": {"coordinates":[16.7787590027,48.0246086121],"type":"Point"}
}