{
  "type": "Feature",
  "properties": {
    "addr:full":"Klosterneuburger Str 93-97 Wien Wien 1200",
    "addr:postcode":"93-97;1200",
    "addr:street":"Str",
    "iso:country":"AT",
    "sg:address":"Klosterneuburger Str 93-97",
    "sg:city":"Wien",
    "sg:orig_category":"Fu\u00c3\u0178pflege U Fu\u00c3\u0178pflegesalons",
    "sg:phone":"+43 1 3341188",
    "sg:postcode":"1200",
    "sg:province":"Wien",
    "wof:name":"Fu\u00dfpflege Regina im Brigittabad",
    "wof:placetype":"venue"
},
  "geometry": {"coordinates":[16.3653926849,48.2355003357],"type":"Point"}
}