{
  "type": "Feature",
  "properties": {
    "addr:full":"Packer Str 49 Edelschrott Steiermark 8583",
    "addr:housenumber":"49",
    "addr:postcode":"8583",
    "addr:street":"Str",
    "iso:country":"AT",
    "sg:address":"Packer Str 49",
    "sg:city":"Edelschrott",
    "sg:orig_category":"Spenglereien",
    "sg:phone":"+43 3145 80007",
    "sg:postcode":"8583",
    "sg:province":"Steiermark",
    "wof:name":"Spenglerei Schratter",
    "wof:placetype":"venue"
},
  "geometry": {"coordinates":[15.0517597198,47.0216178894],"type":"Point"}
}