{
  "type": "Feature",
  "properties": {
    "addr:full":"Parkstr 1 Ostermiething Ober\u00f6sterreich 5121",
    "addr:housenumber":"1",
    "addr:postcode":"5121",
    "addr:street":"Parkstr",
    "iso:country":"AT",
    "sg:address":"Parkstr 1",
    "sg:city":"Ostermiething",
    "sg:orig_category":"Lebensmittel / Einzelhandel",
    "sg:phone":"+43 6278 62530",
    "sg:postcode":"5121",
    "sg:province":"Ober\u00f6sterreich",
    "wof:name":"Scharinger I und H GesmbH",
    "wof:placetype":"venue"
},
  "geometry": {"coordinates":[12.8329343796,48.0424079895],"type":"Point"}
}