{
  "type": "Feature",
  "properties": {
    "addr:full":"Cervantesg 16 Wien Wien 1140",
    "addr:housenumber":"16",
    "addr:postcode":"1140",
    "addr:street":"Cervantesg",
    "iso:country":"AT",
    "sg:address":"Cervantesg 16",
    "sg:city":"Wien",
    "sg:orig_category":"Fu\u00c3\u0178pflege U Fu\u00c3\u0178pflegesalons",
    "sg:phone":"+43 4319 827037",
    "sg:postcode":"1140",
    "sg:province":"Wien",
    "wof:name":"Machan Wolfgang",
    "wof:placetype":"venue"
},
  "geometry": {"coordinates":[16.3082790375,48.1977005005],"type":"Point"}
}