{
  "type": "Feature",
  "properties": {
    "addr:full":"Zinnerstr 10 Waidhofen an der Thaya Nieder\u00f6sterreich 3830",
    "addr:housenumber":"10",
    "addr:postcode":"3830",
    "addr:street":"Zinnerstr",
    "iso:country":"AT",
    "sg:address":"Zinnerstr 10",
    "sg:city":"Waidhofen an der Thaya",
    "sg:orig_category":"Maschinenhandel",
    "sg:phone":"+43 4366 45151156",
    "sg:postcode":"3830",
    "sg:province":"Nieder\u00f6sterreich",
    "wof:name":"P\u00f6ppl Anton",
    "wof:placetype":"venue"
},
  "geometry": {"coordinates":[15.278011322,48.8110771179],"type":"Point"}
}