{
  "type": "Feature",
  "properties": {
    "addr:full":"Europapl 5 Attnang-Puchheim Ober\u00f6sterreich 4800",
    "addr:housenumber":"5",
    "addr:postcode":"4800",
    "addr:street":"Europapl",
    "iso:country":"AT",
    "sg:address":"Europapl 5",
    "sg:city":"Attnang-Puchheim",
    "sg:classifiers":[
        {
            "category":"Professional",
            "subcategory":"Computer Services",
            "type":"Services"
        }
    ],
    "sg:phone":"+43 4376 7465601",
    "sg:postcode":"4800",
    "sg:province":"Ober\u00f6sterreich",
    "sg:tags":[
        "software"
    ],
    "wof:name":"ISH-Industrielle Soft- u Hardware",
    "wof:placetype":"venue"
},
  "geometry": {"coordinates":[13.718621254,48.0084953308],"type":"Point"}
}