{
  "type": "Feature",
  "properties": {
    "iso:country":"AT",
    "sg:address":"Anton-Freunschlag-G 72",
    "sg:city":"Wien",
    "sg:orig_category":"Datenverarbeitung",
    "sg:phone":"+43 1 9822506",
    "sg:postcode":"1230",
    "sg:province":"Wien",
    "wof:name":"EMIG Datenverarbeitung GmbH",
    "wof:placetype":"venue"
},
  "geometry": {"coordinates":[16.3195323944,48.1293945312],"type":"Point"}
}