{
  "type": "Feature",
  "properties": {
    "addr:full":"Waldrain 7 Haiming Tirol 6425",
    "addr:housenumber":"7",
    "addr:postcode":"6425",
    "addr:street":"Waldrain;Tirol",
    "iso:country":"AT",
    "sg:address":"Waldrain 7",
    "sg:city":"Haiming",
    "sg:orig_category":"Automatisierungstechnik",
    "sg:phone":"+43 4369 911988913",
    "sg:postcode":"6425",
    "sg:province":"Tirol",
    "wof:name":"Nagele Electrics",
    "wof:placetype":"venue"
},
  "geometry": {"coordinates":[10.8829202652,47.2561302185],"type":"Point"}
}