{
  "type": "Feature",
  "properties": {
    "addr:full":"Autofabrikstr 15 Wien Wien 1230",
    "addr:housenumber":"15",
    "addr:postcode":"1230",
    "addr:street":"Autofabrikstr",
    "iso:country":"AT",
    "sg:address":"Autofabrikstr 15",
    "sg:city":"Wien",
    "sg:orig_category":"Tankreinigung",
    "sg:phone":"+43 1 8698343",
    "sg:postcode":"1230",
    "sg:province":"Wien",
    "wof:name":"Allgemeine Industrieanlagenservice GesmbH",
    "wof:placetype":"venue"
},
  "geometry": {"coordinates":[16.2973079681,48.1414909363],"type":"Point"}
}