{
  "type": "Feature",
  "properties": {
    "addr:full":"Josef-Pirchl-Str 21 Kitzb\u00fchel Tirol 6370",
    "addr:housenumber":"21",
    "addr:postcode":"6370",
    "addr:street":"Josef-Pirchl-Str;Tirol",
    "iso:country":"AT",
    "sg:address":"Josef-Pirchl-Str 21",
    "sg:city":"Kitzb\u00fchel",
    "sg:classifiers":[
        {
            "category":"Travel",
            "subcategory":"Hotels & Motels",
            "type":"Entertainment"
        }
    ],
    "sg:phone":"+43 5356 648850",
    "sg:postcode":"6370",
    "sg:province":"Tirol",
    "wof:name":"Hotel Erika",
    "wof:placetype":"venue"
},
  "geometry": {"coordinates":[12.3897724152,47.4506340027],"type":"Point"}
}