{
  "type": "Feature",
  "properties": {
    "addr:full":"Werdertorg 10 Wien Wien 1010",
    "addr:housenumber":"10",
    "addr:postcode":"1010",
    "addr:street":"Werdertorg",
    "iso:country":"AT",
    "sg:address":"Werdertorg 10",
    "sg:city":"Wien",
    "sg:orig_category":"Teigwaren",
    "sg:phone":"+43 1 7966542",
    "sg:postcode":"1010",
    "sg:province":"Wien",
    "wof:name":"Pasta e Basta - Michael Meixner",
    "wof:placetype":"venue"
},
  "geometry": {"coordinates":[16.3708953857,48.2152175903],"type":"Point"}
}