{
  "type": "Feature",
  "properties": {
    "addr:full":"Sportplatzstr 1 Bruck an der Gro\u00dfglocknerstra\u00dfe Salzburg 5671",
    "addr:housenumber":"1",
    "addr:postcode":"5671",
    "addr:street":"Sportplatzstr;Grossglocknerstrasse Salzburg",
    "iso:country":"AT",
    "sg:address":"Sportplatzstr 1",
    "sg:city":"Bruck an der Gro\u00dfglocknerstra\u00dfe",
    "sg:orig_category":"Wasserwerke",
    "sg:phone":"+43 6545 7294",
    "sg:postcode":"5671",
    "sg:province":"Salzburg",
    "wof:name":"Wasserbauhof",
    "wof:placetype":"venue"
},
  "geometry": {"coordinates":[12.8195791245,47.2875213623],"type":"Point"}
}