{
  "type": "Feature",
  "properties": {
    "addr:full":"Hauptpl 22 Judenburg Steiermark 8750",
    "addr:housenumber":"22",
    "addr:postcode":"8750",
    "addr:street":"Hauptpl",
    "iso:country":"AT",
    "sg:address":"Hauptpl 22",
    "sg:city":"Judenburg",
    "sg:orig_category":"Brautkleider U -Artikel",
    "sg:phone":"+43 4335 7244326",
    "sg:postcode":"8750",
    "sg:province":"Steiermark",
    "wof:name":"Susi-Brautkleider",
    "wof:placetype":"venue"
},
  "geometry": {"coordinates":[14.6606321335,47.168510437],"type":"Point"}
}