{
  "type": "Feature",
  "properties": {
    "addr:full":"Eipoldschlag 12 Weitersfelden Ober\u00f6sterreich 4272",
    "addr:housenumber":"12",
    "addr:postcode":"4272",
    "addr:street":"Eipoldschlag;Oberoesterreich",
    "iso:country":"AT",
    "sg:address":"Eipoldschlag 12",
    "sg:city":"Weitersfelden",
    "sg:orig_category":"Autohandel",
    "sg:phone":"+43 7952 6560",
    "sg:postcode":"4272",
    "sg:province":"Ober\u00f6sterreich",
    "wof:name":"Autohandel Ewald Grufeneder",
    "wof:placetype":"venue"
},
  "geometry": {"coordinates":[14.7197856903,48.4969139099],"type":"Point"}
}