{
  "type": "Feature",
  "properties": {
    "addr:full":"Mittler Au 3 Bad Wimsbach-Neydharting Ober\u00f6sterreich 4654",
    "addr:housenumber":"3",
    "addr:postcode":"4654",
    "addr:street":"Mittler Au",
    "iso:country":"AT",
    "sg:address":"Mittler Au 3",
    "sg:city":"Bad Wimsbach-Neydharting",
    "sg:orig_category":"Fenster",
    "sg:phone":"+43 7245 25311",
    "sg:postcode":"4654",
    "sg:province":"Ober\u00f6sterreich",
    "wof:name":"Weismann G\u00fcnther",
    "wof:placetype":"venue"
},
  "geometry": {"coordinates":[13.9066200256,48.0474014282],"type":"Point"}
}