{
  "type": "Feature",
  "properties": {
    "addr:full":"Preinsbacher Str 18 Amstetten Nieder\u00f6sterreich 3300",
    "addr:housenumber":"18",
    "addr:postcode":"3300",
    "addr:street":"Str;Niederoesterreich",
    "iso:country":"AT",
    "sg:address":"Preinsbacher Str 18",
    "sg:city":"Amstetten",
    "sg:orig_category":"Personalbereitstellung",
    "sg:phone":"+43 4374 7267474",
    "sg:postcode":"3300",
    "sg:province":"Nieder\u00f6sterreich",
    "wof:name":"MANPOWER Personal\u00fcberlassung GmbH",
    "wof:placetype":"venue"
},
  "geometry": {"coordinates":[14.8758068085,48.1241836548],"type":"Point"}
}