{
  "type": "Feature",
  "properties": {
    "iso:country":"AT",
    "sg:address":"Tobersbachstr 52",
    "sg:city":"Uttendorf",
    "sg:orig_category":"Fenster",
    "sg:phone":"+43 4365 6382160",
    "sg:postcode":"5723",
    "sg:province":"Salzburg",
    "wof:name":"Lechner Franz Fenster u T\u00fcren Innenausbau GesmbH",
    "wof:placetype":"venue"
},
  "geometry": {"coordinates":[12.5809793472,47.2856864929],"type":"Point"}
}