{
  "type": "Feature",
  "properties": {
    "iso:country":"AT",
    "sg:address":"Hohe Warte 64/10",
    "sg:city":"Wien",
    "sg:orig_category":"Unternehmensberatung",
    "sg:phone":"+43 1 3703393",
    "sg:postcode":"1190",
    "sg:province":"Wien",
    "wof:name":"Bluecon - Christian Aichholzer KEG",
    "wof:placetype":"venue"
},
  "geometry": {"coordinates":[16.3551883698,48.2535057068],"type":"Point"}
}