{
  "type": "Feature",
  "properties": {
    "addr:full":"Gm\u00f6ser Strasse 2 Laakirchen Ober\u00f6sterreich 4663",
    "addr:housenumber":"2",
    "addr:postcode":"4663",
    "addr:street":"Gmoeser Strasse",
    "iso:country":"AT",
    "sg:address":"Gm\u00f6ser Strasse 2",
    "sg:city":"Laakirchen",
    "sg:classifiers":[
        {
            "category":"Professional",
            "type":"Services"
        }
    ],
    "sg:phone":"+43 76133297",
    "sg:postcode":"4663",
    "sg:province":"Ober\u00f6sterreich",
    "sg:tags":[
        "transport"
    ],
    "wof:name":"Spitzbart Transporte u. Spedition GmbH & Co KG",
    "wof:placetype":"venue"
},
  "geometry": {"coordinates":[13.8235368729,47.9863929749],"type":"Point"}
}