{
  "type": "Feature",
  "properties": {
    "iso:country":"AT",
    "sg:address":"Hauptpl 10",
    "sg:city":"Neunkirchen",
    "sg:orig_category":"Boutiquen",
    "sg:phone":"+43 2635 67440",
    "sg:postcode":"2620",
    "sg:province":"Nieder\u00f6sterreich",
    "wof:name":"Street One",
    "wof:placetype":"venue"
},
  "geometry": {"coordinates":[16.081035614,47.7213554382],"type":"Point"}
}