{
  "type": "Feature",
  "properties": {
    "addr:full":"Maurer Lange G 78 Wien Wien 1230",
    "addr:housenumber":"78",
    "addr:postcode":"1230",
    "addr:street":"Maurer Lange G",
    "iso:country":"AT",
    "sg:address":"Maurer Lange G 78",
    "sg:city":"Wien",
    "sg:orig_category":"Heurigen / Buschenschank",
    "sg:phone":"+43 1 8885262",
    "sg:postcode":"1230",
    "sg:province":"Wien",
    "wof:name":"Weinbau Lentz",
    "wof:placetype":"venue"
},
  "geometry": {"coordinates":[16.2658519745,48.1479606628],"type":"Point"}
}