{
  "type": "Feature",
  "properties": {
    "addr:full":"Sch\u00f6nbrunner Allee 47 Wien Wien 1120",
    "addr:housenumber":"47",
    "addr:postcode":"1120",
    "addr:street":"Schoenbrunner Allee",
    "iso:country":"AT",
    "sg:address":"Sch\u00f6nbrunner Allee 47",
    "sg:city":"Wien",
    "sg:orig_category":"Physikalische Institute",
    "sg:phone":"+43 1 8042759",
    "sg:postcode":"1120",
    "sg:province":"Wien",
    "wof:name":"Physikalisches Institut Hetzendorf GesmbH",
    "wof:placetype":"venue"
},
  "geometry": {"coordinates":[16.3098583221,48.1682853699],"type":"Point"}
}