{
  "type": "Feature",
  "properties": {
    "addr:full":"Obdacher Bundesstr 295 Bad St. Leonhard im Lavanttal K\u00e4rnten 9462",
    "addr:housenumber":"295",
    "addr:postcode":"9462",
    "iso:country":"AT",
    "sg:address":"Obdacher Bundesstr 295",
    "sg:city":"Bad St. Leonhard im Lavanttal",
    "sg:orig_category":"Tischlereien",
    "sg:phone":"+43 4343 5022580",
    "sg:postcode":"9462",
    "sg:province":"K\u00e4rnten",
    "wof:name":"Tischlerei Kriegl",
    "wof:placetype":"venue"
},
  "geometry": {"coordinates":[14.7980833054,46.9582748413],"type":"Point"}
}