{
  "type": "Feature",
  "properties": {
    "addr:full":"Gudrunstrasse 184/5/2 Wien Wien 1100",
    "addr:housenumber":"184 / 5 / 2",
    "addr:postcode":"1100",
    "addr:street":"Gudrunstrasse",
    "iso:country":"AT",
    "sg:address":"Gudrunstrasse 184/5/2",
    "sg:city":"Wien",
    "sg:classifiers":[
        {
            "category":"Professional",
            "subcategory":"Advertising",
            "type":"Services"
        }
    ],
    "sg:phone":"+43 1 6072240",
    "sg:postcode":"1100",
    "sg:province":"Wien",
    "sg:tags":[
        "cloth",
        "luminous"
    ],
    "wof:name":"MONTRON Ing. Winkler & F\u00f6ldi Ges.m.b.H.",
    "wof:placetype":"venue"
},
  "geometry": {"coordinates":[16.3744049072,48.1782684326],"type":"Point"}
}