{
  "type": "Feature",
  "properties": {
    "addr:full":"Hauptpl 12 Leoben Steiermark 8700",
    "addr:housenumber":"12",
    "addr:postcode":"8700",
    "addr:street":"Hauptpl",
    "iso:country":"AT",
    "sg:address":"Hauptpl 12",
    "sg:city":"Leoben",
    "sg:orig_category":"Friseure U Frisiersalons",
    "sg:phone":"+43 3842 42203",
    "sg:postcode":"8700",
    "sg:province":"Steiermark",
    "wof:name":"Aichbauer Wolfgang",
    "wof:placetype":"venue"
},
  "geometry": {"coordinates":[15.0944318771,47.3803596497],"type":"Point"}
}