{
  "type": "Feature",
  "properties": {
    "iso:country":"AT",
    "sg:address":"Alfred Kubin-Pl 4/7A",
    "sg:city":"Wien",
    "sg:orig_category":"Fitnesscenter",
    "sg:phone":"+43 676 3057902",
    "sg:postcode":"1220",
    "sg:province":"Wien",
    "wof:name":"Kraft Gabriele",
    "wof:placetype":"venue"
},
  "geometry": {"coordinates":[16.4412593842,48.2603034973],"type":"Point"}
}