{
  "type": "Feature",
  "properties": {
    "addr:full":"Alfred Kubin-Pl 4/7A Wien Wien 1220",
    "addr:housenumber":"4 / 7a",
    "addr:postcode":"1220",
    "addr:street":"Kubin-Pl",
    "iso:country":"AT",
    "sg:address":"Alfred Kubin-Pl 4/7A",
    "sg:city":"Wien",
    "sg:orig_category":"Fitnesscenter",
    "sg:phone":"+43 676 3057902",
    "sg:postcode":"1220",
    "sg:province":"Wien",
    "wof:name":"Kraft Gabriele",
    "wof:placetype":"venue"
},
  "geometry": {"coordinates":[16.4412593842,48.2603034973],"type":"Point"}
}