{
  "type": "Feature",
  "properties": {
    "addr:full":"Zeisigstr 11a Gnigl Salzburg 5023",
    "addr:housenumber":"11a",
    "addr:postcode":"5023",
    "addr:street":"Zeisigstr",
    "iso:country":"AT",
    "sg:address":"Zeisigstr 11a",
    "sg:city":"Gnigl",
    "sg:orig_category":"Weiterbildungsinstitute M Allg U Berufl Bildungsangebot",
    "sg:phone":"+43 4366 2660831",
    "sg:postcode":"5023",
    "sg:province":"Salzburg",
    "wof:name":"Bezdek KEG",
    "wof:placetype":"venue"
},
  "geometry": {"coordinates":[13.0742321014,47.8206329346],"type":"Point"}
}