{
  "type": "Feature",
  "properties": {
    "iso:country":"AT",
    "sg:address":"Grubhof 151",
    "sg:city":"St. Martin",
    "sg:orig_category":"Werbeagenturen",
    "sg:phone":"+43 4365 887498",
    "sg:postcode":"5092",
    "sg:province":"Salzburg",
    "wof:name":"Die Hauser - Plattform f\u00fcr Kommunikation - Werbeagentur",
    "wof:placetype":"venue"
},
  "geometry": {"coordinates":[12.7057151794,47.5662536621],"type":"Point"}
}