{
  "type": "Feature",
  "properties": {
    "iso:country":"AT",
    "sg:address":"Hauptpl 7",
    "sg:city":"Lienz",
    "sg:orig_category":"Gemeinden",
    "sg:phone":"+43 4852 6000",
    "sg:postcode":"9900",
    "sg:province":"Tirol",
    "wof:name":"Stadtgemeinde Lienz",
    "wof:placetype":"venue"
},
  "geometry": {"coordinates":[12.7693586349,46.8292503357],"type":"Point"}
}