{
  "type": "Feature",
  "properties": {
    "addr:full":"Milchgraben 15 Ragnitz Steiermark 8047",
    "addr:housenumber":"15",
    "addr:postcode":"8047",
    "addr:street":"Milchgraben",
    "iso:country":"AT",
    "sg:address":"Milchgraben 15",
    "sg:city":"Ragnitz",
    "sg:orig_category":"Transportunternehmen",
    "sg:phone":"+43 316 301968",
    "sg:postcode":"8047",
    "sg:province":"Steiermark",
    "wof:name":"Zengerer Erich",
    "wof:placetype":"venue"
},
  "geometry": {"coordinates":[15.5450687408,47.0907783508],"type":"Point"}
}