{
  "type": "Feature",
  "properties": {
    "addr:full":"B\u00fcrgleg 35 Dornbirn Vorarlberg 6850",
    "addr:housenumber":"35",
    "addr:postcode":"6850",
    "addr:street":"Buergleg",
    "iso:country":"AT",
    "sg:address":"B\u00fcrgleg 35",
    "sg:city":"Dornbirn",
    "sg:orig_category":"Werbegrafik- U Grafik-Design",
    "sg:phone":"+43 5572 394828",
    "sg:postcode":"6850",
    "sg:province":"Vorarlberg",
    "wof:name":"Flack & Oberhauser OEG",
    "wof:placetype":"venue"
},
  "geometry": {"coordinates":[9.7437801361,47.4131889343],"type":"Point"}
}