{
  "type": "Feature",
  "properties": {
    "addr:full":"Ried 80 Gerlos Tirol 6281",
    "addr:housenumber":"80",
    "addr:postcode":"6281",
    "addr:street":"Ried;Tirol",
    "iso:country":"AT",
    "sg:address":"Ried 80",
    "sg:city":"Gerlos",
    "sg:orig_category":"Installationsunternehmen",
    "sg:phone":"+43 5284 5233",
    "sg:postcode":"6281",
    "sg:province":"Tirol",
    "wof:name":"Haas Installationen GesmbH",
    "wof:placetype":"venue"
},
  "geometry": {"coordinates":[12.0283689499,47.2223777771],"type":"Point"}
}