{
  "type": "Feature",
  "properties": {
    "addr:full":"Nr 84 P\u00f6rtschach am W\u00f6rther See K\u00e4rnten 9210",
    "addr:postcode":"9210",
    "addr:street":"Nr 84;Am Woerther;Kaernten",
    "iso:country":"AT",
    "sg:address":"Nr 84",
    "sg:city":"P\u00f6rtschach am W\u00f6rther See",
    "sg:orig_category":"Restaurants: Amerikanisch",
    "sg:phone":"+43 4272 43995504",
    "sg:postcode":"9210",
    "sg:province":"K\u00e4rnten",
    "wof:name":"Burger King Restaurant",
    "wof:placetype":"venue"
},
  "geometry": {"coordinates":[14.1465053558,46.635345459],"type":"Point"}
}