{
  "type": "Feature",
  "properties": {
    "addr:full":"Seutterg 6 Wien Wien 1130",
    "addr:housenumber":"6",
    "addr:postcode":"1130",
    "addr:street":"Seutterg",
    "iso:country":"AT",
    "sg:address":"Seutterg 6",
    "sg:city":"Wien",
    "sg:orig_category":"Bijouteriewaren",
    "sg:phone":"+43 1 8767119",
    "sg:postcode":"1130",
    "sg:province":"Wien",
    "wof:name":"Vienna Strass",
    "wof:placetype":"venue"
},
  "geometry": {"coordinates":[16.2632637024,48.1934051514],"type":"Point"}
}