{
  "type": "Feature",
  "properties": {
    "addr:full":"Hochfeldweg 8 Raaba Steiermark 8074",
    "addr:housenumber":"8",
    "addr:postcode":"8074",
    "addr:street":"Hochfeldweg",
    "iso:country":"AT",
    "sg:address":"Hochfeldweg 8",
    "sg:city":"Raaba",
    "sg:orig_category":"Ingenieurkonsulenten / Zivilingenieure",
    "sg:phone":"+43 316 4012830",
    "sg:postcode":"8074",
    "sg:province":"Steiermark",
    "wof:name":"Eustacchio Peter Dipl-Ing",
    "wof:placetype":"venue"
},
  "geometry": {"coordinates":[15.4974775314,47.0329017639],"type":"Point"}
}