{
  "type": "Feature",
  "properties": {
    "iso:country":"AT",
    "sg:address":"Nr 7",
    "sg:city":"Ried im Innkreis",
    "sg:orig_category":"Banken U Sparkassen",
    "sg:phone":"+43 4377 52831410",
    "sg:postcode":"4910",
    "sg:province":"Ober\u00f6sterreich",
    "wof:name":"Raiffeisenkasse Neuhofen im Innkreis regGenmbH",
    "wof:placetype":"venue"
},
  "geometry": {"coordinates":[13.497300148,48.2311439514],"type":"Point"}
}