{
  "type": "Feature",
  "properties": {
    "addr:full":"W\u00e4hringer Str 145/28 Wien Wien 1180",
    "addr:housenumber":"145 / 28",
    "addr:postcode":"1180",
    "addr:street":"Str",
    "iso:country":"AT",
    "sg:address":"W\u00e4hringer Str 145/28",
    "sg:city":"Wien",
    "sg:orig_category":"Markt- U Meinungsforschung",
    "sg:phone":"+43 1 47002640",
    "sg:postcode":"1180",
    "sg:province":"Wien",
    "wof:name":"tunc Marktforschung und Marketingberatung GesmbH",
    "wof:placetype":"venue"
},
  "geometry": {"coordinates":[16.3359451294,48.2280387878],"type":"Point"}
}