{
  "type": "Feature",
  "properties": {
    "addr:full":"Engerthstr 82/9 Wien Wien 1200",
    "addr:housenumber":"82 / 9",
    "addr:postcode":"1200",
    "addr:street":"Engerthstr",
    "iso:country":"AT",
    "sg:address":"Engerthstr 82/9",
    "sg:city":"Wien",
    "sg:orig_category":"Installationsunternehmen",
    "sg:phone":"+43 4313 320118",
    "sg:postcode":"1200",
    "sg:province":"Wien",
    "wof:name":"Rako Gas- Wasser- u Heizungsanlagen Montage GesmbH",
    "wof:placetype":"venue"
},
  "geometry": {"coordinates":[16.3840198517,48.240737915],"type":"Point"}
}