{
  "type": "Feature",
  "properties": {
    "addr:full":"Weidengasse 1 Pernitz Nieder\u00f6sterreich 2763",
    "addr:housenumber":"1",
    "addr:postcode":"2763",
    "addr:street":"Weidengasse",
    "iso:country":"AT",
    "sg:address":"Weidengasse 1",
    "sg:city":"Pernitz",
    "sg:classifiers":[
        {
            "category":"Manufacturing",
            "subcategory":"Wood Products",
            "type":"Manufacturing & Wholesale Goods"
        }
    ],
    "sg:phone":"+43 2632 72880",
    "sg:postcode":"2763",
    "sg:province":"Nieder\u00f6sterreich",
    "sg:tags":[
        "made",
        "balcony"
    ],
    "sg:website":"eckenfellner.at",
    "wof:name":"Eckenfellner Peter GmbH",
    "wof:placetype":"venue"
},
  "geometry": {"coordinates":[15.9626626968,47.8977355957],"type":"Point"}
}