{
  "type": "Feature",
  "properties": {
    "addr:full":"Teichstrasse 46 Neuzeug Ober\u00f6sterreich 4523",
    "addr:housenumber":"46",
    "addr:postcode":"4523",
    "addr:street":"Teichstrasse",
    "iso:country":"AT",
    "sg:address":"Teichstrasse 46",
    "sg:city":"Neuzeug",
    "sg:classifiers":[
        {
            "category":"Autos & Motor Vehicles",
            "subcategory":"Auto Supplies",
            "type":"Retail Goods"
        }
    ],
    "sg:phone":"+43 7259 4034",
    "sg:postcode":"4523",
    "sg:province":"Ober\u00f6sterreich",
    "sg:tags":[
        "automobile",
        "part",
        "spare"
    ],
    "sg:website":"vimex.cc",
    "wof:name":"VIMEX Vogt Import-Export GmbH",
    "wof:placetype":"venue"
},
  "geometry": {"coordinates":[14.3221750259,48.0261383057],"type":"Point"}
}