{
  "type": "Feature",
  "properties": {
    "addr:full":"Grillparzerstr 3 Ried im Innkreis Ober\u00f6sterreich 4910",
    "addr:housenumber":"3",
    "addr:postcode":"4910",
    "addr:street":"Grillparzerstr",
    "iso:country":"AT",
    "sg:address":"Grillparzerstr 3",
    "sg:city":"Ried im Innkreis",
    "sg:orig_category":"Autohandel",
    "sg:phone":"+43 7752 879790",
    "sg:postcode":"4910",
    "sg:province":"Ober\u00f6sterreich",
    "wof:name":"Rachbauer Autohaus GmbH",
    "wof:placetype":"venue"
},
  "geometry": {"coordinates":[13.4835758209,48.2152442932],"type":"Point"}
}