{
  "type": "Feature",
  "properties": {
    "iso:country":"AT",
    "sg:address":"Nr 100",
    "sg:city":"Stainz",
    "sg:orig_category":"Autohandel",
    "sg:phone":"+43 664 5122766",
    "sg:postcode":"8510",
    "sg:province":"Steiermark",
    "wof:name":"Gatschnig August",
    "wof:placetype":"venue"
},
  "geometry": {"coordinates":[15.2647809982,46.8937683105],"type":"Point"}
}