{
  "type": "Feature",
  "properties": {
    "iso:country":"AT",
    "sg:address":"Ro\u00dfanger 7",
    "sg:city":"Peuerbach",
    "sg:orig_category":"Massagen",
    "sg:phone":"+43 7276 3814",
    "sg:postcode":"4722",
    "sg:province":"Ober\u00f6sterreich",
    "wof:name":"Klaffenb\u00f6ck Mathilde",
    "wof:placetype":"venue"
},
  "geometry": {"coordinates":[13.7729463577,48.3276634216],"type":"Point"}
}