{
  "type": "Feature",
  "properties": {
    "addr:full":"Langmoosweg 3 Gnigl Salzburg 5023",
    "addr:housenumber":"3",
    "addr:postcode":"5023",
    "addr:street":"Langmoosweg",
    "iso:country":"AT",
    "sg:address":"Langmoosweg 3",
    "sg:city":"Gnigl",
    "sg:classifiers":[
        {
            "category":"Restaurant",
            "type":"Food & Drink"
        }
    ],
    "sg:phone":"+43 662 661958",
    "sg:postcode":"5023",
    "sg:province":"Salzburg",
    "sg:tags":[
        "pizzeria"
    ],
    "wof:name":"Pizzeria Gaisbergblick",
    "wof:placetype":"venue"
},
  "geometry": {"coordinates":[13.0662384033,47.8277206421],"type":"Point"}
}