{
  "type": "Feature",
  "properties": {
    "addr:full":"/Parz 3815/17 Wildend\u00fcrnbach Nieder\u00f6sterreich 2164",
    "addr:housenumber":"3815 / 17",
    "addr:postcode":"2164",
    "addr:street":"Niederoesterreich",
    "iso:country":"AT",
    "sg:address":"/Parz 3815/17",
    "sg:city":"Wildend\u00fcrnbach",
    "sg:orig_category":"Gemeinden",
    "sg:phone":"+43 2523 8252",
    "sg:postcode":"2164",
    "sg:province":"Nieder\u00f6sterreich",
    "wof:name":"Gemeinde Wildend\u00fcrnbach",
    "wof:placetype":"venue"
},
  "geometry": {"coordinates":[150.88458251949999,-33.7453193665],"type":"Point"}
}