{
  "type": "Feature",
  "properties": {
    "addr:full":"Silberleithen 10  Biberwier Tirol 6633",
    "addr:housenumber":"10",
    "addr:postcode":"6633",
    "addr:street":"Silberleithen;Tirol",
    "iso:country":"AT",
    "sg:address":"Silberleithen 10 ",
    "sg:city":"Biberwier",
    "sg:classifiers":[
        {
            "category":"Utilities",
            "subcategory":"Electric",
            "type":"Services"
        }
    ],
    "sg:phone":"+43 4356 7322910",
    "sg:postcode":"6633",
    "sg:province":"Tirol",
    "sg:tags":[
        "electricity"
    ],
    "wof:name":"ELEKTRIZIT\u00c4TSWERK REUTTE GES.MBH BIBERWIER",
    "wof:placetype":"venue"
},
  "geometry": {"coordinates":[10.8915700912,47.3769950867],"type":"Point"}
}