{
  "type": "Feature",
  "properties": {
    "addr:full":"Grazer Str. 33  Pinkafeld Burgenland 7423",
    "addr:postcode":"7423",
    "addr:street":"Str.",
    "iso:country":"AT",
    "sg:address":"Grazer Str. 33 ",
    "sg:city":"Pinkafeld",
    "sg:classifiers":[
        {
            "category":"Professional",
            "subcategory":"Printing & Photocopies",
            "type":"Services"
        }
    ],
    "sg:phone":"+43 4333 5742433",
    "sg:postcode":"7423",
    "sg:province":"Burgenland",
    "wof:name":"DONCSECS DRUCK GES.MBH",
    "wof:placetype":"venue"
},
  "geometry": {"coordinates":[16.1111507416,47.3695220947],"type":"Point"}
}