{
  "type": "Feature",
  "properties": {
    "addr:full":"Schalser Str 12/1 Jenbach Tirol 6200",
    "addr:housenumber":"12 / 1",
    "addr:postcode":"6200",
    "addr:street":"Str;Tirol",
    "iso:country":"AT",
    "sg:address":"Schalser Str 12/1",
    "sg:city":"Jenbach",
    "sg:orig_category":"Scheinwerfer",
    "sg:phone":"+43 4352 4463487",
    "sg:postcode":"6200",
    "sg:province":"Tirol",
    "sg:website":"technikus.at",
    "wof:name":"Technikus Arbeitsscheinwerfer GmbH",
    "wof:placetype":"venue"
},
  "geometry": {"coordinates":[11.7752895355,47.3918228149],"type":"Point"}
}