{
  "type": "Feature",
  "properties": {
    "addr:full":"Purtschellerstr 63 Villach K\u00e4rnten 9500",
    "addr:housenumber":"63",
    "addr:postcode":"9500",
    "addr:street":"Purtschellerstr;Kaernten",
    "iso:country":"AT",
    "sg:address":"Purtschellerstr 63",
    "sg:city":"Villach",
    "sg:orig_category":"Markisen, Jalousien",
    "sg:phone":"+43 4242 59199",
    "sg:postcode":"9500",
    "sg:province":"K\u00e4rnten",
    "sg:website":"thmsonnenschutz.at",
    "wof:name":"thm - SONNENSCHUTZ Beratung vor Ort - Qualit\u00e4tsprodukte",
    "wof:placetype":"venue"
},
  "geometry": {"coordinates":[13.8152704239,46.6037597656],"type":"Point"}
}