{
  "type": "Feature",
  "properties": {
    "addr:full":"Aigen 89 Aigen im Ennstal Steiermark 8943",
    "addr:housenumber":"89",
    "addr:postcode":"8943",
    "addr:street":"Aigen",
    "iso:country":"AT",
    "sg:address":"Aigen 89",
    "sg:city":"Aigen im Ennstal",
    "sg:classifiers":[
        {
            "category":"Manufacturing",
            "subcategory":"Wood Products",
            "type":"Manufacturing & Wholesale Goods"
        }
    ],
    "sg:phone":"+43 3682 24855",
    "sg:postcode":"8943",
    "sg:province":"Steiermark",
    "sg:tags":[
        "made",
        "balcony"
    ],
    "sg:website":"mehrl-holzbau.at",
    "wof:name":"Mehrl GmbH",
    "wof:placetype":"venue"
},
  "geometry": {"coordinates":[14.1426610947,47.5210189819],"type":"Point"}
}