{
  "type": "Feature",
  "properties": {
    "addr:full":"Eiseng 18 Dornbirn Vorarlberg 6850",
    "addr:housenumber":"18",
    "addr:postcode":"6850",
    "addr:street":"Eiseng",
    "iso:country":"AT",
    "sg:address":"Eiseng 18",
    "sg:city":"Dornbirn",
    "sg:orig_category":"Baumeister",
    "sg:phone":"+43 5572 279080",
    "sg:postcode":"6850",
    "sg:province":"Vorarlberg",
    "sg:website":"www.atelier-barta.at",
    "wof:name":"Barta G\u00fcnther",
    "wof:placetype":"venue"
},
  "geometry": {"coordinates":[9.7457847595,47.4170303345],"type":"Point"}
}