{
  "type": "Feature",
  "properties": {
    "addr:full":"Ungarg 55 Wien Wien 1030",
    "addr:housenumber":"55",
    "addr:postcode":"1030",
    "addr:street":"Ungarg",
    "iso:country":"AT",
    "sg:address":"Ungarg 55",
    "sg:city":"Wien",
    "sg:orig_category":"Fotoausarbeitungen",
    "sg:phone":"+43 1 7132730",
    "sg:postcode":"1030",
    "sg:province":"Wien",
    "wof:name":"Fotolabor BRENNPUNKT GmbH Nfg KEG",
    "wof:placetype":"venue"
},
  "geometry": {"coordinates":[16.387512207,48.1984138489],"type":"Point"}
}