{
  "type": "Feature",
  "properties": {
    "addr:full":"Quellenstr 79-83 Wien Wien 1100",
    "addr:postcode":"79-83;1100",
    "iso:country":"AT",
    "sg:address":"Quellenstr 79-83",
    "sg:city":"Wien",
    "sg:orig_category":"Bauunternehmen",
    "sg:phone":"+43 4316 000850",
    "sg:postcode":"1100",
    "sg:province":"Wien",
    "wof:name":"S M V BaugmbH",
    "wof:placetype":"venue"
},
  "geometry": {"coordinates":[16.3838691711,48.1746635437],"type":"Point"}
}