{
  "type": "Feature",
  "properties": {
    "addr:full":"Amerlingstr 3 Wien Wien 1060",
    "addr:housenumber":"3",
    "addr:postcode":"1060",
    "addr:street":"Amerlingstr",
    "iso:country":"AT",
    "sg:address":"Amerlingstr 3",
    "sg:city":"Wien",
    "sg:orig_category":"Schneidereien",
    "sg:phone":"+43 1 5870441",
    "sg:postcode":"1060",
    "sg:province":"Wien",
    "wof:name":"Blecha Josef",
    "wof:placetype":"venue"
},
  "geometry": {"coordinates":[16.3512687683,48.1965560913],"type":"Point"}
}