{
  "type": "Feature",
  "properties": {
    "addr:full":"Achenwald 650 Achenkirch Tirol 6215",
    "addr:housenumber":"650",
    "addr:postcode":"6215",
    "addr:street":"Achenwald;Tirol",
    "iso:country":"AT",
    "sg:address":"Achenwald 650",
    "sg:city":"Achenkirch",
    "sg:orig_category":"Transportunternehmen",
    "sg:phone":"+43 5246 6900",
    "sg:postcode":"6215",
    "sg:province":"Tirol",
    "wof:name":"Buchmayer Gaby",
    "wof:placetype":"venue"
},
  "geometry": {"coordinates":[11.6545982361,47.5727577209],"type":"Point"}
}