{
  "type": "Feature",
  "properties": {
    "addr:full":"Hauptpl 18 Frohnleiten Steiermark 8130",
    "addr:housenumber":"18",
    "addr:postcode":"8130",
    "addr:street":"Hauptpl",
    "iso:country":"AT",
    "sg:address":"Hauptpl 18",
    "sg:city":"Frohnleiten",
    "sg:orig_category":"Fotoapparate U -Artikel / Einzelhandel",
    "sg:phone":"+43 4331 2651024",
    "sg:postcode":"8130",
    "sg:province":"Steiermark",
    "wof:name":"Hartlauer HandelsgesmbH",
    "wof:placetype":"venue"
},
  "geometry": {"coordinates":[15.3260469437,47.2707672119],"type":"Point"}
}