{
  "type": "Feature",
  "properties": {
    "addr:full":"Taborstr 52A/10 Wien Wien 1020",
    "addr:housenumber":"52a / 10",
    "addr:postcode":"1020",
    "addr:street":"Taborstr",
    "iso:country":"AT",
    "sg:address":"Taborstr 52A/10",
    "sg:city":"Wien",
    "sg:classifiers":[
        {
            "category":"Professional",
            "subcategory":"Computer Services",
            "type":"Services"
        }
    ],
    "sg:phone":"+43 1 2143240",
    "sg:postcode":"1020",
    "sg:province":"Wien",
    "sg:tags":[
        "software"
    ],
    "wof:name":"Pastner Thomas",
    "wof:placetype":"venue"
},
  "geometry": {"coordinates":[16.3818721771,48.2206993103],"type":"Point"}
}