{
  "type": "Feature",
  "properties": {
    "iso:country":"AT",
    "sg:address":"B\u00fcrgerg 24",
    "sg:city":"Gleisdorf",
    "sg:orig_category":"Biologische Produkte",
    "sg:phone":"+43 4331 124132",
    "sg:postcode":"8200",
    "sg:province":"Steiermark",
    "wof:name":"Bioladen Lebensweise",
    "wof:placetype":"venue"
},
  "geometry": {"coordinates":[15.6912050247,47.103477478],"type":"Point"}
}