{
  "type": "Feature",
  "properties": {
    "addr:full":"Pummererstrasse 12 Linz Ober\u00f6sterreich 4020",
    "addr:housenumber":"12",
    "addr:postcode":"4020",
    "addr:street":"Pummererstrasse",
    "iso:country":"AT",
    "sg:address":"Pummererstrasse 12",
    "sg:city":"Linz",
    "sg:classifiers":[
        {
            "category":"Wholesale",
            "subcategory":"Plants",
            "type":"Manufacturing & Wholesale Goods"
        }
    ],
    "sg:phone":"+43 732 779800",
    "sg:postcode":"4020",
    "sg:province":"Ober\u00f6sterreich",
    "sg:tags":[
        "machine",
        "industrial",
        "automation"
    ],
    "sg:website":"barbaric.at",
    "wof:name":"barbaric gmbh krane - vacuumhebetechnik - service",
    "wof:placetype":"venue"
},
  "geometry": {"coordinates":[14.3223304749,48.3067398071],"type":"Point"}
}