{
  "type": "Feature",
  "properties": {
    "iso:country":"AT",
    "sg:address":"Weinbergg 1",
    "sg:city":"Gro\u00dfebersdorf",
    "sg:orig_category":"Feuerwehren",
    "sg:phone":"+43 2245 6122",
    "sg:postcode":"2203",
    "sg:province":"Nieder\u00f6sterreich",
    "wof:name":"Freiwillige Feuerwehr Eibesbrunn",
    "wof:placetype":"venue"
},
  "geometry": {"coordinates":[16.4689350128,48.3628768921],"type":"Point"}
}