{
  "type": "Feature",
  "properties": {
    "iso:country":"AT",
    "sg:address":"Maurer Lange G 92/5",
    "sg:city":"Wien",
    "sg:classifiers":[
        {
            "category":"Autos & Motor Vehicles",
            "subcategory":"Auto Supplies",
            "type":"Retail Goods"
        }
    ],
    "sg:phone":"+43 1 8128158",
    "sg:postcode":"1230",
    "sg:province":"Wien",
    "sg:tags":[
        "regale"
    ],
    "wof:name":"Desta Stahlm\u00f6bel Handels-GmbH",
    "wof:placetype":"venue"
},
  "geometry": {"coordinates":[16.2636241913,48.1482009888],"type":"Point"}
}