{
  "type": "Feature",
  "properties": {
    "iso:country":"AT",
    "sg:address":"Hauptstr 14",
    "sg:city":"G\u00fcssing",
    "sg:orig_category":"Polizei U Gendarmerie",
    "sg:phone":"+43 5 91331200305",
    "sg:postcode":"7540",
    "sg:province":"Burgenland",
    "wof:name":"Bezirksgendarmeriekommando G\u00fcssing",
    "wof:placetype":"venue"
},
  "geometry": {"coordinates":[16.3203525543,47.0581016541],"type":"Point"}
}