{
  "type": "Feature",
  "properties": {
    "addr:full":"Freundorf 9 St. Marienkirchen an der Polsenz Ober\u00f6sterreich 4076",
    "addr:housenumber":"9",
    "addr:postcode":"4076",
    "addr:street":"Freundorf",
    "iso:country":"AT",
    "sg:address":"Freundorf 9",
    "sg:city":"St. Marienkirchen an der Polsenz",
    "sg:orig_category":"Holzplatten",
    "sg:phone":"+43 4372 4947153",
    "sg:postcode":"4076",
    "sg:province":"Ober\u00f6sterreich",
    "wof:name":"Schweitzer Johann",
    "wof:placetype":"venue"
},
  "geometry": {"coordinates":[13.941775322,48.2603988647],"type":"Point"}
}