{
  "type": "Feature",
  "properties": {
    "addr:full":"Steinaebeng 10 Bad Fischau Nieder\u00f6sterreich 2721",
    "addr:housenumber":"10",
    "addr:postcode":"2721",
    "addr:street":"Steinaebeng",
    "iso:country":"AT",
    "sg:address":"Steinaebeng 10",
    "sg:city":"Bad Fischau",
    "sg:orig_category":"Ingenieurkonsulenten / Zivilingenieure",
    "sg:phone":"+43 4326 3976110",
    "sg:postcode":"2721",
    "sg:province":"Nieder\u00f6sterreich",
    "wof:name":"Sulzgruber Walter Ingenieurkonsulent f\u00fcr KT und WW",
    "wof:placetype":"venue"
},
  "geometry": {"coordinates":[16.1710834503,47.8360786438],"type":"Point"}
}