{
  "type": "Feature",
  "properties": {
    "addr:full":"M\u00f6serer Str 53 Seefeld in Tirol Tirol 6100",
    "addr:housenumber":"53",
    "addr:postcode":"6100",
    "addr:street":"Str;Tirol",
    "iso:country":"AT",
    "sg:address":"M\u00f6serer Str 53",
    "sg:city":"Seefeld in Tirol",
    "sg:classifiers":[
        {
            "category":"Travel",
            "subcategory":"Hotels & Motels",
            "type":"Entertainment"
        }
    ],
    "sg:phone":"+43 5212 45550",
    "sg:postcode":"6100",
    "sg:province":"Tirol",
    "wof:name":"Hotel St Peter",
    "wof:placetype":"venue"
},
  "geometry": {"coordinates":[11.1820354462,47.3285675049],"type":"Point"}
}