{
  "type": "Feature",
  "properties": {
    "addr:full":"Stadtpl 19 Schwanenstadt Ober\u00f6sterreich 4690",
    "addr:housenumber":"19",
    "addr:postcode":"4690",
    "addr:street":"Stadtpl",
    "iso:country":"AT",
    "sg:address":"Stadtpl 19",
    "sg:city":"Schwanenstadt",
    "sg:orig_category":"Juwelen, Gold- U Silberwaren / Einzelhandel",
    "sg:phone":"+43 767324510",
    "sg:postcode":"4690",
    "sg:province":"Ober\u00f6sterreich",
    "wof:name":"Moser Hans GesmbH & Co KG",
    "wof:placetype":"venue"
},
  "geometry": {"coordinates":[13.7746629715,48.0551795959],"type":"Point"}
}