{
  "type": "Feature",
  "properties": {
    "iso:country":"AT",
    "sg:address":"Schoberstr 30",
    "sg:city":"Fuschl am See",
    "sg:orig_category":"Maschinenbau",
    "sg:phone":"+43 6226 8676",
    "sg:postcode":"5330",
    "sg:province":"Salzburg",
    "wof:name":"S&F Scheibner Maschinenbau GesmbH",
    "wof:placetype":"venue"
},
  "geometry": {"coordinates":[13.2992477417,47.8061752319],"type":"Point"}
}