{
  "type": "Feature",
  "properties": {
    "addr:full":"Pfanngasse 4 Tulln an der Donau Nieder\u00f6sterreich 3430",
    "addr:housenumber":"4",
    "addr:postcode":"3430",
    "addr:street":"Pfanngasse",
    "iso:country":"AT",
    "sg:address":"Pfanngasse 4",
    "sg:city":"Tulln an der Donau",
    "sg:classifiers":[
        {
            "category":"Real Estate",
            "subcategory":"Architect",
            "type":"Services"
        }
    ],
    "sg:phone":"+43 2272 64728",
    "sg:postcode":"3430",
    "sg:province":"Nieder\u00f6sterreich",
    "sg:tags":[
        "interior",
        "decoration"
    ],
    "wof:name":"Wohnwerkstatt Helmuth Stif Ges.m.b.H.",
    "wof:placetype":"venue"
},
  "geometry": {"coordinates":[16.0527992249,48.3321838379],"type":"Point"}
}