{
  "type": "Feature",
  "properties": {
    "addr:full":"Treidelstr 6 Kufstein Tirol 6330",
    "addr:housenumber":"6",
    "addr:postcode":"6330",
    "addr:street":"Treidelstr;Tirol",
    "iso:country":"AT",
    "sg:address":"Treidelstr 6",
    "sg:city":"Kufstein",
    "sg:orig_category":"\u00c3\u201erzte / F Allgemeinmedizin",
    "sg:phone":"+43 5372 65574",
    "sg:postcode":"6330",
    "sg:province":"Tirol",
    "wof:name":"Senn Markus Dr",
    "wof:placetype":"venue"
},
  "geometry": {"coordinates":[12.1506576538,47.5751876831],"type":"Point"}
}