{
  "type": "Feature",
  "properties": {
    "addr:full":"Villacher Str 250 Feistritz an der Drau K\u00e4rnten 9710",
    "addr:housenumber":"250",
    "addr:postcode":"9710",
    "addr:street":"Str",
    "iso:country":"AT",
    "sg:address":"Villacher Str 250",
    "sg:city":"Feistritz an der Drau",
    "sg:orig_category":"Polizei U Gendarmerie",
    "sg:phone":"+43 4359 1332255",
    "sg:postcode":"9710",
    "sg:province":"K\u00e4rnten",
    "wof:name":"Gendarmerie",
    "wof:placetype":"venue"
},
  "geometry": {"coordinates":[13.6660671234,46.6996650696],"type":"Point"}
}