{
  "type": "Feature",
  "properties": {
    "iso:country":"AT",
    "sg:address":"Aldranser Str 214",
    "sg:city":"Lans",
    "sg:orig_category":"Feuerwehren",
    "sg:phone":"+43 512 378536",
    "sg:postcode":"6072",
    "sg:province":"Tirol",
    "wof:name":"Feuerwehr Lans",
    "wof:placetype":"venue"
},
  "geometry": {"coordinates":[11.4354534149,47.2407341003],"type":"Point"}
}