{
  "type": "Feature",
  "properties": {
    "addr:full":"Hauptstr 307A Strasshof an der Nordbahn Nieder\u00f6sterreich 2231",
    "addr:housenumber":"307a",
    "addr:postcode":"2231",
    "addr:street":"Hauptstr",
    "iso:country":"AT",
    "sg:address":"Hauptstr 307A",
    "sg:city":"Strasshof an der Nordbahn",
    "sg:orig_category":"Unterhaltungselektronik / Reparatur",
    "sg:phone":"+43 4322 874484",
    "sg:postcode":"2231",
    "sg:province":"Nieder\u00f6sterreich",
    "wof:name":"Vidlak Andreas",
    "wof:placetype":"venue"
},
  "geometry": {"coordinates":[16.6526794434,48.3201828003],"type":"Point"}
}