{
  "type": "Feature",
  "properties": {
    "iso:country":"AT",
    "sg:address":"Ziegelofeng 11",
    "sg:city":"Wien",
    "sg:classifiers":[
        {
            "category":"Professional",
            "subcategory":"Computer Services",
            "type":"Services"
        }
    ],
    "sg:phone":"+43 4369 917050505",
    "sg:postcode":"1050",
    "sg:province":"Wien",
    "sg:tags":[
        "software"
    ],
    "wof:name":"924plus KEG",
    "wof:placetype":"venue"
},
  "geometry": {"coordinates":[16.3630218506,48.1891098022],"type":"Point"}
}