{
  "type": "Feature",
  "properties": {
    "addr:full":"Gemeindestrasse 33 Leibnitz Steiermark 8430",
    "addr:housenumber":"33",
    "addr:postcode":"8430",
    "addr:street":"Gemeindestrasse;Steiermark",
    "iso:country":"AT",
    "sg:address":"Gemeindestrasse 33",
    "sg:city":"Leibnitz",
    "sg:classifiers":[
        {
            "category":"Manufacturing",
            "subcategory":"Textiles",
            "type":"Manufacturing & Wholesale Goods"
        }
    ],
    "sg:phone":"+43 3452 82033",
    "sg:postcode":"8430",
    "sg:province":"Steiermark",
    "sg:tags":[
        "curtain",
        "fabric"
    ],
    "wof:name":"Peter Dingsleder",
    "wof:placetype":"venue"
},
  "geometry": {"coordinates":[15.5235567093,46.8130378723],"type":"Point"}
}