{
  "type": "Feature",
  "properties": {
    "iso:country":"AT",
    "sg:address":"Badstr 1a",
    "sg:city":"Schattendorf",
    "sg:orig_category":"Banken U Sparkassen",
    "sg:phone":"+43 4326 8672260",
    "sg:postcode":"7022",
    "sg:province":"Burgenland",
    "wof:name":"Commerzialbank Mattersburg i Burgenland AG",
    "wof:placetype":"venue"
},
  "geometry": {"coordinates":[16.4806156158,47.6971588135],"type":"Point"}
}