{
  "type": "Feature",
  "properties": {
    "addr:full":"Hauptstr 1d Steyr Ober\u00f6sterreich 4400",
    "addr:housenumber":"1d",
    "addr:postcode":"4400",
    "addr:street":"Hauptstr;Oberoesterreich",
    "iso:country":"AT",
    "sg:address":"Hauptstr 1d",
    "sg:city":"Steyr",
    "sg:orig_category":"Lebensmittel / Einzelhandel",
    "sg:phone":"+43 7252 70585",
    "sg:postcode":"4400",
    "sg:province":"Ober\u00f6sterreich",
    "wof:name":"Billa AG",
    "wof:placetype":"venue"
},
  "geometry": {"coordinates":[14.4193296432,48.0391807556],"type":"Point"}
}