{
  "type": "Feature",
  "properties": {
    "addr:full":"Wolkersdorf 25 St. Stefan im Lavanttal K\u00e4rnten 9431",
    "addr:housenumber":"25",
    "addr:postcode":"9431",
    "addr:street":"Wolkersdorf",
    "iso:country":"AT",
    "sg:address":"Wolkersdorf 25",
    "sg:city":"St. Stefan im Lavanttal",
    "sg:classifiers":[
        {
            "category":"Home & Garden",
            "subcategory":"Carpets & Floor Coverings",
            "type":"Retail Goods"
        }
    ],
    "sg:phone":"+43 4352 3496",
    "sg:postcode":"9431",
    "sg:province":"K\u00e4rnten",
    "sg:tags":[
        "sport"
    ],
    "sg:website":"sportbau-krainz.at",
    "wof:name":"Sportbau Krainz GmbH",
    "wof:placetype":"venue"
},
  "geometry": {"coordinates":[14.832036972,46.8094558716],"type":"Point"}
}