{
  "type": "Feature",
  "properties": {
    "addr:full":"Unter der Leithen 1 Ybbsitz Nieder\u00f6sterreich 3341",
    "addr:housenumber":"1",
    "addr:postcode":"3341",
    "addr:street":"Unter Der Leithen",
    "iso:country":"AT",
    "sg:address":"Unter der Leithen 1",
    "sg:city":"Ybbsitz",
    "sg:orig_category":"Tabaktrafiken",
    "sg:phone":"+43 7443 86336",
    "sg:postcode":"3341",
    "sg:province":"Nieder\u00f6sterreich",
    "wof:name":"Seisenbacher Monika",
    "wof:placetype":"venue"
},
  "geometry": {"coordinates":[14.8939180374,47.9468421936],"type":"Point"}
}