{
  "type": "Feature",
  "properties": {
    "iso:country":"AT",
    "sg:address":"Kendlerstr 38",
    "sg:city":"Salzburg",
    "sg:orig_category":"Druckereien",
    "sg:phone":"+43 4366 2835194",
    "sg:postcode":"5020",
    "sg:province":"Salzburg",
    "wof:name":"Hofinger Robert - Kreative Drucksorten",
    "wof:placetype":"venue"
},
  "geometry": {"coordinates":[13.0190439224,47.7897338867],"type":"Point"}
}