{
  "type": "Feature",
  "properties": {
    "addr:full":"Nu\u00dfdorfer Str 64 Wien Wien 1090",
    "addr:postcode":"1090",
    "addr:street":"Str 64",
    "iso:country":"AT",
    "sg:address":"Nu\u00dfdorfer Str 64",
    "sg:city":"Wien",
    "sg:classifiers":[
        {
            "category":"Transit Center",
            "subcategory":"Passenger",
            "type":"Transportation"
        }
    ],
    "sg:phone":"+43 4313 16700",
    "sg:postcode":"1090",
    "sg:province":"Wien",
    "sg:tags":[
        "call"
    ],
    "wof:name":"call us Assistance International GmbH",
    "wof:placetype":"venue"
},
  "geometry": {"coordinates":[16.351474762,48.2234115601],"type":"Point"}
}