{
  "type": "Feature",
  "properties": {
    "iso:country":"AT",
    "sg:address":"Hochfeldweg 4",
    "sg:city":"Hof",
    "sg:orig_category":"Industrievertretungen",
    "sg:phone":"+43 6229 28610",
    "sg:postcode":"5322",
    "sg:province":"Salzburg",
    "wof:name":"Wurzer Industrievertretungen",
    "wof:placetype":"venue"
},
  "geometry": {"coordinates":[13.1984558105,47.8245811462],"type":"Point"}
}