{
  "type": "Feature",
  "properties": {
    "addr:full":"Rudigierstr 4 Feldkirch Vorarlberg 6800",
    "addr:housenumber":"4",
    "addr:postcode":"6800",
    "addr:street":"Rudigierstr",
    "iso:country":"AT",
    "sg:address":"Rudigierstr 4",
    "sg:city":"Feldkirch",
    "sg:orig_category":"Bettfedern",
    "sg:phone":"+43 5522 730040",
    "sg:postcode":"6800",
    "sg:province":"Vorarlberg",
    "wof:name":"Germa Bettfedernvollreinigung",
    "wof:placetype":"venue"
},
  "geometry": {"coordinates":[9.6083078384,47.2461547852],"type":"Point"}
}