{
  "type": "Feature",
  "properties": {
    "iso:country":"AT",
    "sg:address":"Simon Hafner-Pl 6",
    "sg:city":"Unzmarkt",
    "sg:orig_category":"Bankomat-Standorte",
    "sg:phone":"+43 3583 23170",
    "sg:postcode":"8800",
    "sg:province":"Steiermark",
    "wof:name":"Bankomat d Raiffeisenbank Judenburg regGenmbH",
    "wof:placetype":"venue"
},
  "geometry": {"coordinates":[14.4461374283,47.1993293762],"type":"Point"}
}