{
  "type": "Feature",
  "properties": {
    "iso:country":"AT",
    "sg:address":"Wei\u00dfenbachstr 1",
    "sg:city":"Wolfsberg",
    "sg:orig_category":"Lebensmittel / Einzelhandel",
    "sg:phone":"+43 4352 35345",
    "sg:postcode":"9400",
    "sg:province":"K\u00e4rnten",
    "wof:name":"ADEG aktiv Markt",
    "wof:placetype":"venue"
},
  "geometry": {"coordinates":[14.8418502808,46.8402099609],"type":"Point"}
}