{
  "type": "Feature",
  "properties": {
    "addr:full":"Linzer Str 60 Marchtrenk Ober\u00f6sterreich 4614",
    "addr:housenumber":"60",
    "addr:postcode":"4614",
    "addr:street":"Linzer Str",
    "iso:country":"AT",
    "sg:address":"Linzer Str 60",
    "sg:city":"Marchtrenk",
    "sg:orig_category":"Installationsunternehmen",
    "sg:phone":"+43 7243 52770",
    "sg:postcode":"4614",
    "sg:province":"Ober\u00f6sterreich",
    "sg:website":"mallezek.at",
    "wof:name":"Mallezek Gas-Wasser-Heizung GmbH",
    "wof:placetype":"venue"
},
  "geometry": {"coordinates":[14.1201152802,48.1918334961],"type":"Point"}
}