{
  "type": "Feature",
  "properties": {
    "addr:full":"Maurerg 12 Neunkirchen Nieder\u00f6sterreich 2620",
    "addr:housenumber":"12",
    "addr:postcode":"2620",
    "addr:street":"Maurerg",
    "iso:country":"AT",
    "sg:address":"Maurerg 12",
    "sg:city":"Neunkirchen",
    "sg:orig_category":"Elektroinstallationsunternehmen",
    "sg:phone":"+43 2635 620340",
    "sg:postcode":"2620",
    "sg:province":"Nieder\u00f6sterreich",
    "wof:name":"Haberbichler Wilhelm",
    "wof:placetype":"venue"
},
  "geometry": {"coordinates":[16.0865936279,47.717918396],"type":"Point"}
}