{
  "type": "Feature",
  "properties": {
    "addr:full":"Nr 1 Oberndorf an der Melk Nieder\u00f6sterreich 3281",
    "addr:postcode":"3281",
    "addr:street":"Nr;Niederoesterreich",
    "iso:country":"AT",
    "sg:address":"Nr 1",
    "sg:city":"Oberndorf an der Melk",
    "sg:orig_category":"Tischlereien",
    "sg:phone":"+43 7483 238",
    "sg:postcode":"3281",
    "sg:province":"Nieder\u00f6sterreich",
    "wof:name":"Fr\u00f6schl Franz",
    "wof:placetype":"venue"
},
  "geometry": {"coordinates":[12.6447954178,49.2060699463],"type":"Point"}
}