{
  "type": "Feature",
  "properties": {
    "addr:full":"Br\u00fcnner Str 79-81 Gerasdorf Nieder\u00f6sterreich 2201",
    "addr:postcode":"79-81;2201",
    "addr:street":"Str;Niederoesterreich",
    "iso:country":"AT",
    "sg:address":"Br\u00fcnner Str 79-81",
    "sg:city":"Gerasdorf",
    "sg:orig_category":"Autoreparatur",
    "sg:phone":"+43 4322 4634200",
    "sg:postcode":"2201",
    "sg:province":"Nieder\u00f6sterreich",
    "wof:name":"MS KFZ-Reparatur- u TaxibetriebsgesmbH",
    "wof:placetype":"venue"
},
  "geometry": {"coordinates":[16.4708862305,48.2990150452],"type":"Point"}
}