{
  "type": "Feature",
  "properties": {
    "iso:country":"AT",
    "sg:address":"Nr 30",
    "sg:city":"Litschau",
    "sg:orig_category":"Imkereien",
    "sg:phone":"+43 2865 8414",
    "sg:postcode":"3874",
    "sg:province":"Nieder\u00f6sterreich",
    "wof:name":"Nosko Franz",
    "wof:placetype":"venue"
},
  "geometry": {"coordinates":[15.0453643799,48.9441757202],"type":"Point"}
}