{
  "type": "Feature",
  "properties": {
    "iso:country":"AT",
    "sg:address":"Triester Str 1",
    "sg:city":"Wien",
    "sg:orig_category":"Non-Classified Establishments",
    "sg:phone":"+43 1 6042390",
    "sg:postcode":"1100",
    "sg:province":"Wien",
    "wof:name":"Evangelisches Pfarramt AB",
    "wof:placetype":"venue"
},
  "geometry": {"coordinates":[16.358757019,48.1789245605],"type":"Point"}
}