{
  "type": "Feature",
  "properties": {
    "addr:full":"Hutteng 43 Wien Wien 1160",
    "addr:housenumber":"43",
    "addr:postcode":"1160",
    "addr:street":"Hutteng",
    "iso:country":"AT",
    "sg:address":"Hutteng 43",
    "sg:city":"Wien",
    "sg:orig_category":"Tankstellen",
    "sg:phone":"+43 1 9857595",
    "sg:postcode":"1160",
    "sg:province":"Wien",
    "wof:name":"Shell Austria GmbH",
    "wof:placetype":"venue"
},
  "geometry": {"coordinates":[16.3088874817,48.2070159912],"type":"Point"}
}