{
  "type": "Feature",
  "properties": {
    "addr:full":"Stadtpl 23 Schwanenstadt Ober\u00f6sterreich 4690",
    "addr:housenumber":"23",
    "addr:postcode":"4690",
    "addr:street":"Stadtpl",
    "iso:country":"AT",
    "sg:address":"Stadtpl 23",
    "sg:city":"Schwanenstadt",
    "sg:orig_category":"Damenmoden",
    "sg:phone":"+43 767322720",
    "sg:postcode":"4690",
    "sg:province":"Ober\u00f6sterreich",
    "wof:name":"Stelzhammer Moden GmbH",
    "wof:placetype":"venue"
},
  "geometry": {"coordinates":[13.775478363,48.0555725098],"type":"Point"}
}