{
  "type": "Feature",
  "properties": {
    "addr:full":"Scheibbser Str 15a Wieselburg an der Erlauf Nieder\u00f6sterreich 3250",
    "addr:housenumber":"15a",
    "addr:postcode":"3250",
    "addr:street":"Str",
    "iso:country":"AT",
    "sg:address":"Scheibbser Str 15a",
    "sg:city":"Wieselburg an der Erlauf",
    "sg:orig_category":"Autoreparatur",
    "sg:phone":"+43 4374 1652284",
    "sg:postcode":"3250",
    "sg:province":"Nieder\u00f6sterreich",
    "wof:name":"Heher Peter",
    "wof:placetype":"venue"
},
  "geometry": {"coordinates":[15.1376533508,48.1236076355],"type":"Point"}
}