{
  "type": "Feature",
  "properties": {
    "addr:full":"Nr 52 Griffen K\u00e4rnten 9112",
    "addr:postcode":"9112",
    "addr:street":"Nr;Griffen Kaernten",
    "iso:country":"AT",
    "sg:address":"Nr 52",
    "sg:city":"Griffen",
    "sg:orig_category":"Forstverwaltungen",
    "sg:phone":"+43 4233 2429",
    "sg:postcode":"9112",
    "sg:province":"K\u00e4rnten",
    "wof:name":"Forstverwaltung Forstgut Saualpe",
    "wof:placetype":"venue"
},
  "geometry": {"coordinates":[166.9221496582,-0.5282999873],"type":"Point"}
}