{
  "type": "Feature",
  "properties": {
    "addr:full":"Pl\u00fcddemanng 67a Graz Steiermark 8010",
    "addr:housenumber":"67a",
    "addr:postcode":"8010",
    "addr:street":"Plueddemanng",
    "iso:country":"AT",
    "sg:address":"Pl\u00fcddemanng 67a",
    "sg:city":"Graz",
    "sg:orig_category":"Alternativtherapie",
    "sg:phone":"+43 316 4266660",
    "sg:postcode":"8010",
    "sg:province":"Steiermark",
    "wof:name":"Wittmann Maike Dr med univ",
    "wof:placetype":"venue"
},
  "geometry": {"coordinates":[15.4431800842,47.0685653687],"type":"Point"}
}