{
  "type": "Feature",
  "properties": {
    "iso:country":"AT",
    "sg:address":"Gewerbegebiet",
    "sg:city":"Reutte",
    "sg:classifiers":[
        {
            "category":"Professional",
            "subcategory":"Printing & Photocopies",
            "type":"Services"
        }
    ],
    "sg:phone":"+43 4356 72208",
    "sg:postcode":"6600",
    "sg:province":"Tirol",
    "wof:name":"ARTPRESS DRUCKEREI GMBH",
    "wof:placetype":"venue"
},
  "geometry": {"coordinates":[10.6828422546,47.4664840698],"type":"Point"}
}