{
  "type": "Feature",
  "properties": {
    "addr:full":"Hauptstr 13 Rust Burgenland 7071",
    "addr:housenumber":"13",
    "addr:postcode":"7071",
    "addr:street":"Hauptstr",
    "iso:country":"AT",
    "sg:address":"Hauptstr 13",
    "sg:city":"Rust",
    "sg:orig_category":"Bars-Cafes",
    "sg:phone":"+43 4326 85379",
    "sg:postcode":"7071",
    "sg:province":"Burgenland",
    "wof:name":"Giefing Erich",
    "wof:placetype":"venue"
},
  "geometry": {"coordinates":[16.6753940582,47.8013954163],"type":"Point"}
}