{
  "type": "Feature",
  "properties": {
    "addr:full":"Rottweilerstr 2 Imst Tirol 6460",
    "addr:housenumber":"2",
    "addr:postcode":"6460",
    "addr:street":"Rottweilerstr;Tirol",
    "iso:country":"AT",
    "sg:address":"Rottweilerstr 2",
    "sg:city":"Imst",
    "sg:classifiers":[
        {
            "category":"Restaurant",
            "type":"Food & Drink"
        }
    ],
    "sg:phone":"+43 5412 66414",
    "sg:postcode":"6460",
    "sg:province":"Tirol",
    "wof:name":"Landhotel Hohe Warte",
    "wof:placetype":"venue"
},
  "geometry": {"coordinates":[10.7316226959,47.2331733704],"type":"Point"}
}