{
  "type": "Feature",
  "properties": {
    "addr:full":"Palfner Str 12 Bad Gastein Salzburg 5640",
    "addr:housenumber":"12",
    "addr:postcode":"5640",
    "addr:street":"Str;Salzburg",
    "iso:country":"AT",
    "sg:address":"Palfner Str 12",
    "sg:city":"Bad Gastein",
    "sg:orig_category":"Schlossereien",
    "sg:phone":"+43 4364 3424300",
    "sg:postcode":"5640",
    "sg:province":"Salzburg",
    "wof:name":"Koren Arnulf Bau- u Portalbau - Stahl- u Portalbau - Alukonstruktionen",
    "wof:placetype":"venue"
},
  "geometry": {"coordinates":[13.1372232437,47.1061592102],"type":"Point"}
}