{
  "type": "Feature",
  "properties": {
    "iso:country":"AT",
    "sg:address":"Nr 5A",
    "sg:city":"Innermanzing",
    "sg:orig_category":"Gutsverwaltungen",
    "sg:phone":"+43 2774 2444",
    "sg:postcode":"3052",
    "sg:province":"Nieder\u00f6sterreich",
    "wof:name":"Gut Tannenm\u00fchle - Blaas Elisabeth",
    "wof:placetype":"venue"
},
  "geometry": {"coordinates":[15.9236516953,48.1282501221],"type":"Point"}
}