{
  "type": "Feature",
  "properties": {
    "addr:full":"Neunkirchner Str 31 Ternitz Nieder\u00f6sterreich 2630",
    "addr:postcode":"2630",
    "addr:street":"Str 31",
    "iso:country":"AT",
    "sg:address":"Neunkirchner Str 31",
    "sg:city":"Ternitz",
    "sg:classifiers":[
        {
            "category":"Restaurant",
            "type":"Food & Drink"
        }
    ],
    "sg:phone":"+43 2635 64360",
    "sg:postcode":"2630",
    "sg:province":"Nieder\u00f6sterreich",
    "sg:tags":[
        "pizzeria"
    ],
    "wof:name":"AK LEVENT Pizzeria Ristorante Riccardo",
    "wof:placetype":"venue"
},
  "geometry": {"coordinates":[16.0686817169,47.7135162354],"type":"Point"}
}