{
  "type": "Feature",
  "properties": {
    "iso:country":"AT",
    "sg:address":"Brockmanng 46",
    "sg:city":"Graz",
    "sg:orig_category":"Stoffe / Erzeugung U Gro\u00c3\u0178handel",
    "sg:phone":"+43 316 837124",
    "sg:postcode":"8010",
    "sg:province":"Steiermark",
    "wof:name":"Modestoff VertriebsgmbH",
    "wof:placetype":"venue"
},
  "geometry": {"coordinates":[15.4484176636,47.0636634827],"type":"Point"}
}