{
  "type": "Feature",
  "properties": {
    "addr:full":"Marktstr 37 Dornbirn Vorarlberg 6850",
    "addr:housenumber":"37",
    "addr:postcode":"6850",
    "addr:street":"Marktstr",
    "iso:country":"AT",
    "sg:address":"Marktstr 37",
    "sg:city":"Dornbirn",
    "sg:orig_category":"Steuerberatung",
    "sg:phone":"+43 5572 31200",
    "sg:postcode":"6850",
    "sg:province":"Vorarlberg",
    "wof:name":"K\u00f6nig Helmut Dipl-Vw",
    "wof:placetype":"venue"
},
  "geometry": {"coordinates":[9.7425365448,47.4114646912],"type":"Point"}
}