{
  "type": "Feature",
  "properties": {
    "addr:full":"Pastorstr 2a/1 Wien Wien 1210",
    "addr:housenumber":"2a / 1",
    "addr:postcode":"1210",
    "addr:street":"Pastorstr",
    "iso:country":"AT",
    "sg:address":"Pastorstr 2a/1",
    "sg:city":"Wien",
    "sg:orig_category":"\u00c3\u201erzte / F Allgemeinmedizin",
    "sg:phone":"+43 1 2584663",
    "sg:postcode":"1210",
    "sg:province":"Wien",
    "wof:name":"Kiesel Alexander Dr",
    "wof:placetype":"venue"
},
  "geometry": {"coordinates":[16.4473743439,48.2675895691],"type":"Point"}
}