{
  "type": "Feature",
  "properties": {
    "addr:full":"Kircheng 5 Tulln an der Donau Nieder\u00f6sterreich 3430",
    "addr:housenumber":"5",
    "addr:postcode":"3430",
    "addr:street":"Kircheng",
    "iso:country":"AT",
    "sg:address":"Kircheng 5",
    "sg:city":"Tulln an der Donau",
    "sg:orig_category":"Textilreinigung",
    "sg:phone":"+43 2272 62342",
    "sg:postcode":"3430",
    "sg:province":"Nieder\u00f6sterreich",
    "wof:name":"Putzerei Ing Gerhard Weinstabel",
    "wof:placetype":"venue"
},
  "geometry": {"coordinates":[16.0545940399,48.3307685852],"type":"Point"}
}