{
  "type": "Feature",
  "properties": {
    "iso:country":"AT",
    "sg:address":"Nr 133",
    "sg:city":"Berwang",
    "sg:classifiers":[
        {
            "category":"Restaurant",
            "type":"Food & Drink"
        }
    ],
    "sg:phone":"+43 5674 8375",
    "sg:postcode":"6622",
    "sg:province":"Tirol",
    "wof:name":"Restaurant-Cafe-Konditorei Mirabell",
    "wof:placetype":"venue"
},
  "geometry": {"coordinates":[10.7468204498,47.4090003967],"type":"Point"}
}