{
  "type": "Feature",
  "properties": {
    "addr:full":"Brunnenweg 4 Hallwang Salzburg 5300",
    "addr:housenumber":"4",
    "addr:postcode":"5300",
    "addr:street":"Brunnenweg;Salzburg",
    "iso:country":"AT",
    "sg:address":"Brunnenweg 4",
    "sg:city":"Hallwang",
    "sg:orig_category":"Steuerberatung",
    "sg:phone":"+43 4362 253198",
    "sg:postcode":"5300",
    "sg:province":"Salzburg",
    "wof:name":"Maurerlehner-Aichriedler Christine",
    "wof:placetype":"venue"
},
  "geometry": {"coordinates":[13.1086120605,47.8556518555],"type":"Point"}
}