{
  "type": "Feature",
  "properties": {
    "addr:full":"Jahng 40 Wien Wien 1050",
    "addr:housenumber":"40",
    "addr:postcode":"1050",
    "addr:street":"Jahng",
    "iso:country":"AT",
    "sg:address":"Jahng 40",
    "sg:city":"Wien",
    "sg:orig_category":"Baumeister",
    "sg:phone":"+43 664 5803989",
    "sg:postcode":"1050",
    "sg:province":"Wien",
    "wof:name":"JN-Bau",
    "wof:placetype":"venue"
},
  "geometry": {"coordinates":[16.357465744,48.1834983826],"type":"Point"}
}