{
  "type": "Feature",
  "properties": {
    "addr:full":"Lienfelderg. 91-93 Wien Wien 1170",
    "addr:postcode":"91-93;1170",
    "iso:country":"AT",
    "sg:address":"Lienfelderg. 91-93",
    "sg:city":"Wien",
    "sg:classifiers":[
        {
            "category":"Wholesale",
            "subcategory":"Drugs",
            "type":"Manufacturing & Wholesale Goods"
        }
    ],
    "sg:phone":"+43 4314 801600",
    "sg:postcode":"1170",
    "sg:province":"Wien",
    "sg:tags":[
        "chemical",
        "pharmaceutical"
    ],
    "wof:name":"MADAUS GES.MBH",
    "wof:placetype":"venue"
},
  "geometry": {"coordinates":[16.3176422119,48.2220840454],"type":"Point"}
}