{
  "type": "Feature",
  "properties": {
    "addr:full":"Grazer Str 17-19 Wiener Neustadt Nieder\u00f6sterreich 2700",
    "addr:postcode":"17-19;2700",
    "addr:street":"Str;Niederoesterreich",
    "iso:country":"AT",
    "sg:address":"Grazer Str 17-19",
    "sg:city":"Wiener Neustadt",
    "sg:orig_category":"Fitnesscenter",
    "sg:phone":"+43 4326 2281263",
    "sg:postcode":"2700",
    "sg:province":"Nieder\u00f6sterreich",
    "wof:name":"SHAPE-LINE Ort f\u00fcr Figur u Wohlbefinden",
    "wof:placetype":"venue"
},
  "geometry": {"coordinates":[16.2480831146,47.821308136],"type":"Point"}
}