{
  "type": "Feature",
  "properties": {
    "addr:full":"Liechtingerg 2 Neunkirchen Nieder\u00f6sterreich 2620",
    "addr:housenumber":"2",
    "addr:postcode":"2620",
    "addr:street":"Liechtingerg",
    "iso:country":"AT",
    "sg:address":"Liechtingerg 2",
    "sg:city":"Neunkirchen",
    "sg:orig_category":"Volksschulen",
    "sg:phone":"+43 4326 3037593",
    "sg:postcode":"2620",
    "sg:province":"Nieder\u00f6sterreich",
    "wof:name":"Volksschule",
    "wof:placetype":"venue"
},
  "geometry": {"coordinates":[16.0363445282,47.7392272949],"type":"Point"}
}