{
  "type": "Feature",
  "properties": {
    "addr:full":"Siebenst\u00e4dterstr 15 Salzburg Salzburg 5020",
    "addr:housenumber":"15",
    "addr:postcode":"5020",
    "addr:street":"Siebenstaedterstr;Salzburg",
    "iso:country":"AT",
    "sg:address":"Siebenst\u00e4dterstr 15",
    "sg:city":"Salzburg",
    "sg:orig_category":"Baumeister",
    "sg:phone":"+43 4366 2421109",
    "sg:postcode":"5020",
    "sg:province":"Salzburg",
    "wof:name":"FEGA Bau GmbH & Co KG",
    "wof:placetype":"venue"
},
  "geometry": {"coordinates":[13.033033371,47.8125038147],"type":"Point"}
}