{
  "type": "Feature",
  "properties": {
    "addr:full":"Robert-Stolz-Str 7 Linz Ober\u00f6sterreich 4020",
    "addr:housenumber":"7",
    "addr:postcode":"4020",
    "addr:street":"Robert-Stolz-Str",
    "iso:country":"AT",
    "sg:address":"Robert-Stolz-Str 7",
    "sg:city":"Linz",
    "sg:orig_category":"Architekten",
    "sg:phone":"+43 732 6694170",
    "sg:postcode":"4020",
    "sg:province":"Ober\u00f6sterreich",
    "wof:name":"St\u00f6gm\u00fcller Heinz Dipl-Ing",
    "wof:placetype":"venue"
},
  "geometry": {"coordinates":[14.2764625549,48.285610199],"type":"Point"}
}