{
  "type": "Feature",
  "properties": {
    "addr:full":"Nr 13 Globasnitz K\u00e4rnten 9142",
    "addr:postcode":"9142",
    "addr:street":"Nr;Globasnitz Kaernten",
    "iso:country":"AT",
    "sg:address":"Nr 13",
    "sg:city":"Globasnitz",
    "sg:orig_category":"Elektroinstallationsunternehmen",
    "sg:phone":"+43 4230 223",
    "sg:postcode":"9142",
    "sg:province":"K\u00e4rnten",
    "wof:name":"Wutte Georg",
    "wof:placetype":"venue"
},
  "geometry": {"coordinates":[14.7002391815,46.5574455261],"type":"Point"}
}