{
  "type": "Feature",
  "properties": {
    "addr:full":"Sigmund-Freud-Pl 1 Feldbach Steiermark 8330",
    "addr:housenumber":"1",
    "addr:postcode":"8330",
    "addr:street":"Sigmund-Freud-Pl",
    "iso:country":"AT",
    "sg:address":"Sigmund-Freud-Pl 1",
    "sg:city":"Feldbach",
    "sg:orig_category":"Psychotherapie",
    "sg:phone":"+43 4331 52898400",
    "sg:postcode":"8330",
    "sg:province":"Steiermark",
    "wof:name":"Schwarz Gisela Dr",
    "wof:placetype":"venue"
},
  "geometry": {"coordinates":[15.886882782,46.9577598572],"type":"Point"}
}