{
  "type": "Feature",
  "properties": {
    "addr:full":"Spitalstr 11 Vorau Steiermark 8250",
    "addr:housenumber":"11",
    "addr:postcode":"8250",
    "addr:street":"Spitalstr",
    "iso:country":"AT",
    "sg:address":"Spitalstr 11",
    "sg:city":"Vorau",
    "sg:orig_category":"Rauchfangkehrer",
    "sg:phone":"+43 3337 271424",
    "sg:postcode":"8250",
    "sg:province":"Steiermark",
    "wof:name":"Ingruber Johann jr",
    "wof:placetype":"venue"
},
  "geometry": {"coordinates":[15.8842830658,47.4055290222],"type":"Point"}
}