{
  "type": "Feature",
  "properties": {
    "addr:full":"Bundesstr 10 Rietz Tirol 6421",
    "addr:housenumber":"10",
    "addr:postcode":"6421",
    "addr:street":"Bundesstr;Tirol",
    "iso:country":"AT",
    "sg:address":"Bundesstr 10",
    "sg:city":"Rietz",
    "sg:orig_category":"Autospenglereien",
    "sg:phone":"+43 5262 63528",
    "sg:postcode":"6421",
    "sg:province":"Tirol",
    "wof:name":"Dosch Johann",
    "wof:placetype":"venue"
},
  "geometry": {"coordinates":[11.023563385,47.2914085388],"type":"Point"}
}