{
  "type": "Feature",
  "properties": {
    "iso:country":"AT",
    "sg:address":"Bundesstr 10",
    "sg:city":"Rietz",
    "sg:orig_category":"Autospenglereien",
    "sg:phone":"+43 5262 63528",
    "sg:postcode":"6421",
    "sg:province":"Tirol",
    "wof:name":"Dosch Johann",
    "wof:placetype":"venue"
},
  "geometry": {"coordinates":[11.023563385,47.2914085388],"type":"Point"}
}