{
  "type": "Feature",
  "properties": {
    "addr:full":"Karl-Wagner-Pl 1 St. Veit an der Glan K\u00e4rnten 9300",
    "addr:housenumber":"1",
    "addr:postcode":"9300",
    "addr:street":"Karl-Wagner-Pl;Kaernten",
    "iso:country":"AT",
    "sg:address":"Karl-Wagner-Pl 1",
    "sg:city":"St. Veit an der Glan",
    "sg:orig_category":"Tabaktrafiken",
    "sg:phone":"+43 4212 2712",
    "sg:postcode":"9300",
    "sg:province":"K\u00e4rnten",
    "wof:name":"Polesnig Georg Ing",
    "wof:placetype":"venue"
},
  "geometry": {"coordinates":[14.3664798737,46.770401001],"type":"Point"}
}