{
  "type": "Feature",
  "properties": {
    "addr:full":"Herzog-Friedrich-Str 3 Innsbruck Tirol 6020",
    "addr:housenumber":"3",
    "addr:postcode":"6020",
    "addr:street":"Herzog-Friedrich-Str;Tirol",
    "iso:country":"AT",
    "sg:address":"Herzog-Friedrich-Str 3",
    "sg:city":"Innsbruck",
    "sg:orig_category":"Tabaktrafiken",
    "sg:phone":"+43 512 587381",
    "sg:postcode":"6020",
    "sg:province":"Tirol",
    "wof:name":"Gr\u00e4ssle Elmar",
    "wof:placetype":"venue"
},
  "geometry": {"coordinates":[11.392375946,47.2685508728],"type":"Point"}
}