{
  "type": "Feature",
  "properties": {
    "iso:country":"AT",
    "sg:address":"Hauptpl 12",
    "sg:city":"Leibnitz",
    "sg:orig_category":"Eisenwaren",
    "sg:phone":"+43 4334 52827440",
    "sg:postcode":"8430",
    "sg:province":"Steiermark",
    "wof:name":"Ulbel Paul GmbH & Co KG",
    "wof:placetype":"venue"
},
  "geometry": {"coordinates":[15.539308548,46.7819480896],"type":"Point"}
}