{
  "type": "Feature",
  "properties": {
    "addr:full":"Marieng 8 Leibnitz Steiermark 8430",
    "addr:housenumber":"8",
    "addr:postcode":"8430",
    "addr:street":"Marieng;Steiermark",
    "iso:country":"AT",
    "sg:address":"Marieng 8",
    "sg:city":"Leibnitz",
    "sg:orig_category":"Tischlereien",
    "sg:phone":"+43 4334 5282232",
    "sg:postcode":"8430",
    "sg:province":"Steiermark",
    "sg:website":"bischoff.co.at",
    "wof:name":"Bischoff KG Einrichtungswerkst\u00e4tte",
    "wof:placetype":"venue"
},
  "geometry": {"coordinates":[15.5453548431,46.7759666443],"type":"Point"}
}