{
  "type": "Feature",
  "properties": {
    "addr:full":"Taborstr 53/1 Wien Wien 1020",
    "addr:housenumber":"1",
    "addr:postcode":"1020",
    "iso:country":"AT",
    "sg:address":"Taborstr 53/1",
    "sg:city":"Wien",
    "sg:orig_category":"Werbeagenturen",
    "sg:phone":"+43 1 9545000",
    "sg:postcode":"1020",
    "sg:province":"Wien",
    "wof:name":"Citymotion WerbegesmbH",
    "wof:placetype":"venue"
},
  "geometry": {"coordinates":[16.381570816,48.2209663391],"type":"Point"}
}