{
  "type": "Feature",
  "properties": {
    "addr:full":"Kindergartenweg 1 Lermoos Tirol 6631",
    "addr:housenumber":"1",
    "addr:postcode":"6631",
    "addr:street":"Kindergartenweg;Tirol",
    "iso:country":"AT",
    "sg:address":"Kindergartenweg 1",
    "sg:city":"Lermoos",
    "sg:orig_category":"Appartements / Ferienwohnungen",
    "sg:phone":"+43 5673 2416",
    "sg:postcode":"6631",
    "sg:province":"Tirol",
    "wof:name":"Haus Alexandra",
    "wof:placetype":"venue"
},
  "geometry": {"coordinates":[10.8827209473,47.4028701782],"type":"Point"}
}