{
  "type": "Feature",
  "properties": {
    "addr:full":"Hadikgasse 78 Wien Wien 1140",
    "addr:housenumber":"78",
    "addr:postcode":"1140",
    "addr:street":"Hadikgasse",
    "iso:country":"AT",
    "sg:address":"Hadikgasse 78",
    "sg:city":"Wien",
    "sg:classifiers":[
        {
            "category":"Professional",
            "subcategory":"Advertising",
            "type":"Services"
        }
    ],
    "sg:phone":"+43 1 8972847",
    "sg:postcode":"1140",
    "sg:province":"Wien",
    "sg:tags":[
        "agency"
    ],
    "sg:website":"www.z-works.at",
    "wof:name":"z-works Werbeagentur Zwertnig & Mesaric OEG",
    "wof:placetype":"venue"
},
  "geometry": {"coordinates":[16.3012065887,48.1887931824],"type":"Point"}
}