{
  "type": "Feature",
  "properties": {
    "addr:full":"Auhofstr 40 Wien Wien 1130",
    "addr:housenumber":"40",
    "addr:postcode":"1130",
    "addr:street":"Auhofstr",
    "iso:country":"AT",
    "sg:address":"Auhofstr 40",
    "sg:city":"Wien",
    "sg:orig_category":"Ingenieurkonsulenten / Zivilingenieure",
    "sg:phone":"+43 1 8771611",
    "sg:postcode":"1130",
    "sg:province":"Wien",
    "wof:name":"Keszthelyi Gabor Dipl-Ing Dr",
    "wof:placetype":"venue"
},
  "geometry": {"coordinates":[16.2911319733,48.1883392334],"type":"Point"}
}