{
  "type": "Feature",
  "properties": {
    "addr:full":"Rainerstr 17 Ried im Innkreis Ober\u00f6sterreich 4910",
    "addr:housenumber":"17",
    "addr:postcode":"4910",
    "addr:street":"Rainerstr",
    "iso:country":"AT",
    "sg:address":"Rainerstr 17",
    "sg:city":"Ried im Innkreis",
    "sg:orig_category":"Damenmoden",
    "sg:phone":"+43 7752 82486",
    "sg:postcode":"4910",
    "sg:province":"Ober\u00f6sterreich",
    "wof:name":"Cilli Damenmoden",
    "wof:placetype":"venue"
},
  "geometry": {"coordinates":[13.4862766266,48.2078361511],"type":"Point"}
}