{
  "type": "Feature",
  "properties": {
    "addr:full":"Marktpl 23 Kirchberg am Wagram Nieder\u00f6sterreich 3470",
    "addr:housenumber":"23",
    "addr:postcode":"3470",
    "addr:street":"Marktpl",
    "iso:country":"AT",
    "sg:address":"Marktpl 23",
    "sg:city":"Kirchberg am Wagram",
    "sg:orig_category":"Friseure U Frisiersalons",
    "sg:phone":"+43 4322 792294",
    "sg:postcode":"3470",
    "sg:province":"Nieder\u00f6sterreich",
    "wof:name":"Brandl Alexandra",
    "wof:placetype":"venue"
},
  "geometry": {"coordinates":[15.8971977234,48.4348144531],"type":"Point"}
}