{
  "type": "Feature",
  "properties": {
    "iso:country":"AT",
    "sg:address":"Herrnhauspl 10",
    "sg:city":"Brixlegg",
    "sg:orig_category":"Tabaktrafiken",
    "sg:phone":"+43 5337 63605",
    "sg:postcode":"6230",
    "sg:province":"Tirol",
    "wof:name":"Gredler Friedrich",
    "wof:placetype":"venue"
},
  "geometry": {"coordinates":[11.8779993057,47.4296073914],"type":"Point"}
}