{
  "type": "Feature",
  "properties": {
    "addr:full":"Oberdorf 7 Weng im Innkreis Ober\u00f6sterreich 4952",
    "addr:housenumber":"7",
    "addr:postcode":"4952",
    "addr:street":"Oberdorf",
    "iso:country":"AT",
    "sg:address":"Oberdorf 7",
    "sg:city":"Weng im Innkreis",
    "sg:orig_category":"Tischlereien",
    "sg:phone":"+43 7723 5094",
    "sg:postcode":"4952",
    "sg:province":"Ober\u00f6sterreich",
    "wof:name":"Reitinger Karl",
    "wof:placetype":"venue"
},
  "geometry": {"coordinates":[13.1799316406,48.233417511],"type":"Point"}
}