{
  "type": "Feature",
  "properties": {
    "addr:full":"Hauptstr 124 Wien Wien 1140",
    "addr:housenumber":"124",
    "addr:postcode":"1140",
    "addr:street":"Hauptstr",
    "iso:country":"AT",
    "sg:address":"Hauptstr 124",
    "sg:city":"Wien",
    "sg:orig_category":"Filmproduktionen",
    "sg:phone":"+43 1 5953979",
    "sg:postcode":"1140",
    "sg:province":"Wien",
    "wof:name":"Promotion Pictures - Pavlousek OEG",
    "wof:placetype":"venue"
},
  "geometry": {"coordinates":[16.2117118835,48.2090415955],"type":"Point"}
}