{
  "type": "Feature",
  "properties": {
    "addr:full":"Landstr. 53 Linz Ober\u00f6sterreich 4020",
    "addr:housenumber":"53",
    "addr:postcode":"4020",
    "addr:street":"Landstr.",
    "iso:country":"AT",
    "sg:address":"Landstr. 53",
    "sg:city":"Linz",
    "sg:classifiers":[
        {
            "category":"Personal",
            "subcategory":"Shoe Repair & Shine",
            "type":"Services"
        }
    ],
    "sg:phone":"+43 4373 2775112",
    "sg:postcode":"4020",
    "sg:province":"Ober\u00f6sterreich",
    "sg:tags":[
        "leather"
    ],
    "wof:name":"SCHUHAUS EILEER VIVA GMBH",
    "wof:placetype":"venue"
},
  "geometry": {"coordinates":[14.2915086746,48.2991676331],"type":"Point"}
}