{
  "type": "Feature",
  "properties": {
    "addr:full":"Auenfischerstr 44 Wolfsberg K\u00e4rnten 9400",
    "addr:housenumber":"44;kaernten",
    "addr:postcode":"9400",
    "addr:street":"Auenfischerstr",
    "iso:country":"AT",
    "sg:address":"Auenfischerstr 44",
    "sg:city":"Wolfsberg",
    "sg:orig_category":"Daten- U Aktenvernichtung",
    "sg:phone":"+43 4352 364000",
    "sg:postcode":"9400",
    "sg:province":"K\u00e4rnten",
    "wof:name":"Reisswolf Akten- und Datenvernichtung GmbH",
    "wof:placetype":"venue"
},
  "geometry": {"coordinates":[14.8437595367,46.8170700073],"type":"Point"}
}