{
  "type": "Feature",
  "properties": {
    "addr:full":"Salztorg 6 Wien Wien 1010",
    "addr:housenumber":"6",
    "addr:postcode":"1010",
    "addr:street":"Salztorg",
    "iso:country":"AT",
    "sg:address":"Salztorg 6",
    "sg:city":"Wien",
    "sg:orig_category":"Videotheken",
    "sg:phone":"+43 1 5332321",
    "sg:postcode":"1010",
    "sg:province":"Wien",
    "wof:name":"Austria Video Ring",
    "wof:placetype":"venue"
},
  "geometry": {"coordinates":[16.3735694885,48.2135009766],"type":"Point"}
}