{
  "type": "Feature",
  "properties": {
    "iso:country":"AT",
    "sg:address":"Au 8",
    "sg:city":"Gro\u00dfarl",
    "sg:orig_category":"Erdarbeiten",
    "sg:phone":"+43 6414 8341",
    "sg:postcode":"5611",
    "sg:province":"Salzburg",
    "wof:name":"Gruber Hubert - Erdbau",
    "wof:placetype":"venue"
},
  "geometry": {"coordinates":[-114.0853424072,47.1626281738],"type":"Point"}
}