{
  "type": "Feature",
  "properties": {
    "addr:full":"Hauptstr 3 Hinterbr\u00fchl Nieder\u00f6sterreich 2371",
    "addr:housenumber":"3",
    "addr:postcode":"2371",
    "addr:street":"Hauptstr;Niederoesterreich",
    "iso:country":"AT",
    "sg:address":"Hauptstr 3",
    "sg:city":"Hinterbr\u00fchl",
    "sg:orig_category":"Spenglereien",
    "sg:phone":"+43 2236 25524",
    "sg:postcode":"2371",
    "sg:province":"Nieder\u00f6sterreich",
    "wof:name":"Haindl Gerhard",
    "wof:placetype":"venue"
},
  "geometry": {"coordinates":[16.2570762634,48.0845947266],"type":"Point"}
}