{
  "type": "Feature",
  "properties": {
    "addr:full":"Verdig 3 St. Georgen am Steinfelde Nieder\u00f6sterreich 3151",
    "addr:housenumber":"3",
    "addr:postcode":"3151",
    "addr:street":"Verdig",
    "iso:country":"AT",
    "sg:address":"Verdig 3",
    "sg:city":"St. Georgen am Steinfelde",
    "sg:orig_category":"Hufschmiede",
    "sg:phone":"+43 4327 42885634",
    "sg:postcode":"3151",
    "sg:province":"Nieder\u00f6sterreich",
    "wof:name":"Vavra Robert - Kutschenfahrten",
    "wof:placetype":"venue"
},
  "geometry": {"coordinates":[15.6132936478,48.1385231018],"type":"Point"}
}