{
  "type": "Feature",
  "properties": {
    "addr:full":"Nordstr. 3  Eugendorf Salzburg 5301",
    "addr:housenumber":"3",
    "addr:postcode":"5301",
    "addr:street":"Nordstr.;Salzburg",
    "iso:country":"AT",
    "sg:address":"Nordstr. 3 ",
    "sg:city":"Eugendorf",
    "sg:classifiers":[
        {
            "category":"Professional",
            "subcategory":"Engineering",
            "type":"Services"
        }
    ],
    "sg:phone":"+43 4362 258541",
    "sg:postcode":"5301",
    "sg:province":"Salzburg",
    "sg:tags":[
        "machine",
        "-",
        "mechanical"
    ],
    "wof:name":"HERBERT MUELLNER",
    "wof:placetype":"venue"
},
  "geometry": {"coordinates":[13.1253881454,47.8693237305],"type":"Point"}
}