{
  "type": "Feature",
  "properties": {
    "addr:full":"Gmunden Ober\u00f6sterreich 4810",
    "addr:postcode":"4810",
    "addr:street":"Oberoesterreich",
    "iso:country":"AT",
    "sg:city":"Gmunden",
    "sg:orig_category":"Bildung And Forschung, Museen",
    "sg:postcode":"4810",
    "sg:province":"Ober\u00f6sterreich",
    "sg:website":"http://www.dioezese-linz.at/pfarren/gmunden/kinderstunde.asp",
    "wof:name":"Kindergottesdienste in der Stadtpfarre Gmunden",
    "wof:placetype":"venue"
},
  "geometry": {"coordinates":[13.7981462479,47.918598175],"type":"Point"}
}