{
  "type": "Feature",
  "properties": {
    "addr:full":"Sandgrube 13 Krems an der Donau Nieder\u00f6sterreich 3500",
    "addr:housenumber":"13",
    "addr:postcode":"3500",
    "addr:street":"Sandgrube",
    "iso:country":"AT",
    "sg:address":"Sandgrube 13",
    "sg:city":"Krems an der Donau",
    "sg:orig_category":"Genossenschaften",
    "sg:phone":"+43 4327 32855110",
    "sg:postcode":"3500",
    "sg:province":"Nieder\u00f6sterreich",
    "wof:name":"Winzer Krems regGenmbH",
    "wof:placetype":"venue"
},
  "geometry": {"coordinates":[15.6187601089,48.4202766418],"type":"Point"}
}