{
  "type": "Feature",
  "properties": {
    "addr:full":"Walser Str 36 Hirschegg Vorarlberg 6992",
    "addr:housenumber":"36",
    "addr:postcode":"6992",
    "addr:street":"Str",
    "iso:country":"AT",
    "sg:address":"Walser Str 36",
    "sg:city":"Hirschegg",
    "sg:orig_category":"Lebensmittel / Einzelhandel",
    "sg:phone":"+43 4355 175436",
    "sg:postcode":"6992",
    "sg:province":"Vorarlberg",
    "wof:name":"Spar-Markt Janko",
    "wof:placetype":"venue"
},
  "geometry": {"coordinates":[10.1688728333,47.3459243774],"type":"Point"}
}