{
  "type": "Feature",
  "properties": {
    "addr:full":"Gruberstr 45 Linz Ober\u00f6sterreich 4020",
    "addr:housenumber":"45",
    "addr:postcode":"4020",
    "addr:street":"Gruberstr",
    "iso:country":"AT",
    "sg:address":"Gruberstr 45",
    "sg:city":"Linz",
    "sg:orig_category":"Banken U Sparkassen",
    "sg:phone":"+43 4350 10040012",
    "sg:postcode":"4020",
    "sg:province":"Ober\u00f6sterreich",
    "wof:name":"Allgemeine Sparkasse Ober\u00f6sterreich Bank AG",
    "wof:placetype":"venue"
},
  "geometry": {"coordinates":[14.3004169464,48.3064994812],"type":"Point"}
}