{
  "type": "Feature",
  "properties": {
    "iso:country":"AT",
    "sg:address":"Burgpl 3a",
    "sg:city":"Villach",
    "sg:orig_category":"Steuerberatung",
    "sg:phone":"+43 4242 225440",
    "sg:postcode":"9500",
    "sg:province":"K\u00e4rnten",
    "wof:name":"Waldner Helmut Dr Steuerberatungsges-Wirtschaftstreuhand KEG",
    "wof:placetype":"venue"
},
  "geometry": {"coordinates":[13.844124794,46.6156005859],"type":"Point"}
}