{
  "type": "Feature",
  "properties": {
    "addr:full":"K\u00f6nigswiese 12 Seewalchen am Attersee Ober\u00f6sterreich 4863",
    "addr:housenumber":"12",
    "addr:postcode":"4863",
    "addr:street":"Koenigswiese",
    "iso:country":"AT",
    "sg:address":"K\u00f6nigswiese 12",
    "sg:city":"Seewalchen am Attersee",
    "sg:orig_category":"Steuerungstechnik",
    "sg:phone":"+43 4376 624191",
    "sg:postcode":"4863",
    "sg:province":"Ober\u00f6sterreich",
    "wof:name":"Reiter Peter",
    "wof:placetype":"venue"
},
  "geometry": {"coordinates":[13.5783233643,47.9527130127],"type":"Point"}
}