{
  "type": "Feature",
  "properties": {
    "addr:full":"Hagenbrunner Strasse 49 Bisamberg Nieder\u00f6sterreich 2102",
    "addr:housenumber":"49",
    "addr:postcode":"2102",
    "addr:street":"Hagenbrunner Strasse",
    "iso:country":"AT",
    "sg:address":"Hagenbrunner Strasse 49",
    "sg:city":"Bisamberg",
    "sg:classifiers":[
        {
            "category":"Military Area",
            "subcategory":"Air Force Base",
            "type":"Public Place"
        }
    ],
    "sg:phone":"+43 2262 629000",
    "sg:postcode":"2102",
    "sg:province":"Nieder\u00f6sterreich",
    "sg:tags":[
        "window",
        "skylight",
        "dormer"
    ],
    "sg:website":"ing-veleta.at",
    "wof:name":"Ing. R. Veleta GesmbH & Co KG",
    "wof:placetype":"venue"
},
  "geometry": {"coordinates":[16.3739376068,48.3315353394],"type":"Point"}
}