{
  "type": "Feature",
  "properties": {
    "addr:full":"W\u00e4hringer Str 66 Wien Wien 1090",
    "addr:postcode":"1090",
    "addr:street":"Str 66",
    "iso:country":"AT",
    "sg:address":"W\u00e4hringer Str 66",
    "sg:city":"Wien",
    "sg:orig_category":"Restaurants: Italienisch",
    "sg:phone":"+43 1 3174942",
    "sg:postcode":"1090",
    "sg:province":"Wien",
    "wof:name":"Restaurant Francesco",
    "wof:placetype":"venue"
},
  "geometry": {"coordinates":[16.3521976471,48.2231369019],"type":"Point"}
}