{
  "type": "Feature",
  "properties": {
    "iso:country":"AT",
    "sg:address":"Tschusistr 16",
    "sg:city":"Hallein",
    "sg:orig_category":"Speditionen",
    "sg:phone":"+43 6245 713440",
    "sg:postcode":"5400",
    "sg:province":"Salzburg",
    "wof:name":"Europa Fracht SpeditionsgesmbH",
    "wof:placetype":"venue"
},
  "geometry": {"coordinates":[13.1051874161,47.6860237122],"type":"Point"}
}