{
  "type": "Feature",
  "properties": {
    "addr:full":"Kirchg 6 Oberdrauburg K\u00e4rnten 9781",
    "addr:housenumber":"6",
    "addr:postcode":"9781",
    "addr:street":"Kirchg;Kaernten",
    "iso:country":"AT",
    "sg:address":"Kirchg 6",
    "sg:city":"Oberdrauburg",
    "sg:orig_category":"Non-Classified Establishments",
    "sg:phone":"+43 4710 2289",
    "sg:postcode":"9781",
    "sg:province":"K\u00e4rnten",
    "wof:name":"Pfarramt",
    "wof:placetype":"venue"
},
  "geometry": {"coordinates":[12.9694042206,46.749332428],"type":"Point"}
}