{
  "type": "Feature",
  "properties": {
    "iso:country":"AT",
    "sg:address":"Templstr 16",
    "sg:city":"Innsbruck",
    "sg:orig_category":"Logistik",
    "sg:phone":"+43 512 588588",
    "sg:postcode":"6020",
    "sg:province":"Tirol",
    "wof:name":"Pancheri Hubert - Logistik Service",
    "wof:placetype":"venue"
},
  "geometry": {"coordinates":[11.3935403824,47.2604179382],"type":"Point"}
}