{
  "type": "Feature",
  "properties": {
    "iso:country":"AT",
    "sg:address":"Franz Riepl-G 29",
    "sg:city":"Graz",
    "sg:classifiers":[
        {
            "category":"Professional",
            "subcategory":"Computer Services",
            "type":"Services"
        }
    ],
    "sg:phone":"+43 316 274813",
    "sg:postcode":"8020",
    "sg:province":"Steiermark",
    "sg:tags":[
        "software"
    ],
    "wof:name":"CONCEPT Datasystems Systemanalyse und Softwareentwicklung GesmbH",
    "wof:placetype":"venue"
},
  "geometry": {"coordinates":[15.4185085297,47.0547790527],"type":"Point"}
}