{
  "type": "Feature",
  "properties": {
    "addr:full":"Margareteng\u00fcrtel 116 Wien Wien 1050",
    "addr:housenumber":"116",
    "addr:postcode":"1050",
    "iso:country":"AT",
    "sg:address":"Margareteng\u00fcrtel 116",
    "sg:city":"Wien",
    "sg:orig_category":"Banken U Sparkassen",
    "sg:phone":"+43 5 050532680",
    "sg:postcode":"1050",
    "sg:province":"Wien",
    "wof:name":"Bank Austria Creditanstalt AG",
    "wof:placetype":"venue"
},
  "geometry": {"coordinates":[16.3584918976,48.19165802],"type":"Point"}
}