{
  "type": "Feature",
  "properties": {
    "iso:country":"AT",
    "sg:address":"Illpark",
    "sg:city":"Feldkirch",
    "sg:orig_category":"Textilreinigung",
    "sg:phone":"+43 699 10509012",
    "sg:postcode":"6800",
    "sg:province":"Vorarlberg",
    "wof:name":"Hille Textilpflege",
    "wof:placetype":"venue"
},
  "geometry": {"coordinates":[9.5844116211,47.2480163574],"type":"Point"}
}