{
  "type": "Feature",
  "properties": {
    "addr:full":"Eichstr 58 Gnigl Salzburg 5023",
    "addr:housenumber":"58",
    "addr:postcode":"5023",
    "addr:street":"Eichstr",
    "iso:country":"AT",
    "sg:address":"Eichstr 58",
    "sg:city":"Gnigl",
    "sg:orig_category":"Non-Classified Establishments",
    "sg:phone":"+43 662 640779",
    "sg:postcode":"5023",
    "sg:province":"Salzburg",
    "wof:name":"Pfarramt Gnigl",
    "wof:placetype":"venue"
},
  "geometry": {"coordinates":[13.0752487183,47.811870575],"type":"Point"}
}