{
  "type": "Feature",
  "properties": {
    "addr:full":"Machlandstr 37 Perg Ober\u00f6sterreich 4320",
    "addr:housenumber":"37",
    "addr:postcode":"4320",
    "addr:street":"Machlandstr",
    "iso:country":"AT",
    "sg:address":"Machlandstr 37",
    "sg:city":"Perg",
    "sg:orig_category":"Minigolfanlagen U -Bedarf",
    "sg:phone":"+43 664 5306260",
    "sg:postcode":"4320",
    "sg:province":"Ober\u00f6sterreich",
    "wof:name":"Minigolfplatz Sigis Treff",
    "wof:placetype":"venue"
},
  "geometry": {"coordinates":[14.639380455,48.2436904907],"type":"Point"}
}