{
  "type": "Feature",
  "properties": {
    "addr:full":"Kaspar-Harb-G Leibnitz Steiermark 8430",
    "addr:postcode":"8430",
    "iso:country":"AT",
    "sg:address":"Kaspar-Harb-G",
    "sg:city":"Leibnitz",
    "sg:orig_category":"Blumeneinzelhandel",
    "sg:phone":"+43 3452 82110",
    "sg:postcode":"8430",
    "sg:province":"Steiermark",
    "wof:name":"Pechloff Rosalia",
    "wof:placetype":"venue"
},
  "geometry": {"coordinates":[15.5431203842,46.784828186],"type":"Point"}
}