{
  "type": "Feature",
  "properties": {
    "addr:full":"Hilprigen 15 Frankenburg am Hausruck Ober\u00f6sterreich 4873",
    "addr:housenumber":"15",
    "addr:postcode":"4873",
    "addr:street":"Hilprigen",
    "iso:country":"AT",
    "sg:address":"Hilprigen 15",
    "sg:city":"Frankenburg am Hausruck",
    "sg:orig_category":"Gemeinden",
    "sg:phone":"+43 76838355",
    "sg:postcode":"4873",
    "sg:province":"Ober\u00f6sterreich",
    "wof:name":"Gemeindeamt Redleiten",
    "wof:placetype":"venue"
},
  "geometry": {"coordinates":[13.4677848816,48.0819168091],"type":"Point"}
}