{
  "type": "Feature",
  "properties": {
    "addr:full":"Vorberg 358 Ramsau am Dachstein Steiermark 8972",
    "addr:housenumber":"358",
    "addr:postcode":"8972",
    "addr:street":"Vorberg",
    "iso:country":"AT",
    "sg:address":"Vorberg 358",
    "sg:city":"Ramsau am Dachstein",
    "sg:orig_category":"Pensionen / Privatzimmer",
    "sg:phone":"+43 3687 815700",
    "sg:postcode":"8972",
    "sg:province":"Steiermark",
    "wof:name":"Haus Feriengl\u00fcck Bachler Gerhard",
    "wof:placetype":"venue"
},
  "geometry": {"coordinates":[13.6386823654,47.4179039001],"type":"Point"}
}