{
  "type": "Feature",
  "properties": {
    "addr:full":"Gumpendorfer Str 5a Wien Wien 1060",
    "addr:housenumber":"5a",
    "addr:postcode":"1060",
    "addr:street":"Str",
    "iso:country":"AT",
    "sg:address":"Gumpendorfer Str 5a",
    "sg:city":"Wien",
    "sg:orig_category":"Tonstudios",
    "sg:phone":"+43 1 5874364",
    "sg:postcode":"1060",
    "sg:province":"Wien",
    "wof:name":"Jackson George-Sanford",
    "wof:placetype":"venue"
},
  "geometry": {"coordinates":[16.3619022369,48.2005882263],"type":"Point"}
}