{
  "type": "Feature",
  "properties": {
    "addr:full":"Fisching 2 Wei\u00dfkirchen in Steiermark Steiermark 8741",
    "addr:housenumber":"2",
    "addr:postcode":"8741",
    "addr:street":"Fisching",
    "iso:country":"AT",
    "sg:address":"Fisching 2",
    "sg:city":"Wei\u00dfkirchen in Steiermark",
    "sg:orig_category":"Werbeagenturen",
    "sg:phone":"+43 4367 69570625",
    "sg:postcode":"8741",
    "sg:province":"Steiermark",
    "wof:name":"Werbeagentur Grafikerei",
    "wof:placetype":"venue"
},
  "geometry": {"coordinates":[14.7354774475,47.1580924988],"type":"Point"}
}