{
  "type": "Feature",
  "properties": {
    "addr:full":"H\u00f6llererstr 1 Bruck an der Gro\u00dfglocknerstra\u00dfe Salzburg 5671",
    "addr:housenumber":"1",
    "addr:postcode":"5671",
    "addr:street":"Hoellererstr;Grossglocknerstrasse Salzburg",
    "iso:country":"AT",
    "sg:address":"H\u00f6llererstr 1",
    "sg:city":"Bruck an der Gro\u00dfglocknerstra\u00dfe",
    "sg:orig_category":"Lebensmittel / Erzeugung U Gro\u00c3\u0178handel",
    "sg:phone":"+43 4365 4520047",
    "sg:postcode":"5671",
    "sg:province":"Salzburg",
    "wof:name":"Dekaj Johanna",
    "wof:placetype":"venue"
},
  "geometry": {"coordinates":[12.8262853622,47.2858848572],"type":"Point"}
}