{
  "type": "Feature",
  "properties": {
    "addr:full":"Himberger Str 3 Gansbach Nieder\u00f6sterreich 3122",
    "addr:housenumber":"3",
    "addr:postcode":"3122",
    "addr:street":"Str",
    "iso:country":"AT",
    "sg:address":"Himberger Str 3",
    "sg:city":"Gansbach",
    "sg:orig_category":"Rettungsdienste",
    "sg:phone":"+43 2753 244",
    "sg:postcode":"3122",
    "sg:province":"Nieder\u00f6sterreich",
    "wof:name":"Arbeiter Samariter Bund \u00f6sterreichs Rettungsstelle Gansbach",
    "wof:placetype":"venue"
},
  "geometry": {"coordinates":[15.4733419418,48.3075332642],"type":"Point"}
}