{
  "type": "Feature",
  "properties": {
    "addr:full":"Inzersdorf im Kremstal 197 Kirchdorf an der Krems Ober\u00f6sterreich 4560",
    "addr:housenumber":"197",
    "addr:postcode":"4560",
    "addr:street":"Inzersdorf;Kremstal",
    "iso:country":"AT",
    "sg:address":"Inzersdorf im Kremstal 197",
    "sg:city":"Kirchdorf an der Krems",
    "sg:classifiers":[
        {
            "category":"Communications",
            "subcategory":"Television Station",
            "type":"Services"
        }
    ],
    "sg:phone":"+43 7582 81506",
    "sg:postcode":"4560",
    "sg:province":"Ober\u00f6sterreich",
    "sg:tags":[
        "array",
        "satellite",
        "aerial",
        "reception",
        "antenna"
    ],
    "wof:name":"Rudolf Winkler",
    "wof:placetype":"venue"
},
  "geometry": {"coordinates":[14.0811481476,47.927116394],"type":"Point"}
}