{
  "type": "Feature",
  "properties": {
    "addr:full":"Klosterwiesg 18 Graz Steiermark 8010",
    "addr:housenumber":"18",
    "addr:postcode":"8010",
    "addr:street":"Klosterwiesg",
    "iso:country":"AT",
    "sg:address":"Klosterwiesg 18",
    "sg:city":"Graz",
    "sg:orig_category":"Glasereien",
    "sg:phone":"+43 316 8263920",
    "sg:postcode":"8010",
    "sg:province":"Steiermark",
    "sg:website":"preiner.at",
    "wof:name":"Preiner OHG",
    "wof:placetype":"venue"
},
  "geometry": {"coordinates":[15.4440603256,47.0657463074],"type":"Point"}
}