{
  "type": "Feature",
  "properties": {
    "addr:full":"Donaufelder Str 203 Wien Wien 1220",
    "addr:housenumber":"203",
    "addr:postcode":"1220",
    "iso:country":"AT",
    "sg:address":"Donaufelder Str 203",
    "sg:city":"Wien",
    "sg:orig_category":"Digitaldruck",
    "sg:phone":"+43 1 8955584",
    "sg:postcode":"1220",
    "sg:province":"Wien",
    "wof:name":"PLACARD-LINE - Richard Kubac",
    "wof:placetype":"venue"
},
  "geometry": {"coordinates":[16.4351882935,48.2508811951],"type":"Point"}
}