{
  "type": "Feature",
  "properties": {
    "iso:country":"AT",
    "sg:address":"Alexanderhofstr 34",
    "sg:city":"Millstatt",
    "sg:orig_category":"Pensionen / Privatzimmer",
    "sg:phone":"+43 4347 662192",
    "sg:postcode":"9872",
    "sg:province":"K\u00e4rnten",
    "wof:name":"Pension Haus Rose",
    "wof:placetype":"venue"
},
  "geometry": {"coordinates":[13.5624103546,46.809261322],"type":"Point"}
}