{
  "type": "Feature",
  "properties": {
    "addr:full":"Schleifferg 4 Erpfendorf Tirol 6383",
    "addr:housenumber":"4",
    "addr:postcode":"6383",
    "addr:street":"Schleifferg",
    "iso:country":"AT",
    "sg:address":"Schleifferg 4",
    "sg:city":"Erpfendorf",
    "sg:orig_category":"Appartements / Ferienwohnungen",
    "sg:phone":"+43 5352 8152",
    "sg:postcode":"6383",
    "sg:province":"Tirol",
    "wof:name":"Tirolerhof",
    "wof:placetype":"venue"
},
  "geometry": {"coordinates":[12.4797649384,47.5764122009],"type":"Point"}
}