{
  "type": "Feature",
  "properties": {
    "addr:full":"Kleeblattg 13 Wien Wien 1010",
    "addr:housenumber":"13",
    "addr:postcode":"1010",
    "addr:street":"Kleeblattg",
    "iso:country":"AT",
    "sg:address":"Kleeblattg 13",
    "sg:city":"Wien",
    "sg:classifiers":[
        {
            "category":"Internet Cafe",
            "subcategory":"None",
            "type":"Food & Drink"
        }
    ],
    "sg:phone":"+43 1 4057682",
    "sg:postcode":"1010",
    "sg:province":"Wien",
    "wof:name":"Kabel New Media Wien GmbH",
    "wof:placetype":"venue"
},
  "geometry": {"coordinates":[16.3707885742,48.2106971741],"type":"Point"}
}