{
  "type": "Feature",
  "properties": {
    "addr:full":"Kircheng 2a R\u00fcckersdorf-Harmannsdorf Nieder\u00f6sterreich 2111",
    "addr:housenumber":"2a",
    "addr:postcode":"2111",
    "addr:street":"Kircheng;Niederoesterreich",
    "iso:country":"AT",
    "sg:address":"Kircheng 2a",
    "sg:city":"R\u00fcckersdorf-Harmannsdorf",
    "sg:orig_category":"Physiotherapie",
    "sg:phone":"+43 2264 7375",
    "sg:postcode":"2111",
    "sg:province":"Nieder\u00f6sterreich",
    "wof:name":"Metz Rudolf",
    "wof:placetype":"venue"
},
  "geometry": {"coordinates":[16.3716926575,48.3917503357],"type":"Point"}
}