{
  "type": "Feature",
  "properties": {
    "addr:full":"Nr 120 Hohentauern Steiermark 8785",
    "addr:postcode":"8785",
    "addr:street":"Nr",
    "iso:country":"AT",
    "sg:address":"Nr 120",
    "sg:city":"Hohentauern",
    "sg:orig_category":"Mietautos",
    "sg:phone":"+43 3618 206",
    "sg:postcode":"8785",
    "sg:province":"Steiermark",
    "wof:name":"Kandler Georg",
    "wof:placetype":"venue"
},
  "geometry": {"coordinates":[14.4843893051,47.4336090088],"type":"Point"}
}