{
  "type": "Feature",
  "properties": {
    "addr:full":"Nr 9 P\u00f6ggstall Nieder\u00f6sterreich 3650",
    "addr:postcode":"3650",
    "addr:street":"Nr;Poeggstall Niederoesterreich",
    "iso:country":"AT",
    "sg:address":"Nr 9",
    "sg:city":"P\u00f6ggstall",
    "sg:orig_category":"Pensionen / Privatzimmer",
    "sg:phone":"+43 4327 582909",
    "sg:postcode":"3650",
    "sg:province":"Nieder\u00f6sterreich",
    "wof:name":"Aigner Karl u Gertraude",
    "wof:placetype":"venue"
},
  "geometry": {"coordinates":[15.2011241913,48.3180274963],"type":"Point"}
}