{
  "type": "Feature",
  "properties": {
    "iso:country":"AT",
    "sg:address":"Schwarzenbach 69",
    "sg:city":"St. Wolfgang im Salzkammergut",
    "sg:orig_category":"Canalisation",
    "sg:phone":"+43 6138 2734",
    "sg:postcode":"5360",
    "sg:province":"Ober\u00f6sterreich",
    "sg:website":"nierlich.net",
    "wof:name":"Nierlich GmbH",
    "wof:placetype":"venue"
},
  "geometry": {"coordinates":[13.4459896088,47.7398490906],"type":"Point"}
}