{
  "type": "Feature",
  "properties": {
    "addr:full":"Favoritenstr 52 Wien Wien 1040",
    "addr:housenumber":"52",
    "addr:postcode":"1040",
    "addr:street":"Favoritenstr",
    "iso:country":"AT",
    "sg:address":"Favoritenstr 52",
    "sg:city":"Wien",
    "sg:classifiers":[
        {
            "category":"Travel",
            "subcategory":"Hotels & Motels",
            "type":"Entertainment"
        }
    ],
    "sg:phone":"+43 1 50516060",
    "sg:postcode":"1040",
    "sg:province":"Wien",
    "wof:name":"Austria Trend Hotel beim Theresianum",
    "wof:placetype":"venue"
},
  "geometry": {"coordinates":[16.3722286224,48.1892242432],"type":"Point"}
}