{
  "type": "Feature",
  "properties": {
    "iso:country":"AT",
    "sg:address":"Kernstockg 3a",
    "sg:city":"Fohnsdorf",
    "sg:orig_category":"Erdarbeiten",
    "sg:phone":"+43 4335 732367",
    "sg:postcode":"8753",
    "sg:province":"Steiermark",
    "wof:name":"Maier Alfred u Christine",
    "wof:placetype":"venue"
},
  "geometry": {"coordinates":[14.6826276779,47.188205719],"type":"Point"}
}