{
  "type": "Feature",
  "properties": {
    "addr:full":"Jahnstr 5 Kufstein Tirol 6330",
    "addr:housenumber":"5",
    "addr:postcode":"6330",
    "addr:street":"Jahnstr;Tirol",
    "iso:country":"AT",
    "sg:address":"Jahnstr 5",
    "sg:city":"Kufstein",
    "sg:orig_category":"Bauleitung U -Betreuung",
    "sg:phone":"+43 5372 64334",
    "sg:postcode":"6330",
    "sg:province":"Tirol",
    "wof:name":"Kreutner BauConsult GmbH",
    "wof:placetype":"venue"
},
  "geometry": {"coordinates":[12.1715536118,47.5787391663],"type":"Point"}
}