{
  "type": "Feature",
  "properties": {
    "iso:country":"AT",
    "sg:address":"Vordernberger Str 7",
    "sg:city":"Leoben",
    "sg:orig_category":"Beratungsstellen",
    "sg:phone":"+43 3842 470120",
    "sg:postcode":"8700",
    "sg:province":"Steiermark",
    "wof:name":"LIBIT Leobner Initiative f Beratung Information und Therapie",
    "wof:placetype":"venue"
},
  "geometry": {"coordinates":[15.0902643204,47.379234314],"type":"Point"}
}