{
  "type": "Feature",
  "properties": {
    "iso:country":"AT",
    "sg:address":"Burgg 13",
    "sg:city":"Puchberg am Schneeberg",
    "sg:orig_category":"Hauptschulen",
    "sg:phone":"+43 4326 3631100",
    "sg:postcode":"2734",
    "sg:province":"Nieder\u00f6sterreich",
    "wof:name":"Hauptschule",
    "wof:placetype":"venue"
},
  "geometry": {"coordinates":[15.9133396149,47.7860717773],"type":"Point"}
}