{
  "type": "Feature",
  "properties": {
    "addr:full":"Hauptstr 31/2 Bisamberg Nieder\u00f6sterreich 2102",
    "addr:housenumber":"31 / 2",
    "addr:postcode":"2102",
    "addr:street":"Hauptstr",
    "iso:country":"AT",
    "sg:address":"Hauptstr 31/2",
    "sg:city":"Bisamberg",
    "sg:orig_category":"Politische Parteien",
    "sg:phone":"+43 2262 63816",
    "sg:postcode":"2102",
    "sg:province":"Nieder\u00f6sterreich",
    "wof:name":"Sozialdemokratische Partei \u00f6sterreichs Bezirksorganisation Bisamberg",
    "wof:placetype":"venue"
},
  "geometry": {"coordinates":[16.359336853,48.329460144],"type":"Point"}
}