{
  "type": "Feature",
  "properties": {
    "addr:full":"Seilergasse 16 Wien Wien 1010",
    "addr:housenumber":"16",
    "addr:postcode":"1010",
    "addr:street":"Seilergasse",
    "iso:country":"AT",
    "sg:address":"Seilergasse 16",
    "sg:city":"Wien",
    "sg:classifiers":[
        {
            "category":"Communications",
            "type":"Services"
        }
    ],
    "sg:phone":"+43 1 5121567",
    "sg:postcode":"1010",
    "sg:province":"Wien",
    "sg:tags":[
        "translation"
    ],
    "sg:website":"lingualex.at",
    "wof:name":"LINGUALEX Juridische und Kaufm\u00e4nnische Fach\u00fcbersetzungen GmbH",
    "wof:placetype":"venue"
},
  "geometry": {"coordinates":[16.3701858521,48.2066764832],"type":"Point"}
}