{
  "type": "Feature",
  "properties": {
    "iso:country":"AT",
    "sg:address":"Engelbert-Kessler-Str 17",
    "sg:city":"Riezlern",
    "sg:orig_category":"Transportunternehmen",
    "sg:phone":"+43 4355 175372",
    "sg:postcode":"6991",
    "sg:province":"Vorarlberg",
    "wof:name":"Gebr Rottach Ferntransporte GesmbH",
    "wof:placetype":"venue"
},
  "geometry": {"coordinates":[10.1834726334,47.3588676453],"type":"Point"}
}