{
  "type": "Feature",
  "properties": {
    "addr:full":"Eibeng 59 Wien Wien 1220",
    "addr:housenumber":"59",
    "addr:postcode":"1220",
    "addr:street":"Eibeng",
    "iso:country":"AT",
    "sg:address":"Eibeng 59",
    "sg:city":"Wien",
    "sg:orig_category":"Lebensmittel / Einzelhandel",
    "sg:phone":"+43 1 2859983",
    "sg:postcode":"1220",
    "sg:province":"Wien",
    "wof:name":"Billa AG",
    "wof:placetype":"venue"
},
  "geometry": {"coordinates":[16.4771652222,48.2193145752],"type":"Point"}
}