{
  "type": "Feature",
  "properties": {
    "addr:full":"Hartberger Str 18a Buchkirchen Ober\u00f6sterreich 4611",
    "addr:postcode":"4611",
    "addr:street":"Str 18A",
    "iso:country":"AT",
    "sg:address":"Hartberger Str 18a",
    "sg:city":"Buchkirchen",
    "sg:orig_category":"Werbeagenturen",
    "sg:phone":"+43 7242 28628",
    "sg:postcode":"4611",
    "sg:province":"Ober\u00f6sterreich",
    "wof:name":"Atelier 4611",
    "wof:placetype":"venue"
},
  "geometry": {"coordinates":[14.005361557,48.2312316895],"type":"Point"}
}