{
  "type": "Feature",
  "properties": {
    "iso:country":"AT",
    "sg:address":"Bachstrasse 66",
    "sg:city":"Gnigl",
    "sg:classifiers":[
        {
            "category":"Building & Trades",
            "subcategory":"Construction",
            "type":"Services"
        }
    ],
    "sg:phone":"+43 662 660677",
    "sg:postcode":"5023",
    "sg:province":"Salzburg",
    "sg:tags":[
        "machine"
    ],
    "wof:name":"FBS Fr\u00e4s-, Bohr- und Schwei\u00dftechnik GmbH",
    "wof:placetype":"venue"
},
  "geometry": {"coordinates":[13.0650949478,47.8233108521],"type":"Point"}
}