{
  "type": "Feature",
  "properties": {
    "addr:full":"Gloriette All. 3 Eisenstadt Burgenland 7000",
    "addr:postcode":"7000",
    "iso:country":"AT",
    "sg:address":"Gloriette All. 3",
    "sg:city":"Eisenstadt",
    "sg:classifiers":[
        {
            "category":"Banks & Credit Unions",
            "subcategory":"Financial Services",
            "type":"Services"
        }
    ],
    "sg:phone":"+43 4326 82641000",
    "sg:postcode":"7000",
    "sg:province":"Burgenland",
    "sg:tags":[
        "banking",
        "finance",
        "insurance"
    ],
    "wof:name":"DER ANKER ALLGEMEINE VERSICHERUNGS AG",
    "wof:placetype":"venue"
},
  "geometry": {"coordinates":[16.5174598694,47.8464813232],"type":"Point"}
}