{
  "type": "Feature",
  "properties": {
    "iso:country":"AT",
    "sg:address":"Ing.-Baller-Str 1",
    "sg:city":"Imst",
    "sg:classifiers":[
        {
            "category":"Taxi",
            "type":"Transportation"
        }
    ],
    "sg:phone":"+43 4354 121718",
    "sg:postcode":"6460",
    "sg:province":"Tirol",
    "sg:tags":[
        "personentransporte",
        "u"
    ],
    "wof:name":"Imster Funktaxizentrale Leys OEG",
    "wof:placetype":"venue"
},
  "geometry": {"coordinates":[10.739941597,47.235824585],"type":"Point"}
}