{
  "type": "Feature",
  "properties": {
    "addr:full":"Iglaseeg 23 Wien Wien 1190",
    "addr:housenumber":"23",
    "addr:postcode":"1190",
    "addr:street":"Iglaseeg",
    "iso:country":"AT",
    "sg:address":"Iglaseeg 23",
    "sg:city":"Wien",
    "sg:orig_category":"Betriebs- U Fernverpflegung",
    "sg:phone":"+43 4313 286057",
    "sg:postcode":"1190",
    "sg:province":"Wien",
    "wof:name":"Sodexho MM Catering GmbH",
    "wof:placetype":"venue"
},
  "geometry": {"coordinates":[16.3473892212,48.2470855713],"type":"Point"}
}