{
  "type": "Feature",
  "properties": {
    "iso:country":"AT",
    "sg:address":"Marktstr 41",
    "sg:city":"Rauris",
    "sg:orig_category":"Pensionen / Privatzimmer",
    "sg:phone":"+43 6544 64290",
    "sg:postcode":"5661",
    "sg:province":"Salzburg",
    "wof:name":"Appartement Landhaus R\u00f6ck",
    "wof:placetype":"venue"
},
  "geometry": {"coordinates":[12.9945297241,47.2276611328],"type":"Point"}
}