{
  "type": "Feature",
  "properties": {
    "iso:country":"AT",
    "sg:address":"Asperner Heldenpl 9",
    "sg:city":"Wien",
    "sg:orig_category":"Hauskrankenpflege / Heimhilfe",
    "sg:phone":"+43 1 282230615",
    "sg:postcode":"1220",
    "sg:province":"Wien",
    "wof:name":"Caritas Betreuen und Pflegen Zuhause",
    "wof:placetype":"venue"
},
  "geometry": {"coordinates":[16.4822807312,48.2176055908],"type":"Point"}
}