{
  "type": "Feature",
  "properties": {
    "iso:country":"AT",
    "sg:address":"Hauptstr 130",
    "sg:city":"Seeboden",
    "sg:orig_category":"Magnetfeldtherapie",
    "sg:phone":"+43 4762 82899",
    "sg:postcode":"9871",
    "sg:province":"K\u00e4rnten",
    "wof:name":"Gfrerer Ines GesmbH & Co KG - MAS-Beratungszentrum",
    "wof:placetype":"venue"
},
  "geometry": {"coordinates":[13.5230102539,46.8185882568],"type":"Point"}
}