{
  "type": "Feature",
  "properties": {
    "addr:full":"Stadtpl 35 Steyr Ober\u00f6sterreich 4400",
    "addr:housenumber":"35",
    "addr:postcode":"4400",
    "addr:street":"Stadtpl;Oberoesterreich",
    "iso:country":"AT",
    "sg:address":"Stadtpl 35",
    "sg:city":"Steyr",
    "sg:classifiers":[
        {
            "category":"Restaurant",
            "type":"Food & Drink"
        }
    ],
    "sg:phone":"+43 7252 42000",
    "sg:postcode":"4400",
    "sg:province":"Ober\u00f6sterreich",
    "wof:name":"Br\u00e4uhof Steyr",
    "wof:placetype":"venue"
},
  "geometry": {"coordinates":[14.4190826416,48.038444519],"type":"Point"}
}