{
  "type": "Feature",
  "properties": {
    "addr:full":"Hilfberg 54/1 Mondsee Ober\u00f6sterreich 5310",
    "addr:housenumber":"54 / 1",
    "addr:postcode":"5310",
    "addr:street":"Hilfberg;Oberoesterreich",
    "iso:country":"AT",
    "sg:address":"Hilfberg 54/1",
    "sg:city":"Mondsee",
    "sg:orig_category":"Markt- U Meinungsforschung",
    "sg:phone":"+43 6232 36642",
    "sg:postcode":"5310",
    "sg:province":"Ober\u00f6sterreich",
    "wof:name":"GFM Austria - Gerlinde Fr\u00f6hlich Marktforschung",
    "wof:placetype":"venue"
},
  "geometry": {"coordinates":[13.3643569946,47.8505172729],"type":"Point"}
}