{
  "type": "Feature",
  "properties": {
    "addr:full":"Klammstrasse 7 Linz Ober\u00f6sterreich 4020",
    "addr:housenumber":"7",
    "addr:postcode":"4020",
    "addr:street":"Klammstrasse",
    "iso:country":"AT",
    "sg:address":"Klammstrasse 7",
    "sg:city":"Linz",
    "sg:classifiers":[
        {
            "category":"Communications",
            "subcategory":"Film & Video Production",
            "type":"Services"
        }
    ],
    "sg:phone":"+43 732 778833",
    "sg:postcode":"4020",
    "sg:province":"Ober\u00f6sterreich",
    "sg:tags":[
        "cartoon"
    ],
    "sg:website":"austrianillustration.com",
    "wof:name":"Roland Reznicek",
    "wof:placetype":"venue"
},
  "geometry": {"coordinates":[14.2830486298,48.3023757935],"type":"Point"}
}