{
  "type": "Feature",
  "properties": {
    "addr:full":"Margaretenstr 146/9 Wien Wien 1050",
    "addr:housenumber":"146 / 9",
    "addr:postcode":"1050",
    "iso:country":"AT",
    "sg:address":"Margaretenstr 146/9",
    "sg:city":"Wien",
    "sg:orig_category":"Filmproduktionen",
    "sg:phone":"+43 4367 64043554",
    "sg:postcode":"1050",
    "sg:province":"Wien",
    "sg:website":"cinewolf.com",
    "wof:name":"Cinewolf Production",
    "wof:placetype":"venue"
},
  "geometry": {"coordinates":[16.3491363525,48.1874237061],"type":"Point"}
}