{
  "type": "Feature",
  "properties": {
    "addr:full":"Gasse 175 Sellrain Tirol 6181",
    "addr:housenumber":"175",
    "addr:postcode":"6181",
    "addr:street":"Gasse;Tirol",
    "iso:country":"AT",
    "sg:address":"Gasse 175",
    "sg:city":"Sellrain",
    "sg:orig_category":"Pensionen / Privatzimmer",
    "sg:phone":"+43 5230 260",
    "sg:postcode":"6181",
    "sg:province":"Tirol",
    "wof:name":"Ferienhof Hiasler",
    "wof:placetype":"venue"
},
  "geometry": {"coordinates":[11.2186784744,47.2184753418],"type":"Point"}
}