{
  "type": "Feature",
  "properties": {
    "addr:full":"Laxenburger Str 60 Wien Wien 1100",
    "addr:housenumber":"60",
    "addr:postcode":"1100",
    "addr:street":"Laxenburger Str",
    "iso:country":"AT",
    "sg:address":"Laxenburger Str 60",
    "sg:city":"Wien",
    "sg:orig_category":"Immobilienverwaltungen",
    "sg:phone":"+43 4316 0406400",
    "sg:postcode":"1100",
    "sg:province":"Wien",
    "wof:name":"Stingl Gerhard Dr",
    "wof:placetype":"venue"
},
  "geometry": {"coordinates":[16.3724937439,48.1740226746],"type":"Point"}
}