{
  "type": "Feature",
  "properties": {
    "iso:country":"AT",
    "sg:address":"Wehrgrabeng 1-5",
    "sg:city":"Steyr",
    "sg:orig_category":"Forschungsinstitute",
    "sg:phone":"+43 7252 884200",
    "sg:postcode":"4400",
    "sg:province":"Ober\u00f6sterreich",
    "wof:name":"PROFACTOR Produktionsforschungs GmbH",
    "wof:placetype":"venue"
},
  "geometry": {"coordinates":[14.4171772003,48.0428771973],"type":"Point"}
}