{
  "type": "Feature",
  "properties": {
    "addr:full":"Atterseestr 40 Lenzing Ober\u00f6sterreich 4860",
    "addr:housenumber":"40",
    "addr:postcode":"4860",
    "addr:street":"Atterseestr",
    "iso:country":"AT",
    "sg:address":"Atterseestr 40",
    "sg:city":"Lenzing",
    "sg:orig_category":"Lebensmittel / Einzelhandel",
    "sg:phone":"+43 767292578",
    "sg:postcode":"4860",
    "sg:province":"Ober\u00f6sterreich",
    "wof:name":"Spar-Markt Inh Helmut Fischer",
    "wof:placetype":"venue"
},
  "geometry": {"coordinates":[13.6098546982,47.9758644104],"type":"Point"}
}