{
  "type": "Feature",
  "properties": {
    "iso:country":"AT",
    "sg:address":"Haflingerweg 1",
    "sg:city":"Weitra",
    "sg:orig_category":"Tischlereien",
    "sg:phone":"+43 2856 2460",
    "sg:postcode":"3970",
    "sg:province":"Nieder\u00f6sterreich",
    "wof:name":"Leitner Alois",
    "wof:placetype":"venue"
},
  "geometry": {"coordinates":[14.8881149292,48.6976127625],"type":"Point"}
}