{
  "type": "Feature",
  "properties": {
    "addr:full":"Yllamg 5 Kalsdorf Steiermark 8401",
    "addr:housenumber":"5",
    "addr:postcode":"8401",
    "addr:street":"Yllamg",
    "iso:country":"AT",
    "sg:address":"Yllamg 5",
    "sg:city":"Kalsdorf",
    "sg:orig_category":"Handelsagenturen",
    "sg:phone":"+43 3135 55006",
    "sg:postcode":"8401",
    "sg:province":"Steiermark",
    "wof:name":"D E HandelsgesmbH",
    "wof:placetype":"venue"
},
  "geometry": {"coordinates":[15.4489994049,46.9848098755],"type":"Point"}
}