{
  "type": "Feature",
  "properties": {
    "addr:full":"Erlauftalstr 109 Kienberg Nieder\u00f6sterreich 3291",
    "addr:housenumber":"109;3291",
    "addr:street":"Kienberg Niederoesterreich",
    "iso:country":"AT",
    "sg:address":"Erlauftalstr 109",
    "sg:city":"Kienberg",
    "sg:classifiers":[
        {
            "category":"Restaurant",
            "type":"Food & Drink"
        }
    ],
    "sg:phone":"+43 7485 98590",
    "sg:postcode":"3291",
    "sg:province":"Nieder\u00f6sterreich",
    "wof:name":"Erlauftalerhof",
    "wof:placetype":"venue"
},
  "geometry": {"coordinates":[15.1209745407,47.9406929016],"type":"Point"}
}