{
  "type": "Feature",
  "properties": {
    "iso:country":"AT",
    "sg:address":"Hochberg 33",
    "sg:city":"Innervillgraten",
    "sg:orig_category":"Zimmereien",
    "sg:phone":"+43 4843 20096",
    "sg:postcode":"9932",
    "sg:province":"Tirol",
    "wof:name":"Zimmerei Schett Andreas",
    "wof:placetype":"venue"
},
  "geometry": {"coordinates":[12.3468561172,46.8186378479],"type":"Point"}
}