{
  "type": "Feature",
  "properties": {
    "iso:country":"AT",
    "sg:address":"Etrichg 11",
    "sg:city":"Innsbruck",
    "sg:orig_category":"Fliesen U Platten",
    "sg:phone":"+43 4351 2343403",
    "sg:postcode":"6020",
    "sg:province":"Tirol",
    "wof:name":"Terra Handels-GesmbH",
    "wof:placetype":"venue"
},
  "geometry": {"coordinates":[11.4316368103,47.2654495239],"type":"Point"}
}