{
  "type": "Feature",
  "properties": {
    "iso:country":"AT",
    "sg:address":"Edmund-Hofbauer-Str 19",
    "sg:city":"Krems an der Donau",
    "sg:orig_category":"Fitnesscenter",
    "sg:phone":"+43 2732 73256",
    "sg:postcode":"3500",
    "sg:province":"Nieder\u00f6sterreich",
    "wof:name":"goodlife Lady",
    "wof:placetype":"venue"
},
  "geometry": {"coordinates":[15.5991687775,48.4071807861],"type":"Point"}
}