{
  "type": "Feature",
  "properties": {
    "addr:full":"Waldgasse 37 Wien Wien 1100",
    "addr:housenumber":"37",
    "addr:postcode":"1100",
    "addr:street":"Waldgasse",
    "iso:country":"AT",
    "sg:address":"Waldgasse 37",
    "sg:city":"Wien",
    "sg:orig_category":"Canalisation",
    "sg:phone":"+43 1 6036778",
    "sg:postcode":"1100",
    "sg:province":"Wien",
    "wof:name":"Pilz & Co Bauges.m.b.H.",
    "wof:placetype":"venue"
},
  "geometry": {"coordinates":[16.381149292,48.1732978821],"type":"Point"}
}