{
  "type": "Feature",
  "properties": {
    "addr:full":"Triester Str 23 Neunkirchen Nieder\u00f6sterreich 2620",
    "addr:housenumber":"23",
    "addr:postcode":"2620",
    "addr:street":"Str",
    "iso:country":"AT",
    "sg:address":"Triester Str 23",
    "sg:city":"Neunkirchen",
    "sg:orig_category":"Stempel",
    "sg:phone":"+43 2635 68960",
    "sg:postcode":"2620",
    "sg:province":"Nieder\u00f6sterreich",
    "wof:name":"PRINTSHOP J\u00e4gersberger",
    "wof:placetype":"venue"
},
  "geometry": {"coordinates":[16.0792942047,47.718837738],"type":"Point"}
}