{
  "type": "Feature",
  "properties": {
    "addr:full":"Hauptstr 35 M\u00fcnchendorf Nieder\u00f6sterreich 2482",
    "addr:housenumber":"35",
    "addr:postcode":"2482",
    "addr:street":"Hauptstr",
    "iso:country":"AT",
    "sg:address":"Hauptstr 35",
    "sg:city":"M\u00fcnchendorf",
    "sg:orig_category":"Non-Classified Establishments",
    "sg:phone":"+43 2259 2278",
    "sg:postcode":"2482",
    "sg:province":"Nieder\u00f6sterreich",
    "wof:name":"Pfarre",
    "wof:placetype":"venue"
},
  "geometry": {"coordinates":[16.3795852661,48.0302963257],"type":"Point"}
}