{
  "type": "Feature",
  "properties": {
    "iso:country":"AT",
    "sg:address":"Neubauerstr 6",
    "sg:city":"Traun",
    "sg:orig_category":"Bestattungsunternehmen",
    "sg:phone":"+43 4372 2969055",
    "sg:postcode":"4050",
    "sg:province":"Ober\u00f6sterreich",
    "wof:name":"Bestattung Wilhelm Alkin GesmbH & Co KG",
    "wof:placetype":"venue"
},
  "geometry": {"coordinates":[14.2375421524,48.221534729],"type":"Point"}
}