{
  "type": "Feature",
  "properties": {
    "addr:full":"Hirtenberger Strasse 9 Leobersdorf Nieder\u00f6sterreich 2544",
    "addr:housenumber":"9",
    "addr:postcode":"2544",
    "addr:street":"Hirtenberger Strasse",
    "iso:country":"AT",
    "sg:address":"Hirtenberger Strasse 9",
    "sg:city":"Leobersdorf",
    "sg:classifiers":[
        {
            "category":"Organizations",
            "subcategory":"Community Association",
            "type":"Services"
        }
    ],
    "sg:phone":"+43 2256 64148",
    "sg:postcode":"2544",
    "sg:province":"Nieder\u00f6sterreich",
    "sg:tags":[
        "stacked",
        "carriers",
        "pallet",
        "equipment",
        "lifter",
        "transporting",
        "brick"
    ],
    "wof:name":"Mayer Transporte GesmbH",
    "wof:placetype":"venue"
},
  "geometry": {"coordinates":[16.225610733,47.9359397888],"type":"Point"}
}