{
  "type": "Feature",
  "properties": {
    "addr:full":"Maria Ebene 17 Frastanz Vorarlberg 6820",
    "addr:housenumber":"17",
    "addr:postcode":"6820",
    "addr:street":"Maria Ebene",
    "iso:country":"AT",
    "sg:address":"Maria Ebene 17",
    "sg:city":"Frastanz",
    "sg:orig_category":"Forschungsinstitute",
    "sg:phone":"+43 5522 727461981",
    "sg:postcode":"6820",
    "sg:province":"Vorarlberg",
    "wof:name":"Universit\u00e4tsinstitut f Suchtforschung",
    "wof:placetype":"venue"
},
  "geometry": {"coordinates":[9.6040058136,47.2208518982],"type":"Point"}
}