{
  "type": "Feature",
  "properties": {
    "addr:full":"Landegger Str 4 Neufeld an der Leitha Burgenland 2491",
    "addr:housenumber":"4",
    "addr:postcode":"2491",
    "addr:street":"Str",
    "iso:country":"AT",
    "sg:address":"Landegger Str 4",
    "sg:city":"Neufeld an der Leitha",
    "sg:classifiers":[
        {
            "category":"Restaurant",
            "type":"Food & Drink"
        }
    ],
    "sg:phone":"+43 4326 2452711",
    "sg:postcode":"2491",
    "sg:province":"Burgenland",
    "wof:name":"Gasthof z Post",
    "wof:placetype":"venue"
},
  "geometry": {"coordinates":[16.3777236938,47.870010376],"type":"Point"}
}