{
  "type": "Feature",
  "properties": {
    "iso:country":"AT",
    "sg:address":"Esterhazystr 1/1/1",
    "sg:city":"Eisenstadt",
    "sg:orig_category":"Steuerberatung",
    "sg:phone":"+43 2682 620690",
    "sg:postcode":"7000",
    "sg:province":"Burgenland",
    "wof:name":"Jobst Michael Ing Mag",
    "wof:placetype":"venue"
},
  "geometry": {"coordinates":[16.5189552307,47.8455657959],"type":"Point"}
}