{
  "type": "Feature",
  "properties": {
    "addr:full":"Josef Benc-G 4 Wien Wien 1230",
    "addr:housenumber":"4",
    "addr:postcode":"1230",
    "addr:street":"Benc-G",
    "iso:country":"AT",
    "sg:address":"Josef Benc-G 4",
    "sg:city":"Wien",
    "sg:orig_category":"Me\u00c3\u0178-, Steuer- U Regeltechnik",
    "sg:phone":"+43 1 661080",
    "sg:postcode":"1230",
    "sg:province":"Wien",
    "wof:name":"Schiebel Antriebstechnik GesmbH",
    "wof:placetype":"venue"
},
  "geometry": {"coordinates":[16.3252925873,48.1392021179],"type":"Point"}
}