{
  "type": "Feature",
  "properties": {
    "addr:full":"Mengerstr 23 Linz Ober\u00f6sterreich 4040",
    "addr:housenumber":"23",
    "addr:postcode":"4040",
    "addr:street":"Mengerstr",
    "iso:country":"AT",
    "sg:address":"Mengerstr 23",
    "sg:city":"Linz",
    "sg:orig_category":"Studentenheime",
    "sg:phone":"+43 732 244011",
    "sg:postcode":"4040",
    "sg:province":"Ober\u00f6sterreich",
    "wof:name":"Katholische Hochschulgemeinde",
    "wof:placetype":"venue"
},
  "geometry": {"coordinates":[14.3153495789,48.3360404968],"type":"Point"}
}