{
  "type": "Feature",
  "properties": {
    "iso:country":"AT",
    "sg:address":"Rinner Str 425",
    "sg:city":"Sistrans",
    "sg:orig_category":"Installationsunternehmen",
    "sg:phone":"+43 512 377691",
    "sg:postcode":"6073",
    "sg:province":"Tirol",
    "wof:name":"Riedle M Ing Installationen GesmbH",
    "wof:placetype":"venue"
},
  "geometry": {"coordinates":[11.4547271729,47.2409629822],"type":"Point"}
}