{
  "type": "Feature",
  "properties": {
    "addr:full":"B\u00fcrgerg 48 Feldbach Steiermark 8330",
    "addr:housenumber":"48",
    "addr:postcode":"8330",
    "addr:street":"Buergerg",
    "iso:country":"AT",
    "sg:address":"B\u00fcrgerg 48",
    "sg:city":"Feldbach",
    "sg:classifiers":[
        {
            "category":"Travel",
            "subcategory":"Hotels & Motels",
            "type":"Entertainment"
        }
    ],
    "sg:phone":"+43 3152 2262",
    "sg:postcode":"8330",
    "sg:province":"Steiermark",
    "wof:name":"Hotel Garni - Gertrude Straka",
    "wof:placetype":"venue"
},
  "geometry": {"coordinates":[15.8557338715,46.9628982544],"type":"Point"}
}