{
  "type": "Feature",
  "properties": {
    "addr:full":"H\u00f6flingstr 22 Eggersdorf Steiermark 8063",
    "addr:housenumber":"22",
    "addr:postcode":"8063",
    "addr:street":"Hoeflingstr",
    "iso:country":"AT",
    "sg:address":"H\u00f6flingstr 22",
    "sg:city":"Eggersdorf",
    "sg:orig_category":"Behinderungen / Leben Mit Behinderungen",
    "sg:phone":"+43 3117 24510",
    "sg:postcode":"8063",
    "sg:province":"Steiermark",
    "wof:name":"Sozialtherapeutikum Eggersdorf",
    "wof:placetype":"venue"
},
  "geometry": {"coordinates":[15.5996646881,47.1230659485],"type":"Point"}
}