{
  "type": "Feature",
  "properties": {
    "addr:full":"Pl\u00f6ven 7 Telfes im Stubai Tirol 6165",
    "addr:housenumber":"7",
    "addr:postcode":"6165",
    "addr:street":"Ploeven;Tirol",
    "iso:country":"AT",
    "sg:address":"Pl\u00f6ven 7",
    "sg:city":"Telfes im Stubai",
    "sg:classifiers":[
        {
            "category":"Shopping",
            "subcategory":"Shoes",
            "type":"Retail Goods"
        }
    ],
    "sg:phone":"+43 5225 623310",
    "sg:postcode":"6165",
    "sg:province":"Tirol",
    "sg:tags":[
        "crampon"
    ],
    "wof:name":"Span Metallwaren Ges.m.b.H.",
    "wof:placetype":"venue"
},
  "geometry": {"coordinates":[11.3586997986,47.1647186279],"type":"Point"}
}