{
  "type": "Feature",
  "properties": {
    "iso:country":"AT",
    "sg:address":"Schieferstr 13",
    "sg:city":"Gr\u00fcnburg",
    "sg:orig_category":"Blitzableiter U Blitzschutzanlagen",
    "sg:phone":"+43 7257 7496",
    "sg:postcode":"4594",
    "sg:province":"Ober\u00f6sterreich",
    "wof:name":"Gegenhuber Michael GesmbH",
    "wof:placetype":"venue"
},
  "geometry": {"coordinates":[5.90102005,49.5250816345],"type":"Point"}
}