{
  "type": "Feature",
  "properties": {
    "iso:country":"AT",
    "sg:address":"Ziegelwerkweg 16a",
    "sg:city":"Leibnitz",
    "sg:orig_category":"Tischlereien",
    "sg:phone":"+43 3452 71725",
    "sg:postcode":"8430",
    "sg:province":"Steiermark",
    "wof:name":"Rauch Manfred",
    "wof:placetype":"venue"
},
  "geometry": {"coordinates":[15.5111408234,46.8114814758],"type":"Point"}
}