{
  "type": "Feature",
  "properties": {
    "addr:full":"Laxenburger Str 58 Wien Wien 1100",
    "addr:housenumber":"58",
    "addr:postcode":"1100",
    "addr:street":"Laxenburger Str",
    "iso:country":"AT",
    "sg:address":"Laxenburger Str 58",
    "sg:city":"Wien",
    "sg:orig_category":"Fotografen",
    "sg:phone":"+43 1 6046122",
    "sg:postcode":"1100",
    "sg:province":"Wien",
    "sg:website":"doriskucera.at",
    "wof:name":"Foto Atelier Doris Kucera",
    "wof:placetype":"venue"
},
  "geometry": {"coordinates":[16.3726425171,48.1743583679],"type":"Point"}
}