{
  "type": "Feature",
  "properties": {
    "addr:full":"Bartwinkel 21a Scharnstein Ober\u00f6sterreich 4644",
    "addr:housenumber":"21a",
    "addr:postcode":"4644",
    "addr:street":"Bartwinkel",
    "iso:country":"AT",
    "sg:address":"Bartwinkel 21a",
    "sg:city":"Scharnstein",
    "sg:orig_category":"Tischlereien",
    "sg:phone":"+43 76154555",
    "sg:postcode":"4644",
    "sg:province":"Ober\u00f6sterreich",
    "wof:name":"Holzinger Ernst",
    "wof:placetype":"venue"
},
  "geometry": {"coordinates":[13.9758758545,47.9131736755],"type":"Point"}
}