{
  "type": "Feature",
  "properties": {
    "addr:full":"Albert-Sch\u00e4dler-Str 4 Feldkirch Vorarlberg 6800",
    "addr:housenumber":"4",
    "addr:postcode":"6800",
    "addr:street":"Albert-Schaedler-Str",
    "iso:country":"AT",
    "sg:address":"Albert-Sch\u00e4dler-Str 4",
    "sg:city":"Feldkirch",
    "sg:orig_category":"Lastkraftwagen",
    "sg:phone":"+43 4355 22730740",
    "sg:postcode":"6800",
    "sg:province":"Vorarlberg",
    "wof:name":"Matt Elmar",
    "wof:placetype":"venue"
},
  "geometry": {"coordinates":[9.6062030792,47.2670783997],"type":"Point"}
}