{
  "type": "Feature",
  "properties": {
    "addr:full":"Weyringerg. 35 Wien Wien 1040",
    "addr:housenumber":"35",
    "addr:postcode":"1040",
    "addr:street":"Weyringerg.",
    "iso:country":"AT",
    "sg:address":"Weyringerg. 35",
    "sg:city":"Wien",
    "sg:classifiers":[
        {
            "category":"Professional",
            "subcategory":"Business Services",
            "type":"Services"
        }
    ],
    "sg:phone":"+43 4315 056740",
    "sg:postcode":"1040",
    "sg:province":"Wien",
    "sg:tags":[
        "advice"
    ],
    "wof:name":"FONDS Z. F\u00d6RDERUNG D. WISSENSCHAFTLICHEN FORSCHUNG",
    "wof:placetype":"venue"
},
  "geometry": {"coordinates":[16.3741989136,48.1881332397],"type":"Point"}
}