{
  "type": "Feature",
  "properties": {
    "addr:full":"Grappaweg 20 Schruns Vorarlberg 6780",
    "addr:housenumber":"20",
    "addr:postcode":"6780",
    "addr:street":"Grappaweg",
    "iso:country":"AT",
    "sg:address":"Grappaweg 20",
    "sg:city":"Schruns",
    "sg:orig_category":"Pensionen / Privatzimmer",
    "sg:phone":"+43 5556 75967",
    "sg:postcode":"6780",
    "sg:province":"Vorarlberg",
    "wof:name":"Stemer Werner",
    "wof:placetype":"venue"
},
  "geometry": {"coordinates":[9.9234933853,47.0840492249],"type":"Point"}
}