{
  "type": "Feature",
  "properties": {
    "iso:country":"AT",
    "sg:address":"Rubringer Str 2",
    "sg:city":"St. Valentin",
    "sg:orig_category":"Textilwaren / Erzeugung U Gro\u00c3\u0178handel",
    "sg:phone":"+43 4374 3553157",
    "sg:postcode":"4300",
    "sg:province":"Nieder\u00f6sterreich",
    "wof:name":"Dolzer Josef GesmbH",
    "wof:placetype":"venue"
},
  "geometry": {"coordinates":[14.5330696106,48.174621582],"type":"Point"}
}