{
  "type": "Feature",
  "properties": {
    "addr:full":"Kaiser-Franz-Josef-Str 10a Bad Ischl Ober\u00f6sterreich 4820",
    "addr:housenumber":"10a",
    "addr:postcode":"4820",
    "addr:street":"Kaiser-Franz-Josef-Str",
    "iso:country":"AT",
    "sg:address":"Kaiser-Franz-Josef-Str 10a",
    "sg:city":"Bad Ischl",
    "sg:orig_category":"Gasversorgungsunternehmen",
    "sg:phone":"+43 4361 32238820",
    "sg:postcode":"4820",
    "sg:province":"Ober\u00f6sterreich",
    "wof:name":"Ober\u00f6sterreichische Ferngas AG",
    "wof:placetype":"venue"
},
  "geometry": {"coordinates":[13.623131752,47.7125816345],"type":"Point"}
}