{
  "type": "Feature",
  "properties": {
    "addr:full":"Hauptstr 56 Eisenstadt Burgenland 7000",
    "addr:housenumber":"56",
    "addr:postcode":"7000",
    "addr:street":"Hauptstr",
    "iso:country":"AT",
    "sg:address":"Hauptstr 56",
    "sg:city":"Eisenstadt",
    "sg:orig_category":"Apotheken",
    "sg:phone":"+43 2682 63870",
    "sg:postcode":"7000",
    "sg:province":"Burgenland",
    "wof:name":"Marien-Apotheke",
    "wof:placetype":"venue"
},
  "geometry": {"coordinates":[16.5259246826,47.8467559814],"type":"Point"}
}