{
  "type": "Feature",
  "properties": {
    "addr:full":"Walfischgasse 11 Wien Wien 1010",
    "addr:housenumber":"11",
    "addr:postcode":"1010",
    "addr:street":"Walfischgasse",
    "iso:country":"AT",
    "sg:address":"Walfischgasse 11",
    "sg:city":"Wien",
    "sg:classifiers":[
        {
            "category":"Wholesale",
            "subcategory":"Books, Periodicals, & Newspapers",
            "type":"Manufacturing & Wholesale Goods"
        }
    ],
    "sg:phone":"+43 1 5125109",
    "sg:postcode":"1010",
    "sg:province":"Wien",
    "sg:tags":[
        "professional",
        "journal",
        "journals",
        "publisher"
    ],
    "sg:website":"lisey.at",
    "wof:name":"Lisey Ges.m.b.H.",
    "wof:placetype":"venue"
},
  "geometry": {"coordinates":[16.3718547821,48.2033920288],"type":"Point"}
}