{
  "type": "Feature",
  "properties": {
    "addr:full":"Daniel-Etter-Str 16 Thalgau Salzburg 5303",
    "addr:housenumber":"16",
    "addr:postcode":"5303",
    "addr:street":"Daniel-Etter-Str;Salzburg",
    "iso:country":"AT",
    "sg:address":"Daniel-Etter-Str 16",
    "sg:city":"Thalgau",
    "sg:orig_category":"Fotografen",
    "sg:phone":"+43 6235 7266",
    "sg:postcode":"5303",
    "sg:province":"Salzburg",
    "wof:name":"Foto Studio",
    "wof:placetype":"venue"
},
  "geometry": {"coordinates":[13.2519340515,47.840877533],"type":"Point"}
}