{
  "type": "Feature",
  "properties": {
    "addr:full":"Untermarkt 25 Reutte Tirol 6600",
    "addr:housenumber":"25",
    "addr:postcode":"6600",
    "addr:street":"Untermarkt;Tirol",
    "iso:country":"AT",
    "sg:address":"Untermarkt 25",
    "sg:city":"Reutte",
    "sg:orig_category":"Museen / Ausstellungen",
    "sg:phone":"+43 5672 72304",
    "sg:postcode":"6600",
    "sg:province":"Tirol",
    "wof:name":"Heimatmuseum, Kulturreferat d Marktgemeinde Reutte",
    "wof:placetype":"venue"
},
  "geometry": {"coordinates":[10.7174692154,47.4907531738],"type":"Point"}
}