{
  "type": "Feature",
  "properties": {
    "addr:full":"Lochm\u00fchle 4 Tschagguns Vorarlberg 6774",
    "addr:housenumber":"4",
    "addr:postcode":"6774",
    "addr:street":"Lochmuehle",
    "iso:country":"AT",
    "sg:address":"Lochm\u00fchle 4",
    "sg:city":"Tschagguns",
    "sg:orig_category":"Pensionen / Privatzimmer",
    "sg:phone":"+43 4355 5673353",
    "sg:postcode":"6774",
    "sg:province":"Vorarlberg",
    "wof:name":"Galehr Heinrich",
    "wof:placetype":"venue"
},
  "geometry": {"coordinates":[9.9019699097,47.0777397156],"type":"Point"}
}