{
  "type": "Feature",
  "properties": {
    "addr:full":"Schneidermannweg 12 Altm\u00fcnster Ober\u00f6sterreich 4813",
    "addr:housenumber":"12",
    "addr:postcode":"4813",
    "addr:street":"Schneidermannweg;Oberoesterreich",
    "iso:country":"AT",
    "sg:address":"Schneidermannweg 12",
    "sg:city":"Altm\u00fcnster",
    "sg:orig_category":"Pensionen / Privatzimmer",
    "sg:phone":"+43 761287066",
    "sg:postcode":"4813",
    "sg:province":"Ober\u00f6sterreich",
    "wof:name":"Bauer Johann",
    "wof:placetype":"venue"
},
  "geometry": {"coordinates":[13.7563419342,47.906578064],"type":"Point"}
}