{
  "type": "Feature",
  "properties": {
    "addr:full":"Rabenberg 11 Ried im Innkreis Ober\u00f6sterreich 4910",
    "addr:housenumber":"11",
    "addr:postcode":"4910",
    "addr:street":"Rabenberg",
    "iso:country":"AT",
    "sg:address":"Rabenberg 11",
    "sg:city":"Ried im Innkreis",
    "sg:classifiers":[
        {
            "category":"Structure",
            "subcategory":"Office Building",
            "type":"Public Place"
        }
    ],
    "sg:phone":"+43 7752 82261",
    "sg:postcode":"4910",
    "sg:province":"Ober\u00f6sterreich",
    "sg:tags":[
        "brick",
        "ceiling",
        "module"
    ],
    "sg:website":"danreiter.at",
    "wof:name":"Ziegelwerk Danreiter & Co KG",
    "wof:placetype":"venue"
},
  "geometry": {"coordinates":[13.4900550842,48.2098655701],"type":"Point"}
}