{
  "type": "Feature",
  "properties": {
    "addr:full":"Ybbsitzer Str 68 Waidhofen an der Ybbs Nieder\u00f6sterreich 3340",
    "addr:postcode":"3340",
    "addr:street":"Str 68",
    "iso:country":"AT",
    "sg:address":"Ybbsitzer Str 68",
    "sg:city":"Waidhofen an der Ybbs",
    "sg:orig_category":"Bauunternehmen",
    "sg:phone":"+43 4374 4253592",
    "sg:postcode":"3340",
    "sg:province":"Nieder\u00f6sterreich",
    "wof:name":"AGes-Bau Asphalt-GesmbH",
    "wof:placetype":"venue"
},
  "geometry": {"coordinates":[14.7818260193,47.9570426941],"type":"Point"}
}