{
  "type": "Feature",
  "properties": {
    "addr:full":"Hauptpl 25 Leibnitz Steiermark 8430",
    "addr:housenumber":"25",
    "addr:postcode":"8430",
    "addr:street":"Hauptpl;Steiermark",
    "iso:country":"AT",
    "sg:address":"Hauptpl 25",
    "sg:city":"Leibnitz",
    "sg:orig_category":"Friseure U Frisiersalons",
    "sg:phone":"+43 4334 5282124",
    "sg:postcode":"8430",
    "sg:province":"Steiermark",
    "wof:name":"Toni & Guy",
    "wof:placetype":"venue"
},
  "geometry": {"coordinates":[15.5378446579,46.7813339233],"type":"Point"}
}