{
  "type": "Feature",
  "properties": {
    "addr:full":"Fresach 41 Fresach K\u00e4rnten 9712",
    "addr:housenumber":"41",
    "addr:postcode":"9712",
    "addr:street":"Kaernten",
    "iso:country":"AT",
    "sg:address":"Fresach 41",
    "sg:city":"Fresach",
    "sg:classifiers":[
        {
            "category":"Home & Garden",
            "subcategory":"Household Appliances",
            "type":"Retail Goods"
        }
    ],
    "sg:phone":"+43 4245 4642",
    "sg:postcode":"9712",
    "sg:province":"K\u00e4rnten",
    "sg:tags":[
        "electric"
    ],
    "wof:name":"Elektrotechnik Gerber",
    "wof:placetype":"venue"
},
  "geometry": {"coordinates":[13.6881408691,46.7136497498],"type":"Point"}
}