{
  "type": "Feature",
  "properties": {
    "iso:country":"AT",
    "sg:address":"Hornberg 19",
    "sg:city":"Dimbach",
    "sg:classifiers":[
        {
            "category":"Building & Trades",
            "subcategory":"Construction",
            "type":"Services"
        }
    ],
    "sg:phone":"+43 7260 4451",
    "sg:postcode":"4371",
    "sg:province":"Ober\u00f6sterreich",
    "sg:tags":[
        "industrial",
        "timber"
    ],
    "wof:name":"S\u00e4ge- und Hobelwerk Klaus Steinbauer",
    "wof:placetype":"venue"
},
  "geometry": {"coordinates":[14.9092054367,48.3023338318],"type":"Point"}
}