{
  "type": "Feature",
  "properties": {
    "iso:country":"AT",
    "sg:address":"Koglehen 2a",
    "sg:city":"Fieberbrunn",
    "sg:orig_category":"Architekten",
    "sg:phone":"+43 5354 52147",
    "sg:postcode":"6391",
    "sg:province":"Tirol",
    "wof:name":"Widmann Franz Dipl-Ing",
    "wof:placetype":"venue"
},
  "geometry": {"coordinates":[12.5474452972,47.4726791382],"type":"Point"}
}