{
  "type": "Feature",
  "properties": {
    "iso:country":"AT",
    "sg:address":"Dorf 229",
    "sg:city":"Bad H\u00e4ring",
    "sg:orig_category":"Reiseveranstalter",
    "sg:phone":"+43 5332 77415",
    "sg:postcode":"6323",
    "sg:province":"Tirol",
    "wof:name":"HMS-H\u00fctten-Miet-Service GmbH",
    "wof:placetype":"venue"
},
  "geometry": {"coordinates":[-88.67497253419999,43.9075889587],"type":"Point"}
}