{
  "type": "Feature",
  "properties": {
    "addr:full":"Landesstr 46 Wernberg K\u00e4rnten 9241",
    "addr:housenumber":"46",
    "addr:postcode":"9241",
    "addr:street":"Landesstr;Kaernten",
    "iso:country":"AT",
    "sg:address":"Landesstr 46",
    "sg:city":"Wernberg",
    "sg:orig_category":"Transportbeton",
    "sg:phone":"+43 4252 43250",
    "sg:postcode":"9241",
    "sg:province":"K\u00e4rnten",
    "wof:name":"Lieferbeton GesmbH",
    "wof:placetype":"venue"
},
  "geometry": {"coordinates":[13.9627599716,46.6020698547],"type":"Point"}
}