{
  "type": "Feature",
  "properties": {
    "iso:country":"AT",
    "sg:address":"Waidmannsdorfer Strasse 127 ",
    "sg:city":"Klagenfurt",
    "sg:classifiers":[
        {
            "category":"Professional",
            "subcategory":"Accounting & Tax Preparation",
            "type":"Services"
        }
    ],
    "sg:phone":"+43 463 263391",
    "sg:postcode":"9020",
    "sg:province":"K\u00e4rnten",
    "sg:tags":[
        "bookkeeping"
    ],
    "sg:website":"www.buchfuehrung-hartl.com",
    "wof:name":"Buchf\u00fchrungs- und Controllingb\u00fcro Wolfgang Hartl",
    "wof:placetype":"venue"
},
  "geometry": {"coordinates":[14.2915229797,46.6090927124],"type":"Point"}
}