{
  "type": "Feature",
  "properties": {
    "iso:country":"AT",
    "sg:address":"Feitelstrasse 1",
    "sg:city":"Trattenbach",
    "sg:classifiers":[
        {
            "category":"Train Station",
            "subcategory":"Rail",
            "type":"Transportation"
        }
    ],
    "sg:phone":"+43 7256 6014",
    "sg:postcode":"4453",
    "sg:province":"Ober\u00f6sterreich",
    "sg:tags":[
        "steel",
        "cutlery",
        "rust-proof"
    ],
    "sg:website":"hack.at",
    "wof:name":"Otto Hack Ges.m.b.H.",
    "wof:placetype":"venue"
},
  "geometry": {"coordinates":[14.3394556046,47.9205513],"type":"Point"}
}