{
  "type": "Feature",
  "properties": {
    "addr:full":"Nr 102 Paldau Steiermark 8341",
    "addr:postcode":"8341",
    "addr:street":"Nr",
    "iso:country":"AT",
    "sg:address":"Nr 102",
    "sg:city":"Paldau",
    "sg:orig_category":"Friseure U Frisiersalons",
    "sg:phone":"+43 4331 502418",
    "sg:postcode":"8341",
    "sg:province":"Steiermark",
    "wof:name":"Fris\u00f6r Brigitte",
    "wof:placetype":"venue"
},
  "geometry": {"coordinates":[15.7963991165,46.9407424927],"type":"Point"}
}