{
  "type": "Feature",
  "properties": {
    "iso:country":"AT",
    "sg:address":"Oskar-Jascha-G 38",
    "sg:city":"Wien",
    "sg:orig_category":"Immobilienverwaltungen",
    "sg:phone":"+43 1 8880509",
    "sg:postcode":"1130",
    "sg:province":"Wien",
    "wof:name":"Rossmann Eva",
    "wof:placetype":"venue"
},
  "geometry": {"coordinates":[16.2661647797,48.1598739624],"type":"Point"}
}