{
  "type": "Feature",
  "properties": {
    "addr:full":"Karmarschg 72 Wien Wien 1100",
    "addr:housenumber":"72",
    "addr:postcode":"1100",
    "addr:street":"Karmarschg",
    "iso:country":"AT",
    "sg:address":"Karmarschg 72",
    "sg:city":"Wien",
    "sg:orig_category":"Bauunternehmen",
    "sg:phone":"+43 4316 067116",
    "sg:postcode":"1100",
    "sg:province":"Wien",
    "wof:name":"OBG BAU BaugmbH",
    "wof:placetype":"venue"
},
  "geometry": {"coordinates":[16.363861084,48.1729660034],"type":"Point"}
}