{
  "type": "Feature",
  "properties": {
    "iso:country":"AT",
    "sg:address":"Europapl 1",
    "sg:city":"Attnang-Puchheim",
    "sg:orig_category":"Notare",
    "sg:phone":"+43 767464200",
    "sg:postcode":"4800",
    "sg:province":"Ober\u00f6sterreich",
    "wof:name":"P\u00f6ltner Reinhard Dr",
    "wof:placetype":"venue"
},
  "geometry": {"coordinates":[13.7186222076,48.0089836121],"type":"Point"}
}