{
  "type": "Feature",
  "properties": {
    "addr:full":"Langg 5 St. Martin im M\u00fchlkreis Ober\u00f6sterreich 4113",
    "addr:housenumber":"5",
    "addr:postcode":"4113",
    "addr:street":"Langg;Im Muehlkreis Oberoesterreich",
    "iso:country":"AT",
    "sg:address":"Langg 5",
    "sg:city":"St. Martin im M\u00fchlkreis",
    "sg:orig_category":"Bauunternehmen",
    "sg:phone":"+43 4372 3222370",
    "sg:postcode":"4113",
    "sg:province":"Ober\u00f6sterreich",
    "wof:name":"Gebr\u00fcder Lang & Co BaugesmbH & Co KG",
    "wof:placetype":"venue"
},
  "geometry": {"coordinates":[14.0373363495,48.4174079895],"type":"Point"}
}