{
  "type": "Feature",
  "properties": {
    "iso:country":"AT",
    "sg:address":"Nr 154b",
    "sg:city":"Ischgl",
    "sg:orig_category":"Pensionen / Privatzimmer",
    "sg:phone":"+43 5444 5236",
    "sg:postcode":"6561",
    "sg:province":"Tirol",
    "wof:name":"Fremdenheim Haus Pezinerblick",
    "wof:placetype":"venue"
},
  "geometry": {"coordinates":[10.2881736755,47.0111351013],"type":"Point"}
}