{
  "type": "Feature",
  "properties": {
    "addr:full":"Platzg 4 Klagenfurt K\u00e4rnten 9020",
    "addr:housenumber":"4",
    "addr:postcode":"9020",
    "addr:street":"Platzg;Kaernten",
    "iso:country":"AT",
    "sg:address":"Platzg 4",
    "sg:city":"Klagenfurt",
    "sg:orig_category":"Pensionen / Privatzimmer",
    "sg:phone":"+43 463 32278",
    "sg:postcode":"9020",
    "sg:province":"K\u00e4rnten",
    "wof:name":"Klepp Hermann",
    "wof:placetype":"venue"
},
  "geometry": {"coordinates":[14.3137054443,46.620010376],"type":"Point"}
}