{
  "type": "Feature",
  "properties": {
    "iso:country":"AT",
    "sg:address":"Nr 18",
    "sg:city":"Schwand im Innkreis",
    "sg:orig_category":"Volksschulen",
    "sg:phone":"+43 4377 28300",
    "sg:postcode":"5134",
    "sg:province":"Ober\u00f6sterreich",
    "wof:name":"Volksschule",
    "wof:placetype":"venue"
},
  "geometry": {"coordinates":[12.9669046402,48.1785736084],"type":"Point"}
}