{
  "type": "Feature",
  "properties": {
    "addr:full":"Am Sendergrund 15 Dobl Steiermark 8143",
    "addr:housenumber":"15",
    "addr:postcode":"8143",
    "addr:street":"Am Sendergrund",
    "iso:country":"AT",
    "sg:address":"Am Sendergrund 15",
    "sg:city":"Dobl",
    "sg:orig_category":"Musikunterricht",
    "sg:phone":"+43 3136 52085",
    "sg:postcode":"8143",
    "sg:province":"Steiermark",
    "wof:name":"Volksmusik-Schule",
    "wof:placetype":"venue"
},
  "geometry": {"coordinates":[15.3801546097,46.9484634399],"type":"Point"}
}