{
  "type": "Feature",
  "properties": {
    "iso:country":"AT",
    "sg:address":"Hilberweg 34",
    "sg:city":"Inzing",
    "sg:classifiers":[
        {
            "category":"Education",
            "subcategory":"Library",
            "type":"Public Place"
        }
    ],
    "sg:phone":"+43 5238 879550",
    "sg:postcode":"6401",
    "sg:province":"Tirol",
    "sg:tags":[
        "shelving",
        "archive"
    ],
    "sg:website":"schmuecking.at",
    "wof:name":"Ing. Klaus Schm\u00fccking GmbH & Co KG",
    "wof:placetype":"venue"
},
  "geometry": {"coordinates":[11.2053203583,47.2709007263],"type":"Point"}
}