{
  "type": "Feature",
  "properties": {
    "addr:full":"Hauptstr 25 M\u00f6llbr\u00fccke K\u00e4rnten 9813",
    "addr:housenumber":"25",
    "addr:postcode":"9813",
    "addr:street":"Hauptstr;Kaernten",
    "iso:country":"AT",
    "sg:address":"Hauptstr 25",
    "sg:city":"M\u00f6llbr\u00fccke",
    "sg:orig_category":"Elektroinstallationsunternehmen",
    "sg:phone":"+43 4769 2237",
    "sg:postcode":"9813",
    "sg:province":"K\u00e4rnten",
    "wof:name":"St\u00f6flin Karl",
    "wof:placetype":"venue"
},
  "geometry": {"coordinates":[13.3702917099,46.8344039917],"type":"Point"}
}