{
  "type": "Feature",
  "properties": {
    "addr:full":"Kaiser-Franz-Josef-Str 36-38 Bad Gastein Salzburg 5640",
    "addr:postcode":"5640",
    "addr:street":"Salzburg",
    "iso:country":"AT",
    "sg:address":"Kaiser-Franz-Josef-Str 36-38",
    "sg:city":"Bad Gastein",
    "sg:classifiers":[
        {
            "category":"Travel",
            "subcategory":"Hotels & Motels",
            "type":"Entertainment"
        }
    ],
    "sg:phone":"+43 4364 342369",
    "sg:postcode":"5640",
    "sg:province":"Salzburg",
    "wof:name":"Adler Hotel & Jugendg\u00e4stehaus",
    "wof:placetype":"venue"
},
  "geometry": {"coordinates":[13.1322622299,47.1151885986],"type":"Point"}
}