{
  "type": "Feature",
  "properties": {
    "iso:country":"AT",
    "sg:address":"Keplerg 14",
    "sg:city":"Wien",
    "sg:orig_category":"Nachhilfe U Lernbetreuung",
    "sg:phone":"+43 1 64199890",
    "sg:postcode":"1100",
    "sg:province":"Wien",
    "sg:website":"losdirekt.at",
    "wof:name":"LOS Lehrinstitut f\u00fcr Orthografie und Schreibtechnik",
    "wof:placetype":"venue"
},
  "geometry": {"coordinates":[16.3762741089,48.1792907715],"type":"Point"}
}