{
  "type": "Feature",
  "properties": {
    "addr:full":"Boschstrasse 36 Wels Ober\u00f6sterreich 4600",
    "addr:housenumber":"36",
    "addr:postcode":"4600",
    "addr:street":"Boschstrasse;Oberoesterreich",
    "iso:country":"AT",
    "sg:address":"Boschstrasse 36",
    "sg:city":"Wels",
    "sg:classifiers":[
        {
            "category":"Shopping Center",
            "type":"Public Place"
        }
    ],
    "sg:phone":"+43 7242 47493",
    "sg:postcode":"4600",
    "sg:province":"Ober\u00f6sterreich",
    "sg:tags":[
        "aluminium",
        "casting"
    ],
    "sg:website":"hans-schwarz.at",
    "wof:name":"Hans Schwarz Metallgie\u00dferei Ges.m.b.H. & Co KG",
    "wof:placetype":"venue"
},
  "geometry": {"coordinates":[14.0502624512,48.1606674194],"type":"Point"}
}