{
  "type": "Feature",
  "properties": {
    "addr:full":"Schwarzenberg am B\u00f6hmerwald 147 Schwarzenberg am B\u00f6hmerwald Ober\u00f6sterreich 4164",
    "addr:housenumber":"147",
    "addr:postcode":"4164",
    "iso:country":"AT",
    "sg:address":"Schwarzenberg am B\u00f6hmerwald 147",
    "sg:city":"Schwarzenberg am B\u00f6hmerwald",
    "sg:orig_category":"Furniture, General",
    "sg:phone":"+43 7280 319",
    "sg:postcode":"4164",
    "sg:province":"Ober\u00f6sterreich",
    "sg:website":"tischlerei-krieg.com",
    "wof:name":"Gerald Krieg",
    "wof:placetype":"venue"
},
  "geometry": {"coordinates":[8.3865814209,48.600189209],"type":"Point"}
}