{
  "type": "Feature",
  "properties": {
    "addr:full":"Moidrams 22 Zwettl Nieder\u00f6sterreich 3910",
    "addr:housenumber":"22",
    "addr:postcode":"3910",
    "addr:street":"Moidrams;Niederoesterreich",
    "iso:country":"AT",
    "sg:address":"Moidrams 22",
    "sg:city":"Zwettl",
    "sg:classifiers":[
        {
            "category":"Restaurant",
            "type":"Food & Drink"
        }
    ],
    "sg:phone":"+43 2822 53133",
    "sg:postcode":"3910",
    "sg:province":"Nieder\u00f6sterreich",
    "wof:name":"Wittig Ralf Mag",
    "wof:placetype":"venue"
},
  "geometry": {"coordinates":[15.1586866379,48.5990180969],"type":"Point"}
}