{
  "type": "Feature",
  "properties": {
    "addr:full":"Nr 27 St. Peter am Kammersberg Steiermark 8843",
    "addr:postcode":"8843",
    "addr:street":"Nr 27",
    "iso:country":"AT",
    "sg:address":"Nr 27",
    "sg:city":"St. Peter am Kammersberg",
    "sg:orig_category":"Pensionen / Privatzimmer",
    "sg:phone":"+43 3536 8476",
    "sg:postcode":"8843",
    "sg:province":"Steiermark",
    "wof:name":"Lindschinger Arnold",
    "wof:placetype":"venue"
},
  "geometry": {"coordinates":[14.1869058609,47.187412262],"type":"Point"}
}