{
  "type": "Feature",
  "properties": {
    "addr:full":"Bahnhofstr 12 Saalfelden am Steinernen Meer Salzburg 5760",
    "addr:housenumber":"12",
    "addr:postcode":"5760",
    "addr:street":"Bahnhofstr;Salzburg",
    "iso:country":"AT",
    "sg:address":"Bahnhofstr 12",
    "sg:city":"Saalfelden am Steinernen Meer",
    "sg:orig_category":"Architekten",
    "sg:phone":"+43 4365 82700100",
    "sg:postcode":"5760",
    "sg:province":"Salzburg",
    "wof:name":"Kaserer Reinhard Arch",
    "wof:placetype":"venue"
},
  "geometry": {"coordinates":[12.8450698853,47.4268341064],"type":"Point"}
}