{
  "type": "Feature",
  "properties": {
    "iso:country":"AT",
    "sg:address":"Bachg 2",
    "sg:city":"Hintersdorf",
    "sg:orig_category":"Werbegestalter",
    "sg:phone":"+43 2242 6177",
    "sg:postcode":"3413",
    "sg:province":"Nieder\u00f6sterreich",
    "wof:name":"Buchta Harald",
    "wof:placetype":"venue"
},
  "geometry": {"coordinates":[16.196598053,48.2943763733],"type":"Point"}
}