{
  "type": "Feature",
  "properties": {
    "addr:full":"Sernau 2  Gamlitz Steiermark 8462",
    "addr:housenumber":"2",
    "addr:postcode":"8462",
    "addr:street":"Sernau",
    "iso:country":"AT",
    "sg:address":"Sernau 2 ",
    "sg:city":"Gamlitz",
    "sg:classifiers":[
        {
            "category":"Food & Beverages",
            "subcategory":"Groceries & Convenience Stores",
            "type":"Retail Goods"
        }
    ],
    "sg:phone":"+43 4334 532556",
    "sg:postcode":"8462",
    "sg:province":"Steiermark",
    "sg:tags":[
        "drink"
    ],
    "wof:name":"WEINGUT SATTLERHOF",
    "wof:placetype":"venue"
},
  "geometry": {"coordinates":[15.5397157669,46.7130241394],"type":"Point"}
}