{
  "type": "Feature",
  "properties": {
    "addr:full":"Dornachweg 32 Silz Tirol 6424",
    "addr:housenumber":"32",
    "addr:postcode":"6424",
    "addr:street":"Dornachweg;Tirol",
    "iso:country":"AT",
    "sg:address":"Dornachweg 32",
    "sg:city":"Silz",
    "sg:orig_category":"Tischlereien",
    "sg:phone":"+43 5263 6343",
    "sg:postcode":"6424",
    "sg:province":"Tirol",
    "wof:name":"Hafner Tischlerei GesmbH & Co KG",
    "wof:placetype":"venue"
},
  "geometry": {"coordinates":[10.9334049225,47.2659034729],"type":"Point"}
}