{
  "type": "Feature",
  "properties": {
    "iso:country":"AT",
    "sg:address":"Nr 523",
    "sg:city":"Seitenstetten",
    "sg:orig_category":"Tischlereien",
    "sg:phone":"+43 7476 77800",
    "sg:postcode":"3353",
    "sg:province":"Nieder\u00f6sterreich",
    "wof:name":"Scheiter bringt Holz in Form",
    "wof:placetype":"venue"
},
  "geometry": {"coordinates":[14.7085561752,48.0289573669],"type":"Point"}
}