{
  "type": "Feature",
  "properties": {
    "addr:full":"Schulstr Aschbach Markt Nieder\u00f6sterreich 3361",
    "addr:postcode":"3361",
    "iso:country":"AT",
    "sg:address":"Schulstr",
    "sg:city":"Aschbach Markt",
    "sg:orig_category":"Musikgruppen",
    "sg:phone":"+43 7476 76506",
    "sg:postcode":"3361",
    "sg:province":"Nieder\u00f6sterreich",
    "wof:name":"Musikkapelle Aschbach",
    "wof:placetype":"venue"
},
  "geometry": {"coordinates":[14.7519741058,48.0710258484],"type":"Point"}
}