{
  "type": "Feature",
  "properties": {
    "iso:country":"AT",
    "sg:address":"Wiener Str 29",
    "sg:city":"Wiener Neudorf",
    "sg:orig_category":"Fenster",
    "sg:phone":"+43 4322 36866200",
    "sg:postcode":"2351",
    "sg:province":"Nieder\u00f6sterreich",
    "wof:name":"Mein Fenster HandelsgesmbH",
    "wof:placetype":"venue"
},
  "geometry": {"coordinates":[16.3136768341,48.0883178711],"type":"Point"}
}