{
  "type": "Feature",
  "properties": {
    "addr:full":"Osterstein 126 Arzl im Pitztal Tirol 6471",
    "addr:housenumber":"126",
    "addr:postcode":"6471",
    "addr:street":"Osterstein;Tirol",
    "iso:country":"AT",
    "sg:address":"Osterstein 126",
    "sg:city":"Arzl im Pitztal",
    "sg:orig_category":"Dolmetscher",
    "sg:phone":"+43 5412 65036",
    "sg:postcode":"6471",
    "sg:province":"Tirol",
    "wof:name":"Maurer Anna",
    "wof:placetype":"venue"
},
  "geometry": {"coordinates":[10.7617301941,47.2069854736],"type":"Point"}
}