{
  "type": "Feature",
  "properties": {
    "addr:full":"Schmiedweg 2 Hinterstoder Ober\u00f6sterreich 4573",
    "addr:housenumber":"2",
    "addr:postcode":"4573",
    "addr:street":"Schmiedweg",
    "iso:country":"AT",
    "sg:address":"Schmiedweg 2",
    "sg:city":"Hinterstoder",
    "sg:orig_category":"Montagen U Montagetechnik",
    "sg:phone":"+43 7564 5165",
    "sg:postcode":"4573",
    "sg:province":"Ober\u00f6sterreich",
    "wof:name":"Rohrauer Christian - Tischlerei-Montagen",
    "wof:placetype":"venue"
},
  "geometry": {"coordinates":[14.1441373825,47.6953048706],"type":"Point"}
}