{
  "type": "Feature",
  "properties": {
    "addr:full":"W\u00f6llersdorfer Str 25 Markt Piesting Nieder\u00f6sterreich 2753",
    "addr:postcode":"2753",
    "addr:street":"Str;Markt",
    "iso:country":"AT",
    "sg:address":"W\u00f6llersdorfer Str 25",
    "sg:city":"Markt Piesting",
    "sg:orig_category":"Feuerwehren",
    "sg:phone":"+43 2633 42644",
    "sg:postcode":"2753",
    "sg:province":"Nieder\u00f6sterreich",
    "wof:name":"Freiwillige Feuerwehr Markt Piesting",
    "wof:placetype":"venue"
},
  "geometry": {"coordinates":[16.1367416382,47.8725814819],"type":"Point"}
}