{
  "type": "Feature",
  "properties": {
    "addr:full":"Nr 38 Hitzendorf Steiermark 8151",
    "addr:postcode":"8151",
    "addr:street":"Nr 38",
    "iso:country":"AT",
    "sg:address":"Nr 38",
    "sg:city":"Hitzendorf",
    "sg:orig_category":"Blumeneinzelhandel",
    "sg:phone":"+43 4331 373417",
    "sg:postcode":"8151",
    "sg:province":"Steiermark",
    "wof:name":"Blumen Plettig GesbR",
    "wof:placetype":"venue"
},
  "geometry": {"coordinates":[15.2999134064,47.0351600647],"type":"Point"}
}