{
  "type": "Feature",
  "properties": {
    "addr:full":"Nr 52 Unterrohr Steiermark 8294",
    "addr:postcode":"8294",
    "addr:street":"Nr",
    "iso:country":"AT",
    "sg:address":"Nr 52",
    "sg:city":"Unterrohr",
    "sg:orig_category":"Non-Classified Establishments",
    "sg:phone":"+43 4333 328193",
    "sg:postcode":"8294",
    "sg:province":"Steiermark",
    "wof:name":"Wurzer Anton",
    "wof:placetype":"venue"
},
  "geometry": {"coordinates":[16.051525116,47.2475013733],"type":"Point"}
}