{
  "type": "Feature",
  "properties": {
    "addr:full":"Laurschweg 24 Fiss Tirol 6533",
    "addr:housenumber":"24",
    "addr:postcode":"6533",
    "addr:street":"Laurschweg;Tirol",
    "iso:country":"AT",
    "sg:address":"Laurschweg 24",
    "sg:city":"Fiss",
    "sg:orig_category":"Appartements / Ferienwohnungen",
    "sg:phone":"+43 5476 6543",
    "sg:postcode":"6533",
    "sg:province":"Tirol",
    "wof:name":"Haus Austria Inh Ernst Walser",
    "wof:placetype":"venue"
},
  "geometry": {"coordinates":[10.6107873917,47.0552062988],"type":"Point"}
}