{
  "type": "Feature",
  "properties": {
    "iso:country":"AT",
    "sg:address":"Alemannenstr 4",
    "sg:city":"Bludenz",
    "sg:orig_category":"Pensionen / Privatzimmer",
    "sg:phone":"+43 5552 65704",
    "sg:postcode":"6700",
    "sg:province":"Vorarlberg",
    "wof:name":"Landhaus Muther",
    "wof:placetype":"venue"
},
  "geometry": {"coordinates":[9.8207387924,47.162311554],"type":"Point"}
}