{
  "type": "Feature",
  "properties": {
    "addr:full":"Am Dorfbrunnen 5 Kemeten Burgenland 7531",
    "addr:housenumber":"5",
    "addr:postcode":"7531",
    "addr:street":"Am Dorfbrunnen",
    "iso:country":"AT",
    "sg:address":"Am Dorfbrunnen 5",
    "sg:city":"Kemeten",
    "sg:orig_category":"Friseure U Frisiersalons",
    "sg:phone":"+43 3352 5126",
    "sg:postcode":"7531",
    "sg:province":"Burgenland",
    "wof:name":"Friseursalon Wickerl",
    "wof:placetype":"venue"
},
  "geometry": {"coordinates":[16.1512203217,47.2494277954],"type":"Point"}
}