{
  "type": "Feature",
  "properties": {
    "addr:full":"Aubauerstr 35 Gmunden Ober\u00f6sterreich 4810",
    "addr:housenumber":"35",
    "addr:postcode":"4810",
    "addr:street":"Aubauerstr;Oberoesterreich",
    "iso:country":"AT",
    "sg:address":"Aubauerstr 35",
    "sg:city":"Gmunden",
    "sg:orig_category":"Autoersatzteile",
    "sg:phone":"+43 7612646530",
    "sg:postcode":"4810",
    "sg:province":"Ober\u00f6sterreich",
    "wof:name":"Weichselbaumer Franz GesmbH",
    "wof:placetype":"venue"
},
  "geometry": {"coordinates":[13.7850828171,47.931388855],"type":"Point"}
}