{
  "type": "Feature",
  "properties": {
    "addr:full":"Werndlstrasse 1 Freistadt Ober\u00f6sterreich 4240",
    "addr:housenumber":"1",
    "addr:postcode":"4240",
    "addr:street":"Werndlstrasse",
    "iso:country":"AT",
    "sg:address":"Werndlstrasse 1",
    "sg:city":"Freistadt",
    "sg:classifiers":[
        {
            "category":"Home & Garden",
            "subcategory":"Building Materials",
            "type":"Retail Goods"
        }
    ],
    "sg:phone":"+43 7942 72353",
    "sg:postcode":"4240",
    "sg:province":"Ober\u00f6sterreich",
    "sg:tags":[
        "railing",
        "balcony"
    ],
    "wof:name":"Sitter KEG",
    "wof:placetype":"venue"
},
  "geometry": {"coordinates":[14.4988355637,48.498374939],"type":"Point"}
}