{
  "type": "Feature",
  "properties": {
    "iso:country":"AT",
    "sg:address":"Sparbersbachg 11",
    "sg:city":"Graz",
    "sg:orig_category":"Musikgruppen",
    "sg:phone":"+43 316 842114",
    "sg:postcode":"8010",
    "sg:province":"Steiermark",
    "wof:name":"Voice Factory",
    "wof:placetype":"venue"
},
  "geometry": {"coordinates":[15.4483747482,47.0668106079],"type":"Point"}
}