{
  "type": "Feature",
  "properties": {
    "addr:full":"Schmidtorstr 7 Linz Ober\u00f6sterreich 4020",
    "addr:housenumber":"7",
    "addr:postcode":"4020",
    "addr:street":"Schmidtorstr",
    "iso:country":"AT",
    "sg:address":"Schmidtorstr 7",
    "sg:city":"Linz",
    "sg:orig_category":"Bilderrahmen",
    "sg:phone":"+43 4373 2771615",
    "sg:postcode":"4020",
    "sg:province":"Ober\u00f6sterreich",
    "sg:website":"bilder-prat.at",
    "wof:name":"Bilder Prat GmbH",
    "wof:placetype":"venue"
},
  "geometry": {"coordinates":[14.2878828049,48.304359436],"type":"Point"}
}