{
  "type": "Feature",
  "properties": {
    "iso:country":"AT",
    "sg:address":"W\u00e4scherg 24",
    "sg:city":"Salzburg",
    "sg:orig_category":"Architekten",
    "sg:phone":"+43 662 829497",
    "sg:postcode":"5020",
    "sg:province":"Salzburg",
    "wof:name":"Niklas Friedrich Arch Mag",
    "wof:placetype":"venue"
},
  "geometry": {"coordinates":[13.0509281158,47.7904968262],"type":"Point"}
}