{
  "type": "Feature",
  "properties": {
    "addr:full":"Nr 66 Mathon Tirol 6562",
    "addr:postcode":"6562",
    "addr:street":"Nr;Mathon Tirol",
    "iso:country":"AT",
    "sg:address":"Nr 66",
    "sg:city":"Mathon",
    "sg:orig_category":"Pensionen / Privatzimmer",
    "sg:phone":"+43 4354 445155",
    "sg:postcode":"6562",
    "sg:province":"Tirol",
    "wof:name":"Haus Kathrein",
    "wof:placetype":"venue"
},
  "geometry": {"coordinates":[10.2449302673,46.9883995056],"type":"Point"}
}