{
  "type": "Feature",
  "properties": {
    "addr:full":"Milders Franz-Senn-Str 18 Neustift im Stubaital Tirol 6167",
    "addr:housenumber":"18",
    "addr:postcode":"6167",
    "addr:street":"Tirol",
    "iso:country":"AT",
    "sg:address":"Milders Franz-Senn-Str 18",
    "sg:city":"Neustift im Stubaital",
    "sg:classifiers":[
        {
            "category":"Travel",
            "subcategory":"Hotels & Motels",
            "type":"Entertainment"
        }
    ],
    "sg:phone":"+43 4352 2625410",
    "sg:postcode":"6167",
    "sg:province":"Tirol",
    "wof:name":"Christoph Hotel",
    "wof:placetype":"venue"
},
  "geometry": {"coordinates":[11.291891098,47.105266571],"type":"Point"}
}