{
  "type": "Feature",
  "properties": {
    "addr:full":"Gro\u00df Enzersdorfer Str 4 Wien Wien 1220",
    "addr:housenumber":"4",
    "addr:postcode":"1220",
    "addr:street":"Str",
    "iso:country":"AT",
    "sg:address":"Gro\u00df Enzersdorfer Str 4",
    "sg:city":"Wien",
    "sg:orig_category":"Apotheken",
    "sg:phone":"+43 4312 821382",
    "sg:postcode":"1220",
    "sg:province":"Wien",
    "sg:website":"apo-aspern.at",
    "wof:name":"Apotheke  Zum L\u00f6wen v Aspern",
    "wof:placetype":"venue"
},
  "geometry": {"coordinates":[16.4887294769,48.2170295715],"type":"Point"}
}