{
  "type": "Feature",
  "properties": {
    "iso:country":"AT",
    "sg:address":"Jungferng 1-3",
    "sg:city":"Graz",
    "sg:orig_category":"Fotoapparate U -Artikel / Einzelhandel",
    "sg:phone":"+43 316 8274000",
    "sg:postcode":"8010",
    "sg:province":"Steiermark",
    "sg:website":"www.fotoehmann.at",
    "wof:name":"Foto Ehmann & Co",
    "wof:placetype":"venue"
},
  "geometry": {"coordinates":[15.4404096603,47.0693359375],"type":"Point"}
}