{
  "type": "Feature",
  "properties": {
    "iso:country":"AT",
    "sg:address":"Salzachtal Bundesstr 43",
    "sg:city":"Hallein",
    "sg:orig_category":"Autohandel",
    "sg:phone":"+43 4362 4584060",
    "sg:postcode":"5400",
    "sg:province":"Salzburg",
    "wof:name":"Opel Hallein",
    "wof:placetype":"venue"
},
  "geometry": {"coordinates":[13.1044025421,47.6793823242],"type":"Point"}
}