{
  "type": "Feature",
  "properties": {
    "addr:full":"Wiesengasse 55 Hartberg Steiermark 8230",
    "addr:housenumber":"55",
    "addr:postcode":"8230",
    "addr:street":"Wiesengasse",
    "iso:country":"AT",
    "sg:address":"Wiesengasse 55",
    "sg:city":"Hartberg",
    "sg:classifiers":[
        {
            "category":"Home & Garden",
            "subcategory":"Carpets & Floor Coverings",
            "type":"Retail Goods"
        }
    ],
    "sg:phone":"+43 3332 60100",
    "sg:postcode":"8230",
    "sg:province":"Steiermark",
    "sg:tags":[
        "carpeting"
    ],
    "wof:name":"Durmont Teppichbodenfabrik Ges.m.b.H.",
    "wof:placetype":"venue"
},
  "geometry": {"coordinates":[15.9769849777,47.2767868042],"type":"Point"}
}