{
  "type": "Feature",
  "properties": {
    "addr:full":"Roseng 54 Wallern im Burgenland Burgenland 7151",
    "addr:housenumber":"54",
    "addr:postcode":"7151",
    "addr:street":"Roseng",
    "iso:country":"AT",
    "sg:address":"Roseng 54",
    "sg:city":"Wallern im Burgenland",
    "sg:orig_category":"Friseure U Frisiersalons",
    "sg:phone":"+43 4321 743143",
    "sg:postcode":"7151",
    "sg:province":"Burgenland",
    "wof:name":"Frisiersalon Elisabeth",
    "wof:placetype":"venue"
},
  "geometry": {"coordinates":[16.932472229,47.7281913757],"type":"Point"}
}