{
  "type": "Feature",
  "properties": {
    "addr:full":"Hauptpl 18 Bad St. Leonhard im Lavanttal K\u00e4rnten 9462",
    "addr:housenumber":"18",
    "addr:postcode":"9462",
    "addr:street":"Hauptpl",
    "iso:country":"AT",
    "sg:address":"Hauptpl 18",
    "sg:city":"Bad St. Leonhard im Lavanttal",
    "sg:orig_category":"Polizei U Gendarmerie",
    "sg:phone":"+43 4359 1332161",
    "sg:postcode":"9462",
    "sg:province":"K\u00e4rnten",
    "wof:name":"Gendarmerie",
    "wof:placetype":"venue"
},
  "geometry": {"coordinates":[14.7925739288,46.9632377625],"type":"Point"}
}