{
  "type": "Feature",
  "properties": {
    "iso:country":"AT",
    "sg:address":"Elisabethstr 8c",
    "sg:city":"Salzburg",
    "sg:orig_category":"Internet-Cafes",
    "sg:phone":"+43 662 871020",
    "sg:postcode":"5020",
    "sg:province":"Salzburg",
    "wof:name":"Element People",
    "wof:placetype":"venue"
},
  "geometry": {"coordinates":[13.0421543121,47.8133506775],"type":"Point"}
}