{
  "type": "Feature",
  "properties": {
    "iso:country":"AT",
    "sg:address":"Laaber Str 69",
    "sg:city":"Breitenfurt",
    "sg:orig_category":"Tierkliniken",
    "sg:phone":"+43 2239 5385",
    "sg:postcode":"2384",
    "sg:province":"Nieder\u00f6sterreich",
    "wof:name":"Pferdeklinik Pegasus Dr Georg Hladik",
    "wof:placetype":"venue"
},
  "geometry": {"coordinates":[16.1937427521,48.1447181702],"type":"Point"}
}