{
  "type": "Feature",
  "properties": {
    "addr:full":"Richterg 2a Axams Tirol 6094",
    "addr:housenumber":"2a",
    "addr:postcode":"6094",
    "addr:street":"Richterg;Tirol",
    "iso:country":"AT",
    "sg:address":"Richterg 2a",
    "sg:city":"Axams",
    "sg:orig_category":"Physiotherapie",
    "sg:phone":"+43 4352 3465735",
    "sg:postcode":"6094",
    "sg:province":"Tirol",
    "wof:name":"Eismayr Gerhard Dipl-PT",
    "wof:placetype":"venue"
},
  "geometry": {"coordinates":[11.2789421082,47.2313537598],"type":"Point"}
}