{
  "type": "Feature",
  "properties": {
    "iso:country":"AT",
    "sg:address":"Leystr 126",
    "sg:city":"Wien",
    "sg:orig_category":"Maschinenbau",
    "sg:phone":"+43 1 33037090",
    "sg:postcode":"1200",
    "sg:province":"Wien",
    "wof:name":"Mahr Maschinenbau GesmbH",
    "wof:placetype":"venue"
},
  "geometry": {"coordinates":[16.3888530731,48.2328262329],"type":"Point"}
}