{
  "type": "Feature",
  "properties": {
    "addr:full":"Wagramer Str 201 Wien Wien 1210",
    "addr:housenumber":"201",
    "addr:postcode":"1210",
    "iso:country":"AT",
    "sg:address":"Wagramer Str 201",
    "sg:city":"Wien",
    "sg:orig_category":"Tankstellen",
    "sg:phone":"+43 1 2589460",
    "sg:postcode":"1210",
    "sg:province":"Wien",
    "wof:name":"Shell Austria GmbH",
    "wof:placetype":"venue"
},
  "geometry": {"coordinates":[16.454656601,48.2642059326],"type":"Point"}
}