{
  "type": "Feature",
  "properties": {
    "addr:full":"Bundesstr 26 Seefeld in Tirol Tirol 6100",
    "addr:housenumber":"26",
    "addr:postcode":"6100",
    "addr:street":"Bundesstr;Tirol",
    "iso:country":"AT",
    "sg:address":"Bundesstr 26",
    "sg:city":"Seefeld in Tirol",
    "sg:orig_category":"Autolackierereien",
    "sg:phone":"+43 5212 3301",
    "sg:postcode":"6100",
    "sg:province":"Tirol",
    "wof:name":"Isser Peter",
    "wof:placetype":"venue"
},
  "geometry": {"coordinates":[11.1889953613,47.3294143677],"type":"Point"}
}