{
  "type": "Feature",
  "properties": {
    "iso:country":"AT",
    "sg:address":"An der Leiten 8/2",
    "sg:city":"Vomp",
    "sg:orig_category":"Datenverarbeitung",
    "sg:phone":"+43 5242 72842",
    "sg:postcode":"6134",
    "sg:province":"Tirol",
    "wof:name":"Eller Walter",
    "wof:placetype":"venue"
},
  "geometry": {"coordinates":[11.694899559,47.3494377136],"type":"Point"}
}