{
  "type": "Feature",
  "properties": {
    "addr:full":"Rainerstr 35 Marchtrenk Ober\u00f6sterreich 4614",
    "addr:housenumber":"35",
    "addr:postcode":"4614",
    "addr:street":"Rainerstr",
    "iso:country":"AT",
    "sg:address":"Rainerstr 35",
    "sg:city":"Marchtrenk",
    "sg:orig_category":"Reifen U Reifendienste",
    "sg:phone":"+43 4372 4358314",
    "sg:postcode":"4614",
    "sg:province":"Ober\u00f6sterreich",
    "wof:name":"Richter Theresia",
    "wof:placetype":"venue"
},
  "geometry": {"coordinates":[14.0865221024,48.1834754944],"type":"Point"}
}