{
  "type": "Feature",
  "properties": {
    "iso:country":"AT",
    "sg:address":"Neilreichg 72-74",
    "sg:city":"Wien",
    "sg:orig_category":"Blumeneinzelhandel",
    "sg:phone":"+43 1 6022164",
    "sg:postcode":"1100",
    "sg:province":"Wien",
    "wof:name":"Gitti's Laden - Brigitte Farthofer",
    "wof:placetype":"venue"
},
  "geometry": {"coordinates":[16.3640956879,48.1696128845],"type":"Point"}
}