{
  "type": "Feature",
  "properties": {
    "iso:country":"AT",
    "sg:address":"Waldweg 20",
    "sg:city":"Lambach",
    "sg:orig_category":"Rohrbearbeitung",
    "sg:phone":"+43 7245 288700",
    "sg:postcode":"4650",
    "sg:province":"Ober\u00f6sterreich",
    "wof:name":"INTEC SYSTEMS Handels und VertriebsgesmbH",
    "wof:placetype":"venue"
},
  "geometry": {"coordinates":[13.9046649933,48.0954971313],"type":"Point"}
}