{
  "type": "Feature",
  "properties": {
    "addr:full":"Rosennockstr 34 Bad Kleinkirchheim K\u00e4rnten 9546",
    "addr:housenumber":"34",
    "addr:postcode":"9546",
    "addr:street":"Rosennockstr",
    "iso:country":"AT",
    "sg:address":"Rosennockstr 34",
    "sg:city":"Bad Kleinkirchheim",
    "sg:orig_category":"Mietautos",
    "sg:phone":"+43 4367 65724090",
    "sg:postcode":"9546",
    "sg:province":"K\u00e4rnten",
    "wof:name":"Gritzner Maria",
    "wof:placetype":"venue"
},
  "geometry": {"coordinates":[13.7642822266,46.8358955383],"type":"Point"}
}