{
  "type": "Feature",
  "properties": {
    "iso:country":"AT",
    "sg:address":"Schlo\u00dfsee 2 114",
    "sg:city":"Oberwaltersdorf",
    "sg:classifiers":[
        {
            "category":"Professional",
            "subcategory":"Computer Services",
            "type":"Services"
        }
    ],
    "sg:phone":"+43 664 3301762",
    "sg:postcode":"2522",
    "sg:province":"Nieder\u00f6sterreich",
    "sg:tags":[
        "software"
    ],
    "wof:name":"Infodata Ing Rheden",
    "wof:placetype":"venue"
},
  "geometry": {"coordinates":[16.3228302002,47.9767494202],"type":"Point"}
}