{
  "type": "Feature",
  "properties": {
    "addr:full":"Ungarg 1 Wiener Neustadt Nieder\u00f6sterreich 2700",
    "addr:housenumber":"1",
    "addr:postcode":"2700",
    "addr:street":"Ungarg",
    "iso:country":"AT",
    "sg:address":"Ungarg 1",
    "sg:city":"Wiener Neustadt",
    "sg:orig_category":"Webdesign",
    "sg:phone":"+43 4326 2224126",
    "sg:postcode":"2700",
    "sg:province":"Nieder\u00f6sterreich",
    "wof:name":"ICE Design Birlehm Schibig OEG",
    "wof:placetype":"venue"
},
  "geometry": {"coordinates":[16.2452278137,47.8131217957],"type":"Point"}
}