{
  "type": "Feature",
  "properties": {
    "addr:full":"Seeblickstr 42 Lieserbr\u00fccke K\u00e4rnten 9851",
    "addr:housenumber":"42",
    "addr:postcode":"9851",
    "addr:street":"Seeblickstr;Kaernten",
    "iso:country":"AT",
    "sg:address":"Seeblickstr 42",
    "sg:city":"Lieserbr\u00fccke",
    "sg:orig_category":"Appartements / Ferienwohnungen",
    "sg:phone":"+43 4762 33352",
    "sg:postcode":"9851",
    "sg:province":"K\u00e4rnten",
    "wof:name":"Schwingerhof",
    "wof:placetype":"venue"
},
  "geometry": {"coordinates":[13.4832515717,46.8373031616],"type":"Point"}
}