{
  "type": "Feature",
  "properties": {
    "iso:country":"AT",
    "sg:address":"Bahnhofstr 23",
    "sg:city":"Wattens",
    "sg:orig_category":"Damenmoden",
    "sg:phone":"+43 4352 2451739",
    "sg:postcode":"6112",
    "sg:province":"Tirol",
    "wof:name":"KiK Textilien u Non-Food GesmbH",
    "wof:placetype":"venue"
},
  "geometry": {"coordinates":[11.5899400711,47.2934036255],"type":"Point"}
}