{
  "type": "Feature",
  "properties": {
    "addr:full":"R Billinger-Str 200 M\u00fcnzkirchen Ober\u00f6sterreich 4792",
    "addr:housenumber":"200",
    "addr:postcode":"4792",
    "addr:street":"Muenzkirchen Oberoesterreich",
    "iso:country":"AT",
    "sg:address":"R Billinger-Str 200",
    "sg:city":"M\u00fcnzkirchen",
    "sg:orig_category":"Elektroinstallationsunternehmen",
    "sg:phone":"+43 7716 6693",
    "sg:postcode":"4792",
    "sg:province":"Ober\u00f6sterreich",
    "wof:name":"Schie\u00dfl Rudolf",
    "wof:placetype":"venue"
},
  "geometry": {"coordinates":[175.9476928711,-39.545589447],"type":"Point"}
}