{
  "type": "Feature",
  "properties": {
    "addr:full":"Slamastr 42 Wien Wien 1230",
    "addr:housenumber":"42",
    "addr:postcode":"1230",
    "addr:street":"Slamastr",
    "iso:country":"AT",
    "sg:address":"Slamastr 42",
    "sg:city":"Wien",
    "sg:orig_category":"Offsetdruckereien",
    "sg:phone":"+43 1 4082015",
    "sg:postcode":"1230",
    "sg:province":"Wien",
    "wof:name":"Gessky Alfred GesmbH",
    "wof:placetype":"venue"
},
  "geometry": {"coordinates":[16.3379840851,48.1378555298],"type":"Point"}
}