{
  "type": "Feature",
  "properties": {
    "addr:full":"Stadtpl 40 Klosterneuburg Nieder\u00f6sterreich 3400",
    "addr:housenumber":"40",
    "addr:postcode":"3400",
    "addr:street":"Stadtpl;Niederoesterreich",
    "iso:country":"AT",
    "sg:address":"Stadtpl 40",
    "sg:city":"Klosterneuburg",
    "sg:orig_category":"Juweliere, Gold- U Silberschmiede",
    "sg:phone":"+43 2243 37935",
    "sg:postcode":"3400",
    "sg:province":"Nieder\u00f6sterreich",
    "wof:name":"Wertl Goldschmiede - Reinhold Wertl",
    "wof:placetype":"venue"
},
  "geometry": {"coordinates":[16.3226108551,48.3084564209],"type":"Point"}
}