{
  "type": "Feature",
  "properties": {
    "iso:country":"AT",
    "sg:address":"Stolzstr 75",
    "sg:city":"Klagenfurt",
    "sg:orig_category":"Werbeagenturen",
    "sg:phone":"+43 699 13271000",
    "sg:postcode":"9020",
    "sg:province":"K\u00e4rnten",
    "wof:name":"ECS Werbe & Marketingagentur",
    "wof:placetype":"venue"
},
  "geometry": {"coordinates":[14.3521785736,46.6100616455],"type":"Point"}
}