{
  "type": "Feature",
  "properties": {
    "iso:country":"AT",
    "sg:address":"Abt Karl-Str 80",
    "sg:city":"Melk",
    "sg:orig_category":"Autohandel",
    "sg:phone":"+43 2752 50100",
    "sg:postcode":"3390",
    "sg:province":"Nieder\u00f6sterreich",
    "wof:name":"Senker Autohaus GmbH",
    "wof:placetype":"venue"
},
  "geometry": {"coordinates":[15.3445529938,48.2230262756],"type":"Point"}
}