{
  "type": "Feature",
  "properties": {
    "iso:country":"AT",
    "sg:address":"Mozartstr 92",
    "sg:city":"Klagenfurt",
    "sg:orig_category":"Lebensmittel / Einzelhandel",
    "sg:phone":"+43 463 25010",
    "sg:postcode":"9020",
    "sg:province":"K\u00e4rnten",
    "wof:name":"SPAR \u00f6sterreichische Warenhandels-AG",
    "wof:placetype":"venue"
},
  "geometry": {"coordinates":[14.2783918381,46.6128616333],"type":"Point"}
}