{
  "type": "Feature",
  "properties": {
    "iso:country":"AT",
    "sg:address":"Dominik Eckl-Str 34",
    "sg:city":"Langschlag",
    "sg:orig_category":"Non-Classified Establishments",
    "sg:phone":"+43 2814 8239",
    "sg:postcode":"3921",
    "sg:province":"Nieder\u00f6sterreich",
    "wof:name":"Pfarramt",
    "wof:placetype":"venue"
},
  "geometry": {"coordinates":[14.8832511902,48.5740623474],"type":"Point"}
}