{
  "type": "Feature",
  "properties": {
    "addr:full":"Triester Str 2 Knittelfeld Steiermark 8720",
    "addr:housenumber":"2",
    "addr:postcode":"8720",
    "addr:street":"Str",
    "iso:country":"AT",
    "sg:address":"Triester Str 2",
    "sg:city":"Knittelfeld",
    "sg:orig_category":"Damenmoden",
    "sg:phone":"+43 4335 1244612",
    "sg:postcode":"8720",
    "sg:province":"Steiermark",
    "wof:name":"KiK Textilien u Non-Food GesmbH",
    "wof:placetype":"venue"
},
  "geometry": {"coordinates":[14.7905282974,47.2040710449],"type":"Point"}
}