{
  "type": "Feature",
  "properties": {
    "iso:country":"AT",
    "sg:address":"Donaufelder Str 244",
    "sg:city":"Wien",
    "sg:orig_category":"Politische Parteien",
    "sg:phone":"+43 4312 031173",
    "sg:postcode":"1220",
    "sg:province":"Wien",
    "wof:name":"\u00f6sterr Wirtschaftsbund Landesgr Wien",
    "wof:placetype":"venue"
},
  "geometry": {"coordinates":[16.4414348602,48.249961853],"type":"Point"}
}