{
  "type": "Feature",
  "properties": {
    "addr:full":"Salcherstr 41 St. P\u00f6lten-Harland Nieder\u00f6sterreich 3104",
    "addr:housenumber":"41",
    "addr:postcode":"3104",
    "addr:street":"Salcherstr",
    "iso:country":"AT",
    "sg:address":"Salcherstr 41",
    "sg:city":"St. P\u00f6lten-Harland",
    "sg:orig_category":"Hauptschulen",
    "sg:phone":"+43 2742 881951",
    "sg:postcode":"3104",
    "sg:province":"Nieder\u00f6sterreich",
    "wof:name":"Hauptschule Dr Theodor K\u00f6rner 1",
    "wof:placetype":"venue"
},
  "geometry": {"coordinates":[15.6384372711,48.1618423462],"type":"Point"}
}