{
  "type": "Feature",
  "properties": {
    "addr:full":"Jochen Rindt-Str 41 Wien Wien 1230",
    "addr:housenumber":"41",
    "addr:postcode":"1230",
    "iso:country":"AT",
    "sg:address":"Jochen Rindt-Str 41",
    "sg:city":"Wien",
    "sg:orig_category":"Me\u00c3\u0178-, Steuer- U Regeltechnik",
    "sg:phone":"+43 1 61639290",
    "sg:postcode":"1230",
    "sg:province":"Wien",
    "wof:name":"Nissl Robert GesmbH",
    "wof:placetype":"venue"
},
  "geometry": {"coordinates":[16.350812912,48.1360855103],"type":"Point"}
}