{
  "type": "Feature",
  "properties": {
    "iso:country":"AT",
    "sg:address":"Lagerstr 1-5",
    "sg:city":"Langenzersdorf",
    "sg:classifiers":[
        {
            "category":"Home & Garden",
            "subcategory":"Garden Supply",
            "type":"Retail Goods"
        }
    ],
    "sg:phone":"+43 2244 334455",
    "sg:postcode":"2103",
    "sg:province":"Nieder\u00f6sterreich",
    "sg:tags":[
        "schotter",
        "sand",
        "u"
    ],
    "wof:name":"KIES-UNION GmbH",
    "wof:placetype":"venue"
},
  "geometry": {"coordinates":[16.365190506,48.2871780396],"type":"Point"}
}