{
  "type": "Feature",
  "properties": {
    "iso:country":"AT",
    "sg:address":"Neuer Markt 2/12",
    "sg:city":"Wien",
    "sg:classifiers":[
        {
            "category":"Manufacturing",
            "subcategory":"Chemicals & Compounds",
            "type":"Manufacturing & Wholesale Goods"
        }
    ],
    "sg:phone":"+43 1 5129700",
    "sg:postcode":"1010",
    "sg:province":"Wien",
    "sg:tags":[
        "trade"
    ],
    "wof:name":"F & F Engineering Handels GmbH",
    "wof:placetype":"venue"
},
  "geometry": {"coordinates":[16.3705406189,48.2058029175],"type":"Point"}
}