{
  "type": "Feature",
  "properties": {
    "addr:full":"Pischeldorf 140 Pischeldorf K\u00e4rnten 9064",
    "addr:housenumber":"140",
    "addr:postcode":"9064",
    "addr:street":"Pischeldorf;Pischeldorf Kaernten",
    "iso:country":"AT",
    "sg:address":"Pischeldorf 140",
    "sg:city":"Pischeldorf",
    "sg:classifiers":[
        {
            "category":"Structure",
            "subcategory":"Building",
            "type":"Public Place"
        }
    ],
    "sg:phone":"+43 4224 29480",
    "sg:postcode":"9064",
    "sg:province":"K\u00e4rnten",
    "sg:tags":[
        "apartment"
    ],
    "sg:website":"skorianz-bau.at",
    "wof:name":"Skorianz Bau Ges.m.b.H.",
    "wof:placetype":"venue"
},
  "geometry": {"coordinates":[14.4566326141,46.6874771118],"type":"Point"}
}