{
  "type": "Feature",
  "properties": {
    "iso:country":"AT",
    "sg:address":"Mariazeller Str 3",
    "sg:city":"Ober-Grafendorf",
    "sg:orig_category":"Non-Classified Establishments",
    "sg:phone":"+43 2747 22180",
    "sg:postcode":"3200",
    "sg:province":"Nieder\u00f6sterreich",
    "wof:name":"Kirchenbeitragsstelle",
    "wof:placetype":"venue"
},
  "geometry": {"coordinates":[15.5448522568,48.1493148804],"type":"Point"}
}