{
  "type": "Feature",
  "properties": {
    "addr:full":"Praterstr 48/1/11 Wien Wien 1020",
    "addr:housenumber":"48 / 1 / 11",
    "addr:postcode":"1020",
    "addr:street":"Praterstr",
    "iso:country":"AT",
    "sg:address":"Praterstr 48/1/11",
    "sg:city":"Wien",
    "sg:classifiers":[
        {
            "category":"Organizations",
            "subcategory":"Community Association",
            "type":"Services"
        }
    ],
    "sg:phone":"+43 1 2198542",
    "sg:postcode":"1020",
    "sg:province":"Wien",
    "sg:tags":[
        "relation",
        "public"
    ],
    "wof:name":"senft & partner public relations & fund raising GmbH",
    "wof:placetype":"venue"
},
  "geometry": {"coordinates":[16.3802642822,48.2153701782],"type":"Point"}
}