{
  "type": "Feature",
  "properties": {
    "addr:full":"Schidlachstr 7 Innsbruck Tirol 6020",
    "addr:housenumber":"7",
    "addr:postcode":"6020",
    "addr:street":"Schidlachstr;Tirol",
    "iso:country":"AT",
    "sg:address":"Schidlachstr 7",
    "sg:city":"Innsbruck",
    "sg:orig_category":"Psychologen",
    "sg:phone":"+43 512 560552",
    "sg:postcode":"6020",
    "sg:province":"Tirol",
    "wof:name":"H\u00f6rtnagl Josef Univ Ass Dr phil",
    "wof:placetype":"venue"
},
  "geometry": {"coordinates":[11.3977394104,47.2584495544],"type":"Point"}
}