{
  "type": "Feature",
  "properties": {
    "iso:country":"AT",
    "sg:address":"Schmidtg 7",
    "sg:city":"Wels",
    "sg:orig_category":"Juweliere, Gold- U Silberschmiede",
    "sg:phone":"+43 4372 4246075",
    "sg:postcode":"4600",
    "sg:province":"Ober\u00f6sterreich",
    "wof:name":"Wiesmayr E KEG",
    "wof:placetype":"venue"
},
  "geometry": {"coordinates":[14.0253219604,48.1573791504],"type":"Point"}
}