{
  "type": "Feature",
  "properties": {
    "addr:full":"Nr 91 St. Johann am Wimberg Ober\u00f6sterreich 4172",
    "addr:postcode":"4172",
    "addr:street":"Nr 91",
    "iso:country":"AT",
    "sg:address":"Nr 91",
    "sg:city":"St. Johann am Wimberg",
    "sg:classifiers":[
        {
            "category":"Restaurant",
            "type":"Food & Drink"
        }
    ],
    "sg:phone":"+43 4372 177163",
    "sg:postcode":"4172",
    "sg:province":"Ober\u00f6sterreich",
    "sg:website":"simader-restaurierung.at",
    "wof:name":"Simader Herbert",
    "wof:placetype":"venue"
},
  "geometry": {"coordinates":[14.1302614212,48.4888267517],"type":"Point"}
}