{
  "type": "Feature",
  "properties": {
    "addr:full":"Nr 36 R\u00f6hrenbach Nieder\u00f6sterreich 3592",
    "addr:postcode":"3592",
    "addr:street":"Nr 36 Roehrenbach",
    "iso:country":"AT",
    "sg:address":"Nr 36",
    "sg:city":"R\u00f6hrenbach",
    "sg:orig_category":"Lebensmittel / Einzelhandel",
    "sg:phone":"+43 2989 2514",
    "sg:postcode":"3592",
    "sg:province":"Nieder\u00f6sterreich",
    "wof:name":"MARAP HandelsgesmbH",
    "wof:placetype":"venue"
},
  "geometry": {"coordinates":[15.5094175339,48.6553764343],"type":"Point"}
}