{
  "type": "Feature",
  "properties": {
    "addr:full":"Klosterweg 3 Reutte Tirol 6600",
    "addr:housenumber":"3",
    "addr:postcode":"6600",
    "addr:street":"Klosterweg;Tirol",
    "iso:country":"AT",
    "sg:address":"Klosterweg 3",
    "sg:city":"Reutte",
    "sg:orig_category":"Versicherungsunternehmen",
    "sg:phone":"+43 5672 62759",
    "sg:postcode":"6600",
    "sg:province":"Tirol",
    "wof:name":"Wiener St\u00e4dtische Allgemeine Versicherung AG",
    "wof:placetype":"venue"
},
  "geometry": {"coordinates":[10.7182359695,47.487033844],"type":"Point"}
}