{
  "type": "Feature",
  "properties": {
    "addr:full":"Rennbahnweg 27/22 Wien Wien 1220",
    "addr:housenumber":"27 / 22",
    "addr:postcode":"1220",
    "addr:street":"Rennbahnweg",
    "iso:country":"AT",
    "sg:address":"Rennbahnweg 27/22",
    "sg:city":"Wien",
    "sg:orig_category":"Friseure U Frisiersalons",
    "sg:phone":"+43 1 2581108",
    "sg:postcode":"1220",
    "sg:province":"Wien",
    "wof:name":"Holy Christian",
    "wof:placetype":"venue"
},
  "geometry": {"coordinates":[16.4527301788,48.2562904358],"type":"Point"}
}