{
  "type": "Feature",
  "properties": {
    "iso:country":"AT",
    "sg:address":"Nr 1",
    "sg:city":"Hohenberg",
    "sg:orig_category":"Erdarbeiten",
    "sg:phone":"+43 2767 7357",
    "sg:postcode":"3192",
    "sg:province":"Nieder\u00f6sterreich",
    "wof:name":"Wiesbauer Andreas GmbH",
    "wof:placetype":"venue"
},
  "geometry": {"coordinates":[15.6185703278,47.9116134644],"type":"Point"}
}