{
  "type": "Feature",
  "properties": {
    "iso:country":"AT",
    "sg:address":"Triester Str 3",
    "sg:city":"Wien",
    "sg:orig_category":"Bauunternehmen",
    "sg:phone":"+43 676 5203690",
    "sg:postcode":"1100",
    "sg:province":"Wien",
    "wof:name":"IDS Bau GmbH",
    "wof:placetype":"venue"
},
  "geometry": {"coordinates":[16.358455658,48.1785850525],"type":"Point"}
}