{
  "type": "Feature",
  "properties": {
    "iso:country":"AT",
    "sg:address":"Walchen 46",
    "sg:city":"Steeg",
    "sg:classifiers":[
        {
            "category":"Travel",
            "subcategory":"Hotels & Motels",
            "type":"Entertainment"
        }
    ],
    "sg:phone":"+43 5633 5290",
    "sg:postcode":"6655",
    "sg:province":"Tirol",
    "wof:name":"Hotel Tannenhof",
    "wof:placetype":"venue"
},
  "geometry": {"coordinates":[10.3220453262,47.2531280518],"type":"Point"}
}