{
  "type": "Feature",
  "properties": {
    "addr:full":"Hauptstrasse 18 Enzersfeld Nieder\u00f6sterreich 2202",
    "addr:housenumber":"18",
    "addr:postcode":"2202",
    "addr:street":"Hauptstrasse",
    "iso:country":"AT",
    "sg:address":"Hauptstrasse 18",
    "sg:city":"Enzersfeld",
    "sg:classifiers":[
        {
            "category":"Professional",
            "subcategory":"Computer Services",
            "type":"Services"
        }
    ],
    "sg:phone":"+43 2262 674163",
    "sg:postcode":"2202",
    "sg:province":"Nieder\u00f6sterreich",
    "sg:tags":[
        "development",
        "software"
    ],
    "wof:name":"Richard Salomon BSc (Hons)",
    "wof:placetype":"venue"
},
  "geometry": {"coordinates":[16.4270057678,48.3608093262],"type":"Point"}
}