{
  "type": "Feature",
  "properties": {
    "addr:full":"Schlo\u00dfpl 3 Hohenems Vorarlberg 6845",
    "addr:housenumber":"3",
    "addr:postcode":"6845",
    "addr:street":"Schlosspl",
    "iso:country":"AT",
    "sg:address":"Schlo\u00dfpl 3",
    "sg:city":"Hohenems",
    "sg:classifiers":[
        {
            "category":"Travel",
            "subcategory":"Hotels & Motels",
            "type":"Entertainment"
        }
    ],
    "sg:phone":"+43 5576 78300",
    "sg:postcode":"6845",
    "sg:province":"Vorarlberg",
    "sg:website":"valerian.at",
    "wof:name":"VALERIAN Das Business Hotel",
    "wof:placetype":"venue"
},
  "geometry": {"coordinates":[9.6892251968,47.3623046875],"type":"Point"}
}