{
  "type": "Feature",
  "properties": {
    "addr:full":"Josef-Sattler-Str 1A Jenbach Tirol 6200",
    "addr:housenumber":"1a",
    "addr:postcode":"6200",
    "addr:street":"Josef-Sattler-Str;Tirol",
    "iso:country":"AT",
    "sg:address":"Josef-Sattler-Str 1A",
    "sg:city":"Jenbach",
    "sg:orig_category":"Polytechnische Schulen",
    "sg:phone":"+43 4352 4464178",
    "sg:postcode":"6200",
    "sg:province":"Tirol",
    "wof:name":"Polytechnische Schule",
    "wof:placetype":"venue"
},
  "geometry": {"coordinates":[11.7747602463,47.391998291],"type":"Point"}
}