{
  "type": "Feature",
  "properties": {
    "addr:full":"F\u00fcgen Tirol 6263",
    "addr:postcode":"6263",
    "addr:street":"Tirol",
    "iso:country":"AT",
    "sg:city":"F\u00fcgen",
    "sg:classifiers":[
        {
            "category":"Restaurant",
            "type":"Food & Drink"
        }
    ],
    "sg:phone":"+43 4352 80203",
    "sg:postcode":"6263",
    "sg:province":"Tirol",
    "wof:name":"Panorama Restaurant",
    "wof:placetype":"venue"
},
  "geometry": {"coordinates":[101.76634216310001,30.9142303467],"type":"Point"}
}