{
  "type": "Feature",
  "properties": {
    "addr:full":"Nr 169 Fresach K\u00e4rnten 9712",
    "addr:postcode":"9712",
    "addr:street":"Nr 169;Kaernten",
    "iso:country":"AT",
    "sg:address":"Nr 169",
    "sg:city":"Fresach",
    "sg:orig_category":"Fliesen- U Plattenverlegungen",
    "sg:phone":"+43 4245 4393",
    "sg:postcode":"9712",
    "sg:province":"K\u00e4rnten",
    "wof:name":"Kleinsasser Fritz",
    "wof:placetype":"venue"
},
  "geometry": {"coordinates":[13.6881408691,46.7136497498],"type":"Point"}
}