{
  "type": "Feature",
  "properties": {
    "addr:full":"Reisner Str. 45-47  Wien Wien 1030",
    "addr:postcode":"45-47;1030",
    "addr:street":"Str.",
    "iso:country":"AT",
    "sg:address":"Reisner Str. 45-47 ",
    "sg:city":"Wien",
    "sg:classifiers":[
        {
            "category":"Professional",
            "subcategory":"Business Services",
            "type":"Services"
        }
    ],
    "sg:phone":"+43 4317 121229",
    "sg:postcode":"1030",
    "sg:province":"Wien",
    "sg:tags":[
        "advice"
    ],
    "wof:name":"BOTSCHAFT DER RUSSISCHEN F\u00d6DERATON",
    "wof:placetype":"venue"
},
  "geometry": {"coordinates":[16.3840103149,48.1977653503],"type":"Point"}
}