{
  "type": "Feature",
  "properties": {
    "addr:full":"Spittelbreiteng 34 Wien Wien 1120",
    "addr:housenumber":"34",
    "addr:postcode":"1120",
    "addr:street":"Spittelbreiteng",
    "iso:country":"AT",
    "sg:address":"Spittelbreiteng 34",
    "sg:city":"Wien",
    "sg:orig_category":"Telekommunikation",
    "sg:phone":"+43 1 811500",
    "sg:postcode":"1120",
    "sg:province":"Wien",
    "wof:name":"Frequentis GesmbH",
    "wof:placetype":"venue"
},
  "geometry": {"coordinates":[16.32421875,48.1767578125],"type":"Point"}
}