{
  "type": "Feature",
  "properties": {
    "iso:country":"AT",
    "sg:address":"Wolfsbergg 25",
    "sg:city":"Spittal an der Drau",
    "sg:orig_category":"Baumeister",
    "sg:phone":"+43 4347 6226910",
    "sg:postcode":"9800",
    "sg:province":"K\u00e4rnten",
    "wof:name":"St\u00fcttler Reinhard Ing",
    "wof:placetype":"venue"
},
  "geometry": {"coordinates":[13.5077724457,46.7980308533],"type":"Point"}
}