{
  "type": "Feature",
  "properties": {
    "addr:full":"Grazer Str 102 Wiener Neustadt Nieder\u00f6sterreich 2700",
    "addr:postcode":"2700",
    "iso:country":"AT",
    "sg:address":"Grazer Str 102",
    "sg:city":"Wiener Neustadt",
    "sg:orig_category":"Feuerwerksartikel U Feuerwerke",
    "sg:phone":"+43 4326 22275100",
    "sg:postcode":"2700",
    "sg:province":"Nieder\u00f6sterreich",
    "wof:name":"Schottleitner Ing Anton GmbH, Mechatronik,Elektronik, Pyrotechnik, Feuerwerke, Entwicklung",
    "wof:placetype":"venue"
},
  "geometry": {"coordinates":[16.2447986603,47.8106536865],"type":"Point"}
}