{
  "type": "Feature",
  "properties": {
    "addr:full":"H\u00f6ferweg 45 Neufelden Ober\u00f6sterreich 4120",
    "addr:housenumber":"45",
    "addr:postcode":"4120",
    "addr:street":"Hoeferweg",
    "iso:country":"AT",
    "sg:address":"H\u00f6ferweg 45",
    "sg:city":"Neufelden",
    "sg:orig_category":"Hauptschulen",
    "sg:phone":"+43 7282 631311",
    "sg:postcode":"4120",
    "sg:province":"Ober\u00f6sterreich",
    "wof:name":"Hauptschule",
    "wof:placetype":"venue"
},
  "geometry": {"coordinates":[13.9943561554,48.4808731079],"type":"Point"}
}