{
  "type": "Feature",
  "properties": {
    "iso:country":"AT",
    "sg:address":"Styria Strasse 31",
    "sg:city":"St. Peter",
    "sg:orig_category":"Immobilien U Baugewerbe, Baustoffe U Bauelemente",
    "sg:phone":"+43 43316",
    "sg:postcode":"8042",
    "sg:province":"Steiermark",
    "sg:website":"http://www.buettinghaus.at",
    "wof:name":"B\u00fcttinghaus Fliesen",
    "wof:placetype":"venue"
},
  "geometry": {"coordinates":[15.4799757004,47.0402793884],"type":"Point"}
}