{
  "type": "Feature",
  "properties": {
    "iso:country":"AT",
    "sg:address":"Mariahilfer Str 186",
    "sg:city":"Wien",
    "sg:classifiers":[
        {
            "category":"Restaurant",
            "type":"Food & Drink"
        }
    ],
    "sg:phone":"+43 1 8923741",
    "sg:postcode":"1150",
    "sg:province":"Wien",
    "sg:tags":[
        "pizzeria"
    ],
    "wof:name":"Pizzeria Bella",
    "wof:placetype":"venue"
},
  "geometry": {"coordinates":[16.3281002045,48.1916236877],"type":"Point"}
}