{
  "type": "Feature",
  "properties": {
    "addr:full":"Stadtpl 2 Eferding Ober\u00f6sterreich 4070",
    "addr:housenumber":"2",
    "addr:postcode":"4070",
    "addr:street":"Stadtpl",
    "iso:country":"AT",
    "sg:address":"Stadtpl 2",
    "sg:city":"Eferding",
    "sg:orig_category":"Fenster",
    "sg:phone":"+43 7272 6100",
    "sg:postcode":"4070",
    "sg:province":"Ober\u00f6sterreich",
    "wof:name":"Actual Pro-System GmbH",
    "wof:placetype":"venue"
},
  "geometry": {"coordinates":[14.0236997604,48.3100242615],"type":"Point"}
}