{
  "type": "Feature",
  "properties": {
    "addr:full":"Bahnstrasse 14 Leopoldsdorf im Marchfelde Nieder\u00f6sterreich 2285",
    "addr:housenumber":"14",
    "addr:postcode":"2285",
    "addr:street":"Bahnstrasse",
    "iso:country":"AT",
    "sg:address":"Bahnstrasse 14",
    "sg:city":"Leopoldsdorf im Marchfelde",
    "sg:orig_category":"Deep-Well Pumps",
    "sg:phone":"+43 2216 2295",
    "sg:postcode":"2285",
    "sg:province":"Nieder\u00f6sterreich",
    "sg:website":"geobohr.at",
    "wof:name":"GEOBOHR Brunnenbau GesmbH",
    "wof:placetype":"venue"
},
  "geometry": {"coordinates":[16.6969146729,48.23072052],"type":"Point"}
}