{
  "type": "Feature",
  "properties": {
    "iso:country":"AT",
    "sg:address":"Hauptstr 9",
    "sg:city":"Wiener Neudorf",
    "sg:orig_category":"Blumenbinder",
    "sg:phone":"+43 2236 65650",
    "sg:postcode":"2351",
    "sg:province":"Nieder\u00f6sterreich",
    "wof:name":"Eder Elfriede",
    "wof:placetype":"venue"
},
  "geometry": {"coordinates":[16.315530777,48.0868148804],"type":"Point"}
}