{
  "type": "Feature",
  "properties": {
    "addr:full":"Rembrandtstr 24/13 Wien Wien 1020",
    "addr:housenumber":"24 / 13",
    "addr:postcode":"1020",
    "addr:street":"Rembrandtstr",
    "iso:country":"AT",
    "sg:address":"Rembrandtstr 24/13",
    "sg:city":"Wien",
    "sg:orig_category":"Feldenkraismethode",
    "sg:phone":"+43 676 6037931",
    "sg:postcode":"1020",
    "sg:province":"Wien",
    "wof:name":"Friessner Christina",
    "wof:placetype":"venue"
},
  "geometry": {"coordinates":[16.3726043701,48.2222557068],"type":"Point"}
}