{
  "type": "Feature",
  "properties": {
    "addr:full":"Ursprungweg 12 Mieming Tirol 6414",
    "addr:housenumber":"12",
    "addr:postcode":"6414",
    "addr:street":"Ursprungweg;Tirol",
    "iso:country":"AT",
    "sg:address":"Ursprungweg 12",
    "sg:city":"Mieming",
    "sg:orig_category":"Rauchfangkehrer",
    "sg:phone":"+43 5264 5320",
    "sg:postcode":"6414",
    "sg:province":"Tirol",
    "wof:name":"Schleich Markus",
    "wof:placetype":"venue"
},
  "geometry": {"coordinates":[10.9664773941,47.3104019165],"type":"Point"}
}