{
  "type": "Feature",
  "properties": {
    "iso:country":"AT",
    "sg:address":"Heiliggeiststr 10",
    "sg:city":"Innsbruck",
    "sg:orig_category":"Vinotheken",
    "sg:phone":"+43 4351 258449325",
    "sg:postcode":"6020",
    "sg:province":"Tirol",
    "wof:name":"St Urban Vinothek",
    "wof:placetype":"venue"
},
  "geometry": {"coordinates":[11.3974142075,47.2614021301],"type":"Point"}
}