{
  "type": "Feature",
  "properties": {
    "addr:full":"Ziegelofeng 21-23 Wien Wien 1050",
    "addr:postcode":"21-23;1050",
    "iso:country":"AT",
    "sg:address":"Ziegelofeng 21-23",
    "sg:city":"Wien",
    "sg:orig_category":"Garagen Parkgaragen",
    "sg:phone":"+43 1 5488863",
    "sg:postcode":"1050",
    "sg:province":"Wien",
    "wof:name":"Garage Mittersteig - BIP Garagenges Breiteneder GesmbH & Co KG",
    "wof:placetype":"venue"
},
  "geometry": {"coordinates":[16.3616962433,48.1902770996],"type":"Point"}
}