{
  "type": "Feature",
  "properties": {
    "addr:full":"Faistenau Salzburg 5324",
    "addr:postcode":"5324",
    "addr:street":"Faistenau",
    "iso:country":"AT",
    "sg:city":"Faistenau",
    "sg:orig_category":"Psychotherapie",
    "sg:phone":"+43 4367 66108863",
    "sg:postcode":"5324",
    "sg:province":"Salzburg",
    "wof:name":"Crepaz Anita",
    "wof:placetype":"venue"
},
  "geometry": {"coordinates":[13.2332620621,47.7780952454],"type":"Point"}
}