{
  "type": "Feature",
  "properties": {
    "addr:full":"Nr 186b Gaschurn Vorarlberg 6793",
    "addr:postcode":"6793",
    "addr:street":"Nr 186B",
    "iso:country":"AT",
    "sg:address":"Nr 186b",
    "sg:city":"Gaschurn",
    "sg:classifiers":[
        {
            "category":"Restaurant",
            "type":"Food & Drink"
        }
    ],
    "sg:phone":"+43 5558 8917",
    "sg:postcode":"6793",
    "sg:province":"Vorarlberg",
    "wof:name":"Cafe-Restaurant B\u00e4renh\u00f6hle",
    "wof:placetype":"venue"
},
  "geometry": {"coordinates":[10.0248842239,46.9886512756],"type":"Point"}
}