{
  "type": "Feature",
  "properties": {
    "iso:country":"AT",
    "sg:address":"Markt 164",
    "sg:city":"Abtenau",
    "sg:orig_category":"Massagen",
    "sg:phone":"+43 650 3911867",
    "sg:postcode":"5441",
    "sg:province":"Salzburg",
    "wof:name":"Tom's Massagepraxis Lanner Thomas",
    "wof:placetype":"venue"
},
  "geometry": {"coordinates":[13.3385505676,47.5679168701],"type":"Point"}
}