{
  "type": "Feature",
  "properties": {
    "addr:full":"Leobner Str 75 Bruck an der Mur Steiermark 8600",
    "addr:postcode":"8600",
    "addr:street":"Str 75",
    "iso:country":"AT",
    "sg:address":"Leobner Str 75",
    "sg:city":"Bruck an der Mur",
    "sg:orig_category":"Steinmetzbetriebe",
    "sg:phone":"+43 4338 6251426",
    "sg:postcode":"8600",
    "sg:province":"Steiermark",
    "wof:name":"Becker Robert Mag - Marmor, Granit, Grabsteine",
    "wof:placetype":"venue"
},
  "geometry": {"coordinates":[15.2539558411,47.4040145874],"type":"Point"}
}