{
  "type": "Feature",
  "properties": {
    "iso:country":"AT",
    "sg:address":"Hieflauer Str 22a",
    "sg:city":"Eisenerz",
    "sg:orig_category":"Damenmoden",
    "sg:phone":"+43 3848 60097",
    "sg:postcode":"8790",
    "sg:province":"Steiermark",
    "wof:name":"KiK Textilien und Non-Food GesmbH",
    "wof:placetype":"venue"
},
  "geometry": {"coordinates":[14.8813638687,47.5457267761],"type":"Point"}
}