{
  "type": "Feature",
  "properties": {
    "addr:full":"Erzherzog-Eugen-Str 56 Innsbruck Tirol 6020",
    "addr:housenumber":"56",
    "addr:postcode":"6020",
    "addr:street":"Erzherzog-Eugen-Str;Tirol",
    "iso:country":"AT",
    "sg:address":"Erzherzog-Eugen-Str 56",
    "sg:city":"Innsbruck",
    "sg:orig_category":"Friseure U Frisiersalons",
    "sg:phone":"+43 4351 2585829",
    "sg:postcode":"6020",
    "sg:province":"Tirol",
    "wof:name":"Lamprecht Werner",
    "wof:placetype":"venue"
},
  "geometry": {"coordinates":[11.4118900299,47.2736244202],"type":"Point"}
}