{
  "type": "Feature",
  "properties": {
    "iso:country":"AT",
    "sg:address":"G\u00e4nsackerweg 3",
    "sg:city":"Serfaus",
    "sg:orig_category":"Friseure U Frisiersalons",
    "sg:phone":"+43 4354 766766",
    "sg:postcode":"6534",
    "sg:province":"Tirol",
    "wof:name":"Paradies f\u00fcr Haare",
    "wof:placetype":"venue"
},
  "geometry": {"coordinates":[10.6066408157,47.0387992859],"type":"Point"}
}