{
  "type": "Feature",
  "properties": {
    "addr:full":"Innsbrucker Str 3 Reutte Tirol 6600",
    "addr:housenumber":"3",
    "addr:postcode":"6600",
    "addr:street":"Str;Tirol",
    "iso:country":"AT",
    "sg:address":"Innsbrucker Str 3",
    "sg:city":"Reutte",
    "sg:orig_category":"Autoersatzteile",
    "sg:phone":"+43 5672 64464",
    "sg:postcode":"6600",
    "sg:province":"Tirol",
    "wof:name":"A-Z Autozubeh\u00f6r Inh Wolfgang Pietsch",
    "wof:placetype":"venue"
},
  "geometry": {"coordinates":[10.7218961716,47.4839401245],"type":"Point"}
}