{
  "type": "Feature",
  "properties": {
    "addr:full":"Steinamangerer Str 5 Rotenturm an der Pinka Burgenland 7501",
    "addr:housenumber":"5",
    "addr:postcode":"7501",
    "addr:street":"Str",
    "iso:country":"AT",
    "sg:address":"Steinamangerer Str 5",
    "sg:city":"Rotenturm an der Pinka",
    "sg:orig_category":"Parkettbodenverlegung",
    "sg:phone":"+43 4333 5235266",
    "sg:postcode":"7501",
    "sg:province":"Burgenland",
    "wof:name":"Zach-Parkett GmbH",
    "wof:placetype":"venue"
},
  "geometry": {"coordinates":[16.2521495819,47.2651252747],"type":"Point"}
}