{
  "type": "Feature",
  "properties": {
    "addr:full":"Hauptstrasse 25 Peuerbach Ober\u00f6sterreich 4722",
    "addr:housenumber":"25",
    "addr:postcode":"4722",
    "addr:street":"Hauptstrasse",
    "iso:country":"AT",
    "sg:address":"Hauptstrasse 25",
    "sg:city":"Peuerbach",
    "sg:classifiers":[
        {
            "category":"Ice Cream",
            "type":"Food & Drink"
        }
    ],
    "sg:phone":"+43 7276 2045",
    "sg:postcode":"4722",
    "sg:province":"Ober\u00f6sterreich",
    "sg:tags":[
        "article",
        "gift",
        "glass"
    ],
    "wof:name":"Franz Sickinger",
    "wof:placetype":"venue"
},
  "geometry": {"coordinates":[13.7706041336,48.3448905945],"type":"Point"}
}