{
  "type": "Feature",
  "properties": {
    "iso:country":"AT",
    "sg:address":"Hauptstr 17",
    "sg:city":"Leobersdorf",
    "sg:orig_category":"Volksschulen",
    "sg:phone":"+43 2256 62267",
    "sg:postcode":"2544",
    "sg:province":"Nieder\u00f6sterreich",
    "wof:name":"Volksschule",
    "wof:placetype":"venue"
},
  "geometry": {"coordinates":[16.2173118591,47.9286079407],"type":"Point"}
}