{
  "type": "Feature",
  "properties": {
    "addr:full":"Johann-Giefing-Strasse 8-10 Wiener Neustadt Nieder\u00f6sterreich 2700",
    "addr:housenumber":"8-10",
    "addr:postcode":"2700",
    "iso:country":"AT",
    "sg:address":"Johann-Giefing-Strasse 8-10",
    "sg:city":"Wiener Neustadt",
    "sg:classifiers":[
        {
            "category":"Autos & Motor Vehicles",
            "subcategory":"Auto Supplies",
            "type":"Retail Goods"
        }
    ],
    "sg:phone":"+43 2622 3070",
    "sg:postcode":"2700",
    "sg:province":"Nieder\u00f6sterreich",
    "sg:tags":[
        "lining",
        "brake"
    ],
    "sg:website":"leinweber.at",
    "wof:name":"Leinweber Maschinen GmbH",
    "wof:placetype":"venue"
},
  "geometry": {"coordinates":[16.2403125763,47.8399467468],"type":"Point"}
}