{
  "type": "Feature",
  "properties": {
    "addr:full":"Komzakg 1 Neunkirchen Nieder\u00f6sterreich 2620",
    "addr:housenumber":"1",
    "addr:postcode":"2620",
    "addr:street":"Komzakg",
    "iso:country":"AT",
    "sg:address":"Komzakg 1",
    "sg:city":"Neunkirchen",
    "sg:orig_category":"Modellagenturen",
    "sg:phone":"+43 2635 63167",
    "sg:postcode":"2620",
    "sg:province":"Nieder\u00f6sterreich",
    "wof:name":"modeteam Schneider proFASHIONal",
    "wof:placetype":"venue"
},
  "geometry": {"coordinates":[16.0980548859,47.7119560242],"type":"Point"}
}