{
  "type": "Feature",
  "properties": {
    "addr:full":"Gasser Pl 1 Hermagor K\u00e4rnten 9620",
    "addr:housenumber":"1",
    "addr:postcode":"9620",
    "addr:street":"Gasser Pl;Kaernten",
    "iso:country":"AT",
    "sg:address":"Gasser Pl 1",
    "sg:city":"Hermagor",
    "sg:orig_category":"Banken U Sparkassen",
    "sg:phone":"+43 5 02026200",
    "sg:postcode":"9620",
    "sg:province":"K\u00e4rnten",
    "wof:name":"HYPO ALPE-ADRIA-BANK AG",
    "wof:placetype":"venue"
},
  "geometry": {"coordinates":[13.3714723587,46.6274223328],"type":"Point"}
}