{
  "type": "Feature",
  "properties": {
    "iso:country":"AT",
    "sg:address":"Lois-Welzenbacher-Strasse 3",
    "sg:city":"Hall in Tirol",
    "sg:classifiers":[
        {
            "category":"Organizations",
            "subcategory":"Labor Organization",
            "type":"Services"
        }
    ],
    "sg:phone":"+43 5223 53359",
    "sg:postcode":"6060",
    "sg:province":"Tirol",
    "sg:tags":[
        "cleaning",
        "central",
        "system",
        "vacuum"
    ],
    "sg:website":"disan.at",
    "wof:name":"Helmut Zanger Ges.m.b.H.",
    "wof:placetype":"venue"
},
  "geometry": {"coordinates":[11.5147743225,47.3014144897],"type":"Point"}
}