{
  "type": "Feature",
  "properties": {
    "iso:country":"AT",
    "sg:address":"Siebensterng 5",
    "sg:city":"Wien",
    "sg:orig_category":"Restaurants: Spanisch",
    "sg:phone":"+43 1 5239985",
    "sg:postcode":"1070",
    "sg:province":"Wien",
    "wof:name":"Pedro's Meson",
    "wof:placetype":"venue"
},
  "geometry": {"coordinates":[16.3566513062,48.2026672363],"type":"Point"}
}