{
  "type": "Feature",
  "properties": {
    "iso:country":"AT",
    "sg:address":"Stadtpl 8",
    "sg:city":"Schwanenstadt",
    "sg:orig_category":"Steuerberatung",
    "sg:phone":"+43 4376 7320090",
    "sg:postcode":"4690",
    "sg:province":"Ober\u00f6sterreich",
    "wof:name":"P\u00f6lzleithner Josef Mag Wirtschaftstreuhand KEG",
    "wof:placetype":"venue"
},
  "geometry": {"coordinates":[13.7732181549,48.0546760559],"type":"Point"}
}