{
  "type": "Feature",
  "properties": {
    "iso:country":"AT",
    "sg:address":"Zanderstr 16",
    "sg:city":"Salzburg",
    "sg:classifiers":[
        {
            "category":"Taxi",
            "type":"Transportation"
        }
    ],
    "sg:phone":"+43 4366 43562763",
    "sg:postcode":"5020",
    "sg:province":"Salzburg",
    "sg:tags":[
        "personentransporte",
        "u"
    ],
    "wof:name":"Hillerzeder",
    "wof:placetype":"venue"
},
  "geometry": {"coordinates":[13.0150108337,47.8341178894],"type":"Point"}
}