{
  "type": "Feature",
  "properties": {
    "iso:country":"AT",
    "sg:address":"Kirchenpl 4",
    "sg:city":"Lichtenw\u00f6rth",
    "sg:orig_category":"Hauptschulen",
    "sg:phone":"+43 4326 2275577",
    "sg:postcode":"2493",
    "sg:province":"Nieder\u00f6sterreich",
    "wof:name":"Hauptschule",
    "wof:placetype":"venue"
},
  "geometry": {"coordinates":[16.2962799072,47.8375015259],"type":"Point"}
}