{
  "type": "Feature",
  "properties": {
    "iso:country":"AT",
    "sg:address":"Maria-Ebenort 35",
    "sg:city":"Frohnleiten",
    "sg:classifiers":[
        {
            "category":"Communications",
            "subcategory":"Television Station",
            "type":"Services"
        }
    ],
    "sg:phone":"+43 316 694940",
    "sg:postcode":"8130",
    "sg:province":"Steiermark",
    "sg:tags":[
        "array",
        "satellite",
        "aerial",
        "reception",
        "antenna"
    ],
    "wof:name":"Nuster & M\u00f6stl OEG",
    "wof:placetype":"venue"
},
  "geometry": {"coordinates":[15.3166666031,47.2841186523],"type":"Point"}
}