{
  "type": "Feature",
  "properties": {
    "addr:full":"Hauptstr 14 Prambachkirchen Ober\u00f6sterreich 4731",
    "addr:housenumber":"14",
    "addr:postcode":"4731",
    "addr:street":"Hauptstr",
    "iso:country":"AT",
    "sg:address":"Hauptstr 14",
    "sg:city":"Prambachkirchen",
    "sg:classifiers":[
        {
            "category":"Restaurant",
            "type":"Food & Drink"
        }
    ],
    "sg:phone":"+43 4372 7736630",
    "sg:postcode":"4731",
    "sg:province":"Ober\u00f6sterreich",
    "sg:tags":[
        "pizzeria"
    ],
    "wof:name":"Pizzeria La Fontana",
    "wof:placetype":"venue"
},
  "geometry": {"coordinates":[13.9038610458,48.3161697388],"type":"Point"}
}