{
  "type": "Feature",
  "properties": {
    "addr:full":"Adolf-Sch\u00e4rf-Str 13 Ebenthal in K\u00e4rnten K\u00e4rnten 9065",
    "addr:housenumber":"13",
    "addr:postcode":"9065",
    "addr:street":"Adolf-Schaerf-Str;Kaernten",
    "iso:country":"AT",
    "sg:address":"Adolf-Sch\u00e4rf-Str 13",
    "sg:city":"Ebenthal in K\u00e4rnten",
    "sg:orig_category":"Erdarbeiten",
    "sg:phone":"+43 463 310071",
    "sg:postcode":"9065",
    "sg:province":"K\u00e4rnten",
    "wof:name":"Lager Johann",
    "wof:placetype":"venue"
},
  "geometry": {"coordinates":[14.3621454239,46.6070404053],"type":"Point"}
}