{
  "type": "Feature",
  "properties": {
    "addr:full":"Am M\u00fchlwasser 231 Wien Wien 1220",
    "addr:housenumber":"231",
    "addr:postcode":"1220",
    "addr:street":"Am Muehlwasser",
    "iso:country":"AT",
    "sg:address":"Am M\u00fchlwasser 231",
    "sg:city":"Wien",
    "sg:orig_category":"Tierschutz",
    "sg:phone":"+43 664 1814348",
    "sg:postcode":"1220",
    "sg:province":"Wien",
    "wof:name":"Tierheim am M\u00fchlwasser",
    "wof:placetype":"venue"
},
  "geometry": {"coordinates":[16.444606781,48.2497138977],"type":"Point"}
}