{
  "type": "Feature",
  "properties": {
    "iso:country":"AT",
    "sg:address":"W\u00e4scherg 1",
    "sg:city":"Salzburg",
    "sg:orig_category":"Pensionen / Privatzimmer",
    "sg:phone":"+43 662 8308490",
    "sg:postcode":"5020",
    "sg:province":"Salzburg",
    "wof:name":"Pension Freisaal",
    "wof:placetype":"venue"
},
  "geometry": {"coordinates":[13.0517702103,47.7922973633],"type":"Point"}
}