{
  "type": "Feature",
  "properties": {
    "addr:full":"Tannheim 103 Tannheim Tirol 6675",
    "addr:housenumber":"103",
    "addr:postcode":"6675",
    "addr:street":"Tannheim Tirol",
    "iso:country":"AT",
    "sg:address":"Tannheim 103",
    "sg:city":"Tannheim",
    "sg:classifiers":[
        {
            "category":"Home & Garden",
            "subcategory":"Carpets & Floor Coverings",
            "type":"Retail Goods"
        }
    ],
    "sg:phone":"+43 5675 6295",
    "sg:postcode":"6675",
    "sg:province":"Tirol",
    "sg:tags":[
        "carpeting"
    ],
    "wof:name":"Herbert Gl\u00e4tzle",
    "wof:placetype":"venue"
},
  "geometry": {"coordinates":[10.5161399841,47.4993400574],"type":"Point"}
}