{
  "type": "Feature",
  "properties": {
    "addr:full":"Kirchweg 9 Stra\u00dfgang Steiermark 8054",
    "addr:housenumber":"9",
    "addr:postcode":"8054",
    "addr:street":"Kirchweg",
    "iso:country":"AT",
    "sg:address":"Kirchweg 9",
    "sg:city":"Stra\u00dfgang",
    "sg:orig_category":"Immobilienverwaltungen",
    "sg:phone":"+43 699 10626093",
    "sg:postcode":"8054",
    "sg:province":"Steiermark",
    "wof:name":"Rossmann Immobilien KEG",
    "wof:placetype":"venue"
},
  "geometry": {"coordinates":[15.3810386658,47.0189628601],"type":"Point"}
}