{
  "type": "Feature",
  "properties": {
    "addr:full":"Br\u00e4uhof 207 Grundlsee Steiermark 8993",
    "addr:housenumber":"207",
    "addr:postcode":"8993",
    "addr:street":"Braeuhof",
    "iso:country":"AT",
    "sg:address":"Br\u00e4uhof 207",
    "sg:city":"Grundlsee",
    "sg:orig_category":"Juweliere, Gold- U Silberschmiede",
    "sg:phone":"+43 4336 228504",
    "sg:postcode":"8993",
    "sg:province":"Steiermark",
    "wof:name":"Steiner Goldschmied",
    "wof:placetype":"venue"
},
  "geometry": {"coordinates":[13.8498210907,47.6320877075],"type":"Point"}
}