{
  "type": "Feature",
  "properties": {
    "addr:full":"Maria Anger 16 Enns Ober\u00f6sterreich 4470",
    "addr:housenumber":"16",
    "addr:postcode":"4470",
    "addr:street":"Maria Anger",
    "iso:country":"AT",
    "sg:address":"Maria Anger 16",
    "sg:city":"Enns",
    "sg:orig_category":"Restaurants: Chinesisch",
    "sg:phone":"+43 7223 82058",
    "sg:postcode":"4470",
    "sg:province":"Ober\u00f6sterreich",
    "wof:name":"China-Restaurant Mandarin",
    "wof:placetype":"venue"
},
  "geometry": {"coordinates":[14.4703559875,48.2183952332],"type":"Point"}
}