{
  "type": "Feature",
  "properties": {
    "addr:full":"Gentzg 137 Wien Wien 1180",
    "addr:housenumber":"137",
    "addr:postcode":"1180",
    "iso:country":"AT",
    "sg:address":"Gentzg 137",
    "sg:city":"Wien",
    "sg:orig_category":"Unternehmensberatung",
    "sg:phone":"+43 1 27525450",
    "sg:postcode":"1180",
    "sg:province":"Wien",
    "wof:name":"H\u00fctter MC Management Consulting GmbH",
    "wof:placetype":"venue"
},
  "geometry": {"coordinates":[16.3295593262,48.2311477661],"type":"Point"}
}