{
  "type": "Feature",
  "properties": {
    "addr:full":"Loferer Str 9 Saalfelden am Steinernen Meer Salzburg 5760",
    "addr:housenumber":"9",
    "addr:postcode":"5760",
    "addr:street":"Str",
    "iso:country":"AT",
    "sg:address":"Loferer Str 9",
    "sg:city":"Saalfelden am Steinernen Meer",
    "sg:orig_category":"Bauunternehmen",
    "sg:phone":"+43 4365 8273310",
    "sg:postcode":"5760",
    "sg:province":"Salzburg",
    "wof:name":"BMP BaugesmbH",
    "wof:placetype":"venue"
},
  "geometry": {"coordinates":[12.8489027023,47.4269447327],"type":"Point"}
}