{
  "type": "Feature",
  "properties": {
    "addr:full":"Quellenstr 57 Wien Wien 1100",
    "addr:housenumber":"57",
    "addr:postcode":"1100",
    "addr:street":"Quellenstr",
    "iso:country":"AT",
    "sg:address":"Quellenstr 57",
    "sg:city":"Wien",
    "sg:orig_category":"Papier- U Schreibwaren / Einzelhandel",
    "sg:phone":"+43 4316 040170",
    "sg:postcode":"1100",
    "sg:province":"Wien",
    "wof:name":"Fr\u00f6hlich Papier GmbH & Co KEG",
    "wof:placetype":"venue"
},
  "geometry": {"coordinates":[16.3872718811,48.1740760803],"type":"Point"}
}