{
  "type": "Feature",
  "properties": {
    "iso:country":"AT",
    "sg:address":"Bahnhofstr 31",
    "sg:city":"Lambach",
    "sg:orig_category":"Tischlereien",
    "sg:phone":"+43 7245 21957",
    "sg:postcode":"4650",
    "sg:province":"Ober\u00f6sterreich",
    "wof:name":"Karbiener Thomas",
    "wof:placetype":"venue"
},
  "geometry": {"coordinates":[13.8832769394,48.0906143188],"type":"Point"}
}