{
  "type": "Feature",
  "properties": {
    "addr:full":"Mattigpl 9 Obertrum am See Salzburg 5162",
    "addr:housenumber":"9",
    "addr:postcode":"5162",
    "addr:street":"Mattigpl;Salzburg",
    "iso:country":"AT",
    "sg:address":"Mattigpl 9",
    "sg:city":"Obertrum am See",
    "sg:orig_category":"Bars-Cafes",
    "sg:phone":"+43 6219 6328",
    "sg:postcode":"5162",
    "sg:province":"Salzburg",
    "wof:name":"Sapperlot",
    "wof:placetype":"venue"
},
  "geometry": {"coordinates":[13.075630188,47.9377403259],"type":"Point"}
}