{
  "type": "Feature",
  "properties": {
    "addr:full":"Hauptstrasse 98 H\u00fcrm Nieder\u00f6sterreich 3383",
    "addr:housenumber":"98",
    "addr:postcode":"3383",
    "addr:street":"Hauptstrasse;Niederoesterreich",
    "iso:country":"AT",
    "sg:address":"Hauptstrasse 98",
    "sg:city":"H\u00fcrm",
    "sg:classifiers":[
        {
            "category":"Utilities",
            "subcategory":"Natural Gas",
            "type":"Services"
        }
    ],
    "sg:phone":"+43 2754 71060",
    "sg:postcode":"3383",
    "sg:province":"Nieder\u00f6sterreich",
    "sg:tags":[
        "heater",
        "direct",
        "electric"
    ],
    "sg:website":"gottwald.at",
    "wof:name":"Gottwald GmbH & CO KG",
    "wof:placetype":"venue"
},
  "geometry": {"coordinates":[6.0451698303,49.5095214844],"type":"Point"}
}