{
  "type": "Feature",
  "properties": {
    "iso:country":"AT",
    "sg:address":"B\u00fcntliweg 5",
    "sg:city":"Tschagguns",
    "sg:classifiers":[
        {
            "category":"Manufacturing",
            "subcategory":"Pet Food",
            "type":"Manufacturing & Wholesale Goods"
        }
    ],
    "sg:phone":"+43 5556 77919",
    "sg:postcode":"6774",
    "sg:province":"Vorarlberg",
    "sg:tags":[
        "speciality",
        "animal"
    ],
    "wof:name":"Rollingers Tierfutter GmbH",
    "wof:placetype":"venue"
},
  "geometry": {"coordinates":[9.9019699097,47.0777397156],"type":"Point"}
}