{
  "type": "Feature",
  "properties": {
    "iso:country":"AT",
    "sg:address":"Margaritenweg 2",
    "sg:city":"Bad Kleinkirchheim",
    "sg:classifiers":[
        {
            "category":"Travel",
            "subcategory":"Hotels & Motels",
            "type":"Entertainment"
        }
    ],
    "sg:phone":"+43 4240 88900",
    "sg:postcode":"9546",
    "sg:province":"K\u00e4rnten",
    "wof:name":"Hotel Kirchenwirt",
    "wof:placetype":"venue"
},
  "geometry": {"coordinates":[13.7977104187,46.8153648376],"type":"Point"}
}