{
  "type": "Feature",
  "properties": {
    "addr:full":"Max-Ott-Pl 6/7 Salzburg Salzburg 5020",
    "addr:housenumber":"6 / 7",
    "addr:postcode":"5020",
    "addr:street":"Max-Ott-Pl;Salzburg",
    "iso:country":"AT",
    "sg:address":"Max-Ott-Pl 6/7",
    "sg:city":"Salzburg",
    "sg:classifiers":[
        {
            "category":"Internet Cafe",
            "subcategory":"None",
            "type":"Food & Drink"
        }
    ],
    "sg:phone":"+43 662 8766060",
    "sg:postcode":"5020",
    "sg:province":"Salzburg",
    "wof:name":"elements.at New Media Solutions GmbH",
    "wof:placetype":"venue"
},
  "geometry": {"coordinates":[13.0411968231,47.8080978394],"type":"Point"}
}