{
  "type": "Feature",
  "properties": {
    "addr:full":"Edenbach 5 Aurolzm\u00fcnster Ober\u00f6sterreich 4971",
    "addr:housenumber":"5",
    "addr:postcode":"4971",
    "addr:street":"Edenbach;Oberoesterreich",
    "iso:country":"AT",
    "sg:address":"Edenbach 5",
    "sg:city":"Aurolzm\u00fcnster",
    "sg:orig_category":"Pensionen / Privatzimmer",
    "sg:phone":"+43 4377 5284895",
    "sg:postcode":"4971",
    "sg:province":"Ober\u00f6sterreich",
    "wof:name":"Bauernhof Himetsberger - Reifetshammer Annemarie u Kurt",
    "wof:placetype":"venue"
},
  "geometry": {"coordinates":[13.4307003021,48.2518005371],"type":"Point"}
}