{
  "type": "Feature",
  "properties": {
    "addr:full":"Hauptstr 9 Ebensee Ober\u00f6sterreich 4802",
    "addr:housenumber":"9",
    "addr:postcode":"4802",
    "addr:street":"Hauptstr",
    "iso:country":"AT",
    "sg:address":"Hauptstr 9",
    "sg:city":"Ebensee",
    "sg:orig_category":"Banken U Sparkassen",
    "sg:phone":"+43 4361 3370210",
    "sg:postcode":"4802",
    "sg:province":"Ober\u00f6sterreich",
    "wof:name":"Oberbank AG",
    "wof:placetype":"venue"
},
  "geometry": {"coordinates":[13.7713279724,47.8112564087],"type":"Point"}
}