{
  "type": "Feature",
  "properties": {
    "addr:full":"Erlafstr. 30  Scheibbs Nieder\u00f6sterreich 3270",
    "addr:housenumber":"30",
    "addr:postcode":"3270",
    "addr:street":"Erlafstr.",
    "iso:country":"AT",
    "sg:address":"Erlafstr. 30 ",
    "sg:city":"Scheibbs",
    "sg:classifiers":[
        {
            "category":"Shopping",
            "subcategory":"Crafts & Fabrics",
            "type":"Retail Goods"
        }
    ],
    "sg:phone":"+43 4374 8242334",
    "sg:postcode":"3270",
    "sg:province":"Nieder\u00f6sterreich",
    "sg:tags":[
        "ceramic"
    ],
    "wof:name":"SCHEIBBSER KERAMIK UND BEHINDERTENWERKSTATT",
    "wof:placetype":"venue"
},
  "geometry": {"coordinates":[15.1659259796,48.0031433105],"type":"Point"}
}