{
  "type": "Feature",
  "properties": {
    "addr:full":"Nr 48 Gleinst\u00e4tten Steiermark 8443",
    "addr:postcode":"8443",
    "addr:street":"Nr 48 Gleinstaetten Steiermark",
    "iso:country":"AT",
    "sg:address":"Nr 48",
    "sg:city":"Gleinst\u00e4tten",
    "sg:orig_category":"Landwirtschaftliche Produkte",
    "sg:phone":"+43 3457 22370",
    "sg:postcode":"8443",
    "sg:province":"Steiermark",
    "wof:name":"Oswald Fritz GesmbH",
    "wof:placetype":"venue"
},
  "geometry": {"coordinates":[15.3728399277,46.7680854797],"type":"Point"}
}