{
  "type": "Feature",
  "properties": {
    "addr:full":"Almaweg 7 N\u00fcziders Vorarlberg 6714",
    "addr:housenumber":"7",
    "addr:postcode":"6714",
    "addr:street":"Almaweg",
    "iso:country":"AT",
    "sg:address":"Almaweg 7",
    "sg:city":"N\u00fcziders",
    "sg:orig_category":"Industrievertretungen",
    "sg:phone":"+43 5552 65249",
    "sg:postcode":"6714",
    "sg:province":"Vorarlberg",
    "wof:name":"Engstler Manfred",
    "wof:placetype":"venue"
},
  "geometry": {"coordinates":[9.8139810562,47.1684074402],"type":"Point"}
}