{
  "type": "Feature",
  "properties": {
    "addr:full":"Rosensteing 22 Wien Wien 1170",
    "addr:housenumber":"22",
    "addr:postcode":"1170",
    "addr:street":"Rosensteing",
    "iso:country":"AT",
    "sg:address":"Rosensteing 22",
    "sg:city":"Wien",
    "sg:orig_category":"Spenglereien",
    "sg:phone":"+43 1 4897111",
    "sg:postcode":"1170",
    "sg:province":"Wien",
    "sg:website":"bauspenglerei.info",
    "wof:name":"Spenglerei Walter Huber GesmbH",
    "wof:placetype":"venue"
},
  "geometry": {"coordinates":[16.3260040283,48.2169685364],"type":"Point"}
}