{
  "type": "Feature",
  "properties": {
    "addr:full":"Schlo\u00dfpl 2 Zell am See Salzburg 5700",
    "addr:housenumber":"2",
    "addr:postcode":"5700",
    "addr:street":"Schlosspl;Salzburg",
    "iso:country":"AT",
    "sg:address":"Schlo\u00dfpl 2",
    "sg:city":"Zell am See",
    "sg:orig_category":"Banken U Sparkassen",
    "sg:phone":"+43 4365 42740400",
    "sg:postcode":"5700",
    "sg:province":"Salzburg",
    "wof:name":"Bank f Arbeit u Wirtschaft AG",
    "wof:placetype":"venue"
},
  "geometry": {"coordinates":[12.7971572876,47.3228187561],"type":"Point"}
}