{
  "type": "Feature",
  "properties": {
    "iso:country":"AT",
    "sg:address":"Treustr 19",
    "sg:city":"Wien",
    "sg:orig_category":"Lebensmittel / Einzelhandel",
    "sg:phone":"+43 1 3345561",
    "sg:postcode":"1200",
    "sg:province":"Wien",
    "wof:name":"Melhotra & Co OEG",
    "wof:placetype":"venue"
},
  "geometry": {"coordinates":[16.3666801453,48.228351593],"type":"Point"}
}