{
  "type": "Feature",
  "properties": {
    "addr:full":"Mariazeller Strasse 51 M\u00fcrzzuschlag Steiermark 8680",
    "addr:housenumber":"51",
    "addr:postcode":"8680",
    "addr:street":"Mariazeller Strasse",
    "iso:country":"AT",
    "sg:address":"Mariazeller Strasse 51",
    "sg:city":"M\u00fcrzzuschlag",
    "sg:classifiers":[
        {
            "category":"Manufacturing",
            "subcategory":"Wood Products",
            "type":"Manufacturing & Wholesale Goods"
        }
    ],
    "sg:phone":"+43 3852 3761",
    "sg:postcode":"8680",
    "sg:province":"Steiermark",
    "sg:tags":[
        "gate",
        "made",
        "door"
    ],
    "wof:name":"Franz Schweiger",
    "wof:placetype":"venue"
},
  "geometry": {"coordinates":[7.4943199158,50.8699913025],"type":"Point"}
}