{
  "type": "Feature",
  "properties": {
    "iso:country":"AT",
    "sg:address":"Nr 3",
    "sg:city":"St. Leonhard am Forst",
    "sg:orig_category":"Werbegrafik- U Grafik-Design",
    "sg:phone":"+43 4327 562146",
    "sg:postcode":"3243",
    "sg:province":"Nieder\u00f6sterreich",
    "wof:name":"Frost & Frost OEG",
    "wof:placetype":"venue"
},
  "geometry": {"coordinates":[166.9221496582,-0.5282999873],"type":"Point"}
}