{
  "type": "Feature",
  "properties": {
    "addr:full":"Am Fasangarten 31 Wien Wien 1120",
    "addr:housenumber":"31",
    "addr:postcode":"1120",
    "addr:street":"Am Fasangarten",
    "iso:country":"AT",
    "sg:address":"Am Fasangarten 31",
    "sg:city":"Wien",
    "sg:orig_category":"Markt- U Meinungsforschung",
    "sg:phone":"+43 4318 178532",
    "sg:postcode":"1120",
    "sg:province":"Wien",
    "wof:name":"domestic DATA Markt- u Meinungsforschungs GesmbH",
    "wof:placetype":"venue"
},
  "geometry": {"coordinates":[16.3035316467,48.17137146],"type":"Point"}
}