{
  "type": "Feature",
  "properties": {
    "addr:full":"Moserstrasse 29 Salzburg Salzburg 5020",
    "addr:housenumber":"29",
    "addr:postcode":"5020",
    "addr:street":"Moserstrasse;Salzburg",
    "iso:country":"AT",
    "sg:address":"Moserstrasse 29",
    "sg:city":"Salzburg",
    "sg:classifiers":[
        {
            "category":"Shopping",
            "subcategory":"Bicycles & Sporting Goods",
            "type":"Retail Goods"
        }
    ],
    "sg:phone":"+43 662 842525",
    "sg:postcode":"5020",
    "sg:province":"Salzburg",
    "wof:name":"Bj\u00f6rn Korell",
    "wof:placetype":"venue"
},
  "geometry": {"coordinates":[13.0115003586,47.8015937805],"type":"Point"}
}