{
  "type": "Feature",
  "properties": {
    "addr:full":"Oberhausner Str 3 Gro\u00df-Enzersdorf Nieder\u00f6sterreich 2301",
    "addr:housenumber":"3",
    "addr:postcode":"2301",
    "addr:street":"Str;Niederoesterreich",
    "iso:country":"AT",
    "sg:address":"Oberhausner Str 3",
    "sg:city":"Gro\u00df-Enzersdorf",
    "sg:orig_category":"Waren Aller Art",
    "sg:phone":"+43 4322 493870",
    "sg:postcode":"2301",
    "sg:province":"Nieder\u00f6sterreich",
    "wof:name":"Simlinger Rudolf",
    "wof:placetype":"venue"
},
  "geometry": {"coordinates":[16.5832061768,48.17993927],"type":"Point"}
}