{
  "type": "Feature",
  "properties": {
    "addr:full":"Lazarettg 9 Wien Wien 1090",
    "addr:housenumber":"9",
    "addr:postcode":"1090",
    "addr:street":"Lazarettg",
    "iso:country":"AT",
    "sg:address":"Lazarettg 9",
    "sg:city":"Wien",
    "sg:orig_category":"Handelsagenturen",
    "sg:phone":"+43 1 4021967",
    "sg:postcode":"1090",
    "sg:province":"Wien",
    "wof:name":"Nauton Handels-GmbH",
    "wof:placetype":"venue"
},
  "geometry": {"coordinates":[16.3503932953,48.2178573608],"type":"Point"}
}