{
  "type": "Feature",
  "properties": {
    "iso:country":"AT",
    "sg:address":"Taubstummeng 7-9",
    "sg:city":"Wien",
    "sg:orig_category":"Beratungsstellen",
    "sg:phone":"+43 4313 10888010",
    "sg:postcode":"1040",
    "sg:province":"Wien",
    "wof:name":"Helping Hands - Koordinationsb\u00fcro f\u00fcr integrative und antirassistische Projekte",
    "wof:placetype":"venue"
},
  "geometry": {"coordinates":[16.3716812134,48.1950721741],"type":"Point"}
}