{
  "type": "Feature",
  "properties": {
    "iso:country":"AT",
    "sg:address":"Plesching 1a ",
    "sg:city":"Linz",
    "sg:classifiers":[
        {
            "category":"Autos & Motor Vehicles",
            "subcategory":"Automobile Sales",
            "type":"Retail Goods"
        }
    ],
    "sg:phone":"+43 4373 2245640",
    "sg:postcode":"4040",
    "sg:province":"Ober\u00f6sterreich",
    "sg:tags":[
        "motor-cars"
    ],
    "wof:name":"LIFAG FAHRZEUGHANDELSGES.MBH",
    "wof:placetype":"venue"
},
  "geometry": {"coordinates":[14.309800148,48.3272781372],"type":"Point"}
}