{
  "type": "Feature",
  "properties": {
    "addr:full":"Pielach 6 Melk Nieder\u00f6sterreich 3390",
    "addr:housenumber":"6",
    "addr:postcode":"3390",
    "addr:street":"Pielach",
    "iso:country":"AT",
    "sg:address":"Pielach 6",
    "sg:city":"Melk",
    "sg:orig_category":"Industrie, Elektronik U Elektrik",
    "sg:phone":"+43 2752",
    "sg:postcode":"3390",
    "sg:province":"Nieder\u00f6sterreich",
    "sg:website":"http://www.loysch.at",
    "wof:name":"carlo - Loysch GmbH & Co KG",
    "wof:placetype":"venue"
},
  "geometry": {"coordinates":[15.3722600937,48.2295150757],"type":"Point"}
}