{
  "type": "Feature",
  "properties": {
    "addr:full":"Langgasse 24a Imst Tirol 6460",
    "addr:housenumber":"24a",
    "addr:postcode":"6460",
    "addr:street":"Langgasse;Tirol",
    "iso:country":"AT",
    "sg:address":"Langgasse 24a",
    "sg:city":"Imst",
    "sg:classifiers":[
        {
            "category":"Real Estate",
            "subcategory":"Architect",
            "type":"Services"
        }
    ],
    "sg:phone":"+43 5412 66492",
    "sg:postcode":"6460",
    "sg:province":"Tirol",
    "sg:tags":[
        "interior",
        "decoration"
    ],
    "wof:name":"Rudolf Jais",
    "wof:placetype":"venue"
},
  "geometry": {"coordinates":[10.7434911728,47.2306671143],"type":"Point"}
}