{
  "type": "Feature",
  "properties": {
    "addr:full":"Denkmalweg 8 Ledenitzen K\u00e4rnten 9581",
    "addr:housenumber":"8",
    "addr:postcode":"9581",
    "addr:street":"Denkmalweg;Kaernten",
    "iso:country":"AT",
    "sg:address":"Denkmalweg 8",
    "sg:city":"Ledenitzen",
    "sg:orig_category":"Behinderungen / Leben Mit Behinderungen",
    "sg:phone":"+43 4254 23650",
    "sg:postcode":"9581",
    "sg:province":"K\u00e4rnten",
    "wof:name":"Lebenshilfe K\u00e4rnten Verein f Menschen m geist und mehrf Behinderung",
    "wof:placetype":"venue"
},
  "geometry": {"coordinates":[13.9673147202,46.5644187927],"type":"Point"}
}