{
  "type": "Feature",
  "properties": {
    "addr:full":"Zellbergeben 23 Zell am Ziller Tirol 6280",
    "addr:housenumber":"23",
    "addr:postcode":"6280",
    "addr:street":"Zellbergeben;Tirol",
    "iso:country":"AT",
    "sg:address":"Zellbergeben 23",
    "sg:city":"Zell am Ziller",
    "sg:orig_category":"Bowden Cables",
    "sg:phone":"+43 5282 2651",
    "sg:postcode":"6280",
    "sg:province":"Tirol",
    "sg:website":"al-ko.com",
    "wof:name":"AL-KO KOBER GmbH Bereich Systemtechnik",
    "wof:placetype":"venue"
},
  "geometry": {"coordinates":[11.898935318,47.2374153137],"type":"Point"}
}