{
  "type": "Feature",
  "properties": {
    "iso:country":"AT",
    "sg:address":"M\u00fcllnerweg 7",
    "sg:city":"Seewalchen am Attersee",
    "sg:orig_category":"Pensionen / Privatzimmer",
    "sg:phone":"+43 4376 622581",
    "sg:postcode":"4863",
    "sg:province":"Ober\u00f6sterreich",
    "wof:name":"Pension Lacher",
    "wof:placetype":"venue"
},
  "geometry": {"coordinates":[13.5856723785,47.9540672302],"type":"Point"}
}