{
  "type": "Feature",
  "properties": {
    "addr:full":"Hausleiten 7 Waizenkirchen Ober\u00f6sterreich 4730",
    "addr:housenumber":"7",
    "addr:postcode":"4730",
    "addr:street":"Hausleiten",
    "iso:country":"AT",
    "sg:address":"Hausleiten 7",
    "sg:city":"Waizenkirchen",
    "sg:orig_category":"Tischlereien",
    "sg:phone":"+43 7277 2379",
    "sg:postcode":"4730",
    "sg:province":"Ober\u00f6sterreich",
    "wof:name":"Aichinger Franz",
    "wof:placetype":"venue"
},
  "geometry": {"coordinates":[13.8431749344,48.3425712585],"type":"Point"}
}