{
  "type": "Feature",
  "properties": {
    "addr:full":"Kaing 22 Wien Wien 1210",
    "addr:housenumber":"22",
    "addr:postcode":"1210",
    "addr:street":"Kaing",
    "iso:country":"AT",
    "sg:address":"Kaing 22",
    "sg:city":"Wien",
    "sg:orig_category":"\u00c3\u201erzte / F Allgemeinmedizin",
    "sg:phone":"+43 1 29214700",
    "sg:postcode":"1210",
    "sg:province":"Wien",
    "sg:website":"wien-gesundundschoen.at",
    "wof:name":"Epp-Fr\u00fchst\u00fcck Judith H Dr",
    "wof:placetype":"venue"
},
  "geometry": {"coordinates":[16.3824577332,48.296245575],"type":"Point"}
}