{
  "type": "Feature",
  "properties": {
    "addr:full":"Zwischeng 13 Ternitz Nieder\u00f6sterreich 2630",
    "addr:housenumber":"13",
    "addr:postcode":"2630",
    "addr:street":"Zwischeng",
    "iso:country":"AT",
    "sg:address":"Zwischeng 13",
    "sg:city":"Ternitz",
    "sg:orig_category":"Installationsunternehmen",
    "sg:phone":"+43 2630 38591",
    "sg:postcode":"2630",
    "sg:province":"Nieder\u00f6sterreich",
    "wof:name":"Ziegler GesmbH",
    "wof:placetype":"venue"
},
  "geometry": {"coordinates":[16.0354766846,47.7177886963],"type":"Point"}
}