{
  "type": "Feature",
  "properties": {
    "iso:country":"AT",
    "sg:address":"Klopstockg 34",
    "sg:city":"Wien",
    "sg:orig_category":"Fotoausarbeitungen",
    "sg:phone":"+43 1 4861305",
    "sg:postcode":"1170",
    "sg:province":"Wien",
    "wof:name":"Alfa Fachfotolabor GesmbH",
    "wof:placetype":"venue"
},
  "geometry": {"coordinates":[16.3235092163,48.2182235718],"type":"Point"}
}