{
  "type": "Feature",
  "properties": {
    "addr:full":"Gewerbepark P\u00f6lla 1 Seitenstetten Nieder\u00f6sterreich 3353",
    "addr:housenumber":"1",
    "addr:postcode":"3353",
    "addr:street":"Gewerbepark Poella",
    "iso:country":"AT",
    "sg:address":"Gewerbepark P\u00f6lla 1",
    "sg:city":"Seitenstetten",
    "sg:orig_category":"Lebensmittel / Einzelhandel",
    "sg:phone":"+43 7477 43256",
    "sg:postcode":"3353",
    "sg:province":"Nieder\u00f6sterreich",
    "wof:name":"Billa AG",
    "wof:placetype":"venue"
},
  "geometry": {"coordinates":[14.7085561752,48.0289573669],"type":"Point"}
}