{
  "type": "Feature",
  "properties": {
    "addr:full":"Aspettenstr 50a Perchtoldsdorf Nieder\u00f6sterreich 2380",
    "addr:housenumber":"50a",
    "addr:postcode":"2380",
    "addr:street":"Aspettenstr",
    "iso:country":"AT",
    "sg:address":"Aspettenstr 50a",
    "sg:city":"Perchtoldsdorf",
    "sg:orig_category":"Psychotherapie",
    "sg:phone":"+43 4365 05150809",
    "sg:postcode":"2380",
    "sg:province":"Nieder\u00f6sterreich",
    "wof:name":"Sendera Alice Mag Dr",
    "wof:placetype":"venue"
},
  "geometry": {"coordinates":[16.2843647003,48.1240501404],"type":"Point"}
}