{
  "type": "Feature",
  "properties": {
    "addr:full":"Salzburger Str 162 Wels Ober\u00f6sterreich 4600",
    "addr:housenumber":"162",
    "addr:postcode":"4600",
    "addr:street":"Salzburger Str;Oberoesterreich",
    "iso:country":"AT",
    "sg:address":"Salzburger Str 162",
    "sg:city":"Wels",
    "sg:orig_category":"Holdinggesellschaften",
    "sg:phone":"+43 7242 62261",
    "sg:postcode":"4600",
    "sg:province":"Ober\u00f6sterreich",
    "wof:name":"Arminger Holding GmbH",
    "wof:placetype":"venue"
},
  "geometry": {"coordinates":[13.9977550507,48.1561737061],"type":"Point"}
}