{
  "type": "Feature",
  "properties": {
    "iso:country":"AT",
    "sg:address":"Wiesbauerstr 4a/6",
    "sg:city":"Salzburg",
    "sg:orig_category":"Stahlbau",
    "sg:phone":"+43 662 8334830",
    "sg:postcode":"5020",
    "sg:province":"Salzburg",
    "wof:name":"KARRER STEEL COMPONENTS GmbH",
    "wof:placetype":"venue"
},
  "geometry": {"coordinates":[13.0240507126,47.8001098633],"type":"Point"}
}