{
  "type": "Feature",
  "properties": {
    "iso:country":"AT",
    "sg:address":"Siemensstr 43",
    "sg:city":"Rum",
    "sg:classifiers":[
        {
            "category":"Home & Garden",
            "subcategory":"Building Materials",
            "type":"Retail Goods"
        }
    ],
    "sg:phone":"+43 4350 6260",
    "sg:postcode":"6063",
    "sg:province":"Tirol",
    "sg:tags":[
        "baustoffe",
        "-material",
        "u"
    ],
    "wof:name":"Lieferasphalt GesmbH & Co OHG",
    "wof:placetype":"venue"
},
  "geometry": {"coordinates":[11.4481248856,47.2726745605],"type":"Point"}
}