{
  "type": "Feature",
  "properties": {
    "iso:country":"AT",
    "sg:address":"Hauptpl",
    "sg:city":"Tulln an der Donau",
    "sg:orig_category":"Boutiquen",
    "sg:phone":"+43 2272 61622",
    "sg:postcode":"3430",
    "sg:province":"Nieder\u00f6sterreich",
    "wof:name":"Jones",
    "wof:placetype":"venue"
},
  "geometry": {"coordinates":[16.0520000458,48.3313903809],"type":"Point"}
}