{
  "type": "Feature",
  "properties": {
    "addr:full":"Industriestrasse 30 Unterpremst\u00e4tten Steiermark 8141",
    "addr:housenumber":"30",
    "addr:postcode":"8141",
    "addr:street":"Industriestrasse",
    "iso:country":"AT",
    "sg:address":"Industriestrasse 30",
    "sg:city":"Unterpremst\u00e4tten",
    "sg:classifiers":[
        {
            "category":"Retail",
            "subcategory":"Auto Rental",
            "type":"Services"
        }
    ],
    "sg:phone":"+43 3135 5000",
    "sg:postcode":"8141",
    "sg:province":"Steiermark",
    "sg:tags":[
        "car",
        "transport"
    ],
    "sg:website":"frikus.com",
    "wof:name":"Frikus Friedrich Speditions ges.m.b.H.",
    "wof:placetype":"venue"
},
  "geometry": {"coordinates":[15.4404315948,46.9636001587],"type":"Point"}
}