{
  "type": "Feature",
  "properties": {
    "iso:country":"AT",
    "sg:address":"Bahnstr 7",
    "sg:city":"Aspang-Markt",
    "sg:orig_category":"Waren Aller Art",
    "sg:phone":"+43 2642 52198",
    "sg:postcode":"2870",
    "sg:province":"Nieder\u00f6sterreich",
    "wof:name":"Sorko Alfred",
    "wof:placetype":"venue"
},
  "geometry": {"coordinates":[16.0912837982,47.5566482544],"type":"Point"}
}