{
  "type": "Feature",
  "properties": {
    "addr:full":"Nr 15 Werfenweng Salzburg 5453",
    "addr:postcode":"5453",
    "addr:street":"Nr;Salzburg",
    "iso:country":"AT",
    "sg:address":"Nr 15",
    "sg:city":"Werfenweng",
    "sg:orig_category":"Pensionen / Privatzimmer",
    "sg:phone":"+43 6466 4630",
    "sg:postcode":"5453",
    "sg:province":"Salzburg",
    "wof:name":"Haus Alpina",
    "wof:placetype":"venue"
},
  "geometry": {"coordinates":[13.2578277588,47.46144104],"type":"Point"}
}