{
  "type": "Feature",
  "properties": {
    "addr:full":"Krumauer Str 35 Aigen im M\u00fchlkreis Ober\u00f6sterreich 4160",
    "addr:postcode":"4160",
    "addr:street":"Str 35",
    "iso:country":"AT",
    "sg:address":"Krumauer Str 35",
    "sg:city":"Aigen im M\u00fchlkreis",
    "sg:orig_category":"Tischlereien",
    "sg:phone":"+43 7281 6480",
    "sg:postcode":"4160",
    "sg:province":"Ober\u00f6sterreich",
    "wof:name":"ELA-M\u00f6bel GmbH",
    "wof:placetype":"venue"
},
  "geometry": {"coordinates":[13.976723671,48.6468315125],"type":"Point"}
}