{
  "type": "Feature",
  "properties": {
    "iso:country":"AT",
    "sg:address":"Haizingerg 43",
    "sg:city":"Wien",
    "sg:orig_category":"Psychotherapie",
    "sg:phone":"+43 1 4702443",
    "sg:postcode":"1180",
    "sg:province":"Wien",
    "wof:name":"Bartuska Christian",
    "wof:placetype":"venue"
},
  "geometry": {"coordinates":[16.3381881714,48.2295951843],"type":"Point"}
}