{
  "type": "Feature",
  "properties": {
    "iso:country":"AT",
    "sg:address":"Burgg 2",
    "sg:city":"Klagenfurt",
    "sg:orig_category":"Damenmoden",
    "sg:phone":"+43 463 500311",
    "sg:postcode":"9020",
    "sg:province":"K\u00e4rnten",
    "wof:name":"DWORSCHAK & PARTNER KG",
    "wof:placetype":"venue"
},
  "geometry": {"coordinates":[14.3087387085,46.6241264343],"type":"Point"}
}