{
  "type": "Feature",
  "properties": {
    "addr:full":"Gasser Pl 3 Hermagor K\u00e4rnten 9620",
    "addr:housenumber":"3",
    "addr:postcode":"9620",
    "addr:street":"Gasser Pl;Kaernten",
    "iso:country":"AT",
    "sg:address":"Gasser Pl 3",
    "sg:city":"Hermagor",
    "sg:orig_category":"Nachhilfe U Lernbetreuung",
    "sg:phone":"+43 4282 25195",
    "sg:postcode":"9620",
    "sg:province":"K\u00e4rnten",
    "wof:name":"Lern - und Trainingszentrum learnUP",
    "wof:placetype":"venue"
},
  "geometry": {"coordinates":[13.3705835342,46.6271324158],"type":"Point"}
}