{
  "type": "Feature",
  "properties": {
    "addr:full":"Hauptpl 10 Obersiebenbrunn Nieder\u00f6sterreich 2283",
    "addr:housenumber":"10",
    "addr:postcode":"2283",
    "addr:street":"Hauptpl;Niederoesterreich",
    "iso:country":"AT",
    "sg:address":"Hauptpl 10",
    "sg:city":"Obersiebenbrunn",
    "sg:orig_category":"Volksschulen",
    "sg:phone":"+43 2286 27376",
    "sg:postcode":"2283",
    "sg:province":"Nieder\u00f6sterreich",
    "wof:name":"Volksschule",
    "wof:placetype":"venue"
},
  "geometry": {"coordinates":[16.706817627,48.2651329041],"type":"Point"}
}