{
  "type": "Feature",
  "properties": {
    "addr:full":"Kirchengasse 6 Lackendorf Burgenland 7321",
    "addr:housenumber":"6",
    "addr:postcode":"7321",
    "addr:street":"Kirchengasse",
    "iso:country":"AT",
    "sg:address":"Kirchengasse 6",
    "sg:city":"Lackendorf",
    "sg:orig_category":"Furniture, General",
    "sg:phone":"+43 2619 7468",
    "sg:postcode":"7321",
    "sg:province":"Burgenland",
    "wof:name":"Hans Ecker",
    "wof:placetype":"venue"
},
  "geometry": {"coordinates":[16.5277137756,47.5678672791],"type":"Point"}
}