{
  "type": "Feature",
  "properties": {
    "iso:country":"AT",
    "sg:address":"Nr 37",
    "sg:city":"Gro\u00dfsch\u00f6nau",
    "sg:orig_category":"Fu\u00c3\u0178pflege U Fu\u00c3\u0178pflegesalons",
    "sg:phone":"+43 2815 6553",
    "sg:postcode":"3922",
    "sg:province":"Nieder\u00f6sterreich",
    "wof:name":"Fu\u00dfpflege Fachinstitut und Massage Ottilie Kapeller",
    "wof:placetype":"venue"
},
  "geometry": {"coordinates":[14.941901207,48.6518821716],"type":"Point"}
}