{
  "type": "Feature",
  "properties": {
    "iso:country":"AT",
    "sg:address":"Bahnhofstr 6",
    "sg:city":"Steyr",
    "sg:orig_category":"Bettfedernreinigung",
    "sg:phone":"+43 7252 53128",
    "sg:postcode":"4400",
    "sg:province":"Ober\u00f6sterreich",
    "wof:name":"G\u00e4rber Rupert",
    "wof:placetype":"venue"
},
  "geometry": {"coordinates":[14.4231481552,48.0410766602],"type":"Point"}
}