{
  "type": "Feature",
  "properties": {
    "iso:country":"AT",
    "sg:address":"Joseph Haydn-Pl 1",
    "sg:city":"Eisenstadt",
    "sg:orig_category":"Non-Classified Establishments",
    "sg:phone":"+43 2682 626380",
    "sg:postcode":"7000",
    "sg:province":"Burgenland",
    "wof:name":"Propstei- und Stadtpfarre Eisenstadt-Oberberg",
    "wof:placetype":"venue"
},
  "geometry": {"coordinates":[7.2542300224,51.0903396606],"type":"Point"}
}