{
  "type": "Feature",
  "properties": {
    "addr:full":"1. Str 5 Kematen an der Ybbs Nieder\u00f6sterreich 3331",
    "addr:housenumber":"5",
    "addr:postcode":"3331",
    "addr:street":"Str",
    "iso:country":"AT",
    "sg:address":"1. Str 5",
    "sg:city":"Kematen an der Ybbs",
    "sg:orig_category":"Friseure U Frisiersalons",
    "sg:phone":"+43 4374 482363",
    "sg:postcode":"3331",
    "sg:province":"Nieder\u00f6sterreich",
    "wof:name":"Frisiersalon Gino",
    "wof:placetype":"venue"
},
  "geometry": {"coordinates":[14.764588356,48.0256500244],"type":"Point"}
}