{
  "type": "Feature",
  "properties": {
    "addr:full":"Schruns Vorarlberg 6780",
    "addr:postcode":"6780",
    "iso:country":"AT",
    "sg:city":"Schruns",
    "sg:orig_category":"Feuerwehren",
    "sg:phone":"+43 5556 72300",
    "sg:postcode":"6780",
    "sg:province":"Vorarlberg",
    "wof:name":"Feuerwehr Schruns",
    "wof:placetype":"venue"
},
  "geometry": {"coordinates":[9.9195632935,47.0796165466],"type":"Point"}
}