{
  "type": "Feature",
  "properties": {
    "iso:country":"AT",
    "sg:address":"Mozartweg 12",
    "sg:city":"St. Johann in Tirol",
    "sg:orig_category":"Pensionen / Privatzimmer",
    "sg:phone":"+43 5352 62978",
    "sg:postcode":"6380",
    "sg:province":"Tirol",
    "wof:name":"Haus Griesser",
    "wof:placetype":"venue"
},
  "geometry": {"coordinates":[12.4178848267,47.5203132629],"type":"Point"}
}