{
  "type": "Feature",
  "properties": {
    "addr:full":"Sportplatzstr 458 Kaprun Salzburg 5710",
    "addr:housenumber":"458",
    "addr:postcode":"5710",
    "addr:street":"Kaprun Salzburg",
    "iso:country":"AT",
    "sg:address":"Sportplatzstr 458",
    "sg:city":"Kaprun",
    "sg:orig_category":"Bars-Cafes",
    "sg:phone":"+43 6547 8343",
    "sg:postcode":"5710",
    "sg:province":"Salzburg",
    "wof:name":"Das Grammophon",
    "wof:placetype":"venue"
},
  "geometry": {"coordinates":[12.750620842,47.2661895752],"type":"Point"}
}