{
  "type": "Feature",
  "properties": {
    "iso:country":"AT",
    "sg:address":"Gonzagag 12/13",
    "sg:city":"Wien",
    "sg:orig_category":"Telekommunikation",
    "sg:phone":"+43 1 537778",
    "sg:postcode":"1010",
    "sg:province":"Wien",
    "wof:name":"Contex Business Services GmbH",
    "wof:placetype":"venue"
},
  "geometry": {"coordinates":[16.370891571,48.2150688171],"type":"Point"}
}