{
  "type": "Feature",
  "properties": {
    "addr:full":"Trinser Str 17 Steinach am Brenner Tirol 6150",
    "addr:postcode":"6150",
    "addr:street":"Str 17;Tirol",
    "iso:country":"AT",
    "sg:address":"Trinser Str 17",
    "sg:city":"Steinach am Brenner",
    "sg:orig_category":"Polytechnische Schulen",
    "sg:phone":"+43 5272 6911",
    "sg:postcode":"6150",
    "sg:province":"Tirol",
    "wof:name":"Polytechnischer Lehrgang",
    "wof:placetype":"venue"
},
  "geometry": {"coordinates":[11.4643764496,47.092716217],"type":"Point"}
}