{
  "type": "Feature",
  "properties": {
    "addr:full":"Ledererg 32 Linz Ober\u00f6sterreich 4020",
    "addr:housenumber":"32",
    "addr:postcode":"4020",
    "addr:street":"Ledererg",
    "iso:country":"AT",
    "sg:address":"Ledererg 32",
    "sg:city":"Linz",
    "sg:orig_category":"Personalberatung",
    "sg:phone":"+43 4373 2791230",
    "sg:postcode":"4020",
    "sg:province":"Ober\u00f6sterreich",
    "wof:name":"B\u00dcRORING Beteiligungs GesmbH",
    "wof:placetype":"venue"
},
  "geometry": {"coordinates":[14.2953081131,48.3069953918],"type":"Point"}
}