{
  "type": "Feature",
  "properties": {
    "addr:full":"Oberdorf 15 Lermoos Tirol 6631",
    "addr:housenumber":"15",
    "addr:postcode":"6631",
    "addr:street":"Oberdorf;Tirol",
    "iso:country":"AT",
    "sg:address":"Oberdorf 15",
    "sg:city":"Lermoos",
    "sg:orig_category":"Appartements / Ferienwohnungen",
    "sg:phone":"+43 5673 3470",
    "sg:postcode":"6631",
    "sg:province":"Tirol",
    "wof:name":"Ferienwohnungen Guem Karl und Sonja",
    "wof:placetype":"venue"
},
  "geometry": {"coordinates":[10.8863286972,47.3971405029],"type":"Point"}
}