{
  "type": "Feature",
  "properties": {
    "addr:full":"Boschstr 36 Wels Ober\u00f6sterreich 4600",
    "addr:housenumber":"36",
    "addr:postcode":"4600",
    "addr:street":"Boschstr;Oberoesterreich",
    "iso:country":"AT",
    "sg:address":"Boschstr 36",
    "sg:city":"Wels",
    "sg:orig_category":"Gie\u00c3\u0178ereien",
    "sg:phone":"+43 4372 42474930",
    "sg:postcode":"4600",
    "sg:province":"Ober\u00f6sterreich",
    "wof:name":"Schwarz Hans Metallgie\u00dferei u Presserei GesmbH & Co KG",
    "wof:placetype":"venue"
},
  "geometry": {"coordinates":[14.0502624512,48.1606674194],"type":"Point"}
}