{
  "type": "Feature",
  "properties": {
    "addr:full":"Peter-Buchner-Str 524 Kaprun Salzburg 5710",
    "addr:housenumber":"524",
    "addr:postcode":"5710",
    "addr:street":"Kaprun Salzburg",
    "iso:country":"AT",
    "sg:address":"Peter-Buchner-Str 524",
    "sg:city":"Kaprun",
    "sg:orig_category":"Pensionen / Privatzimmer",
    "sg:phone":"+43 6547 8500",
    "sg:postcode":"5710",
    "sg:province":"Salzburg",
    "wof:name":"Pension Gschwandtner",
    "wof:placetype":"venue"
},
  "geometry": {"coordinates":[12.765291214,47.2689781189],"type":"Point"}
}