{
  "type": "Feature",
  "properties": {
    "addr:full":"Dr.-Schober-Str 14-18 Wien Wien 1130",
    "addr:postcode":"14-18;1130",
    "iso:country":"AT",
    "sg:address":"Dr.-Schober-Str 14-18",
    "sg:city":"Wien",
    "sg:orig_category":"Apotheken",
    "sg:phone":"+43 1 9610918",
    "sg:postcode":"1130",
    "sg:province":"Wien",
    "wof:name":"St Christophorus Apotheke Dr et Mag Walter Pahs KG",
    "wof:placetype":"venue"
},
  "geometry": {"coordinates":[16.2721099854,48.1651191711],"type":"Point"}
}