{
  "type": "Feature",
  "properties": {
    "addr:full":"Ischlerstr. 69 Bad Aussee Steiermark 8990",
    "addr:housenumber":"69",
    "addr:postcode":"8990",
    "addr:street":"Ischlerstr.",
    "iso:country":"AT",
    "sg:address":"Ischlerstr. 69",
    "sg:city":"Bad Aussee",
    "sg:classifiers":[
        {
            "category":"Bars & Pubs",
            "subcategory":"Nightclub",
            "type":"Food & Drink"
        }
    ],
    "sg:phone":"+43 4336 2252497",
    "sg:postcode":"8990",
    "sg:province":"Steiermark",
    "sg:tags":[
        "cake",
        "bread"
    ],
    "wof:name":"KARL SCHL\u00d6GEL",
    "wof:placetype":"venue"
},
  "geometry": {"coordinates":[13.7821416855,47.609336853],"type":"Point"}
}