{
  "type": "Feature",
  "properties": {
    "addr:full":"Mindelheimerstrasse 8 Schwaz Tirol 6130",
    "addr:housenumber":"8",
    "addr:postcode":"6130",
    "addr:street":"Mindelheimerstrasse;Tirol",
    "iso:country":"AT",
    "sg:address":"Mindelheimerstrasse 8",
    "sg:city":"Schwaz",
    "sg:classifiers":[
        {
            "category":"Sports & Exercise",
            "subcategory":"Race Track",
            "type":"Entertainment"
        }
    ],
    "sg:phone":"+43 5242 73666",
    "sg:postcode":"6130",
    "sg:province":"Tirol",
    "sg:tags":[
        "abrasive",
        "belt"
    ],
    "sg:website":"sia-abrasives.at",
    "wof:name":"sia Abrasives GmbH",
    "wof:placetype":"venue"
},
  "geometry": {"coordinates":[11.7097654343,47.3507041931],"type":"Point"}
}