{
  "type": "Feature",
  "properties": {
    "addr:full":"Karl Vogt-Str 1f/13 Zell am See Salzburg 5700",
    "addr:housenumber":"1f / 13",
    "addr:postcode":"5700",
    "addr:street":"Salzburg",
    "iso:country":"AT",
    "sg:address":"Karl Vogt-Str 1f/13",
    "sg:city":"Zell am See",
    "sg:orig_category":"Teppichreinigung U -Reparatur",
    "sg:phone":"+43 4365 4256381",
    "sg:postcode":"5700",
    "sg:province":"Salzburg",
    "wof:name":"Teppichtrockenreinigung Carpet Cleaner - Polsterungen - Erna Steger Handel-Verleih-Verkauf",
    "wof:placetype":"venue"
},
  "geometry": {"coordinates":[12.7946081161,47.3082046509],"type":"Point"}
}