{
  "type": "Feature",
  "properties": {
    "addr:full":"Gatterholzg 26 Wien Wien 1120",
    "addr:housenumber":"26",
    "addr:postcode":"1120",
    "addr:street":"Gatterholzg",
    "iso:country":"AT",
    "sg:address":"Gatterholzg 26",
    "sg:city":"Wien",
    "sg:orig_category":"Bauunternehmen",
    "sg:phone":"+43 1 8100130",
    "sg:postcode":"1120",
    "sg:province":"Wien",
    "wof:name":"ROSCH Bauunternehmung GmbH",
    "wof:placetype":"venue"
},
  "geometry": {"coordinates":[16.3213329315,48.1780166626],"type":"Point"}
}