{
  "type": "Feature",
  "properties": {
    "iso:country":"AT",
    "sg:address":"Harterfeldstr 9a",
    "sg:city":"Leonding",
    "sg:orig_category":"Tabaktrafiken",
    "sg:phone":"+43 732 671703",
    "sg:postcode":"4060",
    "sg:province":"Ober\u00f6sterreich",
    "wof:name":"B\u00f6hm Adelheid",
    "wof:placetype":"venue"
},
  "geometry": {"coordinates":[14.2571401596,48.2641601562],"type":"Point"}
}