{
  "type": "Feature",
  "properties": {
    "iso:country":"AT",
    "sg:address":"St.-Leonhard-Str 6",
    "sg:city":"M\u00f6llbr\u00fccke",
    "sg:orig_category":"Transportunternehmen",
    "sg:phone":"+43 4769 3240",
    "sg:postcode":"9813",
    "sg:province":"K\u00e4rnten",
    "wof:name":"Cervinka Christian",
    "wof:placetype":"venue"
},
  "geometry": {"coordinates":[15.8307695389,46.5753097534],"type":"Point"}
}