{
  "type": "Feature",
  "properties": {
    "addr:full":"K\u00e4rntner Str 8 Wien Wien 1010",
    "addr:housenumber":"8",
    "addr:postcode":"1010",
    "addr:street":"Str",
    "iso:country":"AT",
    "sg:address":"K\u00e4rntner Str 8",
    "sg:city":"Wien",
    "sg:orig_category":"Immobilienverwaltungen",
    "sg:phone":"+43 1 51292620",
    "sg:postcode":"1010",
    "sg:province":"Wien",
    "wof:name":"Neukirchen Heinrich Dr GmbH",
    "wof:placetype":"venue"
},
  "geometry": {"coordinates":[16.371011734,48.2017974854],"type":"Point"}
}