{
  "type": "Feature",
  "properties": {
    "iso:country":"AT",
    "sg:address":"Hauptstr 37",
    "sg:city":"Bad V\u00f6slau",
    "sg:orig_category":"Friseure U Frisiersalons",
    "sg:phone":"+43 4322 5275263",
    "sg:postcode":"2540",
    "sg:province":"Nieder\u00f6sterreich",
    "wof:name":"Braunger Eva & Team",
    "wof:placetype":"venue"
},
  "geometry": {"coordinates":[16.2009372711,47.9630355835],"type":"Point"}
}