{
  "type": "Feature",
  "properties": {
    "addr:full":"Lustenauer Str 37 Hard Vorarlberg 6971",
    "addr:housenumber":"37",
    "addr:postcode":"6971",
    "addr:street":"Str",
    "iso:country":"AT",
    "sg:address":"Lustenauer Str 37",
    "sg:city":"Hard",
    "sg:orig_category":"Chemikalien",
    "sg:phone":"+43 5574 822110",
    "sg:postcode":"6971",
    "sg:province":"Vorarlberg",
    "wof:name":"DEUROWOOD Produktions GmbH",
    "wof:placetype":"venue"
},
  "geometry": {"coordinates":[9.6712188721,47.4704818726],"type":"Point"}
}