{
  "type": "Feature",
  "properties": {
    "iso:country":"AT",
    "sg:address":"Lustenauer Str 37",
    "sg:city":"Hard",
    "sg:orig_category":"Chemikalien",
    "sg:phone":"+43 5574 822110",
    "sg:postcode":"6971",
    "sg:province":"Vorarlberg",
    "wof:name":"DEUROWOOD Produktions GmbH",
    "wof:placetype":"venue"
},
  "geometry": {"coordinates":[9.6712188721,47.4704818726],"type":"Point"}
}