{
  "type": "Feature",
  "properties": {
    "iso:country":"AT",
    "sg:address":"Obere Hauptstr 1",
    "sg:city":"Gols",
    "sg:orig_category":"Telekommunikation",
    "sg:phone":"+43 2173 20025",
    "sg:postcode":"7122",
    "sg:province":"Burgenland",
    "wof:name":"AIRWIRE Informationssysteme Ges.m.b.H.",
    "wof:placetype":"venue"
},
  "geometry": {"coordinates":[16.9075717926,47.8985061646],"type":"Point"}
}