{
  "type": "Feature",
  "properties": {
    "addr:full":"Reininghausstr 80 Graz Steiermark 8020",
    "addr:housenumber":"80",
    "addr:postcode":"8020",
    "addr:street":"Reininghausstr",
    "iso:country":"AT",
    "sg:address":"Reininghausstr 80",
    "sg:city":"Graz",
    "sg:orig_category":"Abschleppdienste",
    "sg:phone":"+43 4331 65040",
    "sg:postcode":"8020",
    "sg:province":"Steiermark",
    "wof:name":"STAMK Lenker Service GmbH",
    "wof:placetype":"venue"
},
  "geometry": {"coordinates":[15.3976783752,47.0619277954],"type":"Point"}
}