{
  "type": "Feature",
  "properties": {
    "iso:country":"AT",
    "sg:address":"Sickenberggasse 15 ",
    "sg:city":"Wien",
    "sg:classifiers":[
        {
            "category":"Government",
            "subcategory":"Fire Station",
            "type":"Public Place"
        }
    ],
    "sg:phone":"+43 1 3705207",
    "sg:postcode":"1190",
    "sg:province":"Wien",
    "sg:tags":[
        "awning",
        "shading",
        "tilt"
    ],
    "wof:name":"Irmgard Bocek-Weber",
    "wof:placetype":"venue"
},
  "geometry": {"coordinates":[16.3679924011,48.2579536438],"type":"Point"}
}