{
  "type": "Feature",
  "properties": {
    "iso:country":"AT",
    "sg:address":"Kornfeld 7",
    "sg:city":"Dornbirn",
    "sg:orig_category":"Sonnenschutzanlagen",
    "sg:phone":"+43 5572 54959",
    "sg:postcode":"6850",
    "sg:province":"Vorarlberg",
    "wof:name":"Baurenhas Walter",
    "wof:placetype":"venue"
},
  "geometry": {"coordinates":[9.7526502609,47.4314727783],"type":"Point"}
}