{
  "type": "Feature",
  "properties": {
    "addr:full":"Kirchstrasse 15 Schlins Vorarlberg 6824",
    "addr:housenumber":"15",
    "addr:postcode":"6824",
    "addr:street":"Kirchstrasse",
    "iso:country":"AT",
    "sg:address":"Kirchstrasse 15",
    "sg:city":"Schlins",
    "sg:classifiers":[
        {
            "category":"Home & Garden",
            "subcategory":"Carpets & Floor Coverings",
            "type":"Retail Goods"
        }
    ],
    "sg:phone":"+43 5524 8308",
    "sg:postcode":"6824",
    "sg:province":"Vorarlberg",
    "sg:tags":[
        "carpeting"
    ],
    "wof:name":"Rudolf Jussel",
    "wof:placetype":"venue"
},
  "geometry": {"coordinates":[9.7070798874,47.2059936523],"type":"Point"}
}