{
  "type": "Feature",
  "properties": {
    "iso:country":"AT",
    "sg:address":"Zetschegasse 13",
    "sg:city":"Wien",
    "sg:classifiers":[
        {
            "category":"Manufacturing",
            "subcategory":"Wood Products",
            "type":"Manufacturing & Wholesale Goods"
        }
    ],
    "sg:phone":"+43 1 6883400",
    "sg:postcode":"1230",
    "sg:province":"Wien",
    "sg:tags":[
        "gate",
        "made",
        "door"
    ],
    "sg:website":"rr-tueren.at",
    "wof:name":"T\u00fcr an T\u00fcr T\u00fcrenhandels- und -montagegmbH",
    "wof:placetype":"venue"
},
  "geometry": {"coordinates":[16.3321990967,48.1411437988],"type":"Point"}
}