{
  "type": "Feature",
  "properties": {
    "iso:country":"AT",
    "sg:address":"Marchfeldstr 15",
    "sg:city":"Wien",
    "sg:orig_category":"Sonnenstudios",
    "sg:phone":"+43 1 3331615",
    "sg:postcode":"1200",
    "sg:province":"Wien",
    "wof:name":"Power Sun",
    "wof:placetype":"venue"
},
  "geometry": {"coordinates":[16.3780899048,48.242023468],"type":"Point"}
}