{
  "type": "Feature",
  "properties": {
    "addr:full":"Pulverturmstr 11 Wels Ober\u00f6sterreich 4600",
    "addr:housenumber":"11",
    "addr:postcode":"4600",
    "addr:street":"Pulverturmstr;Oberoesterreich",
    "iso:country":"AT",
    "sg:address":"Pulverturmstr 11",
    "sg:city":"Wels",
    "sg:orig_category":"Fitnesscenter",
    "sg:phone":"+43 4372 4269380",
    "sg:postcode":"4600",
    "sg:province":"Ober\u00f6sterreich",
    "wof:name":"Freizeitparadies Pyramide GesmbH & Co KG",
    "wof:placetype":"venue"
},
  "geometry": {"coordinates":[14.0054473877,48.1463012695],"type":"Point"}
}