{
  "type": "Feature",
  "properties": {
    "addr:full":"Brockmanng 14 Graz Steiermark 8010",
    "addr:housenumber":"14",
    "addr:postcode":"8010",
    "addr:street":"Brockmanng",
    "iso:country":"AT",
    "sg:address":"Brockmanng 14",
    "sg:city":"Graz",
    "sg:classifiers":[
        {
            "category":"Restaurant",
            "type":"Food & Drink"
        }
    ],
    "sg:phone":"+43 316 846698",
    "sg:postcode":"8010",
    "sg:province":"Steiermark",
    "wof:name":"Bajardi Marion-B.A.D.A. Dipl M\u00f6belrestauratorin",
    "wof:placetype":"venue"
},
  "geometry": {"coordinates":[15.4502744675,47.0658226013],"type":"Point"}
}