{
  "type": "Feature",
  "properties": {
    "iso:country":"AT",
    "sg:address":"Kapellenweg 2",
    "sg:city":"Nu\u00dfdorf am Attersee",
    "sg:orig_category":"Pensionen / Privatzimmer",
    "sg:phone":"+43 76668035",
    "sg:postcode":"4865",
    "sg:province":"Ober\u00f6sterreich",
    "wof:name":"Graus Maria-Lilly",
    "wof:placetype":"venue"
},
  "geometry": {"coordinates":[13.5225925446,47.8832855225],"type":"Point"}
}