{
  "type": "Feature",
  "properties": {
    "addr:full":"Nr 155 Kirchbach K\u00e4rnten 9632",
    "addr:postcode":"9632",
    "addr:street":"Nr;Kirchbach Kaernten",
    "iso:country":"AT",
    "sg:address":"Nr 155",
    "sg:city":"Kirchbach",
    "sg:orig_category":"Gemeinden",
    "sg:phone":"+43 4342 842280",
    "sg:postcode":"9632",
    "sg:province":"K\u00e4rnten",
    "wof:name":"Marktgemeinde Kirchbach",
    "wof:placetype":"venue"
},
  "geometry": {"coordinates":[13.1851024628,46.6416473389],"type":"Point"}
}