{
  "type": "Feature",
  "properties": {
    "addr:full":"Feldg 1 M\u00fcnchendorf Nieder\u00f6sterreich 2482",
    "addr:housenumber":"1",
    "addr:postcode":"2482",
    "addr:street":"Feldg;Niederoesterreich",
    "iso:country":"AT",
    "sg:address":"Feldg 1",
    "sg:city":"M\u00fcnchendorf",
    "sg:orig_category":"Tischlereien",
    "sg:phone":"+43 2259 2245",
    "sg:postcode":"2482",
    "sg:province":"Nieder\u00f6sterreich",
    "wof:name":"Holzhandwerk Hepp",
    "wof:placetype":"venue"
},
  "geometry": {"coordinates":[16.3749675751,48.0265884399],"type":"Point"}
}