{
  "type": "Feature",
  "properties": {
    "iso:country":"AT",
    "sg:address":"Nr 23",
    "sg:city":"Unterlamm",
    "sg:orig_category":"Landwirtschaftliche Hilfsdienste",
    "sg:phone":"+43 4331 558439",
    "sg:postcode":"8352",
    "sg:province":"Steiermark",
    "wof:name":"Thier Alois",
    "wof:placetype":"venue"
},
  "geometry": {"coordinates":[16.0480117798,46.9859352112],"type":"Point"}
}