{
  "type": "Feature",
  "properties": {
    "addr:full":"Bahnstr 37 Schrems Nieder\u00f6sterreich 3943",
    "addr:housenumber":"37",
    "addr:postcode":"3943",
    "addr:street":"Bahnstr",
    "iso:country":"AT",
    "sg:address":"Bahnstr 37",
    "sg:city":"Schrems",
    "sg:orig_category":"Steinmetzbetriebe",
    "sg:phone":"+43 2853 76014",
    "sg:postcode":"3943",
    "sg:province":"Nieder\u00f6sterreich",
    "wof:name":"Joanna Naturstein-GesmbH",
    "wof:placetype":"venue"
},
  "geometry": {"coordinates":[15.0698375702,48.7889022827],"type":"Point"}
}