{
  "type": "Feature",
  "properties": {
    "iso:country":"AT",
    "sg:address":"Bahnstr 37",
    "sg:city":"Schrems",
    "sg:orig_category":"Steinmetzbetriebe",
    "sg:phone":"+43 2853 76014",
    "sg:postcode":"3943",
    "sg:province":"Nieder\u00f6sterreich",
    "wof:name":"Joanna Naturstein-GesmbH",
    "wof:placetype":"venue"
},
  "geometry": {"coordinates":[15.0698375702,48.7889022827],"type":"Point"}
}