{
  "type": "Feature",
  "properties": {
    "addr:full":"Nr 21 Obervellach K\u00e4rnten 9821",
    "addr:postcode":"9821",
    "addr:street":"Nr;Obervellach Kaernten",
    "iso:country":"AT",
    "sg:address":"Nr 21",
    "sg:city":"Obervellach",
    "sg:orig_category":"Gemeinden",
    "sg:phone":"+43 4782 22110",
    "sg:postcode":"9821",
    "sg:province":"K\u00e4rnten",
    "wof:name":"Marktgemeinde Obervellach",
    "wof:placetype":"venue"
},
  "geometry": {"coordinates":[13.202000618,46.9322319031],"type":"Point"}
}