{
  "type": "Feature",
  "properties": {
    "addr:full":"Jakob-Prandtauer-Str 1 Melk Nieder\u00f6sterreich 3390",
    "addr:housenumber":"1",
    "addr:postcode":"3390",
    "addr:street":"Jakob-Prandtauer-Str",
    "iso:country":"AT",
    "sg:address":"Jakob-Prandtauer-Str 1",
    "sg:city":"Melk",
    "sg:orig_category":"Glasereien",
    "sg:phone":"+43 2752 52009",
    "sg:postcode":"3390",
    "sg:province":"Nieder\u00f6sterreich",
    "wof:name":"Glaserei Winter GesmbH",
    "wof:placetype":"venue"
},
  "geometry": {"coordinates":[15.3362550735,48.2276496887],"type":"Point"}
}