{
  "type": "Feature",
  "properties": {
    "iso:country":"AT",
    "sg:address":"Stranach 32",
    "sg:city":"Mariapfarr",
    "sg:orig_category":"Pensionen / Privatzimmer",
    "sg:phone":"+43 6473 8602",
    "sg:postcode":"5571",
    "sg:province":"Salzburg",
    "wof:name":"Pension Krengut",
    "wof:placetype":"venue"
},
  "geometry": {"coordinates":[13.7428789139,47.1411170959],"type":"Point"}
}