{
  "type": "Feature",
  "properties": {
    "iso:country":"AT",
    "sg:address":"Margaretenstrasse 88-90",
    "sg:city":"Wien",
    "sg:classifiers":[
        {
            "category":"Building & Trades",
            "subcategory":"Construction",
            "type":"Services"
        }
    ],
    "sg:phone":"+43 1 5451429",
    "sg:postcode":"1050",
    "sg:province":"Wien",
    "sg:tags":[
        "installation",
        "air-conditioning",
        "system"
    ],
    "wof:name":"Ing. Johannes Schneider GesmbH",
    "wof:placetype":"venue"
},
  "geometry": {"coordinates":[16.3569545746,48.1904640198],"type":"Point"}
}