{
  "type": "Feature",
  "properties": {
    "iso:country":"AT",
    "sg:address":"Weitzendorf 4a",
    "sg:city":"Wei\u00dfkirchen an der Traun",
    "sg:orig_category":"Handelsagenturen",
    "sg:phone":"+43 4367 63317880",
    "sg:postcode":"4616",
    "sg:province":"Ober\u00f6sterreich",
    "wof:name":"HW-K\u00fcchen Helga Wiespointner",
    "wof:placetype":"venue"
},
  "geometry": {"coordinates":[14.110868454,48.128780365],"type":"Point"}
}