{
  "type": "Feature",
  "properties": {
    "addr:full":"Vorderthiersee 38 Thiersee Tirol 6335",
    "addr:housenumber":"38",
    "addr:postcode":"6335",
    "addr:street":"Vorderthiersee;Tirol",
    "iso:country":"AT",
    "sg:address":"Vorderthiersee 38",
    "sg:city":"Thiersee",
    "sg:orig_category":"Fleischhauereien",
    "sg:phone":"+43 4353 76523616",
    "sg:postcode":"6335",
    "sg:province":"Tirol",
    "wof:name":"Pfluger Hans GesmbH & Co KG",
    "wof:placetype":"venue"
},
  "geometry": {"coordinates":[12.1206007004,47.596698761],"type":"Point"}
}