{
  "type": "Feature",
  "properties": {
    "addr:full":"Markt 163 Mauterndorf Salzburg 5570",
    "addr:housenumber":"163",
    "addr:postcode":"5570",
    "addr:street":"Markt;Salzburg",
    "iso:country":"AT",
    "sg:address":"Markt 163",
    "sg:city":"Mauterndorf",
    "sg:orig_category":"Architekten",
    "sg:phone":"+43 4364 7220013",
    "sg:postcode":"5570",
    "sg:province":"Salzburg",
    "wof:name":"Planungsb\u00fcro Stocker & Wieland GmbH & Co KEG",
    "wof:placetype":"venue"
},
  "geometry": {"coordinates":[13.6843643188,47.1337509155],"type":"Point"}
}