{
  "type": "Feature",
  "properties": {
    "addr:full":"Odoakerg 13/3 Wien Wien 1160",
    "addr:housenumber":"13 / 3",
    "addr:postcode":"1160",
    "addr:street":"Odoakerg",
    "iso:country":"AT",
    "sg:address":"Odoakerg 13/3",
    "sg:city":"Wien",
    "sg:orig_category":"Stuckateure U Trockenausbauer",
    "sg:phone":"+43 4314 055633",
    "sg:postcode":"1160",
    "sg:province":"Wien",
    "wof:name":"VARGA Ferdinand Stuck- und Trockenausbau",
    "wof:placetype":"venue"
},
  "geometry": {"coordinates":[16.3083896637,48.2158164978],"type":"Point"}
}