{
  "type": "Feature",
  "properties": {
    "addr:full":"Rockhg 3 Wien Wien 1010",
    "addr:housenumber":"3",
    "addr:postcode":"1010",
    "addr:street":"Rockhg",
    "iso:country":"AT",
    "sg:address":"Rockhg 3",
    "sg:city":"Wien",
    "sg:orig_category":"Restaurants: Indisch",
    "sg:phone":"+43 4315 337516",
    "sg:postcode":"1010",
    "sg:province":"Wien",
    "wof:name":"Pizzeria Buongiorno",
    "wof:placetype":"venue"
},
  "geometry": {"coordinates":[16.3657798767,48.2135047913],"type":"Point"}
}