{
  "type": "Feature",
  "properties": {
    "iso:country":"AT",
    "sg:address":"Rockhg 3",
    "sg:city":"Wien",
    "sg:orig_category":"Restaurants: Indisch",
    "sg:phone":"+43 4315 337516",
    "sg:postcode":"1010",
    "sg:province":"Wien",
    "wof:name":"Pizzeria Buongiorno",
    "wof:placetype":"venue"
},
  "geometry": {"coordinates":[16.3657798767,48.2135047913],"type":"Point"}
}