{
  "type": "Feature",
  "properties": {
    "addr:full":"Am Schlossberg 1 Ladendorf Nieder\u00f6sterreich 2126",
    "addr:housenumber":"1",
    "addr:postcode":"2126",
    "addr:street":"Am Schlossberg",
    "iso:country":"AT",
    "sg:address":"Am Schlossberg 1",
    "sg:city":"Ladendorf",
    "sg:orig_category":"Forstverwaltungen",
    "sg:phone":"+43 4325 752279",
    "sg:postcode":"2126",
    "sg:province":"Nieder\u00f6sterreich",
    "wof:name":"Huck Max-Eduard Dipl-Ing Forst- u Gutsverwaltung",
    "wof:placetype":"venue"
},
  "geometry": {"coordinates":[16.4916610718,48.5364761353],"type":"Point"}
}