{
  "type": "Feature",
  "properties": {
    "addr:full":"M\u00fcrzg 11A Kapfenberg Steiermark 8605",
    "addr:housenumber":"11a",
    "addr:postcode":"8605",
    "addr:street":"Muerzg",
    "iso:country":"AT",
    "sg:address":"M\u00fcrzg 11A",
    "sg:city":"Kapfenberg",
    "sg:orig_category":"Finanz- U Wirtschaftsberatung",
    "sg:phone":"+43 4338 6227260",
    "sg:postcode":"8605",
    "sg:province":"Steiermark",
    "wof:name":"Mazuheli KEG",
    "wof:placetype":"venue"
},
  "geometry": {"coordinates":[15.2912454605,47.4438438416],"type":"Point"}
}