{
  "type": "Feature",
  "properties": {
    "addr:full":"Fernpa\u00dfstr 49 Biberwier Tirol 6633",
    "addr:housenumber":"49",
    "addr:postcode":"6633",
    "addr:street":"Fernpassstr;Tirol",
    "iso:country":"AT",
    "sg:address":"Fernpa\u00dfstr 49",
    "sg:city":"Biberwier",
    "sg:orig_category":"Feuerwehren",
    "sg:phone":"+43 5673 3488",
    "sg:postcode":"6633",
    "sg:province":"Tirol",
    "wof:name":"Freiwillige Feuerwehr Berwang",
    "wof:placetype":"venue"
},
  "geometry": {"coordinates":[10.8891744614,47.3794670105],"type":"Point"}
}