{
  "type": "Feature",
  "properties": {
    "iso:country":"AT",
    "sg:address":"Gmundner Str 22",
    "sg:city":"Sch\u00f6rfling am Attersee",
    "sg:classifiers":[
        {
            "category":"Travel",
            "subcategory":"Hotels & Motels",
            "type":"Entertainment"
        }
    ],
    "sg:phone":"+43 4376 622235",
    "sg:postcode":"4861",
    "sg:province":"Ober\u00f6sterreich",
    "wof:name":"Hotel Brauner B\u00e4r",
    "wof:placetype":"venue"
},
  "geometry": {"coordinates":[13.6066055298,47.9469451904],"type":"Point"}
}