{
  "type": "Feature",
  "properties": {
    "addr:full":"Kroissbergg 28 Wien Wien 1230",
    "addr:housenumber":"28",
    "addr:postcode":"1230",
    "addr:street":"Kroissbergg",
    "iso:country":"AT",
    "sg:address":"Kroissbergg 28",
    "sg:city":"Wien",
    "sg:orig_category":"Psychologen",
    "sg:phone":"+43 1 8894510",
    "sg:postcode":"1230",
    "sg:province":"Wien",
    "wof:name":"Landkammer Erika Dr",
    "wof:placetype":"venue"
},
  "geometry": {"coordinates":[16.2581214905,48.1517753601],"type":"Point"}
}