{
  "type": "Feature",
  "properties": {
    "iso:country":"AT",
    "sg:address":"Innrain 102",
    "sg:city":"Innsbruck",
    "sg:classifiers":[
        {
            "category":"Restaurant",
            "type":"Food & Drink"
        }
    ],
    "sg:phone":"+43 512 567568",
    "sg:postcode":"6020",
    "sg:province":"Tirol",
    "sg:tags":[
        "pizzeria"
    ],
    "wof:name":"Al Pacino",
    "wof:placetype":"venue"
},
  "geometry": {"coordinates":[11.3787899017,47.257648468],"type":"Point"}
}