{
  "type": "Feature",
  "properties": {
    "addr:full":"Schmiedg 8 Feldkirch Vorarlberg 6800",
    "addr:housenumber":"8",
    "addr:postcode":"6800",
    "addr:street":"Schmiedg",
    "iso:country":"AT",
    "sg:address":"Schmiedg 8",
    "sg:city":"Feldkirch",
    "sg:orig_category":"Fotografen",
    "sg:phone":"+43 5522 76158",
    "sg:postcode":"6800",
    "sg:province":"Vorarlberg",
    "wof:name":"Fotostudio Fels",
    "wof:placetype":"venue"
},
  "geometry": {"coordinates":[9.5975427628,47.2377319336],"type":"Point"}
}