{
  "type": "Feature",
  "properties": {
    "addr:full":"Rechbauerstr 10 Graz Steiermark 8010",
    "addr:housenumber":"10",
    "addr:postcode":"8010",
    "addr:street":"Rechbauerstr",
    "iso:country":"AT",
    "sg:address":"Rechbauerstr 10",
    "sg:city":"Graz",
    "sg:orig_category":"Bauunternehmen",
    "sg:phone":"+43 316 821811",
    "sg:postcode":"8010",
    "sg:province":"Steiermark",
    "wof:name":"Winkler Bauunternehmung GmbH",
    "wof:placetype":"venue"
},
  "geometry": {"coordinates":[15.4496841431,47.0697631836],"type":"Point"}
}