{
  "type": "Feature",
  "properties": {
    "addr:full":"Hauptpl 5 Gr\u00fcnbach am Schneeberg Nieder\u00f6sterreich 2733",
    "addr:housenumber":"5",
    "addr:postcode":"2733",
    "addr:street":"Hauptpl;Am Schneeberg",
    "iso:country":"AT",
    "sg:address":"Hauptpl 5",
    "sg:city":"Gr\u00fcnbach am Schneeberg",
    "sg:orig_category":"Lebensmittel / Einzelhandel",
    "sg:phone":"+43 2637 2336",
    "sg:postcode":"2733",
    "sg:province":"Nieder\u00f6sterreich",
    "wof:name":"Billa AG",
    "wof:placetype":"venue"
},
  "geometry": {"coordinates":[9.2478504181,49.6403236389],"type":"Point"}
}