{
  "type": "Feature",
  "properties": {
    "iso:country":"AT",
    "sg:address":"Gluckg 2",
    "sg:city":"Wien",
    "sg:orig_category":"Boutiquen",
    "sg:phone":"+43 1 5122781",
    "sg:postcode":"1010",
    "sg:province":"Wien",
    "wof:name":"Cesar-Collection for men",
    "wof:placetype":"venue"
},
  "geometry": {"coordinates":[16.3696708679,48.205493927],"type":"Point"}
}