{
  "type": "Feature",
  "properties": {
    "iso:country":"AT",
    "sg:address":"Millst\u00e4tter Str 22-24",
    "sg:city":"Feld am See",
    "sg:orig_category":"Elektroinstallationsunternehmen",
    "sg:phone":"+43 4246 3397",
    "sg:postcode":"9544",
    "sg:province":"K\u00e4rnten",
    "wof:name":"Tamberger TEG GmbH",
    "wof:placetype":"venue"
},
  "geometry": {"coordinates":[13.7468080521,46.7735710144],"type":"Point"}
}