{
  "type": "Feature",
  "properties": {
    "addr:full":"Dorf 63 Vomp Tirol 6134",
    "addr:housenumber":"63",
    "addr:postcode":"6134",
    "addr:street":"Dorf;Tirol",
    "iso:country":"AT",
    "sg:address":"Dorf 63",
    "sg:city":"Vomp",
    "sg:classifiers":[
        {
            "category":"Taxi",
            "type":"Transportation"
        }
    ],
    "sg:phone":"+43 5242 62794",
    "sg:postcode":"6134",
    "sg:province":"Tirol",
    "sg:tags":[
        "personentransporte",
        "u"
    ],
    "wof:name":"Taxi Wiedmann",
    "wof:placetype":"venue"
},
  "geometry": {"coordinates":[11.6827220917,47.341632843],"type":"Point"}
}