{
  "type": "Feature",
  "properties": {
    "addr:full":"Dr.-Theodor-K\u00f6rner-Str 51 Trumau Nieder\u00f6sterreich 2521",
    "addr:housenumber":"51",
    "addr:postcode":"2521",
    "addr:street":"Dr.-Theodor-Koerner-Str",
    "iso:country":"AT",
    "sg:address":"Dr.-Theodor-K\u00f6rner-Str 51",
    "sg:city":"Trumau",
    "sg:orig_category":"Balkon-, Loggien- U Terrassenverbauten",
    "sg:phone":"+43 4322 5382010",
    "sg:postcode":"2521",
    "sg:province":"Nieder\u00f6sterreich",
    "sg:website":"alustahl-berger.at",
    "wof:name":"Alu-Stahl Berger GmbH",
    "wof:placetype":"venue"
},
  "geometry": {"coordinates":[16.3423233032,47.9932975769],"type":"Point"}
}