{
  "type": "Feature",
  "properties": {
    "iso:country":"AT",
    "sg:address":"Gr\u00fcnsbach 334",
    "sg:city":"M\u00fcnster",
    "sg:orig_category":"Holzschindeln",
    "sg:phone":"+43 4353 378382",
    "sg:postcode":"6232",
    "sg:province":"Tirol",
    "sg:website":"holzschindeln-astner.at",
    "wof:name":"Astner Alfred",
    "wof:placetype":"venue"
},
  "geometry": {"coordinates":[11.8125801086,47.4356613159],"type":"Point"}
}