{
  "type": "Feature",
  "properties": {
    "addr:full":"Saarpl 20 Wien Wien 1190",
    "addr:housenumber":"20",
    "addr:postcode":"1190",
    "addr:street":"Saarpl",
    "iso:country":"AT",
    "sg:address":"Saarpl 20",
    "sg:city":"Wien",
    "sg:orig_category":"Non-Classified Establishments",
    "sg:phone":"+43 1 3704707",
    "sg:postcode":"1190",
    "sg:province":"Wien",
    "wof:name":"Rektorat der Kirche am Leopoldsberg",
    "wof:placetype":"venue"
},
  "geometry": {"coordinates":[16.3477687836,48.2458763123],"type":"Point"}
}