{
  "type": "Feature",
  "properties": {
    "addr:full":"Raffaelg. 32 Wien Wien 1200",
    "addr:housenumber":"32",
    "addr:postcode":"1200",
    "addr:street":"Raffaelg.",
    "iso:country":"AT",
    "sg:address":"Raffaelg. 32",
    "sg:city":"Wien",
    "sg:classifiers":[
        {
            "category":"Professional",
            "subcategory":"Engineering",
            "type":"Services"
        }
    ],
    "sg:phone":"+43 4313 326116",
    "sg:postcode":"1200",
    "sg:province":"Wien",
    "sg:tags":[
        "machine",
        "-",
        "mechanical"
    ],
    "wof:name":"ST\u00d6LLER DICHTUNGSTECHNIK GMBH",
    "wof:placetype":"venue"
},
  "geometry": {"coordinates":[16.3734645844,48.2306060791],"type":"Point"}
}