{
  "type": "Feature",
  "properties": {
    "addr:full":"Schlachthausg 46 Wien Wien 1030",
    "addr:housenumber":"46",
    "addr:postcode":"1030",
    "addr:street":"Schlachthausg",
    "iso:country":"AT",
    "sg:address":"Schlachthausg 46",
    "sg:city":"Wien",
    "sg:orig_category":"Feuerfestbau U -Materialien",
    "sg:phone":"+43 4317 1425910",
    "sg:postcode":"1030",
    "sg:province":"Wien",
    "wof:name":"Metallschornsteinbau GesmbH & Co KG",
    "wof:placetype":"venue"
},
  "geometry": {"coordinates":[16.4020824432,48.191444397],"type":"Point"}
}