{
  "type": "Feature",
  "properties": {
    "addr:full":"Bundesstr 3 St. Lorenzen im M\u00fcrztal Steiermark 8642",
    "addr:housenumber":"3",
    "addr:postcode":"8642",
    "addr:street":"Bundesstr",
    "iso:country":"AT",
    "sg:address":"Bundesstr 3",
    "sg:city":"St. Lorenzen im M\u00fcrztal",
    "sg:orig_category":"Paketdienste",
    "sg:phone":"+43 4338 6423600",
    "sg:postcode":"8642",
    "sg:province":"Steiermark",
    "sg:website":"gls-austria.com",
    "wof:name":"General Logistics Systems Austria GmbH - Depot 10",
    "wof:placetype":"venue"
},
  "geometry": {"coordinates":[15.3590774536,47.471622467],"type":"Point"}
}