{
  "type": "Feature",
  "properties": {
    "addr:full":"Marburger Str 1 Leibnitz Steiermark 8430",
    "addr:housenumber":"1",
    "addr:postcode":"8430",
    "addr:street":"Str;Steiermark",
    "iso:country":"AT",
    "sg:address":"Marburger Str 1",
    "sg:city":"Leibnitz",
    "sg:orig_category":"Fu\u00c3\u0178pflege U Fu\u00c3\u0178pflegesalons",
    "sg:phone":"+43 3452 866880",
    "sg:postcode":"8430",
    "sg:province":"Steiermark",
    "wof:name":"Atrium Beautyerlebnis",
    "wof:placetype":"venue"
},
  "geometry": {"coordinates":[15.5436429977,46.7787818909],"type":"Point"}
}