{
  "type": "Feature",
  "properties": {
    "addr:full":"Nr 72 Gro\u00dfpesendorf Steiermark 8211",
    "addr:postcode":"8211",
    "addr:street":"Nr",
    "iso:country":"AT",
    "sg:address":"Nr 72",
    "sg:city":"Gro\u00dfpesendorf",
    "sg:orig_category":"Volksschulen",
    "sg:phone":"+43 3113 2144",
    "sg:postcode":"8211",
    "sg:province":"Steiermark",
    "wof:name":"Volksschule",
    "wof:placetype":"venue"
},
  "geometry": {"coordinates":[15.7626972198,47.1513366699],"type":"Point"}
}