{
  "type": "Feature",
  "properties": {
    "addr:full":"Gnaser Str 2a Feldbach Steiermark 8330",
    "addr:postcode":"8330",
    "addr:street":"Str 2A",
    "iso:country":"AT",
    "sg:address":"Gnaser Str 2a",
    "sg:city":"Feldbach",
    "sg:orig_category":"Ingenieurkonsulenten / Zivilingenieure",
    "sg:phone":"+43 4331 522488",
    "sg:postcode":"8330",
    "sg:province":"Steiermark",
    "wof:name":"Reichsthaler Karl Dipl-Ing",
    "wof:placetype":"venue"
},
  "geometry": {"coordinates":[15.8833875656,46.9538192749],"type":"Point"}
}