{
  "type": "Feature",
  "properties": {
    "addr:full":"Steinerg 2 Zell am See Salzburg 5700",
    "addr:housenumber":"2",
    "addr:postcode":"5700",
    "addr:street":"Steinerg;Salzburg",
    "iso:country":"AT",
    "sg:address":"Steinerg 2",
    "sg:city":"Zell am See",
    "sg:orig_category":"Pensionen / Privatzimmer",
    "sg:phone":"+43 6542 737810",
    "sg:postcode":"5700",
    "sg:province":"Salzburg",
    "wof:name":"Andrea-Fr\u00fchst\u00fcckspension - Fam Brandst\u00e4tter",
    "wof:placetype":"venue"
},
  "geometry": {"coordinates":[12.7960691452,47.3246841431],"type":"Point"}
}