{
  "type": "Feature",
  "properties": {
    "addr:full":"Linzer Str 4 Eferding Ober\u00f6sterreich 4070",
    "addr:housenumber":"4",
    "addr:postcode":"4070",
    "addr:street":"Linzer Str",
    "iso:country":"AT",
    "sg:address":"Linzer Str 4",
    "sg:city":"Eferding",
    "sg:orig_category":"Landwirtschaftliche Produkte",
    "sg:phone":"+43 676 6064393",
    "sg:postcode":"4070",
    "sg:province":"Ober\u00f6sterreich",
    "wof:name":"Erzeugergemeinschaft Donautal KG",
    "wof:placetype":"venue"
},
  "geometry": {"coordinates":[14.0248556137,48.3057746887],"type":"Point"}
}