{
  "type": "Feature",
  "properties": {
    "addr:full":"Industriestr 6 Grieskirchen Ober\u00f6sterreich 4710",
    "addr:housenumber":"6",
    "addr:postcode":"4710",
    "addr:street":"Industriestr",
    "iso:country":"AT",
    "sg:address":"Industriestr 6",
    "sg:city":"Grieskirchen",
    "sg:orig_category":"Fleischereimaschinen U -Einrichtungen",
    "sg:phone":"+43 4372 48644340",
    "sg:postcode":"4710",
    "sg:province":"Ober\u00f6sterreich",
    "wof:name":"MOOSHAMMER hygiene & technik GmbH",
    "wof:placetype":"venue"
},
  "geometry": {"coordinates":[13.837808609,48.2304954529],"type":"Point"}
}