{
  "type": "Feature",
  "properties": {
    "addr:full":"Winklern bei Oberw\u00f6lz 23 Oberw\u00f6lz Steiermark 8832",
    "addr:housenumber":"23",
    "addr:postcode":"8832",
    "addr:street":"Oberwoelz Steiermark",
    "iso:country":"AT",
    "sg:address":"Winklern bei Oberw\u00f6lz 23",
    "sg:city":"Oberw\u00f6lz",
    "sg:classifiers":[
        {
            "category":"Shopping",
            "subcategory":"Computers & Home Electronics",
            "type":"Retail Goods"
        }
    ],
    "sg:phone":"+43 3581 8334",
    "sg:postcode":"8832",
    "sg:province":"Steiermark",
    "sg:tags":[
        "cable"
    ],
    "wof:name":"Elektro Kotnig Ges.m.b.H.",
    "wof:placetype":"venue"
},
  "geometry": {"coordinates":[14.2811422348,47.20337677],"type":"Point"}
}