{
  "type": "Feature",
  "properties": {
    "addr:full":"Casinoweg 3 Riezlern Vorarlberg 6991",
    "addr:housenumber":"3",
    "addr:postcode":"6991",
    "addr:street":"Casinoweg",
    "iso:country":"AT",
    "sg:address":"Casinoweg 3",
    "sg:city":"Riezlern",
    "sg:orig_category":"Physiotherapie",
    "sg:phone":"+43 4355 1730295",
    "sg:postcode":"6991",
    "sg:province":"Vorarlberg",
    "wof:name":"Van Gils Hans Dipl-PT",
    "wof:placetype":"venue"
},
  "geometry": {"coordinates":[10.1905345917,47.3584632874],"type":"Point"}
}