{
  "type": "Feature",
  "properties": {
    "addr:full":"Keesgasse 3 Graz Steiermark 8010",
    "addr:housenumber":"3",
    "addr:postcode":"8010",
    "addr:street":"Keesgasse",
    "iso:country":"AT",
    "sg:address":"Keesgasse 3",
    "sg:city":"Graz",
    "sg:classifiers":[
        {
            "category":"Manufacturing",
            "subcategory":"Metals",
            "type":"Manufacturing & Wholesale Goods"
        }
    ],
    "sg:phone":"+43 4331 68147710",
    "sg:postcode":"8010",
    "sg:province":"Steiermark",
    "sg:tags":[
        "processing"
    ],
    "wof:name":"USINOR CONSTRUCTION HAIRONVILLE AUSTRIA GMBH",
    "wof:placetype":"venue"
},
  "geometry": {"coordinates":[15.4395704269,47.0660858154],"type":"Point"}
}