{
  "type": "Feature",
  "properties": {
    "addr:full":"Industriepark 9 Timmersdorf Steiermark 8772",
    "addr:housenumber":"9",
    "addr:postcode":"8772",
    "addr:street":"Industriepark",
    "iso:country":"AT",
    "sg:address":"Industriepark 9",
    "sg:city":"Timmersdorf",
    "sg:orig_category":"Lastkraftwagen",
    "sg:phone":"+43 3833 8118",
    "sg:postcode":"8772",
    "sg:province":"Steiermark",
    "sg:website":"www.scania.at",
    "wof:name":"Scania \u00f6sterreich GesmbH",
    "wof:placetype":"venue"
},
  "geometry": {"coordinates":[14.9785928726,47.3746261597],"type":"Point"}
}