{
  "type": "Feature",
  "properties": {
    "addr:full":"Guntherstr 13 Wien Wien 1150",
    "addr:housenumber":"13",
    "addr:postcode":"1150",
    "addr:street":"Guntherstr",
    "iso:country":"AT",
    "sg:address":"Guntherstr 13",
    "sg:city":"Wien",
    "sg:orig_category":"Autoersatzteile",
    "sg:phone":"+43 1 9852485",
    "sg:postcode":"1150",
    "sg:province":"Wien",
    "wof:name":"Atlas Kfz-Ersatzteilhandel - Inh R Jankovic",
    "wof:placetype":"venue"
},
  "geometry": {"coordinates":[16.3255653381,48.2022781372],"type":"Point"}
}