{
  "type": "Feature",
  "properties": {
    "addr:full":"Mozartstr 6 Prinzersdorf Nieder\u00f6sterreich 3385",
    "addr:housenumber":"6",
    "addr:postcode":"3385",
    "addr:street":"Mozartstr",
    "iso:country":"AT",
    "sg:address":"Mozartstr 6",
    "sg:city":"Prinzersdorf",
    "sg:orig_category":"Elektronik",
    "sg:phone":"+43 2749 89480",
    "sg:postcode":"3385",
    "sg:province":"Nieder\u00f6sterreich",
    "wof:name":"M\u00fcllner Elektronik nach Ma\u00df",
    "wof:placetype":"venue"
},
  "geometry": {"coordinates":[15.5188455582,48.2034912109],"type":"Point"}
}