{
  "type": "Feature",
  "properties": {
    "addr:full":"Panoramastr 23 St. Georgen im Lavanttal K\u00e4rnten 9423",
    "addr:housenumber":"23",
    "addr:postcode":"9423",
    "addr:street":"Panoramastr",
    "iso:country":"AT",
    "sg:address":"Panoramastr 23",
    "sg:city":"St. Georgen im Lavanttal",
    "sg:orig_category":"Fliesen- U Plattenverlegungen",
    "sg:phone":"+43 4343 572805",
    "sg:postcode":"9423",
    "sg:province":"K\u00e4rnten",
    "wof:name":"Findenig Wolfgang",
    "wof:placetype":"venue"
},
  "geometry": {"coordinates":[14.9176588058,46.7218208313],"type":"Point"}
}