{
  "type": "Feature",
  "properties": {
    "iso:country":"AT",
    "sg:address":"Schulstr 11",
    "sg:city":"Hausmening",
    "sg:orig_category":"Politische Parteien",
    "sg:phone":"+43 7475 53575",
    "sg:postcode":"3363",
    "sg:province":"Nieder\u00f6sterreich",
    "wof:name":"Sozialdemokratische Partei \u00f6sterreichs",
    "wof:placetype":"venue"
},
  "geometry": {"coordinates":[14.8200178146,48.0788803101],"type":"Point"}
}