{
  "type": "Feature",
  "properties": {
    "addr:full":"Waidern 8 Schiedlberg Ober\u00f6sterreich 4521",
    "addr:housenumber":"8",
    "addr:postcode":"4521",
    "addr:street":"Waidern",
    "iso:country":"AT",
    "sg:address":"Waidern 8",
    "sg:city":"Schiedlberg",
    "sg:orig_category":"Diamanten U -Werkzeuge / F Industrie U Gewerbe",
    "sg:phone":"+43 4372 51472",
    "sg:postcode":"4521",
    "sg:province":"Ober\u00f6sterreich",
    "wof:name":"Prameshuber HandelsgesmbH",
    "wof:placetype":"venue"
},
  "geometry": {"coordinates":[14.2728557587,48.0709457397],"type":"Point"}
}