{
  "type": "Feature",
  "properties": {
    "addr:full":"Ramseider Str 10c Saalfelden am Steinernen Meer Salzburg 5760",
    "addr:postcode":"5760",
    "addr:street":"Str 10C",
    "iso:country":"AT",
    "sg:address":"Ramseider Str 10c",
    "sg:city":"Saalfelden am Steinernen Meer",
    "sg:orig_category":"Wasserwerke",
    "sg:phone":"+43 4365 8272100",
    "sg:postcode":"5760",
    "sg:province":"Salzburg",
    "wof:name":"Wasserwerk der Stadtgemeinde Saalfelden",
    "wof:placetype":"venue"
},
  "geometry": {"coordinates":[12.8502521515,47.4256668091],"type":"Point"}
}