{
  "type": "Feature",
  "properties": {
    "addr:full":"Michael-Pfurtscheller-Weg 19 Fulpmes Tirol 6166",
    "addr:housenumber":"19",
    "addr:postcode":"6166",
    "addr:street":"Michael-Pfurtscheller-Weg;Tirol",
    "iso:country":"AT",
    "sg:address":"Michael-Pfurtscheller-Weg 19",
    "sg:city":"Fulpmes",
    "sg:orig_category":"Steuerberatung",
    "sg:phone":"+43 4352 2564814",
    "sg:postcode":"6166",
    "sg:province":"Tirol",
    "wof:name":"H\u00f6rtnagl Gerda Mag",
    "wof:placetype":"venue"
},
  "geometry": {"coordinates":[11.3479423523,47.1566085815],"type":"Point"}
}