{
  "type": "Feature",
  "properties": {
    "addr:full":"Hochkreuzstr 19 Mondsee Ober\u00f6sterreich 5310",
    "addr:housenumber":"19",
    "addr:postcode":"5310",
    "addr:street":"Hochkreuzstr;Oberoesterreich",
    "iso:country":"AT",
    "sg:address":"Hochkreuzstr 19",
    "sg:city":"Mondsee",
    "sg:orig_category":"Pensionen / Privatzimmer",
    "sg:phone":"+43 6232 2514",
    "sg:postcode":"5310",
    "sg:province":"Ober\u00f6sterreich",
    "wof:name":"Stallinger Hilde",
    "wof:placetype":"venue"
},
  "geometry": {"coordinates":[13.3453598022,47.861289978],"type":"Point"}
}