{
  "type": "Feature",
  "properties": {
    "iso:country":"AT",
    "sg:address":"Nr 52",
    "sg:city":"Rangersdorf",
    "sg:orig_category":"Zimmereien",
    "sg:phone":"+43 4823 420",
    "sg:postcode":"9833",
    "sg:province":"K\u00e4rnten",
    "wof:name":"Rupitsch Josef",
    "wof:placetype":"venue"
},
  "geometry": {"coordinates":[12.9945631027,46.874256134],"type":"Point"}
}