{
  "type": "Feature",
  "properties": {
    "addr:full":"Hirschgraben 15 Feldkirch Vorarlberg 6800",
    "addr:housenumber":"15",
    "addr:postcode":"6800",
    "addr:street":"Hirschgraben",
    "iso:country":"AT",
    "sg:address":"Hirschgraben 15",
    "sg:city":"Feldkirch",
    "sg:orig_category":"\u00c3\u201erzte / F Allgemeinmedizin",
    "sg:phone":"+43 5522 720970",
    "sg:postcode":"6800",
    "sg:province":"Vorarlberg",
    "wof:name":"Gnaiger-Rathmanner Jutta Dr",
    "wof:placetype":"venue"
},
  "geometry": {"coordinates":[9.5965995789,47.2383766174],"type":"Point"}
}