{
  "type": "Feature",
  "properties": {
    "addr:full":"Nr 95 St. Katharein an der Laming Steiermark 8611",
    "addr:postcode":"8611",
    "addr:street":"Nr 95",
    "iso:country":"AT",
    "sg:address":"Nr 95",
    "sg:city":"St. Katharein an der Laming",
    "sg:orig_category":"Montagen U Montagetechnik",
    "sg:phone":"+43 4338 6920030",
    "sg:postcode":"8611",
    "sg:province":"Steiermark",
    "wof:name":"Wetzelh\u00fctter Industrieanlagen Montage GmbH",
    "wof:placetype":"venue"
},
  "geometry": {"coordinates":[15.1625738144,47.4715538025],"type":"Point"}
}