{
  "type": "Feature",
  "properties": {
    "addr:full":"Fabrikstr 34B Wels Ober\u00f6sterreich 4600",
    "addr:housenumber":"34b",
    "addr:postcode":"4600",
    "addr:street":"Fabrikstr;Oberoesterreich",
    "iso:country":"AT",
    "sg:address":"Fabrikstr 34B",
    "sg:city":"Wels",
    "sg:orig_category":"Werbeagenturen",
    "sg:phone":"+43 7242 207600",
    "sg:postcode":"4600",
    "sg:province":"Ober\u00f6sterreich",
    "wof:name":"Creativ Marketing",
    "wof:placetype":"venue"
},
  "geometry": {"coordinates":[14.019411087,48.1553039551],"type":"Point"}
}