{
  "type": "Feature",
  "properties": {
    "addr:full":"Bahnstr 5 Pinkafeld Burgenland 7423",
    "addr:housenumber":"5",
    "addr:postcode":"7423",
    "addr:street":"Bahnstr",
    "iso:country":"AT",
    "sg:address":"Bahnstr 5",
    "sg:city":"Pinkafeld",
    "sg:orig_category":"Autohandel",
    "sg:phone":"+43 3357 42337",
    "sg:postcode":"7423",
    "sg:province":"Burgenland",
    "wof:name":"Tripamer Paul Dr",
    "wof:placetype":"venue"
},
  "geometry": {"coordinates":[16.1289272308,47.358997345],"type":"Point"}
}