{
  "type": "Feature",
  "properties": {
    "addr:full":"Wiener Str 1 Hainburg an der Donau Nieder\u00f6sterreich 2410",
    "addr:housenumber":"1",
    "addr:postcode":"2410",
    "iso:country":"AT",
    "sg:address":"Wiener Str 1",
    "sg:city":"Hainburg an der Donau",
    "sg:orig_category":"Optiker",
    "sg:phone":"+43 4321 65628100",
    "sg:postcode":"2410",
    "sg:province":"Nieder\u00f6sterreich",
    "wof:name":"Alschinger Franz GesmbH",
    "wof:placetype":"venue"
},
  "geometry": {"coordinates":[16.9407596588,48.1469268799],"type":"Point"}
}