{
  "type": "Feature",
  "properties": {
    "addr:full":"Carnuntumstr 132 Hainburg an der Donau Nieder\u00f6sterreich 2410",
    "addr:housenumber":"132",
    "addr:postcode":"2410",
    "iso:country":"AT",
    "sg:address":"Carnuntumstr 132",
    "sg:city":"Hainburg an der Donau",
    "sg:orig_category":"Spielwaren U Spiele",
    "sg:phone":"+43 4367 67089720",
    "sg:postcode":"2410",
    "sg:province":"Nieder\u00f6sterreich",
    "wof:name":"Herzig Otto",
    "wof:placetype":"venue"
},
  "geometry": {"coordinates":[16.9315662384,48.139831543],"type":"Point"}
}