{
  "type": "Feature",
  "properties": {
    "addr:full":"Eiselbergstr 4 Wels Ober\u00f6sterreich 4600",
    "addr:housenumber":"4",
    "addr:postcode":"4600",
    "addr:street":"Eiselbergstr;Oberoesterreich",
    "iso:country":"AT",
    "sg:address":"Eiselbergstr 4",
    "sg:city":"Wels",
    "sg:orig_category":"Lebensmittel / Einzelhandel",
    "sg:phone":"+43 4372 4245524",
    "sg:postcode":"4600",
    "sg:province":"Ober\u00f6sterreich",
    "wof:name":"Penny Markt",
    "wof:placetype":"venue"
},
  "geometry": {"coordinates":[14.0115404129,48.1653823853],"type":"Point"}
}