{
  "type": "Feature",
  "properties": {
    "addr:full":"Pl\u00f6ven 15 Telfes im Stubai Tirol 6165",
    "addr:housenumber":"15",
    "addr:postcode":"6165",
    "addr:street":"Ploeven;Tirol",
    "iso:country":"AT",
    "sg:address":"Pl\u00f6ven 15",
    "sg:city":"Telfes im Stubai",
    "sg:orig_category":"Animal Claw And Nail Care Tools",
    "sg:phone":"+43 5225 62151",
    "sg:postcode":"6165",
    "sg:province":"Tirol",
    "wof:name":"Herbert Mair GesmbH Messerwaren-Schneidewerkzeuge, Kunststoffspritzerei",
    "wof:placetype":"venue"
},
  "geometry": {"coordinates":[11.3586997986,47.1647186279],"type":"Point"}
}