{
  "type": "Feature",
  "properties": {
    "addr:full":"M\u00fchlg 25 Gols Burgenland 7122",
    "addr:housenumber":"25",
    "addr:postcode":"7122",
    "addr:street":"Muehlg",
    "iso:country":"AT",
    "sg:address":"M\u00fchlg 25",
    "sg:city":"Gols",
    "sg:orig_category":"Personalbereitstellung",
    "sg:phone":"+43 664 1122144",
    "sg:postcode":"7122",
    "sg:province":"Burgenland",
    "wof:name":"Wendelin Personalleasing OEG",
    "wof:placetype":"venue"
},
  "geometry": {"coordinates":[16.9098987579,47.8975830078],"type":"Point"}
}