{
  "type": "Feature",
  "properties": {
    "addr:full":"Schwemmg 3 Hof am Leithagebirge Nieder\u00f6sterreich 2451",
    "addr:housenumber":"3",
    "addr:postcode":"2451",
    "addr:street":"Schwemmg",
    "iso:country":"AT",
    "sg:address":"Schwemmg 3",
    "sg:city":"Hof am Leithagebirge",
    "sg:orig_category":"Feuerwehren",
    "sg:phone":"+43 2168 63939",
    "sg:postcode":"2451",
    "sg:province":"Nieder\u00f6sterreich",
    "wof:name":"Freiwillige Feuerwehr Hof a Leithagebirge",
    "wof:placetype":"venue"
},
  "geometry": {"coordinates":[16.5753288269,47.9440155029],"type":"Point"}
}