{
  "type": "Feature",
  "properties": {
    "addr:full":"Wiener Str 106 Eichgraben Nieder\u00f6sterreich 3032",
    "addr:housenumber":"106",
    "addr:postcode":"3032",
    "addr:street":"Eichgraben Niederoesterreich",
    "iso:country":"AT",
    "sg:address":"Wiener Str 106",
    "sg:city":"Eichgraben",
    "sg:orig_category":"Blumengro\u00c3\u0178handel",
    "sg:phone":"+43 664 3011419",
    "sg:postcode":"3032",
    "sg:province":"Nieder\u00f6sterreich",
    "wof:name":"Kaljosi KEG",
    "wof:placetype":"venue"
},
  "geometry": {"coordinates":[15.9844560623,48.1805915833],"type":"Point"}
}