{
  "type": "Feature",
  "properties": {
    "addr:full":"Nofler Strasse 62 Feldkirch Vorarlberg 6800",
    "addr:housenumber":"62",
    "addr:postcode":"6800",
    "addr:street":"Nofler Strasse",
    "iso:country":"AT",
    "sg:address":"Nofler Strasse 62",
    "sg:city":"Feldkirch",
    "sg:classifiers":[
        {
            "category":"Food & Beverages",
            "subcategory":"Cheese",
            "type":"Retail Goods"
        }
    ],
    "sg:phone":"+43 5522 721300",
    "sg:postcode":"6800",
    "sg:province":"Vorarlberg",
    "sg:website":"vmilch.at",
    "wof:name":"VORARLBERG MILCH reg.Gen.m.b.H.",
    "wof:placetype":"venue"
},
  "geometry": {"coordinates":[9.5833683014,47.2548332214],"type":"Point"}
}