{
  "type": "Feature",
  "properties": {
    "iso:country":"AT",
    "sg:address":"Hofm\u00fchle 5",
    "sg:city":"Haid",
    "sg:orig_category":"Fenster",
    "sg:phone":"+43 699 11810049",
    "sg:postcode":"4053",
    "sg:province":"Ober\u00f6sterreich",
    "wof:name":"F + E Fenster Winterg\u00e4rten Sonnenschutz",
    "wof:placetype":"venue"
},
  "geometry": {"coordinates":[14.2510099411,48.2047348022],"type":"Point"}
}