{
  "type": "Feature",
  "properties": {
    "addr:full":"Pelzmannstrasse 3 Wagna Steiermark 8435",
    "addr:housenumber":"3",
    "addr:postcode":"8435",
    "addr:street":"Pelzmannstrasse",
    "iso:country":"AT",
    "sg:address":"Pelzmannstrasse 3",
    "sg:city":"Wagna",
    "sg:classifiers":[
        {
            "category":"Food & Beverages",
            "subcategory":"Groceries & Convenience Stores",
            "type":"Retail Goods"
        }
    ],
    "sg:phone":"+43 3452 823680",
    "sg:postcode":"8435",
    "sg:province":"Steiermark",
    "sg:tags":[
        "flour",
        "meal"
    ],
    "sg:website":"kuerbiskernoel.com",
    "wof:name":"\u00d6lm\u00fchle Pelzmann GmbH",
    "wof:placetype":"venue"
},
  "geometry": {"coordinates":[15.5559873581,46.7715911865],"type":"Point"}
}