{
  "type": "Feature",
  "properties": {
    "addr:full":"Gentzg 62 Wien Wien 1180",
    "addr:housenumber":"62",
    "addr:postcode":"1180",
    "addr:street":"Gentzg",
    "iso:country":"AT",
    "sg:address":"Gentzg 62",
    "sg:city":"Wien",
    "sg:orig_category":"Lebensmittel / Einzelhandel",
    "sg:phone":"+43 1 4706776",
    "sg:postcode":"1180",
    "sg:province":"Wien",
    "wof:name":"MONDO Lebensmitteldiskonter",
    "wof:placetype":"venue"
},
  "geometry": {"coordinates":[16.340385437,48.2276573181],"type":"Point"}
}