{
  "type": "Feature",
  "properties": {
    "addr:full":"Nr 211 Saalbach Salzburg 5753",
    "addr:postcode":"5753",
    "addr:street":"Nr 211;Salzburg",
    "iso:country":"AT",
    "sg:address":"Nr 211",
    "sg:city":"Saalbach",
    "sg:classifiers":[
        {
            "category":"Travel",
            "subcategory":"Hotels & Motels",
            "type":"Entertainment"
        }
    ],
    "sg:phone":"+43 6541 62280",
    "sg:postcode":"5753",
    "sg:province":"Salzburg",
    "wof:name":"Hotel Haider KG",
    "wof:placetype":"venue"
},
  "geometry": {"coordinates":[12.6367301941,47.3899307251],"type":"Point"}
}