{
  "type": "Feature",
  "properties": {
    "addr:full":"Stumperg 14/22 Wien Wien 1060",
    "addr:housenumber":"14 / 22",
    "addr:postcode":"1060",
    "addr:street":"Stumperg",
    "iso:country":"AT",
    "sg:address":"Stumperg 14/22",
    "sg:city":"Wien",
    "sg:orig_category":"Sportschulen",
    "sg:phone":"+43 4315 963340",
    "sg:postcode":"1060",
    "sg:province":"Wien",
    "sg:website":"ewto.at",
    "wof:name":"Wing Tsun Schule EWTO-Schulen Oliver K\u00f6nig",
    "wof:placetype":"venue"
},
  "geometry": {"coordinates":[16.3460063934,48.192779541],"type":"Point"}
}