{
  "type": "Feature",
  "properties": {
    "iso:country":"AT",
    "sg:address":"Kienmayerg 2",
    "sg:city":"Wien",
    "sg:orig_category":"Restaurants: Chinesisch",
    "sg:phone":"+43 1 9859900",
    "sg:postcode":"1140",
    "sg:province":"Wien",
    "wof:name":"China-Restaurant Sunny",
    "wof:placetype":"venue"
},
  "geometry": {"coordinates":[16.3169403076,48.1992797852],"type":"Point"}
}