{
  "type": "Feature",
  "properties": {
    "addr:full":"Maibrunnenweg 1 Bad Kleinkirchheim K\u00e4rnten 9546",
    "addr:housenumber":"1",
    "addr:postcode":"9546",
    "addr:street":"Maibrunnenweg",
    "iso:country":"AT",
    "sg:address":"Maibrunnenweg 1",
    "sg:city":"Bad Kleinkirchheim",
    "sg:orig_category":"Trachtenbekleidung",
    "sg:phone":"+43 4342 408386",
    "sg:postcode":"9546",
    "sg:province":"K\u00e4rnten",
    "wof:name":"Albeck Tracht u Mode",
    "wof:placetype":"venue"
},
  "geometry": {"coordinates":[13.781129837,46.8131980896],"type":"Point"}
}