{
  "type": "Feature",
  "properties": {
    "addr:full":"Nr 29 Graden Steiermark 8593",
    "addr:postcode":"8593",
    "addr:street":"Nr;Graden",
    "iso:country":"AT",
    "sg:address":"Nr 29",
    "sg:city":"Graden",
    "sg:orig_category":"Bauunternehmen",
    "sg:phone":"+43 4331 444989",
    "sg:postcode":"8593",
    "sg:province":"Steiermark",
    "wof:name":"Steirer Hermann Bauunternehmung GesmbH",
    "wof:placetype":"venue"
},
  "geometry": {"coordinates":[15.033780098,47.132598877],"type":"Point"}
}