{
  "type": "Feature",
  "properties": {
    "addr:full":"Doerenkampgasse 7 Wien Wien 1100",
    "addr:housenumber":"7",
    "addr:postcode":"1100",
    "addr:street":"Doerenkampgasse",
    "iso:country":"AT",
    "sg:address":"Doerenkampgasse 7",
    "sg:city":"Wien",
    "sg:classifiers":[
        {
            "category":"Banks & Credit Unions",
            "subcategory":"Investment Brokerage",
            "type":"Services"
        }
    ],
    "sg:phone":"+43 1 81512710",
    "sg:postcode":"1100",
    "sg:province":"Wien",
    "sg:tags":[
        "label",
        "bar-code"
    ],
    "sg:website":"compactelectric.at",
    "wof:name":"Compact Electric Elektrotechnische Ger\u00e4te Handelsges.m.b.H.",
    "wof:placetype":"venue"
},
  "geometry": {"coordinates":[16.3795642853,48.142326355],"type":"Point"}
}