{
  "type": "Feature",
  "properties": {
    "addr:full":"St. Veiter Str 58 Klagenfurt K\u00e4rnten 9020",
    "addr:housenumber":"58",
    "addr:postcode":"9020",
    "addr:street":"St. Veiter Str;Kaernten",
    "iso:country":"AT",
    "sg:address":"St. Veiter Str 58",
    "sg:city":"Klagenfurt",
    "sg:orig_category":"Elektroinstallationsunternehmen",
    "sg:phone":"+43 4346 3555590",
    "sg:postcode":"9020",
    "sg:province":"K\u00e4rnten",
    "wof:name":"Magerle Elektro GesmbH",
    "wof:placetype":"venue"
},
  "geometry": {"coordinates":[14.3107213974,46.6329650879],"type":"Point"}
}