{
  "type": "Feature",
  "properties": {
    "addr:full":"Mozartstr 2 Persenbeug Nieder\u00f6sterreich 3680",
    "addr:housenumber":"2",
    "addr:postcode":"3680",
    "addr:street":"Mozartstr",
    "iso:country":"AT",
    "sg:address":"Mozartstr 2",
    "sg:city":"Persenbeug",
    "sg:orig_category":"Maschinenbau",
    "sg:phone":"+43 7412 527450",
    "sg:postcode":"3680",
    "sg:province":"Nieder\u00f6sterreich",
    "wof:name":"Metallbau EDER GmbH & Co KG",
    "wof:placetype":"venue"
},
  "geometry": {"coordinates":[15.0908613205,48.188495636],"type":"Point"}
}