{
  "type": "Feature",
  "properties": {
    "addr:full":"Waagg 2a Wien Wien 1040",
    "addr:housenumber":"2a",
    "addr:postcode":"1040",
    "addr:street":"Waagg",
    "iso:country":"AT",
    "sg:address":"Waagg 2a",
    "sg:city":"Wien",
    "sg:classifiers":[
        {
            "category":"Organizations",
            "subcategory":"Community Association",
            "type":"Services"
        }
    ],
    "sg:phone":"+43 699 19678777",
    "sg:postcode":"1040",
    "sg:province":"Wien",
    "sg:tags":[
        "relation",
        "public"
    ],
    "wof:name":"medmarketing O. Pichelmayer",
    "wof:placetype":"venue"
},
  "geometry": {"coordinates":[16.3669013977,48.194896698],"type":"Point"}
}