{
  "type": "Feature",
  "properties": {
    "addr:full":"Reschg 12 Wien Wien 1120",
    "addr:housenumber":"12",
    "addr:postcode":"1120",
    "addr:street":"Reschg",
    "iso:country":"AT",
    "sg:address":"Reschg 12",
    "sg:city":"Wien",
    "sg:orig_category":"Geschenkartikel",
    "sg:phone":"+43 1 8179274",
    "sg:postcode":"1120",
    "sg:province":"Wien",
    "wof:name":"Xiao Yan ZHU KEG",
    "wof:placetype":"venue"
},
  "geometry": {"coordinates":[16.3319396973,48.180393219],"type":"Point"}
}