{
  "type": "Feature",
  "properties": {
    "addr:full":"Hauptstr 59 Gramatneusiedl Nieder\u00f6sterreich 2440",
    "addr:housenumber":"59",
    "addr:postcode":"2440",
    "addr:street":"Hauptstr",
    "iso:country":"AT",
    "sg:address":"Hauptstr 59",
    "sg:city":"Gramatneusiedl",
    "sg:orig_category":"Autohandel",
    "sg:phone":"+43 2234 74015",
    "sg:postcode":"2440",
    "sg:province":"Nieder\u00f6sterreich",
    "wof:name":"Autohaus Gramatneusiedl",
    "wof:placetype":"venue"
},
  "geometry": {"coordinates":[16.4970798492,48.0208206177],"type":"Point"}
}