{
  "type": "Feature",
  "properties": {
    "addr:full":"Gasteig 10 Neustift im Stubaital Tirol 6167",
    "addr:housenumber":"10",
    "addr:postcode":"6167",
    "addr:street":"Gasteig;Tirol",
    "iso:country":"AT",
    "sg:address":"Gasteig 10",
    "sg:city":"Neustift im Stubaital",
    "sg:orig_category":"Fliesen- U Plattenverlegungen",
    "sg:phone":"+43 4352 262524",
    "sg:postcode":"6167",
    "sg:province":"Tirol",
    "wof:name":"Pension Rosenh\u00fcgel",
    "wof:placetype":"venue"
},
  "geometry": {"coordinates":[11.2604389191,47.0727996826],"type":"Point"}
}