{
  "type": "Feature",
  "properties": {
    "addr:full":"Dorfstrasse 78 St. Ulrich am Pillersee Tirol 6393",
    "addr:housenumber":"78",
    "addr:postcode":"6393",
    "addr:street":"Dorfstrasse;Tirol",
    "iso:country":"AT",
    "sg:address":"Dorfstrasse 78",
    "sg:city":"St. Ulrich am Pillersee",
    "sg:classifiers":[
        {
            "category":"Wholesale",
            "subcategory":"Photographic Equipment",
            "type":"Manufacturing & Wholesale Goods"
        }
    ],
    "sg:phone":"+43 5354 88271",
    "sg:postcode":"6393",
    "sg:province":"Tirol",
    "sg:tags":[
        "badminton"
    ],
    "sg:website":"intersportguenther.at",
    "wof:name":"G\u00fcnther Sportartikelhandels-GmbH",
    "wof:placetype":"venue"
},
  "geometry": {"coordinates":[12.573638916,47.5280189514],"type":"Point"}
}