{
  "type": "Feature",
  "properties": {
    "iso:country":"AT",
    "sg:address":"Pottendorfer Str 39",
    "sg:city":"Wiener Neustadt",
    "sg:orig_category":"Raumausstattung",
    "sg:phone":"+43 2622 87295",
    "sg:postcode":"2700",
    "sg:province":"Nieder\u00f6sterreich",
    "wof:name":"Heim & Haus GmbH",
    "wof:placetype":"venue"
},
  "geometry": {"coordinates":[16.2513771057,47.8259773254],"type":"Point"}
}