{
  "type": "Feature",
  "properties": {
    "addr:full":"Kirchenpl 5 Maissau Nieder\u00f6sterreich 3712",
    "addr:housenumber":"5",
    "addr:postcode":"3712",
    "addr:street":"Kirchenpl",
    "iso:country":"AT",
    "sg:address":"Kirchenpl 5",
    "sg:city":"Maissau",
    "sg:orig_category":"Volksschulen",
    "sg:phone":"+43 4329 5882282",
    "sg:postcode":"3712",
    "sg:province":"Nieder\u00f6sterreich",
    "wof:name":"Volksschule",
    "wof:placetype":"venue"
},
  "geometry": {"coordinates":[15.825545311,48.5716209412],"type":"Point"}
}