{
  "type": "Feature",
  "properties": {
    "addr:full":"Oetzerm\u00fchler Weg 3 Oetz Tirol 6433",
    "addr:housenumber":"3",
    "addr:postcode":"6433",
    "addr:street":"Oetzermuehler Weg;Tirol",
    "iso:country":"AT",
    "sg:address":"Oetzerm\u00fchler Weg 3",
    "sg:city":"Oetz",
    "sg:orig_category":"Pensionen / Privatzimmer",
    "sg:phone":"+43 5252 6432",
    "sg:postcode":"6433",
    "sg:province":"Tirol",
    "wof:name":"Frischmann Claudia",
    "wof:placetype":"venue"
},
  "geometry": {"coordinates":[10.8976020813,47.20287323],"type":"Point"}
}