{
  "type": "Feature",
  "properties": {
    "addr:full":"Kaiserin-Elisabeth-Str 7/1/6 Maria Enzersdorf Nieder\u00f6sterreich 2344",
    "addr:housenumber":"7 / 1 / 6",
    "addr:postcode":"2344",
    "addr:street":"Kaiserin-Elisabeth-Str",
    "iso:country":"AT",
    "sg:address":"Kaiserin-Elisabeth-Str 7/1/6",
    "sg:city":"Maria Enzersdorf",
    "sg:orig_category":"Baumeister",
    "sg:phone":"+43 4322 3645810",
    "sg:postcode":"2344",
    "sg:province":"Nieder\u00f6sterreich",
    "wof:name":"Mayer Klaus-J\u00fcrgen Ing",
    "wof:placetype":"venue"
},
  "geometry": {"coordinates":[16.2844219208,48.0951499939],"type":"Point"}
}