{
  "type": "Feature",
  "properties": {
    "iso:country":"AT",
    "sg:address":"Iglaseeg 72",
    "sg:city":"Wien",
    "sg:orig_category":"Waren Aller Art",
    "sg:phone":"+43 1 3205758",
    "sg:postcode":"1190",
    "sg:province":"Wien",
    "wof:name":"Aloe-Zentrum",
    "wof:placetype":"venue"
},
  "geometry": {"coordinates":[16.3406162262,48.2478561401],"type":"Point"}
}