{
  "type": "Feature",
  "properties": {
    "addr:full":"Hauptstr 23 Stockerau Nieder\u00f6sterreich 2000",
    "addr:housenumber":"23",
    "addr:postcode":"2000",
    "addr:street":"Hauptstr",
    "iso:country":"AT",
    "sg:address":"Hauptstr 23",
    "sg:city":"Stockerau",
    "sg:orig_category":"Psychotherapie",
    "sg:phone":"+43 664 2602737",
    "sg:postcode":"2000",
    "sg:province":"Nieder\u00f6sterreich",
    "wof:name":"Langpaul Eva Mag",
    "wof:placetype":"venue"
},
  "geometry": {"coordinates":[16.2110671997,48.3853111267],"type":"Point"}
}