{
  "type": "Feature",
  "properties": {
    "iso:country":"AT",
    "sg:address":"Kapuzinerpl 11",
    "sg:city":"Knittelfeld",
    "sg:orig_category":"Bekleidung / Einzelhandel",
    "sg:phone":"+43 4335 12823380",
    "sg:postcode":"8720",
    "sg:province":"Steiermark",
    "wof:name":"Marchler Wolfgang",
    "wof:placetype":"venue"
},
  "geometry": {"coordinates":[14.8272094727,47.2148895264],"type":"Point"}
}