{
  "type": "Feature",
  "properties": {
    "addr:full":"Grazer Vorstadt 146 Voitsberg Steiermark 8570",
    "addr:housenumber":"146",
    "addr:postcode":"8570",
    "addr:street":"Grazer Vorstadt",
    "iso:country":"AT",
    "sg:address":"Grazer Vorstadt 146",
    "sg:city":"Voitsberg",
    "sg:orig_category":"Schrauben, Muttern U Nieten",
    "sg:phone":"+43 3142 27600",
    "sg:postcode":"8570",
    "sg:province":"Steiermark",
    "wof:name":"EJOT AUSTRIA GmbH",
    "wof:placetype":"venue"
},
  "geometry": {"coordinates":[15.1718206406,47.0367393494],"type":"Point"}
}