{
  "type": "Feature",
  "properties": {
    "addr:full":"Ackerweg 5 Altm\u00fcnster Ober\u00f6sterreich 4813",
    "addr:housenumber":"5",
    "addr:postcode":"4813",
    "addr:street":"Ackerweg;Oberoesterreich",
    "iso:country":"AT",
    "sg:address":"Ackerweg 5",
    "sg:city":"Altm\u00fcnster",
    "sg:orig_category":"Messe- U Ausstellungsbau U -Gestaltung",
    "sg:phone":"+43 4376 1288871",
    "sg:postcode":"4813",
    "sg:province":"Ober\u00f6sterreich",
    "wof:name":"Artdecoration Design & Dekoration GmbH",
    "wof:placetype":"venue"
},
  "geometry": {"coordinates":[13.7666301727,47.9019165039],"type":"Point"}
}