{
  "type": "Feature",
  "properties": {
    "addr:full":"Dornach 29 Axams Tirol 6094",
    "addr:housenumber":"29",
    "addr:postcode":"6094",
    "addr:street":"Dornach;Tirol",
    "iso:country":"AT",
    "sg:address":"Dornach 29",
    "sg:city":"Axams",
    "sg:orig_category":"Elektroinstallationsunternehmen",
    "sg:phone":"+43 5234 66267",
    "sg:postcode":"6094",
    "sg:province":"Tirol",
    "wof:name":"M\u00f6sl Markus",
    "wof:placetype":"venue"
},
  "geometry": {"coordinates":[11.2834339142,47.232421875],"type":"Point"}
}