{
  "type": "Feature",
  "properties": {
    "addr:full":"Gries 2 St. Ulrich am Pillersee Tirol 6393",
    "addr:housenumber":"2",
    "addr:postcode":"6393",
    "addr:street":"Gries;Tirol",
    "iso:country":"AT",
    "sg:address":"Gries 2",
    "sg:city":"St. Ulrich am Pillersee",
    "sg:orig_category":"Pensionen / Privatzimmer",
    "sg:phone":"+43 4353 5488147",
    "sg:postcode":"6393",
    "sg:province":"Tirol",
    "wof:name":"W\u00fcrtl Stefan jun",
    "wof:placetype":"venue"
},
  "geometry": {"coordinates":[12.5670318604,47.5262947083],"type":"Point"}
}