{
  "type": "Feature",
  "properties": {
    "addr:full":"Bersbuch 401 Andelsbuch Vorarlberg 6866",
    "addr:housenumber":"401",
    "addr:postcode":"6866",
    "addr:street":"Bersbuch",
    "iso:country":"AT",
    "sg:address":"Bersbuch 401",
    "sg:city":"Andelsbuch",
    "sg:orig_category":"Autoreparatur",
    "sg:phone":"+43 5512 32140",
    "sg:postcode":"6866",
    "sg:province":"Vorarlberg",
    "wof:name":"R\u00fcf Werner GesmbH & Co",
    "wof:placetype":"venue"
},
  "geometry": {"coordinates":[9.8536272049,47.3979492188],"type":"Point"}
}