{
  "type": "Feature",
  "properties": {
    "iso:country":"AT",
    "sg:address":"Schreyerg 15+17",
    "sg:city":"Wiener Neustadt",
    "sg:orig_category":"Galerien",
    "sg:phone":"+43 2622 89186",
    "sg:postcode":"2700",
    "sg:province":"Nieder\u00f6sterreich",
    "wof:name":"IMPACT Galerie & Pr\u00e4sente & Atelier - Jutta Hutterer",
    "wof:placetype":"venue"
},
  "geometry": {"coordinates":[16.2421188354,47.8181343079],"type":"Point"}
}