{
  "type": "Feature",
  "properties": {
    "addr:full":"Stadtpl 25 Eferding Ober\u00f6sterreich 4070",
    "addr:housenumber":"25",
    "addr:postcode":"4070",
    "addr:street":"Stadtpl",
    "iso:country":"AT",
    "sg:address":"Stadtpl 25",
    "sg:city":"Eferding",
    "sg:orig_category":"Juweliere, Gold- U Silberschmiede",
    "sg:phone":"+43 4372 727544",
    "sg:postcode":"4070",
    "sg:province":"Ober\u00f6sterreich",
    "wof:name":"Schwandl Klaus",
    "wof:placetype":"venue"
},
  "geometry": {"coordinates":[14.023068428,48.308971405],"type":"Point"}
}