{
  "type": "Feature",
  "properties": {
    "addr:full":"Wahringerstrasse, 3/8 -  Wien Wien 1090",
    "addr:housenumber":"3 / 8",
    "addr:postcode":"1090",
    "addr:street":"Wahringerstrasse",
    "iso:country":"AT",
    "sg:address":"Wahringerstrasse, 3/8 - ",
    "sg:city":"Wien",
    "sg:classifiers":[
        {
            "category":"Professional",
            "subcategory":"Art Services",
            "type":"Services"
        }
    ],
    "sg:phone":"+43 4314 033112",
    "sg:postcode":"1090",
    "sg:province":"Wien",
    "sg:tags":[
        "export-import"
    ],
    "wof:name":"Latvia Embassy",
    "wof:placetype":"venue"
},
  "geometry": {"coordinates":[16.3594665527,48.2166824341],"type":"Point"}
}