{
  "type": "Feature",
  "properties": {
    "iso:country":"AT",
    "sg:address":"Oberndorf 2B",
    "sg:city":"St. Marien",
    "sg:orig_category":"Handelsagenturen",
    "sg:phone":"+43 7227 20556",
    "sg:postcode":"4502",
    "sg:province":"Ober\u00f6sterreich",
    "wof:name":"Galleria - Huemer & Sch\u00f6rgendorfer OEG",
    "wof:placetype":"venue"
},
  "geometry": {"coordinates":[14.2750530243,48.1431922913],"type":"Point"}
}