{
  "type": "Feature",
  "properties": {
    "iso:country":"AT",
    "sg:address":"Klappholzstr 3",
    "sg:city":"Innsbruck",
    "sg:orig_category":"Installationsunternehmen",
    "sg:phone":"+43 512 342600",
    "sg:postcode":"6020",
    "sg:province":"Tirol",
    "wof:name":"ANDRE die andere Heizung",
    "wof:placetype":"venue"
},
  "geometry": {"coordinates":[11.4159412384,47.269203186],"type":"Point"}
}