{
  "type": "Feature",
  "properties": {
    "addr:full":"Herreng 3 Graz Steiermark 8010",
    "addr:housenumber":"3",
    "addr:postcode":"8010",
    "addr:street":"Herreng",
    "iso:country":"AT",
    "sg:address":"Herreng 3",
    "sg:city":"Graz",
    "sg:orig_category":"Unterhaltungselektronik / Einzelhandel",
    "sg:phone":"+43 316 817888",
    "sg:postcode":"8010",
    "sg:province":"Steiermark",
    "sg:website":"bang-olufsen.dk",
    "wof:name":"BANG & OLUFSEN Herrengasse",
    "wof:placetype":"venue"
},
  "geometry": {"coordinates":[15.4392108917,47.0707511902],"type":"Point"}
}