{
  "type": "Feature",
  "properties": {
    "addr:full":"Innsbrucker Str 42a Brixlegg Tirol 6230",
    "addr:housenumber":"42a",
    "addr:postcode":"6230",
    "addr:street":"Str;Tirol",
    "iso:country":"AT",
    "sg:address":"Innsbrucker Str 42a",
    "sg:city":"Brixlegg",
    "sg:orig_category":"Markisen",
    "sg:phone":"+43 5337 64328",
    "sg:postcode":"6230",
    "sg:province":"Tirol",
    "wof:name":"Rojal Sonnenschutz Inh Fam Dabbert",
    "wof:placetype":"venue"
},
  "geometry": {"coordinates":[11.8816947937,47.4339561462],"type":"Point"}
}