{
  "type": "Feature",
  "properties": {
    "addr:full":"Gutenbergstr. 12 St. P\u00f6lten Nieder\u00f6sterreich 3100",
    "addr:housenumber":"12",
    "addr:postcode":"3100",
    "addr:street":"Gutenbergstr.",
    "iso:country":"AT",
    "sg:address":"Gutenbergstr. 12",
    "sg:city":"St. P\u00f6lten",
    "sg:classifiers":[
        {
            "category":"Professional",
            "subcategory":"Printing & Photocopies",
            "type":"Services"
        }
    ],
    "sg:phone":"+43 4327 428020",
    "sg:postcode":"3100",
    "sg:province":"Nieder\u00f6sterreich",
    "wof:name":"NIEDER\u00d6STERR. PRESSEHAUS DRUCK- UND VERLAGSGES.MBH",
    "wof:placetype":"venue"
},
  "geometry": {"coordinates":[7.163962841,50.7844772339],"type":"Point"}
}