{
  "type": "Feature",
  "properties": {
    "addr:full":"Brunneng 120 M\u00fcnzkirchen Ober\u00f6sterreich 4792",
    "addr:housenumber":"120",
    "addr:postcode":"4792",
    "addr:street":"Muenzkirchen Oberoesterreich",
    "iso:country":"AT",
    "sg:address":"Brunneng 120",
    "sg:city":"M\u00fcnzkirchen",
    "sg:orig_category":"Stillberatung",
    "sg:phone":"+43 7716 6408",
    "sg:postcode":"4792",
    "sg:province":"Ober\u00f6sterreich",
    "wof:name":"Stillberatung - La Leche Liga Ober\u00f6sterreich - Margit Kitzm\u00fcller",
    "wof:placetype":"venue"
},
  "geometry": {"coordinates":[13.5650320053,48.4837799072],"type":"Point"}
}