{
  "type": "Feature",
  "properties": {
    "iso:country":"AT",
    "sg:address":"Steyrer Str. 39a",
    "sg:city":"Sierning",
    "sg:classifiers":[
        {
            "category":"Manufacturing",
            "subcategory":"Tools & Machinery",
            "type":"Manufacturing & Wholesale Goods"
        }
    ],
    "sg:phone":"+43 4372 593135",
    "sg:postcode":"4522",
    "sg:province":"Ober\u00f6sterreich",
    "sg:tags":[
        "environment",
        "equipment",
        "-"
    ],
    "wof:name":"SW UMWELTTECHNIK STOISER & WOLSCHER AG",
    "wof:placetype":"venue"
},
  "geometry": {"coordinates":[14.3234186172,48.0497894287],"type":"Point"}
}