{
  "type": "Feature",
  "properties": {
    "iso:country":"AT",
    "sg:address":"Kendlerstrasse 14",
    "sg:city":"Salzburg",
    "sg:classifiers":[
        {
            "category":"Professional",
            "subcategory":"Art Services",
            "type":"Services"
        }
    ],
    "sg:phone":"+43 662 829223",
    "sg:postcode":"5020",
    "sg:province":"Salzburg",
    "sg:tags":[
        "development",
        "electronic",
        "engineering",
        "design"
    ],
    "wof:name":"Elex Elektronik GesmbH",
    "wof:placetype":"venue"
},
  "geometry": {"coordinates":[13.0187015533,47.7932090759],"type":"Point"}
}