{
  "type": "Feature",
  "properties": {
    "addr:full":"Linzer Str 8 Bad Schallerbach Ober\u00f6sterreich 4701",
    "addr:housenumber":"8",
    "addr:postcode":"4701",
    "addr:street":"Linzer Str;Oberoesterreich",
    "iso:country":"AT",
    "sg:address":"Linzer Str 8",
    "sg:city":"Bad Schallerbach",
    "sg:orig_category":"Polizei U Gendarmerie",
    "sg:phone":"+43 4359 1334231",
    "sg:postcode":"4701",
    "sg:province":"Ober\u00f6sterreich",
    "wof:name":"Gendarmerie",
    "wof:placetype":"venue"
},
  "geometry": {"coordinates":[13.9222621918,48.2301902771],"type":"Point"}
}