{
  "type": "Feature",
  "properties": {
    "iso:country":"AT",
    "sg:address":"Klausen 6",
    "sg:city":"Kirchberg in Tirol",
    "sg:classifiers":[
        {
            "category":"Park",
            "subcategory":"Provincial",
            "type":"Public Place"
        }
    ],
    "sg:phone":"+43 4353 5735230",
    "sg:postcode":"6365",
    "sg:province":"Tirol",
    "sg:tags":[
        "u",
        "ski-",
        "snowboardschulen"
    ],
    "wof:name":"Schischule Kirchberg Aktiv - Josef Rass",
    "wof:placetype":"venue"
},
  "geometry": {"coordinates":[12.3149347305,47.4481468201],"type":"Point"}
}