{
  "type": "Feature",
  "properties": {
    "iso:country":"AT",
    "sg:address":"Leopold Werndl-Str 2",
    "sg:city":"Steyr",
    "sg:classifiers":[
        {
            "category":"Restaurant",
            "type":"Food & Drink"
        }
    ],
    "sg:phone":"+43 7252 47428",
    "sg:postcode":"4400",
    "sg:province":"Ober\u00f6sterreich",
    "wof:name":"Cafe Restaurant Rossini",
    "wof:placetype":"venue"
},
  "geometry": {"coordinates":[14.4151735306,48.0370979309],"type":"Point"}
}