{
  "type": "Feature",
  "properties": {
    "addr:full":"Hochrie\u00dfer Str Purgstall an der Erlauf Nieder\u00f6sterreich 3251",
    "addr:postcode":"3251",
    "addr:street":"Str Purgstall;Niederoesterreich",
    "iso:country":"AT",
    "sg:address":"Hochrie\u00dfer Str",
    "sg:city":"Purgstall an der Erlauf",
    "sg:classifiers":[
        {
            "category":"Home & Garden",
            "subcategory":"Garden Supply",
            "type":"Retail Goods"
        }
    ],
    "sg:phone":"+43 4374 892866",
    "sg:postcode":"3251",
    "sg:province":"Nieder\u00f6sterreich",
    "sg:tags":[
        "schotter",
        "sand",
        "u"
    ],
    "wof:name":"Mayer Sepp",
    "wof:placetype":"venue"
},
  "geometry": {"coordinates":[15.1404752731,48.0645599365],"type":"Point"}
}