{
  "type": "Feature",
  "properties": {
    "addr:full":"Pfarrg 6 Innsbruck Tirol 6020",
    "addr:housenumber":"6",
    "addr:postcode":"6020",
    "addr:street":"Pfarrg;Tirol",
    "iso:country":"AT",
    "sg:address":"Pfarrg 6",
    "sg:city":"Innsbruck",
    "sg:orig_category":"Architekten",
    "sg:phone":"+43 512 587011",
    "sg:postcode":"6020",
    "sg:province":"Tirol",
    "wof:name":"Brandtner Josef Dipl-Ing",
    "wof:placetype":"venue"
},
  "geometry": {"coordinates":[11.3936424255,47.2688713074],"type":"Point"}
}