{
  "type": "Feature",
  "properties": {
    "addr:full":"Grazer Str 1 Lebring Steiermark 8403",
    "addr:housenumber":"1",
    "addr:postcode":"8403",
    "addr:street":"Str",
    "iso:country":"AT",
    "sg:address":"Grazer Str 1",
    "sg:city":"Lebring",
    "sg:orig_category":"Gemeinden",
    "sg:phone":"+43 4331 8224710",
    "sg:postcode":"8403",
    "sg:province":"Steiermark",
    "wof:name":"Marktgemeinde Lebring-St. Margarethen",
    "wof:placetype":"venue"
},
  "geometry": {"coordinates":[15.5436620712,46.8292732239],"type":"Point"}
}