{
  "type": "Feature",
  "properties": {
    "iso:country":"AT",
    "sg:address":"Nr 96",
    "sg:city":"Kainisch",
    "sg:orig_category":"Pensionen / Privatzimmer",
    "sg:phone":"+43 4336 24285",
    "sg:postcode":"8984",
    "sg:province":"Steiermark",
    "wof:name":"Gaigg vlg Meissl Bauernhof",
    "wof:placetype":"venue"
},
  "geometry": {"coordinates":[13.8435783386,47.5724411011],"type":"Point"}
}