{
  "type": "Feature",
  "properties": {
    "addr:full":"Albrechtstrasse 28 Marchtrenk Ober\u00f6sterreich 4614",
    "addr:housenumber":"28",
    "addr:postcode":"4614",
    "addr:street":"Albrechtstrasse",
    "iso:country":"AT",
    "sg:address":"Albrechtstrasse 28",
    "sg:city":"Marchtrenk",
    "sg:classifiers":[
        {
            "category":"Shopping",
            "subcategory":"Hobbies, Toys, & Games",
            "type":"Retail Goods"
        }
    ],
    "sg:phone":"+43 7243 58121",
    "sg:postcode":"4614",
    "sg:province":"Ober\u00f6sterreich",
    "sg:tags":[
        "baby",
        "infant",
        "toy",
        "toys"
    ],
    "wof:name":"Josef Pickl Ges.m.b.H.",
    "wof:placetype":"venue"
},
  "geometry": {"coordinates":[14.1437158585,48.2009658813],"type":"Point"}
}