{
  "type": "Feature",
  "properties": {
    "addr:full":"Reidl 1 Kemmelbach Nieder\u00f6sterreich 3373",
    "addr:housenumber":"1",
    "addr:postcode":"3373",
    "addr:street":"Reidl",
    "iso:country":"AT",
    "sg:address":"Reidl 1",
    "sg:city":"Kemmelbach",
    "sg:classifiers":[
        {
            "category":"Military Area",
            "subcategory":"Army Base",
            "type":"Public Place"
        }
    ],
    "sg:phone":"+43 664 4505030",
    "sg:postcode":"3373",
    "sg:province":"Nieder\u00f6sterreich",
    "sg:tags":[
        "shop"
    ],
    "sg:website":"military-partner.at",
    "wof:name":"MILITARY - PARTNER Geissberger Alois",
    "wof:placetype":"venue"
},
  "geometry": {"coordinates":[15.0943393707,48.1549682617],"type":"Point"}
}