{
  "type": "Feature",
  "properties": {
    "addr:full":"Nr 200 Gosdorf Steiermark 8482",
    "addr:postcode":"8482",
    "addr:street":"Nr 200",
    "iso:country":"AT",
    "sg:address":"Nr 200",
    "sg:city":"Gosdorf",
    "sg:classifiers":[
        {
            "category":"Utilities",
            "subcategory":"Electric",
            "type":"Services"
        }
    ],
    "sg:phone":"+43 4334 7221280",
    "sg:postcode":"8482",
    "sg:province":"Steiermark",
    "sg:tags":[
        "electricity"
    ],
    "wof:name":"STEIERM\u00c4RKISCHE ELEKTRIZIT\u00c4TS AG",
    "wof:placetype":"venue"
},
  "geometry": {"coordinates":[15.7965946198,46.7270584106],"type":"Point"}
}