{
  "type": "Feature",
  "properties": {
    "addr:full":"Mandorfer Str 21 Adlwang Ober\u00f6sterreich 4541",
    "addr:housenumber":"21",
    "addr:postcode":"4541",
    "addr:street":"Str",
    "iso:country":"AT",
    "sg:address":"Mandorfer Str 21",
    "sg:city":"Adlwang",
    "sg:orig_category":"Raumgestaltung",
    "sg:phone":"+43 7258 3935",
    "sg:postcode":"4541",
    "sg:province":"Ober\u00f6sterreich",
    "wof:name":"Riener Peter",
    "wof:placetype":"venue"
},
  "geometry": {"coordinates":[14.2136259079,47.992893219],"type":"Point"}
}