{
  "type": "Feature",
  "properties": {
    "addr:full":"Sackstr 14 Graz Steiermark 8010",
    "addr:housenumber":"14",
    "addr:postcode":"8010",
    "addr:street":"Sackstr",
    "iso:country":"AT",
    "sg:address":"Sackstr 14",
    "sg:city":"Graz",
    "sg:orig_category":"Massagen",
    "sg:phone":"+43 316 815168",
    "sg:postcode":"8010",
    "sg:province":"Steiermark",
    "wof:name":"Balance Massagefachinstitut",
    "wof:placetype":"venue"
},
  "geometry": {"coordinates":[15.4371681213,47.0721511841],"type":"Point"}
}