{
  "type": "Feature",
  "properties": {
    "addr:full":"Bahnhofstrasse 38a Hausmening Nieder\u00f6sterreich 3363",
    "addr:housenumber":"38a",
    "addr:postcode":"3363",
    "addr:street":"Bahnhofstrasse",
    "iso:country":"AT",
    "sg:address":"Bahnhofstrasse 38a",
    "sg:city":"Hausmening",
    "sg:orig_category":"Furniture, General",
    "sg:phone":"+43 7475 53864",
    "sg:postcode":"3363",
    "sg:province":"Nieder\u00f6sterreich",
    "wof:name":"Tischlerei Schlemmer Johann",
    "wof:placetype":"venue"
},
  "geometry": {"coordinates":[14.816365242,48.0766716003],"type":"Point"}
}