{
  "type": "Feature",
  "properties": {
    "iso:country":"AT",
    "sg:address":"Bleichenweg 20",
    "sg:city":"Innsbruck",
    "sg:orig_category":"Lebensmittel / Erzeugung U Gro\u00c3\u0178handel",
    "sg:phone":"+43 5 93352200",
    "sg:postcode":"6020",
    "sg:province":"Tirol",
    "wof:name":"Wedl & Dick GmbH",
    "wof:placetype":"venue"
},
  "geometry": {"coordinates":[11.434179306,47.2624320984],"type":"Point"}
}