{
  "type": "Feature",
  "properties": {
    "addr:full":"Marktpl 44 Oberneukirchen Ober\u00f6sterreich 4181",
    "addr:housenumber":"44",
    "addr:postcode":"4181",
    "addr:street":"Marktpl",
    "iso:country":"AT",
    "sg:address":"Marktpl 44",
    "sg:city":"Oberneukirchen",
    "sg:orig_category":"Banken U Sparkassen",
    "sg:phone":"+43 4372 127056",
    "sg:postcode":"4181",
    "sg:province":"Ober\u00f6sterreich",
    "wof:name":"Raiffeisenbank Mittleres Rodltal regGenmbH",
    "wof:placetype":"venue"
},
  "geometry": {"coordinates":[14.2272186279,48.4649276733],"type":"Point"}
}