{
  "type": "Feature",
  "properties": {
    "iso:country":"AT",
    "sg:address":"Mohsg 23",
    "sg:city":"Wien",
    "sg:orig_category":"Mietautos",
    "sg:phone":"+43 1 7991071",
    "sg:postcode":"1030",
    "sg:province":"Wien",
    "wof:name":"Intertours - Mietwagen m Chauffeur",
    "wof:placetype":"venue"
},
  "geometry": {"coordinates":[16.3882675171,48.1897163391],"type":"Point"}
}