{
  "type": "Feature",
  "properties": {
    "addr:full":"Am Gr\u00fcnen Weg 20 St. Lambrecht Steiermark 8813",
    "addr:housenumber":"20",
    "addr:postcode":"8813",
    "addr:street":"Am Gruenen Weg",
    "iso:country":"AT",
    "sg:address":"Am Gr\u00fcnen Weg 20",
    "sg:city":"St. Lambrecht",
    "sg:orig_category":"Hauptschulen",
    "sg:phone":"+43 3585 2228",
    "sg:postcode":"8813",
    "sg:province":"Steiermark",
    "wof:name":"Hauptschule",
    "wof:placetype":"venue"
},
  "geometry": {"coordinates":[14.2991170883,47.0689888],"type":"Point"}
}