{
  "type": "Feature",
  "properties": {
    "addr:full":"Ludwig-Poihs-Str 5 Schwechat Nieder\u00f6sterreich 2320",
    "addr:housenumber":"5",
    "addr:postcode":"2320",
    "addr:street":"Ludwig-Poihs-Str;Niederoesterreich",
    "iso:country":"AT",
    "sg:address":"Ludwig-Poihs-Str 5",
    "sg:city":"Schwechat",
    "sg:orig_category":"Maler, Anstreicher U Lackierer",
    "sg:phone":"+43 4317 0710600",
    "sg:postcode":"2320",
    "sg:province":"Nieder\u00f6sterreich",
    "sg:website":"pittoresk.at",
    "wof:name":"PITTORESK Maler u Anstreicher GesmbH",
    "wof:placetype":"venue"
},
  "geometry": {"coordinates":[16.4785232544,48.1524429321],"type":"Point"}
}