{
  "type": "Feature",
  "properties": {
    "addr:full":"Haydng 53a Gro\u00df-Enzersdorf Nieder\u00f6sterreich 2301",
    "addr:housenumber":"53a",
    "addr:postcode":"2301",
    "addr:street":"Haydng;Niederoesterreich",
    "iso:country":"AT",
    "sg:address":"Haydng 53a",
    "sg:city":"Gro\u00df-Enzersdorf",
    "sg:orig_category":"Steuerberatung",
    "sg:phone":"+43 2249 3956",
    "sg:postcode":"2301",
    "sg:province":"Nieder\u00f6sterreich",
    "wof:name":"Siegel Edeltraud",
    "wof:placetype":"venue"
},
  "geometry": {"coordinates":[16.5780353546,48.2006797791],"type":"Point"}
}