{
  "type": "Feature",
  "properties": {
    "addr:full":"Dorf 19 Neidling Nieder\u00f6sterreich 3110",
    "addr:housenumber":"19",
    "addr:postcode":"3110",
    "addr:street":"Dorf;Niederoesterreich",
    "iso:country":"AT",
    "sg:address":"Dorf 19",
    "sg:city":"Neidling",
    "sg:orig_category":"Tischlereien",
    "sg:phone":"+43 4327 4182640",
    "sg:postcode":"3110",
    "sg:province":"Nieder\u00f6sterreich",
    "wof:name":"Gleiss Robert",
    "wof:placetype":"venue"
},
  "geometry": {"coordinates":[15.5568723679,48.2376899719],"type":"Point"}
}