{
  "type": "Feature",
  "properties": {
    "addr:full":"Sandg 16 Illmitz Burgenland 7142",
    "addr:housenumber":"16",
    "addr:postcode":"7142",
    "addr:street":"Sandg",
    "iso:country":"AT",
    "sg:address":"Sandg 16",
    "sg:city":"Illmitz",
    "sg:classifiers":[
        {
            "category":"Restaurant",
            "type":"Food & Drink"
        }
    ],
    "sg:phone":"+43 2175 2147",
    "sg:postcode":"7142",
    "sg:province":"Burgenland",
    "wof:name":"Illmitzer - Fam Christa und Pauli Haider",
    "wof:placetype":"venue"
},
  "geometry": {"coordinates":[16.7998695374,47.7619514465],"type":"Point"}
}