{
  "type": "Feature",
  "properties": {
    "iso:country":"AT",
    "sg:address":"Neusiedler Str 15",
    "sg:city":"Donnerskirchen",
    "sg:orig_category":"Tankstellen",
    "sg:phone":"+43 2683 8184",
    "sg:postcode":"7082",
    "sg:province":"Burgenland",
    "wof:name":"OMV AG",
    "wof:placetype":"venue"
},
  "geometry": {"coordinates":[16.6489543915,47.8954429626],"type":"Point"}
}