{
  "type": "Feature",
  "properties": {
    "addr:full":"Wasserring 3 Amstetten Nieder\u00f6sterreich 3300",
    "addr:housenumber":"3",
    "addr:postcode":"3300",
    "addr:street":"Wasserring;Niederoesterreich",
    "iso:country":"AT",
    "sg:address":"Wasserring 3",
    "sg:city":"Amstetten",
    "sg:classifiers":[
        {
            "category":"Home & Garden",
            "subcategory":"Building Materials",
            "type":"Retail Goods"
        }
    ],
    "sg:phone":"+43 7472 68530",
    "sg:postcode":"3300",
    "sg:province":"Nieder\u00f6sterreich",
    "sg:tags":[
        "gravel",
        "crushed"
    ],
    "wof:name":"Johann Dorner Ges.m.b.H.",
    "wof:placetype":"venue"
},
  "geometry": {"coordinates":[14.8774547577,48.1085128784],"type":"Point"}
}