{
  "type": "Feature",
  "properties": {
    "addr:full":"Lackeng. 301 Altenmarkt im Pongau Salzburg 5541",
    "addr:housenumber":"301",
    "addr:postcode":"5541",
    "addr:street":"Salzburg",
    "iso:country":"AT",
    "sg:address":"Lackeng. 301",
    "sg:city":"Altenmarkt im Pongau",
    "sg:orig_category":"Miscellaneous Products",
    "sg:phone":"+43 4364 523900",
    "sg:postcode":"5541",
    "sg:province":"Salzburg",
    "wof:name":"ATOMIC AUSTRIA GMBH",
    "wof:placetype":"venue"
},
  "geometry": {"coordinates":[13.4229373932,47.3783073425],"type":"Point"}
}