{
  "type": "Feature",
  "properties": {
    "iso:country":"AT",
    "sg:address":"Plainbachstr 12",
    "sg:city":"Bergheim",
    "sg:orig_category":"Autohandel",
    "sg:phone":"+43 664 1403837",
    "sg:postcode":"5101",
    "sg:province":"Salzburg",
    "wof:name":"K\u00fchleitner Robert",
    "wof:placetype":"venue"
},
  "geometry": {"coordinates":[13.0444583893,47.8430976868],"type":"Point"}
}