{
  "type": "Feature",
  "properties": {
    "addr:full":"Wr Neust\u00e4dter Str 86a Bad Sauerbrunn Burgenland 7202",
    "addr:housenumber":"86a",
    "addr:postcode":"7202",
    "addr:street":"Str",
    "iso:country":"AT",
    "sg:address":"Wr Neust\u00e4dter Str 86a",
    "sg:city":"Bad Sauerbrunn",
    "sg:orig_category":"Brandschutz",
    "sg:phone":"+43 2625 37343",
    "sg:postcode":"7202",
    "sg:province":"Burgenland",
    "wof:name":"Leitgeb Michael",
    "wof:placetype":"venue"
},
  "geometry": {"coordinates":[16.3250465393,47.7747840881],"type":"Point"}
}