{
  "type": "Feature",
  "properties": {
    "iso:country":"AT",
    "sg:address":"Nr 297",
    "sg:city":"Gerlos",
    "sg:classifiers":[
        {
            "category":"Restaurant",
            "type":"Food & Drink"
        }
    ],
    "sg:phone":"+43 5284 5378",
    "sg:postcode":"6281",
    "sg:province":"Tirol",
    "wof:name":"Isskogelst\u00fcberl",
    "wof:placetype":"venue"
},
  "geometry": {"coordinates":[12.0359144211,47.2256088257],"type":"Point"}
}