{
  "type": "Feature",
  "properties": {
    "addr:full":"Leobersdorfer Str 20 Berndorf Nieder\u00f6sterreich 2560",
    "addr:postcode":"2560",
    "addr:street":"Str 20",
    "iso:country":"AT",
    "sg:address":"Leobersdorfer Str 20",
    "sg:city":"Berndorf",
    "sg:orig_category":"Metallbe- U -Verarbeitung",
    "sg:phone":"+43 4326 7283717",
    "sg:postcode":"2560",
    "sg:province":"Nieder\u00f6sterreich",
    "wof:name":"Winkelmayer Erwin",
    "wof:placetype":"venue"
},
  "geometry": {"coordinates":[16.1051998138,47.8947486877],"type":"Point"}
}