{
  "type": "Feature",
  "properties": {
    "addr:full":"Nr 21 Waldegg an der Piesting Nieder\u00f6sterreich 2754",
    "addr:postcode":"2754",
    "addr:street":"Nr",
    "iso:country":"AT",
    "sg:address":"Nr 21",
    "sg:city":"Waldegg an der Piesting",
    "sg:orig_category":"Volksschulen",
    "sg:phone":"+43 4326 3348252",
    "sg:postcode":"2754",
    "sg:province":"Nieder\u00f6sterreich",
    "wof:name":"Volksschule",
    "wof:placetype":"venue"
},
  "geometry": {"coordinates":[16.0579948425,47.8691902161],"type":"Point"}
}