{
  "type": "Feature",
  "properties": {
    "iso:country":"AT",
    "sg:address":"Walserstr 15",
    "sg:city":"Hohenems",
    "sg:orig_category":"Tischlereien",
    "sg:phone":"+43 5576 75043",
    "sg:postcode":"6845",
    "sg:province":"Vorarlberg",
    "wof:name":"Drexel & Fleisch Tischlerei GesmbH",
    "wof:placetype":"venue"
},
  "geometry": {"coordinates":[9.6688241959,47.3539466858],"type":"Point"}
}