{
  "type": "Feature",
  "properties": {
    "addr:full":"Adolf-Purtscher-Str 6 Lienz Tirol 9900",
    "addr:housenumber":"6",
    "addr:postcode":"9900",
    "addr:street":"Adolf-Purtscher-Str;Tirol",
    "iso:country":"AT",
    "sg:address":"Adolf-Purtscher-Str 6",
    "sg:city":"Lienz",
    "sg:classifiers":[
        {
            "category":"Restaurant",
            "type":"Food & Drink"
        }
    ],
    "sg:phone":"+43 4852 64454",
    "sg:postcode":"9900",
    "sg:province":"Tirol",
    "wof:name":"Kolpingst\u00fcberl",
    "wof:placetype":"venue"
},
  "geometry": {"coordinates":[12.7589979172,46.8309898376],"type":"Point"}
}