{
  "type": "Feature",
  "properties": {
    "addr:full":"Nr 203 Sebersdorf Steiermark 8272",
    "addr:postcode":"8272",
    "addr:street":"Nr",
    "iso:country":"AT",
    "sg:address":"Nr 203",
    "sg:city":"Sebersdorf",
    "sg:orig_category":"Steinmetzbetriebe",
    "sg:phone":"+43 3333 22030",
    "sg:postcode":"8272",
    "sg:province":"Steiermark",
    "wof:name":"Lang Steine",
    "wof:placetype":"venue"
},
  "geometry": {"coordinates":[15.9478845596,47.1712265015],"type":"Point"}
}