{
  "type": "Feature",
  "properties": {
    "addr:full":"Altenhof 26 Goldegg Salzburg 5622",
    "addr:housenumber":"26",
    "addr:postcode":"5622",
    "addr:street":"Altenhof;Salzburg",
    "iso:country":"AT",
    "sg:address":"Altenhof 26",
    "sg:city":"Goldegg",
    "sg:orig_category":"Handelsagenturen",
    "sg:phone":"+43 6415 8634",
    "sg:postcode":"5622",
    "sg:province":"Salzburg",
    "wof:name":"Heider Otto",
    "wof:placetype":"venue"
},
  "geometry": {"coordinates":[13.099439621,47.3187294006],"type":"Point"}
}