{
  "type": "Feature",
  "properties": {
    "iso:country":"AT",
    "sg:address":"Bahnhofstr 21",
    "sg:city":"Thaya",
    "sg:orig_category":"Dachdeckereien",
    "sg:phone":"+43 2842 52652",
    "sg:postcode":"3842",
    "sg:province":"Nieder\u00f6sterreich",
    "wof:name":"Dachdecker und Spenglerarbeiten Ernst Steiner",
    "wof:placetype":"venue"
},
  "geometry": {"coordinates":[15.2916603088,48.8541717529],"type":"Point"}
}