{
  "type": "Feature",
  "properties": {
    "addr:full":"Ischlerbahnstr 23A Eugendorf Salzburg 5301",
    "addr:housenumber":"23a",
    "addr:postcode":"5301",
    "addr:street":"Ischlerbahnstr;Salzburg",
    "iso:country":"AT",
    "sg:address":"Ischlerbahnstr 23A",
    "sg:city":"Eugendorf",
    "sg:orig_category":"Gastronomie- U Hoteleinrichtungen",
    "sg:phone":"+43 4362 2528482",
    "sg:postcode":"5301",
    "sg:province":"Salzburg",
    "wof:name":"Cinema Audio- & Videotechnik GmbH",
    "wof:placetype":"venue"
},
  "geometry": {"coordinates":[13.1278133392,47.8623313904],"type":"Point"}
}