{
  "type": "Feature",
  "properties": {
    "addr:full":"Holzpl 2 Langenlois Nieder\u00f6sterreich 3550",
    "addr:housenumber":"2",
    "addr:postcode":"3550",
    "addr:street":"Holzpl",
    "iso:country":"AT",
    "sg:address":"Holzpl 2",
    "sg:city":"Langenlois",
    "sg:orig_category":"Textilreinigung",
    "sg:phone":"+43 2734 2273",
    "sg:postcode":"3550",
    "sg:province":"Nieder\u00f6sterreich",
    "wof:name":"Regina Textilreinigungs-GesmbH",
    "wof:placetype":"venue"
},
  "geometry": {"coordinates":[15.675368309,48.4722251892],"type":"Point"}
}