{
  "type": "Feature",
  "properties": {
    "addr:full":"Mirabellpl 4 Salzburg Salzburg 5020",
    "addr:housenumber":"4",
    "addr:postcode":"5020",
    "addr:street":"Mirabellpl;Salzburg",
    "iso:country":"AT",
    "sg:address":"Mirabellpl 4",
    "sg:city":"Salzburg",
    "sg:orig_category":"Friseure U Frisiersalons",
    "sg:phone":"+43 662 885755",
    "sg:postcode":"5020",
    "sg:province":"Salzburg",
    "wof:name":"Werfer Erich",
    "wof:placetype":"venue"
},
  "geometry": {"coordinates":[13.0427856445,47.8055038452],"type":"Point"}
}