{
  "type": "Feature",
  "properties": {
    "addr:full":"Hauptstr 30 Hofkirchen an der Trattnach Ober\u00f6sterreich 4716",
    "addr:housenumber":"30",
    "addr:postcode":"4716",
    "addr:street":"Hauptstr",
    "iso:country":"AT",
    "sg:address":"Hauptstr 30",
    "sg:city":"Hofkirchen an der Trattnach",
    "sg:orig_category":"Gemeinden",
    "sg:phone":"+43 7734 2255",
    "sg:postcode":"4716",
    "sg:province":"Ober\u00f6sterreich",
    "wof:name":"Gemeinde Hofkirchen an der Trattnach",
    "wof:placetype":"venue"
},
  "geometry": {"coordinates":[13.7406759262,48.2207794189],"type":"Point"}
}