{
  "type": "Feature",
  "properties": {
    "iso:country":"AT",
    "sg:address":"Haggenstr 10",
    "sg:city":"Oberndorf",
    "sg:orig_category":"Tischlereien",
    "sg:phone":"+43 4362 725395",
    "sg:postcode":"5110",
    "sg:province":"Salzburg",
    "wof:name":"Tischlerei Ahrer - Inh Erika Prem",
    "wof:placetype":"venue"
},
  "geometry": {"coordinates":[12.921749115,47.9411582947],"type":"Point"}
}