{
  "type": "Feature",
  "properties": {
    "addr:full":"Schlo\u00dfg 8 Bisamberg Nieder\u00f6sterreich 2102",
    "addr:housenumber":"8",
    "addr:postcode":"2102",
    "addr:street":"Schlossg",
    "iso:country":"AT",
    "sg:address":"Schlo\u00dfg 8",
    "sg:city":"Bisamberg",
    "sg:orig_category":"\u00c3\u201erzte / F Allgemeinmedizin",
    "sg:phone":"+43 2262 672300",
    "sg:postcode":"2102",
    "sg:province":"Nieder\u00f6sterreich",
    "wof:name":"Sedmik Alfred Dr",
    "wof:placetype":"venue"
},
  "geometry": {"coordinates":[16.3610553741,48.3311195374],"type":"Point"}
}