{
  "type": "Feature",
  "properties": {
    "addr:full":"Dr.-Karl-Renner-Gasse 4a Weiz Steiermark 8160",
    "addr:housenumber":"4a",
    "addr:postcode":"8160",
    "addr:street":"Dr.-Karl-Renner-Gasse",
    "iso:country":"AT",
    "sg:address":"Dr.-Karl-Renner-Gasse 4a",
    "sg:city":"Weiz",
    "sg:classifiers":[
        {
            "category":"Home & Garden",
            "subcategory":"Carpets & Floor Coverings",
            "type":"Retail Goods"
        }
    ],
    "sg:phone":"+43 3172 42888",
    "sg:postcode":"8160",
    "sg:province":"Steiermark",
    "sg:tags":[
        "carpeting"
    ],
    "wof:name":"R\u00fcdiger Wagner",
    "wof:placetype":"venue"
},
  "geometry": {"coordinates":[15.6229095459,47.2170982361],"type":"Point"}
}