{
  "type": "Feature",
  "properties": {
    "iso:country":"AT",
    "sg:address":"Marktpl 6",
    "sg:city":"St. Georgen an der Gusen",
    "sg:orig_category":"Banken U Sparkassen",
    "sg:phone":"+43 4372 3722430",
    "sg:postcode":"4222",
    "sg:province":"Ober\u00f6sterreich",
    "wof:name":"Bankomat d Raiffeisenbank Perg regGenmbH",
    "wof:placetype":"venue"
},
  "geometry": {"coordinates":[14.448469162,48.2721405029],"type":"Point"}
}