{
  "type": "Feature",
  "properties": {
    "addr:full":"Moosen 18 Kramsach Tirol 6233",
    "addr:housenumber":"18",
    "addr:postcode":"6233",
    "addr:street":"Moosen;Tirol",
    "iso:country":"AT",
    "sg:address":"Moosen 18",
    "sg:city":"Kramsach",
    "sg:classifiers":[
        {
            "category":"Restaurant",
            "type":"Food & Drink"
        }
    ],
    "sg:phone":"+43 4353 3763547",
    "sg:postcode":"6233",
    "sg:province":"Tirol",
    "wof:name":"Restaurant-Cafe Seerose",
    "wof:placetype":"venue"
},
  "geometry": {"coordinates":[11.908331871,47.4669342041],"type":"Point"}
}