{
  "type": "Feature",
  "properties": {
    "addr:full":"Hauptstr 2 Tulbing Nieder\u00f6sterreich 3434",
    "addr:housenumber":"2",
    "addr:postcode":"3434",
    "addr:street":"Hauptstr",
    "iso:country":"AT",
    "sg:address":"Hauptstr 2",
    "sg:city":"Tulbing",
    "sg:orig_category":"Farben U Lacke / Einzelhandel",
    "sg:phone":"+43 4322 7374820",
    "sg:postcode":"3434",
    "sg:province":"Nieder\u00f6sterreich",
    "wof:name":"Edec - Spezialfarben",
    "wof:placetype":"venue"
},
  "geometry": {"coordinates":[16.1228275299,48.2905273438],"type":"Point"}
}