{
  "type": "Feature",
  "properties": {
    "addr:full":"Gro\u00dfbauerstr 8 Wien Wien 1210",
    "addr:housenumber":"8",
    "addr:postcode":"1210",
    "addr:street":"Grossbauerstr",
    "iso:country":"AT",
    "sg:address":"Gro\u00dfbauerstr 8",
    "sg:city":"Wien",
    "sg:orig_category":"Fleischereimaschinen U -Einrichtungen",
    "sg:phone":"+43 1 2905173",
    "sg:postcode":"1210",
    "sg:province":"Wien",
    "wof:name":"Matimex AG",
    "wof:placetype":"venue"
},
  "geometry": {"coordinates":[16.4127902985,48.2813301086],"type":"Point"}
}