{
  "type": "Feature",
  "properties": {
    "addr:full":"Nr 1 St. Georgen an der Leys Nieder\u00f6sterreich 3282",
    "addr:housenumber":"1",
    "addr:postcode":"3282",
    "addr:street":"Nr",
    "iso:country":"AT",
    "sg:address":"Nr 1",
    "sg:city":"St. Georgen an der Leys",
    "sg:orig_category":"Gemeinden",
    "sg:phone":"+43 7482 462350",
    "sg:postcode":"3282",
    "sg:province":"Nieder\u00f6sterreich",
    "wof:name":"Gemeindeamt St Georgen an der Leys",
    "wof:placetype":"venue"
},
  "geometry": {"coordinates":[15.2251644135,48.0312957764],"type":"Point"}
}