{
  "type": "Feature",
  "properties": {
    "addr:full":"Gneiser Strasse 3 Salzburg Salzburg 5020",
    "addr:housenumber":"3",
    "addr:postcode":"5020",
    "addr:street":"Gneiser Strasse;Salzburg",
    "iso:country":"AT",
    "sg:address":"Gneiser Strasse 3",
    "sg:city":"Salzburg",
    "sg:classifiers":[
        {
            "category":"Community Center",
            "subcategory":"Senior",
            "type":"Public Place"
        }
    ],
    "sg:phone":"+43 662 8235400",
    "sg:postcode":"5020",
    "sg:province":"Salzburg",
    "sg:tags":[
        "tile",
        "wall",
        "ceramic"
    ],
    "wof:name":"A Steindl OEG",
    "wof:placetype":"venue"
},
  "geometry": {"coordinates":[13.0641117096,47.7989425659],"type":"Point"}
}