{
  "type": "Feature",
  "properties": {
    "addr:full":"Sterneckstr 60 Klagenfurt K\u00e4rnten 9020",
    "addr:housenumber":"60",
    "addr:postcode":"9020",
    "addr:street":"Sterneckstr;Kaernten",
    "iso:country":"AT",
    "sg:address":"Sterneckstr 60",
    "sg:city":"Klagenfurt",
    "sg:orig_category":"Schienenfahrzeuge",
    "sg:phone":"+43 463 511665",
    "sg:postcode":"9020",
    "sg:province":"K\u00e4rnten",
    "wof:name":"Waggonvermietung Delta Oil GesmbH",
    "wof:placetype":"venue"
},
  "geometry": {"coordinates":[14.2905988693,46.6254196167],"type":"Point"}
}