{
  "type": "Feature",
  "properties": {
    "addr:full":"Thaliastr 53 Wien Wien 1160",
    "addr:housenumber":"53",
    "addr:postcode":"1160",
    "addr:street":"Thaliastr",
    "iso:country":"AT",
    "sg:address":"Thaliastr 53",
    "sg:city":"Wien",
    "sg:orig_category":"Damenmoden",
    "sg:phone":"+43 1 49318690",
    "sg:postcode":"1160",
    "sg:province":"Wien",
    "wof:name":"Kloucek Wilhelm KG",
    "wof:placetype":"venue"
},
  "geometry": {"coordinates":[16.3285198212,48.2099952698],"type":"Point"}
}