{
  "type": "Feature",
  "properties": {
    "addr:full":"Sombartstr 1-5 Linz Ober\u00f6sterreich 4040",
    "addr:housenumber":"1-5",
    "addr:postcode":"4040",
    "addr:street":"Sombartstr",
    "iso:country":"AT",
    "sg:address":"Sombartstr 1-5",
    "sg:city":"Linz",
    "sg:orig_category":"Bibliotheken",
    "sg:phone":"+43 732 25606601",
    "sg:postcode":"4040",
    "sg:province":"Ober\u00f6sterreich",
    "wof:name":"Stadtbibliothek Linz - Dornach-Auhof",
    "wof:placetype":"venue"
},
  "geometry": {"coordinates":[14.3179798126,48.3330612183],"type":"Point"}
}