{
  "type": "Feature",
  "properties": {
    "iso:country":"AT",
    "sg:address":"Kremstalstr 50",
    "sg:city":"Neuhofen an der Krems",
    "sg:orig_category":"Tankstellen",
    "sg:phone":"+43 4372 2720096",
    "sg:postcode":"4501",
    "sg:province":"Ober\u00f6sterreich",
    "wof:name":"BP Austria Marketing GmbH",
    "wof:placetype":"venue"
},
  "geometry": {"coordinates":[14.2209100723,48.13098526],"type":"Point"}
}