{
  "type": "Feature",
  "properties": {
    "addr:full":"Hauptstr 2 Persenbeug Nieder\u00f6sterreich 3680",
    "addr:housenumber":"2",
    "addr:postcode":"3680",
    "addr:street":"Hauptstr",
    "iso:country":"AT",
    "sg:address":"Hauptstr 2",
    "sg:city":"Persenbeug",
    "sg:orig_category":"Friseure U Frisiersalons",
    "sg:phone":"+43 4374 1255504",
    "sg:postcode":"3680",
    "sg:province":"Nieder\u00f6sterreich",
    "wof:name":"Salon Figaro",
    "wof:placetype":"venue"
},
  "geometry": {"coordinates":[15.0799818039,48.1875495911],"type":"Point"}
}