{
  "type": "Feature",
  "properties": {
    "iso:country":"AT",
    "sg:address":"Kapellenweg 7",
    "sg:city":"Nu\u00dfdorf am Attersee",
    "sg:orig_category":"Steuerberatung",
    "sg:phone":"+43 76668039",
    "sg:postcode":"4865",
    "sg:province":"Ober\u00f6sterreich",
    "wof:name":"P\u00f6lzleithner Josef Mag Wirtschaftstreuhand KEG",
    "wof:placetype":"venue"
},
  "geometry": {"coordinates":[13.5220470428,47.8845367432],"type":"Point"}
}