{
  "type": "Feature",
  "properties": {
    "iso:country":"AT",
    "sg:address":"Neuburg 1",
    "sg:city":"Koblach",
    "sg:orig_category":"Sandstrahlarbeiten",
    "sg:phone":"+43 5523 53230",
    "sg:postcode":"6842",
    "sg:province":"Vorarlberg",
    "wof:name":"Sandstrahldesign - Klaus Spalt",
    "wof:placetype":"venue"
},
  "geometry": {"coordinates":[9.612165451,47.345085144],"type":"Point"}
}