{
  "type": "Feature",
  "properties": {
    "addr:full":"Hauptstr 3 Ebenfurth Nieder\u00f6sterreich 2490",
    "addr:housenumber":"3",
    "addr:postcode":"2490",
    "addr:street":"Hauptstr",
    "iso:country":"AT",
    "sg:address":"Hauptstr 3",
    "sg:city":"Ebenfurth",
    "sg:orig_category":"Restaurants: Chinesisch",
    "sg:phone":"+43 2624 52468",
    "sg:postcode":"2490",
    "sg:province":"Nieder\u00f6sterreich",
    "wof:name":"China-Restaurant Storch",
    "wof:placetype":"venue"
},
  "geometry": {"coordinates":[16.368516922,47.8779449463],"type":"Point"}
}