{
  "type": "Feature",
  "properties": {
    "iso:country":"AT",
    "sg:address":"Nr 60",
    "sg:city":"St. Nikolai im Sausal",
    "sg:orig_category":"Installationsunternehmen",
    "sg:phone":"+43 4331 8523740",
    "sg:postcode":"8505",
    "sg:province":"Steiermark",
    "wof:name":"Gruber Michael GesmbH & Co KG",
    "wof:placetype":"venue"
},
  "geometry": {"coordinates":[15.4494228363,46.821395874],"type":"Point"}
}