{
  "type": "Feature",
  "properties": {
    "addr:full":"Mariahilfstr 24 Bregenz Vorarlberg 6900",
    "addr:housenumber":"24",
    "addr:postcode":"6900",
    "addr:street":"Mariahilfstr",
    "iso:country":"AT",
    "sg:address":"Mariahilfstr 24",
    "sg:city":"Bregenz",
    "sg:orig_category":"Weiterbildungsinstitute M Allg U Berufl Bildungsangebot",
    "sg:phone":"+43 4355 7452780",
    "sg:postcode":"6900",
    "sg:province":"Vorarlberg",
    "wof:name":"OBHUT-Beratungsservice f Kinderbetreuung - Holzknecht Andreas",
    "wof:placetype":"venue"
},
  "geometry": {"coordinates":[9.7308111191,47.4965057373],"type":"Point"}
}