{
  "type": "Feature",
  "properties": {
    "addr:full":"Walser Str 65 Hirschegg Vorarlberg 6992",
    "addr:housenumber":"65",
    "addr:postcode":"6992",
    "addr:street":"Str",
    "iso:country":"AT",
    "sg:address":"Walser Str 65",
    "sg:city":"Hirschegg",
    "sg:orig_category":"Banken U Sparkassen",
    "sg:phone":"+43 4355 173360",
    "sg:postcode":"6992",
    "sg:province":"Vorarlberg",
    "wof:name":"Vorarlberger Landes- u Hypothekenbank AG",
    "wof:placetype":"venue"
},
  "geometry": {"coordinates":[10.1674003601,47.3430023193],"type":"Point"}
}