{
  "type": "Feature",
  "properties": {
    "addr:full":"Waidhofner Str 2 Seitenstetten Nieder\u00f6sterreich 3353",
    "addr:housenumber":"2",
    "addr:postcode":"3353",
    "addr:street":"Str",
    "iso:country":"AT",
    "sg:address":"Waidhofner Str 2",
    "sg:city":"Seitenstetten",
    "sg:orig_category":"Internet-Cafes",
    "sg:phone":"+43 7477 43239",
    "sg:postcode":"3353",
    "sg:province":"Nieder\u00f6sterreich",
    "wof:name":"Cafe Mitterer",
    "wof:placetype":"venue"
},
  "geometry": {"coordinates":[14.6532201767,48.0353927612],"type":"Point"}
}