{
  "type": "Feature",
  "properties": {
    "iso:country":"AT",
    "sg:address":"Bahnhofstr 12",
    "sg:city":"Rechnitz",
    "sg:orig_category":"Tankstellen",
    "sg:phone":"+43 3363 79330",
    "sg:postcode":"7471",
    "sg:province":"Burgenland",
    "wof:name":"OMV AG",
    "wof:placetype":"venue"
},
  "geometry": {"coordinates":[16.4430713654,47.3012275696],"type":"Point"}
}