{
  "type": "Feature",
  "properties": {
    "iso:country":"AT",
    "sg:address":"Boos-Waldeck-Weg 5",
    "sg:city":"Raabs an der Thaya",
    "sg:orig_category":"Lebensmittel / Einzelhandel",
    "sg:phone":"+43 2846 7630",
    "sg:postcode":"3820",
    "sg:province":"Nieder\u00f6sterreich",
    "wof:name":"Billa AG",
    "wof:placetype":"venue"
},
  "geometry": {"coordinates":[15.4881801605,48.8519172668],"type":"Point"}
}