{
  "type": "Feature",
  "properties": {
    "addr:full":"Leonhardstr 35 Graz Steiermark 8010",
    "addr:housenumber":"35",
    "addr:postcode":"8010",
    "addr:street":"Leonhardstr",
    "iso:country":"AT",
    "sg:address":"Leonhardstr 35",
    "sg:city":"Graz",
    "sg:orig_category":"Alarmanlagen U Sicherheitssysteme",
    "sg:phone":"+43 4331 63837710",
    "sg:postcode":"8010",
    "sg:province":"Steiermark",
    "wof:name":"Alarmanlagen u Sicherheitstechnik Themmel GmbH",
    "wof:placetype":"venue"
},
  "geometry": {"coordinates":[15.4525051117,47.0727043152],"type":"Point"}
}