{
  "type": "Feature",
  "properties": {
    "addr:full":"Schnaller 51 Ried im Innkreis Ober\u00f6sterreich 4910",
    "addr:housenumber":"51",
    "addr:postcode":"4910",
    "addr:street":"Schnaller",
    "iso:country":"AT",
    "sg:address":"Schnaller 51",
    "sg:city":"Ried im Innkreis",
    "sg:classifiers":[
        {
            "category":"Shopping",
            "subcategory":"Clothing, Apparel, & Fashions",
            "type":"Retail Goods"
        }
    ],
    "sg:phone":"+43 4377 529500",
    "sg:postcode":"4910",
    "sg:province":"Ober\u00f6sterreich",
    "sg:tags":[
        "clothes"
    ],
    "wof:name":"FRANZ MAIRINGER GESMBH",
    "wof:placetype":"venue"
},
  "geometry": {"coordinates":[13.4873600006,48.2222366333],"type":"Point"}
}