{
  "type": "Feature",
  "properties": {
    "iso:country":"AT",
    "sg:address":"St. Veiter Str 123",
    "sg:city":"Klagenfurt",
    "sg:orig_category":"Friseure U Frisiersalons",
    "sg:phone":"+43 4346 341334",
    "sg:postcode":"9020",
    "sg:province":"K\u00e4rnten",
    "wof:name":"Friseursalon Gerlinde",
    "wof:placetype":"venue"
},
  "geometry": {"coordinates":[14.3148384094,46.6433181763],"type":"Point"}
}