{
  "type": "Feature",
  "properties": {
    "addr:full":"Grazer Str 27 St. Stefan im Rosental Steiermark 8083",
    "addr:housenumber":"27",
    "addr:postcode":"8083",
    "addr:street":"Str",
    "iso:country":"AT",
    "sg:address":"Grazer Str 27",
    "sg:city":"St. Stefan im Rosental",
    "sg:orig_category":"Lebensmittel / Einzelhandel",
    "sg:phone":"+43 4331 168741",
    "sg:postcode":"8083",
    "sg:province":"Steiermark",
    "wof:name":"Billa AG",
    "wof:placetype":"venue"
},
  "geometry": {"coordinates":[15.7056837082,46.9037971497],"type":"Point"}
}