{
  "type": "Feature",
  "properties": {
    "addr:full":"Vinzenz-Gredler-Str 15 Telfs Tirol 6410",
    "addr:housenumber":"15",
    "addr:postcode":"6410",
    "addr:street":"Vinzenz-Gredler-Str;Tirol",
    "iso:country":"AT",
    "sg:address":"Vinzenz-Gredler-Str 15",
    "sg:city":"Telfs",
    "sg:orig_category":"Graveure",
    "sg:phone":"+43 664 5017344",
    "sg:postcode":"6410",
    "sg:province":"Tirol",
    "wof:name":"Schwaiger Doris",
    "wof:placetype":"venue"
},
  "geometry": {"coordinates":[11.0639133453,47.3072128296],"type":"Point"}
}