{
  "type": "Feature",
  "properties": {
    "addr:full":"Hauptpl 1 Fehring Steiermark 8350",
    "addr:housenumber":"1",
    "addr:postcode":"8350",
    "addr:street":"Hauptpl",
    "iso:country":"AT",
    "sg:address":"Hauptpl 1",
    "sg:city":"Fehring",
    "sg:orig_category":"Tabaktrafiken",
    "sg:phone":"+43 3155 2219",
    "sg:postcode":"8350",
    "sg:province":"Steiermark",
    "wof:name":"Braunstein Michaela",
    "wof:placetype":"venue"
},
  "geometry": {"coordinates":[16.0107192993,46.936088562],"type":"Point"}
}