{
  "type": "Feature",
  "properties": {
    "iso:country":"AT",
    "sg:address":"Harter Str 44",
    "sg:city":"Eggersdorf",
    "sg:orig_category":"Maler, Anstreicher U Lackierer",
    "sg:phone":"+43 4366 44169413",
    "sg:postcode":"8063",
    "sg:province":"Steiermark",
    "wof:name":"Kreatives Malerteam - Seifried & Janesch",
    "wof:placetype":"venue"
},
  "geometry": {"coordinates":[15.5795526505,47.1320533752],"type":"Point"}
}