{
  "type": "Feature",
  "properties": {
    "addr:full":"Hauptstr 156 Kramsach Tirol 6233",
    "addr:housenumber":"156",
    "addr:postcode":"6233",
    "addr:street":"Hauptstr;Tirol",
    "iso:country":"AT",
    "sg:address":"Hauptstr 156",
    "sg:city":"Kramsach",
    "sg:orig_category":"Lebensmittel / Einzelhandel",
    "sg:phone":"+43 5337 66429",
    "sg:postcode":"6233",
    "sg:province":"Tirol",
    "wof:name":"Ruetz & Fagschlunger OHG",
    "wof:placetype":"venue"
},
  "geometry": {"coordinates":[11.8835477829,47.4473342896],"type":"Point"}
}