{
  "type": "Feature",
  "properties": {
    "addr:full":"Shopping City Seiersberg Top4/2/11 Puntigam Steiermark 8055",
    "addr:housenumber":"/ 2 / 11",
    "addr:postcode":"8055",
    "addr:street":"Shopping City;Top4",
    "iso:country":"AT",
    "sg:address":"Shopping City Seiersberg Top4/2/11",
    "sg:city":"Puntigam",
    "sg:orig_category":"Bekleidung / Einzelhandel",
    "sg:phone":"+43 4331 6711874",
    "sg:postcode":"8055",
    "sg:province":"Steiermark",
    "wof:name":"Popken Ulla GmbH & Co KG",
    "wof:placetype":"venue"
},
  "geometry": {"coordinates":[15.3990154266,47.0103302002],"type":"Point"}
}