{
  "type": "Feature",
  "properties": {
    "addr:full":"Waldstrasse 57 Mistelbach Nieder\u00f6sterreich 2130",
    "addr:housenumber":"57",
    "addr:postcode":"2130",
    "addr:street":"Waldstrasse;Niederoesterreich",
    "iso:country":"AT",
    "sg:address":"Waldstrasse 57",
    "sg:city":"Mistelbach",
    "sg:classifiers":[
        {
            "category":"Building & Trades",
            "subcategory":"Construction",
            "type":"Services"
        }
    ],
    "sg:phone":"+43 2572 2491",
    "sg:postcode":"2130",
    "sg:province":"Nieder\u00f6sterreich",
    "sg:tags":[
        "roofing"
    ],
    "wof:name":"Ernst Kastenhofer Dachdecker-Spengler Ges.m.b.H.",
    "wof:placetype":"venue"
},
  "geometry": {"coordinates":[16.5687561035,48.5771903992],"type":"Point"}
}