{
  "type": "Feature",
  "properties": {
    "addr:full":"Schulstr 7 Wiesmath Nieder\u00f6sterreich 2811",
    "addr:housenumber":"7",
    "addr:postcode":"2811",
    "addr:street":"Schulstr",
    "iso:country":"AT",
    "sg:address":"Schulstr 7",
    "sg:city":"Wiesmath",
    "sg:orig_category":"Hauptschulen",
    "sg:phone":"+43 2645 2250",
    "sg:postcode":"2811",
    "sg:province":"Nieder\u00f6sterreich",
    "wof:name":"Hauptschule Wiesmath",
    "wof:placetype":"venue"
},
  "geometry": {"coordinates":[16.290561676,47.6168861389],"type":"Point"}
}