{
  "type": "Feature",
  "properties": {
    "iso:country":"AT",
    "sg:address":"Dinghoferstr 63",
    "sg:city":"Linz",
    "sg:orig_category":"Elektronische Bauelemente U Bauteile",
    "sg:phone":"+43 4373 2669691",
    "sg:postcode":"4020",
    "sg:province":"Ober\u00f6sterreich",
    "sg:website":"aigner.co.at",
    "wof:name":"Aigner Elektronik HandelsgesmbH & Co KG",
    "wof:placetype":"venue"
},
  "geometry": {"coordinates":[14.299071312,48.2973251343],"type":"Point"}
}