{
  "type": "Feature",
  "properties": {
    "iso:country":"AT",
    "sg:address":"M\u00fcllerg 1",
    "sg:city":"Tulln an der Donau",
    "sg:orig_category":"Lebensmittel / Erzeugung U Gro\u00c3\u0178handel",
    "sg:phone":"+43 4322 7265794",
    "sg:postcode":"3430",
    "sg:province":"Nieder\u00f6sterreich",
    "wof:name":"M\u00fcller Rudolf",
    "wof:placetype":"venue"
},
  "geometry": {"coordinates":[16.0497398376,48.3306999207],"type":"Point"}
}