{
  "type": "Feature",
  "properties": {
    "addr:full":"Kellerg 26 Stixneusiedl Nieder\u00f6sterreich 2463",
    "addr:housenumber":"26",
    "addr:postcode":"2463",
    "addr:street":"Kellerg;Niederoesterreich",
    "iso:country":"AT",
    "sg:address":"Kellerg 26",
    "sg:city":"Stixneusiedl",
    "sg:orig_category":"Autohandel",
    "sg:phone":"+43 2230 3845",
    "sg:postcode":"2463",
    "sg:province":"Nieder\u00f6sterreich",
    "wof:name":"Schedlbauer Guido Ing",
    "wof:placetype":"venue"
},
  "geometry": {"coordinates":[16.6460075378,48.0537948608],"type":"Point"}
}