{
  "type": "Feature",
  "properties": {
    "addr:full":"Schmittenrain 2 Niedernsill Salzburg 5722",
    "addr:housenumber":"2",
    "addr:postcode":"5722",
    "addr:street":"Schmittenrain;Salzburg",
    "iso:country":"AT",
    "sg:address":"Schmittenrain 2",
    "sg:city":"Niedernsill",
    "sg:orig_category":"Schlossereien",
    "sg:phone":"+43 6548 8325",
    "sg:postcode":"5722",
    "sg:province":"Salzburg",
    "wof:name":"Hutter Helmut",
    "wof:placetype":"venue"
},
  "geometry": {"coordinates":[12.6416501999,47.2869110107],"type":"Point"}
}