{
  "type": "Feature",
  "properties": {
    "addr:full":"Hangg 15 Korneuburg Nieder\u00f6sterreich 2100",
    "addr:housenumber":"15",
    "addr:postcode":"2100",
    "addr:street":"Hangg;Niederoesterreich",
    "iso:country":"AT",
    "sg:address":"Hangg 15",
    "sg:city":"Korneuburg",
    "sg:orig_category":"Werbegrafik- U Grafik-Design",
    "sg:phone":"+43 4322 6266259",
    "sg:postcode":"2100",
    "sg:province":"Nieder\u00f6sterreich",
    "wof:name":"B\u00f6hm Jarmila studio XV",
    "wof:placetype":"venue"
},
  "geometry": {"coordinates":[16.3329143524,48.3437843323],"type":"Point"}
}