{
  "type": "Feature",
  "properties": {
    "iso:country":"AT",
    "sg:address":"Dorfpl. 3 ",
    "sg:city":"Zell am Ziller",
    "sg:classifiers":[
        {
            "category":"Banks & Credit Unions",
            "subcategory":"Bank",
            "type":"Services"
        }
    ],
    "sg:phone":"+43 4352 822215",
    "sg:postcode":"6280",
    "sg:province":"Tirol",
    "sg:tags":[
        "banking",
        "institution"
    ],
    "wof:name":"RAIFFEISENBANK ZELL AM ZILLER/REG. GEN. GMBH",
    "wof:placetype":"venue"
},
  "geometry": {"coordinates":[11.882062912,47.2332878113],"type":"Point"}
}