{
  "type": "Feature",
  "properties": {
    "addr:full":"Salzburger Str 7 Haid Ober\u00f6sterreich 4053",
    "addr:housenumber":"7",
    "addr:postcode":"4053",
    "addr:street":"Salzburger Str",
    "iso:country":"AT",
    "sg:address":"Salzburger Str 7",
    "sg:city":"Haid",
    "sg:orig_category":"Blumeneinzelhandel",
    "sg:phone":"+43 4372 2988275",
    "sg:postcode":"4053",
    "sg:province":"Ober\u00f6sterreich",
    "wof:name":"Ottend\u00f6rfer G\u00fcnter",
    "wof:placetype":"venue"
},
  "geometry": {"coordinates":[14.2493152618,48.2046203613],"type":"Point"}
}