{
  "type": "Feature",
  "properties": {
    "addr:full":"Gartenstr 1B Bad Ischl Ober\u00f6sterreich 4820",
    "addr:housenumber":"1b",
    "addr:postcode":"4820",
    "addr:street":"Gartenstr;Oberoesterreich",
    "iso:country":"AT",
    "sg:address":"Gartenstr 1B",
    "sg:city":"Bad Ischl",
    "sg:orig_category":"Physiotherapie",
    "sg:phone":"+43 6132 24313",
    "sg:postcode":"4820",
    "sg:province":"Ober\u00f6sterreich",
    "wof:name":"Van der Leest Gerard Dipl-PT",
    "wof:placetype":"venue"
},
  "geometry": {"coordinates":[13.6127719879,47.7088928223],"type":"Point"}
}