{
  "type": "Feature",
  "properties": {
    "addr:full":"Br\u00fchlegg 5 Hinterbr\u00fchl Nieder\u00f6sterreich 2371",
    "addr:housenumber":"5",
    "addr:postcode":"2371",
    "addr:street":"Bruehlegg;Niederoesterreich",
    "iso:country":"AT",
    "sg:address":"Br\u00fchlegg 5",
    "sg:city":"Hinterbr\u00fchl",
    "sg:orig_category":"Psychotherapie",
    "sg:phone":"+43 2236 48301",
    "sg:postcode":"2371",
    "sg:province":"Nieder\u00f6sterreich",
    "wof:name":"Tuchacek Helga",
    "wof:placetype":"venue"
},
  "geometry": {"coordinates":[116.6831436157,31.7060604095],"type":"Point"}
}