{
  "type": "Feature",
  "properties": {
    "addr:full":"Im Gries 31 Kitzb\u00fchel Tirol 6370",
    "addr:housenumber":"31",
    "addr:postcode":"6370",
    "addr:street":"Im Gries;Tirol",
    "iso:country":"AT",
    "sg:address":"Im Gries 31",
    "sg:city":"Kitzb\u00fchel",
    "sg:orig_category":"Behinderungen / Leben Mit Behinderungen",
    "sg:phone":"+43 5356 62440",
    "sg:postcode":"6370",
    "sg:province":"Tirol",
    "wof:name":"Behindertenberatung im Beratungszentrum Kitzb\u00fchel",
    "wof:placetype":"venue"
},
  "geometry": {"coordinates":[12.3930921555,47.4460334778],"type":"Point"}
}