{
  "type": "Feature",
  "properties": {
    "iso:country":"AT",
    "sg:address":"Amtshausg 9",
    "sg:city":"Frauenkirchen",
    "sg:orig_category":"Non-Classified Establishments",
    "sg:phone":"+43 5 91331136",
    "sg:postcode":"7132",
    "sg:province":"Burgenland",
    "wof:name":"Gendarmerieposten",
    "wof:placetype":"venue"
},
  "geometry": {"coordinates":[16.9265384674,47.837562561],"type":"Point"}
}