{
  "type": "Feature",
  "properties": {
    "iso:country":"AT",
    "sg:address":"Nr 101",
    "sg:city":"Elmen",
    "sg:orig_category":"Appartements / Ferienwohnungen",
    "sg:phone":"+43 4356 35280",
    "sg:postcode":"6644",
    "sg:province":"Tirol",
    "wof:name":"Larcher Christian u Veronika",
    "wof:placetype":"venue"
},
  "geometry": {"coordinates":[10.6220331192,47.2831077576],"type":"Point"}
}