{
  "type": "Feature",
  "properties": {
    "addr:full":"Nr 10 Weng im Ges\u00e4use Steiermark 8913",
    "addr:postcode":"8913",
    "addr:street":"Nr;Weng",
    "iso:country":"AT",
    "sg:address":"Nr 10",
    "sg:city":"Weng im Ges\u00e4use",
    "sg:orig_category":"Forstverwaltungen",
    "sg:phone":"+43 3611 22117",
    "sg:postcode":"8913",
    "sg:province":"Steiermark",
    "wof:name":"Landesforste Steierm\u00e4rkische",
    "wof:placetype":"venue"
},
  "geometry": {"coordinates":[14.635187149,47.5916290283],"type":"Point"}
}