{
  "type": "Feature",
  "properties": {
    "iso:country":"AT",
    "sg:address":"Steinbauergasse 4-6",
    "sg:city":"Wien",
    "sg:classifiers":[
        {
            "category":"Building & Trades",
            "subcategory":"Plumbing",
            "type":"Services"
        }
    ],
    "sg:phone":"+43 1 8107027",
    "sg:postcode":"1120",
    "sg:province":"Wien",
    "sg:tags":[
        "supraregional",
        "gas"
    ],
    "wof:name":"Hei-San Heizungs- und Sanit\u00e4rinstallationsges.m.b.H.",
    "wof:placetype":"venue"
},
  "geometry": {"coordinates":[16.3448104858,48.18384552],"type":"Point"}
}