{
  "type": "Feature",
  "properties": {
    "iso:country":"AT",
    "sg:address":"Aubauerstrasse 6",
    "sg:city":"Gmunden",
    "sg:classifiers":[
        {
            "category":"Utilities",
            "subcategory":"Cable",
            "type":"Services"
        }
    ],
    "sg:phone":"+43 761277202",
    "sg:postcode":"4810",
    "sg:province":"Ober\u00f6sterreich",
    "sg:tags":[
        "ready",
        "use",
        "cables",
        "finished"
    ],
    "sg:website":"pesi.at",
    "wof:name":"Ing. Pesendorfer Elektromaschinenbau GmbH",
    "wof:placetype":"venue"
},
  "geometry": {"coordinates":[13.785987854,47.9293403625],"type":"Point"}
}