{
  "type": "Feature",
  "properties": {
    "addr:full":"Nr 376 Hinterglemm Salzburg 5754",
    "addr:postcode":"5754",
    "addr:street":"Nr",
    "iso:country":"AT",
    "sg:address":"Nr 376",
    "sg:city":"Hinterglemm",
    "sg:orig_category":"Lebensmittel / Einzelhandel",
    "sg:phone":"+43 6541 6439",
    "sg:postcode":"5754",
    "sg:province":"Salzburg",
    "wof:name":"Spar-Markt Inh Ludwig Schr\u00fcmpf",
    "wof:placetype":"venue"
},
  "geometry": {"coordinates":[12.6012058258,47.3800849915],"type":"Point"}
}