{
  "type": "Feature",
  "properties": {
    "iso:country":"AT",
    "sg:address":"Mozartstrasse 5",
    "sg:city":"Sattledt",
    "sg:classifiers":[
        {
            "category":"Shopping",
            "subcategory":"Antiques",
            "type":"Retail Goods"
        }
    ],
    "sg:phone":"+43 7244 87950",
    "sg:postcode":"4642",
    "sg:province":"Ober\u00f6sterreich",
    "sg:tags":[
        "furniture"
    ],
    "wof:name":"Kunsttischlerei Hermann Balasch Meisterbetrieb f\u00fcr sachgerechte Restaurierung von antiken M\u00f6beln",
    "wof:placetype":"venue"
},
  "geometry": {"coordinates":[14.0603322983,48.0716133118],"type":"Point"}
}