{
  "type": "Feature",
  "properties": {
    "addr:full":"Schullerweg 98 Wals Salzburg 5071",
    "addr:housenumber":"98",
    "addr:postcode":"5071",
    "addr:street":"Schullerweg;Salzburg",
    "iso:country":"AT",
    "sg:address":"Schullerweg 98",
    "sg:city":"Wals",
    "sg:orig_category":"Parkettbodenverlegung",
    "sg:phone":"+43 4366 2825405",
    "sg:postcode":"5071",
    "sg:province":"Salzburg",
    "wof:name":"Kirchtag Thomas Fu\u00dfbodenforum GmbH",
    "wof:placetype":"venue"
},
  "geometry": {"coordinates":[12.9730300903,47.7763786316],"type":"Point"}
}