{
  "type": "Feature",
  "properties": {
    "addr:full":"G\u00fcnser Str 4 Pilgersdorf Burgenland 7441",
    "addr:housenumber":"4",
    "addr:postcode":"7441",
    "addr:street":"Str",
    "iso:country":"AT",
    "sg:address":"G\u00fcnser Str 4",
    "sg:city":"Pilgersdorf",
    "sg:orig_category":"Lebensmittel / Einzelhandel",
    "sg:phone":"+43 2616 7729",
    "sg:postcode":"7441",
    "sg:province":"Burgenland",
    "wof:name":"Schneider Gisela",
    "wof:placetype":"venue"
},
  "geometry": {"coordinates":[16.3492603302,47.4413986206],"type":"Point"}
}