{
  "type": "Feature",
  "properties": {
    "iso:country":"AT",
    "sg:address":"Malzg 5",
    "sg:city":"Wien",
    "sg:orig_category":"Installationsunternehmen",
    "sg:phone":"+43 4312 146075",
    "sg:postcode":"1020",
    "sg:province":"Wien",
    "wof:name":"Franye GmbH - Klimatechnik",
    "wof:placetype":"venue"
},
  "geometry": {"coordinates":[16.3756198883,48.2201271057],"type":"Point"}
}