{
  "type": "Feature",
  "properties": {
    "addr:full":"Schulstr 56 Baumgartenberg Ober\u00f6sterreich 4342",
    "addr:housenumber":"56",
    "addr:postcode":"4342",
    "addr:street":"Schulstr",
    "iso:country":"AT",
    "sg:address":"Schulstr 56",
    "sg:city":"Baumgartenberg",
    "sg:orig_category":"Volksschulen",
    "sg:phone":"+43 7269 297",
    "sg:postcode":"4342",
    "sg:province":"Ober\u00f6sterreich",
    "wof:name":"Volksschule",
    "wof:placetype":"venue"
},
  "geometry": {"coordinates":[14.745724678,48.2092475891],"type":"Point"}
}