{
  "type": "Feature",
  "properties": {
    "addr:full":"Salzburger Str 18 Mattsee Salzburg 5163",
    "addr:housenumber":"18",
    "addr:postcode":"5163",
    "addr:street":"Salzburger Str;Salzburg",
    "iso:country":"AT",
    "sg:address":"Salzburger Str 18",
    "sg:city":"Mattsee",
    "sg:orig_category":"Fenster, Tischlereien",
    "sg:phone":"+43 6217 5448",
    "sg:postcode":"5163",
    "sg:province":"Salzburg",
    "sg:website":"www.kalhamer.at",
    "wof:name":"Kalhamer Tischlerei GesmbH",
    "wof:placetype":"venue"
},
  "geometry": {"coordinates":[13.1028203964,47.968372345],"type":"Point"}
}