{
  "type": "Feature",
  "properties": {
    "iso:country":"AT",
    "sg:address":"Prater 196",
    "sg:city":"Wien",
    "sg:orig_category":"Lebensmittel / Einzelhandel",
    "sg:phone":"+43 1 7292710",
    "sg:postcode":"1020",
    "sg:province":"Wien",
    "wof:name":"Zur gr\u00fcnen H\u00fctte Inh Liselotte Zerzan",
    "wof:placetype":"venue"
},
  "geometry": {"coordinates":[16.4028301239,48.2135887146],"type":"Point"}
}