{
  "type": "Feature",
  "properties": {
    "addr:full":"Kranebitter Allee 144 Innsbruck Tirol 6020",
    "addr:housenumber":"144",
    "addr:postcode":"6020",
    "addr:street":"Kranebitter Allee;Tirol",
    "iso:country":"AT",
    "sg:address":"Kranebitter Allee 144",
    "sg:city":"Innsbruck",
    "sg:orig_category":"Restaurants: Griechisch",
    "sg:phone":"+43 512 294428",
    "sg:postcode":"6020",
    "sg:province":"Tirol",
    "wof:name":"Griechische Taverne",
    "wof:placetype":"venue"
},
  "geometry": {"coordinates":[11.3495883942,47.2631721497],"type":"Point"}
}