{
  "type": "Feature",
  "properties": {
    "iso:country":"AT",
    "sg:address":"Hannesgrub 8",
    "sg:city":"Ried im Innkreis",
    "sg:orig_category":"Holzgro\u00c3\u0178handel",
    "sg:phone":"+43 7752 80081",
    "sg:postcode":"4910",
    "sg:province":"Ober\u00f6sterreich",
    "wof:name":"Holz-Nagl GmbH",
    "wof:placetype":"venue"
},
  "geometry": {"coordinates":[13.4977397919,48.2174835205],"type":"Point"}
}