{
  "type": "Feature",
  "properties": {
    "iso:country":"AT",
    "sg:address":"Nr 18",
    "sg:city":"Schwanberg",
    "sg:orig_category":"Pensionen / Privatzimmer",
    "sg:phone":"+43 3467 8433",
    "sg:postcode":"8541",
    "sg:province":"Steiermark",
    "wof:name":"Seewaldhof",
    "wof:placetype":"venue"
},
  "geometry": {"coordinates":[15.2004699707,46.7570381165],"type":"Point"}
}