{
  "type": "Feature",
  "properties": {
    "iso:country":"AT",
    "sg:address":"M\u00fchlg 4",
    "sg:city":"Pinkafeld",
    "sg:orig_category":"Dentalwaren",
    "sg:phone":"+43 3357 438900",
    "sg:postcode":"7423",
    "sg:province":"Burgenland",
    "wof:name":"FITTYDENT INTERNATIONAL GmbH",
    "wof:placetype":"venue"
},
  "geometry": {"coordinates":[16.124250412,47.3718299866],"type":"Point"}
}