{
  "type": "Feature",
  "properties": {
    "addr:full":"Marienstr 11 Linz Ober\u00f6sterreich 4020",
    "addr:housenumber":"11",
    "addr:postcode":"4020",
    "addr:street":"Marienstr",
    "iso:country":"AT",
    "sg:address":"Marienstr 11",
    "sg:city":"Linz",
    "sg:orig_category":"Immobilienmakler",
    "sg:phone":"+43 4365 09008754",
    "sg:postcode":"4020",
    "sg:province":"Ober\u00f6sterreich",
    "wof:name":"Immopoly.at",
    "wof:placetype":"venue"
},
  "geometry": {"coordinates":[14.2903938293,48.3040237427],"type":"Point"}
}