{
  "type": "Feature",
  "properties": {
    "addr:full":"Landstr 15-17 Linz Ober\u00f6sterreich 4020",
    "addr:postcode":"15-17;4020",
    "addr:street":"Landstr;Oberoesterreich",
    "iso:country":"AT",
    "sg:address":"Landstr 15-17",
    "sg:city":"Linz",
    "sg:orig_category":"Blumeneinzelhandel",
    "sg:phone":"+43 732 772745",
    "sg:postcode":"4020",
    "sg:province":"Ober\u00f6sterreich",
    "wof:name":"Rubenzucker Walter",
    "wof:placetype":"venue"
},
  "geometry": {"coordinates":[14.2890501022,48.3032722473],"type":"Point"}
}