{
  "type": "Feature",
  "properties": {
    "iso:country":"AT",
    "sg:address":"Nr 151",
    "sg:city":"Trattenbach",
    "sg:orig_category":"Tischlereien",
    "sg:phone":"+43 2641 84840",
    "sg:postcode":"2881",
    "sg:province":"Nieder\u00f6sterreich",
    "wof:name":"K\u00f6nighofer Franz",
    "wof:placetype":"venue"
},
  "geometry": {"coordinates":[15.8923721313,47.6028823853],"type":"Point"}
}