{
  "type": "Feature",
  "properties": {
    "iso:country":"AT",
    "sg:address":"Landstr 26",
    "sg:city":"Linz",
    "sg:orig_category":"Bankomat-Standorte",
    "sg:phone":"+43 732 7849070",
    "sg:postcode":"4020",
    "sg:province":"Ober\u00f6sterreich",
    "wof:name":"Bankomat d Raiffeisenlandesbank Ober\u00f6sterreich regGenmbH",
    "wof:placetype":"venue"
},
  "geometry": {"coordinates":[14.2891712189,48.30260849],"type":"Point"}
}