{
  "type": "Feature",
  "properties": {
    "iso:country":"AT",
    "sg:address":"Weinz\u00f6ttlstr 42",
    "sg:city":"Andritz",
    "sg:orig_category":"Betten",
    "sg:phone":"+43 316 6969630",
    "sg:postcode":"8045",
    "sg:province":"Steiermark",
    "wof:name":"D\u00e4nisches Bettenlager HandelsgesmbH",
    "wof:placetype":"venue"
},
  "geometry": {"coordinates":[15.4147396088,47.1061134338],"type":"Point"}
}