{
  "type": "Feature",
  "properties": {
    "iso:country":"AT",
    "sg:address":"Linzer Str 15",
    "sg:city":"Melk",
    "sg:orig_category":"Steuerberatung",
    "sg:phone":"+43 2752 54119",
    "sg:postcode":"3390",
    "sg:province":"Nieder\u00f6sterreich",
    "wof:name":"Traxler Leopoldine",
    "wof:placetype":"venue"
},
  "geometry": {"coordinates":[15.3275260925,48.2262306213],"type":"Point"}
}