{
  "type": "Feature",
  "properties": {
    "addr:full":"Walser Str 30 Mittelberg Vorarlberg 6993",
    "addr:housenumber":"30",
    "addr:postcode":"6993",
    "addr:street":"Str",
    "iso:country":"AT",
    "sg:address":"Walser Str 30",
    "sg:city":"Mittelberg",
    "sg:orig_category":"Unterhaltungselektronik / Einzelhandel",
    "sg:phone":"+43 4355 175964",
    "sg:postcode":"6993",
    "sg:province":"Vorarlberg",
    "wof:name":"Matt Guido",
    "wof:placetype":"venue"
},
  "geometry": {"coordinates":[10.1606941223,47.3320846558],"type":"Point"}
}