{
  "type": "Feature",
  "properties": {
    "iso:country":"AT",
    "sg:address":"Franz-Kreutzberger-Str 4",
    "sg:city":"Mondsee",
    "sg:orig_category":"Musikgruppen",
    "sg:phone":"+43 4362 326470",
    "sg:postcode":"5310",
    "sg:province":"Ober\u00f6sterreich",
    "wof:name":"Musikkapelle Tiefgraben",
    "wof:placetype":"venue"
},
  "geometry": {"coordinates":[13.3478832245,47.8543891907],"type":"Point"}
}