{
  "type": "Feature",
  "properties": {
    "iso:country":"AT",
    "sg:address":"Wipplinger Str. 35 ",
    "sg:city":"Wien",
    "sg:classifiers":[
        {
            "category":"Travel",
            "subcategory":"Travel Agent",
            "type":"Entertainment"
        }
    ],
    "sg:phone":"+43 4315 3444600",
    "sg:postcode":"1010",
    "sg:province":"Wien",
    "sg:tags":[
        "business"
    ],
    "wof:name":"SOTOUR-AUSTRIA",
    "wof:placetype":"venue"
},
  "geometry": {"coordinates":[16.3657646179,48.2147140503],"type":"Point"}
}