{
  "type": "Feature",
  "properties": {
    "iso:country":"AT",
    "sg:address":"Winthalstr 21",
    "sg:city":"Hausmening",
    "sg:orig_category":"Lebensmittel / Einzelhandel",
    "sg:phone":"+43 7475 52137",
    "sg:postcode":"3363",
    "sg:province":"Nieder\u00f6sterreich",
    "wof:name":"Schrenk Maria",
    "wof:placetype":"venue"
},
  "geometry": {"coordinates":[14.8206996918,48.0778274536],"type":"Point"}
}