{
  "type": "Feature",
  "properties": {
    "addr:full":"Dorfstr 70 Mieders Tirol 6142",
    "addr:housenumber":"70",
    "addr:postcode":"6142",
    "addr:street":"Dorfstr;Tirol",
    "iso:country":"AT",
    "sg:address":"Dorfstr 70",
    "sg:city":"Mieders",
    "sg:orig_category":"Appartements / Ferienwohnungen",
    "sg:phone":"+43 4352 2562050",
    "sg:postcode":"6142",
    "sg:province":"Tirol",
    "wof:name":"Haus Ruech",
    "wof:placetype":"venue"
},
  "geometry": {"coordinates":[11.3784561157,47.1671829224],"type":"Point"}
}