{
  "type": "Feature",
  "properties": {
    "addr:full":"Zwickerleiten 1b Kitzb\u00fchel Tirol 6370",
    "addr:housenumber":"1b",
    "addr:postcode":"6370",
    "addr:street":"Zwickerleiten;Tirol",
    "iso:country":"AT",
    "sg:address":"Zwickerleiten 1b",
    "sg:city":"Kitzb\u00fchel",
    "sg:orig_category":"Appartements / Ferienwohnungen",
    "sg:phone":"+43 5356 64789",
    "sg:postcode":"6370",
    "sg:province":"Tirol",
    "wof:name":"Appartements Erzherzog Johann",
    "wof:placetype":"venue"
},
  "geometry": {"coordinates":[12.4002151489,47.4477272034],"type":"Point"}
}