{
  "type": "Feature",
  "properties": {
    "addr:full":"Rohrerg 1 Neukirchen am Gro\u00dfvenediger Salzburg 5741",
    "addr:housenumber":"1",
    "addr:postcode":"5741",
    "addr:street":"Rohrerg;Salzburg",
    "iso:country":"AT",
    "sg:address":"Rohrerg 1",
    "sg:city":"Neukirchen am Gro\u00dfvenediger",
    "sg:orig_category":"Pensionen / Privatzimmer",
    "sg:phone":"+43 4365 656376",
    "sg:postcode":"5741",
    "sg:province":"Salzburg",
    "wof:name":"Scharler Anna",
    "wof:placetype":"venue"
},
  "geometry": {"coordinates":[12.2779550552,47.2535400391],"type":"Point"}
}