{
  "type": "Feature",
  "properties": {
    "addr:full":"Caracallastr. 19  Enns Ober\u00f6sterreich 4470",
    "addr:housenumber":"19",
    "addr:postcode":"4470",
    "addr:street":"Caracallastr.",
    "iso:country":"AT",
    "sg:address":"Caracallastr. 19 ",
    "sg:city":"Enns",
    "sg:classifiers":[
        {
            "category":"Manufacturing",
            "subcategory":"Metals",
            "type":"Manufacturing & Wholesale Goods"
        }
    ],
    "sg:phone":"+43 4372 2383201",
    "sg:postcode":"4470",
    "sg:province":"Ober\u00f6sterreich",
    "sg:tags":[
        "metallurgy",
        "metalworking"
    ],
    "wof:name":"EISEN-LENZ-ENNS HANDELSGES.MBH",
    "wof:placetype":"venue"
},
  "geometry": {"coordinates":[14.4626951218,48.2190132141],"type":"Point"}
}