{
  "type": "Feature",
  "properties": {
    "addr:full":"Abbe Stadler-G 6 Melk Nieder\u00f6sterreich 3390",
    "addr:housenumber":"6",
    "addr:postcode":"3390",
    "addr:street":"Stadler-G",
    "iso:country":"AT",
    "sg:address":"Abbe Stadler-G 6",
    "sg:city":"Melk",
    "sg:orig_category":"Banken U Sparkassen",
    "sg:phone":"+43 2752 527270",
    "sg:postcode":"3390",
    "sg:province":"Nieder\u00f6sterreich",
    "wof:name":"Raiffeisenbank Region Melk regGenmbH",
    "wof:placetype":"venue"
},
  "geometry": {"coordinates":[15.3291749954,48.2272262573],"type":"Point"}
}