{
  "type": "Feature",
  "properties": {
    "addr:full":"Fabrikg 1 Ober-Grafendorf Nieder\u00f6sterreich 3200",
    "addr:housenumber":"1",
    "addr:postcode":"3200",
    "addr:street":"Fabrikg",
    "iso:country":"AT",
    "sg:address":"Fabrikg 1",
    "sg:city":"Ober-Grafendorf",
    "sg:orig_category":"Raumausstattung",
    "sg:phone":"+43 2747 23950",
    "sg:postcode":"3200",
    "sg:province":"Nieder\u00f6sterreich",
    "wof:name":"Mayer Helmut",
    "wof:placetype":"venue"
},
  "geometry": {"coordinates":[15.5508918762,48.1478652954],"type":"Point"}
}