{
  "type": "Feature",
  "properties": {
    "iso:country":"AT",
    "sg:address":"Waasen 75",
    "sg:city":"Moosbach",
    "sg:orig_category":"Blitzableiter U Blitzschutzanlagen",
    "sg:phone":"+43 4377 243300",
    "sg:postcode":"5271",
    "sg:province":"Ober\u00f6sterreich",
    "wof:name":"Aigner Erdungs- u Blitzschutzanlagen GesmbH",
    "wof:placetype":"venue"
},
  "geometry": {"coordinates":[13.162560463,48.2022743225],"type":"Point"}
}