{
  "type": "Feature",
  "properties": {
    "addr:full":"Schlo\u00dfberg 8 Murau Steiermark 8850",
    "addr:housenumber":"8",
    "addr:postcode":"8850",
    "addr:street":"Schlossberg",
    "iso:country":"AT",
    "sg:address":"Schlo\u00dfberg 8",
    "sg:city":"Murau",
    "sg:orig_category":"Non-Classified Establishments",
    "sg:phone":"+43 3532 2489",
    "sg:postcode":"8850",
    "sg:province":"Steiermark",
    "wof:name":"Pfarramt",
    "wof:placetype":"venue"
},
  "geometry": {"coordinates":[14.1694002151,47.1105384827],"type":"Point"}
}