{
  "type": "Feature",
  "properties": {
    "addr:full":"M\u00fchlg 18 Weiz Steiermark 8160",
    "addr:housenumber":"18",
    "addr:postcode":"8160",
    "addr:street":"Muehlg",
    "iso:country":"AT",
    "sg:address":"M\u00fchlg 18",
    "sg:city":"Weiz",
    "sg:orig_category":"Elektronik",
    "sg:phone":"+43 3172 64800",
    "sg:postcode":"8160",
    "sg:province":"Steiermark",
    "wof:name":"Ribu Elektronik GesmbH",
    "wof:placetype":"venue"
},
  "geometry": {"coordinates":[15.6215696335,47.2169532776],"type":"Point"}
}