{
  "type": "Feature",
  "properties": {
    "addr:full":"Rosenheimer Str 2 Kufstein Tirol 6330",
    "addr:housenumber":"2",
    "addr:postcode":"6330",
    "addr:street":"Str;Tirol",
    "iso:country":"AT",
    "sg:address":"Rosenheimer Str 2",
    "sg:city":"Kufstein",
    "sg:orig_category":"Autoersatzteile",
    "sg:phone":"+43 5372 630200",
    "sg:postcode":"6330",
    "sg:province":"Tirol",
    "wof:name":"Forstinger Handel und Service GmbH",
    "wof:placetype":"venue"
},
  "geometry": {"coordinates":[12.1740074158,47.5930290222],"type":"Point"}
}