{
  "type": "Feature",
  "properties": {
    "addr:full":"Hauptpl 32 Korneuburg Nieder\u00f6sterreich 2100",
    "addr:housenumber":"32",
    "addr:postcode":"2100",
    "addr:street":"Hauptpl;Niederoesterreich",
    "iso:country":"AT",
    "sg:address":"Hauptpl 32",
    "sg:city":"Korneuburg",
    "sg:orig_category":"Unterhaltungselektronik / Einzelhandel",
    "sg:phone":"+43 2262 72290",
    "sg:postcode":"2100",
    "sg:province":"Nieder\u00f6sterreich",
    "wof:name":"Amst\u00e4tter GmbH",
    "wof:placetype":"venue"
},
  "geometry": {"coordinates":[16.3329124451,48.3447036743],"type":"Point"}
}