{
  "type": "Feature",
  "properties": {
    "iso:country":"AT",
    "sg:address":"Hotterweg 48",
    "sg:city":"Eisenstadt",
    "sg:orig_category":"Physiotherapie",
    "sg:phone":"+43 676 5241310",
    "sg:postcode":"7000",
    "sg:province":"Burgenland",
    "wof:name":"Pingitzer Thomas Dipl-PT",
    "wof:placetype":"venue"
},
  "geometry": {"coordinates":[16.5200557709,47.8398857117],"type":"Point"}
}