{
  "type": "Feature",
  "properties": {
    "addr:full":"Nr B216 P\u00f6ggstall Nieder\u00f6sterreich 3650",
    "addr:postcode":"3650",
    "addr:street":"Nr B216 Poeggstall",
    "iso:country":"AT",
    "sg:address":"Nr B216",
    "sg:city":"P\u00f6ggstall",
    "sg:orig_category":"Lebensmittel / Einzelhandel",
    "sg:phone":"+43 2758 34910",
    "sg:postcode":"3650",
    "sg:province":"Nieder\u00f6sterreich",
    "wof:name":"Billa AG",
    "wof:placetype":"venue"
},
  "geometry": {"coordinates":[166.9221496582,-0.5282999873],"type":"Point"}
}