{
  "type": "Feature",
  "properties": {
    "iso:country":"AT",
    "sg:address":"Obere Str 9",
    "sg:city":"Schiltern",
    "sg:orig_category":"Lebensmittel / Einzelhandel",
    "sg:phone":"+43 2734 8453",
    "sg:postcode":"3553",
    "sg:province":"Nieder\u00f6sterreich",
    "wof:name":"Zwirchy's Kaufladen",
    "wof:placetype":"venue"
},
  "geometry": {"coordinates":[15.6222991943,48.5170211792],"type":"Point"}
}