{
  "type": "Feature",
  "properties": {
    "iso:country":"AT",
    "sg:address":"Otto-Hauberger-Str 54",
    "sg:city":"Kapfenberg",
    "sg:orig_category":"Volksschulen",
    "sg:phone":"+43 3862 224280",
    "sg:postcode":"8605",
    "sg:province":"Steiermark",
    "wof:name":"Volksschule Dr Karl Renner",
    "wof:placetype":"venue"
},
  "geometry": {"coordinates":[15.2982749939,47.4499053955],"type":"Point"}
}