{
  "type": "Feature",
  "properties": {
    "iso:country":"AT",
    "sg:address":"Triester Str 92",
    "sg:city":"Guntramsdorf",
    "sg:orig_category":"Autohandel",
    "sg:phone":"+43 2236 43401",
    "sg:postcode":"2353",
    "sg:province":"Nieder\u00f6sterreich",
    "sg:website":"aebner.at",
    "wof:name":"A. Ebner GesmbH",
    "wof:placetype":"venue"
},
  "geometry": {"coordinates":[16.3086891174,48.0551185608],"type":"Point"}
}