{
  "type": "Feature",
  "properties": {
    "addr:full":"Adolf Loos-G 9 Wien Wien 1210",
    "addr:housenumber":"9",
    "addr:postcode":"1210",
    "iso:country":"AT",
    "sg:address":"Adolf Loos-G 9",
    "sg:city":"Wien",
    "sg:orig_category":"Apotheken",
    "sg:phone":"+43 4312 5956200",
    "sg:postcode":"1210",
    "sg:province":"Wien",
    "wof:name":"Gro\u00dffeld-Apotheke Mag pharm Walter Janku",
    "wof:placetype":"venue"
},
  "geometry": {"coordinates":[16.4525089264,48.2680892944],"type":"Point"}
}