{
  "type": "Feature",
  "properties": {
    "iso:country":"AT",
    "sg:address":"Nr 15",
    "sg:city":"Warth",
    "sg:orig_category":"Chemisch-Technische Produkte",
    "sg:phone":"+43 2629 23610",
    "sg:postcode":"2831",
    "sg:province":"Nieder\u00f6sterreich",
    "wof:name":"Reckitt Benckiser Austria GesmbH",
    "wof:placetype":"venue"
},
  "geometry": {"coordinates":[16.1355209351,47.6589164734],"type":"Point"}
}