{
  "type": "Feature",
  "properties": {
    "iso:country":"AT",
    "sg:address":"Dreyhausenstr 40",
    "sg:city":"Wien",
    "sg:orig_category":"Friseure U Frisiersalons",
    "sg:phone":"+43 1 9123815",
    "sg:postcode":"1140",
    "sg:province":"Wien",
    "wof:name":"Nimmerrichter Silvia",
    "wof:placetype":"venue"
},
  "geometry": {"coordinates":[16.2995758057,48.1971435547],"type":"Point"}
}