{
  "type": "Feature",
  "properties": {
    "iso:country":"AT",
    "sg:address":"Bahnhofstr 76",
    "sg:city":"Ried im Innkreis",
    "sg:orig_category":"Geschenkartikel",
    "sg:phone":"+43 7752 82966",
    "sg:postcode":"4910",
    "sg:province":"Ober\u00f6sterreich",
    "sg:website":"www.oups.com",
    "wof:name":"Innpuls Vertriebs GmbH & Co KEG - incomix",
    "wof:placetype":"venue"
},
  "geometry": {"coordinates":[13.4875488281,48.2010498047],"type":"Point"}
}