{
  "type": "Feature",
  "properties": {
    "iso:country":"AT",
    "sg:address":"Lerchenstr 113",
    "sg:city":"Gnigl",
    "sg:orig_category":"Beschriftungen, Autobeschriftungen",
    "sg:phone":"+43 662 6609230",
    "sg:postcode":"5023",
    "sg:province":"Salzburg",
    "sg:website":"www.kierner.at",
    "wof:name":"Kierner GesmbH",
    "wof:placetype":"venue"
},
  "geometry": {"coordinates":[13.0743284225,47.8241691589],"type":"Point"}
}