{
  "type": "Feature",
  "properties": {
    "iso:country":"AT",
    "sg:address":"Hauptpl 31",
    "sg:city":"Deutschlandsberg",
    "sg:orig_category":"Handarbeiten",
    "sg:phone":"+43 3462 5730",
    "sg:postcode":"8530",
    "sg:province":"Steiermark",
    "wof:name":"Dorlis Handarbeitsecke",
    "wof:placetype":"venue"
},
  "geometry": {"coordinates":[15.2129383087,46.8143920898],"type":"Point"}
}