{
  "type": "Feature",
  "properties": {
    "iso:country":"AT",
    "sg:address":"Nr 6",
    "sg:city":"Millstatt",
    "sg:orig_category":"Pensionen / Privatzimmer",
    "sg:phone":"+43 4766 2642",
    "sg:postcode":"9872",
    "sg:province":"K\u00e4rnten",
    "wof:name":"Klinar Josef",
    "wof:placetype":"venue"
},
  "geometry": {"coordinates":[13.5716075897,46.8050041199],"type":"Point"}
}