{
  "type": "Feature",
  "properties": {
    "addr:full":"Siccardsburgg 83 Wien Wien 1100",
    "addr:housenumber":"83",
    "addr:postcode":"1100",
    "addr:street":"Siccardsburgg",
    "iso:country":"AT",
    "sg:address":"Siccardsburgg 83",
    "sg:city":"Wien",
    "sg:orig_category":"Lebensmittel / Einzelhandel",
    "sg:phone":"+43 1 60225070",
    "sg:postcode":"1100",
    "sg:province":"Wien",
    "wof:name":"SPAR \u00f6sterreichische Warenhandels-AG",
    "wof:placetype":"venue"
},
  "geometry": {"coordinates":[16.369594574,48.1696014404],"type":"Point"}
}