{
  "type": "Feature",
  "properties": {
    "addr:full":"St.-Berthold-Allee 25 Garsten Ober\u00f6sterreich 4451",
    "addr:housenumber":"25",
    "addr:postcode":"4451",
    "addr:street":"St.-Berthold-Allee",
    "iso:country":"AT",
    "sg:address":"St.-Berthold-Allee 25",
    "sg:city":"Garsten",
    "sg:orig_category":"Transportunternehmen",
    "sg:phone":"+43 7252 52732",
    "sg:postcode":"4451",
    "sg:province":"Ober\u00f6sterreich",
    "wof:name":"Halmer Anna",
    "wof:placetype":"venue"
},
  "geometry": {"coordinates":[14.4070501328,48.0259513855],"type":"Point"}
}