{
  "type": "Feature",
  "properties": {
    "iso:country":"AT",
    "sg:address":"Wagramer Str 109/28",
    "sg:city":"Wien",
    "sg:classifiers":[
        {
            "category":"Arts & Performance",
            "subcategory":"Theater",
            "type":"Entertainment"
        }
    ],
    "sg:phone":"+43 699 19224271",
    "sg:postcode":"1220",
    "sg:province":"Wien",
    "wof:name":"Gruam",
    "wof:placetype":"venue"
},
  "geometry": {"coordinates":[16.4395160675,48.2462387085],"type":"Point"}
}