{
  "type": "Feature",
  "properties": {
    "addr:full":"Nr 270 Burgau Steiermark 8291",
    "addr:postcode":"8291",
    "addr:street":"Nr 270",
    "iso:country":"AT",
    "sg:address":"Nr 270",
    "sg:city":"Burgau",
    "sg:orig_category":"Tankstellen",
    "sg:phone":"+43 3383 2230",
    "sg:postcode":"8291",
    "sg:province":"Steiermark",
    "wof:name":"OMV AG",
    "wof:placetype":"venue"
},
  "geometry": {"coordinates":[16.0987606049,47.143081665],"type":"Point"}
}