{
  "type": "Feature",
  "properties": {
    "iso:country":"AT",
    "sg:address":"Niedermoserstr 10",
    "sg:city":"Wien",
    "sg:classifiers":[
        {
            "category":"Professional",
            "subcategory":"Computer Services",
            "type":"Services"
        }
    ],
    "sg:phone":"+43 1 2566666",
    "sg:postcode":"1220",
    "sg:province":"Wien",
    "sg:tags":[
        "software"
    ],
    "wof:name":"Seidl Kurt Software HandelsgesmbH",
    "wof:placetype":"venue"
},
  "geometry": {"coordinates":[16.4631958008,48.2632331848],"type":"Point"}
}