{
  "type": "Feature",
  "properties": {
    "iso:country":"AT",
    "sg:address":"Getreideg 25",
    "sg:city":"Salzburg",
    "sg:orig_category":"Blumeneinzelhandel",
    "sg:phone":"+43 662 840107",
    "sg:postcode":"5020",
    "sg:province":"Salzburg",
    "wof:name":"Florea in der Passage bei Salzburger Blumenschl\u00f6ssl",
    "wof:placetype":"venue"
},
  "geometry": {"coordinates":[13.0421743393,47.7998771667],"type":"Point"}
}