{
  "type": "Feature",
  "properties": {
    "iso:country":"AT",
    "sg:address":"Glaserg 19",
    "sg:city":"Wien",
    "sg:orig_category":"Altbausanierungen",
    "sg:phone":"+43 1 3103689",
    "sg:postcode":"1090",
    "sg:province":"Wien",
    "wof:name":"Thisan Inh Gert Thimm KEG",
    "wof:placetype":"venue"
},
  "geometry": {"coordinates":[16.364616394,48.2250061035],"type":"Point"}
}