{
  "type": "Feature",
  "properties": {
    "addr:full":"Rathauspl 15 Aschbach Markt Nieder\u00f6sterreich 3361",
    "addr:housenumber":"15",
    "addr:postcode":"3361",
    "addr:street":"Rathauspl",
    "iso:country":"AT",
    "sg:address":"Rathauspl 15",
    "sg:city":"Aschbach Markt",
    "sg:orig_category":"Friseure U Frisiersalons",
    "sg:phone":"+43 4374 7677255",
    "sg:postcode":"3361",
    "sg:province":"Nieder\u00f6sterreich",
    "wof:name":"Novotny Rosa",
    "wof:placetype":"venue"
},
  "geometry": {"coordinates":[14.7487411499,48.072769165],"type":"Point"}
}