{
  "type": "Feature",
  "properties": {
    "addr:full":"Peischinger Str Neunkirchen Nieder\u00f6sterreich 2620",
    "addr:postcode":"2620",
    "addr:street":"Str Neunkirchen",
    "iso:country":"AT",
    "sg:address":"Peischinger Str",
    "sg:city":"Neunkirchen",
    "sg:orig_category":"Feinkost",
    "sg:phone":"+43 2635 64938",
    "sg:postcode":"2620",
    "sg:province":"Nieder\u00f6sterreich",
    "wof:name":"Sagmeister Herbert",
    "wof:placetype":"venue"
},
  "geometry": {"coordinates":[16.0968093872,47.7262458801],"type":"Point"}
}