{
  "type": "Feature",
  "properties": {
    "iso:country":"AT",
    "sg:address":"Im Stadtgut A1",
    "sg:city":"Gleink",
    "sg:orig_category":"Forschungsinstitute",
    "sg:phone":"+43 4372 52220100",
    "sg:postcode":"4407",
    "sg:province":"Ober\u00f6sterreich",
    "wof:name":"Fazat Steyr GmbH - Forschungs- u Ausbildungszentrum f Arbeit und Technik",
    "wof:placetype":"venue"
},
  "geometry": {"coordinates":[14.4159860611,48.0908508301],"type":"Point"}
}