{
  "type": "Feature",
  "properties": {
    "iso:country":"AT",
    "sg:address":"Feuchterslebeng 67",
    "sg:city":"Wien",
    "sg:orig_category":"\u00c3\u201erzte / F Allgemeinmedizin",
    "sg:phone":"+43 1 6040919",
    "sg:postcode":"1100",
    "sg:province":"Wien",
    "wof:name":"Skoda Herbert Dr",
    "wof:placetype":"venue"
},
  "geometry": {"coordinates":[16.3858985901,48.1711196899],"type":"Point"}
}