{
  "type": "Feature",
  "properties": {
    "addr:full":"Nr 108 St. Peter am Ottersbach Steiermark 8093",
    "addr:postcode":"8093",
    "addr:street":"Nr 108",
    "iso:country":"AT",
    "sg:address":"Nr 108",
    "sg:city":"St. Peter am Ottersbach",
    "sg:orig_category":"Diskotheken",
    "sg:phone":"+43 4366 44606505",
    "sg:postcode":"8093",
    "sg:province":"Steiermark",
    "wof:name":"P & H Musicfactory - Mobildisco",
    "wof:placetype":"venue"
},
  "geometry": {"coordinates":[15.7594327927,46.79920578],"type":"Point"}
}