{
  "type": "Feature",
  "properties": {
    "addr:full":"Waidhofner Str. 11  Rosenau Nieder\u00f6sterreich 3332",
    "addr:postcode":"3332",
    "addr:street":"Str.;Rosenau",
    "iso:country":"AT",
    "sg:address":"Waidhofner Str. 11 ",
    "sg:city":"Rosenau",
    "sg:classifiers":[
        {
            "category":"Manufacturing",
            "subcategory":"Paper Products",
            "type":"Manufacturing & Wholesale Goods"
        }
    ],
    "sg:phone":"+43 4374 48201810",
    "sg:postcode":"3332",
    "sg:province":"Nieder\u00f6sterreich",
    "sg:tags":[
        "cardboard"
    ],
    "wof:name":"NBG SPECIAL COATINGS GES.MBH",
    "wof:placetype":"venue"
},
  "geometry": {"coordinates":[14.7418012619,48.0094642639],"type":"Point"}
}