{
  "type": "Feature",
  "properties": {
    "addr:full":"Horner Str. 106  Stockerau Nieder\u00f6sterreich 2000",
    "addr:housenumber":"106",
    "addr:postcode":"2000",
    "addr:street":"Str.",
    "iso:country":"AT",
    "sg:address":"Horner Str. 106 ",
    "sg:city":"Stockerau",
    "sg:classifiers":[
        {
            "category":"Home & Garden",
            "subcategory":"Home Furnishings",
            "type":"Retail Goods"
        }
    ],
    "sg:phone":"+43 4322 66639000",
    "sg:postcode":"2000",
    "sg:province":"Nieder\u00f6sterreich",
    "sg:tags":[
        "household"
    ],
    "wof:name":"PETER MAX VERTRIEBSGES.MBH",
    "wof:placetype":"venue"
},
  "geometry": {"coordinates":[16.1804294586,48.3893127441],"type":"Point"}
}