{
  "type": "Feature",
  "properties": {
    "addr:full":"Am Spitz 12 Wien Wien 1210",
    "addr:housenumber":"12",
    "addr:postcode":"1210",
    "addr:street":"Am Spitz",
    "iso:country":"AT",
    "sg:address":"Am Spitz 12",
    "sg:city":"Wien",
    "sg:orig_category":"Personalbereitstellung",
    "sg:phone":"+43 1 51676300",
    "sg:postcode":"1210",
    "sg:province":"Wien",
    "wof:name":"Manpower GmbH - Personal f Industrie/Gewerbe",
    "wof:placetype":"venue"
},
  "geometry": {"coordinates":[16.3966197968,48.257900238],"type":"Point"}
}