{
  "type": "Feature",
  "properties": {
    "addr:full":"Seestr 1 Bregenz Vorarlberg 6900",
    "addr:housenumber":"1",
    "addr:postcode":"6900",
    "addr:street":"Seestr",
    "iso:country":"AT",
    "sg:address":"Seestr 1",
    "sg:city":"Bregenz",
    "sg:orig_category":"Bezirkshauptmannschaften",
    "sg:phone":"+43 5574 49510",
    "sg:postcode":"6900",
    "sg:province":"Vorarlberg",
    "wof:name":"Bezirkshauptmannschaft Bregenz",
    "wof:placetype":"venue"
},
  "geometry": {"coordinates":[9.7479448318,47.5056610107],"type":"Point"}
}