{
  "type": "Feature",
  "properties": {
    "addr:full":"Breitenleer Str 204 Wien Wien 1220",
    "addr:housenumber":"204",
    "addr:postcode":"1220",
    "iso:country":"AT",
    "sg:address":"Breitenleer Str 204",
    "sg:city":"Wien",
    "sg:orig_category":"Lebensmittel / Einzelhandel",
    "sg:phone":"+43 4317 342970",
    "sg:postcode":"1220",
    "sg:province":"Wien",
    "wof:name":"Penny Markt",
    "wof:placetype":"venue"
},
  "geometry": {"coordinates":[16.4892787933,48.2511634827],"type":"Point"}
}