{
  "type": "Feature",
  "properties": {
    "iso:country":"AT",
    "sg:address":"Fabriksg 6",
    "sg:city":"Neunkirchen",
    "sg:orig_category":"Zeitungen U Zeitschriften",
    "sg:phone":"+43 4326 35629490",
    "sg:postcode":"2620",
    "sg:province":"Nieder\u00f6sterreich",
    "wof:name":"Nieder\u00f6sterreichische Nachrichten",
    "wof:placetype":"venue"
},
  "geometry": {"coordinates":[16.0824928284,47.7212486267],"type":"Point"}
}