{
  "type": "Feature",
  "properties": {
    "iso:country":"AT",
    "sg:address":"Wiener Str 5",
    "sg:city":"Maria Lanzendorf",
    "sg:orig_category":"Elektroinstallationsunternehmen",
    "sg:phone":"+43 2235 47273",
    "sg:postcode":"2326",
    "sg:province":"Nieder\u00f6sterreich",
    "wof:name":"Schmidt Dietmar",
    "wof:placetype":"venue"
},
  "geometry": {"coordinates":[16.4179706573,48.0994949341],"type":"Point"}
}