{
  "type": "Feature",
  "properties": {
    "iso:country":"AT",
    "sg:address":"Mariahilfer Strasse 32",
    "sg:city":"Wien",
    "sg:classifiers":[
        {
            "category":"Professional",
            "subcategory":"Management & Consulting",
            "type":"Services"
        }
    ],
    "sg:phone":"+43 1 52417170",
    "sg:postcode":"1070",
    "sg:province":"Wien",
    "sg:tags":[
        "seminar"
    ],
    "sg:website":"mdi.at",
    "wof:name":"MDI Managementinstitut der Industrie",
    "wof:placetype":"venue"
},
  "geometry": {"coordinates":[16.3548851013,48.2001647949],"type":"Point"}
}