{
  "type": "Feature",
  "properties": {
    "addr:full":"Neustiftg 6 Baden Nieder\u00f6sterreich 2500",
    "addr:housenumber":"6",
    "addr:postcode":"2500",
    "addr:street":"Neustiftg;Niederoesterreich",
    "iso:country":"AT",
    "sg:address":"Neustiftg 6",
    "sg:city":"Baden",
    "sg:orig_category":"Bestattungsunternehmen",
    "sg:phone":"+43 2252 86800500",
    "sg:postcode":"2500",
    "sg:province":"Nieder\u00f6sterreich",
    "wof:name":"St\u00e4dtische Bestattung",
    "wof:placetype":"venue"
},
  "geometry": {"coordinates":[16.2370262146,48.0065727234],"type":"Point"}
}