{
  "type": "Feature",
  "properties": {
    "addr:full":"Thalerl 41 Kernhof Nieder\u00f6sterreich 3195",
    "addr:housenumber":"41",
    "addr:postcode":"3195",
    "addr:street":"Thalerl",
    "iso:country":"AT",
    "sg:address":"Thalerl 41",
    "sg:city":"Kernhof",
    "sg:orig_category":"Appartements / Ferienwohnungen",
    "sg:phone":"+43 2768 2524",
    "sg:postcode":"3195",
    "sg:province":"Nieder\u00f6sterreich",
    "wof:name":"Ferienwohnungen Moar",
    "wof:placetype":"venue"
},
  "geometry": {"coordinates":[15.5438318253,47.8151397705],"type":"Point"}
}