{
  "type": "Feature",
  "properties": {
    "addr:full":"Sonnblickgasse 4 Knittelfeld Steiermark 8720",
    "addr:housenumber":"4",
    "addr:postcode":"8720",
    "addr:street":"Sonnblickgasse",
    "iso:country":"AT",
    "sg:address":"Sonnblickgasse 4",
    "sg:city":"Knittelfeld",
    "sg:classifiers":[
        {
            "category":"Building & Trades",
            "subcategory":"Plumbing",
            "type":"Services"
        }
    ],
    "sg:phone":"+43 3512 82532",
    "sg:postcode":"8720",
    "sg:province":"Steiermark",
    "sg:tags":[
        "supraregional",
        "gas"
    ],
    "wof:name":"Kurt Thonhauser",
    "wof:placetype":"venue"
},
  "geometry": {"coordinates":[14.8281669617,47.2210578918],"type":"Point"}
}