{
  "type": "Feature",
  "properties": {
    "iso:country":"AT",
    "sg:address":"Gmundner Str 9",
    "sg:city":"Laakirchen",
    "sg:orig_category":"Non-Classified Establishments",
    "sg:phone":"+43 5 91334107",
    "sg:postcode":"4663",
    "sg:province":"Ober\u00f6sterreich",
    "wof:name":"Gendarmerieposten",
    "wof:placetype":"venue"
},
  "geometry": {"coordinates":[13.8237438202,47.9804840088],"type":"Point"}
}