{
  "type": "Feature",
  "properties": {
    "addr:full":"Heiligenkreuz am Waasen Steiermark 8081",
    "addr:postcode":"8081",
    "iso:country":"AT",
    "sg:city":"Heiligenkreuz am Waasen",
    "sg:orig_category":"Feuerwehren",
    "sg:phone":"+43 3116 2068",
    "sg:postcode":"8081",
    "sg:province":"Steiermark",
    "wof:name":"Freiwillige Feuerwehr Manning",
    "wof:placetype":"venue"
},
  "geometry": {"coordinates":[15.6284952164,46.8996238708],"type":"Point"}
}