{
  "type": "Feature",
  "properties": {
    "iso:country":"AT",
    "sg:address":"Steinbergstr 54",
    "sg:city":"Wetzelsdorf",
    "sg:orig_category":"Restaurants: Chinesisch",
    "sg:phone":"+43 316 581452",
    "sg:postcode":"8052",
    "sg:province":"Steiermark",
    "wof:name":"China-Restaurant Hu Nan",
    "wof:placetype":"venue"
},
  "geometry": {"coordinates":[15.3742361069,47.0561943054],"type":"Point"}
}