{
  "type": "Feature",
  "properties": {
    "iso:country":"AT",
    "sg:address":"Treietstr 56",
    "sg:city":"Sulz-R\u00f6this",
    "sg:orig_category":"Fenster",
    "sg:phone":"+43 4355 2244641",
    "sg:postcode":"6832",
    "sg:province":"Vorarlberg",
    "wof:name":"Fricco Johann Josef Frick",
    "wof:placetype":"venue"
},
  "geometry": {"coordinates":[9.6507492065,47.2916259766],"type":"Point"}
}