{
  "type": "Feature",
  "properties": {
    "iso:country":"AT",
    "sg:address":"Salurner Str 5",
    "sg:city":"Innsbruck",
    "sg:orig_category":"Raumausstattung",
    "sg:phone":"+43 4351 2570317",
    "sg:postcode":"6020",
    "sg:province":"Tirol",
    "wof:name":"Raum-Design Rabitsch",
    "wof:placetype":"venue"
},
  "geometry": {"coordinates":[11.3977127075,47.2628250122],"type":"Point"}
}