{
  "type": "Feature",
  "properties": {
    "addr:full":"Hauptstr. 55  Zams Tirol 6511",
    "addr:housenumber":"55",
    "addr:postcode":"6511",
    "addr:street":"Hauptstr.;Tirol",
    "iso:country":"AT",
    "sg:address":"Hauptstr. 55 ",
    "sg:city":"Zams",
    "sg:classifiers":[
        {
            "category":"Banks & Credit Unions",
            "subcategory":"Bank",
            "type":"Services"
        }
    ],
    "sg:phone":"+43 4354 42628570",
    "sg:postcode":"6511",
    "sg:province":"Tirol",
    "sg:tags":[
        "banking",
        "institution"
    ],
    "wof:name":"RAIFFEISENBANK OBERLAND REG. GESMBH",
    "wof:placetype":"venue"
},
  "geometry": {"coordinates":[10.5888004303,47.1586380005],"type":"Point"}
}