{
  "type": "Feature",
  "properties": {
    "addr:full":"Rechte Wienzeile 29/4 Wien Wien 1040",
    "addr:housenumber":"29 / 4",
    "addr:postcode":"1040",
    "addr:street":"Rechte Wienzeile",
    "iso:country":"AT",
    "sg:address":"Rechte Wienzeile 29/4",
    "sg:city":"Wien",
    "sg:classifiers":[
        {
            "category":"Professional",
            "subcategory":"Computer Services",
            "type":"Services"
        }
    ],
    "sg:phone":"+43 1 5851822",
    "sg:postcode":"1040",
    "sg:province":"Wien",
    "sg:tags":[
        "software"
    ],
    "wof:name":"e-seal Datenverarbeitung GmbH",
    "wof:placetype":"venue"
},
  "geometry": {"coordinates":[16.3617992401,48.1972045898],"type":"Point"}
}