{
  "type": "Feature",
  "properties": {
    "addr:full":"Steyrtalstr 18 Obergr\u00fcnburg Ober\u00f6sterreich 4593",
    "addr:housenumber":"18",
    "addr:postcode":"4593",
    "addr:street":"Steyrtalstr;Oberoesterreich",
    "iso:country":"AT",
    "sg:address":"Steyrtalstr 18",
    "sg:city":"Obergr\u00fcnburg",
    "sg:orig_category":"Tankstellen",
    "sg:phone":"+43 4372 577662",
    "sg:postcode":"4593",
    "sg:province":"Ober\u00f6sterreich",
    "wof:name":"Br\u00fcllmeir Bruno",
    "wof:placetype":"venue"
},
  "geometry": {"coordinates":[14.2542085648,47.9582939148],"type":"Point"}
}