{
  "type": "Feature",
  "properties": {
    "addr:full":"Tuchlauben 20 Wien Wien 1010",
    "addr:housenumber":"20",
    "addr:postcode":"1010",
    "addr:street":"Tuchlauben",
    "iso:country":"AT",
    "sg:address":"Tuchlauben 20",
    "sg:city":"Wien",
    "sg:orig_category":"Geschenkartikel",
    "sg:phone":"+43 1 5330465",
    "sg:postcode":"1010",
    "sg:province":"Wien",
    "wof:name":"Holz und Kunst",
    "wof:placetype":"venue"
},
  "geometry": {"coordinates":[16.3716068268,48.2107963562],"type":"Point"}
}