{
  "type": "Feature",
  "properties": {
    "addr:full":"B\u00e4ckerg 28A Wilfersdorf Nieder\u00f6sterreich 2193",
    "addr:housenumber":"28a",
    "addr:postcode":"2193",
    "addr:street":"Baeckerg",
    "iso:country":"AT",
    "sg:address":"B\u00e4ckerg 28A",
    "sg:city":"Wilfersdorf",
    "sg:orig_category":"Transportunternehmen",
    "sg:phone":"+43 2573 29870",
    "sg:postcode":"2193",
    "sg:province":"Nieder\u00f6sterreich",
    "wof:name":"Zobl Transportspedition GesmbH",
    "wof:placetype":"venue"
},
  "geometry": {"coordinates":[16.6654052734,48.5938606262],"type":"Point"}
}