{
  "type": "Feature",
  "properties": {
    "iso:country":"AT",
    "sg:address":"Roseng 1/2/7",
    "sg:city":"Lienz",
    "sg:orig_category":"Lebens- U Sozialberatung",
    "sg:phone":"+43 4348 5272851",
    "sg:postcode":"9900",
    "sg:province":"Tirol",
    "wof:name":"LSB-Netzwerk Jugend- u SozialbetreuungsgmbH",
    "wof:placetype":"venue"
},
  "geometry": {"coordinates":[12.7684783936,46.8281173706],"type":"Point"}
}