{
  "type": "Feature",
  "properties": {
    "addr:full":"Abt-Karl-Str 86 Melk Nieder\u00f6sterreich 3390",
    "addr:housenumber":"86",
    "addr:postcode":"3390",
    "addr:street":"Abt-Karl-Str",
    "iso:country":"AT",
    "sg:address":"Abt-Karl-Str 86",
    "sg:city":"Melk",
    "sg:orig_category":"Schlossereien",
    "sg:phone":"+43 2752 54652",
    "sg:postcode":"3390",
    "sg:province":"Nieder\u00f6sterreich",
    "wof:name":"Burgstaller Ferdinand",
    "wof:placetype":"venue"
},
  "geometry": {"coordinates":[15.3458356857,48.2227478027],"type":"Point"}
}