{
  "type": "Feature",
  "properties": {
    "addr:full":"Ringstr. 40  Rankweil Vorarlberg 6830",
    "addr:housenumber":"40",
    "addr:postcode":"6830",
    "addr:street":"Ringstr.",
    "iso:country":"AT",
    "sg:address":"Ringstr. 40 ",
    "sg:city":"Rankweil",
    "sg:classifiers":[
        {
            "category":"Shopping",
            "subcategory":"Clothing, Apparel, & Fashions",
            "type":"Retail Goods"
        }
    ],
    "sg:phone":"+43 4355 2242101",
    "sg:postcode":"6830",
    "sg:province":"Vorarlberg",
    "sg:tags":[
        "clothes"
    ],
    "wof:name":"SONDEREGGER TEXTIL GESMBH",
    "wof:placetype":"venue"
},
  "geometry": {"coordinates":[9.6460638046,47.2717628479],"type":"Point"}
}