{
  "type": "Feature",
  "properties": {
    "addr:full":"Grottenhofstr 34/IV Neuhart Steiermark 8053",
    "addr:housenumber":"34 / iv",
    "addr:postcode":"8053",
    "addr:street":"Grottenhofstr;Neuhart Steiermark",
    "iso:country":"AT",
    "sg:address":"Grottenhofstr 34/IV",
    "sg:city":"Neuhart",
    "sg:orig_category":"Farb-, Stil- U Typberatung",
    "sg:phone":"+43 4331 6284321",
    "sg:postcode":"8053",
    "sg:province":"Steiermark",
    "wof:name":"Machazek A Dorothea - meine Mode meine Idee",
    "wof:placetype":"venue"
},
  "geometry": {"coordinates":[15.3950767517,47.0450592041],"type":"Point"}
}