{
  "type": "Feature",
  "properties": {
    "addr:full":"Mauerbachstr 47 Wien Wien 1140",
    "addr:housenumber":"47",
    "addr:postcode":"1140",
    "addr:street":"Mauerbachstr",
    "iso:country":"AT",
    "sg:address":"Mauerbachstr 47",
    "sg:city":"Wien",
    "sg:classifiers":[
        {
            "category":"Restaurant",
            "type":"Food & Drink"
        }
    ],
    "sg:phone":"+43 4319 7910780",
    "sg:postcode":"1140",
    "sg:province":"Wien",
    "sg:website":"jaegerwirt.at",
    "wof:name":"J\u00e4gerwirt Inh Schmidmayer Rainer",
    "wof:placetype":"venue"
},
  "geometry": {"coordinates":[16.2193450928,48.216758728],"type":"Point"}
}