{
  "type": "Feature",
  "properties": {
    "addr:full":"Linzer Str 421 Wien Wien 1140",
    "addr:housenumber":"421",
    "addr:postcode":"1140",
    "addr:street":"Linzer Str",
    "iso:country":"AT",
    "sg:address":"Linzer Str 421",
    "sg:city":"Wien",
    "sg:orig_category":"Restaurants: Chinesisch",
    "sg:phone":"+43 4319 142620",
    "sg:postcode":"1140",
    "sg:province":"Wien",
    "wof:name":"Asia Restaurant-L421",
    "wof:placetype":"venue"
},
  "geometry": {"coordinates":[16.2551231384,48.2024688721],"type":"Point"}
}