{
  "type": "Feature",
  "properties": {
    "addr:full":"Villacher Str 1 Feistritz an der Drau K\u00e4rnten 9710",
    "addr:housenumber":"1",
    "addr:postcode":"9710",
    "addr:street":"Str",
    "iso:country":"AT",
    "sg:address":"Villacher Str 1",
    "sg:city":"Feistritz an der Drau",
    "sg:classifiers":[
        {
            "category":"Restaurant",
            "type":"Food & Drink"
        }
    ],
    "sg:phone":"+43 4342 452583",
    "sg:postcode":"9710",
    "sg:province":"K\u00e4rnten",
    "sg:tags":[
        "pizzeria"
    ],
    "wof:name":"Pizzeria DA FINDING",
    "wof:placetype":"venue"
},
  "geometry": {"coordinates":[13.66314888,46.7018623352],"type":"Point"}
}