{
  "type": "Feature",
  "properties": {
    "addr:full":"Hart 1 Altlengbach Nieder\u00f6sterreich 3033",
    "addr:housenumber":"1",
    "addr:postcode":"3033",
    "addr:street":"Hart",
    "iso:country":"AT",
    "sg:address":"Hart 1",
    "sg:city":"Altlengbach",
    "sg:classifiers":[
        {
            "category":"Shopping",
            "subcategory":"Hobbies, Toys, & Games",
            "type":"Retail Goods"
        }
    ],
    "sg:phone":"+43 2772 54759",
    "sg:postcode":"3033",
    "sg:province":"Nieder\u00f6sterreich",
    "sg:tags":[
        "baby",
        "infant",
        "toy",
        "toys"
    ],
    "sg:website":"matador.at",
    "wof:name":"MATADOR Spielwaren Ges.m.b.H.",
    "wof:placetype":"venue"
},
  "geometry": {"coordinates":[15.9252882004,48.1701431274],"type":"Point"}
}