{
  "type": "Feature",
  "properties": {
    "iso:country":"AT",
    "sg:address":"Mairbachweg 10",
    "sg:city":"Inzing",
    "sg:orig_category":"Stickereien",
    "sg:phone":"+43 5238 86328",
    "sg:postcode":"6401",
    "sg:province":"Tirol",
    "wof:name":"Springer Elke",
    "wof:placetype":"venue"
},
  "geometry": {"coordinates":[11.2036771774,47.2706336975],"type":"Point"}
}