{
  "type": "Feature",
  "properties": {
    "iso:country":"AT",
    "sg:address":"Weilhartstr 56",
    "sg:city":"Ostermiething",
    "sg:orig_category":"Elektroinstallationsunternehmen",
    "sg:phone":"+43 6278 63560",
    "sg:postcode":"5121",
    "sg:province":"Ober\u00f6sterreich",
    "wof:name":"Ulrich Franz",
    "wof:placetype":"venue"
},
  "geometry": {"coordinates":[12.8314800262,48.0432815552],"type":"Point"}
}