{
  "type": "Feature",
  "properties": {
    "addr:full":"Franzensg 25 Wien Wien 1050",
    "addr:housenumber":"25",
    "addr:postcode":"1050",
    "addr:street":"Franzensg",
    "iso:country":"AT",
    "sg:address":"Franzensg 25",
    "sg:city":"Wien",
    "sg:orig_category":"Unternehmensberatung",
    "sg:phone":"+43 664 2092460",
    "sg:postcode":"1050",
    "sg:province":"Wien",
    "wof:name":"Haberfellner Reinhard Dipl-Ing",
    "wof:placetype":"venue"
},
  "geometry": {"coordinates":[16.3585529327,48.1959342957],"type":"Point"}
}