{
  "type": "Feature",
  "properties": {
    "addr:full":"Nr 317 Spital am Pyhrn Ober\u00f6sterreich 4582",
    "addr:postcode":"4582",
    "addr:street":"Nr 317",
    "iso:country":"AT",
    "sg:address":"Nr 317",
    "sg:city":"Spital am Pyhrn",
    "sg:orig_category":"Pensionen / Privatzimmer",
    "sg:phone":"+43 4375 63313",
    "sg:postcode":"4582",
    "sg:province":"Ober\u00f6sterreich",
    "wof:name":"Baumschlager Christine",
    "wof:placetype":"venue"
},
  "geometry": {"coordinates":[14.3418207169,47.6654434204],"type":"Point"}
}