{
  "type": "Feature",
  "properties": {
    "addr:full":"Morzger Str 73 Salzburg Salzburg 5020",
    "addr:housenumber":"73",
    "addr:postcode":"5020",
    "addr:street":"Str;Salzburg",
    "iso:country":"AT",
    "sg:address":"Morzger Str 73",
    "sg:city":"Salzburg",
    "sg:orig_category":"\u00c3\u201erzte / F Allgemeinmedizin",
    "sg:phone":"+43 662 820967",
    "sg:postcode":"5020",
    "sg:province":"Salzburg",
    "wof:name":"Gr\u00e4ff Peter Dr",
    "wof:placetype":"venue"
},
  "geometry": {"coordinates":[13.0587387085,47.7692070007],"type":"Point"}
}