{
  "type": "Feature",
  "properties": {
    "iso:country":"AT",
    "sg:address":"\u00f6d 6",
    "sg:city":"Kirnberg an der Mank",
    "sg:orig_category":"Holzbau",
    "sg:phone":"+43 4327 558088",
    "sg:postcode":"3241",
    "sg:province":"Nieder\u00f6sterreich",
    "sg:website":"naturi.at",
    "wof:name":"Holzsystembau Georg Ganaus",
    "wof:placetype":"venue"
},
  "geometry": {"coordinates":[15.3218803406,48.0697402954],"type":"Point"}
}