{
  "type": "Feature",
  "properties": {
    "addr:full":"Leopold-Loibl-Str 4 Korneuburg Nieder\u00f6sterreich 2100",
    "addr:housenumber":"4",
    "addr:postcode":"2100",
    "addr:street":"Leopold-Loibl-Str;Niederoesterreich",
    "iso:country":"AT",
    "sg:address":"Leopold-Loibl-Str 4",
    "sg:city":"Korneuburg",
    "sg:orig_category":"Reifen U Reifendienste",
    "sg:phone":"+43 4322 6272983",
    "sg:postcode":"2100",
    "sg:province":"Nieder\u00f6sterreich",
    "wof:name":"Mitiszek Reifenhandels GesmbH",
    "wof:placetype":"venue"
},
  "geometry": {"coordinates":[16.3351287842,48.3518333435],"type":"Point"}
}