{
  "type": "Feature",
  "properties": {
    "addr:full":"Lindeng 30 Wien Wien 1070",
    "addr:housenumber":"30",
    "addr:postcode":"1070",
    "addr:street":"Lindeng",
    "iso:country":"AT",
    "sg:address":"Lindeng 30",
    "sg:city":"Wien",
    "sg:orig_category":"Messerschmiede, Stahlwaren",
    "sg:phone":"+43 1 5231047",
    "sg:postcode":"1070",
    "sg:province":"Wien",
    "wof:name":"Musick Franz",
    "wof:placetype":"venue"
},
  "geometry": {"coordinates":[16.3508758545,48.2003135681],"type":"Point"}
}