{
  "type": "Feature",
  "properties": {
    "iso:country":"AT",
    "sg:address":"Krottenbachstr 56",
    "sg:city":"Wien",
    "sg:orig_category":"Elektroinstallationsunternehmen",
    "sg:phone":"+43 1 3683565",
    "sg:postcode":"1190",
    "sg:province":"Wien",
    "wof:name":"Elektro Wolschansky GesmbH",
    "wof:placetype":"venue"
},
  "geometry": {"coordinates":[16.3360710144,48.2405471802],"type":"Point"}
}