{
  "type": "Feature",
  "properties": {
    "iso:country":"AT",
    "sg:address":"Lindauer G 40",
    "sg:city":"Wien",
    "sg:orig_category":"Finanz- U Wirtschaftsberatung",
    "sg:phone":"+43 4369 910696377",
    "sg:postcode":"1230",
    "sg:province":"Wien",
    "wof:name":"Kern Hellwig",
    "wof:placetype":"venue"
},
  "geometry": {"coordinates":[16.258600235,48.1438751221],"type":"Point"}
}