{
  "type": "Feature",
  "properties": {
    "iso:country":"AT",
    "sg:address":"Sportplatzg 1-3",
    "sg:city":"Rohrbach",
    "sg:orig_category":"Schneidemaschinen",
    "sg:phone":"+43 4326 2663058",
    "sg:postcode":"7222",
    "sg:province":"Burgenland",
    "wof:name":"Duroflex Grafl GesmbH",
    "wof:placetype":"venue"
},
  "geometry": {"coordinates":[16.423002243,47.7082862854],"type":"Point"}
}