{
  "type": "Feature",
  "properties": {
    "iso:country":"AT",
    "sg:address":"Dr.-Natterer-G 2-4/4",
    "sg:city":"Wien",
    "sg:orig_category":"Behinderungen / Leben Mit Behinderungen",
    "sg:phone":"+43 1 7261021",
    "sg:postcode":"1020",
    "sg:province":"Wien",
    "wof:name":"Jugend am Werk",
    "wof:placetype":"venue"
},
  "geometry": {"coordinates":[16.3802642822,48.2153701782],"type":"Point"}
}