{
  "type": "Feature",
  "properties": {
    "addr:full":"Fesslers 13 Hohenweiler Vorarlberg 6914",
    "addr:housenumber":"13",
    "addr:postcode":"6914",
    "addr:street":"Fesslers",
    "iso:country":"AT",
    "sg:address":"Fesslers 13",
    "sg:city":"Hohenweiler",
    "sg:orig_category":"Juweliere, Gold- U Silberschmiede",
    "sg:phone":"+43 4355 7382143",
    "sg:postcode":"6914",
    "sg:province":"Vorarlberg",
    "wof:name":"OGA Atelier Galehr Otto",
    "wof:placetype":"venue"
},
  "geometry": {"coordinates":[9.7720413208,47.573513031],"type":"Point"}
}