{
  "type": "Feature",
  "properties": {
    "addr:full":"Walter-Siemer-Str. 4 Mondsee Ober\u00f6sterreich 5310",
    "addr:housenumber":"4",
    "addr:postcode":"5310",
    "addr:street":"Walter-Siemer-Str.;Oberoesterreich",
    "iso:country":"AT",
    "sg:address":"Walter-Siemer-Str. 4",
    "sg:city":"Mondsee",
    "sg:classifiers":[
        {
            "category":"Manufacturing",
            "subcategory":"Tools & Machinery",
            "type":"Manufacturing & Wholesale Goods"
        }
    ],
    "sg:phone":"+43 4362 325011",
    "sg:postcode":"5310",
    "sg:province":"Ober\u00f6sterreich",
    "sg:tags":[
        "environment",
        "equipment",
        "-"
    ],
    "wof:name":"BWT AG",
    "wof:placetype":"venue"
},
  "geometry": {"coordinates":[13.3331365585,47.8625793457],"type":"Point"}
}