{
  "type": "Feature",
  "properties": {
    "addr:full":"Deningfeld 424 Neukirchen am Gro\u00dfvenediger Salzburg 5741",
    "addr:housenumber":"424",
    "addr:postcode":"5741",
    "addr:street":"Salzburg",
    "iso:country":"AT",
    "sg:address":"Deningfeld 424",
    "sg:city":"Neukirchen am Gro\u00dfvenediger",
    "sg:orig_category":"Lebensmittel / Einzelhandel",
    "sg:phone":"+43 4365 652090",
    "sg:postcode":"5741",
    "sg:province":"Salzburg",
    "wof:name":"Billa AG",
    "wof:placetype":"venue"
},
  "geometry": {"coordinates":[12.2779550552,47.2535400391],"type":"Point"}
}