{
  "type": "Feature",
  "properties": {
    "addr:full":"Sankt Oswald bei Plankenwarth 86 St. Oswald Steiermark 8113",
    "addr:housenumber":"86",
    "addr:postcode":"8113",
    "addr:street":"Bei Plankenwarth",
    "iso:country":"AT",
    "sg:address":"Sankt Oswald bei Plankenwarth 86",
    "sg:city":"St. Oswald",
    "sg:classifiers":[
        {
            "category":"Home & Garden",
            "subcategory":"Building Materials",
            "type":"Retail Goods"
        }
    ],
    "sg:phone":"+43 3137 27288",
    "sg:postcode":"8113",
    "sg:province":"Steiermark",
    "sg:tags":[
        "steel",
        "balcony"
    ],
    "wof:name":"Fallend GmbH & Co KG",
    "wof:placetype":"venue"
},
  "geometry": {"coordinates":[15.2193155289,47.1025161743],"type":"Point"}
}