{
  "type": "Feature",
  "properties": {
    "addr:full":"Nr 37 Neukirchen Ober\u00f6sterreich 4671",
    "addr:postcode":"4671",
    "addr:street":"Nr 37",
    "iso:country":"AT",
    "sg:address":"Nr 37",
    "sg:city":"Neukirchen",
    "sg:orig_category":"Waren Aller Art",
    "sg:phone":"+43 4372 4527225",
    "sg:postcode":"4671",
    "sg:province":"Ober\u00f6sterreich",
    "wof:name":"St\u00f6ttinger Johann Ing GesmbH",
    "wof:placetype":"venue"
},
  "geometry": {"coordinates":[13.8145751953,48.0997619629],"type":"Point"}
}