{
  "type": "Feature",
  "properties": {
    "addr:full":"Linzer Str 34 Marchtrenk Ober\u00f6sterreich 4614",
    "addr:housenumber":"34",
    "addr:postcode":"4614",
    "addr:street":"Linzer Str",
    "iso:country":"AT",
    "sg:address":"Linzer Str 34",
    "sg:city":"Marchtrenk",
    "sg:orig_category":"Fotografen",
    "sg:phone":"+43 7243 524790",
    "sg:postcode":"4614",
    "sg:province":"Ober\u00f6sterreich",
    "wof:name":"Holzinger GmbH",
    "wof:placetype":"venue"
},
  "geometry": {"coordinates":[14.11439991,48.1905784607],"type":"Point"}
}