{
  "type": "Feature",
  "properties": {
    "addr:full":"Kirchbergg 33-35 Wien Wien 1070",
    "addr:postcode":"33-35;1070",
    "iso:country":"AT",
    "sg:address":"Kirchbergg 33-35",
    "sg:city":"Wien",
    "sg:orig_category":"Personalbereitstellung",
    "sg:phone":"+43 4315 240512",
    "sg:postcode":"1070",
    "sg:province":"Wien",
    "wof:name":"MANPOWER Personalservice GmbH",
    "wof:placetype":"venue"
},
  "geometry": {"coordinates":[16.3554210663,48.2046165466],"type":"Point"}
}