{
  "type": "Feature",
  "properties": {
    "addr:full":"Geblerg 57 Wien Wien 1170",
    "addr:housenumber":"57",
    "addr:postcode":"1170",
    "addr:street":"Geblerg",
    "iso:country":"AT",
    "sg:address":"Geblerg 57",
    "sg:city":"Wien",
    "sg:orig_category":"Immobilienverwaltungen",
    "sg:phone":"+43 1 4063515",
    "sg:postcode":"1170",
    "sg:province":"Wien",
    "wof:name":"Lintner Dr Eva und Doris Lintner KEG",
    "wof:placetype":"venue"
},
  "geometry": {"coordinates":[16.332277298,48.2163276672],"type":"Point"}
}