{
  "type": "Feature",
  "properties": {
    "addr:full":"Hauptstr. 103 Breitenfurt Nieder\u00f6sterreich 2384",
    "addr:housenumber":"103",
    "addr:postcode":"2384",
    "addr:street":"Hauptstr.",
    "iso:country":"AT",
    "sg:address":"Hauptstr. 103",
    "sg:city":"Breitenfurt",
    "sg:classifiers":[
        {
            "category":"Shopping",
            "subcategory":"Computers & Home Electronics",
            "type":"Retail Goods"
        }
    ],
    "sg:phone":"+43 4322 392721",
    "sg:postcode":"2384",
    "sg:province":"Nieder\u00f6sterreich",
    "sg:tags":[
        "electronic",
        "electrical",
        "equipment"
    ],
    "wof:name":"KOLARZ-LEUCHTEN GMBH",
    "wof:placetype":"venue"
},
  "geometry": {"coordinates":[16.1906681061,48.1353302002],"type":"Point"}
}