{
  "type": "Feature",
  "properties": {
    "addr:full":"Nr 66a Mathon Tirol 6562",
    "addr:housenumber":"66a",
    "addr:postcode":"6562",
    "addr:street":"Nr",
    "iso:country":"AT",
    "sg:address":"Nr 66a",
    "sg:city":"Mathon",
    "sg:orig_category":"Appartements / Ferienwohnungen",
    "sg:phone":"+43 5444 5626",
    "sg:postcode":"6562",
    "sg:province":"Tirol",
    "wof:name":"Haus Dominika",
    "wof:placetype":"venue"
},
  "geometry": {"coordinates":[10.2449302673,46.9883995056],"type":"Point"}
}