{
  "type": "Feature",
  "properties": {
    "addr:full":"Widumweg 4 Schruns Vorarlberg 6780",
    "addr:housenumber":"4",
    "addr:postcode":"6780",
    "addr:street":"Widumweg",
    "iso:country":"AT",
    "sg:address":"Widumweg 4",
    "sg:city":"Schruns",
    "sg:orig_category":"Dolmetscher",
    "sg:phone":"+43 4355 5673793",
    "sg:postcode":"6780",
    "sg:province":"Vorarlberg",
    "wof:name":"Neyer Colette Dipl-Dolm Mag",
    "wof:placetype":"venue"
},
  "geometry": {"coordinates":[9.9227018356,47.0753097534],"type":"Point"}
}