{
  "type": "Feature",
  "properties": {
    "iso:country":"AT",
    "sg:address":"Hauptstr 28",
    "sg:city":"Judenau",
    "sg:orig_category":"Volksschulen",
    "sg:phone":"+43 4322 747271",
    "sg:postcode":"3441",
    "sg:province":"Nieder\u00f6sterreich",
    "wof:name":"Volksschule Judenau-Baumgarten",
    "wof:placetype":"venue"
},
  "geometry": {"coordinates":[16.0288906097,48.2823905945],"type":"Point"}
}