{
  "type": "Feature",
  "properties": {
    "addr:full":"Gaisbergstr 46 Salzburg Salzburg 5020",
    "addr:housenumber":"46",
    "addr:postcode":"5020",
    "addr:street":"Gaisbergstr;Salzburg",
    "iso:country":"AT",
    "sg:address":"Gaisbergstr 46",
    "sg:city":"Salzburg",
    "sg:orig_category":"Immobilienmakler",
    "sg:phone":"+43 4366 263963",
    "sg:postcode":"5020",
    "sg:province":"Salzburg",
    "wof:name":"Fondachhof Verm\u00f6gens- u Beteiligungs GmbH",
    "wof:placetype":"venue"
},
  "geometry": {"coordinates":[13.0770425797,47.802406311],"type":"Point"}
}