{
  "type": "Feature",
  "properties": {
    "addr:full":"Villacher Str 161 Klagenfurt K\u00e4rnten 9020",
    "addr:housenumber":"161",
    "addr:postcode":"9020",
    "addr:street":"Str;Kaernten",
    "iso:country":"AT",
    "sg:address":"Villacher Str 161",
    "sg:city":"Klagenfurt",
    "sg:orig_category":"Fernsehservice",
    "sg:phone":"+43 4346 324244022",
    "sg:postcode":"9020",
    "sg:province":"K\u00e4rnten",
    "sg:website":"klaus-elektronik.at",
    "wof:name":"KLAUS ELEKTRONIK Service u VertriebsgesmbH & Co KG",
    "wof:placetype":"venue"
},
  "geometry": {"coordinates":[14.2788639069,46.6196022034],"type":"Point"}
}