{
  "type": "Feature",
  "properties": {
    "addr:full":"Roseggerstr 6 Amstetten Nieder\u00f6sterreich 3300",
    "addr:housenumber":"6",
    "addr:postcode":"3300",
    "addr:street":"Roseggerstr;Niederoesterreich",
    "iso:country":"AT",
    "sg:address":"Roseggerstr 6",
    "sg:city":"Amstetten",
    "sg:orig_category":"Maler, Anstreicher U Lackierer",
    "sg:phone":"+43 7472 62751",
    "sg:postcode":"3300",
    "sg:province":"Nieder\u00f6sterreich",
    "wof:name":"Friedl Andreas",
    "wof:placetype":"venue"
},
  "geometry": {"coordinates":[14.8717279434,48.1202697754],"type":"Point"}
}