{
  "type": "Feature",
  "properties": {
    "addr:full":"Nr 87-88 Maurach Tirol 6212",
    "addr:postcode":"6212",
    "addr:street":"Nr;Maurach Tirol",
    "iso:country":"AT",
    "sg:address":"Nr 87-88",
    "sg:city":"Maurach",
    "sg:classifiers":[
        {
            "category":"Travel",
            "subcategory":"Hotels & Motels",
            "type":"Entertainment"
        }
    ],
    "sg:phone":"+43 5243 5495",
    "sg:postcode":"6212",
    "sg:province":"Tirol",
    "wof:name":"Hotel Klingler",
    "wof:placetype":"venue"
},
  "geometry": {"coordinates":[11.7518672943,47.4225006104],"type":"Point"}
}