{
  "type": "Feature",
  "properties": {
    "addr:full":"Oberlaaer Str 371 Wien Wien 1230",
    "addr:housenumber":"371",
    "addr:postcode":"1230",
    "iso:country":"AT",
    "sg:address":"Oberlaaer Str 371",
    "sg:city":"Wien",
    "sg:orig_category":"Garten- U Landschaftsgestaltung",
    "sg:phone":"+43 1 6885149",
    "sg:postcode":"1230",
    "sg:province":"Wien",
    "wof:name":"Sterlich Erhard GesmbH",
    "wof:placetype":"venue"
},
  "geometry": {"coordinates":[16.35663414,48.1493835449],"type":"Point"}
}