{
  "type": "Feature",
  "properties": {
    "addr:full":"Obere Marktstr. 31 Etsdorf am Kamp Nieder\u00f6sterreich 3492",
    "addr:housenumber":"31",
    "addr:postcode":"3492",
    "addr:street":"Obere Marktstr.;Niederoesterreich",
    "iso:country":"AT",
    "sg:address":"Obere Marktstr. 31",
    "sg:city":"Etsdorf am Kamp",
    "sg:classifiers":[
        {
            "category":"Home & Garden",
            "subcategory":"Home Furnishings",
            "type":"Retail Goods"
        }
    ],
    "sg:phone":"+43 4327 352871",
    "sg:postcode":"3492",
    "sg:province":"Nieder\u00f6sterreich",
    "sg:tags":[
        "household"
    ],
    "wof:name":"M\u00d6BELWERKST\u00c4TTEN GES.MBH",
    "wof:placetype":"venue"
},
  "geometry": {"coordinates":[15.7446517944,48.4468955994],"type":"Point"}
}