{
  "type": "Feature",
  "properties": {
    "addr:full":"Bundesstr 114a Landeck Tirol 6500",
    "addr:housenumber":"114a",
    "addr:postcode":"6500",
    "addr:street":"Landeck Tirol",
    "iso:country":"AT",
    "sg:address":"Bundesstr 114a",
    "sg:city":"Landeck",
    "sg:orig_category":"Autohandel",
    "sg:phone":"+43 4354 42634200",
    "sg:postcode":"6500",
    "sg:province":"Tirol",
    "wof:name":"Maschler Karl - Mitsubishi - Seat",
    "wof:placetype":"venue"
},
  "geometry": {"coordinates":[10.6277132034,47.1200027466],"type":"Point"}
}