{
  "type": "Feature",
  "properties": {
    "addr:full":"Barichg 20/2 Wien Wien 1030",
    "addr:housenumber":"20 / 2",
    "addr:postcode":"1030",
    "addr:street":"Barichg",
    "iso:country":"AT",
    "sg:address":"Barichg 20/2",
    "sg:city":"Wien",
    "sg:orig_category":"\u00c3\u201erzte / F Allgemeinmedizin",
    "sg:phone":"+43 1 7130366",
    "sg:postcode":"1030",
    "sg:province":"Wien",
    "wof:name":"Alazzawi Eva Dr",
    "wof:placetype":"venue"
},
  "geometry": {"coordinates":[16.3914737701,48.1972923279],"type":"Point"}
}