{
  "type": "Feature",
  "properties": {
    "iso:country":"AT",
    "sg:address":"Leitnerstrasse 660",
    "sg:city":"Puch",
    "sg:orig_category":"Apparatus, Containers, Tanks, Vessels, And Boilers Of Stainless Steel",
    "sg:phone":"+43 6245 84421",
    "sg:postcode":"5412",
    "sg:province":"Salzburg",
    "sg:website":"edelstahl.co.at",
    "wof:name":"Metallbau - Schlosserei Schrattenecker Ges.m.b.H.",
    "wof:placetype":"venue"
},
  "geometry": {"coordinates":[13.0951023102,47.7187614441],"type":"Point"}
}