{
  "type": "Feature",
  "properties": {
    "addr:full":"Obermitterdorf 53 Ruden K\u00e4rnten 9113",
    "addr:housenumber":"53",
    "addr:postcode":"9113",
    "addr:street":"Obermitterdorf;Kaernten",
    "iso:country":"AT",
    "sg:address":"Obermitterdorf 53",
    "sg:city":"Ruden",
    "sg:classifiers":[
        {
            "category":"Home & Garden",
            "subcategory":"Building Materials",
            "type":"Retail Goods"
        }
    ],
    "sg:phone":"+43 4234 729",
    "sg:postcode":"9113",
    "sg:province":"K\u00e4rnten",
    "sg:tags":[
        "banister"
    ],
    "wof:name":"Josef Satler",
    "wof:placetype":"venue"
},
  "geometry": {"coordinates":[14.7703266144,46.6569061279],"type":"Point"}
}