{
  "type": "Feature",
  "properties": {
    "addr:full":"Hauptschulstr 2 Landskron K\u00e4rnten 9523",
    "addr:housenumber":"2",
    "addr:postcode":"9523",
    "addr:street":"Hauptschulstr;Kaernten",
    "iso:country":"AT",
    "sg:address":"Hauptschulstr 2",
    "sg:city":"Landskron",
    "sg:orig_category":"Tankstellen",
    "sg:phone":"+43 4242 41924",
    "sg:postcode":"9523",
    "sg:province":"K\u00e4rnten",
    "wof:name":"BP Austria Marketing GmbH",
    "wof:placetype":"venue"
},
  "geometry": {"coordinates":[13.879904747,46.627658844],"type":"Point"}
}