{
  "type": "Feature",
  "properties": {
    "iso:country":"AT",
    "sg:address":"Farrendorfer Str 34",
    "sg:city":"Velden am W\u00f6rther See",
    "sg:orig_category":"Fenster",
    "sg:phone":"+43 4342 7452991",
    "sg:postcode":"9220",
    "sg:province":"K\u00e4rnten",
    "wof:name":"Lippitsch Stefan",
    "wof:placetype":"venue"
},
  "geometry": {"coordinates":[14.010477066,46.6236000061],"type":"Point"}
}