{
  "type": "Feature",
  "properties": {
    "addr:full":"Marschallg 28 Graz Steiermark 8020",
    "addr:housenumber":"28",
    "addr:postcode":"8020",
    "addr:street":"Marschallg",
    "iso:country":"AT",
    "sg:address":"Marschallg 28",
    "sg:city":"Graz",
    "sg:orig_category":"Schneidereien",
    "sg:phone":"+43 316 717576",
    "sg:postcode":"8020",
    "sg:province":"Steiermark",
    "wof:name":"Oswald Peter",
    "wof:placetype":"venue"
},
  "geometry": {"coordinates":[15.430729866,47.0730209351],"type":"Point"}
}