{
  "type": "Feature",
  "properties": {
    "addr:full":"Ferihumerstr 15 Linz Ober\u00f6sterreich 4040",
    "addr:housenumber":"15",
    "addr:postcode":"4040",
    "addr:street":"Ferihumerstr",
    "iso:country":"AT",
    "sg:address":"Ferihumerstr 15",
    "sg:city":"Linz",
    "sg:orig_category":"Datenverarbeitung",
    "sg:phone":"+43 732 7172150",
    "sg:postcode":"4040",
    "sg:province":"Ober\u00f6sterreich",
    "wof:name":"twyn group IT solutions & marketing services AG",
    "wof:placetype":"venue"
},
  "geometry": {"coordinates":[14.2865495682,48.3129615784],"type":"Point"}
}