{
  "type": "Feature",
  "properties": {
    "addr:full":"R\u00f6mersteinbruch St. Margarethen im Burgenland Burgenland 7062",
    "addr:postcode":"7062",
    "iso:country":"AT",
    "sg:address":"R\u00f6mersteinbruch",
    "sg:city":"St. Margarethen im Burgenland",
    "sg:classifiers":[
        {
            "category":"Shopping",
            "subcategory":"Gifts & Souvenirs",
            "type":"Retail Goods"
        }
    ],
    "sg:phone":"+43 4326 8021880",
    "sg:postcode":"7062",
    "sg:province":"Burgenland",
    "wof:name":"Gossy Reinhard",
    "wof:placetype":"venue"
},
  "geometry": {"coordinates":[16.6361446381,47.8017196655],"type":"Point"}
}