{
  "type": "Feature",
  "properties": {
    "addr:full":"Garteng Gleisdorf Steiermark 8200",
    "addr:postcode":"8200",
    "iso:country":"AT",
    "sg:address":"Garteng",
    "sg:city":"Gleisdorf",
    "sg:orig_category":"Sportanlagen",
    "sg:phone":"+43 3112 2601610",
    "sg:postcode":"8200",
    "sg:province":"Steiermark",
    "wof:name":"Eislaufplatz",
    "wof:placetype":"venue"
},
  "geometry": {"coordinates":[15.7102622986,47.100605011],"type":"Point"}
}