{
  "type": "Feature",
  "properties": {
    "addr:full":"Lemb\u00f6ckg. 51  1234",
    "addr:housenumber":"51",
    "addr:postcode":"1234",
    "addr:street":"Lemboeckg.",
    "iso:country":"AT",
    "sg:address":"Lemb\u00f6ckg. 51 ",
    "sg:classifiers":[
        {
            "category":"Manufacturing",
            "subcategory":"Metals",
            "type":"Manufacturing & Wholesale Goods"
        }
    ],
    "sg:phone":"+43 4318 651721",
    "sg:postcode":"1234",
    "sg:tags":[
        "processing"
    ],
    "wof:name":"BEWEHRUNGSSTAHL GESMBH",
    "wof:placetype":"venue"
},
  "geometry": {"coordinates":[16.2934799194,48.1539306641],"type":"Point"}
}