{
  "type": "Feature",
  "properties": {
    "addr:full":"Forstnerweg 6 Rottenegg Ober\u00f6sterreich 4112",
    "addr:housenumber":"6",
    "addr:postcode":"4112",
    "addr:street":"Forstnerweg;Oberoesterreich",
    "iso:country":"AT",
    "sg:address":"Forstnerweg 6",
    "sg:city":"Rottenegg",
    "sg:orig_category":"Plakatierungsunternehmen",
    "sg:phone":"+43 4372 3488000",
    "sg:postcode":"4112",
    "sg:province":"Ober\u00f6sterreich",
    "wof:name":"Foelser Gerhard",
    "wof:placetype":"venue"
},
  "geometry": {"coordinates":[14.1310148239,48.3719367981],"type":"Point"}
}