{
  "type": "Feature",
  "properties": {
    "iso:country":"AT",
    "sg:address":"Untere Donaustrasse 29",
    "sg:city":"Wien",
    "sg:classifiers":[
        {
            "category":"Organizations",
            "subcategory":"Community Association",
            "type":"Services"
        }
    ],
    "sg:phone":"+43 1 2143269",
    "sg:postcode":"1020",
    "sg:province":"Wien",
    "sg:tags":[
        "box",
        "cardboard"
    ],
    "sg:website":"horn-karton.at",
    "wof:name":"Horn Kartonagen GmbH",
    "wof:placetype":"venue"
},
  "geometry": {"coordinates":[16.385509491,48.2130584717],"type":"Point"}
}