{
  "type": "Feature",
  "properties": {
    "addr:full":"Maria-Theresia-Str 8 Altm\u00fcnster Ober\u00f6sterreich 4813",
    "addr:housenumber":"8",
    "addr:postcode":"4813",
    "addr:street":"Maria-Theresia-Str;Oberoesterreich",
    "iso:country":"AT",
    "sg:address":"Maria-Theresia-Str 8",
    "sg:city":"Altm\u00fcnster",
    "sg:orig_category":"Lebensmittel / Einzelhandel",
    "sg:phone":"+43 7612879560",
    "sg:postcode":"4813",
    "sg:province":"Ober\u00f6sterreich",
    "wof:name":"Unimarkt HandelsgesmbH & Co KG",
    "wof:placetype":"venue"
},
  "geometry": {"coordinates":[13.7599725723,47.8975830078],"type":"Point"}
}