{
  "type": "Feature",
  "properties": {
    "addr:full":"Faistauerg 5 Salzburg Salzburg 5020",
    "addr:housenumber":"5",
    "addr:postcode":"5020",
    "addr:street":"Faistauerg;Salzburg",
    "iso:country":"AT",
    "sg:address":"Faistauerg 5",
    "sg:city":"Salzburg",
    "sg:orig_category":"Weiterbildungsinstitute M Allg U Berufl Bildungsangebot",
    "sg:phone":"+43 800 202081",
    "sg:postcode":"5020",
    "sg:province":"Salzburg",
    "wof:name":"Education Agency -Schaffer Ingeborg",
    "wof:placetype":"venue"
},
  "geometry": {"coordinates":[13.0654296875,47.7903213501],"type":"Point"}
}