{
  "type": "Feature",
  "properties": {
    "iso:country":"AT",
    "sg:address":"Marktstr 3",
    "sg:city":"Eisenstadt",
    "sg:orig_category":"Ingenieurkonsulenten / Zivilingenieure",
    "sg:phone":"+43 2682 704420",
    "sg:postcode":"7000",
    "sg:province":"Burgenland",
    "sg:website":"vwe.at",
    "wof:name":"Vasko-Woschitz Engineering ZiviltechnikergesmbH",
    "wof:placetype":"venue"
},
  "geometry": {"coordinates":[16.5320110321,47.8292007446],"type":"Point"}
}