{
  "type": "Feature",
  "properties": {
    "iso:country":"AT",
    "sg:address":"Salzburger Str 32 M4 W\u00f6rgl",
    "sg:city":"W\u00f6rgl",
    "sg:orig_category":"Tabaktrafiken",
    "sg:phone":"+43 4353 3273278",
    "sg:postcode":"6300",
    "sg:province":"Tirol",
    "wof:name":"Weiss Helga",
    "wof:placetype":"venue"
},
  "geometry": {"coordinates":[-69.3131027222,-51.6091995239],"type":"Point"}
}