{
  "type": "Feature",
  "properties": {
    "addr:full":"Michaelerpl 13 Steyr Ober\u00f6sterreich 4400",
    "addr:housenumber":"13",
    "addr:postcode":"4400",
    "addr:street":"Michaelerpl;Oberoesterreich",
    "iso:country":"AT",
    "sg:address":"Michaelerpl 13",
    "sg:city":"Steyr",
    "sg:orig_category":"Spielwaren U Spiele",
    "sg:phone":"+43 4372 5276795",
    "sg:postcode":"4400",
    "sg:province":"Ober\u00f6sterreich",
    "wof:name":"Schnaubelt Bernhard",
    "wof:placetype":"venue"
},
  "geometry": {"coordinates":[14.4217910767,48.0429763794],"type":"Point"}
}