{
  "type": "Feature",
  "properties": {
    "addr:full":"Schwarzenbergpl 7 Wien Wien 1030",
    "addr:housenumber":"7",
    "addr:postcode":"1030",
    "addr:street":"Schwarzenbergpl",
    "iso:country":"AT",
    "sg:address":"Schwarzenbergpl 7",
    "sg:city":"Wien",
    "sg:orig_category":"Abfallentsorgung U -Verwertung",
    "sg:phone":"+43 1 71241050",
    "sg:postcode":"1030",
    "sg:province":"Wien",
    "wof:name":"Dumag Brennertechnologie GesmbH",
    "wof:placetype":"venue"
},
  "geometry": {"coordinates":[16.3768882751,48.1988182068],"type":"Point"}
}