{
  "type": "Feature",
  "properties": {
    "iso:country":"AT",
    "sg:address":"Nr 67",
    "sg:city":"St. Georgen ob Murau",
    "sg:orig_category":"Pensionen / Privatzimmer",
    "sg:phone":"+43 3537 2580",
    "sg:postcode":"8861",
    "sg:province":"Steiermark",
    "sg:website":"www.zechnerhof.at",
    "wof:name":"Zechnerhof",
    "wof:placetype":"venue"
},
  "geometry": {"coordinates":[14.0995817184,47.1049461365],"type":"Point"}
}