{
  "type": "Feature",
  "properties": {
    "iso:country":"AT",
    "sg:address":"Neuer Markt 1",
    "sg:city":"Zwettl",
    "sg:orig_category":"Versicherungsunternehmen",
    "sg:phone":"+43 2822 52227",
    "sg:postcode":"3910",
    "sg:province":"Nieder\u00f6sterreich",
    "wof:name":"Donau Versicherung",
    "wof:placetype":"venue"
},
  "geometry": {"coordinates":[15.168088913,48.6065101624],"type":"Point"}
}