{
  "type": "Feature",
  "properties": {
    "addr:full":"Jahnstr 10-12 F\u00fcrstenfeld Steiermark 8280",
    "addr:housenumber":"10-12",
    "addr:postcode":"8280",
    "addr:street":"Fuerstenfeld Steiermark",
    "iso:country":"AT",
    "sg:address":"Jahnstr 10-12",
    "sg:city":"F\u00fcrstenfeld",
    "sg:orig_category":"Elektronische Bauelemente U Bauteile",
    "sg:phone":"+43 3382 537800",
    "sg:postcode":"8280",
    "sg:province":"Steiermark",
    "wof:name":"TECWINGS F\u00fcrstenfeld Elektronikproduktion GmbH",
    "wof:placetype":"venue"
},
  "geometry": {"coordinates":[16.0858306885,47.0384902954],"type":"Point"}
}