{
  "type": "Feature",
  "properties": {
    "addr:full":"Poysbrunner Str 6a Herrnbaumgarten Nieder\u00f6sterreich 2171",
    "addr:housenumber":"6a",
    "addr:postcode":"2171",
    "addr:street":"Str",
    "iso:country":"AT",
    "sg:address":"Poysbrunner Str 6a",
    "sg:city":"Herrnbaumgarten",
    "sg:orig_category":"Blumeneinzelhandel",
    "sg:phone":"+43 2555 2346",
    "sg:postcode":"2171",
    "sg:province":"Nieder\u00f6sterreich",
    "wof:name":"Bayer Eduard",
    "wof:placetype":"venue"
},
  "geometry": {"coordinates":[16.6806926727,48.6982307434],"type":"Point"}
}