{
  "type": "Feature",
  "properties": {
    "addr:full":"Elisabethstr 40/3 Salzburg Salzburg 5020",
    "addr:housenumber":"40 / 3",
    "addr:postcode":"5020",
    "addr:street":"Elisabethstr;Salzburg",
    "iso:country":"AT",
    "sg:address":"Elisabethstr 40/3",
    "sg:city":"Salzburg",
    "sg:orig_category":"Bekleidung / Einzelhandel",
    "sg:phone":"+43 662 453038",
    "sg:postcode":"5020",
    "sg:province":"Salzburg",
    "wof:name":"Toni's Moden Demirtas KEG",
    "wof:placetype":"venue"
},
  "geometry": {"coordinates":[13.0446081161,47.8180923462],"type":"Point"}
}