{
  "type": "Feature",
  "properties": {
    "iso:country":"AT",
    "sg:address":"Bachweg 6",
    "sg:city":"Purbach am Neusiedler See",
    "sg:orig_category":"Textilreinigungsmaschinen",
    "sg:phone":"+43 4326 837034",
    "sg:postcode":"7083",
    "sg:province":"Burgenland",
    "wof:name":"Rath KEG",
    "wof:placetype":"venue"
},
  "geometry": {"coordinates":[16.685962677,47.917263031],"type":"Point"}
}