{
  "type": "Feature",
  "properties": {
    "addr:full":"Schmidham 80 V\u00f6cklamarkt Ober\u00f6sterreich 4870",
    "addr:housenumber":"80",
    "addr:postcode":"4870",
    "addr:street":"Schmidham;Oberoesterreich",
    "iso:country":"AT",
    "sg:address":"Schmidham 80",
    "sg:city":"V\u00f6cklamarkt",
    "sg:orig_category":"Tischlereien",
    "sg:phone":"+43 768260800",
    "sg:postcode":"4870",
    "sg:province":"Ober\u00f6sterreich",
    "wof:name":"Paschek Heinz",
    "wof:placetype":"venue"
},
  "geometry": {"coordinates":[13.4818000793,48.0179595947],"type":"Point"}
}