{
  "type": "Feature",
  "properties": {
    "iso:country":"AT",
    "sg:address":"Bahnhofstr 19",
    "sg:city":"St. Georgen an der Gusen",
    "sg:orig_category":"Industrieanlagenbau U -Planung",
    "sg:phone":"+43 4372 3764244",
    "sg:postcode":"4222",
    "sg:province":"Ober\u00f6sterreich",
    "wof:name":"Zauner Anlagenbau GmbH",
    "wof:placetype":"venue"
},
  "geometry": {"coordinates":[14.4460773468,48.2691383362],"type":"Point"}
}