{
  "type": "Feature",
  "properties": {
    "iso:country":"AT",
    "sg:address":"Treustr 9",
    "sg:city":"Wien",
    "sg:orig_category":"Sonderschulen",
    "sg:phone":"+43 1 3304587",
    "sg:postcode":"1200",
    "sg:province":"Wien",
    "wof:name":"Schulen d Stadt Wien",
    "wof:placetype":"venue"
},
  "geometry": {"coordinates":[16.3680934906,48.2272071838],"type":"Point"}
}