{
  "type": "Feature",
  "properties": {
    "iso:country":"AT",
    "sg:address":"Margaretenstr 88-90",
    "sg:city":"Wien",
    "sg:orig_category":"Filmproduktionen",
    "sg:phone":"+43 1 5856373",
    "sg:postcode":"1050",
    "sg:province":"Wien",
    "wof:name":"b & b production",
    "wof:placetype":"venue"
},
  "geometry": {"coordinates":[16.3569545746,48.1904640198],"type":"Point"}
}