{
  "type": "Feature",
  "properties": {
    "addr:full":"Seitenberggasse 18 Wien Wien 1160",
    "addr:housenumber":"18",
    "addr:postcode":"1160",
    "addr:street":"Seitenberggasse",
    "iso:country":"AT",
    "sg:address":"Seitenberggasse 18",
    "sg:city":"Wien",
    "sg:classifiers":[
        {
            "category":"Food & Beverages",
            "subcategory":"Fruits & Vegetables",
            "type":"Retail Goods"
        }
    ],
    "sg:phone":"+43 1 48021900",
    "sg:postcode":"1160",
    "sg:province":"Wien",
    "sg:tags":[
        "preserve",
        "cucumber"
    ],
    "wof:name":"Kolm Pfluger Obst- und Gem\u00fcsekonservierung Peter Pfluger",
    "wof:placetype":"venue"
},
  "geometry": {"coordinates":[16.3125419617,48.2164115906],"type":"Point"}
}