{
  "type": "Feature",
  "properties": {
    "addr:full":"Egger-Lienz-Str 7 Wattens Tirol 6112",
    "addr:housenumber":"7",
    "addr:postcode":"6112",
    "addr:street":"Egger-Lienz-Str;Tirol",
    "iso:country":"AT",
    "sg:address":"Egger-Lienz-Str 7",
    "sg:city":"Wattens",
    "sg:orig_category":"Non-Classified Establishments",
    "sg:phone":"+43 5224 51421",
    "sg:postcode":"6112",
    "sg:province":"Tirol",
    "wof:name":"H\u00f6rmann GmbH & Co KG",
    "wof:placetype":"venue"
},
  "geometry": {"coordinates":[11.5896234512,47.2915840149],"type":"Point"}
}