{
  "type": "Feature",
  "properties": {
    "addr:full":"Jakob Prantdtauer- Str.1 W\u00f6rgl Tirol 6300",
    "addr:postcode":"6300",
    "iso:country":"AT",
    "sg:address":"Jakob Prantdtauer- Str.1",
    "sg:city":"W\u00f6rgl",
    "sg:classifiers":[
        {
            "category":"Wholesale",
            "subcategory":"Machinery & Supplies",
            "type":"Manufacturing & Wholesale Goods"
        }
    ],
    "sg:phone":"+43 4353 3278730",
    "sg:postcode":"6300",
    "sg:province":"Tirol",
    "sg:tags":[
        "equipment",
        "-",
        "instrument",
        "measurement"
    ],
    "wof:name":"SANFORD AUSTRIA GMBH",
    "wof:placetype":"venue"
},
  "geometry": {"coordinates":[-69.3131027222,-51.6091995239],"type":"Point"}
}