{
  "type": "Feature",
  "properties": {
    "addr:full":"Nr 104 Eggersdorf Steiermark 8063",
    "addr:postcode":"8063",
    "addr:street":"Nr 104",
    "iso:country":"AT",
    "sg:address":"Nr 104",
    "sg:city":"Eggersdorf",
    "sg:orig_category":"Physiotherapie",
    "sg:phone":"+43 4369 910506783",
    "sg:postcode":"8063",
    "sg:province":"Steiermark",
    "wof:name":"M\u00e4hr B\u00e4rbel - Fachpraxis f\u00fcr Physiotherapie",
    "wof:placetype":"venue"
},
  "geometry": {"coordinates":[15.5996646881,47.1230659485],"type":"Point"}
}