{
  "type": "Feature",
  "properties": {
    "addr:full":"Nr 97 Liebenfels K\u00e4rnten 9556",
    "addr:postcode":"9556",
    "addr:street":"Nr;Kaernten",
    "iso:country":"AT",
    "sg:address":"Nr 97",
    "sg:city":"Liebenfels",
    "sg:orig_category":"Polizei U Gendarmerie",
    "sg:phone":"+43 4359 1332126",
    "sg:postcode":"9556",
    "sg:province":"K\u00e4rnten",
    "wof:name":"Gendarmerieposten",
    "wof:placetype":"venue"
},
  "geometry": {"coordinates":[14.2895402908,46.7378463745],"type":"Point"}
}