{
  "type": "Feature",
  "properties": {
    "iso:country":"AT",
    "sg:address":"Maria Lanzendorfer Str 16",
    "sg:city":"Leopoldsdorf",
    "sg:orig_category":"Fahrzeugbau",
    "sg:phone":"+43 4322 3544142",
    "sg:postcode":"2333",
    "sg:province":"Nieder\u00f6sterreich",
    "sg:website":"stadlmueller.at",
    "wof:name":"Stadlm\u00fcller GmbH",
    "wof:placetype":"venue"
},
  "geometry": {"coordinates":[16.3975696564,48.1078414917],"type":"Point"}
}