{
  "type": "Feature",
  "properties": {
    "iso:country":"AT",
    "sg:address":"Kleing 2",
    "sg:city":"Wien",
    "sg:orig_category":"Friseure U Frisiersalons",
    "sg:phone":"+43 4317 153720",
    "sg:postcode":"1030",
    "sg:province":"Wien",
    "wof:name":"Kirschbaum Gerhard",
    "wof:placetype":"venue"
},
  "geometry": {"coordinates":[16.4053459167,48.19480896],"type":"Point"}
}