{
  "type": "Feature",
  "properties": {
    "addr:full":"Ketzerg 270 Wien Wien 1230",
    "addr:housenumber":"270",
    "addr:postcode":"1230",
    "iso:country":"AT",
    "sg:address":"Ketzerg 270",
    "sg:city":"Wien",
    "sg:orig_category":"Bauunternehmen",
    "sg:phone":"+43 4319 8515780",
    "sg:postcode":"1230",
    "sg:province":"Wien",
    "sg:website":"huthansl.at",
    "wof:name":"Huthansl Althaussanierung- u BaugesmbH",
    "wof:placetype":"venue"
},
  "geometry": {"coordinates":[16.2800865173,48.1321792603],"type":"Point"}
}