{
  "type": "Feature",
  "properties": {
    "addr:full":"Hauptstr 51 Pernitz Nieder\u00f6sterreich 2763",
    "addr:housenumber":"51",
    "addr:postcode":"2763",
    "addr:street":"Hauptstr",
    "iso:country":"AT",
    "sg:address":"Hauptstr 51",
    "sg:city":"Pernitz",
    "sg:orig_category":"Trachtenbekleidung",
    "sg:phone":"+43 2632 72297",
    "sg:postcode":"2763",
    "sg:province":"Nieder\u00f6sterreich",
    "wof:name":"Lumpi Anselma",
    "wof:placetype":"venue"
},
  "geometry": {"coordinates":[15.9629411697,47.8975486755],"type":"Point"}
}