{
  "type": "Feature",
  "properties": {
    "addr:full":"Palfner Str 6 Bad Gastein Salzburg 5640",
    "addr:housenumber":"6",
    "addr:postcode":"5640",
    "addr:street":"Str;Salzburg",
    "iso:country":"AT",
    "sg:address":"Palfner Str 6",
    "sg:city":"Bad Gastein",
    "sg:orig_category":"Appartements / Ferienwohnungen",
    "sg:phone":"+43 6434 2462",
    "sg:postcode":"5640",
    "sg:province":"Salzburg",
    "wof:name":"Landhaus Neuschmid",
    "wof:placetype":"venue"
},
  "geometry": {"coordinates":[13.1359510422,47.1065826416],"type":"Point"}
}