{
  "type": "Feature",
  "properties": {
    "iso:country":"AT",
    "sg:address":"Dorf 44",
    "sg:city":"Ellmau",
    "sg:orig_category":"Unterhaltungselektronik / Einzelhandel",
    "sg:phone":"+43 5358 2044",
    "sg:postcode":"6352",
    "sg:province":"Tirol",
    "wof:name":"Hochfilzer Hans-Peter",
    "wof:placetype":"venue"
},
  "geometry": {"coordinates":[12.302069664,47.515838623],"type":"Point"}
}