{
  "type": "Feature",
  "properties": {
    "addr:full":"Scheibbser Str 1 Wieselburg an der Erlauf Nieder\u00f6sterreich 3250",
    "addr:housenumber":"1",
    "addr:postcode":"3250",
    "addr:street":"Str",
    "iso:country":"AT",
    "sg:address":"Scheibbser Str 1",
    "sg:city":"Wieselburg an der Erlauf",
    "sg:orig_category":"Autobusunternehmen",
    "sg:phone":"+43 4374 1655335",
    "sg:postcode":"3250",
    "sg:province":"Nieder\u00f6sterreich",
    "wof:name":"Bauer Hans Anton",
    "wof:placetype":"venue"
},
  "geometry": {"coordinates":[15.1388015747,48.1301651001],"type":"Point"}
}