{
  "type": "Feature",
  "properties": {
    "addr:full":"Schweizer Strasse 47 Hohenems Vorarlberg 6845",
    "addr:housenumber":"47",
    "addr:postcode":"6845",
    "addr:street":"Schweizer Strasse",
    "iso:country":"AT",
    "sg:address":"Schweizer Strasse 47",
    "sg:city":"Hohenems",
    "sg:classifiers":[
        {
            "category":"Education",
            "subcategory":"Special Training",
            "type":"Public Place"
        }
    ],
    "sg:phone":"+43 5576 72141",
    "sg:postcode":"6845",
    "sg:province":"Vorarlberg",
    "sg:tags":[
        "bread"
    ],
    "wof:name":"Josef Mathis KG",
    "wof:placetype":"venue"
},
  "geometry": {"coordinates":[9.6857099533,47.3674583435],"type":"Point"}
}