{
  "type": "Feature",
  "properties": {
    "addr:full":"Wiesenweg 9 Rum Tirol 6063",
    "addr:housenumber":"9",
    "addr:postcode":"6063",
    "addr:street":"Wiesenweg;Tirol",
    "iso:country":"AT",
    "sg:address":"Wiesenweg 9",
    "sg:city":"Rum",
    "sg:orig_category":"Tischlereien",
    "sg:phone":"+43 512 260587",
    "sg:postcode":"6063",
    "sg:province":"Tirol",
    "wof:name":"Rabitsch Karl-Heinz",
    "wof:placetype":"venue"
},
  "geometry": {"coordinates":[11.4627399445,47.2867050171],"type":"Point"}
}