{
  "type": "Feature",
  "properties": {
    "addr:full":"Bahnhofstr 8a Natters Tirol 6161",
    "addr:housenumber":"8a",
    "addr:postcode":"6161",
    "addr:street":"Bahnhofstr;Tirol",
    "iso:country":"AT",
    "sg:address":"Bahnhofstr 8a",
    "sg:city":"Natters",
    "sg:orig_category":"Autobusunternehmen",
    "sg:phone":"+43 512 5464540",
    "sg:postcode":"6161",
    "sg:province":"Tirol",
    "sg:website":"www.natterer-reisen.at",
    "wof:name":"Mayr Franz",
    "wof:placetype":"venue"
},
  "geometry": {"coordinates":[11.3757019043,47.2328300476],"type":"Point"}
}