{
  "type": "Feature",
  "properties": {
    "addr:full":"Hofsteigstr 36 Lustenau Vorarlberg 6890",
    "addr:housenumber":"36",
    "addr:postcode":"6890",
    "addr:street":"Hofsteigstr",
    "iso:country":"AT",
    "sg:address":"Hofsteigstr 36",
    "sg:city":"Lustenau",
    "sg:orig_category":"Stickereien",
    "sg:phone":"+43 4355 7782826",
    "sg:postcode":"6890",
    "sg:province":"Vorarlberg",
    "wof:name":"B\u00f6sch Arthur",
    "wof:placetype":"venue"
},
  "geometry": {"coordinates":[9.6664791107,47.4354476929],"type":"Point"}
}