{
  "type": "Feature",
  "properties": {
    "iso:country":"AT",
    "sg:address":"Sch\u00f6nberger Str",
    "sg:city":"Z\u00f6bing",
    "sg:orig_category":"Weine / Einzelhandel",
    "sg:phone":"+43 2734 27810",
    "sg:postcode":"3561",
    "sg:province":"Nieder\u00f6sterreich",
    "wof:name":"Felsenkeller - Rudolf R\u00f6glsperger",
    "wof:placetype":"venue"
},
  "geometry": {"coordinates":[-114.0767440796,46.4432487488],"type":"Point"}
}