{
  "type": "Feature",
  "properties": {
    "iso:country":"AT",
    "sg:address":"Sochorg. 5 ",
    "sg:city":"Tribuswinkel",
    "sg:classifiers":[
        {
            "category":"Shopping",
            "type":"Retail Goods"
        }
    ],
    "sg:phone":"+43 4322 5285180",
    "sg:postcode":"2512",
    "sg:province":"Nieder\u00f6sterreich",
    "sg:tags":[
        "finished",
        "-",
        "metallic"
    ],
    "wof:name":"YOUKOE FORM TECHNIK GMBH",
    "wof:placetype":"venue"
},
  "geometry": {"coordinates":[16.2884216309,47.9842300415],"type":"Point"}
}