{
  "type": "Feature",
  "properties": {
    "addr:full":"Marktpl 8 Mattsee Salzburg 5163",
    "addr:housenumber":"8",
    "addr:postcode":"5163",
    "addr:street":"Marktpl;Salzburg",
    "iso:country":"AT",
    "sg:address":"Marktpl 8",
    "sg:city":"Mattsee",
    "sg:orig_category":"Fliesen U Platten",
    "sg:phone":"+43 4362 175300",
    "sg:postcode":"5163",
    "sg:province":"Salzburg",
    "wof:name":"Wopenka Robert - Kachelofenbau u Fliesenverlegung",
    "wof:placetype":"venue"
},
  "geometry": {"coordinates":[13.10409832,47.9697570801],"type":"Point"}
}