{
  "type": "Feature",
  "properties": {
    "addr:full":"Bichlnweg 62a Kitzb\u00fchel Tirol 6370",
    "addr:housenumber":"62a",
    "addr:postcode":"6370",
    "addr:street":"Bichlnweg;Tirol",
    "iso:country":"AT",
    "sg:address":"Bichlnweg 62a",
    "sg:city":"Kitzb\u00fchel",
    "sg:orig_category":"Handelsagenturen",
    "sg:phone":"+43 5356 71034",
    "sg:postcode":"6370",
    "sg:province":"Tirol",
    "wof:name":"Gruber Krimbacher OEG",
    "wof:placetype":"venue"
},
  "geometry": {"coordinates":[12.4113435745,47.4359092712],"type":"Point"}
}