{
  "type": "Feature",
  "properties": {
    "addr:full":"Nr 3 Natternbach Ober\u00f6sterreich 4723",
    "addr:postcode":"4723",
    "addr:street":"Nr;Oberoesterreich",
    "iso:country":"AT",
    "sg:address":"Nr 3",
    "sg:city":"Natternbach",
    "sg:classifiers":[
        {
            "category":"Utilities",
            "subcategory":"Recycling",
            "type":"Services"
        }
    ],
    "sg:phone":"+43 7278 20118",
    "sg:postcode":"4723",
    "sg:province":"Ober\u00f6sterreich",
    "wof:name":"Biotech Umwelttechnik GmbH",
    "wof:placetype":"venue"
},
  "geometry": {"coordinates":[13.7493953705,48.396736145],"type":"Point"}
}