{
  "type": "Feature",
  "properties": {
    "addr:full":"Industriestr 9 Hard Vorarlberg 6971",
    "addr:housenumber":"9",
    "addr:postcode":"6971",
    "addr:street":"Industriestr",
    "iso:country":"AT",
    "sg:address":"Industriestr 9",
    "sg:city":"Hard",
    "sg:orig_category":"Farben U Lacke / Einzelhandel",
    "sg:phone":"+43 4355 74732080",
    "sg:postcode":"6971",
    "sg:province":"Vorarlberg",
    "sg:website":"dergruene.at",
    "wof:name":"Der Gr\u00fcne Micheluzzi Kurt GmbH + Co MFB-Technik",
    "wof:placetype":"venue"
},
  "geometry": {"coordinates":[9.6773386002,47.4829483032],"type":"Point"}
}