{
  "type": "Feature",
  "properties": {
    "iso:country":"AT",
    "sg:address":"Bahnhofstr 6",
    "sg:city":"Zirl",
    "sg:orig_category":"Spenglereien",
    "sg:phone":"+43 5238 52518",
    "sg:postcode":"6170",
    "sg:province":"Tirol",
    "wof:name":"R\u00f6ck Josef KEG - Spenglerei-Glaserei-Schwarzdecker",
    "wof:placetype":"venue"
},
  "geometry": {"coordinates":[11.2403488159,47.2712593079],"type":"Point"}
}