{
  "type": "Feature",
  "properties": {
    "addr:full":"Stra\u00dflandweg 28 Linz Ober\u00f6sterreich 4030",
    "addr:housenumber":"28",
    "addr:postcode":"4030",
    "addr:street":"Strasslandweg",
    "iso:country":"AT",
    "sg:address":"Stra\u00dflandweg 28",
    "sg:city":"Linz",
    "sg:orig_category":"Automobile Sales Promotional Accessories",
    "sg:phone":"+43 732 681040",
    "sg:postcode":"4030",
    "sg:province":"Ober\u00f6sterreich",
    "sg:website":"wm-austria.at",
    "wof:name":"M\u00fchleder GmbH",
    "wof:placetype":"venue"
},
  "geometry": {"coordinates":[14.3146533966,48.255645752],"type":"Point"}
}