{
  "type": "Feature",
  "properties": {
    "addr:full":"M\u00fchlg 154 Sautens Tirol 6432",
    "addr:housenumber":"154",
    "addr:postcode":"6432",
    "addr:street":"Sautens Tirol",
    "iso:country":"AT",
    "sg:address":"M\u00fchlg 154",
    "sg:city":"Sautens",
    "sg:orig_category":"Architekten",
    "sg:phone":"+43 5252 6503",
    "sg:postcode":"6432",
    "sg:province":"Tirol",
    "wof:name":"Neururer Alfred Dipl-Ing",
    "wof:placetype":"venue"
},
  "geometry": {"coordinates":[10.8634080887,47.2080001831],"type":"Point"}
}