{
  "type": "Feature",
  "properties": {
    "addr:full":"Wiesen 304 Neukirchen am Gro\u00dfvenediger Salzburg 5741",
    "addr:housenumber":"304",
    "addr:postcode":"5741",
    "addr:street":"Wiesen;Salzburg",
    "iso:country":"AT",
    "sg:address":"Wiesen 304",
    "sg:city":"Neukirchen am Gro\u00dfvenediger",
    "sg:classifiers":[
        {
            "category":"Home & Garden",
            "subcategory":"Building Materials",
            "type":"Retail Goods"
        }
    ],
    "sg:phone":"+43 6565 62660",
    "sg:postcode":"5741",
    "sg:province":"Salzburg",
    "sg:tags":[
        "gravel",
        "crushed"
    ],
    "sg:website":"keil-erdbau.at",
    "wof:name":"Walter Keil Transporte und Erdbewegungen Ges.m.b.H. & Co KG",
    "wof:placetype":"venue"
},
  "geometry": {"coordinates":[12.3227596283,47.261390686],"type":"Point"}
}