{
  "type": "Feature",
  "properties": {
    "iso:country":"AT",
    "sg:city":"Hofkirchen im M\u00fchlkreis",
    "sg:orig_category":"Feuerwehren",
    "sg:phone":"+43 7285 215",
    "sg:postcode":"4142",
    "sg:province":"Ober\u00f6sterreich",
    "wof:name":"Freiwillige Feuerwehr Hofkirchen im M\u00fchlkreis",
    "wof:placetype":"venue"
},
  "geometry": {"coordinates":[13.8118095398,48.4825515747],"type":"Point"}
}