{
  "type": "Feature",
  "properties": {
    "addr:full":"Michaelerplatz 8 Steyr Ober\u00f6sterreich 4400",
    "addr:housenumber":"8",
    "addr:postcode":"4400",
    "addr:street":"Michaelerplatz;Oberoesterreich",
    "iso:country":"AT",
    "sg:address":"Michaelerplatz 8",
    "sg:city":"Steyr",
    "sg:classifiers":[
        {
            "category":"Autos & Motor Vehicles",
            "subcategory":"Automobile Sales",
            "type":"Retail Goods"
        }
    ],
    "sg:phone":"+43 7252 76115",
    "sg:postcode":"4400",
    "sg:province":"Ober\u00f6sterreich",
    "sg:tags":[
        "workshop",
        "upholstery"
    ],
    "sg:website":"bilweis-zehethofer.at",
    "wof:name":"Bilweis & Zehethofer OEG",
    "wof:placetype":"venue"
},
  "geometry": {"coordinates":[14.4217367172,48.0433044434],"type":"Point"}
}