{
  "type": "Feature",
  "properties": {
    "addr:full":"Karolingerstr 13A Salzburg Salzburg 5020",
    "addr:housenumber":"13a",
    "addr:postcode":"5020",
    "addr:street":"Karolingerstr;Salzburg",
    "iso:country":"AT",
    "sg:address":"Karolingerstr 13A",
    "sg:city":"Salzburg",
    "sg:orig_category":"Tierschutz",
    "sg:phone":"+43 4366 2832322",
    "sg:postcode":"5020",
    "sg:province":"Salzburg",
    "wof:name":"Tierheim - Tierschutzverein f Stadt u Land Slbg",
    "wof:placetype":"venue"
},
  "geometry": {"coordinates":[13.0087757111,47.7943229675],"type":"Point"}
}