{
  "type": "Feature",
  "properties": {
    "addr:full":"Hetzendorfer Str 27/1/7 Wien Wien 1120",
    "addr:housenumber":"27 / 1 / 7",
    "addr:postcode":"1120",
    "addr:street":"Str",
    "iso:country":"AT",
    "sg:address":"Hetzendorfer Str 27/1/7",
    "sg:city":"Wien",
    "sg:orig_category":"Handelsagenturen",
    "sg:phone":"+43 1 8048306",
    "sg:postcode":"1120",
    "sg:province":"Wien",
    "wof:name":"Castagna Handels KEG",
    "wof:placetype":"venue"
},
  "geometry": {"coordinates":[16.3290939331,48.1824874878],"type":"Point"}
}