{
  "type": "Feature",
  "properties": {
    "addr:full":"Fischamender Str 53 Bruck an der Leitha Nieder\u00f6sterreich 2460",
    "addr:postcode":"2460",
    "addr:street":"Str 53",
    "iso:country":"AT",
    "sg:address":"Fischamender Str 53",
    "sg:city":"Bruck an der Leitha",
    "sg:orig_category":"Heurigen / Buschenschank",
    "sg:phone":"+43 2162 62349",
    "sg:postcode":"2460",
    "sg:province":"Nieder\u00f6sterreich",
    "wof:name":"Seidl-Keller",
    "wof:placetype":"venue"
},
  "geometry": {"coordinates":[16.7696628571,48.0316772461],"type":"Point"}
}