{
  "type": "Feature",
  "properties": {
    "iso:country":"AT",
    "sg:address":"Volksgartenstr 21",
    "sg:city":"Linz",
    "sg:orig_category":"Schneidereien",
    "sg:phone":"+43 732 650050",
    "sg:postcode":"4020",
    "sg:province":"Ober\u00f6sterreich",
    "wof:name":"B\u00e4ck Ursula - Modesalon",
    "wof:placetype":"venue"
},
  "geometry": {"coordinates":[14.290055275,48.2958984375],"type":"Point"}
}