{
  "type": "Feature",
  "properties": {
    "addr:full":"Kirchenstr 13 K\u00f6stendorf Salzburg 5203",
    "addr:housenumber":"13",
    "addr:postcode":"5203",
    "addr:street":"Kirchenstr;Salzburg",
    "iso:country":"AT",
    "sg:address":"Kirchenstr 13",
    "sg:city":"K\u00f6stendorf",
    "sg:orig_category":"Volksschulen",
    "sg:phone":"+43 4362 16531342",
    "sg:postcode":"5203",
    "sg:province":"Salzburg",
    "wof:name":"Volksschule",
    "wof:placetype":"venue"
},
  "geometry": {"coordinates":[13.1981563568,47.9566192627],"type":"Point"}
}