{
  "type": "Feature",
  "properties": {
    "addr:full":"Maximilianstr 19 Innsbruck Tirol 6020",
    "addr:housenumber":"19",
    "addr:postcode":"6020",
    "addr:street":"Maximilianstr;Tirol",
    "iso:country":"AT",
    "sg:address":"Maximilianstr 19",
    "sg:city":"Innsbruck",
    "sg:orig_category":"Friseure U Frisiersalons",
    "sg:phone":"+43 512 586292",
    "sg:postcode":"6020",
    "sg:province":"Tirol",
    "wof:name":"Friseursalon Der kleine Salon",
    "wof:placetype":"venue"
},
  "geometry": {"coordinates":[11.3916740417,47.2622528076],"type":"Point"}
}