{
  "type": "Feature",
  "properties": {
    "addr:full":"Wurzbachg 16/16 Wien Wien 1150",
    "addr:housenumber":"16 / 16",
    "addr:postcode":"1150",
    "addr:street":"Wurzbachg",
    "iso:country":"AT",
    "sg:address":"Wurzbachg 16/16",
    "sg:city":"Wien",
    "sg:orig_category":"Installateurnotdienste",
    "sg:phone":"+43 699 14147000",
    "sg:postcode":"1150",
    "sg:province":"Wien",
    "wof:name":"ROENZ Geb\u00e4udetechnik GmbH",
    "wof:placetype":"venue"
},
  "geometry": {"coordinates":[16.3360137939,48.2033233643],"type":"Point"}
}