{
  "type": "Feature",
  "properties": {
    "addr:full":"Halden 5 Lochau Vorarlberg 6911",
    "addr:housenumber":"5",
    "addr:postcode":"6911",
    "addr:street":"Halden",
    "iso:country":"AT",
    "sg:address":"Halden 5",
    "sg:city":"Lochau",
    "sg:orig_category":"Maschinenbau",
    "sg:phone":"+43 5574 54038",
    "sg:postcode":"6911",
    "sg:province":"Vorarlberg",
    "wof:name":"Wefatex AG",
    "wof:placetype":"venue"
},
  "geometry": {"coordinates":[9.7583608627,47.5311889648],"type":"Point"}
}