{
  "type": "Feature",
  "properties": {
    "addr:full":"Triester Str 342 Wien Wien 1230",
    "addr:housenumber":"342",
    "addr:postcode":"1230",
    "iso:country":"AT",
    "sg:address":"Triester Str 342",
    "sg:city":"Wien",
    "sg:orig_category":"Reifen U Reifendienste",
    "sg:phone":"+43 1 6991705",
    "sg:postcode":"1230",
    "sg:province":"Wien",
    "wof:name":"Reifen-Brawenec GesmbH",
    "wof:placetype":"venue"
},
  "geometry": {"coordinates":[16.319896698,48.1274795532],"type":"Point"}
}