{
  "type": "Feature",
  "properties": {
    "addr:full":"Reifg 3/9 Krems an der Donau Nieder\u00f6sterreich 3500",
    "addr:housenumber":"3 / 9",
    "addr:postcode":"3500",
    "addr:street":"Reifg",
    "iso:country":"AT",
    "sg:address":"Reifg 3/9",
    "sg:city":"Krems an der Donau",
    "sg:classifiers":[
        {
            "category":"Professional",
            "subcategory":"Management & Consulting",
            "type":"Services"
        }
    ],
    "sg:phone":"+43 2732 78084",
    "sg:postcode":"3500",
    "sg:province":"Nieder\u00f6sterreich",
    "sg:tags":[
        "supervision"
    ],
    "wof:name":"Kuniarta Petra",
    "wof:placetype":"venue"
},
  "geometry": {"coordinates":[15.5965108871,48.4088058472],"type":"Point"}
}