{
  "type": "Feature",
  "properties": {
    "addr:full":"Loipersbacher Str 80 Rohrbach Burgenland 7222",
    "addr:postcode":"7222",
    "addr:street":"Str 80",
    "iso:country":"AT",
    "sg:address":"Loipersbacher Str 80",
    "sg:city":"Rohrbach",
    "sg:orig_category":"Hausbetreuung",
    "sg:phone":"+43 4326 2665427",
    "sg:postcode":"7222",
    "sg:province":"Burgenland",
    "wof:name":"Tiewald GmbH",
    "wof:placetype":"venue"
},
  "geometry": {"coordinates":[16.4333019257,47.7028312683],"type":"Point"}
}