{
  "type": "Feature",
  "properties": {
    "addr:full":"Babenbergerg 573 Alland Nieder\u00f6sterreich 2534",
    "addr:housenumber":"573;2534",
    "addr:street":"Alland Niederoesterreich",
    "iso:country":"AT",
    "sg:address":"Babenbergerg 573",
    "sg:city":"Alland",
    "sg:orig_category":"Staubsauger",
    "sg:phone":"+43 2258 7618835",
    "sg:postcode":"2534",
    "sg:province":"Nieder\u00f6sterreich",
    "wof:name":"Friedl Gerhard - Zentralstaubsauganlagen",
    "wof:placetype":"venue"
},
  "geometry": {"coordinates":[16.071390152,48.0603103638],"type":"Point"}
}