{
  "type": "Feature",
  "properties": {
    "iso:country":"AT",
    "sg:address":"Salmhoferstrasse 6",
    "sg:city":"Wien",
    "sg:classifiers":[
        {
            "category":"Wholesale",
            "subcategory":"Painting Supplies",
            "type":"Manufacturing & Wholesale Goods"
        }
    ],
    "sg:phone":"+43 1 61747470",
    "sg:postcode":"1230",
    "sg:province":"Wien",
    "sg:tags":[
        "paint",
        "industrial"
    ],
    "sg:website":"valenta.co.at",
    "wof:name":"Valenta & Valenta GmbH",
    "wof:placetype":"venue"
},
  "geometry": {"coordinates":[16.3542060852,48.1445579529],"type":"Point"}
}