{
  "type": "Feature",
  "properties": {
    "addr:full":"Andechsstr 52a Innsbruck Tirol 6020",
    "addr:housenumber":"52a",
    "addr:postcode":"6020",
    "addr:street":"Andechsstr;Tirol",
    "iso:country":"AT",
    "sg:address":"Andechsstr 52a",
    "sg:city":"Innsbruck",
    "sg:orig_category":"Bausparkassen",
    "sg:phone":"+43 512 336600",
    "sg:postcode":"6020",
    "sg:province":"Tirol",
    "wof:name":"Allgemeine Bausparkasse reg.Gen.m.b.H. ABV-Gesch\u00e4ftsstelle Innsbruck",
    "wof:placetype":"venue"
},
  "geometry": {"coordinates":[11.4211454391,47.2679901123],"type":"Point"}
}