{
  "type": "Feature",
  "properties": {
    "addr:full":"Neuhofenstrasse 35 Gmunden Ober\u00f6sterreich 4810",
    "addr:housenumber":"35",
    "addr:postcode":"4810",
    "addr:street":"Neuhofenstrasse;Oberoesterreich",
    "iso:country":"AT",
    "sg:address":"Neuhofenstrasse 35",
    "sg:city":"Gmunden",
    "sg:classifiers":[
        {
            "category":"Manufacturing",
            "subcategory":"Wood Products",
            "type":"Manufacturing & Wholesale Goods"
        }
    ],
    "sg:phone":"+43 761274575",
    "sg:postcode":"4810",
    "sg:province":"Ober\u00f6sterreich",
    "sg:tags":[
        "gate",
        "made",
        "door"
    ],
    "wof:name":"Ing. Hermann Fr\u00fchwald",
    "wof:placetype":"venue"
},
  "geometry": {"coordinates":[13.7851696014,47.9310188293],"type":"Point"}
}