{
  "type": "Feature",
  "properties": {
    "addr:full":"B\u00e4ckerm\u00fchlweg 59 Linz Ober\u00f6sterreich 4030",
    "addr:housenumber":"59",
    "addr:postcode":"4030",
    "addr:street":"Baeckermuehlweg",
    "iso:country":"AT",
    "sg:address":"B\u00e4ckerm\u00fchlweg 59",
    "sg:city":"Linz",
    "sg:classifiers":[
        {
            "category":"Shopping",
            "subcategory":"Pharmacy",
            "type":"Retail Goods"
        }
    ],
    "sg:phone":"+43 732 3853720",
    "sg:postcode":"4030",
    "sg:province":"Ober\u00f6sterreich",
    "sg:tags":[
        "preparation",
        "pharmaceutical"
    ],
    "sg:website":"alk-abello.at",
    "wof:name":"ALK-ABELLO Allergie-Service GmbH.",
    "wof:placetype":"venue"
},
  "geometry": {"coordinates":[14.3069601059,48.2325248718],"type":"Point"}
}