{
  "type": "Feature",
  "properties": {
    "iso:country":"AT",
    "sg:address":"Josef-Sch\u00f6ffel-G 21",
    "sg:city":"Klosterneuburg",
    "sg:orig_category":"Partyservice",
    "sg:phone":"+43 2243 37624",
    "sg:postcode":"3400",
    "sg:province":"Nieder\u00f6sterreich",
    "wof:name":"Kulinarium - Inh Fam Kapeller",
    "wof:placetype":"venue"
},
  "geometry": {"coordinates":[16.3301391602,48.2908935547],"type":"Point"}
}