{
  "type": "Feature",
  "properties": {
    "iso:country":"AT",
    "sg:address":"Hadikg 252",
    "sg:city":"Wien",
    "sg:orig_category":"Restaurants: Amerikanisch",
    "sg:phone":"+43 1 9143350",
    "sg:postcode":"1140",
    "sg:province":"Wien",
    "wof:name":"McDonald's Restaurant - McDrive",
    "wof:placetype":"venue"
},
  "geometry": {"coordinates":[16.2775363922,48.1926651001],"type":"Point"}
}