{
  "type": "Feature",
  "properties": {
    "addr:full":"Gaadner Str 61/4 Hinterbr\u00fchl Nieder\u00f6sterreich 2371",
    "addr:housenumber":"61 / 4",
    "addr:postcode":"2371",
    "addr:street":"Str;Hinterbruehl Niederoesterreich",
    "iso:country":"AT",
    "sg:address":"Gaadner Str 61/4",
    "sg:city":"Hinterbr\u00fchl",
    "sg:orig_category":"Webdesign",
    "sg:phone":"+43 4366 45221367",
    "sg:postcode":"2371",
    "sg:province":"Nieder\u00f6sterreich",
    "wof:name":"CBL Group",
    "wof:placetype":"venue"
},
  "geometry": {"coordinates":[16.233707428,48.0790481567],"type":"Point"}
}