{
  "type": "Feature",
  "properties": {
    "addr:full":"Wallensteinstr 54 Wien Wien 1200",
    "addr:housenumber":"54",
    "addr:postcode":"1200",
    "addr:street":"Wallensteinstr",
    "iso:country":"AT",
    "sg:address":"Wallensteinstr 54",
    "sg:city":"Wien",
    "sg:orig_category":"Bekleidung / Einzelhandel",
    "sg:phone":"+43 1 3303229",
    "sg:postcode":"1200",
    "sg:province":"Wien",
    "wof:name":"Hausner Walter",
    "wof:placetype":"venue"
},
  "geometry": {"coordinates":[16.3743343353,48.2306594849],"type":"Point"}
}