{
  "type": "Feature",
  "properties": {
    "iso:country":"AT",
    "sg:address":"Diesterwegg 28a",
    "sg:city":"Wien",
    "sg:orig_category":"Direktmarketing",
    "sg:phone":"+43 1 8944621",
    "sg:postcode":"1140",
    "sg:province":"Wien",
    "wof:name":"Engelhardt Dieter",
    "wof:placetype":"venue"
},
  "geometry": {"coordinates":[16.3058204651,48.190738678],"type":"Point"}
}