{
  "type": "Feature",
  "properties": {
    "iso:country":"AT",
    "sg:address":"Leibnizg 47",
    "sg:city":"Wien",
    "sg:orig_category":"Sonnenschutzanlagen",
    "sg:phone":"+43 4367 64201992",
    "sg:postcode":"1100",
    "sg:province":"Wien",
    "wof:name":"Sun-Protector",
    "wof:placetype":"venue"
},
  "geometry": {"coordinates":[16.3754882812,48.1712989807],"type":"Point"}
}