{
  "type": "Feature",
  "properties": {
    "addr:full":"Schollenstr 15 Hohenems Vorarlberg 6845",
    "addr:housenumber":"15",
    "addr:postcode":"6845",
    "addr:street":"Schollenstr",
    "iso:country":"AT",
    "sg:address":"Schollenstr 15",
    "sg:city":"Hohenems",
    "sg:orig_category":"Tischlereien",
    "sg:phone":"+43 5576 431310",
    "sg:postcode":"6845",
    "sg:province":"Vorarlberg",
    "wof:name":"K\u00f6nig Mark",
    "wof:placetype":"venue"
},
  "geometry": {"coordinates":[9.7046661377,47.3780441284],"type":"Point"}
}