{
  "type": "Feature",
  "properties": {
    "iso:country":"AT",
    "sg:address":"Freibacher Str 2",
    "sg:city":"Ferlach",
    "sg:orig_category":"Tabaktrafiken",
    "sg:phone":"+43 4227 22690",
    "sg:postcode":"9170",
    "sg:province":"K\u00e4rnten",
    "wof:name":"Tabakfachgesch\u00e4ft Mikel - Inh Nicole Mikel",
    "wof:placetype":"venue"
},
  "geometry": {"coordinates":[14.3005723953,46.5273971558],"type":"Point"}
}