{
  "type": "Feature",
  "properties": {
    "addr:full":"Airportstr PO Box 1 Fischamend Nieder\u00f6sterreich 2401",
    "addr:housenumber":"po box 1",
    "addr:postcode":"2401",
    "iso:country":"AT",
    "sg:address":"Airportstr PO Box 1",
    "sg:city":"Fischamend",
    "sg:orig_category":"Paketdienste",
    "sg:phone":"+43 1 700733687",
    "sg:postcode":"2401",
    "sg:province":"Nieder\u00f6sterreich",
    "wof:name":"CPXpress",
    "wof:placetype":"venue"
},
  "geometry": {"coordinates":[16.5904502869,48.1244049072],"type":"Point"}
}