{
  "type": "Feature",
  "properties": {
    "addr:full":"Prager Str 78 Wien Wien 1210",
    "addr:postcode":"1210",
    "addr:street":"Str 78",
    "iso:country":"AT",
    "sg:address":"Prager Str 78",
    "sg:city":"Wien",
    "sg:classifiers":[
        {
            "category":"Restaurant",
            "type":"Food & Drink"
        }
    ],
    "sg:phone":"+43 1 2711254",
    "sg:postcode":"1210",
    "sg:province":"Wien",
    "wof:name":"Gambrinus",
    "wof:placetype":"venue"
},
  "geometry": {"coordinates":[16.391752243,48.2697143555],"type":"Point"}
}