{
  "type": "Feature",
  "properties": {
    "addr:full":"Fromillerstr 40 Klagenfurt K\u00e4rnten 9020",
    "addr:housenumber":"40",
    "addr:postcode":"9020",
    "addr:street":"Fromillerstr;Kaernten",
    "iso:country":"AT",
    "sg:address":"Fromillerstr 40",
    "sg:city":"Klagenfurt",
    "sg:orig_category":"Steuerberatung",
    "sg:phone":"+43 463 544770",
    "sg:postcode":"9020",
    "sg:province":"K\u00e4rnten",
    "wof:name":"Pirker & Partner Steuerberatungsgesellschaft",
    "wof:placetype":"venue"
},
  "geometry": {"coordinates":[14.3104324341,46.6165122986],"type":"Point"}
}