{
  "type": "Feature",
  "properties": {
    "addr:full":"Neubauerstr 72 Traun Ober\u00f6sterreich 4050",
    "addr:housenumber":"72",
    "addr:postcode":"4050",
    "addr:street":"Neubauerstr",
    "iso:country":"AT",
    "sg:address":"Neubauerstr 72",
    "sg:city":"Traun",
    "sg:orig_category":"Friseure U Frisiersalons",
    "sg:phone":"+43 4372 2975469",
    "sg:postcode":"4050",
    "sg:province":"Ober\u00f6sterreich",
    "wof:name":"Friseur Happy Hair Shop",
    "wof:placetype":"venue"
},
  "geometry": {"coordinates":[14.2267713547,48.2188835144],"type":"Point"}
}