{
  "type": "Feature",
  "properties": {
    "addr:full":"Innrain 55 Innsbruck Tirol 6020",
    "addr:housenumber":"55",
    "addr:postcode":"6020",
    "addr:street":"Innrain;Tirol",
    "iso:country":"AT",
    "sg:address":"Innrain 55",
    "sg:city":"Innsbruck",
    "sg:orig_category":"Medizintechnik",
    "sg:phone":"+43 512 575760",
    "sg:postcode":"6020",
    "sg:province":"Tirol",
    "wof:name":"Haus der Gesundheit Sussbauer",
    "wof:placetype":"venue"
},
  "geometry": {"coordinates":[11.3843870163,47.2619476318],"type":"Point"}
}