{
  "type": "Feature",
  "properties": {
    "addr:full":"Nr 118 Telfs Tirol 6410",
    "addr:postcode":"6410",
    "addr:street":"Nr 118;Tirol",
    "iso:country":"AT",
    "sg:address":"Nr 118",
    "sg:city":"Telfs",
    "sg:orig_category":"Druckereien",
    "sg:phone":"+43 4352 3888338",
    "sg:postcode":"6410",
    "sg:province":"Tirol",
    "wof:name":"Kranebitter Druck GesmbH",
    "wof:placetype":"venue"
},
  "geometry": {"coordinates":[11.072218895,47.3066978455],"type":"Point"}
}