{
  "type": "Feature",
  "properties": {
    "addr:full":"Marktpl 10 Gmunden Ober\u00f6sterreich 4810",
    "addr:housenumber":"10",
    "addr:postcode":"4810",
    "addr:street":"Marktpl;Oberoesterreich",
    "iso:country":"AT",
    "sg:address":"Marktpl 10",
    "sg:city":"Gmunden",
    "sg:orig_category":"Gerichte",
    "sg:phone":"+43 7612771660",
    "sg:postcode":"4810",
    "sg:province":"Ober\u00f6sterreich",
    "wof:name":"Bezirksgericht Gmunden",
    "wof:placetype":"venue"
},
  "geometry": {"coordinates":[13.8008699417,47.9193687439],"type":"Point"}
}