{
  "type": "Feature",
  "properties": {
    "iso:country":"AT",
    "sg:address":"Rudolf Sallinger-Pl 1",
    "sg:city":"Wien",
    "sg:orig_category":"Innungen",
    "sg:phone":"+43 1 514502254",
    "sg:postcode":"1030",
    "sg:province":"Wien",
    "wof:name":"Allg Fachgr Wien d Gewerbes Metallschleifer und Galvaniseure",
    "wof:placetype":"venue"
},
  "geometry": {"coordinates":[16.3811416626,48.2011451721],"type":"Point"}
}