{
  "type": "Feature",
  "properties": {
    "iso:country":"AT",
    "sg:address":"Schuhmeierstr 1",
    "sg:city":"Wilhelmsburg an der Traisen",
    "sg:orig_category":"Massagen",
    "sg:phone":"+43 4366 42264283",
    "sg:postcode":"3150",
    "sg:province":"Nieder\u00f6sterreich",
    "wof:name":"Pils Erich",
    "wof:placetype":"venue"
},
  "geometry": {"coordinates":[15.6014461517,48.0969581604],"type":"Point"}
}