{
  "type": "Feature",
  "properties": {
    "addr:full":"Oberkoflerweg 2 Innsbruck Tirol 6020",
    "addr:housenumber":"2",
    "addr:postcode":"6020",
    "addr:street":"Oberkoflerweg;Tirol",
    "iso:country":"AT",
    "sg:address":"Oberkoflerweg 2",
    "sg:city":"Innsbruck",
    "sg:orig_category":"Architekten",
    "sg:phone":"+43 512 206460",
    "sg:postcode":"6020",
    "sg:province":"Tirol",
    "wof:name":"Kunzenmann Martin Arch Dipl-Ing",
    "wof:placetype":"venue"
},
  "geometry": {"coordinates":[11.4069242477,47.2822914124],"type":"Point"}
}