{
  "type": "Feature",
  "properties": {
    "iso:country":"AT",
    "sg:address":"Glimpfingerstr 9",
    "sg:city":"Linz",
    "sg:orig_category":"Steuerberatung",
    "sg:phone":"+43 732 343002",
    "sg:postcode":"4020",
    "sg:province":"Ober\u00f6sterreich",
    "wof:name":"Dvorzak Manfred Mag",
    "wof:placetype":"venue"
},
  "geometry": {"coordinates":[14.3086824417,48.2749328613],"type":"Point"}
}