{
  "type": "Feature",
  "properties": {
    "iso:country":"AT",
    "sg:address":"Mechtlerstr 33",
    "sg:city":"Korneuburg",
    "sg:orig_category":"Elektroinstallationsunternehmen",
    "sg:phone":"+43 2262 71533",
    "sg:postcode":"2100",
    "sg:province":"Nieder\u00f6sterreich",
    "wof:name":"Mitterb\u00f6ck Gerhard",
    "wof:placetype":"venue"
},
  "geometry": {"coordinates":[16.3325252533,48.3512382507],"type":"Point"}
}