{
  "type": "Feature",
  "properties": {
    "addr:full":"Gumpendorfer Str 134-136 Wien Wien 1060",
    "addr:housenumber":"134-136",
    "addr:postcode":"1060",
    "addr:street":"Str",
    "iso:country":"AT",
    "sg:address":"Gumpendorfer Str 134-136",
    "sg:city":"Wien",
    "sg:orig_category":"Bierlokale-Pubs",
    "sg:phone":"+43 1 5953838",
    "sg:postcode":"1060",
    "sg:province":"Wien",
    "wof:name":"Bauernbr\u00e4u",
    "wof:placetype":"venue"
},
  "geometry": {"coordinates":[16.3398838043,48.1906585693],"type":"Point"}
}