{
  "type": "Feature",
  "properties": {
    "iso:country":"AT",
    "sg:address":"Burg Hasegg",
    "sg:city":"Hall in Tirol",
    "sg:orig_category":"Museen / Ausstellungen",
    "sg:phone":"+43 5223 44245",
    "sg:postcode":"6060",
    "sg:province":"Tirol",
    "wof:name":"M\u00fcnzpr\u00e4gest\u00e4tte - Alte M\u00fcnze",
    "wof:placetype":"venue"
},
  "geometry": {"coordinates":[11.5065698624,47.2818107605],"type":"Point"}
}