{
  "type": "Feature",
  "properties": {
    "iso:country":"AT",
    "sg:address":"Kremsberger Weg 1",
    "sg:city":"Neuhofen an der Krems",
    "sg:orig_category":"Putze",
    "sg:phone":"+43 7227 4704",
    "sg:postcode":"4501",
    "sg:province":"Ober\u00f6sterreich",
    "wof:name":"LJ-Bau GesmbH",
    "wof:placetype":"venue"
},
  "geometry": {"coordinates":[14.2267112732,48.1477470398],"type":"Point"}
}