{
  "type": "Feature",
  "properties": {
    "addr:full":"null Parz 362/1 Markgrafneusiedl Nieder\u00f6sterreich 2282",
    "addr:housenumber":"362 / 1",
    "addr:postcode":"2282",
    "iso:country":"AT",
    "sg:address":"null Parz 362/1",
    "sg:city":"Markgrafneusiedl",
    "sg:classifiers":[
        {
            "category":"Home & Garden",
            "subcategory":"Garden Supply",
            "type":"Retail Goods"
        }
    ],
    "sg:phone":"+43 4322 482240",
    "sg:postcode":"2282",
    "sg:province":"Nieder\u00f6sterreich",
    "sg:tags":[
        "schotter",
        "sand",
        "u"
    ],
    "wof:name":"Herzer Bau- u Transport GmbH",
    "wof:placetype":"venue"
},
  "geometry": {"coordinates":[16.6323261261,48.2674369812],"type":"Point"}
}