{
  "type": "Feature",
  "properties": {
    "addr:full":"Grazer Str 186 Leibnitz Steiermark 8430",
    "addr:housenumber":"186",
    "addr:postcode":"8430",
    "addr:street":"Steiermark",
    "iso:country":"AT",
    "sg:address":"Grazer Str 186",
    "sg:city":"Leibnitz",
    "sg:orig_category":"Tapezierer U Dekorateure",
    "sg:phone":"+43 4334 5283542",
    "sg:postcode":"8430",
    "sg:province":"Steiermark",
    "wof:name":"Guttmann Thomas",
    "wof:placetype":"venue"
},
  "geometry": {"coordinates":[15.5384950638,46.7981872559],"type":"Point"}
}