{
  "type": "Feature",
  "properties": {
    "addr:full":"Rothenburgstr 1 Wien Wien 1120",
    "addr:housenumber":"1",
    "addr:postcode":"1120",
    "addr:street":"Rothenburgstr",
    "iso:country":"AT",
    "sg:address":"Rothenburgstr 1",
    "sg:city":"Wien",
    "sg:orig_category":"Volksschulen",
    "sg:phone":"+43 1 8049105",
    "sg:postcode":"1120",
    "sg:province":"Wien",
    "wof:name":"Schulen d Stadt Wien",
    "wof:placetype":"venue"
},
  "geometry": {"coordinates":[16.3205814362,48.1622695923],"type":"Point"}
}