{
  "type": "Feature",
  "properties": {
    "addr:full":"Bahnhofstr 24 Waidhofen an der Thaya Nieder\u00f6sterreich 3830",
    "addr:housenumber":"24",
    "addr:postcode":"3830",
    "addr:street":"Bahnhofstr",
    "iso:country":"AT",
    "sg:address":"Bahnhofstr 24",
    "sg:city":"Waidhofen an der Thaya",
    "sg:orig_category":"Tabaktrafiken",
    "sg:phone":"+43 4328 4254750",
    "sg:postcode":"3830",
    "sg:province":"Nieder\u00f6sterreich",
    "wof:name":"Tabak-Trafik Christian Ernst",
    "wof:placetype":"venue"
},
  "geometry": {"coordinates":[15.2786397934,48.8137207031],"type":"Point"}
}