{
  "type": "Feature",
  "properties": {
    "addr:full":"Linzer Str 60a Marchtrenk Ober\u00f6sterreich 4614",
    "addr:housenumber":"60a",
    "addr:postcode":"4614",
    "addr:street":"Linzer Str",
    "iso:country":"AT",
    "sg:address":"Linzer Str 60a",
    "sg:city":"Marchtrenk",
    "sg:orig_category":"Fleischhauereien",
    "sg:phone":"+43 7243 58294",
    "sg:postcode":"4614",
    "sg:province":"Ober\u00f6sterreich",
    "wof:name":"Steiner Josef",
    "wof:placetype":"venue"
},
  "geometry": {"coordinates":[14.1201152802,48.1918334961],"type":"Point"}
}