{
  "type": "Feature",
  "properties": {
    "iso:country":"AT",
    "sg:address":"Brigittenauer L\u00e4nde 156-158/Stg.1/19",
    "sg:city":"Wien",
    "sg:orig_category":"Detekteien",
    "sg:phone":"+43 1 9681593",
    "sg:postcode":"1200",
    "sg:province":"Wien",
    "wof:name":"Agentur f\u00fcr Personenfahndung und Schuldnersuche Inh. Ing. Michael Renger",
    "wof:placetype":"venue"
},
  "geometry": {"coordinates":[16.3734645844,48.2306060791],"type":"Point"}
}