{
  "type": "Feature",
  "properties": {
    "addr:full":"Kagraner Pl 51 Wien Wien 1220",
    "addr:housenumber":"51",
    "addr:postcode":"1220",
    "addr:street":"Kagraner Pl",
    "iso:country":"AT",
    "sg:address":"Kagraner Pl 51",
    "sg:city":"Wien",
    "sg:orig_category":"Tabaktrafiken",
    "sg:phone":"+43 1 2042853",
    "sg:postcode":"1220",
    "sg:province":"Wien",
    "wof:name":"Rosenberger Claudia",
    "wof:placetype":"venue"
},
  "geometry": {"coordinates":[16.4447364807,48.2495422363],"type":"Point"}
}