{
  "type": "Feature",
  "properties": {
    "iso:country":"AT",
    "sg:address":"Schubertring 8/2",
    "sg:city":"Wien",
    "sg:orig_category":"Immobilienverwaltungen",
    "sg:phone":"+43 1 5131224",
    "sg:postcode":"1010",
    "sg:province":"Wien",
    "wof:name":"Lindner Hertha Geb\u00e4udeverwaltung und Realit\u00e4tenvermittlung GesmbH",
    "wof:placetype":"venue"
},
  "geometry": {"coordinates":[16.3753147125,48.2025032043],"type":"Point"}
}