{
  "type": "Feature",
  "properties": {
    "addr:full":"Eisenhandstrasse 8 Linz Ober\u00f6sterreich 4020",
    "addr:housenumber":"8",
    "addr:postcode":"4020",
    "addr:street":"Eisenhandstrasse",
    "iso:country":"AT",
    "sg:address":"Eisenhandstrasse 8",
    "sg:city":"Linz",
    "sg:classifiers":[
        {
            "category":"Wholesale",
            "subcategory":"Books, Periodicals, & Newspapers",
            "type":"Manufacturing & Wholesale Goods"
        }
    ],
    "sg:phone":"+43 732 7788560",
    "sg:postcode":"4020",
    "sg:province":"Ober\u00f6sterreich",
    "sg:tags":[
        "bag",
        "paper",
        "carrier"
    ],
    "sg:website":"gwv.at",
    "wof:name":"GWV Geschenk- und Werbeartikel Vertriebsges.m.b.H.",
    "wof:placetype":"venue"
},
  "geometry": {"coordinates":[14.2954893112,48.3051452637],"type":"Point"}
}