{
  "type": "Feature",
  "properties": {
    "iso:country":"AT",
    "sg:address":"Nr 4",
    "sg:city":"Strengberg",
    "sg:orig_category":"Tischlereien",
    "sg:phone":"+43 7432 20080",
    "sg:postcode":"3314",
    "sg:province":"Nieder\u00f6sterreich",
    "wof:name":"Fehringer Ernst",
    "wof:placetype":"venue"
},
  "geometry": {"coordinates":[166.9221496582,-0.5282999873],"type":"Point"}
}