{
  "type": "Feature",
  "properties": {
    "iso:country":"AT",
    "sg:address":"Gymnasiumstr 17",
    "sg:city":"Wien",
    "sg:orig_category":"Antiquariate",
    "sg:phone":"+43 1 4707022",
    "sg:postcode":"1180",
    "sg:province":"Wien",
    "wof:name":"Cottage Buchhandlung Andreas Sunitsch",
    "wof:placetype":"venue"
},
  "geometry": {"coordinates":[16.3429450989,48.2284507751],"type":"Point"}
}