{
  "type": "Feature",
  "properties": {
    "addr:full":"Hauptstr 52 Seeboden K\u00e4rnten 9871",
    "addr:housenumber":"52",
    "addr:postcode":"9871",
    "addr:street":"Hauptstr;Kaernten",
    "iso:country":"AT",
    "sg:address":"Hauptstr 52",
    "sg:city":"Seeboden",
    "sg:orig_category":"Eisenwaren",
    "sg:phone":"+43 4762 81165",
    "sg:postcode":"9871",
    "sg:province":"K\u00e4rnten",
    "wof:name":"Winkler Karl",
    "wof:placetype":"venue"
},
  "geometry": {"coordinates":[13.5137701035,46.8171958923],"type":"Point"}
}