{
  "type": "Feature",
  "properties": {
    "iso:country":"AT",
    "sg:address":"Gewerbestr 3",
    "sg:city":"Gro\u00dfebersdorf",
    "sg:orig_category":"Baumeister",
    "sg:phone":"+43 4322 4582455",
    "sg:postcode":"2203",
    "sg:province":"Nieder\u00f6sterreich",
    "sg:website":"bm-pichler.at",
    "wof:name":"Baumeister Ing Pichler",
    "wof:placetype":"venue"
},
  "geometry": {"coordinates":[16.4689350128,48.3628768921],"type":"Point"}
}