{
  "type": "Feature",
  "properties": {
    "addr:full":"Feldg 388 Furth Nieder\u00f6sterreich 3511",
    "addr:housenumber":"388",
    "addr:postcode":"3511",
    "addr:street":"Furth Niederoesterreich",
    "iso:country":"AT",
    "sg:address":"Feldg 388",
    "sg:city":"Furth",
    "sg:orig_category":"Werbeagenturen",
    "sg:phone":"+43 2732 73240",
    "sg:postcode":"3511",
    "sg:province":"Nieder\u00f6sterreich",
    "wof:name":"Creazone - Vegh & Wurm OEG",
    "wof:placetype":"venue"
},
  "geometry": {"coordinates":[15.6125049591,48.374168396],"type":"Point"}
}