{
  "type": "Feature",
  "properties": {
    "iso:country":"AT",
    "sg:address":"Adi-Dassler-Gasse 4",
    "sg:city":"Klagenfurt-Viktring",
    "sg:classifiers":[
        {
            "category":"Utilities",
            "subcategory":"Fuel Oil & Lpg",
            "type":"Services"
        }
    ],
    "sg:phone":"+43 463 29718",
    "sg:postcode":"9073",
    "sg:province":"K\u00e4rnten",
    "sg:tags":[
        "flocking"
    ],
    "wof:name":"STAR DRUCK GmbH",
    "wof:placetype":"venue"
},
  "geometry": {"coordinates":[14.2769823074,46.5930862427],"type":"Point"}
}