{
  "type": "Feature",
  "properties": {
    "iso:country":"AT",
    "sg:address":"Trausdorfer Str 2",
    "sg:city":"Siegendorf im Burgenland",
    "sg:orig_category":"Weine / Einzelhandel",
    "sg:phone":"+43 664 5223193",
    "sg:postcode":"7011",
    "sg:province":"Burgenland",
    "wof:name":"Weinhandel Wild",
    "wof:placetype":"venue"
},
  "geometry": {"coordinates":[16.5153503418,47.7649040222],"type":"Point"}
}