{
  "type": "Feature",
  "properties": {
    "addr:full":"Brunhildstr 10 St. Valentin Nieder\u00f6sterreich 4300",
    "addr:housenumber":"10",
    "addr:postcode":"4300",
    "addr:street":"Brunhildstr",
    "iso:country":"AT",
    "sg:address":"Brunhildstr 10",
    "sg:city":"St. Valentin",
    "sg:orig_category":"Elektronik",
    "sg:phone":"+43 7435 52807",
    "sg:postcode":"4300",
    "sg:province":"Nieder\u00f6sterreich",
    "wof:name":"Mayrhofer Ernst Ing",
    "wof:placetype":"venue"
},
  "geometry": {"coordinates":[14.5191812515,48.1717453003],"type":"Point"}
}