{
  "type": "Feature",
  "properties": {
    "addr:full":"Dachsbergg 3 Krems an der Donau Nieder\u00f6sterreich 3500",
    "addr:housenumber":"3",
    "addr:postcode":"3500",
    "addr:street":"Dachsbergg",
    "iso:country":"AT",
    "sg:address":"Dachsbergg 3",
    "sg:city":"Krems an der Donau",
    "sg:orig_category":"Immobilienmakler",
    "sg:phone":"+43 4327 3270576",
    "sg:postcode":"3500",
    "sg:province":"Nieder\u00f6sterreich",
    "wof:name":"Krems Real Immobilienvermittlung",
    "wof:placetype":"venue"
},
  "geometry": {"coordinates":[15.5965108871,48.4088058472],"type":"Point"}
}