{
  "type": "Feature",
  "properties": {
    "addr:full":"Dommesg 16/7 Wien Wien 1110",
    "addr:housenumber":"16 / 7",
    "addr:postcode":"1110",
    "addr:street":"Dommesg",
    "iso:country":"AT",
    "sg:address":"Dommesg 16/7",
    "sg:city":"Wien",
    "sg:orig_category":"Berufsbekleidung / Einzelhandel",
    "sg:phone":"+43 1 6005362",
    "sg:postcode":"1110",
    "sg:province":"Wien",
    "wof:name":"Rauscher Alexander",
    "wof:placetype":"venue"
},
  "geometry": {"coordinates":[16.4197444916,48.1709709167],"type":"Point"}
}