{
  "type": "Feature",
  "properties": {
    "iso:country":"AT",
    "sg:address":"Nr 7",
    "sg:city":"Reutte",
    "sg:classifiers":[
        {
            "category":"Home & Garden",
            "subcategory":"Building Materials",
            "type":"Retail Goods"
        }
    ],
    "sg:phone":"+43 5672 62019",
    "sg:postcode":"6600",
    "sg:province":"Tirol",
    "sg:tags":[
        "baustoffe",
        "-material",
        "u"
    ],
    "wof:name":"Beirer Wilfried",
    "wof:placetype":"venue"
},
  "geometry": {"coordinates":[10.7185935974,47.4889183044],"type":"Point"}
}