{
  "type": "Feature",
  "properties": {
    "addr:full":"Irdning Steiermark 8952",
    "addr:postcode":"8952",
    "iso:country":"AT",
    "sg:city":"Irdning",
    "sg:orig_category":"Internet, Alle Internetdienstleistungen",
    "sg:postcode":"8952",
    "sg:province":"Steiermark",
    "sg:website":"http://www.austriawebhosting.at/index.htm",
    "wof:name":"Austria Webhosting",
    "wof:placetype":"venue"
},
  "geometry": {"coordinates":[14.1031150818,47.5052604675],"type":"Point"}
}