{
  "type": "Feature",
  "properties": {
    "addr:full":"Platzl 4 Salzburg Salzburg 5020",
    "addr:housenumber":"4",
    "addr:postcode":"5020",
    "addr:street":"Platzl;Salzburg",
    "iso:country":"AT",
    "sg:address":"Platzl 4",
    "sg:city":"Salzburg",
    "sg:orig_category":"Bekleidung / Einzelhandel",
    "sg:phone":"+43 662 8764080",
    "sg:postcode":"5020",
    "sg:province":"Salzburg",
    "wof:name":"Wiefler Modenhaus KG",
    "wof:placetype":"venue"
},
  "geometry": {"coordinates":[13.0452013016,47.8017501831],"type":"Point"}
}