{
  "type": "Feature",
  "properties": {
    "iso:country":"AT",
    "sg:address":"Nr 411",
    "sg:city":"F\u00fcgen",
    "sg:orig_category":"Diskotheken",
    "sg:phone":"+43 5288 63011",
    "sg:postcode":"6263",
    "sg:province":"Tirol",
    "wof:name":"Zillertal-Tenne F\u00fcgen",
    "wof:placetype":"venue"
},
  "geometry": {"coordinates":[101.76634216310001,30.9142303467],"type":"Point"}
}