{
  "type": "Feature",
  "properties": {
    "iso:country":"AT",
    "sg:address":"Kaltenprunnersiedlung 2",
    "sg:city":"Micheldorf in Ober\u00f6sterreich",
    "sg:classifiers":[
        {
            "category":"Home & Garden",
            "subcategory":"Building Materials",
            "type":"Retail Goods"
        }
    ],
    "sg:phone":"+43 7582 62668",
    "sg:postcode":"4563",
    "sg:province":"Ober\u00f6sterreich",
    "sg:tags":[
        "gravel",
        "crushed"
    ],
    "wof:name":"H\u00f6rtenhuber Transport Ges.m.b.H.",
    "wof:placetype":"venue"
},
  "geometry": {"coordinates":[14.1317806244,47.8856277466],"type":"Point"}
}