{
  "type": "Feature",
  "properties": {
    "addr:full":"Magazinstr. 4 5027",
    "addr:housenumber":"4",
    "addr:postcode":"5027",
    "addr:street":"Magazinstr.",
    "iso:country":"AT",
    "sg:address":"Magazinstr. 4",
    "sg:classifiers":[
        {
            "category":"Sports & Exercise",
            "subcategory":"Playing Field",
            "type":"Entertainment"
        }
    ],
    "sg:phone":"+43 4366 288921",
    "sg:postcode":"5027",
    "sg:tags":[
        "game"
    ],
    "wof:name":"STADLBAUER MARKETING UND VERTRIEB GESMBH",
    "wof:placetype":"venue"
},
  "geometry": {"coordinates":[13.0522470474,47.8203239441],"type":"Point"}
}