{
  "type": "Feature",
  "properties": {
    "addr:full":"Minifeldweg 212 Winzendorf Nieder\u00f6sterreich 2722",
    "addr:housenumber":"212;2722",
    "addr:street":"Winzendorf Niederoesterreich",
    "iso:country":"AT",
    "sg:address":"Minifeldweg 212",
    "sg:city":"Winzendorf",
    "sg:orig_category":"Sonderschulen",
    "sg:phone":"+43 2638 22059",
    "sg:postcode":"2722",
    "sg:province":"Nieder\u00f6sterreich",
    "wof:name":"Allgemeine Sonderschule",
    "wof:placetype":"venue"
},
  "geometry": {"coordinates":[16.1118373871,47.8077926636],"type":"Point"}
}