{
  "type": "Feature",
  "properties": {
    "iso:country":"AT",
    "sg:address":"Seeuferstr 14",
    "sg:city":"Zell am See",
    "sg:orig_category":"Appartements / Ferienwohnungen",
    "sg:phone":"+43 4365 4274640",
    "sg:postcode":"5700",
    "sg:province":"Salzburg",
    "wof:name":"Appartementhaus Hollaus",
    "wof:placetype":"venue"
},
  "geometry": {"coordinates":[12.8157539368,47.3000183105],"type":"Point"}
}