{
  "type": "Feature",
  "properties": {
    "iso:country":"AT",
    "sg:address":"Museumstr 19",
    "sg:city":"Innsbruck",
    "sg:orig_category":"Friseure U Frisiersalons",
    "sg:phone":"+43 4351 2586608",
    "sg:postcode":"6020",
    "sg:province":"Tirol",
    "wof:name":"Friseursalon-Studio Andrea",
    "wof:placetype":"venue"
},
  "geometry": {"coordinates":[11.3984880447,47.2669868469],"type":"Point"}
}