{
  "type": "Feature",
  "properties": {
    "iso:country":"AT",
    "sg:address":"Nr 81",
    "sg:city":"Winklern",
    "sg:orig_category":"Polizei U Gendarmerie",
    "sg:phone":"+43 4359 1332241",
    "sg:postcode":"9841",
    "sg:province":"K\u00e4rnten",
    "wof:name":"Gendarmerie",
    "wof:placetype":"venue"
},
  "geometry": {"coordinates":[12.9168014526,46.8631591797],"type":"Point"}
}