{
  "type": "Feature",
  "properties": {
    "addr:full":"Alter Markt 15 Salzburg Salzburg 5020",
    "addr:housenumber":"15",
    "addr:postcode":"5020",
    "addr:street":"Alter Markt;Salzburg",
    "iso:country":"AT",
    "sg:address":"Alter Markt 15",
    "sg:city":"Salzburg",
    "sg:orig_category":"Banken U Sparkassen",
    "sg:phone":"+43 662 843533",
    "sg:postcode":"5020",
    "sg:province":"Salzburg",
    "wof:name":"Reise Bank AG",
    "wof:placetype":"venue"
},
  "geometry": {"coordinates":[13.0451059341,47.799911499],"type":"Point"}
}