{
  "type": "Feature",
  "properties": {
    "addr:full":"Dr.-Karl-Renner-Pl Attnang-Puchheim Ober\u00f6sterreich 4800",
    "addr:postcode":"4800",
    "addr:street":"Oberoesterreich",
    "iso:country":"AT",
    "sg:address":"Dr.-Karl-Renner-Pl",
    "sg:city":"Attnang-Puchheim",
    "sg:classifiers":[
        {
            "category":"Restaurant",
            "type":"Food & Drink"
        }
    ],
    "sg:phone":"+43 699 10138760",
    "sg:postcode":"4800",
    "sg:province":"Ober\u00f6sterreich",
    "wof:name":"fast ein Restaurant",
    "wof:placetype":"venue"
},
  "geometry": {"coordinates":[13.7213153839,48.0121116638],"type":"Point"}
}