{
  "type": "Feature",
  "properties": {
    "addr:full":"Holderstauden 290 Schoppernau Vorarlberg 6886",
    "addr:housenumber":"290",
    "addr:postcode":"6886",
    "addr:street":"Holderstauden",
    "iso:country":"AT",
    "sg:address":"Holderstauden 290",
    "sg:city":"Schoppernau",
    "sg:orig_category":"Transportunternehmen",
    "sg:phone":"+43 5515 2024",
    "sg:postcode":"6886",
    "sg:province":"Vorarlberg",
    "wof:name":"Beer Gotthard",
    "wof:placetype":"venue"
},
  "geometry": {"coordinates":[10.015370369,47.3161811829],"type":"Point"}
}