{
  "type": "Feature",
  "properties": {
    "addr:full":"Hietzinger Kai 131a Wien Wien 1130",
    "addr:housenumber":"131a",
    "addr:postcode":"1130",
    "addr:street":"Hietzinger Kai",
    "iso:country":"AT",
    "sg:address":"Hietzinger Kai 131a",
    "sg:city":"Wien",
    "sg:orig_category":"Reproanstalten",
    "sg:phone":"+43 1 8770333",
    "sg:postcode":"1130",
    "sg:province":"Wien",
    "wof:name":"Bernsteiner & Partner GesmbH",
    "wof:placetype":"venue"
},
  "geometry": {"coordinates":[16.2816505432,48.1914024353],"type":"Point"}
}