{
  "type": "Feature",
  "properties": {
    "addr:full":"Herzog Leopold-Str 28 Wiener Neustadt Nieder\u00f6sterreich 2700",
    "addr:housenumber":"28",
    "addr:postcode":"2700",
    "addr:street":"Leopold-Str",
    "iso:country":"AT",
    "sg:address":"Herzog Leopold-Str 28",
    "sg:city":"Wiener Neustadt",
    "sg:orig_category":"Bijouteriewaren",
    "sg:phone":"+43 2622 29998",
    "sg:postcode":"2700",
    "sg:province":"Nieder\u00f6sterreich",
    "wof:name":"Barbl Helga",
    "wof:placetype":"venue"
},
  "geometry": {"coordinates":[16.2402496338,47.8136177063],"type":"Point"}
}