{
  "type": "Feature",
  "properties": {
    "addr:full":"Erlach 15 Neumarkt im Hausruckkreis Ober\u00f6sterreich 4720",
    "addr:housenumber":"15",
    "addr:postcode":"4720",
    "addr:street":"Erlach",
    "iso:country":"AT",
    "sg:address":"Erlach 15",
    "sg:city":"Neumarkt im Hausruckkreis",
    "sg:orig_category":"Partyservice",
    "sg:phone":"+43 4377 336930",
    "sg:postcode":"4720",
    "sg:province":"Ober\u00f6sterreich",
    "wof:name":"W\u00fcrzl Leopold",
    "wof:placetype":"venue"
},
  "geometry": {"coordinates":[13.713467598,48.281955719],"type":"Point"}
}