{
  "type": "Feature",
  "properties": {
    "addr:full":"Achsiedlungsstr 9 Bregenz Vorarlberg 6900",
    "addr:housenumber":"9",
    "addr:postcode":"6900",
    "addr:street":"Achsiedlungsstr",
    "iso:country":"AT",
    "sg:address":"Achsiedlungsstr 9",
    "sg:city":"Bregenz",
    "sg:orig_category":"Isolierungen",
    "sg:phone":"+43 5574 73674",
    "sg:postcode":"6900",
    "sg:province":"Vorarlberg",
    "wof:name":"Mihevc Karl",
    "wof:placetype":"venue"
},
  "geometry": {"coordinates":[9.7093153,47.4943161011],"type":"Point"}
}