{
  "type": "Feature",
  "properties": {
    "addr:full":"Waldstr 7 Rohrbach Burgenland 7222",
    "addr:housenumber":"7",
    "addr:postcode":"7222",
    "addr:street":"Waldstr",
    "iso:country":"AT",
    "sg:address":"Waldstr 7",
    "sg:city":"Rohrbach",
    "sg:orig_category":"Feuerwehren",
    "sg:phone":"+43 2626 64075",
    "sg:postcode":"7222",
    "sg:province":"Burgenland",
    "wof:name":"Freiwillige Feuerwehr Rohrbach b Mattersburg",
    "wof:placetype":"venue"
},
  "geometry": {"coordinates":[16.4289932251,47.7055168152],"type":"Point"}
}