{
  "type": "Feature",
  "properties": {
    "iso:country":"AT",
    "sg:address":"Kreuzpl 10",
    "sg:city":"Bad Ischl",
    "sg:orig_category":"Weiterbildungsinstitute M Allg U Berufl Bildungsangebot",
    "sg:phone":"+43 4357 0005300",
    "sg:postcode":"4820",
    "sg:province":"Ober\u00f6sterreich",
    "wof:name":"WIFI d Wirtschaftskammer Ober\u00f6sterreich",
    "wof:placetype":"venue"
},
  "geometry": {"coordinates":[13.6220788956,47.7134437561],"type":"Point"}
}