{
  "type": "Feature",
  "properties": {
    "addr:full":"Egelseestrasse 52/b Feldkirch Vorarlberg 6800",
    "addr:housenumber":"52 / b",
    "addr:postcode":"6800",
    "addr:street":"Egelseestrasse",
    "iso:country":"AT",
    "sg:address":"Egelseestrasse 52/b",
    "sg:city":"Feldkirch",
    "sg:classifiers":[
        {
            "category":"Retail",
            "subcategory":"Laundry & Dry Cleaning",
            "type":"Services"
        }
    ],
    "sg:phone":"+43 5522 32201",
    "sg:postcode":"6800",
    "sg:province":"Vorarlberg",
    "sg:tags":[
        "camouflage",
        "tent"
    ],
    "sg:website":"geiger-international.com",
    "wof:name":"Geiger International",
    "wof:placetype":"venue"
},
  "geometry": {"coordinates":[9.5775699615,47.2391967773],"type":"Point"}
}