{
  "type": "Feature",
  "properties": {
    "addr:full":"Kalzitstrasse 4 Buchkirchen Ober\u00f6sterreich 4611",
    "addr:housenumber":"4",
    "addr:postcode":"4611",
    "addr:street":"Kalzitstrasse",
    "iso:country":"AT",
    "sg:address":"Kalzitstrasse 4",
    "sg:city":"Buchkirchen",
    "sg:classifiers":[
        {
            "category":"Military Area",
            "subcategory":"Army Base",
            "type":"Public Place"
        }
    ],
    "sg:phone":"+43 7243 53771",
    "sg:postcode":"4611",
    "sg:province":"Ober\u00f6sterreich",
    "sg:tags":[
        "electrostatic",
        "coating",
        "powder"
    ],
    "wof:name":"SF Kunststoffbeschichtungstechnik GmbH",
    "wof:placetype":"venue"
},
  "geometry": {"coordinates":[14.0809574127,48.1977233887],"type":"Point"}
}