{
  "type": "Feature",
  "properties": {
    "addr:full":"Bernsteinstr 8 Hohenau an der March Nieder\u00f6sterreich 2273",
    "addr:housenumber":"8",
    "addr:postcode":"2273",
    "addr:street":"Bernsteinstr",
    "iso:country":"AT",
    "sg:address":"Bernsteinstr 8",
    "sg:city":"Hohenau an der March",
    "sg:orig_category":"Autohandel",
    "sg:phone":"+43 2535 3744",
    "sg:postcode":"2273",
    "sg:province":"Nieder\u00f6sterreich",
    "wof:name":"Goldmann Werner",
    "wof:placetype":"venue"
},
  "geometry": {"coordinates":[16.8991584778,48.6016197205],"type":"Point"}
}