{
  "type": "Feature",
  "properties": {
    "addr:full":"5073",
    "addr:postcode":"5073",
    "iso:country":"AT",
    "sg:classifiers":[
        {
            "category":"Communications",
            "subcategory":"Film & Video Production",
            "type":"Services"
        }
    ],
    "sg:phone":"+43 662 842255",
    "sg:postcode":"5073",
    "sg:tags":[
        "documentary"
    ],
    "wof:name":"UNI-PRO Universal- Programm Ges.m.b.H. & Co KG",
    "wof:placetype":"venue"
},
  "geometry": {"coordinates":[12.9851102829,47.7938690186],"type":"Point"}
}