{
  "type": "Feature",
  "properties": {
    "addr:full":"Landstr 35a Linz Ober\u00f6sterreich 4020",
    "addr:housenumber":"35a",
    "addr:postcode":"4020",
    "addr:street":"Landstr",
    "iso:country":"AT",
    "sg:address":"Landstr 35a",
    "sg:city":"Linz",
    "sg:classifiers":[
        {
            "category":"Restaurant",
            "type":"Food & Drink"
        }
    ],
    "sg:phone":"+43 732 779263",
    "sg:postcode":"4020",
    "sg:province":"Ober\u00f6sterreich",
    "wof:name":"Nordsee GesmbH",
    "wof:placetype":"venue"
},
  "geometry": {"coordinates":[14.2905950546,48.3012771606],"type":"Point"}
}