{
  "type": "Feature",
  "properties": {
    "addr:full":"Pfarrg 7 Steyr Ober\u00f6sterreich 4400",
    "addr:housenumber":"7",
    "addr:postcode":"4400",
    "addr:street":"Pfarrg;Oberoesterreich",
    "iso:country":"AT",
    "sg:address":"Pfarrg 7",
    "sg:city":"Steyr",
    "sg:orig_category":"Fotografen",
    "sg:phone":"+43 7252 523980",
    "sg:postcode":"4400",
    "sg:province":"Ober\u00f6sterreich",
    "wof:name":"Ru\u00dfk\u00e4fer der Fotograf",
    "wof:placetype":"venue"
},
  "geometry": {"coordinates":[14.4176797867,48.0377731323],"type":"Point"}
}