{
  "type": "Feature",
  "properties": {
    "iso:country":"AT",
    "sg:address":"Nr 24",
    "sg:city":"Maurach",
    "sg:orig_category":"Appartements / Ferienwohnungen",
    "sg:phone":"+43 4352 4263123",
    "sg:postcode":"6212",
    "sg:province":"Tirol",
    "wof:name":"Ferienwohnungen Loigner",
    "wof:placetype":"venue"
},
  "geometry": {"coordinates":[11.7518672943,47.4225006104],"type":"Point"}
}