{
  "type": "Feature",
  "properties": {
    "iso:country":"AT",
    "sg:address":"Hauptstr 69",
    "sg:city":"Kindberg",
    "sg:orig_category":"Textilwaren / Einzelhandel",
    "sg:phone":"+43 3865 5107",
    "sg:postcode":"8650",
    "sg:province":"Steiermark",
    "wof:name":"TPS",
    "wof:placetype":"venue"
},
  "geometry": {"coordinates":[15.4477081299,47.5042610168],"type":"Point"}
}