{
  "type": "Feature",
  "properties": {
    "addr:full":"Hauptstr 69 Kindberg Steiermark 8650",
    "addr:housenumber":"69",
    "addr:postcode":"8650",
    "addr:street":"Hauptstr",
    "iso:country":"AT",
    "sg:address":"Hauptstr 69",
    "sg:city":"Kindberg",
    "sg:orig_category":"Textilwaren / Einzelhandel",
    "sg:phone":"+43 3865 5107",
    "sg:postcode":"8650",
    "sg:province":"Steiermark",
    "wof:name":"TPS",
    "wof:placetype":"venue"
},
  "geometry": {"coordinates":[15.4477081299,47.5042610168],"type":"Point"}
}