{
  "type": "Feature",
  "properties": {
    "iso:country":"AT",
    "sg:address":"Kleistweg 13",
    "sg:city":"Traun",
    "sg:orig_category":"Stuckateure U Trockenausbauer",
    "sg:phone":"+43 4366 44424914",
    "sg:postcode":"4050",
    "sg:province":"Ober\u00f6sterreich",
    "wof:name":"RTA Trockenausbau GmbH",
    "wof:placetype":"venue"
},
  "geometry": {"coordinates":[14.2537870407,48.2409439087],"type":"Point"}
}