{
  "type": "Feature",
  "properties": {
    "addr:full":"Tamariskeng Wien Wien 1220",
    "addr:postcode":"1220",
    "iso:country":"AT",
    "sg:address":"Tamariskeng",
    "sg:city":"Wien",
    "sg:classifiers":[
        {
            "category":"Restaurant",
            "type":"Food & Drink"
        }
    ],
    "sg:phone":"+43 1 2836798",
    "sg:postcode":"1220",
    "sg:province":"Wien",
    "sg:tags":[
        "pizzeria"
    ],
    "wof:name":"Pizzeria Ponte",
    "wof:placetype":"venue"
},
  "geometry": {"coordinates":[16.4645042419,48.2159461975],"type":"Point"}
}