{
  "type": "Feature",
  "properties": {
    "addr:full":"Roseggerstr 23 Bruck an der Mur Steiermark 8600",
    "addr:housenumber":"23",
    "addr:postcode":"8600",
    "addr:street":"Roseggerstr",
    "iso:country":"AT",
    "sg:address":"Roseggerstr 23",
    "sg:city":"Bruck an der Mur",
    "sg:orig_category":"Reinigungsservice",
    "sg:phone":"+43 3862 56504",
    "sg:postcode":"8600",
    "sg:province":"Steiermark",
    "wof:name":"Blitz-Blank Reinigung - Dienstleistungsunternehmen GmbH",
    "wof:placetype":"venue"
},
  "geometry": {"coordinates":[15.2725477219,47.4103279114],"type":"Point"}
}