{
  "type": "Feature",
  "properties": {
    "addr:full":"Josef Wiesmayer-G 17 Hennersdorf Nieder\u00f6sterreich 2332",
    "addr:housenumber":"17",
    "addr:postcode":"2332",
    "iso:country":"AT",
    "sg:address":"Josef Wiesmayer-G 17",
    "sg:city":"Hennersdorf",
    "sg:orig_category":"Optische Artikel",
    "sg:phone":"+43 2235 81701",
    "sg:postcode":"2332",
    "sg:province":"Nieder\u00f6sterreich",
    "wof:name":"Akripan HandelsgesmbH",
    "wof:placetype":"venue"
},
  "geometry": {"coordinates":[16.3692207336,48.1136207581],"type":"Point"}
}