{
  "type": "Feature",
  "properties": {
    "iso:country":"AT",
    "sg:address":"Hadeldorfstr 9",
    "sg:city":"Rankweil",
    "sg:classifiers":[
        {
            "category":"Shopping",
            "subcategory":"Party Supplies",
            "type":"Retail Goods"
        }
    ],
    "sg:phone":"+43 4355 2248820",
    "sg:postcode":"6830",
    "sg:province":"Vorarlberg",
    "sg:tags":[
        "u",
        "lichtanlagen",
        "ton-"
    ],
    "wof:name":"Ton + Bild Medientechnik GmbH",
    "wof:placetype":"venue"
},
  "geometry": {"coordinates":[9.6411132812,47.2733879089],"type":"Point"}
}