{
  "type": "Feature",
  "properties": {
    "addr:full":"Gilmstr 29 Bludenz Vorarlberg 6700",
    "addr:housenumber":"29",
    "addr:postcode":"6700",
    "addr:street":"Gilmstr",
    "iso:country":"AT",
    "sg:address":"Gilmstr 29",
    "sg:city":"Bludenz",
    "sg:orig_category":"Beschriftungen",
    "sg:phone":"+43 5552 33027",
    "sg:postcode":"6700",
    "sg:province":"Vorarlberg",
    "wof:name":"Schriften-Atelier Della",
    "wof:placetype":"venue"
},
  "geometry": {"coordinates":[9.8288927078,47.1542778015],"type":"Point"}
}