{
  "type": "Feature",
  "properties": {
    "addr:full":"Schmiedg 13 Leibnitz Steiermark 8430",
    "addr:housenumber":"13",
    "addr:postcode":"8430",
    "addr:street":"Schmiedg;Steiermark",
    "iso:country":"AT",
    "sg:address":"Schmiedg 13",
    "sg:city":"Leibnitz",
    "sg:orig_category":"Juwelen, Gold- U Silberwaren / Einzelhandel",
    "sg:phone":"+43 4334 5285801",
    "sg:postcode":"8430",
    "sg:province":"Steiermark",
    "wof:name":"Pennitz Peter",
    "wof:placetype":"venue"
},
  "geometry": {"coordinates":[15.5393381119,46.7804832458],"type":"Point"}
}