{
  "type": "Feature",
  "properties": {
    "addr:full":"Tirolweg 12 Tulfes Tirol 6075",
    "addr:housenumber":"12",
    "addr:postcode":"6075",
    "addr:street":"Tirolweg;Tirol",
    "iso:country":"AT",
    "sg:address":"Tirolweg 12",
    "sg:city":"Tulfes",
    "sg:orig_category":"Transportunternehmen",
    "sg:phone":"+43 676 3083081",
    "sg:postcode":"6075",
    "sg:province":"Tirol",
    "wof:name":"Roadrunner Transporte - Roehr Reinhard",
    "wof:placetype":"venue"
},
  "geometry": {"coordinates":[11.5363512039,47.257774353],"type":"Point"}
}