{
  "type": "Feature",
  "properties": {
    "iso:country":"AT",
    "sg:address":"Waidhofner Str 8",
    "sg:city":"B\u00f6hlerwerk",
    "sg:classifiers":[
        {
            "category":"Community Center",
            "subcategory":"Social",
            "type":"Public Place"
        }
    ],
    "sg:phone":"+43 7448 70070",
    "sg:postcode":"3333",
    "sg:province":"Nieder\u00f6sterreich",
    "sg:tags":[
        "profile"
    ],
    "wof:name":"B\u00f6hler-Ybbstal Profil GmbH",
    "wof:placetype":"venue"
},
  "geometry": {"coordinates":[9.1929798126,48.6895484924],"type":"Point"}
}