{
  "type": "Feature",
  "properties": {
    "iso:country":"AT",
    "sg:address":"Dorfstr 63",
    "sg:city":"Wartberg im M\u00fcrztal",
    "sg:orig_category":"Autohandel",
    "sg:phone":"+43 3858 31030",
    "sg:postcode":"8661",
    "sg:province":"Steiermark",
    "wof:name":"Krautinger Autohaus GesmbH",
    "wof:placetype":"venue"
},
  "geometry": {"coordinates":[15.5016536713,47.5282478333],"type":"Point"}
}