{
  "type": "Feature",
  "properties": {
    "addr:full":"Rennweg 79/81 Wien Wien 1030",
    "addr:housenumber":"79 / 81",
    "addr:postcode":"1030",
    "addr:street":"Rennweg",
    "iso:country":"AT",
    "sg:address":"Rennweg 79/81",
    "sg:city":"Wien",
    "sg:orig_category":"Tourismusunternehmen",
    "sg:phone":"+43 4315 954969",
    "sg:postcode":"1030",
    "sg:province":"Wien",
    "wof:name":"ARCADE HandelsgesmbH",
    "wof:placetype":"venue"
},
  "geometry": {"coordinates":[16.3937225342,48.1926345825],"type":"Point"}
}