{
  "type": "Feature",
  "properties": {
    "addr:full":"W\u00e4hringer Str 30 Wien Wien 1090",
    "addr:postcode":"1090",
    "addr:street":"Str 30",
    "iso:country":"AT",
    "sg:address":"W\u00e4hringer Str 30",
    "sg:city":"Wien",
    "sg:orig_category":"Sprachschulen U -Unterricht, Institute",
    "sg:phone":"+43 4315 0275311",
    "sg:postcode":"1090",
    "sg:province":"Wien",
    "sg:website":"ambafrance-at.org/vienne/cours",
    "wof:name":"Institut francais de Vienne",
    "wof:placetype":"venue"
},
  "geometry": {"coordinates":[16.3573436737,48.219543457],"type":"Point"}
}