{
  "type": "Feature",
  "properties": {
    "addr:full":"K\u00f6rblerg 42 Graz Steiermark 8010",
    "addr:housenumber":"42",
    "addr:postcode":"8010",
    "addr:street":"Koerblerg",
    "iso:country":"AT",
    "sg:address":"K\u00f6rblerg 42",
    "sg:city":"Graz",
    "sg:orig_category":"Gesundheitsvorsorge",
    "sg:phone":"+43 4331 6722866",
    "sg:postcode":"8010",
    "sg:province":"Steiermark",
    "wof:name":"EccoCell Biotechnologie GmbH",
    "wof:placetype":"venue"
},
  "geometry": {"coordinates":[15.4431800842,47.0685653687],"type":"Point"}
}