{
  "type": "Feature",
  "properties": {
    "addr:full":"Judenburger Str 20 Fohnsdorf Steiermark 8753",
    "addr:housenumber":"20",
    "addr:postcode":"8753",
    "addr:street":"Str",
    "iso:country":"AT",
    "sg:address":"Judenburger Str 20",
    "sg:city":"Fohnsdorf",
    "sg:orig_category":"Musikgruppen",
    "sg:phone":"+43 676 7584572",
    "sg:postcode":"8753",
    "sg:province":"Steiermark",
    "wof:name":"BERGWIND 2000",
    "wof:placetype":"venue"
},
  "geometry": {"coordinates":[14.6787900925,47.2048721313],"type":"Point"}
}