{
  "type": "Feature",
  "properties": {
    "iso:country":"AT",
    "sg:address":"Nr 60",
    "sg:city":"Gro\u00df Gerungs",
    "sg:orig_category":"Autobusunternehmen",
    "sg:phone":"+43 2812 8328",
    "sg:postcode":"3920",
    "sg:province":"Nieder\u00f6sterreich",
    "wof:name":"Eschelm\u00fcller Christian",
    "wof:placetype":"venue"
},
  "geometry": {"coordinates":[14.9585752487,48.5740394592],"type":"Point"}
}