{
  "type": "Feature",
  "properties": {
    "addr:full":"Feldg 16 Halbturn Burgenland 7131",
    "addr:housenumber":"16",
    "addr:postcode":"7131",
    "addr:street":"Feldg",
    "iso:country":"AT",
    "sg:address":"Feldg 16",
    "sg:city":"Halbturn",
    "sg:orig_category":"Maler, Anstreicher U Lackierer",
    "sg:phone":"+43 2172 88440",
    "sg:postcode":"7131",
    "sg:province":"Burgenland",
    "wof:name":"Zinkl Robert",
    "wof:placetype":"venue"
},
  "geometry": {"coordinates":[16.9740753174,47.8713951111],"type":"Point"}
}