{
  "type": "Feature",
  "properties": {
    "addr:full":"Wittelsbachstr 1 Wien Wien 1020",
    "addr:housenumber":"1",
    "addr:postcode":"1020",
    "addr:street":"Wittelsbachstr",
    "iso:country":"AT",
    "sg:address":"Wittelsbachstr 1",
    "sg:city":"Wien",
    "sg:orig_category":"Webdesign",
    "sg:phone":"+43 1 5451856",
    "sg:postcode":"1020",
    "sg:province":"Wien",
    "wof:name":"blacksheep productions",
    "wof:placetype":"venue"
},
  "geometry": {"coordinates":[16.398267746,48.2062225342],"type":"Point"}
}