{
  "type": "Feature",
  "properties": {
    "iso:country":"AT",
    "sg:address":"Franztalstrasse 1",
    "sg:city":"Salzburg",
    "sg:orig_category":"Dust Filtering Systems, Mobile, For Industrial Use",
    "sg:phone":"+43 662 433639",
    "sg:postcode":"5020",
    "sg:province":"Salzburg",
    "sg:website":"exomat.at",
    "wof:name":"GLANTSCHNIG-EXOMAT Absauganlagen Ges.m.b.H. & Co KG",
    "wof:placetype":"venue"
},
  "geometry": {"coordinates":[13.021115303,47.8267669678],"type":"Point"}
}