{
  "type": "Feature",
  "properties": {
    "addr:full":"Guglg 43 Entertainmentcenter Top E08 Wien Wien 1030",
    "addr:housenumber":"43;e08",
    "addr:postcode":"1030",
    "addr:street":"Guglg",
    "iso:country":"AT",
    "sg:address":"Guglg 43 Entertainmentcenter Top E08",
    "sg:city":"Wien",
    "sg:classifiers":[
        {
            "category":"Personal",
            "subcategory":"Adult",
            "type":"Services"
        }
    ],
    "sg:phone":"+43 4317 437990",
    "sg:postcode":"1030",
    "sg:province":"Wien",
    "sg:tags":[
        "sex-shops"
    ],
    "wof:name":"ORION Erotik Fachgesch\u00e4ft",
    "wof:placetype":"venue"
},
  "geometry": {"coordinates":[16.4025096893,48.1936683655],"type":"Point"}
}