{
  "type": "Feature",
  "properties": {
    "addr:full":"Schweizer G 12 Lienz Tirol 9900",
    "addr:housenumber":"12",
    "addr:postcode":"9900",
    "addr:street":"Schweizer G;Tirol",
    "iso:country":"AT",
    "sg:address":"Schweizer G 12",
    "sg:city":"Lienz",
    "sg:orig_category":"Gerbereien",
    "sg:phone":"+43 4852 620810",
    "sg:postcode":"9900",
    "sg:province":"Tirol",
    "wof:name":"Wimmer Josef",
    "wof:placetype":"venue"
},
  "geometry": {"coordinates":[12.763628006,46.8309364319],"type":"Point"}
}