{
  "type": "Feature",
  "properties": {
    "addr:full":"Salzburger Str 293 Linz Ober\u00f6sterreich 4030",
    "addr:housenumber":"293",
    "addr:postcode":"4030",
    "addr:street":"Salzburger Str",
    "iso:country":"AT",
    "sg:address":"Salzburger Str 293",
    "sg:city":"Linz",
    "sg:orig_category":"Botendienste",
    "sg:phone":"+43 664 3821795",
    "sg:postcode":"4030",
    "sg:province":"Ober\u00f6sterreich",
    "wof:name":"SPS Eiltransporte",
    "wof:placetype":"venue"
},
  "geometry": {"coordinates":[14.2772188187,48.2520446777],"type":"Point"}
}