{
  "type": "Feature",
  "properties": {
    "addr:full":"Stadtplatz 27 Mattighofen Ober\u00f6sterreich 5230",
    "addr:housenumber":"27",
    "addr:postcode":"5230",
    "addr:street":"Stadtplatz",
    "iso:country":"AT",
    "sg:address":"Stadtplatz 27",
    "sg:city":"Mattighofen",
    "sg:classifiers":[
        {
            "category":"Banks & Credit Unions",
            "subcategory":"Investment Brokerage",
            "type":"Services"
        }
    ],
    "sg:phone":"+43 7742 2553",
    "sg:postcode":"5230",
    "sg:province":"Ober\u00f6sterreich",
    "sg:tags":[
        "case",
        "spectacle"
    ],
    "wof:name":"Brillenmacher Slatner u. Reisinger Ges.m.b.H.",
    "wof:placetype":"venue"
},
  "geometry": {"coordinates":[13.1501836777,48.1037635803],"type":"Point"}
}