{
  "type": "Feature",
  "properties": {
    "iso:country":"AT",
    "sg:address":"Nr 283",
    "sg:city":"Bad Mitterndorf",
    "sg:classifiers":[
        {
            "category":"Travel",
            "subcategory":"Hotels & Motels",
            "type":"Entertainment"
        }
    ],
    "sg:phone":"+43 4336 232595",
    "sg:postcode":"8983",
    "sg:province":"Steiermark",
    "wof:name":"Hotel-Pension Hubertushof",
    "wof:placetype":"venue"
},
  "geometry": {"coordinates":[13.9318876266,47.5550498962],"type":"Point"}
}