{
  "type": "Feature",
  "properties": {
    "addr:full":"Nr 8 Sitzendorf an der Schmida Nieder\u00f6sterreich 3714",
    "addr:postcode":"3714",
    "addr:street":"Nr;An",
    "iso:country":"AT",
    "sg:address":"Nr 8",
    "sg:city":"Sitzendorf an der Schmida",
    "sg:orig_category":"Weine / Einzelhandel",
    "sg:phone":"+43 2959 3261",
    "sg:postcode":"3714",
    "sg:province":"Nieder\u00f6sterreich",
    "wof:name":"Diem Josef jun",
    "wof:placetype":"venue"
},
  "geometry": {"coordinates":[15.9418134689,48.5982818604],"type":"Point"}
}