{
  "type": "Feature",
  "properties": {
    "addr:full":"Effingerg 12/4/19 Wien Wien 1160",
    "addr:housenumber":"12 / 4 / 19",
    "addr:postcode":"1160",
    "addr:street":"Effingerg",
    "iso:country":"AT",
    "sg:address":"Effingerg 12/4/19",
    "sg:city":"Wien",
    "sg:orig_category":"Webdesign",
    "sg:phone":"+43 699 11364794",
    "sg:postcode":"1160",
    "sg:province":"Wien",
    "wof:name":"BCS",
    "wof:placetype":"venue"
},
  "geometry": {"coordinates":[16.2961292267,48.214931488],"type":"Point"}
}