{
  "type": "Feature",
  "properties": {
    "addr:full":"Nr 14 Rosegg K\u00e4rnten 9232",
    "addr:postcode":"9232",
    "addr:street":"Nr 14;Kaernten",
    "iso:country":"AT",
    "sg:address":"Nr 14",
    "sg:city":"Rosegg",
    "sg:orig_category":"Non-Classified Establishments",
    "sg:phone":"+43 4253 8124",
    "sg:postcode":"9232",
    "sg:province":"K\u00e4rnten",
    "wof:name":"Kaiser Thomas",
    "wof:placetype":"venue"
},
  "geometry": {"coordinates":[14.0191602707,46.5909347534],"type":"Point"}
}