{
  "type": "Feature",
  "properties": {
    "addr:full":"Brielgasse 27 Bregenz Vorarlberg 6900",
    "addr:housenumber":"27",
    "addr:postcode":"6900",
    "addr:street":"Brielgasse",
    "iso:country":"AT",
    "sg:address":"Brielgasse 27",
    "sg:city":"Bregenz",
    "sg:classifiers":[
        {
            "category":"Home & Garden",
            "subcategory":"Furniture",
            "type":"Retail Goods"
        }
    ],
    "sg:phone":"+43 5574 75374",
    "sg:postcode":"6900",
    "sg:province":"Vorarlberg",
    "sg:tags":[
        "designer"
    ],
    "sg:website":"tischlerei-sieber.at",
    "wof:name":"Hubert Sieber",
    "wof:placetype":"venue"
},
  "geometry": {"coordinates":[9.7289457321,47.4929466248],"type":"Point"}
}