{
  "type": "Feature",
  "properties": {
    "addr:full":"St.-Veit-G 76 Wien Wien 1130",
    "addr:housenumber":"76",
    "addr:postcode":"1130",
    "addr:street":"St.-Veit-G",
    "iso:country":"AT",
    "sg:address":"St.-Veit-G 76",
    "sg:city":"Wien",
    "sg:orig_category":"Baumeister",
    "sg:phone":"+43 4318 793808",
    "sg:postcode":"1130",
    "sg:province":"Wien",
    "sg:website":"horvathaus.at",
    "wof:name":"Horvat Planungs- Bau- u HandelsgesmbH",
    "wof:placetype":"venue"
},
  "geometry": {"coordinates":[16.2869567871,48.1904296875],"type":"Point"}
}