{
  "type": "Feature",
  "properties": {
    "addr:full":"Nr 49 Rastenfeld Nieder\u00f6sterreich 3532",
    "addr:postcode":"3532",
    "addr:street":"Nr;Rastenfeld",
    "iso:country":"AT",
    "sg:address":"Nr 49",
    "sg:city":"Rastenfeld",
    "sg:orig_category":"Schlossereien",
    "sg:phone":"+43 2826 238",
    "sg:postcode":"3532",
    "sg:province":"Nieder\u00f6sterreich",
    "wof:name":"Sillipp Ferdinand",
    "wof:placetype":"venue"
},
  "geometry": {"coordinates":[15.3316497803,48.5734481812],"type":"Point"}
}