{
  "type": "Feature",
  "properties": {
    "addr:full":"Schr\u00f6dingerstrasse 61 Klagenfurt K\u00e4rnten 9020",
    "addr:housenumber":"61",
    "addr:postcode":"9020",
    "addr:street":"Schroedingerstrasse;Kaernten",
    "iso:country":"AT",
    "sg:address":"Schr\u00f6dingerstrasse 61",
    "sg:city":"Klagenfurt",
    "sg:classifiers":[
        {
            "category":"Juice Bar",
            "subcategory":"None",
            "type":"Food & Drink"
        }
    ],
    "sg:phone":"+43 463 33444",
    "sg:postcode":"9020",
    "sg:province":"K\u00e4rnten",
    "sg:tags":[
        "apple"
    ],
    "sg:website":"pago.cc",
    "wof:name":"PAGO International Ges.m.b.H.",
    "wof:placetype":"venue"
},
  "geometry": {"coordinates":[14.3137111664,46.600933075],"type":"Point"}
}