{
  "type": "Feature",
  "properties": {
    "iso:country":"AT",
    "sg:address":"Prinz-Eugen-Str 3a",
    "sg:city":"Pasching",
    "sg:orig_category":"Transportunternehmen",
    "sg:phone":"+43 7229 72592",
    "sg:postcode":"4061",
    "sg:province":"Ober\u00f6sterreich",
    "sg:website":"simmerer.at",
    "wof:name":"Simmerer Josef Transportunternehmen GesmbH",
    "wof:placetype":"venue"
},
  "geometry": {"coordinates":[14.2454223633,48.2400016785],"type":"Point"}
}