{
  "type": "Feature",
  "properties": {
    "iso:country":"AT",
    "sg:address":"Bundesstrasse 25 ",
    "sg:city":"Lend",
    "sg:classifiers":[
        {
            "category":"Organizations",
            "subcategory":"Labor Organization",
            "type":"Services"
        }
    ],
    "sg:phone":"+43 6416 6500311",
    "sg:postcode":"5651",
    "sg:province":"Salzburg",
    "sg:tags":[
        "on-site",
        "waste-water",
        "treatment",
        "system"
    ],
    "sg:website":"www.sag.at",
    "wof:name":"Alutech Lend",
    "wof:placetype":"venue"
},
  "geometry": {"coordinates":[13.0434465408,47.299446106],"type":"Point"}
}