{
  "type": "Feature",
  "properties": {
    "iso:country":"AT",
    "sg:address":"G\u00fcttling",
    "sg:city":"Neumarkt im Hausruckkreis",
    "sg:orig_category":"Feuerwehren",
    "sg:phone":"+43 7733 6561",
    "sg:postcode":"4720",
    "sg:province":"Ober\u00f6sterreich",
    "wof:name":"Freiwillige Feuerwehr G\u00fcttling",
    "wof:placetype":"venue"
},
  "geometry": {"coordinates":[13.713467598,48.281955719],"type":"Point"}
}