{
  "type": "Feature",
  "properties": {
    "iso:country":"AT",
    "sg:address":"Heindlkai 11",
    "sg:city":"Mauthausen",
    "sg:orig_category":"Restaurants: Chinesisch",
    "sg:phone":"+43 7238 2180",
    "sg:postcode":"4310",
    "sg:province":"Ober\u00f6sterreich",
    "wof:name":"Chinarestaurant Hong Kong City",
    "wof:placetype":"venue"
},
  "geometry": {"coordinates":[14.5172357559,48.240196228],"type":"Point"}
}