{
  "type": "Feature",
  "properties": {
    "iso:country":"AT",
    "sg:address":"Gasener Str 2",
    "sg:city":"Birkfeld",
    "sg:orig_category":"Banken U Sparkassen",
    "sg:phone":"+43 4331 7421380",
    "sg:postcode":"8190",
    "sg:province":"Steiermark",
    "wof:name":"Volksbank S\u00fcd-Oststeiermark reg GenmbH",
    "wof:placetype":"venue"
},
  "geometry": {"coordinates":[15.6909856796,47.34897995],"type":"Point"}
}