{
  "type": "Feature",
  "properties": {
    "addr:full":"Hauptpl 7 Stainz Steiermark 8510",
    "addr:housenumber":"7",
    "addr:postcode":"8510",
    "addr:street":"Hauptpl",
    "iso:country":"AT",
    "sg:address":"Hauptpl 7",
    "sg:city":"Stainz",
    "sg:orig_category":"Fotografen",
    "sg:phone":"+43 3463 3337",
    "sg:postcode":"8510",
    "sg:province":"Steiermark",
    "wof:name":"Foto Strametz",
    "wof:placetype":"venue"
},
  "geometry": {"coordinates":[15.2651557922,46.8940505981],"type":"Point"}
}