{
  "type": "Feature",
  "properties": {
    "iso:country":"AT",
    "sg:address":"Flatschacher Weg 2",
    "sg:city":"Zeltweg",
    "sg:orig_category":"Autohandel",
    "sg:phone":"+43 4335 7722600",
    "sg:postcode":"8740",
    "sg:province":"Steiermark",
    "wof:name":"Autohaus A Kampl KG",
    "wof:placetype":"venue"
},
  "geometry": {"coordinates":[14.764840126,47.1973304749],"type":"Point"}
}