{
  "type": "Feature",
  "properties": {
    "iso:country":"AT",
    "sg:address":"Linzer Str 104",
    "sg:city":"Arbesbach",
    "sg:orig_category":"Friseure U Frisiersalons",
    "sg:phone":"+43 4328 137284",
    "sg:postcode":"3925",
    "sg:province":"Nieder\u00f6sterreich",
    "wof:name":"Wei\u00dfinger Ingrid",
    "wof:placetype":"venue"
},
  "geometry": {"coordinates":[14.9513788223,48.4919166565],"type":"Point"}
}