{
  "type": "Feature",
  "properties": {
    "addr:full":"Johannesstr 7 Walchsee Tirol 6344",
    "addr:housenumber":"7",
    "addr:postcode":"6344",
    "addr:street":"Johannesstr;Tirol",
    "iso:country":"AT",
    "sg:address":"Johannesstr 7",
    "sg:city":"Walchsee",
    "sg:orig_category":"Blumeneinzelhandel",
    "sg:phone":"+43 5374 50290",
    "sg:postcode":"6344",
    "sg:province":"Tirol",
    "wof:name":"BLUMENSERVICE - Werndle Helmut",
    "wof:placetype":"venue"
},
  "geometry": {"coordinates":[12.3269033432,47.6512413025],"type":"Point"}
}