{
  "type": "Feature",
  "properties": {
    "addr:full":"Dorfstr 6 Lieboch Steiermark 8501",
    "addr:housenumber":"6",
    "addr:postcode":"8501",
    "addr:street":"Dorfstr",
    "iso:country":"AT",
    "sg:address":"Dorfstr 6",
    "sg:city":"Lieboch",
    "sg:orig_category":"Installationsunternehmen",
    "sg:phone":"+43 3136 612880",
    "sg:postcode":"8501",
    "sg:province":"Steiermark",
    "sg:website":"www.bodlos.at",
    "wof:name":"Bodlos Josef GesmbH",
    "wof:placetype":"venue"
},
  "geometry": {"coordinates":[15.3335847855,46.9752082825],"type":"Point"}
}