{
  "type": "Feature",
  "properties": {
    "iso:country":"AT",
    "sg:address":"Bahnstr 19",
    "sg:city":"Knittelfeld",
    "sg:orig_category":"Restaurants: Chinesisch",
    "sg:phone":"+43 4335 1282485",
    "sg:postcode":"8720",
    "sg:province":"Steiermark",
    "wof:name":"Hou Hsien Fang GesmbH",
    "wof:placetype":"venue"
},
  "geometry": {"coordinates":[14.8320302963,47.2156791687],"type":"Point"}
}