{
  "type": "Feature",
  "properties": {
    "iso:country":"AT",
    "sg:address":"Gr\u00fcnbergweg 3",
    "sg:city":"Gmunden",
    "sg:classifiers":[
        {
            "category":"Taxi",
            "type":"Transportation"
        }
    ],
    "sg:phone":"+43 4366 43239510",
    "sg:postcode":"4810",
    "sg:province":"Ober\u00f6sterreich",
    "sg:tags":[
        "personentransporte",
        "u"
    ],
    "wof:name":"Auto Taxi Karl Harringer",
    "wof:placetype":"venue"
},
  "geometry": {"coordinates":[13.7981462479,47.918598175],"type":"Point"}
}