{
  "type": "Feature",
  "properties": {
    "iso:country":"AT",
    "sg:address":"Lustenauer Str 12",
    "sg:city":"Dornbirn",
    "sg:orig_category":"Bettfedernreinigung",
    "sg:phone":"+43 5572 22279",
    "sg:postcode":"6850",
    "sg:province":"Vorarlberg",
    "wof:name":"Feuerstein Betten GesmbH",
    "wof:placetype":"venue"
},
  "geometry": {"coordinates":[9.7378816605,47.4064331055],"type":"Point"}
}