{
  "type": "Feature",
  "properties": {
    "addr:full":"Geusaug 49 Wien Wien 1030",
    "addr:housenumber":"49",
    "addr:postcode":"1030",
    "addr:street":"Geusaug",
    "iso:country":"AT",
    "sg:address":"Geusaug 49",
    "sg:city":"Wien",
    "sg:orig_category":"Architekten",
    "sg:phone":"+43 1 7121672",
    "sg:postcode":"1030",
    "sg:province":"Wien",
    "wof:name":"Winklehner Peter Arch Dipl-Ing",
    "wof:placetype":"venue"
},
  "geometry": {"coordinates":[16.395866394,48.2030982971],"type":"Point"}
}