{
  "type": "Feature",
  "properties": {
    "iso:country":"AT",
    "sg:address":"Tuttenhofstr 23",
    "sg:city":"Langenzersdorf",
    "sg:orig_category":"\u00c3\u201erzte / F Allgemeinmedizin",
    "sg:phone":"+43 2244 51310",
    "sg:postcode":"2103",
    "sg:province":"Nieder\u00f6sterreich",
    "wof:name":"Hickelsberger Johannes Dr",
    "wof:placetype":"venue"
},
  "geometry": {"coordinates":[16.3505382538,48.3157196045],"type":"Point"}
}