{
  "type": "Feature",
  "properties": {
    "addr:full":"W\u00f6rthstr 3 Amstetten Nieder\u00f6sterreich 3300",
    "addr:housenumber":"3",
    "addr:postcode":"3300",
    "addr:street":"Woerthstr;Niederoesterreich",
    "iso:country":"AT",
    "sg:address":"W\u00f6rthstr 3",
    "sg:city":"Amstetten",
    "sg:orig_category":"Spielwaren U Spiele",
    "sg:phone":"+43 4374 7267241",
    "sg:postcode":"3300",
    "sg:province":"Nieder\u00f6sterreich",
    "wof:name":"Piribauer-Wegscheider KG",
    "wof:placetype":"venue"
},
  "geometry": {"coordinates":[14.8694553375,48.1229858398],"type":"Point"}
}