{
  "type": "Feature",
  "properties": {
    "addr:full":"Hauptstr. 11 M\u00f6derbrugg Steiermark 8763",
    "addr:housenumber":"11",
    "addr:postcode":"8763",
    "addr:street":"Hauptstr.",
    "iso:country":"AT",
    "sg:address":"Hauptstr. 11",
    "sg:city":"M\u00f6derbrugg",
    "sg:classifiers":[
        {
            "category":"Bars & Pubs",
            "subcategory":"Nightclub",
            "type":"Food & Drink"
        }
    ],
    "sg:phone":"+43 4335 712331",
    "sg:postcode":"8763",
    "sg:province":"Steiermark",
    "sg:tags":[
        "cake",
        "bread"
    ],
    "wof:name":"HEINRICH BRANDL",
    "wof:placetype":"venue"
},
  "geometry": {"coordinates":[14.4812717438,47.2794494629],"type":"Point"}
}