{
  "type": "Feature",
  "properties": {
    "addr:full":"Penzinger Str 47 Wien Wien 1140",
    "addr:postcode":"1140",
    "addr:street":"Str 47",
    "iso:country":"AT",
    "sg:address":"Penzinger Str 47",
    "sg:city":"Wien",
    "sg:orig_category":"Immobilienmakler",
    "sg:phone":"+43 4318 946457",
    "sg:postcode":"1140",
    "sg:province":"Wien",
    "wof:name":"Ernst Maria u Wilhelm GesmbH",
    "wof:placetype":"venue"
},
  "geometry": {"coordinates":[16.3071022034,48.1895561218],"type":"Point"}
}