{
  "type": "Feature",
  "properties": {
    "addr:full":"S\u00e4gerstr 5 Feldkirch Vorarlberg 6800",
    "addr:housenumber":"5",
    "addr:postcode":"6800",
    "addr:street":"Saegerstr",
    "iso:country":"AT",
    "sg:address":"S\u00e4gerstr 5",
    "sg:city":"Feldkirch",
    "sg:orig_category":"Tischlereien",
    "sg:phone":"+43 5522 721370",
    "sg:postcode":"6800",
    "sg:province":"Vorarlberg",
    "wof:name":"Allg\u00e4uer Josef",
    "wof:placetype":"venue"
},
  "geometry": {"coordinates":[9.5967845917,47.2381515503],"type":"Point"}
}