{
  "type": "Feature",
  "properties": {
    "addr:full":"Industriestr 28 St. Johann im Pongau Salzburg 5600",
    "addr:housenumber":"28",
    "addr:postcode":"5600",
    "addr:street":"Industriestr;Salzburg",
    "iso:country":"AT",
    "sg:address":"Industriestr 28",
    "sg:city":"St. Johann im Pongau",
    "sg:orig_category":"Innenarchitekten",
    "sg:phone":"+43 6412 8161",
    "sg:postcode":"5600",
    "sg:province":"Salzburg",
    "wof:name":"Obinger Michael J",
    "wof:placetype":"venue"
},
  "geometry": {"coordinates":[13.2006835938,47.3544540405],"type":"Point"}
}