{
  "type": "Feature",
  "properties": {
    "addr:full":"Dambachstr 11 Garsten Ober\u00f6sterreich 4451",
    "addr:housenumber":"11",
    "addr:postcode":"4451",
    "addr:street":"Dambachstr",
    "iso:country":"AT",
    "sg:address":"Dambachstr 11",
    "sg:city":"Garsten",
    "sg:orig_category":"Tischlereien",
    "sg:phone":"+43 7252 54792",
    "sg:postcode":"4451",
    "sg:province":"Ober\u00f6sterreich",
    "wof:name":"Wieser Karl",
    "wof:placetype":"venue"
},
  "geometry": {"coordinates":[14.4488067627,47.9824562073],"type":"Point"}
}