{
  "type": "Feature",
  "properties": {
    "addr:full":"Untere Sparchen 18 Kufstein Tirol 6330",
    "addr:housenumber":"18",
    "addr:postcode":"6330",
    "addr:street":"Untere Sparchen;Tirol",
    "iso:country":"AT",
    "sg:address":"Untere Sparchen 18",
    "sg:city":"Kufstein",
    "sg:orig_category":"Autobusunternehmen",
    "sg:phone":"+43 4353 72672762",
    "sg:postcode":"6330",
    "sg:province":"Tirol",
    "wof:name":"Wechselberger Egid Touristik GesmbH Garage",
    "wof:placetype":"venue"
},
  "geometry": {"coordinates":[12.1788101196,47.5990333557],"type":"Point"}
}