{
  "type": "Feature",
  "properties": {
    "addr:full":"Leopoldstr 34 Innsbruck Tirol 6020",
    "addr:housenumber":"34",
    "addr:postcode":"6020",
    "addr:street":"Leopoldstr;Tirol",
    "iso:country":"AT",
    "sg:address":"Leopoldstr 34",
    "sg:city":"Innsbruck",
    "sg:orig_category":"Weine / Gro\u00c3\u0178handel",
    "sg:phone":"+43 512 579535",
    "sg:postcode":"6020",
    "sg:province":"Tirol",
    "wof:name":"Mayr Anton GesmbH & Co KG",
    "wof:placetype":"venue"
},
  "geometry": {"coordinates":[11.3966941833,47.2591972351],"type":"Point"}
}