{
  "type": "Feature",
  "properties": {
    "iso:country":"AT",
    "sg:address":"Hollerg 42",
    "sg:city":"Wien",
    "sg:classifiers":[
        {
            "category":"Restaurant",
            "type":"Food & Drink"
        }
    ],
    "sg:phone":"+43 1 8920208",
    "sg:postcode":"1150",
    "sg:province":"Wien",
    "wof:name":"Wurzelsepp",
    "wof:placetype":"venue"
},
  "geometry": {"coordinates":[16.3243732452,48.188583374],"type":"Point"}
}