{
  "type": "Feature",
  "properties": {
    "addr:full":"Universit\u00e4tsstr 66/I Klagenfurt K\u00e4rnten 9020",
    "addr:housenumber":"66 / i",
    "addr:postcode":"9020",
    "addr:street":"Universitaetsstr;Kaernten",
    "iso:country":"AT",
    "sg:address":"Universit\u00e4tsstr 66/I",
    "sg:city":"Klagenfurt",
    "sg:orig_category":"Lebens- U Sozialberatung",
    "sg:phone":"+43 4346 323482",
    "sg:postcode":"9020",
    "sg:province":"K\u00e4rnten",
    "wof:name":"Psychologische Studentenberatung",
    "wof:placetype":"venue"
},
  "geometry": {"coordinates":[14.3274202347,46.6254196167],"type":"Point"}
}