{
  "type": "Feature",
  "properties": {
    "addr:full":"Hauptpl 24 Pillichsdorf Nieder\u00f6sterreich 2211",
    "addr:housenumber":"24",
    "addr:postcode":"2211",
    "addr:street":"Hauptpl",
    "iso:country":"AT",
    "sg:address":"Hauptpl 24",
    "sg:city":"Pillichsdorf",
    "sg:orig_category":"Fleischhauereien",
    "sg:phone":"+43 2245 2471",
    "sg:postcode":"2211",
    "sg:province":"Nieder\u00f6sterreich",
    "wof:name":"M\u00fcllebner Alois",
    "wof:placetype":"venue"
},
  "geometry": {"coordinates":[16.5405578613,48.3644332886],"type":"Point"}
}