{
  "type": "Feature",
  "properties": {
    "addr:full":"Breitenleer Str 479 Wien Wien 1220",
    "addr:housenumber":"479",
    "addr:postcode":"1220",
    "iso:country":"AT",
    "sg:address":"Breitenleer Str 479",
    "sg:city":"Wien",
    "sg:classifiers":[
        {
            "category":"Home & Garden",
            "subcategory":"Garden Supply",
            "type":"Retail Goods"
        }
    ],
    "sg:phone":"+43 4317 3435860",
    "sg:postcode":"1220",
    "sg:province":"Wien",
    "sg:tags":[
        "schotter",
        "sand",
        "u"
    ],
    "wof:name":"Readymix Kiesunion AG",
    "wof:placetype":"venue"
},
  "geometry": {"coordinates":[16.5358505249,48.2487602234],"type":"Point"}
}