{
  "type": "Feature",
  "properties": {
    "addr:full":"Nr 192 Golling an der Salzach Salzburg 5440",
    "addr:postcode":"5440",
    "addr:street":"Nr;Golling",
    "iso:country":"AT",
    "sg:address":"Nr 192",
    "sg:city":"Golling an der Salzach",
    "sg:orig_category":"Glasereien",
    "sg:phone":"+43 4362 448607",
    "sg:postcode":"5440",
    "sg:province":"Salzburg",
    "wof:name":"Glaserei Norbert Zechner",
    "wof:placetype":"venue"
},
  "geometry": {"coordinates":[13.1678924561,47.5982322693],"type":"Point"}
}