{
  "type": "Feature",
  "properties": {
    "iso:country":"AT",
    "sg:address":"Haus am Berg 347",
    "sg:city":"Alpbach",
    "sg:orig_category":"Appartements / Ferienwohnungen",
    "sg:phone":"+43 5336 5276",
    "sg:postcode":"6236",
    "sg:province":"Tirol",
    "wof:name":"Eigentler KEG",
    "wof:placetype":"venue"
},
  "geometry": {"coordinates":[11.9435110092,47.3986091614],"type":"Point"}
}