{
  "type": "Feature",
  "properties": {
    "addr:full":"Nr 111 St. Ruprecht an der Raab Steiermark 8181",
    "addr:postcode":"8181",
    "addr:street":"Nr 111",
    "iso:country":"AT",
    "sg:address":"Nr 111",
    "sg:city":"St. Ruprecht an der Raab",
    "sg:orig_category":"Transportunternehmen",
    "sg:phone":"+43 3177 2417",
    "sg:postcode":"8181",
    "sg:province":"Steiermark",
    "wof:name":"Neuhold GesmbH",
    "wof:placetype":"venue"
},
  "geometry": {"coordinates":[15.6658182144,47.1803436279],"type":"Point"}
}