{
  "type": "Feature",
  "properties": {
    "iso:country":"AT",
    "sg:address":"Dorfstr 17",
    "sg:city":"Bergheim",
    "sg:orig_category":"Raumausstattung",
    "sg:phone":"+43 4366 2452007",
    "sg:postcode":"5101",
    "sg:province":"Salzburg",
    "wof:name":"Unterer Georg",
    "wof:placetype":"venue"
},
  "geometry": {"coordinates":[13.0247049332,47.8378791809],"type":"Point"}
}