{
  "type": "Feature",
  "properties": {
    "addr:full":"Hochstr 129 Perchtoldsdorf Nieder\u00f6sterreich 2380",
    "addr:housenumber":"129",
    "addr:postcode":"2380",
    "iso:country":"AT",
    "sg:address":"Hochstr 129",
    "sg:city":"Perchtoldsdorf",
    "sg:orig_category":"Heurigen / Buschenschank",
    "sg:phone":"+43 4318 659660",
    "sg:postcode":"2380",
    "sg:province":"Nieder\u00f6sterreich",
    "wof:name":"Zechmeister Karl u Eva",
    "wof:placetype":"venue"
},
  "geometry": {"coordinates":[16.2596321106,48.1283493042],"type":"Point"}
}