{
  "type": "Feature",
  "properties": {
    "addr:full":"Nr 138 Aigen im Ennstal Steiermark 8943",
    "addr:postcode":"8943",
    "addr:street":"Nr 138",
    "iso:country":"AT",
    "sg:address":"Nr 138",
    "sg:city":"Aigen im Ennstal",
    "sg:orig_category":"Werbeagenturen",
    "sg:phone":"+43 3682 228350",
    "sg:postcode":"8943",
    "sg:province":"Steiermark",
    "wof:name":"aktiv B\u00fcro - Friedrich Auer",
    "wof:placetype":"venue"
},
  "geometry": {"coordinates":[14.1433391571,47.5205230713],"type":"Point"}
}