{
  "type": "Feature",
  "properties": {
    "iso:country":"AT",
    "sg:address":"Pog\u00f6riacher Str 14",
    "sg:city":"Latschach ober dem Faaker See",
    "sg:classifiers":[
        {
            "category":"Travel",
            "subcategory":"Hotels & Motels",
            "type":"Entertainment"
        }
    ],
    "sg:phone":"+43 4342 542747",
    "sg:postcode":"9582",
    "sg:province":"K\u00e4rnten",
    "wof:name":"Pog\u00f6riacherhof - Familien- Golf- u Sporthotel",
    "wof:placetype":"venue"
},
  "geometry": {"coordinates":[13.9084186554,46.5558319092],"type":"Point"}
}