{
  "type": "Feature",
  "properties": {
    "iso:country":"AT",
    "sg:address":"Schulgasse 35",
    "sg:city":"Kottingbrunn",
    "sg:classifiers":[
        {
            "category":"Banks & Credit Unions",
            "subcategory":"Investment Brokerage",
            "type":"Services"
        }
    ],
    "sg:phone":"+43 2252 74555",
    "sg:postcode":"2542",
    "sg:province":"Nieder\u00f6sterreich",
    "sg:tags":[
        "grip",
        "climbing"
    ],
    "wof:name":"Flash-Sportmanagement GmbH",
    "wof:placetype":"venue"
},
  "geometry": {"coordinates":[16.2324085236,47.9457244873],"type":"Point"}
}