{
  "type": "Feature",
  "properties": {
    "iso:country":"AT",
    "sg:address":"Gewerbestr. 6",
    "sg:city":"Seekirchen am Wallersee",
    "sg:classifiers":[
        {
            "category":"Real Estate",
            "subcategory":"Surveying",
            "type":"Services"
        }
    ],
    "sg:phone":"+43 4362 1262060",
    "sg:postcode":"5201",
    "sg:province":"Salzburg",
    "sg:tags":[
        "equipment",
        "material",
        "good",
        "-",
        "handling"
    ],
    "wof:name":"W. SCHMIDT GES. MBH",
    "wof:placetype":"venue"
},
  "geometry": {"coordinates":[13.1206388474,47.8871192932],"type":"Point"}
}