{
  "type": "Feature",
  "properties": {
    "iso:country":"AT",
    "sg:address":"Rosenbergstr 1-3",
    "sg:city":"Klagenfurt",
    "sg:orig_category":"Non-Classified Establishments",
    "sg:phone":"+43 463 58630",
    "sg:postcode":"9020",
    "sg:province":"K\u00e4rnten",
    "wof:name":"Windisch Kaserne",
    "wof:placetype":"venue"
},
  "geometry": {"coordinates":[14.3275203705,46.6257591248],"type":"Point"}
}