{
  "type": "Feature",
  "properties": {
    "addr:full":"Judenb\u00fchel 23 Radstadt Salzburg 5550",
    "addr:housenumber":"23",
    "addr:postcode":"5550",
    "addr:street":"Judenbuehel;Salzburg",
    "iso:country":"AT",
    "sg:address":"Judenb\u00fchel 23",
    "sg:city":"Radstadt",
    "sg:orig_category":"Lebensmittel / Einzelhandel",
    "sg:phone":"+43 6452 4288",
    "sg:postcode":"5550",
    "sg:province":"Salzburg",
    "wof:name":"Ziegler Elfriede",
    "wof:placetype":"venue"
},
  "geometry": {"coordinates":[13.4658269882,47.3852462769],"type":"Point"}
}