{
  "type": "Feature",
  "properties": {
    "addr:full":"Berg 27 St. Martin im Innkreis Ober\u00f6sterreich 4973",
    "addr:housenumber":"27",
    "addr:postcode":"4973",
    "addr:street":"Berg",
    "iso:country":"AT",
    "sg:address":"Berg 27",
    "sg:city":"St. Martin im Innkreis",
    "sg:orig_category":"Banken U Sparkassen",
    "sg:phone":"+43 4377 518369",
    "sg:postcode":"4973",
    "sg:province":"Ober\u00f6sterreich",
    "wof:name":"Raiffeisenbank Region Ried regGenmbH",
    "wof:placetype":"venue"
},
  "geometry": {"coordinates":[13.4162845612,48.2599983215],"type":"Point"}
}