{
  "type": "Feature",
  "properties": {
    "addr:full":"Gewerbegebiet 3 Kolsass Tirol 6114",
    "addr:housenumber":"3",
    "addr:postcode":"6114",
    "addr:street":"Gewerbegebiet;Tirol",
    "iso:country":"AT",
    "sg:address":"Gewerbegebiet 3",
    "sg:city":"Kolsass",
    "sg:classifiers":[
        {
            "category":"Structure",
            "subcategory":"Office Building",
            "type":"Public Place"
        }
    ],
    "sg:phone":"+43 5224 67870",
    "sg:postcode":"6114",
    "sg:province":"Tirol",
    "sg:tags":[
        "equipment",
        "ceiling",
        "integral",
        "ventilation"
    ],
    "sg:website":"lueftungstechnik.at",
    "wof:name":"Pataky L\u00fcftungstechnik Ges.m.b.H.",
    "wof:placetype":"venue"
},
  "geometry": {"coordinates":[11.6453399658,47.3049354553],"type":"Point"}
}