{
  "type": "Feature",
  "properties": {
    "addr:full":"Strandbadstrasse 10 Mattsee Salzburg 5163",
    "addr:housenumber":"10",
    "addr:postcode":"5163",
    "addr:street":"Strandbadstrasse;Salzburg",
    "iso:country":"AT",
    "sg:address":"Strandbadstrasse 10",
    "sg:city":"Mattsee",
    "sg:classifiers":[
        {
            "category":"Shopping",
            "subcategory":"Antiques",
            "type":"Retail Goods"
        }
    ],
    "sg:phone":"+43 6217 5475",
    "sg:postcode":"5163",
    "sg:province":"Salzburg",
    "sg:tags":[
        "fitting",
        "furniture"
    ],
    "wof:name":"Herbert Steiner",
    "wof:placetype":"venue"
},
  "geometry": {"coordinates":[13.1046361923,47.9723014832],"type":"Point"}
}