{
  "type": "Feature",
  "properties": {
    "addr:full":"Nr 56 Ebersdorf Steiermark 8273",
    "addr:postcode":"8273",
    "addr:street":"Nr 56",
    "iso:country":"AT",
    "sg:address":"Nr 56",
    "sg:city":"Ebersdorf",
    "sg:orig_category":"Fleisch-, Wurst- U Selchwaren / Erzeugung U Gro\u00c3\u0178handel",
    "sg:phone":"+43 4366 41603074",
    "sg:postcode":"8273",
    "sg:province":"Steiermark",
    "wof:name":"Ziegler Thomas",
    "wof:placetype":"venue"
},
  "geometry": {"coordinates":[15.9603052139,47.1987915039],"type":"Point"}
}