{
  "type": "Feature",
  "properties": {
    "addr:full":"Industriestr 20 Spittal an der Drau K\u00e4rnten 9800",
    "addr:housenumber":"20",
    "addr:postcode":"9800",
    "addr:street":"Industriestr;Kaernten",
    "iso:country":"AT",
    "sg:address":"Industriestr 20",
    "sg:city":"Spittal an der Drau",
    "sg:orig_category":"Metallbe- U -Verarbeitung",
    "sg:phone":"+43 4347 6224110",
    "sg:postcode":"9800",
    "sg:province":"K\u00e4rnten",
    "wof:name":"Ferro-Service Miklitsch W GesmbH",
    "wof:placetype":"venue"
},
  "geometry": {"coordinates":[13.5239076614,46.7839736938],"type":"Point"}
}