{
  "type": "Feature",
  "properties": {
    "iso:country":"AT",
    "sg:address":"Wultendorf 33",
    "sg:city":"Staatz-Kautendorf",
    "sg:classifiers":[
        {
            "category":"Home & Garden",
            "subcategory":"Furniture",
            "type":"Retail Goods"
        }
    ],
    "sg:phone":"+43 2524 24580",
    "sg:postcode":"2134",
    "sg:province":"Nieder\u00f6sterreich",
    "sg:tags":[
        "designer"
    ],
    "sg:website":"oefferl.at",
    "wof:name":"Herta \u00d6fferl Tischlerei",
    "wof:placetype":"venue"
},
  "geometry": {"coordinates":[16.4662799835,48.6589012146],"type":"Point"}
}