{
  "type": "Feature",
  "properties": {
    "addr:full":"Bahnhofsdlg 57 Terfens Tirol 6123",
    "addr:housenumber":"57",
    "addr:postcode":"6123",
    "addr:street":"Bahnhofsdlg;Tirol",
    "iso:country":"AT",
    "sg:address":"Bahnhofsdlg 57",
    "sg:city":"Terfens",
    "sg:orig_category":"Tischlereien",
    "sg:phone":"+43 4352 4272656",
    "sg:postcode":"6123",
    "sg:province":"Tirol",
    "wof:name":"Lechner Anton",
    "wof:placetype":"venue"
},
  "geometry": {"coordinates":[11.6419610977,47.3217391968],"type":"Point"}
}