{
  "type": "Feature",
  "properties": {
    "iso:country":"AT",
    "sg:address":"Hauptpl 4",
    "sg:city":"Linz",
    "sg:orig_category":"Architekten",
    "sg:phone":"+43 732 782939",
    "sg:postcode":"4020",
    "sg:province":"Ober\u00f6sterreich",
    "wof:name":"Ullmann Josef Dipl-Ing",
    "wof:placetype":"venue"
},
  "geometry": {"coordinates":[14.2865133286,48.3064041138],"type":"Point"}
}