{
  "type": "Feature",
  "properties": {
    "iso:country":"AT",
    "sg:address":"Wiener Str 1",
    "sg:city":"Wolkersdorf im Weinviertel",
    "sg:orig_category":"Sonnenstudios",
    "sg:phone":"+43 2245 83583",
    "sg:postcode":"2120",
    "sg:province":"Nieder\u00f6sterreich",
    "wof:name":"Sonnenstudio Fiasco",
    "wof:placetype":"venue"
},
  "geometry": {"coordinates":[16.514793396,48.3842163086],"type":"Point"}
}