{
  "type": "Feature",
  "properties": {
    "addr:full":"Im Astenfeld 2a St. Florian Ober\u00f6sterreich 4490",
    "addr:housenumber":"2a",
    "addr:postcode":"4490",
    "addr:street":"Im Astenfeld",
    "iso:country":"AT",
    "sg:address":"Im Astenfeld 2a",
    "sg:city":"St. Florian",
    "sg:orig_category":"Logistik",
    "sg:phone":"+43 4357 70077",
    "sg:postcode":"4490",
    "sg:province":"Ober\u00f6sterreich",
    "sg:website":"tnt.co.at",
    "wof:name":"TNT Express (Austria) GmbH",
    "wof:placetype":"venue"
},
  "geometry": {"coordinates":[14.3937158585,48.2259101868],"type":"Point"}
}