{
  "type": "Feature",
  "properties": {
    "iso:country":"AT",
    "sg:address":"Staasdorfer Str 15",
    "sg:city":"Tulln an der Donau",
    "sg:orig_category":"Apotheken",
    "sg:phone":"+43 4322 7261796",
    "sg:postcode":"3430",
    "sg:province":"Nieder\u00f6sterreich",
    "wof:name":"Gesundheitsmosaik Tulln",
    "wof:placetype":"venue"
},
  "geometry": {"coordinates":[16.0585899353,48.323059082],"type":"Point"}
}