{
  "type": "Feature",
  "properties": {
    "addr:full":"Nr 124 Zwettl Nieder\u00f6sterreich 3910",
    "addr:postcode":"3910",
    "addr:street":"Nr 124",
    "iso:country":"AT",
    "sg:address":"Nr 124",
    "sg:city":"Zwettl",
    "sg:orig_category":"Schlossereien",
    "sg:phone":"+43 4328 22521330",
    "sg:postcode":"3910",
    "sg:province":"Nieder\u00f6sterreich",
    "wof:name":"Stundner Stahl- u Fahrzeugbau GmbH",
    "wof:placetype":"venue"
},
  "geometry": {"coordinates":[15.1681003571,48.6041564941],"type":"Point"}
}