{
  "type": "Feature",
  "properties": {
    "addr:full":"Weideng 9 Biedermannsdorf Nieder\u00f6sterreich 2362",
    "addr:housenumber":"9",
    "addr:postcode":"2362",
    "addr:street":"Weideng",
    "iso:country":"AT",
    "sg:address":"Weideng 9",
    "sg:city":"Biedermannsdorf",
    "sg:orig_category":"Schlossereien",
    "sg:phone":"+43 2236 71138",
    "sg:postcode":"2362",
    "sg:province":"Nieder\u00f6sterreich",
    "wof:name":"Halbauer GesmbH",
    "wof:placetype":"venue"
},
  "geometry": {"coordinates":[16.3542346954,48.0801849365],"type":"Point"}
}