{
  "type": "Feature",
  "properties": {
    "addr:full":"Werkstr 1 Spital am Semmering Steiermark 8684",
    "addr:housenumber":"1",
    "addr:postcode":"8684",
    "addr:street":"Werkstr",
    "iso:country":"AT",
    "sg:address":"Werkstr 1",
    "sg:city":"Spital am Semmering",
    "sg:orig_category":"Feuerwehren",
    "sg:phone":"+43 3853 4863",
    "sg:postcode":"8684",
    "sg:province":"Steiermark",
    "wof:name":"Freiwillige Feuerwehr",
    "wof:placetype":"venue"
},
  "geometry": {"coordinates":[15.7494449615,47.6154518127],"type":"Point"}
}