{
  "type": "Feature",
  "properties": {
    "addr:full":"Bahnhofstr 18 Waidhofen an der Thaya Nieder\u00f6sterreich 3830",
    "addr:housenumber":"18",
    "addr:postcode":"3830",
    "addr:street":"Bahnhofstr",
    "iso:country":"AT",
    "sg:address":"Bahnhofstr 18",
    "sg:city":"Waidhofen an der Thaya",
    "sg:orig_category":"Psychotherapie",
    "sg:phone":"+43 4366 48981120",
    "sg:postcode":"3830",
    "sg:province":"Nieder\u00f6sterreich",
    "wof:name":"Stattler Gabriele",
    "wof:placetype":"venue"
},
  "geometry": {"coordinates":[15.2797641754,48.8134613037],"type":"Point"}
}