{
  "type": "Feature",
  "properties": {
    "addr:full":"M\u00fchlbachg 12 Markt St. Martin Burgenland 7341",
    "addr:housenumber":"12",
    "addr:postcode":"7341",
    "addr:street":"Muehlbachg;Markt",
    "iso:country":"AT",
    "sg:address":"M\u00fchlbachg 12",
    "sg:city":"Markt St. Martin",
    "sg:orig_category":"Tischlereien",
    "sg:phone":"+43 2618 3732",
    "sg:postcode":"7341",
    "sg:province":"Burgenland",
    "wof:name":"Fuchs Hannes",
    "wof:placetype":"venue"
},
  "geometry": {"coordinates":[16.4283771515,47.5642318726],"type":"Point"}
}