{
  "type": "Feature",
  "properties": {
    "addr:full":"Schulweg 10 Elixhausen Salzburg 5161",
    "addr:housenumber":"10",
    "addr:postcode":"5161",
    "addr:street":"Schulweg;Salzburg",
    "iso:country":"AT",
    "sg:address":"Schulweg 10",
    "sg:city":"Elixhausen",
    "sg:orig_category":"Volksschulen",
    "sg:phone":"+43 662 480274",
    "sg:postcode":"5161",
    "sg:province":"Salzburg",
    "wof:name":"Volksschule",
    "wof:placetype":"venue"
},
  "geometry": {"coordinates":[13.0657110214,47.8658638],"type":"Point"}
}