{
  "type": "Feature",
  "properties": {
    "addr:full":"Laxenburger Str. 252 Wien Wien 1230",
    "addr:housenumber":"252",
    "addr:postcode":"1230",
    "addr:street":"Laxenburger Str.",
    "iso:country":"AT",
    "sg:address":"Laxenburger Str. 252",
    "sg:city":"Wien",
    "sg:classifiers":[
        {
            "category":"Communications",
            "subcategory":"Television Station",
            "type":"Services"
        }
    ],
    "sg:phone":"+43 4316 1080",
    "sg:postcode":"1230",
    "sg:province":"Wien",
    "sg:tags":[
        "audio-visual"
    ],
    "wof:name":"PANASONIC AUSTRIA HANDELS GMBH",
    "wof:placetype":"venue"
},
  "geometry": {"coordinates":[16.3561286926,48.1344108582],"type":"Point"}
}