{
  "type": "Feature",
  "properties": {
    "addr:full":"Kopfingerdorf 43 Kopfing im Innkreis Ober\u00f6sterreich 4794",
    "addr:housenumber":"43",
    "addr:postcode":"4794",
    "addr:street":"Kopfingerdorf",
    "iso:country":"AT",
    "sg:address":"Kopfingerdorf 43",
    "sg:city":"Kopfing im Innkreis",
    "sg:classifiers":[
        {
            "category":"Farming",
            "subcategory":"Livestock Farm",
            "type":"Manufacturing & Wholesale Goods"
        }
    ],
    "sg:phone":"+43 4377 632757",
    "sg:postcode":"4794",
    "sg:province":"Ober\u00f6sterreich",
    "sg:tags":[
        "-handel",
        "viehzucht",
        "u"
    ],
    "wof:name":"Jodlbauer Gottfried",
    "wof:placetype":"venue"
},
  "geometry": {"coordinates":[13.6497535706,48.4358825684],"type":"Point"}
}