{
  "type": "Feature",
  "properties": {
    "addr:full":"Weihburgg 21 Wien Wien 1010",
    "addr:housenumber":"21",
    "addr:postcode":"1010",
    "addr:street":"Weihburgg",
    "iso:country":"AT",
    "sg:address":"Weihburgg 21",
    "sg:city":"Wien",
    "sg:orig_category":"Glasereien",
    "sg:phone":"+43 1 5126436",
    "sg:postcode":"1010",
    "sg:province":"Wien",
    "wof:name":"Lackinger E GesmbH",
    "wof:placetype":"venue"
},
  "geometry": {"coordinates":[16.3749275208,48.2060470581],"type":"Point"}
}