{
  "type": "Feature",
  "properties": {
    "addr:full":"Dir F Danzinger-Str 23 Tattendorf Nieder\u00f6sterreich 2523",
    "addr:housenumber":"23",
    "addr:postcode":"2523",
    "iso:country":"AT",
    "sg:address":"Dir F Danzinger-Str 23",
    "sg:city":"Tattendorf",
    "sg:orig_category":"Me\u00c3\u0178-, Steuer- U Regeltechnik",
    "sg:phone":"+43 4322 5381886",
    "sg:postcode":"2523",
    "sg:province":"Nieder\u00f6sterreich",
    "wof:name":"Technofit Austria - Dipl-HTL-Ing Harald Graf",
    "wof:placetype":"venue"
},
  "geometry": {"coordinates":[16.3026027679,47.9566307068],"type":"Point"}
}