{
  "type": "Feature",
  "properties": {
    "iso:country":"AT",
    "sg:address":"Dr.-Karl-Domenig-Str 4",
    "sg:city":"St. Veit an der Glan",
    "sg:orig_category":"Immobilienmakler",
    "sg:phone":"+43 4212 41580",
    "sg:postcode":"9300",
    "sg:province":"K\u00e4rnten",
    "wof:name":"Kandut G\u00fcnther",
    "wof:placetype":"venue"
},
  "geometry": {"coordinates":[14.3556575775,46.765953064],"type":"Point"}
}