{
  "type": "Feature",
  "properties": {
    "iso:country":"AT",
    "sg:address":"Elisabethstrasse 15/8A",
    "sg:city":"Wien",
    "sg:orig_category":"Sliding Windows",
    "sg:phone":"+43 1 5871211",
    "sg:postcode":"1010",
    "sg:province":"Wien",
    "sg:website":"konigkft.hu",
    "wof:name":"Kiraly Consulting & Trade GmbH",
    "wof:placetype":"venue"
},
  "geometry": {"coordinates":[16.3632946014,48.2028961182],"type":"Point"}
}