{
  "type": "Feature",
  "properties": {
    "addr:full":"Oberachen 2 Ellmau Tirol 6352",
    "addr:housenumber":"2",
    "addr:postcode":"6352",
    "addr:street":"Oberachen;Tirol",
    "iso:country":"AT",
    "sg:address":"Oberachen 2",
    "sg:city":"Ellmau",
    "sg:orig_category":"Physiotherapie",
    "sg:phone":"+43 5358 2507",
    "sg:postcode":"6352",
    "sg:province":"Tirol",
    "wof:name":"Praxis f\u00fcr Physiotherapie - Elisabeth Hechenberger",
    "wof:placetype":"venue"
},
  "geometry": {"coordinates":[12.2713880539,47.5210075378],"type":"Point"}
}