{
  "type": "Feature",
  "properties": {
    "iso:country":"AT",
    "sg:address":"Herdmann 6",
    "sg:city":"Grein",
    "sg:orig_category":"Erdarbeiten",
    "sg:phone":"+43 7268 6604",
    "sg:postcode":"4360",
    "sg:province":"Ober\u00f6sterreich",
    "wof:name":"Grabenschweiger Herbert",
    "wof:placetype":"venue"
},
  "geometry": {"coordinates":[14.8398704529,48.2268600464],"type":"Point"}
}