{
  "type": "Feature",
  "properties": {
    "addr:full":"Gewerbestr 4 Schweiggers Nieder\u00f6sterreich 3931",
    "addr:housenumber":"4",
    "addr:postcode":"3931",
    "addr:street":"Gewerbestr",
    "iso:country":"AT",
    "sg:address":"Gewerbestr 4",
    "sg:city":"Schweiggers",
    "sg:orig_category":"Spenglereien",
    "sg:phone":"+43 2829 7610",
    "sg:postcode":"3931",
    "sg:province":"Nieder\u00f6sterreich",
    "wof:name":"Prinz Franz",
    "wof:placetype":"venue"
},
  "geometry": {"coordinates":[15.0671615601,48.6717376709],"type":"Point"}
}