{
  "type": "Feature",
  "properties": {
    "addr:full":"Herreng. 3  Graz Steiermark 8010",
    "addr:housenumber":"3",
    "addr:postcode":"8010",
    "addr:street":"Herreng.",
    "iso:country":"AT",
    "sg:address":"Herreng. 3 ",
    "sg:city":"Graz",
    "sg:classifiers":[
        {
            "category":"Shopping",
            "type":"Retail Goods"
        }
    ],
    "sg:phone":"+43 4331 6815402",
    "sg:postcode":"8010",
    "sg:province":"Steiermark",
    "sg:tags":[
        "finished",
        "-",
        "metallic"
    ],
    "wof:name":"GULDENBREIN AUFSPERRDIENST GMBH",
    "wof:placetype":"venue"
},
  "geometry": {"coordinates":[15.4392108917,47.0707511902],"type":"Point"}
}