{
  "type": "Feature",
  "properties": {
    "iso:country":"AT",
    "sg:address":"Hauptpl 14",
    "sg:city":"Haid",
    "sg:orig_category":"Bekleidung / Einzelhandel",
    "sg:phone":"+43 7229 87309",
    "sg:postcode":"4053",
    "sg:province":"Ober\u00f6sterreich",
    "wof:name":"TKZ Textil Handel Scherzer GesmbH & Co KG",
    "wof:placetype":"venue"
},
  "geometry": {"coordinates":[14.2508907318,48.203956604],"type":"Point"}
}