{
  "type": "Feature",
  "properties": {
    "addr:full":"Obere Landstr 4 Krems an der Donau Nieder\u00f6sterreich 3500",
    "addr:housenumber":"4",
    "addr:postcode":"3500",
    "addr:street":"Obere Landstr",
    "iso:country":"AT",
    "sg:address":"Obere Landstr 4",
    "sg:city":"Krems an der Donau",
    "sg:classifiers":[
        {
            "category":"Professional",
            "subcategory":"Testing Lab",
            "type":"Services"
        }
    ],
    "sg:phone":"+43 2732 8010",
    "sg:postcode":"3500",
    "sg:province":"Nieder\u00f6sterreich",
    "sg:tags":[
        "magistrate"
    ],
    "wof:name":"Magistrat d Stadt Krems a d Donau",
    "wof:placetype":"venue"
},
  "geometry": {"coordinates":[15.5998859406,48.411239624],"type":"Point"}
}