{
  "type": "Feature",
  "properties": {
    "addr:full":"Markt 35 St. Gallen Steiermark 8933",
    "addr:housenumber":"35",
    "addr:postcode":"8933",
    "addr:street":"Markt",
    "iso:country":"AT",
    "sg:address":"Markt 35",
    "sg:city":"St. Gallen",
    "sg:orig_category":"Tourismusinformation U -Organisationen",
    "sg:phone":"+43 4336 3226449",
    "sg:postcode":"8933",
    "sg:province":"Steiermark",
    "wof:name":"Wasserspielpark Restaurant",
    "wof:placetype":"venue"
},
  "geometry": {"coordinates":[14.6171894073,47.6916503906],"type":"Point"}
}