{
  "type": "Feature",
  "properties": {
    "addr:full":"Am Sportplatz 5 Rust Burgenland 7071",
    "addr:housenumber":"5",
    "addr:postcode":"7071",
    "addr:street":"Am Sportplatz",
    "iso:country":"AT",
    "sg:address":"Am Sportplatz 5",
    "sg:city":"Rust",
    "sg:classifiers":[
        {
            "category":"Travel",
            "subcategory":"Hotels & Motels",
            "type":"Entertainment"
        }
    ],
    "sg:phone":"+43 2685 590",
    "sg:postcode":"7071",
    "sg:province":"Burgenland",
    "wof:name":"Hotel-Pension - Strohmer",
    "wof:placetype":"venue"
},
  "geometry": {"coordinates":[16.6734466553,47.8062553406],"type":"Point"}
}