{
  "type": "Feature",
  "properties": {
    "iso:country":"AT",
    "sg:address":"Kanzelpl 1",
    "sg:city":"Sattendorf",
    "sg:orig_category":"\u00c3\u201erzte / F Allgemeinmedizin",
    "sg:phone":"+43 4248 27100",
    "sg:postcode":"9520",
    "sg:province":"K\u00e4rnten",
    "wof:name":"Hock Irmgard Dr",
    "wof:placetype":"venue"
},
  "geometry": {"coordinates":[13.9019355774,46.6592254639],"type":"Point"}
}