{
  "type": "Feature",
  "properties": {
    "iso:country":"AT",
    "sg:address":"Bahnstr 2",
    "sg:city":"Hatting",
    "sg:orig_category":"Banken U Sparkassen",
    "sg:phone":"+43 4352 3888730",
    "sg:postcode":"6402",
    "sg:province":"Tirol",
    "wof:name":"Raiffeisen-Regionalbank Telfs regGenmbH",
    "wof:placetype":"venue"
},
  "geometry": {"coordinates":[11.1682434082,47.2781105042],"type":"Point"}
}