{
  "type": "Feature",
  "properties": {
    "addr:full":"Nr 55 Laaben Nieder\u00f6sterreich 3053",
    "addr:postcode":"3053",
    "addr:street":"Nr;Laaben",
    "iso:country":"AT",
    "sg:address":"Nr 55",
    "sg:city":"Laaben",
    "sg:orig_category":"Baumeister",
    "sg:phone":"+43 2774 6402",
    "sg:postcode":"3053",
    "sg:province":"Nieder\u00f6sterreich",
    "wof:name":"Steinberger Heimo Dipl-Ing Baumeisterei GmbH",
    "wof:placetype":"venue"
},
  "geometry": {"coordinates":[15.8666439056,48.1101608276],"type":"Point"}
}