{
  "type": "Feature",
  "properties": {
    "addr:full":"Wallrisstrasse 74 Wien Wien 1180",
    "addr:housenumber":"74",
    "addr:postcode":"1180",
    "addr:street":"Wallrisstrasse",
    "iso:country":"AT",
    "sg:address":"Wallrisstrasse 74",
    "sg:city":"Wien",
    "sg:classifiers":[
        {
            "category":"Transit Center",
            "subcategory":"Passenger",
            "type":"Transportation"
        }
    ],
    "sg:phone":"+43 1 4794321",
    "sg:postcode":"1180",
    "sg:province":"Wien",
    "sg:tags":[
        "high-speed",
        "processing"
    ],
    "wof:name":"H. & F. Greuner",
    "wof:placetype":"venue"
},
  "geometry": {"coordinates":[16.3193645477,48.2333221436],"type":"Point"}
}