{
  "type": "Feature",
  "properties": {
    "iso:country":"AT",
    "sg:address":"Werdenbergerstr 26",
    "sg:city":"Bludenz",
    "sg:orig_category":"Apotheken",
    "sg:phone":"+43 5552 620470",
    "sg:postcode":"6700",
    "sg:province":"Vorarlberg",
    "wof:name":"Stadtapotheke Mag pharm Max Fritsche KG",
    "wof:placetype":"venue"
},
  "geometry": {"coordinates":[9.820684433,47.1556587219],"type":"Point"}
}