{
  "type": "Feature",
  "properties": {
    "iso:country":"AT",
    "sg:address":"Wehlistr 127",
    "sg:city":"Wien",
    "sg:orig_category":"Ambulatorien",
    "sg:phone":"+43 4350 3030",
    "sg:postcode":"1020",
    "sg:province":"Wien",
    "wof:name":"Pensionsversicherungsanstalt Sonderkrankenanstalt RZ Zentrum f ambulante Rehabilitation",
    "wof:placetype":"venue"
},
  "geometry": {"coordinates":[16.4001903534,48.2282981873],"type":"Point"}
}