{
  "type": "Feature",
  "properties": {
    "iso:country":"AT",
    "sg:address":"Wienerfeldstrasse 5",
    "sg:city":"Wolkersdorf im Weinviertel",
    "sg:classifiers":[
        {
            "category":"Military Area",
            "subcategory":"Air Force Base",
            "type":"Public Place"
        }
    ],
    "sg:phone":"+43 2245 2313",
    "sg:postcode":"2120",
    "sg:province":"Nieder\u00f6sterreich",
    "sg:tags":[
        "window",
        "skylight",
        "dormer"
    ],
    "sg:website":"fenster-obermayer.at",
    "wof:name":"Gerhard Obermayer GesmbH",
    "wof:placetype":"venue"
},
  "geometry": {"coordinates":[16.5087242126,48.3804130554],"type":"Point"}
}