{
  "type": "Feature",
  "properties": {
    "iso:country":"AT",
    "sg:address":"Blumenaustr 2",
    "sg:city":"Lustenau",
    "sg:orig_category":"Schlossereien",
    "sg:phone":"+43 5577 86580",
    "sg:postcode":"6890",
    "sg:province":"Vorarlberg",
    "wof:name":"Haderer Werner GmbH",
    "wof:placetype":"venue"
},
  "geometry": {"coordinates":[9.6498498917,47.4324073792],"type":"Point"}
}