{
  "type": "Feature",
  "properties": {
    "addr:full":"Lech 339  Lech Vorarlberg 6764",
    "addr:housenumber":"339",
    "addr:postcode":"6764",
    "addr:street":"Lech",
    "iso:country":"AT",
    "sg:address":"Lech 339 ",
    "sg:city":"Lech",
    "sg:classifiers":[
        {
            "category":"Building & Trades",
            "subcategory":"Plumbing",
            "type":"Services"
        }
    ],
    "sg:phone":"+43 5583 2400",
    "sg:postcode":"6764",
    "sg:province":"Vorarlberg",
    "sg:tags":[
        "supraregional",
        "gas"
    ],
    "sg:website":"www.hotel-panorama.at",
    "wof:name":"Grabher KG",
    "wof:placetype":"venue"
},
  "geometry": {"coordinates":[10.1467933655,47.2139129639],"type":"Point"}
}