{
  "type": "Feature",
  "properties": {
    "iso:country":"AT",
    "sg:address":"Baiernstr 98D",
    "sg:city":"Graz",
    "sg:orig_category":"Werbeagenturen",
    "sg:phone":"+43 316 7142420",
    "sg:postcode":"8020",
    "sg:province":"Steiermark",
    "wof:name":"Werbeagentur Maieritsch",
    "wof:placetype":"venue"
},
  "geometry": {"coordinates":[15.3873977661,47.0650672913],"type":"Point"}
}