{
  "type": "Feature",
  "properties": {
    "iso:country":"AT",
    "sg:address":"Egerdachstr 8",
    "sg:city":"Innsbruck",
    "sg:orig_category":"Magnetventile",
    "sg:phone":"+43 512 392260",
    "sg:postcode":"6020",
    "sg:province":"Tirol",
    "wof:name":"B\u00fcrkert-Contromatic GesmbH",
    "wof:placetype":"venue"
},
  "geometry": {"coordinates":[11.409119606,47.2680664062],"type":"Point"}
}