{
  "type": "Feature",
  "properties": {
    "iso:country":"AT",
    "sg:address":"Nesselweg 4",
    "sg:city":"Dornbirn",
    "sg:orig_category":"Signierapparate U -Mittel",
    "sg:phone":"+43 4355 72317330",
    "sg:postcode":"6850",
    "sg:province":"Vorarlberg",
    "wof:name":"Amaco Ing Vonach GmbH",
    "wof:placetype":"venue"
},
  "geometry": {"coordinates":[9.7515878677,47.4249343872],"type":"Point"}
}