{
  "type": "Feature",
  "properties": {
    "addr:full":"Dre\u00dflen 388 Alberschwende Vorarlberg 6861",
    "addr:housenumber":"388",
    "addr:postcode":"6861",
    "iso:country":"AT",
    "sg:address":"Dre\u00dflen 388",
    "sg:city":"Alberschwende",
    "sg:orig_category":"Volksschulen",
    "sg:phone":"+43 5579 4175",
    "sg:postcode":"6861",
    "sg:province":"Vorarlberg",
    "wof:name":"Volksschule",
    "wof:placetype":"venue"
},
  "geometry": {"coordinates":[9.8315839767,47.4503974915],"type":"Point"}
}