{
  "type": "Feature",
  "properties": {
    "addr:full":"Bessarabierstr 72/OG 2 Salzburg Salzburg 5020",
    "addr:housenumber":"72 / og 2",
    "addr:postcode":"5020",
    "addr:street":"Bessarabierstr;Salzburg",
    "iso:country":"AT",
    "sg:address":"Bessarabierstr 72/OG 2",
    "sg:city":"Salzburg",
    "sg:orig_category":"Werbeagenturen",
    "sg:phone":"+43 662 439064",
    "sg:postcode":"5020",
    "sg:province":"Salzburg",
    "wof:name":"myvasco - Regina Kainz",
    "wof:placetype":"venue"
},
  "geometry": {"coordinates":[13.0433769226,47.8006744385],"type":"Point"}
}