{
  "type": "Feature",
  "properties": {
    "addr:full":"Wiener Str 11 Traismauer Nieder\u00f6sterreich 3133",
    "addr:postcode":"3133",
    "addr:street":"11",
    "iso:country":"AT",
    "sg:address":"Wiener Str 11",
    "sg:city":"Traismauer",
    "sg:orig_category":"Fu\u00c3\u0178pflege U Fu\u00c3\u0178pflegesalons",
    "sg:phone":"+43 2783 81181",
    "sg:postcode":"3133",
    "sg:province":"Nieder\u00f6sterreich",
    "wof:name":"Ulmer Anita",
    "wof:placetype":"venue"
},
  "geometry": {"coordinates":[15.7444372177,48.3499717712],"type":"Point"}
}