{
  "type": "Feature",
  "properties": {
    "iso:country":"AT",
    "sg:address":"Nr 75",
    "sg:city":"\u00d6blarn",
    "sg:orig_category":"Pensionen / Privatzimmer",
    "sg:phone":"+43 3684 22580",
    "sg:postcode":"8960",
    "sg:province":"Steiermark",
    "sg:website":"pension-tilly.at",
    "wof:name":"Pension Tilly Monika Stoimaier",
    "wof:placetype":"venue"
},
  "geometry": {"coordinates":[166.9221496582,-0.5282999873],"type":"Point"}
}