{
  "type": "Feature",
  "properties": {
    "addr:full":"Nr 31 Oberhofen am Irrsee Ober\u00f6sterreich 4894",
    "addr:postcode":"4894",
    "addr:street":"Nr 31",
    "iso:country":"AT",
    "sg:address":"Nr 31",
    "sg:city":"Oberhofen am Irrsee",
    "sg:orig_category":"Volksschulen",
    "sg:phone":"+43 4362 1382030",
    "sg:postcode":"4894",
    "sg:province":"Ober\u00f6sterreich",
    "wof:name":"Volksschule",
    "wof:placetype":"venue"
},
  "geometry": {"coordinates":[13.3063650131,47.9511909485],"type":"Point"}
}