{
  "type": "Feature",
  "properties": {
    "addr:full":"D\u00f6blinger G\u00fcrtel Stadtbahnbogen 185 Wien Wien 1190",
    "addr:housenumber":"185",
    "addr:postcode":"1190",
    "addr:street":"Stadtbahnbogen",
    "iso:country":"AT",
    "sg:address":"D\u00f6blinger G\u00fcrtel Stadtbahnbogen 185",
    "sg:city":"Wien",
    "sg:orig_category":"Tapezierer U Dekorateure",
    "sg:phone":"+43 4313 693067",
    "sg:postcode":"1190",
    "sg:province":"Wien",
    "wof:name":"Patzak Leopold",
    "wof:placetype":"venue"
},
  "geometry": {"coordinates":[16.3493022919,48.2389793396],"type":"Point"}
}