{
  "type": "Feature",
  "properties": {
    "iso:country":"AT",
    "sg:address":"Katzensteig 81",
    "sg:city":"Schattwald",
    "sg:orig_category":"Appartements / Ferienwohnungen",
    "sg:phone":"+43 4356 756659",
    "sg:postcode":"6677",
    "sg:province":"Tirol",
    "wof:name":"Ferienwohnung Pany",
    "wof:placetype":"venue"
},
  "geometry": {"coordinates":[-104.542350769,38.2452812195],"type":"Point"}
}