{
  "type": "Feature",
  "properties": {
    "addr:full":"Schneebergstr 26 Puchberg am Schneeberg Nieder\u00f6sterreich 2734",
    "addr:housenumber":"26",
    "addr:postcode":"2734",
    "addr:street":"Schneebergstr",
    "iso:country":"AT",
    "sg:address":"Schneebergstr 26",
    "sg:city":"Puchberg am Schneeberg",
    "sg:orig_category":"Tischlereien",
    "sg:phone":"+43 4326 363710",
    "sg:postcode":"2734",
    "sg:province":"Nieder\u00f6sterreich",
    "wof:name":"Wohn-Sinn Erich Krumb\u00f6ck",
    "wof:placetype":"venue"
},
  "geometry": {"coordinates":[15.9086151123,47.7895393372],"type":"Point"}
}