{
  "type": "Feature",
  "properties": {
    "addr:full":"L\u00e4ngenfeldg 16 Wien Wien 1120",
    "addr:housenumber":"16",
    "addr:postcode":"1120",
    "addr:street":"Laengenfeldg",
    "iso:country":"AT",
    "sg:address":"L\u00e4ngenfeldg 16",
    "sg:city":"Wien",
    "sg:orig_category":"Unterhaltungselektronik / Einzelhandel",
    "sg:phone":"+43 1 5239020",
    "sg:postcode":"1120",
    "sg:province":"Wien",
    "wof:name":"Trynka Stefan Dipl-Ing - Callmaster und TV Service",
    "wof:placetype":"venue"
},
  "geometry": {"coordinates":[16.3368358612,48.1832885742],"type":"Point"}
}