{
  "type": "Feature",
  "properties": {
    "addr:full":"Stadtpl 58 Schwanenstadt Ober\u00f6sterreich 4690",
    "addr:housenumber":"58",
    "addr:postcode":"4690",
    "addr:street":"Stadtpl",
    "iso:country":"AT",
    "sg:address":"Stadtpl 58",
    "sg:city":"Schwanenstadt",
    "sg:orig_category":"Biologische Produkte",
    "sg:phone":"+43 4376 733619",
    "sg:postcode":"4690",
    "sg:province":"Ober\u00f6sterreich",
    "wof:name":"M\u00fcller Karl-Heinz Ing",
    "wof:placetype":"venue"
},
  "geometry": {"coordinates":[13.7731075287,48.0543365479],"type":"Point"}
}