{
  "type": "Feature",
  "properties": {
    "iso:country":"AT",
    "sg:address":"Hauptstr 3",
    "sg:city":"Kapellen",
    "sg:orig_category":"Banken U Sparkassen",
    "sg:phone":"+43 3857 22550",
    "sg:postcode":"8691",
    "sg:province":"Steiermark",
    "wof:name":"Raiffeisenbank Oberes M\u00fcrztal regGenmbH",
    "wof:placetype":"venue"
},
  "geometry": {"coordinates":[15.6306524277,47.6476249695],"type":"Point"}
}