{
  "type": "Feature",
  "properties": {
    "addr:full":"Mariahilfer Str 110 Wien Wien 1070",
    "addr:housenumber":"110",
    "addr:postcode":"1070",
    "iso:country":"AT",
    "sg:address":"Mariahilfer Str 110",
    "sg:city":"Wien",
    "sg:orig_category":"Alternativtherapie",
    "sg:phone":"+43 4315 2626460",
    "sg:postcode":"1070",
    "sg:province":"Wien",
    "sg:website":"kaiserkrone.at",
    "wof:name":"Apotheke Zur Kaiserkrone Mag pharm Dr Koch KG",
    "wof:placetype":"venue"
},
  "geometry": {"coordinates":[16.3430595398,48.1966629028],"type":"Point"}
}