{
  "type": "Feature",
  "properties": {
    "iso:country":"AT",
    "sg:address":"Schirmitzb\u00fchelstr 10",
    "sg:city":"Kapfenberg",
    "sg:orig_category":"Feinkost",
    "sg:phone":"+43 4338 62312830",
    "sg:postcode":"8605",
    "sg:province":"Steiermark",
    "wof:name":"Aichinger Feinkosterzeugung GesmbH",
    "wof:placetype":"venue"
},
  "geometry": {"coordinates":[15.2912454605,47.4438438416],"type":"Point"}
}