{
  "type": "Feature",
  "properties": {
    "addr:full":"Illekg 18 Wien Wien 1150",
    "addr:housenumber":"18",
    "addr:postcode":"1150",
    "addr:street":"Illekg",
    "iso:country":"AT",
    "sg:address":"Illekg 18",
    "sg:city":"Wien",
    "sg:orig_category":"Behinderungen / Leben Mit Behinderungen",
    "sg:phone":"+43 1 9249959",
    "sg:postcode":"1150",
    "sg:province":"Wien",
    "sg:website":"www.startpunkt.org",
    "wof:name":"Startpunkt - Verein f berufliche Integration von Menschen mit Behinderungen",
    "wof:placetype":"venue"
},
  "geometry": {"coordinates":[16.3220424652,48.1955375671],"type":"Point"}
}