{
  "type": "Feature",
  "properties": {
    "iso:country":"AT",
    "sg:address":"Ferdinand-Porsche-Ring 21/6",
    "sg:city":"Wiener Neustadt",
    "sg:orig_category":"Arbeitsvermittlung",
    "sg:phone":"+43 4326 22238000",
    "sg:postcode":"2700",
    "sg:province":"Nieder\u00f6sterreich",
    "wof:name":"B\u00fcroring Personalmanagement GmbH",
    "wof:placetype":"venue"
},
  "geometry": {"coordinates":[16.2370948792,47.8109016418],"type":"Point"}
}