{
  "type": "Feature",
  "properties": {
    "addr:full":"Weiherweg 1 Koppl Salzburg 5321",
    "addr:housenumber":"1",
    "addr:postcode":"5321",
    "addr:street":"Weiherweg;Salzburg",
    "iso:country":"AT",
    "sg:address":"Weiherweg 1",
    "sg:city":"Koppl",
    "sg:orig_category":"Erdarbeiten",
    "sg:phone":"+43 4362 217473",
    "sg:postcode":"5321",
    "sg:province":"Salzburg",
    "wof:name":"Wallner Peter - Erd- u Sprengarbeiten",
    "wof:placetype":"venue"
},
  "geometry": {"coordinates":[13.1450042725,47.8251724243],"type":"Point"}
}