{
  "type": "Feature",
  "properties": {
    "addr:full":"Sieveringer Str 116 a Wien Wien 1190",
    "addr:housenumber":"116 a",
    "addr:postcode":"1190",
    "addr:street":"Sieveringer Str",
    "iso:country":"AT",
    "sg:address":"Sieveringer Str 116 a",
    "sg:city":"Wien",
    "sg:classifiers":[
        {
            "category":"Internet Cafe",
            "subcategory":"None",
            "type":"Food & Drink"
        }
    ],
    "sg:phone":"+43 1 4408880",
    "sg:postcode":"1190",
    "sg:province":"Wien",
    "wof:name":"Wiener Homepage Verlag",
    "wof:placetype":"venue"
},
  "geometry": {"coordinates":[16.3237037659,48.2509994507],"type":"Point"}
}