{
  "type": "Feature",
  "properties": {
    "iso:country":"AT",
    "sg:address":"Strallegg 4",
    "sg:city":"Strallegg",
    "sg:classifiers":[
        {
            "category":"Food & Beverages",
            "subcategory":"Groceries & Convenience Stores",
            "type":"Retail Goods"
        }
    ],
    "sg:phone":"+43 3174 2201",
    "sg:postcode":"8192",
    "sg:province":"Steiermark",
    "sg:tags":[
        "frozen",
        "goods",
        "baked"
    ],
    "sg:website":"felber.baecker.at",
    "wof:name":"B\u00e4ckerei Felber Ges.m.b.H. & Co KG",
    "wof:placetype":"venue"
},
  "geometry": {"coordinates":[15.7317829132,47.4087142944],"type":"Point"}
}