{
  "type": "Feature",
  "properties": {
    "addr:full":"Glang 3 Salzburg Salzburg 5020",
    "addr:housenumber":"3",
    "addr:postcode":"5020",
    "addr:street":"Glang;Salzburg",
    "iso:country":"AT",
    "sg:address":"Glang 3",
    "sg:city":"Salzburg",
    "sg:orig_category":"Detekteien",
    "sg:phone":"+43 662 648391",
    "sg:postcode":"5020",
    "sg:province":"Salzburg",
    "sg:website":"detektei-oberfrank.at",
    "wof:name":"Detektivb\u00fcro Oberfrank",
    "wof:placetype":"venue"
},
  "geometry": {"coordinates":[13.0199317932,47.7974395752],"type":"Point"}
}