{
  "type": "Feature",
  "properties": {
    "addr:full":"Nr 44g Partenen Vorarlberg 6794",
    "addr:housenumber":"44g",
    "addr:postcode":"6794",
    "addr:street":"Nr",
    "iso:country":"AT",
    "sg:address":"Nr 44g",
    "sg:city":"Partenen",
    "sg:orig_category":"Appartements / Ferienwohnungen",
    "sg:phone":"+43 5558 8785",
    "sg:postcode":"6794",
    "sg:province":"Vorarlberg",
    "wof:name":"Appartements Valnova",
    "wof:placetype":"venue"
},
  "geometry": {"coordinates":[10.0550413132,46.9705276489],"type":"Point"}
}