{
  "type": "Feature",
  "properties": {
    "addr:full":"An der Lan-Str 45a Innsbruck Tirol 6020",
    "addr:housenumber":"45a",
    "addr:postcode":"6020",
    "addr:street":"An Der Lan-Str;Tirol",
    "iso:country":"AT",
    "sg:address":"An der Lan-Str 45a",
    "sg:city":"Innsbruck",
    "sg:orig_category":"Transportunternehmen",
    "sg:phone":"+43 699 10107975",
    "sg:postcode":"6020",
    "sg:province":"Tirol",
    "wof:name":"Clari Marko",
    "wof:placetype":"venue"
},
  "geometry": {"coordinates":[11.4457197189,47.2728462219],"type":"Point"}
}