{
  "type": "Feature",
  "properties": {
    "iso:country":"AT",
    "sg:address":"Glor Berg 6",
    "sg:city":"Kals am Gro\u00dfglockner",
    "sg:orig_category":"Mautstra\u00c3\u0178en",
    "sg:phone":"+43 4876 8354",
    "sg:postcode":"9981",
    "sg:province":"Tirol",
    "wof:name":"Kalser Glocknerstra\u00dfe",
    "wof:placetype":"venue"
},
  "geometry": {"coordinates":[12.6881856918,47.0207748413],"type":"Point"}
}