{
  "type": "Feature",
  "properties": {
    "addr:full":"Pichling 143 Stainz Steiermark 8510",
    "addr:housenumber":"143",
    "addr:postcode":"8510",
    "addr:street":"Pichling",
    "iso:country":"AT",
    "sg:address":"Pichling 143",
    "sg:city":"Stainz",
    "sg:orig_category":"Maler, Anstreicher U Lackierer",
    "sg:phone":"+43 4334 636104",
    "sg:postcode":"8510",
    "sg:province":"Steiermark",
    "wof:name":"Scheer Markus",
    "wof:placetype":"venue"
},
  "geometry": {"coordinates":[15.2730865479,46.9033660889],"type":"Point"}
}