{
  "type": "Feature",
  "properties": {
    "addr:full":"Nr 7 G\u00f6stling an der Ybbs Nieder\u00f6sterreich 3345",
    "addr:postcode":"3345",
    "addr:street":"Nr;An Der Ybbs",
    "iso:country":"AT",
    "sg:address":"Nr 7",
    "sg:city":"G\u00f6stling an der Ybbs",
    "sg:orig_category":"Pensionen / Privatzimmer",
    "sg:phone":"+43 4374 842212",
    "sg:postcode":"3345",
    "sg:province":"Nieder\u00f6sterreich",
    "wof:name":"Blamauer Reinhold u Rosina",
    "wof:placetype":"venue"
},
  "geometry": {"coordinates":[166.9221496582,-0.5282999873],"type":"Point"}
}