{
  "type": "Feature",
  "properties": {
    "addr:full":"Josef-Kr\u00e4nzl-Str 35 Ried im Innkreis Ober\u00f6sterreich 4910",
    "addr:housenumber":"35",
    "addr:postcode":"4910",
    "addr:street":"Josef-Kraenzl-Str",
    "iso:country":"AT",
    "sg:address":"Josef-Kr\u00e4nzl-Str 35",
    "sg:city":"Ried im Innkreis",
    "sg:orig_category":"Baumschulen",
    "sg:phone":"+43 676 3368704",
    "sg:postcode":"4910",
    "sg:province":"Ober\u00f6sterreich",
    "wof:name":"Baumschule Jobst",
    "wof:placetype":"venue"
},
  "geometry": {"coordinates":[13.4830961227,48.2033195496],"type":"Point"}
}