{
  "type": "Feature",
  "properties": {
    "addr:full":"Schlo\u00dfweg 1 Deutschkreutz Burgenland 7301",
    "addr:housenumber":"1",
    "addr:postcode":"7301",
    "addr:street":"Schlossweg",
    "iso:country":"AT",
    "sg:address":"Schlo\u00dfweg 1",
    "sg:city":"Deutschkreutz",
    "sg:orig_category":"Boutiquen",
    "sg:phone":"+43 2613 89265",
    "sg:postcode":"7301",
    "sg:province":"Burgenland",
    "wof:name":"Chic'Ola",
    "wof:placetype":"venue"
},
  "geometry": {"coordinates":[16.6330356598,47.5994148254],"type":"Point"}
}