{
  "type": "Feature",
  "properties": {
    "addr:full":"Industriestr. 10  Amstetten Nieder\u00f6sterreich 3300",
    "addr:housenumber":"10",
    "addr:postcode":"3300",
    "addr:street":"Industriestr.;Niederoesterreich",
    "iso:country":"AT",
    "sg:address":"Industriestr. 10 ",
    "sg:city":"Amstetten",
    "sg:classifiers":[
        {
            "category":"Manufacturing",
            "subcategory":"Glass & Minerals",
            "type":"Manufacturing & Wholesale Goods"
        }
    ],
    "sg:phone":"+43 4374 72202",
    "sg:postcode":"3300",
    "sg:province":"Nieder\u00f6sterreich",
    "wof:name":"M. SWAROVSKI GESMBH & CO KG",
    "wof:placetype":"venue"
},
  "geometry": {"coordinates":[14.9069881439,48.1207695007],"type":"Point"}
}