{
  "type": "Feature",
  "properties": {
    "iso:country":"AT",
    "sg:address":"Nr 38",
    "sg:city":"St. Peter am Kammersberg",
    "sg:orig_category":"Pensionen / Privatzimmer",
    "sg:phone":"+43 3536 7317",
    "sg:postcode":"8843",
    "sg:province":"Steiermark",
    "wof:name":"Kreis Otto",
    "wof:placetype":"venue"
},
  "geometry": {"coordinates":[14.1869058609,47.187412262],"type":"Point"}
}