{
  "type": "Feature",
  "properties": {
    "addr:full":"B\u00e4rnbachweg 292 Saalbach Salzburg 5753",
    "addr:housenumber":"292",
    "addr:postcode":"5753",
    "addr:street":"Saalbach Salzburg",
    "iso:country":"AT",
    "sg:address":"B\u00e4rnbachweg 292",
    "sg:city":"Saalbach",
    "sg:classifiers":[
        {
            "category":"Travel",
            "subcategory":"Hotels & Motels",
            "type":"Entertainment"
        }
    ],
    "sg:phone":"+43 6541 62140",
    "sg:postcode":"5753",
    "sg:province":"Salzburg",
    "wof:name":"Karlshof",
    "wof:placetype":"venue"
},
  "geometry": {"coordinates":[12.6367301941,47.3899307251],"type":"Point"}
}