{
  "type": "Feature",
  "properties": {
    "addr:full":"Neuklosterg 1 Wiener Neustadt Nieder\u00f6sterreich 2700",
    "addr:housenumber":"1",
    "addr:postcode":"2700",
    "addr:street":"Neuklosterg",
    "iso:country":"AT",
    "sg:address":"Neuklosterg 1",
    "sg:city":"Wiener Neustadt",
    "sg:orig_category":"Restaurants: Griechisch",
    "sg:phone":"+43 2622 89340",
    "sg:postcode":"2700",
    "sg:province":"Nieder\u00f6sterreich",
    "wof:name":"Restaurant O.L.Y.M.P",
    "wof:placetype":"venue"
},
  "geometry": {"coordinates":[16.246553421,47.8120002747],"type":"Point"}
}