{
  "type": "Feature",
  "properties": {
    "addr:full":"Gmeinerg. 1-3 Feldkirchen Steiermark 8073",
    "addr:housenumber":"1-3",
    "addr:postcode":"8073",
    "addr:street":"Gmeinerg.",
    "iso:country":"AT",
    "sg:address":"Gmeinerg. 1-3",
    "sg:city":"Feldkirchen",
    "sg:classifiers":[
        {
            "category":"Professional",
            "subcategory":"Printing & Photocopies",
            "type":"Services"
        }
    ],
    "sg:phone":"+43 4331 6296107",
    "sg:postcode":"8073",
    "sg:province":"Steiermark",
    "wof:name":"DRUCKHAUS THALERHOF ING FERDINAND MAJCEN",
    "wof:placetype":"venue"
},
  "geometry": {"coordinates":[15.4504613876,46.988735199],"type":"Point"}
}