{
  "type": "Feature",
  "properties": {
    "iso:country":"AT",
    "sg:address":"Nr 11",
    "sg:city":"St. Lorenzen",
    "sg:orig_category":"Banken U Sparkassen",
    "sg:phone":"+43 4335 154640",
    "sg:postcode":"8715",
    "sg:province":"Steiermark",
    "wof:name":"Raiffeisenbank Knittelfeld regGenmbH",
    "wof:placetype":"venue"
},
  "geometry": {"coordinates":[14.8935403824,47.2492713928],"type":"Point"}
}