{
  "type": "Feature",
  "properties": {
    "addr:full":"Altendorf 2a Texing Nieder\u00f6sterreich 3242",
    "addr:housenumber":"2a",
    "addr:postcode":"3242",
    "addr:street":"Altendorf",
    "iso:country":"AT",
    "sg:address":"Altendorf 2a",
    "sg:city":"Texing",
    "sg:classifiers":[
        {
            "category":"Home & Garden",
            "subcategory":"Building Materials",
            "type":"Retail Goods"
        }
    ],
    "sg:phone":"+43 2755 7251",
    "sg:postcode":"3242",
    "sg:province":"Nieder\u00f6sterreich",
    "sg:tags":[
        "gravel",
        "crushed"
    ],
    "wof:name":"Walter Seiberl",
    "wof:placetype":"venue"
},
  "geometry": {"coordinates":[15.3167896271,48.0445213318],"type":"Point"}
}