{
  "type": "Feature",
  "properties": {
    "addr:full":"Bahnhofstr 4 Neumarkt am Wallersee Salzburg 5202",
    "addr:housenumber":"4",
    "addr:postcode":"5202",
    "addr:street":"Bahnhofstr;Salzburg",
    "iso:country":"AT",
    "sg:address":"Bahnhofstr 4",
    "sg:city":"Neumarkt am Wallersee",
    "sg:orig_category":"Baumeister",
    "sg:phone":"+43 6216 5081",
    "sg:postcode":"5202",
    "sg:province":"Salzburg",
    "wof:name":"Stier Thomas Ing",
    "wof:placetype":"venue"
},
  "geometry": {"coordinates":[13.225235939,47.9487609863],"type":"Point"}
}