{
  "type": "Feature",
  "properties": {
    "addr:full":"Wachaustr. 61 Loosdorf Nieder\u00f6sterreich 3382",
    "addr:housenumber":"61",
    "addr:postcode":"3382",
    "addr:street":"Wachaustr.",
    "iso:country":"AT",
    "sg:address":"Wachaustr. 61",
    "sg:city":"Loosdorf",
    "sg:classifiers":[
        {
            "category":"Manufacturing",
            "subcategory":"Food",
            "type":"Manufacturing & Wholesale Goods"
        }
    ],
    "sg:phone":"+43 4327 546212",
    "sg:postcode":"3382",
    "sg:province":"Nieder\u00f6sterreich",
    "sg:tags":[
        "equipment",
        "processing",
        "-",
        "machinery"
    ],
    "wof:name":"BATSCH WAAGEN",
    "wof:placetype":"venue"
},
  "geometry": {"coordinates":[15.3811845779,48.1837120056],"type":"Point"}
}