{
  "type": "Feature",
  "properties": {
    "addr:full":"Neufelder Str. 17 Hornstein Burgenland 7053",
    "addr:postcode":"7053",
    "addr:street":"Str. 17",
    "iso:country":"AT",
    "sg:address":"Neufelder Str. 17",
    "sg:city":"Hornstein",
    "sg:classifiers":[
        {
            "category":"Shopping",
            "type":"Retail Goods"
        }
    ],
    "sg:phone":"+43 4326 8924140",
    "sg:postcode":"7053",
    "sg:province":"Burgenland",
    "sg:tags":[
        "finished",
        "-",
        "metallic"
    ],
    "wof:name":"KLUDI ARMATUREN GMBH & CO. KG",
    "wof:placetype":"venue"
},
  "geometry": {"coordinates":[16.4322032928,47.8743782043],"type":"Point"}
}