{
  "type": "Feature",
  "properties": {
    "iso:country":"AT",
    "sg:address":"Schulstr 1",
    "sg:city":"St. Valentin",
    "sg:orig_category":"Hauptschulen",
    "sg:phone":"+43 7435 535900",
    "sg:postcode":"4300",
    "sg:province":"Nieder\u00f6sterreich",
    "wof:name":"Hauptschule",
    "wof:placetype":"venue"
},
  "geometry": {"coordinates":[14.5124950409,48.169178009],"type":"Point"}
}