{
  "type": "Feature",
  "properties": {
    "addr:full":"Teichg 33 Guntramsdorf Nieder\u00f6sterreich 2353",
    "addr:housenumber":"33",
    "addr:postcode":"2353",
    "addr:street":"Teichg",
    "iso:country":"AT",
    "sg:address":"Teichg 33",
    "sg:city":"Guntramsdorf",
    "sg:orig_category":"Wasseraufbereitungschemikalien",
    "sg:phone":"+43 2236 528630",
    "sg:postcode":"2353",
    "sg:province":"Nieder\u00f6sterreich",
    "wof:name":"MULTICHEM HandelsgesmbH",
    "wof:placetype":"venue"
},
  "geometry": {"coordinates":[16.3131351471,48.0543441772],"type":"Point"}
}