{
  "type": "Feature",
  "properties": {
    "addr:full":"Sonnenstr 1 Satteins Vorarlberg 6822",
    "addr:housenumber":"1",
    "addr:postcode":"6822",
    "addr:street":"Sonnenstr",
    "iso:country":"AT",
    "sg:address":"Sonnenstr 1",
    "sg:city":"Satteins",
    "sg:orig_category":"Solartechnik",
    "sg:phone":"+43 5524 53530",
    "sg:postcode":"6822",
    "sg:province":"Vorarlberg",
    "wof:name":"AKS DOMA Solartechnik",
    "wof:placetype":"venue"
},
  "geometry": {"coordinates":[9.6628293991,47.219203949],"type":"Point"}
}