{
  "type": "Feature",
  "properties": {
    "addr:full":"Industriepark 3 Trieben Steiermark 8784",
    "addr:housenumber":"3",
    "addr:postcode":"8784",
    "addr:street":"Industriepark",
    "iso:country":"AT",
    "sg:address":"Industriepark 3",
    "sg:city":"Trieben",
    "sg:orig_category":"Paletten / Erzeugung U Gro\u00c3\u0178handel",
    "sg:phone":"+43 4336 1522850",
    "sg:postcode":"8784",
    "sg:province":"Steiermark",
    "wof:name":"Koidl Harald",
    "wof:placetype":"venue"
},
  "geometry": {"coordinates":[14.4837818146,47.4931411743],"type":"Point"}
}