{
  "type": "Feature",
  "properties": {
    "addr:full":"Angerweg 13 Oetz Tirol 6433",
    "addr:housenumber":"13",
    "addr:postcode":"6433",
    "addr:street":"Angerweg;Tirol",
    "iso:country":"AT",
    "sg:address":"Angerweg 13",
    "sg:city":"Oetz",
    "sg:orig_category":"Bergbahnen",
    "sg:phone":"+43 5252 6385",
    "sg:postcode":"6433",
    "sg:province":"Tirol",
    "wof:name":"Bergbahnen Oetz",
    "wof:placetype":"venue"
},
  "geometry": {"coordinates":[10.9023342133,47.1995277405],"type":"Point"}
}