{
  "type": "Feature",
  "properties": {
    "addr:full":"Ortsstr 5 Traismauer Nieder\u00f6sterreich 3133",
    "addr:housenumber":"5",
    "addr:postcode":"3133",
    "addr:street":"Ortsstr",
    "iso:country":"AT",
    "sg:address":"Ortsstr 5",
    "sg:city":"Traismauer",
    "sg:orig_category":"Erdbau",
    "sg:phone":"+43 2276 6436",
    "sg:postcode":"3133",
    "sg:province":"Nieder\u00f6sterreich",
    "wof:name":"M\u00fcck Johann",
    "wof:placetype":"venue"
},
  "geometry": {"coordinates":[15.8053274155,48.3378372192],"type":"Point"}
}