{
  "type": "Feature",
  "properties": {
    "iso:country":"AT",
    "sg:address":"Reichenauer Str 16",
    "sg:city":"Innsbruck",
    "sg:orig_category":"Pensionen / Privatzimmer",
    "sg:phone":"+43 512 346368",
    "sg:postcode":"6020",
    "sg:province":"Tirol",
    "wof:name":"Pension Goldener Winkel",
    "wof:placetype":"venue"
},
  "geometry": {"coordinates":[11.4091129303,47.2693824768],"type":"Point"}
}