{
  "type": "Feature",
  "properties": {
    "addr:full":"Alter Platz 5 Klagenfurt K\u00e4rnten 9020",
    "addr:housenumber":"5",
    "addr:postcode":"9020",
    "addr:street":"Alter Platz;Kaernten",
    "iso:country":"AT",
    "sg:address":"Alter Platz 5",
    "sg:city":"Klagenfurt",
    "sg:classifiers":[
        {
            "category":"Banks & Credit Unions",
            "subcategory":"Investment Brokerage",
            "type":"Services"
        }
    ],
    "sg:phone":"+43 463 578841",
    "sg:postcode":"9020",
    "sg:province":"K\u00e4rnten",
    "sg:tags":[
        "hip",
        "pocket",
        "bags",
        "belt"
    ],
    "wof:name":"Paul Hatheyer",
    "wof:placetype":"venue"
},
  "geometry": {"coordinates":[14.3086080551,46.6254501343],"type":"Point"}
}