{
  "type": "Feature",
  "properties": {
    "addr:full":"Badstrasse 9a Grieskirchen Ober\u00f6sterreich 4710",
    "addr:housenumber":"9a",
    "addr:postcode":"4710",
    "addr:street":"Badstrasse",
    "iso:country":"AT",
    "sg:address":"Badstrasse 9a",
    "sg:city":"Grieskirchen",
    "sg:orig_category":"Anti-Mould Coatings",
    "sg:phone":"+43 664 1254306",
    "sg:postcode":"4710",
    "sg:province":"Ober\u00f6sterreich",
    "wof:name":"BESIC Malerei",
    "wof:placetype":"venue"
},
  "geometry": {"coordinates":[13.8323936462,48.2313652039],"type":"Point"}
}