{
  "type": "Feature",
  "properties": {
    "iso:country":"AT",
    "sg:address":"Grundlseer Str 194",
    "sg:city":"Bad Aussee",
    "sg:orig_category":"Installationsunternehmen",
    "sg:phone":"+43 4336 22520620",
    "sg:postcode":"8990",
    "sg:province":"Steiermark",
    "wof:name":"Eder Hans Ing",
    "wof:placetype":"venue"
},
  "geometry": {"coordinates":[13.7870893478,47.6119194031],"type":"Point"}
}