{
  "type": "Feature",
  "properties": {
    "addr:full":"Am Rofen 53 Imst Tirol 6460",
    "addr:housenumber":"53",
    "addr:postcode":"6460",
    "addr:street":"Am Rofen;Tirol",
    "iso:country":"AT",
    "sg:address":"Am Rofen 53",
    "sg:city":"Imst",
    "sg:orig_category":"Transportunternehmen",
    "sg:phone":"+43 5412 66704",
    "sg:postcode":"6460",
    "sg:province":"Tirol",
    "wof:name":"Mark Peter",
    "wof:placetype":"venue"
},
  "geometry": {"coordinates":[10.7457151413,47.2382774353],"type":"Point"}
}