{
  "type": "Feature",
  "properties": {
    "addr:full":"Bahnhofstr 2 Hallein Salzburg 5400",
    "addr:housenumber":"2",
    "addr:postcode":"5400",
    "addr:street":"Bahnhofstr;Salzburg",
    "iso:country":"AT",
    "sg:address":"Bahnhofstr 2",
    "sg:city":"Hallein",
    "sg:orig_category":"\u00c3\u201enderungsschneidereien",
    "sg:phone":"+43 6245 81653",
    "sg:postcode":"5400",
    "sg:province":"Salzburg",
    "wof:name":"\u00e4nderungsschneiderei Sema",
    "wof:placetype":"venue"
},
  "geometry": {"coordinates":[13.097990036,47.6836242676],"type":"Point"}
}