{
  "type": "Feature",
  "properties": {
    "addr:full":"Hauptpl 1 Mattersburg Burgenland 7210",
    "addr:housenumber":"1",
    "addr:postcode":"7210",
    "addr:street":"Hauptpl",
    "iso:country":"AT",
    "sg:address":"Hauptpl 1",
    "sg:city":"Mattersburg",
    "sg:orig_category":"Unterhaltungselektronik / Einzelhandel",
    "sg:phone":"+43 2626 62960",
    "sg:postcode":"7210",
    "sg:province":"Burgenland",
    "wof:name":"M\u00fcllner Wilhelm",
    "wof:placetype":"venue"
},
  "geometry": {"coordinates":[16.3988075256,47.7368888855],"type":"Point"}
}