{
  "type": "Feature",
  "properties": {
    "iso:country":"AT",
    "sg:address":"Ringstr 13",
    "sg:city":"Gutau",
    "sg:orig_category":"Transportunternehmen",
    "sg:phone":"+43 7946 6239",
    "sg:postcode":"4293",
    "sg:province":"Ober\u00f6sterreich",
    "wof:name":"Schwarzbauer A Transport GesmbH",
    "wof:placetype":"venue"
},
  "geometry": {"coordinates":[14.6095438004,48.4171180725],"type":"Point"}
}