{
  "type": "Feature",
  "properties": {
    "addr:full":"Thierweg 2 Salzburg Salzburg 5020",
    "addr:housenumber":"2",
    "addr:postcode":"5020",
    "addr:street":"Thierweg;Salzburg",
    "iso:country":"AT",
    "sg:address":"Thierweg 2",
    "sg:city":"Salzburg",
    "sg:orig_category":"Kinderbetreuung",
    "sg:phone":"+43 662 821512",
    "sg:postcode":"5020",
    "sg:province":"Salzburg",
    "wof:name":"Kindergarten d Pfarrgemeinde Morzg",
    "wof:placetype":"venue"
},
  "geometry": {"coordinates":[13.0560359955,47.7703208923],"type":"Point"}
}