{
  "type": "Feature",
  "properties": {
    "addr:full":"Hauptstr 2a B\u00fcrs Vorarlberg 6706",
    "addr:housenumber":"2a",
    "addr:postcode":"6706",
    "addr:street":"Hauptstr",
    "iso:country":"AT",
    "sg:address":"Hauptstr 2a",
    "sg:city":"B\u00fcrs",
    "sg:orig_category":"Friseure U Frisiersalons",
    "sg:phone":"+43 5552 62682",
    "sg:postcode":"6706",
    "sg:province":"Vorarlberg",
    "wof:name":"La Vogue Frisiersalon",
    "wof:placetype":"venue"
},
  "geometry": {"coordinates":[9.8113069534,47.1519165039],"type":"Point"}
}