{
  "type": "Feature",
  "properties": {
    "iso:country":"AT",
    "sg:address":"Savoyenstr 1a",
    "sg:city":"Wien",
    "sg:orig_category":"Forschungsinstitute",
    "sg:phone":"+43 1 48621210",
    "sg:postcode":"1160",
    "sg:province":"Wien",
    "wof:name":"Konrad Lorenz Institut f vgl Verhaltensforschung d \u00d6sterr Akademie d Wissenschaften",
    "wof:placetype":"venue"
},
  "geometry": {"coordinates":[16.2857112885,48.220287323],"type":"Point"}
}