{
  "type": "Feature",
  "properties": {
    "addr:full":"Natterg 24 Wien Wien 1170",
    "addr:housenumber":"24",
    "addr:postcode":"1170",
    "addr:street":"Natterg",
    "iso:country":"AT",
    "sg:address":"Natterg 24",
    "sg:city":"Wien",
    "sg:classifiers":[
        {
            "category":"Restaurant",
            "type":"Food & Drink"
        }
    ],
    "sg:phone":"+43 1 4854546",
    "sg:postcode":"1170",
    "sg:province":"Wien",
    "sg:tags":[
        "pizzeria"
    ],
    "wof:name":"Alexandro Inh Fouad Wagdy",
    "wof:placetype":"venue"
},
  "geometry": {"coordinates":[16.3273963928,48.2155151367],"type":"Point"}
}