{
  "type": "Feature",
  "properties": {
    "iso:country":"AT",
    "sg:address":"Rainfelder Hauptstr 21",
    "sg:city":"Rainfeld",
    "sg:orig_category":"Feuerwehren",
    "sg:phone":"+43 2763 2828",
    "sg:postcode":"3162",
    "sg:province":"Nieder\u00f6sterreich",
    "wof:name":"Freiwillige Feuerwehr Rainfeld",
    "wof:placetype":"venue"
},
  "geometry": {"coordinates":[15.7206573486,48.0473403931],"type":"Point"}
}