{
  "type": "Feature",
  "properties": {
    "addr:full":"Nr 58a Jenbach Tirol 6200",
    "addr:postcode":"6200",
    "addr:street":"Nr 58A;Tirol",
    "iso:country":"AT",
    "sg:address":"Nr 58a",
    "sg:city":"Jenbach",
    "sg:orig_category":"Gemeinden",
    "sg:phone":"+43 5244 63283",
    "sg:postcode":"6200",
    "sg:province":"Tirol",
    "wof:name":"Gemeindeamt Gallzein",
    "wof:placetype":"venue"
},
  "geometry": {"coordinates":[11.7709331512,47.3917541504],"type":"Point"}
}