{
  "type": "Feature",
  "properties": {
    "addr:full":"Schlo\u00df 1 Artstetten Nieder\u00f6sterreich 3661",
    "addr:housenumber":"1",
    "addr:postcode":"3661",
    "addr:street":"Schloss",
    "iso:country":"AT",
    "sg:address":"Schlo\u00df 1",
    "sg:city":"Artstetten",
    "sg:orig_category":"Museen / Ausstellungen",
    "sg:phone":"+43 4374 138006",
    "sg:postcode":"3661",
    "sg:province":"Nieder\u00f6sterreich",
    "wof:name":"Erzherzog Franz Ferdinand Museum",
    "wof:placetype":"venue"
},
  "geometry": {"coordinates":[15.2035694122,48.243057251],"type":"Point"}
}