{
  "type": "Feature",
  "properties": {
    "iso:country":"AT",
    "sg:address":"Kehlerau 20",
    "sg:city":"Dornbirn",
    "sg:orig_category":"Textilwaren / Erzeugung U Gro\u00c3\u0178handel",
    "sg:phone":"+43 5572 37400",
    "sg:postcode":"6850",
    "sg:province":"Vorarlberg",
    "wof:name":"Erich Gasser Fashion GmbH & Co KG",
    "wof:placetype":"venue"
},
  "geometry": {"coordinates":[9.7501592636,47.4167518616],"type":"Point"}
}