{
  "type": "Feature",
  "properties": {
    "addr:full":"Waagner-Biro-Strasse 39-41 Graz Steiermark 8020",
    "addr:postcode":"39-41;8020",
    "addr:street":"Waagner-Biro-Strasse",
    "iso:country":"AT",
    "sg:address":"Waagner-Biro-Strasse 39-41",
    "sg:city":"Graz",
    "sg:classifiers":[
        {
            "category":"Real Estate",
            "subcategory":"Surveying",
            "type":"Services"
        }
    ],
    "sg:phone":"+43 316 5090",
    "sg:postcode":"8020",
    "sg:province":"Steiermark",
    "sg:tags":[
        "cappuccino"
    ],
    "sg:website":"hornig.at",
    "wof:name":"J. Hornig Kaffee- und Teeproduktion Lebensmittelvertrieb GmbH",
    "wof:placetype":"venue"
},
  "geometry": {"coordinates":[15.4135303497,47.0740356445],"type":"Point"}
}