{
  "type": "Feature",
  "properties": {
    "addr:full":"Edlg 9 Wallern an der Trattnach Ober\u00f6sterreich 4702",
    "addr:housenumber":"9",
    "addr:postcode":"4702",
    "addr:street":"Edlg",
    "iso:country":"AT",
    "sg:address":"Edlg 9",
    "sg:city":"Wallern an der Trattnach",
    "sg:orig_category":"Autohandel",
    "sg:phone":"+43 4372 4946325",
    "sg:postcode":"4702",
    "sg:province":"Ober\u00f6sterreich",
    "wof:name":"Lindinger Werner",
    "wof:placetype":"venue"
},
  "geometry": {"coordinates":[13.9425191879,48.2310943604],"type":"Point"}
}