{
  "type": "Feature",
  "properties": {
    "addr:full":"Oberndorfer Str 264 Altenmarkt im Pongau Salzburg 5541",
    "addr:housenumber":"264",
    "addr:postcode":"5541",
    "addr:street":"Oberndorfer Str;Salzburg",
    "iso:country":"AT",
    "sg:address":"Oberndorfer Str 264",
    "sg:city":"Altenmarkt im Pongau",
    "sg:orig_category":"Tischlereien",
    "sg:phone":"+43 6452 71120",
    "sg:postcode":"5541",
    "sg:province":"Salzburg",
    "wof:name":"Oberreiter Siegfried",
    "wof:placetype":"venue"
},
  "geometry": {"coordinates":[13.4138402939,47.3864593506],"type":"Point"}
}