{
  "type": "Feature",
  "properties": {
    "iso:country":"AT",
    "sg:address":"Unterfeld 17a",
    "sg:city":"Dornbirn",
    "sg:orig_category":"Installationsunternehmen",
    "sg:phone":"+43 5572 25472",
    "sg:postcode":"6850",
    "sg:province":"Vorarlberg",
    "wof:name":"Blaas Richard",
    "wof:placetype":"venue"
},
  "geometry": {"coordinates":[9.7250757217,47.4071044922],"type":"Point"}
}