{
  "type": "Feature",
  "properties": {
    "iso:country":"AT",
    "sg:address":"Hans-Czettel-Pl 1",
    "sg:city":"Ternitz",
    "sg:orig_category":"Zahngesundheitsvorsorge",
    "sg:phone":"+43 2630 38219",
    "sg:postcode":"2630",
    "sg:province":"Nieder\u00f6sterreich",
    "wof:name":"Zahnambulatorium d Nieder\u00f6sterr Gebietskrankenkasse",
    "wof:placetype":"venue"
},
  "geometry": {"coordinates":[16.0209465027,47.7058067322],"type":"Point"}
}