{
  "type": "Feature",
  "properties": {
    "iso:country":"AT",
    "sg:address":"Burgerg 4",
    "sg:city":"Wolfsberg",
    "sg:orig_category":"Handarbeiten",
    "sg:phone":"+43 4352 2549",
    "sg:postcode":"9400",
    "sg:province":"K\u00e4rnten",
    "wof:name":"Anderiasch Christl",
    "wof:placetype":"venue"
},
  "geometry": {"coordinates":[14.8432826996,46.84034729],"type":"Point"}
}