{
  "type": "Feature",
  "properties": {
    "iso:country":"AT",
    "sg:address":"Grazer Str 79",
    "sg:city":"Langenwang",
    "sg:orig_category":"Autohandel",
    "sg:phone":"+43 3854 28440",
    "sg:postcode":"8665",
    "sg:province":"Steiermark",
    "wof:name":"O.K. Orthuber Autohandels-GesmbH",
    "wof:placetype":"venue"
},
  "geometry": {"coordinates":[15.6111011505,47.5609893799],"type":"Point"}
}