{
  "type": "Feature",
  "properties": {
    "addr:full":"Gleisdorf Steiermark 8200",
    "addr:postcode":"8200",
    "iso:country":"AT",
    "sg:city":"Gleisdorf",
    "sg:orig_category":"Feuerwehren",
    "sg:phone":"+43 3112 6622",
    "sg:postcode":"8200",
    "sg:province":"Steiermark",
    "wof:name":"Freiwillige Feuerwehr Labuch",
    "wof:placetype":"venue"
},
  "geometry": {"coordinates":[15.7106227875,47.0878410339],"type":"Point"}
}