{
  "type": "Feature",
  "properties": {
    "addr:full":"Burgfried 145 Gnas Steiermark 8342",
    "addr:housenumber":"145",
    "addr:postcode":"8342",
    "addr:street":"Burgfried",
    "iso:country":"AT",
    "sg:address":"Burgfried 145",
    "sg:city":"Gnas",
    "sg:orig_category":"CarpenterS Work Supraregional",
    "sg:phone":"+43 3151 8221",
    "sg:postcode":"8342",
    "sg:province":"Steiermark",
    "sg:website":"pockdach.at",
    "wof:name":"Franz Pock GesmbH",
    "wof:placetype":"venue"
},
  "geometry": {"coordinates":[15.8180675507,46.8816986084],"type":"Point"}
}