{
  "type": "Feature",
  "properties": {
    "addr:full":"Hauptpl 4 Himberg Nieder\u00f6sterreich 2325",
    "addr:housenumber":"4",
    "addr:postcode":"2325",
    "addr:street":"Hauptpl",
    "iso:country":"AT",
    "sg:address":"Hauptpl 4",
    "sg:city":"Himberg",
    "sg:orig_category":"Politische Parteien",
    "sg:phone":"+43 2235 86607",
    "sg:postcode":"2325",
    "sg:province":"Nieder\u00f6sterreich",
    "wof:name":"\u00f6sterreichische Volkspartei -Gemeindeparteileitung Himberg",
    "wof:placetype":"venue"
},
  "geometry": {"coordinates":[16.4396800995,48.0823249817],"type":"Point"}
}