{
  "type": "Feature",
  "properties": {
    "addr:full":"Hauptstr 22 Hainfeld Nieder\u00f6sterreich 3170",
    "addr:housenumber":"22",
    "addr:postcode":"3170",
    "addr:street":"Hauptstr",
    "iso:country":"AT",
    "sg:address":"Hauptstr 22",
    "sg:city":"Hainfeld",
    "sg:orig_category":"Weiterbildungsinstitute M Allg U Berufl Bildungsangebot",
    "sg:phone":"+43 4327 6430394",
    "sg:postcode":"3170",
    "sg:province":"Nieder\u00f6sterreich",
    "wof:name":"Institut f Bildung u Kultur",
    "wof:placetype":"venue"
},
  "geometry": {"coordinates":[15.7724676132,48.0358581543],"type":"Point"}
}