{
  "type": "Feature",
  "properties": {
    "addr:full":"Litzlfeldner Str 32 Kirchdorf in Tirol Tirol 6382",
    "addr:housenumber":"32",
    "addr:postcode":"6382",
    "addr:street":"Str;Tirol",
    "iso:country":"AT",
    "sg:address":"Litzlfeldner Str 32",
    "sg:city":"Kirchdorf in Tirol",
    "sg:orig_category":"Fu\u00c3\u0178pflege U Fu\u00c3\u0178pflegesalons",
    "sg:phone":"+43 4353 5263818",
    "sg:postcode":"6382",
    "sg:province":"Tirol",
    "wof:name":"Speer Birgit",
    "wof:placetype":"venue"
},
  "geometry": {"coordinates":[12.4409656525,47.5521850586],"type":"Point"}
}