{
  "type": "Feature",
  "properties": {
    "iso:country":"AT",
    "sg:address":"Hofm\u00fchlgasse 18",
    "sg:city":"Wien",
    "sg:classifiers":[
        {
            "category":"Home & Garden",
            "subcategory":"Carpets & Floor Coverings",
            "type":"Retail Goods"
        }
    ],
    "sg:phone":"+43 1 5868686",
    "sg:postcode":"1060",
    "sg:province":"Wien",
    "sg:tags":[
        "carpeting"
    ],
    "wof:name":"Anton Florian",
    "wof:placetype":"venue"
},
  "geometry": {"coordinates":[16.3504657745,48.1947135925],"type":"Point"}
}