{
  "type": "Feature",
  "properties": {
    "iso:country":"AT",
    "sg:address":"Ernst-Swatek-Str 10",
    "sg:city":"Wolfsberg",
    "sg:orig_category":"Hauskrankenpflege / Heimhilfe",
    "sg:phone":"+43 4343 5245325",
    "sg:postcode":"9400",
    "sg:province":"K\u00e4rnten",
    "wof:name":"Hilfswerk K\u00e4rnten - Hauskrankenpflege Bezirk Wolfsberg",
    "wof:placetype":"venue"
},
  "geometry": {"coordinates":[14.8400087357,46.8386116028],"type":"Point"}
}