{
  "type": "Feature",
  "properties": {
    "iso:country":"AT",
    "sg:address":"Audorf 12",
    "sg:city":"Rohr im Kremstal",
    "sg:orig_category":"Reifen U Reifendienste",
    "sg:phone":"+43 4369 911358749",
    "sg:postcode":"4532",
    "sg:province":"Ober\u00f6sterreich",
    "wof:name":"Spernbauer Peter",
    "wof:placetype":"venue"
},
  "geometry": {"coordinates":[14.192029953,48.0744361877],"type":"Point"}
}