{
  "type": "Feature",
  "properties": {
    "addr:full":"Edt 60 Bad Goisern Ober\u00f6sterreich 4822",
    "addr:housenumber":"60",
    "addr:postcode":"4822",
    "addr:street":"Edt",
    "iso:country":"AT",
    "sg:address":"Edt 60",
    "sg:city":"Bad Goisern",
    "sg:classifiers":[
        {
            "category":"Professional",
            "subcategory":"Computer Services",
            "type":"Services"
        }
    ],
    "sg:phone":"+43 4361 3520788",
    "sg:postcode":"4822",
    "sg:province":"Ober\u00f6sterreich",
    "sg:tags":[
        "software"
    ],
    "wof:name":"Irmler Design u Softwareentwicklung",
    "wof:placetype":"venue"
},
  "geometry": {"coordinates":[13.637960434,47.6277275085],"type":"Point"}
}