{
  "type": "Feature",
  "properties": {
    "addr:full":"Hauptstr 8 Wampersdorf Nieder\u00f6sterreich 2485",
    "addr:housenumber":"8",
    "addr:postcode":"2485",
    "addr:street":"Hauptstr",
    "iso:country":"AT",
    "sg:address":"Hauptstr 8",
    "sg:city":"Wampersdorf",
    "sg:orig_category":"Volksschulen",
    "sg:phone":"+43 4326 2374480",
    "sg:postcode":"2485",
    "sg:province":"Nieder\u00f6sterreich",
    "wof:name":"Volksschule",
    "wof:placetype":"venue"
},
  "geometry": {"coordinates":[16.4310035706,47.9187278748],"type":"Point"}
}