{
  "type": "Feature",
  "properties": {
    "iso:country":"AT",
    "sg:address":"Lichtblaustrasse 6",
    "sg:city":"Wien",
    "sg:classifiers":[
        {
            "category":"Manufacturing",
            "subcategory":"Rubber & Plastics",
            "type":"Manufacturing & Wholesale Goods"
        }
    ],
    "sg:phone":"+43 1 250400",
    "sg:postcode":"1220",
    "sg:province":"Wien",
    "sg:tags":[
        "worked",
        "panels"
    ],
    "sg:website":"plastoplan.com",
    "wof:name":"Plastoplan Kunststoff-Handel Ges.m.b.H",
    "wof:placetype":"venue"
},
  "geometry": {"coordinates":[16.4632301331,48.2649497986],"type":"Point"}
}