{
  "type": "Feature",
  "properties": {
    "addr:full":"Haslach 55 St. Georgen an der Stiefing Steiermark 8413",
    "addr:housenumber":"55",
    "addr:postcode":"8413",
    "addr:street":"Haslach",
    "iso:country":"AT",
    "sg:address":"Haslach 55",
    "sg:city":"St. Georgen an der Stiefing",
    "sg:orig_category":"Fenster",
    "sg:phone":"+43 4369 912588968",
    "sg:postcode":"8413",
    "sg:province":"Steiermark",
    "wof:name":"Pappel Adolf",
    "wof:placetype":"venue"
},
  "geometry": {"coordinates":[15.5929555893,46.8366584778],"type":"Point"}
}