{
  "type": "Feature",
  "properties": {
    "addr:full":"Erzherzog Johann-Str 4a St. Marein im M\u00fcrztal Steiermark 8641",
    "addr:housenumber":"4a",
    "addr:postcode":"8641",
    "addr:street":"St. Marein Im Muerztal Steiermark",
    "iso:country":"AT",
    "sg:address":"Erzherzog Johann-Str 4a",
    "sg:city":"St. Marein im M\u00fcrztal",
    "sg:classifiers":[
        {
            "category":"Commercial Area",
            "type":"Public Place"
        }
    ],
    "sg:phone":"+43 3864 20268",
    "sg:postcode":"8641",
    "sg:province":"Steiermark",
    "sg:tags":[
        "e-commerce"
    ],
    "wof:name":"CWB Computer World Baumgartner",
    "wof:placetype":"venue"
},
  "geometry": {"coordinates":[15.3648023605,47.4742355347],"type":"Point"}
}