{
  "type": "Feature",
  "properties": {
    "addr:full":"Thermenstr 1 Bad Radkersburg Steiermark 8490",
    "addr:housenumber":"1",
    "addr:postcode":"8490",
    "addr:street":"Thermenstr",
    "iso:country":"AT",
    "sg:address":"Thermenstr 1",
    "sg:city":"Bad Radkersburg",
    "sg:orig_category":"Friseure U Frisiersalons",
    "sg:phone":"+43 4334 763510",
    "sg:postcode":"8490",
    "sg:province":"Steiermark",
    "wof:name":"Kohl Silvia",
    "wof:placetype":"venue"
},
  "geometry": {"coordinates":[15.9800271988,46.6877098083],"type":"Point"}
}