{
  "type": "Feature",
  "properties": {
    "addr:full":"Draschestr.13-17 1232",
    "addr:housenumber":"1232",
    "iso:country":"AT",
    "sg:address":"Draschestr.13-17",
    "sg:classifiers":[
        {
            "category":"Sports & Exercise",
            "subcategory":"Playing Field",
            "type":"Entertainment"
        }
    ],
    "sg:phone":"+43 4316 10250",
    "sg:postcode":"1232",
    "sg:tags":[
        "game"
    ],
    "wof:name":"\u00d6STERR. GENOSSENSCHAFT D. LANDWIRTSCH. ERWERBSGARTENB. REG.GEN.MBH (OGE)",
    "wof:placetype":"venue"
},
  "geometry": {"coordinates":[16.3598308563,48.1458358765],"type":"Point"}
}