{
  "type": "Feature",
  "properties": {
    "addr:full":"Vogelweiderstrasse 3b Wels Ober\u00f6sterreich 4600",
    "addr:housenumber":"3b",
    "addr:postcode":"4600",
    "addr:street":"Vogelweiderstrasse;Oberoesterreich",
    "iso:country":"AT",
    "sg:address":"Vogelweiderstrasse 3b",
    "sg:city":"Wels",
    "sg:classifiers":[
        {
            "category":"Health Services",
            "subcategory":"Dentist",
            "type":"Services"
        }
    ],
    "sg:phone":"+43 7242 44610",
    "sg:postcode":"4600",
    "sg:province":"Ober\u00f6sterreich",
    "sg:tags":[
        "cermet",
        "dentistry"
    ],
    "sg:website":"prueser.at",
    "wof:name":"Pr\u00fcser Dental Labor",
    "wof:placetype":"venue"
},
  "geometry": {"coordinates":[14.0184679031,48.1606826782],"type":"Point"}
}