{
  "type": "Feature",
  "properties": {
    "addr:full":"Glanfurtstr. 8  Ebenthal in K\u00e4rnten K\u00e4rnten 9065",
    "addr:housenumber":"8",
    "addr:postcode":"9065",
    "addr:street":"Glanfurtstr.;Kaernten",
    "iso:country":"AT",
    "sg:address":"Glanfurtstr. 8 ",
    "sg:city":"Ebenthal in K\u00e4rnten",
    "sg:classifiers":[
        {
            "category":"Food & Beverages",
            "subcategory":"Bakery",
            "type":"Retail Goods"
        }
    ],
    "sg:phone":"+43 4346 3326740",
    "sg:postcode":"9065",
    "sg:province":"K\u00e4rnten",
    "sg:tags":[
        "grain",
        "cereal"
    ],
    "wof:name":"EBENTHALER M\u00dcHLE STEININGER GMBH",
    "wof:placetype":"venue"
},
  "geometry": {"coordinates":[14.3602876663,46.605140686],"type":"Point"}
}