{
  "type": "Feature",
  "properties": {
    "addr:full":"Gasteigstr 24 Kirchbichl Tirol 6322",
    "addr:housenumber":"24",
    "addr:postcode":"6322",
    "addr:street":"Gasteigstr;Tirol",
    "iso:country":"AT",
    "sg:address":"Gasteigstr 24",
    "sg:city":"Kirchbichl",
    "sg:orig_category":"Webdesign",
    "sg:phone":"+43 650 2000750",
    "sg:postcode":"6322",
    "sg:province":"Tirol",
    "wof:name":"ARMIX networks - Armin Baldemair",
    "wof:placetype":"venue"
},
  "geometry": {"coordinates":[12.0868015289,47.496219635],"type":"Point"}
}