{
  "type": "Feature",
  "properties": {
    "iso:country":"AT",
    "sg:address":"H\u00f6henfeld 55",
    "sg:city":"Haus",
    "sg:classifiers":[
        {
            "category":"Manufacturing",
            "subcategory":"Wood Products",
            "type":"Manufacturing & Wholesale Goods"
        }
    ],
    "sg:phone":"+43 3686 4415",
    "sg:postcode":"8967",
    "sg:province":"Steiermark",
    "sg:tags":[
        "installation",
        "sawmill"
    ],
    "wof:name":"Andreas Raudaschl",
    "wof:placetype":"venue"
},
  "geometry": {"coordinates":[13.7679595947,47.4105949402],"type":"Point"}
}