{
  "type": "Feature",
  "properties": {
    "addr:full":"Blaue Lagune Klopeiner See St. Kanzian am Klopeiner See K\u00e4rnten 9122",
    "addr:postcode":"9122",
    "addr:street":"Blaue;Kaernten",
    "iso:country":"AT",
    "sg:address":"Blaue Lagune Klopeiner See",
    "sg:city":"St. Kanzian am Klopeiner See",
    "sg:classifiers":[
        {
            "category":"Travel",
            "subcategory":"Hotels & Motels",
            "type":"Entertainment"
        }
    ],
    "sg:phone":"+43 4342 392236",
    "sg:postcode":"9122",
    "sg:province":"K\u00e4rnten",
    "wof:name":"Promenaden-Strandhotel Marolt",
    "wof:placetype":"venue"
},
  "geometry": {"coordinates":[14.5971727371,46.6079139709],"type":"Point"}
}