{
  "type": "Feature",
  "properties": {
    "iso:country":"AT",
    "sg:address":"J Strau\u00df-Promenade 21",
    "sg:city":"Stockerau",
    "sg:orig_category":"Lebensmittel / Einzelhandel",
    "sg:phone":"+43 2266 62569",
    "sg:postcode":"2000",
    "sg:province":"Nieder\u00f6sterreich",
    "wof:name":"Jirowetz Franziska",
    "wof:placetype":"venue"
},
  "geometry": {"coordinates":[16.2133693695,48.3929214478],"type":"Point"}
}