{
  "type": "Feature",
  "properties": {
    "iso:country":"AT",
    "sg:address":"Franz-Josef-Str 204",
    "sg:city":"Bad Gleichenberg",
    "sg:orig_category":"Banken U Sparkassen",
    "sg:phone":"+43 4331 5922600",
    "sg:postcode":"8344",
    "sg:province":"Steiermark",
    "wof:name":"Bankomat d Raiffeisenbank Feldbach-Bad Gleichenberg",
    "wof:placetype":"venue"
},
  "geometry": {"coordinates":[15.9038906097,46.8549499512],"type":"Point"}
}