{
  "type": "Feature",
  "properties": {
    "addr:full":"Edt 6 Grieskirchen Ober\u00f6sterreich 4710",
    "addr:housenumber":"6",
    "addr:postcode":"4710",
    "addr:street":"Edt",
    "iso:country":"AT",
    "sg:address":"Edt 6",
    "sg:city":"Grieskirchen",
    "sg:classifiers":[
        {
            "category":"Home & Garden",
            "subcategory":"Building Materials",
            "type":"Retail Goods"
        }
    ],
    "sg:phone":"+43 7248 61754",
    "sg:postcode":"4710",
    "sg:province":"Ober\u00f6sterreich",
    "sg:tags":[
        "baustoffe",
        "-material",
        "u"
    ],
    "wof:name":"Em-S\u00e4ulen",
    "wof:placetype":"venue"
},
  "geometry": {"coordinates":[13.8666954041,48.2504692078],"type":"Point"}
}