{
  "type": "Feature",
  "properties": {
    "addr:full":"Linzer Str 76 Wien Wien 1140",
    "addr:housenumber":"76",
    "addr:postcode":"1140",
    "addr:street":"Linzer Str",
    "iso:country":"AT",
    "sg:address":"Linzer Str 76",
    "sg:city":"Wien",
    "sg:classifiers":[
        {
            "category":"Professional",
            "subcategory":"Computer Services",
            "type":"Services"
        }
    ],
    "sg:phone":"+43 1 9836466",
    "sg:postcode":"1140",
    "sg:province":"Wien",
    "sg:tags":[
        "software"
    ],
    "wof:name":"SEB Software Entwicklung & Beratung Datenservice GesmbH",
    "wof:placetype":"venue"
},
  "geometry": {"coordinates":[16.3057136536,48.1939125061],"type":"Point"}
}