{
  "type": "Feature",
  "properties": {
    "iso:country":"AT",
    "sg:address":"Obere Hauptstr 41",
    "sg:city":"Potzneusiedl",
    "sg:orig_category":"Fleisch-, Wurst- U Selchwaren / Erzeugung U Gro\u00c3\u0178handel",
    "sg:phone":"+43 4321 452216",
    "sg:postcode":"2473",
    "sg:province":"Burgenland",
    "wof:name":"Bayer Reinhard - Am Arkadenhof",
    "wof:placetype":"venue"
},
  "geometry": {"coordinates":[16.9366493225,48.0494880676],"type":"Point"}
}