{
  "type": "Feature",
  "properties": {
    "addr:full":"Ing.-Ludwig-Neumann-Str 4 Frauental an der La\u00dfnitz Steiermark 8523",
    "addr:housenumber":"4",
    "addr:postcode":"8523",
    "addr:street":"Ing.-Ludwig-Neumann-Str",
    "iso:country":"AT",
    "sg:address":"Ing.-Ludwig-Neumann-Str 4",
    "sg:city":"Frauental an der La\u00dfnitz",
    "sg:orig_category":"Anlagenbau U -Technik",
    "sg:phone":"+43 4334 625860",
    "sg:postcode":"8523",
    "sg:province":"Steiermark",
    "wof:name":"IAF-Industrieanlagentechnik Frauental GesmbH",
    "wof:placetype":"venue"
},
  "geometry": {"coordinates":[15.2551765442,46.8323020935],"type":"Point"}
}