{
  "type": "Feature",
  "properties": {
    "addr:full":"Am Kanal 2b Katzelsdorf Nieder\u00f6sterreich 2801",
    "addr:housenumber":"2b",
    "addr:postcode":"2801",
    "addr:street":"Am Kanal",
    "iso:country":"AT",
    "sg:address":"Am Kanal 2b",
    "sg:city":"Katzelsdorf",
    "sg:orig_category":"Industrie, Chemie U Biologie",
    "sg:postcode":"2801",
    "sg:province":"Nieder\u00f6sterreich",
    "sg:website":"http://www.aquatron.at/index.html",
    "wof:name":"Fa.Aquatron-Hohenegger Elektronische Ger\u00e4te Ges.m.b.H",
    "wof:placetype":"venue"
},
  "geometry": {"coordinates":[16.2698802948,47.7745018005],"type":"Point"}
}