{
  "type": "Feature",
  "properties": {
    "addr:full":"Ing.-Julius-Raab-Str 7 Eisenstadt Burgenland 7000",
    "addr:housenumber":"7",
    "addr:postcode":"7000",
    "addr:street":"Ing.-Julius-Raab-Str",
    "iso:country":"AT",
    "sg:address":"Ing.-Julius-Raab-Str 7",
    "sg:city":"Eisenstadt",
    "sg:orig_category":"Politische Parteien",
    "sg:phone":"+43 2682 7990",
    "sg:postcode":"7000",
    "sg:province":"Burgenland",
    "wof:name":"\u00f6sterreichische Volkspartei (\u00f6VP)",
    "wof:placetype":"venue"
},
  "geometry": {"coordinates":[16.5277557373,47.8476295471],"type":"Point"}
}