{
  "type": "Feature",
  "properties": {
    "addr:full":"Auweg 72 Going am Wilden Kaiser Tirol 6353",
    "addr:housenumber":"72",
    "addr:postcode":"6353",
    "addr:street":"Auweg;Tirol",
    "iso:country":"AT",
    "sg:address":"Auweg 72",
    "sg:city":"Going am Wilden Kaiser",
    "sg:orig_category":"Pensionen / Privatzimmer",
    "sg:phone":"+43 4353 582471",
    "sg:postcode":"6353",
    "sg:province":"Tirol",
    "wof:name":"Appartements Haus Angela",
    "wof:placetype":"venue"
},
  "geometry": {"coordinates":[12.3236103058,47.5147399902],"type":"Point"}
}