{
  "type": "Feature",
  "properties": {
    "addr:full":"Vogelsangg 35 Bisamberg Nieder\u00f6sterreich 2102",
    "addr:housenumber":"35",
    "addr:postcode":"2102",
    "addr:street":"Vogelsangg",
    "iso:country":"AT",
    "sg:address":"Vogelsangg 35",
    "sg:city":"Bisamberg",
    "sg:orig_category":"Musikgruppen",
    "sg:phone":"+43 2262 63424",
    "sg:postcode":"2102",
    "sg:province":"Nieder\u00f6sterreich",
    "wof:name":"Wiener Concertverein - Christian Roscheck",
    "wof:placetype":"venue"
},
  "geometry": {"coordinates":[16.3610553741,48.3311195374],"type":"Point"}
}