{
  "type": "Feature",
  "properties": {
    "addr:full":"Kleinwarasd Hauptstr 18 Gro\u00dfwarasdorf Burgenland 7304",
    "addr:housenumber":"18",
    "addr:postcode":"7304",
    "addr:street":"Hauptstr",
    "iso:country":"AT",
    "sg:address":"Kleinwarasd Hauptstr 18",
    "sg:city":"Gro\u00dfwarasdorf",
    "sg:orig_category":"Friseure U Frisiersalons",
    "sg:phone":"+43 2614 2710",
    "sg:postcode":"7304",
    "sg:province":"Burgenland",
    "wof:name":"Horvath Helga",
    "wof:placetype":"venue"
},
  "geometry": {"coordinates":[16.586774826,47.5399742126],"type":"Point"}
}