{
  "type": "Feature",
  "properties": {
    "addr:full":"Nr 90 Wildon Steiermark 8410",
    "addr:postcode":"8410",
    "addr:street":"Nr",
    "iso:country":"AT",
    "sg:address":"Nr 90",
    "sg:city":"Wildon",
    "sg:orig_category":"Natursteine U -Platten",
    "sg:phone":"+43 4331 823204",
    "sg:postcode":"8410",
    "sg:province":"Steiermark",
    "wof:name":"Steirische Basalt- u Hartgesteinwerke Appel Steinbruch GesmbH & Co KG",
    "wof:placetype":"venue"
},
  "geometry": {"coordinates":[15.5365247726,46.886920929],"type":"Point"}
}