{
  "type": "Feature",
  "properties": {
    "addr:full":"Lindenpl 4 Neidling Nieder\u00f6sterreich 3110",
    "addr:housenumber":"4",
    "addr:postcode":"3110",
    "addr:street":"Lindenpl;Niederoesterreich",
    "iso:country":"AT",
    "sg:address":"Lindenpl 4",
    "sg:city":"Neidling",
    "sg:orig_category":"Holzhandel",
    "sg:phone":"+43 2741 84620",
    "sg:postcode":"3110",
    "sg:province":"Nieder\u00f6sterreich",
    "wof:name":"Stern Josef - S\u00e4gewerk & Holzhandel",
    "wof:placetype":"venue"
},
  "geometry": {"coordinates":[15.5466165543,48.2307624817],"type":"Point"}
}