{
  "type": "Feature",
  "properties": {
    "addr:full":"Wurzbachgasse 18 PF 50  1152",
    "addr:housenumber":"18;50",
    "addr:postcode":"1152",
    "addr:street":"Wurzbachgasse;Pf",
    "iso:country":"AT",
    "sg:address":"Wurzbachgasse 18 PF 50 ",
    "sg:classifiers":[
        {
            "category":"Wholesale",
            "subcategory":"Drugs",
            "type":"Manufacturing & Wholesale Goods"
        }
    ],
    "sg:phone":"+43 4319 823826",
    "sg:postcode":"1152",
    "sg:tags":[
        "chemical",
        "pharmaceutical"
    ],
    "wof:name":"AMERSHAM BIOSCIENCES TRADING GMBH",
    "wof:placetype":"venue"
},
  "geometry": {"coordinates":[16.3250808716,48.1954498291],"type":"Point"}
}