{
  "type": "Feature",
  "properties": {
    "addr:full":"Auhofstr 15/4/4 Eichgraben Nieder\u00f6sterreich 3032",
    "addr:housenumber":"15 / 4 / 4",
    "addr:postcode":"3032",
    "addr:street":"Auhofstr",
    "iso:country":"AT",
    "sg:address":"Auhofstr 15/4/4",
    "sg:city":"Eichgraben",
    "sg:orig_category":"Steuerberatung",
    "sg:phone":"+43 4327 73424000",
    "sg:postcode":"3032",
    "sg:province":"Nieder\u00f6sterreich",
    "wof:name":"Weidemann Irmgard",
    "wof:placetype":"venue"
},
  "geometry": {"coordinates":[15.976061821,48.1822891235],"type":"Point"}
}