{
  "type": "Feature",
  "properties": {
    "addr:full":"Wilhelm-Kre\u00df-Gasse 25 Tullnerbach Nieder\u00f6sterreich 3013",
    "addr:housenumber":"25",
    "addr:postcode":"3013",
    "addr:street":"Wilhelm-Kress-Gasse",
    "iso:country":"AT",
    "sg:address":"Wilhelm-Kre\u00df-Gasse 25",
    "sg:city":"Tullnerbach",
    "sg:classifiers":[
        {
            "category":"Banks & Credit Unions",
            "subcategory":"Investment Brokerage",
            "type":"Services"
        }
    ],
    "sg:phone":"+43 2233 57917",
    "sg:postcode":"3013",
    "sg:province":"Nieder\u00f6sterreich",
    "sg:tags":[
        "fence"
    ],
    "sg:website":"www.zappe-pflaster.at",
    "wof:name":"Zappe Pflasterungen GesmbH",
    "wof:placetype":"venue"
},
  "geometry": {"coordinates":[16.1210002899,48.1832504272],"type":"Point"}
}