{
  "type": "Feature",
  "properties": {
    "addr:full":"Industriestr 8 Kematen an der Krems Ober\u00f6sterreich 4531",
    "addr:housenumber":"8",
    "addr:postcode":"4531",
    "addr:street":"Industriestr",
    "iso:country":"AT",
    "sg:address":"Industriestr 8",
    "sg:city":"Kematen an der Krems",
    "sg:orig_category":"Metallbe- U -Verarbeitung",
    "sg:phone":"+43 4372 287670",
    "sg:postcode":"4531",
    "sg:province":"Ober\u00f6sterreich",
    "wof:name":"isw innovative schweiss- u w\u00e4rmetechnik GmbH",
    "wof:placetype":"venue"
},
  "geometry": {"coordinates":[14.2082195282,48.1206626892],"type":"Point"}
}