{
  "type": "Feature",
  "properties": {
    "iso:country":"AT",
    "sg:address":"Nr 178",
    "sg:city":"Pruggern",
    "sg:orig_category":"Innenarchitekten",
    "sg:phone":"+43 3685 23553",
    "sg:postcode":"8965",
    "sg:province":"Steiermark",
    "wof:name":"Schrempf August",
    "wof:placetype":"venue"
},
  "geometry": {"coordinates":[13.8756341934,47.4231910706],"type":"Point"}
}