{
  "type": "Feature",
  "properties": {
    "addr:full":"Innerer Graben 12 Ottensheim Ober\u00f6sterreich 4100",
    "addr:housenumber":"12",
    "addr:postcode":"4100",
    "addr:street":"Innerer Graben",
    "iso:country":"AT",
    "sg:address":"Innerer Graben 12",
    "sg:city":"Ottensheim",
    "sg:classifiers":[
        {
            "category":"Professional",
            "subcategory":"Management & Consulting",
            "type":"Services"
        }
    ],
    "sg:phone":"+43 699 10385444",
    "sg:postcode":"4100",
    "sg:province":"Ober\u00f6sterreich",
    "wof:name":"Stockinger G\u00fcnther MAS - Visionswerkstatt",
    "wof:placetype":"venue"
},
  "geometry": {"coordinates":[14.1762218475,48.3328552246],"type":"Point"}
}