{
  "type": "Feature",
  "properties": {
    "addr:full":"Nr 3 St. Valentin Nieder\u00f6sterreich 4300",
    "addr:housenumber":"3",
    "addr:postcode":"4300",
    "addr:street":"Nr",
    "iso:country":"AT",
    "sg:address":"Nr 3",
    "sg:city":"St. Valentin",
    "sg:classifiers":[
        {
            "category":"Restaurant",
            "type":"Food & Drink"
        }
    ],
    "sg:phone":"+43 7435 7272",
    "sg:postcode":"4300",
    "sg:province":"Nieder\u00f6sterreich",
    "sg:tags":[
        "pizzeria"
    ],
    "wof:name":"Pizzeria La Storia",
    "wof:placetype":"venue"
},
  "geometry": {"coordinates":[14.5330696106,48.174621582],"type":"Point"}
}