{
  "type": "Feature",
  "properties": {
    "iso:country":"AT",
    "sg:address":"Nr 84",
    "sg:city":"Gnadendorf",
    "sg:orig_category":"Wasserwerke",
    "sg:phone":"+43 2525 203",
    "sg:postcode":"2152",
    "sg:province":"Nieder\u00f6sterreich",
    "wof:name":"evn wasser GesmbH",
    "wof:placetype":"venue"
},
  "geometry": {"coordinates":[16.4361953735,48.6093597412],"type":"Point"}
}