{
  "type": "Feature",
  "properties": {
    "addr:full":"Bersbuch 405 Andelsbuch Vorarlberg 6866",
    "addr:housenumber":"405",
    "addr:postcode":"6866",
    "addr:street":"Bersbuch",
    "iso:country":"AT",
    "sg:address":"Bersbuch 405",
    "sg:city":"Andelsbuch",
    "sg:orig_category":"Bodenverlegung",
    "sg:phone":"+43 5512 4140",
    "sg:postcode":"6866",
    "sg:province":"Vorarlberg",
    "wof:name":"Fechtig & Co GmbH",
    "wof:placetype":"venue"
},
  "geometry": {"coordinates":[9.8536272049,47.3979492188],"type":"Point"}
}