{
  "type": "Feature",
  "properties": {
    "addr:full":"Landstr 75a Hard Vorarlberg 6971",
    "addr:housenumber":"75a",
    "addr:postcode":"6971",
    "addr:street":"Landstr",
    "iso:country":"AT",
    "sg:address":"Landstr 75a",
    "sg:city":"Hard",
    "sg:orig_category":"Tabaktrafiken",
    "sg:phone":"+43 4355 7472372",
    "sg:postcode":"6971",
    "sg:province":"Vorarlberg",
    "wof:name":"Stadelmann Markus",
    "wof:placetype":"venue"
},
  "geometry": {"coordinates":[9.6835193634,47.4812355042],"type":"Point"}
}