{
  "type": "Feature",
  "properties": {
    "iso:country":"AT",
    "sg:address":"Bellariastr 10",
    "sg:city":"Wien",
    "sg:orig_category":"Schneidereien",
    "sg:phone":"+43 1 5234880",
    "sg:postcode":"1010",
    "sg:province":"Wien",
    "wof:name":"Emmerling Inh Rainer Pittermann",
    "wof:placetype":"venue"
},
  "geometry": {"coordinates":[16.3583183289,48.2056274414],"type":"Point"}
}