{
  "type": "Feature",
  "properties": {
    "addr:full":"Leitenweg 4 Maria Saal K\u00e4rnten 9063",
    "addr:housenumber":"4",
    "addr:postcode":"9063",
    "addr:street":"Leitenweg",
    "iso:country":"AT",
    "sg:address":"Leitenweg 4",
    "sg:city":"Maria Saal",
    "sg:orig_category":"Dienstleistungen, Sonstige Dienstleistungen",
    "sg:phone":"+43 4223 3007",
    "sg:postcode":"9063",
    "sg:province":"K\u00e4rnten",
    "sg:website":"http://www.micheli.co.at",
    "wof:name":"Heiztechnik G. Micheli",
    "wof:placetype":"venue"
},
  "geometry": {"coordinates":[14.3093070984,46.6865844727],"type":"Point"}
}