{
  "type": "Feature",
  "properties": {
    "iso:country":"AT",
    "sg:address":"Grazer Str 34c",
    "sg:city":"Andritz",
    "sg:orig_category":"\u00c3\u201erzte / F Allgemeinmedizin",
    "sg:phone":"+43 316 682514",
    "sg:postcode":"8045",
    "sg:province":"Steiermark",
    "wof:name":"Schroeder David MedR Dr",
    "wof:placetype":"venue"
},
  "geometry": {"coordinates":[15.4194660187,47.0989646912],"type":"Point"}
}