{
  "type": "Feature",
  "properties": {
    "addr:full":"Viktorg 14/11 Wien Wien 1040",
    "addr:housenumber":"14 / 11",
    "addr:postcode":"1040",
    "addr:street":"Viktorg",
    "iso:country":"AT",
    "sg:address":"Viktorg 14/11",
    "sg:city":"Wien",
    "sg:orig_category":"Psychotherapie",
    "sg:phone":"+43 1 5320671",
    "sg:postcode":"1040",
    "sg:province":"Wien",
    "wof:name":"Pall Beatrix",
    "wof:placetype":"venue"
},
  "geometry": {"coordinates":[16.373884201,48.189540863],"type":"Point"}
}