{
  "type": "Feature",
  "properties": {
    "addr:full":"Hauptstr 23 Mitterbach am Erlaufsee Nieder\u00f6sterreich 3224",
    "addr:housenumber":"23",
    "addr:postcode":"3224",
    "addr:street":"Hauptstr",
    "iso:country":"AT",
    "sg:address":"Hauptstr 23",
    "sg:city":"Mitterbach am Erlaufsee",
    "sg:orig_category":"Unterhaltungselektronik / Einzelhandel",
    "sg:phone":"+43 4338 8222280",
    "sg:postcode":"3224",
    "sg:province":"Nieder\u00f6sterreich",
    "wof:name":"Margreiter Werner GesmbH",
    "wof:placetype":"venue"
},
  "geometry": {"coordinates":[15.2959728241,47.8156471252],"type":"Point"}
}