{
  "type": "Feature",
  "properties": {
    "addr:full":"Niederfeldw. 5- 7  Brixlegg Tirol 6230",
    "addr:housenumber":"5 7",
    "addr:postcode":"6230",
    "addr:street":"Niederfeldw.;Tirol",
    "iso:country":"AT",
    "sg:address":"Niederfeldw. 5- 7 ",
    "sg:city":"Brixlegg",
    "sg:classifiers":[
        {
            "category":"Shopping",
            "subcategory":"Clothing, Apparel, & Fashions",
            "type":"Retail Goods"
        }
    ],
    "sg:phone":"+43 4353 376135",
    "sg:postcode":"6230",
    "sg:province":"Tirol",
    "sg:tags":[
        "clothes"
    ],
    "wof:name":"GIESSWEIN WALKWAREN AG",
    "wof:placetype":"venue"
},
  "geometry": {"coordinates":[11.8797426224,47.4364700317],"type":"Point"}
}