{
  "type": "Feature",
  "properties": {
    "addr:full":"Kollersteig 48 Klosterneuburg Nieder\u00f6sterreich 3400",
    "addr:housenumber":"48",
    "addr:postcode":"3400",
    "addr:street":"Kollersteig;Niederoesterreich",
    "iso:country":"AT",
    "sg:address":"Kollersteig 48",
    "sg:city":"Klosterneuburg",
    "sg:orig_category":"Medizintechnik",
    "sg:phone":"+43 2243 25966",
    "sg:postcode":"3400",
    "sg:province":"Nieder\u00f6sterreich",
    "wof:name":"Heliotherm Dr Walter Schiler",
    "wof:placetype":"venue"
},
  "geometry": {"coordinates":[16.3325595856,48.2906455994],"type":"Point"}
}