{
  "type": "Feature",
  "properties": {
    "iso:country":"AT",
    "sg:address":"Nr 155",
    "sg:city":"Kirchbach",
    "sg:orig_category":"Banken U Sparkassen",
    "sg:phone":"+43 4342 84221",
    "sg:postcode":"9632",
    "sg:province":"K\u00e4rnten",
    "wof:name":"Raiffeisenbank K\u00f6tschach-Mauthen regGenmbH",
    "wof:placetype":"venue"
},
  "geometry": {"coordinates":[13.1851024628,46.6416473389],"type":"Point"}
}