{
  "type": "Feature",
  "properties": {
    "addr:full":"Nr 4 Schwarzenberg am B\u00f6hmerwald Ober\u00f6sterreich 4164",
    "addr:postcode":"4164",
    "addr:street":"Nr;Schwarzenberg Am Boehmerwald",
    "iso:country":"AT",
    "sg:address":"Nr 4",
    "sg:city":"Schwarzenberg am B\u00f6hmerwald",
    "sg:orig_category":"Waren Aller Art",
    "sg:phone":"+43 7280 535",
    "sg:postcode":"4164",
    "sg:province":"Ober\u00f6sterreich",
    "wof:name":"Haudum Erwin",
    "wof:placetype":"venue"
},
  "geometry": {"coordinates":[13.8353528976,48.7326164246],"type":"Point"}
}