{
  "type": "Feature",
  "properties": {
    "addr:full":"ed.keilgasse 87 Liebenau Steiermark 8041",
    "addr:housenumber":"87",
    "addr:postcode":"8041",
    "addr:street":"Ed.Keilgasse",
    "iso:country":"AT",
    "sg:address":"ed.keilgasse 87",
    "sg:city":"Liebenau",
    "sg:orig_category":"Freizeit, Musik",
    "sg:phone":"+43 316 464212",
    "sg:postcode":"8041",
    "sg:province":"Steiermark",
    "sg:website":"http://www.explosiv.at/bandscene/str8b/index.html",
    "wof:name":"STR8B",
    "wof:placetype":"venue"
},
  "geometry": {"coordinates":[15.4448699951,47.0435409546],"type":"Point"}
}