{
  "type": "Feature",
  "properties": {
    "addr:full":"Hietzinger Hauptstrasse 42c -  Wien Wien 1130",
    "addr:housenumber":"42c",
    "addr:postcode":"1130",
    "addr:street":"Hietzinger Hauptstrasse",
    "iso:country":"AT",
    "sg:address":"Hietzinger Hauptstrasse 42c - ",
    "sg:city":"Wien",
    "sg:classifiers":[
        {
            "category":"Professional",
            "subcategory":"Art Services",
            "type":"Services"
        }
    ],
    "sg:phone":"+43 4318 777312",
    "sg:postcode":"1130",
    "sg:province":"Wien",
    "sg:tags":[
        "export-import"
    ],
    "sg:website":"http://www.brh - gov - pl.or.at",
    "wof:name":"Poland Embassy",
    "wof:placetype":"venue"
},
  "geometry": {"coordinates":[16.2911453247,48.1872138977],"type":"Point"}
}