{
  "type": "Feature",
  "properties": {
    "addr:full":"St. Oswalder Str 5B Gutau Ober\u00f6sterreich 4293",
    "addr:postcode":"4293",
    "addr:street":"St.;Str 5B",
    "iso:country":"AT",
    "sg:address":"St. Oswalder Str 5B",
    "sg:city":"Gutau",
    "sg:orig_category":"Installationsunternehmen",
    "sg:phone":"+43 7946 20570",
    "sg:postcode":"4293",
    "sg:province":"Ober\u00f6sterreich",
    "wof:name":"Wurm Hans GesmbH",
    "wof:placetype":"venue"
},
  "geometry": {"coordinates":[14.6142454147,48.420375824],"type":"Point"}
}