{
  "type": "Feature",
  "properties": {
    "addr:full":"Nr 84 Kohfidisch Burgenland 7512",
    "addr:postcode":"7512",
    "addr:street":"Nr",
    "iso:country":"AT",
    "sg:address":"Nr 84",
    "sg:city":"Kohfidisch",
    "sg:classifiers":[
        {
            "category":"Professional",
            "subcategory":"Management & Consulting",
            "type":"Services"
        }
    ],
    "sg:phone":"+43 3366 77303",
    "sg:postcode":"7512",
    "sg:province":"Burgenland",
    "sg:tags":[
        "supervision"
    ],
    "wof:name":"Pronegg Annemarie - Sozialp\u00e4dagogin - Supervisorin",
    "wof:placetype":"venue"
},
  "geometry": {"coordinates":[16.3575592041,47.1757698059],"type":"Point"}
}