{
  "type": "Feature",
  "properties": {
    "iso:country":"AT",
    "sg:address":"Auf dem Kikel 343",
    "sg:city":"Feistritz an der Drau",
    "sg:classifiers":[
        {
            "category":"Home & Garden",
            "subcategory":"Furniture",
            "type":"Retail Goods"
        }
    ],
    "sg:phone":"+43 4245 3520",
    "sg:postcode":"9710",
    "sg:province":"K\u00e4rnten",
    "sg:tags":[
        "bathroom"
    ],
    "sg:website":"kapeller-wohnen.at",
    "wof:name":"Kapeller Naturholz Manufaktur GmbH",
    "wof:placetype":"venue"
},
  "geometry": {"coordinates":[13.6812143326,46.6893577576],"type":"Point"}
}