{
  "type": "Feature",
  "properties": {
    "addr:full":"K\u00e4rntner Strasse 49/4 Wien Wien 1010",
    "addr:housenumber":"49 / 4",
    "addr:postcode":"1010",
    "addr:street":"Kaerntner Strasse",
    "iso:country":"AT",
    "sg:address":"K\u00e4rntner Strasse 49/4",
    "sg:city":"Wien",
    "sg:classifiers":[
        {
            "category":"Building & Trades",
            "subcategory":"Construction",
            "type":"Services"
        }
    ],
    "sg:phone":"+43 1 5129490",
    "sg:postcode":"1010",
    "sg:province":"Wien",
    "sg:tags":[
        "exhibition"
    ],
    "sg:website":"at.messe-muenchen.de",
    "wof:name":"MMI-Messe M\u00fcnchen International Regionalb\u00fcro Mittel/Osteuropa GmbH.",
    "wof:placetype":"venue"
},
  "geometry": {"coordinates":[16.3704605103,48.2037200928],"type":"Point"}
}