{
  "type": "Feature",
  "properties": {
    "addr:full":"Hauptstr 7 Strengberg Nieder\u00f6sterreich 3314",
    "addr:housenumber":"7",
    "addr:postcode":"3314",
    "addr:street":"Hauptstr",
    "iso:country":"AT",
    "sg:address":"Hauptstr 7",
    "sg:city":"Strengberg",
    "sg:orig_category":"Autohandel",
    "sg:phone":"+43 7432 2330",
    "sg:postcode":"3314",
    "sg:province":"Nieder\u00f6sterreich",
    "wof:name":"Schneider Johann",
    "wof:placetype":"venue"
},
  "geometry": {"coordinates":[14.6478061676,48.1431846619],"type":"Point"}
}