{
  "type": "Feature",
  "properties": {
    "addr:full":"Tummelpl 3 Linz Ober\u00f6sterreich 4020",
    "addr:housenumber":"3",
    "addr:postcode":"4020",
    "addr:street":"Tummelpl",
    "iso:country":"AT",
    "sg:address":"Tummelpl 3",
    "sg:city":"Linz",
    "sg:orig_category":"Architekten",
    "sg:phone":"+43 732 773148",
    "sg:postcode":"4020",
    "sg:province":"Ober\u00f6sterreich",
    "wof:name":"Fais Karlheinz Arch Dipl-Ing",
    "wof:placetype":"venue"
},
  "geometry": {"coordinates":[14.2840995789,48.3048400879],"type":"Point"}
}