{
  "type": "Feature",
  "properties": {
    "iso:country":"AT",
    "sg:address":"Rathauspl 3",
    "sg:city":"Klosterneuburg",
    "sg:orig_category":"Bars-Cafes",
    "sg:phone":"+43 4322 4336460",
    "sg:postcode":"3400",
    "sg:province":"Nieder\u00f6sterreich",
    "wof:name":"Finale Cafe Bar",
    "wof:placetype":"venue"
},
  "geometry": {"coordinates":[16.3250961304,48.3049240112],"type":"Point"}
}