{
  "type": "Feature",
  "properties": {
    "addr:full":"Oberer Schiffweg 27 Steyr Ober\u00f6sterreich 4400",
    "addr:housenumber":"27",
    "addr:postcode":"4400",
    "addr:street":"Oberer Schiffweg;Oberoesterreich",
    "iso:country":"AT",
    "sg:address":"Oberer Schiffweg 27",
    "sg:city":"Steyr",
    "sg:orig_category":"Feldenkraismethode",
    "sg:phone":"+43 4372 5241820",
    "sg:postcode":"4400",
    "sg:province":"Ober\u00f6sterreich",
    "wof:name":"Emmer Sarah Gertraud Mag",
    "wof:placetype":"venue"
},
  "geometry": {"coordinates":[14.4134750366,48.0273857117],"type":"Point"}
}