{
  "type": "Feature",
  "properties": {
    "iso:country":"AT",
    "sg:address":"Goldschlagstr 12",
    "sg:city":"Wien",
    "sg:orig_category":"Maschinenhandel",
    "sg:phone":"+43 1 9827370",
    "sg:postcode":"1150",
    "sg:province":"Wien",
    "wof:name":"Gajda OHG",
    "wof:placetype":"venue"
},
  "geometry": {"coordinates":[16.335647583,48.1990661621],"type":"Point"}
}