{
  "type": "Feature",
  "properties": {
    "addr:full":"Ladendorfer Str 18 Neubau Nieder\u00f6sterreich 2125",
    "addr:housenumber":"18",
    "addr:postcode":"2125",
    "addr:street":"Str",
    "iso:country":"AT",
    "sg:address":"Ladendorfer Str 18",
    "sg:city":"Neubau",
    "sg:orig_category":"Friseure U Frisiersalons",
    "sg:phone":"+43 4325 758445",
    "sg:postcode":"2125",
    "sg:province":"Nieder\u00f6sterreich",
    "wof:name":"Frisiersalon Angela",
    "wof:placetype":"venue"
},
  "geometry": {"coordinates":[16.5192203522,48.5010375977],"type":"Point"}
}