{
  "type": "Feature",
  "properties": {
    "addr:full":"Kaserng 4 Judenburg Steiermark 8750",
    "addr:housenumber":"4",
    "addr:postcode":"8750",
    "addr:street":"Kaserng",
    "iso:country":"AT",
    "sg:address":"Kaserng 4",
    "sg:city":"Judenburg",
    "sg:orig_category":"Fu\u00c3\u0178pflege U Fu\u00c3\u0178pflegesalons",
    "sg:phone":"+43 4335 7285049",
    "sg:postcode":"8750",
    "sg:province":"Steiermark",
    "wof:name":"Messner Waltraud",
    "wof:placetype":"venue"
},
  "geometry": {"coordinates":[14.6617441177,47.1691207886],"type":"Point"}
}