{
  "type": "Feature",
  "properties": {
    "addr:full":"J\u00e4gerstr 41 Wien Wien 1200",
    "addr:housenumber":"41",
    "addr:postcode":"1200",
    "addr:street":"Jaegerstr",
    "iso:country":"AT",
    "sg:address":"J\u00e4gerstr 41",
    "sg:city":"Wien",
    "sg:orig_category":"Fleischhauereien",
    "sg:phone":"+43 1 3744333",
    "sg:postcode":"1200",
    "sg:province":"Wien",
    "wof:name":"Schirnhofer-Breisler GesmbH - Shop in Shop",
    "wof:placetype":"venue"
},
  "geometry": {"coordinates":[16.3705253601,48.2309761047],"type":"Point"}
}