{
  "type": "Feature",
  "properties": {
    "addr:full":"Hauptpl 14 Leibnitz Steiermark 8430",
    "addr:housenumber":"14",
    "addr:postcode":"8430",
    "addr:street":"Hauptpl;Steiermark",
    "iso:country":"AT",
    "sg:address":"Hauptpl 14",
    "sg:city":"Leibnitz",
    "sg:orig_category":"Damenmoden",
    "sg:phone":"+43 4334 5284336",
    "sg:postcode":"8430",
    "sg:province":"Steiermark",
    "wof:name":"Gauby GesmbH & Co KG",
    "wof:placetype":"venue"
},
  "geometry": {"coordinates":[15.539150238,46.781879425],"type":"Point"}
}