{
  "type": "Feature",
  "properties": {
    "iso:country":"AT",
    "sg:address":"Salzburger Str 250",
    "sg:city":"Gro\u00dfgmain",
    "sg:orig_category":"Tourismusinformation U -Organisationen",
    "sg:phone":"+43 6247 82780",
    "sg:postcode":"5084",
    "sg:province":"Salzburg",
    "wof:name":"Fremdenverkehrsverband Gro\u00dfgmain",
    "wof:placetype":"venue"
},
  "geometry": {"coordinates":[12.0809497833,48.0439414978],"type":"Point"}
}