{
  "type": "Feature",
  "properties": {
    "addr:full":"Kammelweg 11 Wien Wien 1210",
    "addr:housenumber":"11",
    "addr:postcode":"1210",
    "addr:street":"Kammelweg",
    "iso:country":"AT",
    "sg:address":"Kammelweg 11",
    "sg:city":"Wien",
    "sg:classifiers":[
        {
            "category":"Professional",
            "subcategory":"Art Services",
            "type":"Services"
        }
    ],
    "sg:phone":"+43 1 27167000",
    "sg:postcode":"1210",
    "sg:province":"Wien",
    "sg:tags":[
        "stand",
        "construction",
        "exhibition",
        "fair",
        "trade"
    ],
    "sg:website":"exponorm.at",
    "wof:name":"expo norm Werbewerkst\u00e4tte Ges.m.b.H.",
    "wof:placetype":"venue"
},
  "geometry": {"coordinates":[16.3861846924,48.2719917297],"type":"Point"}
}