{
  "type": "Feature",
  "properties": {
    "iso:country":"AT",
    "sg:address":"St. Gertraudi 67",
    "sg:city":"Brixlegg",
    "sg:orig_category":"Transportunternehmen",
    "sg:phone":"+43 5337 62377",
    "sg:postcode":"6230",
    "sg:province":"Tirol",
    "wof:name":"Larch Transporte GesmbH & Co KG",
    "wof:placetype":"venue"
},
  "geometry": {"coordinates":[11.8779993057,47.4296073914],"type":"Point"}
}