{
  "type": "Feature",
  "properties": {
    "addr:full":"Hinterlobming 35 St. Stefan ob Leoben Steiermark 8713",
    "addr:housenumber":"35",
    "addr:postcode":"8713",
    "addr:street":"Hinterlobming",
    "iso:country":"AT",
    "sg:address":"Hinterlobming 35",
    "sg:city":"St. Stefan ob Leoben",
    "sg:orig_category":"Forstverwaltungen",
    "sg:phone":"+43 3832 2817",
    "sg:postcode":"8713",
    "sg:province":"Steiermark",
    "wof:name":"Leobner Realgemeinschaft",
    "wof:placetype":"venue"
},
  "geometry": {"coordinates":[15.0275993347,47.2848815918],"type":"Point"}
}