{
  "type": "Feature",
  "properties": {
    "addr:full":"Durchlaufstr 11 Wien Wien 1200",
    "addr:housenumber":"11",
    "addr:postcode":"1200",
    "addr:street":"Durchlaufstr",
    "iso:country":"AT",
    "sg:address":"Durchlaufstr 11",
    "sg:city":"Wien",
    "sg:orig_category":"Messen U Ausstellungen, Messe- U Ausstellungsbau U -Gestaltung",
    "sg:phone":"+43 4367 63776571",
    "sg:postcode":"1200",
    "sg:province":"Wien",
    "sg:website":"messebau.at",
    "wof:name":"L\u00fcckl GmbH",
    "wof:placetype":"venue"
},
  "geometry": {"coordinates":[16.3815040588,48.2370300293],"type":"Point"}
}