{
  "type": "Feature",
  "properties": {
    "addr:full":"Fisching 4 Asten Ober\u00f6sterreich 4481",
    "addr:housenumber":"4",
    "addr:postcode":"4481",
    "addr:street":"Fisching",
    "iso:country":"AT",
    "sg:address":"Fisching 4",
    "sg:city":"Asten",
    "sg:classifiers":[
        {
            "category":"Home & Garden",
            "subcategory":"Garden Supply",
            "type":"Retail Goods"
        }
    ],
    "sg:phone":"+43 7224 22354",
    "sg:postcode":"4481",
    "sg:province":"Ober\u00f6sterreich",
    "sg:tags":[
        "schotter",
        "sand",
        "u"
    ],
    "wof:name":"Spitzbart Bau GmbH",
    "wof:placetype":"venue"
},
  "geometry": {"coordinates":[14.4223203659,48.2196464539],"type":"Point"}
}