{
  "type": "Feature",
  "properties": {
    "addr:full":"Lindeng 1 Wien Wien 1070",
    "addr:housenumber":"1",
    "addr:postcode":"1070",
    "addr:street":"Lindeng",
    "iso:country":"AT",
    "sg:address":"Lindeng 1",
    "sg:city":"Wien",
    "sg:classifiers":[
        {
            "category":"Restaurant",
            "type":"Food & Drink"
        }
    ],
    "sg:phone":"+43 1 5261377",
    "sg:postcode":"1070",
    "sg:province":"Wien",
    "wof:name":"Stiftkeller",
    "wof:placetype":"venue"
},
  "geometry": {"coordinates":[16.3550205231,48.2013320923],"type":"Point"}
}