{
  "type": "Feature",
  "properties": {
    "addr:full":"Haid 39 am Kirchboden Wagrain Salzburg 5602",
    "addr:housenumber":"39",
    "addr:postcode":"5602",
    "addr:street":"Haid;Kirchboden;Salzburg",
    "iso:country":"AT",
    "sg:address":"Haid 39 am Kirchboden",
    "sg:city":"Wagrain",
    "sg:orig_category":"Reisen, Tourismusinfo",
    "sg:phone":"+43 4364 1382390",
    "sg:postcode":"5602",
    "sg:province":"Salzburg",
    "sg:website":"http://www.haus-kristall.com",
    "wof:name":"Familienapartments Kristall in Wagrain",
    "wof:placetype":"venue"
},
  "geometry": {"coordinates":[13.2964773178,47.3332366943],"type":"Point"}
}