{
  "type": "Feature",
  "properties": {
    "addr:full":"Wiener Str 31 Traiskirchen Nieder\u00f6sterreich 2514",
    "addr:postcode":"2514",
    "addr:street":"31",
    "iso:country":"AT",
    "sg:address":"Wiener Str 31",
    "sg:city":"Traiskirchen",
    "sg:classifiers":[
        {
            "category":"Restaurant",
            "type":"Food & Drink"
        }
    ],
    "sg:phone":"+43 2252 524120",
    "sg:postcode":"2514",
    "sg:province":"Nieder\u00f6sterreich",
    "wof:name":"Winzerhaus",
    "wof:placetype":"venue"
},
  "geometry": {"coordinates":[16.2942333221,48.01770401],"type":"Point"}
}