{
  "type": "Feature",
  "properties": {
    "addr:full":"Bundesstr 10 Fohnsdorf Steiermark 8753",
    "addr:housenumber":"10",
    "addr:postcode":"8753",
    "addr:street":"Bundesstr",
    "iso:country":"AT",
    "sg:address":"Bundesstr 10",
    "sg:city":"Fohnsdorf",
    "sg:orig_category":"Autohandel",
    "sg:phone":"+43 4335 77225830",
    "sg:postcode":"8753",
    "sg:province":"Steiermark",
    "sg:website":"autohaus-neubauer.at",
    "wof:name":"Autohaus Neubauer",
    "wof:placetype":"venue"
},
  "geometry": {"coordinates":[14.7129611969,47.1947593689],"type":"Point"}
}