{
  "type": "Feature",
  "properties": {
    "addr:full":"Stelzhamerstrasse 2 St. Georgen im Attergau Ober\u00f6sterreich 4880",
    "addr:housenumber":"2",
    "addr:postcode":"4880",
    "addr:street":"Stelzhamerstrasse",
    "iso:country":"AT",
    "sg:address":"Stelzhamerstrasse 2",
    "sg:city":"St. Georgen im Attergau",
    "sg:classifiers":[
        {
            "category":"Professional",
            "subcategory":"Art Services",
            "type":"Services"
        }
    ],
    "sg:phone":"+43 76676442",
    "sg:postcode":"4880",
    "sg:province":"Ober\u00f6sterreich",
    "sg:tags":[
        "metalwork"
    ],
    "wof:name":"Franz Schneeweiss",
    "wof:placetype":"venue"
},
  "geometry": {"coordinates":[13.4819536209,47.9353675842],"type":"Point"}
}