{
  "type": "Feature",
  "properties": {
    "iso:country":"AT",
    "sg:address":"Nr 155",
    "sg:city":"St. Martin am Tennengebirge",
    "sg:classifiers":[
        {
            "category":"Park",
            "subcategory":"Provincial",
            "type":"Public Place"
        }
    ],
    "sg:phone":"+43 4366 42100996",
    "sg:postcode":"5522",
    "sg:province":"Salzburg",
    "sg:tags":[
        "u",
        "ski-",
        "snowboardschulen"
    ],
    "wof:name":"Schischule St Martin - Manfred Wei\u00df",
    "wof:placetype":"venue"
},
  "geometry": {"coordinates":[13.3810081482,47.4648284912],"type":"Point"}
}