{
  "type": "Feature",
  "properties": {
    "addr:full":"Stadionstr 12 Wiener Neustadt Nieder\u00f6sterreich 2700",
    "addr:housenumber":"12",
    "addr:postcode":"2700",
    "addr:street":"Stadionstr",
    "iso:country":"AT",
    "sg:address":"Stadionstr 12",
    "sg:city":"Wiener Neustadt",
    "sg:orig_category":"Friseure U Frisiersalons",
    "sg:phone":"+43 4326 2286174",
    "sg:postcode":"2700",
    "sg:province":"Nieder\u00f6sterreich",
    "wof:name":"TRAUNER FRIS\u00f6R",
    "wof:placetype":"venue"
},
  "geometry": {"coordinates":[16.2553596497,47.8241004944],"type":"Point"}
}