{
  "type": "Feature",
  "properties": {
    "addr:full":"Sch\u00fcttelstr 101/3 Wien Wien 1020",
    "addr:housenumber":"101 / 3",
    "addr:postcode":"1020",
    "iso:country":"AT",
    "sg:address":"Sch\u00fcttelstr 101/3",
    "sg:city":"Wien",
    "sg:orig_category":"Architekten",
    "sg:phone":"+43 1 7206260",
    "sg:postcode":"1020",
    "sg:province":"Wien",
    "wof:name":"Charamza Alfred Arch Dipl-Ing",
    "wof:placetype":"venue"
},
  "geometry": {"coordinates":[16.3802642822,48.2153701782],"type":"Point"}
}