{
  "type": "Feature",
  "properties": {
    "addr:full":"Nr 179 Ort im Innkreis Ober\u00f6sterreich 4974",
    "addr:postcode":"4974",
    "addr:street":"Nr 179",
    "iso:country":"AT",
    "sg:address":"Nr 179",
    "sg:city":"Ort im Innkreis",
    "sg:orig_category":"Dachdeckereien",
    "sg:phone":"+43 7751 83820",
    "sg:postcode":"4974",
    "sg:province":"Ober\u00f6sterreich",
    "wof:name":"Bachmair Dachdeckerei & Spenglerei GmbH & Co KG",
    "wof:placetype":"venue"
},
  "geometry": {"coordinates":[13.4339199066,48.3160705566],"type":"Point"}
}