{
  "type": "Feature",
  "properties": {
    "addr:full":"Klagenfurter Str 46 Villach K\u00e4rnten 9500",
    "addr:housenumber":"46",
    "addr:postcode":"9500",
    "addr:street":"Str;Kaernten",
    "iso:country":"AT",
    "sg:address":"Klagenfurter Str 46",
    "sg:city":"Villach",
    "sg:orig_category":"Spenglereien",
    "sg:phone":"+43 4242 285470",
    "sg:postcode":"9500",
    "sg:province":"K\u00e4rnten",
    "wof:name":"Mitzner Heinz GesmbH & Co KG",
    "wof:placetype":"venue"
},
  "geometry": {"coordinates":[13.8545923233,46.6185264587],"type":"Point"}
}