{
  "type": "Feature",
  "properties": {
    "addr:full":"Bismarckg 9 Weiz Steiermark 8160",
    "addr:housenumber":"9",
    "addr:postcode":"8160",
    "addr:street":"Bismarckg",
    "iso:country":"AT",
    "sg:address":"Bismarckg 9",
    "sg:city":"Weiz",
    "sg:orig_category":"Bekleidung / Einzelhandel",
    "sg:phone":"+43 4331 7230421",
    "sg:postcode":"8160",
    "sg:province":"Steiermark",
    "wof:name":"MaXXXi Mode Inh Lydia Hummer",
    "wof:placetype":"venue"
},
  "geometry": {"coordinates":[15.6237945557,47.2182121277],"type":"Point"}
}