{
  "type": "Feature",
  "properties": {
    "iso:country":"AT",
    "sg:address":"Alte Str 3",
    "sg:city":"Wolfsberg",
    "sg:orig_category":"Fliesen U Platten",
    "sg:phone":"+43 4352 81621",
    "sg:postcode":"9400",
    "sg:province":"K\u00e4rnten",
    "sg:website":"www.fliesen-leeb.at",
    "wof:name":"Fliesen Leeb GmbH KG",
    "wof:placetype":"venue"
},
  "geometry": {"coordinates":[14.8418502808,46.8402099609],"type":"Point"}
}