{
  "type": "Feature",
  "properties": {
    "iso:country":"AT",
    "sg:address":"Huschkag 11",
    "sg:city":"Wien",
    "sg:orig_category":"Marketingberatung",
    "sg:phone":"+43 1 71263240",
    "sg:postcode":"1190",
    "sg:province":"Wien",
    "wof:name":"Rotay Len Taylor & Co",
    "wof:placetype":"venue"
},
  "geometry": {"coordinates":[16.3447341919,48.2523803711],"type":"Point"}
}