{
  "type": "Feature",
  "properties": {
    "addr:full":"V\u00f6slauer Strasse 59 Baden Nieder\u00f6sterreich 2500",
    "addr:housenumber":"59",
    "addr:postcode":"2500",
    "addr:street":"Voeslauer Strasse;Niederoesterreich",
    "iso:country":"AT",
    "sg:address":"V\u00f6slauer Strasse 59",
    "sg:city":"Baden",
    "sg:classifiers":[
        {
            "category":"Organizations",
            "subcategory":"Community Association",
            "type":"Services"
        }
    ],
    "sg:phone":"+43 2252 48667",
    "sg:postcode":"2500",
    "sg:province":"Nieder\u00f6sterreich",
    "sg:tags":[
        "stacked",
        "carriers",
        "pallet",
        "equipment",
        "lifter",
        "transporting",
        "brick"
    ],
    "wof:name":"Johann Sulzer GmbH",
    "wof:placetype":"venue"
},
  "geometry": {"coordinates":[16.2295131683,47.9989204407],"type":"Point"}
}