{
  "type": "Feature",
  "properties": {
    "addr:full":"Nr 101 Hitzendorf Steiermark 8151",
    "addr:postcode":"8151",
    "addr:street":"Nr 101",
    "iso:country":"AT",
    "sg:address":"Nr 101",
    "sg:city":"Hitzendorf",
    "sg:orig_category":"Feuerwehren",
    "sg:phone":"+43 3137 4552",
    "sg:postcode":"8151",
    "sg:province":"Steiermark",
    "wof:name":"Freiwillige Feuerwehr Berndorf",
    "wof:placetype":"venue"
},
  "geometry": {"coordinates":[15.2883749008,47.0537490845],"type":"Point"}
}