{
  "type": "Feature",
  "properties": {
    "addr:full":"Gunoldstr 14 Wien Wien 1190",
    "addr:housenumber":"14",
    "addr:postcode":"1190",
    "addr:street":"Gunoldstr",
    "iso:country":"AT",
    "sg:address":"Gunoldstr 14",
    "sg:city":"Wien",
    "sg:orig_category":"Zeitungen U Zeitschriften",
    "sg:phone":"+43 4313 698902",
    "sg:postcode":"1190",
    "sg:province":"Wien",
    "wof:name":"Mainichi Shimbun",
    "wof:placetype":"venue"
},
  "geometry": {"coordinates":[16.3654174805,48.2450714111],"type":"Point"}
}