{
  "type": "Feature",
  "properties": {
    "addr:full":"Scheibenbergstr 51/1 Wien Wien 1180",
    "addr:housenumber":"51 / 1",
    "addr:postcode":"1180",
    "addr:street":"Scheibenbergstr",
    "iso:country":"AT",
    "sg:address":"Scheibenbergstr 51/1",
    "sg:city":"Wien",
    "sg:orig_category":"Lebens- U Sozialberatung",
    "sg:phone":"+43 1 4797060",
    "sg:postcode":"1180",
    "sg:province":"Wien",
    "wof:name":"T\u00fcrk-Lindmaier Renate Dipl Sexualp\u00e4dagogin und dipl Sexualberaterin",
    "wof:placetype":"venue"
},
  "geometry": {"coordinates":[16.3170051575,48.2359924316],"type":"Point"}
}