{
  "type": "Feature",
  "properties": {
    "addr:full":"Schneebergg 47 Wiener Neustadt Nieder\u00f6sterreich 2700",
    "addr:housenumber":"47",
    "addr:postcode":"2700",
    "addr:street":"Schneebergg",
    "iso:country":"AT",
    "sg:address":"Schneebergg 47",
    "sg:city":"Wiener Neustadt",
    "sg:orig_category":"Friseure U Frisiersalons",
    "sg:phone":"+43 4326 2227921",
    "sg:postcode":"2700",
    "sg:province":"Nieder\u00f6sterreich",
    "wof:name":"Hair Point",
    "wof:placetype":"venue"
},
  "geometry": {"coordinates":[16.2240505219,47.8119316101],"type":"Point"}
}