{
  "type": "Feature",
  "properties": {
    "addr:full":"Hauptstr 96 Trofaiach Steiermark 8793",
    "addr:housenumber":"96",
    "addr:postcode":"8793",
    "addr:street":"Hauptstr",
    "iso:country":"AT",
    "sg:address":"Hauptstr 96",
    "sg:city":"Trofaiach",
    "sg:orig_category":"Unterhaltungselektronik / Einzelhandel",
    "sg:phone":"+43 3847 2768",
    "sg:postcode":"8793",
    "sg:province":"Steiermark",
    "wof:name":"Strallhofer Heinrich",
    "wof:placetype":"venue"
},
  "geometry": {"coordinates":[15.0082406998,47.4286727905],"type":"Point"}
}