{
  "type": "Feature",
  "properties": {
    "addr:full":"Rathauspl 1 Pulkau Nieder\u00f6sterreich 3741",
    "addr:housenumber":"1",
    "addr:postcode":"3741",
    "addr:street":"Rathauspl",
    "iso:country":"AT",
    "sg:address":"Rathauspl 1",
    "sg:city":"Pulkau",
    "sg:orig_category":"Banken U Sparkassen",
    "sg:phone":"+43 4329 4622400",
    "sg:postcode":"3741",
    "sg:province":"Nieder\u00f6sterreich",
    "wof:name":"Weinviertler Sparkasse AG",
    "wof:placetype":"venue"
},
  "geometry": {"coordinates":[15.8591403961,48.7058944702],"type":"Point"}
}