{
  "type": "Feature",
  "properties": {
    "addr:full":"Sch\u00f6ffbenkerstr 22 Traunkirchen Ober\u00f6sterreich 4801",
    "addr:housenumber":"22",
    "addr:postcode":"4801",
    "addr:street":"Schoeffbenkerstr",
    "iso:country":"AT",
    "sg:address":"Sch\u00f6ffbenkerstr 22",
    "sg:city":"Traunkirchen",
    "sg:orig_category":"Massagen",
    "sg:phone":"+43 76172206",
    "sg:postcode":"4801",
    "sg:province":"Ober\u00f6sterreich",
    "wof:name":"Wellness-Center Schahla-Burner",
    "wof:placetype":"venue"
},
  "geometry": {"coordinates":[13.7632551193,47.8542938232],"type":"Point"}
}