{
  "type": "Feature",
  "properties": {
    "iso:country":"AT",
    "sg:address":"Industriepark H\u00f6nigsberg 7",
    "sg:city":"M\u00fcrzzuschlag-H\u00f6nigsberg",
    "sg:classifiers":[
        {
            "category":"Manufacturing",
            "subcategory":"Tools & Machinery",
            "type":"Manufacturing & Wholesale Goods"
        }
    ],
    "sg:phone":"+43 3852 5178",
    "sg:postcode":"8682",
    "sg:province":"Steiermark",
    "sg:tags":[
        "construction",
        "container",
        "apparatus"
    ],
    "sg:website":"hdp.at",
    "wof:name":"HDP-Hochdruckprodukte Ges.m.b.H. Maschinen- und Apparatebau",
    "wof:placetype":"venue"
},
  "geometry": {"coordinates":[15.6508703232,47.5816001892],"type":"Point"}
}