{
  "type": "Feature",
  "properties": {
    "addr:full":"Bahnhofstr 27/1 Ried im Innkreis Ober\u00f6sterreich 4910",
    "addr:housenumber":"27 / 1",
    "addr:postcode":"4910",
    "addr:street":"Bahnhofstr",
    "iso:country":"AT",
    "sg:address":"Bahnhofstr 27/1",
    "sg:city":"Ried im Innkreis",
    "sg:orig_category":"Steuerungstechnik",
    "sg:phone":"+43 7752 71747",
    "sg:postcode":"4910",
    "sg:province":"Ober\u00f6sterreich",
    "wof:name":"VAP Futur",
    "wof:placetype":"venue"
},
  "geometry": {"coordinates":[13.4887142181,48.2059707642],"type":"Point"}
}