{
  "type": "Feature",
  "properties": {
    "addr:full":"Gablitzer Steig 1d Mauerbach Nieder\u00f6sterreich 3001",
    "addr:housenumber":"1d",
    "addr:postcode":"3001",
    "addr:street":"Gablitzer Steig",
    "iso:country":"AT",
    "sg:address":"Gablitzer Steig 1d",
    "sg:city":"Mauerbach",
    "sg:orig_category":"Autohandel",
    "sg:phone":"+43 1 9794829",
    "sg:postcode":"3001",
    "sg:province":"Nieder\u00f6sterreich",
    "wof:name":"Die CAR-Agentur - Kurt Langschwert",
    "wof:placetype":"venue"
},
  "geometry": {"coordinates":[16.1648254395,48.2448425293],"type":"Point"}
}