{
  "type": "Feature",
  "properties": {
    "addr:full":"Flirstr 32 Landeck Tirol 6500",
    "addr:housenumber":"32",
    "addr:postcode":"6500",
    "addr:street":"Flirstr;Tirol",
    "iso:country":"AT",
    "sg:address":"Flirstr 32",
    "sg:city":"Landeck",
    "sg:orig_category":"Raumausstattung",
    "sg:phone":"+43 5442 65680",
    "sg:postcode":"6500",
    "sg:province":"Tirol",
    "wof:name":"Polsterei-Raumausstattung Egger",
    "wof:placetype":"venue"
},
  "geometry": {"coordinates":[10.6277132034,47.1200027466],"type":"Point"}
}