{
  "type": "Feature",
  "properties": {
    "addr:full":"Lasserstr 6a Salzburg Salzburg 5020",
    "addr:housenumber":"6a",
    "addr:postcode":"5020",
    "addr:street":"Lasserstr;Salzburg",
    "iso:country":"AT",
    "sg:address":"Lasserstr 6a",
    "sg:city":"Salzburg",
    "sg:orig_category":"Architekten",
    "sg:phone":"+43 662 878799",
    "sg:postcode":"5020",
    "sg:province":"Salzburg",
    "wof:name":"fl\u00f6ckner-schn\u00f6ll Architekten",
    "wof:placetype":"venue"
},
  "geometry": {"coordinates":[13.0505247116,47.8074531555],"type":"Point"}
}