{
  "type": "Feature",
  "properties": {
    "iso:country":"AT",
    "sg:address":"Dorfpl 1",
    "sg:city":"Zell am Ziller",
    "sg:classifiers":[
        {
            "category":"Travel",
            "subcategory":"Hotels & Motels",
            "type":"Entertainment"
        }
    ],
    "sg:phone":"+43 5282 23130",
    "sg:postcode":"6280",
    "sg:province":"Tirol",
    "wof:name":"Hotel Br\u00e4u",
    "wof:placetype":"venue"
},
  "geometry": {"coordinates":[11.8810739517,47.233417511],"type":"Point"}
}