{
  "type": "Feature",
  "properties": {
    "addr:full":"Malta 26 Malta K\u00e4rnten 9854",
    "addr:housenumber":"26",
    "addr:postcode":"9854",
    "addr:street":"Malta;Kaernten",
    "iso:country":"AT",
    "sg:address":"Malta 26",
    "sg:city":"Malta",
    "sg:classifiers":[
        {
            "category":"Banks & Credit Unions",
            "subcategory":"Investment Brokerage",
            "type":"Services"
        }
    ],
    "sg:phone":"+43 4733 20023",
    "sg:postcode":"9854",
    "sg:province":"K\u00e4rnten",
    "sg:tags":[
        "development",
        "cd-rom"
    ],
    "sg:website":"krv.at",
    "wof:name":"Klaus R\u00fcscher Videoproduktion (KRV)",
    "wof:placetype":"venue"
},
  "geometry": {"coordinates":[13.5123491287,46.9512329102],"type":"Point"}
}