{
  "type": "Feature",
  "properties": {
    "addr:full":"Silberbergstrasse 9 Wolfsberg K\u00e4rnten 9400",
    "addr:housenumber":"9;kaernten",
    "addr:postcode":"9400",
    "addr:street":"Silberbergstrasse",
    "iso:country":"AT",
    "sg:address":"Silberbergstrasse 9",
    "sg:city":"Wolfsberg",
    "sg:classifiers":[
        {
            "category":"Banks & Credit Unions",
            "subcategory":"Investment Brokerage",
            "type":"Services"
        }
    ],
    "sg:phone":"+43 4352 2440",
    "sg:postcode":"9400",
    "sg:province":"K\u00e4rnten",
    "sg:tags":[
        "telecommunication",
        "isdn",
        "system"
    ],
    "sg:website":"rse.at",
    "wof:name":"RSE Informationstechnologie GmbH",
    "wof:placetype":"venue"
},
  "geometry": {"coordinates":[14.8569097519,46.8227653503],"type":"Point"}
}