{
  "type": "Feature",
  "properties": {
    "addr:full":"Bl\u00fchnbachstr 38 Tenneck Salzburg 5451",
    "addr:housenumber":"38",
    "addr:postcode":"5451",
    "addr:street":"Bluehnbachstr;Salzburg",
    "iso:country":"AT",
    "sg:address":"Bl\u00fchnbachstr 38",
    "sg:city":"Tenneck",
    "sg:orig_category":"Entsorgungen",
    "sg:phone":"+43 664 4249221",
    "sg:postcode":"5451",
    "sg:province":"Salzburg",
    "wof:name":"R E P GmbH - Reifenentsorgungsprofis",
    "wof:placetype":"venue"
},
  "geometry": {"coordinates":[13.1755714417,47.4936599731],"type":"Point"}
}