{
  "type": "Feature",
  "properties": {
    "iso:country":"AT",
    "sg:address":"Marokkanerg 16",
    "sg:city":"Wien",
    "sg:orig_category":"Botschaften",
    "sg:phone":"+43 1 7103611",
    "sg:postcode":"1030",
    "sg:province":"Wien",
    "wof:name":"Botschaft von Georgien",
    "wof:placetype":"venue"
},
  "geometry": {"coordinates":[16.3801937103,48.1979484558],"type":"Point"}
}