{
  "type": "Feature",
  "properties": {
    "addr:full":"K\u00e4rntner Strasse 355 Stra\u00dfgang Steiermark 8054",
    "addr:housenumber":"355",
    "addr:postcode":"8054",
    "addr:street":"Kaerntner Strasse",
    "iso:country":"AT",
    "sg:address":"K\u00e4rntner Strasse 355",
    "sg:city":"Stra\u00dfgang",
    "sg:orig_category":"Software For The Automobile Accessories Industry",
    "sg:phone":"+43 316 2890000",
    "sg:postcode":"8054",
    "sg:province":"Steiermark",
    "sg:website":"tuneline.at",
    "wof:name":"TuneLine Fahrzeugtechnik GmbH",
    "wof:placetype":"venue"
},
  "geometry": {"coordinates":[15.4015617371,47.0278930664],"type":"Point"}
}