{
  "type": "Feature",
  "properties": {
    "addr:full":"Gemeindepl 11 Pichl Ober\u00f6sterreich 4632",
    "addr:housenumber":"11",
    "addr:postcode":"4632",
    "addr:street":"Gemeindepl",
    "iso:country":"AT",
    "sg:address":"Gemeindepl 11",
    "sg:city":"Pichl",
    "sg:orig_category":"Feuerwehren",
    "sg:phone":"+43 7247 8200",
    "sg:postcode":"4632",
    "sg:province":"Ober\u00f6sterreich",
    "wof:name":"Freiwillige Feuerwehr Pichl b Wels",
    "wof:placetype":"venue"
},
  "geometry": {"coordinates":[13.9004182816,48.1858596802],"type":"Point"}
}