{
  "type": "Feature",
  "properties": {
    "iso:country":"AT",
    "sg:address":"Karlspl 13",
    "sg:city":"Wien",
    "sg:orig_category":"Versuchsanstalten",
    "sg:phone":"+43 4315 880143001",
    "sg:postcode":"1040",
    "sg:province":"Wien",
    "wof:name":"Technische Versuchs u Forschungsanstalt d TU Wien",
    "wof:placetype":"venue"
},
  "geometry": {"coordinates":[16.3698616028,48.1989326477],"type":"Point"}
}