{
  "type": "Feature",
  "properties": {
    "addr:full":"Grafenegger Strasse 124 Etsdorf am Kamp Nieder\u00f6sterreich 3492",
    "addr:housenumber":"124",
    "addr:postcode":"3492",
    "addr:street":"Grafenegger Strasse;Kamp",
    "iso:country":"AT",
    "sg:address":"Grafenegger Strasse 124",
    "sg:city":"Etsdorf am Kamp",
    "sg:classifiers":[
        {
            "category":"Farming",
            "subcategory":"Berry Farm",
            "type":"Manufacturing & Wholesale Goods"
        }
    ],
    "sg:phone":"+43 2735 2548",
    "sg:postcode":"3492",
    "sg:province":"Nieder\u00f6sterreich",
    "sg:tags":[
        "austrian",
        "wine"
    ],
    "wof:name":"Bergkellerei Godfried Steinschaden",
    "wof:placetype":"venue"
},
  "geometry": {"coordinates":[15.7624731064,48.4487190247],"type":"Point"}
}