{
  "type": "Feature",
  "properties": {
    "iso:country":"AT",
    "sg:address":"Fischerg 1",
    "sg:city":"Bregenz",
    "sg:classifiers":[
        {
            "category":"Professional",
            "subcategory":"Computer Services",
            "type":"Services"
        }
    ],
    "sg:phone":"+43 5574 84109",
    "sg:postcode":"6900",
    "sg:province":"Vorarlberg",
    "sg:tags":[
        "software"
    ],
    "wof:name":"sontec",
    "wof:placetype":"venue"
},
  "geometry": {"coordinates":[9.7283678055,47.5024261475],"type":"Point"}
}