{
  "type": "Feature",
  "properties": {
    "addr:full":"Prager Str 14 Wien Wien 1210",
    "addr:postcode":"1210",
    "addr:street":"Str 14",
    "iso:country":"AT",
    "sg:address":"Prager Str 14",
    "sg:city":"Wien",
    "sg:orig_category":"Restaurants: Griechisch",
    "sg:phone":"+43 1 2729305",
    "sg:postcode":"1210",
    "sg:province":"Wien",
    "wof:name":"Akropolis 21",
    "wof:placetype":"venue"
},
  "geometry": {"coordinates":[16.3961715698,48.2598686218],"type":"Point"}
}