{
  "type": "Feature",
  "properties": {
    "addr:full":"Hauptstr 53 Reichenau an der Rax Nieder\u00f6sterreich 2651",
    "addr:housenumber":"53",
    "addr:postcode":"2651",
    "addr:street":"Hauptstr",
    "iso:country":"AT",
    "sg:address":"Hauptstr 53",
    "sg:city":"Reichenau an der Rax",
    "sg:orig_category":"Tabaktrafiken",
    "sg:phone":"+43 2666 52455",
    "sg:postcode":"2651",
    "sg:province":"Nieder\u00f6sterreich",
    "wof:name":"Bauer Eugen",
    "wof:placetype":"venue"
},
  "geometry": {"coordinates":[15.8450603485,47.6952133179],"type":"Point"}
}