{
  "type": "Feature",
  "properties": {
    "iso:country":"AT",
    "sg:address":"Sallaberg 9",
    "sg:city":"Aigen im Ennstal",
    "sg:orig_category":"Alarmanlagen U Sicherheitssysteme",
    "sg:phone":"+43 4336 8223318",
    "sg:postcode":"8943",
    "sg:province":"Steiermark",
    "wof:name":"Sicherheitsger\u00e4te VerkaufsgesmbH",
    "wof:placetype":"venue"
},
  "geometry": {"coordinates":[14.1370725632,47.524974823],"type":"Point"}
}