{
  "type": "Feature",
  "properties": {
    "addr:full":"Volksbadg 4 Wiener Neustadt Nieder\u00f6sterreich 2700",
    "addr:housenumber":"4",
    "addr:postcode":"2700",
    "addr:street":"Volksbadg",
    "iso:country":"AT",
    "sg:address":"Volksbadg 4",
    "sg:city":"Wiener Neustadt",
    "sg:orig_category":"Friseure U Frisiersalons",
    "sg:phone":"+43 4367 65114521",
    "sg:postcode":"2700",
    "sg:province":"Nieder\u00f6sterreich",
    "wof:name":"Mobilfris\u00f6r Nadj Svenja",
    "wof:placetype":"venue"
},
  "geometry": {"coordinates":[16.2552165985,47.8294296265],"type":"Point"}
}