{
  "type": "Feature",
  "properties": {
    "addr:full":"Nr 172 Hof Salzburg 5322",
    "addr:postcode":"5322",
    "addr:street":"Nr 172 Hof Salzburg",
    "iso:country":"AT",
    "sg:address":"Nr 172",
    "sg:city":"Hof",
    "sg:orig_category":"Installationsunternehmen",
    "sg:phone":"+43 6229 3313",
    "sg:postcode":"5322",
    "sg:province":"Salzburg",
    "wof:name":"Gollackner Josef",
    "wof:placetype":"venue"
},
  "geometry": {"coordinates":[-71.91441345210001,41.6812667847],"type":"Point"}
}