{
  "type": "Feature",
  "properties": {
    "addr:full":"Thaliastr 156 Wien Wien 1160",
    "addr:housenumber":"156",
    "addr:postcode":"1160",
    "iso:country":"AT",
    "sg:address":"Thaliastr 156",
    "sg:city":"Wien",
    "sg:orig_category":"Beratungsstellen",
    "sg:phone":"+43 1 4865297",
    "sg:postcode":"1160",
    "sg:province":"Wien",
    "wof:name":"Sektenberatungsstelle d Evangelischen Di\u00f6zese Wien",
    "wof:placetype":"venue"
},
  "geometry": {"coordinates":[16.3072242737,48.2134895325],"type":"Point"}
}