{
  "type": "Feature",
  "properties": {
    "addr:full":"Altenberger Str 45 Linz Ober\u00f6sterreich 4040",
    "addr:postcode":"4040",
    "addr:street":"Str 45",
    "iso:country":"AT",
    "sg:address":"Altenberger Str 45",
    "sg:city":"Linz",
    "sg:orig_category":"Lebensmittel / Einzelhandel",
    "sg:phone":"+43 732 7575300",
    "sg:postcode":"4040",
    "sg:province":"Ober\u00f6sterreich",
    "wof:name":"Winkler Markt GesmbH & Co KG",
    "wof:placetype":"venue"
},
  "geometry": {"coordinates":[14.3194198608,48.3346061707],"type":"Point"}
}