{
  "type": "Feature",
  "properties": {
    "addr:full":"Bahnhofg 21 Neumarkt am Wallersee Salzburg 5202",
    "addr:housenumber":"21",
    "addr:postcode":"5202",
    "addr:street":"Bahnhofg;Salzburg",
    "iso:country":"AT",
    "sg:address":"Bahnhofg 21",
    "sg:city":"Neumarkt am Wallersee",
    "sg:orig_category":"Estriche",
    "sg:phone":"+43 6216 20007",
    "sg:postcode":"5202",
    "sg:province":"Salzburg",
    "wof:name":"WM-Estriche GmbH",
    "wof:placetype":"venue"
},
  "geometry": {"coordinates":[13.2245721817,47.9449386597],"type":"Point"}
}