{
  "type": "Feature",
  "properties": {
    "addr:full":"Marktstr 71 Hof am Leithagebirge Nieder\u00f6sterreich 2451",
    "addr:housenumber":"71",
    "addr:postcode":"2451",
    "addr:street":"Marktstr;Leithagebirge",
    "iso:country":"AT",
    "sg:address":"Marktstr 71",
    "sg:city":"Hof am Leithagebirge",
    "sg:orig_category":"Landwirtschaftliche Produkte",
    "sg:phone":"+43 2168 62648",
    "sg:postcode":"2451",
    "sg:province":"Nieder\u00f6sterreich",
    "wof:name":"Stoynitsch Johann",
    "wof:placetype":"venue"
},
  "geometry": {"coordinates":[16.5718536377,47.9441070557],"type":"Point"}
}