{
  "type": "Feature",
  "properties": {
    "addr:full":"Nr 95 Lienz Tirol 9900",
    "addr:postcode":"9900",
    "addr:street":"Nr 95;Tirol",
    "iso:country":"AT",
    "sg:address":"Nr 95",
    "sg:city":"Lienz",
    "sg:classifiers":[
        {
            "category":"Travel",
            "subcategory":"Hotels & Motels",
            "type":"Entertainment"
        }
    ],
    "sg:phone":"+43 4852 634820",
    "sg:postcode":"9900",
    "sg:province":"Tirol",
    "wof:name":"Tyrol-Hotel",
    "wof:placetype":"venue"
},
  "geometry": {"coordinates":[12.7304296494,46.8440513611],"type":"Point"}
}