{
  "type": "Feature",
  "properties": {
    "addr:full":"Eschenweg 8 Linz Ober\u00f6sterreich 4040",
    "addr:housenumber":"8",
    "addr:postcode":"4040",
    "addr:street":"Eschenweg",
    "iso:country":"AT",
    "sg:address":"Eschenweg 8",
    "sg:city":"Linz",
    "sg:orig_category":"Musiktherapie",
    "sg:phone":"+43 4373 2245014",
    "sg:postcode":"4040",
    "sg:province":"Ober\u00f6sterreich",
    "wof:name":"Mossbauer Veronika MMag",
    "wof:placetype":"venue"
},
  "geometry": {"coordinates":[14.3379421234,48.3294525146],"type":"Point"}
}