{
  "type": "Feature",
  "properties": {
    "iso:country":"AT",
    "sg:address":"Weinweg 33",
    "sg:city":"Gloggnitz",
    "sg:classifiers":[
        {
            "category":"Home & Garden",
            "subcategory":"Home Furnishings",
            "type":"Retail Goods"
        }
    ],
    "sg:phone":"+43 2663 8485",
    "sg:postcode":"2640",
    "sg:province":"Nieder\u00f6sterreich",
    "sg:tags":[
        "bathroom",
        "wc",
        "fitting"
    ],
    "wof:name":"Franz Puchegger",
    "wof:placetype":"venue"
},
  "geometry": {"coordinates":[15.8967094421,47.6612091064],"type":"Point"}
}