{
  "type": "Feature",
  "properties": {
    "iso:country":"AT",
    "sg:address":"Brunnenstr 36",
    "sg:city":"Bad Gleichenberg",
    "sg:classifiers":[
        {
            "category":"Travel",
            "subcategory":"Hotels & Motels",
            "type":"Entertainment"
        }
    ],
    "sg:phone":"+43 4331 5922410",
    "sg:postcode":"8344",
    "sg:province":"Steiermark",
    "wof:name":"Thermenhotel zur Emmaquelle",
    "wof:placetype":"venue"
},
  "geometry": {"coordinates":[15.906206131,46.8702163696],"type":"Point"}
}