{
  "type": "Feature",
  "properties": {
    "addr:full":"Ettenreichg 18 Wien Wien 1100",
    "addr:housenumber":"18",
    "addr:postcode":"1100",
    "addr:street":"Ettenreichg",
    "iso:country":"AT",
    "sg:address":"Ettenreichg 18",
    "sg:city":"Wien",
    "sg:orig_category":"Friseure U Frisiersalons",
    "sg:phone":"+43 1 6002754",
    "sg:postcode":"1100",
    "sg:province":"Wien",
    "wof:name":"Coiffeur Heidi",
    "wof:placetype":"venue"
},
  "geometry": {"coordinates":[16.376121521,48.1716384888],"type":"Point"}
}