{
  "type": "Feature",
  "properties": {
    "addr:full":"Panoramaweg 65 Voitsberg Steiermark 8570",
    "addr:housenumber":"65",
    "addr:postcode":"8570",
    "addr:street":"Panoramaweg",
    "iso:country":"AT",
    "sg:address":"Panoramaweg 65",
    "sg:city":"Voitsberg",
    "sg:classifiers":[
        {
            "category":"Retail",
            "subcategory":"Auto Repair",
            "type":"Services"
        }
    ],
    "sg:phone":"+43 3142 23666",
    "sg:postcode":"8570",
    "sg:province":"Steiermark",
    "sg:tags":[
        "electric",
        "motor"
    ],
    "sg:website":"bo-ss.at/wagner",
    "wof:name":"Karl Wagner",
    "wof:placetype":"venue"
},
  "geometry": {"coordinates":[15.1687612534,47.0275001526],"type":"Point"}
}