{
  "type": "Feature",
  "properties": {
    "addr:full":"Speckbacherstr 55 Innsbruck Tirol 6020",
    "addr:housenumber":"55",
    "addr:postcode":"6020",
    "addr:street":"Speckbacherstr;Tirol",
    "iso:country":"AT",
    "sg:address":"Speckbacherstr 55",
    "sg:city":"Innsbruck",
    "sg:classifiers":[
        {
            "category":"Restaurant",
            "type":"Food & Drink"
        }
    ],
    "sg:phone":"+43 512 588888",
    "sg:postcode":"6020",
    "sg:province":"Tirol",
    "sg:tags":[
        "pizzeria"
    ],
    "wof:name":"Pizzeria Maurizio",
    "wof:placetype":"venue"
},
  "geometry": {"coordinates":[11.3901510239,47.257106781],"type":"Point"}
}