{
  "type": "Feature",
  "properties": {
    "addr:full":"Schlo\u00dfstr 744 Kaprun Salzburg 5710",
    "addr:housenumber":"744",
    "addr:postcode":"5710",
    "addr:street":"Schlossstr;Salzburg",
    "iso:country":"AT",
    "sg:address":"Schlo\u00dfstr 744",
    "sg:city":"Kaprun",
    "sg:classifiers":[
        {
            "category":"Travel",
            "subcategory":"Hotels & Motels",
            "type":"Entertainment"
        }
    ],
    "sg:phone":"+43 6547 76700",
    "sg:postcode":"5710",
    "sg:province":"Salzburg",
    "wof:name":"Hotel Antonius",
    "wof:placetype":"venue"
},
  "geometry": {"coordinates":[12.7671823502,47.2727890015],"type":"Point"}
}