{
  "type": "Feature",
  "properties": {
    "addr:full":"Wei\u00dfenbach am Lech Tirol 6671",
    "addr:postcode":"6671",
    "addr:street":"Tirol",
    "iso:country":"AT",
    "sg:city":"Wei\u00dfenbach am Lech",
    "sg:orig_category":"Feuerwehren",
    "sg:phone":"+43 5632 580",
    "sg:postcode":"6671",
    "sg:province":"Tirol",
    "wof:name":"Feuerwehr Forchach",
    "wof:placetype":"venue"
},
  "geometry": {"coordinates":[10.5874595642,47.4196624756],"type":"Point"}
}