{
  "type": "Feature",
  "properties": {
    "addr:full":"Schubertpl 18 Gm\u00fcnd Nieder\u00f6sterreich 3950",
    "addr:housenumber":"18",
    "addr:postcode":"3950",
    "addr:street":"Schubertpl;Niederoesterreich",
    "iso:country":"AT",
    "sg:address":"Schubertpl 18",
    "sg:city":"Gm\u00fcnd",
    "sg:orig_category":"Ambulatorien",
    "sg:phone":"+43 4328 52538230",
    "sg:postcode":"3950",
    "sg:province":"Nieder\u00f6sterreich",
    "sg:website":"augenlaserzentrum.at",
    "wof:name":"Augenambulatorium f\u00fcr Refraktive Chirurgie \u00e4rztl Leiter: Dr G\u00fcnther R\u00f6ssler",
    "wof:placetype":"venue"
},
  "geometry": {"coordinates":[14.972281456,48.7615432739],"type":"Point"}
}