{
  "type": "Feature",
  "properties": {
    "iso:country":"AT",
    "sg:address":"Bahnhofstr 95",
    "sg:city":"Bad Aussee",
    "sg:classifiers":[
        {
            "category":"Professional",
            "subcategory":"Management & Consulting",
            "type":"Services"
        }
    ],
    "sg:phone":"+43 4336 2252355",
    "sg:postcode":"8990",
    "sg:province":"Steiermark",
    "wof:name":"Regio Z-Regionale Zukunftsmanagement u Projektentwicklung Ausseerland Salzkgt GmbH & CoKEG",
    "wof:placetype":"venue"
},
  "geometry": {"coordinates":[13.7768774033,47.599029541],"type":"Point"}
}