{
  "type": "Feature",
  "properties": {
    "addr:full":"Haberlg 4 Wien Wien 1160",
    "addr:housenumber":"4",
    "addr:postcode":"1160",
    "addr:street":"Haberlg",
    "iso:country":"AT",
    "sg:address":"Haberlg 4",
    "sg:city":"Wien",
    "sg:orig_category":"Unternehmensberatung",
    "sg:phone":"+43 1 4942193",
    "sg:postcode":"1160",
    "sg:province":"Wien",
    "wof:name":"Berger Dr Consult KEG",
    "wof:placetype":"venue"
},
  "geometry": {"coordinates":[16.3276424408,48.2053642273],"type":"Point"}
}