{
  "type": "Feature",
  "properties": {
    "addr:full":"Ro\u00dfauer L\u00e4nde 33/21 Wien Wien 1090",
    "addr:housenumber":"33 / 21",
    "addr:postcode":"1090",
    "iso:country":"AT",
    "sg:address":"Ro\u00dfauer L\u00e4nde 33/21",
    "sg:city":"Wien",
    "sg:orig_category":"Edp Projects",
    "sg:phone":"+43 1 7436880",
    "sg:postcode":"1090",
    "sg:province":"Wien",
    "sg:website":"designers.at",
    "wof:name":"designers.at Informationstechnologie & IT- Consulting GmbH",
    "wof:placetype":"venue"
},
  "geometry": {"coordinates":[16.351474762,48.2234115601],"type":"Point"}
}