{
  "type": "Feature",
  "properties": {
    "iso:country":"AT",
    "sg:address":"Josefspl 5",
    "sg:city":"Wien",
    "sg:orig_category":"Galerien",
    "sg:phone":"+43 1 51332030",
    "sg:postcode":"1010",
    "sg:province":"Wien",
    "wof:name":"Sanct Lucas - Carl Herzig & Co",
    "wof:placetype":"venue"
},
  "geometry": {"coordinates":[16.3676872253,48.2066116333],"type":"Point"}
}