{
  "type": "Feature",
  "properties": {
    "addr:full":"Neilreichg 45 Wien Wien 1100",
    "addr:housenumber":"45",
    "addr:postcode":"1100",
    "addr:street":"Neilreichg",
    "iso:country":"AT",
    "sg:address":"Neilreichg 45",
    "sg:city":"Wien",
    "sg:orig_category":"Elektromotoren / Reparatur U Wickelei, Elektromotoren U -Maschinen, Transformatoren",
    "sg:phone":"+43 1 60422980",
    "sg:postcode":"1100",
    "sg:province":"Wien",
    "wof:name":"Barth GmbH - E-Motoren & Trafos",
    "wof:placetype":"venue"
},
  "geometry": {"coordinates":[16.3654346466,48.1736373901],"type":"Point"}
}