{
  "type": "Feature",
  "properties": {
    "addr:full":"Ybbsstrasse 9 Amstetten Nieder\u00f6sterreich 3300",
    "addr:housenumber":"9",
    "addr:postcode":"3300",
    "addr:street":"Ybbsstrasse;Niederoesterreich",
    "iso:country":"AT",
    "sg:address":"Ybbsstrasse 9",
    "sg:city":"Amstetten",
    "sg:classifiers":[
        {
            "category":"Home & Garden",
            "subcategory":"Household Appliances",
            "type":"Retail Goods"
        }
    ],
    "sg:phone":"+43 7472 63963",
    "sg:postcode":"3300",
    "sg:province":"Nieder\u00f6sterreich",
    "sg:tags":[
        "electric"
    ],
    "wof:name":"Elektro K\u00f6nig GmbH",
    "wof:placetype":"venue"
},
  "geometry": {"coordinates":[14.8708753586,48.1197776794],"type":"Point"}
}