{
  "type": "Feature",
  "properties": {
    "addr:full":"Landfra\u00df 52 Gm\u00fcnd K\u00e4rnten 9853",
    "addr:housenumber":"52",
    "addr:postcode":"9853",
    "addr:street":"Landfrass;Kaernten",
    "iso:country":"AT",
    "sg:address":"Landfra\u00df 52",
    "sg:city":"Gm\u00fcnd",
    "sg:orig_category":"Rauchfangkehrer",
    "sg:phone":"+43 4732 2616",
    "sg:postcode":"9853",
    "sg:province":"K\u00e4rnten",
    "wof:name":"Brandtner Volker",
    "wof:placetype":"venue"
},
  "geometry": {"coordinates":[13.5319061279,46.8985824585],"type":"Point"}
}