{
  "type": "Feature",
  "properties": {
    "addr:full":"Leesdorfer Hauptstr 11 Baden Nieder\u00f6sterreich 2500",
    "addr:housenumber":"11",
    "addr:postcode":"2500",
    "addr:street":"Leesdorfer Hauptstr;Niederoesterreich",
    "iso:country":"AT",
    "sg:address":"Leesdorfer Hauptstr 11",
    "sg:city":"Baden",
    "sg:orig_category":"Apotheken",
    "sg:phone":"+43 4322 52871470",
    "sg:postcode":"2500",
    "sg:province":"Nieder\u00f6sterreich",
    "wof:name":"Marien-Apotheke Magpharm Ingeborg Scholda KG",
    "wof:placetype":"venue"
},
  "geometry": {"coordinates":[16.2452259064,48.0027656555],"type":"Point"}
}