{
  "type": "Feature",
  "properties": {
    "iso:country":"AT",
    "sg:address":"Wilhelminenstr 63-65",
    "sg:city":"Wien",
    "sg:orig_category":"Lebensmittel / Einzelhandel",
    "sg:phone":"+43 1 4803176",
    "sg:postcode":"1160",
    "sg:province":"Wien",
    "wof:name":"Billa AG",
    "wof:placetype":"venue"
},
  "geometry": {"coordinates":[16.312084198,48.2169876099],"type":"Point"}
}