{
  "type": "Feature",
  "properties": {
    "addr:full":"Salurner Str 2-4 Kufstein Tirol 6330",
    "addr:housenumber":"2-4",
    "addr:postcode":"6330",
    "addr:street":"Str;Tirol",
    "iso:country":"AT",
    "sg:address":"Salurner Str 2-4",
    "sg:city":"Kufstein",
    "sg:classifiers":[
        {
            "category":"Utilities",
            "subcategory":"Refuse",
            "type":"Services"
        }
    ],
    "sg:phone":"+43 4367 64651884",
    "sg:postcode":"6330",
    "sg:province":"Tirol",
    "sg:tags":[
        "catering"
    ],
    "wof:name":"St\u00f6ckl Nikolaus",
    "wof:placetype":"venue"
},
  "geometry": {"coordinates":[12.1675977707,47.5791740417],"type":"Point"}
}