{
  "type": "Feature",
  "properties": {
    "addr:full":"Hauptstr 94 Rottenmann Steiermark 8786",
    "addr:housenumber":"94",
    "addr:postcode":"8786",
    "addr:street":"Hauptstr",
    "iso:country":"AT",
    "sg:address":"Hauptstr 94",
    "sg:city":"Rottenmann",
    "sg:orig_category":"Textilreinigung",
    "sg:phone":"+43 3614 21782",
    "sg:postcode":"8786",
    "sg:province":"Steiermark",
    "wof:name":"Putzerei Gasser",
    "wof:placetype":"venue"
},
  "geometry": {"coordinates":[14.3554229736,47.5246124268],"type":"Point"}
}