{
  "type": "Feature",
  "properties": {
    "iso:country":"AT",
    "sg:address":"Nr 32",
    "sg:city":"Thiersee",
    "sg:orig_category":"Biologische Produkte",
    "sg:phone":"+43 4353 765460",
    "sg:postcode":"6335",
    "sg:province":"Tirol",
    "wof:name":"Thierseer Vollwert u Bauernecke Rosi Grasshoff",
    "wof:placetype":"venue"
},
  "geometry": {"coordinates":[12.0649995804,47.584148407],"type":"Point"}
}