{
  "type": "Feature",
  "properties": {
    "addr:full":"Bauweltstr 17 Mattersburg Burgenland 7210",
    "addr:housenumber":"17",
    "addr:postcode":"7210",
    "addr:street":"Bauweltstr",
    "iso:country":"AT",
    "sg:address":"Bauweltstr 17",
    "sg:city":"Mattersburg",
    "sg:orig_category":"Autohandel",
    "sg:phone":"+43 2626 63450",
    "sg:postcode":"7210",
    "sg:province":"Burgenland",
    "wof:name":"Czeczelits GmbH",
    "wof:placetype":"venue"
},
  "geometry": {"coordinates":[16.4126663208,47.7362480164],"type":"Point"}
}