{
  "type": "Feature",
  "properties": {
    "addr:full":"Rosenkranzgasse 14 Bad Ischl Ober\u00f6sterreich 4820",
    "addr:housenumber":"14",
    "addr:postcode":"4820",
    "addr:street":"Rosenkranzgasse",
    "iso:country":"AT",
    "sg:address":"Rosenkranzgasse 14",
    "sg:city":"Bad Ischl",
    "sg:classifiers":[
        {
            "category":"Professional",
            "subcategory":"Art Services",
            "type":"Services"
        }
    ],
    "sg:phone":"+43 6132 23679",
    "sg:postcode":"4820",
    "sg:province":"Ober\u00f6sterreich",
    "sg:tags":[
        "metalwork"
    ],
    "wof:name":"Franz Kefer",
    "wof:placetype":"venue"
},
  "geometry": {"coordinates":[13.6302242279,47.7037506104],"type":"Point"}
}