{
  "type": "Feature",
  "properties": {
    "addr:full":"Arlbergstr 112 Bregenz Vorarlberg 6900",
    "addr:housenumber":"112",
    "addr:postcode":"6900",
    "iso:country":"AT",
    "sg:address":"Arlbergstr 112",
    "sg:city":"Bregenz",
    "sg:orig_category":"Sonnenstudios",
    "sg:phone":"+43 5574 58111",
    "sg:postcode":"6900",
    "sg:province":"Vorarlberg",
    "wof:name":"SUN-DAY Sonnenstudio",
    "wof:placetype":"venue"
},
  "geometry": {"coordinates":[9.7327051163,47.4873847961],"type":"Point"}
}