{
  "type": "Feature",
  "properties": {
    "iso:country":"AT",
    "sg:address":"Arbeiterg 43",
    "sg:city":"Wien",
    "sg:orig_category":"Zahntechnische Laboratorien",
    "sg:phone":"+43 1 5444324",
    "sg:postcode":"1050",
    "sg:province":"Wien",
    "wof:name":"Gaar Joachim",
    "wof:placetype":"venue"
},
  "geometry": {"coordinates":[16.3474998474,48.1844406128],"type":"Point"}
}