{
  "type": "Feature",
  "properties": {
    "addr:full":"P\u00f6llangraben 24 Brunn am Gebirge Nieder\u00f6sterreich 2345",
    "addr:housenumber":"24",
    "addr:postcode":"2345",
    "addr:street":"Poellangraben",
    "iso:country":"AT",
    "sg:address":"P\u00f6llangraben 24",
    "sg:city":"Brunn am Gebirge",
    "sg:orig_category":"Chemisch-Technische Produkte",
    "sg:phone":"+43 4322 3633280",
    "sg:postcode":"2345",
    "sg:province":"Nieder\u00f6sterreich",
    "wof:name":"Lach Hans Gro\u00dfhdl m chem u techn Produkten GesmbH",
    "wof:placetype":"venue"
},
  "geometry": {"coordinates":[16.271490097,48.1115760803],"type":"Point"}
}