{
  "type": "Feature",
  "properties": {
    "addr:full":"Sportplatzstr. 14 Schwaz Tirol 6130",
    "addr:housenumber":"14",
    "addr:postcode":"6130",
    "addr:street":"Sportplatzstr.;Tirol",
    "iso:country":"AT",
    "sg:address":"Sportplatzstr. 14",
    "sg:city":"Schwaz",
    "sg:classifiers":[
        {
            "category":"Professional",
            "subcategory":"Engineering",
            "type":"Services"
        }
    ],
    "sg:phone":"+43 4352 4264755",
    "sg:postcode":"6130",
    "sg:province":"Tirol",
    "sg:tags":[
        "machine",
        "-",
        "mechanical"
    ],
    "wof:name":"ING KLAUS POINTNER GMBH",
    "wof:placetype":"venue"
},
  "geometry": {"coordinates":[11.6999082565,47.3426437378],"type":"Point"}
}