{
  "type": "Feature",
  "properties": {
    "addr:full":"Sparkassenstr 1 Braunau am Inn Ober\u00f6sterreich 5280",
    "addr:housenumber":"1",
    "addr:postcode":"5280",
    "addr:street":"Sparkassenstr",
    "iso:country":"AT",
    "sg:address":"Sparkassenstr 1",
    "sg:city":"Braunau am Inn",
    "sg:orig_category":"Werbegrafik- U Grafik-Design",
    "sg:phone":"+43 4366 44211454",
    "sg:postcode":"5280",
    "sg:province":"Ober\u00f6sterreich",
    "wof:name":"Graphik-Design-Opresnik",
    "wof:placetype":"venue"
},
  "geometry": {"coordinates":[13.0343379974,48.246635437],"type":"Point"}
}