{
  "type": "Feature",
  "properties": {
    "addr:full":"Hauptstrasse 2 Weibern Ober\u00f6sterreich 4675",
    "addr:housenumber":"2",
    "addr:postcode":"4675",
    "addr:street":"Hauptstrasse;Oberoesterreich",
    "iso:country":"AT",
    "sg:address":"Hauptstrasse 2",
    "sg:city":"Weibern",
    "sg:classifiers":[
        {
            "category":"Professional",
            "subcategory":"Engineering",
            "type":"Services"
        }
    ],
    "sg:phone":"+43 7732 4133",
    "sg:postcode":"4675",
    "sg:province":"Ober\u00f6sterreich",
    "sg:tags":[
        "environmental",
        "protection"
    ],
    "sg:website":"vta.cc",
    "wof:name":"VTA Engineering und Umwelttechnik GmbH",
    "wof:placetype":"venue"
},
  "geometry": {"coordinates":[13.7017660141,48.1845169067],"type":"Point"}
}