{
  "type": "Feature",
  "properties": {
    "addr:full":"Traunkai 4a Bad Ischl Ober\u00f6sterreich 4820",
    "addr:housenumber":"4a",
    "addr:postcode":"4820",
    "addr:street":"Traunkai",
    "iso:country":"AT",
    "sg:address":"Traunkai 4a",
    "sg:city":"Bad Ischl",
    "sg:orig_category":"Pensionen / Privatzimmer",
    "sg:phone":"+43 6132 23279",
    "sg:postcode":"4820",
    "sg:province":"Ober\u00f6sterreich",
    "wof:name":"Weinbacher Edith",
    "wof:placetype":"venue"
},
  "geometry": {"coordinates":[13.6199960709,47.7090301514],"type":"Point"}
}