{
  "type": "Feature",
  "properties": {
    "iso:country":"AT",
    "sg:address":"Hauptstr 37",
    "sg:city":"Leobersdorf",
    "sg:orig_category":"Bastelbedarf",
    "sg:phone":"+43 2256 20237",
    "sg:postcode":"2544",
    "sg:province":"Nieder\u00f6sterreich",
    "wof:name":"Hobby-Kunst und Freizeitstudio - Ideen- und Kreativwerkstatt",
    "wof:placetype":"venue"
},
  "geometry": {"coordinates":[16.216178894,47.9269943237],"type":"Point"}
}