{
  "type": "Feature",
  "properties": {
    "addr:full":"Linzer Str 42 Neuhofen an der Krems Ober\u00f6sterreich 4501",
    "addr:housenumber":"42",
    "addr:postcode":"4501",
    "addr:street":"Linzer Str",
    "iso:country":"AT",
    "sg:address":"Linzer Str 42",
    "sg:city":"Neuhofen an der Krems",
    "sg:orig_category":"Fotoapparate U -Artikel / Erzeugung U Gro\u00c3\u0178handel",
    "sg:phone":"+43 4372 2747170",
    "sg:postcode":"4501",
    "sg:province":"Ober\u00f6sterreich",
    "wof:name":"Kirchmayr Fritz GesmbH - Fotoimporte",
    "wof:placetype":"venue"
},
  "geometry": {"coordinates":[14.2288045883,48.1436805725],"type":"Point"}
}