{
  "type": "Feature",
  "properties": {
    "addr:full":"Linzer Str 37 Prinzersdorf Nieder\u00f6sterreich 3385",
    "addr:housenumber":"37",
    "addr:postcode":"3385",
    "addr:street":"Linzer Str",
    "iso:country":"AT",
    "sg:address":"Linzer Str 37",
    "sg:city":"Prinzersdorf",
    "sg:orig_category":"Polizei U Gendarmerie",
    "sg:phone":"+43 4359 1333171",
    "sg:postcode":"3385",
    "sg:province":"Nieder\u00f6sterreich",
    "wof:name":"Gendarmerie",
    "wof:placetype":"venue"
},
  "geometry": {"coordinates":[15.5076580048,48.1996650696],"type":"Point"}
}