{
  "type": "Feature",
  "properties": {
    "addr:full":"Tandelmarktg 1 Wien Wien 1020",
    "addr:housenumber":"1",
    "addr:postcode":"1020",
    "addr:street":"Tandelmarktg",
    "iso:country":"AT",
    "sg:address":"Tandelmarktg 1",
    "sg:city":"Wien",
    "sg:orig_category":"Hunde- U Katzensalons",
    "sg:phone":"+43 4312 764916",
    "sg:postcode":"1020",
    "sg:province":"Wien",
    "wof:name":"Hundesalon Schnautzerl",
    "wof:placetype":"venue"
},
  "geometry": {"coordinates":[16.3779144287,48.217250824],"type":"Point"}
}