{
  "type": "Feature",
  "properties": {
    "addr:full":"Bahnhofstr 45 Altheim Ober\u00f6sterreich 4950",
    "addr:housenumber":"45",
    "addr:postcode":"4950",
    "addr:street":"Bahnhofstr",
    "iso:country":"AT",
    "sg:address":"Bahnhofstr 45",
    "sg:city":"Altheim",
    "sg:orig_category":"Fotografen",
    "sg:phone":"+43 664 2314335",
    "sg:postcode":"4950",
    "sg:province":"Ober\u00f6sterreich",
    "wof:name":"Mitterbauer Fotografie GmbH & Co KG",
    "wof:placetype":"venue"
},
  "geometry": {"coordinates":[13.2373399734,48.2555770874],"type":"Point"}
}