{
  "type": "Feature",
  "properties": {
    "iso:country":"AT",
    "sg:address":"Haus 264",
    "sg:city":"W\u00f6rgl",
    "sg:orig_category":"Bio Filter Grids Of Stainless Steel",
    "sg:phone":"+43 5335 40007",
    "sg:postcode":"6300",
    "sg:province":"Tirol",
    "sg:website":"sbv-itter.at",
    "wof:name":"SBV - Schacht und Bautechnik Vertriebs GmbH",
    "wof:placetype":"venue"
},
  "geometry": {"coordinates":[12.1438121796,47.4709892273],"type":"Point"}
}