{
  "type": "Feature",
  "properties": {
    "addr:full":"Grabensee 23 Asperhofen Nieder\u00f6sterreich 3041",
    "addr:housenumber":"23",
    "addr:postcode":"3041",
    "addr:street":"Grabensee",
    "iso:country":"AT",
    "sg:address":"Grabensee 23",
    "sg:city":"Asperhofen",
    "sg:classifiers":[
        {
            "category":"Banks & Credit Unions",
            "subcategory":"Atm",
            "type":"Services"
        }
    ],
    "sg:phone":"+43 664 1004310",
    "sg:postcode":"3041",
    "sg:province":"Nieder\u00f6sterreich",
    "sg:tags":[
        "voice",
        "response",
        "ivr",
        "interactive"
    ],
    "sg:website":"softart.at",
    "wof:name":"SoftArt Ralph Heger",
    "wof:placetype":"venue"
},
  "geometry": {"coordinates":[15.9243936539,48.2437896729],"type":"Point"}
}