{
  "type": "Feature",
  "properties": {
    "addr:full":"Inge-Ludwig-Neumann-Str. 4 Frauental an der La\u00dfnitz Steiermark 8523",
    "addr:housenumber":"4",
    "addr:postcode":"8523",
    "addr:street":"Inge-Ludwig-Neumann-Str.",
    "iso:country":"AT",
    "sg:address":"Inge-Ludwig-Neumann-Str. 4",
    "sg:city":"Frauental an der La\u00dfnitz",
    "sg:classifiers":[
        {
            "category":"Professional",
            "subcategory":"Engineering",
            "type":"Services"
        }
    ],
    "sg:phone":"+43 4334 625860",
    "sg:postcode":"8523",
    "sg:province":"Steiermark",
    "sg:tags":[
        "machine",
        "-",
        "mechanical"
    ],
    "wof:name":"IAF INDUSTRIEANLAGENTECHNIK FRAUENTAL GMBH",
    "wof:placetype":"venue"
},
  "geometry": {"coordinates":[15.2452449799,46.8533325195],"type":"Point"}
}