{
  "type": "Feature",
  "properties": {
    "addr:full":"Unterhaag 143 Oberhaag Steiermark 8455",
    "addr:housenumber":"143",
    "addr:postcode":"8455",
    "addr:street":"Unterhaag",
    "iso:country":"AT",
    "sg:address":"Unterhaag 143",
    "sg:city":"Oberhaag",
    "sg:orig_category":"Tischlereien",
    "sg:phone":"+43 4334 556131",
    "sg:postcode":"8455",
    "sg:province":"Steiermark",
    "wof:name":"Mersnik Johann",
    "wof:placetype":"venue"
},
  "geometry": {"coordinates":[15.3519897461,46.6851234436],"type":"Point"}
}