{
  "type": "Feature",
  "properties": {
    "addr:full":"Nr 103 Langau Nieder\u00f6sterreich 2091",
    "addr:postcode":"2091",
    "addr:street":"Nr 103",
    "iso:country":"AT",
    "sg:address":"Nr 103",
    "sg:city":"Langau",
    "sg:orig_category":"Gemeinden",
    "sg:phone":"+43 2912 401",
    "sg:postcode":"2091",
    "sg:province":"Nieder\u00f6sterreich",
    "wof:name":"Marktgemeinde Langau",
    "wof:placetype":"venue"
},
  "geometry": {"coordinates":[15.7151498795,48.8315544128],"type":"Point"}
}