{
  "type": "Feature",
  "properties": {
    "iso:country":"AT",
    "sg:city":"Piesendorf",
    "sg:orig_category":"Freizeit, Spiel U Spa\u00c3\u0178",
    "sg:postcode":"5721",
    "sg:province":"Salzburg",
    "sg:website":"http://www.erlebnisberg.at",
    "wof:name":"Erlebnisberg Nagelk\u00f6pfl",
    "wof:placetype":"venue"
},
  "geometry": {"coordinates":[12.7159004211,47.2918968201],"type":"Point"}
}