{
  "type": "Feature",
  "properties": {
    "iso:country":"AT",
    "sg:address":"G Mahler-Promenade 9",
    "sg:city":"Salzburg",
    "sg:orig_category":"Parkettbodenverlegung",
    "sg:phone":"+43 662 825405",
    "sg:postcode":"5020",
    "sg:province":"Salzburg",
    "wof:name":"Fu\u00dfbodenforum Thomas Kirchtag GmbH",
    "wof:placetype":"venue"
},
  "geometry": {"coordinates":[13.0775518417,47.8017730713],"type":"Point"}
}