{
  "type": "Feature",
  "properties": {
    "iso:country":"AT",
    "sg:address":"Nr 28",
    "sg:city":"Weitra",
    "sg:classifiers":[
        {
            "category":"Travel",
            "subcategory":"Hotels & Motels",
            "type":"Entertainment"
        }
    ],
    "sg:phone":"+43 2858 52310",
    "sg:postcode":"3970",
    "sg:province":"Nieder\u00f6sterreich",
    "wof:name":"Hotel Restaurant Waldpension Nebelstein",
    "wof:placetype":"venue"
},
  "geometry": {"coordinates":[166.9221496582,-0.5282999873],"type":"Point"}
}