{
  "type": "Feature",
  "properties": {
    "iso:country":"AT",
    "sg:address":"Lindenthal 81",
    "sg:city":"Abtenau",
    "sg:orig_category":"Baumeister",
    "sg:phone":"+43 4362 433455",
    "sg:postcode":"5441",
    "sg:province":"Salzburg",
    "wof:name":"Gsenger Ewald Baumeister GmbH",
    "wof:placetype":"venue"
},
  "geometry": {"coordinates":[13.3718423843,47.562374115],"type":"Point"}
}