{
  "type": "Feature",
  "properties": {
    "addr:full":"Seebichlweg 37 Kitzb\u00fchel Tirol 6370",
    "addr:housenumber":"37",
    "addr:postcode":"6370",
    "addr:street":"Seebichlweg;Tirol",
    "iso:country":"AT",
    "sg:address":"Seebichlweg 37",
    "sg:city":"Kitzb\u00fchel",
    "sg:classifiers":[
        {
            "category":"Travel",
            "subcategory":"Hotels & Motels",
            "type":"Entertainment"
        }
    ],
    "sg:phone":"+43 5356 625250",
    "sg:postcode":"6370",
    "sg:province":"Tirol",
    "wof:name":"Hotel-Restaurant Seebichl",
    "wof:placetype":"venue"
},
  "geometry": {"coordinates":[12.3745222092,47.4561233521],"type":"Point"}
}