{
  "type": "Feature",
  "properties": {
    "addr:full":"Niederalm Salzachtalbdstr 109 Anif Salzburg 5081",
    "addr:housenumber":"109",
    "addr:postcode":"5081",
    "addr:street":"Salzachtalbdstr;Salzburg",
    "iso:country":"AT",
    "sg:address":"Niederalm Salzachtalbdstr 109",
    "sg:city":"Anif",
    "sg:orig_category":"Autohandel",
    "sg:phone":"+43 4362 46725360",
    "sg:postcode":"5081",
    "sg:province":"Salzburg",
    "sg:website":"meininger.at",
    "wof:name":"Autohaus Meininger GmbH Ing",
    "wof:placetype":"venue"
},
  "geometry": {"coordinates":[13.0639257431,47.7499694824],"type":"Point"}
}