{
  "type": "Feature",
  "properties": {
    "addr:full":"Bienenb\u00fcttelgasse 4  Mistelbach Nieder\u00f6sterreich 2130",
    "addr:housenumber":"4",
    "addr:postcode":"2130",
    "addr:street":"Bienenbuettelgasse;Niederoesterreich",
    "iso:country":"AT",
    "sg:address":"Bienenb\u00fcttelgasse 4 ",
    "sg:city":"Mistelbach",
    "sg:classifiers":[
        {
            "category":"Building & Trades",
            "subcategory":"Equipment Rental",
            "type":"Services"
        }
    ],
    "sg:phone":"+43 2572 20249",
    "sg:postcode":"2130",
    "sg:province":"Nieder\u00f6sterreich",
    "sg:tags":[
        "registers",
        "register",
        "system",
        "cash"
    ],
    "sg:website":"www.yousports.com",
    "wof:name":"Michael Fath",
    "wof:placetype":"venue"
},
  "geometry": {"coordinates":[16.5724334717,48.5700798035],"type":"Point"}
}