{
  "type": "Feature",
  "properties": {
    "addr:full":"Hauptstr 73 Golling an der Erlauf Nieder\u00f6sterreich 3381",
    "addr:housenumber":"73",
    "addr:postcode":"3381",
    "addr:street":"Hauptstr",
    "iso:country":"AT",
    "sg:address":"Hauptstr 73",
    "sg:city":"Golling an der Erlauf",
    "sg:orig_category":"Feuerwehren",
    "sg:phone":"+43 4327 572022",
    "sg:postcode":"3381",
    "sg:province":"Nieder\u00f6sterreich",
    "wof:name":"Freiwillige Feuerwehr Golling",
    "wof:placetype":"venue"
},
  "geometry": {"coordinates":[15.1773738861,48.1965446472],"type":"Point"}
}