{
  "type": "Feature",
  "properties": {
    "addr:full":"Lassallestr 9b Wien Wien 1020",
    "addr:housenumber":"9b",
    "addr:postcode":"1020",
    "addr:street":"Lassallestr",
    "iso:country":"AT",
    "sg:address":"Lassallestr 9b",
    "sg:city":"Wien",
    "sg:classifiers":[
        {
            "category":"Professional",
            "subcategory":"Computer Services",
            "type":"Services"
        }
    ],
    "sg:phone":"+43 1 491030",
    "sg:postcode":"1020",
    "sg:province":"Wien",
    "sg:tags":[
        "software"
    ],
    "wof:name":"Intentia Austria EDV-Beratungs GesmbH",
    "wof:placetype":"venue"
},
  "geometry": {"coordinates":[16.3992786407,48.2231216431],"type":"Point"}
}