{
  "type": "Feature",
  "properties": {
    "addr:full":"Am Hauserbichl 9 Nu\u00dfdorf am Attersee Ober\u00f6sterreich 4865",
    "addr:housenumber":"9",
    "addr:postcode":"4865",
    "addr:street":"Am Hauserbichl",
    "iso:country":"AT",
    "sg:address":"Am Hauserbichl 9",
    "sg:city":"Nu\u00dfdorf am Attersee",
    "sg:orig_category":"Pensionen / Privatzimmer",
    "sg:phone":"+43 76668124",
    "sg:postcode":"4865",
    "sg:province":"Ober\u00f6sterreich",
    "wof:name":"Rosenauer Franz",
    "wof:placetype":"venue"
},
  "geometry": {"coordinates":[13.5168542862,47.8885536194],"type":"Point"}
}