{
  "type": "Feature",
  "properties": {
    "addr:full":"Industriegebiet Weppersdorf Burgenland 7331",
    "addr:postcode":"7331",
    "addr:street":"Industriegebiet Weppersdorf",
    "iso:country":"AT",
    "sg:address":"Industriegebiet",
    "sg:city":"Weppersdorf",
    "sg:orig_category":"Lebensmittel / Erzeugung U Gro\u00c3\u0178handel",
    "sg:phone":"+43 4326 1832950",
    "sg:postcode":"7331",
    "sg:province":"Burgenland",
    "wof:name":"ALONDO Bio.k. Lebensmittelproduktions GmbH",
    "wof:placetype":"venue"
},
  "geometry": {"coordinates":[16.4270782471,47.5783233643],"type":"Point"}
}