{
  "type": "Feature",
  "properties": {
    "addr:full":"Griespl 15 Mureck Steiermark 8480",
    "addr:housenumber":"15",
    "addr:postcode":"8480",
    "addr:street":"Griespl",
    "iso:country":"AT",
    "sg:address":"Griespl 15",
    "sg:city":"Mureck",
    "sg:orig_category":"Textilreinigung",
    "sg:phone":"+43 4334 722450",
    "sg:postcode":"8480",
    "sg:province":"Steiermark",
    "wof:name":"Krainer-Radkohl Margit",
    "wof:placetype":"venue"
},
  "geometry": {"coordinates":[15.7773675919,46.7078285217],"type":"Point"}
}