{
  "type": "Feature",
  "properties": {
    "iso:country":"AT",
    "sg:address":"Obere Hauptstr 67a",
    "sg:city":"Illmitz",
    "sg:orig_category":"Tankstellen",
    "sg:phone":"+43 2175 2325",
    "sg:postcode":"7142",
    "sg:province":"Burgenland",
    "wof:name":"OMV AG",
    "wof:placetype":"venue"
},
  "geometry": {"coordinates":[16.801864624,47.7658538818],"type":"Point"}
}