{
  "type": "Feature",
  "properties": {
    "addr:full":"Bahnzeile 20 Gumpoldskirchen Nieder\u00f6sterreich 2352",
    "addr:housenumber":"20",
    "addr:postcode":"2352",
    "addr:street":"Bahnzeile",
    "iso:country":"AT",
    "sg:address":"Bahnzeile 20",
    "sg:city":"Gumpoldskirchen",
    "sg:orig_category":"Fahrradverleih",
    "sg:phone":"+43 2252 62931",
    "sg:postcode":"2352",
    "sg:province":"Nieder\u00f6sterreich",
    "wof:name":"Radverleih Gumpoldskirchen Billensteiner Eduard KEG",
    "wof:placetype":"venue"
},
  "geometry": {"coordinates":[16.2844352722,48.0400009155],"type":"Point"}
}