{
  "type": "Feature",
  "properties": {
    "iso:country":"AT",
    "sg:address":"Hauptstr 9",
    "sg:city":"Scheibbs",
    "sg:orig_category":"Banken U Sparkassen",
    "sg:phone":"+43 7482 421200",
    "sg:postcode":"3270",
    "sg:province":"Nieder\u00f6sterreich",
    "wof:name":"Sparkasse Scheibbs AG",
    "wof:placetype":"venue"
},
  "geometry": {"coordinates":[15.1659030914,48.007068634],"type":"Point"}
}