{
  "type": "Feature",
  "properties": {
    "iso:country":"AT",
    "sg:address":"Kroisgrabenweg 2",
    "sg:city":"Frauental an der La\u00dfnitz",
    "sg:classifiers":[
        {
            "category":"Home & Garden",
            "subcategory":"Building Materials",
            "type":"Retail Goods"
        }
    ],
    "sg:phone":"+43 3462 4222",
    "sg:postcode":"8523",
    "sg:province":"Steiermark",
    "sg:tags":[
        "gravel",
        "crushed"
    ],
    "wof:name":"Franziska Trummer",
    "wof:placetype":"venue"
},
  "geometry": {"coordinates":[15.2452449799,46.8533325195],"type":"Point"}
}