{
  "type": "Feature",
  "properties": {
    "iso:country":"AT",
    "sg:city":"Egg",
    "sg:orig_category":"Feuerwehren",
    "sg:phone":"+43 5512 23230",
    "sg:postcode":"6863",
    "sg:province":"Vorarlberg",
    "wof:name":"Feuerwehr Egg",
    "wof:placetype":"venue"
},
  "geometry": {"coordinates":[9.897102356,47.4310417175],"type":"Point"}
}