{
  "type": "Feature",
  "properties": {
    "addr:full":"Volkersdorferstrasse 3 Hargelsberg Ober\u00f6sterreich 4483",
    "addr:housenumber":"3",
    "addr:postcode":"4483",
    "addr:street":"Volkersdorferstrasse",
    "iso:country":"AT",
    "sg:address":"Volkersdorferstrasse 3",
    "sg:city":"Hargelsberg",
    "sg:classifiers":[
        {
            "category":"Building & Trades",
            "subcategory":"Electrical",
            "type":"Services"
        }
    ],
    "sg:phone":"+43 7225 7344",
    "sg:postcode":"4483",
    "sg:province":"Ober\u00f6sterreich",
    "sg:tags":[
        "plants",
        "plant",
        "industrial",
        "buildings",
        "construction"
    ],
    "wof:name":"Maschinen- & Industrieanlagenbau Wilhelm Birklbauer",
    "wof:placetype":"venue"
},
  "geometry": {"coordinates":[14.4294652939,48.1547164917],"type":"Point"}
}