{
  "type": "Feature",
  "properties": {
    "addr:full":"Erlenweg 14 Reifnitz K\u00e4rnten 9081",
    "addr:housenumber":"14",
    "addr:postcode":"9081",
    "addr:street":"Erlenweg;Kaernten",
    "iso:country":"AT",
    "sg:address":"Erlenweg 14",
    "sg:city":"Reifnitz",
    "sg:orig_category":"Pensionen / Privatzimmer",
    "sg:phone":"+43 4273 2031",
    "sg:postcode":"9081",
    "sg:province":"K\u00e4rnten",
    "wof:name":"Haus Daniele",
    "wof:placetype":"venue"
},
  "geometry": {"coordinates":[14.1855239868,46.6027259827],"type":"Point"}
}