{
  "type": "Feature",
  "properties": {
    "addr:full":"Franz Kogler-Weg 5 F\u00fcrstenfeld Steiermark 8280",
    "addr:housenumber":"5",
    "addr:postcode":"8280",
    "addr:street":"Franz Kogler-Weg",
    "iso:country":"AT",
    "sg:address":"Franz Kogler-Weg 5",
    "sg:city":"F\u00fcrstenfeld",
    "sg:orig_category":"Tonanlagen / Vermietung",
    "sg:phone":"+43 3382 55078",
    "sg:postcode":"8280",
    "sg:province":"Steiermark",
    "wof:name":"KSR Ton- Lichtanlagenverleih",
    "wof:placetype":"venue"
},
  "geometry": {"coordinates":[16.0868091583,47.0367622375],"type":"Point"}
}