{
  "type": "Feature",
  "properties": {
    "addr:full":"Nr 55 Neudau Steiermark 8292",
    "addr:postcode":"8292",
    "addr:street":"Nr",
    "iso:country":"AT",
    "sg:address":"Nr 55",
    "sg:city":"Neudau",
    "sg:orig_category":"Maler, Anstreicher U Lackierer",
    "sg:phone":"+43 4333 583339",
    "sg:postcode":"8292",
    "sg:province":"Steiermark",
    "wof:name":"Kirisits Wolfgang",
    "wof:placetype":"venue"
},
  "geometry": {"coordinates":[16.1003761292,47.1778526306],"type":"Point"}
}