{
  "type": "Feature",
  "properties": {
    "addr:full":"Rudolfspl 7 Wien Wien 1010",
    "addr:housenumber":"7",
    "addr:postcode":"1010",
    "addr:street":"Rudolfspl",
    "iso:country":"AT",
    "sg:address":"Rudolfspl 7",
    "sg:city":"Wien",
    "sg:orig_category":"Galerien",
    "sg:phone":"+43 1 5353274",
    "sg:postcode":"1010",
    "sg:province":"Wien",
    "wof:name":"Panorama Verlag & Galerie",
    "wof:placetype":"venue"
},
  "geometry": {"coordinates":[16.3728427887,48.2138366699],"type":"Point"}
}