{
  "type": "Feature",
  "properties": {
    "addr:full":"Lendpl 11 Graz Steiermark 8020",
    "addr:housenumber":"11",
    "addr:postcode":"8020",
    "addr:street":"Lendpl",
    "iso:country":"AT",
    "sg:address":"Lendpl 11",
    "sg:city":"Graz",
    "sg:orig_category":"Friseure U Frisiersalons",
    "sg:phone":"+43 316 760170",
    "sg:postcode":"8020",
    "sg:province":"Steiermark",
    "wof:name":"Krill Erna",
    "wof:placetype":"venue"
},
  "geometry": {"coordinates":[15.4302806854,47.0749282837],"type":"Point"}
}