{
  "type": "Feature",
  "properties": {
    "iso:country":"AT",
    "sg:address":"Pettenbacher Str 12",
    "sg:city":"Vorchdorf",
    "sg:orig_category":"Mietautos",
    "sg:phone":"+43 7241 5205",
    "sg:postcode":"4655",
    "sg:province":"Ober\u00f6sterreich",
    "wof:name":"Gollinger Johann",
    "wof:placetype":"venue"
},
  "geometry": {"coordinates":[13.9259157181,48.0006523132],"type":"Point"}
}