{
  "type": "Feature",
  "properties": {
    "iso:country":"AT",
    "sg:address":"Unterer Stadtpl 5",
    "sg:city":"Hall in Tirol",
    "sg:orig_category":"Tabaktrafiken",
    "sg:phone":"+43 5223 43671",
    "sg:postcode":"6060",
    "sg:province":"Tirol",
    "wof:name":"Niederwieser Gertraud",
    "wof:placetype":"venue"
},
  "geometry": {"coordinates":[11.5062427521,47.2804527283],"type":"Point"}
}