{
  "type": "Feature",
  "properties": {
    "addr:full":"Stadtpl 27 Gm\u00fcnd Nieder\u00f6sterreich 3950",
    "addr:housenumber":"27",
    "addr:postcode":"3950",
    "addr:street":"Stadtpl;Niederoesterreich",
    "iso:country":"AT",
    "sg:address":"Stadtpl 27",
    "sg:city":"Gm\u00fcnd",
    "sg:orig_category":"Strick- U Wirkwaren / Einzelhandel",
    "sg:phone":"+43 2852 52297",
    "sg:postcode":"3950",
    "sg:province":"Nieder\u00f6sterreich",
    "wof:name":"Gobl Susanne Ing Mag",
    "wof:placetype":"venue"
},
  "geometry": {"coordinates":[14.9852590561,48.7731056213],"type":"Point"}
}