{
  "type": "Feature",
  "properties": {
    "addr:full":"Rosmaringasse 65 Wien Wien 1220",
    "addr:housenumber":"65",
    "addr:postcode":"1220",
    "addr:street":"Rosmaringasse",
    "iso:country":"AT",
    "sg:address":"Rosmaringasse 65",
    "sg:city":"Wien",
    "sg:classifiers":[
        {
            "category":"Building & Trades",
            "subcategory":"Plumbing",
            "type":"Services"
        }
    ],
    "sg:phone":"+43 1 2825360",
    "sg:postcode":"1220",
    "sg:province":"Wien",
    "sg:tags":[
        "tub",
        "bath"
    ],
    "sg:website":"viennafirstclass.com",
    "wof:name":"GTB Kaltenbrunner",
    "wof:placetype":"venue"
},
  "geometry": {"coordinates":[16.4676952362,48.2240715027],"type":"Point"}
}