{
  "type": "Feature",
  "properties": {
    "iso:country":"AT",
    "sg:address":"Kaserng 10",
    "sg:city":"Judenburg",
    "sg:orig_category":"Juweliere, Gold- U Silberschmiede",
    "sg:phone":"+43 4335 7282205",
    "sg:postcode":"8750",
    "sg:province":"Steiermark",
    "wof:name":"Hawelka Sepp",
    "wof:placetype":"venue"
},
  "geometry": {"coordinates":[14.6623773575,47.1691551208],"type":"Point"}
}