{
  "type": "Feature",
  "properties": {
    "addr:full":"Hauptstr 23 Hieflau Steiermark 8920",
    "addr:housenumber":"23",
    "addr:postcode":"8920",
    "addr:street":"Hauptstr",
    "iso:country":"AT",
    "sg:address":"Hauptstr 23",
    "sg:city":"Hieflau",
    "sg:orig_category":"Lebensmittel / Einzelhandel",
    "sg:phone":"+43 4336 347227",
    "sg:postcode":"8920",
    "sg:province":"Steiermark",
    "wof:name":"Spar-Markt Wagenhofer Armin",
    "wof:placetype":"venue"
},
  "geometry": {"coordinates":[14.7459821701,47.6050834656],"type":"Point"}
}