{
  "type": "Feature",
  "properties": {
    "addr:full":"Falkensteinstr 5 Lembach im M\u00fchlkreis Ober\u00f6sterreich 4132",
    "addr:housenumber":"5",
    "addr:postcode":"4132",
    "addr:street":"Falkensteinstr;Im Muehlkreis Oberoesterreich",
    "iso:country":"AT",
    "sg:address":"Falkensteinstr 5",
    "sg:city":"Lembach im M\u00fchlkreis",
    "sg:orig_category":"Installationsunternehmen",
    "sg:phone":"+43 7286 8213",
    "sg:postcode":"4132",
    "sg:province":"Ober\u00f6sterreich",
    "wof:name":"Stadt Christoph Ing",
    "wof:placetype":"venue"
},
  "geometry": {"coordinates":[13.8934526443,48.4950332642],"type":"Point"}
}