{
  "type": "Feature",
  "properties": {
    "iso:country":"AT",
    "sg:address":"Brucker Str 10",
    "sg:city":"Gratkorn",
    "sg:orig_category":"Elektroinstallationsunternehmen",
    "sg:phone":"+43 4331 24233840",
    "sg:postcode":"8101",
    "sg:province":"Steiermark",
    "wof:name":"R\u00f6\u00dfler Heinz",
    "wof:placetype":"venue"
},
  "geometry": {"coordinates":[15.3374795914,47.1341362],"type":"Point"}
}