{
  "type": "Feature",
  "properties": {
    "addr:full":"Landesstr 16 Henndorf am Wallersee Salzburg 5302",
    "addr:housenumber":"16",
    "addr:postcode":"5302",
    "addr:street":"Landesstr",
    "iso:country":"AT",
    "sg:address":"Landesstr 16",
    "sg:city":"Henndorf am Wallersee",
    "sg:orig_category":"Elektrische Heizungen",
    "sg:phone":"+43 4362 1476770",
    "sg:postcode":"5302",
    "sg:province":"Salzburg",
    "wof:name":"Etherma Elektrow\u00e4rme Verfahrenstechnik GesmbH",
    "wof:placetype":"venue"
},
  "geometry": {"coordinates":[13.1826267242,47.8901329041],"type":"Point"}
}