{
  "type": "Feature",
  "properties": {
    "addr:full":"Stiegergasse 15-17/1 Wien Wien 1150",
    "addr:housenumber":"15-17 / 1",
    "addr:postcode":"1150",
    "addr:street":"Stiegergasse",
    "iso:country":"AT",
    "sg:address":"Stiegergasse 15-17/1",
    "sg:city":"Wien",
    "sg:classifiers":[
        {
            "category":"Professional",
            "subcategory":"Art Services",
            "type":"Services"
        }
    ],
    "sg:phone":"+43 1 8950217",
    "sg:postcode":"1150",
    "sg:province":"Wien",
    "sg:tags":[
        "artistic",
        "glazings"
    ],
    "wof:name":"Carl Geyling's Erben Nfg.Ges.m.b.H. & Co KG",
    "wof:placetype":"venue"
},
  "geometry": {"coordinates":[16.3320903778,48.2006416321],"type":"Point"}
}