{
  "type": "Feature",
  "properties": {
    "addr:full":"Lacknerg 70 Wien Wien 1170",
    "addr:housenumber":"70",
    "addr:postcode":"1170",
    "addr:street":"Lacknerg",
    "iso:country":"AT",
    "sg:address":"Lacknerg 70",
    "sg:city":"Wien",
    "sg:orig_category":"Friseure U Frisiersalons",
    "sg:phone":"+43 4314 815348",
    "sg:postcode":"1170",
    "sg:province":"Wien",
    "wof:name":"Fris\u00f6r Granda",
    "wof:placetype":"venue"
},
  "geometry": {"coordinates":[16.3320922852,48.224773407],"type":"Point"}
}