{
  "type": "Feature",
  "properties": {
    "addr:full":"Salzburger Str 13 Bad Hofgastein Salzburg 5630",
    "addr:housenumber":"13",
    "addr:postcode":"5630",
    "addr:street":"Salzburger Str;Salzburg",
    "iso:country":"AT",
    "sg:address":"Salzburger Str 13",
    "sg:city":"Bad Hofgastein",
    "sg:orig_category":"Wassertechnik",
    "sg:phone":"+43 6432 7950",
    "sg:postcode":"5630",
    "sg:province":"Salzburg",
    "wof:name":"TWP-Wasser-Management-Gerhard Hofmann",
    "wof:placetype":"venue"
},
  "geometry": {"coordinates":[13.1028347015,47.1707115173],"type":"Point"}
}