{
  "type": "Feature",
  "properties": {
    "addr:full":"Kreuzg 262 Nauders Tirol 6543",
    "addr:housenumber":"262",
    "addr:postcode":"6543",
    "addr:street":"Nauders Tirol",
    "iso:country":"AT",
    "sg:address":"Kreuzg 262",
    "sg:city":"Nauders",
    "sg:orig_category":"Pensionen / Privatzimmer",
    "sg:phone":"+43 5473 87344",
    "sg:postcode":"6543",
    "sg:province":"Tirol",
    "wof:name":"Zegg Karl",
    "wof:placetype":"venue"
},
  "geometry": {"coordinates":[10.5038080215,46.8937187195],"type":"Point"}
}