{
  "type": "Feature",
  "properties": {
    "iso:country":"AT",
    "sg:address":"Industriestrasse 3",
    "sg:city":"Wolkersdorf im Weinviertel",
    "sg:classifiers":[
        {
            "category":"Professional",
            "subcategory":"Art Services",
            "type":"Services"
        }
    ],
    "sg:phone":"+43 2245 24970",
    "sg:postcode":"2120",
    "sg:province":"Nieder\u00f6sterreich",
    "sg:tags":[
        "stand",
        "construction",
        "exhibition",
        "fair",
        "trade"
    ],
    "sg:website":"syma.at",
    "wof:name":"SYMA-SYSTEM Vertriebsges.m.b.H.",
    "wof:placetype":"venue"
},
  "geometry": {"coordinates":[16.5077037811,48.378944397],"type":"Point"}
}