{
  "type": "Feature",
  "properties": {
    "iso:country":"AT",
    "sg:address":"Sch\u00f6ndorferpl 6",
    "sg:city":"Hallein",
    "sg:orig_category":"Bibliotheken",
    "sg:phone":"+43 6245 84979",
    "sg:postcode":"5400",
    "sg:province":"Salzburg",
    "wof:name":"Stadtb\u00fccherei der Stadtgemeinde Hallein",
    "wof:placetype":"venue"
},
  "geometry": {"coordinates":[13.0920419693,47.6815872192],"type":"Point"}
}