{
  "type": "Feature",
  "properties": {
    "iso:country":"AT",
    "sg:address":"Fanny-Wibmer-Pedit-Str 6",
    "sg:city":"Lienz",
    "sg:orig_category":"Wasserwerke",
    "sg:phone":"+43 4348 52600721",
    "sg:postcode":"9900",
    "sg:province":"Tirol",
    "wof:name":"St\u00e4dtische Wasserwerk Lienz",
    "wof:placetype":"venue"
},
  "geometry": {"coordinates":[12.7733058929,46.8311729431],"type":"Point"}
}