{
  "type": "Feature",
  "properties": {
    "iso:country":"AT",
    "sg:address":"Walter-Simmer-Strasse 15a ",
    "sg:city":"Mondsee",
    "sg:classifiers":[
        {
            "category":"Building & Trades",
            "subcategory":"Plumbing",
            "type":"Services"
        }
    ],
    "sg:phone":"+43 6232 283116",
    "sg:postcode":"5310",
    "sg:province":"Ober\u00f6sterreich",
    "sg:tags":[
        "supraregional",
        "gas"
    ],
    "wof:name":"Robert Graspointner GmbH",
    "wof:placetype":"venue"
},
  "geometry": {"coordinates":[13.3316478729,47.8639945984],"type":"Point"}
}