{
  "type": "Feature",
  "properties": {
    "iso:country":"AT",
    "sg:city":"Bach",
    "sg:orig_category":"Freizeit, Musik",
    "sg:postcode":"6653",
    "sg:province":"Tirol",
    "sg:website":"http://www.bluatschink.at/",
    "wof:name":"Bluatschink",
    "wof:placetype":"venue"
},
  "geometry": {"coordinates":[10.403676033,47.270198822],"type":"Point"}
}