{
  "type": "Feature",
  "properties": {
    "addr:full":"Bayerhamerstr 33 Salzburg Salzburg 5020",
    "addr:housenumber":"33",
    "addr:postcode":"5020",
    "addr:street":"Bayerhamerstr;Salzburg",
    "iso:country":"AT",
    "sg:address":"Bayerhamerstr 33",
    "sg:city":"Salzburg",
    "sg:orig_category":"Massagen",
    "sg:phone":"+43 662 882498",
    "sg:postcode":"5020",
    "sg:province":"Salzburg",
    "wof:name":"Egger Andrea",
    "wof:placetype":"venue"
},
  "geometry": {"coordinates":[13.0503082275,47.8103370667],"type":"Point"}
}