{
  "type": "Feature",
  "properties": {
    "addr:full":"Obere Hauptstr 47 Unterrabnitz Burgenland 7371",
    "addr:housenumber":"47",
    "addr:postcode":"7371",
    "addr:street":"Obere Hauptstr",
    "iso:country":"AT",
    "sg:address":"Obere Hauptstr 47",
    "sg:city":"Unterrabnitz",
    "sg:orig_category":"Zimmereien",
    "sg:phone":"+43 2617 3329",
    "sg:postcode":"7371",
    "sg:province":"Burgenland",
    "wof:name":"Kogler Gottfried Ing",
    "wof:placetype":"venue"
},
  "geometry": {"coordinates":[16.3543701172,47.4971313477],"type":"Point"}
}