{
  "type": "Feature",
  "properties": {
    "addr:full":"Kirchenstrasse 21 5072",
    "addr:housenumber":"21",
    "addr:postcode":"5072",
    "addr:street":"Kirchenstrasse",
    "iso:country":"AT",
    "sg:address":"Kirchenstrasse 21",
    "sg:classifiers":[
        {
            "category":"Wholesale",
            "subcategory":"Metals & Minerals",
            "type":"Manufacturing & Wholesale Goods"
        }
    ],
    "sg:phone":"+43 662 850275",
    "sg:postcode":"5072",
    "sg:tags":[
        "band",
        "blade",
        "saw",
        "machining"
    ],
    "sg:website":"homas-bandsaegen.at",
    "wof:name":"G\u00fcnter Hochleitner",
    "wof:placetype":"venue"
},
  "geometry": {"coordinates":[12.9871330261,47.8103942871],"type":"Point"}
}