{
  "type": "Feature",
  "properties": {
    "addr:full":"Penzinger Str 39 Wien Wien 1140",
    "addr:postcode":"1140",
    "addr:street":"Str 39",
    "iso:country":"AT",
    "sg:address":"Penzinger Str 39",
    "sg:city":"Wien",
    "sg:orig_category":"Feldenkraismethode",
    "sg:phone":"+43 1 9239429",
    "sg:postcode":"1140",
    "sg:province":"Wien",
    "wof:name":"Kaweh Babak",
    "wof:placetype":"venue"
},
  "geometry": {"coordinates":[16.3084640503,48.189453125],"type":"Point"}
}