{
  "type": "Feature",
  "properties": {
    "addr:full":"Schwarzmayrstr 10 Steyr Ober\u00f6sterreich 4400",
    "addr:housenumber":"10",
    "addr:postcode":"4400",
    "addr:street":"Schwarzmayrstr;Oberoesterreich",
    "iso:country":"AT",
    "sg:address":"Schwarzmayrstr 10",
    "sg:city":"Steyr",
    "sg:orig_category":"Architekten",
    "sg:phone":"+43 7252 77083",
    "sg:postcode":"4400",
    "sg:province":"Ober\u00f6sterreich",
    "wof:name":"Proyer & Proyer Architekten OEG",
    "wof:placetype":"venue"
},
  "geometry": {"coordinates":[14.4204244614,48.0293807983],"type":"Point"}
}