{
  "type": "Feature",
  "properties": {
    "addr:full":"Austr 2 Wimpassing im Schwarzatale Nieder\u00f6sterreich 2632",
    "addr:housenumber":"2",
    "addr:postcode":"2632",
    "addr:street":"Austr",
    "iso:country":"AT",
    "sg:address":"Austr 2",
    "sg:city":"Wimpassing im Schwarzatale",
    "sg:orig_category":"Schlossereien",
    "sg:phone":"+43 4326 3032061",
    "sg:postcode":"2632",
    "sg:province":"Nieder\u00f6sterreich",
    "wof:name":"Schick Karl",
    "wof:placetype":"venue"
},
  "geometry": {"coordinates":[16.0105075836,47.6878814697],"type":"Point"}
}