{
  "type": "Feature",
  "properties": {
    "addr:full":"Hauptpl 24 Bad Leonfelden Ober\u00f6sterreich 4190",
    "addr:housenumber":"24",
    "addr:postcode":"4190",
    "addr:street":"Hauptpl",
    "iso:country":"AT",
    "sg:address":"Hauptpl 24",
    "sg:city":"Bad Leonfelden",
    "sg:orig_category":"Blumeneinzelhandel",
    "sg:phone":"+43 7213 8579",
    "sg:postcode":"4190",
    "sg:province":"Ober\u00f6sterreich",
    "wof:name":"Sch\u00fcrer Wilhelm",
    "wof:placetype":"venue"
},
  "geometry": {"coordinates":[14.294262886,48.521938324],"type":"Point"}
}