{
  "type": "Feature",
  "properties": {
    "addr:full":"Bergg 21 Wien Wien 1090",
    "addr:housenumber":"21",
    "addr:postcode":"1090",
    "addr:street":"Bergg",
    "iso:country":"AT",
    "sg:address":"Bergg 21",
    "sg:city":"Wien",
    "sg:orig_category":"Architekten",
    "sg:phone":"+43 1 3155349",
    "sg:postcode":"1090",
    "sg:province":"Wien",
    "wof:name":"veech.media.architecture.",
    "wof:placetype":"venue"
},
  "geometry": {"coordinates":[16.3637294769,48.2189025879],"type":"Point"}
}