{
  "type": "Feature",
  "properties": {
    "iso:country":"AT",
    "sg:address":"Loferer Bundesstr 71",
    "sg:city":"Zell am See",
    "sg:orig_category":"Lebensmittel / Einzelhandel",
    "sg:phone":"+43 6542 723440",
    "sg:postcode":"5700",
    "sg:province":"Salzburg",
    "wof:name":"Nah & Frisch",
    "wof:placetype":"venue"
},
  "geometry": {"coordinates":[12.7976989746,47.3402824402],"type":"Point"}
}