{
  "type": "Feature",
  "properties": {
    "addr:full":"Wiener Str 24 Schwechat Nieder\u00f6sterreich 2320",
    "addr:postcode":"2320",
    "addr:street":"Niederoesterreich",
    "iso:country":"AT",
    "sg:address":"Wiener Str 24",
    "sg:city":"Schwechat",
    "sg:classifiers":[
        {
            "category":"Restaurant",
            "type":"Food & Drink"
        }
    ],
    "sg:phone":"+43 1 7062787",
    "sg:postcode":"2320",
    "sg:province":"Nieder\u00f6sterreich",
    "sg:tags":[
        "pizzeria"
    ],
    "wof:name":"Pizzeria Rialto",
    "wof:placetype":"venue"
},
  "geometry": {"coordinates":[16.4726696014,48.1434822083],"type":"Point"}
}