{
  "type": "Feature",
  "properties": {
    "iso:country":"AT",
    "sg:address":"Nr 62",
    "sg:city":"Baldramsdorf",
    "sg:orig_category":"Appartements / Ferienwohnungen",
    "sg:phone":"+43 4762 7182",
    "sg:postcode":"9805",
    "sg:province":"K\u00e4rnten",
    "wof:name":"Gasser Josef",
    "wof:placetype":"venue"
},
  "geometry": {"coordinates":[13.4519433975,46.801574707],"type":"Point"}
}