{
  "type": "Feature",
  "properties": {
    "addr:full":"Franzosengraben 3-5 Wien Wien 1030",
    "addr:housenumber":"3-5",
    "addr:postcode":"1030",
    "addr:street":"Franzosengraben",
    "iso:country":"AT",
    "sg:address":"Franzosengraben 3-5",
    "sg:city":"Wien",
    "sg:orig_category":"Spielkasinos",
    "sg:phone":"+43 1 7969933",
    "sg:postcode":"1030",
    "sg:province":"Wien",
    "wof:name":"Pokerworld - Engstler Manfred GmbH",
    "wof:placetype":"venue"
},
  "geometry": {"coordinates":[16.4161109924,48.1893959045],"type":"Point"}
}