{
  "type": "Feature",
  "properties": {
    "addr:full":"Joch\u00e4ckerg 7 Tribuswinkel Nieder\u00f6sterreich 2512",
    "addr:housenumber":"7",
    "addr:postcode":"2512",
    "addr:street":"Jochaeckerg",
    "iso:country":"AT",
    "sg:address":"Joch\u00e4ckerg 7",
    "sg:city":"Tribuswinkel",
    "sg:orig_category":"Autoreparatur",
    "sg:phone":"+43 2252 54935",
    "sg:postcode":"2512",
    "sg:province":"Nieder\u00f6sterreich",
    "wof:name":"Barbach Michael",
    "wof:placetype":"venue"
},
  "geometry": {"coordinates":[16.2880916595,47.9828262329],"type":"Point"}
}