{
  "type": "Feature",
  "properties": {
    "iso:country":"AT",
    "sg:address":"Sch\u00f6nbrunner Allee 1",
    "sg:city":"Wien",
    "sg:classifiers":[
        {
            "category":"Autos & Motor Vehicles",
            "subcategory":"Motorcycle Sales",
            "type":"Retail Goods"
        }
    ],
    "sg:phone":"+43 1 8133413",
    "sg:postcode":"1120",
    "sg:province":"Wien",
    "sg:tags":[
        "cyclist",
        "goggles",
        "motorists",
        "motorcyclist"
    ],
    "wof:name":"Friedrich Winkler Schutz- Sport- u. Sonnenbrillenerzeugung KG",
    "wof:placetype":"venue"
},
  "geometry": {"coordinates":[16.3138637543,48.1748085022],"type":"Point"}
}