{
  "type": "Feature",
  "properties": {
    "addr:full":"Markt 20 Peilstein im M\u00fchlviertel Ober\u00f6sterreich 4153",
    "addr:housenumber":"20",
    "addr:postcode":"4153",
    "addr:street":"Markt;Im Muehlviertel Oberoesterreich",
    "iso:country":"AT",
    "sg:address":"Markt 20",
    "sg:city":"Peilstein im M\u00fchlviertel",
    "sg:orig_category":"Non-Classified Establishments",
    "sg:phone":"+43 7287 7209",
    "sg:postcode":"4153",
    "sg:province":"Ober\u00f6sterreich",
    "wof:name":"Pfarramt",
    "wof:placetype":"venue"
},
  "geometry": {"coordinates":[13.8674449921,48.6588592529],"type":"Point"}
}