{
  "type": "Feature",
  "properties": {
    "addr:full":"Kiechlanger 4a Hall in Tirol Tirol 6060",
    "addr:housenumber":"4a",
    "addr:postcode":"6060",
    "addr:street":"Kiechlanger;Tirol",
    "iso:country":"AT",
    "sg:address":"Kiechlanger 4a",
    "sg:city":"Hall in Tirol",
    "sg:classifiers":[
        {
            "category":"Banks & Credit Unions",
            "subcategory":"Investment Brokerage",
            "type":"Services"
        }
    ],
    "sg:phone":"+43 5223 53060",
    "sg:postcode":"6060",
    "sg:province":"Tirol",
    "sg:tags":[
        "cnc",
        "milling"
    ],
    "wof:name":"Georg Saxer Ges.m.b.H. & Co KG",
    "wof:placetype":"venue"
},
  "geometry": {"coordinates":[11.5126285553,47.2830848694],"type":"Point"}
}