{
  "type": "Feature",
  "properties": {
    "iso:country":"AT",
    "sg:address":"Geyschl\u00e4gerg 14",
    "sg:city":"Wien",
    "sg:classifiers":[
        {
            "category":"Professional",
            "subcategory":"Computer Services",
            "type":"Services"
        }
    ],
    "sg:phone":"+43 1 7863020400",
    "sg:postcode":"1150",
    "sg:province":"Wien",
    "sg:tags":[
        "software"
    ],
    "wof:name":"No Limits Software Informationstechnologie GmbH",
    "wof:placetype":"venue"
},
  "geometry": {"coordinates":[16.3350429535,48.202999115],"type":"Point"}
}