{
  "type": "Feature",
  "properties": {
    "iso:country":"AT",
    "sg:address":"Moosmahdstr 14",
    "sg:city":"Dornbirn",
    "sg:orig_category":"Ingenieurkonsulenten / Zivilingenieure",
    "sg:phone":"+43 5572 222530",
    "sg:postcode":"6850",
    "sg:province":"Vorarlberg",
    "wof:name":"Riedmann & Partner",
    "wof:placetype":"venue"
},
  "geometry": {"coordinates":[9.7376737595,47.4142837524],"type":"Point"}
}