{
  "type": "Feature",
  "properties": {
    "addr:full":"Kolpingstrasse 18 Wien Wien 1230",
    "addr:housenumber":"18",
    "addr:postcode":"1230",
    "addr:street":"Kolpingstrasse",
    "iso:country":"AT",
    "sg:address":"Kolpingstrasse 18",
    "sg:city":"Wien",
    "sg:classifiers":[
        {
            "category":"Shopping",
            "subcategory":"Computers & Home Electronics",
            "type":"Retail Goods"
        }
    ],
    "sg:phone":"+43 1 4852605",
    "sg:postcode":"1230",
    "sg:province":"Wien",
    "sg:tags":[
        "code",
        "bar",
        "scanner",
        "decoder"
    ],
    "sg:website":"tauris.com",
    "wof:name":"Ing. Harald Marbacher GmbH",
    "wof:placetype":"venue"
},
  "geometry": {"coordinates":[16.3433818817,48.1385650635],"type":"Point"}
}