{
  "type": "Feature",
  "properties": {
    "addr:full":"Sch\u00f6nbichlstr 14 Fuschl am See Salzburg 5330",
    "addr:housenumber":"14",
    "addr:postcode":"5330",
    "addr:street":"Schoenbichlstr",
    "iso:country":"AT",
    "sg:address":"Sch\u00f6nbichlstr 14",
    "sg:city":"Fuschl am See",
    "sg:orig_category":"Pensionen / Privatzimmer",
    "sg:phone":"+43 6226 8306",
    "sg:postcode":"5330",
    "sg:province":"Salzburg",
    "wof:name":"Haus Lisa",
    "wof:placetype":"venue"
},
  "geometry": {"coordinates":[13.2871932983,47.7910003662],"type":"Point"}
}