{
  "type": "Feature",
  "properties": {
    "addr:full":"122 Ilz Steiermark 8262",
    "addr:housenumber":"122",
    "addr:postcode":"8262",
    "addr:street":"Ilz Steiermark",
    "iso:country":"AT",
    "sg:address":"122",
    "sg:city":"Ilz",
    "sg:orig_category":"Feuerwehren",
    "sg:phone":"+43 3385 8620",
    "sg:postcode":"8262",
    "sg:province":"Steiermark",
    "wof:name":"Freiwillige Feuerwehr Nestelbach i Ilztal",
    "wof:placetype":"venue"
},
  "geometry": {"coordinates":[15.9260549545,47.086479187],"type":"Point"}
}