{
  "type": "Feature",
  "properties": {
    "iso:country":"AT",
    "sg:address":"Anton-Scheiblin-G 6",
    "sg:city":"St. P\u00f6lten",
    "sg:orig_category":"Banken U Sparkassen",
    "sg:phone":"+43 4350 50530160",
    "sg:postcode":"3100",
    "sg:province":"Nieder\u00f6sterreich",
    "wof:name":"Bank Austria Creditanstalt AG - Bankshop",
    "wof:placetype":"venue"
},
  "geometry": {"coordinates":[15.6240940094,48.2076377869],"type":"Point"}
}