{
  "type": "Feature",
  "properties": {
    "addr:full":"Industriegebiet Medraz B/15 Fulpmes Tirol 6166",
    "addr:housenumber":"15",
    "addr:postcode":"6166",
    "addr:street":"Industriegebiet Medraz B /;Tirol",
    "iso:country":"AT",
    "sg:address":"Industriegebiet Medraz B/15",
    "sg:city":"Fulpmes",
    "sg:classifiers":[
        {
            "category":"Utilities",
            "subcategory":"Mobile Phone",
            "type":"Services"
        }
    ],
    "sg:phone":"+43 5225 63901",
    "sg:postcode":"6166",
    "sg:province":"Tirol",
    "sg:tags":[
        "punching",
        "cnc"
    ],
    "sg:website":"motoolsystem.at",
    "wof:name":"Motoolsystem Felsner & Stern GmbH",
    "wof:placetype":"venue"
},
  "geometry": {"coordinates":[11.3487129211,47.1532936096],"type":"Point"}
}