{
  "type": "Feature",
  "properties": {
    "addr:full":"Gregor-Mendel-Str 33 Wien Wien 1180",
    "addr:housenumber":"33",
    "addr:postcode":"1180",
    "addr:street":"Gregor-Mendel-Str",
    "iso:country":"AT",
    "sg:address":"Gregor-Mendel-Str 33",
    "sg:city":"Wien",
    "sg:orig_category":"Institute",
    "sg:phone":"+43 4314 76544250",
    "sg:postcode":"1180",
    "sg:province":"Wien",
    "wof:name":"Institut f Holzforschung",
    "wof:placetype":"venue"
},
  "geometry": {"coordinates":[16.3375434875,48.236579895],"type":"Point"}
}