{
  "type": "Feature",
  "properties": {
    "iso:country":"AT",
    "sg:address":"Neubau 34",
    "sg:city":"Stockerau",
    "sg:orig_category":"Tabaktrafiken",
    "sg:phone":"+43 2266 63215",
    "sg:postcode":"2000",
    "sg:province":"Nieder\u00f6sterreich",
    "wof:name":"Schober Tabaktrafik",
    "wof:placetype":"venue"
},
  "geometry": {"coordinates":[16.2183704376,48.3840484619],"type":"Point"}
}