{
  "type": "Feature",
  "properties": {
    "iso:country":"AT",
    "sg:address":"August-Scherl-Str 4",
    "sg:city":"Kufstein",
    "sg:orig_category":"Fotografen",
    "sg:phone":"+43 5372 62416",
    "sg:postcode":"6330",
    "sg:province":"Tirol",
    "wof:name":"Foto Brosenbauer",
    "wof:placetype":"venue"
},
  "geometry": {"coordinates":[12.1730728149,47.579662323],"type":"Point"}
}