{
  "type": "Feature",
  "properties": {
    "addr:full":"Pischeldorfer Str 151 Klagenfurt K\u00e4rnten 9020",
    "addr:housenumber":"151",
    "addr:postcode":"9020",
    "addr:street":"Kaernten",
    "iso:country":"AT",
    "sg:address":"Pischeldorfer Str 151",
    "sg:city":"Klagenfurt",
    "sg:orig_category":"Fleischhauereien",
    "sg:phone":"+43 463 41752",
    "sg:postcode":"9020",
    "sg:province":"K\u00e4rnten",
    "wof:name":"J\u00e4ger Stefan",
    "wof:placetype":"venue"
},
  "geometry": {"coordinates":[14.3317651749,46.6379356384],"type":"Point"}
}