{
  "type": "Feature",
  "properties": {
    "addr:full":"Hauptstr 149 Krumpendorf K\u00e4rnten 9201",
    "addr:housenumber":"149",
    "addr:postcode":"9201",
    "addr:street":"Hauptstr;Kaernten",
    "iso:country":"AT",
    "sg:address":"Hauptstr 149",
    "sg:city":"Krumpendorf",
    "sg:orig_category":"Banken U Sparkassen",
    "sg:phone":"+43 4350 10030815",
    "sg:postcode":"9201",
    "sg:province":"K\u00e4rnten",
    "wof:name":"K\u00e4rntner Sparkasse AG",
    "wof:placetype":"venue"
},
  "geometry": {"coordinates":[14.2134399414,46.6264686584],"type":"Point"}
}