{
  "type": "Feature",
  "properties": {
    "addr:full":"Nr 61 Maurach Tirol 6212",
    "addr:postcode":"6212",
    "addr:street":"Nr;Maurach Tirol",
    "iso:country":"AT",
    "sg:address":"Nr 61",
    "sg:city":"Maurach",
    "sg:classifiers":[
        {
            "category":"Professional",
            "subcategory":"Computer Services",
            "type":"Services"
        }
    ],
    "sg:phone":"+43 4352 4364600",
    "sg:postcode":"6212",
    "sg:province":"Tirol",
    "sg:tags":[
        "software"
    ],
    "wof:name":"Tyro-Computer GesmbH",
    "wof:placetype":"venue"
},
  "geometry": {"coordinates":[11.7518672943,47.4225006104],"type":"Point"}
}