{
  "type": "Feature",
  "properties": {
    "addr:full":"Hauptstr 45 Oetz Tirol 6433",
    "addr:housenumber":"45",
    "addr:postcode":"6433",
    "addr:street":"Hauptstr;Tirol",
    "iso:country":"AT",
    "sg:address":"Hauptstr 45",
    "sg:city":"Oetz",
    "sg:orig_category":"Banken U Sparkassen",
    "sg:phone":"+43 4352 5266660",
    "sg:postcode":"6433",
    "sg:province":"Tirol",
    "wof:name":"Sparkasse Imst",
    "wof:placetype":"venue"
},
  "geometry": {"coordinates":[10.8965797424,47.2031707764],"type":"Point"}
}