{
  "type": "Feature",
  "properties": {
    "iso:country":"AT",
    "sg:address":"F Trautenberger-Str 19",
    "sg:city":"Purkersdorf",
    "sg:orig_category":"Exporteure U Importeure",
    "sg:phone":"+43 2231 64289",
    "sg:postcode":"3002",
    "sg:province":"Nieder\u00f6sterreich",
    "wof:name":"Haderer Horst",
    "wof:placetype":"venue"
},
  "geometry": {"coordinates":[16.1694526672,48.2110519409],"type":"Point"}
}