{
  "type": "Feature",
  "properties": {
    "addr:full":"Nr 5 Floing Steiermark 8183",
    "addr:postcode":"8183",
    "addr:street":"Nr",
    "iso:country":"AT",
    "sg:address":"Nr 5",
    "sg:city":"Floing",
    "sg:orig_category":"Banken U Sparkassen",
    "sg:phone":"+43 4331 774125",
    "sg:postcode":"8183",
    "sg:province":"Steiermark",
    "wof:name":"Bankomat d Raiffeisenbank Anger-Puch-Koglhof regGenmbH",
    "wof:placetype":"venue"
},
  "geometry": {"coordinates":[15.7296800613,47.2485237122],"type":"Point"}
}