{
  "type": "Feature",
  "properties": {
    "addr:full":"Fohrenburgstr 1 Bludenz Vorarlberg 6700",
    "addr:housenumber":"1",
    "addr:postcode":"6700",
    "addr:street":"Fohrenburgstr",
    "iso:country":"AT",
    "sg:address":"Fohrenburgstr 1",
    "sg:city":"Bludenz",
    "sg:orig_category":"Schokolade U Schokoladewaren",
    "sg:phone":"+43 4355 526090",
    "sg:postcode":"6700",
    "sg:province":"Vorarlberg",
    "sg:website":"suchard.at",
    "wof:name":"Kraft Foods \u00f6sterreich GmbH",
    "wof:placetype":"venue"
},
  "geometry": {"coordinates":[9.8154439926,47.1554412842],"type":"Point"}
}