{
  "type": "Feature",
  "properties": {
    "iso:country":"AT",
    "sg:address":"St. Martha 29",
    "sg:city":"St. Marein",
    "sg:orig_category":"Partyservice",
    "sg:phone":"+43 4335 154679",
    "sg:postcode":"8733",
    "sg:province":"Steiermark",
    "wof:name":"Mo & Co Moitzi Peter",
    "wof:placetype":"venue"
},
  "geometry": {"coordinates":[14.8505382538,47.2824554443],"type":"Point"}
}