{
  "type": "Feature",
  "properties": {
    "addr:full":"Bichlnweg 7a Kitzb\u00fchel Tirol 6370",
    "addr:housenumber":"7a",
    "addr:postcode":"6370",
    "addr:street":"Bichlnweg;Tirol",
    "iso:country":"AT",
    "sg:address":"Bichlnweg 7a",
    "sg:city":"Kitzb\u00fchel",
    "sg:orig_category":"Fotografen",
    "sg:phone":"+43 5356 66733",
    "sg:postcode":"6370",
    "sg:province":"Tirol",
    "wof:name":"Mitterer Markus",
    "wof:placetype":"venue"
},
  "geometry": {"coordinates":[12.4043121338,47.4372138977],"type":"Point"}
}