{
  "type": "Feature",
  "properties": {
    "addr:full":"Eisenst\u00e4dter Str 6 Rust Burgenland 7071",
    "addr:housenumber":"6",
    "addr:postcode":"7071",
    "addr:street":"Str",
    "iso:country":"AT",
    "sg:address":"Eisenst\u00e4dter Str 6",
    "sg:city":"Rust",
    "sg:orig_category":"Blumeneinzelhandel",
    "sg:phone":"+43 2685 6413",
    "sg:postcode":"7071",
    "sg:province":"Burgenland",
    "wof:name":"Maitz Beatrix",
    "wof:placetype":"venue"
},
  "geometry": {"coordinates":[16.6699085236,47.800453186],"type":"Point"}
}