{
  "type": "Feature",
  "properties": {
    "iso:country":"AT",
    "sg:address":"Zoblstrasse 7",
    "sg:city":"Lambach",
    "sg:classifiers":[
        {
            "category":"Professional",
            "subcategory":"Advertising",
            "type":"Services"
        }
    ],
    "sg:phone":"+43 7245 21591",
    "sg:postcode":"4650",
    "sg:province":"Ober\u00f6sterreich",
    "sg:tags":[
        "bag",
        "paper"
    ],
    "sg:website":"europack.at",
    "wof:name":"EP Verpackungs GmbH Europack",
    "wof:placetype":"venue"
},
  "geometry": {"coordinates":[13.9043903351,48.0935440063],"type":"Point"}
}