{
  "type": "Feature",
  "properties": {
    "iso:country":"AT",
    "sg:address":"Dr.-Karl-Renner-Pl 3",
    "sg:city":"Traiskirchen",
    "sg:orig_category":"Apotheken",
    "sg:phone":"+43 2252 526270",
    "sg:postcode":"2514",
    "sg:province":"Nieder\u00f6sterreich",
    "wof:name":"Engel-Apotheke Mag pharm H Tr\u00f6thandl OHG",
    "wof:placetype":"venue"
},
  "geometry": {"coordinates":[16.2928848267,48.0148582458],"type":"Point"}
}