{
  "type": "Feature",
  "properties": {
    "addr:full":"Millst\u00e4tter Str 103 Afritz am See K\u00e4rnten 9542",
    "addr:housenumber":"103",
    "addr:postcode":"9542",
    "addr:street":"Str;Kaernten",
    "iso:country":"AT",
    "sg:address":"Millst\u00e4tter Str 103",
    "sg:city":"Afritz am See",
    "sg:orig_category":"Lebensmittel / Einzelhandel",
    "sg:phone":"+43 4342 4729966",
    "sg:postcode":"9542",
    "sg:province":"K\u00e4rnten",
    "wof:name":"Billa AG",
    "wof:placetype":"venue"
},
  "geometry": {"coordinates":[13.7836418152,46.7296485901],"type":"Point"}
}