{
  "type": "Feature",
  "properties": {
    "addr:full":"Halbgasse 6 Wien Wien 1070",
    "addr:housenumber":"6",
    "addr:postcode":"1070",
    "addr:street":"Halbgasse",
    "iso:country":"AT",
    "sg:address":"Halbgasse 6",
    "sg:city":"Wien",
    "sg:classifiers":[
        {
            "category":"Communications",
            "subcategory":"Film & Video Production",
            "type":"Services"
        }
    ],
    "sg:phone":"+43 1 5235129",
    "sg:postcode":"1070",
    "sg:province":"Wien",
    "wof:name":"Continental-Film Miksch KEG",
    "wof:placetype":"venue"
},
  "geometry": {"coordinates":[16.3418254852,48.2033615112],"type":"Point"}
}