{
  "type": "Feature",
  "properties": {
    "addr:full":"Roseggerg 44-46 Wien Wien 1160",
    "addr:postcode":"44-46;1160",
    "iso:country":"AT",
    "sg:address":"Roseggerg 44-46",
    "sg:city":"Wien",
    "sg:orig_category":"Lederwaren / Einzelhandel",
    "sg:phone":"+43 1 4802538",
    "sg:postcode":"1160",
    "sg:province":"Wien",
    "wof:name":"Monikas Ledershop",
    "wof:placetype":"venue"
},
  "geometry": {"coordinates":[16.3091812134,48.2132492065],"type":"Point"}
}