{
  "type": "Feature",
  "properties": {
    "addr:full":"Franz-Senn-Str 17 Neustift im Stubaital Tirol 6167",
    "addr:housenumber":"17",
    "addr:postcode":"6167",
    "addr:street":"Franz-Senn-Str;Tirol",
    "iso:country":"AT",
    "sg:address":"Franz-Senn-Str 17",
    "sg:city":"Neustift im Stubaital",
    "sg:classifiers":[
        {
            "category":"Travel",
            "subcategory":"Hotels & Motels",
            "type":"Entertainment"
        }
    ],
    "sg:phone":"+43 4352 262325",
    "sg:postcode":"6167",
    "sg:province":"Tirol",
    "wof:name":"Hotel Rosengarten",
    "wof:placetype":"venue"
},
  "geometry": {"coordinates":[11.2917814255,47.104511261],"type":"Point"}
}