{
  "type": "Feature",
  "properties": {
    "iso:country":"AT",
    "sg:address":"Markt 176",
    "sg:city":"St. Wolfgang im Salzkammergut",
    "sg:classifiers":[
        {
            "category":"Banks & Credit Unions",
            "subcategory":"Investment Brokerage",
            "type":"Services"
        }
    ],
    "sg:phone":"+43 6138 2229",
    "sg:postcode":"5360",
    "sg:province":"Ober\u00f6sterreich",
    "sg:tags":[
        "curtain",
        "rod",
        "accessory"
    ],
    "wof:name":"Josef Helm",
    "wof:placetype":"venue"
},
  "geometry": {"coordinates":[13.4466266632,47.7386398315],"type":"Point"}
}