{
  "type": "Feature",
  "properties": {
    "addr:full":"Karlspl 5 Wien Wien 1010",
    "addr:housenumber":"5",
    "addr:postcode":"1010",
    "addr:street":"Karlspl",
    "iso:country":"AT",
    "sg:address":"Karlspl 5",
    "sg:city":"Wien",
    "sg:orig_category":"Restaurants: Italienisch",
    "sg:phone":"+43 1 5053839",
    "sg:postcode":"1010",
    "sg:province":"Wien",
    "wof:name":"Restaurant Noodles und Co",
    "wof:placetype":"venue"
},
  "geometry": {"coordinates":[16.3723526001,48.2002296448],"type":"Point"}
}