{
  "type": "Feature",
  "properties": {
    "iso:country":"AT",
    "sg:address":"Stelzhamerpl 5",
    "sg:city":"Ried im Innkreis",
    "sg:orig_category":"Lebensmittel / Einzelhandel",
    "sg:phone":"+43 7752 702750",
    "sg:postcode":"4910",
    "sg:province":"Ober\u00f6sterreich",
    "wof:name":"Billa AG Abt Corso",
    "wof:placetype":"venue"
},
  "geometry": {"coordinates":[13.4876623154,48.2088127136],"type":"Point"}
}