{
  "type": "Feature",
  "properties": {
    "addr:full":"Schernbergstr 10 Radstadt Salzburg 5550",
    "addr:housenumber":"10",
    "addr:postcode":"5550",
    "addr:street":"Schernbergstr;Salzburg",
    "iso:country":"AT",
    "sg:address":"Schernbergstr 10",
    "sg:city":"Radstadt",
    "sg:orig_category":"Banken U Sparkassen",
    "sg:phone":"+43 4364 5277110",
    "sg:postcode":"5550",
    "sg:province":"Salzburg",
    "wof:name":"Volksbank Salzburg regGenmbH",
    "wof:placetype":"venue"
},
  "geometry": {"coordinates":[13.4642019272,47.3847694397],"type":"Point"}
}