{
  "type": "Feature",
  "properties": {
    "addr:full":"Sonnwendg 21 Wien Wien 1100",
    "addr:housenumber":"21",
    "addr:postcode":"1100",
    "addr:street":"Sonnwendg",
    "iso:country":"AT",
    "sg:address":"Sonnwendg 21",
    "sg:city":"Wien",
    "sg:orig_category":"Abfall-, Entsorgungs- U Deponietechnik",
    "sg:phone":"+43 4316 0433550",
    "sg:postcode":"1100",
    "sg:province":"Wien",
    "wof:name":"Zuma Beteiligungs GesmbH & Co Abfallstoffverwertungs KG",
    "wof:placetype":"venue"
},
  "geometry": {"coordinates":[16.3744049072,48.1782684326],"type":"Point"}
}