{
  "type": "Feature",
  "properties": {
    "addr:full":"Reinhartsdorfg 2 Schwechat Nieder\u00f6sterreich 2320",
    "addr:housenumber":"2",
    "addr:postcode":"2320",
    "addr:street":"Reinhartsdorfg;Niederoesterreich",
    "iso:country":"AT",
    "sg:address":"Reinhartsdorfg 2",
    "sg:city":"Schwechat",
    "sg:orig_category":"Bauunternehmen",
    "sg:phone":"+43 1 7068984",
    "sg:postcode":"2320",
    "sg:province":"Nieder\u00f6sterreich",
    "wof:name":"Meissl O M & Co Bau GmbH",
    "wof:placetype":"venue"
},
  "geometry": {"coordinates":[16.4553966522,48.1185722351],"type":"Point"}
}