{
  "type": "Feature",
  "properties": {
    "iso:country":"AT",
    "sg:address":"Nr 94",
    "sg:city":"Ottenthal",
    "sg:orig_category":"Volksschulen",
    "sg:phone":"+43 2554 8135",
    "sg:postcode":"2163",
    "sg:province":"Nieder\u00f6sterreich",
    "wof:name":"Volksschule",
    "wof:placetype":"venue"
},
  "geometry": {"coordinates":[16.5781784058,48.7612380981],"type":"Point"}
}