{
  "type": "Feature",
  "properties": {
    "addr:full":"Pyrkersh\u00f6henstr 11 Bad Gastein Salzburg 5640",
    "addr:housenumber":"11",
    "addr:postcode":"5640",
    "addr:street":"Pyrkershoehenstr;Salzburg",
    "iso:country":"AT",
    "sg:address":"Pyrkersh\u00f6henstr 11",
    "sg:city":"Bad Gastein",
    "sg:classifiers":[
        {
            "category":"Travel",
            "subcategory":"Hotels & Motels",
            "type":"Entertainment"
        }
    ],
    "sg:phone":"+43 4364 3433660",
    "sg:postcode":"5640",
    "sg:province":"Salzburg",
    "sg:website":"baerenhof.at",
    "wof:name":"Gesundheitszentrum Johannesbad GmbH - B\u00e4renhof am Felsenbad",
    "wof:placetype":"venue"
},
  "geometry": {"coordinates":[13.135269165,47.1120071411],"type":"Point"}
}