{
  "type": "Feature",
  "properties": {
    "addr:full":"Adamg 30 Innsbruck Tirol 6020",
    "addr:housenumber":"30",
    "addr:postcode":"6020",
    "addr:street":"Adamg;Tirol",
    "iso:country":"AT",
    "sg:address":"Adamg 30",
    "sg:city":"Innsbruck",
    "sg:orig_category":"Stoffe / Erzeugung U Gro\u00c3\u0178handel",
    "sg:phone":"+43 512 575178",
    "sg:postcode":"6020",
    "sg:province":"Tirol",
    "wof:name":"M\u00fcller Franz",
    "wof:placetype":"venue"
},
  "geometry": {"coordinates":[11.3985834122,47.2602882385],"type":"Point"}
}