{
  "type": "Feature",
  "properties": {
    "addr:full":"Niederau Sonnhangweg 5 Wildsch\u00f6nau-Niederau Tirol 6314",
    "addr:housenumber":"5",
    "addr:postcode":"6314",
    "addr:street":"Sonnhangweg;Tirol",
    "iso:country":"AT",
    "sg:address":"Niederau Sonnhangweg 5",
    "sg:city":"Wildsch\u00f6nau-Niederau",
    "sg:classifiers":[
        {
            "category":"Travel",
            "subcategory":"Hotels & Motels",
            "type":"Entertainment"
        }
    ],
    "sg:phone":"+43 4353 3983530",
    "sg:postcode":"6314",
    "sg:province":"Tirol",
    "wof:name":"Hotel Sonnschein GmbH & Co KG",
    "wof:placetype":"venue"
},
  "geometry": {"coordinates":[12.105055809,47.4490509033],"type":"Point"}
}