{
  "type": "Feature",
  "properties": {
    "addr:full":"Ledererg 1 Gallneukirchen Ober\u00f6sterreich 4210",
    "addr:housenumber":"1",
    "addr:postcode":"4210",
    "addr:street":"Ledererg;Oberoesterreich",
    "iso:country":"AT",
    "sg:address":"Ledererg 1",
    "sg:city":"Gallneukirchen",
    "sg:orig_category":"Fotografen",
    "sg:phone":"+43 7235 62376",
    "sg:postcode":"4210",
    "sg:province":"Ober\u00f6sterreich",
    "wof:name":"Fischerlehner Wolfgang",
    "wof:placetype":"venue"
},
  "geometry": {"coordinates":[14.414182663,48.3521080017],"type":"Point"}
}