{
  "type": "Feature",
  "properties": {
    "addr:full":"C Doppler-Str 1 Salzburg Salzburg 5020",
    "addr:housenumber":"1",
    "addr:postcode":"5020",
    "addr:street":"Salzburg",
    "iso:country":"AT",
    "sg:address":"C Doppler-Str 1",
    "sg:city":"Salzburg",
    "sg:orig_category":"Immobilienmakler",
    "sg:phone":"+43 662 441523",
    "sg:postcode":"5020",
    "sg:province":"Salzburg",
    "wof:name":"City-Real Immobilien M Hofer & Co KEG",
    "wof:placetype":"venue"
},
  "geometry": {"coordinates":[13.0352668762,47.8098335266],"type":"Point"}
}