{
  "type": "Feature",
  "properties": {
    "addr:full":"Pirkhof 81A St. Stefan ob Stainz Steiermark 8511",
    "addr:housenumber":"81a",
    "addr:postcode":"8511",
    "addr:street":"Pirkhof",
    "iso:country":"AT",
    "sg:address":"Pirkhof 81A",
    "sg:city":"St. Stefan ob Stainz",
    "sg:orig_category":"Bauleitung U -Betreuung",
    "sg:phone":"+43 4334 6362127",
    "sg:postcode":"8511",
    "sg:province":"Steiermark",
    "wof:name":"BM H\u00f6ller - Bauplanung u Baumanagement",
    "wof:placetype":"venue"
},
  "geometry": {"coordinates":[15.2844800949,46.9473800659],"type":"Point"}
}