{
  "type": "Feature",
  "properties": {
    "addr:full":"Ahrnbachstr 118 Kaltenbach Tirol 6272",
    "addr:housenumber":"118",
    "addr:postcode":"6272",
    "addr:street":"Kaltenbach Tirol",
    "iso:country":"AT",
    "sg:address":"Ahrnbachstr 118",
    "sg:city":"Kaltenbach",
    "sg:orig_category":"Autohandel",
    "sg:phone":"+43 5283 2465",
    "sg:postcode":"6272",
    "sg:province":"Tirol",
    "sg:website":"larl.at",
    "wof:name":"Autohaus Larl",
    "wof:placetype":"venue"
},
  "geometry": {"coordinates":[11.8988409042,47.2742118835],"type":"Point"}
}