{
  "type": "Feature",
  "properties": {
    "addr:full":"Schulg 70 Wien Wien 1180",
    "addr:housenumber":"70",
    "addr:postcode":"1180",
    "addr:street":"Schulg",
    "iso:country":"AT",
    "sg:address":"Schulg 70",
    "sg:city":"Wien",
    "sg:orig_category":"Ergotherapie",
    "sg:phone":"+43 4367 65346017",
    "sg:postcode":"1180",
    "sg:province":"Wien",
    "wof:name":"Stamm Tanja",
    "wof:placetype":"venue"
},
  "geometry": {"coordinates":[16.336894989,48.2265472412],"type":"Point"}
}