{
  "type": "Feature",
  "properties": {
    "addr:full":"Obere Hauptstr 22 Rohrendorf Nieder\u00f6sterreich 3495",
    "addr:housenumber":"22",
    "addr:postcode":"3495",
    "addr:street":"Obere Hauptstr",
    "iso:country":"AT",
    "sg:address":"Obere Hauptstr 22",
    "sg:city":"Rohrendorf",
    "sg:orig_category":"Banken U Sparkassen",
    "sg:phone":"+43 4327 3276944",
    "sg:postcode":"3495",
    "sg:province":"Nieder\u00f6sterreich",
    "wof:name":"Volksbank Krems-Zwettl AG",
    "wof:placetype":"venue"
},
  "geometry": {"coordinates":[15.6542577744,48.4192848206],"type":"Point"}
}