{
  "type": "Feature",
  "properties": {
    "iso:country":"AT",
    "sg:address":"Staldenstr 7",
    "sg:city":"Lustenau",
    "sg:orig_category":"Immobilienmakler",
    "sg:phone":"+43 5577 89230",
    "sg:postcode":"6890",
    "sg:province":"Vorarlberg",
    "wof:name":"DOMUS Immobilien - B\u00f6sch Siegfried F",
    "wof:placetype":"venue"
},
  "geometry": {"coordinates":[9.6637582779,47.4293136597],"type":"Point"}
}