{
  "type": "Feature",
  "properties": {
    "addr:full":"Grabenbauernweg 28a Salzburg Salzburg 5020",
    "addr:housenumber":"28a",
    "addr:postcode":"5020",
    "addr:street":"Grabenbauernweg;Salzburg",
    "iso:country":"AT",
    "sg:address":"Grabenbauernweg 28a",
    "sg:city":"Salzburg",
    "sg:orig_category":"Physiotherapie",
    "sg:phone":"+43 650 4602156",
    "sg:postcode":"5020",
    "sg:province":"Salzburg",
    "wof:name":"Esslmaier Ulrike Dipl-PT",
    "wof:placetype":"venue"
},
  "geometry": {"coordinates":[13.0431680679,47.8272399902],"type":"Point"}
}