{
  "type": "Feature",
  "properties": {
    "addr:full":"Jochberger Str 96 Kitzb\u00fchel Tirol 6370",
    "addr:postcode":"6370",
    "addr:street":"Str 96 Kitzbuehel Tirol",
    "iso:country":"AT",
    "sg:address":"Jochberger Str 96",
    "sg:city":"Kitzb\u00fchel",
    "sg:orig_category":"Werbeagenturen",
    "sg:phone":"+43 5356 73362",
    "sg:postcode":"6370",
    "sg:province":"Tirol",
    "wof:name":"Nothegger & Salinger GesnbR - Ges f Werbung & Marktkommunikation",
    "wof:placetype":"venue"
},
  "geometry": {"coordinates":[12.4028863907,47.4369239807],"type":"Point"}
}