{
  "type": "Feature",
  "properties": {
    "addr:full":"Ringstr 74 Krems an der Donau Nieder\u00f6sterreich 3500",
    "addr:housenumber":"74",
    "addr:postcode":"3500",
    "addr:street":"Ringstr",
    "iso:country":"AT",
    "sg:address":"Ringstr 74",
    "sg:city":"Krems an der Donau",
    "sg:orig_category":"Gastronomie- U Hoteleinrichtungen",
    "sg:phone":"+43 4327 32823810",
    "sg:postcode":"3500",
    "sg:province":"Nieder\u00f6sterreich",
    "wof:name":"Heinl Josef",
    "wof:placetype":"venue"
},
  "geometry": {"coordinates":[15.5909175873,48.4053573608],"type":"Point"}
}