{
  "type": "Feature",
  "properties": {
    "addr:full":"Nr 6 Steinakirchen am Forst Nieder\u00f6sterreich 3261",
    "addr:postcode":"3261",
    "addr:street":"Nr",
    "iso:country":"AT",
    "sg:address":"Nr 6",
    "sg:city":"Steinakirchen am Forst",
    "sg:orig_category":"Appartements / Ferienwohnungen",
    "sg:phone":"+43 4374 8871345",
    "sg:postcode":"3261",
    "sg:province":"Nieder\u00f6sterreich",
    "wof:name":"Ferienheim Rosenteufl Josef Eppensteiner",
    "wof:placetype":"venue"
},
  "geometry": {"coordinates":[15.0643281937,48.077457428],"type":"Point"}
}