{
  "type": "Feature",
  "properties": {
    "iso:country":"AT",
    "sg:address":"Jakoministr 26",
    "sg:city":"Graz",
    "sg:orig_category":"Friseure U Frisiersalons",
    "sg:phone":"+43 4331 6830123",
    "sg:postcode":"8010",
    "sg:province":"Steiermark",
    "wof:name":"Anton Ili'c Haarmode",
    "wof:placetype":"venue"
},
  "geometry": {"coordinates":[15.4422512054,47.0651664734],"type":"Point"}
}