{
  "type": "Feature",
  "properties": {
    "iso:country":"AT",
    "sg:address":"Gumpendorfer Str 18",
    "sg:city":"Wien",
    "sg:orig_category":"Galerien",
    "sg:phone":"+43 1 5875052",
    "sg:postcode":"1060",
    "sg:province":"Wien",
    "wof:name":"Galerie Knoll",
    "wof:placetype":"venue"
},
  "geometry": {"coordinates":[16.3603382111,48.1997756958],"type":"Point"}
}