{
  "type": "Feature",
  "properties": {
    "iso:country":"AT",
    "sg:address":"Teichstr 18",
    "sg:city":"Rosental an der Kainach",
    "sg:orig_category":"Physiotherapie",
    "sg:phone":"+43 4331 4227027",
    "sg:postcode":"8582",
    "sg:province":"Steiermark",
    "wof:name":"Schmid-Kolb Sandra Dipl-PT",
    "wof:placetype":"venue"
},
  "geometry": {"coordinates":[15.1100301743,47.0435256958],"type":"Point"}
}