{
  "type": "Feature",
  "properties": {
    "addr:full":"Grestner Str 12 Wieselburg an der Erlauf Nieder\u00f6sterreich 3250",
    "addr:postcode":"3250",
    "addr:street":"Str 12",
    "iso:country":"AT",
    "sg:address":"Grestner Str 12",
    "sg:city":"Wieselburg an der Erlauf",
    "sg:orig_category":"Maler, Anstreicher U Lackierer",
    "sg:phone":"+43 4374 16522920",
    "sg:postcode":"3250",
    "sg:province":"Nieder\u00f6sterreich",
    "wof:name":"Schiefer Johann - ADLER Farbenmeister Johann",
    "wof:placetype":"venue"
},
  "geometry": {"coordinates":[15.1361341476,48.1298904419],"type":"Point"}
}