{
  "type": "Feature",
  "properties": {
    "addr:full":"Bucheng 172 Wien Wien 1100",
    "addr:housenumber":"172",
    "addr:postcode":"1100",
    "addr:street":"Bucheng",
    "iso:country":"AT",
    "sg:address":"Bucheng 172",
    "sg:city":"Wien",
    "sg:orig_category":"Werbegrafik- U Grafik-Design",
    "sg:phone":"+43 4316 0352930",
    "sg:postcode":"1100",
    "sg:province":"Wien",
    "wof:name":"Kubra Werbegrafik GmbH",
    "wof:placetype":"venue"
},
  "geometry": {"coordinates":[16.3581371307,48.1767539978],"type":"Point"}
}