{
  "type": "Feature",
  "properties": {
    "addr:full":"Wiener Str 181 Linz Ober\u00f6sterreich 4020",
    "addr:housenumber":"181",
    "addr:postcode":"4020",
    "iso:country":"AT",
    "sg:address":"Wiener Str 181",
    "sg:city":"Linz",
    "sg:orig_category":"Berufsschulen",
    "sg:phone":"+43 732 343431",
    "sg:postcode":"4020",
    "sg:province":"Ober\u00f6sterreich",
    "wof:name":"Berufsschule 9 f Maler Fotograf grafische Gewerbe Glaser und Bodenleger",
    "wof:placetype":"venue"
},
  "geometry": {"coordinates":[14.3124923706,48.2767448425],"type":"Point"}
}