{
  "type": "Feature",
  "properties": {
    "addr:full":"Jakominipl 15 Graz Steiermark 8010",
    "addr:housenumber":"15",
    "addr:postcode":"8010",
    "addr:street":"Jakominipl",
    "iso:country":"AT",
    "sg:address":"Jakominipl 15",
    "sg:city":"Graz",
    "sg:orig_category":"Psychotherapie",
    "sg:phone":"+43 664 3017688",
    "sg:postcode":"8010",
    "sg:province":"Steiermark",
    "wof:name":"Nigitz-Arch Michael",
    "wof:placetype":"venue"
},
  "geometry": {"coordinates":[15.4431352615,47.0672492981],"type":"Point"}
}