{
  "type": "Feature",
  "properties": {
    "addr:full":"Unterjoch 38 Bad Goisern Ober\u00f6sterreich 4822",
    "addr:housenumber":"38",
    "addr:postcode":"4822",
    "addr:street":"Unterjoch",
    "iso:country":"AT",
    "sg:address":"Unterjoch 38",
    "sg:city":"Bad Goisern",
    "sg:classifiers":[
        {
            "category":"Travel",
            "subcategory":"Hotels & Motels",
            "type":"Entertainment"
        }
    ],
    "sg:phone":"+43 6135 72850",
    "sg:postcode":"4822",
    "sg:province":"Ober\u00f6sterreich",
    "wof:name":"Alpenhotel Dachstein Hotelbetriebs GesmbH",
    "wof:placetype":"venue"
},
  "geometry": {"coordinates":[13.5983295441,47.6414489746],"type":"Point"}
}