{
  "type": "Feature",
  "properties": {
    "addr:full":"Dorfstr 30 Kolsass Tirol 6114",
    "addr:housenumber":"30",
    "addr:postcode":"6114",
    "addr:street":"Dorfstr;Tirol",
    "iso:country":"AT",
    "sg:address":"Dorfstr 30",
    "sg:city":"Kolsass",
    "sg:orig_category":"Blumeneinzelhandel",
    "sg:phone":"+43 5224 67574",
    "sg:postcode":"6114",
    "sg:province":"Tirol",
    "wof:name":"Blumen Crisma",
    "wof:placetype":"venue"
},
  "geometry": {"coordinates":[11.6411333084,47.3036651611],"type":"Point"}
}