{
  "type": "Feature",
  "properties": {
    "iso:country":"AT",
    "sg:address":"Dorfstr 30",
    "sg:city":"Kolsass",
    "sg:orig_category":"Blumeneinzelhandel",
    "sg:phone":"+43 5224 67574",
    "sg:postcode":"6114",
    "sg:province":"Tirol",
    "wof:name":"Blumen Crisma",
    "wof:placetype":"venue"
},
  "geometry": {"coordinates":[11.6411333084,47.3036651611],"type":"Point"}
}