{
  "type": "Feature",
  "properties": {
    "iso:country":"AT",
    "sg:address":"Leonhardstr 107",
    "sg:city":"Graz",
    "sg:orig_category":"Fenster",
    "sg:phone":"+43 316 371961",
    "sg:postcode":"8010",
    "sg:province":"Steiermark",
    "wof:name":"Winkler Johann",
    "wof:placetype":"venue"
},
  "geometry": {"coordinates":[15.4597520828,47.0759124756],"type":"Point"}
}