{
  "type": "Feature",
  "properties": {
    "addr:full":"Fritz-Sedlazeck-Pl 3 Petzenkirchen Nieder\u00f6sterreich 3252",
    "addr:housenumber":"3",
    "addr:postcode":"3252",
    "addr:street":"Fritz-Sedlazeck-Pl",
    "iso:country":"AT",
    "sg:address":"Fritz-Sedlazeck-Pl 3",
    "sg:city":"Petzenkirchen",
    "sg:orig_category":"Unterhaltungselektronik / Reparatur",
    "sg:phone":"+43 7416 538430",
    "sg:postcode":"3252",
    "sg:province":"Nieder\u00f6sterreich",
    "wof:name":"Voglhuber GmbH",
    "wof:placetype":"venue"
},
  "geometry": {"coordinates":[15.152964592,48.1433868408],"type":"Point"}
}