{
  "type": "Feature",
  "properties": {
    "addr:full":"Otto-Gl\u00f6ckel-Str 10a Gr\u00f6dig Salzburg 5082",
    "addr:housenumber":"10a",
    "addr:postcode":"5082",
    "addr:street":"Otto-Gloeckel-Str;Salzburg",
    "iso:country":"AT",
    "sg:address":"Otto-Gl\u00f6ckel-Str 10a",
    "sg:city":"Gr\u00f6dig",
    "sg:orig_category":"Ingenieurkonsulenten / Zivilingenieure",
    "sg:phone":"+43 6246 745350",
    "sg:postcode":"5082",
    "sg:province":"Salzburg",
    "wof:name":"Mlekusch Alexander Dipl-Ing",
    "wof:placetype":"venue"
},
  "geometry": {"coordinates":[-76.2684555054,37.4373283386],"type":"Point"}
}