{
  "type": "Feature",
  "properties": {
    "iso:country":"AT",
    "sg:address":"Dorfstr 109",
    "sg:city":"Rattenberg",
    "sg:orig_category":"Autoverwertung",
    "sg:phone":"+43 4365 02838973",
    "sg:postcode":"6240",
    "sg:province":"Tirol",
    "wof:name":"Autowrack- u Schrottverwertung Kern",
    "wof:placetype":"venue"
},
  "geometry": {"coordinates":[11.9041719437,47.4463653564],"type":"Point"}
}