{
  "type": "Feature",
  "properties": {
    "addr:full":"Zetscheg 18 Wien Wien 1230",
    "addr:housenumber":"18",
    "addr:postcode":"1230",
    "addr:street":"Zetscheg",
    "iso:country":"AT",
    "sg:address":"Zetscheg 18",
    "sg:city":"Wien",
    "sg:orig_category":"Elektroinstallationsunternehmen",
    "sg:phone":"+43 1 6677789",
    "sg:postcode":"1230",
    "sg:province":"Wien",
    "wof:name":"Elnet Elektroinstallationen und Netzwerkverkabelung GesmbH",
    "wof:placetype":"venue"
},
  "geometry": {"coordinates":[16.3326854706,48.1427459717],"type":"Point"}
}