{
  "type": "Feature",
  "properties": {
    "addr:full":"Nr 2 Haibach ob der Donau Ober\u00f6sterreich 4083",
    "addr:housenumber":"2",
    "addr:postcode":"4083",
    "addr:street":"Nr",
    "iso:country":"AT",
    "sg:address":"Nr 2",
    "sg:city":"Haibach ob der Donau",
    "sg:classifiers":[
        {
            "category":"Travel",
            "subcategory":"Hotels & Motels",
            "type":"Entertainment"
        }
    ],
    "sg:phone":"+43 7279 8212",
    "sg:postcode":"4083",
    "sg:province":"Ober\u00f6sterreich",
    "wof:name":"Hotel Donauschlinge",
    "wof:placetype":"venue"
},
  "geometry": {"coordinates":[166.9221496582,-0.5282999873],"type":"Point"}
}