{
  "type": "Feature",
  "properties": {
    "iso:country":"AT",
    "sg:address":"Sauberg 7",
    "sg:city":"Langenlois",
    "sg:orig_category":"Heurigen / Buschenschank",
    "sg:phone":"+43 2734 4447",
    "sg:postcode":"3550",
    "sg:province":"Nieder\u00f6sterreich",
    "wof:name":"Steinschaden Familienweingut und Heuriger",
    "wof:placetype":"venue"
},
  "geometry": {"coordinates":[15.6692352295,48.4681892395],"type":"Point"}
}