{
  "type": "Feature",
  "properties": {
    "addr:full":"Hauptstr 117 Nagelberg Nieder\u00f6sterreich 3871",
    "addr:housenumber":"117",
    "addr:postcode":"3871",
    "addr:street":"Hauptstr;Niederoesterreich",
    "iso:country":"AT",
    "sg:address":"Hauptstr 117",
    "sg:city":"Nagelberg",
    "sg:orig_category":"Genossenschaften",
    "sg:phone":"+43 2859 6442",
    "sg:postcode":"3871",
    "sg:province":"Nieder\u00f6sterreich",
    "wof:name":"Erste Burgenl\u00e4ndische Gemeinn\u00fctzige Siedlungs regGenmbH",
    "wof:placetype":"venue"
},
  "geometry": {"coordinates":[14.99376297,48.8390808105],"type":"Point"}
}