{
  "type": "Feature",
  "properties": {
    "addr:full":"Pitze 168 S\u00f6lden Tirol 6450",
    "addr:housenumber":"168",
    "addr:postcode":"6450",
    "addr:street":"Pitze;Tirol",
    "iso:country":"AT",
    "sg:address":"Pitze 168",
    "sg:city":"S\u00f6lden",
    "sg:orig_category":"Schneidereien",
    "sg:phone":"+43 5254 3893",
    "sg:postcode":"6450",
    "sg:province":"Tirol",
    "wof:name":"Schneiderei Miftari Sabine",
    "wof:placetype":"venue"
},
  "geometry": {"coordinates":[11.0113515854,46.9527320862],"type":"Point"}
}