{
  "type": "Feature",
  "properties": {
    "addr:full":"Kircheng 8 Sitzenberg-Reidling Nieder\u00f6sterreich 3454",
    "addr:housenumber":"8",
    "addr:postcode":"3454",
    "addr:street":"Kircheng",
    "iso:country":"AT",
    "sg:address":"Kircheng 8",
    "sg:city":"Sitzenberg-Reidling",
    "sg:orig_category":"Volksschulen",
    "sg:phone":"+43 2276 2243",
    "sg:postcode":"3454",
    "sg:province":"Nieder\u00f6sterreich",
    "wof:name":"Volksschule",
    "wof:placetype":"venue"
},
  "geometry": {"coordinates":[15.8198728561,48.3188018799],"type":"Point"}
}