{
  "type": "Feature",
  "properties": {
    "addr:full":"Wienzeile 11 Purkersdorf Nieder\u00f6sterreich 3002",
    "addr:housenumber":"11",
    "addr:postcode":"3002",
    "addr:street":"Wienzeile",
    "iso:country":"AT",
    "sg:address":"Wienzeile 11",
    "sg:city":"Purkersdorf",
    "sg:orig_category":"Partyservice",
    "sg:phone":"+43 676 5519130",
    "sg:postcode":"3002",
    "sg:province":"Nieder\u00f6sterreich",
    "wof:name":"Tischlein deck dich",
    "wof:placetype":"venue"
},
  "geometry": {"coordinates":[16.1842346191,48.2070045471],"type":"Point"}
}