{
  "type": "Feature",
  "properties": {
    "iso:country":"AT",
    "sg:address":"Nr 2",
    "sg:city":"Fehring",
    "sg:orig_category":"Feuerwehren",
    "sg:phone":"+43 3155 40061",
    "sg:postcode":"8350",
    "sg:province":"Steiermark",
    "wof:name":"Freiwillige Feuerwehr Johnsdorf",
    "wof:placetype":"venue"
},
  "geometry": {"coordinates":[16.066734314,46.9451332092],"type":"Point"}
}