{
  "type": "Feature",
  "properties": {
    "iso:country":"AT",
    "sg:address":"Innerberg 10",
    "sg:city":"Weerberg",
    "sg:orig_category":"Volksschulen",
    "sg:phone":"+43 5224 68814",
    "sg:postcode":"6133",
    "sg:province":"Tirol",
    "wof:name":"Volksschule Innerweerberg",
    "wof:placetype":"venue"
},
  "geometry": {"coordinates":[11.6709756851,47.2785606384],"type":"Point"}
}