{
  "type": "Feature",
  "properties": {
    "iso:country":"AT",
    "sg:address":"Konrad-Laib-Str 10",
    "sg:city":"Salzburg",
    "sg:orig_category":"Studentenheime",
    "sg:phone":"+43 662 20630",
    "sg:postcode":"5020",
    "sg:province":"Salzburg",
    "wof:name":"Haus Paracelsus",
    "wof:placetype":"venue"
},
  "geometry": {"coordinates":[13.0620155334,47.7875709534],"type":"Point"}
}