{
  "type": "Feature",
  "properties": {
    "addr:full":"Puelacherweg 25a Telfs Tirol 6410",
    "addr:housenumber":"25a",
    "addr:postcode":"6410",
    "addr:street":"Puelacherweg;Tirol",
    "iso:country":"AT",
    "sg:address":"Puelacherweg 25a",
    "sg:city":"Telfs",
    "sg:orig_category":"Erdarbeiten",
    "sg:phone":"+43 5262 65007",
    "sg:postcode":"6410",
    "sg:province":"Tirol",
    "wof:name":"Tabelander Hanspeter GmbH & Co KEG",
    "wof:placetype":"venue"
},
  "geometry": {"coordinates":[11.0712032318,47.3155555725],"type":"Point"}
}