{
  "type": "Feature",
  "properties": {
    "addr:full":"Hauptstr 50 Wien Wien 1140",
    "addr:housenumber":"50",
    "addr:postcode":"1140",
    "addr:street":"Hauptstr",
    "iso:country":"AT",
    "sg:address":"Hauptstr 50",
    "sg:city":"Wien",
    "sg:orig_category":"Tabaktrafiken",
    "sg:phone":"+43 1 9791209",
    "sg:postcode":"1140",
    "sg:province":"Wien",
    "wof:name":"Schneider Evelyn",
    "wof:placetype":"venue"
},
  "geometry": {"coordinates":[16.2260913849,48.2084121704],"type":"Point"}
}