{
  "type": "Feature",
  "properties": {
    "addr:full":"Kaiserebersdorferstr 163 Wien Wien 1110",
    "addr:housenumber":"163",
    "addr:postcode":"1110",
    "iso:country":"AT",
    "sg:address":"Kaiserebersdorferstr 163",
    "sg:city":"Wien",
    "sg:orig_category":"Autoreparatur",
    "sg:phone":"+43 4317 672391",
    "sg:postcode":"1110",
    "sg:province":"Wien",
    "wof:name":"Weber Anton",
    "wof:placetype":"venue"
},
  "geometry": {"coordinates":[16.4484844208,48.1610946655],"type":"Point"}
}