{
  "type": "Feature",
  "properties": {
    "addr:full":"Weyrerstr. 190 Waidhofen an der Ybbs Nieder\u00f6sterreich 3340",
    "addr:housenumber":"190",
    "addr:postcode":"3340",
    "iso:country":"AT",
    "sg:address":"Weyrerstr. 190",
    "sg:city":"Waidhofen an der Ybbs",
    "sg:classifiers":[
        {
            "category":"Professional",
            "subcategory":"Printing & Photocopies",
            "type":"Services"
        }
    ],
    "sg:phone":"+43 4374 4255535",
    "sg:postcode":"3340",
    "sg:province":"Nieder\u00f6sterreich",
    "wof:name":"STUMMERDRUCK GMBH",
    "wof:placetype":"venue"
},
  "geometry": {"coordinates":[14.7542009354,47.9064102173],"type":"Point"}
}