{
  "type": "Feature",
  "properties": {
    "addr:full":"Plainstr 69/1 Salzburg Salzburg 5020",
    "addr:housenumber":"69 / 1",
    "addr:postcode":"5020",
    "addr:street":"Plainstr;Salzburg",
    "iso:country":"AT",
    "sg:address":"Plainstr 69/1",
    "sg:city":"Salzburg",
    "sg:classifiers":[
        {
            "category":"Landmark",
            "subcategory":"Square",
            "type":"Public Place"
        }
    ],
    "sg:phone":"+43 4366 24501590",
    "sg:postcode":"5020",
    "sg:province":"Salzburg",
    "sg:tags":[
        "geometer"
    ],
    "sg:website":"vermessung-sturm.at",
    "wof:name":"Sturm Christoph Dipl-Ing",
    "wof:placetype":"venue"
},
  "geometry": {"coordinates":[13.040345192,47.8165817261],"type":"Point"}
}