{
  "type": "Feature",
  "properties": {
    "addr:full":"Dauphinestrasse 48 Linz Ober\u00f6sterreich 4030",
    "addr:housenumber":"48",
    "addr:postcode":"4030",
    "addr:street":"Dauphinestrasse",
    "iso:country":"AT",
    "sg:address":"Dauphinestrasse 48",
    "sg:city":"Linz",
    "sg:classifiers":[
        {
            "category":"Organizations",
            "subcategory":"Non-profit Organization",
            "type":"Services"
        }
    ],
    "sg:phone":"+43 732 318931",
    "sg:postcode":"4030",
    "sg:province":"Ober\u00f6sterreich",
    "sg:tags":[
        "alarm",
        "system"
    ],
    "wof:name":"Werner Sch\u00f6nbeck",
    "wof:placetype":"venue"
},
  "geometry": {"coordinates":[14.3137197495,48.2530899048],"type":"Point"}
}