{
  "type": "Feature",
  "properties": {
    "iso:country":"AT",
    "sg:address":"Walgaustra\u00dfe 34",
    "sg:city":"Klaus-Weiler",
    "sg:orig_category":"Dienstleistungen, Fotografie, Grafik U Design",
    "sg:phone":"+43 5523 58555",
    "sg:postcode":"6833",
    "sg:province":"Vorarlberg",
    "sg:website":"http://www.creativ-corner.com",
    "wof:name":"Woblistin Werbung",
    "wof:placetype":"venue"
},
  "geometry": {"coordinates":[9.6528644562,47.3032798767],"type":"Point"}
}