{
  "type": "Feature",
  "properties": {
    "addr:full":"Schulstr 110-114 Langenzersdorf Nieder\u00f6sterreich 2103",
    "addr:postcode":"110-114;2103",
    "addr:street":"Niederoesterreich",
    "iso:country":"AT",
    "sg:address":"Schulstr 110-114",
    "sg:city":"Langenzersdorf",
    "sg:orig_category":"Schwarzdeckereien",
    "sg:phone":"+43 2244 37000",
    "sg:postcode":"2103",
    "sg:province":"Nieder\u00f6sterreich",
    "wof:name":"WIBA Schwarzdeckungen Isolierungen Bauspenglerei KG",
    "wof:placetype":"venue"
},
  "geometry": {"coordinates":[16.3518180847,48.3117904663],"type":"Point"}
}