{
  "type": "Feature",
  "properties": {
    "iso:country":"AT",
    "sg:address":"E\u00dflinger Hauptstr 84-86",
    "sg:city":"Wien",
    "sg:orig_category":"Fassaden",
    "sg:phone":"+43 4317 743081",
    "sg:postcode":"1220",
    "sg:province":"Wien",
    "wof:name":"AGF Armierungen - Ger\u00fcstbau - Fassaden Bau u Handels GmbH",
    "wof:placetype":"venue"
},
  "geometry": {"coordinates":[16.5240783691,48.2145118713],"type":"Point"}
}