{
  "type": "Feature",
  "properties": {
    "addr:full":"St. Martiner Str 104 Villach K\u00e4rnten 9500",
    "addr:housenumber":"104",
    "addr:postcode":"9500",
    "addr:street":"St.;Kaernten",
    "iso:country":"AT",
    "sg:address":"St. Martiner Str 104",
    "sg:city":"Villach",
    "sg:orig_category":"Motoren",
    "sg:phone":"+43 4242 554670",
    "sg:postcode":"9500",
    "sg:province":"K\u00e4rnten",
    "wof:name":"Madritsch KG",
    "wof:placetype":"venue"
},
  "geometry": {"coordinates":[13.8241500854,46.6235809326],"type":"Point"}
}