{
  "type": "Feature",
  "properties": {
    "iso:country":"AT",
    "sg:address":"Heilstollenstr 9",
    "sg:city":"B\u00f6ckstein",
    "sg:classifiers":[
        {
            "category":"Building & Trades",
            "subcategory":"Construction",
            "type":"Services"
        }
    ],
    "sg:phone":"+43 4364 3433140",
    "sg:postcode":"5645",
    "sg:province":"Salzburg",
    "sg:tags":[
        "aggregate"
    ],
    "wof:name":"Kraftwerk B\u00f6ckstein - Salzburg AG f Energie Verkehr u Telekommunikation",
    "wof:placetype":"venue"
},
  "geometry": {"coordinates":[13.0988368988,47.0812683105],"type":"Point"}
}