{
  "type": "Feature",
  "properties": {
    "iso:country":"AT",
    "sg:address":"Sportweg 71",
    "sg:city":"St. Georgen an der Gusen",
    "sg:orig_category":"Freizeitangebote U -Einrichtungen",
    "sg:phone":"+43 4372 3764242",
    "sg:postcode":"4222",
    "sg:province":"Ober\u00f6sterreich",
    "wof:name":"Jugendtreff Luftenberg",
    "wof:placetype":"venue"
},
  "geometry": {"coordinates":[14.4232139587,48.2734718323],"type":"Point"}
}