{
  "type": "Feature",
  "properties": {
    "addr:full":"Nr 38 Liesing K\u00e4rnten 9653",
    "addr:housenumber":"38",
    "addr:postcode":"9653",
    "addr:street":"Nr;Kaernten",
    "iso:country":"AT",
    "sg:address":"Nr 38",
    "sg:city":"Liesing",
    "sg:orig_category":"Tischlereien",
    "sg:phone":"+43 4716 2180",
    "sg:postcode":"9653",
    "sg:province":"K\u00e4rnten",
    "wof:name":"Unter\u00fcberbacher Herwig",
    "wof:placetype":"venue"
},
  "geometry": {"coordinates":[12.8082408905,46.694065094],"type":"Point"}
}