{
  "type": "Feature",
  "properties": {
    "addr:full":"Hauptstr 26 Felixdorf Nieder\u00f6sterreich 2603",
    "addr:housenumber":"26",
    "addr:postcode":"2603",
    "addr:street":"Hauptstr",
    "iso:country":"AT",
    "sg:address":"Hauptstr 26",
    "sg:city":"Felixdorf",
    "sg:orig_category":"Lebensmittel / Einzelhandel",
    "sg:phone":"+43 2628 67910",
    "sg:postcode":"2603",
    "sg:province":"Nieder\u00f6sterreich",
    "wof:name":"SPAR \u00f6sterreichische Warenhandels-AG",
    "wof:placetype":"venue"
},
  "geometry": {"coordinates":[16.2423439026,47.8822288513],"type":"Point"}
}