{
  "type": "Feature",
  "properties": {
    "iso:country":"AT",
    "sg:address":"Josef-Pirchl-Str 26a",
    "sg:city":"Kitzb\u00fchel",
    "sg:orig_category":"Installationsunternehmen",
    "sg:phone":"+43 5356 72972",
    "sg:postcode":"6370",
    "sg:province":"Tirol",
    "sg:website":"www.hoefinger.at",
    "wof:name":"H\u00f6finger Thomas",
    "wof:placetype":"venue"
},
  "geometry": {"coordinates":[12.3901348114,47.4506912231],"type":"Point"}
}