{
  "type": "Feature",
  "properties": {
    "addr:full":"Europastr. 5  Wels Ober\u00f6sterreich 4600",
    "addr:housenumber":"5",
    "addr:postcode":"4600",
    "addr:street":"Europastr.;Oberoesterreich",
    "iso:country":"AT",
    "sg:address":"Europastr. 5 ",
    "sg:city":"Wels",
    "sg:classifiers":[
        {
            "category":"Manufacturing",
            "subcategory":"Motor Vehicles & Parts",
            "type":"Manufacturing & Wholesale Goods"
        }
    ],
    "sg:phone":"+43 4372 4247161",
    "sg:postcode":"4600",
    "sg:province":"Ober\u00f6sterreich",
    "sg:tags":[
        "engine"
    ],
    "wof:name":"VIKTOR TSCHIPANI",
    "wof:placetype":"venue"
},
  "geometry": {"coordinates":[13.9976959229,48.1516990662],"type":"Point"}
}