{
  "type": "Feature",
  "properties": {
    "iso:country":"AT",
    "sg:address":"Bahnhofstr 4",
    "sg:city":"Schruns",
    "sg:orig_category":"Hornwaren",
    "sg:phone":"+43 5556 75076",
    "sg:postcode":"6780",
    "sg:province":"Vorarlberg",
    "sg:website":"www.8ung.at/hirschhorn",
    "wof:name":"Hirschhorn-St\u00f6bli - Fleisch Robert",
    "wof:placetype":"venue"
},
  "geometry": {"coordinates":[9.9194154739,47.0797958374],"type":"Point"}
}