{
  "type": "Feature",
  "properties": {
    "iso:country":"AT",
    "sg:address":"Schulgasse 11",
    "sg:city":"Wien",
    "sg:classifiers":[
        {
            "category":"Building & Trades",
            "subcategory":"Plumbing",
            "type":"Services"
        }
    ],
    "sg:phone":"+43 1 40688150",
    "sg:postcode":"1180",
    "sg:province":"Wien",
    "sg:tags":[
        "supraregional",
        "gas"
    ],
    "sg:website":"sternath.at",
    "wof:name":"Sternath GmbH",
    "wof:placetype":"venue"
},
  "geometry": {"coordinates":[16.3468322754,48.2246360779],"type":"Point"}
}