{
  "type": "Feature",
  "properties": {
    "iso:country":"AT",
    "sg:address":"Hauptstr 90",
    "sg:city":"Schleinbach",
    "sg:orig_category":"Blumeneinzelhandel",
    "sg:phone":"+43 2245 89200",
    "sg:postcode":"2123",
    "sg:province":"Nieder\u00f6sterreich",
    "wof:name":"Melkes Anna",
    "wof:placetype":"venue"
},
  "geometry": {"coordinates":[16.4884815216,48.4443283081],"type":"Point"}
}