{
  "type": "Feature",
  "properties": {
    "addr:full":"Mitterwald 10 Oberpullendorf Burgenland 7350",
    "addr:housenumber":"10",
    "addr:postcode":"7350",
    "addr:street":"Mitterwald",
    "iso:country":"AT",
    "sg:address":"Mitterwald 10",
    "sg:city":"Oberpullendorf",
    "sg:orig_category":"Reinigungsservice",
    "sg:phone":"+43 2612 43811",
    "sg:postcode":"7350",
    "sg:province":"Burgenland",
    "wof:name":"Fraunschiel Beate",
    "wof:placetype":"venue"
},
  "geometry": {"coordinates":[16.5051822662,47.5112075806],"type":"Point"}
}