{
  "type": "Feature",
  "properties": {
    "addr:full":"Rennweg 7A Innsbruck Tirol 6020",
    "addr:housenumber":"7a",
    "addr:postcode":"6020",
    "addr:street":"Rennweg;Tirol",
    "iso:country":"AT",
    "sg:address":"Rennweg 7A",
    "sg:city":"Innsbruck",
    "sg:classifiers":[
        {
            "category":"Professional",
            "subcategory":"Management & Consulting",
            "type":"Services"
        }
    ],
    "sg:phone":"+43 512 583234",
    "sg:postcode":"6020",
    "sg:province":"Tirol",
    "wof:name":"M + W Zander Facility Management GmbH",
    "wof:placetype":"venue"
},
  "geometry": {"coordinates":[11.3983974457,47.2760353088],"type":"Point"}
}