{
  "type": "Feature",
  "properties": {
    "addr:full":"Gudrunstr 160 Wien Wien 1100",
    "addr:housenumber":"160",
    "addr:postcode":"1100",
    "iso:country":"AT",
    "sg:address":"Gudrunstr 160",
    "sg:city":"Wien",
    "sg:orig_category":"Stempel",
    "sg:phone":"+43 1 6048755",
    "sg:postcode":"1100",
    "sg:province":"Wien",
    "wof:name":"PRINTSHOP City-Copy-Service",
    "wof:placetype":"venue"
},
  "geometry": {"coordinates":[16.367685318,48.1788444519],"type":"Point"}
}