{
  "type": "Feature",
  "properties": {
    "addr:full":"Pyhrnstr 71 Micheldorf in Ober\u00f6sterreich Ober\u00f6sterreich 4563",
    "addr:housenumber":"71",
    "addr:postcode":"4563",
    "addr:street":"Pyhrnstr",
    "iso:country":"AT",
    "sg:address":"Pyhrnstr 71",
    "sg:city":"Micheldorf in Ober\u00f6sterreich",
    "sg:orig_category":"Bierdepots",
    "sg:phone":"+43 7582 63095",
    "sg:postcode":"4563",
    "sg:province":"Ober\u00f6sterreich",
    "wof:name":"Bruckmayr GmbH - Brau Union Verkaufsdepot",
    "wof:placetype":"venue"
},
  "geometry": {"coordinates":[14.1431617737,47.8685874939],"type":"Point"}
}