{
  "type": "Feature",
  "properties": {
    "iso:country":"AT",
    "sg:address":"Nr 129",
    "sg:city":"Hohe Wand-Stollhof",
    "sg:orig_category":"Volksschulen",
    "sg:phone":"+43 4326 3888213",
    "sg:postcode":"2724",
    "sg:province":"Nieder\u00f6sterreich",
    "wof:name":"Volksschule",
    "wof:placetype":"venue"
},
  "geometry": {"coordinates":[16.0538883209,47.8195228577],"type":"Point"}
}