{
  "type": "Feature",
  "properties": {
    "addr:full":"Nestroystrasse 20 Marchtrenk Ober\u00f6sterreich 4614",
    "addr:housenumber":"20",
    "addr:postcode":"4614",
    "addr:street":"Nestroystrasse",
    "iso:country":"AT",
    "sg:address":"Nestroystrasse 20",
    "sg:city":"Marchtrenk",
    "sg:classifiers":[
        {
            "category":"Structure",
            "subcategory":"Office Building",
            "type":"Public Place"
        }
    ],
    "sg:phone":"+43 7243 58397",
    "sg:postcode":"4614",
    "sg:province":"Ober\u00f6sterreich",
    "sg:tags":[
        "facade",
        "energy",
        "light-optimized"
    ],
    "wof:name":"Gerhard Mittermayer",
    "wof:placetype":"venue"
},
  "geometry": {"coordinates":[14.1225261688,48.1947021484],"type":"Point"}
}