{
  "type": "Feature",
  "properties": {
    "addr:full":"Paschallern 12 Grieskirchen Ober\u00f6sterreich 4710",
    "addr:housenumber":"12",
    "addr:postcode":"4710",
    "addr:street":"Paschallern",
    "iso:country":"AT",
    "sg:address":"Paschallern 12",
    "sg:city":"Grieskirchen",
    "sg:orig_category":"Webdesign",
    "sg:phone":"+43 664 4318244",
    "sg:postcode":"4710",
    "sg:province":"Ober\u00f6sterreich",
    "wof:name":"Zahrhuber Andreas",
    "wof:placetype":"venue"
},
  "geometry": {"coordinates":[13.8010587692,48.2211875916],"type":"Point"}
}