{
  "type": "Feature",
  "properties": {
    "addr:full":"Glockeng 5 Wien Wien 1020",
    "addr:housenumber":"5",
    "addr:postcode":"1020",
    "addr:street":"Glockeng",
    "iso:country":"AT",
    "sg:address":"Glockeng 5",
    "sg:city":"Wien",
    "sg:orig_category":"Geschenkartikel",
    "sg:phone":"+43 1 2163978",
    "sg:postcode":"1020",
    "sg:province":"Wien",
    "wof:name":"SMS HandelsgesmbH",
    "wof:placetype":"venue"
},
  "geometry": {"coordinates":[16.3815383911,48.2177581787],"type":"Point"}
}