{
  "type": "Feature",
  "properties": {
    "addr:full":"Kalvarienbergstr 73 Graz Steiermark 8020",
    "addr:housenumber":"73",
    "addr:postcode":"8020",
    "addr:street":"Kalvarienbergstr",
    "iso:country":"AT",
    "sg:address":"Kalvarienbergstr 73",
    "sg:city":"Graz",
    "sg:orig_category":"Lebensmittel / Einzelhandel",
    "sg:phone":"+43 4331 6685977",
    "sg:postcode":"8020",
    "sg:province":"Steiermark",
    "wof:name":"Hofer KG",
    "wof:placetype":"venue"
},
  "geometry": {"coordinates":[15.4196443558,47.0865821838],"type":"Point"}
}