{
  "type": "Feature",
  "properties": {
    "addr:full":"Jahnstr 11 F\u00fcrstenfeld Steiermark 8280",
    "addr:housenumber":"11",
    "addr:postcode":"8280",
    "addr:street":"Jahnstr",
    "iso:country":"AT",
    "sg:address":"Jahnstr 11",
    "sg:city":"F\u00fcrstenfeld",
    "sg:orig_category":"Elektronische Bauelemente U Bauteile",
    "sg:phone":"+43 4333 82554100",
    "sg:postcode":"8280",
    "sg:province":"Steiermark",
    "wof:name":"TridonicAtco GmbH & Co KG",
    "wof:placetype":"venue"
},
  "geometry": {"coordinates":[16.0883255005,47.0374526978],"type":"Point"}
}