{
  "type": "Feature",
  "properties": {
    "addr:full":"Bahnhofstr. 1 Gmunden Ober\u00f6sterreich 4810",
    "addr:housenumber":"1",
    "addr:postcode":"4810",
    "addr:street":"Bahnhofstr.;Oberoesterreich",
    "iso:country":"AT",
    "sg:address":"Bahnhofstr. 1",
    "sg:city":"Gmunden",
    "sg:classifiers":[
        {
            "category":"Banks & Credit Unions",
            "subcategory":"Financial Services",
            "type":"Services"
        }
    ],
    "sg:phone":"+43 4376 1273955",
    "sg:postcode":"4810",
    "sg:province":"Ober\u00f6sterreich",
    "sg:tags":[
        "banking",
        "finance",
        "insurance"
    ],
    "wof:name":"ALLIANZ ELEMENTAR VERSICHERUNGS AG",
    "wof:placetype":"venue"
},
  "geometry": {"coordinates":[13.7974405289,47.919342041],"type":"Point"}
}