{
  "type": "Feature",
  "properties": {
    "iso:country":"AT",
    "sg:address":"Sturzgasse 16",
    "sg:city":"Graz",
    "sg:classifiers":[
        {
            "category":"Manufacturing",
            "subcategory":"Metals",
            "type":"Manufacturing & Wholesale Goods"
        }
    ],
    "sg:phone":"+43 316 2952430",
    "sg:postcode":"8020",
    "sg:province":"Steiermark",
    "sg:tags":[
        "alloy",
        "construction",
        "lightweight"
    ],
    "wof:name":"Stahlbau Gregorcic GmbH & Co KG",
    "wof:placetype":"venue"
},
  "geometry": {"coordinates":[15.4369668961,47.0455322266],"type":"Point"}
}