{
  "type": "Feature",
  "properties": {
    "addr:full":"\u00e4gidipl 3 Stegersbach Burgenland 7551",
    "addr:housenumber":"3",
    "addr:postcode":"7551",
    "addr:street":"Aegidipl",
    "iso:country":"AT",
    "sg:address":"\u00e4gidipl 3",
    "sg:city":"Stegersbach",
    "sg:orig_category":"Friseure U Frisiersalons",
    "sg:phone":"+43 4333 2652293",
    "sg:postcode":"7551",
    "sg:province":"Burgenland",
    "wof:name":"Kranz Friseur",
    "wof:placetype":"venue"
},
  "geometry": {"coordinates":[16.1669101715,47.1609344482],"type":"Point"}
}