{
  "type": "Feature",
  "properties": {
    "iso:country":"AT",
    "sg:address":"Peter-Rosegger-Str",
    "sg:city":"Ried im Innkreis",
    "sg:orig_category":"Kinderbetreuung",
    "sg:phone":"+43 7752 901506",
    "sg:postcode":"4910",
    "sg:province":"Ober\u00f6sterreich",
    "wof:name":"Kindergarten d Stadtgemeinde Ried",
    "wof:placetype":"venue"
},
  "geometry": {"coordinates":[13.4911746979,48.2065048218],"type":"Point"}
}