{
  "type": "Feature",
  "properties": {
    "addr:full":"Obere Teichstr 42a Graz Steiermark 8010",
    "addr:housenumber":"42a",
    "addr:postcode":"8010",
    "addr:street":"Obere Teichstr",
    "iso:country":"AT",
    "sg:address":"Obere Teichstr 42a",
    "sg:city":"Graz",
    "sg:orig_category":"Webdesign",
    "sg:phone":"+43 676 6032972",
    "sg:postcode":"8010",
    "sg:province":"Steiermark",
    "wof:name":"Leuchtturm-Design",
    "wof:placetype":"venue"
},
  "geometry": {"coordinates":[15.4762420654,47.0697860718],"type":"Point"}
}