{
  "type": "Feature",
  "properties": {
    "addr:full":"Bachg 11-13 Wolkersdorf im Weinviertel Nieder\u00f6sterreich 2120",
    "addr:housenumber":"11-13",
    "addr:postcode":"2120",
    "iso:country":"AT",
    "sg:address":"Bachg 11-13",
    "sg:city":"Wolkersdorf im Weinviertel",
    "sg:orig_category":"Immobilienmakler",
    "sg:phone":"+43 4322 455522",
    "sg:postcode":"2120",
    "sg:province":"Nieder\u00f6sterreich",
    "sg:website":"wvc.at",
    "wof:name":"WeinViertelConsulting",
    "wof:placetype":"venue"
},
  "geometry": {"coordinates":[16.5177707672,48.3828392029],"type":"Point"}
}