{
  "type": "Feature",
  "properties": {
    "addr:full":"K\u00fchau 24 Frohnleiten Steiermark 8130",
    "addr:housenumber":"24",
    "addr:postcode":"8130",
    "addr:street":"Kuehau",
    "iso:country":"AT",
    "sg:address":"K\u00fchau 24",
    "sg:city":"Frohnleiten",
    "sg:orig_category":"Bauunternehmen",
    "sg:phone":"+43 4331 264288",
    "sg:postcode":"8130",
    "sg:province":"Steiermark",
    "wof:name":"Pr\u00fcgger Bau GesmbH",
    "wof:placetype":"venue"
},
  "geometry": {"coordinates":[15.3268537521,47.271068573],"type":"Point"}
}