{
  "type": "Feature",
  "properties": {
    "addr:full":"Hauptstr 1 Rottenmann Steiermark 8786",
    "addr:housenumber":"1",
    "addr:postcode":"8786",
    "addr:street":"Hauptstr",
    "iso:country":"AT",
    "sg:address":"Hauptstr 1",
    "sg:city":"Rottenmann",
    "sg:orig_category":"Tabaktrafiken",
    "sg:phone":"+43 3614 20405",
    "sg:postcode":"8786",
    "sg:province":"Steiermark",
    "wof:name":"Fritz Wolfgang",
    "wof:placetype":"venue"
},
  "geometry": {"coordinates":[14.3581018448,47.525138855],"type":"Point"}
}