{
  "type": "Feature",
  "properties": {
    "iso:country":"AT",
    "sg:address":"Hauptstr 25",
    "sg:city":"St. Paul im Lavanttal",
    "sg:orig_category":"Fotoapparate U -Artikel / Einzelhandel",
    "sg:phone":"+43 4343 572068",
    "sg:postcode":"9470",
    "sg:province":"K\u00e4rnten",
    "wof:name":"Winter-Photo",
    "wof:placetype":"venue"
},
  "geometry": {"coordinates":[14.8693227768,46.7008895874],"type":"Point"}
}