{
  "type": "Feature",
  "properties": {
    "addr:full":"Hauptstr 20 Wagna Steiermark 8435",
    "addr:housenumber":"20",
    "addr:postcode":"8435",
    "addr:street":"Hauptstr",
    "iso:country":"AT",
    "sg:address":"Hauptstr 20",
    "sg:city":"Wagna",
    "sg:orig_category":"Tanzcafes",
    "sg:phone":"+43 3452 83534",
    "sg:postcode":"8435",
    "sg:province":"Steiermark",
    "wof:name":"Tanzcafe Franz",
    "wof:placetype":"venue"
},
  "geometry": {"coordinates":[15.5587749481,46.7678184509],"type":"Point"}
}