{
  "type": "Feature",
  "properties": {
    "iso:country":"AT",
    "sg:address":"Morsbacher Str 15",
    "sg:city":"Kufstein",
    "sg:orig_category":"Industrievertretungen",
    "sg:phone":"+43 5372 62930",
    "sg:postcode":"6330",
    "sg:province":"Tirol",
    "wof:name":"GKI-Georg Kantor Industrievertretungen",
    "wof:placetype":"venue"
},
  "geometry": {"coordinates":[12.1590499878,47.5871696472],"type":"Point"}
}