{
  "type": "Feature",
  "properties": {
    "addr:full":"Leberstr.29 Wien Wien 1110",
    "addr:postcode":"1110",
    "addr:street":"Leberstr.29",
    "iso:country":"AT",
    "sg:address":"Leberstr.29",
    "sg:city":"Wien",
    "sg:classifiers":[
        {
            "category":"Shopping",
            "subcategory":"Computers & Home Electronics",
            "type":"Retail Goods"
        }
    ],
    "sg:phone":"+43 4326 2452438",
    "sg:postcode":"1110",
    "sg:province":"Wien",
    "sg:tags":[
        "electronic",
        "electrical",
        "equipment"
    ],
    "wof:name":"KEYMILE AG",
    "wof:placetype":"venue"
},
  "geometry": {"coordinates":[16.4034290314,48.1843147278],"type":"Point"}
}