{
  "type": "Feature",
  "properties": {
    "addr:full":"Akazienhofstr 140 Klagenfurt K\u00e4rnten 9020",
    "addr:housenumber":"140",
    "addr:postcode":"9020",
    "addr:street":"Kaernten",
    "iso:country":"AT",
    "sg:address":"Akazienhofstr 140",
    "sg:city":"Klagenfurt",
    "sg:orig_category":"Automaten",
    "sg:phone":"+43 463 42368",
    "sg:postcode":"9020",
    "sg:province":"K\u00e4rnten",
    "wof:name":"Schnut Hans",
    "wof:placetype":"venue"
},
  "geometry": {"coordinates":[14.3032484055,46.6404876709],"type":"Point"}
}