{
  "type": "Feature",
  "properties": {
    "addr:full":"Reitwiesen 2 Unterrabnitz Burgenland 7371",
    "addr:housenumber":"2",
    "addr:postcode":"7371",
    "addr:street":"Reitwiesen",
    "iso:country":"AT",
    "sg:address":"Reitwiesen 2",
    "sg:city":"Unterrabnitz",
    "sg:orig_category":"Non-Classified Establishments",
    "sg:phone":"+43 2616 8708",
    "sg:postcode":"7371",
    "sg:province":"Burgenland",
    "wof:name":"Pfarramt",
    "wof:placetype":"venue"
},
  "geometry": {"coordinates":[16.4192657471,47.4496078491],"type":"Point"}
}