{
  "type": "Feature",
  "properties": {
    "iso:country":"AT",
    "sg:address":"Gf\u00f6hler Str 62",
    "sg:city":"Lengenfeld",
    "sg:orig_category":"Weine / Einzelhandel",
    "sg:phone":"+43 2719 2615",
    "sg:postcode":"3552",
    "sg:province":"Nieder\u00f6sterreich",
    "wof:name":"Weinbau Fam Seiler",
    "wof:placetype":"venue"
},
  "geometry": {"coordinates":[15.5871019363,48.4749221802],"type":"Point"}
}