{
  "type": "Feature",
  "properties": {
    "addr:full":"Salzstrasse 9 Zirl Tirol 6170",
    "addr:housenumber":"9",
    "addr:postcode":"6170",
    "addr:street":"Salzstrasse;Tirol",
    "iso:country":"AT",
    "sg:address":"Salzstrasse 9",
    "sg:city":"Zirl",
    "sg:classifiers":[
        {
            "category":"Transit Center",
            "subcategory":"Freight",
            "type":"Transportation"
        }
    ],
    "sg:phone":"+43 5238 55550",
    "sg:postcode":"6170",
    "sg:province":"Tirol",
    "sg:tags":[
        "forwarding",
        "agency"
    ],
    "wof:name":"Richler Transport- u. Handelsges.m.b.H.",
    "wof:placetype":"venue"
},
  "geometry": {"coordinates":[11.230266571,47.2626304626],"type":"Point"}
}