{
  "type": "Feature",
  "properties": {
    "addr:full":"Unterwald 640 S\u00f6lden Tirol 6450",
    "addr:housenumber":"640",
    "addr:postcode":"6450",
    "addr:street":"Unterwald;Tirol",
    "iso:country":"AT",
    "sg:address":"Unterwald 640",
    "sg:city":"S\u00f6lden",
    "sg:orig_category":"Appartements / Ferienwohnungen",
    "sg:phone":"+43 4352 542332",
    "sg:postcode":"6450",
    "sg:province":"Tirol",
    "wof:name":"Almhof",
    "wof:placetype":"venue"
},
  "geometry": {"coordinates":[11.0057096481,46.9612388611],"type":"Point"}
}