{
  "type": "Feature",
  "properties": {
    "iso:country":"AT",
    "sg:address":"Hauptplatz 46",
    "sg:city":"Kittsee",
    "sg:classifiers":[
        {
            "category":"Wholesale",
            "subcategory":"Construction Materials",
            "type":"Manufacturing & Wholesale Goods"
        }
    ],
    "sg:phone":"+43 2143 30058",
    "sg:postcode":"2421",
    "sg:province":"Burgenland",
    "sg:tags":[
        "bridge",
        "temporary",
        "materials",
        "crown"
    ],
    "wof:name":"M\u00fcllner & Molnar OEG",
    "wof:placetype":"venue"
},
  "geometry": {"coordinates":[17.066028595,48.0900917053],"type":"Point"}
}