{
  "type": "Feature",
  "properties": {
    "addr:full":"Kirchstetterng 10 Wien Wien 1160",
    "addr:housenumber":"10",
    "addr:postcode":"1160",
    "addr:street":"Kirchstetterng",
    "iso:country":"AT",
    "sg:address":"Kirchstetterng 10",
    "sg:city":"Wien",
    "sg:orig_category":"Gastronomie- U Hotelbedarf",
    "sg:phone":"+43 1 4932025",
    "sg:postcode":"1160",
    "sg:province":"Wien",
    "wof:name":"Pauscher Michael",
    "wof:placetype":"venue"
},
  "geometry": {"coordinates":[16.3317947388,48.2052688599],"type":"Point"}
}