{
  "type": "Feature",
  "properties": {
    "addr:full":"Aubergstr 42 Linz Ober\u00f6sterreich 4040",
    "addr:housenumber":"42",
    "addr:postcode":"4040",
    "addr:street":"Aubergstr",
    "iso:country":"AT",
    "sg:address":"Aubergstr 42",
    "sg:city":"Linz",
    "sg:orig_category":"Selbsthilfegruppen",
    "sg:phone":"+43 820 820320",
    "sg:postcode":"4040",
    "sg:province":"Ober\u00f6sterreich",
    "wof:name":"ILCA - Independent Living Center Austria - \u00d6sterr Bund Hilfe zur Selbsthilfe",
    "wof:placetype":"venue"
},
  "geometry": {"coordinates":[14.2756385803,48.314781189],"type":"Point"}
}