{
  "type": "Feature",
  "properties": {
    "iso:country":"AT",
    "sg:address":"Corvinusring 3-5",
    "sg:city":"Wiener Neustadt",
    "sg:orig_category":"Banken U Sparkassen",
    "sg:phone":"+43 4326 2223357",
    "sg:postcode":"2700",
    "sg:province":"Nieder\u00f6sterreich",
    "wof:name":"Bankomat d Nieder\u00f6sterreichische Landesbank - Hypothekenbank AG",
    "wof:placetype":"venue"
},
  "geometry": {"coordinates":[16.2471294403,47.8160667419],"type":"Point"}
}