{
  "type": "Feature",
  "properties": {
    "addr:full":"Aigen 73 Aigen-Voglhub Salzburg 5351",
    "addr:housenumber":"73;5351",
    "addr:street":"Aigen",
    "iso:country":"AT",
    "sg:address":"Aigen 73",
    "sg:city":"Aigen-Voglhub",
    "sg:orig_category":"Tischlereien",
    "sg:phone":"+43 6137 217501",
    "sg:postcode":"5351",
    "sg:province":"Salzburg",
    "wof:name":"Fusban Tobias Ing",
    "wof:placetype":"venue"
},
  "geometry": {"coordinates":[13.5139799118,47.7144966125],"type":"Point"}
}