{
  "type": "Feature",
  "properties": {
    "addr:full":"Dinghoferstr 21 Linz Ober\u00f6sterreich 4020",
    "addr:housenumber":"21",
    "addr:postcode":"4020",
    "addr:street":"Dinghoferstr",
    "iso:country":"AT",
    "sg:address":"Dinghoferstr 21",
    "sg:city":"Linz",
    "sg:orig_category":"Beteiligungen U Finanzierungen",
    "sg:phone":"+43 4373 27778000",
    "sg:postcode":"4020",
    "sg:province":"Ober\u00f6sterreich",
    "sg:website":"kgg-ubg.at",
    "wof:name":"Ober\u00f6sterreichische KreditgarantiegesmbH",
    "wof:placetype":"venue"
},
  "geometry": {"coordinates":[14.2967443466,48.301525116],"type":"Point"}
}