{
  "type": "Feature",
  "properties": {
    "iso:country":"AT",
    "sg:address":"Dorfstr 3",
    "sg:city":"Nestelbach",
    "sg:orig_category":"Behinderungen / Leben Mit Behinderungen",
    "sg:phone":"+43 3133 29430",
    "sg:postcode":"8302",
    "sg:province":"Steiermark",
    "wof:name":"Alpha Nova BetriebsgesmbH",
    "wof:placetype":"venue"
},
  "geometry": {"coordinates":[15.6100635529,47.0608825684],"type":"Point"}
}