{
  "type": "Feature",
  "properties": {
    "addr:full":"Seestr 25 Seeboden K\u00e4rnten 9871",
    "addr:housenumber":"25",
    "addr:postcode":"9871",
    "addr:street":"Seestr;Kaernten",
    "iso:country":"AT",
    "sg:address":"Seestr 25",
    "sg:city":"Seeboden",
    "sg:classifiers":[
        {
            "category":"Travel",
            "subcategory":"Hotels & Motels",
            "type":"Entertainment"
        }
    ],
    "sg:phone":"+43 4347 6281169",
    "sg:postcode":"9871",
    "sg:province":"K\u00e4rnten",
    "wof:name":"Familienzimmer Haus Linder",
    "wof:placetype":"venue"
},
  "geometry": {"coordinates":[13.5216608047,46.8175392151],"type":"Point"}
}