{
  "type": "Feature",
  "properties": {
    "addr:full":"Nr 47 Stockern Nieder\u00f6sterreich 3744",
    "addr:postcode":"3744",
    "addr:street":"Nr;Stockern",
    "iso:country":"AT",
    "sg:address":"Nr 47",
    "sg:city":"Stockern",
    "sg:classifiers":[
        {
            "category":"Restaurant",
            "type":"Food & Drink"
        }
    ],
    "sg:phone":"+43 2983 2365",
    "sg:postcode":"3744",
    "sg:province":"Nieder\u00f6sterreich",
    "wof:name":"Schlo\u00dfheuriger",
    "wof:placetype":"venue"
},
  "geometry": {"coordinates":[15.75299263,48.664478302],"type":"Point"}
}