{
  "type": "Feature",
  "properties": {
    "addr:full":"Ignaz-Mayer-Str 16 Linz Ober\u00f6sterreich 4020",
    "addr:housenumber":"16",
    "addr:postcode":"4020",
    "addr:street":"Ignaz-Mayer-Str",
    "iso:country":"AT",
    "sg:address":"Ignaz-Mayer-Str 16",
    "sg:city":"Linz",
    "sg:orig_category":"Abfall-, Entsorgungs- U Deponietechnik",
    "sg:phone":"+43 4373 2669908",
    "sg:postcode":"4020",
    "sg:province":"Ober\u00f6sterreich",
    "wof:name":"Brantner Walter GesmbH",
    "wof:placetype":"venue"
},
  "geometry": {"coordinates":[14.3255872726,48.309387207],"type":"Point"}
}