{
  "type": "Feature",
  "properties": {
    "addr:full":"Amselg 7 Prinzersdorf Nieder\u00f6sterreich 3385",
    "addr:housenumber":"7",
    "addr:postcode":"3385",
    "addr:street":"Amselg",
    "iso:country":"AT",
    "sg:address":"Amselg 7",
    "sg:city":"Prinzersdorf",
    "sg:orig_category":"Bilderrahmen",
    "sg:phone":"+43 4327 498015",
    "sg:postcode":"3385",
    "sg:province":"Nieder\u00f6sterreich",
    "wof:name":"D\u00fcr Franz",
    "wof:placetype":"venue"
},
  "geometry": {"coordinates":[15.5544900894,48.1992416382],"type":"Point"}
}