{
  "type": "Feature",
  "properties": {
    "iso:country":"AT",
    "sg:address":"Mariazeller Str 11",
    "sg:city":"Purgstall an der Erlauf",
    "sg:orig_category":"Bekleidung / Einzelhandel",
    "sg:phone":"+43 4374 892290",
    "sg:postcode":"3251",
    "sg:province":"Nieder\u00f6sterreich",
    "wof:name":"H\u00f6dl Marion",
    "wof:placetype":"venue"
},
  "geometry": {"coordinates":[15.1344432831,48.0564002991],"type":"Point"}
}