{
  "type": "Feature",
  "properties": {
    "addr:full":"Tauernstr 11 Bad Hofgastein Salzburg 5630",
    "addr:housenumber":"11",
    "addr:postcode":"5630",
    "addr:street":"Tauernstr;Salzburg",
    "iso:country":"AT",
    "sg:address":"Tauernstr 11",
    "sg:city":"Bad Hofgastein",
    "sg:orig_category":"Friseure U Frisiersalons",
    "sg:phone":"+43 4364 328471",
    "sg:postcode":"5630",
    "sg:province":"Salzburg",
    "wof:name":"Friseursalon Reinhold u Rosmarie Reiter",
    "wof:placetype":"venue"
},
  "geometry": {"coordinates":[13.1034927368,47.1716918945],"type":"Point"}
}