{
  "type": "Feature",
  "properties": {
    "addr:full":"Freist\u00e4dter Str 340 Linz Ober\u00f6sterreich 4040",
    "addr:housenumber":"340",
    "addr:postcode":"4040",
    "addr:street":"Str",
    "iso:country":"AT",
    "sg:address":"Freist\u00e4dter Str 340",
    "sg:city":"Linz",
    "sg:orig_category":"Tankstellen",
    "sg:phone":"+43 732 251857",
    "sg:postcode":"4040",
    "sg:province":"Ober\u00f6sterreich",
    "wof:name":"JET Tankstelle",
    "wof:placetype":"venue"
},
  "geometry": {"coordinates":[14.3214130402,48.3286094666],"type":"Point"}
}