{
  "type": "Feature",
  "properties": {
    "addr:full":"Hernalser Hauptstr 78 Wien Wien 1170",
    "addr:housenumber":"78",
    "addr:postcode":"1170",
    "addr:street":"Hernalser Hauptstr",
    "iso:country":"AT",
    "sg:address":"Hernalser Hauptstr 78",
    "sg:city":"Wien",
    "sg:orig_category":"Telekommunikation",
    "sg:phone":"+43 1 4859184",
    "sg:postcode":"1170",
    "sg:province":"Wien",
    "wof:name":"Ben-Zie Aedeward - Handy Time",
    "wof:placetype":"venue"
},
  "geometry": {"coordinates":[16.3306007385,48.2180747986],"type":"Point"}
}