{
  "type": "Feature",
  "properties": {
    "addr:full":"Murg 25 Judenburg Steiermark 8750",
    "addr:housenumber":"25",
    "addr:postcode":"8750",
    "addr:street":"Murg",
    "iso:country":"AT",
    "sg:address":"Murg 25",
    "sg:city":"Judenburg",
    "sg:orig_category":"Restaurants: Chinesisch",
    "sg:phone":"+43 3572 84970",
    "sg:postcode":"8750",
    "sg:province":"Steiermark",
    "wof:name":"China-Restaurant Chinatown",
    "wof:placetype":"venue"
},
  "geometry": {"coordinates":[14.6675271988,47.1696624756],"type":"Point"}
}