{
  "type": "Feature",
  "properties": {
    "addr:full":"Katrinstr 5 Bad Ischl Ober\u00f6sterreich 4820",
    "addr:housenumber":"5",
    "addr:postcode":"4820",
    "addr:street":"Katrinstr",
    "iso:country":"AT",
    "sg:address":"Katrinstr 5",
    "sg:city":"Bad Ischl",
    "sg:classifiers":[
        {
            "category":"Taxi",
            "type":"Transportation"
        }
    ],
    "sg:phone":"+43 4367 65139690",
    "sg:postcode":"4820",
    "sg:province":"Ober\u00f6sterreich",
    "sg:tags":[
        "personentransporte",
        "u"
    ],
    "wof:name":"Heller Clemens",
    "wof:placetype":"venue"
},
  "geometry": {"coordinates":[13.6084413528,47.6998901367],"type":"Point"}
}