{
  "type": "Feature",
  "properties": {
    "addr:full":"Ennsweg 120 Schladming Steiermark 8970",
    "addr:housenumber":"120",
    "addr:postcode":"8970",
    "addr:street":"Ennsweg",
    "iso:country":"AT",
    "sg:address":"Ennsweg 120",
    "sg:city":"Schladming",
    "sg:orig_category":"Steinmetzbetriebe",
    "sg:phone":"+43 4336 8723188",
    "sg:postcode":"8970",
    "sg:province":"Steiermark",
    "wof:name":"Moosbrugger Johann KG",
    "wof:placetype":"venue"
},
  "geometry": {"coordinates":[13.6401290894,47.387802124],"type":"Point"}
}