{
  "type": "Feature",
  "properties": {
    "addr:full":"Adnet Salzburg 5421",
    "addr:housenumber":"5421",
    "iso:country":"AT",
    "sg:city":"Adnet",
    "sg:orig_category":"Fibre Glass Doors",
    "sg:phone":"+43 6245 74697",
    "sg:postcode":"5421",
    "sg:province":"Salzburg",
    "wof:name":"Andreas Putz",
    "wof:placetype":"venue"
},
  "geometry": {"coordinates":[13.1305770874,47.696975708],"type":"Point"}
}