{
  "type": "Feature",
  "properties": {
    "iso:country":"AT",
    "sg:address":"Nr 34a",
    "sg:city":"Gries im Sellrain",
    "sg:orig_category":"Erdarbeiten",
    "sg:phone":"+43 5236 221",
    "sg:postcode":"6182",
    "sg:province":"Tirol",
    "wof:name":"Gebhart Rainer",
    "wof:placetype":"venue"
},
  "geometry": {"coordinates":[11.100684166,47.2032012939],"type":"Point"}
}