{
  "type": "Feature",
  "properties": {
    "addr:full":"Weinberggasse 16, B\u00fcro B Wien Wien 1190",
    "addr:housenumber":"16;b",
    "addr:postcode":"1190",
    "addr:street":"Weinberggasse",
    "iso:country":"AT",
    "sg:address":"Weinberggasse 16, B\u00fcro B",
    "sg:city":"Wien",
    "sg:orig_category":"Reproduction, Electronic, Of Artworks",
    "sg:phone":"+43 1 3286870",
    "sg:postcode":"1190",
    "sg:province":"Wien",
    "wof:name":"DIE OFFICIN Reproanstalt Ges.m.b.H.",
    "wof:placetype":"venue"
},
  "geometry": {"coordinates":[16.3493022919,48.2389793396],"type":"Point"}
}