{
  "type": "Feature",
  "properties": {
    "iso:country":"AT",
    "sg:address":"Ro\u00dfbachstr 2",
    "sg:city":"Kirnberg an der Mank",
    "sg:orig_category":"Erdarbeiten",
    "sg:phone":"+43 676 3289299",
    "sg:postcode":"3241",
    "sg:province":"Nieder\u00f6sterreich",
    "wof:name":"Daxb\u00f6ck Karl",
    "wof:placetype":"venue"
},
  "geometry": {"coordinates":[15.3274621964,48.071472168],"type":"Point"}
}