{
  "type": "Feature",
  "properties": {
    "addr:full":"Lagerstr 2a Bruck an der Leitha Nieder\u00f6sterreich 2460",
    "addr:housenumber":"2a",
    "addr:postcode":"2460",
    "addr:street":"Lagerstr",
    "iso:country":"AT",
    "sg:address":"Lagerstr 2a",
    "sg:city":"Bruck an der Leitha",
    "sg:orig_category":"Banken U Sparkassen",
    "sg:phone":"+43 4350 50536700",
    "sg:postcode":"2460",
    "sg:province":"Nieder\u00f6sterreich",
    "wof:name":"Bank Austria Creditanstalt AG",
    "wof:placetype":"venue"
},
  "geometry": {"coordinates":[16.7770442963,48.0187492371],"type":"Point"}
}