{
  "type": "Feature",
  "properties": {
    "addr:full":"Hochthronstr 14 Bischofshofen Salzburg 5500",
    "addr:housenumber":"14",
    "addr:postcode":"5500",
    "addr:street":"Hochthronstr;Salzburg",
    "iso:country":"AT",
    "sg:address":"Hochthronstr 14",
    "sg:city":"Bischofshofen",
    "sg:orig_category":"Telekommunikation",
    "sg:phone":"+43 5 9059632240",
    "sg:postcode":"5500",
    "sg:province":"Salzburg",
    "wof:name":"Telekom Austria Shop",
    "wof:placetype":"venue"
},
  "geometry": {"coordinates":[13.2184524536,47.4223976135],"type":"Point"}
}