{
  "type": "Feature",
  "properties": {
    "addr:full":"Lasserstr 24 Salzburg Salzburg 5020",
    "addr:housenumber":"24",
    "addr:postcode":"5020",
    "addr:street":"Lasserstr;Salzburg",
    "iso:country":"AT",
    "sg:address":"Lasserstr 24",
    "sg:city":"Salzburg",
    "sg:orig_category":"Psychologen",
    "sg:phone":"+43 4366 2872646",
    "sg:postcode":"5020",
    "sg:province":"Salzburg",
    "wof:name":"Brugger Helga Mag phil",
    "wof:placetype":"venue"
},
  "geometry": {"coordinates":[13.0483026505,47.80834198],"type":"Point"}
}