{
  "type": "Feature",
  "properties": {
    "addr:full":"Wollsberg 28 Steinerkirchen an der Traun Ober\u00f6sterreich 4652",
    "addr:housenumber":"28",
    "addr:postcode":"4652",
    "addr:street":"Wollsberg",
    "iso:country":"AT",
    "sg:address":"Wollsberg 28",
    "sg:city":"Steinerkirchen an der Traun",
    "sg:classifiers":[
        {
            "category":"Retail",
            "subcategory":"Animal Services",
            "type":"Services"
        }
    ],
    "sg:phone":"+43 4372 4153940",
    "sg:postcode":"4652",
    "sg:province":"Ober\u00f6sterreich",
    "sg:tags":[
        "breeding"
    ],
    "wof:name":"ADOLF NIEDERHUMER GMBH",
    "wof:placetype":"venue"
},
  "geometry": {"coordinates":[14.0168180466,48.0773696899],"type":"Point"}
}