{
  "type": "Feature",
  "properties": {
    "iso:country":"AT",
    "sg:address":"Seeblickweg 17",
    "sg:city":"Bodensdorf",
    "sg:classifiers":[
        {
            "category":"Travel",
            "subcategory":"Hotels & Motels",
            "type":"Entertainment"
        }
    ],
    "sg:phone":"+43 4243 24840",
    "sg:postcode":"9551",
    "sg:province":"K\u00e4rnten",
    "wof:name":"Hotel Ossiacher See",
    "wof:placetype":"venue"
},
  "geometry": {"coordinates":[13.9681482315,46.686088562],"type":"Point"}
}