{
  "type": "Feature",
  "properties": {
    "addr:full":"Linzer Str 8 Haag Nieder\u00f6sterreich 3350",
    "addr:housenumber":"8",
    "addr:postcode":"3350",
    "addr:street":"Linzer Str",
    "iso:country":"AT",
    "sg:address":"Linzer Str 8",
    "sg:city":"Haag",
    "sg:orig_category":"Installationsunternehmen",
    "sg:phone":"+43 7434 422360",
    "sg:postcode":"3350",
    "sg:province":"Nieder\u00f6sterreich",
    "wof:name":"Tojner Martin Ing",
    "wof:placetype":"venue"
},
  "geometry": {"coordinates":[14.5646810532,48.1116485596],"type":"Point"}
}