{
  "type": "Feature",
  "properties": {
    "addr:full":"Schanzpl 5 Hallein Salzburg 5400",
    "addr:housenumber":"5",
    "addr:postcode":"5400",
    "addr:street":"Schanzpl;Salzburg",
    "iso:country":"AT",
    "sg:address":"Schanzpl 5",
    "sg:city":"Hallein",
    "sg:classifiers":[
        {
            "category":"Professional",
            "subcategory":"Computer Services",
            "type":"Services"
        }
    ],
    "sg:phone":"+43 6245 81524",
    "sg:postcode":"5400",
    "sg:province":"Salzburg",
    "sg:tags":[
        "software"
    ],
    "wof:name":"Marekovic Miroslav",
    "wof:placetype":"venue"
},
  "geometry": {"coordinates":[13.095459938,47.6816940308],"type":"Point"}
}