{
  "type": "Feature",
  "properties": {
    "addr:full":"Viktoriag. 19  Wien Wien 1150",
    "addr:housenumber":"19",
    "addr:postcode":"1150",
    "addr:street":"Viktoriag.",
    "iso:country":"AT",
    "sg:address":"Viktoriag. 19 ",
    "sg:city":"Wien",
    "sg:classifiers":[
        {
            "category":"Shopping",
            "subcategory":"Computers & Home Electronics",
            "type":"Retail Goods"
        }
    ],
    "sg:phone":"+43 4318 942553",
    "sg:postcode":"1150",
    "sg:province":"Wien",
    "sg:tags":[
        "electronic",
        "electrical",
        "equipment"
    ],
    "wof:name":"PNEUMAT REIFEN- U. BATTERIEN- HANDEL U. SERVICE GESMBH",
    "wof:placetype":"venue"
},
  "geometry": {"coordinates":[16.3303165436,48.1925544739],"type":"Point"}
}