{
  "type": "Feature",
  "properties": {
    "addr:full":"Alte Landstr 4 Wilhering Ober\u00f6sterreich 4073",
    "addr:housenumber":"4",
    "addr:postcode":"4073",
    "addr:street":"Alte Landstr",
    "iso:country":"AT",
    "sg:address":"Alte Landstr 4",
    "sg:city":"Wilhering",
    "sg:orig_category":"Abfallentsorgung U -Verwertung",
    "sg:phone":"+43 4372 2620049",
    "sg:postcode":"4073",
    "sg:province":"Ober\u00f6sterreich",
    "wof:name":"Altstoffsammelzentrum",
    "wof:placetype":"venue"
},
  "geometry": {"coordinates":[14.1732883453,48.3155975342],"type":"Point"}
}