{
  "type": "Feature",
  "properties": {
    "addr:full":"Kirchg 37 Feldkirchen in K\u00e4rnten K\u00e4rnten 9560",
    "addr:housenumber":"37",
    "addr:postcode":"9560",
    "addr:street":"Kirchg;Kaernten",
    "iso:country":"AT",
    "sg:address":"Kirchg 37",
    "sg:city":"Feldkirchen in K\u00e4rnten",
    "sg:orig_category":"Nachhilfe U Lernbetreuung",
    "sg:phone":"+43 4342 7638048",
    "sg:postcode":"9560",
    "sg:province":"K\u00e4rnten",
    "wof:name":"B\u00dcM Feldkirchen in K\u00e4rnten - Betreuen \u00dcben Miteinander",
    "wof:placetype":"venue"
},
  "geometry": {"coordinates":[14.0951356888,46.7268638611],"type":"Point"}
}