{
  "type": "Feature",
  "properties": {
    "addr:full":"Wallackstrasse 8 Bruck an der Gro\u00dfglocknerstra\u00dfe Salzburg 5671",
    "addr:housenumber":"8",
    "addr:postcode":"5671",
    "addr:street":"Wallackstrasse;Grossglocknerstrasse Salzburg",
    "iso:country":"AT",
    "sg:address":"Wallackstrasse 8",
    "sg:city":"Bruck an der Gro\u00dfglocknerstra\u00dfe",
    "sg:classifiers":[
        {
            "category":"Home & Garden",
            "subcategory":"Household Appliances",
            "type":"Retail Goods"
        }
    ],
    "sg:phone":"+43 6545 7268",
    "sg:postcode":"5671",
    "sg:province":"Salzburg",
    "sg:tags":[
        "electric"
    ],
    "sg:website":"elektro-gassner.at",
    "wof:name":"Elektro Franz Gassner",
    "wof:placetype":"venue"
},
  "geometry": {"coordinates":[12.8209438324,47.2856636047],"type":"Point"}
}