{
  "type": "Feature",
  "properties": {
    "iso:country":"AT",
    "sg:address":"Pollheimerstr 2",
    "sg:city":"Wels",
    "sg:orig_category":"Immobilienmakler",
    "sg:phone":"+43 7242 56374",
    "sg:postcode":"4600",
    "sg:province":"Ober\u00f6sterreich",
    "wof:name":"Reitbauer Jutta Dr GesmbH",
    "wof:placetype":"venue"
},
  "geometry": {"coordinates":[14.0226783752,48.1549072266],"type":"Point"}
}