{
  "type": "Feature",
  "properties": {
    "iso:country":"AT",
    "sg:address":"Nr 50",
    "sg:city":"Weikendorf",
    "sg:orig_category":"Datenverarbeitung",
    "sg:phone":"+43 664 4413191",
    "sg:postcode":"2253",
    "sg:province":"Nieder\u00f6sterreich",
    "wof:name":"Gattinger Gerald",
    "wof:placetype":"venue"
},
  "geometry": {"coordinates":[16.7665348053,48.3444709778],"type":"Point"}
}