{
  "type": "Feature",
  "properties": {
    "iso:country":"AT",
    "sg:address":"Bahnhofstr 17",
    "sg:city":"Heidenreichstein",
    "sg:orig_category":"\u00c3\u201erzte / F Allgemeinmedizin",
    "sg:phone":"+43 4328 6252080",
    "sg:postcode":"3860",
    "sg:province":"Nieder\u00f6sterreich",
    "wof:name":"Hammer Stefan Dr",
    "wof:placetype":"venue"
},
  "geometry": {"coordinates":[15.11759758,48.8636322021],"type":"Point"}
}