{
  "type": "Feature",
  "properties": {
    "addr:full":"Bahnhofstr 9 Lambach Ober\u00f6sterreich 4650",
    "addr:housenumber":"9",
    "addr:postcode":"4650",
    "addr:street":"Bahnhofstr",
    "iso:country":"AT",
    "sg:address":"Bahnhofstr 9",
    "sg:city":"Lambach",
    "sg:orig_category":"Personalbereitstellung",
    "sg:phone":"+43 7245 20860",
    "sg:postcode":"4650",
    "sg:province":"Ober\u00f6sterreich",
    "wof:name":"Baier Erwin",
    "wof:placetype":"venue"
},
  "geometry": {"coordinates":[13.878993988,48.0910606384],"type":"Point"}
}