{
  "type": "Feature",
  "properties": {
    "iso:country":"AT",
    "sg:address":"Gro\u00dfarl 118",
    "sg:city":"Gro\u00dfarl",
    "sg:classifiers":[
        {
            "category":"Home & Garden",
            "subcategory":"Furniture",
            "type":"Retail Goods"
        }
    ],
    "sg:phone":"+43 6414 247",
    "sg:postcode":"5611",
    "sg:province":"Salzburg",
    "sg:tags":[
        "bathroom"
    ],
    "wof:name":"Johann Haigl & Hettegger Peter KEG",
    "wof:placetype":"venue"
},
  "geometry": {"coordinates":[-114.0853424072,47.1626281738],"type":"Point"}
}