{
  "type": "Feature",
  "properties": {
    "iso:country":"AT",
    "sg:address":"Konradweg 5",
    "sg:city":"Leibnitz",
    "sg:classifiers":[
        {
            "category":"Travel",
            "subcategory":"Hotels & Motels",
            "type":"Entertainment"
        }
    ],
    "sg:phone":"+43 3452 84310",
    "sg:postcode":"8430",
    "sg:province":"Steiermark",
    "wof:name":"Hotel Weinland",
    "wof:placetype":"venue"
},
  "geometry": {"coordinates":[15.5394201279,46.7773132324],"type":"Point"}
}