{
  "type": "Feature",
  "properties": {
    "iso:country":"AT",
    "sg:address":"Lainach Diesseits 143",
    "sg:city":"Rangersdorf",
    "sg:classifiers":[
        {
            "category":"Banks & Credit Unions",
            "subcategory":"Investment Brokerage",
            "type":"Services"
        }
    ],
    "sg:phone":"+43 4822 7244",
    "sg:postcode":"9833",
    "sg:province":"K\u00e4rnten",
    "sg:tags":[
        "ceiling",
        "covering"
    ],
    "sg:website":"wsg-innenausbau.at",
    "wof:name":"WSG Innenausbau GesmbH",
    "wof:placetype":"venue"
},
  "geometry": {"coordinates":[12.9637470245,46.8620872498],"type":"Point"}
}