{
  "type": "Feature",
  "properties": {
    "iso:country":"AT",
    "sg:address":"Simmeringer Hauptstr 381",
    "sg:city":"Wien",
    "sg:orig_category":"Steinmetzbetriebe",
    "sg:phone":"+43 4317 676286",
    "sg:postcode":"1110",
    "sg:province":"Wien",
    "wof:name":"Fleischmann Ludwig Stadtsteinmetzmeister Nfg Steinmetzmeister Thomas Trinko",
    "wof:placetype":"venue"
},
  "geometry": {"coordinates":[16.4476184845,48.1531867981],"type":"Point"}
}