{
  "type": "Feature",
  "properties": {
    "iso:country":"AT",
    "sg:address":"Davidgasse 87-89",
    "sg:city":"Wien",
    "sg:classifiers":[
        {
            "category":"Banks & Credit Unions",
            "subcategory":"Bureau De Change",
            "type":"Services"
        }
    ],
    "sg:phone":"+43 1 6419941",
    "sg:postcode":"1100",
    "sg:province":"Wien",
    "sg:tags":[
        "solution",
        "complete",
        "internet"
    ],
    "sg:website":"biosnet.at",
    "wof:name":"BIOS Internet Handels- und DienstleistungsgmbH",
    "wof:placetype":"venue"
},
  "geometry": {"coordinates":[16.3582401276,48.1744651794],"type":"Point"}
}