{
  "type": "Feature",
  "properties": {
    "addr:full":"Wei\u00dfenwolffg 36 Wien Wien 1210",
    "addr:housenumber":"36",
    "addr:postcode":"1210",
    "addr:street":"Weissenwolffg",
    "iso:country":"AT",
    "sg:address":"Wei\u00dfenwolffg 36",
    "sg:city":"Wien",
    "sg:orig_category":"Non-Classified Establishments",
    "sg:phone":"+43 1 2713450",
    "sg:postcode":"1210",
    "sg:province":"Wien",
    "wof:name":"Pfarramt Schwarzlackenau Zum hl Anton v Padua",
    "wof:placetype":"venue"
},
  "geometry": {"coordinates":[16.3978404999,48.2579994202],"type":"Point"}
}