{
  "type": "Feature",
  "properties": {
    "iso:country":"AT",
    "sg:address":"Kreisbacher Str 2",
    "sg:city":"Wilhelmsburg an der Traisen",
    "sg:orig_category":"Installationsunternehmen",
    "sg:phone":"+43 4327 466318",
    "sg:postcode":"3150",
    "sg:province":"Nieder\u00f6sterreich",
    "wof:name":"Janisch GesmbH",
    "wof:placetype":"venue"
},
  "geometry": {"coordinates":[15.6048440933,48.102016449],"type":"Point"}
}