{
  "type": "Feature",
  "properties": {
    "addr:full":"Nr 82a Kl\u00f6sterle Vorarlberg 6754",
    "addr:postcode":"6754",
    "addr:street":"Nr 82A Kloesterle",
    "iso:country":"AT",
    "sg:address":"Nr 82a",
    "sg:city":"Kl\u00f6sterle",
    "sg:orig_category":"Friseure U Frisiersalons",
    "sg:phone":"+43 4355 82370",
    "sg:postcode":"6754",
    "sg:province":"Vorarlberg",
    "wof:name":"Fris\u00f6r fortschnitt - Mangeng Sabine",
    "wof:placetype":"venue"
},
  "geometry": {"coordinates":[-101.40701293950001,34.2146606445],"type":"Point"}
}