{
  "type": "Feature",
  "properties": {
    "addr:full":"Abt-Karl-Str 27 Melk Nieder\u00f6sterreich 3390",
    "addr:housenumber":"27",
    "addr:postcode":"3390",
    "addr:street":"Abt-Karl-Str",
    "iso:country":"AT",
    "sg:address":"Abt-Karl-Str 27",
    "sg:city":"Melk",
    "sg:orig_category":"Baumeister",
    "sg:phone":"+43 2752 525520",
    "sg:postcode":"3390",
    "sg:province":"Nieder\u00f6sterreich",
    "wof:name":"Schnabl Andreas Ing",
    "wof:placetype":"venue"
},
  "geometry": {"coordinates":[15.3354721069,48.2255592346],"type":"Point"}
}