{
  "type": "Feature",
  "properties": {
    "addr:full":"Leonhardweg 5 Th\u00fcringen Vorarlberg 6712",
    "addr:housenumber":"5",
    "addr:postcode":"6712",
    "addr:street":"Leonhardweg",
    "iso:country":"AT",
    "sg:address":"Leonhardweg 5",
    "sg:city":"Th\u00fcringen",
    "sg:orig_category":"Elektromotoren / Reparatur U Wickelei",
    "sg:phone":"+43 5550 4803",
    "sg:postcode":"6712",
    "sg:province":"Vorarlberg",
    "wof:name":"Domig Rainer",
    "wof:placetype":"venue"
},
  "geometry": {"coordinates":[9.7615919113,47.1967468262],"type":"Point"}
}