{
  "type": "Feature",
  "properties": {
    "iso:country":"AT",
    "sg:address":"Burgg 2",
    "sg:city":"Wien",
    "sg:orig_category":"Friseure U Frisiersalons",
    "sg:phone":"+43 4315 263366",
    "sg:postcode":"1070",
    "sg:province":"Wien",
    "sg:website":"frisur-agentur-franz.at",
    "wof:name":"Frisur Agentur Franz",
    "wof:placetype":"venue"
},
  "geometry": {"coordinates":[16.3565616608,48.2046279907],"type":"Point"}
}