{
  "type": "Feature",
  "properties": {
    "addr:full":"Werfelstr 3 Leonding Ober\u00f6sterreich 4060",
    "addr:housenumber":"3",
    "addr:postcode":"4060",
    "addr:street":"Werfelstr",
    "iso:country":"AT",
    "sg:address":"Werfelstr 3",
    "sg:city":"Leonding",
    "sg:orig_category":"Hydraulik",
    "sg:phone":"+43 732 680571",
    "sg:postcode":"4060",
    "sg:province":"Ober\u00f6sterreich",
    "wof:name":"Denison Hydraulik GmbH",
    "wof:placetype":"venue"
},
  "geometry": {"coordinates":[14.2671737671,48.2703971863],"type":"Point"}
}