{
  "type": "Feature",
  "properties": {
    "iso:country":"AT",
    "sg:address":"Schanzstr 29-31",
    "sg:city":"Wien",
    "sg:orig_category":"Autoelektrik U -Ersatzteile",
    "sg:phone":"+43 4319 8226470",
    "sg:postcode":"1140",
    "sg:province":"Wien",
    "wof:name":"AMS Nu\u00dfbaumer GesmbH",
    "wof:placetype":"venue"
},
  "geometry": {"coordinates":[16.3149223328,48.2006874084],"type":"Point"}
}