{
  "type": "Feature",
  "properties": {
    "addr:full":"Garteng 7 Achau Nieder\u00f6sterreich 2481",
    "addr:housenumber":"7",
    "addr:postcode":"2481",
    "addr:street":"Garteng",
    "iso:country":"AT",
    "sg:address":"Garteng 7",
    "sg:city":"Achau",
    "sg:orig_category":"Schlossereien",
    "sg:phone":"+43 664 5003328",
    "sg:postcode":"2481",
    "sg:province":"Nieder\u00f6sterreich",
    "wof:name":"Pinczolits Walter",
    "wof:placetype":"venue"
},
  "geometry": {"coordinates":[16.3952598572,48.08228302],"type":"Point"}
}