{
  "type": "Feature",
  "properties": {
    "iso:country":"AT",
    "sg:address":"Stempferg 10",
    "sg:city":"Graz",
    "sg:orig_category":"Boutiquen",
    "sg:phone":"+43 316 829015",
    "sg:postcode":"8010",
    "sg:province":"Steiermark",
    "wof:name":"be-be Designermode",
    "wof:placetype":"venue"
},
  "geometry": {"coordinates":[15.4398670197,47.0704116821],"type":"Point"}
}