{
  "type": "Feature",
  "properties": {
    "iso:country":"AT",
    "sg:address":"Hauptpl 10",
    "sg:city":"Sollenau",
    "sg:orig_category":"Fleischhauereien",
    "sg:phone":"+43 2628 42673",
    "sg:postcode":"2601",
    "sg:province":"Nieder\u00f6sterreich",
    "wof:name":"Pahl GesmbH & Co KG",
    "wof:placetype":"venue"
},
  "geometry": {"coordinates":[16.2497596741,47.8963890076],"type":"Point"}
}