{
  "type": "Feature",
  "properties": {
    "addr:full":"Nr 30 Kasten Nieder\u00f6sterreich 3072",
    "addr:postcode":"3072",
    "addr:street":"Nr;Kasten Niederoesterreich",
    "iso:country":"AT",
    "sg:address":"Nr 30",
    "sg:city":"Kasten",
    "sg:orig_category":"Schaumstoffe",
    "sg:phone":"+43 2744 5376",
    "sg:postcode":"3072",
    "sg:province":"Nieder\u00f6sterreich",
    "wof:name":"M\u00fcller Ewald",
    "wof:placetype":"venue"
},
  "geometry": {"coordinates":[15.7793397903,48.1532783508],"type":"Point"}
}