{
  "type": "Feature",
  "properties": {
    "addr:full":"Mozartstr 1 Persenbeug Nieder\u00f6sterreich 3680",
    "addr:housenumber":"1",
    "addr:postcode":"3680",
    "addr:street":"Mozartstr",
    "iso:country":"AT",
    "sg:address":"Mozartstr 1",
    "sg:city":"Persenbeug",
    "sg:orig_category":"Lebensmittel / Einzelhandel",
    "sg:phone":"+43 7412 59114",
    "sg:postcode":"3680",
    "sg:province":"Nieder\u00f6sterreich",
    "wof:name":"Billa AG",
    "wof:placetype":"venue"
},
  "geometry": {"coordinates":[15.0793266296,48.1879043579],"type":"Point"}
}