{
  "type": "Feature",
  "properties": {
    "addr:full":"Steinb\u00f6ckweg 5 Deutschlandsberg Steiermark 8530",
    "addr:housenumber":"5",
    "addr:postcode":"8530",
    "addr:street":"Steinboeckweg",
    "iso:country":"AT",
    "sg:address":"Steinb\u00f6ckweg 5",
    "sg:city":"Deutschlandsberg",
    "sg:orig_category":"Pensionen / Privatzimmer",
    "sg:phone":"+43 3461 217",
    "sg:postcode":"8530",
    "sg:province":"Steiermark",
    "wof:name":"Gl\u00f6ckner Aloisia",
    "wof:placetype":"venue"
},
  "geometry": {"coordinates":[15.1526765823,46.8256072998],"type":"Point"}
}