{
  "type": "Feature",
  "properties": {
    "addr:full":"Ledererg 67/Stg1 Linz Ober\u00f6sterreich 4020",
    "addr:housenumber":"67 / stg1",
    "addr:postcode":"4020",
    "addr:street":"Ledererg",
    "iso:country":"AT",
    "sg:address":"Ledererg 67/Stg1",
    "sg:city":"Linz",
    "sg:classifiers":[
        {
            "category":"Professional",
            "subcategory":"Computer Services",
            "type":"Services"
        }
    ],
    "sg:phone":"+43 732 348750",
    "sg:postcode":"4020",
    "sg:province":"Ober\u00f6sterreich",
    "sg:tags":[
        "software"
    ],
    "wof:name":"eurowin Software und Handels GmbH",
    "wof:placetype":"venue"
},
  "geometry": {"coordinates":[14.2451400757,48.3018455505],"type":"Point"}
}