{
  "type": "Feature",
  "properties": {
    "addr:full":"Hernalser Hauptstr 217 Wien Wien 1170",
    "addr:housenumber":"217",
    "addr:postcode":"1170",
    "addr:street":"Hernalser Hauptstr",
    "iso:country":"AT",
    "sg:address":"Hernalser Hauptstr 217",
    "sg:city":"Wien",
    "sg:orig_category":"Blumeneinzelhandel",
    "sg:phone":"+43 4314 890262",
    "sg:postcode":"1170",
    "sg:province":"Wien",
    "sg:website":"blumenharmonie.at",
    "wof:name":"Blumenharmonie Wilma",
    "wof:placetype":"venue"
},
  "geometry": {"coordinates":[16.3094596863,48.2254371643],"type":"Point"}
}