{
  "type": "Feature",
  "properties": {
    "addr:full":"Feilplatz 3  Wien Wien 1140",
    "addr:housenumber":"3",
    "addr:postcode":"1140",
    "addr:street":"Feilplatz",
    "iso:country":"AT",
    "sg:address":"Feilplatz 3 ",
    "sg:city":"Wien",
    "sg:classifiers":[
        {
            "category":"Building & Trades",
            "subcategory":"Plumbing",
            "type":"Services"
        }
    ],
    "sg:phone":"+43 1 7862020",
    "sg:postcode":"1140",
    "sg:province":"Wien",
    "sg:tags":[
        "supraregional",
        "gas"
    ],
    "sg:website":"www.wessely-spiess.at",
    "wof:name":"Ing. Andreas Spiess",
    "wof:placetype":"venue"
},
  "geometry": {"coordinates":[16.3106975555,48.1999816895],"type":"Point"}
}