{
  "type": "Feature",
  "properties": {
    "iso:country":"AT",
    "sg:address":"Breitenseer Str 112",
    "sg:city":"Wien",
    "sg:orig_category":"Architekten",
    "sg:phone":"+43 1 7890888",
    "sg:postcode":"1140",
    "sg:province":"Wien",
    "wof:name":"Masser Markus Dipl-Ing",
    "wof:placetype":"venue"
},
  "geometry": {"coordinates":[16.2966022491,48.2027626038],"type":"Point"}
}