{
  "type": "Feature",
  "properties": {
    "addr:full":"Strohbergg 37 Wien Wien 1120",
    "addr:housenumber":"37",
    "addr:postcode":"1120",
    "addr:street":"Strohbergg",
    "iso:country":"AT",
    "sg:address":"Strohbergg 37",
    "sg:city":"Wien",
    "sg:orig_category":"Installationsunternehmen",
    "sg:phone":"+43 4318 0435700",
    "sg:postcode":"1120",
    "sg:province":"Wien",
    "wof:name":"Allkommerz Handels-, Vertriebs- u Service GesmbH & Co KEG",
    "wof:placetype":"venue"
},
  "geometry": {"coordinates":[16.3114910126,48.166847229],"type":"Point"}
}