{
  "type": "Feature",
  "properties": {
    "addr:full":"Schillerstr 13 Gumpoldskirchen Nieder\u00f6sterreich 2352",
    "addr:housenumber":"13",
    "addr:postcode":"2352",
    "addr:street":"Schillerstr",
    "iso:country":"AT",
    "sg:address":"Schillerstr 13",
    "sg:city":"Gumpoldskirchen",
    "sg:orig_category":"Architekten",
    "sg:phone":"+43 2252 631220",
    "sg:postcode":"2352",
    "sg:province":"Nieder\u00f6sterreich",
    "wof:name":"Haderer Wilhard Arch Dipl-Ing",
    "wof:placetype":"venue"
},
  "geometry": {"coordinates":[16.2768802643,48.0457687378],"type":"Point"}
}