{
  "type": "Feature",
  "properties": {
    "iso:country":"AT",
    "sg:address":"Griesg. 23",
    "sg:city":"Salzburg",
    "sg:classifiers":[
        {
            "category":"Travel",
            "subcategory":"Travel Agent",
            "type":"Entertainment"
        }
    ],
    "sg:phone":"+43 4366 2842140",
    "sg:postcode":"5020",
    "sg:province":"Salzburg",
    "sg:tags":[
        "business"
    ],
    "wof:name":"STERNBR\u00c4U GRO\u00dfGASTST\u00c4TTE DR. G\u00dcNTHER PUTTINGER",
    "wof:placetype":"venue"
},
  "geometry": {"coordinates":[13.0433769226,47.8006744385],"type":"Point"}
}