{
  "type": "Feature",
  "properties": {
    "addr:full":"Reinhard-Spielmann-Strasse 2 Ehrwald Tirol 6632",
    "addr:housenumber":"2",
    "addr:postcode":"6632",
    "addr:street":"Reinhard-Spielmann-Strasse;Tirol",
    "iso:country":"AT",
    "sg:address":"Reinhard-Spielmann-Strasse 2",
    "sg:city":"Ehrwald",
    "sg:classifiers":[
        {
            "category":"Food & Beverages",
            "subcategory":"Liquor & Beverages",
            "type":"Retail Goods"
        }
    ],
    "sg:phone":"+43 5673 22440",
    "sg:postcode":"6632",
    "sg:province":"Tirol",
    "sg:tags":[
        "liqueur",
        "alcohol-milk"
    ],
    "wof:name":"A. Linzgieseder Getr\u00e4nkehandel Ges.m.b.H. & Co KG",
    "wof:placetype":"venue"
},
  "geometry": {"coordinates":[10.921546936,47.3984642029],"type":"Point"}
}