{
  "type": "Feature",
  "properties": {
    "addr:full":"Wiener Strasse 5 Maria Lanzendorf Nieder\u00f6sterreich 2326",
    "addr:housenumber":"5",
    "addr:postcode":"2326",
    "addr:street":"Wiener Strasse",
    "iso:country":"AT",
    "sg:address":"Wiener Strasse 5",
    "sg:city":"Maria Lanzendorf",
    "sg:classifiers":[
        {
            "category":"Home & Garden",
            "subcategory":"Household Appliances",
            "type":"Retail Goods"
        }
    ],
    "sg:phone":"+43 2235 47273",
    "sg:postcode":"2326",
    "sg:province":"Nieder\u00f6sterreich",
    "sg:tags":[
        "electric"
    ],
    "wof:name":"Dietmar Schmidt",
    "wof:placetype":"venue"
},
  "geometry": {"coordinates":[16.4179706573,48.0994949341],"type":"Point"}
}