{
  "type": "Feature",
  "properties": {
    "addr:full":"Franziskanerstr 1 Frauenkirchen Burgenland 7132",
    "addr:housenumber":"1",
    "addr:postcode":"7132",
    "addr:street":"Franziskanerstr",
    "iso:country":"AT",
    "sg:address":"Franziskanerstr 1",
    "sg:city":"Frauenkirchen",
    "sg:orig_category":"Tischlereien",
    "sg:phone":"+43 2172 22111",
    "sg:postcode":"7132",
    "sg:province":"Burgenland",
    "wof:name":"Tischlerei-M\u00f6belstudio Thullner GesmbH",
    "wof:placetype":"venue"
},
  "geometry": {"coordinates":[16.9277458191,47.8355636597],"type":"Point"}
}