{
  "type": "Feature",
  "properties": {
    "addr:full":"Ungarg 16 Wien Wien 1030",
    "addr:housenumber":"16",
    "addr:postcode":"1030",
    "addr:street":"Ungarg",
    "iso:country":"AT",
    "sg:address":"Ungarg 16",
    "sg:city":"Wien",
    "sg:orig_category":"Autoreparatur",
    "sg:phone":"+43 1 7145922",
    "sg:postcode":"1030",
    "sg:province":"Wien",
    "wof:name":"Chadoian GesmbH",
    "wof:placetype":"venue"
},
  "geometry": {"coordinates":[16.3869552612,48.2026634216],"type":"Point"}
}