{
  "type": "Feature",
  "properties": {
    "addr:full":"B\u00f6hmerstr 28 Bad Leonfelden Ober\u00f6sterreich 4190",
    "addr:housenumber":"28",
    "addr:postcode":"4190",
    "addr:street":"Boehmerstr",
    "iso:country":"AT",
    "sg:address":"B\u00f6hmerstr 28",
    "sg:city":"Bad Leonfelden",
    "sg:orig_category":"Lebensmittel / Einzelhandel",
    "sg:phone":"+43 7213 6936",
    "sg:postcode":"4190",
    "sg:province":"Ober\u00f6sterreich",
    "wof:name":"SPAR \u00f6sterreichische Warenhandels-AG",
    "wof:placetype":"venue"
},
  "geometry": {"coordinates":[14.2938985825,48.5256652832],"type":"Point"}
}