{
  "type": "Feature",
  "properties": {
    "addr:full":"Rabenberg 11 Ried im Innkreis Ober\u00f6sterreich 4910",
    "addr:housenumber":"11",
    "addr:postcode":"4910",
    "addr:street":"Rabenberg",
    "iso:country":"AT",
    "sg:address":"Rabenberg 11",
    "sg:city":"Ried im Innkreis",
    "sg:orig_category":"Ziegeleien",
    "sg:phone":"+43 4377 5282261",
    "sg:postcode":"4910",
    "sg:province":"Ober\u00f6sterreich",
    "wof:name":"Ziegelwerk Danreiter & Co",
    "wof:placetype":"venue"
},
  "geometry": {"coordinates":[13.5050821304,48.2167854309],"type":"Point"}
}