{
  "type": "Feature",
  "properties": {
    "iso:country":"AT",
    "sg:address":"Wr Neust\u00e4dter Str 20",
    "sg:city":"Bad Fischau",
    "sg:orig_category":"Vinotheken",
    "sg:phone":"+43 664 1359782",
    "sg:postcode":"2721",
    "sg:province":"Nieder\u00f6sterreich",
    "wof:name":"Hartmann Vinothek OEG",
    "wof:placetype":"venue"
},
  "geometry": {"coordinates":[16.1677837372,47.8312492371],"type":"Point"}
}