{
  "type": "Feature",
  "properties": {
    "addr:full":"Maria-Theresien-Str 104 Lustenau Vorarlberg 6890",
    "addr:housenumber":"104",
    "addr:postcode":"6890",
    "iso:country":"AT",
    "sg:address":"Maria-Theresien-Str 104",
    "sg:city":"Lustenau",
    "sg:orig_category":"Telekommunikation",
    "sg:phone":"+43 4355 7782480",
    "sg:postcode":"6890",
    "sg:province":"Vorarlberg",
    "wof:name":"Handy Ambulance Yildrim Ziya",
    "wof:placetype":"venue"
},
  "geometry": {"coordinates":[9.6560907364,47.4371414185],"type":"Point"}
}