{
  "type": "Feature",
  "properties": {
    "addr:full":"Vorgartenstr 72 Wien Wien 1200",
    "addr:housenumber":"72",
    "addr:postcode":"1200",
    "addr:street":"Vorgartenstr",
    "iso:country":"AT",
    "sg:address":"Vorgartenstr 72",
    "sg:city":"Wien",
    "sg:orig_category":"Transportunternehmen",
    "sg:phone":"+43 699 12590459",
    "sg:postcode":"1200",
    "sg:province":"Wien",
    "wof:name":"Markovic L Transport KEG",
    "wof:placetype":"venue"
},
  "geometry": {"coordinates":[16.388502121,48.2350921631],"type":"Point"}
}