{
  "type": "Feature",
  "properties": {
    "addr:full":"Nr 1 St. Florian Ober\u00f6sterreich 4490",
    "addr:housenumber":"1",
    "addr:postcode":"4490",
    "addr:street":"Nr",
    "iso:country":"AT",
    "sg:address":"Nr 1",
    "sg:city":"St. Florian",
    "sg:orig_category":"Werbeagenturen",
    "sg:phone":"+43 7223 81760",
    "sg:postcode":"4490",
    "sg:province":"Ober\u00f6sterreich",
    "wof:name":"WHAT! Dolzer & Ganglberger OEG",
    "wof:placetype":"venue"
},
  "geometry": {"coordinates":[14.3802604675,48.2064056396],"type":"Point"}
}