{
  "type": "Feature",
  "properties": {
    "addr:full":"Albertpl 7 Wien Wien 1080",
    "addr:housenumber":"7",
    "addr:postcode":"1080",
    "addr:street":"Albertpl",
    "iso:country":"AT",
    "sg:address":"Albertpl 7",
    "sg:city":"Wien",
    "sg:orig_category":"Rauchfangkehrer",
    "sg:phone":"+43 4317 343540",
    "sg:postcode":"1080",
    "sg:province":"Wien",
    "wof:name":"Stern Gerd-Dieter",
    "wof:placetype":"venue"
},
  "geometry": {"coordinates":[16.3440513611,48.2147140503],"type":"Point"}
}