{
  "type": "Feature",
  "properties": {
    "iso:country":"AT",
    "sg:address":"Kircheng 31",
    "sg:city":"Gm\u00fcnd",
    "sg:orig_category":"Freizeit- U Sportbekleidung",
    "sg:phone":"+43 4328 52537300",
    "sg:postcode":"3950",
    "sg:province":"Nieder\u00f6sterreich",
    "wof:name":"Bazar Fashion Company Inh Franz Breit",
    "wof:placetype":"venue"
},
  "geometry": {"coordinates":[14.9863471985,48.7737884521],"type":"Point"}
}