{
  "type": "Feature",
  "properties": {
    "iso:country":"AT",
    "sg:address":"Josef-Nachtigall-G 1",
    "sg:city":"Eggendorf",
    "sg:orig_category":"Polizei U Gendarmerie",
    "sg:phone":"+43 4359 1333372",
    "sg:postcode":"2492",
    "sg:province":"Nieder\u00f6sterreich",
    "wof:name":"Gendarmerie",
    "wof:placetype":"venue"
},
  "geometry": {"coordinates":[8.1344404221,49.3539199829],"type":"Point"}
}