{
  "type": "Feature",
  "properties": {
    "iso:country":"AT",
    "sg:address":"Nr 24",
    "sg:city":"St. Ruprecht an der Raab",
    "sg:orig_category":"Baumeister",
    "sg:phone":"+43 3178 3375",
    "sg:postcode":"8181",
    "sg:province":"Steiermark",
    "wof:name":"M\u00f6rth Alfred jun Ing",
    "wof:placetype":"venue"
},
  "geometry": {"coordinates":[8.5020704269,47.5079307556],"type":"Point"}
}