{
  "type": "Feature",
  "properties": {
    "addr:full":"Schlo\u00dfg 2 Dornbirn Vorarlberg 6850",
    "addr:housenumber":"2",
    "addr:postcode":"6850",
    "addr:street":"Schlossg",
    "iso:country":"AT",
    "sg:address":"Schlo\u00dfg 2",
    "sg:city":"Dornbirn",
    "sg:orig_category":"Zeitungen U Zeitschriften",
    "sg:phone":"+43 5572 21418",
    "sg:postcode":"6850",
    "sg:province":"Vorarlberg",
    "wof:name":"Kultur-Zeitschrift f Kultur und Gesellschaft",
    "wof:placetype":"venue"
},
  "geometry": {"coordinates":[9.7510633469,47.410068512],"type":"Point"}
}