{
  "type": "Feature",
  "properties": {
    "iso:country":"AT",
    "sg:address":"Fehlingerg 21",
    "sg:city":"Wien",
    "sg:orig_category":"Handelsagenturen",
    "sg:phone":"+43 1 8042408",
    "sg:postcode":"1130",
    "sg:province":"Wien",
    "wof:name":"Libal Gustav",
    "wof:placetype":"venue"
},
  "geometry": {"coordinates":[16.2889862061,48.167514801],"type":"Point"}
}