{
  "type": "Feature",
  "properties": {
    "addr:full":"P\u00fcrnstein 35 Neufelden Ober\u00f6sterreich 4120",
    "addr:housenumber":"35",
    "addr:postcode":"4120",
    "addr:street":"Puernstein",
    "iso:country":"AT",
    "sg:address":"P\u00fcrnstein 35",
    "sg:city":"Neufelden",
    "sg:orig_category":"Transportunternehmen",
    "sg:phone":"+43 7282 7753",
    "sg:postcode":"4120",
    "sg:province":"Ober\u00f6sterreich",
    "wof:name":"Blitz-Trans Transporte- und Baggerungen GmbH",
    "wof:placetype":"venue"
},
  "geometry": {"coordinates":[13.9999198914,48.4844017029],"type":"Point"}
}