{
  "type": "Feature",
  "properties": {
    "iso:country":"AT",
    "sg:address":"Ipf-Landesstrasse 1",
    "sg:city":"Asten",
    "sg:classifiers":[
        {
            "category":"Manufacturing",
            "subcategory":"Tools & Machinery",
            "type":"Manufacturing & Wholesale Goods"
        }
    ],
    "sg:phone":"+43 7224 2100",
    "sg:postcode":"4481",
    "sg:province":"Ober\u00f6sterreich",
    "sg:tags":[
        "shaft",
        "encoders",
        "absolute"
    ],
    "sg:website":"lenze.at",
    "wof:name":"Lenze Antriebstechnik GmbH",
    "wof:placetype":"venue"
},
  "geometry": {"coordinates":[14.4152784348,48.2315139771],"type":"Point"}
}