{
  "type": "Feature",
  "properties": {
    "iso:country":"AT",
    "sg:address":"Nr 25",
    "sg:city":"Pusterwald",
    "sg:orig_category":"Pensionen / Privatzimmer",
    "sg:phone":"+43 3574 2228",
    "sg:postcode":"8764",
    "sg:province":"Steiermark",
    "wof:name":"J\u00e4gerheim Inh Alfred Diethart",
    "wof:placetype":"venue"
},
  "geometry": {"coordinates":[14.3745698929,47.308467865],"type":"Point"}
}