{
  "type": "Feature",
  "properties": {
    "iso:country":"AT",
    "sg:address":"Eisenhammerstr 3",
    "sg:city":"Krieglach",
    "sg:orig_category":"Industrieanlagenbau U -Planung",
    "sg:phone":"+43 4338 5545425",
    "sg:postcode":"8670",
    "sg:province":"Steiermark",
    "wof:name":"Kremsm\u00fcller Industrieanlagenbau KG",
    "wof:placetype":"venue"
},
  "geometry": {"coordinates":[15.5461397171,47.5467300415],"type":"Point"}
}