{
  "type": "Feature",
  "properties": {
    "iso:country":"AT",
    "sg:address":"Nr 210",
    "sg:city":"Pettneu am Arlberg",
    "sg:classifiers":[
        {
            "category":"Travel",
            "subcategory":"Hotels & Motels",
            "type":"Entertainment"
        }
    ],
    "sg:phone":"+43 5448 82530",
    "sg:postcode":"6574",
    "sg:province":"Tirol",
    "wof:name":"Hotel Olympia",
    "wof:placetype":"venue"
},
  "geometry": {"coordinates":[10.3418588638,47.148349762],"type":"Point"}
}