{
  "type": "Feature",
  "properties": {
    "addr:full":"St. Ruprechter Str 40 Klagenfurt K\u00e4rnten 9020",
    "addr:housenumber":"40",
    "addr:postcode":"9020",
    "addr:street":"St.;Str;Kaernten",
    "iso:country":"AT",
    "sg:address":"St. Ruprechter Str 40",
    "sg:city":"Klagenfurt",
    "sg:orig_category":"Blumeneinzelhandel",
    "sg:phone":"+43 463 346284",
    "sg:postcode":"9020",
    "sg:province":"K\u00e4rnten",
    "wof:name":"Blumen Christa",
    "wof:placetype":"venue"
},
  "geometry": {"coordinates":[14.308968544,46.612903595],"type":"Point"}
}