{
  "type": "Feature",
  "properties": {
    "iso:country":"AT",
    "sg:address":"Scheringweg 1",
    "sg:city":"Jochberg",
    "sg:orig_category":"Pensionen / Privatzimmer",
    "sg:phone":"+43 5355 5276",
    "sg:postcode":"6373",
    "sg:province":"Tirol",
    "wof:name":"Haus Alpenrose",
    "wof:placetype":"venue"
},
  "geometry": {"coordinates":[12.4024686813,47.362663269],"type":"Point"}
}