{
  "type": "Feature",
  "properties": {
    "addr:full":"Grazestr. 186  Pischelsdorf in Steiermark Steiermark 8212",
    "addr:housenumber":"186",
    "addr:postcode":"8212",
    "addr:street":"Pischelsdorf In",
    "iso:country":"AT",
    "sg:address":"Grazestr. 186 ",
    "sg:city":"Pischelsdorf in Steiermark",
    "sg:classifiers":[
        {
            "category":"Shopping",
            "subcategory":"Computers & Home Electronics",
            "type":"Retail Goods"
        }
    ],
    "sg:phone":"+43 4331 138555",
    "sg:postcode":"8212",
    "sg:province":"Steiermark",
    "sg:tags":[
        "electronic",
        "electrical",
        "equipment"
    ],
    "wof:name":"SPINDLER OHG",
    "wof:placetype":"venue"
},
  "geometry": {"coordinates":[15.8019390106,47.170124054],"type":"Point"}
}