{
  "type": "Feature",
  "properties": {
    "addr:full":"Rennweg 97-99 Wien Wien 1030",
    "addr:postcode":"97-99;1030",
    "addr:street":"Rennweg",
    "iso:country":"AT",
    "sg:address":"Rennweg 97-99",
    "sg:city":"Wien",
    "sg:orig_category":"Telekommunikation",
    "sg:phone":"+43 4317 182930",
    "sg:postcode":"1030",
    "sg:province":"Wien",
    "wof:name":"ARGE Telekommunikationsanlagen GesnbR",
    "wof:placetype":"venue"
},
  "geometry": {"coordinates":[16.4026737213,48.1866760254],"type":"Point"}
}