{
  "type": "Feature",
  "properties": {
    "addr:full":"Nr 45 Martinsberg Nieder\u00f6sterreich 3664",
    "addr:postcode":"3664",
    "addr:street":"Nr;Martinsberg Niederoesterreich",
    "iso:country":"AT",
    "sg:address":"Nr 45",
    "sg:city":"Martinsberg",
    "sg:orig_category":"Schlossereien",
    "sg:phone":"+43 2874 6216",
    "sg:postcode":"3664",
    "sg:province":"Nieder\u00f6sterreich",
    "wof:name":"Lederm\u00fcller Franz GmbH",
    "wof:placetype":"venue"
},
  "geometry": {"coordinates":[15.1500616074,48.3754043579],"type":"Point"}
}