{
  "type": "Feature",
  "properties": {
    "iso:country":"AT",
    "sg:address":"Stadtpl 46",
    "sg:city":"Braunau am Inn",
    "sg:orig_category":"Friseure U Frisiersalons",
    "sg:phone":"+43 4377 228468515",
    "sg:postcode":"5280",
    "sg:province":"Ober\u00f6sterreich",
    "wof:name":"Ihr dm Friseur Studio",
    "wof:placetype":"venue"
},
  "geometry": {"coordinates":[13.0352554321,48.2587356567],"type":"Point"}
}