{
  "type": "Feature",
  "properties": {
    "iso:country":"AT",
    "sg:address":"Blumeng 4",
    "sg:city":"Rudersdorf",
    "sg:orig_category":"Schneidereien",
    "sg:phone":"+43 4333 8271410",
    "sg:postcode":"7571",
    "sg:province":"Burgenland",
    "wof:name":"Sifkovits Andrea Ma\u00df - u Vereinsbekleidungsschneiderei",
    "wof:placetype":"venue"
},
  "geometry": {"coordinates":[16.1165428162,47.0522689819],"type":"Point"}
}