{
  "type": "Feature",
  "properties": {
    "addr:full":"M\u00fcnchner Str 48 Schwaz Tirol 6130",
    "addr:postcode":"6130",
    "addr:street":"Str 48;Tirol",
    "iso:country":"AT",
    "sg:address":"M\u00fcnchner Str 48",
    "sg:city":"Schwaz",
    "sg:orig_category":"Zeitungen U Zeitschriften",
    "sg:phone":"+43 5242 731860",
    "sg:postcode":"6130",
    "sg:province":"Tirol",
    "wof:name":"Bezirksblatt Schwaz",
    "wof:placetype":"venue"
},
  "geometry": {"coordinates":[11.7071990967,47.3454208374],"type":"Point"}
}