{
  "type": "Feature",
  "properties": {
    "addr:full":"Plunkerg 13-15 Wien Wien 1150",
    "addr:postcode":"13-15;1150",
    "iso:country":"AT",
    "sg:address":"Plunkerg 13-15",
    "sg:city":"Wien",
    "sg:orig_category":"Brandschutz",
    "sg:phone":"+43 1 98228700",
    "sg:postcode":"1150",
    "sg:province":"Wien",
    "wof:name":"Sprinklerplan Brandschutzanlagen GesmbH",
    "wof:placetype":"venue"
},
  "geometry": {"coordinates":[16.3246898651,48.1991920471],"type":"Point"}
}