{
  "type": "Feature",
  "properties": {
    "iso:country":"AT",
    "sg:address":"Schulg 1A",
    "sg:city":"Guntramsdorf",
    "sg:orig_category":"Bauunternehmen",
    "sg:phone":"+43 2236 52714",
    "sg:postcode":"2353",
    "sg:province":"Nieder\u00f6sterreich",
    "wof:name":"Hartmann Wolfgang GesmbH",
    "wof:placetype":"venue"
},
  "geometry": {"coordinates":[16.311580658,48.0488090515],"type":"Point"}
}