{
  "type": "Feature",
  "properties": {
    "addr:full":"Breitenfurter Str 66 Wien Wien 1120",
    "addr:postcode":"1120",
    "addr:street":"Str 66",
    "iso:country":"AT",
    "sg:address":"Breitenfurter Str 66",
    "sg:city":"Wien",
    "sg:orig_category":"Futtermittel",
    "sg:phone":"+43 1 80415310",
    "sg:postcode":"1120",
    "sg:province":"Wien",
    "wof:name":"Barry Heimtiernahrung GesmbH",
    "wof:placetype":"venue"
},
  "geometry": {"coordinates":[16.3141441345,48.1639518738],"type":"Point"}
}