{
  "type": "Feature",
  "properties": {
    "addr:full":"Hauptplatz 7 Judenburg Steiermark 8750",
    "addr:housenumber":"7",
    "addr:postcode":"8750",
    "addr:street":"Hauptplatz",
    "iso:country":"AT",
    "sg:address":"Hauptplatz 7",
    "sg:city":"Judenburg",
    "sg:classifiers":[
        {
            "category":"Home & Garden",
            "subcategory":"Building Materials",
            "type":"Retail Goods"
        }
    ],
    "sg:phone":"+43 3572 82140",
    "sg:postcode":"8750",
    "sg:province":"Steiermark",
    "sg:tags":[
        "glass",
        "enclosures",
        "balcony"
    ],
    "sg:website":"members.aon.at/prebioglas",
    "wof:name":"Ingeborg Prebio",
    "wof:placetype":"venue"
},
  "geometry": {"coordinates":[14.6612949371,47.1689758301],"type":"Point"}
}