{
  "type": "Feature",
  "properties": {
    "addr:full":"Feldg 35 Kufstein Tirol 6330",
    "addr:housenumber":"35",
    "addr:postcode":"6330",
    "addr:street":"Feldg;Tirol",
    "iso:country":"AT",
    "sg:address":"Feldg 35",
    "sg:city":"Kufstein",
    "sg:classifiers":[
        {
            "category":"Taxi",
            "type":"Transportation"
        }
    ],
    "sg:phone":"+43 4353 7262233",
    "sg:postcode":"6330",
    "sg:province":"Tirol",
    "sg:tags":[
        "personentransporte",
        "u"
    ],
    "wof:name":"Taxi Marianne",
    "wof:placetype":"venue"
},
  "geometry": {"coordinates":[12.1717987061,47.5847892761],"type":"Point"}
}