{
  "type": "Feature",
  "properties": {
    "iso:country":"AT",
    "sg:address":"Salaberg",
    "sg:city":"Haag",
    "sg:orig_category":"Tierparks",
    "sg:phone":"+43 7434 45408",
    "sg:postcode":"3350",
    "sg:province":"Nieder\u00f6sterreich",
    "wof:name":"Tierpark Haag",
    "wof:placetype":"venue"
},
  "geometry": {"coordinates":[14.5540246964,48.1057434082],"type":"Point"}
}