{
  "type": "Feature",
  "properties": {
    "addr:full":"Hafenstrasse 1-3 Linz Ober\u00f6sterreich 4020",
    "addr:housenumber":"1-3",
    "addr:postcode":"4020",
    "addr:street":"Hafenstrasse",
    "iso:country":"AT",
    "sg:address":"Hafenstrasse 1-3",
    "sg:city":"Linz",
    "sg:classifiers":[
        {
            "category":"Professional",
            "subcategory":"Printing & Photocopies",
            "type":"Services"
        }
    ],
    "sg:phone":"+43 732 76060",
    "sg:postcode":"4020",
    "sg:province":"Ober\u00f6sterreich",
    "sg:tags":[
        "newspaper",
        "publisher"
    ],
    "sg:website":"volksblatt.at",
    "wof:name":"\u00d6sterreichische Zeitungs- Verlags- u. Vertriebsges.m.b.H.",
    "wof:placetype":"venue"
},
  "geometry": {"coordinates":[14.3011188507,48.3154640198],"type":"Point"}
}