{
  "type": "Feature",
  "properties": {
    "addr:full":"Alszeile 116 Wien Wien 1170",
    "addr:housenumber":"116",
    "addr:postcode":"1170",
    "addr:street":"Alszeile",
    "iso:country":"AT",
    "sg:address":"Alszeile 116",
    "sg:city":"Wien",
    "sg:orig_category":"Psychotherapie",
    "sg:phone":"+43 1 4854069",
    "sg:postcode":"1170",
    "sg:province":"Wien",
    "wof:name":"Schneiderbauer Eleonore",
    "wof:placetype":"venue"
},
  "geometry": {"coordinates":[16.2977352142,48.2304077148],"type":"Point"}
}