{
  "type": "Feature",
  "properties": {
    "addr:full":"Thal 78 Pernitz Nieder\u00f6sterreich 2763",
    "addr:housenumber":"78",
    "addr:postcode":"2763",
    "addr:street":"Thal",
    "iso:country":"AT",
    "sg:address":"Thal 78",
    "sg:city":"Pernitz",
    "sg:classifiers":[
        {
            "category":"Home & Garden",
            "subcategory":"Garden Supply",
            "type":"Retail Goods"
        }
    ],
    "sg:phone":"+43 2632 74274",
    "sg:postcode":"2763",
    "sg:province":"Nieder\u00f6sterreich",
    "sg:tags":[
        "schotter",
        "sand",
        "u"
    ],
    "wof:name":"Gschaider KEG",
    "wof:placetype":"venue"
},
  "geometry": {"coordinates":[15.9071149826,47.9250831604],"type":"Point"}
}