{
  "type": "Feature",
  "properties": {
    "iso:country":"AT",
    "sg:address":"Neustiftg 23",
    "sg:city":"Wien",
    "sg:classifiers":[
        {
            "category":"Military Area",
            "subcategory":"Army Base",
            "type":"Public Place"
        }
    ],
    "sg:phone":"+43 1 5236364",
    "sg:postcode":"1070",
    "sg:province":"Wien",
    "sg:tags":[
        "shop"
    ],
    "wof:name":"Army-Shop Wow",
    "wof:placetype":"venue"
},
  "geometry": {"coordinates":[16.3532981873,48.2052536011],"type":"Point"}
}