{
  "type": "Feature",
  "properties": {
    "iso:country":"AT",
    "sg:address":"Bahnhofstr 10",
    "sg:city":"St. Veit an der Glan",
    "sg:orig_category":"Versicherungsunternehmen",
    "sg:phone":"+43 4212 6433",
    "sg:postcode":"9300",
    "sg:province":"K\u00e4rnten",
    "wof:name":"Donau Versicherung",
    "wof:placetype":"venue"
},
  "geometry": {"coordinates":[14.3614196777,46.7676582336],"type":"Point"}
}