{
  "type": "Feature",
  "properties": {
    "addr:full":"Rottwiese 65 Oberpullendorf Burgenland 7350",
    "addr:housenumber":"65",
    "addr:postcode":"7350",
    "addr:street":"Rottwiese",
    "iso:country":"AT",
    "sg:address":"Rottwiese 65",
    "sg:city":"Oberpullendorf",
    "sg:orig_category":"Abfallentsorgung U -Verwertung",
    "sg:phone":"+43 2612 421200",
    "sg:postcode":"7350",
    "sg:province":"Burgenland",
    "wof:name":"Umweltdienst Burgenland GmbH",
    "wof:placetype":"venue"
},
  "geometry": {"coordinates":[16.5261211395,47.4876327515],"type":"Point"}
}