{
  "type": "Feature",
  "properties": {
    "iso:country":"AT",
    "sg:address":"Novomaticstr 5",
    "sg:city":"Gumpoldskirchen",
    "sg:orig_category":"Rohrsanierungen",
    "sg:phone":"+43 2252 607020",
    "sg:postcode":"2352",
    "sg:province":"Nieder\u00f6sterreich",
    "wof:name":"Rohrsanierungs GmbH",
    "wof:placetype":"venue"
},
  "geometry": {"coordinates":[16.2881145477,48.0349082947],"type":"Point"}
}