{
  "type": "Feature",
  "properties": {
    "addr:full":"Industriestrasse 3 Persenbeug Nieder\u00f6sterreich 3680",
    "addr:housenumber":"3",
    "addr:postcode":"3680",
    "addr:street":"Industriestrasse",
    "iso:country":"AT",
    "sg:address":"Industriestrasse 3",
    "sg:city":"Persenbeug",
    "sg:classifiers":[
        {
            "category":"Banks & Credit Unions",
            "subcategory":"Bureau De Change",
            "type":"Services"
        }
    ],
    "sg:phone":"+43 7412 524880",
    "sg:postcode":"3680",
    "sg:province":"Nieder\u00f6sterreich",
    "sg:tags":[
        "flat",
        "construction",
        "roof"
    ],
    "wof:name":"Richter GmbH",
    "wof:placetype":"venue"
},
  "geometry": {"coordinates":[15.0793266296,48.1879043579],"type":"Point"}
}