{
  "type": "Feature",
  "properties": {
    "addr:full":"Schuselkagasse 8 Wien Wien 1150",
    "addr:housenumber":"8",
    "addr:postcode":"1150",
    "addr:street":"Schuselkagasse",
    "iso:country":"AT",
    "sg:address":"Schuselkagasse 8",
    "sg:city":"Wien",
    "sg:classifiers":[
        {
            "category":"Shopping",
            "subcategory":"Pharmacy",
            "type":"Retail Goods"
        }
    ],
    "sg:phone":"+43 1 98233990",
    "sg:postcode":"1150",
    "sg:province":"Wien",
    "sg:tags":[
        "lozenge"
    ],
    "wof:name":"Germania Pharmazeutika Ges.m.b.H.",
    "wof:placetype":"venue"
},
  "geometry": {"coordinates":[16.3199539185,48.1996994019],"type":"Point"}
}