{
  "type": "Feature",
  "properties": {
    "addr:full":"Sonnenfelsg 17 Wien Wien 1010",
    "addr:housenumber":"17",
    "addr:postcode":"1010",
    "addr:street":"Sonnenfelsg",
    "iso:country":"AT",
    "sg:address":"Sonnenfelsg 17",
    "sg:city":"Wien",
    "sg:classifiers":[
        {
            "category":"Restaurant",
            "type":"Food & Drink"
        }
    ],
    "sg:phone":"+43 1 5129871",
    "sg:postcode":"1010",
    "sg:province":"Wien",
    "wof:name":"Restaurant Bauer",
    "wof:placetype":"venue"
},
  "geometry": {"coordinates":[16.3769836426,48.2092475891],"type":"Point"}
}