{
  "type": "Feature",
  "properties": {
    "addr:full":"Suppanstr 69/1 Klagenfurt K\u00e4rnten 9020",
    "addr:housenumber":"69 / 1",
    "addr:postcode":"9020",
    "addr:street":"Suppanstr;Kaernten",
    "iso:country":"AT",
    "sg:address":"Suppanstr 69/1",
    "sg:city":"Klagenfurt",
    "sg:orig_category":"Anlagenbau U -Technik",
    "sg:phone":"+43 463 90610",
    "sg:postcode":"9020",
    "sg:province":"K\u00e4rnten",
    "wof:name":"Alpine-Energie Gesellschaft f elektrische und industrielle Unternehmungen GmbH & Co KG",
    "wof:placetype":"venue"
},
  "geometry": {"coordinates":[14.2942228317,46.6484870911],"type":"Point"}
}