{
  "type": "Feature",
  "properties": {
    "addr:full":"Bahnhofstr 4 Wieselburg an der Erlauf Nieder\u00f6sterreich 3250",
    "addr:housenumber":"4",
    "addr:postcode":"3250",
    "addr:street":"Bahnhofstr",
    "iso:country":"AT",
    "sg:address":"Bahnhofstr 4",
    "sg:city":"Wieselburg an der Erlauf",
    "sg:orig_category":"Farben U Lacke / Einzelhandel",
    "sg:phone":"+43 4374 1652383",
    "sg:postcode":"3250",
    "sg:province":"Nieder\u00f6sterreich",
    "wof:name":"Nemecek Gernot",
    "wof:placetype":"venue"
},
  "geometry": {"coordinates":[15.1396493912,48.1315498352],"type":"Point"}
}