{
  "type": "Feature",
  "properties": {
    "iso:country":"AT",
    "sg:address":"Dr. Karl Rennerstrasse 360",
    "sg:city":"Petronell",
    "sg:classifiers":[
        {
            "category":"Professional",
            "subcategory":"Printing & Photocopies",
            "type":"Services"
        }
    ],
    "sg:phone":"+43 1 6898311",
    "sg:postcode":"2404",
    "sg:province":"Nieder\u00f6sterreich",
    "sg:tags":[
        "print",
        "server"
    ],
    "sg:website":"troygroup.at",
    "wof:name":"Extended Systems Distribution GmbH",
    "wof:placetype":"venue"
},
  "geometry": {"coordinates":[16.8762607574,48.1124992371],"type":"Point"}
}