{
  "type": "Feature",
  "properties": {
    "addr:full":"Feldstr 11 Innsbruck Tirol 6020",
    "addr:housenumber":"11",
    "addr:postcode":"6020",
    "addr:street":"Feldstr;Tirol",
    "iso:country":"AT",
    "sg:address":"Feldstr 11",
    "sg:city":"Innsbruck",
    "sg:orig_category":"Weine / Gro\u00c3\u0178handel",
    "sg:phone":"+43 4351 2286533",
    "sg:postcode":"6020",
    "sg:province":"Tirol",
    "wof:name":"Winzer Krems regGenmbH",
    "wof:placetype":"venue"
},
  "geometry": {"coordinates":[11.3882789612,47.2544021606],"type":"Point"}
}