{
  "type": "Feature",
  "properties": {
    "addr:full":"Knappenpl 21/Top 13/FMZRosental Rosental an der Kainach Steiermark 8582",
    "addr:housenumber":"21 / top 13",
    "addr:postcode":"8582",
    "addr:street":"Knappenpl",
    "iso:country":"AT",
    "sg:address":"Knappenpl 21/Top 13/FMZRosental",
    "sg:city":"Rosental an der Kainach",
    "sg:orig_category":"Bekleidung / Einzelhandel",
    "sg:phone":"+43 4331 4226598",
    "sg:postcode":"8582",
    "sg:province":"Steiermark",
    "wof:name":"Sch\u00f6ps Richard & Co AG",
    "wof:placetype":"venue"
},
  "geometry": {"coordinates":[15.1137638092,47.0550537109],"type":"Point"}
}