{
  "type": "Feature",
  "properties": {
    "iso:country":"AT",
    "sg:address":"Verbandsweg 5",
    "sg:city":"Wien",
    "sg:orig_category":"Fernsehservice",
    "sg:phone":"+43 1 2807980",
    "sg:postcode":"1220",
    "sg:province":"Wien",
    "wof:name":"Fernseh-Bernhardt GesmbH Nfg KEG",
    "wof:placetype":"venue"
},
  "geometry": {"coordinates":[16.4677753448,48.2042427063],"type":"Point"}
}