{
  "type": "Feature",
  "properties": {
    "addr:full":"Romerstrasse  5",
    "addr:housenumber":"5",
    "addr:street":"Romerstrasse",
    "iso:country":"AT",
    "sg:address":"Romerstrasse ",
    "sg:classifiers":[
        {
            "category":"Travel",
            "subcategory":"Travel Agent",
            "type":"Entertainment"
        }
    ],
    "sg:postcode":"5",
    "wof:name":"Best Western Hotel Weisses Kreuz",
    "wof:placetype":"venue"
},
  "geometry": {"coordinates":[9.7460126877,47.50182724],"type":"Point"}
}