{
  "type": "Feature",
  "properties": {
    "addr:full":"Ringstrasse 5  Wels Ober\u00f6sterreich 4600",
    "addr:housenumber":"5",
    "addr:postcode":"4600",
    "addr:street":"Ringstrasse;Oberoesterreich",
    "iso:country":"AT",
    "sg:address":"Ringstrasse 5 ",
    "sg:city":"Wels",
    "sg:classifiers":[
        {
            "category":"Ice Cream",
            "type":"Food & Drink"
        }
    ],
    "sg:phone":"+43 7242 46678",
    "sg:postcode":"4600",
    "sg:province":"Ober\u00f6sterreich",
    "sg:tags":[
        "freezers",
        "chest",
        "deep",
        "freezer"
    ],
    "wof:name":"Elektro-Welt",
    "wof:placetype":"venue"
},
  "geometry": {"coordinates":[14.022236824,48.1577148438],"type":"Point"}
}