{
  "type": "Feature",
  "properties": {
    "addr:full":"Julius-Tandler-Pl 11 Wien Wien 1090",
    "addr:housenumber":"11",
    "addr:postcode":"1090",
    "addr:street":"Julius-Tandler-Pl",
    "iso:country":"AT",
    "sg:address":"Julius-Tandler-Pl 11",
    "sg:city":"Wien",
    "sg:orig_category":"Optiker",
    "sg:phone":"+43 1 3101671",
    "sg:postcode":"1090",
    "sg:province":"Wien",
    "wof:name":"Optik Maurer",
    "wof:placetype":"venue"
},
  "geometry": {"coordinates":[16.3607025146,48.2252464294],"type":"Point"}
}