{
  "type": "Feature",
  "properties": {
    "addr:full":"Zichygasse 8 Wien Wien 1140",
    "addr:housenumber":"8",
    "addr:postcode":"1140",
    "addr:street":"Zichygasse",
    "iso:country":"AT",
    "sg:address":"Zichygasse 8",
    "sg:city":"Wien",
    "sg:classifiers":[
        {
            "category":"Utilities",
            "subcategory":"Telephone",
            "type":"Services"
        }
    ],
    "sg:phone":"+43 4318 9579240",
    "sg:postcode":"1140",
    "sg:province":"Wien",
    "sg:tags":[
        "telecommunication"
    ],
    "wof:name":"SWARCO FUTURIT VERKEHRS- SIGNALSYSTEME GES.MBH",
    "wof:placetype":"venue"
},
  "geometry": {"coordinates":[16.3145084381,48.1908416748],"type":"Point"}
}