{
  "type": "Feature",
  "properties": {
    "iso:country":"AT",
    "sg:address":"Unterer Stadtpl 7",
    "sg:city":"Hall in Tirol",
    "sg:orig_category":"Banken U Sparkassen",
    "sg:phone":"+43 4352 23573490",
    "sg:postcode":"6060",
    "sg:province":"Tirol",
    "wof:name":"Bankomat",
    "wof:placetype":"venue"
},
  "geometry": {"coordinates":[11.5066823959,47.2805404663],"type":"Point"}
}