{
  "type": "Feature",
  "properties": {
    "addr:full":"Nr 78 Gnesau K\u00e4rnten 9563",
    "addr:postcode":"9563",
    "addr:street":"Nr 78 Gnesau Kaernten",
    "iso:country":"AT",
    "sg:address":"Nr 78",
    "sg:city":"Gnesau",
    "sg:orig_category":"Banken U Sparkassen",
    "sg:phone":"+43 4278 2930",
    "sg:postcode":"9563",
    "sg:province":"K\u00e4rnten",
    "wof:name":"Raiffeisenbank Reichenau-Gnesau regGenmbH",
    "wof:placetype":"venue"
},
  "geometry": {"coordinates":[13.962677002,46.7755317688],"type":"Point"}
}