{
  "type": "Feature",
  "properties": {
    "addr:full":"Oberwinkl 64a Elsbethen-Glasenbach Salzburg 5061",
    "addr:housenumber":"64a",
    "addr:postcode":"5061",
    "addr:street":"Oberwinkl;Salzburg",
    "iso:country":"AT",
    "sg:address":"Oberwinkl 64a",
    "sg:city":"Elsbethen-Glasenbach",
    "sg:orig_category":"Sprengungen",
    "sg:phone":"+43 662 650881",
    "sg:postcode":"5061",
    "sg:province":"Salzburg",
    "wof:name":"Steindl Peter",
    "wof:placetype":"venue"
},
  "geometry": {"coordinates":[13.1343765259,47.7958374023],"type":"Point"}
}