{
  "type": "Feature",
  "properties": {
    "addr:full":"Engelhorngasse 3 Wien Wien 1210",
    "addr:housenumber":"3",
    "addr:postcode":"1210",
    "addr:street":"Engelhorngasse",
    "iso:country":"AT",
    "sg:address":"Engelhorngasse 3",
    "sg:city":"Wien",
    "sg:classifiers":[
        {
            "category":"Wholesale",
            "subcategory":"Drugs",
            "type":"Manufacturing & Wholesale Goods"
        }
    ],
    "sg:phone":"+43 1 277390",
    "sg:postcode":"1210",
    "sg:province":"Wien",
    "sg:tags":[
        "antibiotic"
    ],
    "sg:website":"roche.at",
    "wof:name":"Roche Austria GmbH",
    "wof:placetype":"venue"
},
  "geometry": {"coordinates":[16.4088573456,48.2601699829],"type":"Point"}
}