{
  "type": "Feature",
  "properties": {
    "iso:country":"AT",
    "sg:address":"Meister Klieber-G 33",
    "sg:city":"Perchtoldsdorf",
    "sg:orig_category":"Etuis",
    "sg:phone":"+43 664 2021076",
    "sg:postcode":"2380",
    "sg:province":"Nieder\u00f6sterreich",
    "wof:name":"ITAL-Etui",
    "wof:placetype":"venue"
},
  "geometry": {"coordinates":[16.2770786285,48.1319007874],"type":"Point"}
}