{
  "type": "Feature",
  "properties": {
    "iso:country":"AT",
    "sg:address":"Liechtensteinstr 3-5",
    "sg:city":"Murau",
    "sg:orig_category":"Psychotherapie",
    "sg:phone":"+43 664 2114716",
    "sg:postcode":"8850",
    "sg:province":"Steiermark",
    "wof:name":"H\u00fcbler Heimo Mag",
    "wof:placetype":"venue"
},
  "geometry": {"coordinates":[14.1714687347,47.1101341248],"type":"Point"}
}