{
  "type": "Feature",
  "properties": {
    "iso:country":"AT",
    "sg:address":"Felixdorfer G 40",
    "sg:city":"Wiener Neustadt",
    "sg:orig_category":"Fliesen- U Plattenverlegungen",
    "sg:phone":"+43 4326 22278120",
    "sg:postcode":"2700",
    "sg:province":"Nieder\u00f6sterreich",
    "wof:name":"Kampichler J & J GesmbH",
    "wof:placetype":"venue"
},
  "geometry": {"coordinates":[16.2390708923,47.8448410034],"type":"Point"}
}