{
  "type": "Feature",
  "properties": {
    "addr:full":"Hauxmoos 14 Wolfsegg am Hausruck Ober\u00f6sterreich 4902",
    "addr:housenumber":"14",
    "addr:postcode":"4902",
    "addr:street":"Hauxmoos",
    "iso:country":"AT",
    "sg:address":"Hauxmoos 14",
    "sg:city":"Wolfsegg am Hausruck",
    "sg:classifiers":[
        {
            "category":"Wholesale",
            "subcategory":"Plants",
            "type":"Manufacturing & Wholesale Goods"
        }
    ],
    "sg:phone":"+43 76768653",
    "sg:postcode":"4902",
    "sg:province":"Ober\u00f6sterreich",
    "sg:tags":[
        "supraregional",
        "geothermal",
        "installation",
        "heating"
    ],
    "wof:name":"Bachmayr GmbH",
    "wof:placetype":"venue"
},
  "geometry": {"coordinates":[13.7124147415,48.1149787903],"type":"Point"}
}