{
  "type": "Feature",
  "properties": {
    "addr:full":"Haydnstr 14 Auersthal Nieder\u00f6sterreich 2214",
    "addr:housenumber":"14",
    "addr:postcode":"2214",
    "addr:street":"Haydnstr",
    "iso:country":"AT",
    "sg:address":"Haydnstr 14",
    "sg:city":"Auersthal",
    "sg:classifiers":[
        {
            "category":"Retail",
            "subcategory":"Event Space",
            "type":"Services"
        }
    ],
    "sg:phone":"+43 4322 882360",
    "sg:postcode":"2214",
    "sg:province":"Nieder\u00f6sterreich",
    "sg:tags":[
        "hand-",
        "u",
        "fu\u00c3\u0178pflege"
    ],
    "wof:name":"Wiesner Christine",
    "wof:placetype":"venue"
},
  "geometry": {"coordinates":[16.6218948364,48.3793067932],"type":"Point"}
}