{
  "type": "Feature",
  "properties": {
    "addr:full":"Gschwandt 163 Bad Goisern Ober\u00f6sterreich 4822",
    "addr:housenumber":"163",
    "addr:postcode":"4822",
    "addr:street":"Gschwandt",
    "iso:country":"AT",
    "sg:address":"Gschwandt 163",
    "sg:city":"Bad Goisern",
    "sg:orig_category":"Fleischhauereien",
    "sg:phone":"+43 4361 3541231",
    "sg:postcode":"4822",
    "sg:province":"Ober\u00f6sterreich",
    "wof:name":"Salzkammergut Back- u Fleischwaren GesmbH",
    "wof:placetype":"venue"
},
  "geometry": {"coordinates":[13.6225156784,47.6323013306],"type":"Point"}
}