{
  "type": "Feature",
  "properties": {
    "addr:full":"Handberg 113 Waldhausen im Strudengau Ober\u00f6sterreich 4391",
    "addr:housenumber":"113",
    "addr:postcode":"4391",
    "addr:street":"Handberg",
    "iso:country":"AT",
    "sg:address":"Handberg 113",
    "sg:city":"Waldhausen im Strudengau",
    "sg:orig_category":"Elektroinstallationsunternehmen",
    "sg:phone":"+43 7260 45140",
    "sg:postcode":"4391",
    "sg:province":"Ober\u00f6sterreich",
    "wof:name":"Lenz Josef",
    "wof:placetype":"venue"
},
  "geometry": {"coordinates":[14.9564037323,48.2801437378],"type":"Point"}
}