{
  "type": "Feature",
  "properties": {
    "iso:country":"AT",
    "sg:address":"Linzer Str 1",
    "sg:city":"Bad Schallerbach",
    "sg:orig_category":"Lebensmittel / Einzelhandel",
    "sg:phone":"+43 7249 49149",
    "sg:postcode":"4701",
    "sg:province":"Ober\u00f6sterreich",
    "wof:name":"Spar-Markt Inh Walter Bauer",
    "wof:placetype":"venue"
},
  "geometry": {"coordinates":[13.9216108322,48.2309455872],"type":"Point"}
}