{
  "type": "Feature",
  "properties": {
    "addr:full":"Industriestr 2h Freistadt Ober\u00f6sterreich 4240",
    "addr:postcode":"4240",
    "addr:street":"Oberoesterreich",
    "iso:country":"AT",
    "sg:address":"Industriestr 2h",
    "sg:city":"Freistadt",
    "sg:orig_category":"Friseure U Frisiersalons",
    "sg:phone":"+43 4379 4272545",
    "sg:postcode":"4240",
    "sg:province":"Ober\u00f6sterreich",
    "wof:name":"Figaro Uno",
    "wof:placetype":"venue"
},
  "geometry": {"coordinates":[14.5021314621,48.4971580505],"type":"Point"}
}