{
  "type": "Feature",
  "properties": {
    "addr:full":"Museumspl 4 Salzburg Salzburg 5020",
    "addr:housenumber":"4",
    "addr:postcode":"5020",
    "addr:street":"Museumspl;Salzburg",
    "iso:country":"AT",
    "sg:address":"Museumspl 4",
    "sg:city":"Salzburg",
    "sg:orig_category":"Schwangerenberatung / Geburtsvorbereitung",
    "sg:phone":"+43 4366 280422887",
    "sg:postcode":"5020",
    "sg:province":"Salzburg",
    "wof:name":"Elternberatung",
    "wof:placetype":"venue"
},
  "geometry": {"coordinates":[13.0390863419,47.8013458252],"type":"Point"}
}