{
  "type": "Feature",
  "properties": {
    "addr:full":"Benediktinerpl 23 Klagenfurt K\u00e4rnten 9020",
    "addr:housenumber":"23",
    "addr:postcode":"9020",
    "addr:street":"Benediktinerpl;Kaernten",
    "iso:country":"AT",
    "sg:address":"Benediktinerpl 23",
    "sg:city":"Klagenfurt",
    "sg:orig_category":"Fische U Fischwaren / Erzeugung U Gro\u00c3\u0178handel",
    "sg:phone":"+43 463 514061",
    "sg:postcode":"9020",
    "sg:province":"K\u00e4rnten",
    "wof:name":"Adria Fisch Import GesmbH - La Pescheria",
    "wof:placetype":"venue"
},
  "geometry": {"coordinates":[14.3066396713,46.6225013733],"type":"Point"}
}