{
  "type": "Feature",
  "properties": {
    "addr:full":"Obere Akazieng 25 Apetlon Burgenland 7143",
    "addr:housenumber":"25",
    "addr:postcode":"7143",
    "addr:street":"Obere Akazieng",
    "iso:country":"AT",
    "sg:address":"Obere Akazieng 25",
    "sg:city":"Apetlon",
    "sg:orig_category":"Pensionen / Privatzimmer",
    "sg:phone":"+43 2175 2397",
    "sg:postcode":"7143",
    "sg:province":"Burgenland",
    "wof:name":"Pension Gerlinde Koppi",
    "wof:placetype":"venue"
},
  "geometry": {"coordinates":[16.8380146027,47.745349884],"type":"Point"}
}