{
  "type": "Feature",
  "properties": {
    "addr:full":"Seestr 36 Hard Vorarlberg 6971",
    "addr:housenumber":"36",
    "addr:postcode":"6971",
    "addr:street":"Seestr",
    "iso:country":"AT",
    "sg:address":"Seestr 36",
    "sg:city":"Hard",
    "sg:orig_category":"Sportanlagen",
    "sg:phone":"+43 650 6970055",
    "sg:postcode":"6971",
    "sg:province":"Vorarlberg",
    "wof:name":"Seesportanlage",
    "wof:placetype":"venue"
},
  "geometry": {"coordinates":[9.6839199066,47.4908981323],"type":"Point"}
}