{
  "type": "Feature",
  "properties": {
    "addr:full":"Johannes-Filzer-Str 28 Salzburg Salzburg 5020",
    "addr:housenumber":"28",
    "addr:postcode":"5020",
    "addr:street":"Johannes-Filzer-Str;Salzburg",
    "iso:country":"AT",
    "sg:address":"Johannes-Filzer-Str 28",
    "sg:city":"Salzburg",
    "sg:orig_category":"Marketingberatung",
    "sg:phone":"+43 4366 2831841",
    "sg:postcode":"5020",
    "sg:province":"Salzburg",
    "wof:name":"Weisl Helmut",
    "wof:placetype":"venue"
},
  "geometry": {"coordinates":[13.0675382614,47.7938461304],"type":"Point"}
}