{
  "type": "Feature",
  "properties": {
    "addr:full":"St. Georgener Str 10 Villach K\u00e4rnten 9500",
    "addr:housenumber":"10",
    "addr:postcode":"9500",
    "addr:street":"St. Georgener Str;Kaernten",
    "iso:country":"AT",
    "sg:address":"St. Georgener Str 10",
    "sg:city":"Villach",
    "sg:orig_category":"Transportunternehmen",
    "sg:phone":"+43 4242 593000",
    "sg:postcode":"9500",
    "sg:province":"K\u00e4rnten",
    "wof:name":"Stechauner Max TransportgesmbH",
    "wof:placetype":"venue"
},
  "geometry": {"coordinates":[13.8136825562,46.6278114319],"type":"Point"}
}