{
  "type": "Feature",
  "properties": {
    "addr:full":"Wehlistr 366/2 Wien Wien 1020",
    "addr:housenumber":"366 / 2",
    "addr:postcode":"1020",
    "iso:country":"AT",
    "sg:address":"Wehlistr 366/2",
    "sg:city":"Wien",
    "sg:orig_category":"Psychologen",
    "sg:phone":"+43 1 7208483",
    "sg:postcode":"1020",
    "sg:province":"Wien",
    "wof:name":"Beiglb\u00f6ck Wolfgang Dr",
    "wof:placetype":"venue"
},
  "geometry": {"coordinates":[16.4349250793,48.2026824951],"type":"Point"}
}