{
  "type": "Feature",
  "properties": {
    "iso:country":"AT",
    "sg:address":"Brunneng 62",
    "sg:city":"Wien",
    "sg:orig_category":"Fleischhauereien",
    "sg:phone":"+43 1 4064715",
    "sg:postcode":"1160",
    "sg:province":"Wien",
    "wof:name":"Sterkl Eva & Sohn",
    "wof:placetype":"venue"
},
  "geometry": {"coordinates":[16.3366222382,48.2127761841],"type":"Point"}
}