{
  "type": "Feature",
  "properties": {
    "addr:full":"Dinghoferstr 5 Ottensheim Ober\u00f6sterreich 4100",
    "addr:housenumber":"5",
    "addr:postcode":"4100",
    "addr:street":"Dinghoferstr",
    "iso:country":"AT",
    "sg:address":"Dinghoferstr 5",
    "sg:city":"Ottensheim",
    "sg:orig_category":"Volkshochschulen",
    "sg:phone":"+43 4365 02700727",
    "sg:postcode":"4100",
    "sg:province":"Ober\u00f6sterreich",
    "wof:name":"Volkshochschule Ottensheim",
    "wof:placetype":"venue"
},
  "geometry": {"coordinates":[14.1729803085,48.3369369507],"type":"Point"}
}