{
  "type": "Feature",
  "properties": {
    "iso:country":"AT",
    "sg:address":"Deutschg 1",
    "sg:city":"Wiener Neustadt",
    "sg:orig_category":"Biologische Produkte",
    "sg:phone":"+43 2622 81050",
    "sg:postcode":"2700",
    "sg:province":"Nieder\u00f6sterreich",
    "wof:name":"OM Namah - der Naturladen",
    "wof:placetype":"venue"
},
  "geometry": {"coordinates":[16.2444953918,47.8155250549],"type":"Point"}
}