{
  "type": "Feature",
  "properties": {
    "iso:country":"AT",
    "sg:address":"Wilhelm-Exner-G 13",
    "sg:city":"Wien",
    "sg:orig_category":"Lebensmittel / Einzelhandel",
    "sg:phone":"+43 1 9612935",
    "sg:postcode":"1090",
    "sg:province":"Wien",
    "wof:name":"EMMA Otto",
    "wof:placetype":"venue"
},
  "geometry": {"coordinates":[16.3521308899,48.2242469788],"type":"Point"}
}