{
  "type": "Feature",
  "properties": {
    "iso:country":"AT",
    "sg:address":"Bahnhofstr 2",
    "sg:city":"Zell am See",
    "sg:orig_category":"Spielwaren U Spiele",
    "sg:phone":"+43 4365 4272232",
    "sg:postcode":"5700",
    "sg:province":"Salzburg",
    "wof:name":"KiMoKo Kindermoden - Spielwaren Koller Inh Rieder Kindermoden KG",
    "wof:placetype":"venue"
},
  "geometry": {"coordinates":[12.7980442047,47.3230857849],"type":"Point"}
}