{
  "type": "Feature",
  "properties": {
    "iso:country":"AT",
    "sg:address":"Schillinghofstrasse 36",
    "sg:city":"Gnigl",
    "sg:orig_category":"Cardboard Registers",
    "sg:phone":"+43 662 643083",
    "sg:postcode":"5023",
    "sg:province":"Salzburg",
    "wof:name":"Karl Winkler",
    "wof:placetype":"venue"
},
  "geometry": {"coordinates":[13.0654087067,47.8193817139],"type":"Point"}
}