{
  "type": "Feature",
  "properties": {
    "addr:full":"Morellenfeldg 15 Graz Steiermark 8010",
    "addr:housenumber":"15",
    "addr:postcode":"8010",
    "addr:street":"Morellenfeldg",
    "iso:country":"AT",
    "sg:address":"Morellenfeldg 15",
    "sg:city":"Graz",
    "sg:orig_category":"Friseure U Frisiersalons",
    "sg:phone":"+43 316 372262",
    "sg:postcode":"8010",
    "sg:province":"Steiermark",
    "wof:name":"Hair & Care Corner Krebs OEG",
    "wof:placetype":"venue"
},
  "geometry": {"coordinates":[15.4533843994,47.0704116821],"type":"Point"}
}