{
  "type": "Feature",
  "properties": {
    "iso:country":"AT",
    "sg:address":"Daulumweg 4",
    "sg:city":"Gummern",
    "sg:classifiers":[
        {
            "category":"Personal",
            "subcategory":"Sauna",
            "type":"Services"
        }
    ],
    "sg:phone":"+43 4342 588194",
    "sg:postcode":"9722",
    "sg:province":"K\u00e4rnten",
    "sg:tags":[
        "u",
        "dampfbad"
    ],
    "wof:name":"SCHWITZKASTL Sauna-Solarium-Massage",
    "wof:placetype":"venue"
},
  "geometry": {"coordinates":[13.7566080093,46.6640281677],"type":"Point"}
}