{
  "type": "Feature",
  "properties": {
    "iso:country":"AT",
    "sg:address":"Muhrengasse 57/12",
    "sg:city":"Wien",
    "sg:classifiers":[
        {
            "category":"Manufacturing",
            "subcategory":"Signs",
            "type":"Manufacturing & Wholesale Goods"
        }
    ],
    "sg:phone":"+43 1 6007582",
    "sg:postcode":"1100",
    "sg:province":"Wien",
    "sg:tags":[
        "display"
    ],
    "sg:website":"display-technik.at",
    "wof:name":"Disp & Tech Ing. Heinrich Schuster",
    "wof:placetype":"venue"
},
  "geometry": {"coordinates":[16.3721027374,48.169216156],"type":"Point"}
}