{
  "type": "Feature",
  "properties": {
    "addr:full":"Nr 182 Gaishorn am See Steiermark 8783",
    "addr:postcode":"8783",
    "addr:street":"Nr 182 Gaishorn Am See Steiermark",
    "iso:country":"AT",
    "sg:address":"Nr 182",
    "sg:city":"Gaishorn am See",
    "sg:orig_category":"Holzwaren",
    "sg:phone":"+43 3617 21510",
    "sg:postcode":"8783",
    "sg:province":"Steiermark",
    "wof:name":"Systemholz AG & Co KG",
    "wof:placetype":"venue"
},
  "geometry": {"coordinates":[14.5492944717,47.4914245605],"type":"Point"}
}