{
  "type": "Feature",
  "properties": {
    "addr:full":"Canisiusg 21 Wien Wien 1090",
    "addr:housenumber":"21",
    "addr:postcode":"1090",
    "addr:street":"Canisiusg",
    "iso:country":"AT",
    "sg:address":"Canisiusg 21",
    "sg:city":"Wien",
    "sg:orig_category":"Werbegrafik- U Grafik-Design",
    "sg:phone":"+43 4313 107796",
    "sg:postcode":"1090",
    "sg:province":"Wien",
    "wof:name":"Mackinger Thomas-Tom Illustration",
    "wof:placetype":"venue"
},
  "geometry": {"coordinates":[16.3520259857,48.2279510498],"type":"Point"}
}