{
  "type": "Feature",
  "properties": {
    "iso:country":"AT",
    "sg:address":"Nr 45",
    "sg:city":"Seewiesen",
    "sg:classifiers":[
        {
            "category":"Travel",
            "subcategory":"Hotels & Motels",
            "type":"Entertainment"
        }
    ],
    "sg:phone":"+43 3863 8115",
    "sg:postcode":"8636",
    "sg:province":"Steiermark",
    "wof:name":"Hotel-Restaurant Seeberghof",
    "wof:placetype":"venue"
},
  "geometry": {"coordinates":[15.2714700699,47.6204414368],"type":"Point"}
}