{
  "type": "Feature",
  "properties": {
    "iso:country":"AT",
    "sg:address":"Kleine Sperlg 2a",
    "sg:city":"Wien",
    "sg:orig_category":"Hauptschulen",
    "sg:phone":"+43 1 2165335211",
    "sg:postcode":"1020",
    "sg:province":"Wien",
    "wof:name":"Schulen d Stadt Wien",
    "wof:placetype":"venue"
},
  "geometry": {"coordinates":[16.3776664734,48.2159538269],"type":"Point"}
}