{
  "type": "Feature",
  "properties": {
    "addr:full":"Karlg 3/1 Villach K\u00e4rnten 9500",
    "addr:housenumber":"3 / 1",
    "addr:postcode":"9500",
    "addr:street":"Karlg;Kaernten",
    "iso:country":"AT",
    "sg:address":"Karlg 3/1",
    "sg:city":"Villach",
    "sg:orig_category":"Familien / Beratung",
    "sg:phone":"+43 4242 21352",
    "sg:postcode":"9500",
    "sg:province":"K\u00e4rnten",
    "wof:name":"Institut f Familienberatung und Psychotherapie (IFP)",
    "wof:placetype":"venue"
},
  "geometry": {"coordinates":[13.8491945267,46.618106842],"type":"Point"}
}