{
  "type": "Feature",
  "properties": {
    "iso:country":"AT",
    "sg:address":"Nr 47",
    "sg:city":"Spitz",
    "sg:orig_category":"Musikgruppen",
    "sg:phone":"+43 4366 43816410",
    "sg:postcode":"3620",
    "sg:province":"Nieder\u00f6sterreich",
    "wof:name":"Toreros & Senorita - Johann Stierschneider",
    "wof:placetype":"venue"
},
  "geometry": {"coordinates":[15.4138097763,48.365776062],"type":"Point"}
}