{
  "type": "Feature",
  "properties": {
    "iso:country":"AT",
    "sg:address":"Nr 18",
    "sg:city":"Wundschuh",
    "sg:orig_category":"Maler, Anstreicher U Lackierer",
    "sg:phone":"+43 664 4406723",
    "sg:postcode":"8142",
    "sg:province":"Steiermark",
    "wof:name":"Malereibetrieb Ehmann Raimund",
    "wof:placetype":"venue"
},
  "geometry": {"coordinates":[15.4498796463,46.9254493713],"type":"Point"}
}