{
  "type": "Feature",
  "properties": {
    "iso:country":"AT",
    "sg:address":"Krottendorf 70",
    "sg:city":"Kirchham",
    "sg:classifiers":[
        {
            "category":"Taxi",
            "type":"Transportation"
        }
    ],
    "sg:phone":"+43 76191711",
    "sg:postcode":"4656",
    "sg:province":"Ober\u00f6sterreich",
    "sg:tags":[
        "personentransporte",
        "u"
    ],
    "wof:name":"Attwenger Norbert",
    "wof:placetype":"venue"
},
  "geometry": {"coordinates":[13.8794260025,47.9475860596],"type":"Point"}
}