{
  "type": "Feature",
  "properties": {
    "addr:full":"Graben 60 Amstetten Nieder\u00f6sterreich 3300",
    "addr:housenumber":"60",
    "addr:postcode":"3300",
    "addr:street":"Graben;Niederoesterreich",
    "iso:country":"AT",
    "sg:address":"Graben 60",
    "sg:city":"Amstetten",
    "sg:orig_category":"Bankomat-Standorte",
    "sg:phone":"+43 7472 644610",
    "sg:postcode":"3300",
    "sg:province":"Nieder\u00f6sterreich",
    "wof:name":"Bankomat der PSK 3300 Amstetten",
    "wof:placetype":"venue"
},
  "geometry": {"coordinates":[14.8792819977,48.1218566895],"type":"Point"}
}