{
  "type": "Feature",
  "properties": {
    "addr:full":"Kirchdorf 203 Doren Vorarlberg 6933",
    "addr:housenumber":"203",
    "addr:postcode":"6933",
    "addr:street":"Kirchdorf",
    "iso:country":"AT",
    "sg:address":"Kirchdorf 203",
    "sg:city":"Doren",
    "sg:orig_category":"Gesundheitsvorsorge",
    "sg:phone":"+43 4366 42614686",
    "sg:postcode":"6933",
    "sg:province":"Vorarlberg",
    "wof:name":"Wellness",
    "wof:placetype":"venue"
},
  "geometry": {"coordinates":[9.8796796799,47.4928436279],"type":"Point"}
}