{
  "type": "Feature",
  "properties": {
    "addr:full":"Dietrichg 17 Wien Wien 1030",
    "addr:housenumber":"17",
    "addr:postcode":"1030",
    "addr:street":"Dietrichg",
    "iso:country":"AT",
    "sg:address":"Dietrichg 17",
    "sg:city":"Wien",
    "sg:orig_category":"Bankomat-Standorte",
    "sg:phone":"+43 1 71542640",
    "sg:postcode":"1030",
    "sg:province":"Wien",
    "wof:name":"Bankomat d Bank f Arbeit und Wirtschaft AG",
    "wof:placetype":"venue"
},
  "geometry": {"coordinates":[16.4015445709,48.200630188],"type":"Point"}
}