{
  "type": "Feature",
  "properties": {
    "iso:country":"AT",
    "sg:address":"Baumschulg 37",
    "sg:city":"Hartberg",
    "sg:orig_category":"Handelsagenturen",
    "sg:phone":"+43 3332 64641",
    "sg:postcode":"8230",
    "sg:province":"Steiermark",
    "wof:name":"Perstling Christian",
    "wof:placetype":"venue"
},
  "geometry": {"coordinates":[15.982843399,47.2907562256],"type":"Point"}
}