{
  "type": "Feature",
  "properties": {
    "iso:country":"AT",
    "sg:address":"Kirchenpl 5",
    "sg:city":"Wien",
    "sg:orig_category":"Fassadenanstriche",
    "sg:phone":"+43 4318 697091",
    "sg:postcode":"1230",
    "sg:province":"Wien",
    "wof:name":"Schaffarik Kurt",
    "wof:placetype":"venue"
},
  "geometry": {"coordinates":[16.2951774597,48.1473617554],"type":"Point"}
}