{
  "type": "Feature",
  "properties": {
    "iso:country":"AT",
    "sg:address":"Seebacher Str 46",
    "sg:city":"Lieserbr\u00fccke",
    "sg:orig_category":"Tischlereien",
    "sg:phone":"+43 4762 37953",
    "sg:postcode":"9851",
    "sg:province":"K\u00e4rnten",
    "wof:name":"Schwarzenbacher Wilhelm",
    "wof:placetype":"venue"
},
  "geometry": {"coordinates":[13.4989509583,46.8238143921],"type":"Point"}
}