{
  "type": "Feature",
  "properties": {
    "addr:full":"Montecuccolipl 12 Wien Wien 1130",
    "addr:housenumber":"12",
    "addr:postcode":"1130",
    "addr:street":"Montecuccolipl",
    "iso:country":"AT",
    "sg:address":"Montecuccolipl 12",
    "sg:city":"Wien",
    "sg:orig_category":"Ingenieurkonsulenten / Zivilingenieure",
    "sg:phone":"+43 1 8762876",
    "sg:postcode":"1130",
    "sg:province":"Wien",
    "wof:name":"Baumgartner Hans Prof Dipl-Ing",
    "wof:placetype":"venue"
},
  "geometry": {"coordinates":[16.2968101501,48.1759376526],"type":"Point"}
}