{
  "type": "Feature",
  "properties": {
    "addr:full":"Tuxer Str 708 Mayrhofen Tirol 6290",
    "addr:housenumber":"708",
    "addr:postcode":"6290",
    "addr:street":"Str;Tirol",
    "iso:country":"AT",
    "sg:address":"Tuxer Str 708",
    "sg:city":"Mayrhofen",
    "sg:orig_category":"Pensionen / Privatzimmer",
    "sg:phone":"+43 5285 62307",
    "sg:postcode":"6290",
    "sg:province":"Tirol",
    "wof:name":"G\u00e4stehaus Vierjahreszeiten",
    "wof:placetype":"venue"
},
  "geometry": {"coordinates":[11.8590240479,47.1618270874],"type":"Point"}
}