{
  "type": "Feature",
  "properties": {
    "addr:full":"Walgaustr 83 Schlins Vorarlberg 6824",
    "addr:housenumber":"83",
    "addr:postcode":"6824",
    "addr:street":"Walgaustr",
    "iso:country":"AT",
    "sg:address":"Walgaustr 83",
    "sg:city":"Schlins",
    "sg:orig_category":"Musikgruppen",
    "sg:phone":"+43 4355 242599",
    "sg:postcode":"6824",
    "sg:province":"Vorarlberg",
    "wof:name":"Musikduo Heli u Manuela",
    "wof:placetype":"venue"
},
  "geometry": {"coordinates":[9.7025852203,47.1987686157],"type":"Point"}
}