{
  "type": "Feature",
  "properties": {
    "addr:full":"Maxingstr 22-24/Stg 2 Wien Wien 1130",
    "addr:housenumber":"22-24 / stg 2",
    "addr:postcode":"1130",
    "iso:country":"AT",
    "sg:address":"Maxingstr 22-24/Stg 2",
    "sg:city":"Wien",
    "sg:orig_category":"Hydrokulturen",
    "sg:phone":"+43 1 8770043",
    "sg:postcode":"1130",
    "sg:province":"Wien",
    "wof:name":"NATCON Nature Construction Sima GmbH & Co KG",
    "wof:placetype":"venue"
},
  "geometry": {"coordinates":[16.3013801575,48.18592453],"type":"Point"}
}