{
  "type": "Feature",
  "properties": {
    "iso:country":"AT",
    "sg:address":"Kircheng 13",
    "sg:city":"Traiskirchen",
    "sg:orig_category":"Botendienste",
    "sg:phone":"+43 664 1131033",
    "sg:postcode":"2514",
    "sg:province":"Nieder\u00f6sterreich",
    "wof:name":"Fenz Express",
    "wof:placetype":"venue"
},
  "geometry": {"coordinates":[16.2947597504,48.0166664124],"type":"Point"}
}