{
  "type": "Feature",
  "properties": {
    "iso:country":"AT",
    "sg:address":"Hauptstr 78",
    "sg:city":"Eggersdorf",
    "sg:orig_category":"Transportunternehmen",
    "sg:phone":"+43 4331 172371",
    "sg:postcode":"8063",
    "sg:province":"Steiermark",
    "wof:name":"Sch\u00f6ngrundner GmbH",
    "wof:placetype":"venue"
},
  "geometry": {"coordinates":[15.5885648727,47.1243247986],"type":"Point"}
}