{
  "type": "Feature",
  "properties": {
    "addr:full":"Schottenring 25 Wien Wien 1010",
    "addr:housenumber":"25",
    "addr:postcode":"1010",
    "addr:street":"Schottenring",
    "iso:country":"AT",
    "sg:address":"Schottenring 25",
    "sg:city":"Wien",
    "sg:orig_category":"Schlankheitsinstitute",
    "sg:phone":"+43 1 3193191",
    "sg:postcode":"1010",
    "sg:province":"Wien",
    "wof:name":"Slenderlife",
    "wof:placetype":"venue"
},
  "geometry": {"coordinates":[16.3678226471,48.21667099],"type":"Point"}
}