{
  "type": "Feature",
  "properties": {
    "iso:country":"AT",
    "sg:address":"Steinhaus 100",
    "sg:city":"Steinhaus",
    "sg:classifiers":[
        {
            "category":"Building & Trades",
            "subcategory":"Electrical",
            "type":"Services"
        }
    ],
    "sg:phone":"+43 7242 27023",
    "sg:postcode":"4641",
    "sg:province":"Ober\u00f6sterreich",
    "sg:tags":[
        "installation"
    ],
    "sg:website":"elektro-schuerz.at",
    "wof:name":"Christian Sch\u00fcrz",
    "wof:placetype":"venue"
},
  "geometry": {"coordinates":[14.0210113525,48.1150779724],"type":"Point"}
}