{
  "type": "Feature",
  "properties": {
    "addr:full":"Adalbert Stifter-Str 35/3 Wien Wien 1200",
    "addr:housenumber":"35 / 3",
    "addr:postcode":"1200",
    "addr:street":"Adalbert",
    "iso:country":"AT",
    "sg:address":"Adalbert Stifter-Str 35/3",
    "sg:city":"Wien",
    "sg:orig_category":"Installationsunternehmen",
    "sg:phone":"+43 699 19253361",
    "sg:postcode":"1200",
    "sg:province":"Wien",
    "wof:name":"MBA Montage GmbH - L\u00fcftungs-, Klima- und Anlagenmontage",
    "wof:placetype":"venue"
},
  "geometry": {"coordinates":[16.3711795807,48.2412490845],"type":"Point"}
}