{
  "type": "Feature",
  "properties": {
    "addr:full":"Kirchenpl 9 Natternbach Ober\u00f6sterreich 4723",
    "addr:housenumber":"9",
    "addr:postcode":"4723",
    "addr:street":"Kirchenpl",
    "iso:country":"AT",
    "sg:address":"Kirchenpl 9",
    "sg:city":"Natternbach",
    "sg:orig_category":"Blumeneinzelhandel",
    "sg:phone":"+43 7278 8644",
    "sg:postcode":"4723",
    "sg:province":"Ober\u00f6sterreich",
    "wof:name":"Blumen Prohaska",
    "wof:placetype":"venue"
},
  "geometry": {"coordinates":[13.7492380142,48.3978767395],"type":"Point"}
}