{
  "type": "Feature",
  "properties": {
    "iso:country":"AT",
    "sg:address":"Schlagberg 15",
    "sg:city":"Ottensheim",
    "sg:orig_category":"Direktmarketing",
    "sg:phone":"+43 4372 34847110",
    "sg:postcode":"4100",
    "sg:province":"Ober\u00f6sterreich",
    "wof:name":"Meiller Druck u VerlagsgmbH \u00d6sterreich",
    "wof:placetype":"venue"
},
  "geometry": {"coordinates":[14.2156705856,48.3423843384],"type":"Point"}
}