{
  "type": "Feature",
  "properties": {
    "addr:full":"Nr 16f Wattens Tirol 6112",
    "addr:housenumber":"16f",
    "addr:postcode":"6112",
    "addr:street":"Nr;Tirol",
    "iso:country":"AT",
    "sg:address":"Nr 16f",
    "sg:city":"Wattens",
    "sg:orig_category":"Transportunternehmen",
    "sg:phone":"+43 4366 42005109",
    "sg:postcode":"6112",
    "sg:province":"Tirol",
    "wof:name":"Knab Johann",
    "wof:placetype":"venue"
},
  "geometry": {"coordinates":[11.6057186127,47.2733573914],"type":"Point"}
}