{
  "type": "Feature",
  "properties": {
    "iso:country":"AT",
    "sg:address":"Bilgeristr 24",
    "sg:city":"Innsbruck-Igls",
    "sg:classifiers":[
        {
            "category":"Travel",
            "subcategory":"Hotels & Motels",
            "type":"Entertainment"
        }
    ],
    "sg:phone":"+43 512 377649",
    "sg:postcode":"6080",
    "sg:province":"Tirol",
    "wof:name":"Berghotel Patscherkofel",
    "wof:placetype":"venue"
},
  "geometry": {"coordinates":[11.4135160446,47.2296333313],"type":"Point"}
}