{
  "type": "Feature",
  "properties": {
    "iso:country":"AT",
    "sg:address":"Roseggerstr. 104",
    "sg:city":"Marchtrenk",
    "sg:classifiers":[
        {
            "category":"Real Estate",
            "subcategory":"Surveying",
            "type":"Services"
        }
    ],
    "sg:phone":"+43 4372 43533330",
    "sg:postcode":"4614",
    "sg:province":"Ober\u00f6sterreich",
    "sg:tags":[
        "equipment",
        "material",
        "good",
        "-",
        "handling"
    ],
    "wof:name":"BT \u00d6STERREICH GMBH",
    "wof:placetype":"venue"
},
  "geometry": {"coordinates":[14.1355218887,48.2017593384],"type":"Point"}
}