{
  "type": "Feature",
  "properties": {
    "iso:country":"AT",
    "sg:address":"Hirtenberger Str 25",
    "sg:city":"Leobersdorf",
    "sg:orig_category":"Autohandel",
    "sg:phone":"+43 2256 622740",
    "sg:postcode":"2544",
    "sg:province":"Nieder\u00f6sterreich",
    "wof:name":"Mayer Andreas GesmbH",
    "wof:placetype":"venue"
},
  "geometry": {"coordinates":[16.2198009491,47.9347267151],"type":"Point"}
}