{
  "type": "Feature",
  "properties": {
    "iso:country":"AT",
    "sg:address":"Defreggerstr 38",
    "sg:city":"Innsbruck",
    "sg:orig_category":"Dolmetscher",
    "sg:phone":"+43 512 396762",
    "sg:postcode":"6020",
    "sg:province":"Tirol",
    "wof:name":"Rotter Harald MMag",
    "wof:placetype":"venue"
},
  "geometry": {"coordinates":[11.4109239578,47.2653503418],"type":"Point"}
}