{
  "type": "Feature",
  "properties": {
    "iso:country":"AT",
    "sg:address":"Nr 30",
    "sg:city":"Rottenbach",
    "sg:orig_category":"Banken U Sparkassen",
    "sg:phone":"+43 7732 2741",
    "sg:postcode":"4681",
    "sg:province":"Ober\u00f6sterreich",
    "wof:name":"Raiffeisenbank Region Hausruck regGenmbH",
    "wof:placetype":"venue"
},
  "geometry": {"coordinates":[13.6808748245,48.205581665],"type":"Point"}
}