{
  "type": "Feature",
  "properties": {
    "addr:full":"Roseggerg 2 Voitsberg Steiermark 8570",
    "addr:housenumber":"2",
    "addr:postcode":"8570",
    "addr:street":"Roseggerg",
    "iso:country":"AT",
    "sg:address":"Roseggerg 2",
    "sg:city":"Voitsberg",
    "sg:orig_category":"Nachtclubs-Bars",
    "sg:phone":"+43 3142 25175",
    "sg:postcode":"8570",
    "sg:province":"Steiermark",
    "wof:name":"Club Jack Daniels",
    "wof:placetype":"venue"
},
  "geometry": {"coordinates":[15.1518583298,47.0481910706],"type":"Point"}
}