{
  "type": "Feature",
  "properties": {
    "addr:full":"Rosalienweg 32b Gumpoldskirchen Nieder\u00f6sterreich 2352",
    "addr:housenumber":"32b",
    "addr:postcode":"2352",
    "addr:street":"Rosalienweg",
    "iso:country":"AT",
    "sg:address":"Rosalienweg 32b",
    "sg:city":"Gumpoldskirchen",
    "sg:orig_category":"Bauunternehmen",
    "sg:phone":"+43 2252 62044",
    "sg:postcode":"2352",
    "sg:province":"Nieder\u00f6sterreich",
    "wof:name":"Levonyak Bau GmbH",
    "wof:placetype":"venue"
},
  "geometry": {"coordinates":[16.2888698578,48.0365142822],"type":"Point"}
}