{
  "type": "Feature",
  "properties": {
    "addr:full":"Br\u00fcnner Str 8 Wolkersdorf im Weinviertel Nieder\u00f6sterreich 2120",
    "addr:housenumber":"8",
    "addr:postcode":"2120",
    "addr:street":"Str",
    "iso:country":"AT",
    "sg:address":"Br\u00fcnner Str 8",
    "sg:city":"Wolkersdorf im Weinviertel",
    "sg:orig_category":"Spenglereien",
    "sg:phone":"+43 4322 4522610",
    "sg:postcode":"2120",
    "sg:province":"Nieder\u00f6sterreich",
    "wof:name":"Spenglerei Wolf",
    "wof:placetype":"venue"
},
  "geometry": {"coordinates":[16.5198898315,48.382976532],"type":"Point"}
}