{
  "type": "Feature",
  "properties": {
    "addr:full":"Mariahilfer Str 166 Wien Wien 1150",
    "addr:housenumber":"166",
    "addr:postcode":"1150",
    "iso:country":"AT",
    "sg:address":"Mariahilfer Str 166",
    "sg:city":"Wien",
    "sg:orig_category":"Zeitungen U Zeitschriften",
    "sg:phone":"+43 1 8920445",
    "sg:postcode":"1150",
    "sg:province":"Wien",
    "wof:name":"Romantausch und Zeitschriftenhandel Bitterer OEG",
    "wof:placetype":"venue"
},
  "geometry": {"coordinates":[16.3324718475,48.1921730042],"type":"Point"}
}