{
  "type": "Feature",
  "properties": {
    "addr:full":"Unterer Steinwandweg 11a Deutschlandsberg Steiermark 8530",
    "addr:housenumber":"11a",
    "addr:postcode":"8530",
    "addr:street":"Unterer Steinwandweg",
    "iso:country":"AT",
    "sg:address":"Unterer Steinwandweg 11a",
    "sg:city":"Deutschlandsberg",
    "sg:orig_category":"Elektroinstallationsunternehmen",
    "sg:phone":"+43 676 5660299",
    "sg:postcode":"8530",
    "sg:province":"Steiermark",
    "wof:name":"Temmel Franz",
    "wof:placetype":"venue"
},
  "geometry": {"coordinates":[15.2176675797,46.8261489868],"type":"Point"}
}