{
  "type": "Feature",
  "properties": {
    "addr:full":"Fleschg 15 Wien Wien 1130",
    "addr:housenumber":"15",
    "addr:postcode":"1130",
    "addr:street":"Fleschg",
    "iso:country":"AT",
    "sg:address":"Fleschg 15",
    "sg:city":"Wien",
    "sg:orig_category":"Escortservice",
    "sg:phone":"+43 664 4501000",
    "sg:postcode":"1130",
    "sg:province":"Wien",
    "wof:name":"Just for Fun",
    "wof:placetype":"venue"
},
  "geometry": {"coordinates":[16.2892150879,48.18932724],"type":"Point"}
}