{
  "type": "Feature",
  "properties": {
    "iso:country":"AT",
    "sg:address":"Sieveringer Str 28",
    "sg:city":"Wien",
    "sg:orig_category":"Bekleidung / Erzeugung U Gro\u00c3\u0178handel",
    "sg:phone":"+43 4313 283072",
    "sg:postcode":"1190",
    "sg:province":"Wien",
    "wof:name":"Internationale Modeagentur Walter Harl",
    "wof:placetype":"venue"
},
  "geometry": {"coordinates":[16.3367996216,48.2466239929],"type":"Point"}
}