{
  "type": "Feature",
  "properties": {
    "addr:full":"Landstr 65 Zwettl Nieder\u00f6sterreich 3910",
    "addr:housenumber":"65",
    "addr:postcode":"3910",
    "addr:street":"Landstr;Niederoesterreich",
    "iso:country":"AT",
    "sg:address":"Landstr 65",
    "sg:city":"Zwettl",
    "sg:orig_category":"Rauchfangkehrer",
    "sg:phone":"+43 2822 52343",
    "sg:postcode":"3910",
    "sg:province":"Nieder\u00f6sterreich",
    "wof:name":"Anton Thomas",
    "wof:placetype":"venue"
},
  "geometry": {"coordinates":[15.1653766632,48.6066017151],"type":"Point"}
}