{
  "type": "Feature",
  "properties": {
    "iso:country":"AT",
    "sg:address":"Aigner Str 53",
    "sg:city":"Aigen",
    "sg:orig_category":"Tabaktrafiken",
    "sg:phone":"+43 662 633499",
    "sg:postcode":"5026",
    "sg:province":"Salzburg",
    "wof:name":"Schiller Friedrich",
    "wof:placetype":"venue"
},
  "geometry": {"coordinates":[13.0746498108,47.7907905579],"type":"Point"}
}