{
  "type": "Feature",
  "properties": {
    "addr:full":"Hauptpl 13 Feldbach Steiermark 8330",
    "addr:housenumber":"13",
    "addr:postcode":"8330",
    "addr:street":"Hauptpl",
    "iso:country":"AT",
    "sg:address":"Hauptpl 13",
    "sg:city":"Feldbach",
    "sg:orig_category":"Gemeinden",
    "sg:phone":"+43 3152 22020",
    "sg:postcode":"8330",
    "sg:province":"Steiermark",
    "wof:name":"Stadtgemeinde Feldbach",
    "wof:placetype":"venue"
},
  "geometry": {"coordinates":[15.8889160156,46.95262146],"type":"Point"}
}