{
  "type": "Feature",
  "properties": {
    "addr:full":"Vernholzg 12 Wien Wien 1220",
    "addr:housenumber":"12",
    "addr:postcode":"1220",
    "addr:street":"Vernholzg",
    "iso:country":"AT",
    "sg:address":"Vernholzg 12",
    "sg:city":"Wien",
    "sg:orig_category":"Elektroinstallationsunternehmen",
    "sg:phone":"+43 1 2805140",
    "sg:postcode":"1220",
    "sg:province":"Wien",
    "sg:website":"frantsits.at",
    "wof:name":"Frantsits Ing Johann GesmbH",
    "wof:placetype":"venue"
},
  "geometry": {"coordinates":[16.4530391693,48.2284545898],"type":"Point"}
}