{
  "type": "Feature",
  "properties": {
    "addr:full":"Feuerbachgasse 2 Graz Steiermark 8020",
    "addr:housenumber":"2",
    "addr:postcode":"8020",
    "addr:street":"Feuerbachgasse",
    "iso:country":"AT",
    "sg:address":"Feuerbachgasse 2",
    "sg:city":"Graz",
    "sg:classifiers":[
        {
            "category":"Professional",
            "subcategory":"Advertising",
            "type":"Services"
        }
    ],
    "sg:phone":"+43 316 713223",
    "sg:postcode":"8020",
    "sg:province":"Steiermark",
    "sg:tags":[
        "agency"
    ],
    "wof:name":"Mondial - Werbung Ges.m.b.H. KG",
    "wof:placetype":"venue"
},
  "geometry": {"coordinates":[15.4324207306,47.0709609985],"type":"Point"}
}