{
  "type": "Feature",
  "properties": {
    "addr:full":"Proding 5 Tamsweg Salzburg 5580",
    "addr:housenumber":"5",
    "addr:postcode":"5580",
    "addr:street":"Proding;Salzburg",
    "iso:country":"AT",
    "sg:address":"Proding 5",
    "sg:city":"Tamsweg",
    "sg:orig_category":"Pensionen / Privatzimmer",
    "sg:phone":"+43 6474 7338",
    "sg:postcode":"5580",
    "sg:province":"Salzburg",
    "wof:name":"Planitzerhof",
    "wof:placetype":"venue"
},
  "geometry": {"coordinates":[13.8219985962,47.1313018799],"type":"Point"}
}