{
  "type": "Feature",
  "properties": {
    "addr:full":"Neilreichg 6a Wien Wien 1100",
    "addr:housenumber":"6a",
    "addr:postcode":"1100",
    "addr:street":"Neilreichg",
    "iso:country":"AT",
    "sg:address":"Neilreichg 6a",
    "sg:city":"Wien",
    "sg:orig_category":"Werbegrafik- U Grafik-Design",
    "sg:phone":"+43 4316 025292",
    "sg:postcode":"1100",
    "sg:province":"Wien",
    "wof:name":"AIRBRUSH - Ing Werner Spitzer",
    "wof:placetype":"venue"
},
  "geometry": {"coordinates":[16.3658733368,48.1791343689],"type":"Point"}
}