{
  "type": "Feature",
  "properties": {
    "addr:full":"Arnsteing 30 Wien Wien 1150",
    "addr:housenumber":"30",
    "addr:postcode":"1150",
    "addr:street":"Arnsteing",
    "iso:country":"AT",
    "sg:address":"Arnsteing 30",
    "sg:city":"Wien",
    "sg:classifiers":[
        {
            "category":"Restaurant",
            "type":"Food & Drink"
        }
    ],
    "sg:phone":"+43 1 8923871",
    "sg:postcode":"1150",
    "sg:province":"Wien",
    "sg:tags":[
        "pizzeria"
    ],
    "wof:name":"Vesuvio Da Mario",
    "wof:placetype":"venue"
},
  "geometry": {"coordinates":[16.331237793,48.1913604736],"type":"Point"}
}