{
  "type": "Feature",
  "properties": {
    "addr:full":"Mariahilfer Str 121b Wien Wien 1060",
    "addr:housenumber":"121b",
    "addr:postcode":"1060",
    "addr:street":"Str",
    "iso:country":"AT",
    "sg:address":"Mariahilfer Str 121b",
    "sg:city":"Wien",
    "sg:classifiers":[
        {
            "category":"Internet Cafe",
            "subcategory":"None",
            "type":"Food & Drink"
        }
    ],
    "sg:phone":"+43 1 53689",
    "sg:postcode":"1060",
    "sg:province":"Wien",
    "wof:name":"ecetra Internet Service AG",
    "wof:placetype":"venue"
},
  "geometry": {"coordinates":[16.3414382935,48.1960754395],"type":"Point"}
}