{
  "type": "Feature",
  "properties": {
    "iso:country":"AT",
    "sg:address":"Stahlstr 1",
    "sg:city":"Weiz",
    "sg:orig_category":"Stahlbau",
    "sg:phone":"+43 4331 7222780",
    "sg:postcode":"8160",
    "sg:province":"Steiermark",
    "wof:name":"Stoppacher GmbH",
    "wof:placetype":"venue"
},
  "geometry": {"coordinates":[15.6485481262,47.197769165],"type":"Point"}
}