{
  "type": "Feature",
  "properties": {
    "iso:country":"AT",
    "sg:address":"Rosensteing 68/9",
    "sg:city":"Wien",
    "sg:orig_category":"\u00c3\u201erzte / F Allgemeinmedizin",
    "sg:phone":"+43 4314 856188",
    "sg:postcode":"1170",
    "sg:province":"Wien",
    "wof:name":"Burkart Monika Dr",
    "wof:placetype":"venue"
},
  "geometry": {"coordinates":[16.3280792236,48.2217979431],"type":"Point"}
}