{
  "type": "Feature",
  "properties": {
    "iso:country":"AT",
    "sg:address":"Salzburger Str 323",
    "sg:city":"Linz",
    "sg:orig_category":"Bauunternehmen",
    "sg:phone":"+43 4373 237310",
    "sg:postcode":"4020",
    "sg:province":"Ober\u00f6sterreich",
    "wof:name":"Lang F und Menhofer K BaugmbH & Co KG",
    "wof:placetype":"venue"
},
  "geometry": {"coordinates":[14.2875900269,48.25522995],"type":"Point"}
}