{
  "type": "Feature",
  "properties": {
    "addr:full":"Malchbachg 14 Imst Tirol 6460",
    "addr:housenumber":"14",
    "addr:postcode":"6460",
    "addr:street":"Malchbachg;Tirol",
    "iso:country":"AT",
    "sg:address":"Malchbachg 14",
    "sg:city":"Imst",
    "sg:orig_category":"Webdesign",
    "sg:phone":"+43 699 18342002",
    "sg:postcode":"6460",
    "sg:province":"Tirol",
    "wof:name":"Gasser Helmut Websolutions Gasser",
    "wof:placetype":"venue"
},
  "geometry": {"coordinates":[10.7379255295,47.2442932129],"type":"Point"}
}