{
  "type": "Feature",
  "properties": {
    "addr:full":"Friedrichstr 2 Wien Wien 1010",
    "addr:housenumber":"2",
    "addr:postcode":"1010",
    "addr:street":"Friedrichstr",
    "iso:country":"AT",
    "sg:address":"Friedrichstr 2",
    "sg:city":"Wien",
    "sg:orig_category":"Bars-Cafes",
    "sg:phone":"+43 1 5874806",
    "sg:postcode":"1010",
    "sg:province":"Wien",
    "wof:name":"Schampus",
    "wof:placetype":"venue"
},
  "geometry": {"coordinates":[16.3685760498,48.2012214661],"type":"Point"}
}