{
  "type": "Feature",
  "properties": {
    "iso:country":"AT",
    "sg:address":"Berg 390",
    "sg:city":"Mellau",
    "sg:orig_category":"Pensionen / Privatzimmer",
    "sg:phone":"+43 5518 2380",
    "sg:postcode":"6881",
    "sg:province":"Vorarlberg",
    "wof:name":"Pension Sonnberg",
    "wof:placetype":"venue"
},
  "geometry": {"coordinates":[9.8945007324,47.3498268127],"type":"Point"}
}