{
  "type": "Feature",
  "properties": {
    "addr:full":"Haslau 56 Zell am Moos Ober\u00f6sterreich 4893",
    "addr:housenumber":"56",
    "addr:postcode":"4893",
    "addr:street":"Haslau;Oberoesterreich",
    "iso:country":"AT",
    "sg:address":"Haslau 56",
    "sg:city":"Zell am Moos",
    "sg:classifiers":[
        {
            "category":"Real Estate",
            "subcategory":"Architect",
            "type":"Services"
        }
    ],
    "sg:phone":"+43 6234 85000",
    "sg:postcode":"4893",
    "sg:province":"Ober\u00f6sterreich",
    "sg:tags":[
        "baseboard",
        "aluminium",
        "made"
    ],
    "sg:website":"fnprofile.com",
    "wof:name":"Neuhofer Holz GmbH",
    "wof:placetype":"venue"
},
  "geometry": {"coordinates":[13.3511400223,47.9300231934],"type":"Point"}
}