{
  "type": "Feature",
  "properties": {
    "addr:full":"Untermarkt 1A Telfs Tirol 6410",
    "addr:housenumber":"1a",
    "addr:postcode":"6410",
    "addr:street":"Untermarkt;Tirol",
    "iso:country":"AT",
    "sg:address":"Untermarkt 1A",
    "sg:city":"Telfs",
    "sg:orig_category":"Architekten",
    "sg:phone":"+43 4352 62620710",
    "sg:postcode":"6410",
    "sg:province":"Tirol",
    "wof:name":"Ofner Erwin Dipl-Ing",
    "wof:placetype":"venue"
},
  "geometry": {"coordinates":[11.0714702606,47.3065032959],"type":"Point"}
}