{
  "type": "Feature",
  "properties": {
    "addr:full":"Gaishorn am See 180 Gaishorn am See Steiermark 8783",
    "addr:housenumber":"180",
    "addr:postcode":"8783",
    "addr:street":"Gaishorn;See",
    "iso:country":"AT",
    "sg:address":"Gaishorn am See 180",
    "sg:city":"Gaishorn am See",
    "sg:classifiers":[
        {
            "category":"Home & Garden",
            "subcategory":"Furniture",
            "type":"Retail Goods"
        }
    ],
    "sg:phone":"+43 3617 22240",
    "sg:postcode":"8783",
    "sg:province":"Steiermark",
    "sg:tags":[
        "bathroom"
    ],
    "sg:website":"rossmann-gmbh.at",
    "wof:name":"Tischlerei und M\u00f6belhandel Ro\u00dfmann GesmbH",
    "wof:placetype":"venue"
},
  "geometry": {"coordinates":[14.5492944717,47.4914245605],"type":"Point"}
}