{
  "type": "Feature",
  "properties": {
    "iso:country":"AT",
    "sg:address":"St\u00fcrzling 1",
    "sg:city":"Pennewang",
    "sg:orig_category":"Holzhandel",
    "sg:phone":"+43 7245 26296",
    "sg:postcode":"4624",
    "sg:province":"Ober\u00f6sterreich",
    "wof:name":"Stritzinger Max",
    "wof:placetype":"venue"
},
  "geometry": {"coordinates":[13.8426761627,48.1287078857],"type":"Point"}
}