{
  "type": "Feature",
  "properties": {
    "addr:full":"Im Br\u00fchl 36 Feldkirch Vorarlberg 6800",
    "addr:housenumber":"36",
    "addr:postcode":"6800",
    "addr:street":"Im Bruehl",
    "iso:country":"AT",
    "sg:address":"Im Br\u00fchl 36",
    "sg:city":"Feldkirch",
    "sg:classifiers":[
        {
            "category":"Taxi",
            "type":"Transportation"
        }
    ],
    "sg:phone":"+43 5522 38700",
    "sg:postcode":"6800",
    "sg:province":"Vorarlberg",
    "sg:tags":[
        "personentransporte",
        "u"
    ],
    "wof:name":"Airport Service Green Cabs",
    "wof:placetype":"venue"
},
  "geometry": {"coordinates":[9.5967845917,47.2381515503],"type":"Point"}
}