{
  "type": "Feature",
  "properties": {
    "addr:full":"Gaisbachstr 8 Rauris Salzburg 5661",
    "addr:housenumber":"8",
    "addr:postcode":"5661",
    "addr:street":"Gaisbachstr;Salzburg",
    "iso:country":"AT",
    "sg:address":"Gaisbachstr 8",
    "sg:city":"Rauris",
    "sg:orig_category":"Pensionen / Privatzimmer",
    "sg:phone":"+43 4365 4462650",
    "sg:postcode":"5661",
    "sg:province":"Salzburg",
    "wof:name":"Pension Anneliese",
    "wof:placetype":"venue"
},
  "geometry": {"coordinates":[12.9954442978,47.2301826477],"type":"Point"}
}