{
  "type": "Feature",
  "properties": {
    "addr:full":"Guntherstrasse 10 Bad Hall Ober\u00f6sterreich 4540",
    "addr:housenumber":"10",
    "addr:postcode":"4540",
    "addr:street":"Guntherstrasse;Oberoesterreich",
    "iso:country":"AT",
    "sg:address":"Guntherstrasse 10",
    "sg:city":"Bad Hall",
    "sg:classifiers":[
        {
            "category":"Government",
            "subcategory":"Post Office",
            "type":"Public Place"
        }
    ],
    "sg:phone":"+43 7258 74600",
    "sg:postcode":"4540",
    "sg:province":"Ober\u00f6sterreich",
    "sg:tags":[
        "part",
        "-axis",
        "cnc",
        "milled"
    ],
    "wof:name":"Haslgr\u00fcbler Metalltechnik GmbH",
    "wof:placetype":"venue"
},
  "geometry": {"coordinates":[14.2138328552,48.036315918],"type":"Point"}
}