{
  "type": "Feature",
  "properties": {
    "addr:full":"Roda Roda-G 5 Wien Wien 1210",
    "addr:housenumber":"5",
    "addr:postcode":"1210",
    "addr:street":"Roda-G",
    "iso:country":"AT",
    "sg:address":"Roda Roda-G 5",
    "sg:city":"Wien",
    "sg:orig_category":"Friseure U Frisiersalons",
    "sg:phone":"+43 1 2901507",
    "sg:postcode":"1210",
    "sg:province":"Wien",
    "wof:name":"Hollywood Friseursalon",
    "wof:placetype":"venue"
},
  "geometry": {"coordinates":[16.3838806152,48.2908096313],"type":"Point"}
}