{
  "type": "Feature",
  "properties": {
    "addr:full":"Hauptpl 36 Amstetten Nieder\u00f6sterreich 3300",
    "addr:housenumber":"36",
    "addr:postcode":"3300",
    "addr:street":"Hauptpl;Niederoesterreich",
    "iso:country":"AT",
    "sg:address":"Hauptpl 36",
    "sg:city":"Amstetten",
    "sg:orig_category":"Friseurbedarf",
    "sg:phone":"+43 7472 65559",
    "sg:postcode":"3300",
    "sg:province":"Nieder\u00f6sterreich",
    "wof:name":"Maurer Robert GmbH",
    "wof:placetype":"venue"
},
  "geometry": {"coordinates":[14.8711414337,48.1238021851],"type":"Point"}
}