{
  "type": "Feature",
  "properties": {
    "iso:country":"AT",
    "sg:address":"Nr 139",
    "sg:city":"Studenzen",
    "sg:orig_category":"Elektroinstallationsunternehmen",
    "sg:phone":"+43 3115 423030",
    "sg:postcode":"8322",
    "sg:province":"Steiermark",
    "sg:website":"intellihome.at",
    "wof:name":"IntelliHome Automatisierungstechnik GmbH",
    "wof:placetype":"venue"
},
  "geometry": {"coordinates":[15.7906103134,47.0232505798],"type":"Point"}
}