{
  "type": "Feature",
  "properties": {
    "addr:full":"Seekirchnerstrasse 11 Obertrum am See Salzburg 5162",
    "addr:housenumber":"11",
    "addr:postcode":"5162",
    "addr:street":"Seekirchnerstrasse;Salzburg",
    "iso:country":"AT",
    "sg:address":"Seekirchnerstrasse 11",
    "sg:city":"Obertrum am See",
    "sg:orig_category":"Internet, Alle Internetdienstleistungen",
    "sg:phone":"+43 4367 64114268",
    "sg:postcode":"5162",
    "sg:province":"Salzburg",
    "sg:website":"http://www.salzweb.com",
    "wof:name":"salzweb",
    "wof:placetype":"venue"
},
  "geometry": {"coordinates":[13.0461006165,47.9350166321],"type":"Point"}
}