{
  "type": "Feature",
  "properties": {
    "iso:country":"AT",
    "sg:address":"Wiener Str 4",
    "sg:city":"Oberwart",
    "sg:orig_category":"Optiker",
    "sg:phone":"+43 3352 38447",
    "sg:postcode":"7400",
    "sg:province":"Burgenland",
    "wof:name":"brilleria augenoptik gmbh",
    "wof:placetype":"venue"
},
  "geometry": {"coordinates":[16.2104053497,47.2891845703],"type":"Point"}
}