{
  "type": "Feature",
  "properties": {
    "addr:full":"Scheibe 20 Neustift im Stubaital Tirol 6167",
    "addr:housenumber":"20",
    "addr:postcode":"6167",
    "addr:street":"Scheibe;Tirol",
    "iso:country":"AT",
    "sg:address":"Scheibe 20",
    "sg:city":"Neustift im Stubaital",
    "sg:orig_category":"Raumausstattung",
    "sg:phone":"+43 4352 262237",
    "sg:postcode":"6167",
    "sg:province":"Tirol",
    "wof:name":"Gleirscher Ernst - R\u00e4UMlich Gleirscher",
    "wof:placetype":"venue"
},
  "geometry": {"coordinates":[11.297369957,47.1076812744],"type":"Point"}
}