{
  "type": "Feature",
  "properties": {
    "iso:country":"AT",
    "sg:address":"Mahrersdorfer Str 14",
    "sg:city":"Neunkirchen",
    "sg:orig_category":"Feuerwehren",
    "sg:phone":"+43 2630 38897",
    "sg:postcode":"2620",
    "sg:province":"Nieder\u00f6sterreich",
    "wof:name":"Freiwillige Feuerwehr Ternitz-Mahrersdorf",
    "wof:placetype":"venue"
},
  "geometry": {"coordinates":[16.0825557709,47.7204246521],"type":"Point"}
}