{
  "type": "Feature",
  "properties": {
    "addr:full":"Nr 69 F\u00fcgen Tirol 6263",
    "addr:postcode":"6263",
    "addr:street":"Nr 69 Fuegen Tirol",
    "iso:country":"AT",
    "sg:address":"Nr 69",
    "sg:city":"F\u00fcgen",
    "sg:orig_category":"Pensionen / Privatzimmer",
    "sg:phone":"+43 5288 62764",
    "sg:postcode":"6263",
    "sg:province":"Tirol",
    "wof:name":"Ebster Burgi",
    "wof:placetype":"venue"
},
  "geometry": {"coordinates":[11.8493213654,47.3472557068],"type":"Point"}
}