{
  "type": "Feature",
  "properties": {
    "iso:country":"AT",
    "sg:address":"Kreativtechnikg. 18 ",
    "sg:city":"Leobersdorf",
    "sg:classifiers":[
        {
            "category":"Communications",
            "subcategory":"Newspaper",
            "type":"Services"
        }
    ],
    "sg:phone":"+43 4322 5662420",
    "sg:postcode":"2544",
    "sg:province":"Nieder\u00f6sterreich",
    "sg:tags":[
        "advertising"
    ],
    "wof:name":"KREATIVTECHNIK DEKORATION MESSEBAU U. HANDELSGESMBH",
    "wof:placetype":"venue"
},
  "geometry": {"coordinates":[16.2234992981,47.934589386],"type":"Point"}
}