{
  "type": "Feature",
  "properties": {
    "addr:full":"Medrazer Str 2a Fulpmes Tirol 6166",
    "addr:postcode":"6166",
    "addr:street":"Str 2A;Tirol",
    "iso:country":"AT",
    "sg:address":"Medrazer Str 2a",
    "sg:city":"Fulpmes",
    "sg:orig_category":"Unterhaltungselektronik / Einzelhandel",
    "sg:phone":"+43 5225 62353",
    "sg:postcode":"6166",
    "sg:province":"Tirol",
    "wof:name":"Radio Auer KG",
    "wof:placetype":"venue"
},
  "geometry": {"coordinates":[11.3481149673,47.1521835327],"type":"Point"}
}