{
  "type": "Feature",
  "properties": {
    "addr:full":"Brillergraben 8 St. Veit an der G\u00f6lsen Nieder\u00f6sterreich 3161",
    "addr:housenumber":"8",
    "addr:postcode":"3161",
    "addr:street":"Brillergraben;Niederoesterreich",
    "iso:country":"AT",
    "sg:address":"Brillergraben 8",
    "sg:city":"St. Veit an der G\u00f6lsen",
    "sg:orig_category":"Fischzucht",
    "sg:phone":"+43 4327 632163",
    "sg:postcode":"3161",
    "sg:province":"Nieder\u00f6sterreich",
    "wof:name":"Forellenhof Dieter u Gundula Sigl",
    "wof:placetype":"venue"
},
  "geometry": {"coordinates":[15.6743049622,48.0406227112],"type":"Point"}
}