{
  "type": "Feature",
  "properties": {
    "addr:full":"Maxglaner Hauptstrasse 39 Salzburg Salzburg 5020",
    "addr:housenumber":"39",
    "addr:postcode":"5020",
    "addr:street":"Maxglaner Hauptstrasse;Salzburg",
    "iso:country":"AT",
    "sg:address":"Maxglaner Hauptstrasse 39",
    "sg:city":"Salzburg",
    "sg:classifiers":[
        {
            "category":"Professional",
            "subcategory":"Art Services",
            "type":"Services"
        }
    ],
    "sg:phone":"+43 662 833598",
    "sg:postcode":"5020",
    "sg:province":"Salzburg",
    "sg:tags":[
        "artistic",
        "glazings"
    ],
    "wof:name":"Bilderrahmen & Postershop Inh. Gabriele Zink",
    "wof:placetype":"venue"
},
  "geometry": {"coordinates":[13.020611763,47.7979125977],"type":"Point"}
}