{
  "type": "Feature",
  "properties": {
    "addr:full":"Feldkirchner Str 140/5 Klagenfurt K\u00e4rnten 9020",
    "addr:housenumber":"140 / 5",
    "addr:postcode":"9020",
    "addr:street":"Str;Kaernten",
    "iso:country":"AT",
    "sg:address":"Feldkirchner Str 140/5",
    "sg:city":"Klagenfurt",
    "sg:orig_category":"Bausparkassen",
    "sg:phone":"+43 4350 10026830",
    "sg:postcode":"9020",
    "sg:province":"K\u00e4rnten",
    "wof:name":"Bausparkasse d \u00f6sterr Sparkassen AG",
    "wof:placetype":"venue"
},
  "geometry": {"coordinates":[14.2889699936,46.641708374],"type":"Point"}
}