{
  "type": "Feature",
  "properties": {
    "addr:full":"Karl-Wiser-Str 6 Linz Ober\u00f6sterreich 4020",
    "addr:housenumber":"6",
    "addr:postcode":"4020",
    "addr:street":"Karl-Wiser-Str",
    "iso:country":"AT",
    "sg:address":"Karl-Wiser-Str 6",
    "sg:city":"Linz",
    "sg:orig_category":"Webdesign",
    "sg:phone":"+43 732 6054230",
    "sg:postcode":"4020",
    "sg:province":"Ober\u00f6sterreich",
    "wof:name":"Intermedien",
    "wof:placetype":"venue"
},
  "geometry": {"coordinates":[14.2880735397,48.2962341309],"type":"Point"}
}