{
  "type": "Feature",
  "properties": {
    "iso:country":"AT",
    "sg:address":"M\u00fchlweg 7",
    "sg:city":"Grafenstein",
    "sg:orig_category":"Holzhandel",
    "sg:phone":"+43 4225 20430",
    "sg:postcode":"9131",
    "sg:province":"K\u00e4rnten",
    "wof:name":"Moritz H und M Grafensteiner HolzhandelsgesmbH",
    "wof:placetype":"venue"
},
  "geometry": {"coordinates":[14.4665212631,46.6106796265],"type":"Point"}
}