{
  "type": "Feature",
  "properties": {
    "addr:full":"Wiegelestr 2 Wien Wien 1230",
    "addr:housenumber":"2",
    "addr:postcode":"1230",
    "addr:street":"Wiegelestr",
    "iso:country":"AT",
    "sg:address":"Wiegelestr 2",
    "sg:city":"Wien",
    "sg:orig_category":"Elektrische Heizungen",
    "sg:phone":"+43 1 8035385",
    "sg:postcode":"1230",
    "sg:province":"Wien",
    "wof:name":"Liboswar GesmbH",
    "wof:placetype":"venue"
},
  "geometry": {"coordinates":[16.304567337,48.1589012146],"type":"Point"}
}