{
  "type": "Feature",
  "properties": {
    "addr:full":"Marktpl 27 Sachsenburg K\u00e4rnten 9751",
    "addr:housenumber":"27",
    "addr:postcode":"9751",
    "addr:street":"Marktpl;Kaernten",
    "iso:country":"AT",
    "sg:address":"Marktpl 27",
    "sg:city":"Sachsenburg",
    "sg:orig_category":"Montagen U Montagetechnik",
    "sg:phone":"+43 4366 41608156",
    "sg:postcode":"9751",
    "sg:province":"K\u00e4rnten",
    "wof:name":"Bodner Michael",
    "wof:placetype":"venue"
},
  "geometry": {"coordinates":[13.3488826752,46.8270988464],"type":"Point"}
}