{
  "type": "Feature",
  "properties": {
    "addr:full":"Albrechtsg 14 Tulln an der Donau Nieder\u00f6sterreich 3430",
    "addr:housenumber":"14",
    "addr:postcode":"3430",
    "addr:street":"Albrechtsg",
    "iso:country":"AT",
    "sg:address":"Albrechtsg 14",
    "sg:city":"Tulln an der Donau",
    "sg:orig_category":"Juweliere, Gold- U Silberschmiede",
    "sg:phone":"+43 4322 7264196",
    "sg:postcode":"3430",
    "sg:province":"Nieder\u00f6sterreich",
    "wof:name":"Czerwinski Anton",
    "wof:placetype":"venue"
},
  "geometry": {"coordinates":[16.0524501801,48.3326759338],"type":"Point"}
}