{
  "type": "Feature",
  "properties": {
    "addr:full":"Hummelstr 17 Hainburg an der Donau Nieder\u00f6sterreich 2410",
    "addr:housenumber":"17",
    "addr:postcode":"2410",
    "addr:street":"Hummelstr",
    "iso:country":"AT",
    "sg:address":"Hummelstr 17",
    "sg:city":"Hainburg an der Donau",
    "sg:orig_category":"Autoreparatur",
    "sg:phone":"+43 4321 6562545",
    "sg:postcode":"2410",
    "sg:province":"Nieder\u00f6sterreich",
    "wof:name":"Wenighofer Rudolf",
    "wof:placetype":"venue"
},
  "geometry": {"coordinates":[16.9404277802,48.1448936462],"type":"Point"}
}