{
  "type": "Feature",
  "properties": {
    "iso:country":"AT",
    "sg:address":"Adlerg 3/1",
    "sg:city":"Wiener Neustadt",
    "sg:orig_category":"Zeitungen U Zeitschriften",
    "sg:phone":"+43 4326 22242240",
    "sg:postcode":"2700",
    "sg:province":"Nieder\u00f6sterreich",
    "wof:name":"Die N\u00f6N Wr Neustadt",
    "wof:placetype":"venue"
},
  "geometry": {"coordinates":[16.2437992096,47.8139305115],"type":"Point"}
}