{
  "type": "Feature",
  "properties": {
    "addr:full":"Feldkircher Str 13 Frastanz Vorarlberg 6820",
    "addr:postcode":"6820",
    "addr:street":"Str 13",
    "iso:country":"AT",
    "sg:address":"Feldkircher Str 13",
    "sg:city":"Frastanz",
    "sg:orig_category":"Tischlereien",
    "sg:phone":"+43 4355 2251789",
    "sg:postcode":"6820",
    "sg:province":"Vorarlberg",
    "wof:name":"Gassner Hubert",
    "wof:placetype":"venue"
},
  "geometry": {"coordinates":[9.6303749084,47.2169532776],"type":"Point"}
}