{
  "type": "Feature",
  "properties": {
    "iso:country":"AT",
    "sg:address":"Kalvarienbergg 46",
    "sg:city":"Wien",
    "sg:orig_category":"Psychotherapie",
    "sg:phone":"+43 1 4033388",
    "sg:postcode":"1170",
    "sg:province":"Wien",
    "wof:name":"Heindl Hilde",
    "wof:placetype":"venue"
},
  "geometry": {"coordinates":[16.3331813812,48.2200279236],"type":"Point"}
}