{
  "type": "Feature",
  "properties": {
    "addr:full":"Nr 32 G\u00f6llersdorf Nieder\u00f6sterreich 2013",
    "addr:postcode":"2013",
    "addr:street":"Nr 32 Goellersdorf",
    "iso:country":"AT",
    "sg:address":"Nr 32",
    "sg:city":"G\u00f6llersdorf",
    "sg:orig_category":"Werbeagenturen",
    "sg:phone":"+43 2954 2514",
    "sg:postcode":"2013",
    "sg:province":"Nieder\u00f6sterreich",
    "wof:name":"Ziolkowski Horst",
    "wof:placetype":"venue"
},
  "geometry": {"coordinates":[16.1194400787,48.4935760498],"type":"Point"}
}