{
  "type": "Feature",
  "properties": {
    "iso:country":"AT",
    "sg:address":"Linzer Str. 4 ",
    "sg:city":"Wilhering",
    "sg:classifiers":[
        {
            "category":"Farming",
            "subcategory":"Livestock Farm",
            "type":"Manufacturing & Wholesale Goods"
        }
    ],
    "sg:phone":"+43 4372 2623930",
    "sg:postcode":"4073",
    "sg:province":"Ober\u00f6sterreich",
    "sg:tags":[
        "agriculture"
    ],
    "wof:name":"STIFT WILHERING STIFTSG\u00c4RTNEREI",
    "wof:placetype":"venue"
},
  "geometry": {"coordinates":[14.1894397736,48.3235054016],"type":"Point"}
}