{
  "type": "Feature",
  "properties": {
    "iso:country":"AT",
    "sg:address":"Ostererweg.3",
    "sg:city":"Leoben",
    "sg:classifiers":[
        {
            "category":"Professional",
            "subcategory":"Printing & Photocopies",
            "type":"Services"
        }
    ],
    "sg:phone":"+43 4338 4244545",
    "sg:postcode":"8700",
    "sg:province":"Steiermark",
    "wof:name":"OBERSTEIRISCHE DRUCKEREI UND VERLAGS GESMBH",
    "wof:placetype":"venue"
},
  "geometry": {"coordinates":[15.1077718735,47.3808441162],"type":"Point"}
}