{
  "type": "Feature",
  "properties": {
    "addr:full":"Hauptstr 28 Henndorf am Wallersee Salzburg 5302",
    "addr:housenumber":"28",
    "addr:postcode":"5302",
    "addr:street":"Hauptstr",
    "iso:country":"AT",
    "sg:address":"Hauptstr 28",
    "sg:city":"Henndorf am Wallersee",
    "sg:orig_category":"Trachtenbekleidung",
    "sg:phone":"+43 4362 1461660",
    "sg:postcode":"5302",
    "sg:province":"Salzburg",
    "wof:name":"Sinnhofer Walter GesmbH",
    "wof:placetype":"venue"
},
  "geometry": {"coordinates":[13.1856508255,47.8968391418],"type":"Point"}
}