{
  "type": "Feature",
  "properties": {
    "addr:full":"Nr 31 Ro\u00dfbach Ober\u00f6sterreich 5273",
    "addr:postcode":"5273",
    "addr:street":"Nr 31",
    "iso:country":"AT",
    "sg:address":"Nr 31",
    "sg:city":"Ro\u00dfbach",
    "sg:orig_category":"Tourismusinformation U -Organisationen",
    "sg:phone":"+43 4377 236113",
    "sg:postcode":"5273",
    "sg:province":"Ober\u00f6sterreich",
    "wof:name":"Tourismusinformation S'INNVIERTEL",
    "wof:placetype":"venue"
},
  "geometry": {"coordinates":[13.2493591309,48.2008399963],"type":"Point"}
}