{
  "type": "Feature",
  "properties": {
    "addr:full":"Hauptpl 1 Villach K\u00e4rnten 9500",
    "addr:housenumber":"1",
    "addr:postcode":"9500",
    "addr:street":"Hauptpl;Kaernten",
    "iso:country":"AT",
    "sg:address":"Hauptpl 1",
    "sg:city":"Villach",
    "sg:classifiers":[
        {
            "category":"Travel",
            "subcategory":"Hotels & Motels",
            "type":"Entertainment"
        }
    ],
    "sg:phone":"+43 4242 241050",
    "sg:postcode":"9500",
    "sg:province":"K\u00e4rnten",
    "wof:name":"Hotel Goldenes Lamm Fischer KG",
    "wof:placetype":"venue"
},
  "geometry": {"coordinates":[13.8474836349,46.6147193909],"type":"Point"}
}