{
  "type": "Feature",
  "properties": {
    "addr:full":"Sterneckstr 16 Salzburg Salzburg 5020",
    "addr:housenumber":"16",
    "addr:postcode":"5020",
    "addr:street":"Sterneckstr;Salzburg",
    "iso:country":"AT",
    "sg:address":"Sterneckstr 16",
    "sg:city":"Salzburg",
    "sg:orig_category":"Tankstellen",
    "sg:phone":"+43 662 872118",
    "sg:postcode":"5020",
    "sg:province":"Salzburg",
    "wof:name":"Shell Austria GmbH",
    "wof:placetype":"venue"
},
  "geometry": {"coordinates":[13.0530376434,47.8085670471],"type":"Point"}
}