{
  "type": "Feature",
  "properties": {
    "addr:full":"Alkersdorfer Str 1 Berndorf Nieder\u00f6sterreich 2560",
    "addr:housenumber":"1",
    "addr:postcode":"2560",
    "addr:street":"Str",
    "iso:country":"AT",
    "sg:address":"Alkersdorfer Str 1",
    "sg:city":"Berndorf",
    "sg:classifiers":[
        {
            "category":"Professional",
            "subcategory":"Art Services",
            "type":"Services"
        }
    ],
    "sg:phone":"+43 2633 47219",
    "sg:postcode":"2560",
    "sg:province":"Nieder\u00f6sterreich",
    "sg:tags":[
        "designer"
    ],
    "wof:name":"Habsburg-Lothringen Dominic",
    "wof:placetype":"venue"
},
  "geometry": {"coordinates":[16.1040058136,47.8943443298],"type":"Point"}
}