{
  "type": "Feature",
  "properties": {
    "addr:full":"Johannesgasse 46  Horitschon Burgenland 7312",
    "addr:housenumber":"46",
    "addr:postcode":"7312",
    "addr:street":"Johannesgasse",
    "iso:country":"AT",
    "sg:address":"Johannesgasse 46 ",
    "sg:city":"Horitschon",
    "sg:classifiers":[
        {
            "category":"Banks & Credit Unions",
            "subcategory":"Investment Brokerage",
            "type":"Services"
        }
    ],
    "sg:phone":"+43 2610 423750",
    "sg:postcode":"7312",
    "sg:province":"Burgenland",
    "sg:tags":[
        "active",
        "aluminium",
        "oxide"
    ],
    "sg:website":"www.leier.at",
    "wof:name":"Terra - Flora Handelsges.m.b.H.",
    "wof:placetype":"venue"
},
  "geometry": {"coordinates":[16.5392894745,47.581905365],"type":"Point"}
}