{
  "type": "Feature",
  "properties": {
    "addr:full":"Bahnstr 16 A Aspang-Markt Nieder\u00f6sterreich 2870",
    "addr:housenumber":"16 a",
    "addr:postcode":"2870",
    "addr:street":"Bahnstr;Niederoesterreich",
    "iso:country":"AT",
    "sg:address":"Bahnstr 16 A",
    "sg:city":"Aspang-Markt",
    "sg:orig_category":"Drogerien",
    "sg:phone":"+43 2642 51355",
    "sg:postcode":"2870",
    "sg:province":"Nieder\u00f6sterreich",
    "wof:name":"dm drogerie markt GmbH",
    "wof:placetype":"venue"
},
  "geometry": {"coordinates":[16.0923805237,47.5573196411],"type":"Point"}
}