{
  "type": "Feature",
  "properties": {
    "addr:full":"St. Christophener Str 62 Neulengbach Nieder\u00f6sterreich 3040",
    "addr:housenumber":"62",
    "addr:postcode":"3040",
    "addr:street":"Str",
    "iso:country":"AT",
    "sg:address":"St. Christophener Str 62",
    "sg:city":"Neulengbach",
    "sg:orig_category":"Lebensmittel / Einzelhandel",
    "sg:phone":"+43 4327 7252445",
    "sg:postcode":"3040",
    "sg:province":"Nieder\u00f6sterreich",
    "wof:name":"Billa AG",
    "wof:placetype":"venue"
},
  "geometry": {"coordinates":[15.9079504013,48.1976547241],"type":"Point"}
}