{
  "type": "Feature",
  "properties": {
    "iso:country":"AT",
    "sg:address":"Gumpendorfer Str 80",
    "sg:city":"Wien",
    "sg:orig_category":"Blumeneinzelhandel",
    "sg:phone":"+43 1 5976763",
    "sg:postcode":"1060",
    "sg:province":"Wien",
    "wof:name":"Blumenstube Gumpendorf - Fischer Richard",
    "wof:placetype":"venue"
},
  "geometry": {"coordinates":[16.3493061066,48.1936531067],"type":"Point"}
}