{
  "type": "Feature",
  "properties": {
    "addr:full":"Vierthalerstr 5 Salzburg Salzburg 5020",
    "addr:housenumber":"5",
    "addr:postcode":"5020",
    "addr:street":"Vierthalerstr;Salzburg",
    "iso:country":"AT",
    "sg:address":"Vierthalerstr 5",
    "sg:city":"Salzburg",
    "sg:classifiers":[
        {
            "category":"Professional",
            "subcategory":"Management & Consulting",
            "type":"Services"
        }
    ],
    "sg:phone":"+43 662 872376",
    "sg:postcode":"5020",
    "sg:province":"Salzburg",
    "wof:name":"d & d Projektmanagement Dimitroff KEG",
    "wof:placetype":"venue"
},
  "geometry": {"coordinates":[13.0492668152,47.8055648804],"type":"Point"}
}