{
  "type": "Feature",
  "properties": {
    "iso:country":"AT",
    "sg:address":"W\u00fchrerstr 2",
    "sg:city":"St. Peter am Hart",
    "sg:orig_category":"\u00c3\u201erzte / F Allgemeinmedizin",
    "sg:phone":"+43 7722 851660",
    "sg:postcode":"4963",
    "sg:province":"Ober\u00f6sterreich",
    "wof:name":"Gl\u00fcck Helmut Dr",
    "wof:placetype":"venue"
},
  "geometry": {"coordinates":[13.097205162,48.2527770996],"type":"Point"}
}