{
  "type": "Feature",
  "properties": {
    "addr:full":"Kirchbergg 24/2 Wien Wien 1070",
    "addr:housenumber":"24 / 2",
    "addr:postcode":"1070",
    "addr:street":"Kirchbergg",
    "iso:country":"AT",
    "sg:address":"Kirchbergg 24/2",
    "sg:city":"Wien",
    "sg:orig_category":"\u00c3\u201erzte / F Allgemeinmedizin",
    "sg:phone":"+43 1 5261566",
    "sg:postcode":"1070",
    "sg:province":"Wien",
    "wof:name":"Schastok Heribert Dr",
    "wof:placetype":"venue"
},
  "geometry": {"coordinates":[16.3558120728,48.2046813965],"type":"Point"}
}