{
  "type": "Feature",
  "properties": {
    "addr:full":"Sparkasseg 21 Hollabrunn Nieder\u00f6sterreich 2020",
    "addr:housenumber":"21",
    "addr:postcode":"2020",
    "addr:street":"Sparkasseg",
    "iso:country":"AT",
    "sg:address":"Sparkasseg 21",
    "sg:city":"Hollabrunn",
    "sg:orig_category":"Waren Aller Art",
    "sg:phone":"+43 4329 5220911",
    "sg:postcode":"2020",
    "sg:province":"Nieder\u00f6sterreich",
    "wof:name":"Weltladen",
    "wof:placetype":"venue"
},
  "geometry": {"coordinates":[16.0798301697,48.5653114319],"type":"Point"}
}