{
  "type": "Feature",
  "properties": {
    "addr:full":"Nr 57 St. Johann in der Haide Steiermark 8295",
    "addr:postcode":"8295",
    "addr:street":"Nr 57;Der Haide Steiermark",
    "iso:country":"AT",
    "sg:address":"Nr 57",
    "sg:city":"St. Johann in der Haide",
    "sg:classifiers":[
        {
            "category":"Travel",
            "subcategory":"Hotels & Motels",
            "type":"Entertainment"
        }
    ],
    "sg:phone":"+43 4333 32625070",
    "sg:postcode":"8295",
    "sg:province":"Steiermark",
    "wof:name":"Waldhotel Konrad",
    "wof:placetype":"venue"
},
  "geometry": {"coordinates":[16.0245819092,47.2807769775],"type":"Point"}
}