{
  "type": "Feature",
  "properties": {
    "addr:full":"Schachadorf 7 Wartberg an der Krems Ober\u00f6sterreich 4552",
    "addr:housenumber":"7",
    "addr:postcode":"4552",
    "addr:street":"Schachadorf",
    "iso:country":"AT",
    "sg:address":"Schachadorf 7",
    "sg:city":"Wartberg an der Krems",
    "sg:orig_category":"Autohandel",
    "sg:phone":"+43 4375 877755",
    "sg:postcode":"4552",
    "sg:province":"Ober\u00f6sterreich",
    "sg:website":"seat-egger.at",
    "wof:name":"Autohaus SEAT Egger",
    "wof:placetype":"venue"
},
  "geometry": {"coordinates":[14.0791053772,47.9796791077],"type":"Point"}
}