{
  "type": "Feature",
  "properties": {
    "iso:country":"AT",
    "sg:address":"Au 18",
    "sg:city":"St. Ulrich am Pillersee",
    "sg:orig_category":"Spenglereien",
    "sg:phone":"+43 4353 5488649",
    "sg:postcode":"6393",
    "sg:province":"Tirol",
    "wof:name":"Eder Johann",
    "wof:placetype":"venue"
},
  "geometry": {"coordinates":[12.5940828323,47.519821167],"type":"Point"}
}