{
  "type": "Feature",
  "properties": {
    "iso:country":"AT",
    "sg:address":"Gro\u00dfstroheim 4",
    "sg:city":"Stroheim",
    "sg:orig_category":"Tonstudios",
    "sg:phone":"+43 7272 75656",
    "sg:postcode":"4074",
    "sg:province":"Ober\u00f6sterreich",
    "wof:name":"Milunovic & Partner OEG",
    "wof:placetype":"venue"
},
  "geometry": {"coordinates":[13.9831056595,48.3220291138],"type":"Point"}
}