{
  "type": "Feature",
  "properties": {
    "iso:country":"AT",
    "sg:address":"Kapellenweg 44",
    "sg:city":"Neukirchen",
    "sg:orig_category":"Bergbahnen",
    "sg:phone":"+43 4376 186314",
    "sg:postcode":"4814",
    "sg:province":"Ober\u00f6sterreich",
    "wof:name":"Hochlecken-Schilifte GesmbH",
    "wof:placetype":"venue"
},
  "geometry": {"coordinates":[13.7193965912,47.8730125427],"type":"Point"}
}