{
  "type": "Feature",
  "properties": {
    "iso:country":"AT",
    "sg:address":"Flachauwinkel",
    "sg:city":"Flachau",
    "sg:classifiers":[
        {
            "category":"Home & Garden",
            "subcategory":"Garden Supply",
            "type":"Retail Goods"
        }
    ],
    "sg:phone":"+43 6457 2433",
    "sg:postcode":"5542",
    "sg:province":"Salzburg",
    "sg:tags":[
        "schotter",
        "sand",
        "u"
    ],
    "wof:name":"Salzburger Sand- und Kieswerke GesmbH",
    "wof:placetype":"venue"
},
  "geometry": {"coordinates":[13.3982801437,47.2944107056],"type":"Point"}
}