{
  "type": "Feature",
  "properties": {
    "iso:country":"AT",
    "sg:address":"Salzburger Str 30",
    "sg:city":"Wattens",
    "sg:orig_category":"Lebensmittel / Einzelhandel",
    "sg:phone":"+43 5224 558850",
    "sg:postcode":"6112",
    "sg:province":"Tirol",
    "wof:name":"SuperM",
    "wof:placetype":"venue"
},
  "geometry": {"coordinates":[11.601360321,47.2925300598],"type":"Point"}
}