{
  "type": "Feature",
  "properties": {
    "addr:full":"Windb\u00fcchelg 2 Ohlsdorf Ober\u00f6sterreich 4694",
    "addr:housenumber":"2",
    "addr:postcode":"4694",
    "addr:street":"Windbuechelg",
    "iso:country":"AT",
    "sg:address":"Windb\u00fcchelg 2",
    "sg:city":"Ohlsdorf",
    "sg:orig_category":"Tankstellen",
    "sg:phone":"+43 761263681",
    "sg:postcode":"4694",
    "sg:province":"Ober\u00f6sterreich",
    "wof:name":"BP Austria Marketing GmbH",
    "wof:placetype":"venue"
},
  "geometry": {"coordinates":[13.7921009064,47.960735321],"type":"Point"}
}