{
  "type": "Feature",
  "properties": {
    "addr:full":"L\u00fcftenegg 11  Laakirchen Ober\u00f6sterreich 4663",
    "addr:housenumber":"11",
    "addr:postcode":"4663",
    "addr:street":"Lueftenegg",
    "iso:country":"AT",
    "sg:address":"L\u00fcftenegg 11 ",
    "sg:city":"Laakirchen",
    "sg:classifiers":[
        {
            "category":"Wholesale",
            "subcategory":"Drugs",
            "type":"Manufacturing & Wholesale Goods"
        }
    ],
    "sg:phone":"+43 4376 132893",
    "sg:postcode":"4663",
    "sg:province":"Ober\u00f6sterreich",
    "sg:tags":[
        "chemical",
        "pharmaceutical"
    ],
    "wof:name":"MANFRED E. SZWAJOR",
    "wof:placetype":"venue"
},
  "geometry": {"coordinates":[13.8235998154,47.9830665588],"type":"Point"}
}