{
  "type": "Feature",
  "properties": {
    "addr:full":"Obere Hauptstr 33 Weikendorf Nieder\u00f6sterreich 2253",
    "addr:housenumber":"33",
    "addr:postcode":"2253",
    "addr:street":"Obere Hauptstr",
    "iso:country":"AT",
    "sg:address":"Obere Hauptstr 33",
    "sg:city":"Weikendorf",
    "sg:orig_category":"Tischlereien",
    "sg:phone":"+43 2282 2348",
    "sg:postcode":"2253",
    "sg:province":"Nieder\u00f6sterreich",
    "wof:name":"Wannemacher Kurt",
    "wof:placetype":"venue"
},
  "geometry": {"coordinates":[16.7634334564,48.3416786194],"type":"Point"}
}