{
  "type": "Feature",
  "properties": {
    "iso:country":"AT",
    "sg:address":"Hauptstr 30",
    "sg:city":"Deutsch Wagram",
    "sg:classifiers":[
        {
            "category":"Restaurant",
            "type":"Food & Drink"
        }
    ],
    "sg:phone":"+43 2247 4111",
    "sg:postcode":"2232",
    "sg:province":"Nieder\u00f6sterreich",
    "sg:tags":[
        "pizzeria"
    ],
    "wof:name":"Pizza Al Forno",
    "wof:placetype":"venue"
},
  "geometry": {"coordinates":[16.5611019135,48.2973175049],"type":"Point"}
}