{
  "type": "Feature",
  "properties": {
    "addr:full":"Pestalozziweg 3 Lustenau Vorarlberg 6890",
    "addr:housenumber":"3",
    "addr:postcode":"6890",
    "addr:street":"Pestalozziweg",
    "iso:country":"AT",
    "sg:address":"Pestalozziweg 3",
    "sg:city":"Lustenau",
    "sg:orig_category":"Non-Classified Establishments",
    "sg:phone":"+43 5577 84372",
    "sg:postcode":"6890",
    "sg:province":"Vorarlberg",
    "wof:name":"Pfarramt",
    "wof:placetype":"venue"
},
  "geometry": {"coordinates":[9.6589097977,47.4156265259],"type":"Point"}
}