{
  "type": "Feature",
  "properties": {
    "iso:country":"AT",
    "sg:address":"Marc Aurel-Str 4",
    "sg:city":"Wien",
    "sg:orig_category":"Fluggesellschaften",
    "sg:phone":"+43 1 71098980",
    "sg:postcode":"1010",
    "sg:province":"Wien",
    "wof:name":"Eva Airways Corporation",
    "wof:placetype":"venue"
},
  "geometry": {"coordinates":[16.3727588654,48.211643219],"type":"Point"}
}