{
  "type": "Feature",
  "properties": {
    "iso:country":"AT",
    "sg:address":"Linke Wienzeile 106",
    "sg:city":"Wien",
    "sg:orig_category":"Physiotherapie",
    "sg:phone":"+43 1 5965767",
    "sg:postcode":"1060",
    "sg:province":"Wien",
    "wof:name":"Schaffgotsch Elisabeth Dipl-PT",
    "wof:placetype":"venue"
},
  "geometry": {"coordinates":[16.3539733887,48.1929664612],"type":"Point"}
}