{
  "type": "Feature",
  "properties": {
    "addr:full":"Ennser Strasse 41 Gleink Ober\u00f6sterreich 4407",
    "addr:housenumber":"41",
    "addr:postcode":"4407",
    "addr:street":"Ennser Strasse",
    "iso:country":"AT",
    "sg:address":"Ennser Strasse 41",
    "sg:city":"Gleink",
    "sg:classifiers":[
        {
            "category":"Autos & Motor Vehicles",
            "subcategory":"Recreational Vehicle Sales",
            "type":"Retail Goods"
        }
    ],
    "sg:phone":"+43 7252 81810",
    "sg:postcode":"4407",
    "sg:province":"Ober\u00f6sterreich",
    "sg:tags":[
        "car",
        "racing",
        "tuning",
        "accessory"
    ],
    "sg:website":"kfzhesch.at",
    "wof:name":"Manfred HESCH GmbH",
    "wof:placetype":"venue"
},
  "geometry": {"coordinates":[14.4222154617,48.0688209534],"type":"Point"}
}