{
  "type": "Feature",
  "properties": {
    "iso:country":"AT",
    "sg:address":"Schneerosenweg 3",
    "sg:city":"Bad Kleinkirchheim",
    "sg:classifiers":[
        {
            "category":"Park",
            "subcategory":"Provincial",
            "type":"Public Place"
        }
    ],
    "sg:phone":"+43 4342 4020602",
    "sg:postcode":"9546",
    "sg:province":"K\u00e4rnten",
    "sg:tags":[
        "u",
        "ski-",
        "snowboardschulen"
    ],
    "wof:name":"Schi- u Sportschulen Bad Kleinkirchheim St Oswald GmbH",
    "wof:placetype":"venue"
},
  "geometry": {"coordinates":[13.798251152,46.8128662109],"type":"Point"}
}