{
  "type": "Feature",
  "properties": {
    "addr:full":"Fockyg 14 Wien Wien 1120",
    "addr:housenumber":"14",
    "addr:postcode":"1120",
    "addr:street":"Fockyg",
    "iso:country":"AT",
    "sg:address":"Fockyg 14",
    "sg:city":"Wien",
    "sg:orig_category":"Tonstudios",
    "sg:phone":"+43 1 8124720",
    "sg:postcode":"1120",
    "sg:province":"Wien",
    "wof:name":"Seemann mastersound",
    "wof:placetype":"venue"
},
  "geometry": {"coordinates":[16.3410434723,48.1827163696],"type":"Point"}
}