{
  "type": "Feature",
  "properties": {
    "iso:country":"AT",
    "sg:address":"Hungerfeldweg 15",
    "sg:city":"Pottenbrunn",
    "sg:orig_category":"Logistik",
    "sg:phone":"+43 664 1452656",
    "sg:postcode":"3140",
    "sg:province":"Nieder\u00f6sterreich",
    "wof:name":"GICC Logistic GmbH",
    "wof:placetype":"venue"
},
  "geometry": {"coordinates":[15.7016096115,48.2394866943],"type":"Point"}
}