{
  "type": "Feature",
  "properties": {
    "addr:full":"Wilhelmstr 43 Wien Wien 1120",
    "addr:housenumber":"43",
    "addr:postcode":"1120",
    "addr:street":"Wilhelmstr",
    "iso:country":"AT",
    "sg:address":"Wilhelmstr 43",
    "sg:city":"Wien",
    "sg:orig_category":"Architekten",
    "sg:phone":"+43 676 5303920",
    "sg:postcode":"1120",
    "sg:province":"Wien",
    "wof:name":"Wutscher Harald Arch Dipl-Ing",
    "wof:placetype":"venue"
},
  "geometry": {"coordinates":[16.3328113556,48.1755523682],"type":"Point"}
}