{
  "type": "Feature",
  "properties": {
    "iso:country":"AT",
    "sg:address":"Roseggerstrasse 25",
    "sg:city":"Bruck an der Mur",
    "sg:classifiers":[
        {
            "category":"Shopping",
            "subcategory":"Crafts & Fabrics",
            "type":"Retail Goods"
        }
    ],
    "sg:phone":"+43 3862 54428",
    "sg:postcode":"8600",
    "sg:province":"Steiermark",
    "sg:tags":[
        "decorative",
        "ceramic",
        "artistic"
    ],
    "sg:website":"kreativwerkstatt.at",
    "wof:name":"Kreativ Werkstatt Sonja Ebner",
    "wof:placetype":"venue"
},
  "geometry": {"coordinates":[15.2727222443,47.4103660583],"type":"Point"}
}