{
  "type": "Feature",
  "properties": {
    "addr:full":"Pi\u00f6smes 202 St. Leonhard im Pitztal Tirol 6481",
    "addr:housenumber":"202",
    "addr:postcode":"6481",
    "addr:street":"Tirol",
    "iso:country":"AT",
    "sg:address":"Pi\u00f6smes 202",
    "sg:city":"St. Leonhard im Pitztal",
    "sg:orig_category":"Pensionen / Privatzimmer",
    "sg:phone":"+43 4354 1387371",
    "sg:postcode":"6481",
    "sg:province":"Tirol",
    "wof:name":"Apart-Pension Romantika",
    "wof:placetype":"venue"
},
  "geometry": {"coordinates":[10.8461503983,47.0666313171],"type":"Point"}
}