{
  "type": "Feature",
  "properties": {
    "addr:full":"Himberger Str 53 Wien Wien 1100",
    "addr:postcode":"1100",
    "addr:street":"Str 53",
    "iso:country":"AT",
    "sg:address":"Himberger Str 53",
    "sg:city":"Wien",
    "sg:classifiers":[
        {
            "category":"Restaurant",
            "type":"Food & Drink"
        }
    ],
    "sg:phone":"+43 1 68871220",
    "sg:postcode":"1100",
    "sg:province":"Wien",
    "wof:name":"Rothneusiedler Hof",
    "wof:placetype":"venue"
},
  "geometry": {"coordinates":[16.3830318451,48.1383590698],"type":"Point"}
}