{
  "type": "Feature",
  "properties": {
    "iso:country":"AT",
    "sg:address":"Anifer Str 11",
    "sg:city":"Anif",
    "sg:orig_category":"Friseure U Frisiersalons",
    "sg:phone":"+43 6246 73929",
    "sg:postcode":"5081",
    "sg:province":"Salzburg",
    "wof:name":"Richter Sonja",
    "wof:placetype":"venue"
},
  "geometry": {"coordinates":[13.0642166138,47.7498893738],"type":"Point"}
}