{
  "type": "Feature",
  "properties": {
    "addr:full":"Perlenstr 5 Enns Ober\u00f6sterreich 4470",
    "addr:housenumber":"5",
    "addr:postcode":"4470",
    "addr:street":"Perlenstr",
    "iso:country":"AT",
    "sg:address":"Perlenstr 5",
    "sg:city":"Enns",
    "sg:orig_category":"Massagen",
    "sg:phone":"+43 7223 83293",
    "sg:postcode":"4470",
    "sg:province":"Ober\u00f6sterreich",
    "wof:name":"Institut f Gesundheitsf\u00f6rderung",
    "wof:placetype":"venue"
},
  "geometry": {"coordinates":[14.4738044739,48.2053947449],"type":"Point"}
}