{
  "type": "Feature",
  "properties": {
    "iso:country":"AT",
    "sg:address":"St. Martiner Str 33a",
    "sg:city":"Villach",
    "sg:orig_category":"Tabaktrafiken",
    "sg:phone":"+43 4242 53684",
    "sg:postcode":"9500",
    "sg:province":"K\u00e4rnten",
    "wof:name":"Pichler Manfred",
    "wof:placetype":"venue"
},
  "geometry": {"coordinates":[13.8324317932,46.616519928],"type":"Point"}
}