{
  "type": "Feature",
  "properties": {
    "addr:full":"Hauptstr 221 Krumpendorf K\u00e4rnten 9201",
    "addr:housenumber":"221",
    "addr:postcode":"9201",
    "addr:street":"Hauptstr;Kaernten",
    "iso:country":"AT",
    "sg:address":"Hauptstr 221",
    "sg:city":"Krumpendorf",
    "sg:orig_category":"Lebensmittel / Einzelhandel",
    "sg:phone":"+43 4229 3686",
    "sg:postcode":"9201",
    "sg:province":"K\u00e4rnten",
    "wof:name":"Billa AG",
    "wof:placetype":"venue"
},
  "geometry": {"coordinates":[14.2041463852,46.6254234314],"type":"Point"}
}