{
  "type": "Feature",
  "properties": {
    "iso:country":"AT",
    "sg:address":"Haydnpl 4",
    "sg:city":"Innsbruck",
    "sg:orig_category":"Beratungsstellen",
    "sg:phone":"+43 4351 2934102",
    "sg:postcode":"6020",
    "sg:province":"Tirol",
    "sg:website":"memory-lerntherapie.at",
    "wof:name":"Memory, Institut f Prozessorientierte Lerntherapie + Diagnostik",
    "wof:placetype":"venue"
},
  "geometry": {"coordinates":[11.4074554443,47.2776641846],"type":"Point"}
}