{
  "type": "Feature",
  "properties": {
    "addr:full":"Haasg 15 Wolkersdorf im Weinviertel Nieder\u00f6sterreich 2120",
    "addr:housenumber":"15",
    "addr:postcode":"2120",
    "addr:street":"Haasg",
    "iso:country":"AT",
    "sg:address":"Haasg 15",
    "sg:city":"Wolkersdorf im Weinviertel",
    "sg:orig_category":"Beratungsstellen",
    "sg:phone":"+43 4322 4563950",
    "sg:postcode":"2120",
    "sg:province":"Nieder\u00f6sterreich",
    "wof:name":"Institut zur beruflichen Integration - IBI",
    "wof:placetype":"venue"
},
  "geometry": {"coordinates":[16.5198898315,48.382976532],"type":"Point"}
}