{
  "type": "Feature",
  "properties": {
    "addr:full":"B\u00f6hmerg 8-10 Freistadt Ober\u00f6sterreich 4240",
    "addr:housenumber":"8-10",
    "addr:postcode":"4240",
    "iso:country":"AT",
    "sg:address":"B\u00f6hmerg 8-10",
    "sg:city":"Freistadt",
    "sg:classifiers":[
        {
            "category":"Travel",
            "subcategory":"Hotels & Motels",
            "type":"Entertainment"
        }
    ],
    "sg:phone":"+43 7942 722580",
    "sg:postcode":"4240",
    "sg:province":"Ober\u00f6sterreich",
    "wof:name":"Hotel Goldener Hirsch",
    "wof:placetype":"venue"
},
  "geometry": {"coordinates":[14.5049953461,48.5119857788],"type":"Point"}
}