{
  "type": "Feature",
  "properties": {
    "iso:country":"AT",
    "sg:city":"Lebring",
    "sg:orig_category":"Bankomat-Standorte",
    "sg:phone":"+43 3182 2580",
    "sg:postcode":"8403",
    "sg:province":"Steiermark",
    "wof:name":"Bankomat d Raiffeisenbank Lebring",
    "wof:placetype":"venue"
},
  "geometry": {"coordinates":[15.5376806259,46.8533821106],"type":"Point"}
}