{
  "type": "Feature",
  "properties": {
    "addr:full":"St.-Peter-Str 19 Bludenz Vorarlberg 6700",
    "addr:housenumber":"19",
    "addr:postcode":"6700",
    "addr:street":"St.-Peter-Str",
    "iso:country":"AT",
    "sg:address":"St.-Peter-Str 19",
    "sg:city":"Bludenz",
    "sg:orig_category":"Lebensmittel / Einzelhandel",
    "sg:phone":"+43 4355 5262799",
    "sg:postcode":"6700",
    "sg:province":"Vorarlberg",
    "wof:name":"Billa AG",
    "wof:placetype":"venue"
},
  "geometry": {"coordinates":[9.8261013031,47.1499900818],"type":"Point"}
}