{
  "type": "Feature",
  "properties": {
    "addr:full":"Priesterhausg 10 Klagenfurt K\u00e4rnten 9020",
    "addr:housenumber":"10",
    "addr:postcode":"9020",
    "addr:street":"Priesterhausg;Kaernten",
    "iso:country":"AT",
    "sg:address":"Priesterhausg 10",
    "sg:city":"Klagenfurt",
    "sg:orig_category":"Lederwaren / Einzelhandel",
    "sg:phone":"+43 4346 355694",
    "sg:postcode":"9020",
    "sg:province":"K\u00e4rnten",
    "wof:name":"Neuner Christof GesmbH & Co KG",
    "wof:placetype":"venue"
},
  "geometry": {"coordinates":[14.3116178513,46.6255455017],"type":"Point"}
}