{
  "type": "Feature",
  "properties": {
    "iso:country":"AT",
    "sg:address":"Endresstr 117",
    "sg:city":"Wien",
    "sg:orig_category":"Non-Classified Establishments",
    "sg:phone":"+43 1 88813180",
    "sg:postcode":"1230",
    "sg:province":"Wien",
    "wof:name":"Pfarramt Mauer St Erhard",
    "wof:placetype":"venue"
},
  "geometry": {"coordinates":[16.2693386078,48.1503753662],"type":"Point"}
}