{
  "type": "Feature",
  "properties": {
    "addr:full":"W\u00e4hringer Str 103 Wien Wien 1180",
    "addr:housenumber":"103",
    "addr:postcode":"1180",
    "addr:street":"Str",
    "iso:country":"AT",
    "sg:address":"W\u00e4hringer Str 103",
    "sg:city":"Wien",
    "sg:orig_category":"Drogerien",
    "sg:phone":"+43 1 4058907",
    "sg:postcode":"1180",
    "sg:province":"Wien",
    "wof:name":"dm drogerie markt GmbH",
    "wof:placetype":"venue"
},
  "geometry": {"coordinates":[16.3429908752,48.226398468],"type":"Point"}
}