{
  "type": "Feature",
  "properties": {
    "addr:full":"Eisteichstr 7 Wien Wien 1110",
    "addr:housenumber":"7",
    "addr:postcode":"1110",
    "addr:street":"Eisteichstr",
    "iso:country":"AT",
    "sg:address":"Eisteichstr 7",
    "sg:city":"Wien",
    "sg:orig_category":"Gerichtsdolmetscher",
    "sg:phone":"+43 1 7485974",
    "sg:postcode":"1110",
    "sg:province":"Wien",
    "wof:name":"Picej Josef H",
    "wof:placetype":"venue"
},
  "geometry": {"coordinates":[16.4144096375,48.1804771423],"type":"Point"}
}