{
  "type": "Feature",
  "properties": {
    "iso:country":"AT",
    "sg:address":"Serlesweg 5",
    "sg:city":"Patsch",
    "sg:orig_category":"Appartements / Ferienwohnungen",
    "sg:phone":"+43 4351 2377635",
    "sg:postcode":"6082",
    "sg:province":"Tirol",
    "wof:name":"Muigg Taxi - Aktivtours",
    "wof:placetype":"venue"
},
  "geometry": {"coordinates":[11.4173088074,47.2057495117],"type":"Point"}
}