{
  "type": "Feature",
  "properties": {
    "addr:full":"Haunsbergstrasse 11 Oberndorf Salzburg 5110",
    "addr:housenumber":"11",
    "addr:postcode":"5110",
    "addr:street":"Haunsbergstrasse",
    "iso:country":"AT",
    "sg:address":"Haunsbergstrasse 11",
    "sg:city":"Oberndorf",
    "sg:classifiers":[
        {
            "category":"Wholesale",
            "subcategory":"Home Furnishings",
            "type":"Manufacturing & Wholesale Goods"
        }
    ],
    "sg:phone":"+43 6272 6373",
    "sg:postcode":"5110",
    "sg:province":"Salzburg",
    "sg:tags":[
        "dh",
        "heating",
        "district",
        "system"
    ],
    "wof:name":"Gas - Wasser - u. Heizungsinstallationen, Bellinghausen GmbH",
    "wof:placetype":"venue"
},
  "geometry": {"coordinates":[12.9325675964,47.9608917236],"type":"Point"}
}