{
  "type": "Feature",
  "properties": {
    "addr:full":"Villacher Strasse 3 Spittal an der Drau K\u00e4rnten 9800",
    "addr:housenumber":"3",
    "addr:postcode":"9800",
    "addr:street":"Villacher Strasse;Kaernten",
    "iso:country":"AT",
    "sg:address":"Villacher Strasse 3",
    "sg:city":"Spittal an der Drau",
    "sg:classifiers":[
        {
            "category":"Home & Garden",
            "subcategory":"Hardware",
            "type":"Retail Goods"
        }
    ],
    "sg:phone":"+43 4762 615000",
    "sg:postcode":"9800",
    "sg:province":"K\u00e4rnten",
    "sg:tags":[
        "agricultural",
        "implement"
    ],
    "wof:name":"Anton H. Fr\u00f6hlich Maschinenhandel und Landmaschinenreparaturwerk Ges.m.b.H.",
    "wof:placetype":"venue"
},
  "geometry": {"coordinates":[13.486869812,46.8216552734],"type":"Point"}
}