{
  "type": "Feature",
  "properties": {
    "addr:full":"Alser Str 55 Wien Wien 1080",
    "addr:postcode":"1080",
    "addr:street":"Str 55",
    "iso:country":"AT",
    "sg:address":"Alser Str 55",
    "sg:city":"Wien",
    "sg:classifiers":[
        {
            "category":"Organizations",
            "subcategory":"Community Association",
            "type":"Services"
        }
    ],
    "sg:phone":"+43 1 4084348",
    "sg:postcode":"1080",
    "sg:province":"Wien",
    "sg:tags":[
        "relation",
        "public"
    ],
    "wof:name":"LADINIG & PARTNER KEG",
    "wof:placetype":"venue"
},
  "geometry": {"coordinates":[16.3446941376,48.215133667],"type":"Point"}
}