{
  "type": "Feature",
  "properties": {
    "addr:full":"Schleierfallstr 6 Gaming Nieder\u00f6sterreich 3292",
    "addr:housenumber":"6",
    "addr:postcode":"3292",
    "addr:street":"Schleierfallstr",
    "iso:country":"AT",
    "sg:address":"Schleierfallstr 6",
    "sg:city":"Gaming",
    "sg:orig_category":"Volksschulen",
    "sg:phone":"+43 4374 8597335",
    "sg:postcode":"3292",
    "sg:province":"Nieder\u00f6sterreich",
    "wof:name":"Volksschule u allgemeine Sonderschule",
    "wof:placetype":"venue"
},
  "geometry": {"coordinates":[15.0940141678,47.9249382019],"type":"Point"}
}