{
  "type": "Feature",
  "properties": {
    "addr:full":"Nr 101 Steinach am Brenner Tirol 6150",
    "addr:postcode":"6150",
    "addr:street":"Nr 101;Tirol",
    "iso:country":"AT",
    "sg:address":"Nr 101",
    "sg:city":"Steinach am Brenner",
    "sg:orig_category":"Gemeinden",
    "sg:phone":"+43 5276 209",
    "sg:postcode":"6150",
    "sg:province":"Tirol",
    "wof:name":"Gemeindeamt Gschnitz",
    "wof:placetype":"venue"
},
  "geometry": {"coordinates":[11.466711998,47.0918159485],"type":"Point"}
}