{
  "type": "Feature",
  "properties": {
    "iso:country":"AT",
    "sg:address":"Kaiserstr 4",
    "sg:city":"Aschach an der Steyr",
    "sg:orig_category":"Waren Aller Art",
    "sg:phone":"+43 7252 53052",
    "sg:postcode":"4421",
    "sg:province":"Ober\u00f6sterreich",
    "wof:name":"Matzer Helmut Dipl-Ing",
    "wof:placetype":"venue"
},
  "geometry": {"coordinates":[14.3637809753,48.0234146118],"type":"Point"}
}