{
  "type": "Feature",
  "properties": {
    "addr:full":"Dorf 51 Kirchberg in Tirol Tirol 6365",
    "addr:housenumber":"51",
    "addr:postcode":"6365",
    "addr:street":"Dorf;Tirol",
    "iso:country":"AT",
    "sg:address":"Dorf 51",
    "sg:city":"Kirchberg in Tirol",
    "sg:orig_category":"Tischlereien",
    "sg:phone":"+43 5357 35772",
    "sg:postcode":"6365",
    "sg:province":"Tirol",
    "wof:name":"Bacher Bernhard - DER MOBILE HOLZWURM",
    "wof:placetype":"venue"
},
  "geometry": {"coordinates":[12.3147678375,47.447101593],"type":"Point"}
}