{
  "type": "Feature",
  "properties": {
    "iso:country":"AT",
    "sg:address":"Hauptpl 2",
    "sg:city":"Ebreichsdorf",
    "sg:orig_category":"Restaurants: Chinesisch",
    "sg:phone":"+43 2254 72623",
    "sg:postcode":"2483",
    "sg:province":"Nieder\u00f6sterreich",
    "wof:name":"China Restaurant Palast",
    "wof:placetype":"venue"
},
  "geometry": {"coordinates":[16.401714325,47.9634780884],"type":"Point"}
}