{
  "type": "Feature",
  "properties": {
    "iso:country":"AT",
    "sg:address":"Buchfeldg 5",
    "sg:city":"Wien",
    "sg:classifiers":[
        {
            "category":"Travel",
            "subcategory":"Hotels & Motels",
            "type":"Entertainment"
        }
    ],
    "sg:phone":"+43 1 40552840",
    "sg:postcode":"1080",
    "sg:province":"Wien",
    "wof:name":"Graf Stadion",
    "wof:placetype":"venue"
},
  "geometry": {"coordinates":[16.3533859253,48.2098655701],"type":"Point"}
}