{
  "type": "Feature",
  "properties": {
    "addr:full":"Schmitternstr 10 Lustenau Vorarlberg 6890",
    "addr:housenumber":"10",
    "addr:postcode":"6890",
    "addr:street":"Schmitternstr",
    "iso:country":"AT",
    "sg:address":"Schmitternstr 10",
    "sg:city":"Lustenau",
    "sg:orig_category":"Beton- U Betonsteinwerke",
    "sg:phone":"+43 4355 77827710",
    "sg:postcode":"6890",
    "sg:province":"Vorarlberg",
    "wof:name":"Vorarlberger Lieferbeton GmbH & Co",
    "wof:placetype":"venue"
},
  "geometry": {"coordinates":[9.6692352295,47.3943595886],"type":"Point"}
}