{
  "type": "Feature",
  "properties": {
    "iso:country":"AT",
    "sg:address":"Nr 160",
    "sg:city":"Litschau",
    "sg:classifiers":[
        {
            "category":"Travel",
            "subcategory":"Hotels & Motels",
            "type":"Entertainment"
        }
    ],
    "sg:phone":"+43 2865 84410",
    "sg:postcode":"3874",
    "sg:province":"Nieder\u00f6sterreich",
    "wof:name":"Golfresort Haugschlag GmbH & Co KG",
    "wof:placetype":"venue"
},
  "geometry": {"coordinates":[15.0453643799,48.9441757202],"type":"Point"}
}