{
  "type": "Feature",
  "properties": {
    "iso:country":"AT",
    "sg:address":"Neusiedler Str 41a",
    "sg:city":"Eisenstadt",
    "sg:orig_category":"Tabaktrafiken",
    "sg:phone":"+43 2682 61353",
    "sg:postcode":"7000",
    "sg:province":"Burgenland",
    "wof:name":"Frank Petra",
    "wof:placetype":"venue"
},
  "geometry": {"coordinates":[16.5316028595,47.8473777771],"type":"Point"}
}