{
  "type": "Feature",
  "properties": {
    "addr:full":"Hintere G 5D Rietz Tirol 6421",
    "addr:housenumber":"5d",
    "addr:postcode":"6421",
    "addr:street":"Hintere G;Tirol",
    "iso:country":"AT",
    "sg:address":"Hintere G 5D",
    "sg:city":"Rietz",
    "sg:orig_category":"Musikgruppen",
    "sg:phone":"+43 5262 63300",
    "sg:postcode":"6421",
    "sg:province":"Tirol",
    "wof:name":"Music Family",
    "wof:placetype":"venue"
},
  "geometry": {"coordinates":[11.0309400558,47.286151886],"type":"Point"}
}