{
  "type": "Feature",
  "properties": {
    "iso:country":"AT",
    "sg:address":"Schildbach 39",
    "sg:city":"Hartberg",
    "sg:orig_category":"Gemeinden",
    "sg:phone":"+43 3332 628490",
    "sg:postcode":"8230",
    "sg:province":"Steiermark",
    "wof:name":"Gemeinde Hartberg-Umgebung",
    "wof:placetype":"venue"
},
  "geometry": {"coordinates":[15.9538917542,47.2759628296],"type":"Point"}
}