{
  "type": "Feature",
  "properties": {
    "addr:full":"Salzburger Str 9 Friedburg Ober\u00f6sterreich 5211",
    "addr:housenumber":"9",
    "addr:postcode":"5211",
    "addr:street":"Salzburger Str",
    "iso:country":"AT",
    "sg:address":"Salzburger Str 9",
    "sg:city":"Friedburg",
    "sg:orig_category":"Non-Classified Establishments",
    "sg:phone":"+43 5 91334206",
    "sg:postcode":"5211",
    "sg:province":"Ober\u00f6sterreich",
    "wof:name":"Gendarmerieposten Friedburg",
    "wof:placetype":"venue"
},
  "geometry": {"coordinates":[13.2485084534,48.0164031982],"type":"Point"}
}