{
  "type": "Feature",
  "properties": {
    "addr:full":"Dolomitenstr 33b/9 Lienz Tirol 9900",
    "addr:housenumber":"33b / 9",
    "addr:postcode":"9900",
    "addr:street":"Dolomitenstr;Tirol",
    "iso:country":"AT",
    "sg:address":"Dolomitenstr 33b/9",
    "sg:city":"Lienz",
    "sg:classifiers":[
        {
            "category":"Taxi",
            "type":"Transportation"
        }
    ],
    "sg:phone":"+43 4348 5272600",
    "sg:postcode":"9900",
    "sg:province":"Tirol",
    "sg:tags":[
        "personentransporte",
        "u"
    ],
    "wof:name":"Taxi Helli",
    "wof:placetype":"venue"
},
  "geometry": {"coordinates":[12.7575187683,46.8236541748],"type":"Point"}
}