{
  "type": "Feature",
  "properties": {
    "iso:country":"AT",
    "sg:address":"Au 44",
    "sg:city":"Bad Wimsbach-Neydharting",
    "sg:orig_category":"Bauunternehmen",
    "sg:phone":"+43 4372 45251890",
    "sg:postcode":"4654",
    "sg:province":"Ober\u00f6sterreich",
    "wof:name":"L\u00fcftinger Baugesellschaft mbH",
    "wof:placetype":"venue"
},
  "geometry": {"coordinates":[13.915099144,48.0363426208],"type":"Point"}
}