{
  "type": "Feature",
  "properties": {
    "addr:full":"Marktfeldstr 310 Neulengbach Nieder\u00f6sterreich 3040",
    "addr:housenumber":"310",
    "addr:postcode":"3040",
    "iso:country":"AT",
    "sg:address":"Marktfeldstr 310",
    "sg:city":"Neulengbach",
    "sg:orig_category":"Weiterbildungsinstitute M Allg U Berufl Bildungsangebot",
    "sg:phone":"+43 2772 55097",
    "sg:postcode":"3040",
    "sg:province":"Nieder\u00f6sterreich",
    "wof:name":"Kurse f Beruf und Freizeit",
    "wof:placetype":"venue"
},
  "geometry": {"coordinates":[15.9078187943,48.2019386292],"type":"Point"}
}