{
  "type": "Feature",
  "properties": {
    "iso:country":"AT",
    "sg:address":"Stuwerstrasse 23",
    "sg:city":"Wien",
    "sg:classifiers":[
        {
            "category":"Shopping",
            "subcategory":"Gifts & Souvenirs",
            "type":"Retail Goods"
        }
    ],
    "sg:phone":"+43 1 7280794",
    "sg:postcode":"1020",
    "sg:province":"Wien",
    "sg:tags":[
        "calendar"
    ],
    "sg:website":"weilguny.at",
    "wof:name":"Dipl.-Ing. Wolfgang Weilguny",
    "wof:placetype":"venue"
},
  "geometry": {"coordinates":[16.4005088806,48.2189064026],"type":"Point"}
}