{
  "type": "Feature",
  "properties": {
    "iso:country":"AT",
    "sg:address":"Alte Poststr 116",
    "sg:city":"Graz",
    "sg:orig_category":"Drogerien",
    "sg:phone":"+43 316 570345",
    "sg:postcode":"8020",
    "sg:province":"Steiermark",
    "wof:name":"Friedel Herta",
    "wof:placetype":"venue"
},
  "geometry": {"coordinates":[15.4077606201,47.0736732483],"type":"Point"}
}