{
  "type": "Feature",
  "properties": {
    "iso:country":"AT",
    "sg:address":"Am Spiegeln 8",
    "sg:city":"Wien",
    "sg:classifiers":[
        {
            "category":"Taxi",
            "type":"Transportation"
        }
    ],
    "sg:phone":"+43 4318 886565",
    "sg:postcode":"1230",
    "sg:province":"Wien",
    "sg:tags":[
        "personentransporte",
        "u"
    ],
    "wof:name":"Hauptvogel Ernest",
    "wof:placetype":"venue"
},
  "geometry": {"coordinates":[16.2844734192,48.1541175842],"type":"Point"}
}