{
  "type": "Feature",
  "properties": {
    "addr:full":"Wiener Str 6 Linz Ober\u00f6sterreich 4020",
    "addr:housenumber":"6",
    "addr:postcode":"4020",
    "iso:country":"AT",
    "sg:address":"Wiener Str 6",
    "sg:city":"Linz",
    "sg:classifiers":[
        {
            "category":"Retail",
            "subcategory":"Event Space",
            "type":"Services"
        }
    ],
    "sg:phone":"+43 732 612957",
    "sg:postcode":"4020",
    "sg:province":"Ober\u00f6sterreich",
    "sg:tags":[
        "hand-",
        "u",
        "fu\u00c3\u0178pflege"
    ],
    "wof:name":"Kosmetik Christine",
    "wof:placetype":"venue"
},
  "geometry": {"coordinates":[14.2974290848,48.2900466919],"type":"Point"}
}