{
  "type": "Feature",
  "properties": {
    "addr:full":"R\u00f6merstr 19 Bregenz Vorarlberg 6900",
    "addr:housenumber":"19",
    "addr:postcode":"6900",
    "addr:street":"Roemerstr",
    "iso:country":"AT",
    "sg:address":"R\u00f6merstr 19",
    "sg:city":"Bregenz",
    "sg:orig_category":"Massagen",
    "sg:phone":"+43 5574 46522",
    "sg:postcode":"6900",
    "sg:province":"Vorarlberg",
    "wof:name":"Degen Michael",
    "wof:placetype":"venue"
},
  "geometry": {"coordinates":[9.743311882,47.5008964539],"type":"Point"}
}