{
  "type": "Feature",
  "properties": {
    "addr:full":"Rosegger Str. 12a Traun Ober\u00f6sterreich 4050",
    "addr:housenumber":"12a",
    "addr:postcode":"4050",
    "addr:street":"Str.",
    "iso:country":"AT",
    "sg:address":"Rosegger Str. 12a",
    "sg:city":"Traun",
    "sg:classifiers":[
        {
            "category":"Manufacturing",
            "subcategory":"Metals",
            "type":"Manufacturing & Wholesale Goods"
        }
    ],
    "sg:phone":"+43 4372 29710010",
    "sg:postcode":"4050",
    "sg:province":"Ober\u00f6sterreich",
    "sg:tags":[
        "metallurgy",
        "metalworking"
    ],
    "wof:name":"OFAE FRIEDRICH GALLI GMBH & CO. KG",
    "wof:placetype":"venue"
},
  "geometry": {"coordinates":[14.2592792511,48.2403640747],"type":"Point"}
}