{
  "type": "Feature",
  "properties": {
    "addr:full":"Friedhofstr 9 Wiener Neudorf Nieder\u00f6sterreich 2351",
    "addr:housenumber":"9",
    "addr:postcode":"2351",
    "addr:street":"Friedhofstr",
    "iso:country":"AT",
    "sg:address":"Friedhofstr 9",
    "sg:city":"Wiener Neudorf",
    "sg:orig_category":"Kinderbetreuung",
    "sg:phone":"+43 2236 61301",
    "sg:postcode":"2351",
    "sg:province":"Nieder\u00f6sterreich",
    "wof:name":"Hort d Gemeindeamt d Marktgemeinde Wiener Neudorf",
    "wof:placetype":"venue"
},
  "geometry": {"coordinates":[16.3212871552,48.0865821838],"type":"Point"}
}