{
  "type": "Feature",
  "properties": {
    "addr:full":"Nr 1 Gerlos Tirol 6281",
    "addr:postcode":"6281",
    "addr:street":"Nr;Gerlos",
    "iso:country":"AT",
    "sg:address":"Nr 1",
    "sg:city":"Gerlos",
    "sg:orig_category":"Non-Classified Establishments",
    "sg:phone":"+43 5284 5444",
    "sg:postcode":"6281",
    "sg:province":"Tirol",
    "wof:name":"Pfarramt",
    "wof:placetype":"venue"
},
  "geometry": {"coordinates":[12.0359144211,47.2256088257],"type":"Point"}
}