{
  "type": "Feature",
  "properties": {
    "addr:full":"Frauentaler Str 100 Deutschlandsberg Steiermark 8530",
    "addr:housenumber":"100",
    "addr:postcode":"8530",
    "iso:country":"AT",
    "sg:address":"Frauentaler Str 100",
    "sg:city":"Deutschlandsberg",
    "sg:orig_category":"Steuerungstechnik",
    "sg:phone":"+43 4334 626800",
    "sg:postcode":"8530",
    "sg:province":"Steiermark",
    "wof:name":"Seidel Elektronik GmbH Nfg KG",
    "wof:placetype":"venue"
},
  "geometry": {"coordinates":[15.2323141098,46.8204841614],"type":"Point"}
}