{
  "type": "Feature",
  "properties": {
    "addr:full":"Nr 43 Waxenberg Ober\u00f6sterreich 4182",
    "addr:postcode":"4182",
    "addr:street":"Nr;Waxenberg",
    "iso:country":"AT",
    "sg:address":"Nr 43",
    "sg:city":"Waxenberg",
    "sg:orig_category":"Berufsbekleidung / Erzeugung U Gro\u00c3\u0178handel",
    "sg:phone":"+43 4372 1763900",
    "sg:postcode":"4182",
    "sg:province":"Ober\u00f6sterreich",
    "wof:name":"Haider GmbH",
    "wof:placetype":"venue"
},
  "geometry": {"coordinates":[14.1926040649,48.4773483276],"type":"Point"}
}