{
  "type": "Feature",
  "properties": {
    "addr:full":"Eberhard-Fugger-Str 4 Salzburg Salzburg 5020",
    "addr:housenumber":"4",
    "addr:postcode":"5020",
    "addr:street":"Eberhard-Fugger-Str;Salzburg",
    "iso:country":"AT",
    "sg:address":"Eberhard-Fugger-Str 4",
    "sg:city":"Salzburg",
    "sg:orig_category":"Schneidereien",
    "sg:phone":"+43 662 650664",
    "sg:postcode":"5020",
    "sg:province":"Salzburg",
    "wof:name":"\u00f6zbek Schneiderei",
    "wof:placetype":"venue"
},
  "geometry": {"coordinates":[13.0668907166,47.8024864197],"type":"Point"}
}