{
  "type": "Feature",
  "properties": {
    "iso:country":"AT",
    "sg:address":"Reichsstr 65a",
    "sg:city":"Lustenau",
    "sg:orig_category":"Massagen",
    "sg:phone":"+43 4355 7788657",
    "sg:postcode":"6890",
    "sg:province":"Vorarlberg",
    "wof:name":"Mogorosi Andreas",
    "wof:placetype":"venue"
},
  "geometry": {"coordinates":[9.6538095474,47.4371681213],"type":"Point"}
}