{
  "type": "Feature",
  "properties": {
    "addr:full":"Unterer Pl 4-5 St. Veit an der Glan K\u00e4rnten 9300",
    "addr:housenumber":"4-5",
    "addr:postcode":"9300",
    "addr:street":"Unterer Pl;Kaernten",
    "iso:country":"AT",
    "sg:address":"Unterer Pl 4-5",
    "sg:city":"St. Veit an der Glan",
    "sg:orig_category":"Pizzazustellungen",
    "sg:phone":"+43 4342 124033",
    "sg:postcode":"9300",
    "sg:province":"K\u00e4rnten",
    "wof:name":"St Veiter Pizza u Schnitzeldienst",
    "wof:placetype":"venue"
},
  "geometry": {"coordinates":[14.3588809967,46.7680435181],"type":"Point"}
}