{
  "type": "Feature",
  "properties": {
    "iso:country":"AT",
    "sg:address":"Nr 34",
    "sg:city":"Pinkafeld",
    "sg:orig_category":"Spenglereien",
    "sg:phone":"+43 3357 43020",
    "sg:postcode":"7423",
    "sg:province":"Burgenland",
    "wof:name":"Reiter David",
    "wof:placetype":"venue"
},
  "geometry": {"coordinates":[12.1902103424,49.134311676],"type":"Point"}
}