{
  "type": "Feature",
  "properties": {
    "iso:country":"AT",
    "sg:address":"Zehnerg\u00fcrtel 12-24 Fischapark Top 34",
    "sg:city":"Wiener Neustadt",
    "sg:orig_category":"Telekommunikation",
    "sg:phone":"+43 4367 620800",
    "sg:postcode":"2700",
    "sg:province":"Nieder\u00f6sterreich",
    "wof:name":"T-Mobile Wiener Neustadt-Fischapark",
    "wof:placetype":"venue"
},
  "geometry": {"coordinates":[16.2455158234,47.8128814697],"type":"Point"}
}