{
  "type": "Feature",
  "properties": {
    "iso:country":"AT",
    "sg:address":"Lieferinger Hauptstrasse 116",
    "sg:city":"Salzburg",
    "sg:classifiers":[
        {
            "category":"Building & Trades",
            "subcategory":"Plumbing",
            "type":"Services"
        }
    ],
    "sg:phone":"+43 662 434386",
    "sg:postcode":"5020",
    "sg:province":"Salzburg",
    "sg:tags":[
        "tub",
        "bath"
    ],
    "wof:name":"Herbert Sturm Ges.m.b.H. & Co KG",
    "wof:placetype":"venue"
},
  "geometry": {"coordinates":[13.0094194412,47.8245048523],"type":"Point"}
}