{
  "type": "Feature",
  "properties": {
    "iso:country":"AT",
    "sg:address":"Donaustr 108/6",
    "sg:city":"Maria Enzersdorf",
    "sg:classifiers":[
        {
            "category":"Professional",
            "subcategory":"Management & Consulting",
            "type":"Services"
        }
    ],
    "sg:phone":"+43 4366 04607184",
    "sg:postcode":"2344",
    "sg:province":"Nieder\u00f6sterreich",
    "wof:name":"Hopf Roman Artist & Event Management",
    "wof:placetype":"venue"
},
  "geometry": {"coordinates":[16.3064212799,48.0998001099],"type":"Point"}
}