{
  "type": "Feature",
  "properties": {
    "addr:full":"Weichselweg 4 Wien Wien 1220",
    "addr:housenumber":"4",
    "addr:postcode":"1220",
    "addr:street":"Weichselweg",
    "iso:country":"AT",
    "sg:address":"Weichselweg 4",
    "sg:city":"Wien",
    "sg:orig_category":"Sprachschulen U -Unterricht",
    "sg:phone":"+43 4319 581972",
    "sg:postcode":"1220",
    "sg:province":"Wien",
    "sg:website":"englishforchildren.com",
    "wof:name":"English for Children",
    "wof:placetype":"venue"
},
  "geometry": {"coordinates":[16.4554271698,48.2076911926],"type":"Point"}
}