{
  "type": "Feature",
  "properties": {
    "addr:full":"Dorfstr 86 St. Anton am Arlberg Tirol 6580",
    "addr:housenumber":"86",
    "addr:postcode":"6580",
    "addr:street":"Dorfstr",
    "iso:country":"AT",
    "sg:address":"Dorfstr 86",
    "sg:city":"St. Anton am Arlberg",
    "sg:classifiers":[
        {
            "category":"Travel",
            "subcategory":"Hotels & Motels",
            "type":"Entertainment"
        }
    ],
    "sg:phone":"+43 5446 2249",
    "sg:postcode":"6580",
    "sg:province":"Tirol",
    "wof:name":"Hotel-Pension Edelwei\u00df",
    "wof:placetype":"venue"
},
  "geometry": {"coordinates":[10.2701482773,47.1321029663],"type":"Point"}
}