{
  "type": "Feature",
  "properties": {
    "addr:full":"Perfektastr 82 Wien Wien 1230",
    "addr:housenumber":"82",
    "addr:postcode":"1230",
    "addr:street":"Perfektastr",
    "iso:country":"AT",
    "sg:address":"Perfektastr 82",
    "sg:city":"Wien",
    "sg:orig_category":"Druckereimaschinen U -Bedarf",
    "sg:phone":"+43 4318 6976060",
    "sg:postcode":"1230",
    "sg:province":"Wien",
    "sg:website":"sunchemical.com",
    "wof:name":"Sun Chemical AG",
    "wof:placetype":"venue"
},
  "geometry": {"coordinates":[16.3110179901,48.1368255615],"type":"Point"}
}