{
  "type": "Feature",
  "properties": {
    "addr:full":"Hugo Wolf-G 13 Leibnitz Steiermark 8430",
    "addr:housenumber":"13",
    "addr:postcode":"8430",
    "addr:street":"Steiermark",
    "iso:country":"AT",
    "sg:address":"Hugo Wolf-G 13",
    "sg:city":"Leibnitz",
    "sg:orig_category":"Werbegrafik- U Grafik-Design",
    "sg:phone":"+43 3452 85065",
    "sg:postcode":"8430",
    "sg:province":"Steiermark",
    "wof:name":"DW-Grafix Inh Dorothea H Wurzinger",
    "wof:placetype":"venue"
},
  "geometry": {"coordinates":[15.5477437973,46.7864379883],"type":"Point"}
}