{
  "type": "Feature",
  "properties": {
    "addr:full":"Bl\u00fcmelgasse 1 Wien Wien 1060",
    "addr:housenumber":"1",
    "addr:postcode":"1060",
    "addr:street":"Bluemelgasse",
    "iso:country":"AT",
    "sg:address":"Bl\u00fcmelgasse 1",
    "sg:city":"Wien",
    "sg:classifiers":[
        {
            "category":"Professional",
            "subcategory":"Advertising",
            "type":"Services"
        }
    ],
    "sg:phone":"+43 1 5856009",
    "sg:postcode":"1060",
    "sg:province":"Wien",
    "sg:tags":[
        "articles"
    ],
    "wof:name":"Unique Promotion Neider Werbemittel Direktimport GmbH",
    "wof:placetype":"venue"
},
  "geometry": {"coordinates":[16.3504657745,48.1947135925],"type":"Point"}
}