{
  "type": "Feature",
  "properties": {
    "iso:country":"AT",
    "sg:address":"Franz-Martin-Str 6a/11",
    "sg:city":"Salzburg",
    "sg:orig_category":"Mess-, Steuer- U Regeltechnik",
    "sg:phone":"+43 4366 2439484",
    "sg:postcode":"5020",
    "sg:province":"Salzburg",
    "wof:name":"hl-trading gmbh",
    "wof:placetype":"venue"
},
  "geometry": {"coordinates":[13.0343513489,47.8162498474],"type":"Point"}
}