{
  "type": "Feature",
  "properties": {
    "addr:full":"Hauptpl 21 Ernstbrunn Nieder\u00f6sterreich 2115",
    "addr:housenumber":"21",
    "addr:postcode":"2115",
    "addr:street":"Hauptpl",
    "iso:country":"AT",
    "sg:address":"Hauptpl 21",
    "sg:city":"Ernstbrunn",
    "sg:orig_category":"Drogerien",
    "sg:phone":"+43 2576 2700",
    "sg:postcode":"2115",
    "sg:province":"Nieder\u00f6sterreich",
    "wof:name":"Manzer Judith",
    "wof:placetype":"venue"
},
  "geometry": {"coordinates":[16.3631782532,48.5276565552],"type":"Point"}
}