{
  "type": "Feature",
  "properties": {
    "addr:full":"Schwarzenauer Str 6 Zwettl Nieder\u00f6sterreich 3910",
    "addr:postcode":"3910",
    "addr:street":"Niederoesterreich",
    "iso:country":"AT",
    "sg:address":"Schwarzenauer Str 6",
    "sg:city":"Zwettl",
    "sg:orig_category":"Steuerberatung",
    "sg:phone":"+43 2822 545060",
    "sg:postcode":"3910",
    "sg:province":"Nieder\u00f6sterreich",
    "wof:name":"Gr\u00fcbl Gerald Mag",
    "wof:placetype":"venue"
},
  "geometry": {"coordinates":[15.1689434052,48.6138076782],"type":"Point"}
}