{
  "type": "Feature",
  "properties": {
    "iso:country":"AT",
    "sg:address":"Frein 9a",
    "sg:city":"Frankenburg am Hausruck",
    "sg:classifiers":[
        {
            "category":"Manufacturing",
            "subcategory":"Rubber & Plastics",
            "type":"Manufacturing & Wholesale Goods"
        }
    ],
    "sg:phone":"+43 768384110",
    "sg:postcode":"4873",
    "sg:province":"Ober\u00f6sterreich",
    "sg:tags":[
        "injection",
        "part",
        "moulded"
    ],
    "wof:name":"metaplast Metall- und Plastikwaren Ges.m.b.H.",
    "wof:placetype":"venue"
},
  "geometry": {"coordinates":[13.4651069641,48.0878677368],"type":"Point"}
}