{
  "type": "Feature",
  "properties": {
    "iso:country":"AT",
    "sg:address":"Anton Schneider-Str 14",
    "sg:city":"Bregenz",
    "sg:orig_category":"Gerichte",
    "sg:phone":"+43 5574 49310",
    "sg:postcode":"6900",
    "sg:province":"Vorarlberg",
    "wof:name":"Bezirksgericht Bregenz",
    "wof:placetype":"venue"
},
  "geometry": {"coordinates":[9.7480602264,47.5036506653],"type":"Point"}
}