{
  "type": "Feature",
  "properties": {
    "addr:full":"Griesmayrstr 18 Linz Ober\u00f6sterreich 4040",
    "addr:housenumber":"18",
    "addr:postcode":"4040",
    "addr:street":"Griesmayrstr",
    "iso:country":"AT",
    "sg:address":"Griesmayrstr 18",
    "sg:city":"Linz",
    "sg:orig_category":"Bars-Cafes",
    "sg:phone":"+43 732 248659",
    "sg:postcode":"4040",
    "sg:province":"Ober\u00f6sterreich",
    "wof:name":"Magdalenal-Bar",
    "wof:placetype":"venue"
},
  "geometry": {"coordinates":[14.3001260757,48.3335189819],"type":"Point"}
}