{
  "type": "Feature",
  "properties": {
    "addr:full":"Obere Au 16 Bad Wimsbach-Neydharting Ober\u00f6sterreich 4654",
    "addr:housenumber":"16",
    "addr:postcode":"4654",
    "addr:street":"Obere Au",
    "iso:country":"AT",
    "sg:address":"Obere Au 16",
    "sg:city":"Bad Wimsbach-Neydharting",
    "sg:orig_category":"Architekten",
    "sg:phone":"+43 7245 25105",
    "sg:postcode":"4654",
    "sg:province":"Ober\u00f6sterreich",
    "wof:name":"Pointner-Waldl Veronika Arch Dipl-Ing - M 3 Architekturb\u00fcro",
    "wof:placetype":"venue"
},
  "geometry": {"coordinates":[13.9086322784,48.0282592773],"type":"Point"}
}