{
  "type": "Feature",
  "properties": {
    "addr:full":"Hauptstr 50 Leobersdorf Nieder\u00f6sterreich 2544",
    "addr:housenumber":"50",
    "addr:postcode":"2544",
    "addr:street":"Hauptstr",
    "iso:country":"AT",
    "sg:address":"Hauptstr 50",
    "sg:city":"Leobersdorf",
    "sg:orig_category":"Bauunternehmen",
    "sg:phone":"+43 2256 622070",
    "sg:postcode":"2544",
    "sg:province":"Nieder\u00f6sterreich",
    "wof:name":"J\u00e4gersberger GesmbH",
    "wof:placetype":"venue"
},
  "geometry": {"coordinates":[16.2148303986,47.9245834351],"type":"Point"}
}