{
  "type": "Feature",
  "properties": {
    "iso:country":"AT",
    "sg:address":"Nr 1",
    "sg:city":"Knittelfeld",
    "sg:orig_category":"Non-Classified Establishments",
    "sg:phone":"+43 3512 82061",
    "sg:postcode":"8720",
    "sg:province":"Steiermark",
    "wof:name":"Pfarramt",
    "wof:placetype":"venue"
},
  "geometry": {"coordinates":[14.7973117828,47.2074241638],"type":"Point"}
}