{
  "type": "Feature",
  "properties": {
    "addr:full":"Kaiserbergstr 18 Kufstein Tirol 6330",
    "addr:housenumber":"18",
    "addr:postcode":"6330",
    "addr:street":"Kaiserbergstr;Tirol",
    "iso:country":"AT",
    "sg:address":"Kaiserbergstr 18",
    "sg:city":"Kufstein",
    "sg:orig_category":"Drogerien",
    "sg:phone":"+43 5372 63865",
    "sg:postcode":"6330",
    "sg:province":"Tirol",
    "wof:name":"dm drogerie markt GmbH",
    "wof:placetype":"venue"
},
  "geometry": {"coordinates":[12.1723737717,47.5857543945],"type":"Point"}
}