{
  "type": "Feature",
  "properties": {
    "addr:full":"Bahnhofstr 38 Klagenfurt K\u00e4rnten 9020",
    "addr:housenumber":"38",
    "addr:postcode":"9020",
    "addr:street":"Bahnhofstr;Kaernten",
    "iso:country":"AT",
    "sg:address":"Bahnhofstr 38",
    "sg:city":"Klagenfurt",
    "sg:orig_category":"Stempel",
    "sg:phone":"+43 463 516245",
    "sg:postcode":"9020",
    "sg:province":"K\u00e4rnten",
    "wof:name":"Stempel-Kenda",
    "wof:placetype":"venue"
},
  "geometry": {"coordinates":[14.3117322922,46.6191558838],"type":"Point"}
}