{
  "type": "Feature",
  "properties": {
    "addr:full":"Hauptpl 14 Oberwart Burgenland 7400",
    "addr:housenumber":"14",
    "addr:postcode":"7400",
    "addr:street":"Hauptpl",
    "iso:country":"AT",
    "sg:address":"Hauptpl 14",
    "sg:city":"Oberwart",
    "sg:orig_category":"Immobilienmakler",
    "sg:phone":"+43 3352 38672",
    "sg:postcode":"7400",
    "sg:province":"Burgenland",
    "wof:name":"Gossy Hans-Michael",
    "wof:placetype":"venue"
},
  "geometry": {"coordinates":[16.2132301331,47.2874107361],"type":"Point"}
}