{
  "type": "Feature",
  "properties": {
    "addr:full":"Linzer Str 9 Freistadt Ober\u00f6sterreich 4240",
    "addr:housenumber":"9",
    "addr:postcode":"4240",
    "addr:street":"Linzer Str",
    "iso:country":"AT",
    "sg:address":"Linzer Str 9",
    "sg:city":"Freistadt",
    "sg:orig_category":"Polizei U Gendarmerie",
    "sg:phone":"+43 4359 1334300",
    "sg:postcode":"4240",
    "sg:province":"Ober\u00f6sterreich",
    "wof:name":"Gendarmerie",
    "wof:placetype":"venue"
},
  "geometry": {"coordinates":[14.5023050308,48.5079116821],"type":"Point"}
}