{
  "type": "Feature",
  "properties": {
    "addr:full":"Anton Regner-Str 17a Knittelfeld Steiermark 8720",
    "addr:housenumber":"17a",
    "addr:postcode":"8720",
    "iso:country":"AT",
    "sg:address":"Anton Regner-Str 17a",
    "sg:city":"Knittelfeld",
    "sg:orig_category":"Lebens- U Sozialberatung",
    "sg:phone":"+43 3512 8221613",
    "sg:postcode":"8720",
    "sg:province":"Steiermark",
    "wof:name":"Schulpsychologische Beratungsstelle",
    "wof:placetype":"venue"
},
  "geometry": {"coordinates":[14.8223810196,47.2165870667],"type":"Point"}
}