{
  "type": "Feature",
  "properties": {
    "addr:full":"Wollzeile 29 Wien Wien 1010",
    "addr:housenumber":"29",
    "addr:postcode":"1010",
    "addr:street":"Wollzeile",
    "iso:country":"AT",
    "sg:address":"Wollzeile 29",
    "sg:city":"Wien",
    "sg:orig_category":"Geschenkartikel",
    "sg:phone":"+43 1 5131311",
    "sg:postcode":"1010",
    "sg:province":"Wien",
    "wof:name":"AHA Wohnen & Schenken",
    "wof:placetype":"venue"
},
  "geometry": {"coordinates":[16.377702713,48.2080535889],"type":"Point"}
}