{
  "type": "Feature",
  "properties": {
    "iso:country":"AT",
    "sg:address":"Egererstr 10",
    "sg:city":"Tullnerbach",
    "sg:orig_category":"Datenverarbeitung",
    "sg:phone":"+43 2233 55751",
    "sg:postcode":"3013",
    "sg:province":"Nieder\u00f6sterreich",
    "wof:name":"ISM Integrierte System Modelle DatenverarbeitungsgesmbH",
    "wof:placetype":"venue"
},
  "geometry": {"coordinates":[16.0981845856,48.1843643188],"type":"Point"}
}