{
  "type": "Feature",
  "properties": {
    "addr:full":"Grinzinger Str 149/6 Wien Wien 1190",
    "addr:housenumber":"149 / 6",
    "addr:postcode":"1190",
    "iso:country":"AT",
    "sg:address":"Grinzinger Str 149/6",
    "sg:city":"Wien",
    "sg:orig_category":"Psychotherapie",
    "sg:phone":"+43 1 3180202",
    "sg:postcode":"1190",
    "sg:province":"Wien",
    "wof:name":"Pasrucker-Wittmann Christine",
    "wof:placetype":"venue"
},
  "geometry": {"coordinates":[16.3679046631,48.2546691895],"type":"Point"}
}