{
  "type": "Feature",
  "properties": {
    "addr:full":"Stubenbergg 9 Graz Steiermark 8010",
    "addr:housenumber":"9",
    "addr:postcode":"8010",
    "addr:street":"Stubenbergg",
    "iso:country":"AT",
    "sg:address":"Stubenbergg 9",
    "sg:city":"Graz",
    "sg:orig_category":"Bausparkassen",
    "sg:phone":"+43 4357 070394",
    "sg:postcode":"8010",
    "sg:province":"Steiermark",
    "wof:name":"Bausparkasse W\u00fcstenrot AG",
    "wof:placetype":"venue"
},
  "geometry": {"coordinates":[15.4399299622,47.0682563782],"type":"Point"}
}