{
  "type": "Feature",
  "properties": {
    "iso:country":"AT",
    "sg:address":"Griesg 5-7",
    "sg:city":"Telfs",
    "sg:orig_category":"Waren Aller Art",
    "sg:phone":"+43 4366 41112353",
    "sg:postcode":"6410",
    "sg:province":"Tirol",
    "wof:name":"aus & raus Warenhandels GmbH",
    "wof:placetype":"venue"
},
  "geometry": {"coordinates":[11.072218895,47.3066978455],"type":"Point"}
}