{
  "type": "Feature",
  "properties": {
    "addr:full":"Breitenfurter Str 360 Wien Wien 1230",
    "addr:housenumber":"360",
    "addr:postcode":"1230",
    "addr:street":"Str",
    "iso:country":"AT",
    "sg:address":"Breitenfurter Str 360",
    "sg:city":"Wien",
    "sg:orig_category":"Papier- U Schreibwaren / Einzelhandel",
    "sg:phone":"+43 1 8691259",
    "sg:postcode":"1230",
    "sg:province":"Wien",
    "wof:name":"Reindl Jutta",
    "wof:placetype":"venue"
},
  "geometry": {"coordinates":[16.2821559906,48.1357498169],"type":"Point"}
}