{
  "type": "Feature",
  "properties": {
    "addr:full":"Kirchenstr 9 Landeck Tirol 6500",
    "addr:housenumber":"9",
    "addr:postcode":"6500",
    "addr:street":"Kirchenstr;Tirol",
    "iso:country":"AT",
    "sg:address":"Kirchenstr 9",
    "sg:city":"Landeck",
    "sg:orig_category":"Videotheken",
    "sg:phone":"+43 5442 64981",
    "sg:postcode":"6500",
    "sg:province":"Tirol",
    "wof:name":"Video Life",
    "wof:placetype":"venue"
},
  "geometry": {"coordinates":[10.6277132034,47.1200027466],"type":"Point"}
}