{
  "type": "Feature",
  "properties": {
    "addr:full":"S\u00fcdtangente 7 Wolfsberg K\u00e4rnten 9400",
    "addr:housenumber":"7;kaernten",
    "addr:postcode":"9400",
    "addr:street":"Suedtangente",
    "iso:country":"AT",
    "sg:address":"S\u00fcdtangente 7",
    "sg:city":"Wolfsberg",
    "sg:orig_category":"Transportunternehmen",
    "sg:phone":"+43 4352 36518",
    "sg:postcode":"9400",
    "sg:province":"K\u00e4rnten",
    "wof:name":"Koitz Transporte GmbH",
    "wof:placetype":"venue"
},
  "geometry": {"coordinates":[14.8418502808,46.8402099609],"type":"Point"}
}