{
  "type": "Feature",
  "properties": {
    "addr:full":"Wolfsgrube 21 Innsbruck Tirol 6020",
    "addr:housenumber":"21",
    "addr:postcode":"6020",
    "addr:street":"Wolfsgrube;Tirol",
    "iso:country":"AT",
    "sg:address":"Wolfsgrube 21",
    "sg:city":"Innsbruck",
    "sg:orig_category":"Dolmetscher",
    "sg:phone":"+43 512 205366",
    "sg:postcode":"6020",
    "sg:province":"Tirol",
    "wof:name":"Schneider Ingrid Mag",
    "wof:placetype":"venue"
},
  "geometry": {"coordinates":[11.4204978943,47.2829704285],"type":"Point"}
}