{
  "type": "Feature",
  "properties": {
    "iso:country":"AT",
    "sg:address":"Nr 33",
    "sg:city":"Ried in der Riedmark",
    "sg:orig_category":"Tischlereien",
    "sg:phone":"+43 7238 2791",
    "sg:postcode":"4312",
    "sg:province":"Ober\u00f6sterreich",
    "wof:name":"Edelbauer Josef",
    "wof:placetype":"venue"
},
  "geometry": {"coordinates":[14.5276536942,48.2708244324],"type":"Point"}
}