{
  "type": "Feature",
  "properties": {
    "addr:full":"Hietzinger Hauptstr 28 Wien Wien 1130",
    "addr:housenumber":"28",
    "addr:postcode":"1130",
    "addr:street":"Hietzinger Hauptstr",
    "iso:country":"AT",
    "sg:address":"Hietzinger Hauptstr 28",
    "sg:city":"Wien",
    "sg:orig_category":"Boutiquen",
    "sg:phone":"+43 1 8765634",
    "sg:postcode":"1130",
    "sg:province":"Wien",
    "wof:name":"Pat's Boutique Inh Patricia Fischerlehner KG",
    "wof:placetype":"venue"
},
  "geometry": {"coordinates":[16.2992153168,48.1866531372],"type":"Point"}
}