{
  "type": "Feature",
  "properties": {
    "addr:full":"Simmeringer Hauptstr 189-191 Wien Wien 1110",
    "addr:postcode":"189-191;1110",
    "addr:street":"Simmeringer Hauptstr",
    "iso:country":"AT",
    "sg:address":"Simmeringer Hauptstr 189-191",
    "sg:city":"Wien",
    "sg:orig_category":"Tapeten",
    "sg:phone":"+43 1 7698200",
    "sg:postcode":"1110",
    "sg:province":"Wien",
    "wof:name":"Simmeringer Tapetenpalette Inh G\u00fcnther Lunghammer",
    "wof:placetype":"venue"
},
  "geometry": {"coordinates":[16.4232349396,48.1678657532],"type":"Point"}
}