{
  "type": "Feature",
  "properties": {
    "addr:full":"Moos 17 Seewalchen am Attersee Ober\u00f6sterreich 4863",
    "addr:housenumber":"17",
    "addr:postcode":"4863",
    "addr:street":"Moos",
    "iso:country":"AT",
    "sg:address":"Moos 17",
    "sg:city":"Seewalchen am Attersee",
    "sg:orig_category":"Fischerei",
    "sg:phone":"+43 4376 622487",
    "sg:postcode":"4863",
    "sg:province":"Ober\u00f6sterreich",
    "wof:name":"Fischerei Ecker",
    "wof:placetype":"venue"
},
  "geometry": {"coordinates":[13.5704393387,47.9477996826],"type":"Point"}
}