{
  "type": "Feature",
  "properties": {
    "addr:full":"Rudolfstr 71 Linz Ober\u00f6sterreich 4040",
    "addr:housenumber":"71",
    "addr:postcode":"4040",
    "addr:street":"Rudolfstr",
    "iso:country":"AT",
    "sg:address":"Rudolfstr 71",
    "sg:city":"Linz",
    "sg:orig_category":"Glasereien",
    "sg:phone":"+43 4373 27310080",
    "sg:postcode":"4040",
    "sg:province":"Ober\u00f6sterreich",
    "wof:name":"Wenna Glas",
    "wof:placetype":"venue"
},
  "geometry": {"coordinates":[14.2753343582,48.3075408936],"type":"Point"}
}