{
  "type": "Feature",
  "properties": {
    "addr:full":"Schulstr 11 Sattledt Ober\u00f6sterreich 4642",
    "addr:housenumber":"11",
    "addr:postcode":"4642",
    "addr:street":"Schulstr",
    "iso:country":"AT",
    "sg:address":"Schulstr 11",
    "sg:city":"Sattledt",
    "sg:orig_category":"Volksschulen",
    "sg:phone":"+43 4372 448894",
    "sg:postcode":"4642",
    "sg:province":"Ober\u00f6sterreich",
    "wof:name":"Volksschule",
    "wof:placetype":"venue"
},
  "geometry": {"coordinates":[14.056019783,48.0721702576],"type":"Point"}
}