{
  "type": "Feature",
  "properties": {
    "iso:country":"AT",
    "sg:address":"Linseng 46",
    "sg:city":"Klagenfurt",
    "sg:orig_category":"Institute",
    "sg:phone":"+43 4346 3540500",
    "sg:postcode":"9020",
    "sg:province":"K\u00e4rnten",
    "sg:website":"kinderwunsch-co.at",
    "wof:name":"Stadler Alexander Dr",
    "wof:placetype":"venue"
},
  "geometry": {"coordinates":[14.2948827744,46.6240272522],"type":"Point"}
}