{
  "type": "Feature",
  "properties": {
    "addr:full":"Amselg 13 Freistadt Ober\u00f6sterreich 4240",
    "addr:housenumber":"13",
    "addr:postcode":"4240",
    "addr:street":"Amselg",
    "iso:country":"AT",
    "sg:address":"Amselg 13",
    "sg:city":"Freistadt",
    "sg:orig_category":"Institute",
    "sg:phone":"+43 7942 7623513",
    "sg:postcode":"4240",
    "sg:province":"Ober\u00f6sterreich",
    "wof:name":"Aigner Praxis f holistische Hilfestellung K\u00f6rper Geist Seele",
    "wof:placetype":"venue"
},
  "geometry": {"coordinates":[14.5049953461,48.5119857788],"type":"Point"}
}