{
  "type": "Feature",
  "properties": {
    "iso:country":"AT",
    "sg:address":"Favoritner Gewerbering 46",
    "sg:city":"Wien",
    "sg:orig_category":"Autobusunternehmen",
    "sg:phone":"+43 4316 023775",
    "sg:postcode":"1100",
    "sg:province":"Wien",
    "wof:name":"Dober GesmbH",
    "wof:placetype":"venue"
},
  "geometry": {"coordinates":[16.3798599243,48.1643791199],"type":"Point"}
}