{
  "type": "Feature",
  "properties": {
    "addr:full":"Dr.-Prem-Str 23 Kufstein Tirol 6330",
    "addr:housenumber":"23",
    "addr:postcode":"6330",
    "addr:street":"Dr.-Prem-Str;Tirol",
    "iso:country":"AT",
    "sg:address":"Dr.-Prem-Str 23",
    "sg:city":"Kufstein",
    "sg:orig_category":"Holzhandel",
    "sg:phone":"+43 676 3265178",
    "sg:postcode":"6330",
    "sg:province":"Tirol",
    "wof:name":"Aigner Karl - Holzagentur",
    "wof:placetype":"venue"
},
  "geometry": {"coordinates":[12.16061306,47.5877456665],"type":"Point"}
}