{
  "type": "Feature",
  "properties": {
    "addr:full":"Nr 51 Kaindorf Steiermark 8224",
    "addr:postcode":"8224",
    "addr:street":"Nr",
    "iso:country":"AT",
    "sg:address":"Nr 51",
    "sg:city":"Kaindorf",
    "sg:classifiers":[
        {
            "category":"Travel",
            "subcategory":"Hotels & Motels",
            "type":"Entertainment"
        }
    ],
    "sg:phone":"+43 4333 342262",
    "sg:postcode":"8224",
    "sg:province":"Steiermark",
    "wof:name":"Ballonhotel",
    "wof:placetype":"venue"
},
  "geometry": {"coordinates":[15.9089851379,47.2246704102],"type":"Point"}
}