{
  "type": "Feature",
  "properties": {
    "iso:country":"AT",
    "sg:address":"Dornacher Str 11",
    "sg:city":"Linz",
    "sg:orig_category":"Massagen",
    "sg:phone":"+43 732 250258",
    "sg:postcode":"4040",
    "sg:province":"Ober\u00f6sterreich",
    "wof:name":"Wellness-Institut Christine",
    "wof:placetype":"venue"
},
  "geometry": {"coordinates":[14.2578554153,48.3602561951],"type":"Point"}
}