{
  "type": "Feature",
  "properties": {
    "addr:full":"Packer Str 173 Lieboch Steiermark 8501",
    "addr:housenumber":"173",
    "addr:postcode":"8501",
    "iso:country":"AT",
    "sg:address":"Packer Str 173",
    "sg:city":"Lieboch",
    "sg:orig_category":"Spenglereien",
    "sg:phone":"+43 3136 611440",
    "sg:postcode":"8501",
    "sg:province":"Steiermark",
    "wof:name":"Gaier GesmbH",
    "wof:placetype":"venue"
},
  "geometry": {"coordinates":[15.3269023895,46.9767913818],"type":"Point"}
}