{
  "type": "Feature",
  "properties": {
    "iso:country":"AT",
    "sg:address":"Spanheimerstr 5",
    "sg:city":"Wolfsberg",
    "sg:classifiers":[
        {
            "category":"Professional",
            "type":"Services"
        }
    ],
    "sg:phone":"+43 4352 527620",
    "sg:postcode":"9400",
    "sg:province":"K\u00e4rnten",
    "sg:tags":[
        "leasing"
    ],
    "wof:name":"Gradischnig GmbH - Versicherungsmakler Leasing Agentur",
    "wof:placetype":"venue"
},
  "geometry": {"coordinates":[14.8403682709,46.8401412964],"type":"Point"}
}