{
  "type": "Feature",
  "properties": {
    "addr:full":"Hauptstr 37 Prambachkirchen Ober\u00f6sterreich 4731",
    "addr:housenumber":"37",
    "addr:postcode":"4731",
    "addr:street":"Hauptstr",
    "iso:country":"AT",
    "sg:address":"Hauptstr 37",
    "sg:city":"Prambachkirchen",
    "sg:orig_category":"Lebensmittel / Einzelhandel",
    "sg:phone":"+43 7277 2309",
    "sg:postcode":"4731",
    "sg:province":"Ober\u00f6sterreich",
    "wof:name":"Spar-Markt Inh Rudolf Lesslhumer",
    "wof:placetype":"venue"
},
  "geometry": {"coordinates":[13.9047842026,48.3138237],"type":"Point"}
}