{
  "type": "Feature",
  "properties": {
    "addr:full":"Neusetzg 7 Wien Wien 1100",
    "addr:housenumber":"7",
    "addr:postcode":"1100",
    "addr:street":"Neusetzg",
    "iso:country":"AT",
    "sg:address":"Neusetzg 7",
    "sg:city":"Wien",
    "sg:orig_category":"Handarbeiten",
    "sg:phone":"+43 1 6043993",
    "sg:postcode":"1100",
    "sg:province":"Wien",
    "wof:name":"Wollstube Eva",
    "wof:placetype":"venue"
},
  "geometry": {"coordinates":[16.37799263,48.1724357605],"type":"Point"}
}