{
  "type": "Feature",
  "properties": {
    "addr:full":"Wilhelm-Exner-G 4 Wien Wien 1090",
    "addr:housenumber":"4",
    "addr:postcode":"1090",
    "addr:street":"Wilhelm-Exner-G",
    "iso:country":"AT",
    "sg:address":"Wilhelm-Exner-G 4",
    "sg:city":"Wien",
    "sg:orig_category":"Studentenheime",
    "sg:phone":"+43 1 40391220",
    "sg:postcode":"1090",
    "sg:province":"Wien",
    "wof:name":"Haus Burgenland 1 der \u00f6JAB",
    "wof:placetype":"venue"
},
  "geometry": {"coordinates":[16.3510189056,48.2211532593],"type":"Point"}
}