{
  "type": "Feature",
  "properties": {
    "addr:full":"Leopold-Werndl-Str 18 Steyr Ober\u00f6sterreich 4400",
    "addr:housenumber":"18",
    "addr:postcode":"4400",
    "addr:street":"Leopold-Werndl-Str;Oberoesterreich",
    "iso:country":"AT",
    "sg:address":"Leopold-Werndl-Str 18",
    "sg:city":"Steyr",
    "sg:orig_category":"Steuerberatung",
    "sg:phone":"+43 4372 52522800",
    "sg:postcode":"4400",
    "sg:province":"Ober\u00f6sterreich",
    "wof:name":"GPU Buchpr\u00fcfungs Beratungs u Treuhandgesellschaft mbH",
    "wof:placetype":"venue"
},
  "geometry": {"coordinates":[14.4118785858,48.0340766907],"type":"Point"}
}