{
  "type": "Feature",
  "properties": {
    "addr:full":"Parkstr 4 Bad Tatzmannsdorf Burgenland 7431",
    "addr:housenumber":"4",
    "addr:postcode":"7431",
    "addr:street":"Parkstr",
    "iso:country":"AT",
    "sg:address":"Parkstr 4",
    "sg:city":"Bad Tatzmannsdorf",
    "sg:orig_category":"Banken U Sparkassen",
    "sg:phone":"+43 4333 5370100",
    "sg:postcode":"7431",
    "sg:province":"Burgenland",
    "wof:name":"Bankomat d Volksbank S\u00fcdburgenland regGenmbH",
    "wof:placetype":"venue"
},
  "geometry": {"coordinates":[16.2303543091,47.3341522217],"type":"Point"}
}