{
  "type": "Feature",
  "properties": {
    "iso:country":"AT",
    "sg:address":"Untere Halde 9",
    "sg:city":"Klaus-Weiler",
    "sg:orig_category":"Reproanstalten",
    "sg:phone":"+43 5523 51295",
    "sg:postcode":"6833",
    "sg:province":"Vorarlberg",
    "wof:name":"K\u00f6NIG KEG",
    "wof:placetype":"venue"
},
  "geometry": {"coordinates":[9.659529686,47.3067016602],"type":"Point"}
}