{
  "type": "Feature",
  "properties": {
    "addr:full":"Gentzgasse 68 Wien Wien 1180",
    "addr:housenumber":"68",
    "addr:postcode":"1180",
    "addr:street":"Gentzgasse",
    "iso:country":"AT",
    "sg:address":"Gentzgasse 68",
    "sg:city":"Wien",
    "sg:classifiers":[
        {
            "category":"Manufacturing",
            "subcategory":"Textiles",
            "type":"Manufacturing & Wholesale Goods"
        }
    ],
    "sg:phone":"+43 1 4705857",
    "sg:postcode":"1180",
    "sg:province":"Wien",
    "sg:tags":[
        "curtain",
        "fabric"
    ],
    "wof:name":"Josef Brandner",
    "wof:placetype":"venue"
},
  "geometry": {"coordinates":[16.3398342133,48.2278022766],"type":"Point"}
}