{
  "type": "Feature",
  "properties": {
    "addr:full":"Erzherzog-Eugen-Str 10 Salzburg Salzburg 5020",
    "addr:housenumber":"10",
    "addr:postcode":"5020",
    "addr:street":"Erzherzog-Eugen-Str;Salzburg",
    "iso:country":"AT",
    "sg:address":"Erzherzog-Eugen-Str 10",
    "sg:city":"Salzburg",
    "sg:orig_category":"Gastronomie- U Hotelbedarf",
    "sg:phone":"+43 4366 43004008",
    "sg:postcode":"5020",
    "sg:province":"Salzburg",
    "wof:name":"K\u00fcchenkozept Kaiser",
    "wof:placetype":"venue"
},
  "geometry": {"coordinates":[13.0376529694,47.818321228],"type":"Point"}
}