{
  "type": "Feature",
  "properties": {
    "iso:country":"AT",
    "sg:address":"Klagenfurter Str 5",
    "sg:city":"Wolfsberg",
    "sg:classifiers":[
        {
            "category":"Restaurant",
            "type":"Food & Drink"
        }
    ],
    "sg:phone":"+43 4352 3123",
    "sg:postcode":"9400",
    "sg:province":"K\u00e4rnten",
    "wof:name":"Pizzeria-Restaurante Moitzi Klaus",
    "wof:placetype":"venue"
},
  "geometry": {"coordinates":[14.8420228958,46.8318328857],"type":"Point"}
}