{
  "type": "Feature",
  "properties": {
    "iso:country":"AT",
    "sg:address":"Babenbergerstr 29",
    "sg:city":"Lilienfeld",
    "sg:orig_category":"\u00c3\u201erzte / F Allgemeinmedizin",
    "sg:phone":"+43 2762 52336",
    "sg:postcode":"3180",
    "sg:province":"Nieder\u00f6sterreich",
    "wof:name":"Bieber Ulrike Dr",
    "wof:placetype":"venue"
},
  "geometry": {"coordinates":[15.5964298248,48.0162391663],"type":"Point"}
}