{
  "type": "Feature",
  "properties": {
    "addr:full":"Birkenweg 7 Imst Tirol 6460",
    "addr:housenumber":"7",
    "addr:postcode":"6460",
    "addr:street":"Birkenweg;Tirol",
    "iso:country":"AT",
    "sg:address":"Birkenweg 7",
    "sg:city":"Imst",
    "sg:orig_category":"Rauchfangkehrer",
    "sg:phone":"+43 5412 66780",
    "sg:postcode":"6460",
    "sg:province":"Tirol",
    "wof:name":"Friess Stefan",
    "wof:placetype":"venue"
},
  "geometry": {"coordinates":[10.7345609665,47.2337379456],"type":"Point"}
}