{
  "type": "Feature",
  "properties": {
    "iso:country":"AT",
    "sg:address":"Schottenring 7-9",
    "sg:city":"Wien",
    "sg:orig_category":"Polizei U Gendarmerie",
    "sg:phone":"+43 1 313100",
    "sg:postcode":"1010",
    "sg:province":"Wien",
    "wof:name":"Bundespolizeidirektion Wien",
    "wof:placetype":"venue"
},
  "geometry": {"coordinates":[16.363861084,48.2148208618],"type":"Point"}
}