{
  "type": "Feature",
  "properties": {
    "addr:full":"Gumpendorfer Str 96/1 Wien Wien 1060",
    "addr:housenumber":"96 / 1",
    "addr:postcode":"1060",
    "addr:street":"Str",
    "iso:country":"AT",
    "sg:address":"Gumpendorfer Str 96/1",
    "sg:city":"Wien",
    "sg:orig_category":"Webdesign",
    "sg:phone":"+43 1 5953718",
    "sg:postcode":"1060",
    "sg:province":"Wien",
    "wof:name":"Jelinek Wolfgang",
    "wof:placetype":"venue"
},
  "geometry": {"coordinates":[16.347650528,48.1913795471],"type":"Point"}
}