{
  "type": "Feature",
  "properties": {
    "addr:full":"Bernoullistr 7 Wien Wien 1220",
    "addr:housenumber":"7",
    "addr:postcode":"1220",
    "addr:street":"Bernoullistr",
    "iso:country":"AT",
    "sg:address":"Bernoullistr 7",
    "sg:city":"Wien",
    "sg:classifiers":[
        {
            "category":"Professional",
            "subcategory":"Testing Lab",
            "type":"Services"
        }
    ],
    "sg:phone":"+43 4312 112322870",
    "sg:postcode":"1220",
    "sg:province":"Wien",
    "sg:tags":[
        "magistrate"
    ],
    "wof:name":"Magistrat d Stadt Wien MA 11A - Betreuung v Kindern - Servicestelle f.d. 22.Bezirk",
    "wof:placetype":"venue"
},
  "geometry": {"coordinates":[16.4419994354,48.2404785156],"type":"Point"}
}