{
  "type": "Feature",
  "properties": {
    "addr:full":"Milser Str 22 Hall in Tirol Tirol 6060",
    "addr:housenumber":"22",
    "addr:postcode":"6060",
    "addr:street":"Milser Str;Tirol",
    "iso:country":"AT",
    "sg:address":"Milser Str 22",
    "sg:city":"Hall in Tirol",
    "sg:orig_category":"Tankstellen",
    "sg:phone":"+43 4352 2356403",
    "sg:postcode":"6060",
    "sg:province":"Tirol",
    "wof:name":"OMV AG",
    "wof:placetype":"venue"
},
  "geometry": {"coordinates":[11.5165576935,47.2831306458],"type":"Point"}
}