{
  "type": "Feature",
  "properties": {
    "addr:full":"Harter Strasse 157 Stra\u00dfgang Steiermark 8054",
    "addr:housenumber":"157",
    "addr:postcode":"8054",
    "addr:street":"Harter Strasse",
    "iso:country":"AT",
    "sg:address":"Harter Strasse 157",
    "sg:city":"Stra\u00dfgang",
    "sg:classifiers":[
        {
            "category":"Wholesale",
            "subcategory":"Books, Periodicals, & Newspapers",
            "type":"Manufacturing & Wholesale Goods"
        }
    ],
    "sg:phone":"+43 316 253302",
    "sg:postcode":"8054",
    "sg:province":"Steiermark",
    "sg:tags":[
        "directory",
        "publisher"
    ],
    "wof:name":"Austria-Presse-Dienst",
    "wof:placetype":"venue"
},
  "geometry": {"coordinates":[15.400885582,47.0396766663],"type":"Point"}
}