{
  "type": "Feature",
  "properties": {
    "addr:full":"Pfefferweg 311 Hinterglemm Salzburg 5754",
    "addr:housenumber":"311",
    "addr:postcode":"5754",
    "addr:street":"Pfefferweg;Salzburg",
    "iso:country":"AT",
    "sg:address":"Pfefferweg 311",
    "sg:city":"Hinterglemm",
    "sg:orig_category":"Pensionen / Privatzimmer",
    "sg:phone":"+43 6541 6616",
    "sg:postcode":"5754",
    "sg:province":"Salzburg",
    "wof:name":"Pension Landhaus Pattis",
    "wof:placetype":"venue"
},
  "geometry": {"coordinates":[12.5859060287,47.3772315979],"type":"Point"}
}