{
  "type": "Feature",
  "properties": {
    "iso:country":"AT",
    "sg:address":"Nr 65",
    "sg:city":"Trattenbach",
    "sg:orig_category":"Metallwaren / Erzeugung U Gro\u00c3\u0178handel",
    "sg:phone":"+43 2641 8231",
    "sg:postcode":"2881",
    "sg:province":"Nieder\u00f6sterreich",
    "wof:name":"Braunsteiner Helmut",
    "wof:placetype":"venue"
},
  "geometry": {"coordinates":[15.8923721313,47.6028823853],"type":"Point"}
}