{
  "type": "Feature",
  "properties": {
    "addr:full":"Imbergstr 2/III Salzburg Salzburg 5020",
    "addr:housenumber":"2 / iii",
    "addr:postcode":"5020",
    "addr:street":"Imbergstr;Salzburg",
    "iso:country":"AT",
    "sg:address":"Imbergstr 2/III",
    "sg:city":"Salzburg",
    "sg:orig_category":"Sprachschulen U -Unterricht",
    "sg:phone":"+43 662 873541",
    "sg:postcode":"5020",
    "sg:province":"Salzburg",
    "sg:website":"www.dante.salzburg.at",
    "wof:name":"Italienisch \u00d6sterreichischer Kulturverein Societa Dante Alighieri",
    "wof:placetype":"venue"
},
  "geometry": {"coordinates":[13.0433769226,47.8006744385],"type":"Point"}
}