{
  "type": "Feature",
  "properties": {
    "iso:country":"AT",
    "sg:address":"Fr\u00f6hlichg 58",
    "sg:city":"Graz",
    "sg:orig_category":"Wasserbetten",
    "sg:phone":"+43 316 819626",
    "sg:postcode":"8010",
    "sg:province":"Steiermark",
    "wof:name":"Moser Gerhard",
    "wof:placetype":"venue"
},
  "geometry": {"coordinates":[15.445728302,47.0551681519],"type":"Point"}
}