{
  "type": "Feature",
  "properties": {
    "addr:full":"Welser Str 47 Neuhofen an der Krems Ober\u00f6sterreich 4501",
    "addr:postcode":"4501",
    "addr:street":"Str 47",
    "iso:country":"AT",
    "sg:address":"Welser Str 47",
    "sg:city":"Neuhofen an der Krems",
    "sg:orig_category":"Erdarbeiten",
    "sg:phone":"+43 4372 2744970",
    "sg:postcode":"4501",
    "sg:province":"Ober\u00f6sterreich",
    "wof:name":"Eisenhuber Gottfried",
    "wof:placetype":"venue"
},
  "geometry": {"coordinates":[14.2202978134,48.1439094543],"type":"Point"}
}