{
  "type": "Feature",
  "properties": {
    "iso:country":"AT",
    "sg:address":"Hauptpl 3",
    "sg:city":"Mattersburg",
    "sg:orig_category":"Steuerberatung",
    "sg:phone":"+43 2626 68000",
    "sg:postcode":"7210",
    "sg:province":"Burgenland",
    "wof:name":"SRT Hennig & M\u00fchl Steuerberatungs-OEG",
    "wof:placetype":"venue"
},
  "geometry": {"coordinates":[16.3982257843,47.7368087769],"type":"Point"}
}