{
  "type": "Feature",
  "properties": {
    "addr:full":"Franz Emerich-G 3 Wien Wien 1120",
    "addr:housenumber":"3",
    "addr:postcode":"1120",
    "iso:country":"AT",
    "sg:address":"Franz Emerich-G 3",
    "sg:city":"Wien",
    "sg:orig_category":"Modistinnen U Modisten",
    "sg:phone":"+43 1 8100107",
    "sg:postcode":"1120",
    "sg:province":"Wien",
    "wof:name":"Bergmayer Karin",
    "wof:placetype":"venue"
},
  "geometry": {"coordinates":[16.3308429718,48.1832275391],"type":"Point"}
}