{
  "type": "Feature",
  "properties": {
    "iso:country":"AT",
    "sg:address":"Kaiserfeldg 22",
    "sg:city":"Graz",
    "sg:orig_category":"Beteiligungen U Finanzierungen",
    "sg:phone":"+43 316 8519450",
    "sg:postcode":"8010",
    "sg:province":"Steiermark",
    "wof:name":"MLP Finanzdienstleistungen AG",
    "wof:placetype":"venue"
},
  "geometry": {"coordinates":[15.4383115768,47.0675811768],"type":"Point"}
}