{
  "type": "Feature",
  "properties": {
    "addr:full":"Marktpl 2 Aurolzm\u00fcnster Ober\u00f6sterreich 4971",
    "addr:housenumber":"2",
    "addr:postcode":"4971",
    "addr:street":"Marktpl;Oberoesterreich",
    "iso:country":"AT",
    "sg:address":"Marktpl 2",
    "sg:city":"Aurolzm\u00fcnster",
    "sg:orig_category":"Polizei U Gendarmerie",
    "sg:phone":"+43 4359 1334242",
    "sg:postcode":"4971",
    "sg:province":"Ober\u00f6sterreich",
    "wof:name":"Gendarmerie",
    "wof:placetype":"venue"
},
  "geometry": {"coordinates":[13.4548110962,48.2487297058],"type":"Point"}
}