{
  "type": "Feature",
  "properties": {
    "addr:full":"Nr 9 Hermagor K\u00e4rnten 9620",
    "addr:postcode":"9620",
    "addr:street":"Nr;Kaernten",
    "iso:country":"AT",
    "sg:address":"Nr 9",
    "sg:city":"Hermagor",
    "sg:classifiers":[
        {
            "category":"Travel",
            "subcategory":"Hotels & Motels",
            "type":"Entertainment"
        }
    ],
    "sg:phone":"+43 4285 82110",
    "sg:postcode":"9620",
    "sg:province":"K\u00e4rnten",
    "wof:name":"Hotel Sonnenalpe Pucher Michael KG",
    "wof:placetype":"venue"
},
  "geometry": {"coordinates":[-81.4354095459,26.5363197327],"type":"Point"}
}