{
  "type": "Feature",
  "properties": {
    "iso:country":"AT",
    "sg:address":"Breitenfurter Str 155",
    "sg:city":"Wien",
    "sg:orig_category":"Autohandel",
    "sg:phone":"+43 1 8044930",
    "sg:postcode":"1120",
    "sg:province":"Wien",
    "wof:name":"Autosalon Stich",
    "wof:placetype":"venue"
},
  "geometry": {"coordinates":[16.3120288849,48.1618804932],"type":"Point"}
}