{
  "type": "Feature",
  "properties": {
    "iso:country":"AT",
    "sg:address":"Dorfstr 55",
    "sg:city":"Brixen im Thale",
    "sg:orig_category":"Erdarbeiten",
    "sg:phone":"+43 5334 8818",
    "sg:postcode":"6364",
    "sg:province":"Tirol",
    "wof:name":"Kreidl Helmut",
    "wof:placetype":"venue"
},
  "geometry": {"coordinates":[12.2572031021,47.4492225647],"type":"Point"}
}