{
  "type": "Feature",
  "properties": {
    "addr:full":"Vorderkrimml 8 Krimml Salzburg 5743",
    "addr:housenumber":"8",
    "addr:postcode":"5743",
    "addr:street":"Vorderkrimml;Salzburg",
    "iso:country":"AT",
    "sg:address":"Vorderkrimml 8",
    "sg:city":"Krimml",
    "sg:orig_category":"Tischlereien",
    "sg:phone":"+43 664 2668194",
    "sg:postcode":"5743",
    "sg:province":"Salzburg",
    "wof:name":"Dengg Martin",
    "wof:placetype":"venue"
},
  "geometry": {"coordinates":[12.1744441986,47.221950531],"type":"Point"}
}