{
  "type": "Feature",
  "properties": {
    "addr:full":"Bahnhofstr 231 Admont Steiermark 8911",
    "addr:housenumber":"231",
    "addr:postcode":"8911",
    "addr:street":"Bahnhofstr",
    "iso:country":"AT",
    "sg:address":"Bahnhofstr 231",
    "sg:city":"Admont",
    "sg:orig_category":"Autohandel",
    "sg:phone":"+43 4336 1324910",
    "sg:postcode":"8911",
    "sg:province":"Steiermark",
    "wof:name":"Bammer GesmbH",
    "wof:placetype":"venue"
},
  "geometry": {"coordinates":[14.4628324509,47.5731048584],"type":"Point"}
}