{
  "type": "Feature",
  "properties": {
    "addr:full":"Adalbert-Stifter-Strasse 4 Braunau am Inn Ober\u00f6sterreich 5280",
    "addr:housenumber":"4",
    "addr:postcode":"5280",
    "addr:street":"Adalbert-Stifter-Strasse",
    "iso:country":"AT",
    "sg:address":"Adalbert-Stifter-Strasse 4",
    "sg:city":"Braunau am Inn",
    "sg:classifiers":[
        {
            "category":"Landmark",
            "subcategory":"Unesco World Heritage Site",
            "type":"Public Place"
        }
    ],
    "sg:phone":"+43 7722 87142",
    "sg:postcode":"5280",
    "sg:province":"Ober\u00f6sterreich",
    "sg:tags":[
        "analysis",
        "contaminated"
    ],
    "wof:name":"G\u00fcnther Eder GesmbH",
    "wof:placetype":"venue"
},
  "geometry": {"coordinates":[13.0348711014,48.2509803772],"type":"Point"}
}