{
  "type": "Feature",
  "properties": {
    "addr:full":"Albert Sch\u00f6pf-Str 56 Linz Ober\u00f6sterreich 4020",
    "addr:housenumber":"56",
    "addr:postcode":"4020",
    "iso:country":"AT",
    "sg:address":"Albert Sch\u00f6pf-Str 56",
    "sg:city":"Linz",
    "sg:orig_category":"Lebens- U Sozialberatung",
    "sg:phone":"+43 732 370928",
    "sg:postcode":"4020",
    "sg:province":"Ober\u00f6sterreich",
    "wof:name":"Trebo Christine",
    "wof:placetype":"venue"
},
  "geometry": {"coordinates":[14.2863683701,48.2639045715],"type":"Point"}
}