{
  "type": "Feature",
  "properties": {
    "addr:full":"Nr 42 Br\u00fcckl K\u00e4rnten 9371",
    "addr:postcode":"9371",
    "addr:street":"Nr 42 Brueckl Kaernten",
    "iso:country":"AT",
    "sg:address":"Nr 42",
    "sg:city":"Br\u00fcckl",
    "sg:orig_category":"Tischlereien",
    "sg:phone":"+43 676 6802052",
    "sg:postcode":"9371",
    "sg:province":"K\u00e4rnten",
    "wof:name":"Zechner Dietmar",
    "wof:placetype":"venue"
},
  "geometry": {"coordinates":[14.5317611694,46.7499198914],"type":"Point"}
}