{
  "type": "Feature",
  "properties": {
    "addr:full":"Altmannsdorfer Strasse 89/2 Wien Wien 1120",
    "addr:housenumber":"89 / 2",
    "addr:postcode":"1120",
    "addr:street":"Altmannsdorfer Strasse",
    "iso:country":"AT",
    "sg:address":"Altmannsdorfer Strasse 89/2",
    "sg:city":"Wien",
    "sg:classifiers":[
        {
            "category":"Building & Trades",
            "subcategory":"Cleaning & Sanitation",
            "type":"Services"
        }
    ],
    "sg:phone":"+43 1 80310000",
    "sg:postcode":"1120",
    "sg:province":"Wien",
    "sg:tags":[
        "chamber",
        "combustion",
        "agent",
        "others"
    ],
    "sg:website":"drweigert.com",
    "wof:name":"Chemische Fabrik Dr. Weigert Handelsges.m.b.H.",
    "wof:placetype":"venue"
},
  "geometry": {"coordinates":[16.3173809052,48.164264679],"type":"Point"}
}