{
  "type": "Feature",
  "properties": {
    "iso:country":"AT",
    "sg:address":"Leobner Strasse 78",
    "sg:city":"Bruck an der Mur",
    "sg:classifiers":[
        {
            "category":"Food & Beverages",
            "subcategory":"Groceries & Convenience Stores",
            "type":"Retail Goods"
        }
    ],
    "sg:phone":"+43 3862 560200",
    "sg:postcode":"8600",
    "sg:province":"Steiermark",
    "sg:tags":[
        "frozen",
        "goods",
        "baked"
    ],
    "sg:website":"oskars.at",
    "wof:name":"Wilhelm Blasko CONVENIENCE-Fertiggerichte GmbH",
    "wof:placetype":"venue"
},
  "geometry": {"coordinates":[15.2424449921,47.4015388489],"type":"Point"}
}