{
  "type": "Feature",
  "properties": {
    "addr:full":"Pirchhof 166 Sautens Tirol 6432",
    "addr:housenumber":"166",
    "addr:postcode":"6432",
    "addr:street":"Pirchhof;Tirol",
    "iso:country":"AT",
    "sg:address":"Pirchhof 166",
    "sg:city":"Sautens",
    "sg:orig_category":"Architekten",
    "sg:phone":"+43 5252 2242",
    "sg:postcode":"6432",
    "sg:province":"Tirol",
    "wof:name":"Sch\u00f6pf Hugo Dismas Dipl-Ing",
    "wof:placetype":"venue"
},
  "geometry": {"coordinates":[10.871720314,47.206199646],"type":"Point"}
}