{
  "type": "Feature",
  "properties": {
    "iso:country":"AT",
    "sg:address":"Marienbergweg 14",
    "sg:city":"Biberwier",
    "sg:orig_category":"Pensionen / Privatzimmer",
    "sg:phone":"+43 4356 733179",
    "sg:postcode":"6633",
    "sg:province":"Tirol",
    "wof:name":"G\u00e4stehaus Alpenland",
    "wof:placetype":"venue"
},
  "geometry": {"coordinates":[10.8909902573,47.374080658],"type":"Point"}
}