{
  "type": "Feature",
  "properties": {
    "iso:country":"AT",
    "sg:address":"Innsbrucker Str 62",
    "sg:city":"Axams",
    "sg:classifiers":[
        {
            "category":"Travel",
            "subcategory":"Hotels & Motels",
            "type":"Entertainment"
        }
    ],
    "sg:phone":"+43 5234 68855",
    "sg:postcode":"6094",
    "sg:province":"Tirol",
    "wof:name":"Hotel Bergland",
    "wof:placetype":"venue"
},
  "geometry": {"coordinates":[11.2889270782,47.2319335938],"type":"Point"}
}