{
  "type": "Feature",
  "properties": {
    "iso:country":"AT",
    "sg:address":"Innrain 105",
    "sg:city":"Innsbruck",
    "sg:orig_category":"Friseure U Frisiersalons",
    "sg:phone":"+43 4351 2580732",
    "sg:postcode":"6020",
    "sg:province":"Tirol",
    "wof:name":"Friseursalon Christine",
    "wof:placetype":"venue"
},
  "geometry": {"coordinates":[11.3801937103,47.2583694458],"type":"Point"}
}