{
  "type": "Feature",
  "properties": {
    "addr:full":"Dorfstr 295 Piesendorf Salzburg 5721",
    "addr:housenumber":"295",
    "addr:postcode":"5721",
    "addr:street":"Dorfstr;Salzburg",
    "iso:country":"AT",
    "sg:address":"Dorfstr 295",
    "sg:city":"Piesendorf",
    "sg:classifiers":[
        {
            "category":"Internet Cafe",
            "subcategory":"None",
            "type":"Food & Drink"
        }
    ],
    "sg:phone":"+43 6549 20156",
    "sg:postcode":"5721",
    "sg:province":"Salzburg",
    "sg:tags":[
        "internet-provider"
    ],
    "wof:name":"Net-Line.at SRAMKIEWICZ & KOTOWSKI OEG",
    "wof:placetype":"venue"
},
  "geometry": {"coordinates":[12.7160758972,47.2918319702],"type":"Point"}
}