{
  "type": "Feature",
  "properties": {
    "addr:full":"Zeller Strasse 9 Andorf Ober\u00f6sterreich 4770",
    "addr:housenumber":"9",
    "addr:postcode":"4770",
    "addr:street":"Zeller Strasse",
    "iso:country":"AT",
    "sg:address":"Zeller Strasse 9",
    "sg:city":"Andorf",
    "sg:classifiers":[
        {
            "category":"Manufacturing",
            "subcategory":"Glass & Minerals",
            "type":"Manufacturing & Wholesale Goods"
        }
    ],
    "sg:phone":"+43 7766 3385",
    "sg:postcode":"4770",
    "sg:province":"Ober\u00f6sterreich",
    "sg:tags":[
        "antique"
    ],
    "wof:name":"Seidl Glasbau Ges.m.b.H. & Co KG",
    "wof:placetype":"venue"
},
  "geometry": {"coordinates":[13.5688734055,48.3672714233],"type":"Point"}
}