{
  "type": "Feature",
  "properties": {
    "addr:full":"Wehlistr 71/10 Wien Wien 1200",
    "addr:housenumber":"71 / 10",
    "addr:postcode":"1200",
    "addr:street":"Wehlistr",
    "iso:country":"AT",
    "sg:address":"Wehlistr 71/10",
    "sg:city":"Wien",
    "sg:orig_category":"Glaswaren",
    "sg:phone":"+43 1 3305033",
    "sg:postcode":"1200",
    "sg:province":"Wien",
    "wof:name":"Bleikristall SOOS",
    "wof:placetype":"venue"
},
  "geometry": {"coordinates":[16.3885803223,48.2383308411],"type":"Point"}
}