{
  "type": "Feature",
  "properties": {
    "addr:full":"Camillo-Sitte-G 21 Wien Wien 1150",
    "addr:housenumber":"21",
    "addr:postcode":"1150",
    "addr:street":"Camillo-Sitte-G",
    "iso:country":"AT",
    "sg:address":"Camillo-Sitte-G 21",
    "sg:city":"Wien",
    "sg:orig_category":"Friseure U Frisiersalons",
    "sg:phone":"+43 4314 932725",
    "sg:postcode":"1150",
    "sg:province":"Wien",
    "wof:name":"W\u00f6lfl Gabriele",
    "wof:placetype":"venue"
},
  "geometry": {"coordinates":[16.3270664215,48.2048530579],"type":"Point"}
}