{
  "type": "Feature",
  "properties": {
    "addr:full":"Hauptstr 67 Henndorf am Wallersee Salzburg 5302",
    "addr:housenumber":"67",
    "addr:postcode":"5302",
    "addr:street":"Hauptstr",
    "iso:country":"AT",
    "sg:address":"Hauptstr 67",
    "sg:city":"Henndorf am Wallersee",
    "sg:orig_category":"Damenmoden",
    "sg:phone":"+43 4362 147034",
    "sg:postcode":"5302",
    "sg:province":"Salzburg",
    "wof:name":"IXIX-Die Mode",
    "wof:placetype":"venue"
},
  "geometry": {"coordinates":[13.1895523071,47.9009513855],"type":"Point"}
}