{
  "type": "Feature",
  "properties": {
    "addr:full":"Maxlhaid 32 Wels Ober\u00f6sterreich 4600",
    "addr:housenumber":"32",
    "addr:postcode":"4600",
    "addr:street":"Maxlhaid;Oberoesterreich",
    "iso:country":"AT",
    "sg:address":"Maxlhaid 32",
    "sg:city":"Wels",
    "sg:orig_category":"Farben U Lacke / Einzelhandel",
    "sg:phone":"+43 676 7004138",
    "sg:postcode":"4600",
    "sg:province":"Ober\u00f6sterreich",
    "wof:name":"Kneho-Lacke \u00d6sterreich",
    "wof:placetype":"venue"
},
  "geometry": {"coordinates":[14.0779600143,48.1872138977],"type":"Point"}
}