{
  "type": "Feature",
  "properties": {
    "addr:full":"Brodersdorf 128 Eggersdorf Steiermark 8063",
    "addr:housenumber":"128",
    "addr:postcode":"8063",
    "addr:street":"Brodersdorf",
    "iso:country":"AT",
    "sg:address":"Brodersdorf 128",
    "sg:city":"Eggersdorf",
    "sg:orig_category":"Schlossereien",
    "sg:phone":"+43 3117 3334",
    "sg:postcode":"8063",
    "sg:province":"Steiermark",
    "wof:name":"Lieb Helmut",
    "wof:placetype":"venue"
},
  "geometry": {"coordinates":[15.6164493561,47.1219100952],"type":"Point"}
}