{
  "type": "Feature",
  "properties": {
    "addr:full":"An der Ingering 37 Knittelfeld Steiermark 8720",
    "addr:housenumber":"37",
    "addr:postcode":"8720",
    "addr:street":"An Der Ingering",
    "iso:country":"AT",
    "sg:address":"An der Ingering 37",
    "sg:city":"Knittelfeld",
    "sg:orig_category":"Fleischhauereien",
    "sg:phone":"+43 4335 1244890",
    "sg:postcode":"8720",
    "sg:province":"Steiermark",
    "wof:name":"Schirnhofer-Breisler GesmbH - Shop in Shop",
    "wof:placetype":"venue"
},
  "geometry": {"coordinates":[14.7950801849,47.2150382996],"type":"Point"}
}