{
  "type": "Feature",
  "properties": {
    "iso:country":"AT",
    "sg:address":"Bierweg 1",
    "sg:city":"Taiskirchen im Innkreis",
    "sg:classifiers":[
        {
            "category":"Organizations",
            "subcategory":"Non-profit Organization",
            "type":"Services"
        }
    ],
    "sg:phone":"+43 7764 7261",
    "sg:postcode":"4753",
    "sg:province":"Ober\u00f6sterreich",
    "sg:tags":[
        "alarm",
        "system"
    ],
    "wof:name":"Gottfried Scheuringer",
    "wof:placetype":"venue"
},
  "geometry": {"coordinates":[13.5804300308,48.2662162781],"type":"Point"}
}