{
  "type": "Feature",
  "properties": {
    "addr:full":"Laiter 45 Oberhofen am Irrsee Ober\u00f6sterreich 4894",
    "addr:housenumber":"45",
    "addr:postcode":"4894",
    "addr:street":"Laiter",
    "iso:country":"AT",
    "sg:address":"Laiter 45",
    "sg:city":"Oberhofen am Irrsee",
    "sg:orig_category":"Steinmetzbetriebe",
    "sg:phone":"+43 664 2002127",
    "sg:postcode":"4894",
    "sg:province":"Ober\u00f6sterreich",
    "wof:name":"Bildhauerwerkstatt Salzkammergut - UNIKA Natursteinwerk GesmbH",
    "wof:placetype":"venue"
},
  "geometry": {"coordinates":[13.3108348846,47.9338188171],"type":"Point"}
}