{
  "type": "Feature",
  "properties": {
    "addr:full":"Bayerhamerstr 27 Salzburg Salzburg 5020",
    "addr:housenumber":"27",
    "addr:postcode":"5020",
    "addr:street":"Bayerhamerstr;Salzburg",
    "iso:country":"AT",
    "sg:address":"Bayerhamerstr 27",
    "sg:city":"Salzburg",
    "sg:orig_category":"Friseure U Frisiersalons",
    "sg:phone":"+43 4366 2874219",
    "sg:postcode":"5020",
    "sg:province":"Salzburg",
    "wof:name":"Hairstudio M",
    "wof:placetype":"venue"
},
  "geometry": {"coordinates":[13.0505065918,47.8094024658],"type":"Point"}
}