{
  "type": "Feature",
  "properties": {
    "iso:country":"AT",
    "sg:address":"Siegelg 1",
    "sg:city":"Wien",
    "sg:orig_category":"Ausweissysteme",
    "sg:phone":"+43 4317 1266440",
    "sg:postcode":"1030",
    "sg:province":"Wien",
    "sg:website":"tuschl.com",
    "wof:name":"Tuschl Roland Ing",
    "wof:placetype":"venue"
},
  "geometry": {"coordinates":[16.3913631439,48.2040901184],"type":"Point"}
}