{
  "type": "Feature",
  "properties": {
    "iso:country":"AT",
    "sg:address":"St\u00f6cklfeld 17",
    "sg:city":"Kirchberg in Tirol",
    "sg:orig_category":"Appartements / Ferienwohnungen",
    "sg:phone":"+43 5357 2806",
    "sg:postcode":"6365",
    "sg:province":"Tirol",
    "wof:name":"Appartementhaus Hartmann",
    "wof:placetype":"venue"
},
  "geometry": {"coordinates":[12.310590744,47.4479103088],"type":"Point"}
}