{
  "type": "Feature",
  "properties": {
    "addr:full":"Wiener Str 48 Theresienfeld Nieder\u00f6sterreich 2604",
    "addr:postcode":"2604",
    "addr:street":"Niederoesterreich",
    "iso:country":"AT",
    "sg:address":"Wiener Str 48",
    "sg:city":"Theresienfeld",
    "sg:orig_category":"Hunde- U Katzensalons",
    "sg:phone":"+43 4326 2272292",
    "sg:postcode":"2604",
    "sg:province":"Nieder\u00f6sterreich",
    "wof:name":"Hundesalon Struppi & Boutique",
    "wof:placetype":"venue"
},
  "geometry": {"coordinates":[16.2488613129,47.8677787781],"type":"Point"}
}