{
  "type": "Feature",
  "properties": {
    "addr:full":"Eduard-Sue\u00df-Gasse 5 Wien Wien 1150",
    "addr:housenumber":"5",
    "addr:postcode":"1150",
    "addr:street":"Eduard-Suess-Gasse",
    "iso:country":"AT",
    "sg:address":"Eduard-Sue\u00df-Gasse 5",
    "sg:city":"Wien",
    "sg:classifiers":[
        {
            "category":"Recreation",
            "subcategory":"Barbecue",
            "type":"Entertainment"
        }
    ],
    "sg:phone":"+43 1 9858188",
    "sg:postcode":"1150",
    "sg:province":"Wien",
    "sg:tags":[
        "grills",
        "commercial"
    ],
    "sg:website":"barbecue-king.at",
    "wof:name":"Barbecue King Handelsges.m.b.H.",
    "wof:placetype":"venue"
},
  "geometry": {"coordinates":[16.3189525604,48.1945037842],"type":"Point"}
}