{
  "type": "Feature",
  "properties": {
    "iso:country":"AT",
    "sg:address":"Salinenpl 11",
    "sg:city":"Ebensee",
    "sg:orig_category":"Rettungsdienste",
    "sg:phone":"+43 6133 20091",
    "sg:postcode":"4802",
    "sg:province":"Ober\u00f6sterreich",
    "wof:name":"Rotes Kreuz \u00f6sterreichisches",
    "wof:placetype":"venue"
},
  "geometry": {"coordinates":[13.7742099762,47.8120651245],"type":"Point"}
}