{
  "type": "Feature",
  "properties": {
    "iso:country":"AT",
    "sg:address":"Grete Bittner-Str 7",
    "sg:city":"Klagenfurt",
    "sg:orig_category":"Blut- U Plasmaspenden",
    "sg:phone":"+43 463 466551904",
    "sg:postcode":"9020",
    "sg:province":"K\u00e4rnten",
    "wof:name":"Rotes Kreuz \u00d6sterr Blutspendezentrale f K\u00e4rnten",
    "wof:placetype":"venue"
},
  "geometry": {"coordinates":[14.3005170822,46.6367111206],"type":"Point"}
}