{
  "type": "Feature",
  "properties": {
    "iso:country":"AT",
    "sg:address":"10.-Oktober-Str 8",
    "sg:city":"Villach",
    "sg:orig_category":"Boutiquen",
    "sg:phone":"+43 4342 4224924",
    "sg:postcode":"9500",
    "sg:province":"K\u00e4rnten",
    "wof:name":"Tally Weijl",
    "wof:placetype":"venue"
},
  "geometry": {"coordinates":[13.8457889557,46.6125030518],"type":"Point"}
}