{
  "type": "Feature",
  "properties": {
    "addr:full":"Schreyvogelg 2 Wien Wien 1010",
    "addr:housenumber":"2",
    "addr:postcode":"1010",
    "addr:street":"Schreyvogelg",
    "iso:country":"AT",
    "sg:address":"Schreyvogelg 2",
    "sg:city":"Wien",
    "sg:orig_category":"Bildungsservice / Allgemeine Informationsstellen",
    "sg:phone":"+43 1 5340817",
    "sg:postcode":"1010",
    "sg:province":"Wien",
    "wof:name":"Sokrates Nationalagentur",
    "wof:placetype":"venue"
},
  "geometry": {"coordinates":[16.3631820679,48.2118339539],"type":"Point"}
}