{
  "type": "Feature",
  "properties": {
    "addr:full":"Dauphinestr 208 Linz Ober\u00f6sterreich 4030",
    "addr:housenumber":"208",
    "addr:postcode":"4030",
    "iso:country":"AT",
    "sg:address":"Dauphinestr 208",
    "sg:city":"Linz",
    "sg:classifiers":[
        {
            "category":"Restaurant",
            "type":"Food & Drink"
        }
    ],
    "sg:phone":"+43 732 377515",
    "sg:postcode":"4030",
    "sg:province":"Ober\u00f6sterreich",
    "sg:tags":[
        "pizzeria"
    ],
    "wof:name":"Pizza-Hot",
    "wof:placetype":"venue"
},
  "geometry": {"coordinates":[14.2887859344,48.2533874512],"type":"Point"}
}