{
  "type": "Feature",
  "properties": {
    "iso:country":"AT",
    "sg:address":"Landstr. 57 ",
    "sg:city":"Lochau",
    "sg:classifiers":[
        {
            "category":"Manufacturing",
            "subcategory":"Rubber & Plastics",
            "type":"Manufacturing & Wholesale Goods"
        }
    ],
    "sg:phone":"+43 4355 74423620",
    "sg:postcode":"6911",
    "sg:province":"Vorarlberg",
    "wof:name":"FORSTER REIFEN GESMBH",
    "wof:placetype":"venue"
},
  "geometry": {"coordinates":[9.7511644363,47.5248260498],"type":"Point"}
}