{
  "type": "Feature",
  "properties": {
    "addr:full":"Felix Mottl Strasse 20 -  Wien Wien 1190",
    "addr:housenumber":"20",
    "addr:postcode":"1190",
    "addr:street":"Mottl Strasse",
    "iso:country":"AT",
    "sg:address":"Felix Mottl Strasse 20 - ",
    "sg:city":"Wien",
    "sg:classifiers":[
        {
            "category":"Professional",
            "subcategory":"Art Services",
            "type":"Services"
        }
    ],
    "sg:phone":"+43 4313 680755",
    "sg:postcode":"1190",
    "sg:province":"Wien",
    "sg:tags":[
        "export-import"
    ],
    "wof:name":"Vietnam Embassy",
    "wof:placetype":"venue"
},
  "geometry": {"coordinates":[16.3439350128,48.2347221375],"type":"Point"}
}