{
  "type": "Feature",
  "properties": {
    "addr:full":"Braung 15 G\u00fcnselsdorf Nieder\u00f6sterreich 2525",
    "addr:housenumber":"15",
    "addr:postcode":"2525",
    "addr:street":"Braung;Niederoesterreich",
    "iso:country":"AT",
    "sg:address":"Braung 15",
    "sg:city":"G\u00fcnselsdorf",
    "sg:orig_category":"Weine / Einzelhandel",
    "sg:phone":"+43 4322 5664381",
    "sg:postcode":"2525",
    "sg:province":"Nieder\u00f6sterreich",
    "wof:name":"Mayer Ferdinand u Johannes",
    "wof:placetype":"venue"
},
  "geometry": {"coordinates":[16.2561817169,47.9361763],"type":"Point"}
}