{
  "type": "Feature",
  "properties": {
    "addr:full":"G\u00fcterstr 4a/24 Saalfelden am Steinernen Meer Salzburg 5760",
    "addr:housenumber":"4a / 24",
    "addr:postcode":"5760",
    "addr:street":"Gueterstr;Salzburg",
    "iso:country":"AT",
    "sg:address":"G\u00fcterstr 4a/24",
    "sg:city":"Saalfelden am Steinernen Meer",
    "sg:orig_category":"Kosmetikanwendungsberatung",
    "sg:phone":"+43 4367 69634039",
    "sg:postcode":"5760",
    "sg:province":"Salzburg",
    "wof:name":"CHANNOINE COSMETIC - Christa Dick",
    "wof:placetype":"venue"
},
  "geometry": {"coordinates":[12.8474750519,47.426410675],"type":"Point"}
}