{
  "type": "Feature",
  "properties": {
    "addr:full":"Pfarrg 2 Westendorf Tirol 6363",
    "addr:housenumber":"2",
    "addr:postcode":"6363",
    "addr:street":"Pfarrg",
    "iso:country":"AT",
    "sg:address":"Pfarrg 2",
    "sg:city":"Westendorf",
    "sg:orig_category":"Banken U Sparkassen",
    "sg:phone":"+43 4353 346266",
    "sg:postcode":"6363",
    "sg:province":"Tirol",
    "wof:name":"Sparkasse d Stadt Kitzb\u00fchel",
    "wof:placetype":"venue"
},
  "geometry": {"coordinates":[12.2147397995,47.4321594238],"type":"Point"}
}