{
  "type": "Feature",
  "properties": {
    "addr:full":"Heinrichstr 18 Graz Steiermark 8010",
    "addr:housenumber":"18",
    "addr:postcode":"8010",
    "addr:street":"Heinrichstr",
    "iso:country":"AT",
    "sg:address":"Heinrichstr 18",
    "sg:city":"Graz",
    "sg:orig_category":"Textilreinigung",
    "sg:phone":"+43 316 325222",
    "sg:postcode":"8010",
    "sg:province":"Steiermark",
    "wof:name":"RUPP - Qualit\u00e4tsreinigung",
    "wof:placetype":"venue"
},
  "geometry": {"coordinates":[15.4465970993,47.0784645081],"type":"Point"}
}