{
  "type": "Feature",
  "properties": {
    "addr:full":"Gilmstr 5 Innsbruck Tirol 6020",
    "addr:housenumber":"5",
    "addr:postcode":"6020",
    "addr:street":"Gilmstr;Tirol",
    "iso:country":"AT",
    "sg:address":"Gilmstr 5",
    "sg:city":"Innsbruck",
    "sg:classifiers":[
        {
            "category":"Travel",
            "subcategory":"Hotels & Motels",
            "type":"Entertainment"
        }
    ],
    "sg:phone":"+43 512 59200",
    "sg:postcode":"6020",
    "sg:province":"Tirol",
    "wof:name":"Hotel-Cafe-Central GesmbH",
    "wof:placetype":"venue"
},
  "geometry": {"coordinates":[11.3965473175,47.2658843994],"type":"Point"}
}