{
  "type": "Feature",
  "properties": {
    "addr:full":"Kendlbachstr 11 Kapfenberg Steiermark 8605",
    "addr:housenumber":"11",
    "addr:postcode":"8605",
    "addr:street":"Kendlbachstr",
    "iso:country":"AT",
    "sg:address":"Kendlbachstr 11",
    "sg:city":"Kapfenberg",
    "sg:orig_category":"Weiterbildungsinstitute M Allg U Berufl Bildungsangebot",
    "sg:phone":"+43 3862 21313150",
    "sg:postcode":"8605",
    "sg:province":"Steiermark",
    "wof:name":"BFI-Berufsf\u00f6rderungsinstitut Steiermark",
    "wof:placetype":"venue"
},
  "geometry": {"coordinates":[15.2717685699,47.4506263733],"type":"Point"}
}