{
  "type": "Feature",
  "properties": {
    "addr:full":"Ro\u00dfmarkt 2 Grieskirchen Ober\u00f6sterreich 4710",
    "addr:housenumber":"2",
    "addr:postcode":"4710",
    "addr:street":"Rossmarkt",
    "iso:country":"AT",
    "sg:address":"Ro\u00dfmarkt 2",
    "sg:city":"Grieskirchen",
    "sg:orig_category":"Spielwaren U Spiele",
    "sg:phone":"+43 7248 65582",
    "sg:postcode":"4710",
    "sg:province":"Ober\u00f6sterreich",
    "wof:name":"Fr\u00f6mel Carina",
    "wof:placetype":"venue"
},
  "geometry": {"coordinates":[13.8257322311,48.2358856201],"type":"Point"}
}