{
  "type": "Feature",
  "properties": {
    "addr:full":"Illsandstr 4 Bludesch Vorarlberg 6719",
    "addr:housenumber":"4",
    "addr:postcode":"6719",
    "addr:street":"Illsandstr",
    "iso:country":"AT",
    "sg:address":"Illsandstr 4",
    "sg:city":"Bludesch",
    "sg:orig_category":"Tischlereien",
    "sg:phone":"+43 5525 62206",
    "sg:postcode":"6719",
    "sg:province":"Vorarlberg",
    "wof:name":"Frei Johann",
    "wof:placetype":"venue"
},
  "geometry": {"coordinates":[9.7409362793,47.1968688965],"type":"Point"}
}