{
  "type": "Feature",
  "properties": {
    "addr:full":"P\u00f6llach 87 St. Gilgen Salzburg 5340",
    "addr:housenumber":"87",
    "addr:postcode":"5340",
    "addr:street":"Poellach",
    "iso:country":"AT",
    "sg:address":"P\u00f6llach 87",
    "sg:city":"St. Gilgen",
    "sg:orig_category":"Werbeagenturen",
    "sg:phone":"+43 664 4334288",
    "sg:postcode":"5340",
    "sg:province":"Salzburg",
    "wof:name":"Werbeagentur Schuheker",
    "wof:placetype":"venue"
},
  "geometry": {"coordinates":[13.3638296127,47.7669639587],"type":"Point"}
}