{
  "type": "Feature",
  "properties": {
    "iso:country":"AT",
    "sg:address":"Dorfpl 23",
    "sg:city":"Kirchdorf in Tirol",
    "sg:orig_category":"Volksschulen",
    "sg:phone":"+43 5352 63145",
    "sg:postcode":"6382",
    "sg:province":"Tirol",
    "wof:name":"Volksschule",
    "wof:placetype":"venue"
},
  "geometry": {"coordinates":[12.4484367371,47.5585746765],"type":"Point"}
}