{
  "type": "Feature",
  "properties": {
    "addr:full":"Dorfpl 23 Kirchdorf in Tirol Tirol 6382",
    "addr:housenumber":"23",
    "addr:postcode":"6382",
    "addr:street":"Dorfpl;Tirol",
    "iso:country":"AT",
    "sg:address":"Dorfpl 23",
    "sg:city":"Kirchdorf in Tirol",
    "sg:orig_category":"Volksschulen",
    "sg:phone":"+43 5352 63145",
    "sg:postcode":"6382",
    "sg:province":"Tirol",
    "wof:name":"Volksschule",
    "wof:placetype":"venue"
},
  "geometry": {"coordinates":[12.4484367371,47.5585746765],"type":"Point"}
}