{
  "type": "Feature",
  "properties": {
    "iso:country":"AT",
    "sg:address":"Bachweg 9",
    "sg:city":"Knittelfeld",
    "sg:classifiers":[
        {
            "category":"Professional",
            "subcategory":"Computer Services",
            "type":"Services"
        }
    ],
    "sg:phone":"+43 3512 85839",
    "sg:postcode":"8720",
    "sg:province":"Steiermark",
    "sg:tags":[
        "software"
    ],
    "wof:name":"Purgstaller Thomas",
    "wof:placetype":"venue"
},
  "geometry": {"coordinates":[14.8211612701,47.1893730164],"type":"Point"}
}