{
  "type": "Feature",
  "properties": {
    "addr:full":"Stadtpl 7 Klosterneuburg Nieder\u00f6sterreich 3400",
    "addr:housenumber":"7",
    "addr:postcode":"3400",
    "addr:street":"Stadtpl;Niederoesterreich",
    "iso:country":"AT",
    "sg:address":"Stadtpl 7",
    "sg:city":"Klosterneuburg",
    "sg:orig_category":"Boutiquen",
    "sg:phone":"+43 2243 36920",
    "sg:postcode":"3400",
    "sg:province":"Nieder\u00f6sterreich",
    "wof:name":"Boutique Joker",
    "wof:placetype":"venue"
},
  "geometry": {"coordinates":[16.3227977753,48.3089370728],"type":"Point"}
}