{
  "type": "Feature",
  "properties": {
    "addr:full":"Kirchstr 39 Bregenz Vorarlberg 6900",
    "addr:housenumber":"39",
    "addr:postcode":"6900",
    "addr:street":"Kirchstr",
    "iso:country":"AT",
    "sg:address":"Kirchstr 39",
    "sg:city":"Bregenz",
    "sg:orig_category":"Tragtaschen",
    "sg:phone":"+43 5574 72915",
    "sg:postcode":"6900",
    "sg:province":"Vorarlberg",
    "wof:name":"P.O.S. Support Tragetaschen Schrott Markus",
    "wof:placetype":"venue"
},
  "geometry": {"coordinates":[9.7468128204,47.5006637573],"type":"Point"}
}