{
  "type": "Feature",
  "properties": {
    "addr:full":"Tullner Str 145 Langenlebarn Nieder\u00f6sterreich 3425",
    "addr:housenumber":"145",
    "addr:postcode":"3425",
    "iso:country":"AT",
    "sg:address":"Tullner Str 145",
    "sg:city":"Langenlebarn",
    "sg:classifiers":[
        {
            "category":"Government",
            "subcategory":"Post Office",
            "type":"Public Place"
        }
    ],
    "sg:phone":"+43 2272 62540",
    "sg:postcode":"3425",
    "sg:province":"Nieder\u00f6sterreich",
    "sg:tags":[
        "yoga"
    ],
    "wof:name":"Baranyai Yoga Helene Sanft",
    "wof:placetype":"venue"
},
  "geometry": {"coordinates":[16.0993442535,48.3295936584],"type":"Point"}
}