{
  "type": "Feature",
  "properties": {
    "addr:full":"Kalsdorfer Str 30 Feldkirchen Steiermark 8073",
    "addr:postcode":"8073",
    "addr:street":"Str 30",
    "iso:country":"AT",
    "sg:address":"Kalsdorfer Str 30",
    "sg:city":"Feldkirchen",
    "sg:orig_category":"Fluggesellschaften",
    "sg:phone":"+43 316 9020",
    "sg:postcode":"8073",
    "sg:province":"Steiermark",
    "wof:name":"Fairline Luftfahrt GmbH & Co KG",
    "wof:placetype":"venue"
},
  "geometry": {"coordinates":[15.4492511749,46.9908485413],"type":"Point"}
}