{
  "type": "Feature",
  "properties": {
    "addr:full":"Mariahilfer Str 85-87 Wien Wien 1060",
    "addr:postcode":"85-87;1060",
    "addr:street":"Str",
    "iso:country":"AT",
    "sg:address":"Mariahilfer Str 85-87",
    "sg:city":"Wien",
    "sg:orig_category":"Bekleidung / Einzelhandel",
    "sg:phone":"+43 1 5861783",
    "sg:postcode":"1060",
    "sg:province":"Wien",
    "wof:name":"Sch\u00f6ps Richard & Co AG",
    "wof:placetype":"venue"
},
  "geometry": {"coordinates":[16.3484249115,48.1976051331],"type":"Point"}
}