{
  "type": "Feature",
  "properties": {
    "addr:full":"Hintausstr 20/10 Achau Nieder\u00f6sterreich 2481",
    "addr:housenumber":"20 / 10",
    "addr:postcode":"2481",
    "addr:street":"Hintausstr",
    "iso:country":"AT",
    "sg:address":"Hintausstr 20/10",
    "sg:city":"Achau",
    "sg:orig_category":"Psychotherapie",
    "sg:phone":"+43 2236 73628",
    "sg:postcode":"2481",
    "sg:province":"Nieder\u00f6sterreich",
    "wof:name":"Maderb\u00f6ck Gabriele",
    "wof:placetype":"venue"
},
  "geometry": {"coordinates":[16.3836345673,48.0815696716],"type":"Point"}
}