{
  "type": "Feature",
  "properties": {
    "addr:full":"Auhofstrasse 142a Wien Wien 1130",
    "addr:housenumber":"142a",
    "addr:postcode":"1130",
    "addr:street":"Auhofstrasse",
    "iso:country":"AT",
    "sg:address":"Auhofstrasse 142a",
    "sg:city":"Wien",
    "sg:classifiers":[
        {
            "category":"Manufacturing",
            "subcategory":"Wood Products",
            "type":"Manufacturing & Wholesale Goods"
        }
    ],
    "sg:phone":"+43 1 8795416",
    "sg:postcode":"1130",
    "sg:province":"Wien",
    "sg:tags":[
        "firewood"
    ],
    "sg:website":"abex.at",
    "wof:name":"ABEX Handels GmbH",
    "wof:placetype":"venue"
},
  "geometry": {"coordinates":[16.270029068,48.1911773682],"type":"Point"}
}