{
  "type": "Feature",
  "properties": {
    "addr:full":"Oberer Markt 220 St. Gallen Steiermark 8933",
    "addr:housenumber":"220",
    "addr:postcode":"8933",
    "addr:street":"Oberer Markt",
    "iso:country":"AT",
    "sg:address":"Oberer Markt 220",
    "sg:city":"St. Gallen",
    "sg:orig_category":"Bibliotheken",
    "sg:phone":"+43 3632 7154",
    "sg:postcode":"8933",
    "sg:province":"Steiermark",
    "wof:name":"B\u00fccherei",
    "wof:placetype":"venue"
},
  "geometry": {"coordinates":[14.6183948517,47.690322876],"type":"Point"}
}