{
  "type": "Feature",
  "properties": {
    "addr:full":"Kaiser-Josef-Pl 39 Wels Ober\u00f6sterreich 4600",
    "addr:housenumber":"39",
    "addr:postcode":"4600",
    "addr:street":"Kaiser-Josef-Pl;Oberoesterreich",
    "iso:country":"AT",
    "sg:address":"Kaiser-Josef-Pl 39",
    "sg:city":"Wels",
    "sg:orig_category":"Damenmoden",
    "sg:phone":"+43 7242 45434",
    "sg:postcode":"4600",
    "sg:province":"Ober\u00f6sterreich",
    "wof:name":"Migl Andrea",
    "wof:placetype":"venue"
},
  "geometry": {"coordinates":[14.0219154358,48.1591072083],"type":"Point"}
}