{
  "type": "Feature",
  "properties": {
    "addr:full":"Wichnerstr 14 Dornbirn Vorarlberg 6850",
    "addr:housenumber":"14",
    "addr:postcode":"6850",
    "addr:street":"Wichnerstr",
    "iso:country":"AT",
    "sg:address":"Wichnerstr 14",
    "sg:city":"Dornbirn",
    "sg:orig_category":"Markisen",
    "sg:phone":"+43 5572 227280",
    "sg:postcode":"6850",
    "sg:province":"Vorarlberg",
    "wof:name":"FOLIFLEX Sonnenschutztechnik GmbH",
    "wof:placetype":"venue"
},
  "geometry": {"coordinates":[9.7339172363,47.4238471985],"type":"Point"}
}