{
  "type": "Feature",
  "properties": {
    "addr:full":"M\u00fchlg 2 Telfs Tirol 6410",
    "addr:housenumber":"2",
    "addr:postcode":"6410",
    "addr:street":"Muehlg;Tirol",
    "iso:country":"AT",
    "sg:address":"M\u00fchlg 2",
    "sg:city":"Telfs",
    "sg:orig_category":"Futtermittel",
    "sg:phone":"+43 5262 61777",
    "sg:postcode":"6410",
    "sg:province":"Tirol",
    "wof:name":"Leckerbissen - Tiernahrung Pilsinger Thomas",
    "wof:placetype":"venue"
},
  "geometry": {"coordinates":[11.072218895,47.3066978455],"type":"Point"}
}