{
  "type": "Feature",
  "properties": {
    "addr:full":"Winterburgergasse 9/19 Wien Wien 1160",
    "addr:housenumber":"9 / 19",
    "addr:postcode":"1160",
    "addr:street":"Winterburgergasse",
    "iso:country":"AT",
    "sg:address":"Winterburgergasse 9/19",
    "sg:city":"Wien",
    "sg:classifiers":[
        {
            "category":"Bars & Pubs",
            "subcategory":"Nightclub",
            "type":"Food & Drink"
        }
    ],
    "sg:phone":"+43 1 4855337",
    "sg:postcode":"1160",
    "sg:province":"Wien",
    "sg:tags":[
        "upright",
        "piano",
        "hammer",
        "grand"
    ],
    "wof:name":"G\u00fcnther Mader",
    "wof:placetype":"venue"
},
  "geometry": {"coordinates":[16.3040943146,48.2203140259],"type":"Point"}
}