{
  "type": "Feature",
  "properties": {
    "iso:country":"AT",
    "sg:address":"Leibnitzer Str 13",
    "sg:city":"Lebring",
    "sg:orig_category":"Feuerwehren",
    "sg:phone":"+43 3182 3322",
    "sg:postcode":"8403",
    "sg:province":"Steiermark",
    "wof:name":"Freiwillige Feuerwehr St Margarethen-Lebring",
    "wof:placetype":"venue"
},
  "geometry": {"coordinates":[15.5379533768,46.8537445068],"type":"Point"}
}