{
  "type": "Feature",
  "properties": {
    "addr:full":"Marktstr 3 Eisenstadt Burgenland 7000",
    "addr:housenumber":"3",
    "addr:postcode":"7000",
    "addr:street":"Marktstr",
    "iso:country":"AT",
    "sg:address":"Marktstr 3",
    "sg:city":"Eisenstadt",
    "sg:orig_category":"Steuerungstechnik",
    "sg:phone":"+43 4359 010100",
    "sg:postcode":"7000",
    "sg:province":"Burgenland",
    "wof:name":"Telegyr Systems Leit- u Fernwirktechnik GesmbH & Co OHG",
    "wof:placetype":"venue"
},
  "geometry": {"coordinates":[16.5320110321,47.8292007446],"type":"Point"}
}