{
  "type": "Feature",
  "properties": {
    "addr:full":"Nr 11a Lamprechtshausen Salzburg 5112",
    "addr:postcode":"5112",
    "addr:street":"Nr 11A;Salzburg",
    "iso:country":"AT",
    "sg:address":"Nr 11a",
    "sg:city":"Lamprechtshausen",
    "sg:orig_category":"Damenmoden",
    "sg:phone":"+43 4362 746671",
    "sg:postcode":"5112",
    "sg:province":"Salzburg",
    "wof:name":"Pfaffinger Rosa",
    "wof:placetype":"venue"
},
  "geometry": {"coordinates":[12.9562635422,47.9924926758],"type":"Point"}
}