{
  "type": "Feature",
  "properties": {
    "iso:country":"AT",
    "sg:address":"Im Stadtgut B1",
    "sg:city":"Gleink",
    "sg:classifiers":[
        {
            "category":"Autos & Motor Vehicles",
            "subcategory":"Fuel & Gas Station",
            "type":"Retail Goods"
        }
    ],
    "sg:phone":"+43 7435 501552",
    "sg:postcode":"4407",
    "sg:province":"Ober\u00f6sterreich",
    "sg:tags":[
        "engine",
        "set",
        "diesel"
    ],
    "sg:website":"steyr-motors.com",
    "wof:name":"STEYR MOTORS GmbH",
    "wof:placetype":"venue"
},
  "geometry": {"coordinates":[14.4159860611,48.0908508301],"type":"Point"}
}