{
  "type": "Feature",
  "properties": {
    "addr:full":"Kaiserstr 20 Bregenz Vorarlberg 6900",
    "addr:housenumber":"20",
    "addr:postcode":"6900",
    "addr:street":"Kaiserstr",
    "iso:country":"AT",
    "sg:address":"Kaiserstr 20",
    "sg:city":"Bregenz",
    "sg:orig_category":"Optiker",
    "sg:phone":"+43 5574 53821",
    "sg:postcode":"6900",
    "sg:province":"Vorarlberg",
    "wof:name":"Fielmann GmbH",
    "wof:placetype":"venue"
},
  "geometry": {"coordinates":[9.7461528778,47.503326416],"type":"Point"}
}