{
  "type": "Feature",
  "properties": {
    "iso:country":"AT",
    "sg:address":"Anderseng 17",
    "sg:city":"Wien",
    "sg:orig_category":"Elektroinstallationsunternehmen",
    "sg:phone":"+43 4316 673217",
    "sg:postcode":"1120",
    "sg:province":"Wien",
    "wof:name":"Kadlec Franz",
    "wof:placetype":"venue"
},
  "geometry": {"coordinates":[16.3277072906,48.1625595093],"type":"Point"}
}