{
  "type": "Feature",
  "properties": {
    "addr:full":"D\u00fcrne 1a Koblach Vorarlberg 6842",
    "addr:housenumber":"1a",
    "addr:postcode":"6842",
    "addr:street":"Duerne",
    "iso:country":"AT",
    "sg:address":"D\u00fcrne 1a",
    "sg:city":"Koblach",
    "sg:orig_category":"Kosmetische Produkte / Erzeugung U Gro\u00c3\u0178handel",
    "sg:phone":"+43 5523 53750",
    "sg:postcode":"6842",
    "sg:province":"Vorarlberg",
    "wof:name":"CosTrade Beauty Consulting GmbH",
    "wof:placetype":"venue"
},
  "geometry": {"coordinates":[9.6024236679,47.3305778503],"type":"Point"}
}