{
  "type": "Feature",
  "properties": {
    "addr:full":"Gewerbestr. 21 Gerasdorf Nieder\u00f6sterreich 2201",
    "addr:housenumber":"21",
    "addr:postcode":"2201",
    "addr:street":"Gewerbestr.",
    "iso:country":"AT",
    "sg:address":"Gewerbestr. 21",
    "sg:city":"Gerasdorf",
    "sg:classifiers":[
        {
            "category":"Manufacturing",
            "subcategory":"Metals",
            "type":"Manufacturing & Wholesale Goods"
        }
    ],
    "sg:phone":"+43 4322 4628330",
    "sg:postcode":"2201",
    "sg:province":"Nieder\u00f6sterreich",
    "sg:tags":[
        "metallurgy",
        "metalworking"
    ],
    "wof:name":"METRA AUSTRIA GMBH",
    "wof:placetype":"venue"
},
  "geometry": {"coordinates":[16.4708862305,48.2990150452],"type":"Point"}
}