{
  "type": "Feature",
  "properties": {
    "addr:full":"Predlitz 156 Predlitz Steiermark 8863",
    "addr:housenumber":"156",
    "addr:postcode":"8863",
    "addr:street":"Predlitz",
    "iso:country":"AT",
    "sg:address":"Predlitz 156",
    "sg:city":"Predlitz",
    "sg:orig_category":"Feuerwehren",
    "sg:phone":"+43 3534 20170",
    "sg:postcode":"8863",
    "sg:province":"Steiermark",
    "wof:name":"Feuerwehr Predlitz",
    "wof:placetype":"venue"
},
  "geometry": {"coordinates":[13.9153490067,47.0723609924],"type":"Point"}
}