{
  "type": "Feature",
  "properties": {
    "iso:country":"AT",
    "sg:address":"Eichfelder Strasse 19",
    "sg:city":"Mureck",
    "sg:classifiers":[
        {
            "category":"Military Area",
            "subcategory":"Air Force Base",
            "type":"Public Place"
        }
    ],
    "sg:phone":"+43 3472 22120",
    "sg:postcode":"8480",
    "sg:province":"Steiermark",
    "sg:tags":[
        "attic",
        "stair"
    ],
    "wof:name":"Romann Ges.m.b.H.",
    "wof:placetype":"venue"
},
  "geometry": {"coordinates":[15.7684650421,46.71301651],"type":"Point"}
}