{
  "type": "Feature",
  "properties": {
    "addr:full":"Modsiedler Steig 3 Raabs an der Thaya Nieder\u00f6sterreich 3820",
    "addr:housenumber":"3",
    "addr:postcode":"3820",
    "addr:street":"Modsiedler Steig",
    "iso:country":"AT",
    "sg:address":"Modsiedler Steig 3",
    "sg:city":"Raabs an der Thaya",
    "sg:orig_category":"Spirituosen / Erzeugung U Gro\u00c3\u0178handel",
    "sg:phone":"+43 4328 46384",
    "sg:postcode":"3820",
    "sg:province":"Nieder\u00f6sterreich",
    "wof:name":"Landwirtschaftliche Brennereien f Raabs a d Thaya u UmgebungregGenmbH",
    "wof:placetype":"venue"
},
  "geometry": {"coordinates":[15.4931097031,48.8490638733],"type":"Point"}
}