{
  "type": "Feature",
  "properties": {
    "addr:full":"Nr 91 Oberwang Ober\u00f6sterreich 4882",
    "addr:postcode":"4882",
    "addr:street":"Nr;Oberoesterreich",
    "iso:country":"AT",
    "sg:address":"Nr 91",
    "sg:city":"Oberwang",
    "sg:orig_category":"Transportunternehmen",
    "sg:phone":"+43 6233 8206",
    "sg:postcode":"4882",
    "sg:province":"Ober\u00f6sterreich",
    "wof:name":"Zieher Harald",
    "wof:placetype":"venue"
},
  "geometry": {"coordinates":[13.4338312149,47.8680839539],"type":"Point"}
}