{
  "type": "Feature",
  "properties": {
    "addr:full":"Wiener Str 151 Spillern Nieder\u00f6sterreich 2104",
    "addr:housenumber":"151",
    "addr:postcode":"2104",
    "iso:country":"AT",
    "sg:address":"Wiener Str 151",
    "sg:city":"Spillern",
    "sg:orig_category":"Transportbeton",
    "sg:phone":"+43 2266 81686",
    "sg:postcode":"2104",
    "sg:province":"Nieder\u00f6sterreich",
    "wof:name":"Lieferbeton GesmbH",
    "wof:placetype":"venue"
},
  "geometry": {"coordinates":[16.2727203369,48.3761405945],"type":"Point"}
}