{
  "type": "Feature",
  "properties": {
    "addr:full":"Raasdorfer Str 5 Leopoldsdorf im Marchfelde Nieder\u00f6sterreich 2285",
    "addr:housenumber":"5",
    "addr:postcode":"2285",
    "addr:street":"Str",
    "iso:country":"AT",
    "sg:address":"Raasdorfer Str 5",
    "sg:city":"Leopoldsdorf im Marchfelde",
    "sg:orig_category":"Non-Classified Establishments",
    "sg:phone":"+43 5 91333211",
    "sg:postcode":"2285",
    "sg:province":"Nieder\u00f6sterreich",
    "wof:name":"Gendarmerie",
    "wof:placetype":"venue"
},
  "geometry": {"coordinates":[16.6874294281,48.2232093811],"type":"Point"}
}