{
  "type": "Feature",
  "properties": {
    "addr:full":"Unterm Hohen Rain 1A Imst Tirol 6460",
    "addr:housenumber":"1a",
    "addr:postcode":"6460",
    "addr:street":"Unterm Hohen Rain;Tirol",
    "iso:country":"AT",
    "sg:address":"Unterm Hohen Rain 1A",
    "sg:city":"Imst",
    "sg:orig_category":"Physiotherapie",
    "sg:phone":"+43 5412 62527",
    "sg:postcode":"6460",
    "sg:province":"Tirol",
    "wof:name":"Physiotherapiezentrum Imst",
    "wof:placetype":"venue"
},
  "geometry": {"coordinates":[10.7379646301,47.2366142273],"type":"Point"}
}