{
  "type": "Feature",
  "properties": {
    "addr:full":"Wiener Str 109 Wiener Neustadt Nieder\u00f6sterreich 2700",
    "addr:postcode":"2700",
    "iso:country":"AT",
    "sg:address":"Wiener Str 109",
    "sg:city":"Wiener Neustadt",
    "sg:orig_category":"Fitnesscenter",
    "sg:phone":"+43 4326 2220720",
    "sg:postcode":"2700",
    "sg:province":"Nieder\u00f6sterreich",
    "wof:name":"Freizeittempel Fitness",
    "wof:placetype":"venue"
},
  "geometry": {"coordinates":[16.2442760468,47.8321228027],"type":"Point"}
}