{
  "type": "Feature",
  "properties": {
    "addr:full":"Peter-Rosegger-Str 18 Ried im Innkreis Ober\u00f6sterreich 4910",
    "addr:housenumber":"18",
    "addr:postcode":"4910",
    "addr:street":"Peter-Rosegger-Str",
    "iso:country":"AT",
    "sg:address":"Peter-Rosegger-Str 18",
    "sg:city":"Ried im Innkreis",
    "sg:orig_category":"Handelsagenturen",
    "sg:phone":"+43 4377 529500",
    "sg:postcode":"4910",
    "sg:province":"Ober\u00f6sterreich",
    "wof:name":"M & M Retail GmbH & Co KG",
    "wof:placetype":"venue"
},
  "geometry": {"coordinates":[13.4916000366,48.2054901123],"type":"Point"}
}