{
  "type": "Feature",
  "properties": {
    "addr:full":"Strausseng. 16 Wien Wien 1050",
    "addr:housenumber":"16",
    "addr:postcode":"1050",
    "addr:street":"Strausseng.",
    "iso:country":"AT",
    "sg:address":"Strausseng. 16",
    "sg:city":"Wien",
    "sg:classifiers":[
        {
            "category":"Professional",
            "subcategory":"Computer Services",
            "type":"Services"
        }
    ],
    "sg:phone":"+43 4315 868610",
    "sg:postcode":"1050",
    "sg:province":"Wien",
    "sg:tags":[
        "information",
        "technology"
    ],
    "wof:name":"A-NULL EDV GMBH",
    "wof:placetype":"venue"
},
  "geometry": {"coordinates":[16.3616638184,48.1918029785],"type":"Point"}
}