{
  "type": "Feature",
  "properties": {
    "iso:country":"AT",
    "sg:address":"Wollzeile 25 ",
    "sg:city":"Wien",
    "sg:classifiers":[
        {
            "category":"Military Area",
            "subcategory":"Air Force Base",
            "type":"Public Place"
        }
    ],
    "sg:phone":"+43 1 5133220",
    "sg:postcode":"1010",
    "sg:province":"Wien",
    "sg:tags":[
        "garden",
        "element"
    ],
    "sg:website":"www.floralstudiowien.at",
    "wof:name":"Floralstudio Hobiger",
    "wof:placetype":"venue"
},
  "geometry": {"coordinates":[16.3772506714,48.2082214355],"type":"Point"}
}