{
  "type": "Feature",
  "properties": {
    "addr:full":"Schwefel 84 Dornbirn Vorarlberg 6850",
    "addr:housenumber":"84",
    "addr:postcode":"6850",
    "addr:street":"Schwefel",
    "iso:country":"AT",
    "sg:address":"Schwefel 84",
    "sg:city":"Dornbirn",
    "sg:orig_category":"Autohandel",
    "sg:phone":"+43 5572 37510",
    "sg:postcode":"6850",
    "sg:province":"Vorarlberg",
    "wof:name":"Auto Gerster GmbH",
    "wof:placetype":"venue"
},
  "geometry": {"coordinates":[9.7391853333,47.4315986633],"type":"Point"}
}