{
  "type": "Feature",
  "properties": {
    "addr:full":"C v H\u00f6tzendorf-Str 72 Graz Steiermark 8010",
    "addr:housenumber":"72",
    "addr:postcode":"8010",
    "addr:street":"V Hoetzendorf-Str",
    "iso:country":"AT",
    "sg:address":"C v H\u00f6tzendorf-Str 72",
    "sg:city":"Graz",
    "sg:classifiers":[
        {
            "category":"Restaurant",
            "type":"Food & Drink"
        }
    ],
    "sg:phone":"+43 316 822288",
    "sg:postcode":"8010",
    "sg:province":"Steiermark",
    "sg:tags":[
        "pizzeria"
    ],
    "wof:name":"Georgi Pizzeria",
    "wof:placetype":"venue"
},
  "geometry": {"coordinates":[15.4431800842,47.0685653687],"type":"Point"}
}