{
  "type": "Feature",
  "properties": {
    "addr:full":"Breitenfurter Str 149 Wien Wien 1120",
    "addr:housenumber":"149",
    "addr:postcode":"1120",
    "addr:street":"Str",
    "iso:country":"AT",
    "sg:address":"Breitenfurter Str 149",
    "sg:city":"Wien",
    "sg:orig_category":"Reifen U Reifendienste",
    "sg:phone":"+43 4318 041666",
    "sg:postcode":"1120",
    "sg:province":"Wien",
    "wof:name":"Euromaster Reifenservice GmbH",
    "wof:placetype":"venue"
},
  "geometry": {"coordinates":[16.3123931885,48.1621551514],"type":"Point"}
}