{
  "type": "Feature",
  "properties": {
    "addr:full":"Wagramer Str 4 Wien Wien 1220",
    "addr:housenumber":"4",
    "addr:postcode":"1220",
    "addr:street":"Str",
    "iso:country":"AT",
    "sg:address":"Wagramer Str 4",
    "sg:city":"Wien",
    "sg:orig_category":"Paletten / Erzeugung U Gro\u00c3\u0178handel",
    "sg:phone":"+43 4312 091518",
    "sg:postcode":"1220",
    "sg:province":"Wien",
    "wof:name":"Europaletten Pal Trans GesmbH",
    "wof:placetype":"venue"
},
  "geometry": {"coordinates":[16.4150791168,48.2309494019],"type":"Point"}
}