{
  "type": "Feature",
  "properties": {
    "addr:full":"Grazer Str 18 F\u00fcrstenfeld Steiermark 8280",
    "addr:postcode":"8280",
    "addr:street":"Str 18 Fuerstenfeld Steiermark",
    "iso:country":"AT",
    "sg:address":"Grazer Str 18",
    "sg:city":"F\u00fcrstenfeld",
    "sg:orig_category":"Betten",
    "sg:phone":"+43 3382 514990",
    "sg:postcode":"8280",
    "sg:province":"Steiermark",
    "wof:name":"D\u00e4nisches Bettenlager HandelsgesmbH",
    "wof:placetype":"venue"
},
  "geometry": {"coordinates":[16.0679264069,47.0581665039],"type":"Point"}
}