{
  "type": "Feature",
  "properties": {
    "addr:full":"Schulg 36/2 Dornbirn Vorarlberg 6850",
    "addr:housenumber":"36 / 2",
    "addr:postcode":"6850",
    "addr:street":"Schulg",
    "iso:country":"AT",
    "sg:address":"Schulg 36/2",
    "sg:city":"Dornbirn",
    "sg:orig_category":"Politische Parteien",
    "sg:phone":"+43 4355 72225480",
    "sg:postcode":"6850",
    "sg:province":"Vorarlberg",
    "wof:name":"Vorarlberger Seniorenbund",
    "wof:placetype":"venue"
},
  "geometry": {"coordinates":[9.7405443192,47.4124641418],"type":"Point"}
}