{
  "type": "Feature",
  "properties": {
    "addr:full":"Brunneng 46 Wien Wien 1160",
    "addr:housenumber":"46",
    "addr:postcode":"1160",
    "addr:street":"Brunneng",
    "iso:country":"AT",
    "sg:address":"Brunneng 46",
    "sg:city":"Wien",
    "sg:orig_category":"Fleischhauereien",
    "sg:phone":"+43 1 9476764",
    "sg:postcode":"1160",
    "sg:province":"Wien",
    "wof:name":"Doguc KEG",
    "wof:placetype":"venue"
},
  "geometry": {"coordinates":[16.336057663,48.2106933594],"type":"Point"}
}