{
  "type": "Feature",
  "properties": {
    "addr:full":"Nr 8 Schwarzenau Nieder\u00f6sterreich 3900",
    "addr:postcode":"3900",
    "addr:street":"Nr;Schwarzenau",
    "iso:country":"AT",
    "sg:address":"Nr 8",
    "sg:city":"Schwarzenau",
    "sg:orig_category":"Tischlereien",
    "sg:phone":"+43 4328 492940",
    "sg:postcode":"3900",
    "sg:province":"Nieder\u00f6sterreich",
    "wof:name":"Reif Anton Bau- u M\u00f6beltischlerei Stiegen- u Gel\u00e4ndebau",
    "wof:placetype":"venue"
},
  "geometry": {"coordinates":[15.2588233948,48.7432861328],"type":"Point"}
}