{
  "type": "Feature",
  "properties": {
    "iso:country":"AT",
    "sg:address":"Neunkirchner Str 119",
    "sg:city":"Wiener Neustadt",
    "sg:orig_category":"Autovermietung",
    "sg:phone":"+43 2622 81034",
    "sg:postcode":"2700",
    "sg:province":"Nieder\u00f6sterreich",
    "wof:name":"Laa KEG",
    "wof:placetype":"venue"
},
  "geometry": {"coordinates":[16.224647522,47.7981147766],"type":"Point"}
}