{
  "type": "Feature",
  "properties": {
    "addr:full":"Markt 1 Schenkenfelden Ober\u00f6sterreich 4192",
    "addr:housenumber":"1",
    "addr:postcode":"4192",
    "addr:street":"Markt",
    "iso:country":"AT",
    "sg:address":"Markt 1",
    "sg:city":"Schenkenfelden",
    "sg:orig_category":"Gemeinden",
    "sg:phone":"+43 7214 70050",
    "sg:postcode":"4192",
    "sg:province":"Ober\u00f6sterreich",
    "wof:name":"Gemeinde Schenkenfelden",
    "wof:placetype":"venue"
},
  "geometry": {"coordinates":[14.3621559143,48.5024757385],"type":"Point"}
}