{
  "type": "Feature",
  "properties": {
    "addr:full":"Kollergerng 4 Wien Wien 1060",
    "addr:housenumber":"4",
    "addr:postcode":"1060",
    "addr:street":"Kollergerng",
    "iso:country":"AT",
    "sg:address":"Kollergerng 4",
    "sg:city":"Wien",
    "sg:orig_category":"Friseure U Frisiersalons",
    "sg:phone":"+43 1 5876284",
    "sg:postcode":"1060",
    "sg:province":"Wien",
    "wof:name":"Frisiersalon Gerard",
    "wof:placetype":"venue"
},
  "geometry": {"coordinates":[16.3515548706,48.1984672546],"type":"Point"}
}