{
  "type": "Feature",
  "properties": {
    "addr:full":"Kohlmarkt 4 Wien Wien 1010",
    "addr:housenumber":"4",
    "addr:postcode":"1010",
    "addr:street":"Kohlmarkt",
    "iso:country":"AT",
    "sg:address":"Kohlmarkt 4",
    "sg:city":"Wien",
    "sg:orig_category":"Boutiquen",
    "sg:phone":"+43 1 5353053",
    "sg:postcode":"1010",
    "sg:province":"Wien",
    "wof:name":"AKRIS (Austria) GmbH",
    "wof:placetype":"venue"
},
  "geometry": {"coordinates":[16.3680286407,48.2092781067],"type":"Point"}
}