{
  "type": "Feature",
  "properties": {
    "addr:full":"Herzog-Odilo-Str 110 Mondsee Ober\u00f6sterreich 5310",
    "addr:housenumber":"110",
    "addr:postcode":"5310",
    "addr:street":"Mondsee Oberoesterreich",
    "iso:country":"AT",
    "sg:address":"Herzog-Odilo-Str 110",
    "sg:city":"Mondsee",
    "sg:orig_category":"Metallbau",
    "sg:phone":"+43 6232 3124",
    "sg:postcode":"5310",
    "sg:province":"Ober\u00f6sterreich",
    "wof:name":"Pichler Hans Metallbau GesmbH",
    "wof:placetype":"venue"
},
  "geometry": {"coordinates":[13.3344545364,47.8657302856],"type":"Point"}
}