{
  "type": "Feature",
  "properties": {
    "addr:full":"Mozartstrasse 6  Innsbruck Tirol 6020",
    "addr:housenumber":"6",
    "addr:postcode":"6020",
    "addr:street":"Mozartstrasse;Tirol",
    "iso:country":"AT",
    "sg:address":"Mozartstrasse 6 ",
    "sg:city":"Innsbruck",
    "sg:classifiers":[
        {
            "category":"Manufacturing",
            "subcategory":"Jewelry",
            "type":"Manufacturing & Wholesale Goods"
        }
    ],
    "sg:phone":"+43 512 576105",
    "sg:postcode":"6020",
    "sg:province":"Tirol",
    "sg:tags":[
        "jewellery",
        "silver",
        "gold",
        "combined"
    ],
    "wof:name":"Herbert Spindlegger",
    "wof:placetype":"venue"
},
  "geometry": {"coordinates":[11.408115387,47.2748641968],"type":"Point"}
}