{
  "type": "Feature",
  "properties": {
    "iso:country":"AT",
    "sg:address":"Austr. 17 ",
    "sg:city":"Kundl",
    "sg:classifiers":[
        {
            "category":"Building & Trades",
            "subcategory":"Construction",
            "type":"Services"
        }
    ],
    "sg:phone":"+43 4353 387331",
    "sg:postcode":"6250",
    "sg:province":"Tirol",
    "sg:tags":[
        "work",
        "public"
    ],
    "wof:name":"ANDREAS RUPPRECHTER",
    "wof:placetype":"venue"
},
  "geometry": {"coordinates":[11.9875164032,47.4722862244],"type":"Point"}
}