{
  "type": "Feature",
  "properties": {
    "addr:full":"Ganglgutstrasse 87b Traun Ober\u00f6sterreich 4050",
    "addr:housenumber":"87b",
    "addr:postcode":"4050",
    "addr:street":"Ganglgutstrasse",
    "iso:country":"AT",
    "sg:address":"Ganglgutstrasse 87b",
    "sg:city":"Traun",
    "sg:classifiers":[
        {
            "category":"Manufacturing",
            "subcategory":"Tools & Machinery",
            "type":"Manufacturing & Wholesale Goods"
        }
    ],
    "sg:phone":"+43 7229 71829",
    "sg:postcode":"4050",
    "sg:province":"Ober\u00f6sterreich",
    "sg:tags":[
        "customized"
    ],
    "sg:website":"tfm.at",
    "wof:name":"T.F.M. Technologie f\u00fcr Metallbearbeitung GmbH",
    "wof:placetype":"venue"
},
  "geometry": {"coordinates":[14.2160196304,48.211971283],"type":"Point"}
}