{
  "type": "Feature",
  "properties": {
    "addr:full":"Gartenland 187 Ried im Oberinntal Tirol 6531",
    "addr:housenumber":"187",
    "addr:postcode":"6531",
    "addr:street":"Gartenland;Tirol",
    "iso:country":"AT",
    "sg:address":"Gartenland 187",
    "sg:city":"Ried im Oberinntal",
    "sg:orig_category":"Appartements / Ferienwohnungen",
    "sg:phone":"+43 5472 6578",
    "sg:postcode":"6531",
    "sg:province":"Tirol",
    "wof:name":"Konrad Walter",
    "wof:placetype":"venue"
},
  "geometry": {"coordinates":[10.654545784,47.0553817749],"type":"Point"}
}