{
  "type": "Feature",
  "properties": {
    "addr:full":"Obermarkt 21 Telfs Tirol 6410",
    "addr:housenumber":"21",
    "addr:postcode":"6410",
    "addr:street":"Obermarkt;Tirol",
    "iso:country":"AT",
    "sg:address":"Obermarkt 21",
    "sg:city":"Telfs",
    "sg:orig_category":"Altwaren",
    "sg:phone":"+43 4365 06574001",
    "sg:postcode":"6410",
    "sg:province":"Tirol",
    "wof:name":"Stecher's Tr\u00f6dlerladen",
    "wof:placetype":"venue"
},
  "geometry": {"coordinates":[11.0689382553,47.3064079285],"type":"Point"}
}