{
  "type": "Feature",
  "properties": {
    "iso:country":"AT",
    "sg:address":"Freisinger Berg 6",
    "sg:city":"Waidhofen an der Ybbs",
    "sg:orig_category":"Lebensmittel / Einzelhandel",
    "sg:phone":"+43 4374 4252124",
    "sg:postcode":"3340",
    "sg:province":"Nieder\u00f6sterreich",
    "wof:name":"SPAR \u00f6sterreichische Warenhandels-AG",
    "wof:placetype":"venue"
},
  "geometry": {"coordinates":[14.7739677429,47.9608306885],"type":"Point"}
}